Workbook

Sheet BTR Quoting Rents
B2: COMMERCIAL HOLDINGS
B4: Property | C4: Marketing Name | D4: Commercial Asset Manager | E4: Asset Manager | F4: Development Manager | G4: Location | H4: Region | I4: Unit No. | J4: Qube Reference | K4: Qube Unit ref | L4: Qube Unit Description | M4: Salesforce uniit id | N4: Completion Date (PC) | O4: Status | P4: Units | Q4: Leases | R4: Floor Area | S4: Tenant | T4: U/O | U4: Months Vacant | V4: Service Charge | W4: EPC Rating | X4: Lease Start | Y4: Rent Commencement | Z4: RF Expiry | AA4: RF - Time Value | AB4: RF - [£]Value | AC4: Rent Review Date | AD4: Break Date | AE4: Lease Expiration Date | AF4: Capital Contribution £ | AG4: Headline Rent £PA | AH4: Headline Rent £/sqft | AI4: NER [£] | AJ4: Grown Underwritten Rent | AK4: Cap. Con - Time Value | AL4: Total TI - Time Value | AM4: Total TI - [£] Value | AN4: Lease Length | AO4: Unexpired Term | AP4: Time to Rent Review | AQ4: Lease Length - Break | AR4: Time to Break | AS4: CBRE ERV £pa | AT4: CBRE ERV £psf | AU4: Current QR £pa | AV4: Current QR £psf
A5: Clippers Quay1 Zegera Way | B5: Clippers Quay | C5: Clippers Quay | D5: Stewart Blackford | E5: Vicki Turnbull | G5: Manchester | H5: Regions | I5: 1 Zegera Way | J5: 222577002 | K5: 222577002 | L5: Clippers - Unit 1 Zerega Way M50 | M5: a1G4J0000025xoHUAQ | N5: 21/12/2018 | O5: Operational | P5: 1 | Q5: 1 | R5: 1249 | S5: Teta Ltd | U5: - | V5: exclusive | X5: 45449 | Y5: 45571 | Z5: - | AA5: 4.0109545 | AB5: -6684.9242 | AC5: 47275 | AD5: 46544 | AE5: 49101 | AG5: 20000 | AH5: 16.01281 | AI5: 17770.213 | AK5: 0 | AL5: 4.0109545 | AM5: 6684.9242 | AN5: 9.9988446 | AO5: 9.2897261 | AP5: 4.2903038 | AQ5: 2.9980106 | AR5: 2.2888921 | AS5: 20000 | AT5: 16.01281
A6: Clippers Quay2 Zegera Way | B6: Clippers Quay | C6: Clippers Quay | D6: Stewart Blackford | E6: Vicki Turnbull | G6: Manchester | H6: Regions | I6: 2 Zegera Way | J6: 222577003 | K6: 222577003 | L6: Clippers - Unit 2 Zerega Way M50 | M6: a1G4J0000025xMrUAI | N6: 43142 | O6: Operational | P6: 1 | Q6: 1 | R6: 1461 | S6: OB1 Bars Ltd. | U6: - | V6: exclusive | X6: 43817 | Y6: 43879 | Z6: - | AA6: 2.0383539 | AB6: -3736.9822 | AC6: 45644 | AD6: 44913 | AE6: 47469 | AG6: 22000 | AH6: 15.058179 | AI6: 20754.65 | AK6: 0 | AL6: 2.0383539 | AM6: 3736.9822 | AN6: 9.9988446 | AO6: 4.8214582 | AP6: - | AQ6: 3.0007485 | AR6: - | AS6: 21900 | AT6: 14.989733
A7: Clippers QuayUnit 4 & 5 Waterman Walk | B7: Clippers Quay | C7: Clippers Quay | D7: Stewart Blackford | E7: Vicki Turnbull | G7: Manchester | H7: Regions | I7: Unit 4 & 5 Waterman Walk | J7: 222577001 | K7: 222577001 | L7: Clippers - Unit 4-5 Waterman Walk | M7: a1G4J0000025xf4UAA | N7: 43318 | O7: Operational | P7: 2 | Q7: 1 | R7: 3832 | S7: Co-Operative Group Food Ltd. | U7: - | V7: exclusive | X7: 43616 | Y7: 43799 | Z7: - | AA7: 6.0164318 | AB7: -31242.282 | AC7: 45443 | AD7: 47268 | AE7: 49094 | AG7: 62313.91 | AH7: 16.261459 | AI7: 59189.321 | AK7: 0 | AL7: 6.0164318 | AM7: 31242.282 | AN7: 14.998267 | AO7: 9.2705607 | AP7: - | AQ7: 9.9988446 | AR7: 4.2711384 | AS7: 54800 | AT7: 14.300626
A8: Clippers Quay2 & 3 Waterman Walk | B8: Clippers Quay | C8: Clippers Quay | D8: Stewart Blackford | E8: Vicki Turnbull | G8: Manchester | H8: Regions | I8: 2 & 3 Waterman Walk | J8: 222577005 | K8: 222577005 | L8: Clippers - Unit 2 Waterman Walk (GPLC Office) | M8: a1G4J0000025x0gUAA | N8: 43142 | O8: Operational | P8: 2 | Q8: 1 | R8: 2388 | S8: Grainger Plc | U8: - | V8: exclusive | X8: 44124 | Y8: - | Z8: - | AA8: - | AB8: - | AE8: 45949 | AH8: 0 | AI8: 0 | AK8: - | AL8: - | AM8: - | AN8: 4.9966844 | AO8: 0.65983613 | AP8: - | AQ8: - | AR8: - | AS8: 41800 | AT8: 17.504188
J9: 222577004 | K9: 222577004 | L9: Clippers - Unit 3 Waterman Walk (GPLC Office) | M9: a1G4J0000025xvyUAA
A10: Clippers Quay1 Waterman Walk | B10: Clippers Quay | C10: Clippers Quay | D10: Stewart Blackford | E10: Vicki Turnbull | G10: Manchester | H10: Regions | I10: 1 Waterman Walk | J10: 222577006 | K10: 222577006 | L10: Clippers - Unit 1 Waterman Walk | M10: a1G4J0000025xRhUAI | N10: 43142 | O10: Operational | P10: 1 | Q10: 1 | R10: 1435 | S10: Cult Group Ltd | U10: - | V10: exclusive | X10: 43472 | Y10: 43776 | Z10: - | AA10: 9.9945096 | AB10: -19072.856 | AC10: 47125 | AD10: 45298 | AE10: 48950 | AG10: 22900 | AH10: 15.958188 | AI10: 19084.988 | AK10: 0 | AL10: 9.9945096 | AM10: 19072.856 | AN10: 14.998267 | AO10: 8.8763018 | AP10: 3.8796174 | AQ10: 4.9994223 | AR10: - | AS10: 20000 | AT10: 13.937282
A11: Hawkins & George1 | B11: Hawkins & George | C11: Hawkins & George | D11: Becky Day | E11: Vicki Turnbull | G11: Bristol | H11: Regions | I11: 1 | J11: 222625001 | K11: 222625001 | L11: Unit 1, Hawkins Lane Building, East Tucker St | M11: a1G4J0000025wsUUAQ | N11: 21/05/2019 | O11: Operational | P11: 1 | Q11: 1 | R11: 1635 | S11: Vacant | U11: 68 | W11: B | Z11: - | AA11: 0 | AB11: 0 | AH11: 0 | AI11: 0 | AK11: - | AL11: - | AM11: - | AN11: 0 | AO11: - | AP11: - | AQ11: 0 | AR11: - | AS11: 38050 | AT11: 23.272171 | AU11: 40875 | AV11: 25
A12: Hawkins & George2 | B12: Hawkins & George | C12: Hawkins & George | D12: Becky Day | E12: Vicki Turnbull | G12: Bristol | H12: Regions | I12: 2 | J12: 222625002 | K12: 222625002 | L12: Unit 2, Hawkins Lane Building, East Tucker St | M12: a1G4J0000025y18UAA | N12: 21/05/2019 | O12: Operational | P12: 1 | Q12: 1 | R12: 439 | S12: The Ruby Hue Ltd | U12: - | W12: C | X12: 44867 | Y12: 44987 | Z12: - | AA12: 3.9452012 | AB12: -3608.2152 | AC12: 46693 | AD12: 46693 | AE12: 48520 | AG12: 10975 | AH12: 25 | AI12: 10253.274 | AK12: 0 | AL12: 3.9452012 | AM12: 3608.2152 | AN12: 10.001583 | AO12: 7.6990008 | AP12: 2.6968406 | AQ12: 4.9994223 | AR12: 2.6968406 | AS12: 10975 | AT12: 25
A13: Hawkins & George3 | B13: Hawkins & George | C13: Hawkins & George | D13: Becky Day | E13: Vicki Turnbull | G13: Bristol | H13: Regions | I13: 3 | J13: 222625003 | K13: 222625003 | L13: Unit 3, Hawkins Lane Building, East Tucker St | M13: a1G4J0000025xJHUAY | N13: 21/05/2019 | O13: Operational | P13: 1 | Q13: 1 | R13: 1470 | S13: Vacant | U13: 68 | W13: B | Z13: - | AA13: 0 | AB13: 0 | AH13: 0 | AI13: 0 | AK13: - | AL13: - | AM13: - | AN13: 0 | AO13: - | AP13: - | AQ13: 0 | AR13: - | AS13: 28500 | AT13: 19.387755 | AU13: 36750 | AV13: 25
A14: Redcliffe Quarter1.1 | B14: Redcliffe Quarter | C14: Glasshouse Square | D14: Bradley Wallace | E14: Sarah Norstrom | G14: Bristol | H14: Regions | I14: 1.1 | J14: 222707001 | K14: 222707001 | L14: Unit 1.1 Redcliffe Quarter, Bristol. BS1 6WL | M14: a1G8d0000005cWREAY | N14: 13/07/2022 | O14: Operational | P14: 1 | Q14: 1 | R14: 1452 | S14: Vacant | U14: 31 | Z14: - | AA14: 0 | AB14: 0 | AH14: 0 | AI14: 0 | AK14: - | AL14: - | AM14: - | AN14: 0 | AO14: - | AP14: - | AQ14: 0 | AR14: - | AS14: 33733 | AT14: 23.232094 | AU14: 36300 | AV14: 25
A15: Redcliffe Quarter1.2 | B15: Redcliffe Quarter | C15: Glasshouse Square | D15: Bradley Wallace | E15: Sarah Norstrom | G15: Bristol | H15: Regions | I15: 1.2 | J15: 222707002 | K15: 222707002 | L15: Unit 1.2 Redcliffe Quarter, Bristol. BS1 6WL | M15: a1G8d0000005cWWEAY | N15: 13/07/2022 | O15: Operational | P15: 1 | Q15: 1 | R15: 1024 | S15: J Turok t/a Doubleshot barbers | U15: - | X15: 45541 | Y15: 45722 | Z15: 0 | AA15: 5.9506784 | AB15: -10572.372 | AC15: 47183 | AD15: 47183 | AE15: 47278 | AF15: 0 | AG15: 21320 | AH15: 20.820312 | AI15: 18968.309 | AK15: 0 | AL15: 5.9506784 | AM15: 10572.372 | AN15: 4.7557484 | AO15: 4.2985175 | AP15: 4.0384162 | AQ15: 4.495647 | AR15: 4.0384162 | AS15: 21853 | AT15: 21.34082
A16: Redcliffe Quarter1.3 | B16: Redcliffe Quarter | C16: Glasshouse Square | D16: Bradley Wallace | E16: Sarah Norstrom | G16: Bristol | H16: Regions | I16: 1.3 | J16: 222707003 | K16: 222707003 | L16: Unit 1.3 Redcliffe Quarter, Bristol. BS1 6WL | M16: a1G8d0000005cWbEAI | N16: 13/07/2022 | O16: Operational | P16: 1 | Q16: 1 | R16: 1066 | S16: UKGolfbox Bristol Ltd | U16: - | X16: 45596 | Y16: 45787 | Z16: 2 | AA16: 6.2794452 | AB16: -11459.987 | AE16: 47432 | AF16: 0 | AG16: 21900 | AH16: 20.54409 | AI16: 19620.223 | AK16: 0 | AL16: 6.2794452 | AM16: 11459.987 | AN16: 5.0268014 | AO16: 4.7201556 | AP16: - | AQ16: - | AR16: - | AS16: 26650 | AT16: 25
A17: Redcliffe Quarter2.1 | B17: Redcliffe Quarter | C17: Glasshouse Square | D17: Bradley Wallace | E17: Sarah Norstrom | G17: Bristol | H17: Regions | I17: 2.1 | J17: 222707004 | K17: 222707004 | L17: Unit 2.1 Redcliffe Quarter, Bristol. BS1 6WL | M17: a1G8d0000005cWgEAI | N17: 13/07/2022 | O17: Operational | P17: 1 | Q17: 1 | R17: 4539 | S17: Under Offer | T17: ASDA | U17: 31 | Z17: - | AA17: 0 | AB17: 0 | AH17: 0 | AI17: 0 | AK17: - | AL17: - | AM17: - | AN17: 0 | AO17: - | AP17: - | AQ17: 0 | AR17: - | AS17: 99858 | AT17: 22 | AU17: 104397 | AV17: 23
A18: Redcliffe Quarter2.2 (Unit 5) | B18: Redcliffe Quarter | C18: Glasshouse Square | D18: Bradley Wallace | E18: Sarah Norstrom | G18: Bristol | H18: Regions | I18: 2.2 (Unit 5) | K18: #N/A | L18: Not on Qube yet | M18: Not on SF yet | N18: est. 01/09/2025 | O18: Under Construction | P18: 1 | Q18: 1 | R18: 2393 | S18: Winvic Construction | U18: - | Z18: - | AA18: 0 | AB18: 0 | AH18: 0 | AT18: 0 | AU18: 59825 | AV18: 25 | AW18: this is on the market as the tenant will be vacating in a few months
A19: Redcliffe Quarter2.3 (unit 6) | B19: Redcliffe Quarter | C19: Glasshouse Square | D19: Bradley Wallace | E19: Sarah Norstrom | G19: Bristol | H19: Regions | I19: 2.3 (unit 6) | K19: #N/A | L19: Not on Qube yet | M19: Not on SF yet | N19: est. 01/09/2025 | O19: Under Construction | P19: 1 | Q19: 1 | R19: 2754 | S19: Winvic Construction | U19: - | Z19: - | AA19: 0 | AB19: 0 | AH19: 0 | AT19: 0 | AU19: 68850 | AV19: 25 | AW19: this is on the market as the tenant will be vacating in a few months
A20: Glasshouse1 | B20: Glasshouse | C20: Glasshouse | D20: Bradley Wallace | E20: Sarah Norstrom | F20: Maria Sabat | G20: Bristol | H20: Regions | I20: 1 | K20: #N/A | L20: Not on Qube yet | M20: Not on SF yet | N20: est 08/08/2025 | O20: Under Construction | P20: 1 | Q20: 1 | R20: 2667.2944 | S20: Vacant | Z20: - | AA20: 0 | AB20: 0 | AG20: 0 | AH20: 0 | AI20: 0 | AK20: - | AL20: - | AM20: - | AN20: 0 | AO20: - | AP20: - | AQ20: 0 | AR20: - | AS20: #N/A | AT20: #N/A
A21: Glasshouse2 | B21: Glasshouse | C21: Glasshouse | D21: Bradley Wallace | E21: Sarah Norstrom | F21: Maria Sabat | G21: Bristol | H21: Regions | I21: 2 | K21: #N/A | L21: Not on Qube yet | M21: Not on SF yet | N21: est 08/08/2025 | O21: Under Construction | P21: 1 | Q21: 1 | R21: 3119.3782 | S21: Vacant | Z21: - | AA21: 0 | AB21: 0 | AG21: 0 | AH21: 0 | AI21: 0 | AK21: - | AL21: - | AM21: - | AN21: 0 | AO21: - | AP21: - | AQ21: 0 | AR21: - | AS21: #N/A | AT21: #N/A
A22: Glasshouse3 | B22: Glasshouse | C22: Glasshouse | D22: Bradley Wallace | E22: Sarah Norstrom | F22: Maria Sabat | G22: Bristol | H22: Regions | I22: 3 | K22: #N/A | L22: Not on Qube yet | M22: Not on SF yet | N22: est 08/08/2025 | O22: Under Construction | P22: 1 | Q22: 1 | R22: 1791.113 | S22: Vacant | Z22: - | AA22: 0 | AB22: 0 | AG22: 0 | AH22: 0 | AI22: 0 | AK22: - | AL22: - | AM22: - | AN22: 0 | AO22: - | AP22: - | AQ22: 0 | AR22: - | AS22: #N/A | AT22: #N/A
A23: Glasshouse4 | B23: Glasshouse | C23: Glasshouse | D23: Bradley Wallace | E23: Sarah Norstrom | F23: Maria Sabat | G23: Bristol | H23: Regions | I23: 4 | K23: #N/A | L23: Not on Qube yet | M23: Not on SF yet | N23: est 14/04/2025 (Dev think 26/05/2025) | O23: Under Construction | P23: 1 | Q23: 1 | R23: 992.43158 | S23: Vacant | Z23: - | AA23: 0 | AB23: 0 | AG23: 0 | AH23: 0 | AI23: 0 | AK23: - | AL23: - | AM23: - | AN23: 0 | AO23: - | AP23: - | AQ23: 0 | AR23: - | AS23: #N/A | AT23: #N/A
A24: Brook Place1/2 | B24: Brook Place | C24: Brook Place | D24: Stewart Blackford | E24: Vicki Turnbull | G24: Sheffield | H24: Regions | I24: 1/2 | J24: 222632001 | K24: 222632001 | L24: Unit 1 Brook Place 110 Napier Street S11 8BR | M24: a1G4J0000025y3lUAA | N24: 30/09/2019 | O24: Operational | P24: 2 | Q24: 1 | R24: 3721 | S24: R1SE Brook Place Ltd | U24: - | V24: Inclusive | W24: B | X24: 44326 | Y24: 44691 | Z24: - | AA24: 11.999987 | AB24: -32360.965 | AC24: 46152 | AD24: 46152 | AE24: 47977 | AG24: 32361 | AH24: 8.6968557 | AI24: 25888.059 | AK24: 0 | AL24: 11.999987 | AM24: 32360.965 | AN24: 9.9961067 | AO24: 6.2123161 | AP24: 1.2156317 | AQ24: 4.9994223 | AR24: 1.2156317 | AS24: 31600 | AT24: 8.4923408
J25: 222632002 | K25: 222632002 | L25: Unit 2, Brook Place, 112 Napier Street, S11 8 | M25: a1G4J0000025x8FUAQ
A26: Brook Place3 | B26: Brook Place | C26: Brook Place | D26: Stewart Blackford | E26: Vicki Turnbull | G26: Sheffield | H26: Regions | I26: 3 | J26: 222632003 | K26: 222632003 | L26: Unit 3, Brook Place, 114 Napier Street, S11 8 | M26: a1G4J0000025yBfUAI | N26: 30/09/2019 | O26: Operational | P26: 1 | Q26: 1 | R26: 1981 | S26: Smile 2 Impress | U26: - | V26: Inclusive | W26: B | X26: 44729 | Y26: 45002 | Z26: - | AA26: 8.9753326 | AB26: -19359.045 | AC26: 46555 | AD26: 46555 | AE26: 48381 | AG26: 25883 | AH26: 13.065623 | AI26: 22010.744 | AK26: 0 | AL26: 8.9753326 | AM26: 19359.045 | AN26: 9.9988446 | AO26: 7.3184314 | AP26: 2.3190091 | AQ26: 4.9994223 | AR26: 2.3190091 | AS26: 24800 | AT26: 12.51893
A27: Solstice Apartments1/2 | B27: Solstice Apartments | C27: Solstice Apartments | D27: Stewart Blackford | E27: Vicki Turnbull | G27: Milton Keynes | H27: Regions | I27: 1/2 | J27: 222641001 | K27: 222641001 | L27: 809, Silbury Boulevard, Milton Keynes, MK9 | M27: a1G4J0000025y5HUAQ | N27: 43954 | O27: Operational | P27: 2 | Q27: 1 | R27: 4498 | S27: Spectrum Associates (MK) Ltd | U27: - | V27: exclusive | W27: B | X27: 44448 | Y27: 44751 | Z27: - | AA27: 9.9616329 | AB27: -62542.452 | AC27: 46274 | AD27: 48100 | AE27: 49835 | AF27: -45000 | AG27: 75340 | AH27: 16.749667 | AI27: 64584.512 | AK27: 7.1675073 | AL27: 17.12914 | AM27: 107542.45 | AN27: 14.749117 | AO27: 11.299351 | AP27: 1.5496566 | AQ27: 9.9988446 | AR27: 6.5490789 | AS27: 75340 | AT27: 16.749667
J28: 222641002 | K28: 222641002 | L28: 811, Silbury Boulevard, Milton Keynes, MK9 | M28: a1G4J0000025y35UAA
A29: Millet Place1 | B29: Millet Place | C29: Millet Place | D29: Bradley Wallace | E29: Harriet Shaw & Sarah Norstrom | G29: London | H29: London | I29: 1 | J29: 900005001 | K29: 900005001 | L29: Unit 1, 1 Millet Place, London E16 2YJ | M29: a1G4J00000260JEUAY | N29: 43924 | O29: Operational | P29: 1 | Q29: 1 | R29: 2250 | S29: Vacant | U29: 58 | W29: B | Z29: - | AA29: 0 | AB29: 0 | AH29: 0 | AI29: 0 | AK29: - | AL29: - | AM29: - | AN29: 0 | AO29: - | AP29: - | AQ29: 0 | AR29: - | AS29: 51731.25 | AT29: 22.991667 | AU29: 52000 | AV29: 23.111111
A30: Millet Place2 | B30: Millet Place | C30: Millet Place | D30: Bradley Wallace | E30: Harriet Shaw & Sarah Norstrom | G30: London | H30: London | I30: 2 | J30: 900005002 | K30: 900005002 | L30: Unit 2, 5 Millet Place, London E16 2YJ | M30: a1G4J000002605CUAQ | N30: 43924 | O30: Operational | P30: 1 | Q30: 1 | R30: 3451 | S30: Under Offer | T30: Tesco | U30: 58 | W30: A | Z30: - | AA30: 0 | AB30: 0 | AH30: 0 | AI30: 0 | AK30: - | AL30: - | AM30: - | AN30: 0 | AO30: - | AP30: - | AQ30: 0 | AR30: - | AS30: 60000 | AT30: 17.386265 | AU30: 80000 | AV30: 23.181686
A31: Millet Place3 | B31: Millet Place | C31: Millet Place | D31: Bradley Wallace | E31: Harriet Shaw & Sarah Norstrom | G31: London | H31: London | I31: 3 | J31: 900005003 | K31: 900005003 | L31: Unit 3,7 Millet Place, London E16 2YJ | M31: a1G4J000002607zUAA | N31: 43924 | O31: Operational | P31: 1 | Q31: 1 | R31: 904 | S31: Vacant | U31: 58 | W31: B | Z31: - | AA31: 0 | AB31: 0 | AH31: 0 | AI31: 0 | AK31: - | AL31: - | AM31: - | AN31: 0 | AO31: - | AP31: - | AQ31: 0 | AR31: - | AS31: 20340 | AT31: 22.5 | AU31: 26000 | AV31: 28.761062
A32: Millet Place4 | B32: Millet Place | C32: Millet Place | D32: Bradley Wallace | E32: Harriet Shaw & Sarah Norstrom | G32: London | H32: London | I32: 4 | J32: 900005004 | K32: 900005004 | L32: Unit 4, 9 Millet Place, London E16 2YJ | M32: a1G4J00000260MYUAY | N32: 43924 | O32: Operational | P32: 1 | Q32: 1 | R32: 1132 | S32: Under Offer | T32: Subway | U32: 58 | W32: A | Z32: - | AA32: 0 | AB32: 0 | AH32: 0 | AI32: 0 | AK32: - | AL32: - | AM32: - | AN32: 0 | AO32: - | AP32: - | AQ32: 0 | AR32: - | AS32: 24055 | AT32: 21.25 | AU32: 30000 | AV32: 26.501767
A33: The FilamentsPodium A/B - Unit 1 | B33: The Filaments | C33: The Filaments | D33: Bradley Wallace | E33: Vicki Turnbull | G33: Manchester | H33: Regions | I33: Podium A/B - Unit 1 | J33: 222653001 | K33: 222653001 | L33: Unit 1 Halogen House, 217 Chapel St, Salford | M33: a1G8d0000004Me4EAE | N33: 19/02/2021 | O33: Operational | P33: 1 | Q33: 1 | R33: 1069 | S33: Vacant | T33: Fiori Ltd | U33: 48 | W33: C | Z33: - | AA33: 0 | AB33: 0 | AH33: 0 | AI33: 0 | AK33: - | AL33: - | AM33: - | AN33: 0 | AO33: - | AP33: - | AQ33: 0 | AR33: - | AS33: 24000 | AT33: 22.450889 | AU33: 25000 | AV33: 23.386342
A34: The FilamentsPodium A/B - Unit 2 | B34: The Filaments | C34: The Filaments | D34: Stewart Blackford | E34: Vicki Turnbull | G34: Manchester | H34: Regions | I34: Podium A/B - Unit 2 | J34: 222653002 | K34: 222653002 | L34: Unit 2, Halogen House, 217 Chapel St, Salford | M34: a1G8d0000004Me9EAE | N34: 19/02/2021 | O34: Operational | P34: 1 | Q34: 1 | R34: 828 | S34: K&K Hospitality | U34: - | W34: D | X34: 44642 | Y34: 44733 | Z34: - | AA34: 2.9917775 | AB34: -4986.2959 | AC34: 46468 | AD34: 46468 | AE34: 47198 | AG34: 20000 | AH34: 24.154589 | AI34: 19002.626 | AK34: 0 | AL34: 2.9917775 | AM34: 4986.2959 | AN34: 6.9980961 | AO34: 4.0794848 | AP34: 2.080811 | AQ34: 4.9994223 | AR34: 2.080811 | AS34: 20000 | AT34: 24.154589
A35: The FilamentsPodium A/B - Unit 3 | B35: The Filaments | C35: The Filaments | D35: Stewart Blackford | E35: Vicki Turnbull | G35: Manchester | H35: Regions | I35: Podium A/B - Unit 3 | J35: 222653003 | K35: 222653003 | L35: Unit 3, Halogen House, 217 Chapel St, Salford | M35: a1G8d0000004MeEEAU | N35: 19/02/2021 | O35: Operational | P35: 1 | Q35: 1 | R35: 426 | S35: Inner West Coffee | U35: - | W35: D | X35: 44470 | Y35: 44547 | Z35: - | AA35: 2.5315041 | AB35: -2729.8052 | AC35: 45566 | AE35: 46295 | AG35: 12940 | AH35: 30.375587 | AI35: 12393.677 | AK35: 0 | AL35: 2.5315041 | AM35: 2729.8052 | AN35: 4.9966844 | AO35: 1.6071527 | AP35: - | AQ35: - | AR35: - | AS35: 12800 | AT35: 30.046948
A36: The FilamentsPodium C - Unit 4 | B36: The Filaments | C36: The Filaments | D36: Stewart Blackford | E36: Vicki Turnbull | G36: Manchester | H36: Regions | I36: Podium C - Unit 4 | J36: 222653004 | K36: 222653004 | L36: Unit 4, Neon House, 207 Chapel St, Salford, M | M36: a1G8d0000004MeJEAU | N36: 14/03/2021 | O36: Operational | P36: 1 | Q36: 1 | R36: 1231 | S36: Shoalter Automation (UK) | U36: - | W36: D | X36: 44992 | Y36: 45358 | Z36: - | AA36: 12.032864 | AB36: -25569.835 | AC36: 46819 | AD36: 47184 | AE36: 48645 | AF36: - | AG36: 25500 | AH36: 20.714866 | AI36: 25500 | AK36: - | AL36: - | AM36: - | AN36: 10.001583 | AO36: 8.0412395 | AP36: 3.0418172 | AQ36: 6.0014971 | AR36: 4.0411541 | AS36: 25500 | AT36: 20.714866
A37: The FilamentsPodium C - Unit 5 | B37: The Filaments | C37: The Filaments | D37: Stewart Blackford | E37: Vicki Turnbull | G37: Manchester | H37: Regions | I37: Podium C - Unit 5 | J37: 222653005 | K37: 222653005 | L37: Unit 5, Neon House, 207 Chapel St, Salford, M | M37: a1G8d0000004MeOEAU | N37: 14/03/2021 | O37: Operational | P37: 1 | Q37: 1 | R37: 1332 | S37: Rush242 Ltd | U37: - | W37: D | X37: 45064 | Y37: 45248 | Z37: - | AA37: 6.0493084 | AB37: -14745.189 | AC37: 46905 | AD37: 46905 | AE37: 48716 | AF37: -15000 | AG37: 29250 | AH37: 21.959459 | AI37: 23348.752 | AK37: 6.1538462 | AL37: 12.203155 | AM37: 29745.189 | AN37: 9.9988446 | AO37: 8.235631 | AP37: 3.2772774 | AQ37: 5.0404909 | AR37: 3.2772774 | AS37: 29250 | AT37: 21.959459
A38: The FilamentsPodium C - Unit 6 | B38: The Filaments | C38: The Filaments | D38: Stewart Blackford | E38: Vicki Turnbull | G38: Manchester | H38: Regions | I38: Podium C - Unit 6 | J38: 222653006 | K38: 222653006 | L38: Unit 6, Neon House, 207 Chapel St, Salford, M | M38: a1G8d0000004MeTEAU | N38: 14/03/2021 | O38: Operational | P38: 1 | Q38: 1 | R38: 2940 | S38: BLS International Services | U38: - | W38: D | X38: 45156 | Y38: 45340 | Z38: - | AA38: 6.0493084 | AB38: -22684.907 | AC38: 46983 | AD38: 46252 | AE38: 48808 | AG38: 45000 | AH38: 15.306122 | AI38: 37440.251 | AK38: 0 | AL38: 6.0493084 | AM38: 22684.907 | AN38: 9.9988446 | AO38: 8.4875187 | AP38: 3.4908343 | AQ38: 3.0007485 | AR38: 1.4894226 | AS38: 45000 | AT38: 15.306122
A39: Apex Gardens1 | B39: Apex Gardens | C39: Apex Gardens | D39: Bradley Wallace | E39: Harriet Shaw & Alexa Byrne | G39: London | H39: London | I39: 1 | J39: 222646001 | K39: 222646001 | L39: Unit 1, Aster Apartments. | M39: a1G8d0000004RxMEAU | N39: 21/06/2021 | O39: Operational | P39: 1 | Q39: 1 | R39: 1780 | S39: Under Offer | T39: Ellies Nursery | U39: 43 | Z39: - | AA39: 0 | AB39: 0 | AH39: 0 | AI39: 0 | AK39: - | AL39: - | AM39: - | AN39: 0 | AO39: - | AP39: - | AQ39: 0 | AR39: - | AS39: 44500 | AT39: 25 | AU39: 45000 | AV39: 25.280899
A40: Apex Gardens2 | B40: Apex Gardens | C40: Apex Gardens | D40: Stewart Blackford | E40: Harriet Shaw & Alexa Byrne | G40: London | H40: London | I40: 2 | J40: 222644002 | K40: 222644002 | L40: Unit 2, Juniper House | M40: a1G8d0000004RwxEAE | N40: 21/06/2021 | O40: Operational | P40: 6 | Q40: 1 | R40: 7704 | S40: Pure Gym | U40: - | X40: 45191 | Y40: 45285 | Z40: - | AA40: 3.0904076 | AB40: -50219.123 | AD40: 25/09/2033 | AE40: 50672 | AF40: -100000 | AG40: 195000 | AH40: 25.311526 | AI40: 179992.79 | AK40: 6.1538462 | AL40: 9.2442537 | AM40: 150219.12 | AN40: 15.006481 | AO40: 13.590982 | AP40: - | AQ40: 10.009796 | AR40: 8.5942972 | AS40: #N/A | AT40: #N/A
I41: 3 | J41: 222644003 | K41: 222644003 | L41: Unit 3, Juniper House | M41: a1G8d0000004Rx2EAE
I42: 4 | J42: 222644004 | K42: 222644004 | L42: Unit 4, Juniper House | M42: a1G8d0000004Rx7EAE
I43: 5 | J43: 222644005 | K43: 222644005 | L43: Unit 5, Juniper House | M43: a1G8d0000004RxCEAU
I44: 6 | J44: 222644006 | K44: 222644006 | L44: Unit 6, Juniper House | M44: a1G8d0000004RxHEAU
A45: Gilders YardB02 | B45: Gilders Yard | C45: Gilders Yard | D45: Bradley Wallace | E45: Vicki Turnbull | G45: Birmingham | H45: Regions | I45: B02 | J45: 222690003 | K45: 222690003 | L45: Gilders Yard - B.02, 12 Great Hampton St | M45: a1G8d0000004bzrEAA | N45: 16/08/2022 | O45: Operational | P45: 1 | Q45: 1 | R45: 1747 | S45: Vacant | U45: 30 | Z45: - | AA45: 0 | AB45: 0 | AH45: 0 | AI45: 0 | AK45: - | AL45: - | AM45: - | AN45: 0 | AO45: - | AP45: - | AQ45: 0 | AR45: - | AS45: 25768.25 | AT45: 14.75 | AU45: 27500 | AV45: 15.741271
A46: Gilders YardA02 | B46: Gilders Yard | C46: Gilders Yard | D46: Stewart Blackford | E46: Vicki Turnbull | G46: Birmingham | H46: Regions | I46: A02 | J46: 222690002 | K46: 222690002 | L46: Gilders Yard - A.02, 1 Harford Street | M46: a1G8d0000004bzmEAA | N46: 16/08/2022 | O46: Operational | P46: 1 | Q46: 1 | R46: 1886 | S46: C Barber Ltd | U46: - | W46: B | X46: 45037 | Y46: 45403 | Z46: - | AA46: 12.032864 | AB46: -22627.8 | AC46: 21/04/2028 | AD46: 21/04/2028 | AE46: 48689 | AG46: 22566 | AH46: 11.965005 | AI46: 18042.394 | AK46: 0 | AL46: 12.032864 | AM46: 22627.8 | AN46: 9.9988446 | AO46: 8.1617075 | AP46: 3.1650231 | AQ46: 5.0021602 | AR46: 3.1650231 | AS46: 22632 | AT46: 12
A47: Gilders YardA01 | B47: Gilders Yard | C47: Gilders Yard | D47: Stewart Blackford | E47: Vicki Turnbull | G47: Birmingham | H47: Regions | I47: A01 | J47: 222690001 | K47: 222690001 | L47: Gilders Yard - A.01, 19/21 Great Hampton St | M47: a1G8d0000004bzhEAA | N47: 16/08/2022 | O47: Operational | P47: 1 | Q47: 1 | R47: 1872 | S47: J S Convenience Stores | U47: - | W47: B | X47: 45107 | Z47: - | AA47: 0 | AB47: 0 | AC47: 46934 | AE47: 50585 | AG47: 27500 | AH47: 14.690171 | AI47: 27500 | AK47: 0 | AL47: 0 | AM47: 0 | AN47: 14.998267 | AO47: 13.352783 | AP47: 3.3566767 | AQ47: - | AR47: - | AS47: 27612 | AT47: 14.75
A48: Gilders YardOffices | B48: Gilders Yard | C48: Gilders Yard | D48: Stewart Blackford | E48: Vicki Turnbull | G48: Birmingham | H48: Regions | I48: Offices | J48: 222690004 | K48: 222690004 | L48: Gilders Yard-Office, 16/18 Great Hampton St | M48: a1G8d0000004bzwEAA | N48: 16/08/2022 | O48: Operational | P48: 1 | Q48: 1 | R48: 1043 | S48: Grainger Residential Management | U48: - | W48: B | X48: 45223 | Z48: - | AA48: 0 | AB48: 0 | AE48: 47049 | AG48: 20000 | AH48: 19.175455 | AI48: 20000 | AK48: 0 | AL48: 0 | AM48: 0 | AN48: 4.9994223 | AO48: 3.6715363 | AP48: - | AQ48: - | AR48: - | AS48: 20000 | AT48: 19.175455
A49: Gatehouse Apartments1 | B49: Gatehouse Apartments | C49: Gatehouse Apartments | D49: Stewart Blackford | E49: Harriet Shaw & Alexa Byrne | G49: Southampton | H49: Regions | I49: 1 | J49: 222662001 | K49: 222662001 | L49: Unit 1, 87 East St, Southampton | M49: a1G8d0000004MdpEAE | O49: Operational | P49: 1 | Q49: 1 | R49: 2508 | S49: Aesthetic House | U49: - | V49: Inclusive | W49: A | X49: 44494 | Y49: 44676 | Z49: - | AA49: 5.9835551 | AB49: -12228.891 | AC49: 46320 | AD49: 45955 | AE49: 48145 | AG49: 24525 | AH49: 9.7787081 | AI49: 21467.843 | AK49: 0 | AL49: 5.9835551 | AM49: 12228.891 | AN49: 9.9961067 | AO49: 6.6722849 | AP49: 1.6756005 | AQ49: 4.0000854 | AR49: 0.67626359 | AS49: 27250 | AT49: 10.865231
A50: The Forge1 | B50: The Forge | C50: The Forge | D50: Bradley Wallace | E50: Vicki Turnbull | G50: Newcastle | H50: Regions | I50: 1 | J50: 222680001 | K50: 222680001 | L50: Unit 1, The Forge, Newcastle, NE1 3AA | M50: a1G8d0000004Gl5EAE | N50: 44475 | O50: Operational | P50: 1 | Q50: 1 | R50: 2901 | S50: Under offer | T50: Sanco Pizza Limited | U50: 40 | W50: B | Z50: - | AA50: 0 | AB50: 0 | AH50: 0 | AI50: 0 | AK50: - | AL50: - | AM50: - | AN50: 0 | AO50: - | AP50: - | AQ50: 0 | AR50: - | AS50: 29010 | AT50: 10 | AU50: 34812 | AV50: 12
A51: The Headline1 | B51: The Headline | C51: The Headline | D51: Stewart Blackford | E51: Vicki Turnbull | G51: Leeds | H51: Regions | I51: 1 | J51: 222669001 | K51: 222669001 | L51: Unit 1, Wellington Park Way, Leeds | M51: a1G8d0000004Jy5EAE | N51: 18/06/2021 | O51: Operational | P51: 1 | Q51: 1 | R51: 3791 | S51: Dexastrong Ltd | U51: - | W51: A | X51: 44756 | Y51: 44940 | Z51: - | AA51: 6.0493084 | AB51: -18335.454 | AC51: 46582 | AD51: 46582 | AE51: 48408 | AF51: -100000 | AG51: 36372 | AH51: 9.5943023 | AI51: 12702.174 | AK51: 32.992412 | AL51: 39.04172 | AM51: 118335.45 | AN51: 9.9988446 | AO51: 7.392355 | AP51: 2.3929327 | AQ51: 4.9994223 | AR51: 2.3929327 | AS51: 30000 | AT51: 7.9134793
A52: Weavers YardBlock A - Unit 1 (Unit A Bamboo House) | B52: Weavers Yard | C52: Weavers Yard | D52: Becky Day / Bradley Wallace | E52: Harriet Shaw & Alexa Byrne | G52: Newbury | H52: Regions | I52: Block A - Unit 1 (Unit A Bamboo House) | J52: 222698001 | K52: 222698001 | L52: Unit A Bamboo House, Weavers Yard, Newbury | M52: a1G8d0000004qhAEAQ | N52: 44655 | O52: Operational | P52: 1 | Q52: 1 | R52: 2166 | S52: Under Offer | T52: Craft Beer | U52: 34 | V52: 0 | Z52: - | AA52: 0 | AB52: 0 | AG52: 0 | AH52: 0 | AI52: 0 | AK52: - | AL52: - | AM52: - | AN52: 0 | AO52: - | AP52: - | AQ52: 0 | AR52: - | AS52: 49818 | AT52: 23 | AU52: 48000 | AV52: 22.160665
A53: Weavers YardBlock B - Unit 2 (Unit A) | B53: Weavers Yard | C53: Weavers Yard | D53: Becky Day / Bradley Wallace | E53: Harriet Shaw & Alexa Byrne | G53: Newbury | H53: Regions | I53: Block B - Unit 2 (Unit A) | J53: 222698002 | K53: 222698002 | L53: Unit A Garter House, Weavers Yard, Newbury | M53: a1G8d0000004qhKEAQ | N53: 13/12/2023 | O53: Operational | P53: 1 | Q53: 1 | R53: 871 | S53: Vacant | U53: 14 | V53: 0 | Z53: - | AA53: 0 | AB53: 0 | AG53: 0 | AH53: 0 | AI53: 0 | AK53: - | AL53: - | AM53: - | AN53: 0 | AO53: - | AP53: - | AQ53: 0 | AR53: - | AS53: 26130 | AT53: 30 | AU53: 20000 | AV53: 22.962113
A54: Weavers YardBlock B - Unit 3 (Unit B) | B54: Weavers Yard | C54: Weavers Yard | D54: Becky Day / Bradley Wallace | E54: Harriet Shaw & Alexa Byrne | G54: Newbury | H54: Regions | I54: Block B - Unit 3 (Unit B) | J54: 222698003 | K54: 222698003 | L54: Unit B Garter House, Weavers Yard, Newbury | M54: a1G8d0000004qhUEAQ | N54: 13/12/2023 | O54: Operational | P54: 1 | Q54: 1 | R54: 1399 | S54: Under Offer | T54: Sundaes Gelato | U54: 14 | V54: 0 | Z54: - | AA54: 0 | AB54: 0 | AG54: 0 | AH54: 0 | AI54: 0 | AK54: - | AL54: - | AM54: - | AN54: 0 | AO54: - | AP54: - | AQ54: 0 | AR54: - | AS54: 41970 | AT54: 30 | AU54: 30000 | AV54: 21.443888
A55: Weavers YardBlock C - Unit 4 (Unit A) | B55: Weavers Yard | C55: Weavers Yard | D55: Becky Day / Bradley Wallace | E55: Harriet Shaw & Alexa Byrne | G55: Newbury | H55: Regions | I55: Block C - Unit 4 (Unit A) | J55: 222698004 | K55: 222698004 | L55: Unit A Purl House, Weavers Yard, Newbury | M55: a1G8d0000004qheEAA | N55: 44655 | O55: Operational | P55: 1 | Q55: 1 | R55: 813 | S55: Vacant | U55: 34 | V55: 0 | Z55: - | AA55: 0 | AB55: 0 | AG55: 0 | AH55: 0 | AI55: 0 | AK55: - | AL55: - | AM55: - | AN55: 0 | AO55: - | AP55: - | AQ55: 0 | AR55: - | AS55: 24390 | AT55: 30 | AU55: 20325 | AV55: 25
A56: Weavers YardBlock D - Unit 5 (Linen Place) | B56: Weavers Yard | C56: Weavers Yard | D56: Becky Day / Bradley Wallace | E56: Harriet Shaw & Alexa Byrne | G56: Newbury | H56: Regions | I56: Block D - Unit 5 (Linen Place) | J56: 222698005 | K56: 222698005 | L56: Unit A Linen Place, Weavers Yard, Newbury | M56: a1G8d0000004qZvEAI | N56: 24/06/2024 | O56: Operational | P56: 1 | Q56: 1 | R56: 1463 | S56: Vacant | U56: 7 | V56: 0 | Z56: - | AA56: 0 | AB56: 0 | AG56: 0 | AH56: 0 | AI56: 0 | AK56: - | AL56: - | AM56: - | AN56: 0 | AO56: - | AP56: - | AQ56: 0 | AR56: - | AS56: 29260 | AT56: 20 | AU56: 32000 | AV56: 21.872864
A57: Weavers YardBlock G - Unit 6 (Unit A) | B57: Weavers Yard | C57: Weavers Yard | D57: Becky Day / Bradley Wallace | E57: Harriet Shaw & Alexa Byrne | G57: Newbury | H57: Regions | I57: Block G - Unit 6 (Unit A) | J57: 222698006 | K57: 222698006 | L57: Unit A Farrow House, Weavers Yard, Newbury | M57: a1G8d0000004qeREAQ | N57: 30/08/2023 | O57: Operational | P57: 1 | Q57: 1 | R57: 364 | S57: Vacant | U57: 17 | V57: 0 | Z57: - | AA57: 0 | AB57: 0 | AG57: 0 | AH57: 0 | AI57: 0 | AK57: - | AL57: - | AM57: - | AN57: 0 | AO57: - | AP57: - | AQ57: 0 | AR57: - | AS57: 10010 | AT57: 27.5 | AU57: 8400 | AV57: 23.076923
A58: Weavers YardBlock H - Unit 7 (5 Station Approach) | B58: Weavers Yard | C58: Weavers Yard | D58: Becky Day / Bradley Wallace | E58: Harriet Shaw & Alexa Byrne | G58: Newbury | H58: Regions | I58: Block H - Unit 7 (5 Station Approach) | J58: 222698007 | K58: 222698007 | L58: 5 Station Approach, Weavers Yard, Newbury | M58: a1G8d0000004qhoEAA | N58: 17/06/2024 | O58: Operational | P58: 1 | Q58: 1 | R58: 361 | S58: Vacant | U58: 8 | V58: 0 | Z58: - | AA58: 0 | AB58: 0 | AG58: 0 | AH58: 0 | AI58: 0 | AK58: - | AL58: - | AM58: - | AN58: 0 | AO58: - | AP58: - | AQ58: 0 | AR58: - | AS58: 9928 | AT58: 27.501385 | AU58: 10000 | AV58: 27.700831
A59: Weavers YardBlock H - Unit 8 (4 Station Approach) | B59: Weavers Yard | C59: Weavers Yard | D59: Becky Day / Bradley Wallace | E59: Harriet Shaw & Alexa Byrne | G59: Newbury | H59: Regions | I59: Block H - Unit 8 (4 Station Approach) | J59: 222698008 | K59: 222698008 | L59: 4 Station Approach, Weavers Yard, Newbury | M59: a1G8d0000004qf5EAA | N59: 17/06/2024 | O59: Operational | P59: 1 | Q59: 1 | R59: 646 | S59: Under Offer | T59: Parasol Coffee | U59: 8 | V59: 0 | Z59: - | AA59: 0 | AB59: 0 | AG59: 0 | AH59: 0 | AI59: 0 | AK59: - | AL59: - | AM59: - | AN59: 0 | AO59: - | AP59: - | AQ59: 0 | AR59: - | AS59: 12274 | AT59: 19 | AU59: 16150 | AV59: 25
A60: Weavers YardBlock H - Unit 9 (3 Station Approach) | B60: Weavers Yard | C60: Weavers Yard | D60: Becky Day / Bradley Wallace | E60: Harriet Shaw & Alexa Byrne | G60: Newbury | H60: Regions | I60: Block H - Unit 9 (3 Station Approach) | J60: 222698009 | K60: 222698009 | L60: 3 Station Approach, Weavers Yard, Newbury | M60: a1G8d0000004qi3EAA | N60: 17/06/2024 | O60: Operational | P60: 1 | Q60: 1 | R60: 616 | S60: Under Offer | T60: Strawberry Local | U60: 8 | V60: 0 | Z60: - | AA60: 0 | AB60: 0 | AG60: 0 | AH60: 0 | AI60: 0 | AK60: - | AL60: - | AM60: - | AN60: 0 | AO60: - | AP60: - | AQ60: 0 | AR60: - | AS60: 12000 | AT60: 19.480519 | AU60: 14000 | AV60: 22.727273
A61: Exchange Square1 | B61: Exchange Square | C61: The Silver Yard | D61: Bradley Wallace | E61: Sarah Norstrom | G61: Birmingham | H61: Regions | I61: 1 | J61: 222795001 | K61: 222795001 | L61: Commercial Unit, 98 Moor Street Queensway | M61: a1GNz000001HUHFMA4 | N61: 45331 | O61: Operational | P61: 1 | Q61: 1 | R61: 2104 | S61: Under Offer | T61: Londis | U61: 12 | Z61: - | AA61: 0 | AB61: 0 | AG61: 0 | AH61: 0 | AI61: 0 | AK61: - | AL61: - | AM61: - | AN61: 0 | AO61: - | AP61: - | AQ61: 0 | AR61: - | AS61: 33700 | AT61: 16.01711 | AU61: 39008.16 | AV61: 18.54
A62: Capital QuarterMSCP Car Park Office + 5 Parking spaces | B62: Capital Quarter | C62: The Copper Works | D62: Stewart Blackford | E62: Sarah Norstrom | G62: Cardiff | H62: Regions | I62: MSCP Car Park Office + 5 Parking spaces | J62: 222798001 | K62: 222798001 | L62: MSCP Office | M62: a1GNz000002oc8BMAQ | N62: please add | O62: Operational | P62: 1 | Q62: 1 | R62: 1570 | S62: Specialist Security Co Ltd | U62: - | X62: 44655 | Z62: - | AA62: 0 | AB62: 0 | AD62: 45750 | AE62: 46480 | AG62: 18250 | AH62: 11.624204 | AI62: 18250 | AK62: 0 | AL62: 0 | AM62: 0 | AN62: 4.9966844 | AO62: 2.1136659 | AP62: - | AQ62: 2.9980106 | AR62: 0.11499219 | AS62: #N/A | AT62: #N/A | AU62: 22500 | AV62: 14.33121 | AW62: this is on the market as the tenant will be vacating in a few months
A63: Capital Quarter1 | B63: Capital Quarter | C63: The Copper Works | D63: Stewart Blackford | E63: Sarah Norstrom | G63: Cardiff | H63: Regions | I63: 1 | J63: 222736001 | K63: 222736001 | L63: Copperworks, 5 Capital Quarter, Cardiff | M63: a1G8d000002PHNdEAO | N63: 45150 | O63: Operational | P63: 1 | Q63: 1 | R63: 2132 | S63: Vacant | U63: 18 | V63: No Service charge | Z63: - | AA63: 0 | AB63: 0 | AG63: 0 | AH63: 0 | AI63: 0 | AK63: - | AL63: - | AM63: - | AN63: 0 | AO63: - | AP63: - | AQ63: 0 | AR63: - | AS63: 35000 | AT63: 16.41651 | AU63: 32000 | AV63: 15.009381
A64: Enigma Square1 | B64: Enigma Square | C64: Enigma Square | D64: Bradley Wallace | E64: Sarah Norstrom | G64: Milton Keynes | H64: Regions | I64: 1 | J64: 222711001 | K64: 222711001 | L64: Commercial unit 1 Enigma Square | M64: a1G8d0000005r5aEAA | N64: 44722 | O64: Operational | P64: 1 | Q64: 1 | R64: 5489 | S64: Krishna Asian Food Market Limited | U64: - | X64: 45645 | Y64: 19/12/2025 | Z64: 9 | AA64: 11.999987 | AB64: -137224.85 | AC64: 47471 | AD64: 51122 | AE64: 51122 | AF64: 0 | AG64: 137225 | AH64: 25 | AI64: 128073.95 | AK64: 0 | AL64: 11.999987 | AM64: 137224.85 | AN64: 14.995529 | AO64: 14.823041 | AP64: 4.826934 | AQ64: 14.995529 | AR64: 14.823041
A65: Enigma Square2 | B65: Enigma Square | C65: Enigma Square | D65: Bradley Wallace | E65: Sarah Norstrom | G65: Milton Keynes | H65: Regions | I65: 2 | J65: 222711002 | K65: 222711002 | L65: Commercial unit 2 Enigma Square | M65: a1G8d0000005r5fEAA | N65: 44722 | O65: Operational | P65: 1 | Q65: 1 | R65: 1241 | S65: Vacant | U65: 32 | Z65: - | AA65: 0 | AB65: 0 | AG65: 0 | AH65: 0 | AI65: 0 | AK65: - | AL65: - | AM65: - | AN65: 0 | AO65: - | AP65: - | AQ65: 0 | AR65: - | AS65: 27922.5 | AT65: 22.5 | AU65: 31000 | AV65: 24.979855
A66: Enigma Square3 | B66: Enigma Square | C66: Enigma Square | D66: Bradley Wallace | E66: Sarah Norstrom | G66: Milton Keynes | H66: Regions | I66: 3 | J66: 222711003 | K66: 222711003 | L66: Commercial unit 3 Enigma Square | M66: a1G8d0000005r5kEAA | N66: 44722 | O66: Operational | P66: 1 | Q66: 1 | R66: 1492 | S66: Vacant | U66: 32 | Z66: - | AA66: 0 | AB66: 0 | AG66: 0 | AH66: 0 | AI66: 0 | AK66: - | AL66: - | AM66: - | AN66: 0 | AO66: - | AP66: - | AQ66: 0 | AR66: - | AS66: 26572.5 | AT66: 17.809987 | AU66: 38000 | AV66: 25.469169
A67: Block D2 Hallsville Q Unit 1 | B67: Block D2 Hallsville Q | C67: Nautilus Apartments | D67: Bradley Wallace | E67: Harriet Shaw & Alexa Byrne | F67: Kate Casey | G67: London | H67: London | I67: Unit 1 | J67: 222746001 | K67: 222746001 | L67: Commercial unit 1, 18 Silvertown way, London | M67: a1G8d000002QBVNEA4 | N67: 28/07/2023 | O67: Operational | P67: 1 | Q67: 1 | R67: 2862 | S67: Vacant | T67: Kiki Miu Miu | U67: 18 | W67: A | Z67: - | AA67: 0 | AB67: 0 | AG67: 0 | AH67: 0 | AI67: 0 | AK67: - | AL67: - | AM67: - | AN67: 0 | AO67: - | AP67: - | AQ67: 0 | AR67: - | AS67: 61533 | AT67: 21.5 | AU67: 94446 | AV67: 33
A68: Block D2 Hallsville Q Unit 2 | B68: Block D2 Hallsville Q | C68: Nautilus Apartments | D68: Bradley Wallace | E68: Harriet Shaw & Alexa Byrne | F68: Kate Casey | G68: London | H68: London | I68: Unit 2 | J68: 222746002 | K68: 222746002 | L68: Commercial unit 2, 18 Silvertown way, London | M68: a1G8d000002QBVSEA4 | N68: 28/07/2023 | O68: Operational | P68: 1 | Q68: 1 | R68: 1819 | S68: Vacant | T68: Kiki Miu Miu | U68: 18 | W68: A | Z68: - | AA68: 0 | AB68: 0 | AG68: 0 | AH68: 0 | AI68: 0 | AK68: - | AL68: - | AM68: - | AN68: 0 | AO68: - | AP68: - | AQ68: 0 | AR68: - | AS68: 45020 | AT68: 24.749863 | AU68: 54570 | AV68: 30
A69: Block D2 Hallsville Q Unit 3 | B69: Block D2 Hallsville Q | C69: Nautilus Apartments | D69: Bradley Wallace | E69: Harriet Shaw & Alexa Byrne | F69: Kate Casey | G69: London | H69: London | I69: Unit 3 | J69: 222746003 | K69: 222746003 | L69: Commercial unit 3, 18 Silvertown way, London | M69: a1G8d000002QBVXEA4 | N69: 28/07/2023 | O69: Operational | P69: 1 | Q69: 1 | R69: 1035 | S69: Vacant | T69: NewCo (247 Dental) | U69: 18 | W69: A | Z69: - | AA69: 0 | AB69: 0 | AG69: 0 | AH69: 0 | AI69: 0 | AK69: - | AL69: - | AM69: - | AN69: 0 | AO69: - | AP69: - | AQ69: 0 | AR69: - | AS69: 31050 | AT69: 30 | AU69: 35000 | AV69: 34
A70: Block D2 Hallsville Q Unit 4 | B70: Block D2 Hallsville Q | C70: Nautilus Apartments | D70: Bradley Wallace | E70: Harriet Shaw & Alexa Byrne | F70: Kate Casey | G70: London | H70: London | I70: Unit 4 | J70: 222746004 | K70: 222746004 | L70: Commercial unit 4, 18 Silvertown way, London | M70: a1G8d000002QBVcEAO | N70: 28/07/2023 | O70: Operational | P70: 1 | Q70: 1 | R70: 2772 | S70: Under Offer | T70: Norman H Barnett | U70: 18 | W70: A | Z70: - | AA70: 0 | AB70: 0 | AG70: 0 | AH70: 0 | AI70: 0 | AK70: - | AL70: - | AM70: - | AN70: 0 | AO70: - | AP70: - | AQ70: 0 | AR70: - | AS70: 60430 | AT70: 21.800144 | AU70: 86000 | AV70: 31
A71: Block D2 Hallsville Q Workspace | B71: Block D2 Hallsville Q | C71: Nautilus Apartments | D71: Bradley Wallace | E71: Harriet Shaw & Alexa Byrne | F71: Kate Casey | G71: London | H71: London | I71: Workspace | J71: 222746005 | K71: 222746005 | L71: Commercial unit 5, 18 Silvertown way, London | M71: a1G8d000002QBVhEAO | N71: 28/07/2023 | O71: Operational | P71: 1 | Q71: 1 | R71: 4146 | S71: Vacant | U71: 18 | W71: A | Z71: - | AA71: 0 | AB71: 0 | AG71: 0 | AH71: 0 | AI71: 0 | AK71: - | AL71: - | AM71: - | AN71: 0 | AO71: - | AP71: - | AQ71: 0 | AR71: - | AS71: 103650 | AT71: 25 | AU71: 103650 | AV71: 25
A72: Block D1 Hallsville Q Unit 1 | B72: Block D1 Hallsville Q | C72: Seraphina Apartments | D72: Becky Day / Bradley Wallace | E72: Sarah Norstrom | F72: Kate Casey | G72: London | H72: London | I72: Unit 1 | K72: #N/A | L72: Not on Qube yet | M72: Not on SF yet | N72: est 15/05/2025 | O72: Under Construction | P72: 1 | Q72: 1 | R72: 2746 | S72: Vacant | U72: - | Z72: - | AA72: 0 | AB72: 0 | AG72: 0 | AH72: 0 | AI72: 0 | AK72: - | AL72: - | AM72: - | AN72: 0 | AO72: - | AP72: - | AQ72: 0 | AR72: - | AS72: 68650 | AT72: 25 | AU72: 100000 | AV72: 36.4
A73: Block D1 Hallsville Q Unit 2 | B73: Block D1 Hallsville Q | C73: Seraphina Apartments | D73: Becky Day / Bradley Wallace | E73: Sarah Norstrom | F73: Kate Casey | G73: London | H73: London | I73: Unit 2 | K73: #N/A | L73: Not on Qube yet | M73: Not on SF yet | N73: est 15/05/2025 | O73: Under Construction | P73: 1 | Q73: 1 | R73: 1247 | S73: Vacant | T73: Holland & Barrett | U73: - | Z73: - | AA73: 0 | AB73: 0 | AG73: 0 | AH73: 0 | AI73: 0 | AK73: - | AL73: - | AM73: - | AN73: 0 | AO73: - | AP73: - | AQ73: 0 | AR73: - | AS73: 31175 | AT73: 25 | AU73: 40000 | AV73: 32
A74: Block D1 Hallsville Q Unit 3 | B74: Block D1 Hallsville Q | C74: Seraphina Apartments | D74: Becky Day / Bradley Wallace | E74: Sarah Norstrom | F74: Kate Casey | G74: London | H74: London | I74: Unit 3 | K74: #N/A | L74: Not on Qube yet | M74: Not on SF yet | N74: est 15/05/2025 | O74: Under Construction | P74: 1 | Q74: 1 | R74: 1124 | S74: Vacant | T74: Nail luxury (interest) | U74: - | Z74: - | AA74: 0 | AB74: 0 | AG74: 0 | AH74: 0 | AI74: 0 | AK74: - | AL74: - | AM74: - | AN74: 0 | AO74: - | AP74: - | AQ74: 0 | AR74: - | AS74: 28100 | AT74: 25 | AU74: 38000 | AV74: 34
A75: Block D1 Hallsville Q Unit 4 | B75: Block D1 Hallsville Q | C75: Seraphina Apartments | D75: Becky Day / Bradley Wallace | E75: Sarah Norstrom | F75: Kate Casey | G75: London | H75: London | I75: Unit 4 | K75: #N/A | L75: Not on Qube yet | M75: Not on SF yet | N75: est 15/05/2025 | O75: Under Construction | P75: 1 | Q75: 1 | R75: 1182 | S75: Vacant | T75: Nandos Chickenland Ltd | U75: - | Z75: - | AA75: 0 | AB75: 0 | AG75: 0 | AH75: 0 | AI75: 0 | AK75: - | AL75: - | AM75: - | AN75: 0 | AO75: - | AP75: - | AQ75: 0 | AR75: - | AS75: 29550 | AT75: 25 | AU75: 40000 | AV75: 34
A76: Block D1 Hallsville Q Unit 5 | B76: Block D1 Hallsville Q | C76: Seraphina Apartments | D76: Becky Day / Bradley Wallace | E76: Sarah Norstrom | F76: Kate Casey | G76: London | H76: London | I76: Unit 5 | K76: #N/A | L76: Not on Qube yet | M76: Not on SF yet | N76: est 15/05/2025 | O76: Under Construction | P76: 1 | Q76: 1 | R76: 2518 | S76: Vacant | T76: Nandos Chickenland Ltd | U76: - | Z76: - | AA76: 0 | AB76: 0 | AG76: 0 | AH76: 0 | AI76: 0 | AK76: - | AL76: - | AM76: - | AN76: 0 | AO76: - | AP76: - | AQ76: 0 | AR76: - | AS76: 62950 | AT76: 25 | AU76: 83000 | AV76: 33
A77: Block D1 Hallsville Q Unit 6 | B77: Block D1 Hallsville Q | C77: Seraphina Apartments | D77: Becky Day / Bradley Wallace | E77: Sarah Norstrom | F77: Kate Casey | G77: London | H77: London | I77: Unit 6 | K77: #N/A | L77: Not on Qube yet | M77: Not on SF yet | N77: est 15/05/2025 | O77: Under Construction | P77: 1 | Q77: 1 | R77: 2180 | S77: Vacant | U77: - | Z77: - | AA77: 0 | AB77: 0 | AG77: 0 | AH77: 0 | AI77: 0 | AK77: - | AL77: - | AM77: - | AN77: 0 | AO77: - | AP77: - | AQ77: 0 | AR77: - | AS77: 54500 | AT77: 25 | AU77: 54500 | AV77: 25
A78: Queens Road1 | B78: Queens Road | C78: The Barnum | D78: Bradley Wallace | E78: Vicki Turnbull | G78: Nottingham | H78: Regions | I78: 1 | J78: 222761001 | K78: 222761001 | L78: Commercial unit, 21 Queens Road | M78: a1GNz0000000zgDMAQ | N78: 45179 | O78: Operational | P78: 1 | Q78: 1 | R78: 1800 | S78: Vacant | U78: 17 | Z78: - | AA78: 0 | AB78: 0 | AG78: 0 | AH78: 0 | AI78: 0 | AK78: - | AL78: - | AM78: - | AN78: 0 | AO78: - | AP78: - | AQ78: 0 | AR78: - | AS78: 22500 | AT78: 12.5 | AU78: 25000 | AV78: 13.888889
A79: The Tilt Works1 | B79: The Tilt Works | C79: The Tilt Works | D79: Bradley Wallace | E79: Vicki Turnbull | G79: Sheffield | H79: Regions | I79: 1 | J79: 222757001 | K79: 222757001 | L79: 86 Upper Allen Street, Sheffield | M79: a1GNz0000000v37MAA | N79: 18/08/2023 | O79: Operational | P79: 1 | Q79: 1 | R79: 613 | S79: Under Offer | U79: 18 | Z79: - | AA79: 0 | AB79: 0 | AG79: 0 | AH79: 0 | AI79: 0 | AK79: - | AL79: - | AM79: - | AN79: 0 | AO79: - | AP79: - | AQ79: 0 | AR79: - | AS79: 9384 | AT79: 15.30832 | AU79: 12000 | AV79: 19.575856
A80: The Condor1 | B80: The Condor | C80: The Condor | D80: Stewart Blackford | E80: Vicki Turnbull | G80: Derby | H80: Regions | I80: 1 | J80: 222740001 | K80: 222740001 | L80: Commercial Unit 1, 1 Springwell Sq | M80: a1G8d000002QBf5EAG | N80: 31/07/2023 | O80: Operational | P80: 1 | Q80: 1 | R80: 4266 | S80: Phenix UK Realty | T80: Phenix Realty | U80: - | V80: exclusive | X80: 45471 | Y80: 46009 | Z80: 9 | AA80: 17.687652 | AB80: -73698.549 | AC80: 47297 | AE80: 50948 | AG80: 50000 | AH80: 11.720581 | AI80: 45085.298 | AK80: 0 | AL80: 17.687652 | AM80: 73698.549 | AN80: 14.995529 | AO80: 14.346645 | AP80: 4.3505378 | AQ80: - | AR80: - | AS80: 50125.5 | AT80: 11.75
A81: The Condor2 | B81: The Condor | C81: The Condor | D81: Stewart Blackford | E81: Vicki Turnbull | G81: Derby | H81: Regions | I81: 2 | J81: 222740002 | K81: 222740002 | L81: Commercial Unit 2, 1 Springwell Sq | M81: a1G8d000002QBhOEAW | N81: 31/07/2023 | O81: Operational | P81: 1 | Q81: 1 | R81: 2590 | S81: Coffee #1 | U81: - | V81: exclusive | X81: 45229 | Y81: 45595 | Z81: - | AA81: 12.032864 | AB81: -31586.267 | AC81: 47056 | AD81: 47420 | AE81: 48881 | AF81: 0 | AG81: 31500 | AH81: 12.162162 | AI81: 26234.533 | AK81: 0 | AL81: 12.032864 | AM81: 31586.267 | AN81: 9.9988446 | AO81: 8.6873861 | AP81: 3.6907017 | AQ81: 5.9987592 | AR81: 4.6873006 | AS81: 31500 | AT81: 12.162162
A82: The Astley1 | B82: The Astley | C82: The Astley | D82: Stewart Blackford | E82: Vicki Turnbull | G82: Manchester | H82: Regions | I82: 1 | J82: 222801001 | K82: 222801001 | L82: Commercial Unit 1, Great Ancoats Street | M82: a1GNz000002tEQzMAM | N82: 22/05/2024 | O82: Operational | P82: 1 | Q82: 1 | R82: 3481 | S82: Colony (Astley) Ltd | U82: - | X82: 43719 | Z82: - | AA82: 0 | AB82: 0 | AC82: 47372 | AD82: 47372 | AE82: 51024 | AF82: 0 | AG82: 48734 | AH82: 14 | AS82: 41750 | AT82: 11.99368
A83: The Astley2 | B83: The Astley | C83: The Astley | D83: Stewart Blackford | E83: Vicki Turnbull | G83: Manchester | H83: Regions | I83: 2 | J83: 222801002 | K83: 222801002 | L83: Commercial Unit 2, Great Ancoats Street | M83: a1GNz000002tESbMAM | N83: 22/05/2024 | O83: Operational | P83: 1 | Q83: 1 | R83: 1483.58 | S83: The Victoria Altrincham | U83: - | X83: 43579 | Z83: - | AA83: 0 | AB83: 0 | AC83: 45405 | AE83: 47231 | AF83: 0 | AG83: 37997 | AH83: 25.611696 | AS83: 16500 | AT83: 11.121746
A84: The Astley3 | B84: The Astley | C84: The Astley | D84: Stewart Blackford | E84: Vicki Turnbull | G84: Manchester | H84: Regions | I84: 3 | J84: 222801003 | K84: 222801003 | L84: Commercial Unit 3, Great Ancoats Street | M84: a1GNz000002tCFWMA2 | N84: 22/05/2024 | O84: Operational | P84: 1 | Q84: 1 | R84: 526 | S84: Not Just Barbers | U84: - | X84: 43532 | Z84: - | AA84: 0 | AB84: 0 | AC84: 45359 | AE84: 47184 | AF84: 0 | AG84: 17500 | AH84: 33.269962 | AS84: 8500 | AT84: 16.159696
A85: Merrick Place1 | B85: Merrick Place | C85: Merrick Place | D85: Becky Day | E85: Sarah Norstrom | F85: Jessica Leedham | G85: London | H85: London | I85: 1 | K85: #N/A | L85: Not on Qube yet | M85: Not on SF yet | N85: est 01/04/2026 | O85: Under Construction | P85: 1 | Q85: 1 | R85: 1531 | S85: Vacant | U85: - | Z85: - | AA85: 0 | AB85: 0 | AG85: 0 | AH85: 0 | AI85: 0 | AK85: - | AL85: - | AM85: - | AN85: 0 | AO85: - | AP85: - | AQ85: 0 | AR85: - | AS85: #N/A | AT85: #N/A
A86: Merrick Place2 | B86: Merrick Place | C86: Merrick Place | D86: Becky Day | E86: Sarah Norstrom | F86: Jessica Leedham | G86: London | H86: London | I86: 2 | K86: #N/A | L86: Not on Qube yet | M86: Not on SF yet | N86: est 01/09/2026 | O86: Under Construction | P86: 1 | Q86: 1 | R86: 1178 | S86: Vacant | U86: - | Z86: - | AA86: 0 | AB86: 0 | AG86: 0 | AH86: 0 | AI86: 0 | AK86: - | AL86: - | AM86: - | AN86: 0 | AO86: - | AP86: - | AQ86: 0 | AR86: - | AS86: #N/A | AT86: #N/A
A87: Merrick Place3 | B87: Merrick Place | C87: Merrick Place | D87: Becky Day | E87: Sarah Norstrom | F87: Jessica Leedham | G87: London | H87: London | I87: 3 | K87: #N/A | L87: Not on Qube yet | M87: Not on SF yet | N87: est 01/09/2026 | O87: Under Construction | P87: 1 | Q87: 1 | R87: 15823 | S87: Vacant | U87: - | Z87: - | AA87: 0 | AB87: 0 | AG87: 0 | AH87: 0 | AI87: 0 | AK87: - | AL87: - | AM87: - | AN87: 0 | AO87: - | AP87: - | AQ87: 0 | AR87: - | AS87: #N/A | AT87: #N/A
A88: West Way Square1 | B88: West Way Square | C88: The Kimmeridge | D88: Becky Day | E88: Sarah Norstrom | F88: Katherine Stephens | G88: Oxford | H88: Regions | I88: 1 | J88: 222813001 | K88: 222813001 | L88: The Kimmeridge Retail Unit 1 | M88: a1GNz000006cEcoMAE | N88: 45645 | O88: Operational | P88: 1 | Q88: 1 | R88: 1842 | S88: Vacant | U88: 2 | Z88: - | AA88: 0 | AB88: 0 | AG88: 0 | AH88: 0 | AI88: 0 | AK88: - | AL88: - | AM88: - | AN88: 0 | AO88: - | AP88: - | AQ88: 0 | AR88: - | AS88: 80500 | AT88: 43.702497 | AU88: 59000 | AV88: 32.030402
A89: West Way Square2 | B89: West Way Square | C89: The Kimmeridge | D89: Becky Day | E89: Sarah Norstrom | F89: Katherine Stephens | G89: Oxford | H89: Regions | I89: 2 | J89: 222813002 | K89: 222813002 | L89: The Kimmeridge Retail Unit 2 | M89: a1GNz000006cG0HMAU | N89: 45645 | O89: Operational | P89: 1 | Q89: 1 | R89: 1132.4 | S89: Vacant | U89: 2 | Z89: - | AA89: 0 | AB89: 0 | AG89: 0 | AH89: 0 | AI89: 0 | AK89: - | AL89: - | AM89: - | AN89: 0 | AO89: - | AP89: - | AQ89: 0 | AR89: - | AS89: 33960 | AT89: 29.989403 | AU89: 32500 | AV89: 28.700106
A90: West Way Square3 | B90: West Way Square | C90: The Kimmeridge | D90: Becky Day | E90: Sarah Norstrom | F90: Katherine Stephens | G90: Oxford | H90: Regions | I90: 3 | J90: 222813003 | K90: 222813003 | L90: The Kimmeridge Retail Unit 3 | M90: a1GNz000006c7eYMAQ | N90: 45645 | O90: Operational | P90: 1 | Q90: 1 | R90: 1132.4 | S90: Vacant | U90: 2 | Z90: - | AA90: 0 | AB90: 0 | AG90: 0 | AH90: 0 | AI90: 0 | AK90: - | AL90: - | AM90: - | AN90: 0 | AO90: - | AP90: - | AQ90: 0 | AR90: - | AS90: 33960 | AT90: 29.989403 | AU90: 32500 | AV90: 28.700106
A91: West Way Square4 | B91: West Way Square | C91: The Kimmeridge | D91: Becky Day | E91: Sarah Norstrom | F91: Katherine Stephens | G91: Oxford | H91: Regions | I91: 4 | J91: 222813004 | K91: 222813004 | L91: The Kimmeridge Retail Unit 4 | M91: a1GNz000006cG8LMAU | N91: 45645 | O91: Operational | P91: 1 | Q91: 1 | R91: 1080.7 | S91: Vacant | U91: 2 | Z91: - | AA91: 0 | AB91: 0 | AG91: 0 | AH91: 0 | AI91: 0 | AK91: - | AL91: - | AM91: - | AN91: 0 | AO91: - | AP91: - | AQ91: 0 | AR91: - | AS91: 32430 | AT91: 30.008328 | AU91: 31000 | AV91: 28.685112
A92: West Way Square5 | B92: West Way Square | C92: The Kimmeridge | D92: Becky Day | E92: Sarah Norstrom | F92: Katherine Stephens | G92: Oxford | H92: Regions | I92: 5 | J92: 222813005 | K92: 222813005 | L92: The Kimmeridge Retail Unit 5 | M92: a1GNz000006cENWMA2 | N92: 45645 | O92: Operational | P92: 1 | Q92: 1 | R92: 2079.6 | S92: Vacant | U92: 2 | Z92: - | AA92: 0 | AB92: 0 | AG92: 0 | AH92: 0 | AI92: 0 | AK92: - | AL92: - | AM92: - | AN92: 0 | AO92: - | AP92: - | AQ92: 0 | AR92: - | AS92: 62400 | AT92: 30.00577 | AU92: 68000 | AV92: 32.698596
A93: West Way Square6 | B93: West Way Square | C93: The Kimmeridge | D93: Becky Day | E93: Sarah Norstrom | F93: Katherine Stephens | G93: Oxford | H93: Regions | I93: 6 | J93: 222813006 | K93: 222813006 | L93: The Kimmeridge Retail Unit 6 | M93: a1GNz000006cGGPMA2 | N93: 45645 | O93: Operational | P93: 1 | Q93: 1 | R93: 1305.7 | S93: Vacant | U93: 2 | Z93: - | AA93: 0 | AB93: 0 | AG93: 0 | AH93: 0 | AI93: 0 | AK93: - | AL93: - | AM93: - | AN93: 0 | AO93: - | AP93: - | AQ93: 0 | AR93: - | AS93: 39180 | AT93: 30.006893 | AU93: 38500 | AV93: 29.486099
A94: West Way Square7 | B94: West Way Square | C94: The Kimmeridge | D94: Becky Day | E94: Sarah Norstrom | F94: Katherine Stephens | G94: Oxford | H94: Regions | I94: 7 | J94: 222813007 | K94: 222813007 | L94: The Kimmeridge Retail Unit 7 | M94: a1GNz000006cGMrMAM | N94: 45645 | O94: Operational | P94: 1 | Q94: 1 | R94: 995.7 | S94: Vacant | U94: 2 | Z94: - | AA94: 0 | AB94: 0 | AG94: 0 | AH94: 0 | AI94: 0 | AK94: - | AL94: - | AM94: - | AN94: 0 | AO94: - | AP94: - | AQ94: 0 | AR94: - | AS94: 29880 | AT94: 30.009039 | AU94: 29000 | AV94: 29.125239
A95: Hale Wharf 21 | B95: Hale Wharf 2 | C95: Hale Wharf 2 | D95: Bradley Wallace | E95: Sarah Norstrom | F95: Ganesh Vijayan | G95: London | H95: London | I95: 1 | J95: 222808001 | K95: 222808001 | L95: Commerical Approach, 6 Ferry Lane, Tottenham | M95: a1GNz0000054K5KMAU | N95: 45561 | O95: Operational | P95: 1 | Q95: 1 | R95: 1159 | S95: Vacant | U95: 4 | Z95: - | AA95: 0 | AB95: 0 | AG95: 0 | AH95: 0 | AI95: 0 | AK95: - | AL95: - | AM95: - | AN95: 0 | AO95: - | AP95: - | AQ95: 0 | AR95: - | AS95: 26078 | AT95: 22.500431 | AU95: 29000 | AV95: 25.02157
A96: Hale Wharf 22 | B96: Hale Wharf 2 | C96: Hale Wharf 2 | D96: Bradley Wallace | E96: Sarah Norstrom | F96: Ganesh Vijayan | G96: London | H96: London | I96: 2 | K96: #N/A | L96: This is not a Commercial unit-it is being converted to an amenity | M96: This is not a Commercial unit-it is being converted to an amenity | N96: 45562 | O96: Operational | P96: 1 | Q96: 1 | R96: 763 | S96: Vacant | U96: 4 | Z96: - | AA96: 0 | AB96: 0 | AG96: 0 | AH96: 0 | AI96: 0 | AK96: - | AL96: - | AM96: - | AN96: 0 | AO96: - | AP96: - | AQ96: 0 | AR96: - | AS96: 19075 | AT96: 25 | AU96: 19000 | AV96: 24.901704

Sheet PRS Quoting rents
B1: Address | D1: Qube ref | E1: Qube description | F1: Salesforce id | G1: Quoting rent | H1: QR £psf | J1: Lessee / Assignee | K1: Description | L1: Use Class | N1: Term | O1: Start | P1: Expiry | Q1: Rent Review | R1: Earliest Break Date / Landlord & Tenants Enforcement | S1: Excluded from '54 Act | T1: Service Charge | U1: Insurance | V1: Rent Deposit | W1: Current Rent (p.a.) | X1: CBRE September 2024 ERV | AB1: Measured Floor Areas | AC1: NIA | AD1: ITZA (sq. ft.) | AH1: £/Sqft | AI1: Remarks / Action
A2: 1 | B2: Ospringe House | C2: Ospringe House, SE1 8TP | D2: 317670001 | E2: Ospringe House Grnd Flr office Wooton St SE1 | F2: a1G4J0000025yKMUAY | G2: 25000 | H2: 26.096033 | I2: 1 | J2: VACANT | K2: Office | L2: B1 | M2: 1 | AB2: 958 | AC2: Keys held with Rebecca Crow / Maria Dev | AI2: Refresh quote requested
A3: 1 | B3: 16 & 18 | C3: Wilcox Rd, SW8 2UX | D3: 317652009 | E3: 16/18 Wilcox Road London SW8 2UX | F3: a1G4J000002632zUAA | G3: 35000 | H3: 37.768426 | I3: 1 | J3: Colin Gallagher 27/11/24 -lease forfieted | K3: Ground floor shop and yard | L3: A1 | M3: 1 | N3: 10 years | O3: 21/11/2022 | P3: 20/11/2032 | Q3: 21/11/2027 | R3: 21/11/2027 | S3: Yes | T3: Exclusive | U3: Exclusive | V3: £1743.91 (Holding £1644.08) | W3: 27000 | X3: 23000 | AB3: 926.7 | AC3: 906 | AD3: 493 | AH3: 29.135643 | AI3: 27/11/24 russell cooke forfieted lease, houston lawrence estimated rent between £30-£35k, passing rent £28k need to inspect. 13/01 agent opinion awaited, exploring refresh of unit. Pedro owns 32/34 viewed wk comm 2nd feb. viewing with estate agent scheduled 06/02. Collin gallagher is offering to pay arrears off. QR £35k
A4: 1 | B4: G01 | C4: ABILITY PLAZA, 298-316 KINGSLAND RD, 1A ARBUTUS ST, E8 4DT | D4: 418576001 | E4: Unit 1 Ability Plaza, London, E8 | F4: a1G4J0000025zy0UAA | G4: 22770 | H4: 22.5 | J4: VACANT | K4: Ground floor | L4: B1 with ancillary A2 | O4: 45398 | W4: 0 | X4: 22300 | Z4: 0 | AA4: 1012 | AB4: 1012 | AD4: BKR | AE4: D82 | AF4: 44898 | AH4: 0 | AI4: lease discalimed 08/10/24 on market Strettons / Ellis Brown at "22.50 psf | AJ4: Ellis Brown | AK4: Rightmove
A5: 1 | B5: G02 (SEE ABOVE) | C5: ABILITY PLAZA, 298-316 KINGSLAND RD, 1A ARBUTUS ST, E8 4DT | D5: 418576002 | E5: Unit 2 Ability Plaza, London, E8 | F5: a1G4J000002600AUAQ | G5: 22522.5 | H5: 22.5 | J5: VACANT | K5: Ground floor | L5: B1 | N5: At Will | O5: 45177 | P5: monthly | R5: Tenancy at will | W5: 0 | X5: 59800 | Z5: 5405 | AA5: 1001 | AB5: 1001 | AD5: BKR | AE5: D78 | AF5: 44988 | AH5: 59.74026 | AI5: as above | AJ5: Strettons | AK5: Rightmove Zoopla
A6: 1 | B6: G03 | C6: ABILITY PLAZA, 298-316 KINGSLAND RD, 1A ARBUTUS ST, E8 4DT | D6: 418576003 | E6: Unit 3 Ability Plaza, London, E8 | F6: a1G4J0000025zx3UAA | G6: 19350 | H6: 22.5 | J6: VACANT | K6: Ground & Mezzanine floor | L6: B1 | R6: Tenancy at will | W6: 0 | X6: 0 | Z6: 0 | AA6: 860 | AB6: 1001 | AD6: BKR | AE6: C69 | AF6: 44988 | AH6: 0 | AI6: as above
A7: 1 | B7: G04 | C7: ABILITY PLAZA, 298-316 KINGSLAND RD, 1A ARBUTUS ST, E8 4DT | D7: 418576004 | E7: Unit 4 Ability Plaza, London, E8 | F7: a1G4J0000025zuGUAQ | G7: 19327.5 | H7: 22.5 | J7: VACANT | K7: Ground floor | L7: B1 | R7: Tenancy at will | W7: 0 | X7: 0 | Z7: 0 | AA7: 859 | AD7: None | AE7: C70 | AF7: 44898 | AH7: 0 | AI7: as above
A8: 1 | B8: G05 | C8: ABILITY PLAZA, 298-316 KINGSLAND RD, 1A ARBUTUS ST, E8 4DT | D8: 418576005 | E8: Unit 5 Ability Plaza, London, E8 | F8: a1G4J0000025zM4UAI | G8: 26000 | H8: 25.641026 | I8: 25.641026 | J8: VACANT | K8: Ground floor | L8: B1 | N8: At Will | O8: 25/05/2023 | P8: Monthly | Q8: N/A | R8: Tenancy at will | S8: Yes | T8: N/A | U8: Landlord | V8: N/A | W8: 33420 | X8: 25400 | Z8: 3342 | AA8: 1014 | AD8: BKR | AE8: D97 | AF8: 44898 | AG8: 1 space | AH8: 32.95858 | AI8: keys back 16th jan, agents have inspected, office revival instruted to clear unit and get marketing (chased for update 10/02/25)
A9: 1 | B9: Unit GA1 (222) | C9: ABILITY VIEW, 218/222 KINGSLAND RD, E2 | D9: 418577012 | E9: Unit GA1, 222 Kingsland Road, E2 8AX | F9: a1G4J0000025zr9UAA | G9: 37000 | H9: 35.852713 | J9: RWD Since 2001 Ltd | K9: Ground & Lower ground floors | L9: B1 | N9: 5 years | O9: 44104 | P9: 45929 | Q9: 45199 | R9: N/A | S9: Yes | T9: Exclusive | U9: Exclusive | V9: 9900 | W9: 37000 | X9: 30700 | Z9: 9900 | AA9: 1662 | AD9: BKR | AE9: E116 | AF9: 46144 | AH9: 22.262335 | AI9: 28/01 Initial approach to tenant on their intentions at lease expiry
A10: 1 | B10: Unit GA2 (Unit 2 - 222) | C10: ABILITY VIEW, 218/222 KINGSLAND RD, E2 | D10: 418577013 | E10: Unit GA2 Ability view, 222 Kingsland Road | F10: a1G4J0000025zj4UAA | G10: 29000 | H10: 28.100775 | J10: Skyway Charity | K10: Ground & Lower ground floors | L10: B1 | N10: 10 Years | O10: 42095 | P10: 45747 | Q10: N/A | R10: N/A | S10: Yes | T10: Inclusive | U10: Exclusive - 3.2% | V10: 2625 | W10: 29000 | X10: 25800 | Z10: 0 | AA10: 1032 | AD10: None | AE10: D82 | AF10: 44212 | AH10: 28.100775 | AI10: tenant has advised they will not be renewing 31/03/25. Awaitng marketing report from Strettons & Ellis Brown, chased 10/02/25
A11: 1 | B11: Unit 3 | C11: ABILITY TOWERS, EC1V 5AE | D11: 418576003 | E11: Unit 3 Ability Plaza, London, E8 | F11: a1G4J0000025zx3UAA | G11: 77220 | H11: 22.5 | J11: VACANT | K11: GF | L11: Office B1 | W11: 0 | X11: 89200 | Y11: 76050 | Z11: 0 | AA11: 3432 | AE11: C65 | AF11: 44478 | AH11: 25.990676 | AI11: QR dropped to £22.50 psf. agents have advised full flexible use class to include e and f1 - to reach out to planner | AJ11: as above | AK11: as above
A12: 1 | B12: Unit 22 & 23 | C12: SPRINGFIELD HOUSE LOFTS, TYSSEN ST, E8 2LY | D12: 418578022 | E12: Unit 22 & 23 Springfield Hse,Tyssen St | F12: a1G4J000002605ZUAQ | G12: 41775 | H12: 25 | J12: VACANT | K12: Ground floor | L12: B1 | W12: 0 | X12: 45000 | Y12: 41775 | Z12: 0 | AA12: 1671 | AE12: B47 | AI12: on market with Strettons & Belcor, qr reduced to £47,500. 09/07 rent reduced to £25 psf. whats the latest on planning app? no interest at present | AJ12: Belcor | AK12: Zoopla rightmove

Sheet All Qube commercial units
A1: 1. Vacant Units
A2: Qube Unit Reference | B2: sheet | C2: DS sheet | D2: SF unit id | E2: Portfolio | F2: Old Reference | G2: Qube and Salesforce Description | H2: Type | I2: Status | J2: Tenure | K2: ERV | L2: ERV As At | M2: On Commercial quoting Rent sheet | N2: Description | O2: Total | P2: Missing from SF | Q2: On SF | R2: On Comm Team sheet | S2: Not on Comm Team sheet
A3: 222625001 | B3: 222625001 | C3: =VLOOKUP(A3,'DS Tenanted units'!A:A,1,FALSE) -> #N/A | D3: a1G4J0000025wsUUAQ | E3: GRML | F3: 373713 | G3: Unit 1, Hawkins Lane Building, East Tucker St | H3: Commercial | I3: For Let | J3: Vac-C | K3: 38050 | L3: 45565 | M3: Yes | N3: Vacant Units | O3: 138 | P3: 71 | Q3: =O3-P3 -> 67 | R3: 40 | S3: =O3-R3 -> 98
A4: 222625003 | B4: 222625003 | C4: =VLOOKUP(A4,'DS Tenanted units'!A:A,1,FALSE) -> #N/A | D4: a1G4J0000025xJHUAY | E4: GRML | F4: 373715 | G4: Unit 3, Hawkins Lane Building, East Tucker St | H4: Commercial | I4: For Let | J4: Vac-C | K4: 28500 | L4: 45565 | M4: Yes | N4: Tenanted units-CommLease | O4: 161 | P4: 11 | Q4: =O4-P4 -> 150 | R4: 36 | S4: =O4-R4 -> 125
A5: 222646001 | B5: 222646001 | C5: =VLOOKUP(A5,'DS Tenanted units'!A:A,1,FALSE) -> #N/A | D5: a1G8d0000004RxMEAU | E5: GRML | F5: 10095637138 | G5: Unit 1, Aster Apartments. | H5: Commercial | I5: For Let | J5: Vac-C | K5: 44500 | L5: 45565 | M5: Yes | N5: Tenanted units-Comm LIC | O5: 294 | P5: 0 | Q5: =O5-P5 -> 294 | R5: 0 | S5: =O5-R5 -> 294
A6: 222653001 | B6: 222653001 | C6: =VLOOKUP(A6,'DS Tenanted units'!A:A,1,FALSE) -> #N/A | D6: a1G8d0000004Me4EAE | E6: GRIP | G6: Unit 1 Halogen House, 217 Chapel St, Salford | H6: COMMERCIAL | I6: For Let | J6: Vac-C | K6: 24000 | L6: 45565 | M6: Yes | N6: Tenanted Units-Queries e.g Wayleaves | O6: 43 | P6: 3 | Q6: =O6-P6 -> 40 | R6: 0 | S6: =O6-R6 -> 43
A7: 222680001 | B7: 222680001 | C7: =VLOOKUP(A7,'DS Tenanted units'!A:A,1,FALSE) -> #N/A | D7: a1G8d0000004Gl5EAE | E7: GRML | F7: 4510747827 | G7: Unit 1, The Forge, Newcastle, NE1 3AA | H7: COMMERCIAL | I7: For Let | J7: Vac-C | K7: 29010 | L7: 45565 | M7: Yes | N7: Tenanted Units-Comm-Let | O7: 107 | P7: 1 | Q7: =O7-P7 -> 106 | R7: 0 | S7: =O7-R7 -> 107
A8: 222690003 | B8: 222690003 | C8: =VLOOKUP(A8,'DS Tenanted units'!A:A,1,FALSE) -> #N/A | D8: a1G8d0000004bzrEAA | E8: GRML | G8: Gilders Yard - B.02, 12 Great Hampton St | H8: COMMERCIAL | I8: For Let | J8: Vac-C | K8: 25768 | L8: 45565 | M8: Yes | O8: =SUM(O3:O7) -> 743 | P8: =SUM(P3:P7) -> 86 | Q8: =SUM(Q3:Q7) -> 657 | R8: =SUM(R3:R7) -> 76 | S8: =SUM(S3:S7) -> 667
A9: 222698001 | B9: 222698001 | C9: =VLOOKUP(A9,'DS Tenanted units'!A:A,1,FALSE) -> #N/A | D9: a1G8d0000004qhAEAQ | E9: GRML | F9: 10095672408 | G9: Unit A Bamboo House, Weavers Yard, Newbury | H9: COMMERCIAL | I9: For Let | J9: Vac-C | K9: 49818 | L9: 45565 | M9: Yes
A10: 222698002 | B10: 222698002 | C10: =VLOOKUP(A10,'DS Tenanted units'!A:A,1,FALSE) -> #N/A | D10: a1G8d0000004qhKEAQ | E10: GRML | G10: Unit A Garter House, Weavers Yard, Newbury | H10: COMMERCIAL | I10: For Let | J10: Vac-C | K10: 26130 | L10: 45565 | M10: Yes
A11: 222698003 | B11: 222698003 | C11: =VLOOKUP(A11,'DS Tenanted units'!A:A,1,FALSE) -> #N/A | D11: a1G8d0000004qhUEAQ | E11: GRML | G11: Unit B Garter House, Weavers Yard, Newbury | H11: COMMERCIAL | I11: For Let | J11: Vac-C | K11: 41970 | L11: 45565 | M11: Yes
A12: 222698004 | B12: 222698004 | C12: =VLOOKUP(A12,'DS Tenanted units'!A:A,1,FALSE) -> #N/A | D12: a1G8d0000004qheEAA | E12: GRML | F12: 10095672457 | G12: Unit A Purl House, Weavers Yard, Newbury | H12: COMMERCIAL | I12: For Let | J12: Vac-C | K12: 24390 | L12: 45565 | M12: Yes
A13: 222698005 | B13: 222698005 | C13: =VLOOKUP(A13,'DS Tenanted units'!A:A,1,FALSE) -> #N/A | D13: a1G8d0000004qZvEAI | E13: GRML | G13: Unit A Linen Place, Weavers Yard, Newbury | H13: COMMERCIAL | I13: For Let | J13: Vac-C | K13: 29260 | L13: 45565 | M13: Yes
A14: 222698006 | B14: 222698006 | C14: =VLOOKUP(A14,'DS Tenanted units'!A:A,1,FALSE) -> #N/A | D14: a1G8d0000004qeREAQ | E14: GRML | G14: Unit A Farrow House, Weavers Yard, Newbury | H14: COMMERCIAL | I14: For Let | J14: Vac-C | K14: 10010 | L14: 45565 | M14: Yes
A15: 222698007 | B15: 222698007 | C15: =VLOOKUP(A15,'DS Tenanted units'!A:A,1,FALSE) -> #N/A | D15: a1G8d0000004qhoEAA | E15: GRML | G15: 5 Station Approach, Weavers Yard, Newbury | H15: COMMERCIAL | I15: For Let | J15: Vac-C | K15: 9928 | L15: 45565 | M15: Yes
A16: 222698008 | B16: 222698008 | C16: =VLOOKUP(A16,'DS Tenanted units'!A:A,1,FALSE) -> #N/A | D16: a1G8d0000004qf5EAA | E16: GRML | G16: 4 Station Approach, Weavers Yard, Newbury | H16: COMMERCIAL | I16: For Let | J16: Vac-C | K16: 12274 | L16: 45565 | M16: Yes
A17: 222698009 | B17: 222698009 | C17: =VLOOKUP(A17,'DS Tenanted units'!A:A,1,FALSE) -> #N/A | D17: a1G8d0000004qi3EAA | E17: GRML | G17: 3 Station Approach, Weavers Yard, Newbury | H17: COMMERCIAL | I17: For Let | J17: Vac-C | K17: 12000 | L17: 45565 | M17: Yes
A18: 222707001 | B18: 222707001 | C18: =VLOOKUP(A18,'DS Tenanted units'!A:A,1,FALSE) -> #N/A | D18: a1G8d0000005cWREAY | E18: GRML | G18: Unit 1.1 Redcliffe Quarter, Bristol. BS1 6WL | H18: COMMERCIAL | I18: For Let | J18: Vac-C | K18: 33733 | L18: 45565 | M18: Yes
A19: 222707004 | B19: 222707004 | C19: =VLOOKUP(A19,'DS Tenanted units'!A:A,1,FALSE) -> #N/A | D19: a1G8d0000005cWgEAI | E19: GRML | F19: 365551 | G19: Unit 2.1 Redcliffe Quarter, Bristol. BS1 6WL | H19: COMMERCIAL | I19: For Let | J19: Vac-C | K19: 99858 | L19: 45565 | M19: Yes
A20: 222711002 | B20: 222711002 | C20: =VLOOKUP(A20,'DS Tenanted units'!A:A,1,FALSE) -> #N/A | D20: a1G8d0000005r5fEAA | E20: GRML | G20: Commercial unit 2 Enigma Square | H20: COMMERCIAL | I20: For Let | J20: Vac-C | K20: 26573 | L20: 45565 | M20: Yes
A21: 222711003 | B21: 222711003 | C21: =VLOOKUP(A21,'DS Tenanted units'!A:A,1,FALSE) -> #N/A | D21: a1G8d0000005r5kEAA | E21: GRML | G21: Commercial unit 3 Enigma Square | H21: COMMERCIAL | I21: For Let | J21: Vac-C | K21: 26573 | L21: 45565 | M21: Yes
A22: 222736001 | B22: 222736001 | C22: =VLOOKUP(A22,'DS Tenanted units'!A:A,1,FALSE) -> #N/A | D22: a1G8d000002PHNdEAO | E22: GRML | G22: Copperworks, 5 Capital Quarter, Cardiff | H22: COMMERCIAL | I22: For Let | J22: Vac-C | K22: 35000 | L22: 45565 | M22: Yes
A23: 222746001 | B23: 222746001 | C23: =VLOOKUP(A23,'DS Tenanted units'!A:A,1,FALSE) -> #N/A | D23: a1G8d000002QBVNEA4 | E23: GRML | G23: Commercial unit 1, 18 Silvertown way, London | H23: COMMERCIAL | I23: For Let | J23: Vac-C | K23: 61533 | L23: 45565 | M23: Yes
A24: 222746002 | B24: 222746002 | C24: =VLOOKUP(A24,'DS Tenanted units'!A:A,1,FALSE) -> #N/A | D24: a1G8d000002QBVSEA4 | E24: GRML | G24: Commercial unit 2, 18 Silvertown way, London | H24: COMMERCIAL | I24: For Let | J24: Vac-C | K24: 45020 | L24: 45565 | M24: Yes
A25: 222746003 | B25: 222746003 | C25: =VLOOKUP(A25,'DS Tenanted units'!A:A,1,FALSE) -> #N/A | D25: a1G8d000002QBVXEA4 | E25: GRML | G25: Commercial unit 3, 18 Silvertown way, London | H25: COMMERCIAL | I25: For Let | J25: Vac-C | K25: 31050 | L25: 45565 | M25: Yes
A26: 222746004 | B26: 222746004 | C26: =VLOOKUP(A26,'DS Tenanted units'!A:A,1,FALSE) -> #N/A | D26: a1G8d000002QBVcEAO | E26: GRML | G26: Commercial unit 4, 18 Silvertown way, London | H26: COMMERCIAL | I26: For Let | J26: Vac-C | K26: 61533 | L26: 45565 | M26: Yes
A27: 222746005 | B27: 222746005 | C27: =VLOOKUP(A27,'DS Tenanted units'!A:A,1,FALSE) -> #N/A | D27: a1G8d000002QBVhEAO | E27: GRML | G27: Commercial unit 5, 18 Silvertown way, London | H27: COMMERCIAL | I27: For Let | J27: Vac-C | K27: 103650 | L27: 45565 | M27: Yes
A28: 222757001 | B28: 222757001 | C28: =VLOOKUP(A28,'DS Tenanted units'!A:A,1,FALSE) -> #N/A | D28: a1GNz0000000v37MAA | E28: GRML | F28: 10095947501 | G28: 86 Upper Allen Street, Sheffield | H28: COMMERCIAL | I28: For Let | J28: Vac-C | K28: 9384 | L28: 45565 | M28: Yes
A29: 222761001 | B29: 222761001 | C29: =VLOOKUP(A29,'DS Tenanted units'!A:A,1,FALSE) -> #N/A | D29: a1GNz0000000zgDMAQ | E29: GRML | G29: Commercial unit, 21 Queens Road | H29: COMMERCIAL | I29: For Let | J29: Vac-C | K29: 22500 | L29: 45565 | M29: Yes
A30: 222795001 | B30: 222795001 | C30: =VLOOKUP(A30,'DS Tenanted units'!A:A,1,FALSE) -> #N/A | D30: a1GNz000001HUHFMA4 | E30: GRML | G30: Commercial Unit, 98 Moor Street Queensway | H30: COMMERCIAL | I30: For Let | J30: Vac-C | K30: 33700 | L30: 45565 | M30: Yes
A31: 222808001 | B31: #N/A | C31: =VLOOKUP(A31,'DS Tenanted units'!A:A,1,FALSE) -> #N/A | D31: a1GNz0000054K5KMAU | E31: GRML | F31: 10095640582 | G31: Commerical Approach, 6 Ferry Lane, Tottenham | H31: Commercial | I31: For Let | J31: Vac-C | K31: 17400 | L31: 45565 | M31: Yes
A32: 222813001 | B32: 222813001 | C32: =VLOOKUP(A32,'DS Tenanted units'!A:A,1,FALSE) -> #N/A | D32: a1GNz000006cEcoMAE | E32: GRML | G32: The Kimmeridge Retail Unit 1 | H32: COMMERCIAL | I32: For Let | J32: Vac-C | K32: 80500 | L32: 45645 | M32: Yes
A33: 222813002 | B33: 222813002 | C33: =VLOOKUP(A33,'DS Tenanted units'!A:A,1,FALSE) -> #N/A | D33: a1GNz000006cG0HMAU | E33: GRML | G33: The Kimmeridge Retail Unit 2 | H33: COMMERCIAL | I33: For Let | J33: Vac-C | K33: 33960 | L33: 45645 | M33: Yes
A34: 222813003 | B34: 222813003 | C34: =VLOOKUP(A34,'DS Tenanted units'!A:A,1,FALSE) -> #N/A | D34: a1GNz000006c7eYMAQ | E34: GRML | G34: The Kimmeridge Retail Unit 3 | H34: COMMERCIAL | I34: For Let | J34: Vac-C | K34: 33960 | L34: 45645 | M34: Yes
A35: 222813004 | B35: 222813004 | C35: =VLOOKUP(A35,'DS Tenanted units'!A:A,1,FALSE) -> #N/A | D35: a1GNz000006cG8LMAU | E35: GRML | G35: The Kimmeridge Retail Unit 4 | H35: COMMERCIAL | I35: For Let | J35: Vac-C | K35: 32430 | L35: 45645 | M35: Yes
A36: 222813005 | B36: 222813005 | C36: =VLOOKUP(A36,'DS Tenanted units'!A:A,1,FALSE) -> #N/A | D36: a1GNz000006cENWMA2 | E36: GRML | G36: The Kimmeridge Retail Unit 5 | H36: COMMERCIAL | I36: For Let | J36: Vac-C | K36: 62400 | L36: 45645 | M36: Yes
A37: 222813006 | B37: 222813006 | C37: =VLOOKUP(A37,'DS Tenanted units'!A:A,1,FALSE) -> #N/A | D37: a1GNz000006cGGPMA2 | E37: GRML | G37: The Kimmeridge Retail Unit 6 | H37: COMMERCIAL | I37: For Let | J37: Vac-C | K37: 39180 | L37: 45645 | M37: Yes
A38: 222813007 | B38: 222813007 | C38: =VLOOKUP(A38,'DS Tenanted units'!A:A,1,FALSE) -> #N/A | D38: a1GNz000006cGMrMAM | E38: GRML | G38: The Kimmeridge Retail Unit 7 | H38: COMMERCIAL | I38: For Let | J38: Vac-C | K38: 29880 | L38: 45645 | M38: Yes
A39: 900005001 | B39: 900005001 | C39: =VLOOKUP(A39,'DS Tenanted units'!A:A,1,FALSE) -> #N/A | D39: a1G4J00000260JEUAY | E39: Vesta | F39: 10094370345 | G39: Unit 1, 1 Millet Place, London E16 2YJ | H39: Commercial | I39: For Let | J39: Vac-C | K39: 51731 | L39: 45565 | M39: Yes
A40: 900005002 | B40: 900005002 | C40: =VLOOKUP(A40,'DS Tenanted units'!A:A,1,FALSE) -> #N/A | D40: a1G4J000002605CUAQ | E40: Vesta | F40: 10094370347 | G40: Unit 2, 5 Millet Place, London E16 2YJ | H40: Commercial | I40: For Let | J40: Vac-C | K40: 60000 | L40: 45565 | M40: Yes
A41: 900005003 | B41: 900005003 | C41: =VLOOKUP(A41,'DS Tenanted units'!A:A,1,FALSE) -> #N/A | D41: a1G4J000002607zUAA | E41: Vesta | F41: 10094370348 | G41: Unit 3,7 Millet Place, London E16 2YJ | H41: Commercial | I41: For Let | J41: Vac-C | K41: 20340 | L41: 45565 | M41: Yes
A42: 900005004 | B42: 900005004 | C42: =VLOOKUP(A42,'DS Tenanted units'!A:A,1,FALSE) -> #N/A | D42: a1G4J00000260MYUAY | E42: Vesta | F42: 10094370349 | G42: Unit 4, 9 Millet Place, London E16 2YJ | H42: Commercial | I42: For Let | J42: Vac-C | K42: 24055 | L42: 45565 | M42: Yes
A43: 106535002 | B43: #N/A | C43: =VLOOKUP(A43,'DS Tenanted units'!A:A,1,FALSE) -> #N/A | D43: a1G4J0000025udgUAA | E43: GRML | F43: 100071533871 | G43: 7a, Three Trees, Castle Street SY11 4DB | H43: Commercial | I43: For Sale | J43: Vac-C | K43: 2520 | L43: 45565 | M43: No
A44: 109643009 | B44: #N/A | C44: =VLOOKUP(A44,'DS Tenanted units'!A:A,1,FALSE) -> #N/A | D44: a1G4J0000025v08UAA | E44: GRML | G44: Land at Knightley Grange Estate, Stafford | H44: Land | I44: AwaitDecision | J44: Vac-C | K44: 0 | L44: 45565 | M44: No
A45: 109691002 | B45: #N/A | C45: =VLOOKUP(A45,'DS Tenanted units'!A:A,1,FALSE) -> #N/A | D45: a1G4J0000025v3eUAA | E45: GRML | G45: Ashwoodhead Farm Hse, Knightley, Stafford St. | H45: Wayleave | I45: AwaitDecision | J45: Vac-C | K45: 1 | L45: 45565 | M45: No
A46: 112180004 | B46: #N/A | C46: =VLOOKUP(A46,'DS Tenanted units'!A:A,1,FALSE) -> #N/A | D46: a1GNz0000080yijMAA | E46: GRML | G46: Martlesham: Land North of Burgess Place | H46: Land | I46: For Let | J46: Vac-C | K46: 0 | L46: 43122 | M46: No
A47: 112180005 | B47: #N/A | C47: =VLOOKUP(A47,'DS Tenanted units'!A:A,1,FALSE) -> #N/A | D47: a1GNz0000080tb0MAA | E47: GRML | G47: Martlesham: Land East of Lark Rise | H47: Land | I47: For Let | J47: Vac-C | K47: 0 | L47: 43122 | M47: No
A48: 112180008 | B48: #N/A | C48: =VLOOKUP(A48,'DS Tenanted units'!A:A,1,FALSE) -> #N/A | D48: a1GNz0000080ykLMAQ | E48: GRML | G48: Martlesham: Land South of Village Centre | H48: Land | I48: For Let | J48: Vac-C | K48: 0 | L48: 45565 | M48: No
A49: 112180009 | B49: #N/A | C49: =VLOOKUP(A49,'DS Tenanted units'!A:A,1,FALSE) -> #N/A | D49: a1GNz0000080ylxMAA | E49: GRML | G49: Martlesham: Land South of Village | H49: Land | I49: For Let | J49: Vac-C | K49: 0 | L49: 43122 | M49: No
A50: 122489002 | B50: #N/A | C50: =VLOOKUP(A50,'DS Tenanted units'!A:A,1,FALSE) -> #N/A | D50: a1G8d00000067yxEAA | E50: GRML | G50: Aldershot AA0008 ABRO Building 14 | H50: Commercial | I50: AwaitDecision | J50: Vac-C | K50: 0 | L50: 43122 | M50: No
A51: 122489003 | B51: #N/A | C51: =VLOOKUP(A51,'DS Tenanted units'!A:A,1,FALSE) -> #N/A | D51: Missing | E51: GRML | G51: Aldershot AA0009 ABRO West Workshop | H51: Commercial | I51: AwaitDecision | J51: Vac-C | K51: 0 | L51: 43122 | M51: No
A52: 122489004 | B52: #N/A | C52: =VLOOKUP(A52,'DS Tenanted units'!A:A,1,FALSE) -> #N/A | D52: Missing | E52: GRML | G52: Aldershot AA0010 ABRO Building 9 | H52: Commercial | I52: AwaitDecision | J52: Vac-C | K52: 0 | L52: 43122 | M52: No
A53: 122489005 | B53: #N/A | C53: =VLOOKUP(A53,'DS Tenanted units'!A:A,1,FALSE) -> #N/A | D53: Missing | E53: GRML | G53: Aldershot AA0111 ABRO Building 10 | H53: Commercial | I53: AwaitDecision | J53: Vac-C | K53: 0 | L53: 43122 | M53: No
A54: 122489006 | B54: #N/A | C54: =VLOOKUP(A54,'DS Tenanted units'!A:A,1,FALSE) -> #N/A | D54: Missing | E54: GRML | G54: Aldershot AA0112 ABRO Building 11 | H54: Commercial | I54: AwaitDecision | J54: Vac-C | K54: 0 | L54: 43122 | M54: No
A55: 122489007 | B55: #N/A | C55: =VLOOKUP(A55,'DS Tenanted units'!A:A,1,FALSE) -> #N/A | D55: Missing | E55: GRML | G55: Aldershot AA0113 ABRO Building 12 | H55: Commercial | I55: AwaitDecision | J55: Vac-C | K55: 0 | L55: 43122 | M55: No
... A123: 122501005 | B123: #N/A | C123: =VLOOKUP(A123,'DS Tenanted units'!A:A,1,FALSE) -> #N/A | D123: Missing | E123: GRML | G123: Aldershot PR0071 PARSONS Hse/Office/Store | H123: Commercial | I123: AwaitDecision | J123: Vac-C | K123: 0 | L123: 43122 | M123: No
A124: 127272001 | B124: #N/A | C124: =VLOOKUP(A124,'DS Tenanted units'!A:A,1,FALSE) -> #N/A | D124: Missing | E124: GRML | G124: Malta Barracks Parade Square | H124: Commercial | I124: For Let | J124: Vac-C | K124: 0 | L124: n/a | M124: No
A125: 127272002 | B125: #N/A | C125: =VLOOKUP(A125,'DS Tenanted units'!A:A,1,FALSE) -> #N/A | D125: Missing | E125: GRML | G125: Land at Forge Lane opp Runways End | H125: Commercial | I125: AwaitDecision | J125: Vac-C | K125: 0 | L125: n/a | M125: No
A126: 222803001 | B126: #N/A | C126: =VLOOKUP(A126,'DS Tenanted units'!A:A,1,FALSE) -> #N/A | D126: a1GNz000003M2XhMAK | E126: GRML | G126: Unit 1, The Arches, John St, Cardiff CF10 5PE | H126: Commercial | I126: For Let | J126: Vac-C | K126: 0 | L126: 45565 | M126: No
A127: 222803002 | B127: #N/A | C127: =VLOOKUP(A127,'DS Tenanted units'!A:A,1,FALSE) -> #N/A | D127: a1GNz000003M8V4MAK | E127: GRML | G127: Unit 2, The Arches, John St, Cardiff CF10 5PE | H127: Commercial | I127: For Let | J127: Vac-C | K127: 0 | L127: 45565 | M127: No
A128: 222803003 | B128: #N/A | C128: =VLOOKUP(A128,'DS Tenanted units'!A:A,1,FALSE) -> #N/A | D128: a1GNz000003M4KMMA0 | E128: GRML | G128: Unit 4, The Arches, John St, Cardiff CF10 5PE | H128: Commercial | I128: For Let | J128: Vac-C | K128: 0 | L128: 45565 | M128: No
A129: 222803004 | B129: #N/A | C129: =VLOOKUP(A129,'DS Tenanted units'!A:A,1,FALSE) -> #N/A | D129: a1GNz000003MAWrMAO | E129: GRML | G129: Unit 5, The Arches, John St, Cardiff CF10 5PE | H129: Commercial | I129: For Let | J129: Vac-C | K129: 0 | L129: 45565 | M129: No
A130: 222803005 | B130: #N/A | C130: =VLOOKUP(A130,'DS Tenanted units'!A:A,1,FALSE) -> #N/A | D130: a1GNz000003MCAUMA4 | E130: GRML | G130: Unit 6, The Arches, John St, Cardiff CF10 5PE | H130: Commercial | I130: For Let | J130: Vac-C | K130: 0 | L130: 45565 | M130: No
A131: 317669001 | B131: #N/A | C131: =VLOOKUP(A131,'DS Tenanted units'!A:A,1,FALSE) -> #N/A | D131: a1G4J0000025yHRUAY | E131: GRML | G131: Workshop, Ospringe House, Wotton St, SE1 8TB | H131: Commercial | I131: For Let | J131: Vac-C | K131: 0 | L131: 44834 | M131: No
A132: 317670001 | B132: #N/A | C132: =VLOOKUP(A132,'DS Tenanted units'!A:A,1,FALSE) -> #N/A | D132: a1G4J0000025yKMUAY | E132: GRML | G132: Ospringe House Grnd Flr office Wooton St SE1 | H132: Commercial | I132: For Let | J132: Vac-C | K132: 0 | L132: 44834 | M132: No
A133: 317671001 | B133: #N/A | C133: =VLOOKUP(A133,'DS Tenanted units'!A:A,1,FALSE) -> #N/A | D133: a1G4J0000025yVqUAI | E133: GRML | F133: 200000460443 | G133: Ethelm House, London, SE1 | H133: Commercial | I133: AwaitDecision | J133: Vac-C | K133: 0 | L133: 44834 | M133: No
A134: 418572003 | B134: #N/A | C134: =VLOOKUP(A134,'DS Tenanted units'!A:A,1,FALSE) -> #N/A | D134: a1G4J0000025zt7UAA | E134: GRIP | F134: 10091005857 | G134: 146 Central St London EC1V 8AY | H134: Commercial | I134: For Let | J134: Vac-C | K134: 89200 | L134: 45565 | M134: No
A135: 418576001 | B135: #N/A | C135: =VLOOKUP(A135,'DS Tenanted units'!A:A,1,FALSE) -> #N/A | D135: a1G4J0000025zy0UAA | E135: GRIP | G135: Unit 1 Ability Plaza, London, E8 | H135: Commercial | I135: For Let | J135: Vac-C | K135: 22300 | L135: 45565 | M135: No
A136: 418576002 | B136: #N/A | C136: =VLOOKUP(A136,'DS Tenanted units'!A:A,1,FALSE) -> #N/A | D136: a1G4J000002600AUAQ | E136: GRIP | G136: Unit 2 Ability Plaza, London, E8 | H136: Commercial | I136: For Let | J136: Vac-C | K136: 59800 | L136: 45565 | M136: No
A137: 418576003 | B137: #N/A | C137: =VLOOKUP(A137,'DS Tenanted units'!A:A,1,FALSE) -> #N/A | D137: a1G4J0000025zx3UAA | E137: GRIP | G137: Unit 3 Ability Plaza, London, E8 | H137: Commercial | I137: For Let | J137: Vac-C | K137: 17200 | L137: 45565 | M137: No
A138: 418576004 | B138: #N/A | C138: =VLOOKUP(A138,'DS Tenanted units'!A:A,1,FALSE) -> #N/A | D138: a1G4J0000025zuGUAQ | E138: GRIP | G138: Unit 4 Ability Plaza, London, E8 | H138: Commercial | I138: For Let | J138: Vac-C | K138: 17180 | L138: 45565 | M138: No
A139: 418576122 | B139: #N/A | C139: =VLOOKUP(A139,'DS Tenanted units'!A:A,1,FALSE) -> #N/A | D139: a1G4J000002605uUAA | E139: GRIP | G139: Car Park Space 12 Ability Plaza, London, E8 | H139: ParkingSpac | I139: For Let | J139: Vac-C | K139: 0 | L139: 45565 | M139: No
A140: 418578022 | B140: #N/A | C140: =VLOOKUP(A140,'DS Tenanted units'!A:A,1,FALSE) -> #N/A | D140: a1G4J000002605ZUAQ | E140: GRIP | F140: 10008240142 | G140: Unit 22 & 23 Springfield Hse,Tyssen St | H140: Commercial | I140: For Let | J140: Vac-C | K140: 45000 | L140: 45565 | M140: No
A141: 2. Tenanted Units
A142: Reference | B142: sheet | C142: DS sheet | E142: Portfolio | F142: Old Reference | G142: Description | H142: Type | I142: Status | J142: Tenure | K142: ERV | L142: ERV As At | M142: On Commercial quoting Rent sheet
A143: 222577001 | B143: 222577001 | C143: =VLOOKUP(A143,'DS Tenanted units'!A:A,1,FALSE) -> 222577001 | D143: a1G4J0000025xf4UAA | E143: GRML | F143: 10094190555 | G143: Clippers - Unit 4-5 Waterman Walk | H143: Commercial | I143: Tenanted | J143: CommLease | K143: 54800 | L143: 45565 | M143: Yes
A144: 222577002 | B144: 222577002 | C144: =VLOOKUP(A144,'DS Tenanted units'!A:A,1,FALSE) -> 222577002 | D144: a1G4J0000025xoHUAQ | E144: GRML | F144: 10094190852 | G144: Clippers - Unit 1 Zerega Way M50 | H144: Commercial | I144: Tenanted | J144: CommLease | K144: 20000 | L144: 45565 | M144: Yes
A145: 222577003 | B145: 222577003 | C145: =VLOOKUP(A145,'DS Tenanted units'!A:A,1,FALSE) -> 222577003 | D145: a1G4J0000025xMrUAI | E145: GRML | F145: 10094190853 | G145: Clippers - Unit 2 Zerega Way M50 | H145: Commercial | I145: Tenanted | J145: CommLease | K145: 21900 | L145: 45565 | M145: Yes
A146: 222577004 | B146: 222577004 | C146: =VLOOKUP(A146,'DS Tenanted units'!A:A,1,FALSE) -> 222577004 | D146: a1G4J0000025xvyUAA | E146: GRML | F146: 10094190849 | G146: Clippers - Unit 3 Waterman Walk (GPLC Office) | H146: Commercial | I146: Tenanted | J146: CommLease | K146: 20900 | L146: 45565 | M146: Yes
A147: 222577005 | B147: 222577005 | C147: =VLOOKUP(A147,'DS Tenanted units'!A:A,1,FALSE) -> 222577005 | D147: a1G4J0000025x0gUAA | E147: GRML | F147: 10094190848 | G147: Clippers - Unit 2 Waterman Walk (GPLC Office) | H147: Commercial | I147: Tenanted | J147: CommLease | K147: 20900 | L147: 45565 | M147: Yes
A148: 222577006 | B148: 222577006 | C148: =VLOOKUP(A148,'DS Tenanted units'!A:A,1,FALSE) -> 222577006 | D148: a1G4J0000025xRhUAI | E148: GRML | F148: 10095312460 | G148: Clippers - Unit 1 Waterman Walk | H148: Commercial | I148: Tenanted | J148: CommLease | K148: 20000 | L148: 45565 | M148: Yes
A149: 222625002 | B149: 222625002 | C149: =VLOOKUP(A149,'DS Tenanted units'!A:A,1,FALSE) -> 222625002 | D149: a1G4J0000025y18UAA | E149: GRML | F149: 373714 | G149: Unit 2, Hawkins Lane Building, East Tucker St | H149: Commercial | I149: Tenanted | J149: CommLease | K149: 10975 | L149: 45565 | M149: Yes
A150: 222632001 | B150: 222632001 | C150: =VLOOKUP(A150,'DS Tenanted units'!A:A,1,FALSE) -> 222632001 | D150: a1G4J0000025y3lUAA | E150: GRML | G150: Unit 1 Brook Place 110 Napier Street S11 8BR | H150: Commercial | I150: Tenanted | J150: CommLease | K150: 31600 | L150: 45565 | M150: Yes
A151: 222632002 | B151: 222632002 | C151: =VLOOKUP(A151,'DS Tenanted units'!A:A,1,FALSE) -> 222632002 | D151: a1G4J0000025x8FUAQ | E151: GRML | G151: Unit 2, Brook Place, 112 Napier Street, S11 8 | H151: Commercial | I151: Tenanted | J151: CommLease | K151: 0 | L151: 45565 | M151: Yes
A152: 222632003 | B152: 222632003 | C152: =VLOOKUP(A152,'DS Tenanted units'!A:A,1,FALSE) -> 222632003 | D152: a1G4J0000025yBfUAI | E152: GRML | G152: Unit 3, Brook Place, 114 Napier Street, S11 8 | H152: Commercial | I152: Tenanted | J152: CommLease | K152: 24800 | L152: 45565 | M152: Yes
A153: 222641001 | B153: 222641001 | C153: =VLOOKUP(A153,'DS Tenanted units'!A:A,1,FALSE) -> 222641001 | D153: a1G4J0000025y5HUAQ | E153: GRML | F153: 10093919740 | G153: 809, Silbury Boulevard, Milton Keynes, MK9 | H153: Commercial | I153: Tenanted | J153: CommLease | K153: 75340 | L153: 45565 | M153: Yes
A154: 222641002 | B154: 222641002 | C154: =VLOOKUP(A154,'DS Tenanted units'!A:A,1,FALSE) -> 222641002 | D154: a1G4J0000025y35UAA | E154: GRML | F154: 10093919741 | G154: 811, Silbury Boulevard, Milton Keynes, MK9 | H154: Commercial | I154: Tenanted | J154: CommLease | K154: 0 | L154: 45565 | M154: Yes
A155: 222644002 | B155: 222644002 | C155: =VLOOKUP(A155,'DS Tenanted units'!A:A,1,FALSE) -> 222644002 | D155: a1G8d0000004RwxEAE | E155: GRML | F155: 10095637005 | G155: Unit 2, Juniper House | H155: Commercial | I155: Tenanted | J155: CommLease | K155: 0 | L155: 45565 | M155: Yes | N155: a1G8d0000004RwxEAE
A156: 222644003 | B156: 222644003 | C156: =VLOOKUP(A156,'DS Tenanted units'!A:A,1,FALSE) -> 222644003 | D156: a1G8d0000004Rx2EAE | E156: GRML | F156: 10095637006 | G156: Unit 3, Juniper House | H156: Commercial | I156: Tenanted | J156: CommLease | K156: 0 | L156: 45565 | M156: Yes
A157: 222644004 | B157: 222644004 | C157: =VLOOKUP(A157,'DS Tenanted units'!A:A,1,FALSE) -> 222644004 | D157: a1G8d0000004Rx7EAE | E157: GRML | F157: 10095637007 | G157: Unit 4, Juniper House | H157: Commercial | I157: Tenanted | J157: CommLease | K157: 195000 | L157: 45565 | M157: Yes
A158: 222644005 | B158: 222644005 | C158: =VLOOKUP(A158,'DS Tenanted units'!A:A,1,FALSE) -> 222644005 | D158: a1G8d0000004RxCEAU | E158: GRML | F158: 10095637008 | G158: Unit 5, Juniper House | H158: Commercial | I158: Tenanted | J158: CommLease | K158: 0 | L158: 45565 | M158: Yes
A159: 222644006 | B159: 222644006 | C159: =VLOOKUP(A159,'DS Tenanted units'!A:A,1,FALSE) -> 222644006 | D159: a1G8d0000004RxHEAU | E159: GRML | G159: Unit 6, Juniper House | H159: Commercial | I159: Tenanted | J159: CommLease | K159: 0 | L159: 45565 | M159: Yes
A160: 222653002 | B160: 222653002 | C160: =VLOOKUP(A160,'DS Tenanted units'!A:A,1,FALSE) -> 222653002 | D160: a1G8d0000004Me9EAE | E160: GRIP | G160: Unit 2, Halogen House, 217 Chapel St, Salford | H160: COMMERCIAL | I160: Tenanted | J160: CommLease | K160: 20000 | L160: 45565 | M160: Yes
A161: 222653003 | B161: 222653003 | C161: =VLOOKUP(A161,'DS Tenanted units'!A:A,1,FALSE) -> 222653003 | D161: a1G8d0000004MeEEAU | E161: GRIP | G161: Unit 3, Halogen House, 217 Chapel St, Salford | H161: Commercial | I161: Tenanted | J161: CommLease | K161: 12800 | L161: 45565 | M161: Yes
A162: 222653004 | B162: 222653004 | C162: =VLOOKUP(A162,'DS Tenanted units'!A:A,1,FALSE) -> 222653004 | D162: a1G8d0000004MeJEAU | E162: GRIP | G162: Unit 4, Neon House, 207 Chapel St, Salford, M | H162: COMMERCIAL | I162: Tenanted | J162: CommLease | K162: 25500 | L162: 45565 | M162: Yes
A163: 222653005 | B163: 222653005 | C163: =VLOOKUP(A163,'DS Tenanted units'!A:A,1,FALSE) -> 222653005 | D163: a1G8d0000004MeOEAU | E163: GRIP | G163: Unit 5, Neon House, 207 Chapel St, Salford, M | H163: COMMERCIAL | I163: Tenanted | J163: CommLease | K163: 29250 | L163: 45565 | M163: Yes
A164: 222653006 | B164: 222653006 | C164: =VLOOKUP(A164,'DS Tenanted units'!A:A,1,FALSE) -> 222653006 | D164: a1G8d0000004MeTEAU | E164: GRIP | G164: Unit 6, Neon House, 207 Chapel St, Salford, M | H164: COMMERCIAL | I164: Tenanted | J164: CommLease | K164: 45000 | L164: 45565 | M164: Yes
A165: 222662001 | B165: 222662001 | C165: =VLOOKUP(A165,'DS Tenanted units'!A:A,1,FALSE) -> 222662001 | D165: a1G8d0000004MdpEAE | E165: GRML | G165: Unit 1, 87 East St, Southampton | H165: COMMERCIAL | I165: Tenanted | J165: CommLease | K165: 27250 | L165: 45565 | M165: Yes
A166: 222669001 | B166: 222669001 | C166: =VLOOKUP(A166,'DS Tenanted units'!A:A,1,FALSE) -> 222669001 | D166: a1G8d0000004Jy5EAE | E166: GRML | G166: Unit 1, Wellington Park Way, Leeds | H166: COMMERCIAL | I166: Tenanted | J166: CommLease | K166: 30000 | L166: 45565 | M166: Yes
A167: 222690001 | B167: 222690001 | C167: =VLOOKUP(A167,'DS Tenanted units'!A:A,1,FALSE) -> 222690001 | D167: a1G8d0000004bzhEAA | E167: GRML | G167: Gilders Yard - A.01, 19/21 Great Hampton St | H167: COMMERCIAL | I167: Tenanted | J167: CommLease | K167: 96012 | L167: 45565 | M167: Yes
...

Sheet DS Tenanted units
A1: Grainger plc
A2: Commercial Units and tenancies 11/02/25
J4: Terms of Lease | Q4: Rent Review | T4: Break Clause
A5: Unit | B5: Unit Description | C5: Type | D5: Tenure | E5: Status | F5: Tenant (parent) | G5: Unit Exists in Salesforce | H5: Salesforce Opportunity | I5: Qube v SF comment | J5: Lease Start Dtae | K5: Lease End date | L5: Lease term-years | M5: Lease term-months | N5: Lease term-days | O5: Vacant due date | P5: Date vacant | Q5: Next rent review | R5: Rent review frequency | S5: Rent Review Required Notiice | T5: Break clause date | U5: landlord breaks | V5: tenant breaks | W5: Years to next break clause | X5: required notice | Y5: months notice-break clause
C6: Field name | J6: leasedate[5] | K6: leasedate[6] | L6: leaseterm[1] | M6: leaseterm[2] | N6: leaseterm[3] | O6: leasedate[4] | P6: leasedate[2] | Q6: leasedate[1] | R6: gap 1[1] | T6: leasedate[8] | U6: whobreaks[1] | V6: whobreaks[2] | W6: gap [6] | X6: notice [4] | Y6: notice [6]
C7: Comment | O7: This field can be ignored-data does not seem to be accurate | P7: This field can be ignored-data does not seem to be accurate
A8: 109866001 | B8: 40/42 Kensington Park Rd G/F & Basement | C8: Commercial | D8: CommLease | E8: Tenanted | F8: Trustees re Sir John Morden | G8: 40/42 Kensington Park Rd G/F & Basement | H8: GREP-CoA Trustees re Sir John Morden - 40/42 Kensington Park Rd G/F & Basement | I8: Dummy Opportunity exists in Salesforce | J8: 40505 | K8: 131815 | L8: 250 | M8: 0 | N8: 0 | O8: n/a | P8: n/a | Q8: n/a | R8: 0 | S8: 0 | T8: =VLOOKUP(A8,#REF!,9,FALSE) -> #REF! | U8: No | V8: No | W8: 0 | X8: 6 | Y8: 0
A9: 109918015 | B9: Berewood - Woodside House Orchard | C9: Commercial | D9: CommLease | E9: Tenanted | F9: Lynda Joy Harding | G9: #N/A | H9: #N/A | I9: Opportunity does not exist in Salesforce | J9: 45426 | K9: 47251 | L9: 5 | M9: 0 | N9: 0 | O9: n/a | P9: n/a | Q9: 46204 | R9: 0 | S9: 0 | T9: =VLOOKUP(A9,#REF!,9,FALSE) -> #REF! | U9: Yes | V9: Yes | W9: 0 | X9: 6 | Y9: 0
A10: 109918017 | B10: Berewood - Berewood Allotment | C10: Commercial | D10: CommLease | E10: Tenanted | F10: Havant Borough Council. | G10: #N/A | H10: #N/A | I10: Opportunity does not exist in Salesforce | J10: 38467 | K10: n/a | L10: 0 | M10: 0 | N10: 0 | O10: n/a | P10: n/a | Q10: n/a | R10: 0 | S10: 0 | T10: =VLOOKUP(A10,#REF!,9,FALSE) -> #REF! | U10: No | V10: No | W10: 0 | X10: 0 | Y10: 0
A11: 109956007 | B11: Telephone Mast 7 Kennel Fm Dummer | C11: Commercial | D11: CommLease | E11: Tenanted | F11: Vodafone Limited. | G11: #N/A | H11: #N/A | I11: Opportunity does not exist in Salesforce | J11: 37728 | K11: 45032 | L11: 20 | M11: 0 | N11: 0 | O11: n/a | P11: n/a | Q11: n/a | R11: 0 | S11: 0 | T11: =VLOOKUP(A11,#REF!,9,FALSE) -> #REF! | U11: No | V11: No | W11: 0 | X11: 0 | Y11: 0
A12: 109961004 | B12: Woodcroft Farm Petersfield Fields Waterloovil | C12: Land | D12: CommLease | E12: Tenanted | F12: Jennifer Ann Manson | G12: Woodcroft Farm Petersfield Fields Waterloovil | H12: GREP-CoA Jennifer Ann Manson - Woodcroft Farm Petersfield Fields Waterloovil | I12: Dummy Opportunity exists in Salesforce | J12: 44859 | K12: 45589 | L12: 2 | M12: 0 | N12: 0 | O12: n/a | P12: n/a | Q12: n/a | R12: 0 | S12: 0 | T12: =VLOOKUP(A12,#REF!,9,FALSE) -> #REF! | U12: No | V12: No | W12: 0 | X12: 0 | Y12: 0
A13: 109961005 | B13: Woodcroft Farm Eastland Gate Fields Waterloov | C13: Land | D13: CommLease | E13: Tenanted | F13: Jennifer A Manson & Caroline J Eastwood | G13: Woodcroft Farm Eastland Gate Fields Waterloov | H13: REP-CoA Jennifer A Manson & Caroline J Eastwood - Woodcroft Farm Eastland Gate Fields Waterloov | I13: Dummy Opportunity exists in Salesforce | J13: 42669 | K13: 46320 | L13: 10 | M13: 0 | N13: 0 | O13: n/a | P13: n/a | Q13: 44495 | R13: 0 | S13: 3 | T13: =VLOOKUP(A13,#REF!,9,FALSE) -> #REF! | U13: Yes | V13: No | W13: 0 | X13: 0 | Y13: 3
A14: 112179001 | B14: Kesgrave - Dev Site | C14: Commercial | D14: CommLease | E14: Tenanted | F14: William Kerr(Farms)Limited. | G14: #N/A | H14: #N/A | I14: Opportunity does not exist in Salesforce | J14: 43739 | K14: 44834 | L14: 3 | M14: 0 | N14: 0 | O14: n/a | P14: n/a | Q14: n/a | R14: 0 | S14: 0 | T14: =VLOOKUP(A14,#REF!,9,FALSE) -> #REF! | U14: No | V14: No | W14: 0 | X14: 0 | Y14: 0
A15: 112179002 | B15: Bell Lane, Kesgrave,Ipswich. Right of Way | C15: Commercial | D15: CommLease | E15: Tenanted | F15: Ipswich Speedway Limited. | G15: #N/A | H15: #N/A | I15: Opportunity does not exist in Salesforce | J15: 42370 | K15: 43100 | L15: 2 | M15: 0 | N15: 0 | O15: n/a | P15: n/a | Q15: n/a | R15: 0 | S15: 0 | T15: =VLOOKUP(A15,#REF!,9,FALSE) -> #REF! | U15: No | V15: No | W15: 0 | X15: 0 | Y15: 0
A16: 113352001 | B16: Unit A, The Old Generator House, Foxall, Ipsw | C16: Commercial | D16: CommLease | E16: Tenanted | F16: Suffolk Aviation Heritage Group. | G16: Unit A, The Old Generator House, Foxall, Ipsw | H16: GREP-CoA Suffolk Aviation Heritage Group - Unit A, The Old Generator House, Foxall, Ipsw | I16: Dummy Opportunity exists in Salesforce | J16: 44697 | K16: 53827 | L16: 25 | M16: 0 | N16: 0 | O16: n/a | P16: n/a | Q16: 46522 | R16: 0 | S16: 12 | T16: =VLOOKUP(A16,#REF!,9,FALSE) -> #REF! | U16: Yes | V16: No | W16: 0 | X16: 6 | Y16: 6
A17: 113352002 | B17: Land @Foxall Martlesham. Telecomm Mast | C17: Land | D17: CommLease | E17: Tenanted | F17: Buz Broadband Limited. | G17: Land @Foxall Martlesham. Telecomm Mast | H17: GREP-CoA Buz Broadband Limited. - Land @Foxall Martlesham. Telecomm Mast | I17: Dummy Opportunity exists in Salesforce | J17: 42324 | K17: 45976 | L17: 10 | M17: 0 | N17: 0 | O17: n/a | P17: n/a | Q17: 43420 | R17: 3 | S17: 6 | T17: =VLOOKUP(A17,#REF!,9,FALSE) -> #REF! | U17: No | V17: No | W17: 0 | X17: 0 | Y17: 0
A18: 122489021 | B18: Aldershot CM0065 McGrigor Barracks Hosp | C18: Commercial | D18: CommLease | E18: Tenanted | F18: Carry Gently Limited. | G18: Aldershot CM0065 McGrigor Barracks Hosp | H18: GREP-CoA Carry Gently Limited. - Aldershot CM0065 McGrigor Barracks Hosp | I18: Dummy Opportunity exists in Salesforce | J18: 45383 | K18: 46477 | L18: 3 | M18: 0 | N18: 0 | O18: n/a | P18: n/a | Q18: n/a | R18: 0 | S18: 3 | T18: =VLOOKUP(A18,#REF!,9,FALSE) -> #REF! | U18: Yes | V18: No | W18: 0 | X18: 0 | Y18: 6
A19: 122489022 | B19: Aldershot TS0031 Resettlement Centre. | C19: Commercial | D19: CommLease | E19: Tenanted | F19: Gold Valley Lake House Limited | G19: Aldershot TS0031 Resettlement Centre. | H19: GREP-CoA Gold Valley Lake House Limited - Aldershot TS0031 Resettlement Centre. | I19: Dummy Opportunity exists in Salesforce | J19: 45292 | K19: 46022 | L19: 2 | M19: 0 | N19: 0 | O19: n/a | P19: n/a | Q19: n/a | R19: 0 | S19: 3 | T19: =VLOOKUP(A19,#REF!,9,FALSE) -> #REF! | U19: Yes | V19: Yes | W19: 0 | X19: 0 | Y19: 6
A20: 122489023 | B20: Aldershot TS0108 Resettlement Centre | C20: Commercial | D20: CommLease | E20: Tenanted | F20: Mixed Freight Services Limited. | G20: #N/A | H20: #N/A | I20: Opportunity does not exist in Salesforce | J20: 42430 | K20: n/a | L20: 0 | M20: 0 | N20: 0 | O20: n/a | P20: n/a | Q20: n/a | R20: 0 | S20: 0 | T20: =VLOOKUP(A20,#REF!,9,FALSE) -> #REF! | U20: No | V20: No | W20: 0 | X20: 0 | Y20: 0
A21: 122489024 | B21: Aldershot TS0106 Resettlement Centre | C21: Commercial | D21: CommLease | E21: Tenanted | F21: Charters of Aldershot. | G21: #N/A | H21: #N/A | I21: Opportunity does not exist in Salesforce | J21: 45292 | K21: 46387 | L21: 3 | M21: 0 | N21: 0 | O21: n/a | P21: n/a | Q21: n/a | R21: 0 | S21: 0 | T21: =VLOOKUP(A21,#REF!,9,FALSE) -> #REF! | U21: No | V21: No | W21: 0 | X21: 6 | Y21: 0
A22: 122489025 | B22: Aldershot RV0032 Resettlement Centre/ Galwey | C22: Commercial | D22: CommLease | E22: Tenanted | F22: Yeomans Limited | G22: Aldershot RV0032 Resettlement Centre/ Galwey | H22: GREP-CoA Yeomans Limited - Aldershot RV0032 Resettlement Centre/ Galwey | I22: Dummy Opportunity exists in Salesforce | J22: 45658 | K22: 46477 | L22: 2 | M22: 3 | N22: 0 | O22: n/a | P22: n/a | Q22: n/a | R22: 0 | S22: 0 | T22: =VLOOKUP(A22,#REF!,9,FALSE) -> #REF! | U22: Yes | V22: Yes | W22: 0 | X22: 6 | Y22: 0
A23: 122489028 | B23: Aldershot RV0035 RAVC Building 8’ | C23: Commercial | D23: CommLease | E23: Tenanted | F23: Millgrove Construction Ltd | G23: #N/A | H23: #N/A | I23: Opportunity does not exist in Salesforce | J23: 44743 | K23: 45838 | L23: 3 | M23: 0 | N23: 0 | O23: n/a | P23: n/a | Q23: 45658 | R23: 0 | S23: 0 | T23: =VLOOKUP(A23,#REF!,9,FALSE) -> #REF! | U23: Yes | V23: Yes | W23: 0 | X23: 6 | Y23: 0
A24: 122489032 | B24: Storage and Hardstanding at Fitzwygram House | C24: Commercial | D24: CommLease | E24: Tenanted | F24: Paul Winch | G24: Storage and Hardstanding at Fitzwygram House | H24: REP-CoA Paul Winch - Storage and Hardstanding at Fitzwygram House | I24: Dummy Opportunity exists in Salesforce | J24: 44927 | K24: 45657 | L24: 2 | M24: 0 | N24: 0 | O24: n/a | P24: n/a | Q24: n/a | R24: 0 | S24: 0 | T24: =VLOOKUP(A24,#REF!,9,FALSE) -> #REF! | U24: Yes | V24: Yes | W24: 0 | X24: 6 | Y24: 0
A25: 122494014 | B25: Aldershot BG0091 BROWNING Drill Shed 19A | C25: Commercial | D25: CommLease | E25: Tenanted | F25: Woodend Removals. | G25: Aldershot BG0091 BROWNING Drill Shed 19A | H25: GREP-CoA Woodend Removals. - Aldershot BG0091 BROWNING Drill Shed 19A | I25: Dummy Opportunity exists in Salesforce | J25: 45292 | K25: 46022 | L25: 2 | M25: 0 | N25: 0 | O25: n/a | P25: n/a | Q25: n/a | R25: 0 | S25: 0 | T25: =VLOOKUP(A25,#REF!,9,FALSE) -> #REF! | U25: Yes | V25: Yes | W25: 0 | X25: 6 | Y25: 0
A26: 122494018 | B26: Aldershot BGA092 BROWNING 14 DOORS. | C26: Commercial | D26: CommLease | E26: Tenanted | F26: Express Transport (UK) Ltd | G26: Aldershot BGA092 BROWNING 14 DOORS UTILITIES. | H26: GREP-CoA Express Transport (UK) Ltd. - Aldershot BGA092 BROWNING 14 DOORS UTILITIES. | I26: Dummy Opportunity exists in Salesforce | J26: 45292 | K26: 46112 | L26: 2 | M26: 3 | N26: 0 | O26: n/a | P26: n/a | Q26: 45658 | R26: 0 | S26: 0 | T26: =VLOOKUP(A26,#REF!,9,FALSE) -> #REF! | U26: Yes | V26: Yes | W26: 0 | X26: 6 | Y26: 6
A27: 122494019 | B27: Aldershot BGD092.11 quartermasters stores | C27: Commercial | D27: CommLease | E27: Tenanted | F27: Trustees of Farnborogh Foodbank | G27: Aldershot BGD092.11 quartermasters stores | H27: GREP-CoA Trustees of Farnborough Foodbank. - Aldershot BGD092.11 quartermasters stores | I27: Dummy Opportunity exists in Salesforce | J27: 44442 | K27: 45291 | L27: 2 | M27: 3 | N27: 29 | O27: n/a | P27: n/a | Q27: n/a | R27: 0 | S27: 0 | T27: =VLOOKUP(A27,#REF!,9,FALSE) -> #REF! | U27: Yes | V27: No | W27: 0 | X27: 6 | Y27: 3
A28: 122494021 | B28: Aldershot BG0088/BG0080 Browning Mess/ac | C28: Commercial | D28: CommLease | E28: Tenanted | F28: Civil Nuclear Police Authority. | G28: #N/A | H28: #N/A | I28: Opportunity does not exist in Salesforce | J28: 45292 | K28: 46112 | L28: 2 | M28: 3 | N28: 0 | O28: n/a | P28: n/a | Q28: n/a | R28: 0 | S28: 0 | T28: =VLOOKUP(A28,#REF!,9,FALSE) -> #REF! | U28: Yes | V28: Yes | W28: 0 | X28: 0 | Y28: 3
A29: 122494022 | B29: Aldershot 2 Grass Open spaceBrowning barracks | C29: Commercial | D29: CommLease | E29: Tenanted | F29: Civil Nuclear Police Authority. | G29: #N/A | H29: #N/A | I29: Opportunity does not exist in Salesforce | J29: 43831 | K29: 45291 | L29: 4 | M29: 0 | N29: 0 | O29: n/a | P29: n/a | Q29: n/a | R29: 0 | S29: 0 | T29: =VLOOKUP(A29,#REF!,9,FALSE) -> #REF! | U29: No | V29: No | W29: 0 | X29: 0 | Y29: 0
A30: 122494025 | B30: Aldershot BG0090 MT Workshop Browning Brks. | C30: Commercial | D30: CommLease | E30: Tenanted | F30: De Angelo Brothers UK Limited. | G30: #N/A | H30: #N/A | I30: Opportunity does not exist in Salesforce | J30: 44927 | K30: 46022 | L30: 3 | M30: 0 | N30: 0 | O30: n/a | P30: n/a | Q30: n/a | R30: 0 | S30: 0 | T30: =VLOOKUP(A30,#REF!,9,FALSE) -> #REF! | U30: No | V30: No | W30: 0 | X30: 0 | Y30: 0
A31: 122494026 | B31: Aldershot BG0094R Portacabin Browning Brks | C31: Commercial | D31: CommLease | E31: Tenanted | F31: APCymru Limited. | G31: #N/A | H31: #N/A | I31: Opportunity does not exist in Salesforce | J31: 45149 | K31: 45879 | L31: 2 | M31: 0 | N31: 0 | O31: n/a | P31: n/a | Q31: n/a | R31: 0 | S31: 0 | T31: =VLOOKUP(A31,#REF!,9,FALSE) -> #REF! | U31: Yes | V31: Yes | W31: 0 | X31: 6 | Y31: 3
A32: 122494027 | B32: Aldershot BGD092 L quartermasters stores | C32: Commercial | D32: CommLease | E32: Tenanted | F32: David Noyes | G32: Aldershot BGD092 L quartermasters stores | I32: Opportunity does not exist in Salesforce | J32: 45658 | K32: 46112 | L32: 1 | M32: 3 | N32: 0 | O32: n/a | P32: n/a | Q32: n/a | R32: 0 | S32: 0 | T32: =VLOOKUP(A32,#REF!,9,FALSE) -> #REF! | U32: Yes | V32: Yes | W32: 0 | X32: 6 | Y32: 0
A33: 122494028 | B33: Aldershot BGD092 R quartermasters stores | C33: Commercial | D33: CommLease | E33: Tenanted | F33: Annek Services Ltd | G33: #N/A | H33: #N/A | I33: Opportunity does not exist in Salesforce | J33: 45177 | K33: 46082 | L33: 2 | M33: 5 | N33: 22 | O33: n/a | P33: n/a | Q33: 45908 | R33: 0 | S33: 0 | T33: =VLOOKUP(A33,#REF!,9,FALSE) -> #REF! | U33: Yes | V33: Yes | W33: 0 | X33: 6 | Y33: 0
A34: 122494029 | B34: Aldershot BGD092.17 quartermasters stores | C34: Commercial | D34: CommLease | E34: Tenanted | F34: The Source Young Peoples Charity. | G34: Aldershot BGD092.17 quartermasters stores | H34: GREP-CoA The Source Young Peoples Charity. - Aldershot BGD092.17 quartermasters stores | I34: Dummy Opportunity exists in Salesforce | J34: 42200 | K34: n/a | L34: 0 | M34: 0 | N34: 0 | O34: n/a | P34: n/a | Q34: n/a | R34: 0 | S34: 0 | T34: =VLOOKUP(A34,#REF!,9,FALSE) -> #REF! | U34: No | V34: No | W34: 0 | X34: 0 | Y34: 0
A35: 122494036 | B35: Aldershot BGD092 BROWNING quartermasters stor | C35: Commercial | D35: CommLease | E35: Tenanted | F35: Logical Fulfilment Limited. | G35: #N/A | H35: #N/A | I35: Opportunity does not exist in Salesforce | J35: 45292 | K35: 46112 | L35: 2 | M35: 3 | N35: 0 | O35: n/a | P35: n/a | Q35: n/a | R35: 0 | S35: 0 | T35: =VLOOKUP(A35,#REF!,9,FALSE) -> #REF! | U35: Yes | V35: No | W35: 0 | X35: 6 | Y35: 3
A36: 122494041 | B36: Aldershot BGA092 BROWNING 14 DOORS UTILITIES. | C36: Commercial | D36: CommLease | E36: Tenanted | F36: Express Limited | G36: Aldershot BGA092 BROWNING 14 DOORS UTILITIES. | H36: GREP-CoA Express Transport (UK) Ltd. - Aldershot BGA092 BROWNING 14 DOORS UTILITIES. | I36: Dummy Opportunity exists in Salesforce | J36: 43261 | K36: 44721 | L36: 4 | M36: 0 | N36: 0 | O36: n/a | P36: n/a | Q36: n/a | R36: 0 | S36: 0 | T36: =VLOOKUP(A36,#REF!,9,FALSE) -> #REF! | U36: No | V36: No | W36: 0 | X36: 0 | Y36: 0
A37: 122494044 | B37: Aldershot BG0090 MT Workshop Browning Brks. | C37: Commercial | D37: CommLease | E37: Tenanted | F37: Bywell productions ltd. | G37: #N/A | H37: #N/A | I37: Opportunity does not exist in Salesforce | J37: 45292 | K37: 46112 | L37: 2 | M37: 3 | N37: 0 | O37: n/a | P37: n/a | Q37: 45658 | R37: 0 | S37: 0 | T37: =VLOOKUP(A37,#REF!,9,FALSE) -> #REF! | U37: Yes | V37: No | W37: 0 | X37: 3 | Y37: 0
A38: 122495021 | B38: East Car Park at Mandora House. | C38: Commercial | D38: CommLease | E38: Tenanted | F38: Rhino Recovery Ltd | G38: East Car Park at Mandora House. | H38: GREP-CoA Rhino Recovery Ltd - East Car Park at Mandora House. | I38: Dummy Opportunity exists in Salesforce | J38: 45658 | K38: 46022 | L38: 1 | M38: 0 | N38: 0 | O38: n/a | P38: n/a | Q38: n/a | R38: 0 | S38: 0 | T38: =VLOOKUP(A38,#REF!,9,FALSE) -> #REF! | U38: Yes | V38: Yes | W38: 0 | X38: 1 | Y38: 0
A39: 122495023 | B39: Aldershot Mandora Part of West Car Park 1 | C39: Commercial | D39: CommLease | E39: Tenanted | F39: We Buy Any Car Limited | G39: Aldershot Mandora Part of West Car Park 1 | H39: GREP-CoA We Buy Any Car Limited - Aldershot Mandora Part of West Car Park 1 | I39: Dummy Opportunity exists in Salesforce | J39: 45139 | K39: 45657 | L39: 1 | M39: 5 | N39: 0 | O39: n/a | P39: n/a | Q39: n/a | R39: 0 | S39: 0 | T39: =VLOOKUP(A39,#REF!,9,FALSE) -> #REF! | U39: Yes | V39: Yes | W39: 0 | X39: 0 | Y39: 0
A40: 122495025 | B40: Aldershot BL0187 BULLER Block A Offcrs Mess | C40: Commercial | D40: CommLease | E40: Tenanted | F40: Civil Nuclear Police Authority. | G40: #N/A | H40: #N/A | I40: Opportunity does not exist in Salesforce | J40: 45292 | K40: 45930 | L40: 1 | M40: 9 | N40: 0 | O40: n/a | P40: n/a | Q40: n/a | R40: 0 | S40: 0 | T40: =VLOOKUP(A40,#REF!,9,FALSE) -> #REF! | U40: Yes | V40: Yes | W40: 0 | X40: 0 | Y40: 3
A41: 122495033 | B41: Aldershot Buller Barracks PrdGrnd1/hardstndng | C41: Commercial | D41: CommLic | E41: Tenanted | F41: Tercel Medical Group Limited. | G41: #N/A | H41: #N/A | I41: Opportunity does not exist in Salesforce | J41: 45658 | K41: 46022 | L41: 1 | M41: 0 | N41: 0 | O41: n/a | P41: n/a | Q41: n/a | R41: 0 | S41: 0 | T41: =VLOOKUP(A41,#REF!,9,FALSE) -> #REF! | U41: Yes | V41: Yes | W41: 0 | X41: 3 | Y41: 0
A42: 122497011 | B42: Clayton Barracks - Hardstanding. | C42: Commercial | D42: CommLease | E42: Tenanted | F42: Shred on Site Ltd | G42: Clayton Barracks - Hardstanding. | H42: GREP-CoA Shred on Site Ltd - Clayton Barracks - Hardstanding. | I42: Dummy Opportunity exists in Salesforce | J42: 45383 | K42: 46064 | L42: 1 | M42: 10 | N42: 11 | O42: n/a | P42: n/a | Q42: 45700 | R42: 0 | S42: 0 | T42: =VLOOKUP(A42,#REF!,9,FALSE) -> #REF! | U42: Yes | V42: Yes | W42: 0 | X42: 0 | Y42: 0
A43: 122498004 | B43: Aldershot GS0061 GARRISON Sergeants Mess | C43: Commercial | D43: CommLease | E43: Tenanted | F43: Oak Housing Limited. | G43: #N/A | H43: #N/A | I43: Opportunity does not exist in Salesforce | J43: 44549 | K43: 46374 | L43: 5 | M43: 0 | N43: 0 | O43: n/a | P43: n/a | Q43: 45645 | R43: 1 | S43: 6 | T43: =VLOOKUP(A43,#REF!,9,FALSE) -> #REF! | U43: Yes | V43: Yes | W43: 0 | X43: 6 | Y43: 6
A44: 122501007 | B44: Aldershot PR0041 Parsons Barracks Portakabin | C44: Commercial | D44: CommLease | E44: Tenanted | F44: UK Power networks Services(Commercial)Ltd. | G44: #N/A | H44: #N/A | I44: Opportunity does not exist in Salesforce | J44: 45658 | K44: 46022 | L44: 1 | M44: 0 | N44: 0 | O44: n/a | P44: n/a | Q44: n/a | R44: 0 | S44: 0 | T44: =VLOOKUP(A44,#REF!,9,FALSE) -> #REF! | U44: Yes | V44: Yes | W44: 0 | X44: 6 | Y44: 0
A45: 122503001 | B45: Aldershot AG0049 Maida Gym | C45: Commercial | D45: CommLease | E45: Tenanted | F45: Fight Science Limited. | G45: #N/A | H45: #N/A | I45: Opportunity does not exist in Salesforce | J45: 44897 | K45: 45656 | L45: 2 | M45: 0 | N45: 29 | O45: n/a | P45: n/a | Q45: n/a | R45: 0 | S45: 0 | T45: =VLOOKUP(A45,#REF!,9,FALSE) -> #REF! | U45: Yes | V45: Yes | W45: 0 | X45: 3 | Y45: 6
A46: 122503002 | B46: Aldershot AG0050 Smith Dorrien Part of Bldg. | C46: Commercial | D46: CommLease | E46: Tenanted | F46: Mayer Brown Limited. | G46: Aldershot AG0050 Smith Dorrien Part of Bldg. | H46: GREP-CoA Mayer Brown Limited - Aldershot AG0050 Smith Dorrien Part of Bldg. | I46: Dummy Opportunity exists in Salesforce | J46: 45306 | K46: 46401 | L46: 3 | M46: 0 | N46: 0 | O46: n/a | P46: n/a | Q46: 46022 | R46: 0 | S46: 0 | T46: =VLOOKUP(A46,#REF!,9,FALSE) -> #REF! | U46: Yes | V46: Yes | W46: 0 | X46: 6 | Y46: 6
A47: 122505001 | B47: Wellesley Barracks ABRO Warehouse | C47: Commercial | D47: CommLease | E47: Tenanted | F47: The Location Collective Limited. | G47: #N/A | H47: #N/A | I47: Opportunity does not exist in Salesforce | J47: 43644 | K47: n/a | L47: 0 | M47: 0 | N47: 0 | O47: n/a | P47: n/a | Q47: n/a | R47: 0 | S47: 0 | T47: =VLOOKUP(A47,#REF!,9,FALSE) -> #REF! | U47: No | V47: No | W47: 0 | X47: 0 | Y47: 0
A48: 127057246 | B48: GR-Hotel, Kings Dock Mill, Liverpool, L1 | C48: Commercial | D48: CommLease | E48: Tenanted | F48: Hampton by Hilton | G48: GR-Hotel, Kings Dock Mill, Liverpool, L1 | H48: GREP-CoA Hampton by Hilton - GR-Hotel, Kings Dock Mill, Liverpool, L1 | I48: Dummy Opportunity exists in Salesforce | J48: 39420 | K48: 94203 | L48: 149 | M48: 11 | N48: 27 | O48: n/a | P48: n/a | Q48: n/a | R48: 0 | S48: 0 | T48: =VLOOKUP(A48,#REF!,9,FALSE) -> #REF! | U48: No | V48: No | W48: 0 | X48: 0 | Y48: 0
A49: 127139001 | B49: 2, Highfield Avenue, Newbury, RG14 5DS | C49: DEVELOPMENT | D49: Comm-Let | E49: Tenanted | F49: Mr Nicholas Battle | G49: #N/A | H49: #N/A | I49: Opportunity does not exist in Salesforce | J49: n/a | K49: n/a | L49: 0 | M49: 0 | N49: 0 | O49: n/a | P49: n/a | Q49: n/a | R49: 0 | S49: 0 | T49: =VLOOKUP(A49,#REF!,9,FALSE) -> #REF! | U49: No | V49: No | W49: 0 | X49: 0 | Y49: 0
A50: 127771003 | B50: Compound - Marrelsmoor - Phase 9 Redrow | C50: Land | D50: CommLease | E50: Tenanted | F50: Redrow Homes Limited | G50: Compound - Marrelsmoor - Phase 9 Redrow | H50: GREP-CoA Redrow Homes Limited - Compound - Marrelsmoor - Phase 9 Redrow | I50: Dummy Opportunity exists in Salesforce | J50: 44998 | K50: 46824 | L50: 5 | M50: 0 | N50: 0 | O50: n/a | P50: n/a | Q50: 45729 | R50: 0 | S50: 0 | T50: =VLOOKUP(A50,#REF!,9,FALSE) -> #REF! | U50: Yes | V50: Yes | W50: 0 | X50: 6 | Y50: 0
A51: 127771004 | B51: Compound at Berewood – 6b Local Centre | C51: Land | D51: CommLease | E51: Tenanted | F51: BDW Trading Limited | G51: Compound at Berewood – 6b Local Centre | H51: GREP-CoA BDW Trading Limited - Compound at Berewood – 6b Local Centre | I51: Dummy Opportunity exists in Salesforce | J51: 45568 | K51: 45718 | L51: 0 | M51: 5 | N51: 0 | O51: n/a | P51: n/a | Q51: n/a | R51: 0 | S51: 0 | T51: =VLOOKUP(A51,#REF!,9,FALSE) -> #REF! | U51: No | V51: No | W51: 0 | X51: 3 | Y51: 0
A52: 222577001 | B52: Clippers - Unit 4-5 Waterman Walk | C52: Commercial | D52: CommLease | E52: Tenanted | F52: Co-operative Group Food Limited. | G52: Clippers - Unit 4-5 Waterman Walk | H52: GREP-CoA Co-operative Group Food Limited. - Clippers - Unit 4-5 Waterman Walk | I52: Dummy Opportunity exists in Salesforce | J52: 43616 | K52: 49094 | L52: 15 | M52: 0 | N52: 0 | O52: n/a | P52: n/a | Q52: 47269 | R52: 5 | S52: 3 | T52: =VLOOKUP(A52,#REF!,9,FALSE) -> #REF! | U52: No | V52: No | W52: 0 | X52: 0 | Y52: 3
A53: 222577002 | B53: Clippers - Unit 1 Zerega Way M50 | C53: Commercial | D53: CommLease | E53: Tenanted | F53: TETA Ltd | G53: Unit 1 Zerega Way M50 | H53: GREP-CoA TETA Ltd - Clippers - Unit 1 Zerega Way M50 | I53: Dummy Opportunity exists in Salesforce | J53: 45449 | K53: 49100 | L53: 10 | M53: 0 | N53: 0 | O53: n/a | P53: n/a | Q53: 47275 | R53: 0 | S53: 0 | T53: =VLOOKUP(A53,#REF!,9,FALSE) -> #REF! | U53: No | V53: Yes | W53: 0 | X53: 6 | Y53: 0
A54: 222577003 | B54: Clippers - Unit 2 Zerega Way M50 | C54: Commercial | D54: CommLease | E54: Tenanted | F54: OB1 Bars Ltd | G54: Clippers - Unit 2 Zerega Way M50 | H54: GREP-CoA OB1 Bars Ltd - Clippers - Unit 2 Zerega Way M50 | I54: Dummy Opportunity exists in Salesforce | J54: 43817 | K54: 47469 | L54: 10 | M54: 0 | N54: 0 | O54: n/a | P54: n/a | Q54: 45644 | R54: 0 | S54: 0 | T54: =VLOOKUP(A54,#REF!,9,FALSE) -> #REF! | U54: No | V54: Yes | W54: 0 | X54: 0 | Y54: 3
A55: 222577004 | B55: Clippers - Unit 3 Waterman Walk (GPLC Office) | C55: Commercial | D55: CommLease | E55: Tenanted | F55: Grainger Land & Regeneration Limited. | G55: Clippers - Unit 3 Waterman Walk (GPLC Office) | H55: GREP-CoA Grainger Land & Regeneration Limited. - Clippers - Unit 3 Waterman Walk (GPLC Office) | I55: Dummy Opportunity exists in Salesforce | J55: 44124 | K55: 45949 | L55: 5 | M55: 0 | N55: 0 | O55: n/a | P55: n/a | Q55: n/a | R55: 0 | S55: 0 | T55: =VLOOKUP(A55,#REF!,9,FALSE) -> #REF! | U55: No | V55: No | W55: 0 | X55: 0 | Y55: 0
A56: 222577005 | B56: Clippers - Unit 2 Waterman Walk (GPLC Office) | C56: Commercial | D56: CommLease | E56: Tenanted | F56: Grainger Land & Regeneration Limited. | G56: Clippers - Unit 2 Waterman Walk (GPLC Office) | H56: GREP-CoA Grainger Land & Regeneration Limited. - Clippers - Unit 2 Waterman Walk (GPLC Office) | I56: Dummy Opportunity exists in Salesforce | J56: 44133 | K56: 45958 | L56: 5 | M56: 0 | N56: 0 | O56: n/a | P56: n/a | Q56: n/a | R56: 0 | S56: 0 | T56: =VLOOKUP(A56,#REF!,9,FALSE) -> #REF! | U56: No | V56: No | W56: 0 | X56: 0 | Y56: 0
A57: 222577006 | B57: Clippers - Unit 1 Waterman Walk | C57: Commercial | D57: CommLease | E57: Tenanted | F57: Cult Group Limited. | G57: Clippers - Unit 1 Waterman Walk | H57: GREP-CoA Cult Group Limited. - Clippers - Unit 1 Waterman Walk | I57: Dummy Opportunity exists in Salesforce | J57: 43472 | K57: 48950 | L57: 15 | M57: 0 | N57: 0 | O57: n/a | P57: n/a | Q57: 45298 | R57: 5 | S57: 6 | T57: =VLOOKUP(A57,#REF!,9,FALSE) -> #REF! | U57: No | V57: Yes | W57: 0 | X57: 0 | Y57: 6
A58: 222625002 | B58: Unit 2, Hawkins Lane Building, East Tucker St | C58: Commercial | D58: CommLease | E58: Tenanted | F58: Ruby Hue Ltd | G58: Unit 2, Hawkins Lane Building, East Tucker St | H58: GREP-CoA Ruby Hue Ltd - Unit 2, Hawkins Lane Building, East Tucker St | I58: Dummy Opportunity exists in Salesforce | J58: 44867 | K58: 48519 | L58: 10 | M58: 0 | N58: 0 | O58: n/a | P58: n/a | Q58: 46693 | R58: 0 | S58: 0 | T58: =VLOOKUP(A58,#REF!,9,FALSE) -> #REF! | U58: Yes | V58: Yes | W58: 0 | X58: 6 | Y58: 0
A59: 222632001 | B59: Unit 1 Brook Place 110 Napier Street S11 8BR | C59: Commercial | D59: CommLease | E59: Tenanted | F59: R1SE Brook Place Ltd. | G59: Unit 1 Brook Place 110 Napier Street S11 8BR | H59: GREP-CoA R1SE Brook Place Ltd. - Unit 1 Brook Place 110 Napier Street S11 8BR | I59: Dummy Opportunity exists in Salesforce | J59: 44326 | K59: 47977 | L59: 10 | M59: 0 | N59: 0 | O59: n/a | P59: n/a | Q59: 46152 | R59: 5 | S59: 6 | T59: =VLOOKUP(A59,#REF!,9,FALSE) -> #REF! | U59: No | V59: Yes | W59: 0 | X59: 0 | Y59: 6
A60: 222632002 | B60: Unit 2, Brook Place, 112 Napier Street, S11 8 | C60: Commercial | D60: CommLease | E60: Tenanted | F60: R1SE Brook Place Ltd. | G60: Unit 2, Brook Place, 112 Napier Street, S11 8 | H60: GREP-CoA R1SE Brook Place Ltd. - Unit 2, Brook Place, 112 Napier Street, S11 8 | I60: Dummy Opportunity exists in Salesforce | J60: 44326 | K60: 47977 | L60: 10 | M60: 0 | N60: 0 | O60: n/a | P60: n/a | Q60: n/a | R60: 0 | S60: 0 | T60: =VLOOKUP(A60,#REF!,9,FALSE) -> #REF! | U60: No | V60: No | W60: 0 | X60: 0 | Y60: 0
A61: 222632003 | B61: Unit 3, Brook Place, 114 Napier Street, S11 8 | C61: Commercial | D61: CommLease | E61: Tenanted | F61: Smile2Impress Clinics Ltd | G61: Unit 3, Brook Place, 114 Napier Street, S11 8 | H61: GREP-CoA Smile2Impress Clinics Ltd - Unit 3, Brook Place, 114 Napier Street, S11 8 | I61: Dummy Opportunity exists in Salesforce | J61: 44729 | K61: 48381 | L61: 10 | M61: 0 | N61: 0 | O61: n/a | P61: n/a | Q61: 46555 | R61: 0 | S61: 0 | T61: =VLOOKUP(A61,#REF!,9,FALSE) -> #REF! | U61: No | V61: No | W61: 0 | X61: 6 | Y61: 0
A62: 222641001 | B62: 809, Silbury Boulevard, Milton Keynes, MK9 | C62: Commercial | D62: CommLease | E62: Tenanted | F62: Spectrum Associates (MK) Ltd | G62: 809, Silbury Boulevard, Milton Keynes, MK9 | H62: REP-CoA Spectrum Associates (MK) Ltd - 809, Silbury Boulevard, Milton Keynes, MK9 | I62: Dummy Opportunity exists in Salesforce | J62: 44448 | K62: 49865 | L62: 14 | M62: 10 | N62: 1 | O62: n/a | P62: n/a | Q62: 46274 | R62: 0 | S62: 0 | T62: =VLOOKUP(A62,#REF!,9,FALSE) -> #REF! | U62: No | V62: No | W62: 0 | X62: 5 | Y62: 0
A63: 222641002 | B63: 811, Silbury Boulevard, Milton Keynes, MK9 | C63: Commercial | D63: CommLease | E63: Tenanted | F63: Spectrum Associates (MK) Ltd | G63: 811, Silbury Boulevard, Milton Keynes, MK9 | H63: GREP-CoA Spectrum Associates (MK) Ltd - 811, Silbury Boulevard, Milton Keynes, MK9 | I63: Dummy Opportunity exists in Salesforce | J63: 44448 | K63: 49865 | L63: 14 | M63: 10 | N63: 1 | O63: n/a | P63: n/a | Q63: n/a | R63: 0 | S63: 0 | T63: =VLOOKUP(A63,#REF!,9,FALSE) -> #REF! | U63: No | V63: No | W63: 0 | X63: 0 | Y63: 0
A64: 222644002 | B64: Unit 2, Juniper House | C64: Commercial | D64: CommLease | E64: Tenanted | F64: Pure Gym Limited | G64: Unit 2, Juniper House | H64: #N/A | I64: Opportunity does not exist in Salesforce | J64: 45194 | K64: 50672 | L64: 15 | M64: 0 | N64: 0 | O64: n/a | P64: n/a | Q64: n/a | R64: 0 | S64: 0 | T64: =VLOOKUP(A64,#REF!,9,FALSE) -> #REF! | U64: No | V64: No | W64: 0 | X64: 0 | Y64: 0
A65: 222644003 | B65: Unit 3, Juniper House | C65: Commercial | D65: CommLease | E65: Tenanted | F65: Pure Gym Limited | G65: Unit 3, Juniper House | H65: #N/A | I65: Opportunity does not exist in Salesforce | J65: 45194 | K65: 50672 | L65: 15 | M65: 0 | N65: 0 | O65: n/a | P65: n/a | Q65: n/a | R65: 0 | S65: 0 | T65: =VLOOKUP(A65,#REF!,9,FALSE) -> #REF! | U65: No | V65: No | W65: 0 | X65: 0 | Y65: 0
A66: 222644004 | B66: Unit 4, Juniper House | C66: Commercial | D66: CommLease | E66: Tenanted | F66: Pure Gym Limited | G66: Unit 4, Juniper House | H66: GREP-CoA Pure Gym Limited - Unit 4, Juniper House | I66: Dummy Opportunity exists in Salesforce | J66: 45194 | K66: 50672 | L66: 15 | M66: 0 | N66: 0 | O66: n/a | P66: n/a | Q66: 45559 | R66: 0 | S66: 0 | T66: =VLOOKUP(A66,#REF!,9,FALSE) -> #REF! | U66: No | V66: No | W66: 0 | X66: 6 | Y66: 0
A67: 222644005 | B67: Unit 5, Juniper House | C67: Commercial | D67: CommLease | E67: Tenanted | F67: Pure Gym Limited | G67: Unit 5, Juniper House | H67: #N/A | I67: Opportunity does not exist in Salesforce | J67: 45194 | K67: 50672 | L67: 15 | M67: 0 | N67: 0 | O67: n/a | P67: n/a | Q67: n/a | R67: 0 | S67: 0 | T67: =VLOOKUP(A67,#REF!,9,FALSE) -> #REF! | U67: No | V67: No | W67: 0 | X67: 0 | Y67: 0
A68: 222644006 | B68: Unit 6, Juniper House | C68: Commercial | D68: CommLease | E68: Tenanted | F68: Pure Gym Limited | G68: Unit 6, Juniper House | H68: #N/A | I68: Opportunity does not exist in Salesforce | J68: 45194 | K68: 50672 | L68: 15 | M68: 0 | N68: 0 | O68: n/a | P68: n/a | Q68: n/a | R68: 0 | S68: 0 | T68: =VLOOKUP(A68,#REF!,9,FALSE) -> #REF! | U68: No | V68: No | W68: 0 | X68: 0 | Y68: 0
A69: 222653002 | B69: Unit 2, Halogen House, 217 Chapel St, Salford | C69: COMMERCIAL | D69: CommLease | E69: Tenanted | F69: K&K Hospitality Ltd | G69: Unit 2, Halogen House, 217 Chapel St, Salford | H69: GREP-CoA K&K Hospitality Ltd - Unit 2, Halogen House, 217 Chapel St, Salford | I69: Dummy Opportunity exists in Salesforce | J69: 44642 | K69: 47198 | L69: 7 | M69: 0 | N69: 0 | O69: n/a | P69: n/a | Q69: 46468 | R69: 0 | S69: 0 | T69: =VLOOKUP(A69,#REF!,9,FALSE) -> #REF! | U69: No | V69: No | W69: 0 | X69: 6 | Y69: 0
A70: 222653003 | B70: Unit 3, Halogen House, 217 Chapel St, Salford | C70: Commercial | D70: CommLease | E70: Tenanted | F70: BMSJ Company Limited | G70: Unit 3, Halogen House, 217 Chapel St, Salford | H70: GREP-CoA BMSJ Company Limited - Unit 3, Halogen House, 217 Chapel St, Salford | I70: Dummy Opportunity exists in Salesforce | J70: 44470 | K70: 46295 | L70: 5 | M70: 0 | N70: 0 | O70: n/a | P70: n/a | Q70: 45566 | R70: 0 | S70: 0 | T70: =VLOOKUP(A70,#REF!,9,FALSE) -> #REF! | U70: No | V70: No | W70: 0 | X70: 6 | Y70: 0
A71: 222653004 | B71: Unit 4, Neon House, 207 Chapel St, Salford, M | C71: COMMERCIAL | D71: CommLease | E71: Tenanted | F71: Shoalter Automation (UK) Limited | G71: Unit 4, Neon House, 207 Chapel St, Salford, M | H71: GREP-CoA Shoalter Automation (UK) Limited - Unit 4, Neon House, 207 Chapel St, Salford, M | I71: Dummy Opportunity exists in Salesforce | J71: 44992 | K71: 48645 | L71: 10 | M71: 0 | N71: 1 | O71: n/a | P71: n/a | Q71: 46819 | R71: 0 | S71: 0 | T71: =VLOOKUP(A71,#REF!,9,FALSE) -> #REF! | U71: No | V71: No | W71: 0 | X71: 0 | Y71: 0
A72: 222653005 | B72: Unit 5, Neon House, 207 Chapel St, Salford, M | C72: COMMERCIAL | D72: CommLease | E72: Tenanted | F72: Rush 242 Ltd | G72: Unit 5, Neon House, 207 Chapel St, Salford, M | H72: GREP-CoA Rush 242 Ltd - Unit 5, Neon House, 207 Chapel St, Salford, M | I72: Dummy Opportunity exists in Salesforce | J72: 45064 | K72: 48716 | L72: 10 | M72: 0 | N72: 0 | O72: n/a | P72: n/a | Q72: 46905 | R72: 0 | S72: 0 | T72: =VLOOKUP(A72,#REF!,9,FALSE) -> #REF! | U72: No | V72: No | W72: 0 | X72: 6 | Y72: 0
A73: 222653006 | B73: Unit 6, Neon House, 207 Chapel St, Salford, M | C73: COMMERCIAL | D73: CommLease | E73: Tenanted | F73: BLS International Services (UK) Ltd | G73: Unit 6, Neon House, 207 Chapel St, Salford, M | H73: GREP-CoA BLS International Services (UK) Ltd - Unit 6, Neon House, 207 Chapel St, Salford, M | I73: Dummy Opportunity exists in Salesforce | J73: 45156 | K73: 48808 | L73: 10 | M73: 0 | N73: 0 | O73: n/a | P73: n/a | Q73: 46983 | R73: 0 | S73: 0 | T73: =VLOOKUP(A73,#REF!,9,FALSE) -> #REF! | U73: Yes | V73: Yes | W73: 0 | X73: 0 | Y73: 0
A74: 222662001 | B74: Unit 1, 87 East St, Southampton | C74: COMMERCIAL | D74: CommLease | E74: Tenanted | F74: Aesthetic House Ltd - DO NOT USE | G74: Unit 1, 87 East St, Southampton | H74: GREP-CoA Aesthetic House Ltd - Unit 1, 87 East St, Southampton | I74: Dummy Opportunity exists in Salesforce | J74: 44494 | K74: 48145 | L74: 10 | M74: 0 | N74: 0 | O74: n/a | P74: n/a | Q74: 46320 | R74: 0 | S74: 0 | T74: =VLOOKUP(A74,#REF!,9,FALSE) -> #REF! | U74: No | V74: No | W74: 0 | X74: 6 | Y74: 0
A75: 222669001 | B75: Unit 1, Wellington Park Way, Leeds | C75: COMMERCIAL | D75: CommLease | E75: Tenanted | F75: Dexastrong Ltd - in Liquidation | G75: Unit 1, Wellington Park Way, Leeds | H75: GREP-CoA Dexastrong Ltd - Unit 1, Wellington Park Way, Leeds | I75: Dummy Opportunity exists in Salesforce | J75: 44756 | K75: 48408 | L75: 10 | M75: 0 | N75: 0 | O75: n/a | P75: n/a | Q75: 46582 | R75: 0 | S75: 0 | T75: =VLOOKUP(A75,#REF!,9,FALSE) -> #REF! | U75: Yes | V75: Yes | W75: 0 | X75: 6 | Y75: 0
A76: 222690001 | B76: Gilders Yard - A.01, 19/21 Great Hampton St | C76: COMMERCIAL | D76: CommLease | E76: Tenanted | F76: J S Convenience Stores Ltd | G76: Gilders Yard - A.01, 19/21 Great Hampton St | H76: GREP-CoA J S Convenience Stores Ltd - Gilders Yard - A.01, 19/21 Great Hampton St | I76: Dummy Opportunity exists in Salesforce | J76: 45107 | K76: 50585 | L76: 15 | M76: 0 | N76: 0 | O76: n/a | P76: n/a | Q76: 46934 | R76: 0 | S76: 0 | T76: =VLOOKUP(A76,#REF!,9,FALSE) -> #REF! | U76: No | V76: No | W76: 0 | X76: 6 | Y76: 0
A77: 222690002 | B77: Gilders Yard - A.02, 1 Harford Street | C77: COMMERCIAL | D77: CommLease | E77: Tenanted | F77: C. Barber Limited t/a Venture Studios | G77: Gilders Yard - A.02, 1 Harford Street | H77: GREP-CoA C. Barber Limited t/a Venture Studios - Gilders Yard - A.02, 1 Harford Street | I77: Dummy Opportunity exists in Salesforce | J77: 45037 | K77: 48689 | L77: 10 | M77: 0 | N77: 0 | O77: n/a | P77: n/a | Q77: 46864 | R77: 0 | S77: 0 | T77: =VLOOKUP(A77,#REF!,9,FALSE) -> #REF! | U77: No | V77: No | W77: 0 | X77: 6 | Y77: 0
A78: 222690004 | B78: Gilders Yard-Office, 16/18 Great Hampton St | C78: COMMERCIAL | D78: CommLease | E78: Tenanted | F78: Grainger Residential Management Limited | G78: Gilders Yard-Office, 16/18 Great Hampton St | H78: GREP-CoA Grainger Residential Management Limited - Gilders Yard-Office, 16/18 Great Hampton St | I78: Dummy Opportunity exists in Salesforce | J78: 45223 | K78: 47049 | L78: 5 | M78: 0 | N78: 0 | O78: n/a | P78: n/a | Q78: n/a | R78: 0 | S78: 0 | T78: =VLOOKUP(A78,#REF!,9,FALSE) -> #REF! | U78: No | V78: No | W78: 0 | X78: 6 | Y78: 0
A79: 222707002 | B79: Unit 1.2 Redcliffe Quarter, Bristol. BS1 6WL | C79: COMMERCIAL | D79: CommLease | E79: Tenanted | F79: Jozsef Turok T/A Doubleshot Barbers | G79: Unit 1.2 Redcliffe Quarter, Bristol. BS1 6WL | H79: GREP-CoA Jozsef Turok T/A Doubleshot Barbers - Unit 1.2 Redcliffe Quarter, Bristol. BS1 6WL | I79: Dummy Opportunity exists in Salesforce | J79: 45541 | K79: 49192 | L79: 10 | M79: 0 | N79: 0 | O79: n/a | P79: n/a | Q79: 47367 | R79: 0 | S79: 0 | T79: =VLOOKUP(A79,#REF!,9,FALSE) -> #REF! | U79: Yes | V79: Yes | W79: 0 | X79: 6 | Y79: 0
A80: 222707003 | B80: Unit 1.3 Redcliffe Quarter, Bristol. BS1 6WL | C80: COMMERCIAL | D80: CommLease | E80: Tenanted | F80: UKGolfbox Bristol Ltd | G80: Unit 1.3 Redcliffe Quarter, Bristol. BS1 6WL | H80: GREP-CoA UKGolfbox Bristol Ltd - Unit 1.3 Redcliffe Quarter, Bristol. BS1 6WL | I80: Dummy Opportunity exists in Salesforce | J80: 45607 | K80: 47432 | L80: 5 | M80: 0 | N80: 0 | O80: n/a | P80: n/a | Q80: n/a | R80: 0 | S80: 0 | T80: =VLOOKUP(A80,#REF!,9,FALSE) -> #REF! | U80: No | V80: No | W80: 0 | X80: 6 | Y80: 0
A81: 222710019 | B81: Parking 19 Enigma Square | C81: ParkingSpac | D81: CommLease | E81: Tenanted | F81: Krishna Asian Food Market Limited | G81: Parking 19 Enigma Square | H81: GREP-CoA Krishna Asian Food Market Limited - Parking 19 Enigma Square | I81: Dummy Opportunity exists in Salesforce | J81: 45645 | K81: 51122 | L81: 15 | M81: 0 | N81: 0 | O81: 45511 | P81: n/a | Q81: n/a | R81: 0 | S81: 0 | T81: =VLOOKUP(A81,#REF!,9,FALSE) -> #REF! | U81: No | V81: No | W81: 0 | X81: 3 | Y81: 0
A82: 222710030 | B82: Parking 30 Enigma Square | C82: ParkingSpac | D82: CommLease | E82: Tenanted | F82: Krishna Asian Food Market Limited | G82: Parking 30 Enigma Square | H82: #N/A | I82: Opportunity does not exist in Salesforce | J82: 45645 | K82: 51122 | L82: 15 | M82: 0 | N82: 0 | O82: n/a | P82: n/a | Q82: n/a | R82: 0 | S82: 0 | T82: =VLOOKUP(A82,#REF!,9,FALSE) -> #REF! | U82: No | V82: No | W82: 0 | X82: 3 | Y82: 0
A83: 222710037 | B83: Parking 37 Enigma Square | C83: ParkingSpac | D83: CommLease | E83: Tenanted | F83: Krishna Asian Food Market Limited | G83: Parking 37 Enigma Square | H83: GREP-CoA Krishna Asian Food Market Limited - Parking 37 Enigma Square | I83: Dummy Opportunity exists in Salesforce | J83: 45645 | K83: 51122 | L83: 15 | M83: 0 | N83: 0 | O83: 45352 | P83: n/a | Q83: n/a | R83: 0 | S83: 0 | T83: =VLOOKUP(A83,#REF!,9,FALSE) -> #REF! | U83: No | V83: No | W83: 0 | X83: 3 | Y83: 2
A84: 222710102 | B84: Parking 102 Enigma Square | C84: ParkingSpac | D84: CommLease | E84: Tenanted | F84: Krishna Asian Food Market Limited | G84: Parking 102 Enigma Square | H84: GREP-CoA Krishna Asian Food Market Limited - Parking 102 Enigma Square | I84: Dummy Opportunity exists in Salesforce | J84: 45645 | K84: 51122 | L84: 15 | M84: 0 | N84: 0 | O84: n/a | P84: 45633 | Q84: n/a | R84: 0 | S84: 0 | T84: =VLOOKUP(A84,#REF!,9,FALSE) -> #REF! | U84: No | V84: No | W84: 0 | X84: 3 | Y84: 0
A85: 222710107 | B85: Parking 107 Enigma Square | C85: ParkingSpac | D85: CommLease | E85: Tenanted | F85: Krishna Asian Food Market Limited | G85: Parking 107 Enigma Square | H85: GREP-CoA Krishna Asian Food Market Limited - Parking 107 Enigma Square | I85: Dummy Opportunity exists in Salesforce | J85: 45645 | K85: 51122 | L85: 15 | M85: 0 | N85: 0 | O85: 45510 | P85: n/a | Q85: n/a | R85: 0 | S85: 0 | T85: =VLOOKUP(A85,#REF!,9,FALSE) -> #REF! | U85: No | V85: No | W85: 0 | X85: 3 | Y85: 0
A86: 222710108 | B86: Parking 108 Enigma Square | C86: ParkingSpac | D86: CommLease | E86: Tenanted | F86: Krishna Asian Food Market Limited | G86: Parking 108 Enigma Square | H86: GREP-CoA Krishna Asian Food Market Limited - Parking 108 Enigma Square | I86: Dummy Opportunity exists in Salesforce | J86: 45645 | K86: 51122 | L86: 15 | M86: 0 | N86: 0 | O86: 45510 | P86: n/a | Q86: n/a | R86: 0 | S86: 0 | T86: =VLOOKUP(A86,#REF!,9,FALSE) -> #REF! | U86: No | V86: No | W86: 0 | X86: 3 | Y86: 0
A87: 222710112 | B87: Parking 112 Enigma Square | C87: ParkingSpac | D87: CommLease | E87: Tenanted | F87: Krishna Asian Food Market Limited | G87: Parking 112 Enigma Square | H87: GREP-CoA Krishna Asian Food Market Limited - Parking 112 Enigma Square | I87: Dummy Opportunity exists in Salesforce | J87: 45645 | K87: 51122 | L87: 15 | M87: 0 | N87: 0 | O87: 45473 | P87: n/a | Q87: n/a | R87: 0 | S87: 0 | T87: =VLOOKUP(A87,#REF!,9,FALSE) -> #REF! | U87: No | V87: No | W87: 0 | X87: 3 | Y87: 2
A88: 222710153 | B88: Parking 153 Enigma Square | C88: ParkingSpac | D88: CommLease | E88: Tenanted | F88: Krishna Asian Food Market Limited | G88: Parking 153 Enigma Square | H88: GREP-CoA Krishna Asian Food Market Limited - Parking 153 Enigma Square | I88: Dummy Opportunity exists in Salesforce | J88: 45645 | K88: 51122 | L88: 15 | M88: 0 | N88: 0 | O88: n/a | P88: n/a | Q88: n/a | R88: 0 | S88: 0 | T88: =VLOOKUP(A88,#REF!,9,FALSE) -> #REF! | U88: No | V88: No | W88: 0 | X88: 0 | Y88: 0
A89: 222710154 | B89: Parking 154 Enigma Square | C89: ParkingSpac | D89: CommLease | E89: Tenanted | F89: Krishna Asian Food Market Limited | G89: Parking 154 Enigma Square | H89: GREP-CoA Krishna Asian Food Market Limited - Parking 154 Enigma Square | I89: Dummy Opportunity exists in Salesforce | J89: 45645 | K89: 51122 | L89: 15 | M89: 0 | N89: 0 | O89: 45484 | P89: n/a | Q89: n/a | R89: 0 | S89: 0 | T89: =VLOOKUP(A89,#REF!,9,FALSE) -> #REF! | U89: No | V89: No | W89: 0 | X89: 3 | Y89: 0
A90: 222710162 | B90: Parking 162 Enigma Square | C90: ParkingSpac | D90: CommLease | E90: Tenanted | F90: Krishna Asian Food Market Limited | G90: Parking 162 Enigma Square | H90: GREP-CoA Krishna Asian Food Market Limited - Parking 162 Enigma Square | I90: Dummy Opportunity exists in Salesforce | J90: 45645 | K90: 51122 | L90: 15 | M90: 0 | N90: 0 | O90: n/a | P90: n/a | Q90: n/a | R90: 0 | S90: 0 | T90: =VLOOKUP(A90,#REF!,9,FALSE) -> #REF! | U90: No | V90: No | W90: 0 | X90: 0 | Y90: 2
A91: 222711001 | B91: Commercial unit 1 Enigma Square | C91: COMMERCIAL | D91: CommLease | E91: Tenanted | F91: Krishna Asian Food Market Limited | G91: Commercial unit 1 Enigma Square | H91: GREP-CoA Krishna Asian Food Market Limited - Commercial unit 1 Enigma Square | I91: Dummy Opportunity exists in Salesforce | J91: 45645 | K91: 51122 | L91: 15 | M91: 0 | N91: 0 | O91: n/a | P91: n/a | Q91: 47471 | R91: 0 | S91: 0 | T91: =VLOOKUP(A91,#REF!,9,FALSE) -> #REF! | U91: No | V91: No | W91: 0 | X91: 6 | Y91: 0
A92: 222740001 | B92: Commercial Unit 1, 1 Springwell Sq | C92: COMMERCIAL | D92: CommLease | E92: Tenanted | F92: Phenix-UK Realty Ltd | G92: Commercial Unit 1, 1 Springwell Sq | H92: GREP-CoA Phenix-UK Realty Ltd - Commercial Unit 1, 1 Springwell Sq | I92: Dummy Opportunity exists in Salesforce | J92: 45471 | K92: 50948 | L92: 15 | M92: 0 | N92: 0 | O92: n/a | P92: n/a | Q92: 47297 | R92: 0 | S92: 0 | T92: =VLOOKUP(A92,#REF!,9,FALSE) -> #REF! | U92: No | V92: No | W92: 0 | X92: 0 | Y92: 0
A93: 222740002 | B93: Commercial Unit 2, 1 Springwell Sq | C93: COMMERCIAL | D93: CommLease | E93: Tenanted | F93: Coffee £1 Ltd | G93: Commercial Unit 2, 1 Springwell Sq | H93: GREP-CoA Coffee #1 Ltd - Commercial Unit 2, 1 Springwell Sq | I93: Dummy Opportunity exists in Salesforce | J93: 45229 | K93: 48881 | L93: 10 | M93: 0 | N93: 0 | O93: n/a | P93: n/a | Q93: 47056 | R93: 0 | S93: 0 | T93: =VLOOKUP(A93,#REF!,9,FALSE) -> #REF! | U93: Yes | V93: Yes | W93: 0 | X93: 6 | Y93: 0
A94: 222797001 | B94: 0.01 MSCP, 5 Capital Quarter, Tyndall St. | C94: ParkingSpac | D94: CommLic | E94: Tenanted | F94: Public Health Wales NHS Trust | G94: 0.01 MSCP, 5 Capital Quarter, Tyndall St. | H94: GREP-CoA Public Health Wales NHS Trust - 0.01 MSCP, 5 Capital Quarter, Tyndall St. | I94: Dummy Opportunity exists in Salesforce | J94: 42552 | K94: 46934 | L94: 0 | M94: 0 | N94: 0 | O94: n/a | P94: n/a | Q94: n/a | R94: 0 | S94: 0 | T94: =VLOOKUP(A94,#REF!,9,FALSE) -> #REF! | U94: No | V94: No | W94: 0 | X94: 0 | Y94: 0
A95: 222797002 | B95: 0.02 MSCP, 5 Capital Quarter, Tyndall St, | C95: ParkingSpac | D95: CommLic | E95: Tenanted | F95: Public Health Wales NHS Trust | G95: 0.02 MSCP, 5 Capital Quarter, Tyndall St, | H95: GREP-CoA Public Health Wales NHS Trust - 0.02 MSCP, 5 Capital Quarter, Tyndall St, | I95: Dummy Opportunity exists in Salesforce | J95: 42552 | K95: 46934 | L95: 0 | M95: 0 | N95: 0 | O95: n/a | P95: n/a | Q95: n/a | R95: 0 | S95: 0 | T95: =VLOOKUP(A95,#REF!,9,FALSE) -> #REF! | U95: No | V95: No | W95: 0 | X95: 0 | Y95: 0
A96: 222797003 | B96: 0.03 MSCP, 5 Capital Quarter, Tyndall St, | C96: ParkingSpac | D96: CommLic | E96: Tenanted | F96: Public Health Wales NHS Trust | G96: 0.03 MSCP, 5 Capital Quarter, Tyndall St, | H96: GREP-CoA Public Health Wales NHS Trust - 0.03 MSCP, 5 Capital Quarter, Tyndall St, | I96: Dummy Opportunity exists in Salesforce | J96: 42552 | K96: 46934 | L96: 0 | M96: 0 | N96: 0 | O96: n/a | P96: n/a | Q96: n/a | R96: 0 | S96: 0 | T96: =VLOOKUP(A96,#REF!,9,FALSE) -> #REF! | U96: No | V96: No | W96: 0 | X96: 0 | Y96: 0
A97: 222797005 | B97: 0.05 MSCP, 5 Capital Quarter, Tyndall St, | C97: ParkingSpac | D97: CommLic | E97: Tenanted | F97: Grainger Residential Limited | G97: 0.05 MSCP, 5 Capital Quarter, Tyndall St, | H97: GREP-CoA Grainger Residential Limited - 0.05 MSCP, 5 Capital Quarter, Tyndall St, | I97: Dummy Opportunity exists in Salesforce | J97: n/a | K97: n/a | L97: 0 | M97: 0 | N97: 0 | O97: n/a | P97: n/a | Q97: n/a | R97: 0 | S97: 0 | T97: =VLOOKUP(A97,#REF!,9,FALSE) -> #REF! | U97: No | V97: No | W97: 0 | X97: 0 | Y97: 0
A98: 222797006 | B98: 0.06 MSCP, 5 Capital Quarter, Tyndall St, | C98: ParkingSpac | D98: CommLic | E98: Tenanted | F98: Grainger Residential Limited | G98: 0.06 MSCP, 5 Capital Quarter, Tyndall St, | H98: GREP-CoA Grainger Residential Limited - 0.06 MSCP, 5 Capital Quarter, Tyndall St, | I98: Dummy Opportunity exists in Salesforce | J98: n/a | K98: n/a | L98: 0 | M98: 0 | N98: 0 | O98: n/a | P98: n/a | Q98: n/a | R98: 0 | S98: 0 | T98: =VLOOKUP(A98,#REF!,9,FALSE) -> #REF! | U98: No | V98: No | W98: 0 | X98: 0 | Y98: 0
A99: 222797007 | B99: 0.07 MSCP, 5 Capital Quarter, Tyndall St, | C99: ParkingSpac | D99: CommLic | E99: Tenanted | F99: WSP UK Limited | G99: 0.07 MSCP, 5 Capital Quarter, Tyndall St, | H99: GREP-CoA WSP UK Limited - 4.07 MSCP, 5 Capital Quarter, Tyndall St, | I99: Dummy Opportunity exists in Salesforce | J99: 44954 | K99: 46052 | L99: 0 | M99: 0 | N99: 0 | O99: n/a | P99: n/a | Q99: n/a | R99: 0 | S99: 0 | T99: =VLOOKUP(A99,#REF!,9,FALSE) -> #REF! | U99: No | V99: No | W99: 0 | X99: 0 | Y99: 0
A100: 222797008 | B100: 0.08 MSCP, 5 Capital Quarter, Tyndall St, | C100: ParkingSpac | D100: CommLic | E100: Tenanted | F100: WSP UK Limited | G100: 0.08 MSCP, 5 Capital Quarter, Tyndall St, | H100: GREP-CoA WSP UK Limited - 4.08 MSCP, 5 Capital Quarter, Tyndall St, | I100: Dummy Opportunity exists in Salesforce | J100: 44954 | K100: 46052 | L100: 0 | M100: 0 | N100: 0 | O100: n/a | P100: n/a | Q100: n/a | R100: 0 | S100: 0 | T100: =VLOOKUP(A100,#REF!,9,FALSE) -> #REF! | U100: No | V100: No | W100: 0 | X100: 0 | Y100: 0
A101: 222797009 | B101: 0.09 MSCP, 5 Capital Quarter, Tyndall St, | C101: ParkingSpac | D101: CommLic | E101: Tenanted | F101: WSP UK Limited | G101: 0.09 MSCP, 5 Capital Quarter, Tyndall St, | H101: GREP-CoA WSP UK Limited - 4.09 MSCP, 5 Capital Quarter, Tyndall St, | I101: Dummy Opportunity exists in Salesforce | J101: 44954 | K101: 46052 | L101: 0 | M101: 0 | N101: 0 | O101: n/a | P101: n/a | Q101: n/a | R101: 0 | S101: 0 | T101: =VLOOKUP(A101,#REF!,9,FALSE) -> #REF! | U101: No | V101: No | W101: 0 | X101: 0 | Y101: 0
...
