Workbook

Sheet Survey responses Data extension
A1: id | B1: Feedback | C1: Happy to be contacted | D1: Preferred contact details | E1: Email | F1: Survey sent time | G1: Like best about home | H1: Home Storage | I1: Furnishing Quality | J1: Design and layout comments | K1: Recommend living in a Grainger home | L1: One thing we could do to improve | M1: Month 3 Recommend Score comments | N1: Recommend Grainger home | O1: M3 Contact consent | P1: One thing to improve
A2: 335121209 | C2: Yes | E2: ornela.doku@gmail.com | F2: 1/1/2023 3:03:50 AM | H2: Just enough | I2: It‚Äôs pretty good
A3: 336557361 | C3: Yes | E3: guy.lewis4@btinternet.com | F3: 1/1/2023 3:05:34 AM | G3: It's ideal for my needs. | H3: Just enough | I3: It‚Äôs ok | J3: Nothing really, the layouts fine.
A4: 434491725 | C4: No | E4: roberttaryn@gmail.com | F4: 1/1/2024 3:01:25 AM | G4: Well maintained, resident services team is very helpful | I4: It‚Äôs ok | J4: Apartment is very well located, resident services team are friendly and responsive, many amenities and services making it a very convenient place to live. | K4: 10 | L4: Nothing to note
A5: 266770073 | C5: Yes | E5: okezieemekaik@gmail.com | F5: 1/1/2024 3:03:10 AM | G5: Cost effective | I5: The quality is high | J5: This is because I always get quick responses to my requests | K5: 1 | L5: Avoid mould in the windows
A6: 438157905 | C6: No | E6: vsena2019@outlook.com | F6: 1/1/2024 3:03:10 AM | G6: Very good materials, the position and the fact it has the key furniture (such as a sofa, table and appliances). | I6: It‚Äôs pretty good | J6: The flat is pristine and of high quality. No problem at all with plumbing and appliances. The reception team is very nice and proactive and it is a pleasure to deal with them. | K6: 10 | L6: Upload the appliances' manuals to the app.
A7: 444268080 | C7: Yes | E7: saoud.ali2@gmail.com | F7: 1/1/2024 3:03:11 AM | G7: Staff members | I7: It‚Äôs pretty good | J7: 9 out of 10 _x000D_ Great staff members | K7: 9 | L7: Maybe _x000D_ Swimming Pool in the building
A8: 447957566 | C8: Yes | E8: gurshinsidhu2609@gmail.com | F8: 1/10/2024 3:01:12 AM | G8: Focus on resident well-being, welcoming and inclusive environment, sense of community, location and convenience | I8: It‚Äôs ok | J8: Grainger is known for their commitment to resident well-being, offering a variety of programs and services to support physical, mental, and emotional health. | K8: 10 | L8: Everything is wonderful.
A9: 412558798 | C9: No | E9: jennyellen@live.co.uk | F9: 1/10/2024 3:01:12 AM | G9: Design of the apartment, spaciousness | I9: It‚Äôs pretty good | J9: Very happy here | K9: 10 | L9: N/A
A10: 449016273 | C10: No | E10: krishnajap@gmail.com | F10: 1/10/2024 3:01:12 AM | G10: Interiors are pleasing to the eye, all appliances are top notch and the bed has been changed before i arrived | I10: It‚Äôs pretty good | J10: Im pretty happy about the team, they very helpful and take initiatives to make all of us comfortable | K10: 7 | L10: Bedroom bed is not proportionate to the small room
A11: 447735429 | C11: Yes | E11: marcsantm98@gmail.com | F11: 1/10/2024 3:01:12 AM | G11: it‚Äôs located in a nice area, very quiet, home itself is spacious and cozy | I11: The quality is high | J11: The entire process from viewing the place, contacting them, moving in was so smooth and stress free | K11: 10 | L11: getting notifications when packages get delivered
A12: 440945794 | C12: Yes | E12: katiehargadon@outlook.com | F12: 1/10/2024 3:02:15 AM | G12: Good quality furniture and finishes, lovely staff team | I12: It‚Äôs pretty good | J12: Good living environment and decent price for location | K12: 10 | L12: Car parking! Having to pay for ncp whilst on wait
A13: 323014711 | C13: Yes | E13: harrynettleton1@gmail.com | F13: 1/11/2023 3:05:32 AM | G13: The bathroom | H13: Just enough | I13: It‚Äôs not great | J13: Kitchen units shouldn‚Äôt be white, higher quality carpets for sure. Sofa is a little small.
A14: 341526721 | C14: Yes | E14: damla.koyuncu.dk@gmail.com | F14: 1/11/2023 3:05:32 AM | H14: The perfect amount | I14: It‚Äôs ok | J14: Bedside lamp, providing basic kitchen appliances (kettle/microwave).
A15: 336558003 | C15: Yes | E15: jessica-lawton@hotmail.co.uk | F15: 1/11/2023 3:05:32 AM | G15: Spacious bedroom_x000D_ Balcony _x000D_ Modern and neutral decor _x000D_ Extras in the building e.g. sky lounge, gym, parcel room etc. | H15: Would like more | I15: It‚Äôs pretty good | J15: Just the storage could be better
A16: 264201920 | C16: Yes | E16: alandcoleman@aol.com | F16: 1/11/2023 3:05:32 AM | G16: Easy access to town | H16: Would like more | J16: The meters for electricity readings should be moved so that we can actually take a reading without having to demolish a wall to read it
A17: 334293048 | C17: Yes | E17: alexpurvis95@gmail.com | F17: 1/11/2024 3:02:11 AM | G17: Proximity to centre | H17: Would like more | I17: It‚Äôs pretty good | J17: Good flat, simple layout, appliances work, staff are friendly and helpful, location is good | K17: 10 | L17: Clear out the water from the UG carpark
A18: 442959822 | C18: Yes | E18: neilkkw@hotmail.com | F18: 1/11/2024 3:02:11 AM | G18: location is very well. near the station! | I18: It‚Äôs pretty good | J18: all respond are very quick | K18: 10 | L18: indicator and garbage collection
A19: 442960033 | C19: Yes | E19: kikipinga@msn.com | F19: 1/11/2024 3:02:11 AM | G19: I like the monthly or special session events such as breakfast morning, christmas party, halloween competition. These events give me a great opportunity to knowing our neighbours and built up my sense of belonging. | I19: It‚Äôs pretty good | J19: The Grainger Team consistently provides prompt responses to all my inquiries. Even if they can't immediately resolve my issues, they promptly inform me of when they can be fixed. | K19: 8 | L19: a free and regular window cleaning service
A20: 434278401 | C20: No | E20: kachun1220@gmail.com | F20: 1/11/2024 3:02:11 AM | G20: Near more shop and market | I20: It‚Äôs pretty good | K20: 8
A21: 442010571 | C21: Yes | E21: letsgochingu@gmail.com | F21: 1/11/2024 3:02:11 AM | G21: good service | I21: It‚Äôs pretty good | J21: the building is quite nice | K21: 8 | L21: helping residents to set up utility bills
A22: 439636585 | C22: No | E22: hardikagrawal18@gmail.com | F22: 1/11/2024 3:02:11 AM | G22: Management is quite professional and helpful. | I22: It‚Äôs pretty good | J22: Due to a couple of negatives like thin walls and bin room being outside and a little messy | K22: 8 | L22: Walls are too thin, so less noise other rooms help
A23: 343712490 | C23: Yes | E23: angsumanbhanjdeo@gmail.com | F23: 1/12/2023 3:03:35 AM | G23: I have been impressed with the decor, planning and maintenance. The attention to detail in the design and layout of the space is evident and adds to the overall aesthetic appeal. The spaces are well-maintained and clean, with everything in order. | H23: Would like more | I23: The quality is high | J23: Storage Space - The wardrobe space can be increased, current space doesn't suffice. There is space opposite to the current wardrobe which can be easily utilised to add some additional space for storage of clothes
A24: 264932505 | C24: Yes | E24: soumya.jena.nayak@gmail.com | F24: 1/12/2023 3:03:35 AM | G24: The Flat was spacious and apartment safety rules were good. All the staffs very friendly and supportive and ready to answer all the queries. | H24: The perfect amount | I24: It‚Äôs pretty good | J24: Yes they can work on the lighting part as it was not enough for study and work purpose.
A25: 340652457 | C25: No | E25: aimable.mardel@gmail.com | F25: 1/12/2023 3:05:41 AM | G25: High ceilings, lots of natural light and a modern finish. | H25: Would like more | I25: It‚Äôs pretty good | J25: Better usage of space. For example, the beds could have storage in them and the sofas could be sofa beds.
A26: 436448244 | C26: Yes | E26: churu.takudzwa.peter@icloud.com | F26: 1/12/2024 3:02:02 AM | G26: The free gym membership and Conceirge team are always helpful | I26: It‚Äôs ok | J26: I scored an 8 as there is not too much negative things to say. I haven‚Äôt had many issues and the few ones I had were managed quickly | K26: 8 | L26: I think L shaped sofas would be a better option
A27: 447036611 | C27: Yes | E27: abhilasha_kakkar@hotmail.co.uk | F27: 1/12/2024 3:02:02 AM | G27: The spacious-ness of the flat; the events and freebies offered; the reception team are always very friendly and courteous to requests/issues | I27: It‚Äôs ok | J27: Although most of the experience has been good, the flat had obvious signs of wear and tear and felt 'lived in' when I moved in, despite it being professionally cleaned by Grainger beforehand. Also, the parking spaces are far too limited! | K27: 8 | L27: quicker/better maintenance & more parking.
A28: 340877429 | C28: No | E28: rawan.t@windowslive.com | F28: 1/13/2023 3:05:31 AM | G28: The lounge area is amazing_x000D_ I wish though it can be booked not the kitchen alone | H28: Would like more | I28: It‚Äôs pretty good
A29: 263523402 | C29: Yes | E29: v.marike@gmail.com | F29: 1/13/2023 3:05:31 AM | G29: Rental agreement and renewal_x000D_ Central App to log repairs_x000D_ Open plan space in living areas | H29: Just enough | J29: Have separate washing/dryer machine. The combined one reduces capacity and results in a very useless dryer.
A30: 443850810 | C30: Yes | E30: yeungderek@hotmail.com | F30: 1/14/2024 3:01:00 AM | G30: The onsite staff are attentive and a joy to see/speak to every day. | I30: It‚Äôs ok | J30: Purely driven by the helpfulness of staff along with the modern look and feel of the apartments. | K30: 10 | L30: Self service parcel collection
A31: 447734744 | C31: No | E31: ummul_ashraf96@ymail.com | F31: 1/14/2024 3:03:12 AM | G31: The security, communal area and friendly staff | I31: The quality is high | J31: Very comfortable, approachable staff and excellent location. | K31: 10 | L31: Efficient delivery of parcels
A32: 447036361 | C32: Yes | E32: lyslys52013@gmail.com | F32: 1/14/2024 3:03:12 AM | G32: I really like the river view, and the facilities are excellent. I also enjoy the gym. | I32: It‚Äôs ok | K32: 8 | L32: Please open both elevators for use.
A33: 210057862 | C33: Yes | E33: vidubov@yahoo.com | F33: 1/15/2023 3:04:44 AM | G33: Fed up with construction works for the last 1,5 years. Its not acceptable, very noisy and we don‚Äôt know when it will stop. Communal area should be finished by Christmas but still not done. | H33: Would like more | I33: It‚Äôs ok | J33: Would need a new boiler as I've got old one and it needs to be re-set almost daily.
A34: 447271698 | C34: Yes | E34: shinice_98@hotmail.com | F34: 1/16/2024 3:02:02 AM | G34: Great staff | I34: It‚Äôs pretty good | J34: Great property management | K34: 10 | L34: More community events
A35: 440511048 | C35: No | E35: danielconn15@gmail.com | F35: 1/16/2024 3:02:03 AM | G35: Lovely and spacious + balcony | I35: The quality is high | J35: nothing really - still early days. | K35: 8 | L35: better contractors for emergency situations
A36: 452198630 | C36: Yes | E36: mehrnoosh.tavassoli@gmail.com | F36: 1/16/2024 3:02:03 AM | G36: Its perfect management and my unique window view | I36: It‚Äôs pretty good | J36: Due to I believe your building is the best one in this level all around Derby. | K36: 10 | L36: Fixing anything in the house that needs.
A37: 340657894 | C37: Yes | E37: bhekithembafortune@yahoo.com | F37: 1/17/2023 3:05:34 AM | G37: The Team on-site! | H37: Would like more | I37: It‚Äôs ok | J37: Nothing
A38: 450107440 | C38: Yes | E38: ningzhi.wang97@gmail.com | F38: 1/17/2024 3:01:39 AM | G38: Staff are welcoming and helpful._x000D_ Common space is well decorated and maintained. | I38: It‚Äôs not great | J38: The overall experience is good and common space is great for parties. | K38: 9 | L38: Try to get the elevator fixed faster.
A39: 345693207 | C39: Yes | E39: gamalkuw20@icloud.com | F39: 1/18/2023 3:05:37 AM | H39: The perfect amount | I39: It‚Äôs ok
A40: 210064790 | C40: Yes | E40: drewcon45@gmail.com | F40: 1/18/2023 3:05:37 AM | G40: I‚Äôve been here a while and it‚Äôs cool. The location is excellent as are the buildings in general and the facilities. The RST are first class and it‚Äôs a real hassle free living experience. | H40: Would like more | I40: It‚Äôs ok | J40: Maybe more durable flooring but that‚Äôs just a nice to have. The building is as advertised and the fixtures and fitting quality on the whole are pretty solid.
A41: 440730809 | C41: Yes | E41: sophieetolson@gmail.com | F41: 1/18/2024 3:02:04 AM | G41: I like how modern the apartment is and the neutral colours fitting to everyone‚Äôs style. I also really enjoy the building facilities, such as the sky lounge. I work from home so these facilities are really great from me. | I41: The quality is high | J41: I really enjoy living here and plan to do so for as long as possible. | K41: 10 | L41: Balcony furniture within furnished apartments.
A42: 445325064 | C42: Yes | E42: hobson.tom@icloud.com | F42: 1/18/2024 3:02:04 AM | G42: It‚Äôs a great space and I love the small things like the super fast internet and the hard wired Ethernet connections to each room | I42: The quality is high | J42: Overall, it‚Äôs a fantastic place to live and the staff are super friendly and helpful.9/10 because there‚Äôs always something to improve on haha | K42: 9 | L42: Fix my lights in my room
A43: 447037146 | C43: No | E43: tianxingyu668@gmail.com | F43: 1/18/2024 3:02:04 AM | G43: The location | I43: It‚Äôs ok | J43: Good location and good service | K43: 10 | L43: repair the lift or something else quickly
A44: 345252303 | C44: Yes | E44: jayramji7@gmail.com | F44: 1/18/2024 3:02:04 AM | G44: The warm welcome we get every time we enter and exit the building or use any facilities. _x000D_ This includes the team at the front desk, security overnight and the cleaning staff. | I44: It‚Äôs pretty good | J44: The only thing stopping a 10 is that not all of my friends, colleagues etc are able to afford the extra amenities that come with living in a well furnished building with a gym and concierge etc. I would recommend if they can afford the extra cost. | K44: 9 | L44: Gym temperature control.
A45: 449267876 | C45: Yes | E45: kasidit@outlook.com | F45: 1/18/2024 3:02:04 AM | G45: It's clean, well-insulated, feature-complete, and is just nice to live in. | I45: The quality is high | K45: 8 | L45: Electrical appliances servicing time
A46: 437723386 | C46: Yes | E46: balqees-shaaban1@hotmail.com | F46: 1/18/2024 3:03:25 AM | G46: The staff, specially Zara ana Sonia | I46: It‚Äôs ok | K46: 2 | L46: Need carpet in the flat and desk
A47: 434278137 | C47: Yes | E47: laimyeung@gmail.com | F47: 1/18/2024 3:03:25 AM | G47: Spacious and clean. Furnished apartment can move in directly when I landed since I come from other country. That's great. | I47: It‚Äôs pretty good | J47: overall is good and just had a bad beginning when I moved in | K47: 8 | L47: inform me for the Top-up meter in advance
A48: 210053598 | C48: Yes | E48: prime.eddie@hotmail.com | F48: 1/19/2023 3:03:37 AM | G48: Location | H48: Would like more | I48: It‚Äôs ok | J48: Redesigning of the kitchen could have a bigger built in fridge & freezer, sofa cum beds or Lounge sofas (L-shaped) with better cushioning, built in wardrobe with cabinets in the bedrooms.
A49: 335122395 | C49: No | E49: adsequeira@hotmail.com | F49: 1/19/2023 3:03:37 AM | G49: Location. | H49: Would like more | I49: It‚Äôs ok | J49: Kitchen redesigned with bigger standing fridge/freezer and storage cupboards. _x000D_ Bedrooms to have inbuilt cupboards.
A50: 333201311 | C50: No | E50: danielsequeiraa@gmail.com | F50: 1/19/2023 3:05:33 AM | G50: Good overall size for a 1 bed flat, large windows, full fridge/frizer. Calm neighbourhood. | H50: Would like more | I50: It‚Äôs ok | J50: Smarter storage and furniture for small spaces. The space is enough but it was not well planned. Some storage under the bed or a more efficient wardrobe or a mirror in the bathroom with storage. A smaller table that could be extended when needed.
A51: 338676007 | C51: Yes | E51: 1866david@gmail.com | F51: 1/19/2023 3:05:33 AM | G51: Close to family member | H51: Just enough | J51: Put adequate insulation in the loft and wall. Clean gutters and block up hole in wall where old boiler flue us to be.
A52: 445544031 | C52: Yes | E52: cyo@sky.com | F52: 1/19/2024 3:02:10 AM | G52: Modern and convenient location | I52: It‚Äôs ok | J52: A few changes are needed | K52: 8 | L52: Clean the car park the litter is disgusting .
A53: 332782905 | C53: Yes | E53: beratmerickarabulut2@gmail.com | F53: 1/2/2023 3:03:38 AM | G53: Staff | H53: The perfect amount | I53: It‚Äôs ok
A54: 263472111 | C54: No | E54: pmcfadden1@me.com | F54: 1/2/2023 3:04:31 AM | G54: Location and facilities are good | H54: The perfect amount | I54: It‚Äôs pretty good | J54: No I‚Äôm quite happy with the layout and design
A55: 328801335 | C55: Yes | E55: boscocheng0117@gmail.com | F55: 1/2/2023 3:04:31 AM | G55: Great location | H55: Just enough | I55: It‚Äôs pretty good | J55: The bed is too soft for me, but it came furnished, so I couldn‚Äôt buy another one
A56: 337060228 | C56: No | E56: tk.zanaty_1992@yahoo.com | F56: 1/2/2023 3:04:31 AM | G56: Quiet and safe | H56: The perfect amount | I56: The quality is high | J56: Provide a microwave and increase blind at the living room
A57: 339764911 | C57: Yes | E57: aujadhav10@gmail.com | F57: 1/2/2023 3:04:31 AM | G57: It‚Äôs a lovely home, just very comfortable and spacious. The best part is sufficient space for storage in all the rooms. | H57: The perfect amount | I57: It‚Äôs pretty good | J57: Everything works well. No complaints about the home but it‚Äôll be appreciated if the building services are improved. Example, the entrance door is out of service for quite a long time and it‚Äôs inconvenient for most of us.
A58: 338461961 | C58: Yes | E58: kunal.atkare.t@gmail.com | F58: 1/2/2023 3:04:31 AM | G58: The ambience | H58: The perfect amount | I58: It‚Äôs pretty good | J58: Everything is fine except the main door, its been month now the main door has not been repaired. Also the door which is al the way through parking is not working automatically, we really have to push hard to open and close.
A59: 264016543 | C59: Yes | E59: sollis88@gmail.com | F59: 1/2/2023 3:04:31 AM | G59: Nice and quiet. | H59: The perfect amount | I59: It‚Äôs ok | J59: Improve the lifts that keep breaking - living on the 10th and always have 1/2 lifts broken isn‚Äôt ideal. But a small thing. Otherwise no real complaints.
A60: 434927507 | C60: No | E60: sonjadanby@me.com | F60: 1/2/2024 3:02:13 AM | G60: spacious flat, lovely reception staff, fab balcony | I60: It‚Äôs pretty good | J60: The staff at reception are extremely helpful and rhe entire accommodation feels clean and welcoming | K60: 9 | L60: improve initial conditions assessment
A61: 332572705 | C61: Yes | E61: jamiefloss2010@gmail.com | F61: 1/2/2024 3:02:13 AM | G61: The kitchen is great. | I61: It‚Äôs pretty good | J61: It‚Äôs great to move in and live in. But its quite higher rent compared to the same area around. | K61: 8 | L61: Should provide more chair.
A62: 447037749 | C62: No | E62: galang.arhath@gmail.com | F62: 1/2/2024 3:03:14 AM | G62: Location near tube | I62: The quality is high | J62: A really comfortable home with a very good location and its worth the price | K62: 1 | L62: Lifts and gates are never broken
A63: 437518243 | C63: Yes | E63: casual.ho0312@gmail.com | F63: 1/2/2024 3:03:14 AM | G63: common room | I63: It‚Äôs ok | J63: Pretty good. | K63: 8 | L63: More party.
A64: 445761737 | C64: Yes | E64: hallema.l@hotmail.co.uk | F64: 1/2/2024 3:03:14 AM | G64: It was brand new and fully furnished, in a good location. | I64: It‚Äôs not great | J64: Friendly staff, beautiful location, great facilities. | K64: 9 | L64: Decrease the rent :)
A65: 261166578 | C65: Yes | E65: yuri.cardoso96@gmail.com | F65: 1/21/2023 3:04:45 AM | G65: How spacious it is in relation to similar apartments in the same price range | H65: Would like more | I65: It‚Äôs pretty good | J65: Change the light fixtures in the living-room to something that can either shine brighter or fit more bulbs, add an outlet in the toilet for an optional bidet attachment, change the location of the thermostat
A66: 450320689 | C66: Yes | E66: richard.dolben@ymail.com | F66: 1/21/2024 3:01:29 AM | G66: Central | I66: It‚Äôs ok | J66: Good value | K66: 8 | L66: Better quality fixtures
A67: 439220347 | C67: Yes | E67: kiera.liesel@gmail.com | F67: 1/21/2024 3:01:29 AM | G67: Location, the feeling of safety and the cleanliness of the building. Staff are all super friendly as well. | I67: It‚Äôs pretty good | J67: I‚Äôve had no issues so far and think it‚Äôs a great way to live! | K67: 5 | L67: Host more social events!
A68: 441148688 | C68: Yes | E68: mikehung888@gmail.com | F68: 1/21/2024 3:01:49 AM | G68: I like the security here; it's not easy for people to break in. The parcel room is also a safe place for packages. Moreover, when help is needed, people here respond quickly to provide assistance. | I68: It‚Äôs pretty good | J68: There are no major problems in the Grainger home; everything is basically fine. However, there are some minor things that could be improved. | K68: 9 | L68: The gym room could have a greater variety.
A69: 451773407 | C69: No | E69: jayden.pearson.oga@outlook.com | F69: 1/21/2024 3:01:49 AM | G69: It‚Äôs location | I69: It‚Äôs pretty good | J69: As mentioned struggled to get in contact with anyone when we first moved in to mention issues | K69: 5 | L69: Be more responsive with issues
A70: 336123163 | C70: No | E70: cwhui01@gmail.com | F70: 1/22/2023 3:04:46 AM | G70: The services provided bt the management staff. | H70: Would like more | I70: It‚Äôs ok | J70: A separate drying machine instead of integrating with the washing machine is preferred.
A71: 328593493 | C71: No | E71: gioulisapo@gmail.com | F71: 1/22/2023 3:05:35 AM | H71: Just enough | I71: It‚Äôs ok | J71: Microwave, not as harsh lighting,
A72: 320371035 | C72: Yes | E72: chloemarsh6@yahoo.co.uk | F72: 1/22/2023 3:05:35 AM | G72: All the staff are so lovely and helpful! It is clean, modern and feels very safe. The facilities are great. | H72: Just enough | I72: The quality is high | J72: Under bed storage would be really useful!
A73: 442003287 | C73: No | E73: eml.turner16@btinternet.com | F73: 1/22/2024 3:01:34 AM | G73: The space and design of the flat, and the building amenities | I73: It‚Äôs pretty good | K73: 7 | L73: Ensure the flat is up to standard before moving in
A74: 435801352 | C74: Yes | E74: susankate.decena@gmail.com | F74: 1/22/2024 3:01:52 AM | G74: Best for location. Amenities like bus stop is just a minute walk outside the building and the gym downstairs is such a great thing to have! | I74: The quality is high | J74: Everything‚Äôs perfect, apart from the fact that it‚Äôs on the pricey side. But it‚Äôs definitely a place I‚Äôd recommend if you can afford it! | K74: 9 | L74: More get togethers
A75: 436026430 | C75: No | E75: raphelimperial.junio@gmail.com | F75: 1/22/2024 3:01:52 AM | G75: Facilities are great, easy commute everywhere with bus stop just in front of the building. | I75: The quality is high | J75: Great place, if you can afford the rent. | K75: 9 | L75: More events in the sky lounge to meet new people
A76: 443206882 | C76: Yes | E76: t.ngo1296@live.com.au | F76: 1/22/2024 3:01:52 AM | G76: Very friendly and helpful staff, events for residents in the complex, being kept in the loop with news about the building, how easy it is to contact staff with enquiries and how prompts the replies are, the picturesque and practical communal areas. | I76: It‚Äôs pretty good | J76: Felt very welcome and looked after since moving in and the reasons listed in answer for the first question. | K76: 9
A77: 210065611 | C77: No | E77: saywhat29@gmail.com | F77: 1/23/2023 3:05:37 AM | H77: Would like more | I77: It‚Äôs ok | J77: The craftsman ship of work looks like it was done by an amuter and corner were cut
A78: 461653093 | C78: No | E78: janiceluk04@gmail.com | F78: 1/23/2024 3:01:20 AM | G78: Good facilities, nice reception staff | I78: It‚Äôs ok | J78: No family friendly parking spaces available, expensive for little flexibility | K78: 6 | L78: Flexible tenancies and parking spaces
A79: 450741834 | C79: No | E79: oliveroletizia17@gmail.com | F79: 1/23/2024 3:01:20 AM | G79: Modern and quiet | I79: It‚Äôs pretty good | J79: It‚Äôs great | K79: 9 | L79: New carpets
A80: 451776180 | C80: Yes | E80: m.manouchehri2007@gmail.com | F80: 1/23/2024 3:03:13 AM | G80: Good and timely notification and management of Grainger_x000D_ Good building design and materials,_x000D_ Thermal and sound insulation of the walls and floors of the units_x000D_ Security design of entrances_x000D_ Furnishing of units | I80: It‚Äôs pretty good | J80: Because of Grainger's good management in this building_x000D_ New construction and quality of the building_x000D_ The superiority of the building compared to other buildings in the city of Darby | K80: 10 | L80: Faster action in building damage and problems
A81: 449018346 | C81: Yes | E81: shameem.ascar88@gmail.com | F81: 1/23/2024 3:03:13 AM | G81: The management is really good at responding to my queries and have been so helpful. I feel safe to live in filaments. | I81: It‚Äôs pretty good | K81: 10 | L81: Work station at apartment
A82: 210057738 | C82: Yes | E82: emilykuiper@googlemail.com | F82: 1/24/2023 3:03:29 AM | G82: Decor | H82: The perfect amount | I82: The quality is high | J82: Heat in the summer is unlivable (reached 38¬∞C regularly with all windows, blinds closed and reflective film)
A83: 450317107 | C83: Yes | E83: ekalligeres@gmail.com | F83: 1/24/2024 3:01:48 AM | G83: 1. The fact that everything is brand new and exactly as described._x000D_ 2. The hospitality of the receptionists. | I83: It‚Äôs pretty good | J83: Because even though is a little bit expensive, it ticks all the boxes promised. | K83: 10 | L83: The lounge to be accessible 24/7.
A84: 452201930 | C84: No | E84: ccc1kun@gmail.com | F84: 1/24/2024 3:03:07 AM | G84: nice staff | I84: It‚Äôs ok | J84: Almost good | K84: 9 | L84: bad lift, always out of service
A85: 443428066 | C85: Yes | E85: gillianmuchedzi@hotmail.com | F85: 1/25/2024 3:01:54 AM | G85: Try he onsite gym. | I85: It‚Äôs ok | J85: Reception staff can be a bit passive aggressive, and they‚Äôre not helpful. For example, can see you looking for you keys in the rain and ignore you, don‚Äôt say hello ect and know I don‚Äôt receive parcel notifications and I always have to remind them. | K85: 7 | L85: mattresses is very hard.
A86: 444056939 | C86: Yes | E86: jonnyc30@aol.com | F86: 1/25/2024 3:01:54 AM | G86: Location, gym, roof terrace, cosey, secure. | I86: The quality is high | J86: For the reasons given in question 3 | K86: 8 | L86: Blinds in all living are see through
A87: 446399414 | C87: Yes | E87: yxm732@gmail.com | F87: 1/25/2024 3:03:11 AM | G87: The communal area, gym and reception | I87: It‚Äôs pretty good | J87: It‚Äôs a lovely building with lovely staff. It‚Äôs just taking some time when we need things fixed. | K87: 7 | L87: Providing more shelf space for the double beds.
A88: 274771870 | C88: No | E88: oliver.pt.myers@gmail.com | F88: 1/26/2023 3:01:47 AM | G88: Decor | H88: Would like more | I88: It‚Äôs pretty good | J88: More storage
A89: 332777023 | C89: Yes | E89: pompeu314@hotmail.com | F89: 1/26/2023 3:01:47 AM | G89: Location | H89: Just enough | I89: It‚Äôs ok | J89: Appliances I had to buy , microwave , toaster , vacuum, hair dryer eletric kettle , juicer , etc
A90: 345255800 | C90: Yes | E90: rujutanap@gmail.com | F90: 1/26/2023 3:01:48 AM | H90: Would like more | I90: It‚Äôs pretty good
A91: 265098538 | C91: Yes | E91: m12coo@sky.com | F91: 1/26/2023 3:03:44 AM | G91: I really like the hole in our ceiling, the three leaks coming into our flat. I‚Äôm also a big fan of the amount of condensation buildup and as a result the mould which comes with it. | H91: Would like more | I91: It‚Äôs pretty good | J91: Larger fridge_x000D_ More ventilation in the bathroom
A92: 334287570 | C92: No | E92: daniellforde@gmail.com | F92: 1/26/2023 3:03:44 AM | G92: Staff and views | H92: The perfect amount | I92: It‚Äôs pretty good | J92: Sofa that you can lie on - i.e. reclining or L-shape
A93: 345252593 | C93: Yes | E93: mathur.nimit@gmail.com | F93: 1/26/2023 3:03:45 AM | G93: The size of the flat and size of windows. | H93: The perfect amount | I93: The quality is high | J93: No microwave. wooden flooring (dark) not asthetically suitable. heating radiators too small. Kitchen basin too small.
A94: 440521848 | C94: No | E94: pelintr5@gmail.com | F94: 1/26/2024 3:01:07 AM | G94: Quick solution_x000D_ Good application_x000D_ Easily accessible | I94: It‚Äôs ok | J94: Your service is good, effective and has friendly staff_x000D_ Thanks for your help | K94: 9 | L94: I think everything is ok now
A95: 447506909 | C95: Yes | E95: rebekahnewey@gmail.com | F95: 1/26/2024 3:01:07 AM | G95: The staff are lovely, the location is great, really good value for money, convenient gym and work areas, well maintained, good service. | I95: The quality is high | J95: I think the service we have received is very good, while it might be out of some people's price range I think it's definitely worth it. | K95: 10 | L95: Nothing
A96: 440728779 | C96: Yes | E96: hassnaahamdielnaggar@gmail.com | F96: 1/26/2024 3:01:07 AM | G96: Everything!_x000D_ I would say 2 things are the best._x000D_ 1. 24hours receptionists_x000D_ 2. Notifications about new deliveries | I96: The quality is high | J96: Everything is really great._x000D_ Reception_x000D_ Gym_x000D_ Workingspace_x000D_ Social area_x000D_ Events you do | K96: 10 | L96: The too hot air while entering the door of halogen
A97: 440275807 | C97: No | E97: mtayyipgurbuz@gmail.com | F97: 1/26/2024 3:01:07 AM | G97: The maintenance or kind of a small jobs all done by Grainger is a great thing. | I97: The quality is high | J97: Fresh building, grainger provides necessary items (table, chair, oven tray etc.). The floor to ceiling windows are great_x000D_ | K97: 9 | L97: It would be good to remove scaffolding soon.
A98: 457789431 | C98: Yes | E98: debbiepedro80@gmail.com | F98: 1/26/2024 3:02:08 AM | G98: I love my city view from my balcony, the movie room, the staff hospitality, the rooftop lounge, the gym I mean everything is great. | I98: The quality is high | J98: The calm, serene, clean, safe environment and security. | K98: 10 | L98: Nothing for now.
A99: 341085222 | C99: No | E99: emi-2010@hotmail.co.uk | F99: 1/27/2023 3:03:44 AM | G99: 1. The space _x000D_ 2. The modern design _x000D_ 3. The amenities _x000D_ 4. Friendly and helpful concierge and receptionists | H99: Would like more | I99: It‚Äôs not great | J99: 1. The vent is very noisy_x000D_ 2. The heater is located behind the sofa which means I have to pull the sofa out each time I put the heater on _x000D_ 3. A storage room would be great for thing like my hoover, mop etc. there is currently no space for that
A100: 264909876 | C100: Yes | E100: soud.zayid@hotmail.com | F100: 1/27/2023 3:03:44 AM | G100: Every thing, from the reception staff to the living experience here . The convenience of having use the amenities. But I hope you could change the biliardo or the gaming board in the work area. We love to study from the lounge but it is very noisy . | H100: Would like more | I100: It‚Äôs pretty good | J100: The lighting is too strong, I hope to be changed to warm yallow
...

Sheet Touchpoint - Full Response - 3 
A1: Contact ID 18 Digit | B1: 18 digit OPP ID | C1: First Name | D1: Last Name | E1: Title | F1: Tenancy End Date | G1: Tenancy Start Date | H1: Role | I1: Email | J1: Phone | K1: Unit Address _Subject_ | L1: Active | M1: Tenancy Type | N1: Primary Offer Estate | O1: Move-In Date | P1: Agreed Unit | Q1: Property Type | R1: Unit Status | S1: Fund | T1: Estate | U1: Portfolio | V1: Unit Manager: Full Name | W1: Property Manager: Full Name | X1: Asset Manager: Full Name | Y1: Property Manager Assistant: Full Name | Z1: Future Vacant Date | AA1: Building Name | AB1: Plot No | AC1: Opportunity Name | AD1: id | AE1: Feedback | AF1: Happy to be contacted | AG1: Preferred contact details | AH1: Like best about home | AI1: Home Storage | AJ1: Furnishing Quality | AK1: Design and layout comments | AL1: Survey sent time | AM1: Month 3 Recommend Score comments | AN1: Recommend living in a Grainger home | AO1: One thing we could do to improve | AP1: M3 Contact consent | AR1: Count id
A2: 003Nz00000JSncNIAT | B2: 006Nz00000FAHDRIA5 | C2: Wing Shiu | D2: Lo | F2: 45901 | G2: 45537 | H2: Tenant | I2: chlws01@alumni.ust.hk | J2: 07901619214 | K2: FLAT 127, Gatehouse Apartments,86 East Street, Southampton, SO14 3HP | L2: TRUE | M2: New | O2: 45537 | P2: <a href="a1G4J0000025xJE" target="_blank">127 Gatehouse Apts, 86 East St, Southampton</a> | Q2: Apartment | R2: Tenanted | T2: Gatehouse Apartments | U2: BTR-London & SE | V2: Alice Shaw | X2: Harriet Shaw | Y2: Hayley Fry | Z2: 45915 | AA2: Gatehouse Apts, 86 East St, Southampton | AB2: 25 Gatehouse Apts, 86 East St, Southampton | AC2: GREP-CoA Hoi Yan Yu & Wing Shiu Lo - 127 Gatehouse Apts, 86 East St, Southampton | AD2: 540162006 | AH2: Great | AJ2: It‚Äôs pretty good | AL2: 45627.126 | AM2: Nice staff, prompt response on service enquiry | AN2: 10 | AO2: Lift service maintenance | AR2: =COUNTIF(AD:AD,AD2) -> 1
A3: 003Nz00000JLDycIAH | B3: 006Nz00000FAHDRIA5 | C3: Hoi Yan | D3: Yu | F3: 45901 | G3: 45537 | H3: Lead Tenant | I3: junelowbb825@gmail.com | J3: 07901619214 | K3: FLAT 127, Gatehouse Apartments,86 East Street, Southampton, SO14 3HP | L3: TRUE | M3: New | O3: 45537 | P3: <a href="a1G4J0000025xJE" target="_blank">127 Gatehouse Apts, 86 East St, Southampton</a> | Q3: Apartment | R3: Tenanted | T3: Gatehouse Apartments | U3: BTR-London & SE | V3: Alice Shaw | X3: Harriet Shaw | Y3: Hayley Fry | Z3: 45915 | AA3: Gatehouse Apts, 86 East St, Southampton | AB3: 25 Gatehouse Apts, 86 East St, Southampton | AC3: GREP-CoA Hoi Yan Yu & Wing Shiu Lo - 127 Gatehouse Apts, 86 East St, Southampton | AD3: 539721296 | AH3: The view is excellent. I enjoy the sea view._x000D_ The service team is also great with helpful and friendly staff. | AJ3: It‚Äôs pretty good | AL3: 45627.126 | AM3: great service team, no extra pet charges | AN3: 10 | AO3: lift maintenance service | AR3: =COUNTIF(AD:AD,AD3) -> 1
A4: 003Nz00000JKmAQIA1 | B4: 006Nz00000F6dJ1IAJ | C4: Renato Jose | D4: Valerio | F4: 45905 | G4: 45541 | H4: Tenant | I4: renato3.1projectos@gmail.com | J4: 07902578105 | K4: Apartment 89 Kings Dock Mill,32 Tabley Street, Liverpool, L1 8DX | L4: TRUE | M4: New | O4: 45541 | P4: <a href="a1G4J0000025yHK" target="_blank">Apt 89, Kings Dock Mill, Liverpool, L1</a> | Q4: Apartment | R4: Tenanted | T4: Kings Dock Mill | U4: PRS-Regions | V4: Luke Pollard | X4: Vicki Turnbull | Y4: Matthew Grayton | Z4: 45534 | AA4: Kings Dock Mill, Liverpool, L1 | AB4: Apt 89, Kings Dock Mill, Liverpool, L1 | AC4: GREP-CoA Debora Marques Ferreira Cunha, Renato Jose Valerio - Apt 89, Kings Dock Mill, Liverpool, L1 | AD4: 539720258 | AH4: Location | AJ4: It‚Äôs ok | AL4: 45631.126 | AM4: Na | AN4: 9 | AO4: Na | AR4: =COUNTIF(AD:AD,AD4) -> 1
A5: 003Nz00000IF65zIAD | B5: 006Nz00000EOc0yIAD | C5: Alghalia | D5: Marafie | F5: 45901 | G5: 45537 | H5: Lead Tenant | I5: ghaliamarafie@gmail.com | J5: 0096566604978 | K5: Apartment 108, Millwrights Place,Temple Back, Bristol, BS1 6ZS | L5: TRUE | M5: New | O5: 45537 | P5: <a href="a1GNz0000019Hx7" target="_blank">108 Millwrights Place, Temple Back, Bristol</a> | Q5: Apartment | R5: Tenanted | T5: Millwrights Place | U5: BTR-Regions | X5: Sarah Norstrom | Z5: 45901 | AA5: Millwrights Place - Apartments | AB5: 108 Millwrights Place, Temple Back, Bristol | AC5: GREP-CoA Alghalia Marafie, Amal Hani & Salem Marafie - 108 Millwrights Place, Temple Back, Bristol | AD5: 535380882 | AH5: Nice and safe | AJ5: The quality is high | AL5: 45627.126 | AM5: It‚Äôs a really nice apartment, I like the staff too | AN5: 10 | AO5: Fixing the back elevator | AR5: =COUNTIF(AD:AD,AD5) -> 1
A6: 003Nz00000ICcNJIA1 | B6: 006Nz00000DejtVIAR | C6: Chido | D6: shahwe | F6: 45874 | G6: 45510 | H6: Tenant | I6: chido8shahwe@gmail.com | J6: 07736592694 | K6: Apartment 56, Gilders Yard,14 Great Hampton Street, Birmingham, B18 6ER | L6: TRUE | M6: New | O6: 45510 | P6: <a href="a1G8d0000004c7l" target="_blank">56, Gilders Yard, 14 Great Hampton St, Birm</a> | Q6: Apartment | R6: Tenanted | T6: Gilders Yard | U6: BTR-Regions | V6: Lewis Morris | X6: Vicki Turnbull | Y6: Neil Persad | Z6: 45874 | AA6: Gilders Yard - Apartments A-C | AB6: 56, Gilders Yard, 14 Great Hampton St, Birm | AC6: GREP-CoA Susannah Mbenga & Chido Shahwe - 56, Gilders Yard, 14 Great Hampton St, Birm | AD6: 535163160 | AH6: Clean space | AJ6: It‚Äôs not great | AL6: 45600.126 | AR6: =COUNTIF(AD:AD,AD6) -> 1
A7: 003Nz00000H9fQLIAZ | B7: 006Nz00000D4TK7IAN | C7: Ramaswamy Swaminatha | D7: Manikandan | F7: 45847 | G7: 45483 | H7: Tenant | I7: rsmanikandan@yahoo.com | J7: 07536524526 | K7: 7,Highfield Avenue, Newbury, RG14 5DS | L7: TRUE | M7: New | O7: 45483 | P7: <a href="a1G8d000002OmUX" target="_blank">7 Highfield Avenue, Newbury</a> | Q7: House | R7: Tenanted | T7: Weavers Yard | U7: BTR-London & SE | V7: Kimberley Pope | X7: Harriet Shaw | Y7: Daniel Hind | Z7: 45847 | AA7: 7 Highfield Avenue | AB7: 7 Highfield Avenue, Newbury | AC7: GREP-CoA Anithadevi Manikandan & Ramaswamy Swaminatha Manikandan - 7 Highfield Avenue, Newbury | AD7: 531158779 | AH7: Teams availability and friendly support | AJ7: It‚Äôs pretty good | AL7: 45573.084 | AR7: =COUNTIF(AD:AD,AD7) -> 1
A8: 003Nz00000GYWAjIAP | B8: 006Nz00000DBAarIAH | C8: Keri | D8: Castillo | F8: 45884 | G8: 45520 | H8: Lead Tenant | I8: kerilouisee@hotmail.co.uk | J8: 07763920820 | K8: 30,Houghton Avenue, Hampshire, PO7 3AA | L8: TRUE | M8: New | O8: 45520 | P8: <a href="a1G4J0000025xkt" target="_blank">30 Houghton Avenue, Waterlooville, PO7 3AA</a> | Q8: House | R8: Tenanted | T8: Berewood PRS | U8: BTR-London & SE | V8: Megan Fleming | X8: Harriet Shaw | Y8: Megan Fleming | Z8: 45511 | AA8: 30 Houghton Avenue, Waterlooville, PO7 3AA | AB8: 30 Houghton Avenue, Waterlooville, PO7 3AA | AC8: GREP-CoA Keri Castillo - 30 Houghton Avenue, Waterlooville, PO7 3AA | AD8: 528400757 | AH8: I like the natural, clean look of the property | AL8: 45610.126 | AM8: garden sizes are small | AN8: 7 | AO8: Check the sizes of the bathrooms - too big | AR8: =COUNTIF(AD:AD,AD8) -> 1
A9: 003Nz00000G5WPRIA3 | B9: 006Nz00000Cp0wmIAB | C9: Sandra Jayne | D9: Trippier | F9: 47292 | G9: 45467 | H9: Lead Tenant | I9: sandrajt47@hotmail.com | J9: 07543795144 | K9: 106,Plant Farm Crescent, Winchester, PO7 3DB | L9: TRUE | M9: New | O9: 45467 | P9: <a href="a1G4J000004PtLo" target="_blank">106 Plant Farm Cres, Waterlooville, PO7 3DB</a> | R9: Tenanted | T9: GT - Berewood | U9: Grainger Trust | V9: Shelby Overington | X9: Georgia Kirby-Watt | AA9: 98-108 Plant Farm Cres, Waterlooville, PO73DB | AB9: 106 Plant Farm Cres, Waterlooville, PO7 3DB | AC9: GREP-CoA Sandra Jayne Trippier - 106 Plant Farm Cres, Waterlooville, PO7 3DB | AD9: 526572176 | AH9: It is very clean inside and nicely decorated | AJ9: It‚Äôs pretty good | AL9: 45557.085 | AR9: =COUNTIF(AD:AD,AD9) -> 1
A10: 003Nz00000FZb49IAD | B10: 006Nz00000C5sDpIAJ | C10: Riya | D10: Rajan Shayla | F10: 45870 | G10: 45506 | H10: Tenant | I10: riyarajanshalya@gmail.com | J10: 07401084330 | K10: Apartment 506 Torrens Apartments,Waterman Walk, Salford, M50 3AS | L10: TRUE | M10: New | O10: 45506 | P10: <a href="a1G4J0000025z4I" target="_blank">506 Torrens Apt, Waterman Wlk, Salford M50</a> | Q10: Apartment | R10: Tenanted | T10: Clippers Quay | U10: BTR-Regions | V10: Helen Bowers | X10: Vicki Turnbull | Y10: Helen Bowers | Z10: 45870 | AA10: Clippers - Torrens Apartments | AB10: 506 Torrens Apt, Waterman Wlk, Salford M50 | AC10: GREP-CoA Fernanda Breame and Riya Rajan Shayla - 506 Torrens Apt, Waterman Wlk, Salford M50 | AD10: 524649833 | AH10: The view from my window | AJ10: It‚Äôs ok | AL10: 45596.126 | AR10: =COUNTIF(AD:AD,AD10) -> 1
A11: 003Nz00000FG1PJIA1 | B11: 006Nz00000CDIJZIA5 | C11: William | D11: Teoh | F11: 45863 | G11: 45499 | H11: Lead Tenant | I11: williamtzs@gmail.com | J11: 07594136149 | K11: 108 Assay Apartments,Station View, Guildford, GU1 4BQ | L11: TRUE | M11: New | O11: 45499 | P11: <a href="a1G8d000002Q2Z7" target="_blank">108 Assay Apartments, Station View, Guildford</a> | Q11: Apartment | R11: Tenanted | T11: The Mint | U11: BTR-London & SE | V11: Kimberley Pope | X11: Harriet Shaw | Z11: 45498 | AA11: The Mint - Assay Apartments. | AB11: 108 Assay Apartments, Station View, Guildford | AC11: GREP-CoA William Teoh and Heather Fitzpatrick - 108 Assay Apartments, Station View, Guildford | AD11: 523138734 | AH11: A mordern design, all facilities like washing machine, dishwasher, bathroom and cooker are provided in working and clean condition & overall very comfortable layout. The reception team are very friendly and helpful with things as well. | AJ11: It‚Äôs ok | AL11: 45589.084 | AR11: =COUNTIF(AD:AD,AD11) -> 1
A12: 003Nz00000ER1PnIAL | B12: 006Nz00000BaNB4IAN | C12: Angela | D12: Robinson | F12: 45856 | G12: 45492 | H12: Lead Tenant | I12: angelarobinson63@yahoo.com | J12: 07368228039 | K12: Apartment 24,15 St. Johns Gardens, Bury, BL9 0QW | L12: TRUE | M12: New | O12: 45492 | P12: <a href="a1G4J0000025xsh" target="_blank">24, 15 St. Johns Gardens, Bury, BL9</a> | Q12: Apartment | R12: Tenanted | T12: The Rock | U12: PRS-Regions | V12: David Hancock | X12: Vicki Turnbull | Y12: Lorraine Cree | Z12: 45813 | AA12: St. Johns Gardens, 5, Bury, Lancs, BL9 | AB12: 46, 5 St. Johns Gardens, Bury, BL9 | AC12: GREP-CoA Angela Robinson - 24, 15 St. Johns Gardens, Bury, BL9 | AD12: 519742842 | AH12: I love the size and layout. It‚Äôs perfect for me and my son. | AL12: 45582.084 | AR12: =COUNTIF(AD:AD,AD12) -> 1
A13: 003Nz00000EMW63IAH | B13: 006Nz00000BWsLZIA1 | C13: Sean | D13: Pillay | F13: 45818 | G13: 45454 | H13: Lead Tenant | I13: sean.pillay88@gmail.com | J13: 7426868860 | K13: 201 Brook Place,10 Summerfield Street, Sheffield, S11 8BR | L13: TRUE | M13: New | O13: 45454 | P13: <a href="a1G4J0000025zIZ" target="_blank">201, Brook Place Apts, Sheffield, S11 8BR</a> | Q13: Apartment | R13: Tenanted | T13: Brook Place | U13: BTR-Regions | V13: Emma Cramer-Mitchell | X13: Vicki Turnbull | Y13: Leanne Hargreaves | Z13: 46212 | AA13: Brook Place Apts, 10 Summerfield Street, Shef | AB13: 430, Brook Place Apts, Sheffield, S11 8BS | AC13: GREP-CoA Sean Pillay, Dominika Matuszkiewicz - 201, Brook Place Apts, Sheffield, S11 8BR | AD13: 519499748 | AF13: Yes | AH13: It is very quiet and the space is very peaceful - plus comes with a gym! Can't even start to elaborate how practical that is. | AJ13: The quality is high | AK13: My experience has been really wonderful and the reception team is so nice and gets all our problems sorted promptly. Haven't lived in such a nice place before. | AL13: 45544.085 | AR13: =COUNTIF(AD:AD,AD13) -> 1
A14: 003Nz00000EknwyIAB | B14: 006Nz00000BpLNfIAN | C14: Peter | D14: Little | F14: 45870 | G14: 45506 | H14: Lead Tenant | I14: peterjameslittle41@hotmail.com | J14: 07594444586 | K14: Apartment 209 The Condor,1 Springwell Square, Derby, DE1 1FB | L14: TRUE | M14: New | O14: 45506 | P14: <a href="a1G8d000002QBYq" target="_blank">209 The Condor, 1 Springwell Sq</a> | Q14: Apartment | R14: Tenanted | T14: The Condor | U14: BTR-Regions | V14: Jessica Coates | X14: Vicki Turnbull | Y14: Leanne Hargreaves | Z14: 45870 | AA14: The Condor - Apartments | AB14: 209 The Condor, 1 Springwell Sq | AC14: GREP-CoA Peter Little - 209 The Condor, 1 Springwell Sq | AD14: 521196636 | AH14: I like the fact that the property is so central to Derby shops etc. | AJ14: It‚Äôs pretty good | AL14: 45596.126 | AR14: =COUNTIF(AD:AD,AD14) -> 1
A15: 003Nz00000EJKXdIAP | B15: 006Nz00000BUahIIAT | C15: Caleb | D15: Ogwu | F15: 45850 | G15: 45486 | H15: Lead Tenant | I15: calebogwu7@gmail.com | J15: 07482363828 | K15: Flat 707, Pin Yard,11 Sweet Street, Leeds, LS11 9FB | L15: TRUE | M15: New | O15: 45486 | P15: <a href="a1G8d0000004Xcn" target="_blank">707 Pin Yard, 11 Sweet Street, Leeds</a> | Q15: Apartment | R15: On the Market Available to View | T15: The Headline | U15: BTR-Regions | V15: George Diamantopoulos | X15: Vicki Turnbull | Y15: Leanne Hargreaves | Z15: 45666 | AA15: The Headline Apts, Wellington Park Way, Leeds | AB15: 104, The Headline, Wellington Park Way, Leeds | AC15: GREP-CoA Mr Caleb Ogwu & Miss Anuoluwapo Ikotun - 707 Pin Yard, 11 Sweet Street, Leeds | AD15: 519273414 | AJ15: It‚Äôs pretty good | AL15: 45576.084 | AR15: =COUNTIF(AD:AD,AD15) -> 1
A16: 003Nz00000E38LxIAJ | B16: 006Nz00000BJg6rIAD | C16: Erik Youngtaek | D16: Yu | F16: 45817 | G16: 45453 | H16: Lead Tenant | I16: youngtaek.yu@hotmail.co.uk | J16: 07450208063 | K16: Flat 33, Nautilus Apartments,2 Norah Smyth Road, London, E16 1FE | L16: TRUE | M16: New | O16: 45453 | P16: <a href="a1G8d000002QBMz" target="_blank">33 Nautilus Apts, 2 Norah Smyth Rd, London</a> | Q16: Apartment | R16: Tenanted | T16: Nautilus Apartments | U16: BTR-London & SE | V16: Fatma Azakli | X16: Harriet Shaw | Y16: Fatma Azakli | Z16: 45813 | AA16: Nautilus - Apartments | AB16: 122 Nautilus Apts, 1 Jam Lane, London | AC16: GREP-CoA Erik Youngtaek Yu & Jarim Koo - 33 Nautilus Apts, 2 Norah Smyth Rd, London | AD16: 518048632 | AL16: 45543.084 | AR16: =COUNTIF(AD:AD,AD16) -> 1
A17: 003Nz00000E35mHIAR | B17: 006Nz00000BJcEXIA1 | C17: Valentina | D17: Rumyantseva | F17: 45864 | G17: 45500 | H17: Lead Tenant | I17: vale.obsgyn@gmail.com | J17: 07774085392 | K17: Apartment 617, The Barnum,23 Queens Road, Nottingham, NG2 3FP | L17: TRUE | M17: New | O17: 45500 | P17: <a href="a1GNz00000016GI" target="_blank">617 The Barnum, 23 Queens Road, Nottingham</a> | Q17: Apartment | R17: Tenanted | T17: The Barnum | U17: BTR-Regions | V17: Natasha Burns | X17: Vicki Turnbull | Y17: Leanne Hargreaves | Z17: 45822 | AA17: The Barnum - Apartments | AB17: 631 The Barnum, 23 Queens Road, Nottingham | AC17: GREP-CoA Valentina Rumyantseva - 617 The Barnum, 23 Queens Road, Nottingham | AD17: 518048414 | AH17: Super comfy, the best place I ever lived | AJ17: The quality is high | AL17: 45590.084 | AR17: =COUNTIF(AD:AD,AD17) -> 1
A18: 003Nz00000E1RB0IAN | B18: 006Nz00000BM0mDIAT | C18: Desiree | D18: Brito | F18: 45838 | G18: 45474 | H18: Tenant | I18: estaesjkde@gmail.com | J18: 07587693558 | K18: Flat 520, Pin Yard,11 Sweet Street, Leeds, LS11 9FB | L18: TRUE | M18: New | O18: 45474 | P18: <a href="a1G8d0000004Xit" target="_blank">520 Pin Yard, 11 Sweet Street, Leeds</a> | Q18: Apartment | R18: Tenanted | T18: Pin Yard | U18: BTR-Regions | V18: Ruth Friend | X18: Vicki Turnbull | Y18: Ruth Friend | Z18: 45838 | AA18: Pin Yard - Apartments | AB18: 520 Pin Yard, 11 Sweet Street, Leeds | AC18: GREP-CoA Omolade Osinaike, Desiree Brito - 520 Pin Yard, 11 Sweet Street, Leeds | AD18: 518043880 | AH18: It‚Äôs a good size for 2 people but kitchen could have more storage space, wish the ceiling lights had the option to choose to turn on or off a certain number of them , not all of them as it is now. The yelowish color of the floors corridors is awful. | AJ18: It‚Äôs pretty good | AL18: 45564.085 | AR18: =COUNTIF(AD:AD,AD18) -> 1
A19: 003Nz00000Dze7WIAR | B19: 006Nz00000Al1SjIAJ | C19: Trina | D19: Persyn | F19: 45805 | G19: 45441 | H19: Tenant | I19: trinapersyn@outlook.com | J19: 07562618895 | K19: Apartment 206, Neon House,207 Chapel Street, Salford, M3 5PF | L19: TRUE | M19: New | O19: 45441 | P19: <a href="a1G4J0000025yF6" target="_blank">206, Neon House, 207 Chapel St, Salford, M3 5</a> | Q19: Apartment | R19: Tenanted | T19: The Filaments | U19: BTR-Regions | V19: Samantha Lancaster | X19: Vicki Turnbull | Y19: Samantha Lancaster | Z19: 45805 | AA19: The Filaments, 207 Chapel St, Salford, M3 5PF | AB19: 206, Neon House, 207 Chapel St, Salford, M3 5 | AC19: GREP-CoA Jaspreet Kaur Ghuman, Chloe Self and Trina Persyn - 206, Neon House, 207 Chapel St, Salford, M3 5 | AD19: 517820092 | AF19: Yes | AH19: The sense of community and amenities | AJ19: The quality is high | AK19: Really enjoy living here | AL19: 45531.084 | AR19: =COUNTIF(AD:AD,AD19) -> 1
A20: 003Nz00000DwS7hIAF | B20: 006Nz00000BEbFvIAL | C20: Alicia | D20: Platts | F20: 45800 | G20: 45436 | H20: Tenant | I20: allie.platts98@gmail.com | J20: 07563089559 | K20: Apartment 615 Torrens Apartments,Waterman Walk, Salford, M50 3AT | L20: TRUE | M20: New | O20: 45436 | P20: <a href="a1G4J0000025zDd" target="_blank">615 Torrens Apt, Waterman Wlk, Salford M50</a> | Q20: Apartment | R20: Tenanted | T20: Clippers Quay | U20: BTR-Regions | V20: Helen Bowers | X20: Vicki Turnbull | Y20: Helen Bowers | Z20: 45800 | AA20: Clippers - Torrens Apartments | AB20: 615 Torrens Apt, Waterman Wlk, Salford M50 | AC20: GREP-CoA Max Goodwin and Alicia Platts - 615 Torrens Apt, Waterman Wlk, Salford M50 | AD20: 517585939 | AF20: Yes | AH20: Everything is such good quality - not only my apartment but also the reception and communal areas, the staff, and the extra offerings. | AJ20: It‚Äôs pretty good | AK20: Everything about our experience living here has been considered, from extra help with moving into how easy it is to submit a maintenance request. | AL20: 45526.085 | AR20: =COUNTIF(AD:AD,AD20) -> 1
A21: 003Nz00000DvxTlIAJ | B21: 006Nz00000BEh24IAD | C21: Samuel | D21: Perry | F21: 45836 | G21: 45472 | H21: Lead Tenant | I21: samperrycoach@gmail.com | J21: 07960306865 | K21: Apartment 506, The Copper Works,5 Capital Quarter,, Cardiff, CF10 4DT | L21: TRUE | M21: New | O21: 45472 | P21: <a href="a1GNz0000000bil" target="_blank">506, 5 Capital Quarter, Tyndall St., Cardiff</a> | Q21: Apartment | R21: Tenanted | T21: The Copper Works | U21: BTR-Regions | V21: Karen Meek | X21: Sarah Norstrom | Z21: 45820 | AA21: The Copper Works - Apartments | AB21: 210, 5 Capital Quarter, Tyndall St., Cardiff | AC21: GREP-CoA Samuel Perry - 506, 5 Capital Quarter, Tyndall St., Cardiff | AD21: 517584226 | AH21: The communal spaces | AJ21: It‚Äôs ok | AL21: 45562.085 | AR21: =COUNTIF(AD:AD,AD21) -> 1
A22: 003Nz00000DIUxuIAH | B22: 006Nz00000Alz2IIAR | C22: Pui Fun | D22: Cheng | F22: 45601 | G22: 45418 | H22: Tenant | I22: pandabb123abc@gmail.com | J22: 07407374811 | K22: Apartment 504 Syren Apartments,Ottinger Close, Salford, M50 3AP | L22: TRUE | M22: New | O22: 45418 | P22: <a href="a1G4J0000025xyC" target="_blank">504 Syren Apt , Ottinger Close, Salford M50</a> | Q22: Apartment | R22: Tenanted | T22: Clippers Quay | U22: BTR-Regions | V22: Helen Bowers | X22: Vicki Turnbull | Y22: Helen Bowers | Z22: 45601 | AA22: Clippers - Syren Apartments | AB22: 504 Syren Apt , Ottinger Close, Salford M50 | AC22: GREP-CoA M Cheng, P F Cheng, P C Cheng & P H Cheng - 504 Syren Apt , Ottinger Close, Salford M50 | AD22: 514679292 | AF22: Yes | AH22: dinning room and gym room | AJ22: The quality is high | AK22: up to now quite good | AL22: 45508.085 | AR22: =COUNTIF(AD:AD,AD22) -> 1
A23: 003Nz00000DgR5yIAF | B23: 006Nz00000B3fDCIAZ | C23: Lai Ming | D23: Kong | F23: 45840 | G23: 45476 | H23: Lead Tenant | I23: klming1026@hotmail.com | J23: 07881122025 | K23: Apartment 806 Ambassador Apartments,Waterman Walk, Salford, M50 3AW | L23: TRUE | M23: New | O23: 45476 | P23: <a href="a1G4J0000025ykt" target="_blank">806 Ambassador Apt, Waterman Wlk, Salford M50</a> | Q23: Apartment | R23: Tenanted | T23: Clippers Quay | U23: BTR-Regions | V23: Helen Bowers | X23: Vicki Turnbull | Y23: Helen Bowers | Z23: 45500 | AA23: Clippers - Ambassador Apartments | AB23: 806 Ambassador Apt, Waterman Wlk, Salford M50 | AC23: GREP-CoA Lai Ming Kong & Yun Lau Tang - 806 Ambassador Apt, Waterman Wlk, Salford M50 | AD23: 516376794 | AH23: Nice environment and Service | AJ23: It‚Äôs ok | AL23: 45566.084 | AR23: =COUNTIF(AD:AD,AD23) -> 1
A24: 003Nz00000Dgh98IAB | B24: 006Nz00000B2Qg1IAF | C24: Grace | D24: Mead | F24: 45806 | G24: 45442 | H24: Lead Tenant | I24: mead.grace@hotmail.com | J24: 07887811322 | K24: 1707, Silver Yard,297 Moor Street Queensway, Birmingham, B4 6GJ | L24: TRUE | M24: New | O24: 45442 | P24: <a href="a1GNz000001HRhZ" target="_blank">1707 The Silver Yard, 100 Moor St Queensway</a> | Q24: Apartment | R24: Tenanted | T24: The Silver Yard | U24: BTR-Regions | X24: Sarah Norstrom | Y24: Emma Billingham | AA24: The Silver Yard - Apartments | AB24: 1707 The Silver Yard, 100 Moor St Queensway | AC24: GREP-CoA Daniel Clark and Grace Mead - 1707 The Silver Yard, 100 Moor St Queensway | AD24: 516378915 | AF24: Yes | AH24: Very clean, modern, staff is very friendly and helpful | AJ24: It‚Äôs pretty good | AK24: Well looked after, facilities are good and staff is great- also feels very secure and safe with security 24/7 and having to fob into everywhere | AL24: 45532.085 | AR24: =COUNTIF(AD:AD,AD24) -> 1
A25: 003Nz00000DFqQFIA1 | B25: 006Nz00000AWd28IAD | C25: Lydia Anne | D25: Tibbet | F25: 45807 | G25: 45444 | H25: Tenant | I25: lydia.tibbet@gmail.com | J25: 07360158053 | K25: Apartment 401, The Copper Works,5 Capital Quarter,, Cardiff, CF10 4DS | L25: TRUE | M25: New | O25: 45444 | P25: <a href="a1GNz0000000cZx" target="_blank">401, 5 Capital Quarter, Tyndall St., Cardiff</a> | Q25: Apartment | R25: Tenanted | T25: The Copper Works | U25: BTR-Regions | V25: Karen Meek | X25: Sarah Norstrom | AA25: The Copper Works - Apartments | AB25: 401, 5 Capital Quarter, Tyndall St., Cardiff | AC25: GREP-CoA Jessica Debono and Lydia Anne Tibbet - 401, 5 Capital Quarter, Tyndall St., Cardiff | AD25: 514457897 | AF25: Yes | AH25: I like the necessities, I like the gym and communal areas specifically. Concierge also great. | AJ25: It‚Äôs ok | AK25: As above ref parking. The fact parking is an extra ¬£150 a month when that mirrors NCP charges is really ridiculous. That has been a real difficulty. Plus 6 months with no outdoor space and furniture when that was promised upon arrival. | AL25: 45534.085 | AR25: =COUNTIF(AD:AD,AD25) -> 1
A26: 003Nz00000DBqNBIA1 | B26: 006Nz00000AikkXIAR | C26: Amy | D26: Clift | F26: 46196 | G26: 45467 | H26: Lead Tenant | I26: amyclift.ac@gmail.com | J26: 07469243953 | K26: Apartment 417, Ingot Place,84 Upper Allen Street, Sheffield, S3 7NY | L26: TRUE | M26: New | O26: 45467 | P26: <a href="a1GNz0000000yH7" target="_blank">417, 84 Upper Allen St, Sheffield</a> | Q26: Apartment | R26: Tenanted | T26: Brook Place | U26: BTR-Regions | V26: Emma Cramer-Mitchell | X26: Vicki Turnbull | Y26: Leanne Hargreaves | Z26: 45808 | AA26: Brook Place Apts, 10 Summerfield Street, Shef | AB26: 218, Brook Place Apts, Sheffield, S11 8BR | AC26: GREP-CoA Amy Clift & Alexander Shaw - 417, 84 Upper Allen St, Sheffield | AD26: 514225006 | AH26: The actual flat | AJ26: It‚Äôs pretty good | AL26: 45557.085 | AR26: =COUNTIF(AD:AD,AD26) -> 1
A27: 003Nz00000DbNPbIAN | B27: 006Nz00000AzhjrIAB | C27: Louise | D27: Henderson | F27: 45793 | G27: 45429 | H27: Lead Tenant | I27: lhjhenderson@gmail.com | J27: 07885685804 | K27: Apartment 915 Torrens Apartments,Waterman Walk, Salford, M50 3AT | L27: TRUE | M27: New | O27: 45429 | P27: <a href="a1G4J0000025ys9" target="_blank">915 Torrens Apt, Waterman Wlk, Salford M50</a> | Q27: Apartment | R27: Tenanted | T27: Clippers Quay | U27: BTR-Regions | V27: Helen Bowers | X27: Vicki Turnbull | Y27: Helen Bowers | Z27: 45793 | AA27: Clippers - Torrens Apartments | AB27: 915 Torrens Apt, Waterman Wlk, Salford M50 | AC27: GREP-CoA Louise Henderson - 915 Torrens Apt, Waterman Wlk, Salford M50 | AD27: 516137169 | AF27: Yes | AH27: The security and friendly staff | AJ27: It‚Äôs pretty good | AK27: Nice safe building and a good location. The building is well cared for the staff are very friendly. Car parking is expensive considering the high rent. And I can‚Äôt get my bath water hot. | AL27: 45519.085 | AR27: =COUNTIF(AD:AD,AD27) -> 1
A28: 003Nz00000DbID6IAN | B28: 006Nz00000Azhs0IAB | C28: Ahmed Mohamed Elmagh | D28: Elgendy | F28: 45838 | G28: 45474 | H28: Lead Tenant | I28: a.elgendy78@gmail.com | J28: 36300123565 | K28: Flat 328 , Enigma Square,414 North Row, Milton Keynes, MK9 2GF | L28: TRUE | M28: New | O28: 45474 | P28: <a href="a1G8d0000005rSf" target="_blank">328 Enigma Square, 414 North Row, MK9 2GF</a> | Q28: Apartment | R28: Tenanted | T28: Solstice Apartments | U28: BTR-Regions | V28: Tina Viragh | X28: Sarah Norstrom | Y28: Kaycee Cooper | Z28: 45535 | AA28: Solstice Apts, 801 Silbury Boulevard, MK9 | AB28: 325, Solstice Apts, Silbury Boulevard | AC28: GREP-CoA Ahmed Elgendy, Hager Amer - 328 Enigma Square, 414 North Row, MK9 2GF | AD28: 516140415 | AH28: Best thing is the amazing team | AL28: 45564.085 | AR28: =COUNTIF(AD:AD,AD28) -> 1
A29: 003Nz00000CX9buIAD | B29: 006Nz00000AIgcXIAT | C29: YIU WAI | D29: FUNG | F29: 45796 | G29: 45432 | H29: Tenant | I29: andyfungjewelry@gmail.com | J29: 07867083456 | K29: Apartment 409 Ambassador Apartments,Waterman Walk, Salford, M50 3AU | L29: TRUE | M29: New | O29: 45432 | P29: <a href="a1G4J0000025yu2" target="_blank">409 Ambassador Apt, Waterman Wlk, Salford M50</a> | Q29: Apartment | R29: Tenanted | T29: Clippers Quay | U29: BTR-Regions | V29: Helen Bowers | X29: Vicki Turnbull | Y29: Helen Bowers | Z29: 45425 | AA29: Clippers - Ambassador Apartments | AB29: 409 Ambassador Apt, Waterman Wlk, Salford M50 | AC29: GREP-CoA Pui Ki Ho & Yiu Wai Fung - 409 Ambassador Apt, Waterman Wlk, Salford M50 | AD29: 511267792 | AF29: Yes | AH29: The resident service team | AJ29: It‚Äôs ok | AK29: Because of great resident service team | AL29: 45522.085 | AR29: =COUNTIF(AD:AD,AD29) -> 1
A30: 003Nz00000CX72DIAT | B30: 006Nz00000AIWQMIA5 | C30: Charlotte | D30: Noerregaard-Ettle | F30: 45777 | G30: 45413 | H30: Lead Tenant | I30: charlotte@wordenskjold.dk | J30: '+44 7974 396908 | K30: Flat 51, Hawkins Lane Building,East Tucker Street, Bristol, BS1 6WQ | L30: TRUE | M30: New | O30: 45413 | P30: <a href="a1G4J0000025yl8" target="_blank">FLAT 51, Hawkins Ln, Finzels Reach, Bristol,</a> | Q30: Apartment | R30: Tenanted | T30: Hawkins & George | U30: BTR-Regions | V30: Sarah Regan | X30: Vicki Turnbull | Y30: Craig Parkinson | Z30: 45777 | AA30: HG-Hawkins Ln, Finzels Reach, Bristol, BS1 | AB30: FLAT 51, Hawkins Ln, Finzels Reach, Bristol, | AC30: GREP-CoA Charlotte & Andrew Noerregaard-Ettle - FLAT 51, Hawkins Ln, Finzels Reach, Bristol, | AD30: 511267593 | AF30: Yes | AH30: Amenities-fitness, rooftop, mail and package service. Support from the reception when needed | AJ30: It‚Äôs ok | AK30: Very noisy apartment- pub on the left side and glass container on the right side. Plus Parking availability. | AL30: 45503.085 | AR30: =COUNTIF(AD:AD,AD30) -> 1
A31: 003Nz00000CuluzIAB | B31: 006Nz00000AVB7uIAH | C31: Koon Hong | D31: Kwok | F31: 45777 | G31: 45413 | H31: Tenant | I31: kukukux3@gmail.com | J31: 07752064317 | K31: Flat 604 , Enigma Square,414 North Row, Milton Keynes, MK9 2FU | L31: TRUE | M31: New | O31: 45413 | P31: <a href="a1G8d0000005rDF" target="_blank">604 Enigma Square, 414 North Row, MK9 2FU</a> | Q31: Apartment | R31: Reserved | T31: Enigma Square | U31: BTR-Regions | V31: Tina Viragh | X31: Sarah Norstrom | Y31: Grace Fiske | Z31: 45841 | AA31: Enigma Square - Apartments | AB31: 320 Enigma Square, 414 North Row, MK9 2GE | AC31: GREP-CoA Suet Ying Chow, Koon Hong Kwok - 604 Enigma Square, 414 North Row, MK9 2FU | AD31: 512999361 | AF31: No | AH31: Good management | AJ31: It‚Äôs pretty good | AK31: location is good and staff is nice. | AL31: 45503.085 | AR31: =COUNTIF(AD:AD,AD31) -> 1
A32: 003Nz00000CUIIRIA5 | B32: 006Nz00000AGSPDIA5 | C32: Matthew | D32: Kizintas | F32: 45817 | G32: 45453 | H32: Tenant | I32: mattkizintas@gmail.com | J32: 07799480709 | K32: Apartment 45, Millwrights Place,Temple Back, Bristol, BS1 6ZS | L32: TRUE | M32: New | O32: 45453 | P32: <a href="a1GNz0000019GzR" target="_blank">45 Millwrights Place, Temple Back, Bristol</a> | Q32: Apartment | R32: Tenanted | T32: Millwrights Place | U32: BTR-Regions | X32: Sarah Norstrom | AA32: Millwrights Place - Apartments | AB32: 45 Millwrights Place, Temple Back, Bristol | AC32: GREP-CoA Carin Madeleine Selenius & Matthew Kizintas - 45 Millwrights Place, Temple Back, Bristol | AD32: 511042214 | AF32: Yes | AH32: The home Is in a good location | AJ32: It‚Äôs ok | AK32: Numerous issues when we moved into the flat with which we did not feel particularly well Supported by the building manager. | AL32: 45543.084 | AR32: =COUNTIF(AD:AD,AD32) -> 1
A33: 003Nz00000CUGYNIA5 | B33: 006Nz00000AGu3hIAD | C33: Leung Lai Ping | D33: Gloria | F33: 45770 | G33: 45406 | H33: Lead Tenant | I33: glorialeung318@gmail.com | J33: 85269398910 | K33: 805 Brook Place,10 Summerfield Street, Sheffield, S11 8DA | L33: TRUE | M33: New | O33: 45406 | P33: <a href="a1G4J0000025zMK" target="_blank">805, Brook Place Apts, Sheffield, S11 8DA</a> | Q33: Apartment | R33: Tenanted | T33: Brook Place | U33: BTR-Regions | V33: Emma Cramer-Mitchell | X33: Vicki Turnbull | Y33: Leanne Hargreaves | Z33: 45770 | AA33: Brook Place Apts, 10 Summerfield Street, Shef | AB33: 805, Brook Place Apts, Sheffield, S11 8DA | AC33: GREP-CoA Leung Lai Ping Gloria - 805, Brook Place Apts, Sheffield, S11 8DA | AD33: 511042358 | AF33: No | AH33: Grainger is great in terms of the apartment itself and staff quality. Property is quite new. And it's located near city centre. Staff is nice and helpful | AJ33: It‚Äôs pretty good | AK33: everything seems perfect but there is always room for improvement | AL33: 45496.085 | AR33: =COUNTIF(AD:AD,AD33) -> 1
A34: 003Nz00000CSZDdIAP | B34: 006Nz00000AFtxiIAD | C34: Abdulmohsen | D34: Alkhanbashi | E34: PHD | F34: 45817 | G34: 45453 | H34: Lead Tenant | I34: amohsen.alkanbashi@gmail.com | J34: 07555971045 | K34: Apartment 67, Millwrights Place,Temple Back, Bristol, BS1 6ZS | L34: TRUE | M34: New | O34: 45453 | P34: <a href="a1GNz0000019HHB" target="_blank">67 Millwrights Place, Temple Back, Bristol</a> | Q34: Apartment | R34: Tenanted | T34: Millwrights Place | U34: BTR-Regions | X34: Sarah Norstrom | Z34: 45817 | AA34: Millwrights Place - Apartments | AB34: 67 Millwrights Place, Temple Back, Bristol | AC34: GREP-CoA Abdulmohsen Alkhanbashi - 67 Millwrights Place, Temple Back, Bristol | AD34: 511035015 | AF34: Yes | AH34: Apartment is spacious, great amenities, brilliant staff, and perfect location. | AJ34: It‚Äôs pretty good | AK34: I love the place. I am already recommending it to people. | AL34: 45543.084 | AR34: =COUNTIF(AD:AD,AD34) -> 1
A35: 003Nz00000CSNyuIAH | B35: 006Nz00000A1zQHIAZ | C35: Delia | D35: Kong | F35: 45817 | G35: 45450 | H35: Tenant | I35: moonlightwave216@gmail.com | J35: 07917957437 | K35: Flat 134, Nautilus Apartments,1 Jam Lane, London, E16 1GT | L35: TRUE | M35: New | O35: 45450 | P35: <a href="a1G8d000002QBMW" target="_blank">134 Nautilus Apts, 1 Jam Lane, London</a> | Q35: Apartment | R35: Tenanted | T35: Argo Apartments | U35: BTR-London & SE | V35: Raihana Parveen | X35: Harriet Shaw | Y35: Holly Boggis | Z35: 45828 | AA35: Argo Apartments | AB35: 76 Argo Apts, 4 Silvertown Way,London,E16 1YD | AC35: GREP-CoA Scott Tham, Delia Kong - 134 Nautilus Apts, 1 Jam Lane, London | AD35: 511034863 | AF35: Yes | AH35: Appreciate the efficient use of space and generally good quality furnitures. | AJ35: It‚Äôs pretty good | AK35: I would recommend the apartment. However, the whole process prior to getting the keys was not smooth, such as inaccurate information shared during the letting process and issues with the contract took weeks to resolve. | AL35: 45540.084 | AR35: =COUNTIF(AD:AD,AD35) -> 1
A36: 003Nz00000CriNPIAZ | B36: 006Nz00000AW4ikIAD | C36: Chloe | D36: Brown | F36: 45779 | G36: 45414 | H36: Lead Tenant | I36: chloebrownuk@outlook.com | J36: 07568386061 | K36: 117 Brook Place,10 Summerfield Street, Sheffield, S11 8BR | L36: TRUE | M36: New | O36: 45414 | P36: <a href="a1G4J0000025zJm" target="_blank">117, Brook Place Apts, Sheffield, S11 8BR</a> | Q36: Apartment | R36: Tenanted | T36: Brook Place | U36: BTR-Regions | V36: Emma Cramer-Mitchell | X36: Vicki Turnbull | Y36: Leanne Hargreaves | Z36: 45778 | AA36: Brook Place Apts, 10 Summerfield Street, Shef | AB36: 117, Brook Place Apts, Sheffield, S11 8BR | AC36: GREP-CoA Chloe Brown - 117, Brook Place Apts, Sheffield, S11 8BR | AD36: 512747822 | AF36: Yes | AH36: It allows pets | AJ36: It‚Äôs not great | AK36: It‚Äôs a little pricey and the parking is limited | AL36: 45504.085 | AR36: =COUNTIF(AD:AD,AD36) -> 1
A37: 003Nz00000CRDjpIAH | B37: 006Nz00000AEYQfIAP | C37: John Steven | D37: Lee | F37: 46558 | G37: 45464 | H37: Lead Tenant | I37: johnstevenlee08@gmail.com | J37: 07360340696 | K37: 508, Silver Yard,100 Moor Street Queensway, Birmingham, B4 6GF | L37: TRUE | M37: New | O37: 45464 | P37: <a href="a1GNz000001HPCj" target="_blank">508 The Silver Yard, 100 Moor St Queensway</a> | Q37: Apartment | R37: Tenanted | T37: The Silver Yard | U37: BTR-Regions | X37: Sarah Norstrom | Y37: Emma Billingham | Z37: 46558 | AA37: The Silver Yard - Apartments | AB37: 508 The Silver Yard, 100 Moor St Queensway | AC37: GREP-CoA John Steven Lee - 508 The Silver Yard, 100 Moor St Queensway | AD37: 510808855 | AH37: location | AJ37: It‚Äôs ok | AL37: 45554.085 | AR37: =COUNTIF(AD:AD,AD37) -> 1
A38: 003Nz00000CrCs9IAF | B38: 006Nz00000AVnOUIA1 | C38: Ruth | D38: Howells | F38: 45596 | G38: 45413 | H38: Lead Tenant | I38: ruthkhowells@gmail.com | J38: '+44 7736 468158 | K38: 234 Brook Place,10 Summerfield Street, Sheffield, S11 8BR | L38: TRUE | M38: New | O38: 45413 | P38: <a href="a1G4J0000025zJo" target="_blank">234, Brook Place Apts, Sheffield, S11 8BR</a> | Q38: Apartment | R38: Tenanted | T38: Brook Place | U38: BTR-Regions | V38: Emma Cramer-Mitchell | X38: Vicki Turnbull | Y38: Leanne Hargreaves | Z38: 45626 | AA38: Brook Place Apts, 10 Summerfield Street, Shef | AB38: 234, Brook Place Apts, Sheffield, S11 8BR | AC38: GREP-CoA Ruth Howells, Robert Howells - 234, Brook Place Apts, Sheffield, S11 8BR | AD38: 512744837 | AF38: Yes | AH38: Pet friendly, flexible rental period, safe and quiet and good amenities | AJ38: It‚Äôs pretty good | AK38: It is early days but so far we are happy. We really like the flat and it suits our family well. | AL38: 45503.085 | AR38: =COUNTIF(AD:AD,AD38) -> 1
A39: 003Nz00000CoKshIAF | B39: 006Nz00000AVB7uIAH | C39: Suet Ying | D39: Chow | F39: 45777 | G39: 45413 | H39: Lead Tenant | I39: louisechow621@gmail.com | J39: 07752064317 | K39: Flat 604 , Enigma Square,414 North Row, Milton Keynes, MK9 2FU | L39: TRUE | M39: New | O39: 45413 | P39: <a href="a1G8d0000005rDF" target="_blank">604 Enigma Square, 414 North Row, MK9 2FU</a> | Q39: Apartment | R39: Reserved | T39: Enigma Square | U39: BTR-Regions | V39: Tina Viragh | X39: Sarah Norstrom | Y39: Grace Fiske | Z39: 45841 | AA39: Enigma Square - Apartments | AB39: 320 Enigma Square, 414 North Row, MK9 2GE | AC39: GREP-CoA Suet Ying Chow, Koon Hong Kwok - 604 Enigma Square, 414 North Row, MK9 2FU | AD39: 512720968 | AF39: Yes | AH39: Staff is nice and helpful esp. Michelle, Janki. | AJ39: It‚Äôs pretty good | AK39: Building quality is good, can keep the home very warm. | AL39: 45503.085 | AR39: =COUNTIF(AD:AD,AD39) -> 1
A40: 003Nz00000CIhxGIAT | B40: 006Nz00000A8kb1IAB | C40: Carol | D40: George | F40: 45781 | G40: 45416 | H40: Lead Tenant | I40: ohcarolinah@yahoo.com | J40: 07765740226 | K40: Apartment 625, The Barnum,23 Queens Road, Nottingham, NG2 3FJ | L40: TRUE | M40: New | O40: 45416 | P40: <a href="a1GNz000000163O" target="_blank">625 The Barnum, 23 Queens Road, Nottingham</a> | Q40: Apartment | R40: Tenanted | T40: The Barnum | U40: BTR-Regions | V40: Natasha Burns | X40: Vicki Turnbull | Y40: Leanne Hargreaves | Z40: 45780 | AA40: The Barnum - Apartments | AB40: 625 The Barnum, 23 Queens Road, Nottingham | AC40: GREP-CoA Carol George - 625 The Barnum, 23 Queens Road, Nottingham | AD40: 510045017 | AF40: Yes | AH40: Lounges, amenities and onsite team especially Natasha and Amy. | AJ40: It‚Äôs ok | AK40: I love my home but just fix the issues I raised above. | AL40: 45506.085 | AR40: =COUNTIF(AD:AD,AD40) -> 1
A41: 003Nz00000CIcftIAD | B41: 006Nz00000A8d6WIAR | C41: Itsun | D41: Wang | F41: 45817 | G41: 45453 | H41: Lead Tenant | I41: d2289404y@gmail.com | J41: 07470886719 | K41: Apartment 51, Millwrights Place,Temple Back, Bristol, BS1 6ZS | L41: TRUE | M41: New | O41: 45453 | P41: <a href="a1GNz0000019DQW" target="_blank">51 Millwrights Place, Temple Back, Bristol</a> | Q41: Apartment | R41: Tenanted | T41: Millwrights Place | U41: BTR-Regions | X41: Sarah Norstrom | Z41: 45817 | AA41: Millwrights Place - Apartments | AB41: 51 Millwrights Place, Temple Back, Bristol | AC41: GREP-CoA Itsun Wang - 51 Millwrights Place, Temple Back, Bristol | AD41: 510046068 | AF41: Yes | AH41: Location | AJ41: It‚Äôs not great | AK41: The intercom took whole month to be fixed, which can be down in one day. Also The new staff in the reception is stock up | AL41: 45543.084 | AR41: =COUNTIF(AD:AD,AD41) -> 1
A42: 003Nz00000CEpBpIAL | B42: 006Nz00000A5uVGIAZ | C42: Vaiva | D42: Valinskyte | F42: 45588 | G42: 45405 | H42: Lead Tenant | I42: vaiva.valinskyte@icloud.com | J42: 07889743050 | K42: 606, Neon House,207 Chapel Street, Salford, M3 5PF | L42: TRUE | M42: New | O42: 45405 | P42: <a href="a1G4J0000025y3H" target="_blank">606, Neon House, 207 Chapel St, Salford, M3 5</a> | Q42: Apartment | R42: Tenanted | T42: The Filaments | U42: BTR-Regions | V42: Samantha Lancaster | X42: Vicki Turnbull | Y42: Samantha Lancaster | Z42: 45960 | AA42: The Filaments, 207 Chapel St, Salford, M3 5PF | AB42: 606, Neon House, 207 Chapel St, Salford, M3 5 | AC42: GREP-CoA Vaiva Valinskyte & Kieran Michael Lloyd. - 606, Neon House, 207 Chapel St, Salford, M3 5 | AD42: 509799327 | AF42: No | AH42: Most Concierge staff and the repair guy are great. | AJ42: It‚Äôs not great | AK42: Due to improvements listed in section 3 | AL42: 45495.085 | AR42: =COUNTIF(AD:AD,AD42) -> 1
A43: 003Nz00000Cc1llIAB | B43: 006Nz00000ALXWIIA5 | C43: Josie | D43: Cyrus | F43: 46171 | G43: 45442 | H43: Lead Tenant | I43: jcyrus71@gmail.com | J43: 07586716741 | K43: Flat 5, Eagle House,Eagle Wharf Road, London, N1 7EH | L43: TRUE | M43: New | O43: 45442 | P43: <a href="a1G4J0000025znd" target="_blank">Flat 5 Eagle House, Eagle Wharf Road, London,</a> | Q43: Apartment | R43: Tenanted | T43: Eagle House | U43: PRS-London & SE | V43: Nicolette McRae | X43: Daisy Stuckey | Y43: Hugh Peel | Z43: 45430 | AA43: Eagle House | AB43: Flat 5 Eagle House, Eagle Wharf Road, London, | AC43: GREP-CoA Josie Cyrus - Flat 5 Eagle House, Eagle Wharf Road, London, | AD43: 511499577 | AF43: Yes | AJ43: It‚Äôs not great | AK43: No | AL43: 45532.085 | AR43: =COUNTIF(AD:AD,AD43) -> 1
A44: 003Nz00000CAzcsIAD | B44: 006Nz000009xwZ4IAI | C44: Caitlin | D44: Fox Davis | F44: 45997 | G44: 45450 | H44: Tenant | I44: kitty_fd112@hotmail.com | J44: 07846471661 | K44: Ground Floor,32a The Gardens, London, SE22 9QF | L44: TRUE | M44: New | O44: 45450 | P44: <a href="a1G4J0000025zj1" target="_blank">32a The Gardens, GF, London SE22 9QF</a> | Q44: Apartment | R44: Tenanted | T44: Tilt Core | U44: PRS-London & SE | V44: Mitchell Foot | X44: Daisy Stuckey | Y44: Gav Rowley | Z44: 45443 | AA44: The Gardens, 32a, London, SE22 9QF | AB44: 32a The Gardens, GF, London SE22 9QF | AC44: GREP-CoA Kurtis Lowe, Omar Qasim, Elise Anderson, Caitlin Fox Davis - 32a The Gardens, GF, London SE22 9QF | AD44: 509567230 | AF44: No | AH44: The garden | AJ44: The quality is high | AK44: Because it's a great quality home, in a great location and any issues you have are fixed instantly | AL44: 45540.084 | AR44: =COUNTIF(AD:AD,AD44) -> 1
A45: 003Nz00000C7qiwIAB | B45: 006Nz00000A0z0xIAB | C45: Chun-yu | D45: Yeh | F45: 46212 | G45: 45483 | H45: Lead Tenant | I45: jack18tm@gmail.com | J45: 07521116670 | K45: Flat 1, Ospringe House,Wootton Street, London, SE1 8TS | L45: TRUE | M45: New | O45: 45483 | P45: <a href="a1G4J0000025yZ2" target="_blank">Flat 1, Ospringe House, Wootton St, SE1 8TP</a> | Q45: Apartment | R45: Tenanted | T45: OCCC Estate | U45: Development-DD | V45: Darin Solomon | X45: Alexa Byrne | Y45: Tayla Bonwick | Z45: 45472 | AA45: Ospringe House, Wootton Street, Waterloo, Lon | AB45: Flat 1, Ospringe House, Wootton St, SE1 8TP | AC45: GREP-CoA Chun-yu Yeh & Diego Pablo Sanchez Sanchez - Flat 1, Ospringe House, Wootton St, SE1 8TP | AD45: 509334707 | AH45: Poor maintenance service | AJ45: It‚Äôs not great | AL45: 45573.084 | AR45: =COUNTIF(AD:AD,AD45) -> 1
A46: 003Nz00000C5O9GIAV | B46: 006Nz000005n2gwIAA | C46: Zoe | D46: Labarrere | F46: 45598 | G46: 45415 | H46: Tenant | I46: zoelabarrere4@gmail.com | J46: 07873274855 | K46: Apartment 417, The Barnum,23 Queens Road, Nottingham, NG2 3FJ | L46: TRUE | M46: New | O46: 45415 | P46: <a href="a1GNz00000017kD" target="_blank">417 The Barnum, 23 Queens Road, Nottingham</a> | Q46: Apartment | R46: Tenanted - Up for Renewal | T46: The Barnum | U46: BTR-Regions | V46: Natasha Burns | X46: Vicki Turnbull | Y46: Leanne Hargreaves | Z46: 45598 | AA46: The Barnum - Apartments | AB46: 417 The Barnum, 23 Queens Road, Nottingham | AC46: GREP-CoA William Pikett & Zoe Labarrere - 417 The Barnum, 23 Queens Road, Nottingham | AD46: 509108171 | AF46: No | AH46: The location is very convenient, the flat is clean and new and the staff is great | AJ46: The quality is high | AK46: Everything is great, but a bit more storage could be handy and parking is very expensive. Parking is ¬£100pm in Grainger against ¬£50pm for residents in the building opposite ours | AL46: 45505.085 | AR46: =COUNTIF(AD:AD,AD46) -> 1
A47: 003Nz00000C4xygIAB | B47: 006Nz000009z99IIAQ | C47: Chun Kit Raymond | D47: WU | F47: 45856 | G47: 45492 | H47: Lead Tenant | I47: man1968monkeyuk@gmail.com | J47: 07793517164 | K47: Apartment 907 Ambassador Apartments,Waterman Walk, Salford, M50 3AW | L47: TRUE | M47: New | O47: 45492 | P47: <a href="a1G4J0000025yoq" target="_blank">907 Ambassador Apt, Waterman Wlk, Salford M50</a> | Q47: Apartment | R47: Tenanted | T47: Clippers Quay | U47: BTR-Regions | V47: Helen Bowers | X47: Vicki Turnbull | Y47: Helen Bowers | Z47: 45486 | AA47: Clippers - Ambassador Apartments | AB47: 907 Ambassador Apt, Waterman Wlk, Salford M50 | AC47: GREP-CoA Chun Kit Raymond WU - 907 Ambassador Apt, Waterman Wlk, Salford M50 | AD47: 509104875 | AH47: parcel room | AJ47: It‚Äôs pretty good | AL47: 45582.084 | AR47: =COUNTIF(AD:AD,AD47) -> 1
A48: 003Nz00000C4nCwIAJ | B48: 006Nz000009z6krIAA | C48: Ebong | D48: Thompson | F48: 45761 | G48: 45397 | H48: Lead Tenant | I48: ebongthompson744@gmail.com | J48: 07961093351 | K48: Apartment 5,5 St. Johns Gardens, Bury, BL9 0QY | L48: TRUE | M48: New | O48: 45397 | P48: <a href="a1G4J0000025xnF" target="_blank">5, 5 St. Johns Gardens, Bury, BL9</a> | Q48: Apartment | R48: Tenanted | T48: The Rock | U48: PRS-Regions | V48: David Hancock | X48: Vicki Turnbull | Y48: Lorraine Cree | Z48: 45761 | AA48: St. Johns Gardens, 5, Bury, Lancs, BL9 | AB48: 5, 5 St. Johns Gardens, Bury, BL9 | AC48: GREP-CoA Ebong Thompson and Francisca Nsima - 5, 5 St. Johns Gardens, Bury, BL9 | AD48: 509103616 | AF48: Yes | AH48: The serenity and safety of the environment and apartment | AJ48: The quality is high | AK48: It‚Äôs a lovely and safe place to live | AL48: 45487.085 | AR48: =COUNTIF(AD:AD,AD48) -> 1
A49: 003Nz00000BWFqRIAX | B49: 006Nz000009HH7KIAW | C49: Georgia | D49: Burrows | F49: 45776 | G49: 45412 | H49: Tenant | I49: georgiaburrows23@gmail.com | J49: 07753869096 | K49: Apartment 325 The Condor,1 Springwell Square, Derby, DE1 1BZ | L49: TRUE | M49: New | O49: 45412 | P49: <a href="a1G8d000002QBba" target="_blank">325 The Condor, 1 Springwell Sq</a> | Q49: Apartment | R49: Tenanted | T49: The Condor | U49: BTR-Regions | V49: Jessica Coates | X49: Vicki Turnbull | Y49: Leanne Hargreaves | Z49: 45594 | AA49: The Condor - Apartments | AB49: 318 The Condor, 1 Springwell Sq | AC49: GREP-CoA Sam Atter & Georgia Burrows - 325 The Condor, 1 Springwell Sq | AD49: 506067545 | AF49: Yes | AH49: The open space, the lights the windows let in is incredible. | AJ49: It‚Äôs pretty good | AK49: We love it here, honestly the staff make the place worth it. | AL49: 45502.085 | AR49: =COUNTIF(AD:AD,AD49) -> 1
A50: 003Nz00000BVOZCIA5 | B50: 006Nz000009PkDlIAK | C50: Wai Yin Vivien | D50: Ha | F50: 45789 | G50: 45425 | H50: Tenant | I50: yinahvi@gmail.com | J50: 07597047792 | K50: Flat 1004, The Headline,Wellington Park Way, Leeds, LS1 4EX | L50: TRUE | M50: New | O50: 45425 | P50: <a href="a1G4J000004jys8" target="_blank">1004,The Headline, Wellington Park Way, Leeds</a> | Q50: Apartment | R50: Tenanted | T50: The Headline | U50: BTR-Regions | V50: George Diamantopoulos | X50: Vicki Turnbull | Y50: Leanne Hargreaves | Z50: 46207 | AA50: The Headline Apts, Wellington Park Way, Leeds | AB50: 310, The Headline, Wellington Park Way, Leeds | AC50: GREP-CoA Ting Ting Tammy Cheung, Wai Yin Vivien Ha - 1004,The Headline, Wellington Park Way, Leeds | AD50: 506063107 | AF50: No | AH50: My deliveries service._x000D_ No need to worry about my order. | AJ50: The quality is high | AK50: Service team is the best | AL50: 45515.085 | AR50: =COUNTIF(AD:AD,AD50) -> 1
A51: 003Nz00000BtSF3IAN | B51: 006Nz000009orAPIAY | C51: Thom | D51: Byrne | F51: 45769 | G51: 45404 | H51: Tenant | I51: thomasbyrneuk@gmail.com | J51: 07375370713 | K51: 19 Garter House,12 Market Street, Newbury, RG14 5ER | L51: TRUE | M51: New | O51: 45404 | P51: <a href="a1G8d0000004qmG" target="_blank">19 Garter House, 12 Market Street, Newbury</a> | Q51: Apartment | R51: Tenanted | T51: Weavers Yard | U51: BTR-London & SE | V51: Kimberley Pope | X51: Harriet Shaw | Y51: Daniel Hind | Z51: 45793 | AA51: Weavers Yard - Cable House | AB51: 18 Cable House, 2 Echo Walk, Newbury | AC51: GREP-CoA Eleanor Reynard & Thom Byrne - 19 Garter House, 12 Market Street, Newbury | AD51: 508107550 | AF51: No | AH51: Closeness to town | AK51: Number of issues including heat, and issues with front door of building being locked and taking long time to resolve. | AL51: 45494.085 | AR51: =COUNTIF(AD:AD,AD51) -> 1
A52: 003Nz00000BsX7EIAV | B52: 006Nz000009njy7IAA | C52: Miyuki | D52: Takahashi | F52: 45800 | G52: 45436 | H52: Tenant | I52: myk.sw1t.0916@gmail.com | J52: 7803 448266 | K52: 1113,5 Capital Quarter, Tyndall St., Cardiff, CF10 4EF | L52: TRUE | M52: New | O52: 45436 | P52: <a href="a1GNz0000000e77" target="_blank">1113, 5 Capital Quarter, Tyndall St., Cardiff</a> | Q52: Apartment | R52: Tenanted | T52: The Copper Works | U52: BTR-Regions | V52: Karen Meek | X52: Sarah Norstrom | Z52: 45619 | AA52: The Copper Works - Apartments | AB52: 1113, 5 Capital Quarter, Tyndall St., Cardiff | AC52: GREP-CoA Matthew James Hall and Miyuki Takahashi - 1113, 5 Capital Quarter, Tyndall St., Cardiff | AD52: 508095020 | AF52: No | AH52: Easy to use. | AJ52: It‚Äôs pretty good | AL52: 45526.085 | AR52: =COUNTIF(AD:AD,AD52) -> 1
A53: 003Nz00000BsLdpIAF | B53: 006Nz00000AGVlHIAX | C53: Juan Jose | D53: Gonzalez Fernandez | F53: 45766 | G53: 45401 | H53: Lead Tenant | I53: gonzalezjuanjo1@gmail.com | J53: 07565734549 | K53: Apartment 98, Gilders Yard,14 Great Hampton Street, Birmingham, B18 6ER | L53: TRUE | M53: New | O53: 45401 | P53: <a href="a1G8d0000004cAL" target="_blank">98, Gilders Yard, 14 Great Hampton St, Birm</a> | Q53: Apartment | R53: Tenanted | T53: Gilders Yard | U53: BTR-Regions | V53: Lewis Morris | X53: Vicki Turnbull | Y53: Neil Persad | Z53: 45401 | AA53: Gilders Yard - Apartments A-C | AB53: 98, Gilders Yard, 14 Great Hampton St, Birm | AC53: GREP-CoA Juan Jose Gonzalez Fernandez & Ana Cristina Carrascosa Franco - 98, Gilders Yard, 14 Great Hampton St, Birm | AD53: 508091868 | AF53: Yes | AH53: only the gym and need more machines | AJ53: It‚Äôs not great | AK53: the windows doesn¬¥t open enough and the Kitchen hood does not extract the smoke from the property, it spreads it all over the room. the property vibrates when walking through the living room or when the upstairs neighbour do, lack of security | AL53: 45491.085 | AR53: =COUNTIF(AD:AD,AD53) -> 1
A54: 003Nz00000BSHZ6IAP | B54: 006Nz000009Xi3XIAS | C54: Kristina | D54: Kattapuram | F54: 45776 | G54: 45411 | H54: Tenant | I54: kkattapuram2@gmail.com | J54: 0017788999099 | K54: Flat 113, Hawkins Lane Building,East Tucker Street, Bristol, BS1 6WR | L54: TRUE | M54: New | O54: 45411 | P54: <a href="a1G4J0000025yz2" target="_blank">FLAT 113, Hawkins Ln, Finzels Reach, Bristol,</a> | Q54: Apartment | R54: Tenanted | T54: Hawkins & George | U54: BTR-Regions | V54: Sarah Regan | X54: Vicki Turnbull | Y54: Craig Parkinson | Z54: 45389 | AA54: HG-Georges Whrf, Finzels Reach, Bristol, BS1 | AB54: FLAT 44 Georges Whrf Finzels Reach Bristol BS | AC54: GREP-CoA Kevin van der Meij, Kristina Kattapuram - FLAT 113, Hawkins Ln, Finzels Reach, Bristol, | AD54: 505831299 | AF54: No | AH54: The reception team is kind, friendly and welcoming! | AJ54: It‚Äôs pretty good | AK54: The maintenance issues | AL54: 45501.085 | AR54: =COUNTIF(AD:AD,AD54) -> 1
A55: 003Nz00000BrwNiIAJ | B55: 006Nz000009qPRlIAM | C55: Zainab | D55: Muhamed-Khail | F55: 47231 | G55: 45405 | H55: Tenant | I55: zmkhail@gmail.com | K55: 49,Mandora Road, Aldershot, GU11 4FQ | L55: TRUE | M55: New | O55: 45405 | P55: <a href="a1GNz000001fuwv" target="_blank">49 Mandora Road, GU11 4FQ</a> | R55: Tenanted | T55: GT - Wellesley | U55: Grainger Trust | V55: Shelby Overington | X55: Anish Thobhani | Y55: Andrea Gorman | AA55: 49 Mandora Road, GU11 4FQ | AB55: 49 Mandora Road, GU11 4FQ | AC55: GREP-CoA Mr Zabihulluh Muhamed-Khail & Mrs Zainab Muhamad-Khail - 49 Mandora Road, GU11 4FQ | AD55: 508088479 | AF55: Yes | AH55: The service, and the structure of homes. | AJ55: The quality is high | AK55: Why shouldn‚Äôt i they are perfect. | AL55: 45495.085 | AR55: =COUNTIF(AD:AD,AD55) -> 1
A56: 003Nz00000BOPlLIAX | B56: 006Nz000009UrPtIAK | C56: Sam | D56: Raine | F56: 45801 | G56: 45437 | H56: Lead Tenant | I56: samraine89@hotmail.co.uk | J56: 07940243010 | K56: Flat 96, Hawkins Lane Building,East Tucker Street, Bristol, BS1 6WR | L56: TRUE | M56: New | O56: 45437 | P56: <a href="a1G4J0000025yyJ" target="_blank">FLAT 96, Hawkins Ln, Finzels Reach, Bristol,</a> | Q56: Apartment | R56: Tenanted | T56: Hawkins & George | U56: BTR-Regions | V56: Sarah Regan | X56: Vicki Turnbull | Y56: Craig Parkinson | Z56: 45961 | AA56: HG-Hawkins Ln, Finzels Reach, Bristol, BS1 | AB56: FLAT 96, Hawkins Ln, Finzels Reach, Bristol, | AC56: GREP-CoA Sam Raine - FLAT 96, Hawkins Ln, Finzels Reach, Bristol, | AD56: 505597616 | AF56: Yes | AH56: It feels private and has good natural light | AJ56: It‚Äôs not great | AK56: Great building and staff and location | AL56: 45527.085 | AR56: =COUNTIF(AD:AD,AD56) -> 1
A57: 003Nz00000BOPF4IAP | B57: 006Nz000009EMOZIA4 | C57: Oluwaseyi | D57: Shobayo | F57: 45777 | G57: 45412 | H57: Tenant | I57: shobayooluwaseyifunmi5@gmail.com | J57: 07541563141 | K57: Apartment 530 The Condor,1 Springwell Square, Derby, DE1 1EB | L57: TRUE | M57: New | O57: 45412 | P57: <a href="a1G8d000002QBg1" target="_blank">530 The Condor, 1 Springwell Sq</a> | Q57: Apartment | R57: Tenanted | T57: The Condor | U57: BTR-Regions | V57: Jessica Coates | X57: Vicki Turnbull | Y57: Leanne Hargreaves | Z57: 45594 | AA57: The Condor - Apartments | AB57: 318 The Condor, 1 Springwell Sq | AC57: GREP-CoA Kolawole Akinola & Oluwaseyi Shobayo - 530 The Condor, 1 Springwell Sq | AD57: 505597615 | AF57: No | AJ57: It‚Äôs ok | AL57: 45502.085 | AR57: =COUNTIF(AD:AD,AD57) -> 1
A58: 003Nz00000Bl6zjIAB | B58: 006Nz000009lQgFIAU | C58: Kevin | D58: Meurling | F58: 45803 | G58: 45439 | H58: Lead Tenant | I58: kevin.meurling@cloudimperiumgames.com | J58: '+46 70 579 54 63 | K58: Apartment 207, Neon House,207 Chapel Street, Salford, M3 5PH | L58: TRUE | M58: New | O58: 45439 | P58: <a href="a1G4J0000025yib" target="_blank">207 Neon House, 207 Chapel St, Salford, M3 5P</a> | Q58: House | R58: Tenanted | T58: The Filaments | U58: BTR-Regions | V58: Samantha Lancaster | X58: Vicki Turnbull | Y58: Samantha Lancaster | Z58: 45435 | AA58: The Filaments, 207 Chapel St, Salford, M3 5PF | AB58: 207 Neon House, 207 Chapel St, Salford, M3 5P | AC58: GREP-CoA Kevin Meurling & Nasir Kakar - 207 Neon House, 207 Chapel St, Salford, M3 5P | AD58: 507559547 | AF58: Yes | AH58: I love the layout of the apartment | AJ58: The quality is high | AK58: Because I love it here | AL58: 45529.085 | AR58: =COUNTIF(AD:AD,AD58) -> 1
A59: 003Nz00000Bi9cNIAR | B59: 006Nz000009jMbwIAE | C59: George | D59: Hill | F59: 45813 | G59: 45449 | H59: Lead Tenant | I59: georgehhill17@gmail.com | J59: 07851695453 | K59: Apartment 305, Lamp House,215 Chapel Street, Salford, M3 5PE | L59: TRUE | M59: New | O59: 45449 | P59: <a href="a1G4J0000025yKp" target="_blank">305, Lamp House, 215 Chapel St, Salford, M3 5</a> | Q59: Apartment | R59: Tenanted | T59: The Filaments | U59: BTR-Regions | V59: Samantha Lancaster | X59: Vicki Turnbull | Y59: Samantha Lancaster | Z59: 45832 | AA59: The Filaments, 217 Chapel St, Salford, M3 5PA | AB59: 201, Halogen House, 217 Chapel St, Salford, | AC59: GREP-CoA George Hill & Anna Campbell - 305, Lamp House, 215 Chapel St, Salford, M3 5 | AD59: 507316473 | AF59: Yes | AH59: Amazing space! Felt just like home as soon as we moved in | AJ59: It‚Äôs pretty good | AK59: By far the best place we have lived in Manchester | AL59: 45539.084 | AR59: =COUNTIF(AD:AD,AD59) -> 1
A60: 003Nz00000BGHWPIA5 | B60: 006Nz000009PkDlIAK | C60: Ting Ting Tammy | D60: Cheung | F60: 45789 | G60: 45425 | H60: Lead Tenant | I60: tingcheung821@gmail.com | J60: 07597047792 | K60: Flat 1004, The Headline,Wellington Park Way, Leeds, LS1 4EX | L60: TRUE | M60: New | O60: 45425 | P60: <a href="a1G4J000004jys8" target="_blank">1004,The Headline, Wellington Park Way, Leeds</a> | Q60: Apartment | R60: Tenanted | T60: The Headline | U60: BTR-Regions | V60: George Diamantopoulos | X60: Vicki Turnbull | Y60: Leanne Hargreaves | Z60: 46207 | AA60: The Headline Apts, Wellington Park Way, Leeds | AB60: 310, The Headline, Wellington Park Way, Leeds | AC60: GREP-CoA Ting Ting Tammy Cheung, Wai Yin Vivien Ha - 1004,The Headline, Wellington Park Way, Leeds | AD60: 504881567 | AF60: No | AH60: Fairly new and good condition | AJ60: It‚Äôs pretty good | AK60: Overall experience | AL60: 45515.085 | AR60: =COUNTIF(AD:AD,AD60) -> 1
A61: 003Nz00000BFxxbIAD | B61: 006Nz000009PdNaIAK | C61: Dogukan | D61: Kurt | F61: 45570 | G61: 45387 | H61: Lead Tenant | I61: dogukankurt@gmail.com | J61: 07888494502 | K61: Apartment 530 Enigma Square,414 North Row, Milton Keynes, MK9 2GF | L61: TRUE | M61: New | O61: 45387 | P61: <a href="a1G8d0000005rBO" target="_blank">530 Enigma Square, 414 North Row, MK9 2GF</a> | Q61: Apartment | R61: Tenanted | T61: Enigma Square | U61: BTR-Regions | V61: Tina Viragh | X61: Sarah Norstrom | Y61: Grace Fiske | Z61: 45569 | AA61: Enigma Square - Apartments | AB61: 530 Enigma Square, 414 North Row, MK9 2GF | AC61: GREP-CoA Dogukan Kurt & Alexandra Livesey - 530 Enigma Square, 414 North Row, MK9 2GF | AD61: 504880763 | AF61: Yes | AH61: The view, peacefulness, safety, security, communication, everything is repaired or sorted out relatively quickly. | AJ61: It‚Äôs ok | AK61: It‚Äôs in the centre of town so everything is walking distance, plenty of parking spaces, respectful and nice staff, great common facilities. | AL61: 45477.084 | AR61: =COUNTIF(AD:AD,AD61) -> 1
A62: 003Nz00000B8MWWIA3 | B62: 006Nz000009JbgEIAS | C62: Kit Shan | D62: Ko | F62: 45612 | G62: 45429 | H62: Tenant | I62: sandrashandy@outlook.com | J62: '+852 9090 4213 | K62: Apartment 705 Syren Apartments,Ottinger Close, Salford, M50 3AP | L62: TRUE | M62: New | O62: 45429 | P62: <a href="a1G4J0000025xBm" target="_blank">705 Syren Apt , Ottinger Close, Salford M50</a> | Q62: Apartment | R62: Tenanted | T62: Clippers Quay | U62: BTR-Regions | V62: Helen Bowers | X62: Vicki Turnbull | Y62: Helen Bowers | Z62: 45612 | AA62: Clippers - Syren Apartments | AB62: 705 Syren Apt , Ottinger Close, Salford M50 | AC62: GREP-CoA Anthony Kar Wah Chang & Kit Shan Ko - 705 Syren Apt , Ottinger Close, Salford M50 | AD62: 504413180 | AF62: Yes | AH62: Not bad, always have friendly staff | AJ62: It‚Äôs ok | AK62: Very clean and organised estate,customer service staff always on duty! | AL62: 45519.085 | AR62: =COUNTIF(AD:AD,AD62) -> 1
A63: 003Nz00000B1D9nIAF | B63: 006Nz000009EebYIAS | C63: Lorancee | D63: De Asis | F63: 45584 | G63: 45402 | H63: Lead Tenant | I63: deasis_lorancee@yahoo.com | J63: 9153448462 | K63: Apartment 101 Ambassador Apartments,Waterman Walk, Salford, M50 3AU | L63: TRUE | M63: New | O63: 45402 | P63: <a href="a1G4J0000025yhY" target="_blank">101 Ambassador Apt, Waterman Wlk, Salford M50</a> | Q63: Apartment | R63: Tenanted | T63: Clippers Quay | U63: BTR-Regions | V63: Helen Bowers | X63: Vicki Turnbull | Y63: Helen Bowers | Z63: 45744 | AA63: Clippers - Ambassador Apartments | AB63: 203 Ambassador Apt, Waterman Wlk, Salford M50 | AC63: GREP-CoA L. De Asis, T. Sereno & M. Marrero - 101 Ambassador Apt, Waterman Wlk, Salford M50 | AD63: 503958919 | AF63: Yes | AH63: Very spacious, safe and secure. Added points for the location, views and surroundings. | AJ63: The quality is high | AK63: The apartment and staff are awesome. | AL63: 45492.199 | AR63: =COUNTIF(AD:AD,AD63) -> 1
A64: 003Nz00000AtqxtIAB | B64: 006Nz000009AYmPIAW | C64: Lionel | D64: Sawadogo | F64: 45565 | G64: 45383 | H64: Lead Tenant | I64: lionel.sawadogo@yahoo.fr | J64: '+33 7 67 70 63 54 | K64: Flat 64, Nautilus Apartments,2 Norah Smyth Road, London, E16 1FE | L64: TRUE | M64: New | O64: 45383 | P64: <a href="a1G8d000002QBPU" target="_blank">64 Nautilus Apts, 2 Norah Smyth Rd, London</a> | Q64: Apartment | R64: Tenanted | T64: Nautilus Apartments | U64: BTR-London & SE | V64: Fatma Azakli | X64: Harriet Shaw | Y64: Fatma Azakli | Z64: 45565 | AA64: Nautilus - Apartments | AB64: 64 Nautilus Apts, 2 Norah Smyth Rd, London | AC64: GREP-CoA Lionel Sawadogo and Junior Ebong Moudoubou - 64 Nautilus Apts, 2 Norah Smyth Rd, London | AD64: 503190664 | AF64: Yes | AH64: The proximity to the tube | AJ64: It‚Äôs ok | AK64: The place is brand new and well isolated | AL64: 45473.084 | AR64: =COUNTIF(AD:AD,AD64) -> 1
A65: 003Nz00000AsgHSIAZ | B65: 006Nz0000099JJEIA2 | C65: Gabriel | D65: Azeredo | F65: 45740 | G65: 45376 | H65: Lead Tenant | I65: gabriel_penques@hotmail.com | J65: 07522032989 | K65: Flat 7,43 Chippenham Road, Manchester, M4 6BY | L65: TRUE | M65: New | O65: 45376 | P65: <a href="a1G4J0000025wjj" target="_blank">7, New Islington, 43 Chippenham Road, M4 6BY</a> | Q65: Apartment | R65: Reserved | T65: Tribe | U65: PRS-Regions | V65: Mark Weeden | X65: Vicki Turnbull | Z65: 45627 | AA65: New Islington, Manchester, M4 6BY | AB65: 7, New Islington, 43 Chippenham Road, M4 6BY | AC65: GREP-CoA Gabriel Azeredo and Tatiane Da Lomba - 7, New Islington, 43 Chippenham Road, M4 6BY | AD65: 503182198 | AF65: Yes | AH65: Location/price | AJ65: It‚Äôs pretty good | AK65: Perfect for me | AL65: 45466.084 | AR65: =COUNTIF(AD:AD,AD65) -> 1
A66: 003Nz00000AmTeiIAF | B66: 006Nz0000094Rm6IAE | C66: Anagha Samir | D66: Jadhav | F66: 45776 | G66: 45412 | H66: Tenant | I66: anaghasworld@gmail.com | J66: 07448987100 | K66: 103 Assay Apartments,Station View, Guildford, GU1 4BQ | L66: TRUE | M66: New | O66: 45412 | P66: <a href="a1G8d000002Q2YO" target="_blank">103 Assay Apartments, Station View, Guildford</a> | Q66: Apartment | R66: Tenanted | T66: Argo Apartments | U66: BTR-London & SE | V66: Raihana Parveen | X66: Harriet Shaw | Y66: Holly Boggis | Z66: 45549 | AA66: Argo Apartments | AB66: 103 Argo Apts,4 Silvertown Way,London,E16 1YD | AC66: GREP-CoA S. Chandraknt Jadhav, S Jadhav & A Jadhav - 103 Assay Apartments, Station View, Guildford | AD66: 502728829 | AF66: No | AH66: Location | AJ66: The quality is high | AK66: Need some green space around | AL66: 45502.085 | AR66: =COUNTIF(AD:AD,AD66) -> 1
A67: 003Nz00000Am1SLIAZ | B67: 006Nz0000094YCRIA2 | C67: Samuel | D67: Phelps | F67: 45767 | G67: 45402 | H67: Lead Tenant | I67: samphelps31@gmail.com | J67: 07943369280 | K67: 715,5 Capital Quarter, Tyndall St., Cardiff, CF10 4DT | L67: TRUE | M67: New | O67: 45402 | P67: <a href="a1GNz0000000dNx" target="_blank">715, 5 Capital Quarter, Tyndall St., Cardiff</a> | Q67: Apartment | R67: Tenanted | T67: The Copper Works | U67: BTR-Regions | V67: Karen Meek | X67: Sarah Norstrom | Z67: 45596 | AA67: The Copper Works - Apartments | AB67: 1106, 5 Capital Quarter, Tyndall St., Cardiff | AC67: GREP-CoA Samuel Phelps and Olivia Dumureau - 715, 5 Capital Quarter, Tyndall St., Cardiff | AD67: 502726569 | AF67: Yes | AH67: Location, new build, helpful staff | AJ67: It‚Äôs pretty good | AK67: As we‚Äôve had a pleasant experience so far but have encountered a few things that have caused me to put a slightly lower score. But overall it‚Äôs a good score | AL67: 45492.199 | AR67: =COUNTIF(AD:AD,AD67) -> 1
A68: 003Nz00000Aj9qzIAB | B68: 006Nz0000091BSXIA2 | C68: Benjamin | D68: Richards | F68: 45929 | G68: 45381 | H68: Tenant | I68: benjsrichards@gmail.com | J68: 07594689606 | K68: 1C Shillington Old School,181 Este Road, London, SW11 2TB | L68: TRUE | M68: New | O68: 45381 | P68: <a href="a1G4J0000025zkL" target="_blank">1C Shillington Old School</a> | Q68: Apartment | R68: Tenanted | T68: Shillington Old School | U68: PRS-London & SE | V68: Kathrine Castle | X68: Alexa Byrne | Y68: Gav Rowley | Z68: 45929 | AA68: Shillington Old School | AB68: 1C Shillington Old School | AC68: GREP-CoA Charlie Richards,Daniel Knuckle,Benjamin Richards - 1C Shillington Old School | AD68: 502498438 | AF68: Yes | AH68: No ambiguity with the property when renting | AJ68: It‚Äôs pretty good | AK68: Moving around London is tough and grainger we‚Äôre very transparent with everything | AL68: 45471.085 | AR68: =COUNTIF(AD:AD,AD68) -> 1
A69: 003Nz00000AiLcTIAV | B69: 006Nz0000091uW9IAI | C69: Hanna | D69: Suomalainen | F69: 45773 | G69: 45408 | H69: Lead Tenant | I69: hanna.suomalainen1@gmail.com | J69: 07562758861 | K69: First Floor Flat,40 The Gardens, London, SE22 9QG | L69: TRUE | M69: New | O69: 45408 | P69: <a href="a1G4J0000025vH9" target="_blank">40 The Gardens, FF, London SE22 9QG</a> | Q69: Apartment | R69: Tenanted | T69: Tilt Core | U69: PRS-London & SE | V69: Mitchell Foot | X69: Daisy Stuckey | Y69: Gav Rowley | Z69: 45394 | AA69: The Gardens, 40, London, SE22 9QG | AB69: 40 The Gardens, FF, London SE22 9QG | AC69: GREP-CoA Hanna Suomalainen, Neil Walker - 40 The Gardens, FF, London SE22 9QG | AD69: 502493162 | AF69: Yes | AH69: The area | AJ69: It‚Äôs pretty good | AK69: Havent got help with my repair for months. But I love the flat and area, it's amazing | AL69: 45498.085 | AR69: =COUNTIF(AD:AD,AD69) -> 1
A70: 003Nz00000AIFsTIAX | B70: 006Nz000008kAJCIA2 | C70: Goncalo | D70: Mata | F70: 45786 | G70: 45422 | H70: Lead Tenant | I70: goncalomatarm@gmail.com | J70: 7706244433 | K70: FLAT 109, Gatehouse Apartments,86 East Street, Southampton, SO14 3HP | L70: TRUE | M70: New | O70: 45422 | P70: <a href="a1G4J0000025ySL" target="_blank">109 Gatehouse Apts, 86 East St, Southampton</a> | Q70: Apartment | R70: Tenanted | T70: Gatehouse Apartments | U70: BTR-London & SE | V70: Alice Shaw | X70: Harriet Shaw | Y70: Hayley Fry | Z70: 45418 | AA70: Gatehouse Apts, 86 East St, Southampton | AB70: 109 Gatehouse Apts, 86 East St, Southampton | AC70: GREP-CoA Goncalo Mata, Juliana Nogueira - 109 Gatehouse Apts, 86 East St, Southampton | AD70: 500797090 | AF70: Yes | AH70: I like that it‚Äôs kept cleaned, and it has a gym on site._x000D_ Plus the staff is friendly and very helpful | AK70: Because the apartments are cleaned and new._x000D_ Staff is friendly and always eager to help._x000D_ Has nice amenities like a rooftop and a gym._x000D_ The building gives a nice sense of security with all the doors you have to go through._x000D_ _x000D_ _x000D_ | AL70: 45512.085 | AR70: =COUNTIF(AD:AD,AD70) -> 1
A71: 003Nz00000AI6veIAD | B71: 006Nz000008kBANIA2 | C71: Claire | D71: Boteler | F71: 45566 | G71: 45384 | H71: Lead Tenant | I71: claire.boteler@gmail.com | J71: 6138828642 | K71: 19 Gatehouse Apartments,86 East Street, Southampton, SO14 3HP | L71: TRUE | M71: New | O71: 45384 | P71: <a href="a1G4J0000025yJo" target="_blank">19 Gatehouse Apts, 86 East St, Southampton</a> | Q71: Apartment | R71: Tenanted | T71: Gatehouse Apartments | U71: BTR-London & SE | V71: Alice Shaw | X71: Harriet Shaw | Y71: Hayley Fry | Z71: 46139 | AA71: Gatehouse Apts, 86 East St, Southampton | AB71: 19 Gatehouse Apts, 86 East St, Southampton | AC71: GREP-CoA Claire Boteler - 19 Gatehouse Apts, 86 East St, Southampton | AD71: 500796858 | AF71: No | AH71: In home laundry, the big fridge/freezer. | AJ71: It‚Äôs not great | AK71: Unfriendly front desk. Enquires take long time to get even get acknowledged and get fixed. | AL71: 45474.084 | AR71: =COUNTIF(AD:AD,AD71) -> 1
A72: 003Nz00000AhZhbIAF | B72: 006Nz0000091BSXIA2 | C72: Charlie | D72: Richards | F72: 45929 | G72: 45381 | H72: Lead Tenant | I72: richarc1998@hotmail.com | J72: 07594689606 | K72: 1C Shillington Old School,181 Este Road, London, SW11 2TB | L72: TRUE | M72: New | O72: 45381 | P72: <a href="a1G4J0000025zkL" target="_blank">1C Shillington Old School</a> | Q72: Apartment | R72: Tenanted | T72: Shillington Old School | U72: PRS-London & SE | V72: Kathrine Castle | X72: Alexa Byrne | Y72: Gav Rowley | Z72: 45929 | AA72: Shillington Old School | AB72: 1C Shillington Old School | AC72: GREP-CoA Charlie Richards,Daniel Knuckle,Benjamin Richards - 1C Shillington Old School | AD72: 502490380 | AF72: No | AH72: The flat itself is lovely | AJ72: It‚Äôs ok | AK72: I really like the flat but grainger don‚Äôt really do much. | AL72: 45471.085 | AR72: =COUNTIF(AD:AD,AD72) -> 1
A73: 003Nz00000AhY5YIAV | B73: 006Nz0000090zxcIAA | C73: Abbie | D73: Foxton | F73: 45758 | G73: 45394 | H73: Lead Tenant | I73: a.foxton@outlook.com | J73: 07988992348 | K73: 719 Brook Place,10 Summerfield Street, Sheffield, S11 8DA | L73: TRUE | M73: New | O73: 45394 | P73: <a href="a1G4J0000025zV3" target="_blank">719, Brook Place Apts, Sheffield, S11 8DA</a> | Q73: Apartment | R73: Tenanted | T73: Brook Place | U73: BTR-Regions | V73: Emma Cramer-Mitchell | X73: Vicki Turnbull | Y73: Leanne Hargreaves | Z73: 45758 | AA73: Brook Place Apts, 10 Summerfield Street, Shef | AB73: 719, Brook Place Apts, Sheffield, S11 8DA | AC73: GREP-CoA Abbie Foxton - 719, Brook Place Apts, Sheffield, S11 8DA | AD73: 502489468 | AF73: Yes | AH73: The terraces. | AJ73: It‚Äôs ok | AK73: Good amenities, community and reception are responsive and friendly. | AL73: 45484.085 | AR73: =COUNTIF(AD:AD,AD73) -> 1
A74: 003Nz00000AeDX7IAN | B74: 006Nz000008yoBsIAI | C74: Nabela | D74: Ahmed | F74: 45556 | G74: 45373 | H74: Lead Tenant | I74: nabela@me.com | J74: 07444771417 | K74: Apartment 435 Enigma Square,414 North Row, Milton Keynes, MK9 2GF | L74: TRUE | M74: New | O74: 45373 | P74: <a href="a1G8d0000005r6O" target="_blank">435 Enigma Square, 414 North Row, MK9 2GF</a> | Q74: Apartment | R74: Tenanted | T74: Enigma Square | U74: BTR-Regions | V74: Tina Viragh | X74: Sarah Norstrom | Y74: Grace Fiske | Z74: 45556 | AA74: Enigma Square - Apartments | AB74: 437 Enigma Square, 414 North Row, MK9 2GF | AC74: GREP-CoA Nabela Ahmed, Abdul Hamid Ahmed. - 435 Enigma Square, 414 North Row, MK9 2GF | AD74: 502262960 | AF74: Yes | AH74: That it‚Äôs open plan and spacious. A great sized room. | AJ74: It‚Äôs pretty good | AK74: It‚Äôs been a great experience. Love the community living aspect too! | AL74: 45463.084 | AR74: =COUNTIF(AD:AD,AD74) -> 1
A75: 003Nz00000AEc2sIAD | B75: 006Nz000008hhQ7IAI | C75: Olanrewaju | D75: Adu | F75: 45755 | G75: 45391 | H75: Lead Tenant | I75: adulanrex@gmail.com | J75: 07760915435 | K75: Apartment 34, Gilders Yard,14 Great Hampton Street, Birmingham, B18 6ER | L75: TRUE | M75: New | O75: 45391 | P75: <a href="a1G8d0000004c6Y" target="_blank">34, Gilders Yard, 14 Great Hampton St, Birm</a> | Q75: Apartment | R75: Tenanted | T75: Gilders Yard | U75: BTR-Regions | V75: Lewis Morris | X75: Vicki Turnbull | Y75: Neil Persad | Z75: 45864 | AA75: Gilders Yard - Apartments A-C | AB75: 7, Gilders Yard, 14 Great Hampton St, Birm | AC75: GREP-CoA Olanrewaju Adu & Oreoluwa Ajayi - 34, Gilders Yard, 14 Great Hampton St, Birm | AD75: 500565435 | AF75: Yes | AK75: It‚Äôs beautiful here | AL75: 45481.085 | AR75: =COUNTIF(AD:AD,AD75) -> 1
A76: 003Nz00000AdadmIAB | B76: 006Nz000008yKH2IAM | C76: Suroush | D76: Lisle-Pourzyaie | F76: 45773 | G76: 45409 | H76: Lead Tenant | I76: suroush10@yahoo.co.uk | J76: 07975705557 | K76: Flat 205, Pin Yard,11 Sweet Street, Leeds, LS11 9FA | L76: TRUE | M76: New | O76: 45409 | P76: <a href="a1G8d0000004XYz" target="_blank">205 Pin Yard, 11 Sweet Street, Leeds</a> | Q76: Apartment | R76: Tenanted | T76: Pin Yard | U76: BTR-Regions | V76: Ruth Friend | X76: Vicki Turnbull | Y76: Ruth Friend | Z76: 45399 | AA76: Pin Yard - Apartments | AB76: 1 Pin Yard, 11 Sweet Street, Leeds. | AC76: GREP-CoA Suroush Lisle-Pourzyaie, Patrick Cullen - 205 Pin Yard, 11 Sweet Street, Leeds | AD76: 502259729 | AF76: No | AH76: The ease when moving in | AJ76: It‚Äôs not great | AK76: It‚Äôs easy, fairly priced and there are many pros such as the team at the front desk._x000D_ Negatives are the bed is extremely uncomfortable, when the handy man comes it‚Äôs when it‚Äôs suitable day for him if he‚Äôs around, walls are slightly thin so can hear | AL76: 45499.086 | AR76: =COUNTIF(AD:AD,AD76) -> 1
A77: 003Nz000009vqJMIAY | B77: 006Nz000008VULPIA4 | C77: James | D77: Dixon | F77: 45772 | G77: 45408 | H77: Lead Tenant | I77: jwdixonmail@gmail.com | J77: 07764864935 | K77: 3,82 Upper Allen St, Sheffield, S3 7HP | L77: TRUE | M77: New | O77: 45408 | P77: <a href="a1GNz0000000vMT" target="_blank">3 Nickel Pl, Well Meadow Drive, Sheffield</a> | Q77: Apartment | R77: Tenanted | T77: The Tilt Works | U77: BTR-Regions | X77: Vicki Turnbull | Y77: Leanne Hargreaves | Z77: 45772 | AA77: The Tilt Works - Nickel Place | AB77: 3 Nickel Pl, Well Meadow Drive, Sheffield | AC77: GREP-CoA James Dixon - 3 Nickel Pl, Well Meadow Drive, Sheffield | AD77: 499323568 | AF77: Yes | AH77: The new appliances, kitchen, carpets etc. Easy to keep clean and maintain the apartment. | AJ77: It‚Äôs pretty good | AK77: Because of the price. The home itself is a 9 due to its quality. Would be a 10 if it was larger or had better on-street parking availability (or cheaper car park access). The price of the rent and the high car park access price bring the score down t | AL77: 45498.085 | AR77: =COUNTIF(AD:AD,AD77) -> 1
A78: 003Nz000009V1QvIAK | B78: 006Nz000008CZALIA4 | C78: Hassan | D78: Khan | F78: 45770 | G78: 45406 | H78: Lead Tenant | I78: hassan.khan0296@gmail.com | J78: 07438563809 | K78: 310,5 Capital Quarter, Tyndall St., Cardiff, CF10 4DS | L78: TRUE | M78: New | O78: 45406 | P78: <a href="a1GNz0000000cV7" target="_blank">310, 5 Capital Quarter, Tyndall St., Cardiff</a> | Q78: Apartment | R78: Tenanted | T78: The Copper Works | U78: BTR-Regions | V78: Karen Meek | X78: Sarah Norstrom | Z78: 45969 | AA78: The Copper Works - Apartments | AB78: 404, 5 Capital Quarter, Tyndall St., Cardiff | AC78: GREP-CoA Hassan Khan and Anum Naz - 310, 5 Capital Quarter, Tyndall St., Cardiff | AD78: 497167295 | AF78: Yes | AH78: The communal area :) | AJ78: It‚Äôs pretty good | AK78: The standard of living is really great in very nice price. | AL78: 45496.085 | AR78: =COUNTIF(AD:AD,AD78) -> 1
A79: 003Nz000009TBisIAG | B79: 006Nz000008Al2fIAC | C79: Deborah | D79: Green | F79: 45534 | G79: 45351 | H79: Lead Tenant | I79: deborahgreen94@hotmail.co.uk | J79: 07572145351 | K79: 205,84 Upper Allen St, Sheffield, S3 7NY | L79: TRUE | M79: New | O79: 45351 | P79: <a href="a1GNz0000000wf8" target="_blank">205, 84 Upper Allen St, Sheffield</a> | Q79: Apartment | R79: Tenanted | T79: The Tilt Works | U79: BTR-Regions | X79: Vicki Turnbull | Y79: Leanne Hargreaves | Z79: 45772 | AA79: The Tilt Works - Nickel Place | AB79: 3 Nickel Pl, Well Meadow Drive, Sheffield | AC79: GREP-CoA Deborah Green - 205, 84 Upper Allen St, Sheffield | AD79: 496940925 | AF79: No | AH79: I like that everything is new and modern. It is a comfortable place to live. | AJ79: The quality is high | AK79: I feel happy here & have no issues with my flat. However it is expensive. There aren't many social events & the communal areas are not open all the time, or open to book whenever. After 8 on a Saturday is when I am most likely to have people around. | AL79: 45441.085 | AR79: =COUNTIF(AD:AD,AD79) -> 1
A80: 003Nz000009T8UzIAK | B80: 006Nz000008AdBgIAK | C80: Rebecca | D80: Wilson | F80: 45592 | G80: 45409 | H80: Lead Tenant | I80: rebecca.leyla.wilson@gmail.com | J80: 07933563474 | K80: 1213,5 Capital Quarter, Tyndall St., Cardiff, CF10 4EF | L80: TRUE | M80: New | O80: 45409 | P80: <a href="a1GNz0000000eGn" target="_blank">1213, 5 Capital Quarter, Tyndall St., Cardiff</a> | Q80: Apartment | R80: Tenanted | T80: The Copper Works | U80: BTR-Regions | V80: Karen Meek | X80: Sarah Norstrom | Z80: 45594 | AA80: The Copper Works - Apartments | AB80: 1213, 5 Capital Quarter, Tyndall St., Cardiff | AC80: GREP-CoA Rebecca Wilson and Daniel Mapatac - 1213, 5 Capital Quarter, Tyndall St., Cardiff | AD80: 496941517 | AF80: Yes | AH80: The co-working space and the pool table. In the flat, I like the utility room and kitchen utilities. The reception team are also great and really helpful. | AJ80: It‚Äôs pretty good | AK80: Overall, it's a great place to live, the only down scoring is for the AC. | AL80: 45499.086 | AR80: =COUNTIF(AD:AD,AD80) -> 1
A81: 003Nz000009t4sGIAQ | B81: 006Nz000008TNSvIAO | C81: Christopher | D81: Uzaizi | F81: 45738 | G81: 45374 | H81: Tenant | I81: uzaizi@live.com | J81: 07388800754 | K81: Apartment 29, Juniper House,106 Phoebe Street, Salford, M5 3GZ | L81: TRUE | M81: New | O81: 45374 | P81: <a href="a1G4J0000025wu7" target="_blank">Flat 29, Juniper House, Salford, M5</a> | Q81: Apartment | R81: Tenanted | T81: Resi | U81: PRS-Regions | V81: Louise Spooner | X81: Vicki Turnbull | Y81: Lynn Robson | Z81: 45550 | AA81: Juniper House, Salford, M5 | AB81: Flat 12, Juniper House, Salford, M5 | AC81: GREP-CoA Alexander Uzaizi & Christopher Uzaizi - Flat 29, Juniper House, Salford, M5 | AD81: 499097771 | AF81: Yes | AH81: Value for money | AJ81: It‚Äôs ok | AK81: I'd mention my experience and let them decide | AL81: 45464.084 | AR81: =COUNTIF(AD:AD,AD81) -> 1
A82: 003Nz000009spDGIAY | B82: 006Nz00000ChN7KIAV | C82: Nathan | D82: Keeble | F82: 45838 | G82: 45481 | H82: Lead Tenant | I82: nathankeeble1@gmail.com | J82: 07508618775 | K82: Apartment 1102, Ingot Place,84 Upper Allen Street, Sheffield, S3 7QE | L82: TRUE | M82: New | O82: 45481 | P82: <a href="a1GNz0000000zGP" target="_blank">1102, 84 Upper Allen St, Sheffield</a> | Q82: Apartment | R82: Tenanted | T82: The Tilt Works | U82: BTR-Regions | X82: Vicki Turnbull | Y82: Leanne Hargreaves | Z82: 45845 | AA82: The Tilt Works - Ingot Place | AB82: 1102, 84 Upper Allen St, Sheffield | AC82: GREP-CoA Nathan Keeble and Eve Butterell - 1102, 84 Upper Allen St, Sheffield | AD82: 499095891 | AH82: The view | AJ82: It‚Äôs not great | AL82: 45571.084 | AR82: =COUNTIF(AD:AD,AD82) -> 1
A83: 003Nz000009pKYzIAM | B83: 006Nz000007zVECIA2 | C83: Deogracias Gonzalez | D83: Moreno | F83: 45727 | G83: 45363 | H83: Tenant | I83: deogracias.gonzalezm@gmail.com | J83: '+34640364408 | K83: 1001 The Headline,1 Wellington Way, Leeds, LS1 4EX | L83: TRUE | M83: New | O83: 45363 | P83: <a href="a1G4J000004jyfy" target="_blank">1001,The Headline, Wellington Park Way, Leeds</a> | Q83: Apartment | R83: Tenanted | T83: The Headline | U83: BTR-Regions | V83: George Diamantopoulos | X83: Vicki Turnbull | Y83: Leanne Hargreaves | Z83: 45727 | AA83: The Headline Apts, Wellington Park Way, Leeds | AB83: 1001,The Headline, Wellington Park Way, Leeds | AC83: GREP-CoA Raquel Oeo Farelo, Deogracias Gonzalez Moreno - 1001,The Headline, Wellington Park Way, Leeds | AD83: 498842392 | AF83: Yes | AH83: The Gym and Wellness Room | AJ83: It‚Äôs pretty good | AK83: Good services, good attention from reception, nice apartment | AL83: 45453.085 | AR83: =COUNTIF(AD:AD,AD83) -> 1
A84: 003Nz000009p61NIAQ | B84: 006Nz000008QemoIAC | C84: Sophie k | D84: Hill | F84: 45773 | G84: 45409 | H84: Lead Tenant | I84: sophie.k.hill@warwick.ac.uk | J84: 07443853776 | K84: 302,5 Capital Quarter, Tyndall St., Cardiff, CF10 4DS | L84: TRUE | M84: New | O84: 45409 | P84: <a href="a1GNz0000000cF0" target="_blank">302, 5 Capital Quarter, Tyndall St., Cardiff</a> | Q84: Apartment | R84: Tenanted | T84: The Copper Works | U84: BTR-Regions | V84: Karen Meek | X84: Sarah Norstrom | Z84: 45773 | AA84: The Copper Works - Apartments | AB84: 302, 5 Capital Quarter, Tyndall St., Cardiff | AC84: GREP-CoA Sophie Hill - 302, 5 Capital Quarter, Tyndall St., Cardiff | AD84: 498840696 | AF84: Yes | AH84: The property is an excellent standard - clean, high quality fittings and secure! I can‚Äôt really fault my apartment at all it‚Äôs definitely the best quality place I‚Äôve rented and it‚Äôs definitely worth the money I pay for rent. | AJ84: The quality is high | AK84: Great place to stay and worth the money when you compare it to everything else out there. Building is clean and importantly I feel safe due to multiple fob access entry points. Also the reception collecting parcels for you when I am away is great. | AL84: 45499.086 | AR84: =COUNTIF(AD:AD,AD84) -> 1
A85: 003Nz000009JKh0IAG | B85: 006Nz0000084rKUIAY | C85: Safiyah | D85: Malik | F85: 45742 | G85: 45377 | H85: Lead Tenant | I85: safmalik786@msn.com | J85: 07581225510 | K85: 1103 Pin Yard,11 Sweet Street, Leeds, LS11 9FD | L85: TRUE | M85: New | O85: 45377 | P85: <a href="a1G8d0000004Xb9" target="_blank">1103 Pin Yard, 11 Sweet Street, Leeds</a> | Q85: Apartment | R85: Tenanted | T85: Pin Yard | U85: BTR-Regions | V85: Ruth Friend | X85: Vicki Turnbull | Y85: Ruth Friend | Z85: 45741 | AA85: Pin Yard - Apartments | AB85: 1103 Pin Yard, 11 Sweet Street, Leeds | AC85: GREP-CoA Safiyah Malik - 1103 Pin Yard, 11 Sweet Street, Leeds | AD85: 495975289 | AF85: No | AH85: Convenient location_x000D_ Has secure parking underground _x000D_ Nice apartment - kitchen/bathroom etc | AJ85: It‚Äôs pretty good | AK85: I feel like my previous apartment was larger 1 bed when I was with Dandara Living | AL85: 45467.084 | AR85: =COUNTIF(AD:AD,AD85) -> 1
A86: 003Nz000009j9egIAA | B86: 006Nz0000081yqLIAQ | C86: Anna | D86: McDonald | F86: 45769 | G86: 45405 | H86: Tenant | I86: anna.mcdonald@pleo.io | J86: 07757057778 | K86: 41 Ability Plaza,Arbutus Street, London, E8 4DT | L86: TRUE | M86: New | O86: 45405 | P86: <a href="a1G4J0000025zrR" target="_blank">Flat 41 Ability Plaza, London, E8</a> | Q86: Apartment | R86: Tenanted | T86: Ability Plaza | U86: PRS-London & SE | V86: Kathrine Castle | X86: Daisy Stuckey | Y86: Gav Rowley | Z86: 45769 | AA86: Ability Plaza | AB86: Flat 41 Ability Plaza, London, E8 | AC86: GREP-CoA Freddie Higgs & Anna McDonald - Flat 41 Ability Plaza, London, E8 | AD86: 498099105 | AF86: Yes | AH86: '- beautiful flats and open space _x000D_ - all functions in the house work well eg. shower, oven. No problems! | AK86: Everything is great bar security. | AL86: 45495.085 | AR86: =COUNTIF(AD:AD,AD86) -> 1
A87: 003Nz000009IjHgIAK | B87: 006Nz0000084CE7IAM | C87: Matilda | D87: Howells | F87: 46116 | G87: 45387 | H87: Lead Tenant | I87: matildajanehowells@icloud.com | J87: 07496275666 | K87: 1K Shillington Old School,181 Este Road, London, SW11 2TB | L87: TRUE | M87: New | O87: 45387 | P87: <a href="a1G4J000002602A" target="_blank">1K Shillington Old School</a> | Q87: Apartment | R87: Tenanted | T87: Shillington Old School | U87: PRS-London & SE | V87: Kathrine Castle | X87: Alexa Byrne | Y87: Gav Rowley | Z87: 45726 | AA87: Shillington Old School | AB87: 2G Shillington Old School | AC87: GREP-CoA Matilda Howells & William Sethna - 1K Shillington Old School | AD87: 495963263 | AF87: Yes | AH87: The location, the sense_x000D_ Of community | AJ87: It‚Äôs pretty good | AK87: People are easy to get hold of and the whole process of renting was straightforward. | AL87: 45477.084 | AR87: =COUNTIF(AD:AD,AD87) -> 1
A88: 003Nz000009g4d9IAA | B88: 006Nz000008KZbOIAW | C88: Deborah Princess | D88: Ekpu | F88: 45537 | G88: 45353 | H88: Lead Tenant | I88: princessdeborah1234@gmail.com | J88: 07782175459 | K88: Apartment 107, Gilders Yard,14 Great Hampton Street, Birmingham, B18 6ER | L88: TRUE | M88: New | O88: 45353 | P88: <a href="a1G8d0000004c81" target="_blank">107, Gilders Yard, 14 Great Hampton St Birm</a> | Q88: Apartment | R88: Tenanted - Up for Renewal | T88: Gilders Yard | U88: BTR-Regions | V88: Lewis Morris | X88: Vicki Turnbull | Y88: Neil Persad | Z88: 45536 | AA88: Gilders Yard - Apartments A-C | AB88: 107, Gilders Yard, 14 Great Hampton St Birm | AC88: GREP-CoA Deborah Ekpu and Julius Djebrughwe - 107, Gilders Yard, 14 Great Hampton St Birm | AD88: 497874001 | AF88: Yes | AH88: It‚Äôs homely and comfortable | AJ88: The quality is high | AK88: It‚Äôs homely and friendly | AL88: 45443.084 | AR88: =COUNTIF(AD:AD,AD88) -> 1
A89: 003Nz000009flykIAA | B89: 006Nz000008KDxWIAW | C89: Joe | D89: Gillespie | F89: 45538 | G89: 45355 | H89: Lead Tenant | I89: joe.gillespie14@gmail.com | J89: 07743452917 | K89: 26 Garter House,12 Market Street, Newbury, RG14 5ER | L89: TRUE | M89: New | O89: 45355 | P89: <a href="a1G8d0000004qoL" target="_blank">26 Garter House, 12 Market Street, Newbury</a> | Q89: Apartment | R89: Tenanted - Up for Renewal | T89: Weavers Yard | U89: BTR-London & SE | V89: Kimberley Pope | X89: Harriet Shaw | Y89: Daniel Hind | Z89: 45538 | AA89: Weavers Yard - Garter House | AB89: 26 Garter House, 12 Market Street, Newbury | AC89: GREP-CoA Joe Gillespie - 26 Garter House, 12 Market Street, Newbury | AD89: 497872689 | AF89: Yes | AH89: Nice and new | AJ89: The quality is high | AK89: Good place, good team always on call just bit expensive on the renting side | AL89: 45445.084 | AR89: =COUNTIF(AD:AD,AD89) -> 1
A90: 003Nz000009EJiLIAW | B90: 006Nz000007uQwgIAE | C90: Hamid Imam | D90: Siddiqui | F90: 45541 | G90: 45358 | H90: Tenant | I90: hamidimam87@hotmail.com | J90: 07867218109 | K90: Apartment 213 Abbeville Apartments,37 London Road, Barking, IG11 8FW | L90: TRUE | M90: New | O90: 45358 | P90: <a href="a1G4J0000025wxV" target="_blank">Apt 213, Abbeville Apts, 37 London Rd, Barkin</a> | R90: Tenanted | T90: Abbeville Apartments | U90: BTR-London & SE | V90: Raihana Parveen | X90: Harriet Shaw | Y90: Mohammed Khan | Z90: 45419 | AA90: Abbeville Apartments, 37 London Road, Barking | AB90: Apt 213, Abbeville Apts, 37 London Rd, Barkin | AC90: GREP-CoA Delna Dotivala, Hamid Imam Siddiqui - Apt 213, Abbeville Apts, 37 London Rd, Barkin | AD90: 495515101 | AF90: Yes | AH90: The view from balcony and serene nature surrounded by park. | AJ90: The quality is high | AK90: The team and the front office people are very responsive and good at providing guidance for any issues or concerns. | AL90: 45448.085 | AR90: =COUNTIF(AD:AD,AD90) -> 1
A91: 003Nz0000095KCDIA2 | B91: 006Nz000007tRgLIAU | C91: Nikos | D91: Tokos | F91: 45748 | G91: 45383 | H91: Lead Tenant | I91: nikos.tokos@hotmail.co.uk | J91: 07487821357 | K91: Apartment 129, Gilders Yard,14 Great Hampton Street, Birmingham, B18 6ER | L91: TRUE | M91: New | O91: 45383 | P91: <a href="a1G8d0000004cBn" target="_blank">129, Gilders Yard, 14 Great Hampton St Birm</a> | Q91: Apartment | R91: Tenanted | T91: Gilders Yard | U91: BTR-Regions | V91: Lewis Morris | X91: Vicki Turnbull | Y91: Neil Persad | Z91: 45747 | AA91: Gilders Yard - Apartments A-C | AB91: 129, Gilders Yard, 14 Great Hampton St Birm | AC91: GREP-CoA Nikos Tokos & Amy Johnson - 129, Gilders Yard, 14 Great Hampton St Birm | AD91: 495065153 | AF91: Yes | AH91: The furnishing and apartment | AJ91: The quality is high | AK91: I am extremely happy so far with the apartment | AL91: 45473.084 | AR91: =COUNTIF(AD:AD,AD91) -> 1
A92: 003Nz000008vhreIAA | B92: 006Nz000007nbKCIAY | C92: Marcelo Ribeiro | D92: Meireles | F92: 46125 | G92: 45395 | H92: Lead Tenant | I92: mrmeireles@gmail.com | J92: 07868618921 | K92: 2001, Neon House,207 Chapel Street, Salford, M3 5PH | L92: TRUE | M92: New | O92: 45395 | P92: <a href="a1G4J0000025yT2" target="_blank">2001, Neon House, 207 Chapel St, Salford, M3</a> | Q92: Apartment | R92: Tenanted | T92: The Filaments | U92: BTR-Regions | V92: Samantha Lancaster | X92: Vicki Turnbull | Y92: Samantha Lancaster | Z92: 45392 | AA92: The Filaments, 207 Chapel St, Salford, M3 5PF | AB92: 2001, Neon House, 207 Chapel St, Salford, M3 | AC92: GREP-CoA Marcelo Ribeiro Meireles - 2001, Neon House, 207 Chapel St, Salford, M3 | AD92: 494187381 | AF92: Yes | AH92: It's new and the staff is great. | AJ92: It‚Äôs ok | AK92: Policy is extremely rigid about me trying to improve the apartment, like changing wall outlets in order to get internet sockets where I need them. | AL92: 45485.085 | AR92: =COUNTIF(AD:AD,AD92) -> 1
A93: 003Nz000008st1LIAQ | B93: 006Nz000007kjZFIAY | C93: Bethany | D93: Carter | F93: 45543 | G93: 45360 | H93: Lead Tenant | I93: beth.c.carter3@gmail.com | J93: 07528725108 | K93: 911 The Barnum,23 Queens Road, Nottingham, NG2 3FU | L93: TRUE | M93: New | O93: 45360 | P93: <a href="a1GNz00000016o9" target="_blank">911 The Barnum, 23 Queens Road, Nottingham</a> | Q93: Apartment | R93: Tenanted | T93: The Barnum | U93: BTR-Regions | V93: Natasha Burns | X93: Vicki Turnbull | Y93: Leanne Hargreaves | Z93: 45543 | AA93: The Barnum - Apartments | AB93: 911 The Barnum, 23 Queens Road, Nottingham | AC93: GREP-CoA Bethany Carter, Alexander Bragg & Katharine Fairbairn - 911 The Barnum, 23 Queens Road, Nottingham | AD93: 493968800 | AF93: No | AJ93: It‚Äôs pretty good | AK93: Clean apartments, good quality furniture, nice communal spaces. Reception friendly. Every thing is fixed quickly. Lost points for parking. | AL93: 45450.085 | AR93: =COUNTIF(AD:AD,AD93) -> 1
A94: 003Nz000008r20mIAA | B94: 006Nz000007k262IAA | C94: Ankita | D94: Gupta | F94: 45567 | G94: 45385 | H94: Tenant | I94: ankita.105055@gmail.com | J94: 07405772522 | K94: Apartment 207 Abbeville Apartments,37 London Road, Barking, IG11 8FW | L94: TRUE | M94: New | O94: 45385 | P94: <a href="a1G4J0000025x4t" target="_blank">Apt 207, Abbeville Apts, 37 London Rd, Barkin</a> | Q94: Apartment | R94: Tenanted | T94: Abbeville Apartments | U94: BTR-London & SE | V94: Raihana Parveen | X94: Harriet Shaw | Y94: Mohammed Khan | Z94: 45366 | AA94: Abbeville Apartments, 37 London Road, Barking | AB94: Apt 207, Abbeville Apts, 37 London Rd, Barkin | AC94: GREP-CoA Sanu Gupta and Ankita Gupta - Apt 207, Abbeville Apts, 37 London Rd, Barkin | AD94: 493965373 | AF94: Yes | AH94: Great location and well maintained apartment. | AJ94: The quality is high | AK94: There should always be some scope of improvement even when its best .üòä | AL94: 45475.084 | AR94: =COUNTIF(AD:AD,AD94) -> 1
A95: 003Nz000008PAFjIAO | B95: 006Nz000007PEn3IAG | C95: Caroline | D95: Taylor | F95: 46446 | G95: 45352 | H95: Lead Tenant | I95: carytaylor@btinternet.com | J95: 07745598809 | K95: 403 Assay Apartments,Station View, Guildford, GU1 4BQ | L95: TRUE | M95: New | O95: 45352 | P95: <a href="a1G8d000002Q2cz" target="_blank">403 Assay Apartments, Station View, Guildford</a> | Q95: Apartment | R95: Tenanted | T95: The Mint | U95: BTR-London & SE | V95: Kimberley Pope | X95: Harriet Shaw | Z95: 46446 | AA95: The Mint - Assay Apartments. | AB95: 403 Assay Apartments, Station View, Guildford | AC95: GREP-CoA Caroline Taylor, John Taylor & Louis Taylor - 403 Assay Apartments, Station View, Guildford | AD95: 492007328 | AF95: Yes | AH95: Cleanliness and location | AJ95: It‚Äôs pretty good | AK95: Easy process. Good concierge | AL95: 45442.084 | AR95: =COUNTIF(AD:AD,AD95) -> 1
A96: 003Nz000008LXapIAG | B96: 006Nz000007MWGhIAO | C96: Ana Maria | D96: Costescu | F96: 45543 | G96: 45331 | H96: Lead Tenant | I96: ana.costescu@allianz-trade.com | J96: '+40747203174 | K96: 44 Nautilus Apts,2 Norah Smyth Rd, London, E16 1FE | L96: TRUE | M96: New | O96: 45331 | P96: <a href="a1G8d000002QBNs" target="_blank">44 Nautilus Apts, 2 Norah Smyth Rd, London</a> | Q96: Apartment | R96: On the Market Available to View | T96: Nautilus Apartments | U96: BTR-London & SE | V96: Fatma Azakli | X96: Harriet Shaw | Y96: Fatma Azakli | Z96: 45595 | AA96: Nautilus - Apartments | AB96: 44 Nautilus Apts, 2 Norah Smyth Rd, London | AC96: GREP-CoA Ana Maria Costescu & Nicolae - Alexandru Costescu - 44 Nautilus Apts, 2 Norah Smyth Rd, London | AD96: 491803648 | AF96: Yes | AH96: nice and natural, not so much furniture, but exactly what you need | AJ96: It‚Äôs pretty good | AK96: can`t understand the questions being honest | AL96: 45421.085 | AR96: =COUNTIF(AD:AD,AD96) -> 1
A97: 003Nz000008l4tFIAQ | B97: 006Nz000007bFX7IAM | C97: DIMITRIOS | D97: DIAMANTIDIS | F97: 46085 | G97: 45356 | H97: Tenant | I97: diamantidis.dim@gmail.com | J97: 07821332195 | K97: 59 Nautilus Apts,2 Norah Smyth Rd, London, E16 1FE | L97: TRUE | M97: New | O97: 45356 | P97: <a href="a1G8d000002QBPA" target="_blank">59 Nautilus Apts, 2 Norah Smyth Rd, London</a> | Q97: Apartment | R97: Tenanted | T97: Nautilus Apartments | U97: BTR-London & SE | V97: Fatma Azakli | X97: Harriet Shaw | Y97: Fatma Azakli | Z97: 46085 | AA97: Nautilus - Apartments | AB97: 59 Nautilus Apts, 2 Norah Smyth Rd, London | AC97: GREP-CoA Aikaterini Antoniou, Dimitrios Diamantidis - 59 Nautilus Apts, 2 Norah Smyth Rd, London | AD97: 493541081 | AF97: Yes | AH97: Great new build. | AJ97: It‚Äôs pretty good | AK97: Great team. Pleasant experience. | AL97: 45446.084 | AR97: =COUNTIF(AD:AD,AD97) -> 1
A98: 003Nz000008frBuIAI | B98: 006Nz000007bLpTIAU | C98: Oliver | D98: Boag | F98: 45744 | G98: 45380 | H98: Lead Tenant | I98: ollieboag1998@hotmail.co.uk | J98: 07940701987 | K98: Apartment 203 Ambassador Apartments,Waterman Walk, Salford, M50 3AU | L98: TRUE | M98: New | O98: 45380 | P98: <a href="a1G4J0000025yvJ" target="_blank">203 Ambassador Apt, Waterman Wlk, Salford M50</a> | Q98: Apartment | R98: Tenanted | T98: Clippers Quay | U98: BTR-Regions | V98: Helen Bowers | X98: Vicki Turnbull | Y98: Helen Bowers | Z98: 45723 | AA98: Clippers - Torrens Apartments | AB98: 707 Torrens Apt, Waterman Wlk, Salford M50 | AC98: GREP-CoA Oliver Boag, William Bell and Gugulabazali Ndlovu - 203 Ambassador Apt, Waterman Wlk, Salford M50 | AD98: 493324711 | AF98: No | AH98: The open space and modern designs. | AJ98: It‚Äôs pretty good | AK98: I think it would be great to live amongst a community of friends and itd make it the building feel like home | AL98: 45470.084 | AR98: =COUNTIF(AD:AD,AD98) -> 1
A99: 003Nz000008e0xaIAA | B99: 006Nz000007aBXFIA2 | C99: Oluwafunke | D99: Jegede | F99: 45524 | G99: 45342 | H99: Lead Tenant | I99: oluwafunkejegede@gmail.com | J99: 07901138871 | K99: Apartment 111 The Condor,1 Springwell Square, Derby, DE1 1FB | L99: TRUE | M99: New | O99: 45342 | P99: <a href="a1G8d000002QBWa" target="_blank">111 The Condor, 1 Springwell Sq</a> | Q99: Apartment | R99: Tenanted | T99: The Condor | U99: BTR-Regions | V99: Jessica Coates | X99: Vicki Turnbull | Y99: Leanne Hargreaves | Z99: 45971 | AA99: The Condor - Apartments | AB99: 111 The Condor, 1 Springwell Sq | AC99: GREP-CoA Oluwafunke Jegede - 111 The Condor, 1 Springwell Sq | AD99: 493318322 | AF99: Yes | AH99: It‚Äôs a beautiful & condusive apartment that helps you navigate to other places easily. | AJ99: It‚Äôs pretty good | AK99: It‚Äôs a conducive apartment. | AL99: 45432.085 | AR99: =COUNTIF(AD:AD,AD99) -> 1
A100: 003Nz0000084ZvTIAU | B100: 006Nz000007B58eIAC | C100: Sajid Nawaz | D100: Khan | F100: 46085 | G100: 45355 | H100: Lead Tenant | I100: hello@snkhan.co.uk | J100: 07980742284 | K100: 608 Brook Place,10 Summerfield Street, Sheffield, S11 8DA | L100: TRUE | M100: New | O100: 45355 | P100: <a href="a1G4J0000025zN9" target="_blank">608, Brook Place Apts, Sheffield, S11 8DA</a> | Q100: Apartment | R100: Tenanted | T100: Brook Place | U100: BTR-Regions | V100: Emma Cramer-Mitchell | X100: Vicki Turnbull | Y100: Leanne Hargreaves | Z100: 45734 | AA100: Brook Place Apts, 10 Summerfield Street, Shef | AB100: 122, Brook Place Apts, Sheffield, S11 8BR | AC100: GREP-CoA Sajid Nawaz Khan - 608, Brook Place Apts, Sheffield, S11 8DA | AD100: 490466208 | AF100: Yes | AH100: Nicely proportioned rooms, outstanding concierge service. Always feel safe. Neighbours are quiet and considerate. | AJ100: It‚Äôs ok | AK100: I love my flat. | AL100: 45445.084 | AR100: =COUNTIF(AD:AD,AD100) -> 1
...

Sheet Mnth 3 TP survey records in SF
A1: Id | B1: Name | C1: Contact_ID_Mapped__c | D1: Opportunity_ID_Mapped__c | E1: RecordType.Name | F1: CreatedDate | G1: CreatedBy.Name | H1: Opportunity_Name__c | I1: LastModifiedBy.Name | J1: LastModifiedDate | K1: Unit_Address__c | L1: Opportunity_ID_Mapped__r.Name | M1: Opportunity_ID_Mapped__r.Primary_Offer__r.Unit__c | N1: Opportunity_ID_Mapped__r.Primary_Offer__r.Unit__r.Name | O1: Opportunity_ID_Mapped__r.Primary_Offer__r.Unit__r.Display_Address__c | P1: Unit check | Q1: Count of same name | R1: count of same opp name | S1: Count of same opp id
A2: a1kNz000004e0v3IAA | B2: 539720258 | C2: 003Nz00000JKmAQIA1 | D2: 006Nz00000F6dJ1IAJ | E2: Month 3: How can we make things better (Specification) Survey | F2: 2024-12-05T23:30:17.000+0000 | G2: marketing cloud connector | H2: GREP-CoA Debora Marques Ferreira Cunha, Renato Jose Valerio - Apt 89, Kings Dock Mill, Liverpool, L1 | I2: marketing cloud connector | J2: 2024-12-05T23:30:17.000+0000 | K2: <a href="a1G4J0000025yHK" target="_blank">Apt 89, Kings Dock Mill, Liverpool, L1</a> | L2: GREP-CoA Debora Marques Ferreira Cunha, Renato Jose Valerio - Apt 89, Kings Dock Mill, Liverpool, L1 | M2: a1G4J0000025yHKUAY | N2: Apt 89, Kings Dock Mill, Liverpool, L1 | O2: Kings Dock Mill, Liverpool Liverpool L1 | P2: =N2=K2 -> FALSE | Q2: =COUNTIF($B$2:$B$1196,B2) -> 1 | R2: =COUNTIF($H$2:$H$1196,H2) -> 1 | S2: =COUNTIF($D$2:$D$1196,D2) -> 1
A3: a1kNz000004c4edIAA | B3: 535380882 | C3: 003Nz00000IF65zIAD | D3: 006Nz00000EOc0yIAD | E3: Month 3: How can we make things better (Specification) Survey | F3: 2024-12-01T23:30:47.000+0000 | G3: marketing cloud connector | H3: GREP-CoA Alghalia Marafie, Amal Hani & Salem Marafie - 108 Millwrights Place, Temple Back, Bristol | I3: marketing cloud connector | J3: 2024-12-01T23:30:47.000+0000 | K3: <a href="a1GNz0000019Hx7" target="_blank">108 Millwrights Place, Temple Back, Bristol</a> | L3: GREP-CoA Alghalia Marafie, Amal Hani & Salem Marafie - 108 Millwrights Place, Temple Back, Bristol | M3: a1GNz0000019Hx7MAE | N3: 108 Millwrights Place, Temple Back, Bristol | O3: Millwrights Place, Bristol Bristol BS1 | P3: =N3=K3 -> FALSE | Q3: =COUNTIF($B$2:$B$1196,B3) -> 1 | R3: =COUNTIF($H$2:$H$1196,H3) -> 1 | S3: =COUNTIF($D$2:$D$1196,D3) -> 1
A4: a1kNz000004c4ecIAA | B4: 540162006 | C4: 003Nz00000JSncNIAT | D4: 006Nz00000FAHDRIA5 | E4: Month 3: How can we make things better (Specification) Survey | F4: 2024-12-01T23:30:47.000+0000 | G4: marketing cloud connector | H4: GREP-CoA Hoi Yan Yu & Wing Shiu Lo - 127 Gatehouse Apts, 86 East St, Southampton | I4: marketing cloud connector | J4: 2024-12-01T23:30:47.000+0000 | K4: <a href="a1G4J0000025xJE" target="_blank">127 Gatehouse Apts, 86 East St, Southampton</a> | L4: GREP-CoA Hoi Yan Yu & Wing Shiu Lo - 127 Gatehouse Apts, 86 East St, Southampton | M4: a1G4J0000025xJEUAY | N4: 127 Gatehouse Apts, 86 East St, Southampton | O4: Gatehouse Apartments, Southampton Southampton SO14 | P4: =N4=K4 -> FALSE | Q4: =COUNTIF($B$2:$B$1196,B4) -> 1 | R4: =COUNTIF($H$2:$H$1196,H4) -> 2 | S4: =COUNTIF($D$2:$D$1196,D4) -> 2
A5: a1kNz000004c4ebIAA | B5: 539721296 | C5: 003Nz00000JLDycIAH | D5: 006Nz00000FAHDRIA5 | E5: Month 3: How can we make things better (Specification) Survey | F5: 2024-12-01T23:30:47.000+0000 | G5: marketing cloud connector | H5: GREP-CoA Hoi Yan Yu & Wing Shiu Lo - 127 Gatehouse Apts, 86 East St, Southampton | I5: marketing cloud connector | J5: 2024-12-01T23:30:47.000+0000 | K5: <a href="a1G4J0000025xJE" target="_blank">127 Gatehouse Apts, 86 East St, Southampton</a> | L5: GREP-CoA Hoi Yan Yu & Wing Shiu Lo - 127 Gatehouse Apts, 86 East St, Southampton | M5: a1G4J0000025xJEUAY | N5: 127 Gatehouse Apts, 86 East St, Southampton | O5: Gatehouse Apartments, Southampton Southampton SO14 | P5: =N5=K5 -> FALSE | Q5: =COUNTIF($B$2:$B$1196,B5) -> 1 | R5: =COUNTIF($H$2:$H$1196,H5) -> 2 | S5: =COUNTIF($D$2:$D$1196,D5) -> 2
A6: a1kNz000004aMXZIA2 | B6: 471138769 | C6: 003Nz000004AhxRIAS | D6: 006Nz00000EItagIAD | E6: Month 3: How can we make things better (Specification) Survey | F6: 2024-11-27T23:30:11.000+0000 | G6: marketing cloud connector | H6: GREP-CoA Dev Bhuta, Palak Bhatt - 426 Enigma Square, 414 North Row, MK9 2GE | I6: Saji Gunasekaran | J6: 2024-11-27T23:32:52.000+0000 | K6: 426 Enigma Square, 414 North Row, MK9 2GE | L6: GREP-CoA Dev Bhuta, Palak Bhatt - 426 Enigma Square, 414 North Row, MK9 2GE | M6: a1G8d0000005rSQEAY | N6: 426 Enigma Square, 414 North Row, MK9 2GE | O6: Enigma Square, Milton Keynes Milton Keynes MK9 | P6: =N6=K6 -> TRUE | Q6: =COUNTIF($B$2:$B$1196,B6) -> 2 | R6: =COUNTIF($H$2:$H$1196,H6) -> 1 | S6: =COUNTIF($D$2:$D$1196,D6) -> 1
A7: a1kNz000004ZwgZIAS | B7: 527014030 | C7: 003Nz00000GDOUmIAP | D7: 006Nz00000DABdrIAH | E7: Month 3: How can we make things better (Specification) Survey | F7: 2024-11-25T23:30:25.000+0000 | G7: Saji Gunasekaran | I7: Saji Gunasekaran | J7: 2024-11-27T14:48:48.000+0000 | K7: 1002, Lamp House, 215 Chapel St, Salford, M3 | L7: GREP-CoA Mahmoudreza Oshagh & Banafsheh Shahzamanian Sichani - 1002, Lamp House, 215 Chapel St, Salford, M3 | M7: a1G4J0000025yS9UAI | N7: 1002, Lamp House, 215 Chapel St, Salford, M3 | O7: The Filaments, Salford Salford M3 | P7: =N7=K7 -> TRUE | Q7: =COUNTIF($B$2:$B$1196,B7) -> 1 | R7: =COUNTIF($H$2:$H$1196,H7) -> 0 | S7: =COUNTIF($D$2:$D$1196,D7) -> 1
A8: a1kNz000004ZwgYIAS | B8: 523136143 | C8: 003Nz00000FFGNDIA5 | D8: 006Nz00000CCr6UIAT | E8: Month 3: How can we make things better (Specification) Survey | F8: 2024-11-17T23:30:25.000+0000 | G8: Saji Gunasekaran | I8: Saji Gunasekaran | J8: 2024-11-27T14:47:55.000+0000 | K8: 82 Gatehouse Apts, 86 East St, Southampton | L8: GREP-CoA Puspinder Singh and Kritika Gambhir - 82 Gatehouse Apts, 86 East St, Southampton | M8: a1G4J0000025yQJUAY | N8: 82 Gatehouse Apts, 86 East St, Southampton | O8: Gatehouse Apartments, Southampton Southampton SO14 | P8: =N8=K8 -> TRUE | Q8: =COUNTIF($B$2:$B$1196,B8) -> 1 | R8: =COUNTIF($H$2:$H$1196,H8) -> 0 | S8: =COUNTIF($D$2:$D$1196,D8) -> 1
A9: a1kNz000004ZwgXIAS | B9: 524354677 | C9: 003Nz00000FV3FWIA1 | D9: 006Nz00000COf1XIAT | E9: Month 3: How can we make things better (Specification) Survey | F9: 2024-11-15T23:30:25.000+0000 | G9: Saji Gunasekaran | I9: Saji Gunasekaran | J9: 2024-11-27T14:47:03.000+0000 | K9: 608 The Silver Yard, 100 Moor St Queensway | L9: GREP-CoA Jiashu Wang and Yi Zheng - 608 The Silver Yard, 100 Moor St Queensway | M9: a1GNz000001HPPdMAO | N9: 608 The Silver Yard, 100 Moor St Queensway | O9: The Silver Yard, Birmingham Birmingham B4 | P9: =N9=K9 -> TRUE | Q9: =COUNTIF($B$2:$B$1196,B9) -> 1 | R9: =COUNTIF($H$2:$H$1196,H9) -> 0 | S9: =COUNTIF($D$2:$D$1196,D9) -> 1
A10: a1kNz000004ZwgWIAS | B10: 526344635 | C10: 003Nz00000G13E0IAJ | D10: 006Nz00000ClhLxIAJ | E10: Month 3: How can we make things better (Specification) Survey | F10: 2024-11-15T23:30:25.000+0000 | G10: Saji Gunasekaran | I10: Saji Gunasekaran | J10: 2024-11-27T14:45:57.000+0000 | K10: 506 Assay Apartments, Station View, Guildford | L10: GREP-CoA Emre Tarasil and Gulsah Tarasli - 506 Assay Apartments, Station View, Guildford | M10: a1G8d000002Q2T8EAK | N10: 506 Assay Apartments, Station View, Guildford | O10: The Mint, Guildford Guildford GU1 | P10: =N10=K10 -> TRUE | Q10: =COUNTIF($B$2:$B$1196,B10) -> 1 | R10: =COUNTIF($H$2:$H$1196,H10) -> 0 | S10: =COUNTIF($D$2:$D$1196,D10) -> 1
A11: a1kNz000004SYE9IAO | B11: 528400757 | C11: 003Nz00000GYWAjIAP | D11: 006Nz00000DBAarIAH | E11: Month 3: How can we make things better (Specification) Survey | F11: 2024-11-14T23:30:29.000+0000 | G11: marketing cloud connector | H11: GREP-CoA Keri Castillo - 30 Houghton Avenue, Waterlooville, PO7 3AA | I11: Saji Gunasekaran | J11: 2024-11-25T00:42:05.000+0000 | K11: 30 Houghton Avenue, Waterlooville, PO7 3AA | L11: GREP-CoA Keri Castillo - 30 Houghton Avenue, Waterlooville, PO7 3AA | M11: a1G4J0000025xktUAA | N11: 30 Houghton Avenue, Waterlooville, PO7 3AA | O11: The Grainger Collection at Berewood Hampshire PO7 | P11: =N11=K11 -> TRUE | Q11: =COUNTIF($B$2:$B$1196,B11) -> 2 | R11: =COUNTIF($H$2:$H$1196,H11) -> 1 | S11: =COUNTIF($D$2:$D$1196,D11) -> 2
A12: a1kNz000004ZwgVIAS | B12: 528400757 | C12: 003Nz00000GYWAjIAP | D12: 006Nz00000DBAarIAH | E12: Month 3: How can we make things better (Specification) Survey | F12: 2024-11-14T23:30:25.000+0000 | G12: Saji Gunasekaran | I12: Saji Gunasekaran | J12: 2024-11-27T14:45:01.000+0000 | K12: 30 Houghton Avenue, Waterlooville, PO7 3AA | L12: GREP-CoA Keri Castillo - 30 Houghton Avenue, Waterlooville, PO7 3AA | M12: a1G4J0000025xktUAA | N12: 30 Houghton Avenue, Waterlooville, PO7 3AA | O12: The Grainger Collection at Berewood Hampshire PO7 | P12: =N12=K12 -> TRUE | Q12: =COUNTIF($B$2:$B$1196,B12) -> 2 | R12: =COUNTIF($H$2:$H$1196,H12) -> 0 | S12: =COUNTIF($D$2:$D$1196,D12) -> 2
A13: a1kNz000004ZwgUIAS | B13: 531161716 | C13: 003Nz00000HARQ9IAP | D13: 006Nz00000DcigTIAR | E13: Month 3: How can we make things better (Specification) Survey | F13: 2024-11-12T23:30:25.000+0000 | G13: Saji Gunasekaran | I13: Saji Gunasekaran | J13: 2024-11-27T14:44:10.000+0000 | K13: Apt 111, Kings Dock Mill, Liverpool, L1 | L13: GREP-CoA Lauren Gibson and Sean Farrell - Apt 111, Kings Dock Mill, Liverpool, L1 | M13: a1G4J0000025yK9UAI | N13: Apt 111, Kings Dock Mill, Liverpool, L1 | O13: Kings Dock Mill, Liverpool Liverpool L1 | P13: =N13=K13 -> TRUE | Q13: =COUNTIF($B$2:$B$1196,B13) -> 1 | R13: =COUNTIF($H$2:$H$1196,H13) -> 0 | S13: =COUNTIF($D$2:$D$1196,D13) -> 1
A14: a1kNz000004ZwgTIAS | B14: 523133171 | C14: 003Nz00000FDzD7IAL | D14: 006Nz00000EUZYGIA5 | E14: Month 3: How can we make things better (Specification) Survey | F14: 2024-11-12T23:30:25.000+0000 | G14: Saji Gunasekaran | I14: Saji Gunasekaran | J14: 2024-11-27T14:42:26.000+0000 | K14: 1102 The Silver Yard, 100 Moor St Queensway | L14: GREP-CoA Sumita Datta - 1102 The Silver Yard, 100 Moor St Queensway | M14: a1GNz000001HQITMA4 | N14: 1102 The Silver Yard, 100 Moor St Queensway | O14: The Silver Yard, Birmingham Birmingham B4 | P14: =N14=K14 -> TRUE | Q14: =COUNTIF($B$2:$B$1196,B14) -> 1 | R14: =COUNTIF($H$2:$H$1196,H14) -> 0 | S14: =COUNTIF($D$2:$D$1196,D14) -> 1
A15: a1kNz000004ZwgSIAS | B15: 523600891 | C15: 003Nz00000FNvxqIAD | D15: 006Nz00000CHxfuIAD | E15: Month 3: How can we make things better (Specification) Survey | F15: 2024-11-10T23:30:25.000+0000 | G15: Saji Gunasekaran | I15: Saji Gunasekaran | J15: 2024-11-27T14:41:12.000+0000 | K15: 25 The Gardens, FF, London SE22 9QE | L15: GREP-CoA Zoe, Isaac, Eleanor and James - 25 The Gardens, FF, London SE22 9QE | M15: a1G4J0000025zg9UAA | N15: 25 The Gardens, FF, London SE22 9QE | O15: The Gardens, East Dulwich London SE22 | P15: =N15=K15 -> TRUE | Q15: =COUNTIF($B$2:$B$1196,B15) -> 1 | R15: =COUNTIF($H$2:$H$1196,H15) -> 0 | S15: =COUNTIF($D$2:$D$1196,D15) -> 1
A16: a1kNz000004ZwgRIAS | B16: 529605464 | C16: 003Nz00000GniWXIAZ | D16: 006Nz00000DMXHBIA5 | E16: Month 3: How can we make things better (Specification) Survey | F16: 2024-11-10T23:30:25.000+0000 | G16: Saji Gunasekaran | I16: Saji Gunasekaran | J16: 2024-11-27T14:39:52.000+0000 | K16: 1309, 5 Capital Quarter, Tyndall St., Cardiff | L16: GREP-CoA Nikos Tteralli - 1309, 5 Capital Quarter, Tyndall St., Cardiff | M16: a1GNz0000000bHKMAY | N16: 1309, 5 Capital Quarter, Tyndall St., Cardiff | O16: The Copper Works, Cardiff Cardiff CF10 | P16: =N16=K16 -> TRUE | Q16: =COUNTIF($B$2:$B$1196,B16) -> 1 | R16: =COUNTIF($H$2:$H$1196,H16) -> 0 | S16: =COUNTIF($D$2:$D$1196,D16) -> 1
A17: a1kNz000004ZwgQIAS | B17: 323013647 | C17: 0038d00000EbJYtAAN | D17: 006Nz00000D4zlNIAR | E17: Month 3: How can we make things better (Specification) Survey | F17: 2024-11-10T23:30:25.000+0000 | G17: Saji Gunasekaran | I17: Saji Gunasekaran | J17: 2024-11-27T14:38:48.000+0000 | K17: 1012 Tayleur Apt , Waterman Wlk, Salford M50 | L17: GREP-CoA Yee Lok Lai and Yan Chi Chu - 1012 Tayleur Apt , Waterman Wlk, Salford M50 | M17: a1G4J0000025yeaUAA | N17: 1012 Tayleur Apt , Waterman Wlk, Salford M50 | O17: Clippers Quay Salford M50 | P17: =N17=K17 -> TRUE | Q17: =COUNTIF($B$2:$B$1196,B17) -> 1 | R17: =COUNTIF($H$2:$H$1196,H17) -> 0 | S17: =COUNTIF($D$2:$D$1196,D17) -> 1
A18: a1kNz000004ZwgOIAS | B18: 524358822 | C18: 003Nz00000FX0S1IAL | D18: 006Nz00000CHyFPIA1 | E18: Month 3: How can we make things better (Specification) Survey | F18: 2024-11-07T23:30:25.000+0000 | G18: Saji Gunasekaran | I18: Saji Gunasekaran | J18: 2024-11-27T14:33:25.000+0000 | K18: 508 Assay Apartments, Station View, Guildford | L18: GREP-CoA Alastair Weeks and Rachel McCoubrey - 508 Assay Apartments, Station View, Guildford | M18: a1G8d000002Q2TNEA0 | N18: 508 Assay Apartments, Station View, Guildford | O18: The Mint, Guildford Guildford GU1 | P18: =N18=K18 -> TRUE | Q18: =COUNTIF($B$2:$B$1196,B18) -> 1 | R18: =COUNTIF($H$2:$H$1196,H18) -> 0 | S18: =COUNTIF($D$2:$D$1196,D18) -> 1
A19: a1kNz000004ZwgLIAS | B19: 484736179 | C19: 003Nz000006sVBUIA2 | D19: 006Nz00000BfxibIAB | E19: Month 3: How can we make things better (Specification) Survey | F19: 2024-11-05T23:30:25.000+0000 | G19: Saji Gunasekaran | I19: Saji Gunasekaran | J19: 2024-11-27T14:29:23.000+0000 | K19: 815 The Barnum, 23 Queens Road, Nottingham | L19: GREP-CoA Kashaf Naeem Malik and Nabeel Kandaan - 815 The Barnum, 23 Queens Road, Nottingham | M19: a1GNz00000015VWMAY | N19: 815 The Barnum, 23 Queens Road, Nottingham | O19: The Barnum, Nottingham Nottingham NG2 | P19: =N19=K19 -> TRUE | Q19: =COUNTIF($B$2:$B$1196,B19) -> 1 | R19: =COUNTIF($H$2:$H$1196,H19) -> 0 | S19: =COUNTIF($D$2:$D$1196,D19) -> 1
A20: a1kNz000004ZwgNIAS | B20: 531378646 | C20: 003Nz00000HCYaPIAX | D20: 006Nz00000DenH3IAJ | E20: Month 3: How can we make things better (Specification) Survey | F20: 2024-11-05T23:30:25.000+0000 | G20: Saji Gunasekaran | I20: Saji Gunasekaran | J20: 2024-11-27T14:32:26.000+0000 | K20: 1110 Pin Yard, 11 Sweet Street, Leeds | L20: GREP-CoA Charlotte Hewerdine, Thomas Sheridan - 1110 Pin Yard, 11 Sweet Street, Leeds | M20: a1G8d0000004XbiEAE | N20: 1110 Pin Yard, 11 Sweet Street, Leeds | O20: Pin Yard, Leeds Leeds LS11 | P20: =N20=K20 -> TRUE | Q20: =COUNTIF($B$2:$B$1196,B20) -> 1 | R20: =COUNTIF($H$2:$H$1196,H20) -> 0 | S20: =COUNTIF($D$2:$D$1196,D20) -> 1
A21: a1kNz000004ZwgMIAS | B21: 509796160 | C21: 003Nz00000CERB8IAP | D21: 006Nz00000A5NpSIAV | E21: Month 3: How can we make things better (Specification) Survey | F21: 2024-11-05T23:30:25.000+0000 | G21: Saji Gunasekaran | I21: Saji Gunasekaran | J21: 2024-11-27T14:31:19.000+0000 | K21: 207, 5 Capital Quarter, Tyndall St., Cardiff | L21: GREP-CoA William Bushby & Alistair Watkins-Stuart - 207, 5 Capital Quarter, Tyndall St., Cardiff | M21: a1GNz0000000cA9MAI | N21: 207, 5 Capital Quarter, Tyndall St., Cardiff | O21: The Copper Works, Cardiff Cardiff CF10 | P21: =N21=K21 -> TRUE | Q21: =COUNTIF($B$2:$B$1196,B21) -> 1 | R21: =COUNTIF($H$2:$H$1196,H21) -> 0 | S21: =COUNTIF($D$2:$D$1196,D21) -> 1
A22: a1kNz000004KshtIAC | B22: 535163160 | C22: 003Nz00000ICcNJIA1 | D22: 006Nz00000DejtVIAR | E22: Month 3: How can we make things better (Specification) Survey | F22: 2024-11-04T23:30:43.000+0000 | G22: marketing cloud connector | I22: Saji Gunasekaran | J22: 2024-11-25T00:46:18.000+0000 | K22: 56, Gilders Yard, 14 Great Hampton St, Birm | L22: GREP-CoA Susannah Mbenga & Chido Shahwe - 56, Gilders Yard, 14 Great Hampton St, Birm | M22: a1G8d0000004c7lEAA | N22: 56, Gilders Yard, 14 Great Hampton St, Birm | O22: Gilders Yard, Birmingham Birmingham B18 | P22: =N22=K22 -> TRUE | Q22: =COUNTIF($B$2:$B$1196,B22) -> 1 | R22: =COUNTIF($H$2:$H$1196,H22) -> 0 | S22: =COUNTIF($D$2:$D$1196,D22) -> 1
A23: a1kNz000004ZwgPIAS | B23: 521913417 | C23: 003Nz00000Exh5jIAB | D23: 006Nz00000DxQdNIAV | E23: Month 3: How can we make things better (Specification) Survey | F23: 2024-11-03T23:30:25.000+0000 | G23: Saji Gunasekaran | I23: Saji Gunasekaran | J23: 2024-11-27T14:34:52.000+0000 | K23: 159 Millwrights Place, Temple Back, Bristol | L23: GREP-CoA Alexandra-Maria Anastase - 159 Millwrights Place, Temple Back, Bristol | M23: a1GNz0000019IZpMAM | N23: 159 Millwrights Place, Temple Back, Bristol | O23: Millwrights Place, Bristol Bristol BS1 | P23: =N23=K23 -> TRUE | Q23: =COUNTIF($B$2:$B$1196,B23) -> 1 | R23: =COUNTIF($H$2:$H$1196,H23) -> 0 | S23: =COUNTIF($D$2:$D$1196,D23) -> 1
... A26: a1kNz000004HMzVIAW | B26: 524649833 | C26: 003Nz00000FZb49IAD | D26: 006Nz00000C5sDpIAJ | E26: Month 3: How can we make things better (Specification) Survey | F26: 2024-10-31T23:30:47.000+0000 | G26: marketing cloud connector | I26: Saji Gunasekaran | J26: 2024-11-25T00:50:42.000+0000 | K26: 506 Torrens Apt, Waterman Wlk, Salford M50 | L26: GREP-CoA Fernanda Breame and Riya Rajan Shayla - 506 Torrens Apt, Waterman Wlk, Salford M50 | M26: a1G4J0000025z4IUAQ | N26: 506 Torrens Apt, Waterman Wlk, Salford M50 | O26: Clippers Quay Salford M50 | P26: =N26=K26 -> TRUE | Q26: =COUNTIF($B$2:$B$1196,B26) -> 1 | R26: =COUNTIF($H$2:$H$1196,H26) -> 0 | S26: =COUNTIF($D$2:$D$1196,D26) -> 1
A27: a1kNz0000049ZInIAM | B27: 518048414 | C27: 003Nz00000E35mHIAR | D27: 006Nz00000BJcEXIA1 | E27: Month 3: How can we make things better (Specification) Survey | F27: 2024-10-25T22:30:45.000+0000 | G27: marketing cloud connector | H27: GREP-CoA Valentina Rumyantseva - 617 The Barnum, 23 Queens Road, Nottingham | I27: Saji Gunasekaran | J27: 2024-11-25T00:56:04.000+0000 | K27: 617 The Barnum, 23 Queens Road, Nottingham | L27: GREP-CoA Valentina Rumyantseva - 617 The Barnum, 23 Queens Road, Nottingham | M27: a1GNz00000016GIMAY | N27: 617 The Barnum, 23 Queens Road, Nottingham | O27: The Barnum, Nottingham Nottingham NG2 | P27: =N27=K27 -> TRUE | Q27: =COUNTIF($B$2:$B$1196,B27) -> 1 | R27: =COUNTIF($H$2:$H$1196,H27) -> 1 | S27: =COUNTIF($D$2:$D$1196,D27) -> 1
A28: a1kNz0000049CKbIAM | B28: 523138734 | C28: 003Nz00000FG1PJIA1 | D28: 006Nz00000CDIJZIA5 | E28: Month 3: How can we make things better (Specification) Survey | F28: 2024-10-24T22:30:30.000+0000 | G28: marketing cloud connector | H28: GREP-CoA William Teoh and Heather Fitzpatrick - 108 Assay Apartments, Station View, Guildford | I28: Saji Gunasekaran | J28: 2024-11-25T00:57:13.000+0000 | K28: 108 Assay Apartments, Station View, Guildford | L28: GREP-CoA William Teoh and Heather Fitzpatrick - 108 Assay Apartments, Station View, Guildford | M28: a1G8d000002Q2Z7EAK | N28: 108 Assay Apartments, Station View, Guildford | O28: The Mint, Guildford Guildford GU1 | P28: =N28=K28 -> TRUE | Q28: =COUNTIF($B$2:$B$1196,B28) -> 1 | R28: =COUNTIF($H$2:$H$1196,H28) -> 1 | S28: =COUNTIF($D$2:$D$1196,D28) -> 1
A29: a1kNz00000447ewIAA | B29: 519742842 | C29: 003Nz00000ER1PnIAL | D29: 006Nz00000BaNB4IAN | E29: Month 3: How can we make things better (Specification) Survey | F29: 2024-10-17T22:30:26.000+0000 | G29: marketing cloud connector | H29: GREP-CoA Angela Robinson - 24, 15 St. Johns Gardens, Bury, BL9 | I29: Saji Gunasekaran | J29: 2024-11-25T00:59:45.000+0000 | K29: 24, 15 St. Johns Gardens, Bury, BL9 | L29: GREP-CoA Angela Robinson - 24, 15 St. Johns Gardens, Bury, BL9 | M29: a1G4J0000025xshUAA | N29: 24, 15 St. Johns Gardens, Bury, BL9 | O29: The Rock, Bury Bury BL9 | P29: =N29=K29 -> TRUE | Q29: =COUNTIF($B$2:$B$1196,B29) -> 1 | R29: =COUNTIF($H$2:$H$1196,H29) -> 1 | S29: =COUNTIF($D$2:$D$1196,D29) -> 1
A30: a1kNz00000447evIAA | B30: 509104875 | C30: 003Nz00000C4xygIAB | D30: 006Nz000009z99IIAQ | E30: Month 3: How can we make things better (Specification) Survey | F30: 2024-10-17T22:30:26.000+0000 | G30: marketing cloud connector | I30: Saji Gunasekaran | J30: 2024-11-25T00:58:57.000+0000 | K30: 907 Ambassador Apt, Waterman Wlk, Salford M50 | L30: GREP-CoA Chun Kit Raymond WU - 907 Ambassador Apt, Waterman Wlk, Salford M50 | M30: a1G4J0000025yoqUAA | N30: 907 Ambassador Apt, Waterman Wlk, Salford M50 | O30: Clippers Quay Salford M50 | P30: =N30=K30 -> TRUE | Q30: =COUNTIF($B$2:$B$1196,B30) -> 1 | R30: =COUNTIF($H$2:$H$1196,H30) -> 0 | S30: =COUNTIF($D$2:$D$1196,D30) -> 1
A31: a1kNz000003znDNIAY | B31: 519273414 | C31: 003Nz00000EJKXdIAP | D31: 006Nz00000BUahIIAT | E31: Month 3: How can we make things better (Specification) Survey | F31: 2024-10-11T22:30:30.000+0000 | G31: marketing cloud connector | H31: GREP-CoA Mr Caleb Ogwu & Miss Anuoluwapo Ikotun - 707 Pin Yard, 11 Sweet Street, Leeds | I31: Saji Gunasekaran | J31: 2024-11-25T01:00:49.000+0000 | K31: 707 Pin Yard, 11 Sweet Street, Leeds | L31: GREP-CoA Mr Caleb Ogwu & Miss Anuoluwapo Ikotun - 707 Pin Yard, 11 Sweet Street, Leeds | M31: a1G8d0000004XcnEAE | N31: 707 Pin Yard, 11 Sweet Street, Leeds | O31: Pin Yard, Leeds Leeds LS11 | P31: =N31=K31 -> TRUE | Q31: =COUNTIF($B$2:$B$1196,B31) -> 1 | R31: =COUNTIF($H$2:$H$1196,H31) -> 1 | S31: =COUNTIF($D$2:$D$1196,D31) -> 1
A32: a1kNz000003zDJZIA2 | B32: 316966480 | C32: 0038d00000DV2C6AAL | D32: 006Nz00000ChSwbIAF | E32: Month 3: How can we make things better (Specification) Survey | F32: 2024-10-10T22:30:28.000+0000 | G32: marketing cloud connector | I32: Saji Gunasekaran | J32: 2024-11-25T01:03:59.000+0000 | K32: 1601 Aster Apts 822 Seven Sisters Rd London N | L32: GREP-CoA Jordan Rodrigues, Sam Thomas and Huilin Qiu - 1601 Aster Apts 822 Seven Sisters Rd London N | M32: a1G4J0000025yTbUAI | N32: 1601 Aster Apts 822 Seven Sisters Rd London N | O32: Apex Gardens, Seven Sisters London N15 | P32: =N32=K32 -> TRUE | Q32: =COUNTIF($B$2:$B$1196,B32) -> 1 | R32: =COUNTIF($H$2:$H$1196,H32) -> 0 | S32: =COUNTIF($D$2:$D$1196,D32) -> 1
A33: a1kNz000003uKDeIAM | B33: 509334707 | C33: 003Nz00000C7qiwIAB | D33: 006Nz00000A0z0xIAB | E33: Month 3: How can we make things better (Specification) Survey | F33: 2024-10-08T22:30:51.000+0000 | G33: marketing cloud connector | H33: GREP-CoA Chun-yu Yeh & Diego Pablo Sanchez Sanchez - Flat 1, Ospringe House, Wootton St, SE1 8TP | I33: Saji Gunasekaran | J33: 2024-11-25T01:05:29.000+0000 | K33: Flat 1, Ospringe House, Wootton St, SE1 8TP | L33: GREP-CoA Chun-yu Yeh & Diego Pablo Sanchez Sanchez - Flat 1, Ospringe House, Wootton St, SE1 8TP | M33: a1G4J0000025yZ2UAI | N33: Flat 1, Ospringe House, Wootton St, SE1 8TP | O33: Ospringe House, Wootton Street London SE1 | P33: =N33=K33 -> TRUE | Q33: =COUNTIF($B$2:$B$1196,B33) -> 1 | R33: =COUNTIF($H$2:$H$1196,H33) -> 1 | S33: =COUNTIF($D$2:$D$1196,D33) -> 1
A34: a1kNz000003uKDdIAM | B34: 531158779 | C34: 003Nz00000H9fQLIAZ | D34: 006Nz00000D4TK7IAN | E34: Month 3: How can we make things better (Specification) Survey | F34: 2024-10-08T22:30:51.000+0000 | G34: marketing cloud connector | H34: GREP-CoA Anithadevi Manikandan & Ramaswamy Swaminatha Manikandan - 7 Highfield Avenue, Newbury | I34: Saji Gunasekaran | J34: 2024-11-25T01:04:45.000+0000 | K34: 7 Highfield Avenue, Newbury | L34: GREP-CoA Anithadevi Manikandan & Ramaswamy Swaminatha Manikandan - 7 Highfield Avenue, Newbury | M34: a1G8d000002OmUXEA0 | N34: 7 Highfield Avenue, Newbury | O34: Weavers Yard, Newbury Newbury RG14 | P34: =N34=K34 -> TRUE | Q34: =COUNTIF($B$2:$B$1196,B34) -> 1 | R34: =COUNTIF($H$2:$H$1196,H34) -> 1 | S34: =COUNTIF($D$2:$D$1196,D34) -> 1
A35: a1kNz000003raurIAA | B35: 485162486 | C35: 003Nz000006zvM7IAI | D35: 006Nz00000AZ0LyIAL | E35: Month 3: How can we make things better (Specification) Survey | F35: 2024-10-07T22:30:30.000+0000 | G35: marketing cloud connector | I35: Saji Gunasekaran | J35: 2024-11-25T01:06:30.000+0000 | K35: 623 The Barnum, 23 Queens Road, Nottingham | L35: GREP-CoA Scott Robertson & Sophia Oliver - 623 The Barnum, 23 Queens Road, Nottingham | M35: a1GNz00000017M1MAI | N35: 623 The Barnum, 23 Queens Road, Nottingham | O35: The Barnum, Nottingham Nottingham NG2 | P35: =N35=K35 -> TRUE | Q35: =COUNTIF($B$2:$B$1196,B35) -> 2 | R35: =COUNTIF($H$2:$H$1196,H35) -> 0 | S35: =COUNTIF($D$2:$D$1196,D35) -> 1
A36: a1kNz000003qvDNIAY | B36: 499095891 | C36: 003Nz000009spDGIAY | D36: 006Nz00000ChN7KIAV | E36: Month 3: How can we make things better (Specification) Survey | F36: 2024-10-06T22:31:09.000+0000 | G36: marketing cloud connector | I36: Saji Gunasekaran | J36: 2024-11-25T01:07:14.000+0000 | K36: 1102, 84 Upper Allen St, Sheffield | L36: GREP-CoA Nathan Keeble and Eve Butterell - 1102, 84 Upper Allen St, Sheffield | M36: a1GNz0000000zGPMAY | N36: 1102, 84 Upper Allen St, Sheffield | O36: The Tilt Works, Sheffield Sheffield S3 | P36: =N36=K36 -> TRUE | Q36: =COUNTIF($B$2:$B$1196,B36) -> 1 | R36: =COUNTIF($H$2:$H$1196,H36) -> 0 | S36: =COUNTIF($D$2:$D$1196,D36) -> 1
A37: a1kNz000003nym5IAA | B37: 376138984 | C37: 0038d00000QdtIHAAZ | D37: 006Nz00000AadRiIAJ | E37: Month 3: How can we make things better (Specification) Survey | F37: 2024-10-02T22:30:29.000+0000 | G37: marketing cloud connector | I37: Saji Gunasekaran | J37: 2024-11-25T01:08:29.000+0000 | K37: 603 The Silver Yard, 100 Moor St Queensway | L37: GREP-CoA Asad Ahmad - 603 The Silver Yard, 100 Moor St Queensway | M37: a1GNz000001HOTaMAO | N37: 603 The Silver Yard, 100 Moor St Queensway | O37: The Silver Yard, Birmingham Birmingham B4 | P37: =N37=K37 -> TRUE | Q37: =COUNTIF($B$2:$B$1196,B37) -> 1 | R37: =COUNTIF($H$2:$H$1196,H37) -> 0 | S37: =COUNTIF($D$2:$D$1196,D37) -> 1
A38: a1kNz000003n3SrIAI | B38: 516376794 | C38: 003Nz00000DgR5yIAF | D38: 006Nz00000B3fDCIAZ | E38: Month 3: How can we make things better (Specification) Survey | F38: 2024-10-01T22:30:29.000+0000 | G38: marketing cloud connector | I38: Saji Gunasekaran | J38: 2024-11-04T18:57:31.000+0000 | K38: 806 Ambassador Apt, Waterman Wlk, Salford M50 | L38: GREP-CoA Lai Ming Kong & Yun Lau Tang - 806 Ambassador Apt, Waterman Wlk, Salford M50 | M38: a1G4J0000025yktUAA | N38: 806 Ambassador Apt, Waterman Wlk, Salford M50 | O38: Clippers Quay Salford M50 | P38: =N38=K38 -> TRUE | Q38: =COUNTIF($B$2:$B$1196,B38) -> 1 | R38: =COUNTIF($H$2:$H$1196,H38) -> 0 | S38: =COUNTIF($D$2:$D$1196,D38) -> 1
A39: a1kNz000003m2yhIAA | B39: 518043880 | C39: 003Nz00000E1RB0IAN | D39: 006Nz00000BM0mDIAT | E39: Month 3: How can we make things better (Specification) Survey | F39: 2024-09-29T22:30:31.000+0000 | G39: marketing cloud connector | I39: Saji Gunasekaran | J39: 2024-10-31T02:39:18.000+0000 | K39: 520 Pin Yard, 11 Sweet Street, Leeds | L39: GREP-CoA Omolade Osinaike, Desiree Brito - 520 Pin Yard, 11 Sweet Street, Leeds | M39: a1G8d0000004XitEAE | N39: 520 Pin Yard, 11 Sweet Street, Leeds | O39: Pin Yard, Leeds Leeds LS11 | P39: =N39=K39 -> TRUE | Q39: =COUNTIF($B$2:$B$1196,B39) -> 1 | R39: =COUNTIF($H$2:$H$1196,H39) -> 0 | S39: =COUNTIF($D$2:$D$1196,D39) -> 1
A40: a1kNz000003m2ygIAA | B40: 516140415 | C40: 003Nz00000DbID6IAN | D40: 006Nz00000Azhs0IAB | E40: Month 3: How can we make things better (Specification) Survey | F40: 2024-09-29T22:30:31.000+0000 | G40: marketing cloud connector | H40: GREP-CoA Ahmed Elgendy, Hager Amer - 328 Enigma Square, 414 North Row, MK9 2GF | I40: Saji Gunasekaran | J40: 2024-10-31T02:39:18.000+0000 | K40: 328 Enigma Square, 414 North Row, MK9 2GF | L40: GREP-CoA Ahmed Elgendy, Hager Amer - 328 Enigma Square, 414 North Row, MK9 2GF | M40: a1G8d0000005rSfEAI | N40: 328 Enigma Square, 414 North Row, MK9 2GF | O40: Enigma Square, Milton Keynes Milton Keynes MK9 | P40: =N40=K40 -> TRUE | Q40: =COUNTIF($B$2:$B$1196,B40) -> 1 | R40: =COUNTIF($H$2:$H$1196,H40) -> 1 | S40: =COUNTIF($D$2:$D$1196,D40) -> 1
A41: a1kNz000003m2yfIAA | B41: 378717074 | C41: 0038d00000QgiL1AAJ | D41: 006Nz00000BThxjIAD | E41: Month 3: How can we make things better (Specification) Survey | F41: 2024-09-29T22:30:31.000+0000 | G41: marketing cloud connector | H41: GREP-CoA Joshua Indenhuck & Xenia Masoura - 37, Gilders Yard, 14 Great Hampton St, Birm | I41: Saji Gunasekaran | J41: 2024-10-31T02:39:18.000+0000 | K41: 37, Gilders Yard, 14 Great Hampton St, Birm | L41: GREP-CoA Joshua Indenhuck & Xenia Masoura - 37, Gilders Yard, 14 Great Hampton St, Birm | M41: a1G8d0000004c6nEAA | N41: 37, Gilders Yard, 14 Great Hampton St, Birm | O41: Gilders Yard, Birmingham Birmingham B18 | P41: =N41=K41 -> TRUE | Q41: =COUNTIF($B$2:$B$1196,B41) -> 2 | R41: =COUNTIF($H$2:$H$1196,H41) -> 1 | S41: =COUNTIF($D$2:$D$1196,D41) -> 1
A42: a1kNz000003lKsnIAE | B42: 517584226 | C42: 003Nz00000DvxTlIAJ | D42: 006Nz00000BEh24IAD | E42: Month 3: How can we make things better (Specification) Survey | F42: 2024-09-27T22:30:46.000+0000 | G42: marketing cloud connector | H42: GREP-CoA Samuel Perry - 506, 5 Capital Quarter, Tyndall St., Cardiff | I42: Saji Gunasekaran | J42: 2024-10-31T02:39:18.000+0000 | K42: 506, 5 Capital Quarter, Tyndall St., Cardiff | L42: GREP-CoA Samuel Perry - 506, 5 Capital Quarter, Tyndall St., Cardiff | M42: a1GNz0000000bilMAA | N42: 506, 5 Capital Quarter, Tyndall St., Cardiff | O42: The Copper Works, Cardiff Cardiff CF10 | P42: =N42=K42 -> TRUE | Q42: =COUNTIF($B$2:$B$1196,B42) -> 1 | R42: =COUNTIF($H$2:$H$1196,H42) -> 1 | S42: =COUNTIF($D$2:$D$1196,D42) -> 1
A43: a1kNz000003f3EjIAI | B43: 526572176 | C43: 003Nz00000G5WPRIA3 | D43: 006Nz00000Cp0wmIAB | E43: Month 3: How can we make things better (Specification) Survey | F43: 2024-09-22T22:30:37.000+0000 | G43: marketing cloud connector | I43: Saji Gunasekaran | J43: 2024-10-31T02:39:18.000+0000 | K43: 106 Plant Farm Cres, Waterlooville, PO7 3DB | L43: GREP-CoA Sandra Jayne Trippier - 106 Plant Farm Cres, Waterlooville, PO7 3DB | M43: a1G4J000004PtLoUAK | N43: 106 Plant Farm Cres, Waterlooville, PO7 3DB | O43: The Grainger Collection at Berewood Winchester PO7 | P43: =N43=K43 -> TRUE | Q43: =COUNTIF($B$2:$B$1196,B43) -> 1 | R43: =COUNTIF($H$2:$H$1196,H43) -> 0 | S43: =COUNTIF($D$2:$D$1196,D43) -> 1
A44: a1kNz000003f3EkIAI | B44: 514225006 | C44: 003Nz00000DBqNBIA1 | D44: 006Nz00000AikkXIAR | E44: Month 3: How can we make things better (Specification) Survey | F44: 2024-09-22T22:30:37.000+0000 | G44: marketing cloud connector | H44: GREP-CoA Amy Clift & Alexander Shaw - 417, 84 Upper Allen St, Sheffield | I44: Saji Gunasekaran | J44: 2024-10-31T02:39:18.000+0000 | K44: 417, 84 Upper Allen St, Sheffield | L44: GREP-CoA Amy Clift & Alexander Shaw - 417, 84 Upper Allen St, Sheffield | M44: a1GNz0000000yH7MAI | N44: 417, 84 Upper Allen St, Sheffield | O44: The Tilt Works, Sheffield Sheffield S3 | P44: =N44=K44 -> TRUE | Q44: =COUNTIF($B$2:$B$1196,B44) -> 1 | R44: =COUNTIF($H$2:$H$1196,H44) -> 1 | S44: =COUNTIF($D$2:$D$1196,D44) -> 1
A45: a1kNz000003eEc1IAE | B45: 510808855 | C45: 003Nz00000CRDjpIAH | D45: 006Nz00000AEYQfIAP | E45: Month 3: How can we make things better (Specification) Survey | F45: 2024-09-19T22:30:20.000+0000 | G45: marketing cloud connector | I45: Saji Gunasekaran | J45: 2024-10-31T02:39:18.000+0000 | K45: 508 The Silver Yard, 100 Moor St Queensway | L45: GREP-CoA John Steven Lee - 508 The Silver Yard, 100 Moor St Queensway | M45: a1GNz000001HPCjMAO | N45: 508 The Silver Yard, 100 Moor St Queensway | O45: The Silver Yard, Birmingham Birmingham B4 | P45: =N45=K45 -> TRUE | Q45: =COUNTIF($B$2:$B$1196,B45) -> 1 | R45: =COUNTIF($H$2:$H$1196,H45) -> 0 | S45: =COUNTIF($D$2:$D$1196,D45) -> 1
A46: a1kNz000003eFOqIAM | B46: 394536817 | E46: Month 3: How can we make things better (Specification) Survey | F46: 2024-09-15T02:02:12.000+0000 | G46: Saji Gunasekaran | H46: GREP-CoA Himanshu Arora & Sneha Elizabeth Jacob - 65, Gilders Yard, 14 Great Hampton St, Birm | I46: Saji Gunasekaran | J46: 2024-10-31T02:39:18.000+0000 | K46: 65, Gilders Yard, 14 Great Hampton St, Birm | P46: =N46=K46 -> FALSE | Q46: =COUNTIF($B$2:$B$1196,B46) -> 1 | R46: =COUNTIF($H$2:$H$1196,H46) -> 1 | S46: =COUNTIF($D$2:$D$1196,D46) -> 0
A47: a1kNz000003YfGjIAK | B47: 439009515 | C47: 003Nz000001T5jhIAC | D47: 006Nz00000BPTQHIA5 | E47: Month 3: How can we make things better (Specification) Survey | F47: 2024-09-13T22:30:35.000+0000 | G47: marketing cloud connector | I47: Saji Gunasekaran | J47: 2024-10-31T02:39:18.000+0000 | K47: 706, Brook Place Apts, Sheffield, S11 8DA | L47: GREP-CoA Katie Baugh, Will Whittaker - 706, Brook Place Apts, Sheffield, S11 8DA | M47: a1G4J0000025zN6UAI | N47: 706, Brook Place Apts, Sheffield, S11 8DA | O47: Brook Place, Sheffield Sheffield S11 | P47: =N47=K47 -> TRUE | Q47: =COUNTIF($B$2:$B$1196,B47) -> 1 | R47: =COUNTIF($H$2:$H$1196,H47) -> 0 | S47: =COUNTIF($D$2:$D$1196,D47) -> 1
A48: a1kNz000003QrVBIA0 | B48: 210053775 | C48: 0034J00000a4fNSQAY | D48: 006Nz000008UyK0IAK | E48: Month 3: How can we make things better (Specification) Survey | F48: 2024-09-10T22:30:48.000+0000 | G48: marketing cloud connector | I48: Saji Gunasekaran | J48: 2024-10-31T02:39:18.000+0000 | K48: 39, Ancoats, 2 Butler Street, M4 6BZ | L48: GREP-CoA Daniel Linford-Downes & Emily Ballentine - 39, Ancoats, 2 Butler Street, M4 6BZ | M48: a1G4J0000025yFpUAI | N48: 39, Ancoats, 2 Butler Street, M4 6BZ | O48: The Tribe, Ancoats, Manchester Manchester M4 | P48: =N48=K48 -> TRUE | Q48: =COUNTIF($B$2:$B$1196,B48) -> 1 | R48: =COUNTIF($H$2:$H$1196,H48) -> 0 | S48: =COUNTIF($D$2:$D$1196,D48) -> 1
A49: a1kNz000003QHOTIA4 | B49: 519499748 | C49: 003Nz00000EMW63IAH | D49: 006Nz00000BWsLZIA1 | E49: Month 3: How can we make things better (Specification) Survey | F49: 2024-09-09T22:30:48.000+0000 | G49: marketing cloud connector | H49: GREP-CoA Sean Pillay, Dominika Matuszkiewicz - 201, Brook Place Apts, Sheffield, S11 8BR | I49: Saji Gunasekaran | J49: 2024-10-31T02:39:18.000+0000 | K49: 201, Brook Place Apts, Sheffield, S11 8BR | L49: GREP-CoA Sean Pillay, Dominika Matuszkiewicz - 201, Brook Place Apts, Sheffield, S11 8BR | M49: a1G4J0000025zIZUAY | N49: 201, Brook Place Apts, Sheffield, S11 8BR | O49: Brook Place, Sheffield Sheffield S11 | P49: =N49=K49 -> TRUE | Q49: =COUNTIF($B$2:$B$1196,B49) -> 1 | R49: =COUNTIF($H$2:$H$1196,H49) -> 1 | S49: =COUNTIF($D$2:$D$1196,D49) -> 1
A50: a1kNz000003PlusIAC | B50: 511035015 | C50: 003Nz00000CSZDdIAP | D50: 006Nz00000AFtxiIAD | E50: Month 3: How can we make things better (Specification) Survey | F50: 2024-09-08T22:30:43.000+0000 | G50: marketing cloud connector | I50: Saji Gunasekaran | J50: 2024-10-31T02:39:18.000+0000 | K50: 67 Millwrights Place, Temple Back, Bristol | L50: GREP-CoA Abdulmohsen Alkhanbashi - 67 Millwrights Place, Temple Back, Bristol | M50: a1GNz0000019HHBMA2 | N50: 67 Millwrights Place, Temple Back, Bristol | O50: Millwrights Place, Bristol Bristol BS1 | P50: =N50=K50 -> TRUE | Q50: =COUNTIF($B$2:$B$1196,B50) -> 1 | R50: =COUNTIF($H$2:$H$1196,H50) -> 0 | S50: =COUNTIF($D$2:$D$1196,D50) -> 1
A51: a1kNz000003PlurIAC | B51: 518048632 | C51: 003Nz00000E38LxIAJ | D51: 006Nz00000BJg6rIAD | E51: Month 3: How can we make things better (Specification) Survey | F51: 2024-09-08T22:30:43.000+0000 | G51: marketing cloud connector | H51: GREP-CoA Erik Youngtaek Yu - 33 Nautilus Apts, 2 Norah Smyth Rd, London | I51: Saji Gunasekaran | J51: 2024-10-31T02:39:18.000+0000 | K51: 33 Nautilus Apts, 2 Norah Smyth Rd, London | L51: GREP-CoA Erik Youngtaek Yu & Jarim Koo - 33 Nautilus Apts, 2 Norah Smyth Rd, London | M51: a1G8d000002QBMzEAO | N51: 33 Nautilus Apts, 2 Norah Smyth Rd, London | O51: Fortunes Dock, Canning Town London E16 | P51: =N51=K51 -> TRUE | Q51: =COUNTIF($B$2:$B$1196,B51) -> 1 | R51: =COUNTIF($H$2:$H$1196,H51) -> 1 | S51: =COUNTIF($D$2:$D$1196,D51) -> 1
A52: a1kNz000003PluuIAC | B52: 510046068 | C52: 003Nz00000CIcftIAD | D52: 006Nz00000A8d6WIAR | E52: Month 3: How can we make things better (Specification) Survey | F52: 2024-09-08T22:30:43.000+0000 | G52: marketing cloud connector | I52: Saji Gunasekaran | J52: 2024-10-31T02:39:18.000+0000 | K52: 51 Millwrights Place, Temple Back, Bristol | L52: GREP-CoA Itsun Wang - 51 Millwrights Place, Temple Back, Bristol | M52: a1GNz0000019DQWMA2 | N52: 51 Millwrights Place, Temple Back, Bristol | O52: Millwrights Place, Bristol Bristol BS1 | P52: =N52=K52 -> TRUE | Q52: =COUNTIF($B$2:$B$1196,B52) -> 1 | R52: =COUNTIF($H$2:$H$1196,H52) -> 0 | S52: =COUNTIF($D$2:$D$1196,D52) -> 1
A53: a1kNz000003PlutIAC | B53: 511042214 | C53: 003Nz00000CUIIRIA5 | D53: 006Nz00000AGSPDIA5 | E53: Month 3: How can we make things better (Specification) Survey | F53: 2024-09-08T22:30:43.000+0000 | G53: marketing cloud connector | I53: Saji Gunasekaran | J53: 2024-10-31T02:39:18.000+0000 | K53: 45 Millwrights Place, Temple Back, Bristol | L53: GREP-CoA Carin Madeleine Selenius & Matthew Kizintas - 45 Millwrights Place, Temple Back, Bristol | M53: a1GNz0000019GzRMAU | N53: 45 Millwrights Place, Temple Back, Bristol | O53: Millwrights Place, Bristol Bristol BS1 | P53: =N53=K53 -> TRUE | Q53: =COUNTIF($B$2:$B$1196,B53) -> 1 | R53: =COUNTIF($H$2:$H$1196,H53) -> 0 | S53: =COUNTIF($D$2:$D$1196,D53) -> 1
A54: a1kNz000003ObeEIAS | B54: 511034863 | C54: 003Nz00000CSNyuIAH | D54: 006Nz00000A1zQHIAZ | E54: Month 3: How can we make things better (Specification) Survey | F54: 2024-09-05T22:31:00.000+0000 | G54: marketing cloud connector | H54: GREP-CoA Scott Tham, Delia Kong - 134 Nautilus Apts, 1 Jam Lane, London | I54: Saji Gunasekaran | J54: 2024-10-31T02:39:18.000+0000 | K54: 134 Nautilus Apts, 1 Jam Lane, London | L54: GREP-CoA Scott Tham, Delia Kong - 134 Nautilus Apts, 1 Jam Lane, London | M54: a1G8d000002QBMWEA4 | N54: 134 Nautilus Apts, 1 Jam Lane, London | O54: Fortunes Dock, Canning Town London E16 | P54: =N54=K54 -> TRUE | Q54: =COUNTIF($B$2:$B$1196,B54) -> 1 | R54: =COUNTIF($H$2:$H$1196,H54) -> 1 | S54: =COUNTIF($D$2:$D$1196,D54) -> 1
A55: a1kNz000003ObeDIAS | B55: 509567230 | C55: 003Nz00000CAzcsIAD | D55: 006Nz000009xwZ4IAI | E55: Month 3: How can we make things better (Specification) Survey | F55: 2024-09-05T22:31:00.000+0000 | G55: marketing cloud connector | H55: GREP-CoA Kurtis Lowe, Omar Qasim, Elise Anderson, Caitlin Fox Davis - 32a The Gardens, GF, London SE22 9QF | I55: Saji Gunasekaran | J55: 2024-10-31T02:39:18.000+0000 | K55: 32a The Gardens, GF, London SE22 9QF | L55: GREP-CoA Kurtis Lowe, Omar Qasim, Elise Anderson, Caitlin Fox Davis - 32a The Gardens, GF, London SE22 9QF | M55: a1G4J0000025zj1UAA | N55: 32a The Gardens, GF, London SE22 9QF | O55: The Gardens, East Dulwich London SE22 | P55: =N55=K55 -> TRUE | Q55: =COUNTIF($B$2:$B$1196,B55) -> 1 | R55: =COUNTIF($H$2:$H$1196,H55) -> 1 | S55: =COUNTIF($D$2:$D$1196,D55) -> 1
A56: a1kNz000003eFNMIA2 | B56: 477384768 | E56: Month 3: How can we make things better (Specification) Survey | F56: 2024-09-05T02:02:27.000+0000 | G56: Saji Gunasekaran | H56: GREP-CoA Mirabel Greenaway & Francis Walsh - 509 Torrens Apt, Waterman Wlk, Salford M50 | I56: Saji Gunasekaran | J56: 2024-10-31T02:39:18.000+0000 | K56: 509 Torrens Apt, Waterman Wlk, Salford M50 | P56: =N56=K56 -> FALSE | Q56: =COUNTIF($B$2:$B$1196,B56) -> 1 | R56: =COUNTIF($H$2:$H$1196,H56) -> 1 | S56: =COUNTIF($D$2:$D$1196,D56) -> 0
A57: a1kNz000003NgZVIA0 | B57: 507316473 | C57: 003Nz00000Bi9cNIAR | D57: 006Nz000009jMbwIAE | E57: Month 3: How can we make things better (Specification) Survey | F57: 2024-09-04T22:31:50.000+0000 | G57: marketing cloud connector | H57: GREP-CoA George Hill & Anna Campbell - 305, Lamp House, 215 Chapel St, Salford, M3 5 | I57: Saji Gunasekaran | J57: 2024-10-31T02:39:18.000+0000 | K57: 305, Lamp House, 215 Chapel St, Salford, M3 5 | L57: GREP-CoA George Hill & Anna Campbell - 305, Lamp House, 215 Chapel St, Salford, M3 5 | M57: a1G4J0000025yKpUAI | N57: 305, Lamp House, 215 Chapel St, Salford, M3 5 | O57: The Filaments, Salford Salford M3 | P57: =N57=K57 -> TRUE | Q57: =COUNTIF($B$2:$B$1196,B57) -> 1 | R57: =COUNTIF($H$2:$H$1196,H57) -> 1 | S57: =COUNTIF($D$2:$D$1196,D57) -> 1
A58: a1kNz000003eFNBIA2 | B58: 467767890 | E58: Month 3: How can we make things better (Specification) Survey | F58: 2024-09-04T02:03:20.000+0000 | G58: Saji Gunasekaran | H58: GREP-CoA Mr Azeez, Miss Thomas & Mrs Saidali Mr Ramachandran - 12, Rosemary Lane, Hampshire, PO7 | I58: Saji Gunasekaran | J58: 2024-10-31T02:39:18.000+0000 | K58: 12, Rosemary Lane, Hampshire, PO7 | P58: =N58=K58 -> FALSE | Q58: =COUNTIF($B$2:$B$1196,B58) -> 1 | R58: =COUNTIF($H$2:$H$1196,H58) -> 1 | S58: =COUNTIF($D$2:$D$1196,D58) -> 0
A59: a1kNz000003eFM3IAM | B59: 445764681 | E59: Month 3: How can we make things better (Specification) Survey | F59: 2024-09-01T03:03:07.000+0000 | G59: Saji Gunasekaran | H59: RENEWAL - 85 Nautilus Apartments - 04.10.2024 | I59: Saji Gunasekaran | J59: 2024-10-31T02:39:18.000+0000 | K59: 85 Nautilus Apts, 1 Jam Lane , London | P59: =N59=K59 -> FALSE | Q59: =COUNTIF($B$2:$B$1196,B59) -> 1 | R59: =COUNTIF($H$2:$H$1196,H59) -> 1 | S59: =COUNTIF($D$2:$D$1196,D59) -> 0
A60: a1kNz000003eFM5IAM | B60: 444272745 | E60: Month 3: How can we make things better (Specification) Survey | F60: 2024-09-01T03:01:45.000+0000 | G60: Saji Gunasekaran | H60: Renewal 28, Gilders Yard - 11/10/2024 | I60: Saji Gunasekaran | J60: 2024-10-31T02:39:18.000+0000 | K60: 28, Gilders Yard, 14 Great Hampton St, Birm | P60: =N60=K60 -> FALSE | Q60: =COUNTIF($B$2:$B$1196,B60) -> 1 | R60: =COUNTIF($H$2:$H$1196,H60) -> 1 | S60: =COUNTIF($D$2:$D$1196,D60) -> 0
A61: a1kNz000003K2lVIAS | B61: 514457897 | C61: 003Nz00000DFqQFIA1 | D61: 006Nz00000AWd28IAD | E61: Month 3: How can we make things better (Specification) Survey | F61: 2024-08-30T22:31:04.000+0000 | G61: marketing cloud connector | I61: Saji Gunasekaran | J61: 2024-09-02T09:26:12.000+0000 | K61: 401, 5 Capital Quarter, Tyndall St., Cardiff | L61: GREP-CoA Jessica Debono and Lydia Anne Tibbet - 401, 5 Capital Quarter, Tyndall St., Cardiff | M61: a1GNz0000000cZxMAI | N61: 401, 5 Capital Quarter, Tyndall St., Cardiff | O61: The Copper Works, Cardiff Cardiff CF10 | P61: =N61=K61 -> TRUE | Q61: =COUNTIF($B$2:$B$1196,B61) -> 1 | R61: =COUNTIF($H$2:$H$1196,H61) -> 0 | S61: =COUNTIF($D$2:$D$1196,D61) -> 1
A62: a1kNz000003eFOjIAM | B62: 511739765 | E62: Month 3: How can we make things better (Specification) Survey | F62: 2024-08-30T02:03:06.000+0000 | G62: Saji Gunasekaran | I62: Saji Gunasekaran | J62: 2024-09-19T23:16:26.000+0000 | P62: =N62=K62 -> TRUE | Q62: =COUNTIF($B$2:$B$1196,B62) -> 1 | R62: =COUNTIF($H$2:$H$1196,H62) -> 0 | S62: =COUNTIF($D$2:$D$1196,D62) -> 0
A63: a1kNz000003JD6HIAW | B63: 410441041 | C63: 003Nz000000WsF2IAK | D63: 006Nz00000B7cTfIAJ | E63: Month 3: How can we make things better (Specification) Survey | F63: 2024-08-29T22:31:08.000+0000 | G63: marketing cloud connector | I63: Saji Gunasekaran | J63: 2024-09-02T11:22:50.000+0000 | K63: 603 Ambassador Apt, Waterman Wlk, Salford M50 | L63: GREP-CoA Archie Gardiner, Isobel Fox & Kameron Cherry - 603 Ambassador Apt, Waterman Wlk, Salford M50 | M63: a1G4J0000025ykLUAQ | N63: 603 Ambassador Apt, Waterman Wlk, Salford M50 | O63: Clippers Quay Salford M50 | P63: =N63=K63 -> TRUE | Q63: =COUNTIF($B$2:$B$1196,B63) -> 1 | R63: =COUNTIF($H$2:$H$1196,H63) -> 0 | S63: =COUNTIF($D$2:$D$1196,D63) -> 1
A64: a1kNz000003eFOlIAM | B64: 519968969 | E64: Month 3: How can we make things better (Specification) Survey | F64: 2024-08-29T02:03:11.000+0000 | G64: Saji Gunasekaran | H64: GREP-CoA Sophia Bertilla Poletto,Ria Dhawan - Flat 6, The Astley, 61 Houldsworth St, Manc | I64: Saji Gunasekaran | J64: 2024-10-02T21:45:01.000+0000 | K64: Flat 6, The Astley, 61 Houldsworth St, Manc | P64: =N64=K64 -> FALSE | Q64: =COUNTIF($B$2:$B$1196,B64) -> 1 | R64: =COUNTIF($H$2:$H$1196,H64) -> 1 | S64: =COUNTIF($D$2:$D$1196,D64) -> 0
A65: a1kNz000003eFOkIAM | B65: 507794497 | E65: Month 3: How can we make things better (Specification) Survey | F65: 2024-08-29T02:01:46.000+0000 | G65: Saji Gunasekaran | H65: GREP-CoA Chukwuemeka Maduabum and Esther Iwoh - 101, 5 Capital Quarter, Tyndall St., Cardiff | I65: Saji Gunasekaran | J65: 2024-10-02T21:45:01.000+0000 | K65: 101, 5 Capital Quarter, Tyndall St., Cardiff | P65: =N65=K65 -> FALSE | Q65: =COUNTIF($B$2:$B$1196,B65) -> 1 | R65: =COUNTIF($H$2:$H$1196,H65) -> 1 | S65: =COUNTIF($D$2:$D$1196,D65) -> 0
A66: a1kNz000003GEGcIAO | B66: 516378915 | C66: 003Nz00000Dgh98IAB | D66: 006Nz00000B2Qg1IAF | E66: Month 3: How can we make things better (Specification) Survey | F66: 2024-08-28T22:30:59.000+0000 | G66: marketing cloud connector | I66: marketing cloud connector | J66: 2024-08-28T22:30:59.000+0000 | K66: <a href="a1GNz000001HRhZ" target="_blank">1707 The Silver Yard, 100 Moor St Queensway</a> | L66: GREP-CoA Daniel Clark and Grace Mead - 1707 The Silver Yard, 100 Moor St Queensway | M66: a1GNz000001HRhZMAW | N66: 1707 The Silver Yard, 100 Moor St Queensway | O66: The Silver Yard, Birmingham Birmingham B4 | P66: =N66=K66 -> FALSE | Q66: =COUNTIF($B$2:$B$1196,B66) -> 1 | R66: =COUNTIF($H$2:$H$1196,H66) -> 0 | S66: =COUNTIF($D$2:$D$1196,D66) -> 1
A67: a1kNz000003GEGbIAO | B67: 511499577 | C67: 003Nz00000Cc1llIAB | D67: 006Nz00000ALXWIIA5 | E67: Month 3: How can we make things better (Specification) Survey | F67: 2024-08-28T22:30:59.000+0000 | G67: marketing cloud connector | I67: Saji Gunasekaran | J67: 2024-09-02T09:27:58.000+0000 | K67: Flat 5 Eagle House, Eagle Wharf Road, London, | L67: GREP-CoA Josie Cyrus - Flat 5 Eagle House, Eagle Wharf Road, London, | M67: a1G4J0000025zndUAA | N67: Flat 5 Eagle House, Eagle Wharf Road, London, | O67: Eagle House, Islington London N1 | P67: =N67=K67 -> TRUE | Q67: =COUNTIF($B$2:$B$1196,B67) -> 1 | R67: =COUNTIF($H$2:$H$1196,H67) -> 0 | S67: =COUNTIF($D$2:$D$1196,D67) -> 1
A68: a1kNz000003FJTdIAO | B68: 517820092 | C68: 003Nz00000Dze7WIAR | D68: 006Nz00000Al1SjIAJ | E68: Month 3: How can we make things better (Specification) Survey | F68: 2024-08-27T22:30:30.000+0000 | G68: marketing cloud connector | H68: GREP-CoA Jaspreet Kaur Ghuman, Chloe Self and Trina Persyn - 206, Neon House, 207 Chapel St, Salford, M3 5 | I68: Saji Gunasekaran | J68: 2024-09-02T09:29:26.000+0000 | K68: 206, Neon House, 207 Chapel St, Salford, M3 | L68: GREP-CoA Jaspreet Kaur Ghuman, Chloe Self and Trina Persyn - 206, Neon House, 207 Chapel St, Salford, M3 5 | M68: a1G4J0000025yF6UAI | N68: 206, Neon House, 207 Chapel St, Salford, M3 5 | O68: The Filaments, Salford Salford M3 | P68: =N68=K68 -> FALSE | Q68: =COUNTIF($B$2:$B$1196,B68) -> 1 | R68: =COUNTIF($H$2:$H$1196,H68) -> 1 | S68: =COUNTIF($D$2:$D$1196,D68) -> 1
A69: a1kNz000003ECafIAG | B69: 412139820 | C69: 003Nz000000dIjUIAU | D69: 006Nz00000BHETFIA5 | E69: Month 3: How can we make things better (Specification) Survey | F69: 2024-08-25T22:31:11.000+0000 | G69: marketing cloud connector | I69: Saji Gunasekaran | J69: 2024-09-02T09:31:34.000+0000 | K69: 804 South, The Forge, Newcastle, NE1 3AR | L69: GREP-CoA Emily Monk, Esther Beales & Rachel Dawson - 804 South, The Forge, Newcastle, NE1 3AR | M69: a1G8d0000004DGwEAM | N69: 804 South, The Forge, Newcastle, NE1 3AR | O69: The Forge, Newcastle Newcastle upon Tyne NE1 | P69: =N69=K69 -> TRUE | Q69: =COUNTIF($B$2:$B$1196,B69) -> 1 | R69: =COUNTIF($H$2:$H$1196,H69) -> 0 | S69: =COUNTIF($D$2:$D$1196,D69) -> 1
A70: a1kNz000003ECagIAG | B70: 507559547 | C70: 003Nz00000Bl6zjIAB | D70: 006Nz000009lQgFIAU | E70: Month 3: How can we make things better (Specification) Survey | F70: 2024-08-25T22:31:11.000+0000 | G70: marketing cloud connector | I70: Saji Gunasekaran | J70: 2024-09-02T09:32:09.000+0000 | K70: 207 Neon House, 207 Chapel St, Salford, M3 5P | L70: GREP-CoA Kevin Meurling & Nasir Kakar - 207 Neon House, 207 Chapel St, Salford, M3 5P | M70: a1G4J0000025yibUAA | N70: 207 Neon House, 207 Chapel St, Salford, M3 5P | O70: The Filaments, Salford Salford M3 | P70: =N70=K70 -> TRUE | Q70: =COUNTIF($B$2:$B$1196,B70) -> 1 | R70: =COUNTIF($H$2:$H$1196,H70) -> 0 | S70: =COUNTIF($D$2:$D$1196,D70) -> 1
A71: a1kNz000003eFOhIAM | B71: 516837847 | E71: Month 3: How can we make things better (Specification) Survey | F71: 2024-08-25T02:02:12.000+0000 | G71: Saji Gunasekaran | I71: Saji Gunasekaran | J71: 2024-09-19T23:16:26.000+0000 | P71: =N71=K71 -> TRUE | Q71: =COUNTIF($B$2:$B$1196,B71) -> 1 | R71: =COUNTIF($H$2:$H$1196,H71) -> 0 | S71: =COUNTIF($D$2:$D$1196,D71) -> 0
A72: a1kNz000003eFOiIAM | B72: 274234728 | E72: Month 3: How can we make things better (Specification) Survey | F72: 2024-08-25T02:01:47.000+0000 | G72: Saji Gunasekaran | H72: Renewal 104 Syren Apt 23/05/2024 | I72: Saji Gunasekaran | J72: 2024-10-02T21:45:01.000+0000 | K72: 104 Syren Apt , Ottinger Close, Salford M50 | P72: =N72=K72 -> FALSE | Q72: =COUNTIF($B$2:$B$1196,B72) -> 1 | R72: =COUNTIF($H$2:$H$1196,H72) -> 1 | S72: =COUNTIF($D$2:$D$1196,D72) -> 0
A73: a1kNz000003DxVBIA0 | B73: 505597616 | C73: 003Nz00000BOPlLIAX | D73: 006Nz000009UrPtIAK | E73: Month 3: How can we make things better (Specification) Survey | F73: 2024-08-23T22:30:56.000+0000 | G73: marketing cloud connector | I73: Saji Gunasekaran | J73: 2024-09-02T09:33:07.000+0000 | K73: FLAT 96, Hawkins Ln, Finzels Reach, Bristol, | L73: GREP-CoA Sam Raine - FLAT 96, Hawkins Ln, Finzels Reach, Bristol, | M73: a1G4J0000025yyJUAQ | N73: FLAT 96, Hawkins Ln, Finzels Reach, Bristol, | O73: Hawkins & George, Bristol Bristol BS1 | P73: =N73=K73 -> TRUE | Q73: =COUNTIF($B$2:$B$1196,B73) -> 1 | R73: =COUNTIF($H$2:$H$1196,H73) -> 0 | S73: =COUNTIF($D$2:$D$1196,D73) -> 1
A74: a1kNz000003DgUNIA0 | B74: 210056845 | C74: 0034J00000a4gSfQAI | D74: 0064J00000FV0nKQAT | E74: Month 3: How can we make things better (Specification) Survey | F74: 2024-08-22T22:30:52.000+0000 | G74: marketing cloud connector | I74: Saji Gunasekaran | J74: 2024-09-02T11:23:14.000+0000 | K74: 306 Tayleur Apt , Waterman Wlk, Salford M50 | L74: GREP-CoA Dorcelin Mcatamney - 306 Tayleur Apt , Waterman Wlk, Salford M50 | M74: a1G4J0000025yM8UAI | N74: 306 Tayleur Apt , Waterman Wlk, Salford M50 | O74: Clippers Quay Salford M50 | P74: =N74=K74 -> TRUE | Q74: =COUNTIF($B$2:$B$1196,B74) -> 1 | R74: =COUNTIF($H$2:$H$1196,H74) -> 0 | S74: =COUNTIF($D$2:$D$1196,D74) -> 1
A75: a1kNz000003DgUMIA0 | B75: 508095020 | C75: 003Nz00000BsX7EIAV | D75: 006Nz000009njy7IAA | E75: Month 3: How can we make things better (Specification) Survey | F75: 2024-08-22T22:30:52.000+0000 | G75: marketing cloud connector | H75: GREP-CoA Matthew James Hall and Miyuki Takahashi - 1113, 5 Capital Quarter, Tyndall St., Cardiff | I75: Saji Gunasekaran | J75: 2024-09-02T09:34:05.000+0000 | K75: 1113, 5 Capital Quarter, Tyndall St., Cardiff | L75: GREP-CoA Matthew James Hall and Miyuki Takahashi - 1113, 5 Capital Quarter, Tyndall St., Cardiff | M75: a1GNz0000000e77MAA | N75: 1113, 5 Capital Quarter, Tyndall St., Cardiff | O75: The Copper Works, Cardiff Cardiff CF10 | P75: =N75=K75 -> TRUE | Q75: =COUNTIF($B$2:$B$1196,B75) -> 1 | R75: =COUNTIF($H$2:$H$1196,H75) -> 1 | S75: =COUNTIF($D$2:$D$1196,D75) -> 1
A76: a1kNz000003DgULIA0 | B76: 517585939 | C76: 003Nz00000DwS7hIAF | D76: 006Nz00000BEbFvIAL | E76: Month 3: How can we make things better (Specification) Survey | F76: 2024-08-22T22:30:52.000+0000 | G76: marketing cloud connector | H76: GREP-CoA Max Goodwin and Alicia Platts - 615 Torrens Apt, Waterman Wlk, Salford M50 | I76: Saji Gunasekaran | J76: 2024-09-02T09:33:36.000+0000 | K76: 615 Torrens Apt, Waterman Wlk, Salford M50 | L76: GREP-CoA Max Goodwin and Alicia Platts - 615 Torrens Apt, Waterman Wlk, Salford M50 | M76: a1G4J0000025zDdUAI | N76: 615 Torrens Apt, Waterman Wlk, Salford M50 | O76: Clippers Quay Salford M50 | P76: =N76=K76 -> TRUE | Q76: =COUNTIF($B$2:$B$1196,B76) -> 1 | R76: =COUNTIF($H$2:$H$1196,H76) -> 1 | S76: =COUNTIF($D$2:$D$1196,D76) -> 1
A77: a1kNz000003CmjtIAC | B77: 383870515 | C77: 0038d000004XYOZAA4 | D77: 006Nz00000BHJj6IAH | E77: Month 3: How can we make things better (Specification) Survey | F77: 2024-08-20T22:30:37.000+0000 | G77: marketing cloud connector | I77: Saji Gunasekaran | J77: 2024-09-02T09:36:39.000+0000 | K77: 820 Enigma Square, 414 North Row, MK9 2GF | L77: GREP-CoA Aditi Kapoor - 820 Enigma Square, 414 North Row, MK9 2GF | M77: a1G8d0000005rO3EAI | N77: 820 Enigma Square, 414 North Row, MK9 2GF | O77: Enigma Square, Milton Keynes Milton Keynes MK9 | P77: =N77=K77 -> TRUE | Q77: =COUNTIF($B$2:$B$1196,B77) -> 1 | R77: =COUNTIF($H$2:$H$1196,H77) -> 0 | S77: =COUNTIF($D$2:$D$1196,D77) -> 1
A78: a1kNz000003eFOgIAM | B78: 513229428 | E78: Month 3: How can we make things better (Specification) Survey | F78: 2024-08-20T02:03:14.000+0000 | G78: Saji Gunasekaran | H78: GREP-CoA Raghu Kandagatla - 9, East Quarter, 2 Ridgway Street, M4 7LB | I78: Saji Gunasekaran | J78: 2024-10-02T21:45:01.000+0000 | K78: 9, East Quarter, 2 Ridgway Street, M4 7LB | P78: =N78=K78 -> FALSE | Q78: =COUNTIF($B$2:$B$1196,B78) -> 1 | R78: =COUNTIF($H$2:$H$1196,H78) -> 1 | S78: =COUNTIF($D$2:$D$1196,D78) -> 0
A79: a1kNz000003BoZFIA0 | B79: 511267792 | C79: 003Nz00000CX9buIAD | D79: 006Nz00000AIgcXIAT | E79: Month 3: How can we make things better (Specification) Survey | F79: 2024-08-18T22:30:49.000+0000 | G79: marketing cloud connector | H79: GREP-CoA Pui Ki Ho & Yiu Wai Fung - 409 Ambassador Apt, Waterman Wlk, Salford M50 | I79: Saji Gunasekaran | J79: 2024-09-02T11:22:24.000+0000 | K79: 409 Ambassador Apt, Waterman Wlk, Salford M50 | L79: GREP-CoA Pui Ki Ho & Yiu Wai Fung - 409 Ambassador Apt, Waterman Wlk, Salford M50 | M79: a1G4J0000025yu2UAA | N79: 409 Ambassador Apt, Waterman Wlk, Salford M50 | O79: Clippers Quay Salford M50 | P79: =N79=K79 -> TRUE | Q79: =COUNTIF($B$2:$B$1196,B79) -> 1 | R79: =COUNTIF($H$2:$H$1196,H79) -> 1 | S79: =COUNTIF($D$2:$D$1196,D79) -> 1
A80: a1kNz000003eFOfIAM | B80: 514912880 | E80: Month 3: How can we make things better (Specification) Survey | F80: 2024-08-18T02:02:17.000+0000 | G80: Saji Gunasekaran | I80: Saji Gunasekaran | J80: 2024-09-19T23:16:26.000+0000 | P80: =N80=K80 -> TRUE | Q80: =COUNTIF($B$2:$B$1196,B80) -> 1 | R80: =COUNTIF($H$2:$H$1196,H80) -> 0 | S80: =COUNTIF($D$2:$D$1196,D80) -> 0
A81: a1kNz000003AQsMIAW | B81: 504413180 | C81: 003Nz00000B8MWWIA3 | D81: 006Nz000009JbgEIAS | E81: Month 3: How can we make things better (Specification) Survey | F81: 2024-08-15T22:30:57.000+0000 | G81: marketing cloud connector | I81: Saji Gunasekaran | J81: 2024-09-02T09:40:37.000+0000 | K81: 705 Syren Apt , Ottinger Close, Salford M50 | L81: GREP-CoA Anthony Kar Wah Chang & Kit Shan Ko - 705 Syren Apt , Ottinger Close, Salford M50 | M81: a1G4J0000025xBmUAI | N81: 705 Syren Apt , Ottinger Close, Salford M50 | O81: Clippers Quay Salford M50 | P81: =N81=K81 -> TRUE | Q81: =COUNTIF($B$2:$B$1196,B81) -> 1 | R81: =COUNTIF($H$2:$H$1196,H81) -> 0 | S81: =COUNTIF($D$2:$D$1196,D81) -> 1
A82: a1kNz000003AQsLIAW | B82: 516137169 | C82: 003Nz00000DbNPbIAN | D82: 006Nz00000AzhjrIAB | E82: Month 3: How can we make things better (Specification) Survey | F82: 2024-08-15T22:30:57.000+0000 | G82: marketing cloud connector | H82: GREP-CoA Louise Henderson - 915 Torrens Apt, Waterman Wlk, Salford M50 | I82: Saji Gunasekaran | J82: 2024-09-02T09:40:03.000+0000 | K82: 915 Torrens Apt, Waterman Wlk, Salford M50 | L82: GREP-CoA Louise Henderson - 915 Torrens Apt, Waterman Wlk, Salford M50 | M82: a1G4J0000025ys9UAA | N82: 915 Torrens Apt, Waterman Wlk, Salford M50 | O82: Clippers Quay Salford M50 | P82: =N82=K82 -> TRUE | Q82: =COUNTIF($B$2:$B$1196,B82) -> 1 | R82: =COUNTIF($H$2:$H$1196,H82) -> 1 | S82: =COUNTIF($D$2:$D$1196,D82) -> 1
A83: a1kNz000003eFOeIAM | B83: 510798175 | E83: Month 3: How can we make things better (Specification) Survey | F83: 2024-08-14T02:02:02.000+0000 | G83: Saji Gunasekaran | H83: GREP-CoA Flora Hellman, Eleanor Crawford, Poppy Saraby - 2B Shillington Old School | I83: Saji Gunasekaran | J83: 2024-10-02T21:45:01.000+0000 | K83: 2B Shillington Old School | P83: =N83=K83 -> FALSE | Q83: =COUNTIF($B$2:$B$1196,B83) -> 1 | R83: =COUNTIF($H$2:$H$1196,H83) -> 1 | S83: =COUNTIF($D$2:$D$1196,D83) -> 0
A84: a1kNz0000037j57IAA | B84: 305268178 | C84: 0038d00000Cte8LAAR | D84: 006Nz000000YtZxIAK | E84: Month 3: How can we make things better (Specification) Survey | F84: 2024-08-11T22:30:47.000+0000 | G84: marketing cloud connector | I84: Saji Gunasekaran | J84: 2024-09-02T09:41:07.000+0000 | K84: 16, Ancoats, 2 Butler Street, M4 6BZ | L84: GREP-CoA Ka Yip & Fung Chow - 16, Ancoats, 2 Butler Street, M4 6BZ | M84: a1G4J0000025xskUAA | N84: 16, Ancoats, 2 Butler Street, M4 6BZ | O84: The Tribe, Ancoats, Manchester Manchester M4 | P84: =N84=K84 -> TRUE | Q84: =COUNTIF($B$2:$B$1196,B84) -> 1 | R84: =COUNTIF($H$2:$H$1196,H84) -> 0 | S84: =COUNTIF($D$2:$D$1196,D84) -> 1
A85: a1kNz0000037j58IAA | B85: 504881567 | C85: 003Nz00000BGHWPIA5 | D85: 006Nz000009PkDlIAK | E85: Month 3: How can we make things better (Specification) Survey | F85: 2024-08-11T22:30:47.000+0000 | G85: marketing cloud connector | H85: GREP-CoA Ting Ting Tammy Cheung, Wai Yin Vivien Ha - 1004,The Headline, Wellington Park Way, Leeds | I85: Saji Gunasekaran | J85: 2024-09-02T09:41:50.000+0000 | K85: 1004,The Headline, Wellington Park Way, Leeds | L85: GREP-CoA Ting Ting Tammy Cheung, Wai Yin Vivien Ha - 1004,The Headline, Wellington Park Way, Leeds | M85: a1G4J000004jys8UAA | N85: 1004,The Headline, Wellington Park Way, Leeds | O85: The Headline, Leeds Leeds LS1 | P85: =N85=K85 -> TRUE | Q85: =COUNTIF($B$2:$B$1196,B85) -> 1 | R85: =COUNTIF($H$2:$H$1196,H85) -> 2 | S85: =COUNTIF($D$2:$D$1196,D85) -> 2
A86: a1kNz0000037j59IAA | B86: 506063107 | C86: 003Nz00000BVOZCIA5 | D86: 006Nz000009PkDlIAK | E86: Month 3: How can we make things better (Specification) Survey | F86: 2024-08-11T22:30:47.000+0000 | G86: marketing cloud connector | H86: GREP-CoA Ting Ting Tammy Cheung, Wai Yin Vivien Ha - 1004,The Headline, Wellington Park Way, Leeds | I86: Saji Gunasekaran | J86: 2024-09-02T09:42:31.000+0000 | K86: 1004,The Headline, Wellington Park Way, Leeds | L86: GREP-CoA Ting Ting Tammy Cheung, Wai Yin Vivien Ha - 1004,The Headline, Wellington Park Way, Leeds | M86: a1G4J000004jys8UAA | N86: 1004,The Headline, Wellington Park Way, Leeds | O86: The Headline, Leeds Leeds LS1 | P86: =N86=K86 -> TRUE | Q86: =COUNTIF($B$2:$B$1196,B86) -> 1 | R86: =COUNTIF($H$2:$H$1196,H86) -> 2 | S86: =COUNTIF($D$2:$D$1196,D86) -> 2
A87: a1kNz000003eFOpIAM | B87: 518299742 | E87: Month 3: How can we make things better (Specification) Survey | F87: 2024-08-09T02:01:34.000+0000 | G87: Saji Gunasekaran | I87: Saji Gunasekaran | J87: 2024-09-19T23:16:26.000+0000 | P87: =N87=K87 -> TRUE | Q87: =COUNTIF($B$2:$B$1196,B87) -> 1 | R87: =COUNTIF($H$2:$H$1196,H87) -> 0 | S87: =COUNTIF($D$2:$D$1196,D87) -> 0
A88: a1kNz00000376yDIAQ | B88: 500797090 | C88: 003Nz00000AIFsTIAX | D88: 006Nz000008kAJCIA2 | E88: Month 3: How can we make things better (Specification) Survey | F88: 2024-08-08T22:30:51.000+0000 | G88: marketing cloud connector | H88: GREP-CoA Goncalo Mata, Juliana Nogueira - 109 Gatehouse Apts, 86 East St, Southampton | I88: Saji Gunasekaran | J88: 2024-09-02T11:28:17.000+0000 | K88: 109 Gatehouse Apts, 86 East St, Southampton | L88: GREP-CoA Goncalo Mata, Juliana Nogueira - 109 Gatehouse Apts, 86 East St, Southampton | M88: a1G4J0000025ySLUAY | N88: 109 Gatehouse Apts, 86 East St, Southampton | O88: Gatehouse Apartments, Southampton Southampton SO14 | P88: =N88=K88 -> TRUE | Q88: =COUNTIF($B$2:$B$1196,B88) -> 1 | R88: =COUNTIF($H$2:$H$1196,H88) -> 1 | S88: =COUNTIF($D$2:$D$1196,D88) -> 1
A89: a1kNz000003eFNLIA2 | B89: 486955185 | E89: Month 3: How can we make things better (Specification) Survey | F89: 2024-08-05T02:02:11.000+0000 | G89: Saji Gunasekaran | I89: Saji Gunasekaran | J89: 2024-09-19T23:16:26.000+0000 | P89: =N89=K89 -> TRUE | Q89: =COUNTIF($B$2:$B$1196,B89) -> 1 | R89: =COUNTIF($H$2:$H$1196,H89) -> 0 | S89: =COUNTIF($D$2:$D$1196,D89) -> 0
A90: a1kNz0000033YhmIAE | B90: 514679292 | C90: 003Nz00000DIUxuIAH | D90: 006Nz00000Alz2IIAR | E90: Month 3: How can we make things better (Specification) Survey | F90: 2024-08-04T22:31:11.000+0000 | G90: marketing cloud connector | I90: Saji Gunasekaran | J90: 2024-09-02T11:21:56.000+0000 | K90: 504 Syren Apt , Ottinger Close, Salford M50 | L90: GREP-CoA M Cheng, P F Cheng, P C Cheng & P H Cheng - 504 Syren Apt , Ottinger Close, Salford M50 | M90: a1G4J0000025xyCUAQ | N90: 504 Syren Apt , Ottinger Close, Salford M50 | O90: Clippers Quay Salford M50 | P90: =N90=K90 -> TRUE | Q90: =COUNTIF($B$2:$B$1196,B90) -> 1 | R90: =COUNTIF($H$2:$H$1196,H90) -> 0 | S90: =COUNTIF($D$2:$D$1196,D90) -> 1
A91: a1kNz000003eFNCIA2 | B91: 485162486 | E91: Month 3: How can we make things better (Specification) Survey | F91: 2024-08-04T02:01:29.000+0000 | G91: Saji Gunasekaran | H91: GREP-CoA Scott Robertson - Parking space 11, 23 Queens Road, Nottingham | I91: Saji Gunasekaran | J91: 2024-10-02T21:45:01.000+0000 | K91: Parking space 11, 23 Queens Road, Nottingham | P91: =N91=K91 -> FALSE | Q91: =COUNTIF($B$2:$B$1196,B91) -> 2 | R91: =COUNTIF($H$2:$H$1196,H91) -> 1 | S91: =COUNTIF($D$2:$D$1196,D91) -> 0
A92: a1kNz0000033429IAA | B92: 510045017 | C92: 003Nz00000CIhxGIAT | D92: 006Nz00000A8kb1IAB | E92: Month 3: How can we make things better (Specification) Survey | F92: 2024-08-02T22:30:58.000+0000 | G92: marketing cloud connector | I92: Saji Gunasekaran | J92: 2024-09-02T11:21:34.000+0000 | K92: 625 The Barnum, 23 Queens Road, Nottingham | L92: GREP-CoA Carol George - 625 The Barnum, 23 Queens Road, Nottingham | M92: a1GNz000000163OMAQ | N92: 625 The Barnum, 23 Queens Road, Nottingham | O92: The Barnum, Nottingham Nottingham NG2 | P92: =N92=K92 -> TRUE | Q92: =COUNTIF($B$2:$B$1196,B92) -> 1 | R92: =COUNTIF($H$2:$H$1196,H92) -> 0 | S92: =COUNTIF($D$2:$D$1196,D92) -> 1
A93: a1kNz000002rG0fIAE | B93: 509108171 | C93: 003Nz00000C5O9GIAV | D93: 006Nz000005n2gwIAA | E93: Month 3: How can we make things better (Specification) Survey | F93: 2024-08-01T22:30:39.000+0000 | G93: marketing cloud connector | I93: Saji Gunasekaran | J93: 2024-09-02T11:21:00.000+0000 | K93: 417 The Barnum, 23 Queens Road, Nottingham | L93: GREP-CoA William Pikett & Zoe Labarrere - 417 The Barnum, 23 Queens Road, Nottingham | M93: a1GNz00000017kDMAQ | N93: 417 The Barnum, 23 Queens Road, Nottingham | O93: The Barnum, Nottingham Nottingham NG2 | P93: =N93=K93 -> TRUE | Q93: =COUNTIF($B$2:$B$1196,B93) -> 1 | R93: =COUNTIF($H$2:$H$1196,H93) -> 0 | S93: =COUNTIF($D$2:$D$1196,D93) -> 1
A94: a1kNz000003eFM2IAM | B94: 446831917 | E94: Month 3: How can we make things better (Specification) Survey | F94: 2024-08-01T03:02:08.000+0000 | G94: Saji Gunasekaran | I94: Saji Gunasekaran | J94: 2024-09-19T23:16:26.000+0000 | P94: =N94=K94 -> TRUE | Q94: =COUNTIF($B$2:$B$1196,B94) -> 1 | R94: =COUNTIF($H$2:$H$1196,H94) -> 0 | S94: =COUNTIF($D$2:$D$1196,D94) -> 0
A95: a1kNz000003eFM1IAM | B95: 446824865 | E95: Month 3: How can we make things better (Specification) Survey | F95: 2024-08-01T03:02:08.000+0000 | G95: Saji Gunasekaran | H95: Renewal 217 The Condor - 10/10/2024 | I95: Saji Gunasekaran | J95: 2024-10-02T21:45:01.000+0000 | K95: 217 The Condor, 1 Springwell Sq | P95: =N95=K95 -> FALSE | Q95: =COUNTIF($B$2:$B$1196,B95) -> 1 | R95: =COUNTIF($H$2:$H$1196,H95) -> 1 | S95: =COUNTIF($D$2:$D$1196,D95) -> 0
A96: a1kNz000002qtC9IAI | B96: 512747822 | C96: 003Nz00000CriNPIAZ | D96: 006Nz00000AW4ikIAD | E96: Month 3: How can we make things better (Specification) Survey | F96: 2024-07-31T22:31:07.000+0000 | G96: marketing cloud connector | I96: Saji Gunasekaran | J96: 2024-08-06T10:26:28.000+0000 | K96: 117, Brook Place Apts, Sheffield, S11 8BR | L96: GREP-CoA Chloe Brown - 117, Brook Place Apts, Sheffield, S11 8BR | M96: a1G4J0000025zJmUAI | N96: 117, Brook Place Apts, Sheffield, S11 8BR | O96: Brook Place, Sheffield Sheffield S11 | P96: =N96=K96 -> TRUE | Q96: =COUNTIF($B$2:$B$1196,B96) -> 1 | R96: =COUNTIF($H$2:$H$1196,H96) -> 0 | S96: =COUNTIF($D$2:$D$1196,D96) -> 1
A97: a1kNz000002qX6nIAE | B97: 512999361 | C97: 003Nz00000CuluzIAB | D97: 006Nz00000AVB7uIAH | E97: Month 3: How can we make things better (Specification) Survey | F97: 2024-07-30T22:31:02.000+0000 | G97: marketing cloud connector | H97: GREP-CoA Suet Ying Chow, Koon Hong Kwok - 604 Enigma Square, 414 North Row, MK9 2FU | I97: Saji Gunasekaran | J97: 2024-08-05T17:28:53.000+0000 | K97: 604 Enigma Square, 414 North Row, MK9 2FU | L97: GREP-CoA Suet Ying Chow, Koon Hong Kwok - 604 Enigma Square, 414 North Row, MK9 2FU | M97: a1G8d0000005rDFEAY | N97: 604 Enigma Square, 414 North Row, MK9 2FU | O97: Enigma Square, Milton Keynes Milton Keynes MK9 | P97: =N97=K97 -> TRUE | Q97: =COUNTIF($B$2:$B$1196,B97) -> 1 | R97: =COUNTIF($H$2:$H$1196,H97) -> 2 | S97: =COUNTIF($D$2:$D$1196,D97) -> 2
A98: a1kNz000002qX6qIAE | B98: 512744837 | C98: 003Nz00000CrCs9IAF | D98: 006Nz00000AVnOUIA1 | E98: Month 3: How can we make things better (Specification) Survey | F98: 2024-07-30T22:31:02.000+0000 | G98: marketing cloud connector | H98: GREP-CoA Ruth Howells, Robert Howells - 234, Brook Place Apts, Sheffield, S11 8BR | I98: Saji Gunasekaran | J98: 2024-08-05T17:30:42.000+0000 | K98: 234, Brook Place Apts, Sheffield, S11 8BR | L98: GREP-CoA Ruth Howells, Robert Howells - 234, Brook Place Apts, Sheffield, S11 8BR | M98: a1G4J0000025zJoUAI | N98: 234, Brook Place Apts, Sheffield, S11 8BR | O98: Brook Place, Sheffield Sheffield S11 | P98: =N98=K98 -> TRUE | Q98: =COUNTIF($B$2:$B$1196,B98) -> 1 | R98: =COUNTIF($H$2:$H$1196,H98) -> 1 | S98: =COUNTIF($D$2:$D$1196,D98) -> 1
A99: a1kNz000002qX6pIAE | B99: 511267593 | C99: 003Nz00000CX72DIAT | D99: 006Nz00000AIWQMIA5 | E99: Month 3: How can we make things better (Specification) Survey | F99: 2024-07-30T22:31:02.000+0000 | G99: marketing cloud connector | I99: Saji Gunasekaran | J99: 2024-08-05T17:29:59.000+0000 | K99: FLAT 51, Hawkins Ln, Finzels Reach, Bristol | L99: GREP-CoA Charlotte & Andrew Noerregaard-Ettle - FLAT 51, Hawkins Ln, Finzels Reach, Bristol, | M99: a1G4J0000025yl8UAA | N99: FLAT 51, Hawkins Ln, Finzels Reach, Bristol, | O99: Hawkins & George, Bristol Bristol BS1 | P99: =N99=K99 -> FALSE | Q99: =COUNTIF($B$2:$B$1196,B99) -> 1 | R99: =COUNTIF($H$2:$H$1196,H99) -> 0 | S99: =COUNTIF($D$2:$D$1196,D99) -> 1
A100: a1kNz000002qX6oIAE | B100: 512720968 | C100: 003Nz00000CoKshIAF | D100: 006Nz00000AVB7uIAH | E100: Month 3: How can we make things better (Specification) Survey | F100: 2024-07-30T22:31:02.000+0000 | G100: marketing cloud connector | H100: GREP-CoA Suet Ying Chow, Koon Hong Kwok - 604 Enigma Square, 414 North Row, MK9 2FU | I100: Saji Gunasekaran | J100: 2024-08-05T17:29:31.000+0000 | K100: 604 Enigma Square, 414 North Row, MK9 2FU | L100: GREP-CoA Suet Ying Chow, Koon Hong Kwok - 604 Enigma Square, 414 North Row, MK9 2FU | M100: a1G8d0000005rDFEAY | N100: 604 Enigma Square, 414 North Row, MK9 2FU | O100: Enigma Square, Milton Keynes Milton Keynes MK9 | P100: =N100=K100 -> TRUE | Q100: =COUNTIF($B$2:$B$1196,B100) -> 1 | R100: =COUNTIF($H$2:$H$1196,H100) -> 2 | S100: =COUNTIF($D$2:$D$1196,D100) -> 2
A101: a1kNz000002quIPIAY | B101: 503957143 | C101: 003Nz00000B0nQhIAJ | D101: 006Nz000009EMOZIA4 | E101: Month 3: How can we make things better (Specification) Survey | F101: 2024-07-30T12:00:00.000+0000 | G101: Saji Gunasekaran | I101: Saji Gunasekaran | J101: 2024-08-05T17:31:52.000+0000 | K101: 530 The Condor, 1 Springwell Sq | L101: GREP-CoA Kolawole Akinola & Oluwaseyi Shobayo - 530 The Condor, 1 Springwell Sq | M101: a1G8d000002QBg1EAG | N101: 530 The Condor, 1 Springwell Sq | O101: The Condor, Derby Derby DE1 | P101: =N101=K101 -> TRUE | Q101: =COUNTIF($B$2:$B$1196,B101) -> 1 | R101: =COUNTIF($H$2:$H$1196,H101) -> 0 | S101: =COUNTIF($D$2:$D$1196,D101) -> 2
A102: a1kNz000002qAmxIAE | B102: 502728829 | C102: 003Nz00000AmTeiIAF | D102: 006Nz0000094Rm6IAE | E102: Month 3: How can we make things better (Specification) Survey | F102: 2024-07-29T22:30:59.000+0000 | G102: marketing cloud connector | H102: GREP-CoA S. Chandraknt Jadhav, S Jadhav & A Jadhav - 103 Assay Apartments, Station View, Guildford | I102: Saji Gunasekaran | J102: 2024-08-05T17:33:07.000+0000 | K102: 103 Assay Apartments, Station View, Guildford | L102: GREP-CoA S. Chandraknt Jadhav, S Jadhav & A Jadhav - 103 Assay Apartments, Station View, Guildford | M102: a1G8d000002Q2YOEA0 | N102: 103 Assay Apartments, Station View, Guildford | O102: The Mint, Guildford Guildford GU1 | P102: =N102=K102 -> TRUE | Q102: =COUNTIF($B$2:$B$1196,B102) -> 1 | R102: =COUNTIF($H$2:$H$1196,H102) -> 1 | S102: =COUNTIF($D$2:$D$1196,D102) -> 1
...

Sheet Mnth 8 full response DE
A1: Contact ID 18 Digit | B1: 18 digit OPP ID | C1: First Name | D1: Last Name | E1: Title | F1: Tenancy End Date | G1: Tenancy Start Date | H1: Role | I1: Email | J1: Phone | K1: Unit Address _Subject_ | L1: Active | M1: Tenancy Type | N1: Primary Offer Estate | O1: Move-In Date | P1: Agreed Unit | Q1: Property Type | R1: Unit Status | S1: Fund | T1: Estate | U1: Portfolio | V1: Unit Manager: Full Name | W1: Property Manager: Full Name | X1: Asset Manager: Full Name | Y1: Property Manager Assistant: Full Name | Z1: Future Vacant Date | AA1: Building Name | AB1: Plot No | AC1: Opportunity Name | AD1: id | AE1: How are you enjoying your stay 1-10 | AF1: Survey sent time | AG1: Happy to be contacted | AH1: Reason for enjoyment score | AI1: Home enjoyment comments | AJ1: Recommend Grainger 1-10
A2: 0038d000008xWEDAA2 | B2: 0068d000006aOgOAAU | C2: Anita | D2: Masters | F2: 45107 | G2: 44742 | H2: Lead Tenant | I2: mjones@graingerplc.co.uk | J2: 07741509604 | K2: Tudor House, 7 Tudor House, Abbey Way, Northwich, CW8 1LY | L2: TRUE | M2: New | N2: Dummy (N) | O2: 44742 | P2: <a href="a1G4J00000261fu" target="_blank">7 Tudor House, Hartford</a> | AD2: 281674183 | AE2: 2 | AF2: 44708.336 | AG2: Yes | AH2: Mike Jones Test | AI2: happy happy happy | AJ2: 7
A3: 0038d0000026HYAAA2 | B3: 0068d0000037X9hAAE | C3: Rachel | D3: Herbert | F3: 44854 | G3: 44490 | H3: Tenant | I3: iloveyourjunk@gmail.com | J3: 07706536708 | K3: Woodleigh Gardens 14/68, 31 Woodleigh Gardens, London, SW16 2SX | L3: FALSE | M3: New | N3: STREATHAM ESTATE | O3: 44490 | P3: <a href="a1G4J0000025zyy" target="_blank">31 Woodleigh Gardens, Streatham, London</a> | Q3: Apartment | R3: Tenanted | S3: PRS-London & SE | T3: Streatham Estate | U3: PRS-London & SE | V3: Sarah Georgiades | X3: Stewart Blackford | Y3: Lynn Robson | AA3: Woodleigh Gardens 14/68 | AB3: 31 Woodleigh Gardens, Streatham, London | AC3: GREP-CoA Kia Brame, Rachel Herbert & Alexandra Simpson - 31 Woodleigh Gardens, Streatham, London | AD3: 264927538 | AE3: 1 | AF3: 44730.089 | AG3: No | AH3: It was mouldy, damp, the windows didn‚Äôt close, we had a pest infestation on arrival. Grainger were awful at every step. | AI3: Not living there | AJ3: 1
A4: 0038d0000025pxfAAA | B4: 0068d000009DppZAAS | C4: Marc | D4: Murray | F4: 45586 | G4: 44855 | H4: Lead Tenant | I4: marcmurray1979@outlook.com | J4: 07849706010 | K4: Willow Rise, Liverpool, L33, Apartment 48, Willow Rise,Roughwood Drive, Liverpool, L33 8WZ | L4: TRUE | M4: Renewal | O4: 44855 | P4: <a href="a1G4J0000025wgt" target="_blank">Flat 48, Willow Rise, Liverpool, L33</a> | R4: Tenanted | T4: Resi | U4: PRS-Regions | V4: Luke Pollard | X4: Vicki Turnbull | Y4: Fern Ireland-Ferguson | AA4: Willow Rise, Liverpool, L33 | AB4: Flat 48, Willow Rise, Liverpool, L33 | AC4: RENEWAL- 48 Willow Rise-21/10/2022 | AD4: 263922610 | AE4: 9 | AF4: 44730.089 | AG4: Yes | AH4: Public areas in the building have improved but are still below the standard you would expect. | AJ4: 9
A5: 0038d0000026Zb9AAE | B5: 0068d000009feqVAAQ | C5: Molly | D5: Dixon | F5: 45259 | G5: 44894 | H5: Lead Tenant | I5: mollydixon53@googlemail.com | J5: 07518251243 | K5: New Islington, Manchester, M4 6BY, Flat 7,43 Chippenham Road, Manchester, M4 6BY | L5: TRUE | M5: Renewal | O5: 44894 | P5: <a href="a1G4J0000025wjj" target="_blank">7, New Islington, 43 Chippenham Road, M4 6BY</a> | Q5: Apartment | R5: Reserved | T5: Tribe | U5: PRS-Regions | V5: Mark Weeden | X5: Vicki Turnbull | Z5: 45627 | AA5: New Islington, Manchester, M4 6BY | AB5: 7, New Islington, 43 Chippenham Road, M4 6BY | AC5: RENEWAL- 7 New Islington- 29/11/2022 | AD5: 265238139 | AE5: 2 | AF5: 44753.087 | AG5: Yes | AH5: Scaffolding still up after all this time | AI5: Take down the scaffolding | AJ5: 2
A6: 0034J00000a4evfQAA | B6: 0068d000002xfKuAAI | C6: Gemma | D6: Tarry | F6: 44882 | G6: 44518 | H6: Lead Tenant | I6: gemmatarry3@gmail.com | J6: 07985319341 | K6: Nelson Apt, Darbyshire Rd, Hants, GU11, Apartment 2, Nelson Apartments,Darbyshire Road, Aldershot, GU11 1FL | L6: TRUE | M6: Renewal | N6: Wellesley PRS - Nelson Apartments | O6: 44518 | P6: <a href="a1G4J0000025y3h" target="_blank">2 Nelson Apt, Darbyshire Rd, Aldershot, Hants</a> | Q6: Apartment | R6: Future Vacant | T6: Gunhill | U6: BTR-London & SE | V6: Megan Fleming | X6: Harriet Shaw | Y6: Megan Fleming | Z6: 45589 | AA6: Nelson Apt, Darbyshire Rd, Hants, GU11 | AB6: 2 Nelson Apt, Darbyshire Rd, Aldershot, Hants | AC6: RENEWAL - 2 Nelson apt - 18/11/21. | AD6: 210052807 | AE6: 7 | AF6: 44758.087 | AG6: No | AH6: Some unresolved maintenance issues that were brought up multiple times and never solved_x000D_ Mold and condensation issues | AI6: Resolving maintenance issues | AJ6: 7
A7: 0034J00000a4gdPQAQ | B7: 0068d000002cZ4IAAU | C7: Hettie | D7: Maylam | F7: 45137 | G7: 44834 | H7: Lead Tenant | I7: hettiemaylam@hotmail.co.uk | J7: 07896568924 | K7: Torrens308 Clippers - Torrens Apartments, Apartment 308 Torrens Apartments,Waterman Walk, Salford, M50 3AS | L7: TRUE | M7: Renewal | N7: Clippers - Torrens Apartments | O7: 44834 | P7: <a href="a1G4J0000025xes" target="_blank">308 Torrens Apt, Waterman Wlk, Salford M50</a> | Q7: Apartment | R7: Tenanted | T7: Clippers Quay | U7: BTR-Regions | V7: Helen Bowers | X7: Vicki Turnbull | Y7: Helen Bowers | Z7: 45835 | AA7: Clippers - Torrens Apartments | AB7: 308 Torrens Apt, Waterman Wlk, Salford M50 | AC7: PERMITTED OCC- Hettie Maylam- 308 Torrens- 30/09/2021 | AD7: 210057397 | AE7: 7 | AF7: 45013.085 | AG7: Yes | AH7: We love it but the cost increase every year means we probably can't stay any longer | AI7: Charges reflecting the cost of living crisis | AJ7: 5
A8: 0038d0000027Dr5AAE | B8: 0068d0000039AAwAAM | C8: Judith | D8: Smithson | F8: 46348 | G8: 44523 | H8: Lead Tenant | I8: smithsonjudith1@gmail.com | J8: 07307855679 | K8: 506 GT ‚Äì Apex Gardens - Aster Apts, 822 506 Astor Apartments,822 Seven Sisters Road, London, N15 5EZ | L8: TRUE | M8: New | N8: Apex - Aster Apts, GT | O8: 44523 | P8: <a href="a1G4J0000025xbY" target="_blank">506 Aster Apts 822 Seven Sisters Rd London N1</a> | R8: Tenanted | T8: GT - Apex Gardens | U8: Grainger Trust | V8: Alex Naumanen-Ley | X8: Georgia Kirby-Watt | Y8: Kim Miller | AA8: GT ‚Äì Apex Gardens - Aster Apts | AB8: 506 Aster Apts 822 Seven Sisters Rd London N1 | AC8: GREP-CoA Miss Judith Smithson - 506 Aster Apts 822 Seven Sisters Rd London N1 | AD8: 265606858 | AE8: 10 | AF8: 44763.087 | AG8: Yes | AH8: The view, the staff and the facilities | AI8: A swimming pool | AJ8: 10
