Workbook
Name aspectpremium: '2. GRI Pricing Inputs'!$C$53:$E$55
Name balcony: '2. GRI Pricing Inputs'!$C$67:$E$69
Name baseprice: '2. GRI Pricing Inputs'!$C$15:$F$17
Name bathpremium: '2. GRI Pricing Inputs'!$C$21:$E$24
Name floorpremium: '2. GRI Pricing Inputs'!$C$45:$E$47
Name other: '2. GRI Pricing Inputs'!$O$32:$P$47
Name phasedrelease: '2. GRI Pricing Inputs'!$I$54
Name sizepremium: '2. GRI Pricing Inputs'!$C$28:$E$31

Sheet Cover
C3: BTR PRICING WORKBOOK
K5: ACQ | L5: CFT | M5: ONB | N5: AM | O5: LET
C6: Project: | E6: Enigma Square | J6: Project Team | L6: [Name] | M6: [Name] | N6: [Name] | O6: [Name]
C7: Pricing Date: | E7: 45502 | J7: Reviewer | L7: [Name] | M7: [Name] | N7: [Name] | O7: [Name]
C9: INSTRUCTIONS
C11: Key: | E11: Light blue = input | G11: White = calculation
C13: Tab | D13: Process
C14: 1. Accomodation tab | D14: 1 | E14: Input accomodation to be constructed, as per the Development agreement, in columns D-F (request final DA from the acquistions manager)
D15: 2 | E15: Update Qube for Qube location data (fund/portfolio/estate) as per BTR example provided (check with asset manager if unsure)
D16: 3 | E16: Create Grainger schedule as required in the format provided (Col L-AA)
D17: 4 | E17: Input Grainger required accomodation attributes (Col S-AA)
C19: 2. GRI Pricing inputs | D19: 5 | E19: Input premium values and growth inputs (Number 1-15)
D20: 6 | E20: Describe methodology for each inputs
C22: 3. GRI Pricing | D22: 7 | E22: Review and sense check pricing framework unit by unit
D23: 8 | E23: Add any manual adjustment and provide rationale for adjustments
D24: 9 | E24: Review and sense check overall and average pricing
C26: 4. CBRE ERV's | D26: 10 | E26: CFT to provide i) approved underwritten rents ii) market ERV per the latest CBRE valuation
D27: 11 | E27: Communication expected launch date to CFT in order to grow benchmarks to same point in time.
D28: 12 | E28: All rents must be compared at the same point in time, on a like for like basis.
D29: 13 | E29: If appraising the current market rent today, we must grow both the underwriting and CBRE from their respective points in time to today.
D30: 14 | E30: Grainger underwrite rental growth for each project and CBRE assume rental growth in their valuation (check growth % for each specific project).
C32: 5. Dashboard | D32: 15 | E32: Review dashboard, ensure current pricing are in line as expected of the current view of the market
D33: 16 | E33: Aim to launch at and outperform the higher of i) ‘grown underwritten ERV’ and ii) ‘CBRE Est. Forecast' ERV
D34: 17 | E34: Append the table within leasing and marketing report
C36: 6. IC Appendix | D36: 18 | E36: Append the full master schedule within leasing and marketing report.
C38: 7. Archive Pricing | D38: 19 | E38: To allow tracking of previously approved prices for each unit.

Sheet 1. Accomodation
H3: 1. ACCOMODATION SCHEDULE | Y3: ='4. Valuation'!$D$6 -> 45536
H5: Project | I5: =Cover!E6 -> Enigma Square
H7: Qube Location Data | L7: Grainger Accomodation
H8: Qube Field | I8: Inputs | J8: Example | L8: Bedroom | M8: No. of Homes | N8: Av. Size (sqft) | O8: Notes
H9: Fund | I9: BTR-London & SE | L9: Studio | M9: =IFERROR(COUNTIF($P$21:$P$622,$L9),"-") -> 13 | N9: =IFERROR(AVERAGEIF($P$21:$P$622,$L9,$O$21:$O$622),"-") -> 389.98462 | O9: [XXX]
H10: Portfolio | I10: Enigma Square | L10: 1 Bed | M10: =IFERROR(COUNTIF($P$21:$P$622,$L10),"-") -> 182 | N10: =IFERROR(AVERAGEIF($P$21:$P$622,$L10,$O$21:$O$622),"-") -> 504.70418 | O10: [XXX]
H11: Estate | I11: Enigma Square Apartments | J11: XXXX - Apartments | L11: 2 Bed | M11: =IFERROR(COUNTIF($P$21:$P$622,$L11),"-") -> 54 | N11: =IFERROR(AVERAGEIF($P$21:$P$622,$L11,$O$21:$O$622),"-") -> 734.66111 | O11: [XXX]
J12: XXXX - XXX Apts | L12: 3 bed | M12: =IFERROR(COUNTIF($P$21:$P$622,$L12),"-") -> 12 | N12: =IFERROR(AVERAGEIF($P$21:$P$622,$L12,$O$21:$O$622),"-") -> 1007.4292
J13: XXXX - Amenity | M13: =IFERROR(COUNTIF($P$21:$P$622,$L13),"-") -> 0 | N13: =IFERROR(AVERAGEIF($P$21:$P$622,$L13,$O$21:$O$622),"-") -> -
J14: XXXX - Commercial | M14: =IFERROR(COUNTIF($P$21:$P$622,$L14),"-") -> 0 | N14: =IFERROR(AVERAGEIF($P$21:$P$622,$L14,$O$21:$O$622),"-") -> -
L15: Total | M15: =SUM(M9:M13) -> 261 | N15: =IFERROR(SUM(O21:O620)/M15,0) -> 569.68126
J16: XXXX - Car Parking | L16: Car Park | M16: 178
D19: DA ACCOMODATION | H19: Qube Property Location Inputs | L19: GRAINGER ACCOMODATION
C20: Plot Number | D20: Home type | E20: Size (sq.ft) | F20: Bedroom | H20: Fund | I20: Portfolio | J20: Estate | L20: Block Name | M20: =D20 -> Home type | N20: Door Number | O20: =E20 -> Size (sq.ft) | P20: ='2. GRI Pricing Inputs'!C15 -> Bedroom | Q20: ='2. GRI Pricing Inputs'!C22 -> Bath | R20: ='2. GRI Pricing Inputs'!C45 -> Floor | S20: ='2. GRI Pricing Inputs'!C53 -> Aspect | T20: ='2. GRI Pricing Inputs'!C60 -> Storage | U20: ='2. GRI Pricing Inputs'!C67 -> Balcony | V20: ='2. GRI Pricing Inputs'!C83 -> Additional Toilet | W20: ='2. GRI Pricing Inputs'!C90 -> Larger Master Bedroom | X20: ='2. GRI Pricing Inputs'!C98 -> 0 | Y20: ='2. GRI Pricing Inputs'!C105 -> 0
D21: [Select] | H21: =$I$9 -> BTR-London & SE | I21: =$I$10 -> Enigma Square | J21: Enigma Square Apartments | L21: C | M21: Apartment | N21: 101 | O21: 517.1 | P21: 1 Bed | Q21: 1 | R21: 1 | S21: North Row below Treeline | U21: Small Terrace Balcony | V21: [Select] | X21: [Select] | Y21: [Select]
D22: [Select] | H22: =$I$9 -> BTR-London & SE | I22: =$I$10 -> Enigma Square | J22: Enigma Square Apartments | L22: C | M22: Apartment | N22: 102 | O22: 385.46 | P22: Studio | Q22: 1 | R22: 1 | S22: Nursery and mixed other buildings | U22: None | V22: [Select] | X22: [Select] | Y22: [Select]
D23: [Select] | H23: =$I$9 -> BTR-London & SE | I23: =$I$10 -> Enigma Square | J23: Enigma Square Apartments | L23: C | M23: Apartment | N23: 103 | O23: 394.17 | P23: Studio | Q23: 1 | R23: 1 | S23: Nursery and mixed other buildings | U23: None | V23: [Select] | X23: [Select] | Y23: [Select]
D24: [Select] | H24: =$I$9 -> BTR-London & SE | I24: =$I$10 -> Enigma Square | J24: Enigma Square Apartments | L24: C | M24: Apartment | N24: 104 | O24: 521.51 | P24: 1 Bed | Q24: 1 | R24: 1 | S24: North Row below Treeline | U24: Small Terrace Balcony | V24: [Select] | X24: [Select] | Y24: [Select]
D25: [Select] | H25: =$I$9 -> BTR-London & SE | I25: =$I$10 -> Enigma Square | J25: Enigma Square Apartments | L25: C | M25: Apartment | N25: 105 | O25: 532.49 | P25: 1 Bed | Q25: 1 | R25: 1 | S25: North Row below Treeline | U25: Small Terrace Balcony | V25: [Select] | X25: [Select] | Y25: [Select]
D26: [Select] | H26: =$I$9 -> BTR-London & SE | I26: =$I$10 -> Enigma Square | J26: Enigma Square Apartments | L26: C | M26: Apartment | N26: 106 | O26: 728.18 | P26: 2 Bed | Q26: 2 | R26: 1 | S26: Carpark and other block | U26: Long Terrace Balcony | V26: [Select] | X26: [Select] | Y26: [Select]
D27: [Select] | H27: =$I$9 -> BTR-London & SE | I27: =$I$10 -> Enigma Square | J27: Enigma Square Apartments | L27: C | M27: Apartment | N27: 107 | O27: 489.44 | P27: 1 Bed | Q27: 1 | R27: 1 | S27: Nursery and mixed other buildings | U27: None | V27: [Select] | X27: [Select] | Y27: [Select]
D28: [Select] | H28: =$I$9 -> BTR-London & SE | I28: =$I$10 -> Enigma Square | J28: Enigma Square Apartments | L28: C | M28: Apartment | N28: 108 | O28: 509.56 | P28: 1 Bed | Q28: 1 | R28: 1 | S28: Carpark and other block | U28: Small Terrace Balcony | V28: [Select] | X28: [Select] | Y28: [Select]
D29: [Select] | H29: =$I$9 -> BTR-London & SE | I29: =$I$10 -> Enigma Square | J29: Enigma Square Apartments | L29: C | M29: Apartment | N29: 109 | O29: 506.87 | P29: 1 Bed | Q29: 1 | R29: 1 | S29: Nursery and mixed other buildings | U29: None | V29: [Select] | X29: [Select] | Y29: [Select]
D30: [Select] | H30: =$I$9 -> BTR-London & SE | I30: =$I$10 -> Enigma Square | J30: Enigma Square Apartments | L30: C | M30: Apartment | N30: 110 | O30: 509.56 | P30: 1 Bed | Q30: 1 | R30: 1 | S30: Carpark and other block | U30: Small Terrace Balcony | V30: [Select] | X30: [Select] | Y30: [Select]
D31: [Select] | H31: =$I$9 -> BTR-London & SE | I31: =$I$10 -> Enigma Square | J31: Enigma Square Apartments | L31: C | M31: Apartment | N31: 111 | O31: 747.02 | P31: 2 Bed | Q31: 2 | R31: 1 | S31: Carpark and other block | U31: None | V31: [Select] | X31: [Select] | Y31: [Select]
D32: [Select] | H32: =$I$9 -> BTR-London & SE | I32: =$I$10 -> Enigma Square | J32: Enigma Square Apartments | L32: C | M32: Apartment | N32: 112 | O32: 506.76 | P32: 1 Bed | Q32: 1 | R32: 1 | S32: Carpark and other block | U32: Small Terrace Balcony | V32: [Select] | X32: [Select] | Y32: [Select]
... D36: [Select] | H36: =$I$9 -> BTR-London & SE | I36: =$I$10 -> Enigma Square | J36: Enigma Square Apartments | L36: C | M36: Apartment | N36: 204 | O36: 521.51 | P36: 1 Bed | Q36: 1 | R36: 2 | S36: North Row below Treeline | U36: Cantilever Balcony | V36: [Select] | X36: [Select] | Y36: [Select]
D37: [Select] | H37: =$I$9 -> BTR-London & SE | I37: =$I$10 -> Enigma Square | J37: Enigma Square Apartments | L37: C | M37: Apartment | N37: 205 | O37: 762.95 | P37: 2 Bed | Q37: 2 | R37: 2 | S37: North Row below Treeline | T37: One storage | U37: Enclosed Cantiliever | V37: [Select] | X37: [Select] | Y37: [Select]
D38: [Select] | H38: =$I$9 -> BTR-London & SE | I38: =$I$10 -> Enigma Square | J38: Enigma Square Apartments | L38: C | M38: Apartment | N38: 206 | O38: 529.8 | P38: 1 Bed | Q38: 1 | R38: 2 | S38: Amenity Pebble Roof | U38: Juliette | V38: [Select] | X38: [Select] | Y38: [Select]
D39: [Select] | H39: =$I$9 -> BTR-London & SE | I39: =$I$10 -> Enigma Square | J39: Enigma Square Apartments | L39: C | M39: Apartment | N39: 207 | O39: 509.56 | P39: 1 Bed | Q39: 1 | R39: 2 | S39: Carpark and other block | U39: Juliette | V39: [Select] | X39: [Select] | Y39: [Select]
D40: [Select] | H40: =$I$9 -> BTR-London & SE | I40: =$I$10 -> Enigma Square | J40: Enigma Square Apartments | L40: C | M40: Apartment | N40: 208 | O40: 489.44 | P40: 1 Bed | Q40: 1 | R40: 2 | S40: Nursery and mixed other buildings | U40: Cantilever Balcony | V40: [Select] | X40: [Select] | Y40: [Select]
D41: [Select] | H41: =$I$9 -> BTR-London & SE | I41: =$I$10 -> Enigma Square | J41: Enigma Square Apartments | L41: C | M41: Apartment | N41: 209 | O41: 509.56 | P41: 1 Bed | Q41: 1 | R41: 2 | S41: Carpark and other block | U41: Juliette | V41: [Select] | X41: [Select] | Y41: [Select]
D42: [Select] | H42: =$I$9 -> BTR-London & SE | I42: =$I$10 -> Enigma Square | J42: Enigma Square Apartments | L42: C | M42: Apartment | N42: 210 | O42: 506.87 | P42: 1 Bed | Q42: 1 | R42: 2 | S42: Nursery and mixed other buildings | U42: Cantilever Balcony | V42: [Select] | X42: [Select] | Y42: [Select]
D43: [Select] | H43: =$I$9 -> BTR-London & SE | I43: =$I$10 -> Enigma Square | J43: Enigma Square Apartments | L43: C | M43: Apartment | N43: 211 | O43: 509.56 | P43: 1 Bed | Q43: 1 | R43: 2 | S43: Carpark and other block | U43: Juliette | V43: [Select] | X43: [Select] | Y43: [Select]
D44: [Select] | H44: =$I$9 -> BTR-London & SE | I44: =$I$10 -> Enigma Square | J44: Enigma Square Apartments | L44: C | M44: Apartment | N44: 212 | O44: 747.02 | P44: 2 Bed | Q44: 2 | R44: 2 | S44: Nursery and mixed other buildings | U44: Cantilever Balcony | V44: [Select] | X44: [Select] | Y44: [Select]
D45: [Select] | H45: =$I$9 -> BTR-London & SE | I45: =$I$10 -> Enigma Square | J45: Enigma Square Apartments | L45: C | M45: Apartment | N45: 213 | O45: 506.76 | P45: 1 Bed | Q45: 1 | R45: 2 | S45: Carpark and other block | U45: Juliette | V45: [Select] | X45: [Select] | Y45: [Select]
D46: [Select] | H46: =$I$9 -> BTR-London & SE | I46: =$I$10 -> Enigma Square | J46: Enigma Square Apartments | L46: D | M46: Apartment | N46: 214 | O46: 507.41 | P46: 1 Bed | Q46: 1 | R46: 2 | S46: Carpark and other block | U46: Small Terrace Balcony | V46: [Select] | X46: [Select] | Y46: [Select]
D47: [Select] | H47: =$I$9 -> BTR-London & SE | I47: =$I$10 -> Enigma Square | J47: Enigma Square Apartments | L47: D | M47: Apartment | N47: 215 | O47: 749.38 | P47: 2 Bed | Q47: 2 | R47: 2 | S47: Private patio / Internal Courtyard | U47: Courtyard Terrace | V47: [Select] | X47: [Select] | Y47: [Select]
D48: [Select] | H48: =$I$9 -> BTR-London & SE | I48: =$I$10 -> Enigma Square | J48: Enigma Square Apartments | L48: D | M48: Apartment | N48: 216 | O48: 510.21 | P48: 1 Bed | Q48: 1 | R48: 2 | S48: Carpark and other block | U48: Small Terrace Balcony | V48: [Select] | X48: [Select] | Y48: [Select]
D49: [Select] | H49: =$I$9 -> BTR-London & SE | I49: =$I$10 -> Enigma Square | J49: Enigma Square Apartments | L49: D | M49: Apartment | N49: 217 | O49: 506.87 | P49: 1 Bed | Q49: 1 | R49: 2 | S49: Private patio / Internal Courtyard | U49: Courtyard Terrace | V49: [Select] | W49: Yes | X49: [Select] | Y49: [Select]
D50: [Select] | H50: =$I$9 -> BTR-London & SE | I50: =$I$10 -> Enigma Square | J50: Enigma Square Apartments | L50: D | M50: Apartment | N50: 218 | O50: 510.21 | P50: 1 Bed | Q50: 1 | R50: 2 | S50: Carpark and other block | U50: Small Terrace Balcony | V50: [Select] | X50: [Select] | Y50: [Select]
D51: [Select] | H51: =$I$9 -> BTR-London & SE | I51: =$I$10 -> Enigma Square | J51: Enigma Square Apartments | L51: D | M51: Apartment | N51: 219 | O51: 392.02 | P51: Studio | Q51: 1 | R51: 2 | S51: Private patio / Internal Courtyard | U51: Courtyard Terrace | V51: [Select] | X51: [Select] | Y51: [Select]
D52: [Select] | H52: =$I$9 -> BTR-London & SE | I52: =$I$10 -> Enigma Square | J52: Enigma Square Apartments | L52: D | M52: Apartment | N52: 220 | O52: 510.21 | P52: 1 Bed | Q52: 1 | R52: 2 | S52: Carpark and other block | U52: Small Terrace Balcony | V52: [Select] | X52: [Select] | Y52: [Select]
D53: [Select] | H53: =$I$9 -> BTR-London & SE | I53: =$I$10 -> Enigma Square | J53: Enigma Square Apartments | L53: D | M53: Apartment | N53: 221 | O53: 530.55 | P53: 1 Bed | Q53: 1 | R53: 2 | S53: Amenity Pebble Roof | U53: Small Terrace Balcony | V53: [Select] | X53: [Select] | Y53: [Select]
D54: [Select] | H54: =$I$9 -> BTR-London & SE | I54: =$I$10 -> Enigma Square | J54: Enigma Square Apartments | L54: D | M54: Apartment | N54: 222 | O54: 759.93 | P54: 2 Bed | Q54: 2 | R54: 2 | S54: North Row below Treeline | T54: One storage | U54: Small Terrace Balcony | V54: [Select] | X54: [Select] | Y54: [Select]
D55: [Select] | H55: =$I$9 -> BTR-London & SE | I55: =$I$10 -> Enigma Square | J55: Enigma Square Apartments | L55: D | M55: Apartment | N55: 223 | O55: 521.51 | P55: 1 Bed | Q55: 1 | R55: 2 | S55: North Row below Treeline | U55: Small Terrace Balcony | V55: [Select] | X55: [Select] | Y55: [Select]
D56: [Select] | H56: =$I$9 -> BTR-London & SE | I56: =$I$10 -> Enigma Square | J56: Enigma Square Apartments | L56: D | M56: Apartment | N56: 224 | O56: 517.53 | P56: 1 Bed | Q56: 1 | R56: 2 | S56: Private patio / Internal Courtyard | U56: Courtyard Terrace | V56: [Select] | W56: Yes | X56: [Select] | Y56: [Select]
D57: [Select] | H57: =$I$9 -> BTR-London & SE | I57: =$I$10 -> Enigma Square | J57: Enigma Square Apartments | L57: D | M57: Apartment | N57: 225 | O57: 761.44 | P57: 2 Bed | Q57: 2 | R57: 2 | S57: North Row below Treeline | U57: Small Terrace Balcony | V57: [Select] | X57: [Select] | Y57: [Select]
D58: [Select] | H58: =$I$9 -> BTR-London & SE | I58: =$I$10 -> Enigma Square | J58: Enigma Square Apartments | L58: D | M58: Apartment | N58: 226 | O58: 497.72 | P58: 1 Bed | Q58: 1 | R58: 2 | S58: Private patio / Internal Courtyard | U58: Courtyard Terrace | V58: [Select] | W58: Yes | X58: [Select] | Y58: [Select]
D59: [Select] | H59: =$I$9 -> BTR-London & SE | I59: =$I$10 -> Enigma Square | J59: Enigma Square Apartments | L59: D | M59: Apartment | N59: 227 | O59: 512.04 | P59: 1 Bed | Q59: 1 | R59: 2 | S59: Private patio / Internal Courtyard | U59: Courtyard Terrace | V59: [Select] | W59: Yes | X59: [Select] | Y59: [Select]
D60: [Select] | H60: =$I$9 -> BTR-London & SE | I60: =$I$10 -> Enigma Square | J60: Enigma Square Apartments | L60: D | M60: Apartment | N60: 228 | O60: 761.44 | P60: 2 Bed | Q60: 2 | R60: 2 | S60: North Row below Treeline | U60: Small Terrace Balcony | V60: [Select] | X60: [Select] | Y60: [Select]
D61: [Select] | H61: =$I$9 -> BTR-London & SE | I61: =$I$10 -> Enigma Square | J61: Enigma Square Apartments | L61: D | M61: Apartment | N61: 229 | O61: 517.53 | P61: 1 Bed | Q61: 1 | R61: 2 | S61: Private patio / Internal Courtyard | U61: Courtyard Terrace | V61: [Select] | W61: Yes | X61: [Select] | Y61: [Select]
D62: [Select] | H62: =$I$9 -> BTR-London & SE | I62: =$I$10 -> Enigma Square | J62: Enigma Square Apartments | L62: D | M62: Apartment | N62: 230 | O62: 521.51 | P62: 1 Bed | Q62: 1 | R62: 2 | S62: North Row below Treeline | U62: Small Terrace Balcony | V62: [Select] | X62: [Select] | Y62: [Select]
D63: [Select] | H63: =$I$9 -> BTR-London & SE | I63: =$I$10 -> Enigma Square | J63: Enigma Square Apartments | L63: D | M63: Apartment | N63: 231 | O63: 760.9 | P63: 2 Bed | Q63: 2 | R63: 2 | S63: North Row below Treeline | T63: One storage | U63: Small Terrace Balcony | V63: [Select] | X63: [Select] | Y63: [Select]
D64: [Select] | H64: =$I$9 -> BTR-London & SE | I64: =$I$10 -> Enigma Square | J64: Enigma Square Apartments | L64: D | M64: Apartment | N64: 232 | O64: 524.74 | P64: 1 Bed | Q64: 1 | R64: 2 | S64: Saxon Gate below Treeline | U64: Small Terrace Balcony | V64: [Select] | X64: [Select] | Y64: [Select]
D65: [Select] | H65: =$I$9 -> BTR-London & SE | I65: =$I$10 -> Enigma Square | J65: Enigma Square Apartments | L65: D | M65: Apartment | N65: 233 | O65: 510.96 | P65: 1 Bed | Q65: 1 | R65: 2 | S65: Saxon Gate below Treeline | U65: Small Terrace Balcony | V65: [Select] | X65: [Select] | Y65: [Select]
D66: [Select] | H66: =$I$9 -> BTR-London & SE | I66: =$I$10 -> Enigma Square | J66: Enigma Square Apartments | L66: D | M66: Apartment | N66: 234 | O66: 492.56 | P66: 1 Bed | Q66: 1 | R66: 2 | S66: Private patio / Internal Courtyard | U66: Courtyard Terrace | V66: [Select] | W66: Yes | X66: [Select] | Y66: [Select]
D67: [Select] | H67: =$I$9 -> BTR-London & SE | I67: =$I$10 -> Enigma Square | J67: Enigma Square Apartments | L67: D | M67: Apartment | N67: 235 | O67: 510.96 | P67: 1 Bed | Q67: 1 | R67: 2 | S67: Saxon Gate below Treeline | U67: Small Terrace Balcony | V67: [Select] | X67: [Select] | Y67: [Select]
D68: [Select] | H68: =$I$9 -> BTR-London & SE | I68: =$I$10 -> Enigma Square | J68: Enigma Square Apartments | L68: D | M68: Apartment | N68: 236 | O68: 506.87 | P68: 1 Bed | Q68: 1 | R68: 2 | S68: Private patio / Internal Courtyard | U68: Courtyard Terrace | V68: [Select] | W68: Yes | X68: [Select] | Y68: [Select]
D69: [Select] | H69: =$I$9 -> BTR-London & SE | I69: =$I$10 -> Enigma Square | J69: Enigma Square Apartments | L69: D | M69: Apartment | N69: 237 | O69: 510.96 | P69: 1 Bed | Q69: 1 | R69: 2 | S69: Saxon Gate below Treeline | U69: Small Terrace Balcony | V69: [Select] | X69: [Select] | Y69: [Select]
D70: [Select] | H70: =$I$9 -> BTR-London & SE | I70: =$I$10 -> Enigma Square | J70: Enigma Square Apartments | L70: D | M70: Apartment | N70: 238 | O70: 749.38 | P70: 2 Bed | Q70: 2 | R70: 2 | S70: Private patio / Internal Courtyard | U70: Courtyard Terrace | V70: [Select] | X70: [Select] | Y70: [Select]
D71: [Select] | H71: =$I$9 -> BTR-London & SE | I71: =$I$10 -> Enigma Square | J71: Enigma Square Apartments | L71: D | M71: Apartment | N71: 239 | O71: 508.16 | P71: 1 Bed | Q71: 1 | R71: 2 | S71: Saxon Gate below Treeline | U71: Small Terrace Balcony | V71: [Select] | X71: [Select] | Y71: [Select]
D72: [Select] | H72: =$I$9 -> BTR-London & SE | I72: =$I$10 -> Enigma Square | J72: Enigma Square Apartments | L72: C | M72: Apartment | N72: 301 | O72: 517.1 | P72: 1 Bed | Q72: 1 | R72: 3 | S72: North Row below Treeline | U72: Cantilever balcony | V72: [Select] | X72: [Select] | Y72: [Select]
D73: [Select] | H73: =$I$9 -> BTR-London & SE | I73: =$I$10 -> Enigma Square | J73: Enigma Square Apartments | L73: C | M73: Apartment | N73: 302 | O73: 385.46 | P73: Studio | Q73: 1 | R73: 3 | S73: Nursery and mixed other buildings | U73: Juliette | V73: [Select] | X73: [Select] | Y73: [Select]
D74: [Select] | H74: =$I$9 -> BTR-London & SE | I74: =$I$10 -> Enigma Square | J74: Enigma Square Apartments | L74: C | M74: Apartment | N74: 303 | O74: 394.17 | P74: Studio | Q74: 1 | R74: 3 | S74: Nursery and mixed other buildings | U74: Juliette | V74: [Select] | X74: [Select] | Y74: [Select]
D75: [Select] | H75: =$I$9 -> BTR-London & SE | I75: =$I$10 -> Enigma Square | J75: Enigma Square Apartments | L75: C | M75: Apartment | N75: 304 | O75: 521.51 | P75: 1 Bed | Q75: 1 | R75: 3 | S75: North Row below Treeline | U75: Cantilever balcony | V75: [Select] | X75: [Select] | Y75: [Select]
D76: [Select] | H76: =$I$9 -> BTR-London & SE | I76: =$I$10 -> Enigma Square | J76: Enigma Square Apartments | L76: C | M76: Apartment | N76: 305 | O76: 762.95 | P76: 2 Bed | Q76: 2 | R76: 3 | S76: North Row below Treeline | T76: One storage | U76: Cantilever balcony | V76: [Select] | X76: [Select] | Y76: [Select]
D77: [Select] | H77: =$I$9 -> BTR-London & SE | I77: =$I$10 -> Enigma Square | J77: Enigma Square Apartments | L77: C | M77: Apartment | N77: 306 | O77: 529.8 | P77: 1 Bed | Q77: 1 | R77: 3 | S77: Amenity Pebble Roof | U77: Juliette | V77: [Select] | X77: [Select] | Y77: [Select]
D78: [Select] | H78: =$I$9 -> BTR-London & SE | I78: =$I$10 -> Enigma Square | J78: Enigma Square Apartments | L78: C | M78: Apartment | N78: 307 | O78: 509.56 | P78: 1 Bed | Q78: 1 | R78: 3 | S78: Carpark and other block | U78: Juliette | V78: [Select] | X78: [Select] | Y78: [Select]
D79: [Select] | H79: =$I$9 -> BTR-London & SE | I79: =$I$10 -> Enigma Square | J79: Enigma Square Apartments | L79: C | M79: Apartment | N79: 308 | O79: 489.44 | P79: 1 Bed | Q79: 1 | R79: 3 | S79: Nursery and mixed other buildings | U79: Cantilever balcony | V79: [Select] | W79: Yes | X79: [Select] | Y79: [Select]
D80: [Select] | H80: =$I$9 -> BTR-London & SE | I80: =$I$10 -> Enigma Square | J80: Enigma Square Apartments | L80: C | M80: Apartment | N80: 309 | O80: 509.56 | P80: 1 Bed | Q80: 1 | R80: 3 | S80: Carpark and other block | U80: Juliette | V80: [Select] | X80: [Select] | Y80: [Select]
D81: [Select] | H81: =$I$9 -> BTR-London & SE | I81: =$I$10 -> Enigma Square | J81: Enigma Square Apartments | L81: C | M81: Apartment | N81: 310 | O81: 506.87 | P81: 1 Bed | Q81: 1 | R81: 3 | S81: Nursery and mixed other buildings | U81: Cantilever balcony | V81: [Select] | W81: Yes | X81: [Select] | Y81: [Select]
D82: [Select] | H82: =$I$9 -> BTR-London & SE | I82: =$I$10 -> Enigma Square | J82: Enigma Square Apartments | L82: C | M82: Apartment | N82: 311 | O82: 509.56 | P82: 1 Bed | Q82: 1 | R82: 3 | S82: Carpark and other block | U82: Juliette | V82: [Select] | X82: [Select] | Y82: [Select]
D83: [Select] | H83: =$I$9 -> BTR-London & SE | I83: =$I$10 -> Enigma Square | J83: Enigma Square Apartments | L83: C | M83: Apartment | N83: 312 | O83: 747.02 | P83: 2 Bed | Q83: 2 | R83: 3 | S83: Nursery and mixed other buildings | U83: Cantilever balcony | V83: [Select] | X83: [Select] | Y83: [Select]
D84: [Select] | H84: =$I$9 -> BTR-London & SE | I84: =$I$10 -> Enigma Square | J84: Enigma Square Apartments | L84: C | M84: Apartment | N84: 313 | O84: 506.76 | P84: 1 Bed | Q84: 1 | R84: 3 | S84: Carpark and other block | U84: Juliette | V84: [Select] | X84: [Select] | Y84: [Select]
D85: [Select] | H85: =$I$9 -> BTR-London & SE | I85: =$I$10 -> Enigma Square | J85: Enigma Square Apartments | L85: D | M85: Apartment | N85: 314 | O85: 507.41 | P85: 1 Bed | Q85: 1 | R85: 3 | S85: Carpark and other block | U85: Juliette | V85: [Select] | X85: [Select] | Y85: [Select]
D86: [Select] | H86: =$I$9 -> BTR-London & SE | I86: =$I$10 -> Enigma Square | J86: Enigma Square Apartments | L86: D | M86: Apartment | N86: 315 | O86: 749.38 | P86: 2 Bed | Q86: 2 | R86: 3 | S86: Internal Courtyard | U86: Cantilever Balcony | V86: [Select] | X86: [Select] | Y86: [Select]
D87: [Select] | H87: =$I$9 -> BTR-London & SE | I87: =$I$10 -> Enigma Square | J87: Enigma Square Apartments | L87: D | M87: Apartment | N87: 316 | O87: 510.21 | P87: 1 Bed | Q87: 1 | R87: 3 | S87: Carpark and other block | U87: Juliette | V87: [Select] | X87: [Select] | Y87: [Select]
D88: [Select] | H88: =$I$9 -> BTR-London & SE | I88: =$I$10 -> Enigma Square | J88: Enigma Square Apartments | L88: D | M88: Apartment | N88: 317 | O88: 506.87 | P88: 1 Bed | Q88: 1 | R88: 3 | S88: Internal Courtyard | U88: Cantilever Balcony | V88: [Select] | W88: Yes | X88: [Select] | Y88: [Select]
D89: [Select] | H89: =$I$9 -> BTR-London & SE | I89: =$I$10 -> Enigma Square | J89: Enigma Square Apartments | L89: D | M89: Apartment | N89: 318 | O89: 510.21 | P89: 1 Bed | Q89: 1 | R89: 3 | S89: Carpark and other block | U89: Juliette | V89: [Select] | X89: [Select] | Y89: [Select]
D90: [Select] | H90: =$I$9 -> BTR-London & SE | I90: =$I$10 -> Enigma Square | J90: Enigma Square Apartments | L90: D | M90: Apartment | N90: 319 | O90: 492.56 | P90: 1 Bed | Q90: 1 | R90: 3 | S90: Internal Courtyard | U90: Cantilever Balcony | V90: [Select] | W90: Yes | X90: [Select] | Y90: [Select]
D91: [Select] | H91: =$I$9 -> BTR-London & SE | I91: =$I$10 -> Enigma Square | J91: Enigma Square Apartments | L91: D | M91: Apartment | N91: 320 | O91: 510.21 | P91: 1 Bed | Q91: 1 | R91: 3 | S91: Carpark and other block | U91: Juliette | V91: [Select] | X91: [Select] | Y91: [Select]
D92: [Select] | H92: =$I$9 -> BTR-London & SE | I92: =$I$10 -> Enigma Square | J92: Enigma Square Apartments | L92: D | M92: Apartment | N92: 321 | O92: 530.55 | P92: 1 Bed | Q92: 1 | R92: 3 | S92: Amenity Pebble Roof | U92: Juliette | V92: [Select] | X92: [Select] | Y92: [Select]
D93: [Select] | H93: =$I$9 -> BTR-London & SE | I93: =$I$10 -> Enigma Square | J93: Enigma Square Apartments | L93: D | M93: Apartment | N93: 322 | O93: 759.93 | P93: 2 Bed | Q93: 2 | R93: 3 | S93: North Row below Treeline | T93: One storage | U93: Cantilever Balcony | V93: [Select] | X93: [Select] | Y93: [Select]
D94: [Select] | H94: =$I$9 -> BTR-London & SE | I94: =$I$10 -> Enigma Square | J94: Enigma Square Apartments | L94: D | M94: Apartment | N94: 323 | O94: 521.51 | P94: 1 Bed | Q94: 1 | R94: 3 | S94: North Row below Treeline | U94: Cantilever Balcony | V94: [Select] | X94: [Select] | Y94: [Select]
D95: [Select] | H95: =$I$9 -> BTR-London & SE | I95: =$I$10 -> Enigma Square | J95: Enigma Square Apartments | L95: D | M95: Apartment | N95: 324 | O95: 517.53 | P95: 1 Bed | Q95: 1 | R95: 3 | S95: Internal Courtyard | U95: Juliette | V95: [Select] | W95: Yes | X95: [Select] | Y95: [Select]
D96: [Select] | H96: =$I$9 -> BTR-London & SE | I96: =$I$10 -> Enigma Square | J96: Enigma Square Apartments | L96: D | M96: Apartment | N96: 325 | O96: 761.44 | P96: 2 Bed | Q96: 2 | R96: 3 | S96: North Row below Treeline | U96: Cantilever Balcony | V96: [Select] | X96: [Select] | Y96: [Select]
D97: [Select] | H97: =$I$9 -> BTR-London & SE | I97: =$I$10 -> Enigma Square | J97: Enigma Square Apartments | L97: D | M97: Apartment | N97: 326 | O97: 497.72 | P97: 1 Bed | Q97: 1 | R97: 3 | S97: Internal Courtyard | U97: Juliette | V97: [Select] | W97: Yes | X97: [Select] | Y97: [Select]
D98: [Select] | H98: =$I$9 -> BTR-London & SE | I98: =$I$10 -> Enigma Square | J98: Enigma Square Apartments | L98: D | M98: Apartment | N98: 327 | O98: 512.04 | P98: 1 Bed | Q98: 1 | R98: 3 | S98: Internal Courtyard | U98: Juliette | V98: [Select] | W98: Yes | X98: [Select] | Y98: [Select]
D99: [Select] | H99: =$I$9 -> BTR-London & SE | I99: =$I$10 -> Enigma Square | J99: Enigma Square Apartments | L99: D | M99: Apartment | N99: 328 | O99: 761.44 | P99: 2 Bed | Q99: 2 | R99: 3 | S99: North Row below Treeline | U99: Cantilever Balcony | V99: [Select] | X99: [Select] | Y99: [Select]
D100: [Select] | H100: =$I$9 -> BTR-London & SE | I100: =$I$10 -> Enigma Square | J100: Enigma Square Apartments | L100: D | M100: Apartment | N100: 329 | O100: 517.53 | P100: 1 Bed | Q100: 1 | R100: 3 | S100: Internal Courtyard | U100: Juliette | V100: [Select] | W100: Yes | X100: [Select] | Y100: [Select]
D101: [Select] | H101: =$I$9 -> BTR-London & SE | I101: =$I$10 -> Enigma Square | J101: Enigma Square Apartments | L101: D | M101: Apartment | N101: 330 | O101: 521.51 | P101: 1 Bed | Q101: 1 | R101: 3 | S101: North Row below Treeline | U101: Cantilever Balcony | V101: [Select] | X101: [Select] | Y101: [Select]
D102: [Select] | H102: =$I$9 -> BTR-London & SE | I102: =$I$10 -> Enigma Square | J102: Enigma Square Apartments | L102: D | M102: Apartment | N102: 331 | O102: 760.9 | P102: 2 Bed | Q102: 2 | R102: 3 | S102: North Row below Treeline | T102: One storage | U102: Cantilever Balcony | V102: [Select] | X102: [Select] | Y102: [Select]
D103: [Select] | H103: =$I$9 -> BTR-London & SE | I103: =$I$10 -> Enigma Square | J103: Enigma Square Apartments | L103: D | M103: Apartment | N103: 332 | O103: 524.74 | P103: 1 Bed | Q103: 1 | R103: 3 | S103: Saxon Gate below Treeline | U103: Cantilever Balcony | V103: [Select] | X103: [Select] | Y103: [Select]
D104: [Select] | H104: =$I$9 -> BTR-London & SE | I104: =$I$10 -> Enigma Square | J104: Enigma Square Apartments | L104: D | M104: Apartment | N104: 333 | O104: 510.96 | P104: 1 Bed | Q104: 1 | R104: 3 | S104: Saxon Gate below Treeline | U104: Cantilever Balcony | V104: [Select] | X104: [Select] | Y104: [Select]
D105: [Select] | H105: =$I$9 -> BTR-London & SE | I105: =$I$10 -> Enigma Square | J105: Enigma Square Apartments | L105: D | M105: Apartment | N105: 334 | O105: 492.56 | P105: 1 Bed | Q105: 1 | R105: 3 | S105: Internal Courtyard | U105: Juliette | V105: [Select] | W105: Yes | X105: [Select] | Y105: [Select]
D106: [Select] | H106: =$I$9 -> BTR-London & SE | I106: =$I$10 -> Enigma Square | J106: Enigma Square Apartments | L106: D | M106: Apartment | N106: 335 | O106: 510.96 | P106: 1 Bed | Q106: 1 | R106: 3 | S106: Saxon Gate below Treeline | U106: Cantilever Balcony | V106: [Select] | X106: [Select] | Y106: [Select]
D107: [Select] | H107: =$I$9 -> BTR-London & SE | I107: =$I$10 -> Enigma Square | J107: Enigma Square Apartments | L107: D | M107: Apartment | N107: 336 | O107: 506.87 | P107: 1 Bed | Q107: 1 | R107: 3 | S107: Internal Courtyard | U107: Juliette | V107: [Select] | W107: Yes | X107: [Select] | Y107: [Select]
D108: [Select] | H108: =$I$9 -> BTR-London & SE | I108: =$I$10 -> Enigma Square | J108: Enigma Square Apartments | L108: D | M108: Apartment | N108: 337 | O108: 510.96 | P108: 1 Bed | Q108: 1 | R108: 3 | S108: Saxon Gate below Treeline | U108: Cantilever Balcony | V108: [Select] | X108: [Select] | Y108: [Select]
D109: [Select] | H109: =$I$9 -> BTR-London & SE | I109: =$I$10 -> Enigma Square | J109: Enigma Square Apartments | L109: D | M109: Apartment | N109: 338 | O109: 749.38 | P109: 2 Bed | Q109: 2 | R109: 3 | S109: Internal Courtyard | U109: Juliette | V109: [Select] | X109: [Select] | Y109: [Select]
...

Sheet 2. GRI Pricing Inputs
C3: 2. GRAINGER PRICING INPUTS | AL3: METHODOLOGY
C5: 0. Accomodation information
C7: Home Type | D7: [Select] | E7: Apartment | F7: House | G7: Townhouse
C9: Block Name | D9: [Select]
C11: 1. Base price
C13: The base pricing for each bed type based on comparable evidence of the local market.
C15: Bedroom | D15: [Select] | E15: ='1. Accomodation'!L9 -> Studio | F15: ='1. Accomodation'!L10 -> 1 Bed | G15: ='1. Accomodation'!L11 -> 2 Bed | H15: ='1. Accomodation'!L12 -> 3 bed | I15: ='1. Accomodation'!L13 -> 0 | J15: ='1. Accomodation'!M13 -> 0
C16: Base Price (£pm) | E16: 1175 | F16: 1275 | G16: 1665 | H16: 1915
C18: 2. Bath premium
C20: The premium to the base pricing (assumes a standard X bed homes) to reflect either the discount for only have 1 bathroom or the premium for having two.
C22: Bath | D22: [Select] | E22: 1 | F22: 2
C23: Bath Premium
C25: 3. Size premium by range
C27: The premium to the base pricing (assumes a standard X bed homes) to reflect units which are above or below the standard size.
C29: Bedroom | D29: [Select] | E29: 1 Bed | F29: 2 Bed | G29: 3 Bed | H29: [Select] | I29: [Select] | J29: [Select] | K29: [Select] | L29: [Select] | M29: [Select] | N29: [Select]
C30: Average size (sqft) | E30: =IFERROR(INDEX('1. Accomodation'!$N$9:$N$14,MATCH('2. GRI Pricing Inputs'!E$29,'1. Accomodation'!$L$9:$L$14,0)),0) -> 504.70418 | F30: =IFERROR(INDEX('1. Accomodation'!$N$9:$N$14,MATCH('2. GRI Pricing Inputs'!F$29,'1. Accomodation'!$L$9:$L$14,0)),0) -> 734.66111 | G30: =IFERROR(INDEX('1. Accomodation'!$N$9:$N$14,MATCH('2. GRI Pricing Inputs'!G$29,'1. Accomodation'!$L$9:$L$14,0)),0) -> 1007.4292 | H30: =IFERROR(INDEX('1. Accomodation'!$N$9:$N$14,MATCH('2. GRI Pricing Inputs'!H$29,'1. Accomodation'!$L$9:$L$14,0)),0) -> 0 | I30: =IFERROR(INDEX('1. Accomodation'!$N$9:$N$14,MATCH('2. GRI Pricing Inputs'!I$29,'1. Accomodation'!$L$9:$L$14,0)),0) -> 0 | J30: =IFERROR(INDEX('1. Accomodation'!$N$9:$N$14,MATCH('2. GRI Pricing Inputs'!J$29,'1. Accomodation'!$L$9:$L$14,0)),0) -> 0 | K30: =IFERROR(INDEX('1. Accomodation'!$N$9:$N$14,MATCH('2. GRI Pricing Inputs'!K$29,'1. Accomodation'!$L$9:$L$14,0)),0) -> 0 | L30: =IFERROR(INDEX('1. Accomodation'!$N$9:$N$14,MATCH('2. GRI Pricing Inputs'!L$29,'1. Accomodation'!$L$9:$L$14,0)),0) -> 0 | ... N30: =IFERROR(INDEX('1. Accomodation'!$N$9:$N$14,MATCH('2. GRI Pricing Inputs'!N$29,'1. Accomodation'!$L$9:$L$14,0)),0) -> 0
C32: Size premium | D32: 1 | F32: 2 | H32: 3 | J32: 4 | L32: 5 | N32: 6 | P32: 7 | R32: 8 | T32: 9 | V32: 10 | X32: 11 | Z32: 12 | AB32: 13 | AD32: 14 | AF32: 15
D33: 385 | E33: 395 | F33: 437 | G33: 437 | H33: 485 | I33: 489 | J33: 492 | K33: 497 | L33: 506 | M33: 512 | N33: 517 | O33: 524 | P33: 529 | Q33: 532 | R33: 656 | S33: 666 | T33: 728 | U33: 728 | V33: 747 | W33: 749 | X33: 759 | Y33: 763 | Z33: 972 | AA33: 973 | AB33: 986 | AC33: 996 | AD33: 1015 | AE33: 1017 | AF33: 1052 | AG33: 1066
C34: Studio | D34: 0
C35: 1 Bed | F35: -10 | H35: -5 | J35: 0 | L35: 5 | N35: 10 | P35: 20
C36: 2 Bed | R36: -30 | T36: 0 | V36: 15 | X36: 30
C37: 3 bed | Z37: -5 | AB37: 0 | AD37: 10 | AF37: 20
C38: [Select]
C39: [Select]
C41: 4. Floor premium
C43: A discount or premium to the base price is dependent on what floor the unit is located on (typical increments are between £5 - £20 per floor).
C45: Floor | D45: [Select] | E45: 1 | F45: 2 | G45: 3 | H45: 4 | I45: 5 | J45: 6 | K45: 7 | L45: 8
C46: Floor premium | E46: 20 | F46: 25 | G46: 30 | H46: 35 | I46: 40 | J46: 45 | K46: 50 | L46: 55
C49: 5. Aspect premium
C51: The premium to the base pricing is dependent on which direction the unit is facing (for e.g. south being the best).
C53: Aspect | D53: [Select] | E53: North Row above Treeline | F53: Saxon Gate above Treeline | G53: North Row below Treeline | H53: Saxon Gate below Treeline | I53: Internal Courtyard | J53: Private patio / Internal Courtyard | K53: Amenity Pebble Roof | L53: Carpark and other block | M53: YMCA facing another block of apartments
C54: Aspect premium | E54: 50 | F54: 50 | G54: 30 | H54: 30 | I54: 15 | J54: 10 | K54: 10 | L54: 5 | M54: -20
C56: 6. Storage premium
C58: The premium to the base pricing is dependent on the storage offered in the units.
C60: Storage | D60: [Select] | E60: One storage
C61: Storage premium | E61: 10
C63: 7. Balcony premium
C65: A premium to base to reflect if there is a balcony present. Price is further broken down as below.
C67: Balcony | D67: [Select] | E67: Extra large concrete wall terrace | F67: Long Terrace Balcony | G67: Concrete Wall Terrace | H67: Long Concrete Wall Terrace | I67: Cantilever Balcony | J67: Small Terrace Balcony | K67: Enclosed Cantilever | L67: Courtyard Terrace | M67: Juliette | N67: None
C68: Balcony premium | E68: 80 | F68: 55 | G68: 30 | H68: 30 | I68: 40 | J68: 30 | K68: 30 | L68: 15 | M68: 10 | N68: 0
C70: 8. Amenity premium
C72: The premium to the base pricing is dependent on the amenity offered in the portfolio.
C74: Amenity | D74: [Select] | E74: Gym | F74: Dining | G74: Lounge | H74: Yoga | I74: Concierge | J74: Outdoor space | K74: Internet | AI74: All
C75: Amenity premium | AI75: =SUM(E75:AH75) -> 0
C78: 9. Character #1
C80: The premium to the base pricing is dependent on the character of the building.
C82: Character | D82: [Select] | E82: Yes
C83: Additional Toilet | E83: 15
C85: 10. Character #2
C87: The premium to the base pricing is dependent on the character of the building.
C89: Character | D89: [Select] | E89: Yes
C90: Larger Master Bedroom | E90: 10 | AJ90: =SUM(E90:J90)='1. Accomodation'!E14 -> FALSE
C93: 11. Character #3
C95: The premium to the base pricing is dependent on the character of the building.
C97: Character | D97: [Select]
C100: 12. Character #4
C102: The premium to the base pricing is dependent on the character of the building.
C104: Character | D104: [Select]
C108: 13. Growth rate
C110: Rents are assumed to grow at the below rate per annum stipulated by Asset Manager. | AL110: Per CBRE/ Budget assumption
C114: Business Plan Growth Rate | D114: p.a | E114: ='3. GRI Pricing'!AD16 -> 45596 | F114: ='3. GRI Pricing'!AE16 -> 45626 | G114: ='3. GRI Pricing'!AF16 -> 45657 | H114: ='3. GRI Pricing'!AG16 -> 45688 | I114: ='3. GRI Pricing'!AH16 -> 45716 | J114: ='3. GRI Pricing'!AI16 -> 45747 | K114: ='3. GRI Pricing'!AJ16 -> 45777 | L114: ='3. GRI Pricing'!AK16 -> 45808 | ... Q114: ='3. GRI Pricing'!AP16 -> 45961
C115: PRS | D115: 0.06 | E115: 0.06 | F115: 0.06 | G115: 0.06 | H115: 0.06 | I115: 0.06 | J115: 0.06 | K115: 0.06 | L115: 0.06 | M115: 0.06 | N115: 0.06 | O115: 0.06 | P115: 0.06 | Q115: 0.06
C116: Commercial | D116: 0.02
C117: Car Parking | D117: 0
C119: 14. Car Park
C121: Units | D121: ='1. Accomodation'!M16 -> 178 | AL121: Per CBRE
C122: Base price

Sheet 3. GRI Pricing
C3: 3. GRAINGER PRICING SCHEDULE
C5: ='1. Accomodation'!L8 -> Bedroom | D5: ='1. Accomodation'!M8 -> No. of Homes | E5: Av. Size (sqft) | F5: Launch Rent (pcm) | G5: Launch Rent (pa) | H5: Launch Rent (psf) | AC5: =C5 -> Bedroom | AD5: =AD16 -> 45596 | AE5: =AE16 -> 45626 | AF5: =AF16 -> 45657 | AG5: =AG16 -> 45688 | AH5: =AH16 -> 45716 | AI5: =AI16 -> 45747 | AJ5: =AJ16 -> 45777 | AK5: =AK16 -> 45808 | ... AP5: =AP16 -> 45961
C6: ='1. Accomodation'!L9 -> Studio | D6: ='1. Accomodation'!M9 -> 13 | E6: ='1. Accomodation'!N9 -> 389.98462 | F6: =IFERROR(AVERAGEIF($E$17:$E$616,$C6,$Z$17:$Z$616),0) -> 1216.5385 | G6: =F6*12 -> 14598.462 | H6: =IFERROR(G6/E6,0) -> 37.433429 | AC6: =C6 -> Studio | AD6: =IFERROR(AVERAGEIF($E$17:$E$616,$C6,AD$17:AD$616),0) -> 1222.5739 | AE6: =IFERROR(AVERAGEIF($E$17:$E$616,$C6,AE$17:AE$616),0) -> 1228.4431 | AF6: =IFERROR(AVERAGEIF($E$17:$E$616,$C6,AF$17:AF$616),0) -> 1234.5376 | AG6: =IFERROR(AVERAGEIF($E$17:$E$616,$C6,AG$17:AG$616),0) -> 1240.6623 | AH6: =IFERROR(AVERAGEIF($E$17:$E$616,$C6,AH$17:AH$616),0) -> 1246.2204 | AI6: =IFERROR(AVERAGEIF($E$17:$E$616,$C6,AI$17:AI$616),0) -> 1252.403 | AJ6: =IFERROR(AVERAGEIF($E$17:$E$616,$C6,AJ$17:AJ$616),0) -> 1258.4155 | AK6: =IFERROR(AVERAGEIF($E$17:$E$616,$C6,AK$17:AK$616),0) -> 1264.6586 | ... AP6: =IFERROR(AVERAGEIF($E$17:$E$616,$C6,AP$17:AP$616),0) -> 1295.9283
C7: ='1. Accomodation'!L10 -> 1 Bed | D7: ='1. Accomodation'!M10 -> 182 | E7: ='1. Accomodation'!N10 -> 504.70418 | F7: =IFERROR(AVERAGEIF($E$17:$E$616,$C7,$Z$17:$Z$616),0) -> 1360.467 | G7: =F7*12 -> 16325.604 | H7: =IFERROR(G7/E7,0) -> 32.346878 | AC7: =C7 -> 1 Bed | AD7: =IFERROR(AVERAGEIF($E$17:$E$616,$C7,AD$17:AD$616),0) -> 1367.2165 | AE7: =IFERROR(AVERAGEIF($E$17:$E$616,$C7,AE$17:AE$616),0) -> 1373.7801 | AF7: =IFERROR(AVERAGEIF($E$17:$E$616,$C7,AF$17:AF$616),0) -> 1380.5956 | AG7: =IFERROR(AVERAGEIF($E$17:$E$616,$C7,AG$17:AG$616),0) -> 1387.4449 | AH7: =IFERROR(AVERAGEIF($E$17:$E$616,$C7,AH$17:AH$616),0) -> 1393.6606 | AI7: =IFERROR(AVERAGEIF($E$17:$E$616,$C7,AI$17:AI$616),0) -> 1400.5747 | AJ7: =IFERROR(AVERAGEIF($E$17:$E$616,$C7,AJ$17:AJ$616),0) -> 1407.2985 | AK7: =IFERROR(AVERAGEIF($E$17:$E$616,$C7,AK$17:AK$616),0) -> 1414.2803 | ... AP7: =IFERROR(AVERAGEIF($E$17:$E$616,$C7,AP$17:AP$616),0) -> 1449.2495
C8: ='1. Accomodation'!L11 -> 2 Bed | D8: ='1. Accomodation'!M11 -> 54 | E8: ='1. Accomodation'!N11 -> 734.66111 | F8: =IFERROR(AVERAGEIF($E$17:$E$616,$C8,$Z$17:$Z$616),0) -> 1770.8333 | G8: =F8*12 -> 21250 | H8: =IFERROR(G8/E8,0) -> 28.924901 | AC8: =C8 -> 2 Bed | AD8: =IFERROR(AVERAGEIF($E$17:$E$616,$C8,AD$17:AD$616),0) -> 1779.6187 | AE8: =IFERROR(AVERAGEIF($E$17:$E$616,$C8,AE$17:AE$616),0) -> 1788.1621 | AF8: =IFERROR(AVERAGEIF($E$17:$E$616,$C8,AF$17:AF$616),0) -> 1797.0334 | AG8: =IFERROR(AVERAGEIF($E$17:$E$616,$C8,AG$17:AG$616),0) -> 1805.9487 | AH8: =IFERROR(AVERAGEIF($E$17:$E$616,$C8,AH$17:AH$616),0) -> 1814.0393 | AI8: =IFERROR(AVERAGEIF($E$17:$E$616,$C8,AI$17:AI$616),0) -> 1823.039 | AJ8: =IFERROR(AVERAGEIF($E$17:$E$616,$C8,AJ$17:AJ$616),0) -> 1831.7909 | AK8: =IFERROR(AVERAGEIF($E$17:$E$616,$C8,AK$17:AK$616),0) -> 1840.8786 | ... AP8: =IFERROR(AVERAGEIF($E$17:$E$616,$C8,AP$17:AP$616),0) -> 1886.3958
C9: ='1. Accomodation'!L12 -> 3 bed | D9: ='1. Accomodation'!M12 -> 12 | E9: ='1. Accomodation'!N12 -> 1007.4292 | F9: =IFERROR(AVERAGEIF($E$17:$E$616,$C9,$Z$17:$Z$616),0) -> 2069.1667 | G9: =F9*12 -> 24830 | H9: =IFERROR(G9/E9,0) -> 24.646894 | AC9: =C9 -> 3 bed | AD9: =IFERROR(AVERAGEIF($E$17:$E$616,$C9,AD$17:AD$616),0) -> 2079.4321 | AE9: =IFERROR(AVERAGEIF($E$17:$E$616,$C9,AE$17:AE$616),0) -> 2089.4148 | AF9: =IFERROR(AVERAGEIF($E$17:$E$616,$C9,AF$17:AF$616),0) -> 2099.7807 | AG9: =IFERROR(AVERAGEIF($E$17:$E$616,$C9,AG$17:AG$616),0) -> 2110.198 | AH9: =IFERROR(AVERAGEIF($E$17:$E$616,$C9,AH$17:AH$616),0) -> 2119.6516 | AI9: =IFERROR(AVERAGEIF($E$17:$E$616,$C9,AI$17:AI$616),0) -> 2130.1674 | AJ9: =IFERROR(AVERAGEIF($E$17:$E$616,$C9,AJ$17:AJ$616),0) -> 2140.3938 | AK9: =IFERROR(AVERAGEIF($E$17:$E$616,$C9,AK$17:AK$616),0) -> 2151.0125 | ... AP9: =IFERROR(AVERAGEIF($E$17:$E$616,$C9,AP$17:AP$616),0) -> 2204.198
C10: ='1. Accomodation'!L13 -> 0 | D10: ='1. Accomodation'!M13 -> 0 | E10: ='1. Accomodation'!N13 -> - | F10: =IFERROR(AVERAGEIF($E$17:$E$616,$C10,$Z$17:$Z$616),0) -> 0 | G10: =F10*12 -> 0 | H10: =IFERROR(G10/E10,0) -> 0 | AC10: =C10 -> 0 | AD10: =IFERROR(AVERAGEIF($E$17:$E$616,$C10,AD$17:AD$616),0) -> 0 | AE10: =IFERROR(AVERAGEIF($E$17:$E$616,$C10,AE$17:AE$616),0) -> 0 | AF10: =IFERROR(AVERAGEIF($E$17:$E$616,$C10,AF$17:AF$616),0) -> 0 | AG10: =IFERROR(AVERAGEIF($E$17:$E$616,$C10,AG$17:AG$616),0) -> 0 | AH10: =IFERROR(AVERAGEIF($E$17:$E$616,$C10,AH$17:AH$616),0) -> 0 | AI10: =IFERROR(AVERAGEIF($E$17:$E$616,$C10,AI$17:AI$616),0) -> 0 | AJ10: =IFERROR(AVERAGEIF($E$17:$E$616,$C10,AJ$17:AJ$616),0) -> 0 | AK10: =IFERROR(AVERAGEIF($E$17:$E$616,$C10,AK$17:AK$616),0) -> 0 | ... AP10: =IFERROR(AVERAGEIF($E$17:$E$616,$C10,AP$17:AP$616),0) -> 0
C11: ='1. Accomodation'!L14 -> 0 | D11: ='1. Accomodation'!M14 -> 0 | E11: ='1. Accomodation'!N14 -> - | F11: =IFERROR(AVERAGEIF($E$17:$E$616,$C11,$Z$17:$Z$616),0) -> 0 | G11: =F11*12 -> 0 | H11: =IFERROR(G11/E11,0) -> 0 | AC11: =C11 -> 0 | AD11: =IFERROR(AVERAGEIF($E$17:$E$616,$C11,AD$17:AD$616),0) -> 0 | AE11: =IFERROR(AVERAGEIF($E$17:$E$616,$C11,AE$17:AE$616),0) -> 0 | AF11: =IFERROR(AVERAGEIF($E$17:$E$616,$C11,AF$17:AF$616),0) -> 0 | AG11: =IFERROR(AVERAGEIF($E$17:$E$616,$C11,AG$17:AG$616),0) -> 0 | AH11: =IFERROR(AVERAGEIF($E$17:$E$616,$C11,AH$17:AH$616),0) -> 0 | AI11: =IFERROR(AVERAGEIF($E$17:$E$616,$C11,AI$17:AI$616),0) -> 0 | AJ11: =IFERROR(AVERAGEIF($E$17:$E$616,$C11,AJ$17:AJ$616),0) -> 0 | AK11: =IFERROR(AVERAGEIF($E$17:$E$616,$C11,AK$17:AK$616),0) -> 0 | ... AP11: =IFERROR(AVERAGEIF($E$17:$E$616,$C11,AP$17:AP$616),0) -> 0
C12: AVERAGE | D12: ='1. Accomodation'!M15 -> 261 | E12: =IFERROR('1. Accomodation'!N15,0) -> 569.68126 | F12: =IFERROR(G12/12,0) -> 1470.7854 | G12: =IFERROR(Z617/$D$12,0) -> 17649.425 | H12: =IFERROR(G12/$E$12,0) -> 30.981228 | AC12: =C12 -> AVERAGE | AD12: =IFERROR(AVERAGEIF($E$17:$E$616,$C12,AD$17:AD$616),0) -> 0 | AE12: =IFERROR(AVERAGEIF($E$17:$E$616,$C12,AE$17:AE$616),0) -> 0 | AF12: =IFERROR(AVERAGEIF($E$17:$E$616,$C12,AF$17:AF$616),0) -> 0 | AG12: =IFERROR(AVERAGEIF($E$17:$E$616,$C12,AG$17:AG$616),0) -> 0 | AH12: =IFERROR(AVERAGEIF($E$17:$E$616,$C12,AH$17:AH$616),0) -> 0 | AI12: =IFERROR(AVERAGEIF($E$17:$E$616,$C12,AI$17:AI$616),0) -> 0 | AJ12: =IFERROR(AVERAGEIF($E$17:$E$616,$C12,AJ$17:AJ$616),0) -> 0 | AK12: =IFERROR(AVERAGEIF($E$17:$E$616,$C12,AK$17:AK$616),0) -> 0 | ... AP12: =IFERROR(AVERAGEIF($E$17:$E$616,$C12,AP$17:AP$616),0) -> 0
C13: Car park | D13: ='1. Accomodation'!M16 -> 178 | F13: ='2. GRI Pricing Inputs'!D122 -> 0 | G13: =F13*12 -> 0 | AC13: =C13 -> Car park | AD13: =IFERROR(AVERAGEIF($E$17:$E$616,$C13,AD$17:AD$616),0) -> 0 | AE13: =IFERROR(AVERAGEIF($E$17:$E$616,$C13,AE$17:AE$616),0) -> 0 | AF13: =IFERROR(AVERAGEIF($E$17:$E$616,$C13,AF$17:AF$616),0) -> 0 | AG13: =IFERROR(AVERAGEIF($E$17:$E$616,$C13,AG$17:AG$616),0) -> 0 | AH13: =IFERROR(AVERAGEIF($E$17:$E$616,$C13,AH$17:AH$616),0) -> 0 | AI13: =IFERROR(AVERAGEIF($E$17:$E$616,$C13,AI$17:AI$616),0) -> 0 | AJ13: =IFERROR(AVERAGEIF($E$17:$E$616,$C13,AJ$17:AJ$616),0) -> 0 | AK13: =IFERROR(AVERAGEIF($E$17:$E$616,$C13,AK$17:AK$616),0) -> 0 | ... AP13: =IFERROR(AVERAGEIF($E$17:$E$616,$C13,AP$17:AP$616),0) -> 0
C15: Accomodation Attributes | L15: GRI PRICING FRAMEWORK | AC15: 45565 | AD15: Monthly rent increase over 12 months (using Grainger growth rate)
A16: Unit Reference | C16: ='1. Accomodation'!N20 -> Door Number | D16: ='1. Accomodation'!L20 -> Block Name | E16: ='1. Accomodation'!P20 -> Bedroom | F16: ='1. Accomodation'!Q20 -> Bath | G16: ='1. Accomodation'!O20 -> Size (sq.ft) | H16: ='1. Accomodation'!R20 -> Floor | I16: ='1. Accomodation'!S20 -> Aspect | L16: ='2. GRI Pricing Inputs'!C16 -> Base Price (£pm) | M16: ='2. GRI Pricing Inputs'!C23 -> Bath Premium | N16: Area Range | O16: ='2. GRI Pricing Inputs'!C32 -> Size premium | P16: ='2. GRI Pricing Inputs'!C46 -> Floor premium | Q16: ='2. GRI Pricing Inputs'!C54 -> Aspect premium | R16: ='2. GRI Pricing Inputs'!C61 -> Storage premium | S16: ='2. GRI Pricing Inputs'!C68 -> Balcony premium | T16: ='2. GRI Pricing Inputs'!C75 -> Amenity premium | U16: ='2. GRI Pricing Inputs'!C83 -> Additional Toilet | V16: ='2. GRI Pricing Inputs'!C90 -> Larger Master Bedroom | W16: ='2. GRI Pricing Inputs'!C98 -> 0 | X16: ='2. GRI Pricing Inputs'!C105 -> 0 | Y16: Manual Adjustment (must provide reason) | Z16: Proposed Rent (pcm) | AD16: =EOMONTH(AC15,1) -> 45596 | AE16: =EOMONTH(AD16,1) -> 45626 | AF16: =EOMONTH(AE16,1) -> 45657 | AG16: =EOMONTH(AF16,1) -> 45688 | AH16: =EOMONTH(AG16,1) -> 45716 | AI16: =EOMONTH(AH16,1) -> 45747 | AJ16: =EOMONTH(AI16,1) -> 45777 | AK16: =EOMONTH(AJ16,1) -> 45808 | AL16: =EOMONTH(AK16,1) -> 45838 | ... AP16: =EOMONTH(AO16,1) -> 45961 | AQ16: Cumulative Annual Growth
A17: =_xlfn.XLOOKUP($C17,'Data Ref'!$D:$D,'Data Ref'!$B:$B,0) -> 222708001 | C17: ='1. Accomodation'!N21 -> 101 | D17: ='1. Accomodation'!L21 -> C | E17: ='1. Accomodation'!P21 -> 1 Bed | F17: ='1. Accomodation'!Q21 -> 1 | G17: ='1. Accomodation'!O21 -> 517.1 | H17: ='1. Accomodation'!R21 -> 1 | I17: ='1. Accomodation'!S21 -> North Row below Treeline | L17: =IFERROR(INDEX('2. GRI Pricing Inputs'!$C$15:$AI$16,MATCH($L$16,'2. GRI Pricing Inputs'!$C$15:$C$16,0),MATCH(E17,'2. GRI Pricing Inputs'!$C$15:$AI$15,0)),0) -> 1275 | M17: =IFERROR(INDEX('2. GRI Pricing Inputs'!$C$22:$AI$23,MATCH($M$16,'2. GRI Pricing Inputs'!$C$22:$C$23,0),MATCH(F17,'2. GRI Pricing Inputs'!$C$22:$AI$22,0)),0) -> 0 | N17: =IF(AND('3. GRI Pricing'!$G17>='2. GRI Pricing Inputs'!$D$33,'3. GRI Pricing'!$G17<='2. GRI Pricing Inputs'!$E$33),'2. GRI Pricing Inputs'!$D$32,IF(AND('3. GRI Pricing'!$G17>='2. GRI Pricing Inputs'!$F$33,'3. GRI Pricing'!$G17<='2. GRI Pricing Inputs'!$G$33),'2. GRI Pricing Inputs'!$F$32,IF(AND('3. GRI Pricing'!$G17>='2. GRI Pricing Inputs'!$H$33,'3. GRI Pricing'!$G17<='2. GRI Pricing Inputs'!$I$33),'2. GRI Pricing Inputs'!$H$32,IF(AND('3. GRI Pricing'!$G17>='2. GRI Pricing Inputs'!$J$33,'3. GRI Pricing'!$G17<='2. GRI Pricing Inputs'!$K$33),'2. GRI Pricing Inputs'!$J$32,IF(AND('3. GRI Pricing'!$G17>='2. GRI Pricing Inputs'!$L$33,'3. GRI Pricing'!$G17<='2. GRI Pricing Inputs'!$M$33),'2. GRI Pricing Inputs'!$L$32,IF(AND('3. GRI Pricing'!$G17>='2. GRI Pricing Inputs'!$N$33,'3. GRI Pricing'!$G17<='2. GRI Pricing Inputs'!$O$33),'2. GRI Pricing Inputs'!$N$32,IF(AND('3. GRI Pricing'!$G17>='2. GRI Pricing Inputs'!$P$33,'3. GRI Pricing'!$G17<='2. GRI Pricing Inputs'!$Q$33),'2. GRI Pricing Inputs'!$P$32,IF(AND('3. GRI Pricing'!$G17>='2. GRI Pricing Inputs'!$R$33,'3. GRI Pricing'!$G17<='2. GRI Pricing Inputs'!$S$33),'2. GRI Pricing Inputs'!$R$32,IF(AND('3. GRI Pricing'!$G17>='2. GRI Pricing Inputs'!$T$33,'3. GRI Pricing'!$G17<='2. GRI Pricing Inputs'!$U$33),'2. GRI Pricing Inputs'!$T$32,IF(AND('3. GRI Pricing'!$G17>='2. GRI Pricing Inputs'!$V$33,'3. GRI Pricing'!$G17<='2. GRI Pricing Inputs'!$W$33),'2. GRI Pricing Inputs'!$V$32,IF(AND('3. GRI Pricing'!$G17>='2. GRI Pricing Inputs'!$X$33,'3. GRI Pricing'!$G17<='2. GRI Pricing Inputs'!$Y$33),'2. GRI Pricing Inputs'!$X$32,IF(AND('3. GRI Pricing'!$G17>='2. GRI Pricing Inputs'!$Z$33,'3. GRI Pricing'!$G17<='2. GRI Pricing Inputs'!$AA$33),'2. GRI Pricing Inputs'!$Z$32,IF(AND('3. GRI Pricing'!$G17>='2. GRI Pricing Inputs'!$AB$33,'3. GRI Pricing'!$G17<='2. GRI Pricing Inputs'!$AC$33),'2. GRI Pricing Inputs'!$AB$32,IF(AND('3. GRI Pricing'!$G17>='2. GRI Pricing Inputs'!$AD$33,'3. GRI Pricing'!$G17<='2. GRI Pricing Inputs'!$AE$33),'2. GRI Pricing Inputs'!$AD$32,IF(AND('3. GRI Pricing'!$G17>='2. GRI Pricing Inputs'!$AF$33,'3. GRI Pricing'!$G17<='2. GRI Pricing Inputs'!$AG$33),'2. GRI Pricing Inputs'!$AF$32,IF(AND('3. GRI Pricing'!$G17>='2. GRI Pricing Inputs'!$AH$33,'3. GRI Pricing'!$G17<='2. GRI Pricing Inputs'!$AI$33),'2. GRI Pricing Inputs'!$AH$32,0)))))))))))))))) -> 6 | O17: {=IFERROR(INDEX('2. GRI Pricing Inputs'!$C$32:$AI$39,MATCH('3. GRI Pricing'!E17,'2. GRI Pricing Inputs'!$C$32:$C$39,0),(MATCH('3. GRI Pricing'!N17,'2. GRI Pricing Inputs'!$D$32:$AI$32,0)+1)),0)} -> 10 | P17: =IFERROR(INDEX('2. GRI Pricing Inputs'!$C$45:$AI$46,MATCH($P$16,'2. GRI Pricing Inputs'!$C$45:$C$46,0),MATCH(H17,'2. GRI Pricing Inputs'!$C$45:$AI$45,0)),0) -> 20 | Q17: =IFERROR(INDEX('2. GRI Pricing Inputs'!$C$53:$AI$54,MATCH('3. GRI Pricing'!$Q$16,'2. GRI Pricing Inputs'!$C$53:$C$54,0),MATCH('3. GRI Pricing'!I17,'2. GRI Pricing Inputs'!$C$53:$AI$53,0)),0) -> 30 | R17: =IFERROR(INDEX('2. GRI Pricing Inputs'!$C$60:$AI$61,MATCH('3. GRI Pricing'!$R$16,'2. GRI Pricing Inputs'!$C$60:$C$61,0),MATCH('1. Accomodation'!T21,'2. GRI Pricing Inputs'!$C$60:$AI$60,0)),0) -> 0 | S17: =IFERROR(INDEX('2. GRI Pricing Inputs'!$C$67:$AI$68,MATCH('3. GRI Pricing'!$S$16,'2. GRI Pricing Inputs'!$C$67:$C$68,0),MATCH('1. Accomodation'!U21,'2. GRI Pricing Inputs'!$C$67:$AI$67,0)),0) -> 30 | T17: =IF(E17=0,0,'2. GRI Pricing Inputs'!$AI$75) -> 0 | U17: =IFERROR(INDEX('2. GRI Pricing Inputs'!$C$82:$AI$83,MATCH('3. GRI Pricing'!$U$16,'2. GRI Pricing Inputs'!$C$82:$C$83,0),MATCH('1. Accomodation'!V21,'2. GRI Pricing Inputs'!$C$82:$AI$82,0)),0) -> 0 | V17: =IFERROR(INDEX('2. GRI Pricing Inputs'!$C$89:$AI$90,MATCH('3. GRI Pricing'!$V$16,'2. GRI Pricing Inputs'!$C$89:$C$90,0),MATCH('1. Accomodation'!W21,'2. GRI Pricing Inputs'!$C$89:$AI$89,0)),0) -> 0 | W17: =IFERROR(INDEX('2. GRI Pricing Inputs'!$C$97:$AI$98,MATCH('3. GRI Pricing'!$W$16,'2. GRI Pricing Inputs'!$C$97:$C$98,0),MATCH('1. Accomodation'!X21,'2. GRI Pricing Inputs'!$C$97:$AI$97,0)),0) -> 0 | X17: =IFERROR(INDEX('2. GRI Pricing Inputs'!$C$104:$AI$105,MATCH('3. GRI Pricing'!$X$16,'2. GRI Pricing Inputs'!$C$104:$C$105,0),MATCH('1. Accomodation'!Y21,'2. GRI Pricing Inputs'!$C$104:$AI$104,0)),0) -> 0 | Z17: =L17+M17+O17+P17+Q17+R17+S17+T17+U17+V17+W17+X17+Y17 -> 1365 | AD17: =Z17*(1+'2. GRI Pricing Inputs'!E$115)^(($AD$16-$AC$15)/365) -> 1371.7719 | AE17: =AD17*(1+'2. GRI Pricing Inputs'!F$115)^((AE$16-AD$16)/365) -> 1378.3574 | AF17: =AE17*(1+'2. GRI Pricing Inputs'!G$115)^((AF$16-AE$16)/365) -> 1385.1956 | AG17: =AF17*(1+'2. GRI Pricing Inputs'!H$115)^((AG$16-AF$16)/365) -> 1392.0678 | AH17: =AG17*(1+'2. GRI Pricing Inputs'!I$115)^((AH$16-AG$16)/365) -> 1398.3042 | AI17: =AH17*(1+'2. GRI Pricing Inputs'!J$115)^((AI$16-AH$16)/365) -> 1405.2413 | AJ17: =AI17*(1+'2. GRI Pricing Inputs'!K$115)^((AJ$16-AI$16)/365) -> 1411.9875 | AK17: =AJ17*(1+'2. GRI Pricing Inputs'!L$115)^((AK$16-AJ$16)/365) -> 1418.9926 | AL17: =AK17*(1+'2. GRI Pricing Inputs'!M$115)^((AL$16-AK$16)/365) -> 1425.8047 | ... AP17: =AO17*(1+'2. GRI Pricing Inputs'!Q$115)^((AP$16-AO$16)/365) -> 1454.0783 | AQ17: =IFERROR(AP17/AD17-1,0) -> 0.06
A18: =_xlfn.XLOOKUP($C18,'Data Ref'!$D:$D,'Data Ref'!$B:$B,0) -> 222708002 | C18: ='1. Accomodation'!N22 -> 102 | D18: ='1. Accomodation'!L22 -> C | E18: ='1. Accomodation'!P22 -> Studio | F18: ='1. Accomodation'!Q22 -> 1 | G18: ='1. Accomodation'!O22 -> 385.46 | H18: ='1. Accomodation'!R22 -> 1 | I18: ='1. Accomodation'!S22 -> Nursery and mixed other buildings | L18: =IFERROR(INDEX('2. GRI Pricing Inputs'!$C$15:$AI$16,MATCH($L$16,'2. GRI Pricing Inputs'!$C$15:$C$16,0),MATCH(E18,'2. GRI Pricing Inputs'!$C$15:$AI$15,0)),0) -> 1175 | M18: =IFERROR(INDEX('2. GRI Pricing Inputs'!$C$22:$AI$23,MATCH($M$16,'2. GRI Pricing Inputs'!$C$22:$C$23,0),MATCH(F18,'2. GRI Pricing Inputs'!$C$22:$AI$22,0)),0) -> 0 | N18: =IF(AND('3. GRI Pricing'!$G18>='2. GRI Pricing Inputs'!$D$33,'3. GRI Pricing'!$G18<='2. GRI Pricing Inputs'!$E$33),'2. GRI Pricing Inputs'!$D$32,IF(AND('3. GRI Pricing'!$G18>='2. GRI Pricing Inputs'!$F$33,'3. GRI Pricing'!$G18<='2. GRI Pricing Inputs'!$G$33),'2. GRI Pricing Inputs'!$F$32,IF(AND('3. GRI Pricing'!$G18>='2. GRI Pricing Inputs'!$H$33,'3. GRI Pricing'!$G18<='2. GRI Pricing Inputs'!$I$33),'2. GRI Pricing Inputs'!$H$32,IF(AND('3. GRI Pricing'!$G18>='2. GRI Pricing Inputs'!$J$33,'3. GRI Pricing'!$G18<='2. GRI Pricing Inputs'!$K$33),'2. GRI Pricing Inputs'!$J$32,IF(AND('3. GRI Pricing'!$G18>='2. GRI Pricing Inputs'!$L$33,'3. GRI Pricing'!$G18<='2. GRI Pricing Inputs'!$M$33),'2. GRI Pricing Inputs'!$L$32,IF(AND('3. GRI Pricing'!$G18>='2. GRI Pricing Inputs'!$N$33,'3. GRI Pricing'!$G18<='2. GRI Pricing Inputs'!$O$33),'2. GRI Pricing Inputs'!$N$32,IF(AND('3. GRI Pricing'!$G18>='2. GRI Pricing Inputs'!$P$33,'3. GRI Pricing'!$G18<='2. GRI Pricing Inputs'!$Q$33),'2. GRI Pricing Inputs'!$P$32,IF(AND('3. GRI Pricing'!$G18>='2. GRI Pricing Inputs'!$R$33,'3. GRI Pricing'!$G18<='2. GRI Pricing Inputs'!$S$33),'2. GRI Pricing Inputs'!$R$32,IF(AND('3. GRI Pricing'!$G18>='2. GRI Pricing Inputs'!$T$33,'3. GRI Pricing'!$G18<='2. GRI Pricing Inputs'!$U$33),'2. GRI Pricing Inputs'!$T$32,IF(AND('3. GRI Pricing'!$G18>='2. GRI Pricing Inputs'!$V$33,'3. GRI Pricing'!$G18<='2. GRI Pricing Inputs'!$W$33),'2. GRI Pricing Inputs'!$V$32,IF(AND('3. GRI Pricing'!$G18>='2. GRI Pricing Inputs'!$X$33,'3. GRI Pricing'!$G18<='2. GRI Pricing Inputs'!$Y$33),'2. GRI Pricing Inputs'!$X$32,IF(AND('3. GRI Pricing'!$G18>='2. GRI Pricing Inputs'!$Z$33,'3. GRI Pricing'!$G18<='2. GRI Pricing Inputs'!$AA$33),'2. GRI Pricing Inputs'!$Z$32,IF(AND('3. GRI Pricing'!$G18>='2. GRI Pricing Inputs'!$AB$33,'3. GRI Pricing'!$G18<='2. GRI Pricing Inputs'!$AC$33),'2. GRI Pricing Inputs'!$AB$32,IF(AND('3. GRI Pricing'!$G18>='2. GRI Pricing Inputs'!$AD$33,'3. GRI Pricing'!$G18<='2. GRI Pricing Inputs'!$AE$33),'2. GRI Pricing Inputs'!$AD$32,IF(AND('3. GRI Pricing'!$G18>='2. GRI Pricing Inputs'!$AF$33,'3. GRI Pricing'!$G18<='2. GRI Pricing Inputs'!$AG$33),'2. GRI Pricing Inputs'!$AF$32,IF(AND('3. GRI Pricing'!$G18>='2. GRI Pricing Inputs'!$AH$33,'3. GRI Pricing'!$G18<='2. GRI Pricing Inputs'!$AI$33),'2. GRI Pricing Inputs'!$AH$32,0)))))))))))))))) -> 1 | O18: {=IFERROR(INDEX('2. GRI Pricing Inputs'!$C$32:$AI$39,MATCH('3. GRI Pricing'!E18,'2. GRI Pricing Inputs'!$C$32:$C$39,0),(MATCH('3. GRI Pricing'!N18,'2. GRI Pricing Inputs'!$D$32:$AI$32,0)+1)),0)} -> 0 | P18: =IFERROR(INDEX('2. GRI Pricing Inputs'!$C$45:$AI$46,MATCH($P$16,'2. GRI Pricing Inputs'!$C$45:$C$46,0),MATCH(H18,'2. GRI Pricing Inputs'!$C$45:$AI$45,0)),0) -> 20 | Q18: =IFERROR(INDEX('2. GRI Pricing Inputs'!$C$53:$AI$54,MATCH('3. GRI Pricing'!$Q$16,'2. GRI Pricing Inputs'!$C$53:$C$54,0),MATCH('3. GRI Pricing'!I18,'2. GRI Pricing Inputs'!$C$53:$AI$53,0)),0) -> 0 | R18: =IFERROR(INDEX('2. GRI Pricing Inputs'!$C$60:$AI$61,MATCH('3. GRI Pricing'!$R$16,'2. GRI Pricing Inputs'!$C$60:$C$61,0),MATCH('1. Accomodation'!T22,'2. GRI Pricing Inputs'!$C$60:$AI$60,0)),0) -> 0 | S18: =IFERROR(INDEX('2. GRI Pricing Inputs'!$C$67:$AI$68,MATCH('3. GRI Pricing'!$S$16,'2. GRI Pricing Inputs'!$C$67:$C$68,0),MATCH('1. Accomodation'!U22,'2. GRI Pricing Inputs'!$C$67:$AI$67,0)),0) -> 0 | T18: =IF(E18=0,0,'2. GRI Pricing Inputs'!$AI$75) -> 0 | U18: =IFERROR(INDEX('2. GRI Pricing Inputs'!$C$82:$AI$83,MATCH('3. GRI Pricing'!$U$16,'2. GRI Pricing Inputs'!$C$82:$C$83,0),MATCH('1. Accomodation'!V22,'2. GRI Pricing Inputs'!$C$82:$AI$82,0)),0) -> 0 | V18: =IFERROR(INDEX('2. GRI Pricing Inputs'!$C$89:$AI$90,MATCH('3. GRI Pricing'!$V$16,'2. GRI Pricing Inputs'!$C$89:$C$90,0),MATCH('1. Accomodation'!W22,'2. GRI Pricing Inputs'!$C$89:$AI$89,0)),0) -> 0 | W18: =IFERROR(INDEX('2. GRI Pricing Inputs'!$C$97:$AI$98,MATCH('3. GRI Pricing'!$W$16,'2. GRI Pricing Inputs'!$C$97:$C$98,0),MATCH('1. Accomodation'!X22,'2. GRI Pricing Inputs'!$C$97:$AI$97,0)),0) -> 0 | X18: =IFERROR(INDEX('2. GRI Pricing Inputs'!$C$104:$AI$105,MATCH('3. GRI Pricing'!$X$16,'2. GRI Pricing Inputs'!$C$104:$C$105,0),MATCH('1. Accomodation'!Y22,'2. GRI Pricing Inputs'!$C$104:$AI$104,0)),0) -> 0 | Z18: =L18+M18+O18+P18+Q18+R18+S18+T18+U18+V18+W18+X18+Y18 -> 1195 | AD18: =Z18*(1+'2. GRI Pricing Inputs'!E$115)^(($AD$16-$AC$15)/365) -> 1200.9286 | AE18: =AD18*(1+'2. GRI Pricing Inputs'!F$115)^((AE$16-AD$16)/365) -> 1206.6939 | AF18: =AE18*(1+'2. GRI Pricing Inputs'!G$115)^((AF$16-AE$16)/365) -> 1212.6804 | AG18: =AF18*(1+'2. GRI Pricing Inputs'!H$115)^((AG$16-AF$16)/365) -> 1218.6967 | AH18: =AG18*(1+'2. GRI Pricing Inputs'!I$115)^((AH$16-AG$16)/365) -> 1224.1564 | AI18: =AH18*(1+'2. GRI Pricing Inputs'!J$115)^((AI$16-AH$16)/365) -> 1230.2296 | AJ18: =AI18*(1+'2. GRI Pricing Inputs'!K$115)^((AJ$16-AI$16)/365) -> 1236.1356 | AK18: =AJ18*(1+'2. GRI Pricing Inputs'!L$115)^((AK$16-AJ$16)/365) -> 1242.2682 | AL18: =AK18*(1+'2. GRI Pricing Inputs'!M$115)^((AL$16-AK$16)/365) -> 1248.232 | ... AP18: =AO18*(1+'2. GRI Pricing Inputs'!Q$115)^((AP$16-AO$16)/365) -> 1272.9843 | AQ18: =IFERROR(AP18/AD18-1,0) -> 0.06
A19: =_xlfn.XLOOKUP($C19,'Data Ref'!$D:$D,'Data Ref'!$B:$B,0) -> 222708003 | C19: ='1. Accomodation'!N23 -> 103 | D19: ='1. Accomodation'!L23 -> C | E19: ='1. Accomodation'!P23 -> Studio | F19: ='1. Accomodation'!Q23 -> 1 | G19: ='1. Accomodation'!O23 -> 394.17 | H19: ='1. Accomodation'!R23 -> 1 | I19: ='1. Accomodation'!S23 -> Nursery and mixed other buildings | L19: =IFERROR(INDEX('2. GRI Pricing Inputs'!$C$15:$AI$16,MATCH($L$16,'2. GRI Pricing Inputs'!$C$15:$C$16,0),MATCH(E19,'2. GRI Pricing Inputs'!$C$15:$AI$15,0)),0) -> 1175 | M19: =IFERROR(INDEX('2. GRI Pricing Inputs'!$C$22:$AI$23,MATCH($M$16,'2. GRI Pricing Inputs'!$C$22:$C$23,0),MATCH(F19,'2. GRI Pricing Inputs'!$C$22:$AI$22,0)),0) -> 0 | N19: =IF(AND('3. GRI Pricing'!$G19>='2. GRI Pricing Inputs'!$D$33,'3. GRI Pricing'!$G19<='2. GRI Pricing Inputs'!$E$33),'2. GRI Pricing Inputs'!$D$32,IF(AND('3. GRI Pricing'!$G19>='2. GRI Pricing Inputs'!$F$33,'3. GRI Pricing'!$G19<='2. GRI Pricing Inputs'!$G$33),'2. GRI Pricing Inputs'!$F$32,IF(AND('3. GRI Pricing'!$G19>='2. GRI Pricing Inputs'!$H$33,'3. GRI Pricing'!$G19<='2. GRI Pricing Inputs'!$I$33),'2. GRI Pricing Inputs'!$H$32,IF(AND('3. GRI Pricing'!$G19>='2. GRI Pricing Inputs'!$J$33,'3. GRI Pricing'!$G19<='2. GRI Pricing Inputs'!$K$33),'2. GRI Pricing Inputs'!$J$32,IF(AND('3. GRI Pricing'!$G19>='2. GRI Pricing Inputs'!$L$33,'3. GRI Pricing'!$G19<='2. GRI Pricing Inputs'!$M$33),'2. GRI Pricing Inputs'!$L$32,IF(AND('3. GRI Pricing'!$G19>='2. GRI Pricing Inputs'!$N$33,'3. GRI Pricing'!$G19<='2. GRI Pricing Inputs'!$O$33),'2. GRI Pricing Inputs'!$N$32,IF(AND('3. GRI Pricing'!$G19>='2. GRI Pricing Inputs'!$P$33,'3. GRI Pricing'!$G19<='2. GRI Pricing Inputs'!$Q$33),'2. GRI Pricing Inputs'!$P$32,IF(AND('3. GRI Pricing'!$G19>='2. GRI Pricing Inputs'!$R$33,'3. GRI Pricing'!$G19<='2. GRI Pricing Inputs'!$S$33),'2. GRI Pricing Inputs'!$R$32,IF(AND('3. GRI Pricing'!$G19>='2. GRI Pricing Inputs'!$T$33,'3. GRI Pricing'!$G19<='2. GRI Pricing Inputs'!$U$33),'2. GRI Pricing Inputs'!$T$32,IF(AND('3. GRI Pricing'!$G19>='2. GRI Pricing Inputs'!$V$33,'3. GRI Pricing'!$G19<='2. GRI Pricing Inputs'!$W$33),'2. GRI Pricing Inputs'!$V$32,IF(AND('3. GRI Pricing'!$G19>='2. GRI Pricing Inputs'!$X$33,'3. GRI Pricing'!$G19<='2. GRI Pricing Inputs'!$Y$33),'2. GRI Pricing Inputs'!$X$32,IF(AND('3. GRI Pricing'!$G19>='2. GRI Pricing Inputs'!$Z$33,'3. GRI Pricing'!$G19<='2. GRI Pricing Inputs'!$AA$33),'2. GRI Pricing Inputs'!$Z$32,IF(AND('3. GRI Pricing'!$G19>='2. GRI Pricing Inputs'!$AB$33,'3. GRI Pricing'!$G19<='2. GRI Pricing Inputs'!$AC$33),'2. GRI Pricing Inputs'!$AB$32,IF(AND('3. GRI Pricing'!$G19>='2. GRI Pricing Inputs'!$AD$33,'3. GRI Pricing'!$G19<='2. GRI Pricing Inputs'!$AE$33),'2. GRI Pricing Inputs'!$AD$32,IF(AND('3. GRI Pricing'!$G19>='2. GRI Pricing Inputs'!$AF$33,'3. GRI Pricing'!$G19<='2. GRI Pricing Inputs'!$AG$33),'2. GRI Pricing Inputs'!$AF$32,IF(AND('3. GRI Pricing'!$G19>='2. GRI Pricing Inputs'!$AH$33,'3. GRI Pricing'!$G19<='2. GRI Pricing Inputs'!$AI$33),'2. GRI Pricing Inputs'!$AH$32,0)))))))))))))))) -> 1 | O19: {=IFERROR(INDEX('2. GRI Pricing Inputs'!$C$32:$AI$39,MATCH('3. GRI Pricing'!E19,'2. GRI Pricing Inputs'!$C$32:$C$39,0),(MATCH('3. GRI Pricing'!N19,'2. GRI Pricing Inputs'!$D$32:$AI$32,0)+1)),0)} -> 0 | P19: =IFERROR(INDEX('2. GRI Pricing Inputs'!$C$45:$AI$46,MATCH($P$16,'2. GRI Pricing Inputs'!$C$45:$C$46,0),MATCH(H19,'2. GRI Pricing Inputs'!$C$45:$AI$45,0)),0) -> 20 | Q19: =IFERROR(INDEX('2. GRI Pricing Inputs'!$C$53:$AI$54,MATCH('3. GRI Pricing'!$Q$16,'2. GRI Pricing Inputs'!$C$53:$C$54,0),MATCH('3. GRI Pricing'!I19,'2. GRI Pricing Inputs'!$C$53:$AI$53,0)),0) -> 0 | R19: =IFERROR(INDEX('2. GRI Pricing Inputs'!$C$60:$AI$61,MATCH('3. GRI Pricing'!$R$16,'2. GRI Pricing Inputs'!$C$60:$C$61,0),MATCH('1. Accomodation'!T23,'2. GRI Pricing Inputs'!$C$60:$AI$60,0)),0) -> 0 | S19: =IFERROR(INDEX('2. GRI Pricing Inputs'!$C$67:$AI$68,MATCH('3. GRI Pricing'!$S$16,'2. GRI Pricing Inputs'!$C$67:$C$68,0),MATCH('1. Accomodation'!U23,'2. GRI Pricing Inputs'!$C$67:$AI$67,0)),0) -> 0 | T19: =IF(E19=0,0,'2. GRI Pricing Inputs'!$AI$75) -> 0 | U19: =IFERROR(INDEX('2. GRI Pricing Inputs'!$C$82:$AI$83,MATCH('3. GRI Pricing'!$U$16,'2. GRI Pricing Inputs'!$C$82:$C$83,0),MATCH('1. Accomodation'!V23,'2. GRI Pricing Inputs'!$C$82:$AI$82,0)),0) -> 0 | V19: =IFERROR(INDEX('2. GRI Pricing Inputs'!$C$89:$AI$90,MATCH('3. GRI Pricing'!$V$16,'2. GRI Pricing Inputs'!$C$89:$C$90,0),MATCH('1. Accomodation'!W23,'2. GRI Pricing Inputs'!$C$89:$AI$89,0)),0) -> 0 | W19: =IFERROR(INDEX('2. GRI Pricing Inputs'!$C$97:$AI$98,MATCH('3. GRI Pricing'!$W$16,'2. GRI Pricing Inputs'!$C$97:$C$98,0),MATCH('1. Accomodation'!X23,'2. GRI Pricing Inputs'!$C$97:$AI$97,0)),0) -> 0 | X19: =IFERROR(INDEX('2. GRI Pricing Inputs'!$C$104:$AI$105,MATCH('3. GRI Pricing'!$X$16,'2. GRI Pricing Inputs'!$C$104:$C$105,0),MATCH('1. Accomodation'!Y23,'2. GRI Pricing Inputs'!$C$104:$AI$104,0)),0) -> 0 | Z19: =L19+M19+O19+P19+Q19+R19+S19+T19+U19+V19+W19+X19+Y19 -> 1195 | AD19: =Z19*(1+'2. GRI Pricing Inputs'!E$115)^(($AD$16-$AC$15)/365) -> 1200.9286 | AE19: =AD19*(1+'2. GRI Pricing Inputs'!F$115)^((AE$16-AD$16)/365) -> 1206.6939 | AF19: =AE19*(1+'2. GRI Pricing Inputs'!G$115)^((AF$16-AE$16)/365) -> 1212.6804 | AG19: =AF19*(1+'2. GRI Pricing Inputs'!H$115)^((AG$16-AF$16)/365) -> 1218.6967 | AH19: =AG19*(1+'2. GRI Pricing Inputs'!I$115)^((AH$16-AG$16)/365) -> 1224.1564 | AI19: =AH19*(1+'2. GRI Pricing Inputs'!J$115)^((AI$16-AH$16)/365) -> 1230.2296 | AJ19: =AI19*(1+'2. GRI Pricing Inputs'!K$115)^((AJ$16-AI$16)/365) -> 1236.1356 | AK19: =AJ19*(1+'2. GRI Pricing Inputs'!L$115)^((AK$16-AJ$16)/365) -> 1242.2682 | AL19: =AK19*(1+'2. GRI Pricing Inputs'!M$115)^((AL$16-AK$16)/365) -> 1248.232 | ... AP19: =AO19*(1+'2. GRI Pricing Inputs'!Q$115)^((AP$16-AO$16)/365) -> 1272.9843 | AQ19: =IFERROR(AP19/AD19-1,0) -> 0.06
A20: =_xlfn.XLOOKUP($C20,'Data Ref'!$D:$D,'Data Ref'!$B:$B,0) -> 222708004 | C20: ='1. Accomodation'!N24 -> 104 | D20: ='1. Accomodation'!L24 -> C | E20: ='1. Accomodation'!P24 -> 1 Bed | F20: ='1. Accomodation'!Q24 -> 1 | G20: ='1. Accomodation'!O24 -> 521.51 | H20: ='1. Accomodation'!R24 -> 1 | I20: ='1. Accomodation'!S24 -> North Row below Treeline | L20: =IFERROR(INDEX('2. GRI Pricing Inputs'!$C$15:$AI$16,MATCH($L$16,'2. GRI Pricing Inputs'!$C$15:$C$16,0),MATCH(E20,'2. GRI Pricing Inputs'!$C$15:$AI$15,0)),0) -> 1275 | M20: =IFERROR(INDEX('2. GRI Pricing Inputs'!$C$22:$AI$23,MATCH($M$16,'2. GRI Pricing Inputs'!$C$22:$C$23,0),MATCH(F20,'2. GRI Pricing Inputs'!$C$22:$AI$22,0)),0) -> 0 | N20: =IF(AND('3. GRI Pricing'!$G20>='2. GRI Pricing Inputs'!$D$33,'3. GRI Pricing'!$G20<='2. GRI Pricing Inputs'!$E$33),'2. GRI Pricing Inputs'!$D$32,IF(AND('3. GRI Pricing'!$G20>='2. GRI Pricing Inputs'!$F$33,'3. GRI Pricing'!$G20<='2. GRI Pricing Inputs'!$G$33),'2. GRI Pricing Inputs'!$F$32,IF(AND('3. GRI Pricing'!$G20>='2. GRI Pricing Inputs'!$H$33,'3. GRI Pricing'!$G20<='2. GRI Pricing Inputs'!$I$33),'2. GRI Pricing Inputs'!$H$32,IF(AND('3. GRI Pricing'!$G20>='2. GRI Pricing Inputs'!$J$33,'3. GRI Pricing'!$G20<='2. GRI Pricing Inputs'!$K$33),'2. GRI Pricing Inputs'!$J$32,IF(AND('3. GRI Pricing'!$G20>='2. GRI Pricing Inputs'!$L$33,'3. GRI Pricing'!$G20<='2. GRI Pricing Inputs'!$M$33),'2. GRI Pricing Inputs'!$L$32,IF(AND('3. GRI Pricing'!$G20>='2. GRI Pricing Inputs'!$N$33,'3. GRI Pricing'!$G20<='2. GRI Pricing Inputs'!$O$33),'2. GRI Pricing Inputs'!$N$32,IF(AND('3. GRI Pricing'!$G20>='2. GRI Pricing Inputs'!$P$33,'3. GRI Pricing'!$G20<='2. GRI Pricing Inputs'!$Q$33),'2. GRI Pricing Inputs'!$P$32,IF(AND('3. GRI Pricing'!$G20>='2. GRI Pricing Inputs'!$R$33,'3. GRI Pricing'!$G20<='2. GRI Pricing Inputs'!$S$33),'2. GRI Pricing Inputs'!$R$32,IF(AND('3. GRI Pricing'!$G20>='2. GRI Pricing Inputs'!$T$33,'3. GRI Pricing'!$G20<='2. GRI Pricing Inputs'!$U$33),'2. GRI Pricing Inputs'!$T$32,IF(AND('3. GRI Pricing'!$G20>='2. GRI Pricing Inputs'!$V$33,'3. GRI Pricing'!$G20<='2. GRI Pricing Inputs'!$W$33),'2. GRI Pricing Inputs'!$V$32,IF(AND('3. GRI Pricing'!$G20>='2. GRI Pricing Inputs'!$X$33,'3. GRI Pricing'!$G20<='2. GRI Pricing Inputs'!$Y$33),'2. GRI Pricing Inputs'!$X$32,IF(AND('3. GRI Pricing'!$G20>='2. GRI Pricing Inputs'!$Z$33,'3. GRI Pricing'!$G20<='2. GRI Pricing Inputs'!$AA$33),'2. GRI Pricing Inputs'!$Z$32,IF(AND('3. GRI Pricing'!$G20>='2. GRI Pricing Inputs'!$AB$33,'3. GRI Pricing'!$G20<='2. GRI Pricing Inputs'!$AC$33),'2. GRI Pricing Inputs'!$AB$32,IF(AND('3. GRI Pricing'!$G20>='2. GRI Pricing Inputs'!$AD$33,'3. GRI Pricing'!$G20<='2. GRI Pricing Inputs'!$AE$33),'2. GRI Pricing Inputs'!$AD$32,IF(AND('3. GRI Pricing'!$G20>='2. GRI Pricing Inputs'!$AF$33,'3. GRI Pricing'!$G20<='2. GRI Pricing Inputs'!$AG$33),'2. GRI Pricing Inputs'!$AF$32,IF(AND('3. GRI Pricing'!$G20>='2. GRI Pricing Inputs'!$AH$33,'3. GRI Pricing'!$G20<='2. GRI Pricing Inputs'!$AI$33),'2. GRI Pricing Inputs'!$AH$32,0)))))))))))))))) -> 6 | O20: {=IFERROR(INDEX('2. GRI Pricing Inputs'!$C$32:$AI$39,MATCH('3. GRI Pricing'!E20,'2. GRI Pricing Inputs'!$C$32:$C$39,0),(MATCH('3. GRI Pricing'!N20,'2. GRI Pricing Inputs'!$D$32:$AI$32,0)+1)),0)} -> 10 | P20: =IFERROR(INDEX('2. GRI Pricing Inputs'!$C$45:$AI$46,MATCH($P$16,'2. GRI Pricing Inputs'!$C$45:$C$46,0),MATCH(H20,'2. GRI Pricing Inputs'!$C$45:$AI$45,0)),0) -> 20 | Q20: =IFERROR(INDEX('2. GRI Pricing Inputs'!$C$53:$AI$54,MATCH('3. GRI Pricing'!$Q$16,'2. GRI Pricing Inputs'!$C$53:$C$54,0),MATCH('3. GRI Pricing'!I20,'2. GRI Pricing Inputs'!$C$53:$AI$53,0)),0) -> 30 | R20: =IFERROR(INDEX('2. GRI Pricing Inputs'!$C$60:$AI$61,MATCH('3. GRI Pricing'!$R$16,'2. GRI Pricing Inputs'!$C$60:$C$61,0),MATCH('1. Accomodation'!T24,'2. GRI Pricing Inputs'!$C$60:$AI$60,0)),0) -> 0 | S20: =IFERROR(INDEX('2. GRI Pricing Inputs'!$C$67:$AI$68,MATCH('3. GRI Pricing'!$S$16,'2. GRI Pricing Inputs'!$C$67:$C$68,0),MATCH('1. Accomodation'!U24,'2. GRI Pricing Inputs'!$C$67:$AI$67,0)),0) -> 30 | T20: =IF(E20=0,0,'2. GRI Pricing Inputs'!$AI$75) -> 0 | U20: =IFERROR(INDEX('2. GRI Pricing Inputs'!$C$82:$AI$83,MATCH('3. GRI Pricing'!$U$16,'2. GRI Pricing Inputs'!$C$82:$C$83,0),MATCH('1. Accomodation'!V24,'2. GRI Pricing Inputs'!$C$82:$AI$82,0)),0) -> 0 | V20: =IFERROR(INDEX('2. GRI Pricing Inputs'!$C$89:$AI$90,MATCH('3. GRI Pricing'!$V$16,'2. GRI Pricing Inputs'!$C$89:$C$90,0),MATCH('1. Accomodation'!W24,'2. GRI Pricing Inputs'!$C$89:$AI$89,0)),0) -> 0 | W20: =IFERROR(INDEX('2. GRI Pricing Inputs'!$C$97:$AI$98,MATCH('3. GRI Pricing'!$W$16,'2. GRI Pricing Inputs'!$C$97:$C$98,0),MATCH('1. Accomodation'!X24,'2. GRI Pricing Inputs'!$C$97:$AI$97,0)),0) -> 0 | X20: =IFERROR(INDEX('2. GRI Pricing Inputs'!$C$104:$AI$105,MATCH('3. GRI Pricing'!$X$16,'2. GRI Pricing Inputs'!$C$104:$C$105,0),MATCH('1. Accomodation'!Y24,'2. GRI Pricing Inputs'!$C$104:$AI$104,0)),0) -> 0 | Z20: =L20+M20+O20+P20+Q20+R20+S20+T20+U20+V20+W20+X20+Y20 -> 1365 | AD20: =Z20*(1+'2. GRI Pricing Inputs'!E$115)^(($AD$16-$AC$15)/365) -> 1371.7719 | AE20: =AD20*(1+'2. GRI Pricing Inputs'!F$115)^((AE$16-AD$16)/365) -> 1378.3574 | AF20: =AE20*(1+'2. GRI Pricing Inputs'!G$115)^((AF$16-AE$16)/365) -> 1385.1956 | AG20: =AF20*(1+'2. GRI Pricing Inputs'!H$115)^((AG$16-AF$16)/365) -> 1392.0678 | AH20: =AG20*(1+'2. GRI Pricing Inputs'!I$115)^((AH$16-AG$16)/365) -> 1398.3042 | AI20: =AH20*(1+'2. GRI Pricing Inputs'!J$115)^((AI$16-AH$16)/365) -> 1405.2413 | AJ20: =AI20*(1+'2. GRI Pricing Inputs'!K$115)^((AJ$16-AI$16)/365) -> 1411.9875 | AK20: =AJ20*(1+'2. GRI Pricing Inputs'!L$115)^((AK$16-AJ$16)/365) -> 1418.9926 | AL20: =AK20*(1+'2. GRI Pricing Inputs'!M$115)^((AL$16-AK$16)/365) -> 1425.8047 | ... AP20: =AO20*(1+'2. GRI Pricing Inputs'!Q$115)^((AP$16-AO$16)/365) -> 1454.0783 | AQ20: =IFERROR(AP20/AD20-1,0) -> 0.06
A21: =_xlfn.XLOOKUP($C21,'Data Ref'!$D:$D,'Data Ref'!$B:$B,0) -> 222708005 | C21: ='1. Accomodation'!N25 -> 105 | D21: ='1. Accomodation'!L25 -> C | E21: ='1. Accomodation'!P25 -> 1 Bed | F21: ='1. Accomodation'!Q25 -> 1 | G21: ='1. Accomodation'!O25 -> 532.49 | H21: ='1. Accomodation'!R25 -> 1 | I21: ='1. Accomodation'!S25 -> North Row below Treeline | L21: =IFERROR(INDEX('2. GRI Pricing Inputs'!$C$15:$AI$16,MATCH($L$16,'2. GRI Pricing Inputs'!$C$15:$C$16,0),MATCH(E21,'2. GRI Pricing Inputs'!$C$15:$AI$15,0)),0) -> 1275 | M21: =IFERROR(INDEX('2. GRI Pricing Inputs'!$C$22:$AI$23,MATCH($M$16,'2. GRI Pricing Inputs'!$C$22:$C$23,0),MATCH(F21,'2. GRI Pricing Inputs'!$C$22:$AI$22,0)),0) -> 0 | N21: =IF(AND('3. GRI Pricing'!$G21>='2. GRI Pricing Inputs'!$D$33,'3. GRI Pricing'!$G21<='2. GRI Pricing Inputs'!$E$33),'2. GRI Pricing Inputs'!$D$32,IF(AND('3. GRI Pricing'!$G21>='2. GRI Pricing Inputs'!$F$33,'3. GRI Pricing'!$G21<='2. GRI Pricing Inputs'!$G$33),'2. GRI Pricing Inputs'!$F$32,IF(AND('3. GRI Pricing'!$G21>='2. GRI Pricing Inputs'!$H$33,'3. GRI Pricing'!$G21<='2. GRI Pricing Inputs'!$I$33),'2. GRI Pricing Inputs'!$H$32,IF(AND('3. GRI Pricing'!$G21>='2. GRI Pricing Inputs'!$J$33,'3. GRI Pricing'!$G21<='2. GRI Pricing Inputs'!$K$33),'2. GRI Pricing Inputs'!$J$32,IF(AND('3. GRI Pricing'!$G21>='2. GRI Pricing Inputs'!$L$33,'3. GRI Pricing'!$G21<='2. GRI Pricing Inputs'!$M$33),'2. GRI Pricing Inputs'!$L$32,IF(AND('3. GRI Pricing'!$G21>='2. GRI Pricing Inputs'!$N$33,'3. GRI Pricing'!$G21<='2. GRI Pricing Inputs'!$O$33),'2. GRI Pricing Inputs'!$N$32,IF(AND('3. GRI Pricing'!$G21>='2. GRI Pricing Inputs'!$P$33,'3. GRI Pricing'!$G21<='2. GRI Pricing Inputs'!$Q$33),'2. GRI Pricing Inputs'!$P$32,IF(AND('3. GRI Pricing'!$G21>='2. GRI Pricing Inputs'!$R$33,'3. GRI Pricing'!$G21<='2. GRI Pricing Inputs'!$S$33),'2. GRI Pricing Inputs'!$R$32,IF(AND('3. GRI Pricing'!$G21>='2. GRI Pricing Inputs'!$T$33,'3. GRI Pricing'!$G21<='2. GRI Pricing Inputs'!$U$33),'2. GRI Pricing Inputs'!$T$32,IF(AND('3. GRI Pricing'!$G21>='2. GRI Pricing Inputs'!$V$33,'3. GRI Pricing'!$G21<='2. GRI Pricing Inputs'!$W$33),'2. GRI Pricing Inputs'!$V$32,IF(AND('3. GRI Pricing'!$G21>='2. GRI Pricing Inputs'!$X$33,'3. GRI Pricing'!$G21<='2. GRI Pricing Inputs'!$Y$33),'2. GRI Pricing Inputs'!$X$32,IF(AND('3. GRI Pricing'!$G21>='2. GRI Pricing Inputs'!$Z$33,'3. GRI Pricing'!$G21<='2. GRI Pricing Inputs'!$AA$33),'2. GRI Pricing Inputs'!$Z$32,IF(AND('3. GRI Pricing'!$G21>='2. GRI Pricing Inputs'!$AB$33,'3. GRI Pricing'!$G21<='2. GRI Pricing Inputs'!$AC$33),'2. GRI Pricing Inputs'!$AB$32,IF(AND('3. GRI Pricing'!$G21>='2. GRI Pricing Inputs'!$AD$33,'3. GRI Pricing'!$G21<='2. GRI Pricing Inputs'!$AE$33),'2. GRI Pricing Inputs'!$AD$32,IF(AND('3. GRI Pricing'!$G21>='2. GRI Pricing Inputs'!$AF$33,'3. GRI Pricing'!$G21<='2. GRI Pricing Inputs'!$AG$33),'2. GRI Pricing Inputs'!$AF$32,IF(AND('3. GRI Pricing'!$G21>='2. GRI Pricing Inputs'!$AH$33,'3. GRI Pricing'!$G21<='2. GRI Pricing Inputs'!$AI$33),'2. GRI Pricing Inputs'!$AH$32,0)))))))))))))))) -> 0 | O21: {=IFERROR(INDEX('2. GRI Pricing Inputs'!$C$32:$AI$39,MATCH('3. GRI Pricing'!E21,'2. GRI Pricing Inputs'!$C$32:$C$39,0),(MATCH('3. GRI Pricing'!N21,'2. GRI Pricing Inputs'!$D$32:$AI$32,0)+1)),0)} -> 0 | P21: =IFERROR(INDEX('2. GRI Pricing Inputs'!$C$45:$AI$46,MATCH($P$16,'2. GRI Pricing Inputs'!$C$45:$C$46,0),MATCH(H21,'2. GRI Pricing Inputs'!$C$45:$AI$45,0)),0) -> 20 | Q21: =IFERROR(INDEX('2. GRI Pricing Inputs'!$C$53:$AI$54,MATCH('3. GRI Pricing'!$Q$16,'2. GRI Pricing Inputs'!$C$53:$C$54,0),MATCH('3. GRI Pricing'!I21,'2. GRI Pricing Inputs'!$C$53:$AI$53,0)),0) -> 30 | R21: =IFERROR(INDEX('2. GRI Pricing Inputs'!$C$60:$AI$61,MATCH('3. GRI Pricing'!$R$16,'2. GRI Pricing Inputs'!$C$60:$C$61,0),MATCH('1. Accomodation'!T25,'2. GRI Pricing Inputs'!$C$60:$AI$60,0)),0) -> 0 | S21: =IFERROR(INDEX('2. GRI Pricing Inputs'!$C$67:$AI$68,MATCH('3. GRI Pricing'!$S$16,'2. GRI Pricing Inputs'!$C$67:$C$68,0),MATCH('1. Accomodation'!U25,'2. GRI Pricing Inputs'!$C$67:$AI$67,0)),0) -> 30 | T21: =IF(E21=0,0,'2. GRI Pricing Inputs'!$AI$75) -> 0 | U21: =IFERROR(INDEX('2. GRI Pricing Inputs'!$C$82:$AI$83,MATCH('3. GRI Pricing'!$U$16,'2. GRI Pricing Inputs'!$C$82:$C$83,0),MATCH('1. Accomodation'!V25,'2. GRI Pricing Inputs'!$C$82:$AI$82,0)),0) -> 0 | V21: =IFERROR(INDEX('2. GRI Pricing Inputs'!$C$89:$AI$90,MATCH('3. GRI Pricing'!$V$16,'2. GRI Pricing Inputs'!$C$89:$C$90,0),MATCH('1. Accomodation'!W25,'2. GRI Pricing Inputs'!$C$89:$AI$89,0)),0) -> 0 | W21: =IFERROR(INDEX('2. GRI Pricing Inputs'!$C$97:$AI$98,MATCH('3. GRI Pricing'!$W$16,'2. GRI Pricing Inputs'!$C$97:$C$98,0),MATCH('1. Accomodation'!X25,'2. GRI Pricing Inputs'!$C$97:$AI$97,0)),0) -> 0 | X21: =IFERROR(INDEX('2. GRI Pricing Inputs'!$C$104:$AI$105,MATCH('3. GRI Pricing'!$X$16,'2. GRI Pricing Inputs'!$C$104:$C$105,0),MATCH('1. Accomodation'!Y25,'2. GRI Pricing Inputs'!$C$104:$AI$104,0)),0) -> 0 | Z21: =L21+M21+O21+P21+Q21+R21+S21+T21+U21+V21+W21+X21+Y21 -> 1355 | AD21: =Z21*(1+'2. GRI Pricing Inputs'!E$115)^(($AD$16-$AC$15)/365) -> 1361.7223 | AE21: =AD21*(1+'2. GRI Pricing Inputs'!F$115)^((AE$16-AD$16)/365) -> 1368.2596 | AF21: =AE21*(1+'2. GRI Pricing Inputs'!G$115)^((AF$16-AE$16)/365) -> 1375.0477 | AG21: =AF21*(1+'2. GRI Pricing Inputs'!H$115)^((AG$16-AF$16)/365) -> 1381.8695 | AH21: =AG21*(1+'2. GRI Pricing Inputs'!I$115)^((AH$16-AG$16)/365) -> 1388.0602 | AI21: =AH21*(1+'2. GRI Pricing Inputs'!J$115)^((AI$16-AH$16)/365) -> 1394.9465 | AJ21: =AI21*(1+'2. GRI Pricing Inputs'!K$115)^((AJ$16-AI$16)/365) -> 1401.6433 | AK21: =AJ21*(1+'2. GRI Pricing Inputs'!L$115)^((AK$16-AJ$16)/365) -> 1408.597 | AL21: =AK21*(1+'2. GRI Pricing Inputs'!M$115)^((AL$16-AK$16)/365) -> 1415.3593 | ... AP21: =AO21*(1+'2. GRI Pricing Inputs'!Q$115)^((AP$16-AO$16)/365) -> 1443.4257 | AQ21: =IFERROR(AP21/AD21-1,0) -> 0.06
A22: =_xlfn.XLOOKUP($C22,'Data Ref'!$D:$D,'Data Ref'!$B:$B,0) -> 222708006 | C22: ='1. Accomodation'!N26 -> 106 | D22: ='1. Accomodation'!L26 -> C | E22: ='1. Accomodation'!P26 -> 2 Bed | F22: ='1. Accomodation'!Q26 -> 2 | G22: ='1. Accomodation'!O26 -> 728.18 | H22: ='1. Accomodation'!R26 -> 1 | I22: ='1. Accomodation'!S26 -> Carpark and other block | L22: =IFERROR(INDEX('2. GRI Pricing Inputs'!$C$15:$AI$16,MATCH($L$16,'2. GRI Pricing Inputs'!$C$15:$C$16,0),MATCH(E22,'2. GRI Pricing Inputs'!$C$15:$AI$15,0)),0) -> 1665 | M22: =IFERROR(INDEX('2. GRI Pricing Inputs'!$C$22:$AI$23,MATCH($M$16,'2. GRI Pricing Inputs'!$C$22:$C$23,0),MATCH(F22,'2. GRI Pricing Inputs'!$C$22:$AI$22,0)),0) -> 0 | N22: =IF(AND('3. GRI Pricing'!$G22>='2. GRI Pricing Inputs'!$D$33,'3. GRI Pricing'!$G22<='2. GRI Pricing Inputs'!$E$33),'2. GRI Pricing Inputs'!$D$32,IF(AND('3. GRI Pricing'!$G22>='2. GRI Pricing Inputs'!$F$33,'3. GRI Pricing'!$G22<='2. GRI Pricing Inputs'!$G$33),'2. GRI Pricing Inputs'!$F$32,IF(AND('3. GRI Pricing'!$G22>='2. GRI Pricing Inputs'!$H$33,'3. GRI Pricing'!$G22<='2. GRI Pricing Inputs'!$I$33),'2. GRI Pricing Inputs'!$H$32,IF(AND('3. GRI Pricing'!$G22>='2. GRI Pricing Inputs'!$J$33,'3. GRI Pricing'!$G22<='2. GRI Pricing Inputs'!$K$33),'2. GRI Pricing Inputs'!$J$32,IF(AND('3. GRI Pricing'!$G22>='2. GRI Pricing Inputs'!$L$33,'3. GRI Pricing'!$G22<='2. GRI Pricing Inputs'!$M$33),'2. GRI Pricing Inputs'!$L$32,IF(AND('3. GRI Pricing'!$G22>='2. GRI Pricing Inputs'!$N$33,'3. GRI Pricing'!$G22<='2. GRI Pricing Inputs'!$O$33),'2. GRI Pricing Inputs'!$N$32,IF(AND('3. GRI Pricing'!$G22>='2. GRI Pricing Inputs'!$P$33,'3. GRI Pricing'!$G22<='2. GRI Pricing Inputs'!$Q$33),'2. GRI Pricing Inputs'!$P$32,IF(AND('3. GRI Pricing'!$G22>='2. GRI Pricing Inputs'!$R$33,'3. GRI Pricing'!$G22<='2. GRI Pricing Inputs'!$S$33),'2. GRI Pricing Inputs'!$R$32,IF(AND('3. GRI Pricing'!$G22>='2. GRI Pricing Inputs'!$T$33,'3. GRI Pricing'!$G22<='2. GRI Pricing Inputs'!$U$33),'2. GRI Pricing Inputs'!$T$32,IF(AND('3. GRI Pricing'!$G22>='2. GRI Pricing Inputs'!$V$33,'3. GRI Pricing'!$G22<='2. GRI Pricing Inputs'!$W$33),'2. GRI Pricing Inputs'!$V$32,IF(AND('3. GRI Pricing'!$G22>='2. GRI Pricing Inputs'!$X$33,'3. GRI Pricing'!$G22<='2. GRI Pricing Inputs'!$Y$33),'2. GRI Pricing Inputs'!$X$32,IF(AND('3. GRI Pricing'!$G22>='2. GRI Pricing Inputs'!$Z$33,'3. GRI Pricing'!$G22<='2. GRI Pricing Inputs'!$AA$33),'2. GRI Pricing Inputs'!$Z$32,IF(AND('3. GRI Pricing'!$G22>='2. GRI Pricing Inputs'!$AB$33,'3. GRI Pricing'!$G22<='2. GRI Pricing Inputs'!$AC$33),'2. GRI Pricing Inputs'!$AB$32,IF(AND('3. GRI Pricing'!$G22>='2. GRI Pricing Inputs'!$AD$33,'3. GRI Pricing'!$G22<='2. GRI Pricing Inputs'!$AE$33),'2. GRI Pricing Inputs'!$AD$32,IF(AND('3. GRI Pricing'!$G22>='2. GRI Pricing Inputs'!$AF$33,'3. GRI Pricing'!$G22<='2. GRI Pricing Inputs'!$AG$33),'2. GRI Pricing Inputs'!$AF$32,IF(AND('3. GRI Pricing'!$G22>='2. GRI Pricing Inputs'!$AH$33,'3. GRI Pricing'!$G22<='2. GRI Pricing Inputs'!$AI$33),'2. GRI Pricing Inputs'!$AH$32,0)))))))))))))))) -> 0 | O22: {=IFERROR(INDEX('2. GRI Pricing Inputs'!$C$32:$AI$39,MATCH('3. GRI Pricing'!E22,'2. GRI Pricing Inputs'!$C$32:$C$39,0),(MATCH('3. GRI Pricing'!N22,'2. GRI Pricing Inputs'!$D$32:$AI$32,0)+1)),0)} -> 0 | P22: =IFERROR(INDEX('2. GRI Pricing Inputs'!$C$45:$AI$46,MATCH($P$16,'2. GRI Pricing Inputs'!$C$45:$C$46,0),MATCH(H22,'2. GRI Pricing Inputs'!$C$45:$AI$45,0)),0) -> 20 | Q22: =IFERROR(INDEX('2. GRI Pricing Inputs'!$C$53:$AI$54,MATCH('3. GRI Pricing'!$Q$16,'2. GRI Pricing Inputs'!$C$53:$C$54,0),MATCH('3. GRI Pricing'!I22,'2. GRI Pricing Inputs'!$C$53:$AI$53,0)),0) -> 5 | R22: =IFERROR(INDEX('2. GRI Pricing Inputs'!$C$60:$AI$61,MATCH('3. GRI Pricing'!$R$16,'2. GRI Pricing Inputs'!$C$60:$C$61,0),MATCH('1. Accomodation'!T26,'2. GRI Pricing Inputs'!$C$60:$AI$60,0)),0) -> 0 | S22: =IFERROR(INDEX('2. GRI Pricing Inputs'!$C$67:$AI$68,MATCH('3. GRI Pricing'!$S$16,'2. GRI Pricing Inputs'!$C$67:$C$68,0),MATCH('1. Accomodation'!U26,'2. GRI Pricing Inputs'!$C$67:$AI$67,0)),0) -> 55 | T22: =IF(E22=0,0,'2. GRI Pricing Inputs'!$AI$75) -> 0 | U22: =IFERROR(INDEX('2. GRI Pricing Inputs'!$C$82:$AI$83,MATCH('3. GRI Pricing'!$U$16,'2. GRI Pricing Inputs'!$C$82:$C$83,0),MATCH('1. Accomodation'!V26,'2. GRI Pricing Inputs'!$C$82:$AI$82,0)),0) -> 0 | V22: =IFERROR(INDEX('2. GRI Pricing Inputs'!$C$89:$AI$90,MATCH('3. GRI Pricing'!$V$16,'2. GRI Pricing Inputs'!$C$89:$C$90,0),MATCH('1. Accomodation'!W26,'2. GRI Pricing Inputs'!$C$89:$AI$89,0)),0) -> 0 | W22: =IFERROR(INDEX('2. GRI Pricing Inputs'!$C$97:$AI$98,MATCH('3. GRI Pricing'!$W$16,'2. GRI Pricing Inputs'!$C$97:$C$98,0),MATCH('1. Accomodation'!X26,'2. GRI Pricing Inputs'!$C$97:$AI$97,0)),0) -> 0 | X22: =IFERROR(INDEX('2. GRI Pricing Inputs'!$C$104:$AI$105,MATCH('3. GRI Pricing'!$X$16,'2. GRI Pricing Inputs'!$C$104:$C$105,0),MATCH('1. Accomodation'!Y26,'2. GRI Pricing Inputs'!$C$104:$AI$104,0)),0) -> 0 | Z22: =L22+M22+O22+P22+Q22+R22+S22+T22+U22+V22+W22+X22+Y22 -> 1745 | AD22: =Z22*(1+'2. GRI Pricing Inputs'!E$115)^(($AD$16-$AC$15)/365) -> 1753.6572 | AE22: =AD22*(1+'2. GRI Pricing Inputs'!F$115)^((AE$16-AD$16)/365) -> 1762.076 | AF22: =AE22*(1+'2. GRI Pricing Inputs'!G$115)^((AF$16-AE$16)/365) -> 1770.8179 | AG22: =AF22*(1+'2. GRI Pricing Inputs'!H$115)^((AG$16-AF$16)/365) -> 1779.6031 | AH22: =AG22*(1+'2. GRI Pricing Inputs'!I$115)^((AH$16-AG$16)/365) -> 1787.5757 | AI22: =AH22*(1+'2. GRI Pricing Inputs'!J$115)^((AI$16-AH$16)/365) -> 1796.4441 | AJ22: =AI22*(1+'2. GRI Pricing Inputs'!K$115)^((AJ$16-AI$16)/365) -> 1805.0683 | AK22: =AJ22*(1+'2. GRI Pricing Inputs'!L$115)^((AK$16-AJ$16)/365) -> 1814.0235 | AL22: =AK22*(1+'2. GRI Pricing Inputs'!M$115)^((AL$16-AK$16)/365) -> 1822.7321 | ... AP22: =AO22*(1+'2. GRI Pricing Inputs'!Q$115)^((AP$16-AO$16)/365) -> 1858.8766 | AQ22: =IFERROR(AP22/AD22-1,0) -> 0.06
A23: =_xlfn.XLOOKUP($C23,'Data Ref'!$D:$D,'Data Ref'!$B:$B,0) -> 222708007 | C23: ='1. Accomodation'!N27 -> 107 | D23: ='1. Accomodation'!L27 -> C | E23: ='1. Accomodation'!P27 -> 1 Bed | F23: ='1. Accomodation'!Q27 -> 1 | G23: ='1. Accomodation'!O27 -> 489.44 | H23: ='1. Accomodation'!R27 -> 1 | I23: ='1. Accomodation'!S27 -> Nursery and mixed other buildings | L23: =IFERROR(INDEX('2. GRI Pricing Inputs'!$C$15:$AI$16,MATCH($L$16,'2. GRI Pricing Inputs'!$C$15:$C$16,0),MATCH(E23,'2. GRI Pricing Inputs'!$C$15:$AI$15,0)),0) -> 1275 | M23: =IFERROR(INDEX('2. GRI Pricing Inputs'!$C$22:$AI$23,MATCH($M$16,'2. GRI Pricing Inputs'!$C$22:$C$23,0),MATCH(F23,'2. GRI Pricing Inputs'!$C$22:$AI$22,0)),0) -> 0 | N23: =IF(AND('3. GRI Pricing'!$G23>='2. GRI Pricing Inputs'!$D$33,'3. GRI Pricing'!$G23<='2. GRI Pricing Inputs'!$E$33),'2. GRI Pricing Inputs'!$D$32,IF(AND('3. GRI Pricing'!$G23>='2. GRI Pricing Inputs'!$F$33,'3. GRI Pricing'!$G23<='2. GRI Pricing Inputs'!$G$33),'2. GRI Pricing Inputs'!$F$32,IF(AND('3. GRI Pricing'!$G23>='2. GRI Pricing Inputs'!$H$33,'3. GRI Pricing'!$G23<='2. GRI Pricing Inputs'!$I$33),'2. GRI Pricing Inputs'!$H$32,IF(AND('3. GRI Pricing'!$G23>='2. GRI Pricing Inputs'!$J$33,'3. GRI Pricing'!$G23<='2. GRI Pricing Inputs'!$K$33),'2. GRI Pricing Inputs'!$J$32,IF(AND('3. GRI Pricing'!$G23>='2. GRI Pricing Inputs'!$L$33,'3. GRI Pricing'!$G23<='2. GRI Pricing Inputs'!$M$33),'2. GRI Pricing Inputs'!$L$32,IF(AND('3. GRI Pricing'!$G23>='2. GRI Pricing Inputs'!$N$33,'3. GRI Pricing'!$G23<='2. GRI Pricing Inputs'!$O$33),'2. GRI Pricing Inputs'!$N$32,IF(AND('3. GRI Pricing'!$G23>='2. GRI Pricing Inputs'!$P$33,'3. GRI Pricing'!$G23<='2. GRI Pricing Inputs'!$Q$33),'2. GRI Pricing Inputs'!$P$32,IF(AND('3. GRI Pricing'!$G23>='2. GRI Pricing Inputs'!$R$33,'3. GRI Pricing'!$G23<='2. GRI Pricing Inputs'!$S$33),'2. GRI Pricing Inputs'!$R$32,IF(AND('3. GRI Pricing'!$G23>='2. GRI Pricing Inputs'!$T$33,'3. GRI Pricing'!$G23<='2. GRI Pricing Inputs'!$U$33),'2. GRI Pricing Inputs'!$T$32,IF(AND('3. GRI Pricing'!$G23>='2. GRI Pricing Inputs'!$V$33,'3. GRI Pricing'!$G23<='2. GRI Pricing Inputs'!$W$33),'2. GRI Pricing Inputs'!$V$32,IF(AND('3. GRI Pricing'!$G23>='2. GRI Pricing Inputs'!$X$33,'3. GRI Pricing'!$G23<='2. GRI Pricing Inputs'!$Y$33),'2. GRI Pricing Inputs'!$X$32,IF(AND('3. GRI Pricing'!$G23>='2. GRI Pricing Inputs'!$Z$33,'3. GRI Pricing'!$G23<='2. GRI Pricing Inputs'!$AA$33),'2. GRI Pricing Inputs'!$Z$32,IF(AND('3. GRI Pricing'!$G23>='2. GRI Pricing Inputs'!$AB$33,'3. GRI Pricing'!$G23<='2. GRI Pricing Inputs'!$AC$33),'2. GRI Pricing Inputs'!$AB$32,IF(AND('3. GRI Pricing'!$G23>='2. GRI Pricing Inputs'!$AD$33,'3. GRI Pricing'!$G23<='2. GRI Pricing Inputs'!$AE$33),'2. GRI Pricing Inputs'!$AD$32,IF(AND('3. GRI Pricing'!$G23>='2. GRI Pricing Inputs'!$AF$33,'3. GRI Pricing'!$G23<='2. GRI Pricing Inputs'!$AG$33),'2. GRI Pricing Inputs'!$AF$32,IF(AND('3. GRI Pricing'!$G23>='2. GRI Pricing Inputs'!$AH$33,'3. GRI Pricing'!$G23<='2. GRI Pricing Inputs'!$AI$33),'2. GRI Pricing Inputs'!$AH$32,0)))))))))))))))) -> 0 | O23: {=IFERROR(INDEX('2. GRI Pricing Inputs'!$C$32:$AI$39,MATCH('3. GRI Pricing'!E23,'2. GRI Pricing Inputs'!$C$32:$C$39,0),(MATCH('3. GRI Pricing'!N23,'2. GRI Pricing Inputs'!$D$32:$AI$32,0)+1)),0)} -> 0 | P23: =IFERROR(INDEX('2. GRI Pricing Inputs'!$C$45:$AI$46,MATCH($P$16,'2. GRI Pricing Inputs'!$C$45:$C$46,0),MATCH(H23,'2. GRI Pricing Inputs'!$C$45:$AI$45,0)),0) -> 20 | Q23: =IFERROR(INDEX('2. GRI Pricing Inputs'!$C$53:$AI$54,MATCH('3. GRI Pricing'!$Q$16,'2. GRI Pricing Inputs'!$C$53:$C$54,0),MATCH('3. GRI Pricing'!I23,'2. GRI Pricing Inputs'!$C$53:$AI$53,0)),0) -> 0 | R23: =IFERROR(INDEX('2. GRI Pricing Inputs'!$C$60:$AI$61,MATCH('3. GRI Pricing'!$R$16,'2. GRI Pricing Inputs'!$C$60:$C$61,0),MATCH('1. Accomodation'!T27,'2. GRI Pricing Inputs'!$C$60:$AI$60,0)),0) -> 0 | S23: =IFERROR(INDEX('2. GRI Pricing Inputs'!$C$67:$AI$68,MATCH('3. GRI Pricing'!$S$16,'2. GRI Pricing Inputs'!$C$67:$C$68,0),MATCH('1. Accomodation'!U27,'2. GRI Pricing Inputs'!$C$67:$AI$67,0)),0) -> 0 | T23: =IF(E23=0,0,'2. GRI Pricing Inputs'!$AI$75) -> 0 | U23: =IFERROR(INDEX('2. GRI Pricing Inputs'!$C$82:$AI$83,MATCH('3. GRI Pricing'!$U$16,'2. GRI Pricing Inputs'!$C$82:$C$83,0),MATCH('1. Accomodation'!V27,'2. GRI Pricing Inputs'!$C$82:$AI$82,0)),0) -> 0 | V23: =IFERROR(INDEX('2. GRI Pricing Inputs'!$C$89:$AI$90,MATCH('3. GRI Pricing'!$V$16,'2. GRI Pricing Inputs'!$C$89:$C$90,0),MATCH('1. Accomodation'!W27,'2. GRI Pricing Inputs'!$C$89:$AI$89,0)),0) -> 0 | W23: =IFERROR(INDEX('2. GRI Pricing Inputs'!$C$97:$AI$98,MATCH('3. GRI Pricing'!$W$16,'2. GRI Pricing Inputs'!$C$97:$C$98,0),MATCH('1. Accomodation'!X27,'2. GRI Pricing Inputs'!$C$97:$AI$97,0)),0) -> 0 | X23: =IFERROR(INDEX('2. GRI Pricing Inputs'!$C$104:$AI$105,MATCH('3. GRI Pricing'!$X$16,'2. GRI Pricing Inputs'!$C$104:$C$105,0),MATCH('1. Accomodation'!Y27,'2. GRI Pricing Inputs'!$C$104:$AI$104,0)),0) -> 0 | Z23: =L23+M23+O23+P23+Q23+R23+S23+T23+U23+V23+W23+X23+Y23 -> 1295 | AD23: =Z23*(1+'2. GRI Pricing Inputs'!E$115)^(($AD$16-$AC$15)/365) -> 1301.4247 | AE23: =AD23*(1+'2. GRI Pricing Inputs'!F$115)^((AE$16-AD$16)/365) -> 1307.6724 | AF23: =AE23*(1+'2. GRI Pricing Inputs'!G$115)^((AF$16-AE$16)/365) -> 1314.16 | AG23: =AF23*(1+'2. GRI Pricing Inputs'!H$115)^((AG$16-AF$16)/365) -> 1320.6797 | AH23: =AG23*(1+'2. GRI Pricing Inputs'!I$115)^((AH$16-AG$16)/365) -> 1326.5963 | AI23: =AH23*(1+'2. GRI Pricing Inputs'!J$115)^((AI$16-AH$16)/365) -> 1333.1777 | AJ23: =AI23*(1+'2. GRI Pricing Inputs'!K$115)^((AJ$16-AI$16)/365) -> 1339.5779 | AK23: =AJ23*(1+'2. GRI Pricing Inputs'!L$115)^((AK$16-AJ$16)/365) -> 1346.2237 | AL23: =AK23*(1+'2. GRI Pricing Inputs'!M$115)^((AL$16-AK$16)/365) -> 1352.6865 | ... AP23: =AO23*(1+'2. GRI Pricing Inputs'!Q$115)^((AP$16-AO$16)/365) -> 1379.5101 | AQ23: =IFERROR(AP23/AD23-1,0) -> 0.06
A24: =_xlfn.XLOOKUP($C24,'Data Ref'!$D:$D,'Data Ref'!$B:$B,0) -> 222708008 | C24: ='1. Accomodation'!N28 -> 108 | D24: ='1. Accomodation'!L28 -> C | E24: ='1. Accomodation'!P28 -> 1 Bed | F24: ='1. Accomodation'!Q28 -> 1 | G24: ='1. Accomodation'!O28 -> 509.56 | H24: ='1. Accomodation'!R28 -> 1 | I24: ='1. Accomodation'!S28 -> Carpark and other block | L24: =IFERROR(INDEX('2. GRI Pricing Inputs'!$C$15:$AI$16,MATCH($L$16,'2. GRI Pricing Inputs'!$C$15:$C$16,0),MATCH(E24,'2. GRI Pricing Inputs'!$C$15:$AI$15,0)),0) -> 1275 | M24: =IFERROR(INDEX('2. GRI Pricing Inputs'!$C$22:$AI$23,MATCH($M$16,'2. GRI Pricing Inputs'!$C$22:$C$23,0),MATCH(F24,'2. GRI Pricing Inputs'!$C$22:$AI$22,0)),0) -> 0 | N24: =IF(AND('3. GRI Pricing'!$G24>='2. GRI Pricing Inputs'!$D$33,'3. GRI Pricing'!$G24<='2. GRI Pricing Inputs'!$E$33),'2. GRI Pricing Inputs'!$D$32,IF(AND('3. GRI Pricing'!$G24>='2. GRI Pricing Inputs'!$F$33,'3. GRI Pricing'!$G24<='2. GRI Pricing Inputs'!$G$33),'2. GRI Pricing Inputs'!$F$32,IF(AND('3. GRI Pricing'!$G24>='2. GRI Pricing Inputs'!$H$33,'3. GRI Pricing'!$G24<='2. GRI Pricing Inputs'!$I$33),'2. GRI Pricing Inputs'!$H$32,IF(AND('3. GRI Pricing'!$G24>='2. GRI Pricing Inputs'!$J$33,'3. GRI Pricing'!$G24<='2. GRI Pricing Inputs'!$K$33),'2. GRI Pricing Inputs'!$J$32,IF(AND('3. GRI Pricing'!$G24>='2. GRI Pricing Inputs'!$L$33,'3. GRI Pricing'!$G24<='2. GRI Pricing Inputs'!$M$33),'2. GRI Pricing Inputs'!$L$32,IF(AND('3. GRI Pricing'!$G24>='2. GRI Pricing Inputs'!$N$33,'3. GRI Pricing'!$G24<='2. GRI Pricing Inputs'!$O$33),'2. GRI Pricing Inputs'!$N$32,IF(AND('3. GRI Pricing'!$G24>='2. GRI Pricing Inputs'!$P$33,'3. GRI Pricing'!$G24<='2. GRI Pricing Inputs'!$Q$33),'2. GRI Pricing Inputs'!$P$32,IF(AND('3. GRI Pricing'!$G24>='2. GRI Pricing Inputs'!$R$33,'3. GRI Pricing'!$G24<='2. GRI Pricing Inputs'!$S$33),'2. GRI Pricing Inputs'!$R$32,IF(AND('3. GRI Pricing'!$G24>='2. GRI Pricing Inputs'!$T$33,'3. GRI Pricing'!$G24<='2. GRI Pricing Inputs'!$U$33),'2. GRI Pricing Inputs'!$T$32,IF(AND('3. GRI Pricing'!$G24>='2. GRI Pricing Inputs'!$V$33,'3. GRI Pricing'!$G24<='2. GRI Pricing Inputs'!$W$33),'2. GRI Pricing Inputs'!$V$32,IF(AND('3. GRI Pricing'!$G24>='2. GRI Pricing Inputs'!$X$33,'3. GRI Pricing'!$G24<='2. GRI Pricing Inputs'!$Y$33),'2. GRI Pricing Inputs'!$X$32,IF(AND('3. GRI Pricing'!$G24>='2. GRI Pricing Inputs'!$Z$33,'3. GRI Pricing'!$G24<='2. GRI Pricing Inputs'!$AA$33),'2. GRI Pricing Inputs'!$Z$32,IF(AND('3. GRI Pricing'!$G24>='2. GRI Pricing Inputs'!$AB$33,'3. GRI Pricing'!$G24<='2. GRI Pricing Inputs'!$AC$33),'2. GRI Pricing Inputs'!$AB$32,IF(AND('3. GRI Pricing'!$G24>='2. GRI Pricing Inputs'!$AD$33,'3. GRI Pricing'!$G24<='2. GRI Pricing Inputs'!$AE$33),'2. GRI Pricing Inputs'!$AD$32,IF(AND('3. GRI Pricing'!$G24>='2. GRI Pricing Inputs'!$AF$33,'3. GRI Pricing'!$G24<='2. GRI Pricing Inputs'!$AG$33),'2. GRI Pricing Inputs'!$AF$32,IF(AND('3. GRI Pricing'!$G24>='2. GRI Pricing Inputs'!$AH$33,'3. GRI Pricing'!$G24<='2. GRI Pricing Inputs'!$AI$33),'2. GRI Pricing Inputs'!$AH$32,0)))))))))))))))) -> 5 | O24: {=IFERROR(INDEX('2. GRI Pricing Inputs'!$C$32:$AI$39,MATCH('3. GRI Pricing'!E24,'2. GRI Pricing Inputs'!$C$32:$C$39,0),(MATCH('3. GRI Pricing'!N24,'2. GRI Pricing Inputs'!$D$32:$AI$32,0)+1)),0)} -> 5 | P24: =IFERROR(INDEX('2. GRI Pricing Inputs'!$C$45:$AI$46,MATCH($P$16,'2. GRI Pricing Inputs'!$C$45:$C$46,0),MATCH(H24,'2. GRI Pricing Inputs'!$C$45:$AI$45,0)),0) -> 20 | Q24: =IFERROR(INDEX('2. GRI Pricing Inputs'!$C$53:$AI$54,MATCH('3. GRI Pricing'!$Q$16,'2. GRI Pricing Inputs'!$C$53:$C$54,0),MATCH('3. GRI Pricing'!I24,'2. GRI Pricing Inputs'!$C$53:$AI$53,0)),0) -> 5 | R24: =IFERROR(INDEX('2. GRI Pricing Inputs'!$C$60:$AI$61,MATCH('3. GRI Pricing'!$R$16,'2. GRI Pricing Inputs'!$C$60:$C$61,0),MATCH('1. Accomodation'!T28,'2. GRI Pricing Inputs'!$C$60:$AI$60,0)),0) -> 0 | S24: =IFERROR(INDEX('2. GRI Pricing Inputs'!$C$67:$AI$68,MATCH('3. GRI Pricing'!$S$16,'2. GRI Pricing Inputs'!$C$67:$C$68,0),MATCH('1. Accomodation'!U28,'2. GRI Pricing Inputs'!$C$67:$AI$67,0)),0) -> 30 | T24: =IF(E24=0,0,'2. GRI Pricing Inputs'!$AI$75) -> 0 | U24: =IFERROR(INDEX('2. GRI Pricing Inputs'!$C$82:$AI$83,MATCH('3. GRI Pricing'!$U$16,'2. GRI Pricing Inputs'!$C$82:$C$83,0),MATCH('1. Accomodation'!V28,'2. GRI Pricing Inputs'!$C$82:$AI$82,0)),0) -> 0 | V24: =IFERROR(INDEX('2. GRI Pricing Inputs'!$C$89:$AI$90,MATCH('3. GRI Pricing'!$V$16,'2. GRI Pricing Inputs'!$C$89:$C$90,0),MATCH('1. Accomodation'!W28,'2. GRI Pricing Inputs'!$C$89:$AI$89,0)),0) -> 0 | W24: =IFERROR(INDEX('2. GRI Pricing Inputs'!$C$97:$AI$98,MATCH('3. GRI Pricing'!$W$16,'2. GRI Pricing Inputs'!$C$97:$C$98,0),MATCH('1. Accomodation'!X28,'2. GRI Pricing Inputs'!$C$97:$AI$97,0)),0) -> 0 | X24: =IFERROR(INDEX('2. GRI Pricing Inputs'!$C$104:$AI$105,MATCH('3. GRI Pricing'!$X$16,'2. GRI Pricing Inputs'!$C$104:$C$105,0),MATCH('1. Accomodation'!Y28,'2. GRI Pricing Inputs'!$C$104:$AI$104,0)),0) -> 0 | Z24: =L24+M24+O24+P24+Q24+R24+S24+T24+U24+V24+W24+X24+Y24 -> 1335 | AD24: =Z24*(1+'2. GRI Pricing Inputs'!E$115)^(($AD$16-$AC$15)/365) -> 1341.6231 | AE24: =AD24*(1+'2. GRI Pricing Inputs'!F$115)^((AE$16-AD$16)/365) -> 1348.0639 | AF24: =AE24*(1+'2. GRI Pricing Inputs'!G$115)^((AF$16-AE$16)/365) -> 1354.7518 | AG24: =AF24*(1+'2. GRI Pricing Inputs'!H$115)^((AG$16-AF$16)/365) -> 1361.4729 | AH24: =AG24*(1+'2. GRI Pricing Inputs'!I$115)^((AH$16-AG$16)/365) -> 1367.5722 | AI24: =AH24*(1+'2. GRI Pricing Inputs'!J$115)^((AI$16-AH$16)/365) -> 1374.3569 | AJ24: =AI24*(1+'2. GRI Pricing Inputs'!K$115)^((AJ$16-AI$16)/365) -> 1380.9548 | AK24: =AJ24*(1+'2. GRI Pricing Inputs'!L$115)^((AK$16-AJ$16)/365) -> 1387.8059 | AL24: =AK24*(1+'2. GRI Pricing Inputs'!M$115)^((AL$16-AK$16)/365) -> 1394.4684 | ... AP24: =AO24*(1+'2. GRI Pricing Inputs'!Q$115)^((AP$16-AO$16)/365) -> 1422.1205 | AQ24: =IFERROR(AP24/AD24-1,0) -> 0.06
A25: =_xlfn.XLOOKUP($C25,'Data Ref'!$D:$D,'Data Ref'!$B:$B,0) -> 222708009 | C25: ='1. Accomodation'!N29 -> 109 | D25: ='1. Accomodation'!L29 -> C | E25: ='1. Accomodation'!P29 -> 1 Bed | F25: ='1. Accomodation'!Q29 -> 1 | G25: ='1. Accomodation'!O29 -> 506.87 | H25: ='1. Accomodation'!R29 -> 1 | I25: ='1. Accomodation'!S29 -> Nursery and mixed other buildings | L25: =IFERROR(INDEX('2. GRI Pricing Inputs'!$C$15:$AI$16,MATCH($L$16,'2. GRI Pricing Inputs'!$C$15:$C$16,0),MATCH(E25,'2. GRI Pricing Inputs'!$C$15:$AI$15,0)),0) -> 1275 | M25: =IFERROR(INDEX('2. GRI Pricing Inputs'!$C$22:$AI$23,MATCH($M$16,'2. GRI Pricing Inputs'!$C$22:$C$23,0),MATCH(F25,'2. GRI Pricing Inputs'!$C$22:$AI$22,0)),0) -> 0 | N25: =IF(AND('3. GRI Pricing'!$G25>='2. GRI Pricing Inputs'!$D$33,'3. GRI Pricing'!$G25<='2. GRI Pricing Inputs'!$E$33),'2. GRI Pricing Inputs'!$D$32,IF(AND('3. GRI Pricing'!$G25>='2. GRI Pricing Inputs'!$F$33,'3. GRI Pricing'!$G25<='2. GRI Pricing Inputs'!$G$33),'2. GRI Pricing Inputs'!$F$32,IF(AND('3. GRI Pricing'!$G25>='2. GRI Pricing Inputs'!$H$33,'3. GRI Pricing'!$G25<='2. GRI Pricing Inputs'!$I$33),'2. GRI Pricing Inputs'!$H$32,IF(AND('3. GRI Pricing'!$G25>='2. GRI Pricing Inputs'!$J$33,'3. GRI Pricing'!$G25<='2. GRI Pricing Inputs'!$K$33),'2. GRI Pricing Inputs'!$J$32,IF(AND('3. GRI Pricing'!$G25>='2. GRI Pricing Inputs'!$L$33,'3. GRI Pricing'!$G25<='2. GRI Pricing Inputs'!$M$33),'2. GRI Pricing Inputs'!$L$32,IF(AND('3. GRI Pricing'!$G25>='2. GRI Pricing Inputs'!$N$33,'3. GRI Pricing'!$G25<='2. GRI Pricing Inputs'!$O$33),'2. GRI Pricing Inputs'!$N$32,IF(AND('3. GRI Pricing'!$G25>='2. GRI Pricing Inputs'!$P$33,'3. GRI Pricing'!$G25<='2. GRI Pricing Inputs'!$Q$33),'2. GRI Pricing Inputs'!$P$32,IF(AND('3. GRI Pricing'!$G25>='2. GRI Pricing Inputs'!$R$33,'3. GRI Pricing'!$G25<='2. GRI Pricing Inputs'!$S$33),'2. GRI Pricing Inputs'!$R$32,IF(AND('3. GRI Pricing'!$G25>='2. GRI Pricing Inputs'!$T$33,'3. GRI Pricing'!$G25<='2. GRI Pricing Inputs'!$U$33),'2. GRI Pricing Inputs'!$T$32,IF(AND('3. GRI Pricing'!$G25>='2. GRI Pricing Inputs'!$V$33,'3. GRI Pricing'!$G25<='2. GRI Pricing Inputs'!$W$33),'2. GRI Pricing Inputs'!$V$32,IF(AND('3. GRI Pricing'!$G25>='2. GRI Pricing Inputs'!$X$33,'3. GRI Pricing'!$G25<='2. GRI Pricing Inputs'!$Y$33),'2. GRI Pricing Inputs'!$X$32,IF(AND('3. GRI Pricing'!$G25>='2. GRI Pricing Inputs'!$Z$33,'3. GRI Pricing'!$G25<='2. GRI Pricing Inputs'!$AA$33),'2. GRI Pricing Inputs'!$Z$32,IF(AND('3. GRI Pricing'!$G25>='2. GRI Pricing Inputs'!$AB$33,'3. GRI Pricing'!$G25<='2. GRI Pricing Inputs'!$AC$33),'2. GRI Pricing Inputs'!$AB$32,IF(AND('3. GRI Pricing'!$G25>='2. GRI Pricing Inputs'!$AD$33,'3. GRI Pricing'!$G25<='2. GRI Pricing Inputs'!$AE$33),'2. GRI Pricing Inputs'!$AD$32,IF(AND('3. GRI Pricing'!$G25>='2. GRI Pricing Inputs'!$AF$33,'3. GRI Pricing'!$G25<='2. GRI Pricing Inputs'!$AG$33),'2. GRI Pricing Inputs'!$AF$32,IF(AND('3. GRI Pricing'!$G25>='2. GRI Pricing Inputs'!$AH$33,'3. GRI Pricing'!$G25<='2. GRI Pricing Inputs'!$AI$33),'2. GRI Pricing Inputs'!$AH$32,0)))))))))))))))) -> 5 | O25: {=IFERROR(INDEX('2. GRI Pricing Inputs'!$C$32:$AI$39,MATCH('3. GRI Pricing'!E25,'2. GRI Pricing Inputs'!$C$32:$C$39,0),(MATCH('3. GRI Pricing'!N25,'2. GRI Pricing Inputs'!$D$32:$AI$32,0)+1)),0)} -> 5 | P25: =IFERROR(INDEX('2. GRI Pricing Inputs'!$C$45:$AI$46,MATCH($P$16,'2. GRI Pricing Inputs'!$C$45:$C$46,0),MATCH(H25,'2. GRI Pricing Inputs'!$C$45:$AI$45,0)),0) -> 20 | Q25: =IFERROR(INDEX('2. GRI Pricing Inputs'!$C$53:$AI$54,MATCH('3. GRI Pricing'!$Q$16,'2. GRI Pricing Inputs'!$C$53:$C$54,0),MATCH('3. GRI Pricing'!I25,'2. GRI Pricing Inputs'!$C$53:$AI$53,0)),0) -> 0 | R25: =IFERROR(INDEX('2. GRI Pricing Inputs'!$C$60:$AI$61,MATCH('3. GRI Pricing'!$R$16,'2. GRI Pricing Inputs'!$C$60:$C$61,0),MATCH('1. Accomodation'!T29,'2. GRI Pricing Inputs'!$C$60:$AI$60,0)),0) -> 0 | S25: =IFERROR(INDEX('2. GRI Pricing Inputs'!$C$67:$AI$68,MATCH('3. GRI Pricing'!$S$16,'2. GRI Pricing Inputs'!$C$67:$C$68,0),MATCH('1. Accomodation'!U29,'2. GRI Pricing Inputs'!$C$67:$AI$67,0)),0) -> 0 | T25: =IF(E25=0,0,'2. GRI Pricing Inputs'!$AI$75) -> 0 | U25: =IFERROR(INDEX('2. GRI Pricing Inputs'!$C$82:$AI$83,MATCH('3. GRI Pricing'!$U$16,'2. GRI Pricing Inputs'!$C$82:$C$83,0),MATCH('1. Accomodation'!V29,'2. GRI Pricing Inputs'!$C$82:$AI$82,0)),0) -> 0 | V25: =IFERROR(INDEX('2. GRI Pricing Inputs'!$C$89:$AI$90,MATCH('3. GRI Pricing'!$V$16,'2. GRI Pricing Inputs'!$C$89:$C$90,0),MATCH('1. Accomodation'!W29,'2. GRI Pricing Inputs'!$C$89:$AI$89,0)),0) -> 0 | W25: =IFERROR(INDEX('2. GRI Pricing Inputs'!$C$97:$AI$98,MATCH('3. GRI Pricing'!$W$16,'2. GRI Pricing Inputs'!$C$97:$C$98,0),MATCH('1. Accomodation'!X29,'2. GRI Pricing Inputs'!$C$97:$AI$97,0)),0) -> 0 | X25: =IFERROR(INDEX('2. GRI Pricing Inputs'!$C$104:$AI$105,MATCH('3. GRI Pricing'!$X$16,'2. GRI Pricing Inputs'!$C$104:$C$105,0),MATCH('1. Accomodation'!Y29,'2. GRI Pricing Inputs'!$C$104:$AI$104,0)),0) -> 0 | Z25: =L25+M25+O25+P25+Q25+R25+S25+T25+U25+V25+W25+X25+Y25 -> 1300 | AD25: =Z25*(1+'2. GRI Pricing Inputs'!E$115)^(($AD$16-$AC$15)/365) -> 1306.4495 | AE25: =AD25*(1+'2. GRI Pricing Inputs'!F$115)^((AE$16-AD$16)/365) -> 1312.7214 | AF25: =AE25*(1+'2. GRI Pricing Inputs'!G$115)^((AF$16-AE$16)/365) -> 1319.2339 | AG25: =AF25*(1+'2. GRI Pricing Inputs'!H$115)^((AG$16-AF$16)/365) -> 1325.7788 | AH25: =AG25*(1+'2. GRI Pricing Inputs'!I$115)^((AH$16-AG$16)/365) -> 1331.7183 | AI25: =AH25*(1+'2. GRI Pricing Inputs'!J$115)^((AI$16-AH$16)/365) -> 1338.3251 | AJ25: =AI25*(1+'2. GRI Pricing Inputs'!K$115)^((AJ$16-AI$16)/365) -> 1344.75 | AK25: =AJ25*(1+'2. GRI Pricing Inputs'!L$115)^((AK$16-AJ$16)/365) -> 1351.4215 | AL25: =AK25*(1+'2. GRI Pricing Inputs'!M$115)^((AL$16-AK$16)/365) -> 1357.9093 | ... AP25: =AO25*(1+'2. GRI Pricing Inputs'!Q$115)^((AP$16-AO$16)/365) -> 1384.8364 | AQ25: =IFERROR(AP25/AD25-1,0) -> 0.06
A26: =_xlfn.XLOOKUP($C26,'Data Ref'!$D:$D,'Data Ref'!$B:$B,0) -> 222708010 | C26: ='1. Accomodation'!N30 -> 110 | D26: ='1. Accomodation'!L30 -> C | E26: ='1. Accomodation'!P30 -> 1 Bed | F26: ='1. Accomodation'!Q30 -> 1 | G26: ='1. Accomodation'!O30 -> 509.56 | H26: ='1. Accomodation'!R30 -> 1 | I26: ='1. Accomodation'!S30 -> Carpark and other block | L26: =IFERROR(INDEX('2. GRI Pricing Inputs'!$C$15:$AI$16,MATCH($L$16,'2. GRI Pricing Inputs'!$C$15:$C$16,0),MATCH(E26,'2. GRI Pricing Inputs'!$C$15:$AI$15,0)),0) -> 1275 | M26: =IFERROR(INDEX('2. GRI Pricing Inputs'!$C$22:$AI$23,MATCH($M$16,'2. GRI Pricing Inputs'!$C$22:$C$23,0),MATCH(F26,'2. GRI Pricing Inputs'!$C$22:$AI$22,0)),0) -> 0 | N26: =IF(AND('3. GRI Pricing'!$G26>='2. GRI Pricing Inputs'!$D$33,'3. GRI Pricing'!$G26<='2. GRI Pricing Inputs'!$E$33),'2. GRI Pricing Inputs'!$D$32,IF(AND('3. GRI Pricing'!$G26>='2. GRI Pricing Inputs'!$F$33,'3. GRI Pricing'!$G26<='2. GRI Pricing Inputs'!$G$33),'2. GRI Pricing Inputs'!$F$32,IF(AND('3. GRI Pricing'!$G26>='2. GRI Pricing Inputs'!$H$33,'3. GRI Pricing'!$G26<='2. GRI Pricing Inputs'!$I$33),'2. GRI Pricing Inputs'!$H$32,IF(AND('3. GRI Pricing'!$G26>='2. GRI Pricing Inputs'!$J$33,'3. GRI Pricing'!$G26<='2. GRI Pricing Inputs'!$K$33),'2. GRI Pricing Inputs'!$J$32,IF(AND('3. GRI Pricing'!$G26>='2. GRI Pricing Inputs'!$L$33,'3. GRI Pricing'!$G26<='2. GRI Pricing Inputs'!$M$33),'2. GRI Pricing Inputs'!$L$32,IF(AND('3. GRI Pricing'!$G26>='2. GRI Pricing Inputs'!$N$33,'3. GRI Pricing'!$G26<='2. GRI Pricing Inputs'!$O$33),'2. GRI Pricing Inputs'!$N$32,IF(AND('3. GRI Pricing'!$G26>='2. GRI Pricing Inputs'!$P$33,'3. GRI Pricing'!$G26<='2. GRI Pricing Inputs'!$Q$33),'2. GRI Pricing Inputs'!$P$32,IF(AND('3. GRI Pricing'!$G26>='2. GRI Pricing Inputs'!$R$33,'3. GRI Pricing'!$G26<='2. GRI Pricing Inputs'!$S$33),'2. GRI Pricing Inputs'!$R$32,IF(AND('3. GRI Pricing'!$G26>='2. GRI Pricing Inputs'!$T$33,'3. GRI Pricing'!$G26<='2. GRI Pricing Inputs'!$U$33),'2. GRI Pricing Inputs'!$T$32,IF(AND('3. GRI Pricing'!$G26>='2. GRI Pricing Inputs'!$V$33,'3. GRI Pricing'!$G26<='2. GRI Pricing Inputs'!$W$33),'2. GRI Pricing Inputs'!$V$32,IF(AND('3. GRI Pricing'!$G26>='2. GRI Pricing Inputs'!$X$33,'3. GRI Pricing'!$G26<='2. GRI Pricing Inputs'!$Y$33),'2. GRI Pricing Inputs'!$X$32,IF(AND('3. GRI Pricing'!$G26>='2. GRI Pricing Inputs'!$Z$33,'3. GRI Pricing'!$G26<='2. GRI Pricing Inputs'!$AA$33),'2. GRI Pricing Inputs'!$Z$32,IF(AND('3. GRI Pricing'!$G26>='2. GRI Pricing Inputs'!$AB$33,'3. GRI Pricing'!$G26<='2. GRI Pricing Inputs'!$AC$33),'2. GRI Pricing Inputs'!$AB$32,IF(AND('3. GRI Pricing'!$G26>='2. GRI Pricing Inputs'!$AD$33,'3. GRI Pricing'!$G26<='2. GRI Pricing Inputs'!$AE$33),'2. GRI Pricing Inputs'!$AD$32,IF(AND('3. GRI Pricing'!$G26>='2. GRI Pricing Inputs'!$AF$33,'3. GRI Pricing'!$G26<='2. GRI Pricing Inputs'!$AG$33),'2. GRI Pricing Inputs'!$AF$32,IF(AND('3. GRI Pricing'!$G26>='2. GRI Pricing Inputs'!$AH$33,'3. GRI Pricing'!$G26<='2. GRI Pricing Inputs'!$AI$33),'2. GRI Pricing Inputs'!$AH$32,0)))))))))))))))) -> 5 | O26: {=IFERROR(INDEX('2. GRI Pricing Inputs'!$C$32:$AI$39,MATCH('3. GRI Pricing'!E26,'2. GRI Pricing Inputs'!$C$32:$C$39,0),(MATCH('3. GRI Pricing'!N26,'2. GRI Pricing Inputs'!$D$32:$AI$32,0)+1)),0)} -> 5 | P26: =IFERROR(INDEX('2. GRI Pricing Inputs'!$C$45:$AI$46,MATCH($P$16,'2. GRI Pricing Inputs'!$C$45:$C$46,0),MATCH(H26,'2. GRI Pricing Inputs'!$C$45:$AI$45,0)),0) -> 20 | Q26: =IFERROR(INDEX('2. GRI Pricing Inputs'!$C$53:$AI$54,MATCH('3. GRI Pricing'!$Q$16,'2. GRI Pricing Inputs'!$C$53:$C$54,0),MATCH('3. GRI Pricing'!I26,'2. GRI Pricing Inputs'!$C$53:$AI$53,0)),0) -> 5 | R26: =IFERROR(INDEX('2. GRI Pricing Inputs'!$C$60:$AI$61,MATCH('3. GRI Pricing'!$R$16,'2. GRI Pricing Inputs'!$C$60:$C$61,0),MATCH('1. Accomodation'!T30,'2. GRI Pricing Inputs'!$C$60:$AI$60,0)),0) -> 0 | S26: =IFERROR(INDEX('2. GRI Pricing Inputs'!$C$67:$AI$68,MATCH('3. GRI Pricing'!$S$16,'2. GRI Pricing Inputs'!$C$67:$C$68,0),MATCH('1. Accomodation'!U30,'2. GRI Pricing Inputs'!$C$67:$AI$67,0)),0) -> 30 | T26: =IF(E26=0,0,'2. GRI Pricing Inputs'!$AI$75) -> 0 | U26: =IFERROR(INDEX('2. GRI Pricing Inputs'!$C$82:$AI$83,MATCH('3. GRI Pricing'!$U$16,'2. GRI Pricing Inputs'!$C$82:$C$83,0),MATCH('1. Accomodation'!V30,'2. GRI Pricing Inputs'!$C$82:$AI$82,0)),0) -> 0 | V26: =IFERROR(INDEX('2. GRI Pricing Inputs'!$C$89:$AI$90,MATCH('3. GRI Pricing'!$V$16,'2. GRI Pricing Inputs'!$C$89:$C$90,0),MATCH('1. Accomodation'!W30,'2. GRI Pricing Inputs'!$C$89:$AI$89,0)),0) -> 0 | W26: =IFERROR(INDEX('2. GRI Pricing Inputs'!$C$97:$AI$98,MATCH('3. GRI Pricing'!$W$16,'2. GRI Pricing Inputs'!$C$97:$C$98,0),MATCH('1. Accomodation'!X30,'2. GRI Pricing Inputs'!$C$97:$AI$97,0)),0) -> 0 | X26: =IFERROR(INDEX('2. GRI Pricing Inputs'!$C$104:$AI$105,MATCH('3. GRI Pricing'!$X$16,'2. GRI Pricing Inputs'!$C$104:$C$105,0),MATCH('1. Accomodation'!Y30,'2. GRI Pricing Inputs'!$C$104:$AI$104,0)),0) -> 0 | Z26: =L26+M26+O26+P26+Q26+R26+S26+T26+U26+V26+W26+X26+Y26 -> 1335 | AD26: =Z26*(1+'2. GRI Pricing Inputs'!E$115)^(($AD$16-$AC$15)/365) -> 1341.6231 | AE26: =AD26*(1+'2. GRI Pricing Inputs'!F$115)^((AE$16-AD$16)/365) -> 1348.0639 | AF26: =AE26*(1+'2. GRI Pricing Inputs'!G$115)^((AF$16-AE$16)/365) -> 1354.7518 | AG26: =AF26*(1+'2. GRI Pricing Inputs'!H$115)^((AG$16-AF$16)/365) -> 1361.4729 | AH26: =AG26*(1+'2. GRI Pricing Inputs'!I$115)^((AH$16-AG$16)/365) -> 1367.5722 | AI26: =AH26*(1+'2. GRI Pricing Inputs'!J$115)^((AI$16-AH$16)/365) -> 1374.3569 | AJ26: =AI26*(1+'2. GRI Pricing Inputs'!K$115)^((AJ$16-AI$16)/365) -> 1380.9548 | AK26: =AJ26*(1+'2. GRI Pricing Inputs'!L$115)^((AK$16-AJ$16)/365) -> 1387.8059 | AL26: =AK26*(1+'2. GRI Pricing Inputs'!M$115)^((AL$16-AK$16)/365) -> 1394.4684 | ... AP26: =AO26*(1+'2. GRI Pricing Inputs'!Q$115)^((AP$16-AO$16)/365) -> 1422.1205 | AQ26: =IFERROR(AP26/AD26-1,0) -> 0.06
A27: =_xlfn.XLOOKUP($C27,'Data Ref'!$D:$D,'Data Ref'!$B:$B,0) -> 222708011 | C27: ='1. Accomodation'!N31 -> 111 | D27: ='1. Accomodation'!L31 -> C | E27: ='1. Accomodation'!P31 -> 2 Bed | F27: ='1. Accomodation'!Q31 -> 2 | G27: ='1. Accomodation'!O31 -> 747.02 | H27: ='1. Accomodation'!R31 -> 1 | I27: ='1. Accomodation'!S31 -> Carpark and other block | L27: =IFERROR(INDEX('2. GRI Pricing Inputs'!$C$15:$AI$16,MATCH($L$16,'2. GRI Pricing Inputs'!$C$15:$C$16,0),MATCH(E27,'2. GRI Pricing Inputs'!$C$15:$AI$15,0)),0) -> 1665 | M27: =IFERROR(INDEX('2. GRI Pricing Inputs'!$C$22:$AI$23,MATCH($M$16,'2. GRI Pricing Inputs'!$C$22:$C$23,0),MATCH(F27,'2. GRI Pricing Inputs'!$C$22:$AI$22,0)),0) -> 0 | N27: =IF(AND('3. GRI Pricing'!$G27>='2. GRI Pricing Inputs'!$D$33,'3. GRI Pricing'!$G27<='2. GRI Pricing Inputs'!$E$33),'2. GRI Pricing Inputs'!$D$32,IF(AND('3. GRI Pricing'!$G27>='2. GRI Pricing Inputs'!$F$33,'3. GRI Pricing'!$G27<='2. GRI Pricing Inputs'!$G$33),'2. GRI Pricing Inputs'!$F$32,IF(AND('3. GRI Pricing'!$G27>='2. GRI Pricing Inputs'!$H$33,'3. GRI Pricing'!$G27<='2. GRI Pricing Inputs'!$I$33),'2. GRI Pricing Inputs'!$H$32,IF(AND('3. GRI Pricing'!$G27>='2. GRI Pricing Inputs'!$J$33,'3. GRI Pricing'!$G27<='2. GRI Pricing Inputs'!$K$33),'2. GRI Pricing Inputs'!$J$32,IF(AND('3. GRI Pricing'!$G27>='2. GRI Pricing Inputs'!$L$33,'3. GRI Pricing'!$G27<='2. GRI Pricing Inputs'!$M$33),'2. GRI Pricing Inputs'!$L$32,IF(AND('3. GRI Pricing'!$G27>='2. GRI Pricing Inputs'!$N$33,'3. GRI Pricing'!$G27<='2. GRI Pricing Inputs'!$O$33),'2. GRI Pricing Inputs'!$N$32,IF(AND('3. GRI Pricing'!$G27>='2. GRI Pricing Inputs'!$P$33,'3. GRI Pricing'!$G27<='2. GRI Pricing Inputs'!$Q$33),'2. GRI Pricing Inputs'!$P$32,IF(AND('3. GRI Pricing'!$G27>='2. GRI Pricing Inputs'!$R$33,'3. GRI Pricing'!$G27<='2. GRI Pricing Inputs'!$S$33),'2. GRI Pricing Inputs'!$R$32,IF(AND('3. GRI Pricing'!$G27>='2. GRI Pricing Inputs'!$T$33,'3. GRI Pricing'!$G27<='2. GRI Pricing Inputs'!$U$33),'2. GRI Pricing Inputs'!$T$32,IF(AND('3. GRI Pricing'!$G27>='2. GRI Pricing Inputs'!$V$33,'3. GRI Pricing'!$G27<='2. GRI Pricing Inputs'!$W$33),'2. GRI Pricing Inputs'!$V$32,IF(AND('3. GRI Pricing'!$G27>='2. GRI Pricing Inputs'!$X$33,'3. GRI Pricing'!$G27<='2. GRI Pricing Inputs'!$Y$33),'2. GRI Pricing Inputs'!$X$32,IF(AND('3. GRI Pricing'!$G27>='2. GRI Pricing Inputs'!$Z$33,'3. GRI Pricing'!$G27<='2. GRI Pricing Inputs'!$AA$33),'2. GRI Pricing Inputs'!$Z$32,IF(AND('3. GRI Pricing'!$G27>='2. GRI Pricing Inputs'!$AB$33,'3. GRI Pricing'!$G27<='2. GRI Pricing Inputs'!$AC$33),'2. GRI Pricing Inputs'!$AB$32,IF(AND('3. GRI Pricing'!$G27>='2. GRI Pricing Inputs'!$AD$33,'3. GRI Pricing'!$G27<='2. GRI Pricing Inputs'!$AE$33),'2. GRI Pricing Inputs'!$AD$32,IF(AND('3. GRI Pricing'!$G27>='2. GRI Pricing Inputs'!$AF$33,'3. GRI Pricing'!$G27<='2. GRI Pricing Inputs'!$AG$33),'2. GRI Pricing Inputs'!$AF$32,IF(AND('3. GRI Pricing'!$G27>='2. GRI Pricing Inputs'!$AH$33,'3. GRI Pricing'!$G27<='2. GRI Pricing Inputs'!$AI$33),'2. GRI Pricing Inputs'!$AH$32,0)))))))))))))))) -> 10 | O27: {=IFERROR(INDEX('2. GRI Pricing Inputs'!$C$32:$AI$39,MATCH('3. GRI Pricing'!E27,'2. GRI Pricing Inputs'!$C$32:$C$39,0),(MATCH('3. GRI Pricing'!N27,'2. GRI Pricing Inputs'!$D$32:$AI$32,0)+1)),0)} -> 15 | P27: =IFERROR(INDEX('2. GRI Pricing Inputs'!$C$45:$AI$46,MATCH($P$16,'2. GRI Pricing Inputs'!$C$45:$C$46,0),MATCH(H27,'2. GRI Pricing Inputs'!$C$45:$AI$45,0)),0) -> 20 | Q27: =IFERROR(INDEX('2. GRI Pricing Inputs'!$C$53:$AI$54,MATCH('3. GRI Pricing'!$Q$16,'2. GRI Pricing Inputs'!$C$53:$C$54,0),MATCH('3. GRI Pricing'!I27,'2. GRI Pricing Inputs'!$C$53:$AI$53,0)),0) -> 5 | R27: =IFERROR(INDEX('2. GRI Pricing Inputs'!$C$60:$AI$61,MATCH('3. GRI Pricing'!$R$16,'2. GRI Pricing Inputs'!$C$60:$C$61,0),MATCH('1. Accomodation'!T31,'2. GRI Pricing Inputs'!$C$60:$AI$60,0)),0) -> 0 | S27: =IFERROR(INDEX('2. GRI Pricing Inputs'!$C$67:$AI$68,MATCH('3. GRI Pricing'!$S$16,'2. GRI Pricing Inputs'!$C$67:$C$68,0),MATCH('1. Accomodation'!U31,'2. GRI Pricing Inputs'!$C$67:$AI$67,0)),0) -> 0 | T27: =IF(E27=0,0,'2. GRI Pricing Inputs'!$AI$75) -> 0 | U27: =IFERROR(INDEX('2. GRI Pricing Inputs'!$C$82:$AI$83,MATCH('3. GRI Pricing'!$U$16,'2. GRI Pricing Inputs'!$C$82:$C$83,0),MATCH('1. Accomodation'!V31,'2. GRI Pricing Inputs'!$C$82:$AI$82,0)),0) -> 0 | V27: =IFERROR(INDEX('2. GRI Pricing Inputs'!$C$89:$AI$90,MATCH('3. GRI Pricing'!$V$16,'2. GRI Pricing Inputs'!$C$89:$C$90,0),MATCH('1. Accomodation'!W31,'2. GRI Pricing Inputs'!$C$89:$AI$89,0)),0) -> 0 | W27: =IFERROR(INDEX('2. GRI Pricing Inputs'!$C$97:$AI$98,MATCH('3. GRI Pricing'!$W$16,'2. GRI Pricing Inputs'!$C$97:$C$98,0),MATCH('1. Accomodation'!X31,'2. GRI Pricing Inputs'!$C$97:$AI$97,0)),0) -> 0 | X27: =IFERROR(INDEX('2. GRI Pricing Inputs'!$C$104:$AI$105,MATCH('3. GRI Pricing'!$X$16,'2. GRI Pricing Inputs'!$C$104:$C$105,0),MATCH('1. Accomodation'!Y31,'2. GRI Pricing Inputs'!$C$104:$AI$104,0)),0) -> 0 | Z27: =L27+M27+O27+P27+Q27+R27+S27+T27+U27+V27+W27+X27+Y27 -> 1705 | AD27: =Z27*(1+'2. GRI Pricing Inputs'!E$115)^(($AD$16-$AC$15)/365) -> 1713.4587 | AE27: =AD27*(1+'2. GRI Pricing Inputs'!F$115)^((AE$16-AD$16)/365) -> 1721.6846 | AF27: =AE27*(1+'2. GRI Pricing Inputs'!G$115)^((AF$16-AE$16)/365) -> 1730.2261 | AG27: =AF27*(1+'2. GRI Pricing Inputs'!H$115)^((AG$16-AF$16)/365) -> 1738.8099 | AH27: =AG27*(1+'2. GRI Pricing Inputs'!I$115)^((AH$16-AG$16)/365) -> 1746.5997 | AI27: =AH27*(1+'2. GRI Pricing Inputs'!J$115)^((AI$16-AH$16)/365) -> 1755.2648 | AJ27: =AI27*(1+'2. GRI Pricing Inputs'!K$115)^((AJ$16-AI$16)/365) -> 1763.6913 | AK27: =AJ27*(1+'2. GRI Pricing Inputs'!L$115)^((AK$16-AJ$16)/365) -> 1772.4413 | AL27: =AK27*(1+'2. GRI Pricing Inputs'!M$115)^((AL$16-AK$16)/365) -> 1780.9502 | ... AP27: =AO27*(1+'2. GRI Pricing Inputs'!Q$115)^((AP$16-AO$16)/365) -> 1816.2663 | AQ27: =IFERROR(AP27/AD27-1,0) -> 0.06
A28: =_xlfn.XLOOKUP($C28,'Data Ref'!$D:$D,'Data Ref'!$B:$B,0) -> 222708012 | C28: ='1. Accomodation'!N32 -> 112 | D28: ='1. Accomodation'!L32 -> C | E28: ='1. Accomodation'!P32 -> 1 Bed | F28: ='1. Accomodation'!Q32 -> 1 | G28: ='1. Accomodation'!O32 -> 506.76 | H28: ='1. Accomodation'!R32 -> 1 | I28: ='1. Accomodation'!S32 -> Carpark and other block | L28: =IFERROR(INDEX('2. GRI Pricing Inputs'!$C$15:$AI$16,MATCH($L$16,'2. GRI Pricing Inputs'!$C$15:$C$16,0),MATCH(E28,'2. GRI Pricing Inputs'!$C$15:$AI$15,0)),0) -> 1275 | M28: =IFERROR(INDEX('2. GRI Pricing Inputs'!$C$22:$AI$23,MATCH($M$16,'2. GRI Pricing Inputs'!$C$22:$C$23,0),MATCH(F28,'2. GRI Pricing Inputs'!$C$22:$AI$22,0)),0) -> 0 | N28: =IF(AND('3. GRI Pricing'!$G28>='2. GRI Pricing Inputs'!$D$33,'3. GRI Pricing'!$G28<='2. GRI Pricing Inputs'!$E$33),'2. GRI Pricing Inputs'!$D$32,IF(AND('3. GRI Pricing'!$G28>='2. GRI Pricing Inputs'!$F$33,'3. GRI Pricing'!$G28<='2. GRI Pricing Inputs'!$G$33),'2. GRI Pricing Inputs'!$F$32,IF(AND('3. GRI Pricing'!$G28>='2. GRI Pricing Inputs'!$H$33,'3. GRI Pricing'!$G28<='2. GRI Pricing Inputs'!$I$33),'2. GRI Pricing Inputs'!$H$32,IF(AND('3. GRI Pricing'!$G28>='2. GRI Pricing Inputs'!$J$33,'3. GRI Pricing'!$G28<='2. GRI Pricing Inputs'!$K$33),'2. GRI Pricing Inputs'!$J$32,IF(AND('3. GRI Pricing'!$G28>='2. GRI Pricing Inputs'!$L$33,'3. GRI Pricing'!$G28<='2. GRI Pricing Inputs'!$M$33),'2. GRI Pricing Inputs'!$L$32,IF(AND('3. GRI Pricing'!$G28>='2. GRI Pricing Inputs'!$N$33,'3. GRI Pricing'!$G28<='2. GRI Pricing Inputs'!$O$33),'2. GRI Pricing Inputs'!$N$32,IF(AND('3. GRI Pricing'!$G28>='2. GRI Pricing Inputs'!$P$33,'3. GRI Pricing'!$G28<='2. GRI Pricing Inputs'!$Q$33),'2. GRI Pricing Inputs'!$P$32,IF(AND('3. GRI Pricing'!$G28>='2. GRI Pricing Inputs'!$R$33,'3. GRI Pricing'!$G28<='2. GRI Pricing Inputs'!$S$33),'2. GRI Pricing Inputs'!$R$32,IF(AND('3. GRI Pricing'!$G28>='2. GRI Pricing Inputs'!$T$33,'3. GRI Pricing'!$G28<='2. GRI Pricing Inputs'!$U$33),'2. GRI Pricing Inputs'!$T$32,IF(AND('3. GRI Pricing'!$G28>='2. GRI Pricing Inputs'!$V$33,'3. GRI Pricing'!$G28<='2. GRI Pricing Inputs'!$W$33),'2. GRI Pricing Inputs'!$V$32,IF(AND('3. GRI Pricing'!$G28>='2. GRI Pricing Inputs'!$X$33,'3. GRI Pricing'!$G28<='2. GRI Pricing Inputs'!$Y$33),'2. GRI Pricing Inputs'!$X$32,IF(AND('3. GRI Pricing'!$G28>='2. GRI Pricing Inputs'!$Z$33,'3. GRI Pricing'!$G28<='2. GRI Pricing Inputs'!$AA$33),'2. GRI Pricing Inputs'!$Z$32,IF(AND('3. GRI Pricing'!$G28>='2. GRI Pricing Inputs'!$AB$33,'3. GRI Pricing'!$G28<='2. GRI Pricing Inputs'!$AC$33),'2. GRI Pricing Inputs'!$AB$32,IF(AND('3. GRI Pricing'!$G28>='2. GRI Pricing Inputs'!$AD$33,'3. GRI Pricing'!$G28<='2. GRI Pricing Inputs'!$AE$33),'2. GRI Pricing Inputs'!$AD$32,IF(AND('3. GRI Pricing'!$G28>='2. GRI Pricing Inputs'!$AF$33,'3. GRI Pricing'!$G28<='2. GRI Pricing Inputs'!$AG$33),'2. GRI Pricing Inputs'!$AF$32,IF(AND('3. GRI Pricing'!$G28>='2. GRI Pricing Inputs'!$AH$33,'3. GRI Pricing'!$G28<='2. GRI Pricing Inputs'!$AI$33),'2. GRI Pricing Inputs'!$AH$32,0)))))))))))))))) -> 5 | O28: {=IFERROR(INDEX('2. GRI Pricing Inputs'!$C$32:$AI$39,MATCH('3. GRI Pricing'!E28,'2. GRI Pricing Inputs'!$C$32:$C$39,0),(MATCH('3. GRI Pricing'!N28,'2. GRI Pricing Inputs'!$D$32:$AI$32,0)+1)),0)} -> 5 | P28: =IFERROR(INDEX('2. GRI Pricing Inputs'!$C$45:$AI$46,MATCH($P$16,'2. GRI Pricing Inputs'!$C$45:$C$46,0),MATCH(H28,'2. GRI Pricing Inputs'!$C$45:$AI$45,0)),0) -> 20 | Q28: =IFERROR(INDEX('2. GRI Pricing Inputs'!$C$53:$AI$54,MATCH('3. GRI Pricing'!$Q$16,'2. GRI Pricing Inputs'!$C$53:$C$54,0),MATCH('3. GRI Pricing'!I28,'2. GRI Pricing Inputs'!$C$53:$AI$53,0)),0) -> 5 | R28: =IFERROR(INDEX('2. GRI Pricing Inputs'!$C$60:$AI$61,MATCH('3. GRI Pricing'!$R$16,'2. GRI Pricing Inputs'!$C$60:$C$61,0),MATCH('1. Accomodation'!T32,'2. GRI Pricing Inputs'!$C$60:$AI$60,0)),0) -> 0 | S28: =IFERROR(INDEX('2. GRI Pricing Inputs'!$C$67:$AI$68,MATCH('3. GRI Pricing'!$S$16,'2. GRI Pricing Inputs'!$C$67:$C$68,0),MATCH('1. Accomodation'!U32,'2. GRI Pricing Inputs'!$C$67:$AI$67,0)),0) -> 30 | T28: =IF(E28=0,0,'2. GRI Pricing Inputs'!$AI$75) -> 0 | U28: =IFERROR(INDEX('2. GRI Pricing Inputs'!$C$82:$AI$83,MATCH('3. GRI Pricing'!$U$16,'2. GRI Pricing Inputs'!$C$82:$C$83,0),MATCH('1. Accomodation'!V32,'2. GRI Pricing Inputs'!$C$82:$AI$82,0)),0) -> 0 | V28: =IFERROR(INDEX('2. GRI Pricing Inputs'!$C$89:$AI$90,MATCH('3. GRI Pricing'!$V$16,'2. GRI Pricing Inputs'!$C$89:$C$90,0),MATCH('1. Accomodation'!W32,'2. GRI Pricing Inputs'!$C$89:$AI$89,0)),0) -> 0 | W28: =IFERROR(INDEX('2. GRI Pricing Inputs'!$C$97:$AI$98,MATCH('3. GRI Pricing'!$W$16,'2. GRI Pricing Inputs'!$C$97:$C$98,0),MATCH('1. Accomodation'!X32,'2. GRI Pricing Inputs'!$C$97:$AI$97,0)),0) -> 0 | X28: =IFERROR(INDEX('2. GRI Pricing Inputs'!$C$104:$AI$105,MATCH('3. GRI Pricing'!$X$16,'2. GRI Pricing Inputs'!$C$104:$C$105,0),MATCH('1. Accomodation'!Y32,'2. GRI Pricing Inputs'!$C$104:$AI$104,0)),0) -> 0 | Z28: =L28+M28+O28+P28+Q28+R28+S28+T28+U28+V28+W28+X28+Y28 -> 1335 | AD28: =Z28*(1+'2. GRI Pricing Inputs'!E$115)^(($AD$16-$AC$15)/365) -> 1341.6231 | AE28: =AD28*(1+'2. GRI Pricing Inputs'!F$115)^((AE$16-AD$16)/365) -> 1348.0639 | AF28: =AE28*(1+'2. GRI Pricing Inputs'!G$115)^((AF$16-AE$16)/365) -> 1354.7518 | AG28: =AF28*(1+'2. GRI Pricing Inputs'!H$115)^((AG$16-AF$16)/365) -> 1361.4729 | AH28: =AG28*(1+'2. GRI Pricing Inputs'!I$115)^((AH$16-AG$16)/365) -> 1367.5722 | AI28: =AH28*(1+'2. GRI Pricing Inputs'!J$115)^((AI$16-AH$16)/365) -> 1374.3569 | AJ28: =AI28*(1+'2. GRI Pricing Inputs'!K$115)^((AJ$16-AI$16)/365) -> 1380.9548 | AK28: =AJ28*(1+'2. GRI Pricing Inputs'!L$115)^((AK$16-AJ$16)/365) -> 1387.8059 | AL28: =AK28*(1+'2. GRI Pricing Inputs'!M$115)^((AL$16-AK$16)/365) -> 1394.4684 | ... AP28: =AO28*(1+'2. GRI Pricing Inputs'!Q$115)^((AP$16-AO$16)/365) -> 1422.1205 | AQ28: =IFERROR(AP28/AD28-1,0) -> 0.06
... A277: =_xlfn.XLOOKUP($C277,'Data Ref'!$D:$D,'Data Ref'!$B:$B,0) -> 222708261 | C277: ='1. Accomodation'!N281 -> 821 | D277: ='1. Accomodation'!L281 -> D | E277: ='1. Accomodation'!P281 -> 1 Bed | F277: ='1. Accomodation'!Q281 -> 1 | G277: ='1. Accomodation'!O281 -> 485.13 | H277: ='1. Accomodation'!R281 -> 8 | I277: ='1. Accomodation'!S281 -> Internal Courtyard | L277: =IFERROR(INDEX('2. GRI Pricing Inputs'!$C$15:$AI$16,MATCH($L$16,'2. GRI Pricing Inputs'!$C$15:$C$16,0),MATCH(E277,'2. GRI Pricing Inputs'!$C$15:$AI$15,0)),0) -> 1275 | M277: =IFERROR(INDEX('2. GRI Pricing Inputs'!$C$22:$AI$23,MATCH($M$16,'2. GRI Pricing Inputs'!$C$22:$C$23,0),MATCH(F277,'2. GRI Pricing Inputs'!$C$22:$AI$22,0)),0) -> 0 | N277: =IF(AND('3. GRI Pricing'!$G277>='2. GRI Pricing Inputs'!$D$33,'3. GRI Pricing'!$G277<='2. GRI Pricing Inputs'!$E$33),'2. GRI Pricing Inputs'!$D$32,IF(AND('3. GRI Pricing'!$G277>='2. GRI Pricing Inputs'!$F$33,'3. GRI Pricing'!$G277<='2. GRI Pricing Inputs'!$G$33),'2. GRI Pricing Inputs'!$F$32,IF(AND('3. GRI Pricing'!$G277>='2. GRI Pricing Inputs'!$H$33,'3. GRI Pricing'!$G277<='2. GRI Pricing Inputs'!$I$33),'2. GRI Pricing Inputs'!$H$32,IF(AND('3. GRI Pricing'!$G277>='2. GRI Pricing Inputs'!$J$33,'3. GRI Pricing'!$G277<='2. GRI Pricing Inputs'!$K$33),'2. GRI Pricing Inputs'!$J$32,IF(AND('3. GRI Pricing'!$G277>='2. GRI Pricing Inputs'!$L$33,'3. GRI Pricing'!$G277<='2. GRI Pricing Inputs'!$M$33),'2. GRI Pricing Inputs'!$L$32,IF(AND('3. GRI Pricing'!$G277>='2. GRI Pricing Inputs'!$N$33,'3. GRI Pricing'!$G277<='2. GRI Pricing Inputs'!$O$33),'2. GRI Pricing Inputs'!$N$32,IF(AND('3. GRI Pricing'!$G277>='2. GRI Pricing Inputs'!$P$33,'3. GRI Pricing'!$G277<='2. GRI Pricing Inputs'!$Q$33),'2. GRI Pricing Inputs'!$P$32,IF(AND('3. GRI Pricing'!$G277>='2. GRI Pricing Inputs'!$R$33,'3. GRI Pricing'!$G277<='2. GRI Pricing Inputs'!$S$33),'2. GRI Pricing Inputs'!$R$32,IF(AND('3. GRI Pricing'!$G277>='2. GRI Pricing Inputs'!$T$33,'3. GRI Pricing'!$G277<='2. GRI Pricing Inputs'!$U$33),'2. GRI Pricing Inputs'!$T$32,IF(AND('3. GRI Pricing'!$G277>='2. GRI Pricing Inputs'!$V$33,'3. GRI Pricing'!$G277<='2. GRI Pricing Inputs'!$W$33),'2. GRI Pricing Inputs'!$V$32,IF(AND('3. GRI Pricing'!$G277>='2. GRI Pricing Inputs'!$X$33,'3. GRI Pricing'!$G277<='2. GRI Pricing Inputs'!$Y$33),'2. GRI Pricing Inputs'!$X$32,IF(AND('3. GRI Pricing'!$G277>='2. GRI Pricing Inputs'!$Z$33,'3. GRI Pricing'!$G277<='2. GRI Pricing Inputs'!$AA$33),'2. GRI Pricing Inputs'!$Z$32,IF(AND('3. GRI Pricing'!$G277>='2. GRI Pricing Inputs'!$AB$33,'3. GRI Pricing'!$G277<='2. GRI Pricing Inputs'!$AC$33),'2. GRI Pricing Inputs'!$AB$32,IF(AND('3. GRI Pricing'!$G277>='2. GRI Pricing Inputs'!$AD$33,'3. GRI Pricing'!$G277<='2. GRI Pricing Inputs'!$AE$33),'2. GRI Pricing Inputs'!$AD$32,IF(AND('3. GRI Pricing'!$G277>='2. GRI Pricing Inputs'!$AF$33,'3. GRI Pricing'!$G277<='2. GRI Pricing Inputs'!$AG$33),'2. GRI Pricing Inputs'!$AF$32,IF(AND('3. GRI Pricing'!$G277>='2. GRI Pricing Inputs'!$AH$33,'3. GRI Pricing'!$G277<='2. GRI Pricing Inputs'!$AI$33),'2. GRI Pricing Inputs'!$AH$32,0)))))))))))))))) -> 3 | O277: {=IFERROR(INDEX('2. GRI Pricing Inputs'!$C$32:$AI$39,MATCH('3. GRI Pricing'!E277,'2. GRI Pricing Inputs'!$C$32:$C$39,0),(MATCH('3. GRI Pricing'!N277,'2. GRI Pricing Inputs'!$D$32:$AI$32,0)+1)),0)} -> -5 | P277: =IFERROR(INDEX('2. GRI Pricing Inputs'!$C$45:$AI$46,MATCH($P$16,'2. GRI Pricing Inputs'!$C$45:$C$46,0),MATCH(H277,'2. GRI Pricing Inputs'!$C$45:$AI$45,0)),0) -> 55 | Q277: =IFERROR(INDEX('2. GRI Pricing Inputs'!$C$53:$AI$54,MATCH('3. GRI Pricing'!$Q$16,'2. GRI Pricing Inputs'!$C$53:$C$54,0),MATCH('3. GRI Pricing'!I277,'2. GRI Pricing Inputs'!$C$53:$AI$53,0)),0) -> 15 | R277: =IFERROR(INDEX('2. GRI Pricing Inputs'!$C$60:$AI$61,MATCH('3. GRI Pricing'!$R$16,'2. GRI Pricing Inputs'!$C$60:$C$61,0),MATCH('1. Accomodation'!T281,'2. GRI Pricing Inputs'!$C$60:$AI$60,0)),0) -> 0 | S277: =IFERROR(INDEX('2. GRI Pricing Inputs'!$C$67:$AI$68,MATCH('3. GRI Pricing'!$S$16,'2. GRI Pricing Inputs'!$C$67:$C$68,0),MATCH('1. Accomodation'!U281,'2. GRI Pricing Inputs'!$C$67:$AI$67,0)),0) -> 10 | T277: =IF(E277=0,0,'2. GRI Pricing Inputs'!$AI$75) -> 0 | U277: =IFERROR(INDEX('2. GRI Pricing Inputs'!$C$82:$AI$83,MATCH('3. GRI Pricing'!$U$16,'2. GRI Pricing Inputs'!$C$82:$C$83,0),MATCH('1. Accomodation'!V281,'2. GRI Pricing Inputs'!$C$82:$AI$82,0)),0) -> 0 | V277: =IFERROR(INDEX('2. GRI Pricing Inputs'!$C$89:$AI$90,MATCH('3. GRI Pricing'!$V$16,'2. GRI Pricing Inputs'!$C$89:$C$90,0),MATCH('1. Accomodation'!W281,'2. GRI Pricing Inputs'!$C$89:$AI$89,0)),0) -> 10 | W277: =IFERROR(INDEX('2. GRI Pricing Inputs'!$C$97:$AI$98,MATCH('3. GRI Pricing'!$W$16,'2. GRI Pricing Inputs'!$C$97:$C$98,0),MATCH('1. Accomodation'!X281,'2. GRI Pricing Inputs'!$C$97:$AI$97,0)),0) -> 0 | X277: =IFERROR(INDEX('2. GRI Pricing Inputs'!$C$104:$AI$105,MATCH('3. GRI Pricing'!$X$16,'2. GRI Pricing Inputs'!$C$104:$C$105,0),MATCH('1. Accomodation'!Y281,'2. GRI Pricing Inputs'!$C$104:$AI$104,0)),0) -> 0 | Z277: =L277+M277+O277+P277+Q277+R277+S277+T277+U277+V277+W277+X277+Y277 -> 1360 | AD277: =Z277*(1+'2. GRI Pricing Inputs'!E$115)^(($AD$16-$AC$15)/365) -> 1366.7471 | AE277: =AD277*(1+'2. GRI Pricing Inputs'!F$115)^((AE$16-AD$16)/365) -> 1373.3085 | AF277: =AE277*(1+'2. GRI Pricing Inputs'!G$115)^((AF$16-AE$16)/365) -> 1380.1217 | AG277: =AF277*(1+'2. GRI Pricing Inputs'!H$115)^((AG$16-AF$16)/365) -> 1386.9686 | AH277: =AG277*(1+'2. GRI Pricing Inputs'!I$115)^((AH$16-AG$16)/365) -> 1393.1822 | AI277: =AH277*(1+'2. GRI Pricing Inputs'!J$115)^((AI$16-AH$16)/365) -> 1400.0939 | AJ277: =AI277*(1+'2. GRI Pricing Inputs'!K$115)^((AJ$16-AI$16)/365) -> 1406.8154 | AK277: =AJ277*(1+'2. GRI Pricing Inputs'!L$115)^((AK$16-AJ$16)/365) -> 1413.7948 | AL277: =AK277*(1+'2. GRI Pricing Inputs'!M$115)^((AL$16-AK$16)/365) -> 1420.582 | ... AP277: =AO277*(1+'2. GRI Pricing Inputs'!Q$115)^((AP$16-AO$16)/365) -> 1448.752 | AQ277: =IFERROR(AP277/AD277-1,0) -> 0.06
C278: ='1. Accomodation'!N282 -> 0 | D278: ='1. Accomodation'!L282 -> [Select] | E278: ='1. Accomodation'!P282 -> [Select] | F278: ='1. Accomodation'!Q282 -> [Select] | G278: ='1. Accomodation'!O282 -> 0 | H278: ='1. Accomodation'!R282 -> [Select] | I278: ='1. Accomodation'!S282 -> [Select] | L278: =IFERROR(INDEX('2. GRI Pricing Inputs'!$C$15:$AI$16,MATCH($L$16,'2. GRI Pricing Inputs'!$C$15:$C$16,0),MATCH(E278,'2. GRI Pricing Inputs'!$C$15:$AI$15,0)),0) -> 0 | M278: =IFERROR(INDEX('2. GRI Pricing Inputs'!$C$22:$AI$23,MATCH($M$16,'2. GRI Pricing Inputs'!$C$22:$C$23,0),MATCH(F278,'2. GRI Pricing Inputs'!$C$22:$AI$22,0)),0) -> 0 | N278: =IF(AND('3. GRI Pricing'!$G278>='2. GRI Pricing Inputs'!$D$33,'3. GRI Pricing'!$G278<='2. GRI Pricing Inputs'!$E$33),'2. GRI Pricing Inputs'!$D$32,IF(AND('3. GRI Pricing'!$G278>='2. GRI Pricing Inputs'!$F$33,'3. GRI Pricing'!$G278<='2. GRI Pricing Inputs'!$G$33),'2. GRI Pricing Inputs'!$F$32,IF(AND('3. GRI Pricing'!$G278>='2. GRI Pricing Inputs'!$H$33,'3. GRI Pricing'!$G278<='2. GRI Pricing Inputs'!$I$33),'2. GRI Pricing Inputs'!$H$32,IF(AND('3. GRI Pricing'!$G278>='2. GRI Pricing Inputs'!$J$33,'3. GRI Pricing'!$G278<='2. GRI Pricing Inputs'!$K$33),'2. GRI Pricing Inputs'!$J$32,IF(AND('3. GRI Pricing'!$G278>='2. GRI Pricing Inputs'!$L$33,'3. GRI Pricing'!$G278<='2. GRI Pricing Inputs'!$M$33),'2. GRI Pricing Inputs'!$L$32,IF(AND('3. GRI Pricing'!$G278>='2. GRI Pricing Inputs'!$N$33,'3. GRI Pricing'!$G278<='2. GRI Pricing Inputs'!$O$33),'2. GRI Pricing Inputs'!$N$32,IF(AND('3. GRI Pricing'!$G278>='2. GRI Pricing Inputs'!$P$33,'3. GRI Pricing'!$G278<='2. GRI Pricing Inputs'!$Q$33),'2. GRI Pricing Inputs'!$P$32,IF(AND('3. GRI Pricing'!$G278>='2. GRI Pricing Inputs'!$R$33,'3. GRI Pricing'!$G278<='2. GRI Pricing Inputs'!$S$33),'2. GRI Pricing Inputs'!$R$32,IF(AND('3. GRI Pricing'!$G278>='2. GRI Pricing Inputs'!$T$33,'3. GRI Pricing'!$G278<='2. GRI Pricing Inputs'!$U$33),'2. GRI Pricing Inputs'!$T$32,IF(AND('3. GRI Pricing'!$G278>='2. GRI Pricing Inputs'!$V$33,'3. GRI Pricing'!$G278<='2. GRI Pricing Inputs'!$W$33),'2. GRI Pricing Inputs'!$V$32,IF(AND('3. GRI Pricing'!$G278>='2. GRI Pricing Inputs'!$X$33,'3. GRI Pricing'!$G278<='2. GRI Pricing Inputs'!$Y$33),'2. GRI Pricing Inputs'!$X$32,IF(AND('3. GRI Pricing'!$G278>='2. GRI Pricing Inputs'!$Z$33,'3. GRI Pricing'!$G278<='2. GRI Pricing Inputs'!$AA$33),'2. GRI Pricing Inputs'!$Z$32,IF(AND('3. GRI Pricing'!$G278>='2. GRI Pricing Inputs'!$AB$33,'3. GRI Pricing'!$G278<='2. GRI Pricing Inputs'!$AC$33),'2. GRI Pricing Inputs'!$AB$32,IF(AND('3. GRI Pricing'!$G278>='2. GRI Pricing Inputs'!$AD$33,'3. GRI Pricing'!$G278<='2. GRI Pricing Inputs'!$AE$33),'2. GRI Pricing Inputs'!$AD$32,IF(AND('3. GRI Pricing'!$G278>='2. GRI Pricing Inputs'!$AF$33,'3. GRI Pricing'!$G278<='2. GRI Pricing Inputs'!$AG$33),'2. GRI Pricing Inputs'!$AF$32,IF(AND('3. GRI Pricing'!$G278>='2. GRI Pricing Inputs'!$AH$33,'3. GRI Pricing'!$G278<='2. GRI Pricing Inputs'!$AI$33),'2. GRI Pricing Inputs'!$AH$32,0)))))))))))))))) -> 0 | O278: {=IFERROR(INDEX('2. GRI Pricing Inputs'!$C$32:$AI$39,MATCH('3. GRI Pricing'!E278,'2. GRI Pricing Inputs'!$C$32:$C$39,0),(MATCH('3. GRI Pricing'!N278,'2. GRI Pricing Inputs'!$D$32:$AI$32,0)+1)),0)} -> 0 | P278: =IFERROR(INDEX('2. GRI Pricing Inputs'!$C$45:$AI$46,MATCH($P$16,'2. GRI Pricing Inputs'!$C$45:$C$46,0),MATCH(H278,'2. GRI Pricing Inputs'!$C$45:$AI$45,0)),0) -> 0 | Q278: =IFERROR(INDEX('2. GRI Pricing Inputs'!$C$53:$AI$54,MATCH('3. GRI Pricing'!$Q$16,'2. GRI Pricing Inputs'!$C$53:$C$54,0),MATCH('3. GRI Pricing'!I278,'2. GRI Pricing Inputs'!$C$53:$AI$53,0)),0) -> 0 | R278: =IFERROR(INDEX('2. GRI Pricing Inputs'!$C$60:$AI$61,MATCH('3. GRI Pricing'!$R$16,'2. GRI Pricing Inputs'!$C$60:$C$61,0),MATCH('1. Accomodation'!T282,'2. GRI Pricing Inputs'!$C$60:$AI$60,0)),0) -> 0 | S278: =IFERROR(INDEX('2. GRI Pricing Inputs'!$C$67:$AI$68,MATCH('3. GRI Pricing'!$S$16,'2. GRI Pricing Inputs'!$C$67:$C$68,0),MATCH('1. Accomodation'!U282,'2. GRI Pricing Inputs'!$C$67:$AI$67,0)),0) -> 0 | T278: =IF(E278=0,0,'2. GRI Pricing Inputs'!$AI$75) -> 0 | U278: =IFERROR(INDEX('2. GRI Pricing Inputs'!$C$82:$AI$83,MATCH('3. GRI Pricing'!$U$16,'2. GRI Pricing Inputs'!$C$82:$C$83,0),MATCH('1. Accomodation'!V282,'2. GRI Pricing Inputs'!$C$82:$AI$82,0)),0) -> 0 | V278: =IFERROR(INDEX('2. GRI Pricing Inputs'!$C$89:$AI$90,MATCH('3. GRI Pricing'!$V$16,'2. GRI Pricing Inputs'!$C$89:$C$90,0),MATCH('1. Accomodation'!W282,'2. GRI Pricing Inputs'!$C$89:$AI$89,0)),0) -> 0 | W278: =IFERROR(INDEX('2. GRI Pricing Inputs'!$C$97:$AI$98,MATCH('3. GRI Pricing'!$W$16,'2. GRI Pricing Inputs'!$C$97:$C$98,0),MATCH('1. Accomodation'!X282,'2. GRI Pricing Inputs'!$C$97:$AI$97,0)),0) -> 0 | X278: =IFERROR(INDEX('2. GRI Pricing Inputs'!$C$104:$AI$105,MATCH('3. GRI Pricing'!$X$16,'2. GRI Pricing Inputs'!$C$104:$C$105,0),MATCH('1. Accomodation'!Y282,'2. GRI Pricing Inputs'!$C$104:$AI$104,0)),0) -> 0 | Z278: =L278+M278+O278+P278+Q278+R278+S278+T278+U278+V278+W278+X278+Y278 -> 0 | AD278: =Z278*(1+'2. GRI Pricing Inputs'!E$115)^(($AD$16-$AC$15)/365) -> 0 | AE278: =AD278*(1+'2. GRI Pricing Inputs'!F$115)^((AE$16-AD$16)/365) -> 0 | AF278: =AE278*(1+'2. GRI Pricing Inputs'!G$115)^((AF$16-AE$16)/365) -> 0 | AG278: =AF278*(1+'2. GRI Pricing Inputs'!H$115)^((AG$16-AF$16)/365) -> 0 | AH278: =AG278*(1+'2. GRI Pricing Inputs'!I$115)^((AH$16-AG$16)/365) -> 0 | AI278: =AH278*(1+'2. GRI Pricing Inputs'!J$115)^((AI$16-AH$16)/365) -> 0 | AJ278: =AI278*(1+'2. GRI Pricing Inputs'!K$115)^((AJ$16-AI$16)/365) -> 0 | AK278: =AJ278*(1+'2. GRI Pricing Inputs'!L$115)^((AK$16-AJ$16)/365) -> 0 | AL278: =AK278*(1+'2. GRI Pricing Inputs'!M$115)^((AL$16-AK$16)/365) -> 0 | ... AP278: =AO278*(1+'2. GRI Pricing Inputs'!Q$115)^((AP$16-AO$16)/365) -> 0 | AQ278: =IFERROR(AP278/AD278-1,0) -> 0
C279: ='1. Accomodation'!N283 -> 0 | D279: ='1. Accomodation'!L283 -> [Select] | E279: ='1. Accomodation'!P283 -> [Select] | F279: ='1. Accomodation'!Q283 -> [Select] | G279: ='1. Accomodation'!O283 -> 0 | H279: ='1. Accomodation'!R283 -> [Select] | I279: ='1. Accomodation'!S283 -> [Select] | L279: =IFERROR(INDEX('2. GRI Pricing Inputs'!$C$15:$AI$16,MATCH($L$16,'2. GRI Pricing Inputs'!$C$15:$C$16,0),MATCH(E279,'2. GRI Pricing Inputs'!$C$15:$AI$15,0)),0) -> 0 | M279: =IFERROR(INDEX('2. GRI Pricing Inputs'!$C$22:$AI$23,MATCH($M$16,'2. GRI Pricing Inputs'!$C$22:$C$23,0),MATCH(F279,'2. GRI Pricing Inputs'!$C$22:$AI$22,0)),0) -> 0 | N279: =IF(AND('3. GRI Pricing'!$G279>='2. GRI Pricing Inputs'!$D$33,'3. GRI Pricing'!$G279<='2. GRI Pricing Inputs'!$E$33),'2. GRI Pricing Inputs'!$D$32,IF(AND('3. GRI Pricing'!$G279>='2. GRI Pricing Inputs'!$F$33,'3. GRI Pricing'!$G279<='2. GRI Pricing Inputs'!$G$33),'2. GRI Pricing Inputs'!$F$32,IF(AND('3. GRI Pricing'!$G279>='2. GRI Pricing Inputs'!$H$33,'3. GRI Pricing'!$G279<='2. GRI Pricing Inputs'!$I$33),'2. GRI Pricing Inputs'!$H$32,IF(AND('3. GRI Pricing'!$G279>='2. GRI Pricing Inputs'!$J$33,'3. GRI Pricing'!$G279<='2. GRI Pricing Inputs'!$K$33),'2. GRI Pricing Inputs'!$J$32,IF(AND('3. GRI Pricing'!$G279>='2. GRI Pricing Inputs'!$L$33,'3. GRI Pricing'!$G279<='2. GRI Pricing Inputs'!$M$33),'2. GRI Pricing Inputs'!$L$32,IF(AND('3. GRI Pricing'!$G279>='2. GRI Pricing Inputs'!$N$33,'3. GRI Pricing'!$G279<='2. GRI Pricing Inputs'!$O$33),'2. GRI Pricing Inputs'!$N$32,IF(AND('3. GRI Pricing'!$G279>='2. GRI Pricing Inputs'!$P$33,'3. GRI Pricing'!$G279<='2. GRI Pricing Inputs'!$Q$33),'2. GRI Pricing Inputs'!$P$32,IF(AND('3. GRI Pricing'!$G279>='2. GRI Pricing Inputs'!$R$33,'3. GRI Pricing'!$G279<='2. GRI Pricing Inputs'!$S$33),'2. GRI Pricing Inputs'!$R$32,IF(AND('3. GRI Pricing'!$G279>='2. GRI Pricing Inputs'!$T$33,'3. GRI Pricing'!$G279<='2. GRI Pricing Inputs'!$U$33),'2. GRI Pricing Inputs'!$T$32,IF(AND('3. GRI Pricing'!$G279>='2. GRI Pricing Inputs'!$V$33,'3. GRI Pricing'!$G279<='2. GRI Pricing Inputs'!$W$33),'2. GRI Pricing Inputs'!$V$32,IF(AND('3. GRI Pricing'!$G279>='2. GRI Pricing Inputs'!$X$33,'3. GRI Pricing'!$G279<='2. GRI Pricing Inputs'!$Y$33),'2. GRI Pricing Inputs'!$X$32,IF(AND('3. GRI Pricing'!$G279>='2. GRI Pricing Inputs'!$Z$33,'3. GRI Pricing'!$G279<='2. GRI Pricing Inputs'!$AA$33),'2. GRI Pricing Inputs'!$Z$32,IF(AND('3. GRI Pricing'!$G279>='2. GRI Pricing Inputs'!$AB$33,'3. GRI Pricing'!$G279<='2. GRI Pricing Inputs'!$AC$33),'2. GRI Pricing Inputs'!$AB$32,IF(AND('3. GRI Pricing'!$G279>='2. GRI Pricing Inputs'!$AD$33,'3. GRI Pricing'!$G279<='2. GRI Pricing Inputs'!$AE$33),'2. GRI Pricing Inputs'!$AD$32,IF(AND('3. GRI Pricing'!$G279>='2. GRI Pricing Inputs'!$AF$33,'3. GRI Pricing'!$G279<='2. GRI Pricing Inputs'!$AG$33),'2. GRI Pricing Inputs'!$AF$32,IF(AND('3. GRI Pricing'!$G279>='2. GRI Pricing Inputs'!$AH$33,'3. GRI Pricing'!$G279<='2. GRI Pricing Inputs'!$AI$33),'2. GRI Pricing Inputs'!$AH$32,0)))))))))))))))) -> 0 | O279: {=IFERROR(INDEX('2. GRI Pricing Inputs'!$C$32:$AI$39,MATCH('3. GRI Pricing'!E279,'2. GRI Pricing Inputs'!$C$32:$C$39,0),(MATCH('3. GRI Pricing'!N279,'2. GRI Pricing Inputs'!$D$32:$AI$32,0)+1)),0)} -> 0 | P279: =IFERROR(INDEX('2. GRI Pricing Inputs'!$C$45:$AI$46,MATCH($P$16,'2. GRI Pricing Inputs'!$C$45:$C$46,0),MATCH(H279,'2. GRI Pricing Inputs'!$C$45:$AI$45,0)),0) -> 0 | Q279: =IFERROR(INDEX('2. GRI Pricing Inputs'!$C$53:$AI$54,MATCH('3. GRI Pricing'!$Q$16,'2. GRI Pricing Inputs'!$C$53:$C$54,0),MATCH('3. GRI Pricing'!I279,'2. GRI Pricing Inputs'!$C$53:$AI$53,0)),0) -> 0 | R279: =IFERROR(INDEX('2. GRI Pricing Inputs'!$C$60:$AI$61,MATCH('3. GRI Pricing'!$R$16,'2. GRI Pricing Inputs'!$C$60:$C$61,0),MATCH('1. Accomodation'!T283,'2. GRI Pricing Inputs'!$C$60:$AI$60,0)),0) -> 0 | S279: =IFERROR(INDEX('2. GRI Pricing Inputs'!$C$67:$AI$68,MATCH('3. GRI Pricing'!$S$16,'2. GRI Pricing Inputs'!$C$67:$C$68,0),MATCH('1. Accomodation'!U283,'2. GRI Pricing Inputs'!$C$67:$AI$67,0)),0) -> 0 | T279: =IF(E279=0,0,'2. GRI Pricing Inputs'!$AI$75) -> 0 | U279: =IFERROR(INDEX('2. GRI Pricing Inputs'!$C$82:$AI$83,MATCH('3. GRI Pricing'!$U$16,'2. GRI Pricing Inputs'!$C$82:$C$83,0),MATCH('1. Accomodation'!V283,'2. GRI Pricing Inputs'!$C$82:$AI$82,0)),0) -> 0 | V279: =IFERROR(INDEX('2. GRI Pricing Inputs'!$C$89:$AI$90,MATCH('3. GRI Pricing'!$V$16,'2. GRI Pricing Inputs'!$C$89:$C$90,0),MATCH('1. Accomodation'!W283,'2. GRI Pricing Inputs'!$C$89:$AI$89,0)),0) -> 0 | W279: =IFERROR(INDEX('2. GRI Pricing Inputs'!$C$97:$AI$98,MATCH('3. GRI Pricing'!$W$16,'2. GRI Pricing Inputs'!$C$97:$C$98,0),MATCH('1. Accomodation'!X283,'2. GRI Pricing Inputs'!$C$97:$AI$97,0)),0) -> 0 | X279: =IFERROR(INDEX('2. GRI Pricing Inputs'!$C$104:$AI$105,MATCH('3. GRI Pricing'!$X$16,'2. GRI Pricing Inputs'!$C$104:$C$105,0),MATCH('1. Accomodation'!Y283,'2. GRI Pricing Inputs'!$C$104:$AI$104,0)),0) -> 0 | Z279: =L279+M279+O279+P279+Q279+R279+S279+T279+U279+V279+W279+X279+Y279 -> 0 | AD279: =Z279*(1+'2. GRI Pricing Inputs'!E$115)^(($AD$16-$AC$15)/365) -> 0 | AE279: =AD279*(1+'2. GRI Pricing Inputs'!F$115)^((AE$16-AD$16)/365) -> 0 | AF279: =AE279*(1+'2. GRI Pricing Inputs'!G$115)^((AF$16-AE$16)/365) -> 0 | AG279: =AF279*(1+'2. GRI Pricing Inputs'!H$115)^((AG$16-AF$16)/365) -> 0 | AH279: =AG279*(1+'2. GRI Pricing Inputs'!I$115)^((AH$16-AG$16)/365) -> 0 | AI279: =AH279*(1+'2. GRI Pricing Inputs'!J$115)^((AI$16-AH$16)/365) -> 0 | AJ279: =AI279*(1+'2. GRI Pricing Inputs'!K$115)^((AJ$16-AI$16)/365) -> 0 | AK279: =AJ279*(1+'2. GRI Pricing Inputs'!L$115)^((AK$16-AJ$16)/365) -> 0 | AL279: =AK279*(1+'2. GRI Pricing Inputs'!M$115)^((AL$16-AK$16)/365) -> 0 | ... AP279: =AO279*(1+'2. GRI Pricing Inputs'!Q$115)^((AP$16-AO$16)/365) -> 0 | AQ279: =IFERROR(AP279/AD279-1,0) -> 0
C280: ='1. Accomodation'!N284 -> 0 | D280: ='1. Accomodation'!L284 -> [Select] | E280: ='1. Accomodation'!P284 -> [Select] | F280: ='1. Accomodation'!Q284 -> [Select] | G280: ='1. Accomodation'!O284 -> 0 | H280: ='1. Accomodation'!R284 -> [Select] | I280: ='1. Accomodation'!S284 -> [Select] | L280: =IFERROR(INDEX('2. GRI Pricing Inputs'!$C$15:$AI$16,MATCH($L$16,'2. GRI Pricing Inputs'!$C$15:$C$16,0),MATCH(E280,'2. GRI Pricing Inputs'!$C$15:$AI$15,0)),0) -> 0 | M280: =IFERROR(INDEX('2. GRI Pricing Inputs'!$C$22:$AI$23,MATCH($M$16,'2. GRI Pricing Inputs'!$C$22:$C$23,0),MATCH(F280,'2. GRI Pricing Inputs'!$C$22:$AI$22,0)),0) -> 0 | N280: =IF(AND('3. GRI Pricing'!$G280>='2. GRI Pricing Inputs'!$D$33,'3. GRI Pricing'!$G280<='2. GRI Pricing Inputs'!$E$33),'2. GRI Pricing Inputs'!$D$32,IF(AND('3. GRI Pricing'!$G280>='2. GRI Pricing Inputs'!$F$33,'3. GRI Pricing'!$G280<='2. GRI Pricing Inputs'!$G$33),'2. GRI Pricing Inputs'!$F$32,IF(AND('3. GRI Pricing'!$G280>='2. GRI Pricing Inputs'!$H$33,'3. GRI Pricing'!$G280<='2. GRI Pricing Inputs'!$I$33),'2. GRI Pricing Inputs'!$H$32,IF(AND('3. GRI Pricing'!$G280>='2. GRI Pricing Inputs'!$J$33,'3. GRI Pricing'!$G280<='2. GRI Pricing Inputs'!$K$33),'2. GRI Pricing Inputs'!$J$32,IF(AND('3. GRI Pricing'!$G280>='2. GRI Pricing Inputs'!$L$33,'3. GRI Pricing'!$G280<='2. GRI Pricing Inputs'!$M$33),'2. GRI Pricing Inputs'!$L$32,IF(AND('3. GRI Pricing'!$G280>='2. GRI Pricing Inputs'!$N$33,'3. GRI Pricing'!$G280<='2. GRI Pricing Inputs'!$O$33),'2. GRI Pricing Inputs'!$N$32,IF(AND('3. GRI Pricing'!$G280>='2. GRI Pricing Inputs'!$P$33,'3. GRI Pricing'!$G280<='2. GRI Pricing Inputs'!$Q$33),'2. GRI Pricing Inputs'!$P$32,IF(AND('3. GRI Pricing'!$G280>='2. GRI Pricing Inputs'!$R$33,'3. GRI Pricing'!$G280<='2. GRI Pricing Inputs'!$S$33),'2. GRI Pricing Inputs'!$R$32,IF(AND('3. GRI Pricing'!$G280>='2. GRI Pricing Inputs'!$T$33,'3. GRI Pricing'!$G280<='2. GRI Pricing Inputs'!$U$33),'2. GRI Pricing Inputs'!$T$32,IF(AND('3. GRI Pricing'!$G280>='2. GRI Pricing Inputs'!$V$33,'3. GRI Pricing'!$G280<='2. GRI Pricing Inputs'!$W$33),'2. GRI Pricing Inputs'!$V$32,IF(AND('3. GRI Pricing'!$G280>='2. GRI Pricing Inputs'!$X$33,'3. GRI Pricing'!$G280<='2. GRI Pricing Inputs'!$Y$33),'2. GRI Pricing Inputs'!$X$32,IF(AND('3. GRI Pricing'!$G280>='2. GRI Pricing Inputs'!$Z$33,'3. GRI Pricing'!$G280<='2. GRI Pricing Inputs'!$AA$33),'2. GRI Pricing Inputs'!$Z$32,IF(AND('3. GRI Pricing'!$G280>='2. GRI Pricing Inputs'!$AB$33,'3. GRI Pricing'!$G280<='2. GRI Pricing Inputs'!$AC$33),'2. GRI Pricing Inputs'!$AB$32,IF(AND('3. GRI Pricing'!$G280>='2. GRI Pricing Inputs'!$AD$33,'3. GRI Pricing'!$G280<='2. GRI Pricing Inputs'!$AE$33),'2. GRI Pricing Inputs'!$AD$32,IF(AND('3. GRI Pricing'!$G280>='2. GRI Pricing Inputs'!$AF$33,'3. GRI Pricing'!$G280<='2. GRI Pricing Inputs'!$AG$33),'2. GRI Pricing Inputs'!$AF$32,IF(AND('3. GRI Pricing'!$G280>='2. GRI Pricing Inputs'!$AH$33,'3. GRI Pricing'!$G280<='2. GRI Pricing Inputs'!$AI$33),'2. GRI Pricing Inputs'!$AH$32,0)))))))))))))))) -> 0 | O280: {=IFERROR(INDEX('2. GRI Pricing Inputs'!$C$32:$AI$39,MATCH('3. GRI Pricing'!E280,'2. GRI Pricing Inputs'!$C$32:$C$39,0),(MATCH('3. GRI Pricing'!N280,'2. GRI Pricing Inputs'!$D$32:$AI$32,0)+1)),0)} -> 0 | P280: =IFERROR(INDEX('2. GRI Pricing Inputs'!$C$45:$AI$46,MATCH($P$16,'2. GRI Pricing Inputs'!$C$45:$C$46,0),MATCH(H280,'2. GRI Pricing Inputs'!$C$45:$AI$45,0)),0) -> 0 | Q280: =IFERROR(INDEX('2. GRI Pricing Inputs'!$C$53:$AI$54,MATCH('3. GRI Pricing'!$Q$16,'2. GRI Pricing Inputs'!$C$53:$C$54,0),MATCH('3. GRI Pricing'!I280,'2. GRI Pricing Inputs'!$C$53:$AI$53,0)),0) -> 0 | R280: =IFERROR(INDEX('2. GRI Pricing Inputs'!$C$60:$AI$61,MATCH('3. GRI Pricing'!$R$16,'2. GRI Pricing Inputs'!$C$60:$C$61,0),MATCH('1. Accomodation'!T284,'2. GRI Pricing Inputs'!$C$60:$AI$60,0)),0) -> 0 | S280: =IFERROR(INDEX('2. GRI Pricing Inputs'!$C$67:$AI$68,MATCH('3. GRI Pricing'!$S$16,'2. GRI Pricing Inputs'!$C$67:$C$68,0),MATCH('1. Accomodation'!U284,'2. GRI Pricing Inputs'!$C$67:$AI$67,0)),0) -> 0 | T280: =IF(E280=0,0,'2. GRI Pricing Inputs'!$AI$75) -> 0 | U280: =IFERROR(INDEX('2. GRI Pricing Inputs'!$C$82:$AI$83,MATCH('3. GRI Pricing'!$U$16,'2. GRI Pricing Inputs'!$C$82:$C$83,0),MATCH('1. Accomodation'!V284,'2. GRI Pricing Inputs'!$C$82:$AI$82,0)),0) -> 0 | V280: =IFERROR(INDEX('2. GRI Pricing Inputs'!$C$89:$AI$90,MATCH('3. GRI Pricing'!$V$16,'2. GRI Pricing Inputs'!$C$89:$C$90,0),MATCH('1. Accomodation'!W284,'2. GRI Pricing Inputs'!$C$89:$AI$89,0)),0) -> 0 | W280: =IFERROR(INDEX('2. GRI Pricing Inputs'!$C$97:$AI$98,MATCH('3. GRI Pricing'!$W$16,'2. GRI Pricing Inputs'!$C$97:$C$98,0),MATCH('1. Accomodation'!X284,'2. GRI Pricing Inputs'!$C$97:$AI$97,0)),0) -> 0 | X280: =IFERROR(INDEX('2. GRI Pricing Inputs'!$C$104:$AI$105,MATCH('3. GRI Pricing'!$X$16,'2. GRI Pricing Inputs'!$C$104:$C$105,0),MATCH('1. Accomodation'!Y284,'2. GRI Pricing Inputs'!$C$104:$AI$104,0)),0) -> 0 | Z280: =L280+M280+O280+P280+Q280+R280+S280+T280+U280+V280+W280+X280+Y280 -> 0 | AD280: =Z280*(1+'2. GRI Pricing Inputs'!E$115)^(($AD$16-$AC$15)/365) -> 0 | AE280: =AD280*(1+'2. GRI Pricing Inputs'!F$115)^((AE$16-AD$16)/365) -> 0 | AF280: =AE280*(1+'2. GRI Pricing Inputs'!G$115)^((AF$16-AE$16)/365) -> 0 | AG280: =AF280*(1+'2. GRI Pricing Inputs'!H$115)^((AG$16-AF$16)/365) -> 0 | AH280: =AG280*(1+'2. GRI Pricing Inputs'!I$115)^((AH$16-AG$16)/365) -> 0 | AI280: =AH280*(1+'2. GRI Pricing Inputs'!J$115)^((AI$16-AH$16)/365) -> 0 | AJ280: =AI280*(1+'2. GRI Pricing Inputs'!K$115)^((AJ$16-AI$16)/365) -> 0 | AK280: =AJ280*(1+'2. GRI Pricing Inputs'!L$115)^((AK$16-AJ$16)/365) -> 0 | AL280: =AK280*(1+'2. GRI Pricing Inputs'!M$115)^((AL$16-AK$16)/365) -> 0 | ... AP280: =AO280*(1+'2. GRI Pricing Inputs'!Q$115)^((AP$16-AO$16)/365) -> 0 | AQ280: =IFERROR(AP280/AD280-1,0) -> 0
C281: ='1. Accomodation'!N285 -> 0 | D281: ='1. Accomodation'!L285 -> [Select] | E281: ='1. Accomodation'!P285 -> [Select] | F281: ='1. Accomodation'!Q285 -> [Select] | G281: ='1. Accomodation'!O285 -> 0 | H281: ='1. Accomodation'!R285 -> [Select] | I281: ='1. Accomodation'!S285 -> [Select] | L281: =IFERROR(INDEX('2. GRI Pricing Inputs'!$C$15:$AI$16,MATCH($L$16,'2. GRI Pricing Inputs'!$C$15:$C$16,0),MATCH(E281,'2. GRI Pricing Inputs'!$C$15:$AI$15,0)),0) -> 0 | M281: =IFERROR(INDEX('2. GRI Pricing Inputs'!$C$22:$AI$23,MATCH($M$16,'2. GRI Pricing Inputs'!$C$22:$C$23,0),MATCH(F281,'2. GRI Pricing Inputs'!$C$22:$AI$22,0)),0) -> 0 | N281: =IF(AND('3. GRI Pricing'!$G281>='2. GRI Pricing Inputs'!$D$33,'3. GRI Pricing'!$G281<='2. GRI Pricing Inputs'!$E$33),'2. GRI Pricing Inputs'!$D$32,IF(AND('3. GRI Pricing'!$G281>='2. GRI Pricing Inputs'!$F$33,'3. GRI Pricing'!$G281<='2. GRI Pricing Inputs'!$G$33),'2. GRI Pricing Inputs'!$F$32,IF(AND('3. GRI Pricing'!$G281>='2. GRI Pricing Inputs'!$H$33,'3. GRI Pricing'!$G281<='2. GRI Pricing Inputs'!$I$33),'2. GRI Pricing Inputs'!$H$32,IF(AND('3. GRI Pricing'!$G281>='2. GRI Pricing Inputs'!$J$33,'3. GRI Pricing'!$G281<='2. GRI Pricing Inputs'!$K$33),'2. GRI Pricing Inputs'!$J$32,IF(AND('3. GRI Pricing'!$G281>='2. GRI Pricing Inputs'!$L$33,'3. GRI Pricing'!$G281<='2. GRI Pricing Inputs'!$M$33),'2. GRI Pricing Inputs'!$L$32,IF(AND('3. GRI Pricing'!$G281>='2. GRI Pricing Inputs'!$N$33,'3. GRI Pricing'!$G281<='2. GRI Pricing Inputs'!$O$33),'2. GRI Pricing Inputs'!$N$32,IF(AND('3. GRI Pricing'!$G281>='2. GRI Pricing Inputs'!$P$33,'3. GRI Pricing'!$G281<='2. GRI Pricing Inputs'!$Q$33),'2. GRI Pricing Inputs'!$P$32,IF(AND('3. GRI Pricing'!$G281>='2. GRI Pricing Inputs'!$R$33,'3. GRI Pricing'!$G281<='2. GRI Pricing Inputs'!$S$33),'2. GRI Pricing Inputs'!$R$32,IF(AND('3. GRI Pricing'!$G281>='2. GRI Pricing Inputs'!$T$33,'3. GRI Pricing'!$G281<='2. GRI Pricing Inputs'!$U$33),'2. GRI Pricing Inputs'!$T$32,IF(AND('3. GRI Pricing'!$G281>='2. GRI Pricing Inputs'!$V$33,'3. GRI Pricing'!$G281<='2. GRI Pricing Inputs'!$W$33),'2. GRI Pricing Inputs'!$V$32,IF(AND('3. GRI Pricing'!$G281>='2. GRI Pricing Inputs'!$X$33,'3. GRI Pricing'!$G281<='2. GRI Pricing Inputs'!$Y$33),'2. GRI Pricing Inputs'!$X$32,IF(AND('3. GRI Pricing'!$G281>='2. GRI Pricing Inputs'!$Z$33,'3. GRI Pricing'!$G281<='2. GRI Pricing Inputs'!$AA$33),'2. GRI Pricing Inputs'!$Z$32,IF(AND('3. GRI Pricing'!$G281>='2. GRI Pricing Inputs'!$AB$33,'3. GRI Pricing'!$G281<='2. GRI Pricing Inputs'!$AC$33),'2. GRI Pricing Inputs'!$AB$32,IF(AND('3. GRI Pricing'!$G281>='2. GRI Pricing Inputs'!$AD$33,'3. GRI Pricing'!$G281<='2. GRI Pricing Inputs'!$AE$33),'2. GRI Pricing Inputs'!$AD$32,IF(AND('3. GRI Pricing'!$G281>='2. GRI Pricing Inputs'!$AF$33,'3. GRI Pricing'!$G281<='2. GRI Pricing Inputs'!$AG$33),'2. GRI Pricing Inputs'!$AF$32,IF(AND('3. GRI Pricing'!$G281>='2. GRI Pricing Inputs'!$AH$33,'3. GRI Pricing'!$G281<='2. GRI Pricing Inputs'!$AI$33),'2. GRI Pricing Inputs'!$AH$32,0)))))))))))))))) -> 0 | O281: {=IFERROR(INDEX('2. GRI Pricing Inputs'!$C$32:$AI$39,MATCH('3. GRI Pricing'!E281,'2. GRI Pricing Inputs'!$C$32:$C$39,0),(MATCH('3. GRI Pricing'!N281,'2. GRI Pricing Inputs'!$D$32:$AI$32,0)+1)),0)} -> 0 | P281: =IFERROR(INDEX('2. GRI Pricing Inputs'!$C$45:$AI$46,MATCH($P$16,'2. GRI Pricing Inputs'!$C$45:$C$46,0),MATCH(H281,'2. GRI Pricing Inputs'!$C$45:$AI$45,0)),0) -> 0 | Q281: =IFERROR(INDEX('2. GRI Pricing Inputs'!$C$53:$AI$54,MATCH('3. GRI Pricing'!$Q$16,'2. GRI Pricing Inputs'!$C$53:$C$54,0),MATCH('3. GRI Pricing'!I281,'2. GRI Pricing Inputs'!$C$53:$AI$53,0)),0) -> 0 | R281: =IFERROR(INDEX('2. GRI Pricing Inputs'!$C$60:$AI$61,MATCH('3. GRI Pricing'!$R$16,'2. GRI Pricing Inputs'!$C$60:$C$61,0),MATCH('1. Accomodation'!T285,'2. GRI Pricing Inputs'!$C$60:$AI$60,0)),0) -> 0 | S281: =IFERROR(INDEX('2. GRI Pricing Inputs'!$C$67:$AI$68,MATCH('3. GRI Pricing'!$S$16,'2. GRI Pricing Inputs'!$C$67:$C$68,0),MATCH('1. Accomodation'!U285,'2. GRI Pricing Inputs'!$C$67:$AI$67,0)),0) -> 0 | T281: =IF(E281=0,0,'2. GRI Pricing Inputs'!$AI$75) -> 0 | U281: =IFERROR(INDEX('2. GRI Pricing Inputs'!$C$82:$AI$83,MATCH('3. GRI Pricing'!$U$16,'2. GRI Pricing Inputs'!$C$82:$C$83,0),MATCH('1. Accomodation'!V285,'2. GRI Pricing Inputs'!$C$82:$AI$82,0)),0) -> 0 | V281: =IFERROR(INDEX('2. GRI Pricing Inputs'!$C$89:$AI$90,MATCH('3. GRI Pricing'!$V$16,'2. GRI Pricing Inputs'!$C$89:$C$90,0),MATCH('1. Accomodation'!W285,'2. GRI Pricing Inputs'!$C$89:$AI$89,0)),0) -> 0 | W281: =IFERROR(INDEX('2. GRI Pricing Inputs'!$C$97:$AI$98,MATCH('3. GRI Pricing'!$W$16,'2. GRI Pricing Inputs'!$C$97:$C$98,0),MATCH('1. Accomodation'!X285,'2. GRI Pricing Inputs'!$C$97:$AI$97,0)),0) -> 0 | X281: =IFERROR(INDEX('2. GRI Pricing Inputs'!$C$104:$AI$105,MATCH('3. GRI Pricing'!$X$16,'2. GRI Pricing Inputs'!$C$104:$C$105,0),MATCH('1. Accomodation'!Y285,'2. GRI Pricing Inputs'!$C$104:$AI$104,0)),0) -> 0 | Z281: =L281+M281+O281+P281+Q281+R281+S281+T281+U281+V281+W281+X281+Y281 -> 0 | AD281: =Z281*(1+'2. GRI Pricing Inputs'!E$115)^(($AD$16-$AC$15)/365) -> 0 | AE281: =AD281*(1+'2. GRI Pricing Inputs'!F$115)^((AE$16-AD$16)/365) -> 0 | AF281: =AE281*(1+'2. GRI Pricing Inputs'!G$115)^((AF$16-AE$16)/365) -> 0 | AG281: =AF281*(1+'2. GRI Pricing Inputs'!H$115)^((AG$16-AF$16)/365) -> 0 | AH281: =AG281*(1+'2. GRI Pricing Inputs'!I$115)^((AH$16-AG$16)/365) -> 0 | AI281: =AH281*(1+'2. GRI Pricing Inputs'!J$115)^((AI$16-AH$16)/365) -> 0 | AJ281: =AI281*(1+'2. GRI Pricing Inputs'!K$115)^((AJ$16-AI$16)/365) -> 0 | AK281: =AJ281*(1+'2. GRI Pricing Inputs'!L$115)^((AK$16-AJ$16)/365) -> 0 | AL281: =AK281*(1+'2. GRI Pricing Inputs'!M$115)^((AL$16-AK$16)/365) -> 0 | ... AP281: =AO281*(1+'2. GRI Pricing Inputs'!Q$115)^((AP$16-AO$16)/365) -> 0 | AQ281: =IFERROR(AP281/AD281-1,0) -> 0
C282: ='1. Accomodation'!N286 -> 0 | D282: ='1. Accomodation'!L286 -> [Select] | E282: ='1. Accomodation'!P286 -> [Select] | F282: ='1. Accomodation'!Q286 -> [Select] | G282: ='1. Accomodation'!O286 -> 0 | H282: ='1. Accomodation'!R286 -> [Select] | I282: ='1. Accomodation'!S286 -> [Select] | L282: =IFERROR(INDEX('2. GRI Pricing Inputs'!$C$15:$AI$16,MATCH($L$16,'2. GRI Pricing Inputs'!$C$15:$C$16,0),MATCH(E282,'2. GRI Pricing Inputs'!$C$15:$AI$15,0)),0) -> 0 | M282: =IFERROR(INDEX('2. GRI Pricing Inputs'!$C$22:$AI$23,MATCH($M$16,'2. GRI Pricing Inputs'!$C$22:$C$23,0),MATCH(F282,'2. GRI Pricing Inputs'!$C$22:$AI$22,0)),0) -> 0 | N282: =IF(AND('3. GRI Pricing'!$G282>='2. GRI Pricing Inputs'!$D$33,'3. GRI Pricing'!$G282<='2. GRI Pricing Inputs'!$E$33),'2. GRI Pricing Inputs'!$D$32,IF(AND('3. GRI Pricing'!$G282>='2. GRI Pricing Inputs'!$F$33,'3. GRI Pricing'!$G282<='2. GRI Pricing Inputs'!$G$33),'2. GRI Pricing Inputs'!$F$32,IF(AND('3. GRI Pricing'!$G282>='2. GRI Pricing Inputs'!$H$33,'3. GRI Pricing'!$G282<='2. GRI Pricing Inputs'!$I$33),'2. GRI Pricing Inputs'!$H$32,IF(AND('3. GRI Pricing'!$G282>='2. GRI Pricing Inputs'!$J$33,'3. GRI Pricing'!$G282<='2. GRI Pricing Inputs'!$K$33),'2. GRI Pricing Inputs'!$J$32,IF(AND('3. GRI Pricing'!$G282>='2. GRI Pricing Inputs'!$L$33,'3. GRI Pricing'!$G282<='2. GRI Pricing Inputs'!$M$33),'2. GRI Pricing Inputs'!$L$32,IF(AND('3. GRI Pricing'!$G282>='2. GRI Pricing Inputs'!$N$33,'3. GRI Pricing'!$G282<='2. GRI Pricing Inputs'!$O$33),'2. GRI Pricing Inputs'!$N$32,IF(AND('3. GRI Pricing'!$G282>='2. GRI Pricing Inputs'!$P$33,'3. GRI Pricing'!$G282<='2. GRI Pricing Inputs'!$Q$33),'2. GRI Pricing Inputs'!$P$32,IF(AND('3. GRI Pricing'!$G282>='2. GRI Pricing Inputs'!$R$33,'3. GRI Pricing'!$G282<='2. GRI Pricing Inputs'!$S$33),'2. GRI Pricing Inputs'!$R$32,IF(AND('3. GRI Pricing'!$G282>='2. GRI Pricing Inputs'!$T$33,'3. GRI Pricing'!$G282<='2. GRI Pricing Inputs'!$U$33),'2. GRI Pricing Inputs'!$T$32,IF(AND('3. GRI Pricing'!$G282>='2. GRI Pricing Inputs'!$V$33,'3. GRI Pricing'!$G282<='2. GRI Pricing Inputs'!$W$33),'2. GRI Pricing Inputs'!$V$32,IF(AND('3. GRI Pricing'!$G282>='2. GRI Pricing Inputs'!$X$33,'3. GRI Pricing'!$G282<='2. GRI Pricing Inputs'!$Y$33),'2. GRI Pricing Inputs'!$X$32,IF(AND('3. GRI Pricing'!$G282>='2. GRI Pricing Inputs'!$Z$33,'3. GRI Pricing'!$G282<='2. GRI Pricing Inputs'!$AA$33),'2. GRI Pricing Inputs'!$Z$32,IF(AND('3. GRI Pricing'!$G282>='2. GRI Pricing Inputs'!$AB$33,'3. GRI Pricing'!$G282<='2. GRI Pricing Inputs'!$AC$33),'2. GRI Pricing Inputs'!$AB$32,IF(AND('3. GRI Pricing'!$G282>='2. GRI Pricing Inputs'!$AD$33,'3. GRI Pricing'!$G282<='2. GRI Pricing Inputs'!$AE$33),'2. GRI Pricing Inputs'!$AD$32,IF(AND('3. GRI Pricing'!$G282>='2. GRI Pricing Inputs'!$AF$33,'3. GRI Pricing'!$G282<='2. GRI Pricing Inputs'!$AG$33),'2. GRI Pricing Inputs'!$AF$32,IF(AND('3. GRI Pricing'!$G282>='2. GRI Pricing Inputs'!$AH$33,'3. GRI Pricing'!$G282<='2. GRI Pricing Inputs'!$AI$33),'2. GRI Pricing Inputs'!$AH$32,0)))))))))))))))) -> 0 | O282: {=IFERROR(INDEX('2. GRI Pricing Inputs'!$C$32:$AI$39,MATCH('3. GRI Pricing'!E282,'2. GRI Pricing Inputs'!$C$32:$C$39,0),(MATCH('3. GRI Pricing'!N282,'2. GRI Pricing Inputs'!$D$32:$AI$32,0)+1)),0)} -> 0 | P282: =IFERROR(INDEX('2. GRI Pricing Inputs'!$C$45:$AI$46,MATCH($P$16,'2. GRI Pricing Inputs'!$C$45:$C$46,0),MATCH(H282,'2. GRI Pricing Inputs'!$C$45:$AI$45,0)),0) -> 0 | Q282: =IFERROR(INDEX('2. GRI Pricing Inputs'!$C$53:$AI$54,MATCH('3. GRI Pricing'!$Q$16,'2. GRI Pricing Inputs'!$C$53:$C$54,0),MATCH('3. GRI Pricing'!I282,'2. GRI Pricing Inputs'!$C$53:$AI$53,0)),0) -> 0 | R282: =IFERROR(INDEX('2. GRI Pricing Inputs'!$C$60:$AI$61,MATCH('3. GRI Pricing'!$R$16,'2. GRI Pricing Inputs'!$C$60:$C$61,0),MATCH('1. Accomodation'!T286,'2. GRI Pricing Inputs'!$C$60:$AI$60,0)),0) -> 0 | S282: =IFERROR(INDEX('2. GRI Pricing Inputs'!$C$67:$AI$68,MATCH('3. GRI Pricing'!$S$16,'2. GRI Pricing Inputs'!$C$67:$C$68,0),MATCH('1. Accomodation'!U286,'2. GRI Pricing Inputs'!$C$67:$AI$67,0)),0) -> 0 | T282: =IF(E282=0,0,'2. GRI Pricing Inputs'!$AI$75) -> 0 | U282: =IFERROR(INDEX('2. GRI Pricing Inputs'!$C$82:$AI$83,MATCH('3. GRI Pricing'!$U$16,'2. GRI Pricing Inputs'!$C$82:$C$83,0),MATCH('1. Accomodation'!V286,'2. GRI Pricing Inputs'!$C$82:$AI$82,0)),0) -> 0 | V282: =IFERROR(INDEX('2. GRI Pricing Inputs'!$C$89:$AI$90,MATCH('3. GRI Pricing'!$V$16,'2. GRI Pricing Inputs'!$C$89:$C$90,0),MATCH('1. Accomodation'!W286,'2. GRI Pricing Inputs'!$C$89:$AI$89,0)),0) -> 0 | W282: =IFERROR(INDEX('2. GRI Pricing Inputs'!$C$97:$AI$98,MATCH('3. GRI Pricing'!$W$16,'2. GRI Pricing Inputs'!$C$97:$C$98,0),MATCH('1. Accomodation'!X286,'2. GRI Pricing Inputs'!$C$97:$AI$97,0)),0) -> 0 | X282: =IFERROR(INDEX('2. GRI Pricing Inputs'!$C$104:$AI$105,MATCH('3. GRI Pricing'!$X$16,'2. GRI Pricing Inputs'!$C$104:$C$105,0),MATCH('1. Accomodation'!Y286,'2. GRI Pricing Inputs'!$C$104:$AI$104,0)),0) -> 0 | Z282: =L282+M282+O282+P282+Q282+R282+S282+T282+U282+V282+W282+X282+Y282 -> 0 | AD282: =Z282*(1+'2. GRI Pricing Inputs'!E$115)^(($AD$16-$AC$15)/365) -> 0 | AE282: =AD282*(1+'2. GRI Pricing Inputs'!F$115)^((AE$16-AD$16)/365) -> 0 | AF282: =AE282*(1+'2. GRI Pricing Inputs'!G$115)^((AF$16-AE$16)/365) -> 0 | AG282: =AF282*(1+'2. GRI Pricing Inputs'!H$115)^((AG$16-AF$16)/365) -> 0 | AH282: =AG282*(1+'2. GRI Pricing Inputs'!I$115)^((AH$16-AG$16)/365) -> 0 | AI282: =AH282*(1+'2. GRI Pricing Inputs'!J$115)^((AI$16-AH$16)/365) -> 0 | AJ282: =AI282*(1+'2. GRI Pricing Inputs'!K$115)^((AJ$16-AI$16)/365) -> 0 | AK282: =AJ282*(1+'2. GRI Pricing Inputs'!L$115)^((AK$16-AJ$16)/365) -> 0 | AL282: =AK282*(1+'2. GRI Pricing Inputs'!M$115)^((AL$16-AK$16)/365) -> 0 | ... AP282: =AO282*(1+'2. GRI Pricing Inputs'!Q$115)^((AP$16-AO$16)/365) -> 0 | AQ282: =IFERROR(AP282/AD282-1,0) -> 0
C283: ='1. Accomodation'!N287 -> 0 | D283: ='1. Accomodation'!L287 -> [Select] | E283: ='1. Accomodation'!P287 -> [Select] | F283: ='1. Accomodation'!Q287 -> [Select] | G283: ='1. Accomodation'!O287 -> 0 | H283: ='1. Accomodation'!R287 -> [Select] | I283: ='1. Accomodation'!S287 -> [Select] | L283: =IFERROR(INDEX('2. GRI Pricing Inputs'!$C$15:$AI$16,MATCH($L$16,'2. GRI Pricing Inputs'!$C$15:$C$16,0),MATCH(E283,'2. GRI Pricing Inputs'!$C$15:$AI$15,0)),0) -> 0 | M283: =IFERROR(INDEX('2. GRI Pricing Inputs'!$C$22:$AI$23,MATCH($M$16,'2. GRI Pricing Inputs'!$C$22:$C$23,0),MATCH(F283,'2. GRI Pricing Inputs'!$C$22:$AI$22,0)),0) -> 0 | N283: =IF(AND('3. GRI Pricing'!$G283>='2. GRI Pricing Inputs'!$D$33,'3. GRI Pricing'!$G283<='2. GRI Pricing Inputs'!$E$33),'2. GRI Pricing Inputs'!$D$32,IF(AND('3. GRI Pricing'!$G283>='2. GRI Pricing Inputs'!$F$33,'3. GRI Pricing'!$G283<='2. GRI Pricing Inputs'!$G$33),'2. GRI Pricing Inputs'!$F$32,IF(AND('3. GRI Pricing'!$G283>='2. GRI Pricing Inputs'!$H$33,'3. GRI Pricing'!$G283<='2. GRI Pricing Inputs'!$I$33),'2. GRI Pricing Inputs'!$H$32,IF(AND('3. GRI Pricing'!$G283>='2. GRI Pricing Inputs'!$J$33,'3. GRI Pricing'!$G283<='2. GRI Pricing Inputs'!$K$33),'2. GRI Pricing Inputs'!$J$32,IF(AND('3. GRI Pricing'!$G283>='2. GRI Pricing Inputs'!$L$33,'3. GRI Pricing'!$G283<='2. GRI Pricing Inputs'!$M$33),'2. GRI Pricing Inputs'!$L$32,IF(AND('3. GRI Pricing'!$G283>='2. GRI Pricing Inputs'!$N$33,'3. GRI Pricing'!$G283<='2. GRI Pricing Inputs'!$O$33),'2. GRI Pricing Inputs'!$N$32,IF(AND('3. GRI Pricing'!$G283>='2. GRI Pricing Inputs'!$P$33,'3. GRI Pricing'!$G283<='2. GRI Pricing Inputs'!$Q$33),'2. GRI Pricing Inputs'!$P$32,IF(AND('3. GRI Pricing'!$G283>='2. GRI Pricing Inputs'!$R$33,'3. GRI Pricing'!$G283<='2. GRI Pricing Inputs'!$S$33),'2. GRI Pricing Inputs'!$R$32,IF(AND('3. GRI Pricing'!$G283>='2. GRI Pricing Inputs'!$T$33,'3. GRI Pricing'!$G283<='2. GRI Pricing Inputs'!$U$33),'2. GRI Pricing Inputs'!$T$32,IF(AND('3. GRI Pricing'!$G283>='2. GRI Pricing Inputs'!$V$33,'3. GRI Pricing'!$G283<='2. GRI Pricing Inputs'!$W$33),'2. GRI Pricing Inputs'!$V$32,IF(AND('3. GRI Pricing'!$G283>='2. GRI Pricing Inputs'!$X$33,'3. GRI Pricing'!$G283<='2. GRI Pricing Inputs'!$Y$33),'2. GRI Pricing Inputs'!$X$32,IF(AND('3. GRI Pricing'!$G283>='2. GRI Pricing Inputs'!$Z$33,'3. GRI Pricing'!$G283<='2. GRI Pricing Inputs'!$AA$33),'2. GRI Pricing Inputs'!$Z$32,IF(AND('3. GRI Pricing'!$G283>='2. GRI Pricing Inputs'!$AB$33,'3. GRI Pricing'!$G283<='2. GRI Pricing Inputs'!$AC$33),'2. GRI Pricing Inputs'!$AB$32,IF(AND('3. GRI Pricing'!$G283>='2. GRI Pricing Inputs'!$AD$33,'3. GRI Pricing'!$G283<='2. GRI Pricing Inputs'!$AE$33),'2. GRI Pricing Inputs'!$AD$32,IF(AND('3. GRI Pricing'!$G283>='2. GRI Pricing Inputs'!$AF$33,'3. GRI Pricing'!$G283<='2. GRI Pricing Inputs'!$AG$33),'2. GRI Pricing Inputs'!$AF$32,IF(AND('3. GRI Pricing'!$G283>='2. GRI Pricing Inputs'!$AH$33,'3. GRI Pricing'!$G283<='2. GRI Pricing Inputs'!$AI$33),'2. GRI Pricing Inputs'!$AH$32,0)))))))))))))))) -> 0 | O283: {=IFERROR(INDEX('2. GRI Pricing Inputs'!$C$32:$AI$39,MATCH('3. GRI Pricing'!E283,'2. GRI Pricing Inputs'!$C$32:$C$39,0),(MATCH('3. GRI Pricing'!N283,'2. GRI Pricing Inputs'!$D$32:$AI$32,0)+1)),0)} -> 0 | P283: =IFERROR(INDEX('2. GRI Pricing Inputs'!$C$45:$AI$46,MATCH($P$16,'2. GRI Pricing Inputs'!$C$45:$C$46,0),MATCH(H283,'2. GRI Pricing Inputs'!$C$45:$AI$45,0)),0) -> 0 | Q283: =IFERROR(INDEX('2. GRI Pricing Inputs'!$C$53:$AI$54,MATCH('3. GRI Pricing'!$Q$16,'2. GRI Pricing Inputs'!$C$53:$C$54,0),MATCH('3. GRI Pricing'!I283,'2. GRI Pricing Inputs'!$C$53:$AI$53,0)),0) -> 0 | R283: =IFERROR(INDEX('2. GRI Pricing Inputs'!$C$60:$AI$61,MATCH('3. GRI Pricing'!$R$16,'2. GRI Pricing Inputs'!$C$60:$C$61,0),MATCH('1. Accomodation'!T287,'2. GRI Pricing Inputs'!$C$60:$AI$60,0)),0) -> 0 | S283: =IFERROR(INDEX('2. GRI Pricing Inputs'!$C$67:$AI$68,MATCH('3. GRI Pricing'!$S$16,'2. GRI Pricing Inputs'!$C$67:$C$68,0),MATCH('1. Accomodation'!U287,'2. GRI Pricing Inputs'!$C$67:$AI$67,0)),0) -> 0 | T283: =IF(E283=0,0,'2. GRI Pricing Inputs'!$AI$75) -> 0 | U283: =IFERROR(INDEX('2. GRI Pricing Inputs'!$C$82:$AI$83,MATCH('3. GRI Pricing'!$U$16,'2. GRI Pricing Inputs'!$C$82:$C$83,0),MATCH('1. Accomodation'!V287,'2. GRI Pricing Inputs'!$C$82:$AI$82,0)),0) -> 0 | V283: =IFERROR(INDEX('2. GRI Pricing Inputs'!$C$89:$AI$90,MATCH('3. GRI Pricing'!$V$16,'2. GRI Pricing Inputs'!$C$89:$C$90,0),MATCH('1. Accomodation'!W287,'2. GRI Pricing Inputs'!$C$89:$AI$89,0)),0) -> 0 | W283: =IFERROR(INDEX('2. GRI Pricing Inputs'!$C$97:$AI$98,MATCH('3. GRI Pricing'!$W$16,'2. GRI Pricing Inputs'!$C$97:$C$98,0),MATCH('1. Accomodation'!X287,'2. GRI Pricing Inputs'!$C$97:$AI$97,0)),0) -> 0 | X283: =IFERROR(INDEX('2. GRI Pricing Inputs'!$C$104:$AI$105,MATCH('3. GRI Pricing'!$X$16,'2. GRI Pricing Inputs'!$C$104:$C$105,0),MATCH('1. Accomodation'!Y287,'2. GRI Pricing Inputs'!$C$104:$AI$104,0)),0) -> 0 | Z283: =L283+M283+O283+P283+Q283+R283+S283+T283+U283+V283+W283+X283+Y283 -> 0 | AD283: =Z283*(1+'2. GRI Pricing Inputs'!E$115)^(($AD$16-$AC$15)/365) -> 0 | AE283: =AD283*(1+'2. GRI Pricing Inputs'!F$115)^((AE$16-AD$16)/365) -> 0 | AF283: =AE283*(1+'2. GRI Pricing Inputs'!G$115)^((AF$16-AE$16)/365) -> 0 | AG283: =AF283*(1+'2. GRI Pricing Inputs'!H$115)^((AG$16-AF$16)/365) -> 0 | AH283: =AG283*(1+'2. GRI Pricing Inputs'!I$115)^((AH$16-AG$16)/365) -> 0 | AI283: =AH283*(1+'2. GRI Pricing Inputs'!J$115)^((AI$16-AH$16)/365) -> 0 | AJ283: =AI283*(1+'2. GRI Pricing Inputs'!K$115)^((AJ$16-AI$16)/365) -> 0 | AK283: =AJ283*(1+'2. GRI Pricing Inputs'!L$115)^((AK$16-AJ$16)/365) -> 0 | AL283: =AK283*(1+'2. GRI Pricing Inputs'!M$115)^((AL$16-AK$16)/365) -> 0 | ... AP283: =AO283*(1+'2. GRI Pricing Inputs'!Q$115)^((AP$16-AO$16)/365) -> 0 | AQ283: =IFERROR(AP283/AD283-1,0) -> 0
C284: ='1. Accomodation'!N288 -> 0 | D284: ='1. Accomodation'!L288 -> [Select] | E284: ='1. Accomodation'!P288 -> [Select] | F284: ='1. Accomodation'!Q288 -> [Select] | G284: ='1. Accomodation'!O288 -> 0 | H284: ='1. Accomodation'!R288 -> [Select] | I284: ='1. Accomodation'!S288 -> [Select] | L284: =IFERROR(INDEX('2. GRI Pricing Inputs'!$C$15:$AI$16,MATCH($L$16,'2. GRI Pricing Inputs'!$C$15:$C$16,0),MATCH(E284,'2. GRI Pricing Inputs'!$C$15:$AI$15,0)),0) -> 0 | M284: =IFERROR(INDEX('2. GRI Pricing Inputs'!$C$22:$AI$23,MATCH($M$16,'2. GRI Pricing Inputs'!$C$22:$C$23,0),MATCH(F284,'2. GRI Pricing Inputs'!$C$22:$AI$22,0)),0) -> 0 | N284: =IF(AND('3. GRI Pricing'!$G284>='2. GRI Pricing Inputs'!$D$33,'3. GRI Pricing'!$G284<='2. GRI Pricing Inputs'!$E$33),'2. GRI Pricing Inputs'!$D$32,IF(AND('3. GRI Pricing'!$G284>='2. GRI Pricing Inputs'!$F$33,'3. GRI Pricing'!$G284<='2. GRI Pricing Inputs'!$G$33),'2. GRI Pricing Inputs'!$F$32,IF(AND('3. GRI Pricing'!$G284>='2. GRI Pricing Inputs'!$H$33,'3. GRI Pricing'!$G284<='2. GRI Pricing Inputs'!$I$33),'2. GRI Pricing Inputs'!$H$32,IF(AND('3. GRI Pricing'!$G284>='2. GRI Pricing Inputs'!$J$33,'3. GRI Pricing'!$G284<='2. GRI Pricing Inputs'!$K$33),'2. GRI Pricing Inputs'!$J$32,IF(AND('3. GRI Pricing'!$G284>='2. GRI Pricing Inputs'!$L$33,'3. GRI Pricing'!$G284<='2. GRI Pricing Inputs'!$M$33),'2. GRI Pricing Inputs'!$L$32,IF(AND('3. GRI Pricing'!$G284>='2. GRI Pricing Inputs'!$N$33,'3. GRI Pricing'!$G284<='2. GRI Pricing Inputs'!$O$33),'2. GRI Pricing Inputs'!$N$32,IF(AND('3. GRI Pricing'!$G284>='2. GRI Pricing Inputs'!$P$33,'3. GRI Pricing'!$G284<='2. GRI Pricing Inputs'!$Q$33),'2. GRI Pricing Inputs'!$P$32,IF(AND('3. GRI Pricing'!$G284>='2. GRI Pricing Inputs'!$R$33,'3. GRI Pricing'!$G284<='2. GRI Pricing Inputs'!$S$33),'2. GRI Pricing Inputs'!$R$32,IF(AND('3. GRI Pricing'!$G284>='2. GRI Pricing Inputs'!$T$33,'3. GRI Pricing'!$G284<='2. GRI Pricing Inputs'!$U$33),'2. GRI Pricing Inputs'!$T$32,IF(AND('3. GRI Pricing'!$G284>='2. GRI Pricing Inputs'!$V$33,'3. GRI Pricing'!$G284<='2. GRI Pricing Inputs'!$W$33),'2. GRI Pricing Inputs'!$V$32,IF(AND('3. GRI Pricing'!$G284>='2. GRI Pricing Inputs'!$X$33,'3. GRI Pricing'!$G284<='2. GRI Pricing Inputs'!$Y$33),'2. GRI Pricing Inputs'!$X$32,IF(AND('3. GRI Pricing'!$G284>='2. GRI Pricing Inputs'!$Z$33,'3. GRI Pricing'!$G284<='2. GRI Pricing Inputs'!$AA$33),'2. GRI Pricing Inputs'!$Z$32,IF(AND('3. GRI Pricing'!$G284>='2. GRI Pricing Inputs'!$AB$33,'3. GRI Pricing'!$G284<='2. GRI Pricing Inputs'!$AC$33),'2. GRI Pricing Inputs'!$AB$32,IF(AND('3. GRI Pricing'!$G284>='2. GRI Pricing Inputs'!$AD$33,'3. GRI Pricing'!$G284<='2. GRI Pricing Inputs'!$AE$33),'2. GRI Pricing Inputs'!$AD$32,IF(AND('3. GRI Pricing'!$G284>='2. GRI Pricing Inputs'!$AF$33,'3. GRI Pricing'!$G284<='2. GRI Pricing Inputs'!$AG$33),'2. GRI Pricing Inputs'!$AF$32,IF(AND('3. GRI Pricing'!$G284>='2. GRI Pricing Inputs'!$AH$33,'3. GRI Pricing'!$G284<='2. GRI Pricing Inputs'!$AI$33),'2. GRI Pricing Inputs'!$AH$32,0)))))))))))))))) -> 0 | O284: {=IFERROR(INDEX('2. GRI Pricing Inputs'!$C$32:$AI$39,MATCH('3. GRI Pricing'!E284,'2. GRI Pricing Inputs'!$C$32:$C$39,0),(MATCH('3. GRI Pricing'!N284,'2. GRI Pricing Inputs'!$D$32:$AI$32,0)+1)),0)} -> 0 | P284: =IFERROR(INDEX('2. GRI Pricing Inputs'!$C$45:$AI$46,MATCH($P$16,'2. GRI Pricing Inputs'!$C$45:$C$46,0),MATCH(H284,'2. GRI Pricing Inputs'!$C$45:$AI$45,0)),0) -> 0 | Q284: =IFERROR(INDEX('2. GRI Pricing Inputs'!$C$53:$AI$54,MATCH('3. GRI Pricing'!$Q$16,'2. GRI Pricing Inputs'!$C$53:$C$54,0),MATCH('3. GRI Pricing'!I284,'2. GRI Pricing Inputs'!$C$53:$AI$53,0)),0) -> 0 | R284: =IFERROR(INDEX('2. GRI Pricing Inputs'!$C$60:$AI$61,MATCH('3. GRI Pricing'!$R$16,'2. GRI Pricing Inputs'!$C$60:$C$61,0),MATCH('1. Accomodation'!T288,'2. GRI Pricing Inputs'!$C$60:$AI$60,0)),0) -> 0 | S284: =IFERROR(INDEX('2. GRI Pricing Inputs'!$C$67:$AI$68,MATCH('3. GRI Pricing'!$S$16,'2. GRI Pricing Inputs'!$C$67:$C$68,0),MATCH('1. Accomodation'!U288,'2. GRI Pricing Inputs'!$C$67:$AI$67,0)),0) -> 0 | T284: =IF(E284=0,0,'2. GRI Pricing Inputs'!$AI$75) -> 0 | U284: =IFERROR(INDEX('2. GRI Pricing Inputs'!$C$82:$AI$83,MATCH('3. GRI Pricing'!$U$16,'2. GRI Pricing Inputs'!$C$82:$C$83,0),MATCH('1. Accomodation'!V288,'2. GRI Pricing Inputs'!$C$82:$AI$82,0)),0) -> 0 | V284: =IFERROR(INDEX('2. GRI Pricing Inputs'!$C$89:$AI$90,MATCH('3. GRI Pricing'!$V$16,'2. GRI Pricing Inputs'!$C$89:$C$90,0),MATCH('1. Accomodation'!W288,'2. GRI Pricing Inputs'!$C$89:$AI$89,0)),0) -> 0 | W284: =IFERROR(INDEX('2. GRI Pricing Inputs'!$C$97:$AI$98,MATCH('3. GRI Pricing'!$W$16,'2. GRI Pricing Inputs'!$C$97:$C$98,0),MATCH('1. Accomodation'!X288,'2. GRI Pricing Inputs'!$C$97:$AI$97,0)),0) -> 0 | X284: =IFERROR(INDEX('2. GRI Pricing Inputs'!$C$104:$AI$105,MATCH('3. GRI Pricing'!$X$16,'2. GRI Pricing Inputs'!$C$104:$C$105,0),MATCH('1. Accomodation'!Y288,'2. GRI Pricing Inputs'!$C$104:$AI$104,0)),0) -> 0 | Z284: =L284+M284+O284+P284+Q284+R284+S284+T284+U284+V284+W284+X284+Y284 -> 0 | AD284: =Z284*(1+'2. GRI Pricing Inputs'!E$115)^(($AD$16-$AC$15)/365) -> 0 | AE284: =AD284*(1+'2. GRI Pricing Inputs'!F$115)^((AE$16-AD$16)/365) -> 0 | AF284: =AE284*(1+'2. GRI Pricing Inputs'!G$115)^((AF$16-AE$16)/365) -> 0 | AG284: =AF284*(1+'2. GRI Pricing Inputs'!H$115)^((AG$16-AF$16)/365) -> 0 | AH284: =AG284*(1+'2. GRI Pricing Inputs'!I$115)^((AH$16-AG$16)/365) -> 0 | AI284: =AH284*(1+'2. GRI Pricing Inputs'!J$115)^((AI$16-AH$16)/365) -> 0 | AJ284: =AI284*(1+'2. GRI Pricing Inputs'!K$115)^((AJ$16-AI$16)/365) -> 0 | AK284: =AJ284*(1+'2. GRI Pricing Inputs'!L$115)^((AK$16-AJ$16)/365) -> 0 | AL284: =AK284*(1+'2. GRI Pricing Inputs'!M$115)^((AL$16-AK$16)/365) -> 0 | ... AP284: =AO284*(1+'2. GRI Pricing Inputs'!Q$115)^((AP$16-AO$16)/365) -> 0 | AQ284: =IFERROR(AP284/AD284-1,0) -> 0
C285: ='1. Accomodation'!N289 -> 0 | D285: ='1. Accomodation'!L289 -> [Select] | E285: ='1. Accomodation'!P289 -> [Select] | F285: ='1. Accomodation'!Q289 -> [Select] | G285: ='1. Accomodation'!O289 -> 0 | H285: ='1. Accomodation'!R289 -> [Select] | I285: ='1. Accomodation'!S289 -> [Select] | L285: =IFERROR(INDEX('2. GRI Pricing Inputs'!$C$15:$AI$16,MATCH($L$16,'2. GRI Pricing Inputs'!$C$15:$C$16,0),MATCH(E285,'2. GRI Pricing Inputs'!$C$15:$AI$15,0)),0) -> 0 | M285: =IFERROR(INDEX('2. GRI Pricing Inputs'!$C$22:$AI$23,MATCH($M$16,'2. GRI Pricing Inputs'!$C$22:$C$23,0),MATCH(F285,'2. GRI Pricing Inputs'!$C$22:$AI$22,0)),0) -> 0 | N285: =IF(AND('3. GRI Pricing'!$G285>='2. GRI Pricing Inputs'!$D$33,'3. GRI Pricing'!$G285<='2. GRI Pricing Inputs'!$E$33),'2. GRI Pricing Inputs'!$D$32,IF(AND('3. GRI Pricing'!$G285>='2. GRI Pricing Inputs'!$F$33,'3. GRI Pricing'!$G285<='2. GRI Pricing Inputs'!$G$33),'2. GRI Pricing Inputs'!$F$32,IF(AND('3. GRI Pricing'!$G285>='2. GRI Pricing Inputs'!$H$33,'3. GRI Pricing'!$G285<='2. GRI Pricing Inputs'!$I$33),'2. GRI Pricing Inputs'!$H$32,IF(AND('3. GRI Pricing'!$G285>='2. GRI Pricing Inputs'!$J$33,'3. GRI Pricing'!$G285<='2. GRI Pricing Inputs'!$K$33),'2. GRI Pricing Inputs'!$J$32,IF(AND('3. GRI Pricing'!$G285>='2. GRI Pricing Inputs'!$L$33,'3. GRI Pricing'!$G285<='2. GRI Pricing Inputs'!$M$33),'2. GRI Pricing Inputs'!$L$32,IF(AND('3. GRI Pricing'!$G285>='2. GRI Pricing Inputs'!$N$33,'3. GRI Pricing'!$G285<='2. GRI Pricing Inputs'!$O$33),'2. GRI Pricing Inputs'!$N$32,IF(AND('3. GRI Pricing'!$G285>='2. GRI Pricing Inputs'!$P$33,'3. GRI Pricing'!$G285<='2. GRI Pricing Inputs'!$Q$33),'2. GRI Pricing Inputs'!$P$32,IF(AND('3. GRI Pricing'!$G285>='2. GRI Pricing Inputs'!$R$33,'3. GRI Pricing'!$G285<='2. GRI Pricing Inputs'!$S$33),'2. GRI Pricing Inputs'!$R$32,IF(AND('3. GRI Pricing'!$G285>='2. GRI Pricing Inputs'!$T$33,'3. GRI Pricing'!$G285<='2. GRI Pricing Inputs'!$U$33),'2. GRI Pricing Inputs'!$T$32,IF(AND('3. GRI Pricing'!$G285>='2. GRI Pricing Inputs'!$V$33,'3. GRI Pricing'!$G285<='2. GRI Pricing Inputs'!$W$33),'2. GRI Pricing Inputs'!$V$32,IF(AND('3. GRI Pricing'!$G285>='2. GRI Pricing Inputs'!$X$33,'3. GRI Pricing'!$G285<='2. GRI Pricing Inputs'!$Y$33),'2. GRI Pricing Inputs'!$X$32,IF(AND('3. GRI Pricing'!$G285>='2. GRI Pricing Inputs'!$Z$33,'3. GRI Pricing'!$G285<='2. GRI Pricing Inputs'!$AA$33),'2. GRI Pricing Inputs'!$Z$32,IF(AND('3. GRI Pricing'!$G285>='2. GRI Pricing Inputs'!$AB$33,'3. GRI Pricing'!$G285<='2. GRI Pricing Inputs'!$AC$33),'2. GRI Pricing Inputs'!$AB$32,IF(AND('3. GRI Pricing'!$G285>='2. GRI Pricing Inputs'!$AD$33,'3. GRI Pricing'!$G285<='2. GRI Pricing Inputs'!$AE$33),'2. GRI Pricing Inputs'!$AD$32,IF(AND('3. GRI Pricing'!$G285>='2. GRI Pricing Inputs'!$AF$33,'3. GRI Pricing'!$G285<='2. GRI Pricing Inputs'!$AG$33),'2. GRI Pricing Inputs'!$AF$32,IF(AND('3. GRI Pricing'!$G285>='2. GRI Pricing Inputs'!$AH$33,'3. GRI Pricing'!$G285<='2. GRI Pricing Inputs'!$AI$33),'2. GRI Pricing Inputs'!$AH$32,0)))))))))))))))) -> 0 | O285: {=IFERROR(INDEX('2. GRI Pricing Inputs'!$C$32:$AI$39,MATCH('3. GRI Pricing'!E285,'2. GRI Pricing Inputs'!$C$32:$C$39,0),(MATCH('3. GRI Pricing'!N285,'2. GRI Pricing Inputs'!$D$32:$AI$32,0)+1)),0)} -> 0 | P285: =IFERROR(INDEX('2. GRI Pricing Inputs'!$C$45:$AI$46,MATCH($P$16,'2. GRI Pricing Inputs'!$C$45:$C$46,0),MATCH(H285,'2. GRI Pricing Inputs'!$C$45:$AI$45,0)),0) -> 0 | Q285: =IFERROR(INDEX('2. GRI Pricing Inputs'!$C$53:$AI$54,MATCH('3. GRI Pricing'!$Q$16,'2. GRI Pricing Inputs'!$C$53:$C$54,0),MATCH('3. GRI Pricing'!I285,'2. GRI Pricing Inputs'!$C$53:$AI$53,0)),0) -> 0 | R285: =IFERROR(INDEX('2. GRI Pricing Inputs'!$C$60:$AI$61,MATCH('3. GRI Pricing'!$R$16,'2. GRI Pricing Inputs'!$C$60:$C$61,0),MATCH('1. Accomodation'!T289,'2. GRI Pricing Inputs'!$C$60:$AI$60,0)),0) -> 0 | S285: =IFERROR(INDEX('2. GRI Pricing Inputs'!$C$67:$AI$68,MATCH('3. GRI Pricing'!$S$16,'2. GRI Pricing Inputs'!$C$67:$C$68,0),MATCH('1. Accomodation'!U289,'2. GRI Pricing Inputs'!$C$67:$AI$67,0)),0) -> 0 | T285: =IF(E285=0,0,'2. GRI Pricing Inputs'!$AI$75) -> 0 | U285: =IFERROR(INDEX('2. GRI Pricing Inputs'!$C$82:$AI$83,MATCH('3. GRI Pricing'!$U$16,'2. GRI Pricing Inputs'!$C$82:$C$83,0),MATCH('1. Accomodation'!V289,'2. GRI Pricing Inputs'!$C$82:$AI$82,0)),0) -> 0 | V285: =IFERROR(INDEX('2. GRI Pricing Inputs'!$C$89:$AI$90,MATCH('3. GRI Pricing'!$V$16,'2. GRI Pricing Inputs'!$C$89:$C$90,0),MATCH('1. Accomodation'!W289,'2. GRI Pricing Inputs'!$C$89:$AI$89,0)),0) -> 0 | W285: =IFERROR(INDEX('2. GRI Pricing Inputs'!$C$97:$AI$98,MATCH('3. GRI Pricing'!$W$16,'2. GRI Pricing Inputs'!$C$97:$C$98,0),MATCH('1. Accomodation'!X289,'2. GRI Pricing Inputs'!$C$97:$AI$97,0)),0) -> 0 | X285: =IFERROR(INDEX('2. GRI Pricing Inputs'!$C$104:$AI$105,MATCH('3. GRI Pricing'!$X$16,'2. GRI Pricing Inputs'!$C$104:$C$105,0),MATCH('1. Accomodation'!Y289,'2. GRI Pricing Inputs'!$C$104:$AI$104,0)),0) -> 0 | Z285: =L285+M285+O285+P285+Q285+R285+S285+T285+U285+V285+W285+X285+Y285 -> 0 | AD285: =Z285*(1+'2. GRI Pricing Inputs'!E$115)^(($AD$16-$AC$15)/365) -> 0 | AE285: =AD285*(1+'2. GRI Pricing Inputs'!F$115)^((AE$16-AD$16)/365) -> 0 | AF285: =AE285*(1+'2. GRI Pricing Inputs'!G$115)^((AF$16-AE$16)/365) -> 0 | AG285: =AF285*(1+'2. GRI Pricing Inputs'!H$115)^((AG$16-AF$16)/365) -> 0 | AH285: =AG285*(1+'2. GRI Pricing Inputs'!I$115)^((AH$16-AG$16)/365) -> 0 | AI285: =AH285*(1+'2. GRI Pricing Inputs'!J$115)^((AI$16-AH$16)/365) -> 0 | AJ285: =AI285*(1+'2. GRI Pricing Inputs'!K$115)^((AJ$16-AI$16)/365) -> 0 | AK285: =AJ285*(1+'2. GRI Pricing Inputs'!L$115)^((AK$16-AJ$16)/365) -> 0 | AL285: =AK285*(1+'2. GRI Pricing Inputs'!M$115)^((AL$16-AK$16)/365) -> 0 | ... AP285: =AO285*(1+'2. GRI Pricing Inputs'!Q$115)^((AP$16-AO$16)/365) -> 0 | AQ285: =IFERROR(AP285/AD285-1,0) -> 0
C286: ='1. Accomodation'!N290 -> 0 | D286: ='1. Accomodation'!L290 -> [Select] | E286: ='1. Accomodation'!P290 -> [Select] | F286: ='1. Accomodation'!Q290 -> [Select] | G286: ='1. Accomodation'!O290 -> 0 | H286: ='1. Accomodation'!R290 -> [Select] | I286: ='1. Accomodation'!S290 -> [Select] | L286: =IFERROR(INDEX('2. GRI Pricing Inputs'!$C$15:$AI$16,MATCH($L$16,'2. GRI Pricing Inputs'!$C$15:$C$16,0),MATCH(E286,'2. GRI Pricing Inputs'!$C$15:$AI$15,0)),0) -> 0 | M286: =IFERROR(INDEX('2. GRI Pricing Inputs'!$C$22:$AI$23,MATCH($M$16,'2. GRI Pricing Inputs'!$C$22:$C$23,0),MATCH(F286,'2. GRI Pricing Inputs'!$C$22:$AI$22,0)),0) -> 0 | N286: =IF(AND('3. GRI Pricing'!$G286>='2. GRI Pricing Inputs'!$D$33,'3. GRI Pricing'!$G286<='2. GRI Pricing Inputs'!$E$33),'2. GRI Pricing Inputs'!$D$32,IF(AND('3. GRI Pricing'!$G286>='2. GRI Pricing Inputs'!$F$33,'3. GRI Pricing'!$G286<='2. GRI Pricing Inputs'!$G$33),'2. GRI Pricing Inputs'!$F$32,IF(AND('3. GRI Pricing'!$G286>='2. GRI Pricing Inputs'!$H$33,'3. GRI Pricing'!$G286<='2. GRI Pricing Inputs'!$I$33),'2. GRI Pricing Inputs'!$H$32,IF(AND('3. GRI Pricing'!$G286>='2. GRI Pricing Inputs'!$J$33,'3. GRI Pricing'!$G286<='2. GRI Pricing Inputs'!$K$33),'2. GRI Pricing Inputs'!$J$32,IF(AND('3. GRI Pricing'!$G286>='2. GRI Pricing Inputs'!$L$33,'3. GRI Pricing'!$G286<='2. GRI Pricing Inputs'!$M$33),'2. GRI Pricing Inputs'!$L$32,IF(AND('3. GRI Pricing'!$G286>='2. GRI Pricing Inputs'!$N$33,'3. GRI Pricing'!$G286<='2. GRI Pricing Inputs'!$O$33),'2. GRI Pricing Inputs'!$N$32,IF(AND('3. GRI Pricing'!$G286>='2. GRI Pricing Inputs'!$P$33,'3. GRI Pricing'!$G286<='2. GRI Pricing Inputs'!$Q$33),'2. GRI Pricing Inputs'!$P$32,IF(AND('3. GRI Pricing'!$G286>='2. GRI Pricing Inputs'!$R$33,'3. GRI Pricing'!$G286<='2. GRI Pricing Inputs'!$S$33),'2. GRI Pricing Inputs'!$R$32,IF(AND('3. GRI Pricing'!$G286>='2. GRI Pricing Inputs'!$T$33,'3. GRI Pricing'!$G286<='2. GRI Pricing Inputs'!$U$33),'2. GRI Pricing Inputs'!$T$32,IF(AND('3. GRI Pricing'!$G286>='2. GRI Pricing Inputs'!$V$33,'3. GRI Pricing'!$G286<='2. GRI Pricing Inputs'!$W$33),'2. GRI Pricing Inputs'!$V$32,IF(AND('3. GRI Pricing'!$G286>='2. GRI Pricing Inputs'!$X$33,'3. GRI Pricing'!$G286<='2. GRI Pricing Inputs'!$Y$33),'2. GRI Pricing Inputs'!$X$32,IF(AND('3. GRI Pricing'!$G286>='2. GRI Pricing Inputs'!$Z$33,'3. GRI Pricing'!$G286<='2. GRI Pricing Inputs'!$AA$33),'2. GRI Pricing Inputs'!$Z$32,IF(AND('3. GRI Pricing'!$G286>='2. GRI Pricing Inputs'!$AB$33,'3. GRI Pricing'!$G286<='2. GRI Pricing Inputs'!$AC$33),'2. GRI Pricing Inputs'!$AB$32,IF(AND('3. GRI Pricing'!$G286>='2. GRI Pricing Inputs'!$AD$33,'3. GRI Pricing'!$G286<='2. GRI Pricing Inputs'!$AE$33),'2. GRI Pricing Inputs'!$AD$32,IF(AND('3. GRI Pricing'!$G286>='2. GRI Pricing Inputs'!$AF$33,'3. GRI Pricing'!$G286<='2. GRI Pricing Inputs'!$AG$33),'2. GRI Pricing Inputs'!$AF$32,IF(AND('3. GRI Pricing'!$G286>='2. GRI Pricing Inputs'!$AH$33,'3. GRI Pricing'!$G286<='2. GRI Pricing Inputs'!$AI$33),'2. GRI Pricing Inputs'!$AH$32,0)))))))))))))))) -> 0 | O286: {=IFERROR(INDEX('2. GRI Pricing Inputs'!$C$32:$AI$39,MATCH('3. GRI Pricing'!E286,'2. GRI Pricing Inputs'!$C$32:$C$39,0),(MATCH('3. GRI Pricing'!N286,'2. GRI Pricing Inputs'!$D$32:$AI$32,0)+1)),0)} -> 0 | P286: =IFERROR(INDEX('2. GRI Pricing Inputs'!$C$45:$AI$46,MATCH($P$16,'2. GRI Pricing Inputs'!$C$45:$C$46,0),MATCH(H286,'2. GRI Pricing Inputs'!$C$45:$AI$45,0)),0) -> 0 | Q286: =IFERROR(INDEX('2. GRI Pricing Inputs'!$C$53:$AI$54,MATCH('3. GRI Pricing'!$Q$16,'2. GRI Pricing Inputs'!$C$53:$C$54,0),MATCH('3. GRI Pricing'!I286,'2. GRI Pricing Inputs'!$C$53:$AI$53,0)),0) -> 0 | R286: =IFERROR(INDEX('2. GRI Pricing Inputs'!$C$60:$AI$61,MATCH('3. GRI Pricing'!$R$16,'2. GRI Pricing Inputs'!$C$60:$C$61,0),MATCH('1. Accomodation'!T290,'2. GRI Pricing Inputs'!$C$60:$AI$60,0)),0) -> 0 | S286: =IFERROR(INDEX('2. GRI Pricing Inputs'!$C$67:$AI$68,MATCH('3. GRI Pricing'!$S$16,'2. GRI Pricing Inputs'!$C$67:$C$68,0),MATCH('1. Accomodation'!U290,'2. GRI Pricing Inputs'!$C$67:$AI$67,0)),0) -> 0 | T286: =IF(E286=0,0,'2. GRI Pricing Inputs'!$AI$75) -> 0 | U286: =IFERROR(INDEX('2. GRI Pricing Inputs'!$C$82:$AI$83,MATCH('3. GRI Pricing'!$U$16,'2. GRI Pricing Inputs'!$C$82:$C$83,0),MATCH('1. Accomodation'!V290,'2. GRI Pricing Inputs'!$C$82:$AI$82,0)),0) -> 0 | V286: =IFERROR(INDEX('2. GRI Pricing Inputs'!$C$89:$AI$90,MATCH('3. GRI Pricing'!$V$16,'2. GRI Pricing Inputs'!$C$89:$C$90,0),MATCH('1. Accomodation'!W290,'2. GRI Pricing Inputs'!$C$89:$AI$89,0)),0) -> 0 | W286: =IFERROR(INDEX('2. GRI Pricing Inputs'!$C$97:$AI$98,MATCH('3. GRI Pricing'!$W$16,'2. GRI Pricing Inputs'!$C$97:$C$98,0),MATCH('1. Accomodation'!X290,'2. GRI Pricing Inputs'!$C$97:$AI$97,0)),0) -> 0 | X286: =IFERROR(INDEX('2. GRI Pricing Inputs'!$C$104:$AI$105,MATCH('3. GRI Pricing'!$X$16,'2. GRI Pricing Inputs'!$C$104:$C$105,0),MATCH('1. Accomodation'!Y290,'2. GRI Pricing Inputs'!$C$104:$AI$104,0)),0) -> 0 | Z286: =L286+M286+O286+P286+Q286+R286+S286+T286+U286+V286+W286+X286+Y286 -> 0 | AD286: =Z286*(1+'2. GRI Pricing Inputs'!E$115)^(($AD$16-$AC$15)/365) -> 0 | AE286: =AD286*(1+'2. GRI Pricing Inputs'!F$115)^((AE$16-AD$16)/365) -> 0 | AF286: =AE286*(1+'2. GRI Pricing Inputs'!G$115)^((AF$16-AE$16)/365) -> 0 | AG286: =AF286*(1+'2. GRI Pricing Inputs'!H$115)^((AG$16-AF$16)/365) -> 0 | AH286: =AG286*(1+'2. GRI Pricing Inputs'!I$115)^((AH$16-AG$16)/365) -> 0 | AI286: =AH286*(1+'2. GRI Pricing Inputs'!J$115)^((AI$16-AH$16)/365) -> 0 | AJ286: =AI286*(1+'2. GRI Pricing Inputs'!K$115)^((AJ$16-AI$16)/365) -> 0 | AK286: =AJ286*(1+'2. GRI Pricing Inputs'!L$115)^((AK$16-AJ$16)/365) -> 0 | AL286: =AK286*(1+'2. GRI Pricing Inputs'!M$115)^((AL$16-AK$16)/365) -> 0 | ... AP286: =AO286*(1+'2. GRI Pricing Inputs'!Q$115)^((AP$16-AO$16)/365) -> 0 | AQ286: =IFERROR(AP286/AD286-1,0) -> 0
C287: ='1. Accomodation'!N291 -> 0 | D287: ='1. Accomodation'!L291 -> [Select] | E287: ='1. Accomodation'!P291 -> [Select] | F287: ='1. Accomodation'!Q291 -> [Select] | G287: ='1. Accomodation'!O291 -> 0 | H287: ='1. Accomodation'!R291 -> [Select] | I287: ='1. Accomodation'!S291 -> [Select] | L287: =IFERROR(INDEX('2. GRI Pricing Inputs'!$C$15:$AI$16,MATCH($L$16,'2. GRI Pricing Inputs'!$C$15:$C$16,0),MATCH(E287,'2. GRI Pricing Inputs'!$C$15:$AI$15,0)),0) -> 0 | M287: =IFERROR(INDEX('2. GRI Pricing Inputs'!$C$22:$AI$23,MATCH($M$16,'2. GRI Pricing Inputs'!$C$22:$C$23,0),MATCH(F287,'2. GRI Pricing Inputs'!$C$22:$AI$22,0)),0) -> 0 | N287: =IF(AND('3. GRI Pricing'!$G287>='2. GRI Pricing Inputs'!$D$33,'3. GRI Pricing'!$G287<='2. GRI Pricing Inputs'!$E$33),'2. GRI Pricing Inputs'!$D$32,IF(AND('3. GRI Pricing'!$G287>='2. GRI Pricing Inputs'!$F$33,'3. GRI Pricing'!$G287<='2. GRI Pricing Inputs'!$G$33),'2. GRI Pricing Inputs'!$F$32,IF(AND('3. GRI Pricing'!$G287>='2. GRI Pricing Inputs'!$H$33,'3. GRI Pricing'!$G287<='2. GRI Pricing Inputs'!$I$33),'2. GRI Pricing Inputs'!$H$32,IF(AND('3. GRI Pricing'!$G287>='2. GRI Pricing Inputs'!$J$33,'3. GRI Pricing'!$G287<='2. GRI Pricing Inputs'!$K$33),'2. GRI Pricing Inputs'!$J$32,IF(AND('3. GRI Pricing'!$G287>='2. GRI Pricing Inputs'!$L$33,'3. GRI Pricing'!$G287<='2. GRI Pricing Inputs'!$M$33),'2. GRI Pricing Inputs'!$L$32,IF(AND('3. GRI Pricing'!$G287>='2. GRI Pricing Inputs'!$N$33,'3. GRI Pricing'!$G287<='2. GRI Pricing Inputs'!$O$33),'2. GRI Pricing Inputs'!$N$32,IF(AND('3. GRI Pricing'!$G287>='2. GRI Pricing Inputs'!$P$33,'3. GRI Pricing'!$G287<='2. GRI Pricing Inputs'!$Q$33),'2. GRI Pricing Inputs'!$P$32,IF(AND('3. GRI Pricing'!$G287>='2. GRI Pricing Inputs'!$R$33,'3. GRI Pricing'!$G287<='2. GRI Pricing Inputs'!$S$33),'2. GRI Pricing Inputs'!$R$32,IF(AND('3. GRI Pricing'!$G287>='2. GRI Pricing Inputs'!$T$33,'3. GRI Pricing'!$G287<='2. GRI Pricing Inputs'!$U$33),'2. GRI Pricing Inputs'!$T$32,IF(AND('3. GRI Pricing'!$G287>='2. GRI Pricing Inputs'!$V$33,'3. GRI Pricing'!$G287<='2. GRI Pricing Inputs'!$W$33),'2. GRI Pricing Inputs'!$V$32,IF(AND('3. GRI Pricing'!$G287>='2. GRI Pricing Inputs'!$X$33,'3. GRI Pricing'!$G287<='2. GRI Pricing Inputs'!$Y$33),'2. GRI Pricing Inputs'!$X$32,IF(AND('3. GRI Pricing'!$G287>='2. GRI Pricing Inputs'!$Z$33,'3. GRI Pricing'!$G287<='2. GRI Pricing Inputs'!$AA$33),'2. GRI Pricing Inputs'!$Z$32,IF(AND('3. GRI Pricing'!$G287>='2. GRI Pricing Inputs'!$AB$33,'3. GRI Pricing'!$G287<='2. GRI Pricing Inputs'!$AC$33),'2. GRI Pricing Inputs'!$AB$32,IF(AND('3. GRI Pricing'!$G287>='2. GRI Pricing Inputs'!$AD$33,'3. GRI Pricing'!$G287<='2. GRI Pricing Inputs'!$AE$33),'2. GRI Pricing Inputs'!$AD$32,IF(AND('3. GRI Pricing'!$G287>='2. GRI Pricing Inputs'!$AF$33,'3. GRI Pricing'!$G287<='2. GRI Pricing Inputs'!$AG$33),'2. GRI Pricing Inputs'!$AF$32,IF(AND('3. GRI Pricing'!$G287>='2. GRI Pricing Inputs'!$AH$33,'3. GRI Pricing'!$G287<='2. GRI Pricing Inputs'!$AI$33),'2. GRI Pricing Inputs'!$AH$32,0)))))))))))))))) -> 0 | O287: {=IFERROR(INDEX('2. GRI Pricing Inputs'!$C$32:$AI$39,MATCH('3. GRI Pricing'!E287,'2. GRI Pricing Inputs'!$C$32:$C$39,0),(MATCH('3. GRI Pricing'!N287,'2. GRI Pricing Inputs'!$D$32:$AI$32,0)+1)),0)} -> 0 | P287: =IFERROR(INDEX('2. GRI Pricing Inputs'!$C$45:$AI$46,MATCH($P$16,'2. GRI Pricing Inputs'!$C$45:$C$46,0),MATCH(H287,'2. GRI Pricing Inputs'!$C$45:$AI$45,0)),0) -> 0 | Q287: =IFERROR(INDEX('2. GRI Pricing Inputs'!$C$53:$AI$54,MATCH('3. GRI Pricing'!$Q$16,'2. GRI Pricing Inputs'!$C$53:$C$54,0),MATCH('3. GRI Pricing'!I287,'2. GRI Pricing Inputs'!$C$53:$AI$53,0)),0) -> 0 | R287: =IFERROR(INDEX('2. GRI Pricing Inputs'!$C$60:$AI$61,MATCH('3. GRI Pricing'!$R$16,'2. GRI Pricing Inputs'!$C$60:$C$61,0),MATCH('1. Accomodation'!T291,'2. GRI Pricing Inputs'!$C$60:$AI$60,0)),0) -> 0 | S287: =IFERROR(INDEX('2. GRI Pricing Inputs'!$C$67:$AI$68,MATCH('3. GRI Pricing'!$S$16,'2. GRI Pricing Inputs'!$C$67:$C$68,0),MATCH('1. Accomodation'!U291,'2. GRI Pricing Inputs'!$C$67:$AI$67,0)),0) -> 0 | T287: =IF(E287=0,0,'2. GRI Pricing Inputs'!$AI$75) -> 0 | U287: =IFERROR(INDEX('2. GRI Pricing Inputs'!$C$82:$AI$83,MATCH('3. GRI Pricing'!$U$16,'2. GRI Pricing Inputs'!$C$82:$C$83,0),MATCH('1. Accomodation'!V291,'2. GRI Pricing Inputs'!$C$82:$AI$82,0)),0) -> 0 | V287: =IFERROR(INDEX('2. GRI Pricing Inputs'!$C$89:$AI$90,MATCH('3. GRI Pricing'!$V$16,'2. GRI Pricing Inputs'!$C$89:$C$90,0),MATCH('1. Accomodation'!W291,'2. GRI Pricing Inputs'!$C$89:$AI$89,0)),0) -> 0 | W287: =IFERROR(INDEX('2. GRI Pricing Inputs'!$C$97:$AI$98,MATCH('3. GRI Pricing'!$W$16,'2. GRI Pricing Inputs'!$C$97:$C$98,0),MATCH('1. Accomodation'!X291,'2. GRI Pricing Inputs'!$C$97:$AI$97,0)),0) -> 0 | X287: =IFERROR(INDEX('2. GRI Pricing Inputs'!$C$104:$AI$105,MATCH('3. GRI Pricing'!$X$16,'2. GRI Pricing Inputs'!$C$104:$C$105,0),MATCH('1. Accomodation'!Y291,'2. GRI Pricing Inputs'!$C$104:$AI$104,0)),0) -> 0 | Z287: =L287+M287+O287+P287+Q287+R287+S287+T287+U287+V287+W287+X287+Y287 -> 0 | AD287: =Z287*(1+'2. GRI Pricing Inputs'!E$115)^(($AD$16-$AC$15)/365) -> 0 | AE287: =AD287*(1+'2. GRI Pricing Inputs'!F$115)^((AE$16-AD$16)/365) -> 0 | AF287: =AE287*(1+'2. GRI Pricing Inputs'!G$115)^((AF$16-AE$16)/365) -> 0 | AG287: =AF287*(1+'2. GRI Pricing Inputs'!H$115)^((AG$16-AF$16)/365) -> 0 | AH287: =AG287*(1+'2. GRI Pricing Inputs'!I$115)^((AH$16-AG$16)/365) -> 0 | AI287: =AH287*(1+'2. GRI Pricing Inputs'!J$115)^((AI$16-AH$16)/365) -> 0 | AJ287: =AI287*(1+'2. GRI Pricing Inputs'!K$115)^((AJ$16-AI$16)/365) -> 0 | AK287: =AJ287*(1+'2. GRI Pricing Inputs'!L$115)^((AK$16-AJ$16)/365) -> 0 | AL287: =AK287*(1+'2. GRI Pricing Inputs'!M$115)^((AL$16-AK$16)/365) -> 0 | ... AP287: =AO287*(1+'2. GRI Pricing Inputs'!Q$115)^((AP$16-AO$16)/365) -> 0 | AQ287: =IFERROR(AP287/AD287-1,0) -> 0
C288: ='1. Accomodation'!N292 -> 0 | D288: ='1. Accomodation'!L292 -> [Select] | E288: ='1. Accomodation'!P292 -> [Select] | F288: ='1. Accomodation'!Q292 -> [Select] | G288: ='1. Accomodation'!O292 -> 0 | H288: ='1. Accomodation'!R292 -> [Select] | I288: ='1. Accomodation'!S292 -> [Select] | L288: =IFERROR(INDEX('2. GRI Pricing Inputs'!$C$15:$AI$16,MATCH($L$16,'2. GRI Pricing Inputs'!$C$15:$C$16,0),MATCH(E288,'2. GRI Pricing Inputs'!$C$15:$AI$15,0)),0) -> 0 | M288: =IFERROR(INDEX('2. GRI Pricing Inputs'!$C$22:$AI$23,MATCH($M$16,'2. GRI Pricing Inputs'!$C$22:$C$23,0),MATCH(F288,'2. GRI Pricing Inputs'!$C$22:$AI$22,0)),0) -> 0 | N288: =IF(AND('3. GRI Pricing'!$G288>='2. GRI Pricing Inputs'!$D$33,'3. GRI Pricing'!$G288<='2. GRI Pricing Inputs'!$E$33),'2. GRI Pricing Inputs'!$D$32,IF(AND('3. GRI Pricing'!$G288>='2. GRI Pricing Inputs'!$F$33,'3. GRI Pricing'!$G288<='2. GRI Pricing Inputs'!$G$33),'2. GRI Pricing Inputs'!$F$32,IF(AND('3. GRI Pricing'!$G288>='2. GRI Pricing Inputs'!$H$33,'3. GRI Pricing'!$G288<='2. GRI Pricing Inputs'!$I$33),'2. GRI Pricing Inputs'!$H$32,IF(AND('3. GRI Pricing'!$G288>='2. GRI Pricing Inputs'!$J$33,'3. GRI Pricing'!$G288<='2. GRI Pricing Inputs'!$K$33),'2. GRI Pricing Inputs'!$J$32,IF(AND('3. GRI Pricing'!$G288>='2. GRI Pricing Inputs'!$L$33,'3. GRI Pricing'!$G288<='2. GRI Pricing Inputs'!$M$33),'2. GRI Pricing Inputs'!$L$32,IF(AND('3. GRI Pricing'!$G288>='2. GRI Pricing Inputs'!$N$33,'3. GRI Pricing'!$G288<='2. GRI Pricing Inputs'!$O$33),'2. GRI Pricing Inputs'!$N$32,IF(AND('3. GRI Pricing'!$G288>='2. GRI Pricing Inputs'!$P$33,'3. GRI Pricing'!$G288<='2. GRI Pricing Inputs'!$Q$33),'2. GRI Pricing Inputs'!$P$32,IF(AND('3. GRI Pricing'!$G288>='2. GRI Pricing Inputs'!$R$33,'3. GRI Pricing'!$G288<='2. GRI Pricing Inputs'!$S$33),'2. GRI Pricing Inputs'!$R$32,IF(AND('3. GRI Pricing'!$G288>='2. GRI Pricing Inputs'!$T$33,'3. GRI Pricing'!$G288<='2. GRI Pricing Inputs'!$U$33),'2. GRI Pricing Inputs'!$T$32,IF(AND('3. GRI Pricing'!$G288>='2. GRI Pricing Inputs'!$V$33,'3. GRI Pricing'!$G288<='2. GRI Pricing Inputs'!$W$33),'2. GRI Pricing Inputs'!$V$32,IF(AND('3. GRI Pricing'!$G288>='2. GRI Pricing Inputs'!$X$33,'3. GRI Pricing'!$G288<='2. GRI Pricing Inputs'!$Y$33),'2. GRI Pricing Inputs'!$X$32,IF(AND('3. GRI Pricing'!$G288>='2. GRI Pricing Inputs'!$Z$33,'3. GRI Pricing'!$G288<='2. GRI Pricing Inputs'!$AA$33),'2. GRI Pricing Inputs'!$Z$32,IF(AND('3. GRI Pricing'!$G288>='2. GRI Pricing Inputs'!$AB$33,'3. GRI Pricing'!$G288<='2. GRI Pricing Inputs'!$AC$33),'2. GRI Pricing Inputs'!$AB$32,IF(AND('3. GRI Pricing'!$G288>='2. GRI Pricing Inputs'!$AD$33,'3. GRI Pricing'!$G288<='2. GRI Pricing Inputs'!$AE$33),'2. GRI Pricing Inputs'!$AD$32,IF(AND('3. GRI Pricing'!$G288>='2. GRI Pricing Inputs'!$AF$33,'3. GRI Pricing'!$G288<='2. GRI Pricing Inputs'!$AG$33),'2. GRI Pricing Inputs'!$AF$32,IF(AND('3. GRI Pricing'!$G288>='2. GRI Pricing Inputs'!$AH$33,'3. GRI Pricing'!$G288<='2. GRI Pricing Inputs'!$AI$33),'2. GRI Pricing Inputs'!$AH$32,0)))))))))))))))) -> 0 | O288: {=IFERROR(INDEX('2. GRI Pricing Inputs'!$C$32:$AI$39,MATCH('3. GRI Pricing'!E288,'2. GRI Pricing Inputs'!$C$32:$C$39,0),(MATCH('3. GRI Pricing'!N288,'2. GRI Pricing Inputs'!$D$32:$AI$32,0)+1)),0)} -> 0 | P288: =IFERROR(INDEX('2. GRI Pricing Inputs'!$C$45:$AI$46,MATCH($P$16,'2. GRI Pricing Inputs'!$C$45:$C$46,0),MATCH(H288,'2. GRI Pricing Inputs'!$C$45:$AI$45,0)),0) -> 0 | Q288: =IFERROR(INDEX('2. GRI Pricing Inputs'!$C$53:$AI$54,MATCH('3. GRI Pricing'!$Q$16,'2. GRI Pricing Inputs'!$C$53:$C$54,0),MATCH('3. GRI Pricing'!I288,'2. GRI Pricing Inputs'!$C$53:$AI$53,0)),0) -> 0 | R288: =IFERROR(INDEX('2. GRI Pricing Inputs'!$C$60:$AI$61,MATCH('3. GRI Pricing'!$R$16,'2. GRI Pricing Inputs'!$C$60:$C$61,0),MATCH('1. Accomodation'!T292,'2. GRI Pricing Inputs'!$C$60:$AI$60,0)),0) -> 0 | S288: =IFERROR(INDEX('2. GRI Pricing Inputs'!$C$67:$AI$68,MATCH('3. GRI Pricing'!$S$16,'2. GRI Pricing Inputs'!$C$67:$C$68,0),MATCH('1. Accomodation'!U292,'2. GRI Pricing Inputs'!$C$67:$AI$67,0)),0) -> 0 | T288: =IF(E288=0,0,'2. GRI Pricing Inputs'!$AI$75) -> 0 | U288: =IFERROR(INDEX('2. GRI Pricing Inputs'!$C$82:$AI$83,MATCH('3. GRI Pricing'!$U$16,'2. GRI Pricing Inputs'!$C$82:$C$83,0),MATCH('1. Accomodation'!V292,'2. GRI Pricing Inputs'!$C$82:$AI$82,0)),0) -> 0 | V288: =IFERROR(INDEX('2. GRI Pricing Inputs'!$C$89:$AI$90,MATCH('3. GRI Pricing'!$V$16,'2. GRI Pricing Inputs'!$C$89:$C$90,0),MATCH('1. Accomodation'!W292,'2. GRI Pricing Inputs'!$C$89:$AI$89,0)),0) -> 0 | W288: =IFERROR(INDEX('2. GRI Pricing Inputs'!$C$97:$AI$98,MATCH('3. GRI Pricing'!$W$16,'2. GRI Pricing Inputs'!$C$97:$C$98,0),MATCH('1. Accomodation'!X292,'2. GRI Pricing Inputs'!$C$97:$AI$97,0)),0) -> 0 | X288: =IFERROR(INDEX('2. GRI Pricing Inputs'!$C$104:$AI$105,MATCH('3. GRI Pricing'!$X$16,'2. GRI Pricing Inputs'!$C$104:$C$105,0),MATCH('1. Accomodation'!Y292,'2. GRI Pricing Inputs'!$C$104:$AI$104,0)),0) -> 0 | Z288: =L288+M288+O288+P288+Q288+R288+S288+T288+U288+V288+W288+X288+Y288 -> 0 | AD288: =Z288*(1+'2. GRI Pricing Inputs'!E$115)^(($AD$16-$AC$15)/365) -> 0 | AE288: =AD288*(1+'2. GRI Pricing Inputs'!F$115)^((AE$16-AD$16)/365) -> 0 | AF288: =AE288*(1+'2. GRI Pricing Inputs'!G$115)^((AF$16-AE$16)/365) -> 0 | AG288: =AF288*(1+'2. GRI Pricing Inputs'!H$115)^((AG$16-AF$16)/365) -> 0 | AH288: =AG288*(1+'2. GRI Pricing Inputs'!I$115)^((AH$16-AG$16)/365) -> 0 | AI288: =AH288*(1+'2. GRI Pricing Inputs'!J$115)^((AI$16-AH$16)/365) -> 0 | AJ288: =AI288*(1+'2. GRI Pricing Inputs'!K$115)^((AJ$16-AI$16)/365) -> 0 | AK288: =AJ288*(1+'2. GRI Pricing Inputs'!L$115)^((AK$16-AJ$16)/365) -> 0 | AL288: =AK288*(1+'2. GRI Pricing Inputs'!M$115)^((AL$16-AK$16)/365) -> 0 | ... AP288: =AO288*(1+'2. GRI Pricing Inputs'!Q$115)^((AP$16-AO$16)/365) -> 0 | AQ288: =IFERROR(AP288/AD288-1,0) -> 0
C289: ='1. Accomodation'!N293 -> 0 | D289: ='1. Accomodation'!L293 -> [Select] | E289: ='1. Accomodation'!P293 -> [Select] | F289: ='1. Accomodation'!Q293 -> [Select] | G289: ='1. Accomodation'!O293 -> 0 | H289: ='1. Accomodation'!R293 -> [Select] | I289: ='1. Accomodation'!S293 -> [Select] | L289: =IFERROR(INDEX('2. GRI Pricing Inputs'!$C$15:$AI$16,MATCH($L$16,'2. GRI Pricing Inputs'!$C$15:$C$16,0),MATCH(E289,'2. GRI Pricing Inputs'!$C$15:$AI$15,0)),0) -> 0 | M289: =IFERROR(INDEX('2. GRI Pricing Inputs'!$C$22:$AI$23,MATCH($M$16,'2. GRI Pricing Inputs'!$C$22:$C$23,0),MATCH(F289,'2. GRI Pricing Inputs'!$C$22:$AI$22,0)),0) -> 0 | N289: =IF(AND('3. GRI Pricing'!$G289>='2. GRI Pricing Inputs'!$D$33,'3. GRI Pricing'!$G289<='2. GRI Pricing Inputs'!$E$33),'2. GRI Pricing Inputs'!$D$32,IF(AND('3. GRI Pricing'!$G289>='2. GRI Pricing Inputs'!$F$33,'3. GRI Pricing'!$G289<='2. GRI Pricing Inputs'!$G$33),'2. GRI Pricing Inputs'!$F$32,IF(AND('3. GRI Pricing'!$G289>='2. GRI Pricing Inputs'!$H$33,'3. GRI Pricing'!$G289<='2. GRI Pricing Inputs'!$I$33),'2. GRI Pricing Inputs'!$H$32,IF(AND('3. GRI Pricing'!$G289>='2. GRI Pricing Inputs'!$J$33,'3. GRI Pricing'!$G289<='2. GRI Pricing Inputs'!$K$33),'2. GRI Pricing Inputs'!$J$32,IF(AND('3. GRI Pricing'!$G289>='2. GRI Pricing Inputs'!$L$33,'3. GRI Pricing'!$G289<='2. GRI Pricing Inputs'!$M$33),'2. GRI Pricing Inputs'!$L$32,IF(AND('3. GRI Pricing'!$G289>='2. GRI Pricing Inputs'!$N$33,'3. GRI Pricing'!$G289<='2. GRI Pricing Inputs'!$O$33),'2. GRI Pricing Inputs'!$N$32,IF(AND('3. GRI Pricing'!$G289>='2. GRI Pricing Inputs'!$P$33,'3. GRI Pricing'!$G289<='2. GRI Pricing Inputs'!$Q$33),'2. GRI Pricing Inputs'!$P$32,IF(AND('3. GRI Pricing'!$G289>='2. GRI Pricing Inputs'!$R$33,'3. GRI Pricing'!$G289<='2. GRI Pricing Inputs'!$S$33),'2. GRI Pricing Inputs'!$R$32,IF(AND('3. GRI Pricing'!$G289>='2. GRI Pricing Inputs'!$T$33,'3. GRI Pricing'!$G289<='2. GRI Pricing Inputs'!$U$33),'2. GRI Pricing Inputs'!$T$32,IF(AND('3. GRI Pricing'!$G289>='2. GRI Pricing Inputs'!$V$33,'3. GRI Pricing'!$G289<='2. GRI Pricing Inputs'!$W$33),'2. GRI Pricing Inputs'!$V$32,IF(AND('3. GRI Pricing'!$G289>='2. GRI Pricing Inputs'!$X$33,'3. GRI Pricing'!$G289<='2. GRI Pricing Inputs'!$Y$33),'2. GRI Pricing Inputs'!$X$32,IF(AND('3. GRI Pricing'!$G289>='2. GRI Pricing Inputs'!$Z$33,'3. GRI Pricing'!$G289<='2. GRI Pricing Inputs'!$AA$33),'2. GRI Pricing Inputs'!$Z$32,IF(AND('3. GRI Pricing'!$G289>='2. GRI Pricing Inputs'!$AB$33,'3. GRI Pricing'!$G289<='2. GRI Pricing Inputs'!$AC$33),'2. GRI Pricing Inputs'!$AB$32,IF(AND('3. GRI Pricing'!$G289>='2. GRI Pricing Inputs'!$AD$33,'3. GRI Pricing'!$G289<='2. GRI Pricing Inputs'!$AE$33),'2. GRI Pricing Inputs'!$AD$32,IF(AND('3. GRI Pricing'!$G289>='2. GRI Pricing Inputs'!$AF$33,'3. GRI Pricing'!$G289<='2. GRI Pricing Inputs'!$AG$33),'2. GRI Pricing Inputs'!$AF$32,IF(AND('3. GRI Pricing'!$G289>='2. GRI Pricing Inputs'!$AH$33,'3. GRI Pricing'!$G289<='2. GRI Pricing Inputs'!$AI$33),'2. GRI Pricing Inputs'!$AH$32,0)))))))))))))))) -> 0 | O289: {=IFERROR(INDEX('2. GRI Pricing Inputs'!$C$32:$AI$39,MATCH('3. GRI Pricing'!E289,'2. GRI Pricing Inputs'!$C$32:$C$39,0),(MATCH('3. GRI Pricing'!N289,'2. GRI Pricing Inputs'!$D$32:$AI$32,0)+1)),0)} -> 0 | P289: =IFERROR(INDEX('2. GRI Pricing Inputs'!$C$45:$AI$46,MATCH($P$16,'2. GRI Pricing Inputs'!$C$45:$C$46,0),MATCH(H289,'2. GRI Pricing Inputs'!$C$45:$AI$45,0)),0) -> 0 | Q289: =IFERROR(INDEX('2. GRI Pricing Inputs'!$C$53:$AI$54,MATCH('3. GRI Pricing'!$Q$16,'2. GRI Pricing Inputs'!$C$53:$C$54,0),MATCH('3. GRI Pricing'!I289,'2. GRI Pricing Inputs'!$C$53:$AI$53,0)),0) -> 0 | R289: =IFERROR(INDEX('2. GRI Pricing Inputs'!$C$60:$AI$61,MATCH('3. GRI Pricing'!$R$16,'2. GRI Pricing Inputs'!$C$60:$C$61,0),MATCH('1. Accomodation'!T293,'2. GRI Pricing Inputs'!$C$60:$AI$60,0)),0) -> 0 | S289: =IFERROR(INDEX('2. GRI Pricing Inputs'!$C$67:$AI$68,MATCH('3. GRI Pricing'!$S$16,'2. GRI Pricing Inputs'!$C$67:$C$68,0),MATCH('1. Accomodation'!U293,'2. GRI Pricing Inputs'!$C$67:$AI$67,0)),0) -> 0 | T289: =IF(E289=0,0,'2. GRI Pricing Inputs'!$AI$75) -> 0 | U289: =IFERROR(INDEX('2. GRI Pricing Inputs'!$C$82:$AI$83,MATCH('3. GRI Pricing'!$U$16,'2. GRI Pricing Inputs'!$C$82:$C$83,0),MATCH('1. Accomodation'!V293,'2. GRI Pricing Inputs'!$C$82:$AI$82,0)),0) -> 0 | V289: =IFERROR(INDEX('2. GRI Pricing Inputs'!$C$89:$AI$90,MATCH('3. GRI Pricing'!$V$16,'2. GRI Pricing Inputs'!$C$89:$C$90,0),MATCH('1. Accomodation'!W293,'2. GRI Pricing Inputs'!$C$89:$AI$89,0)),0) -> 0 | W289: =IFERROR(INDEX('2. GRI Pricing Inputs'!$C$97:$AI$98,MATCH('3. GRI Pricing'!$W$16,'2. GRI Pricing Inputs'!$C$97:$C$98,0),MATCH('1. Accomodation'!X293,'2. GRI Pricing Inputs'!$C$97:$AI$97,0)),0) -> 0 | X289: =IFERROR(INDEX('2. GRI Pricing Inputs'!$C$104:$AI$105,MATCH('3. GRI Pricing'!$X$16,'2. GRI Pricing Inputs'!$C$104:$C$105,0),MATCH('1. Accomodation'!Y293,'2. GRI Pricing Inputs'!$C$104:$AI$104,0)),0) -> 0 | Z289: =L289+M289+O289+P289+Q289+R289+S289+T289+U289+V289+W289+X289+Y289 -> 0 | AD289: =Z289*(1+'2. GRI Pricing Inputs'!E$115)^(($AD$16-$AC$15)/365) -> 0 | AE289: =AD289*(1+'2. GRI Pricing Inputs'!F$115)^((AE$16-AD$16)/365) -> 0 | AF289: =AE289*(1+'2. GRI Pricing Inputs'!G$115)^((AF$16-AE$16)/365) -> 0 | AG289: =AF289*(1+'2. GRI Pricing Inputs'!H$115)^((AG$16-AF$16)/365) -> 0 | AH289: =AG289*(1+'2. GRI Pricing Inputs'!I$115)^((AH$16-AG$16)/365) -> 0 | AI289: =AH289*(1+'2. GRI Pricing Inputs'!J$115)^((AI$16-AH$16)/365) -> 0 | AJ289: =AI289*(1+'2. GRI Pricing Inputs'!K$115)^((AJ$16-AI$16)/365) -> 0 | AK289: =AJ289*(1+'2. GRI Pricing Inputs'!L$115)^((AK$16-AJ$16)/365) -> 0 | AL289: =AK289*(1+'2. GRI Pricing Inputs'!M$115)^((AL$16-AK$16)/365) -> 0 | ... AP289: =AO289*(1+'2. GRI Pricing Inputs'!Q$115)^((AP$16-AO$16)/365) -> 0 | AQ289: =IFERROR(AP289/AD289-1,0) -> 0
... C616: ='1. Accomodation'!N620 -> 0 | D616: ='1. Accomodation'!L620 -> [Select] | E616: ='1. Accomodation'!P620 -> [Select] | F616: ='1. Accomodation'!Q620 -> [Select] | G616: ='1. Accomodation'!O620 -> 0 | H616: ='1. Accomodation'!R620 -> [Select] | I616: ='1. Accomodation'!S620 -> [Select] | L616: =IFERROR(INDEX('2. GRI Pricing Inputs'!$C$15:$AI$16,MATCH($L$16,'2. GRI Pricing Inputs'!$C$15:$C$16,0),MATCH(E616,'2. GRI Pricing Inputs'!$C$15:$AI$15,0)),0) -> 0 | M616: =IFERROR(INDEX('2. GRI Pricing Inputs'!$C$22:$AI$23,MATCH($M$16,'2. GRI Pricing Inputs'!$C$22:$C$23,0),MATCH(F616,'2. GRI Pricing Inputs'!$C$22:$AI$22,0)),0) -> 0 | N616: =IF(AND('3. GRI Pricing'!$G616>='2. GRI Pricing Inputs'!$D$33,'3. GRI Pricing'!$G616<='2. GRI Pricing Inputs'!$E$33),'2. GRI Pricing Inputs'!$D$32,IF(AND('3. GRI Pricing'!$G616>='2. GRI Pricing Inputs'!$F$33,'3. GRI Pricing'!$G616<='2. GRI Pricing Inputs'!$G$33),'2. GRI Pricing Inputs'!$F$32,IF(AND('3. GRI Pricing'!$G616>='2. GRI Pricing Inputs'!$H$33,'3. GRI Pricing'!$G616<='2. GRI Pricing Inputs'!$I$33),'2. GRI Pricing Inputs'!$H$32,IF(AND('3. GRI Pricing'!$G616>='2. GRI Pricing Inputs'!$J$33,'3. GRI Pricing'!$G616<='2. GRI Pricing Inputs'!$K$33),'2. GRI Pricing Inputs'!$J$32,IF(AND('3. GRI Pricing'!$G616>='2. GRI Pricing Inputs'!$L$33,'3. GRI Pricing'!$G616<='2. GRI Pricing Inputs'!$M$33),'2. GRI Pricing Inputs'!$L$32,IF(AND('3. GRI Pricing'!$G616>='2. GRI Pricing Inputs'!$N$33,'3. GRI Pricing'!$G616<='2. GRI Pricing Inputs'!$O$33),'2. GRI Pricing Inputs'!$N$32,IF(AND('3. GRI Pricing'!$G616>='2. GRI Pricing Inputs'!$P$33,'3. GRI Pricing'!$G616<='2. GRI Pricing Inputs'!$Q$33),'2. GRI Pricing Inputs'!$P$32,IF(AND('3. GRI Pricing'!$G616>='2. GRI Pricing Inputs'!$R$33,'3. GRI Pricing'!$G616<='2. GRI Pricing Inputs'!$S$33),'2. GRI Pricing Inputs'!$R$32,IF(AND('3. GRI Pricing'!$G616>='2. GRI Pricing Inputs'!$T$33,'3. GRI Pricing'!$G616<='2. GRI Pricing Inputs'!$U$33),'2. GRI Pricing Inputs'!$T$32,IF(AND('3. GRI Pricing'!$G616>='2. GRI Pricing Inputs'!$V$33,'3. GRI Pricing'!$G616<='2. GRI Pricing Inputs'!$W$33),'2. GRI Pricing Inputs'!$V$32,IF(AND('3. GRI Pricing'!$G616>='2. GRI Pricing Inputs'!$X$33,'3. GRI Pricing'!$G616<='2. GRI Pricing Inputs'!$Y$33),'2. GRI Pricing Inputs'!$X$32,IF(AND('3. GRI Pricing'!$G616>='2. GRI Pricing Inputs'!$Z$33,'3. GRI Pricing'!$G616<='2. GRI Pricing Inputs'!$AA$33),'2. GRI Pricing Inputs'!$Z$32,IF(AND('3. GRI Pricing'!$G616>='2. GRI Pricing Inputs'!$AB$33,'3. GRI Pricing'!$G616<='2. GRI Pricing Inputs'!$AC$33),'2. GRI Pricing Inputs'!$AB$32,IF(AND('3. GRI Pricing'!$G616>='2. GRI Pricing Inputs'!$AD$33,'3. GRI Pricing'!$G616<='2. GRI Pricing Inputs'!$AE$33),'2. GRI Pricing Inputs'!$AD$32,IF(AND('3. GRI Pricing'!$G616>='2. GRI Pricing Inputs'!$AF$33,'3. GRI Pricing'!$G616<='2. GRI Pricing Inputs'!$AG$33),'2. GRI Pricing Inputs'!$AF$32,IF(AND('3. GRI Pricing'!$G616>='2. GRI Pricing Inputs'!$AH$33,'3. GRI Pricing'!$G616<='2. GRI Pricing Inputs'!$AI$33),'2. GRI Pricing Inputs'!$AH$32,0)))))))))))))))) -> 0 | O616: {=IFERROR(INDEX('2. GRI Pricing Inputs'!$C$32:$AI$39,MATCH('3. GRI Pricing'!E616,'2. GRI Pricing Inputs'!$C$32:$C$39,0),(MATCH('3. GRI Pricing'!N616,'2. GRI Pricing Inputs'!$D$32:$AI$32,0)+1)),0)} -> 0 | P616: =IFERROR(INDEX('2. GRI Pricing Inputs'!$C$45:$AI$46,MATCH($P$16,'2. GRI Pricing Inputs'!$C$45:$C$46,0),MATCH(H616,'2. GRI Pricing Inputs'!$C$45:$AI$45,0)),0) -> 0 | Q616: =IFERROR(INDEX('2. GRI Pricing Inputs'!$C$53:$AI$54,MATCH('3. GRI Pricing'!$Q$16,'2. GRI Pricing Inputs'!$C$53:$C$54,0),MATCH('3. GRI Pricing'!I616,'2. GRI Pricing Inputs'!$C$53:$AI$53,0)),0) -> 0 | R616: =IFERROR(INDEX('2. GRI Pricing Inputs'!$C$60:$AI$61,MATCH('3. GRI Pricing'!$R$16,'2. GRI Pricing Inputs'!$C$60:$C$61,0),MATCH('1. Accomodation'!T620,'2. GRI Pricing Inputs'!$C$60:$AI$60,0)),0) -> 0 | S616: =IFERROR(INDEX('2. GRI Pricing Inputs'!$C$67:$AI$68,MATCH('3. GRI Pricing'!$S$16,'2. GRI Pricing Inputs'!$C$67:$C$68,0),MATCH('1. Accomodation'!U620,'2. GRI Pricing Inputs'!$C$67:$AI$67,0)),0) -> 0 | T616: =IF(E616=0,0,'2. GRI Pricing Inputs'!$AI$75) -> 0 | U616: =IFERROR(INDEX('2. GRI Pricing Inputs'!$C$82:$AI$83,MATCH('3. GRI Pricing'!$U$16,'2. GRI Pricing Inputs'!$C$82:$C$83,0),MATCH('1. Accomodation'!V620,'2. GRI Pricing Inputs'!$C$82:$AI$82,0)),0) -> 0 | V616: =IFERROR(INDEX('2. GRI Pricing Inputs'!$C$89:$AI$90,MATCH('3. GRI Pricing'!$V$16,'2. GRI Pricing Inputs'!$C$89:$C$90,0),MATCH('1. Accomodation'!W620,'2. GRI Pricing Inputs'!$C$89:$AI$89,0)),0) -> 0 | W616: =IFERROR(INDEX('2. GRI Pricing Inputs'!$C$97:$AI$98,MATCH('3. GRI Pricing'!$W$16,'2. GRI Pricing Inputs'!$C$97:$C$98,0),MATCH('1. Accomodation'!X620,'2. GRI Pricing Inputs'!$C$97:$AI$97,0)),0) -> 0 | X616: =IFERROR(INDEX('2. GRI Pricing Inputs'!$C$104:$AI$105,MATCH('3. GRI Pricing'!$X$16,'2. GRI Pricing Inputs'!$C$104:$C$105,0),MATCH('1. Accomodation'!Y620,'2. GRI Pricing Inputs'!$C$104:$AI$104,0)),0) -> 0 | Z616: =L616+M616+O616+P616+Q616+R616+S616+T616+U616+V616+W616+X616+Y616 -> 0 | AD616: =Z616*(1+'2. GRI Pricing Inputs'!E$115)^(($AD$16-$AC$15)/365) -> 0 | AE616: =AD616*(1+'2. GRI Pricing Inputs'!F$115)^((AE$16-AD$16)/365) -> 0 | AF616: =AE616*(1+'2. GRI Pricing Inputs'!G$115)^((AF$16-AE$16)/365) -> 0 | AG616: =AF616*(1+'2. GRI Pricing Inputs'!H$115)^((AG$16-AF$16)/365) -> 0 | AH616: =AG616*(1+'2. GRI Pricing Inputs'!I$115)^((AH$16-AG$16)/365) -> 0 | AI616: =AH616*(1+'2. GRI Pricing Inputs'!J$115)^((AI$16-AH$16)/365) -> 0 | AJ616: =AI616*(1+'2. GRI Pricing Inputs'!K$115)^((AJ$16-AI$16)/365) -> 0 | AK616: =AJ616*(1+'2. GRI Pricing Inputs'!L$115)^((AK$16-AJ$16)/365) -> 0 | AL616: =AK616*(1+'2. GRI Pricing Inputs'!M$115)^((AL$16-AK$16)/365) -> 0 | ... AP616: =AO616*(1+'2. GRI Pricing Inputs'!Q$115)^((AP$16-AO$16)/365) -> 0 | AQ616: =IFERROR(AP616/AD616-1,0) -> 0
Y617: Total ERV | Z617: =SUM(Z17:Z616)*12 -> 4606500 | AD617: =SUM(AD17:AD616)*12 -> 4629353.5 | AE617: =SUM(AE17:AE616)*12 -> 4651577.6 | AF617: =SUM(AF17:AF616)*12 -> 4674654.7 | AG617: =SUM(AG17:AG616)*12 -> 4697846.3 | AH617: =SUM(AH17:AH616)*12 -> 4718892.4 | AI617: =SUM(AI17:AI616)*12 -> 4742303.5 | AJ617: =SUM(AJ17:AJ616)*12 -> 4765069.9 | AK617: =SUM(AK17:AK616)*12 -> 4788710.1 | ... AP617: =SUM(AP17:AP616)*12 -> 4907114.7
C621: =COUNT(C17:C616) -> 600

Sheet 4. Valuation
C3: 4. ERV COMPARISON AGAINST VALUER
C5: Valuer | D5: Allsop/CBRE
C6: Pricing Update Date | D6: 45536 | I6: PRS | J6: Car Parking | X6: PRS | Y6: Car Parking
C7: Last Valuation Date | D7: 45536 | H7: =TEXT(D5,0)&" Growth Rate" -> Allsop/CBRE Growth Rate | I7: 0.03 | J7: 0 | W7: Budget Growth Rate | X7: 0.03 | Y7: 0
C8: Budget period: 12m up to | D8: 45901 | L8: Check dates as hardcoded | S8: Check dates as hardcoded | W8: Check dates as hardcoded | AA8: Check dates as hardcoded
H9: =TEXT($D$5,0)&" "&TEXT($D$7,"mmm-yy") -> Allsop/CBRE Sep-24 | L9: =TEXT($D$5,0)&" Grown to "&TEXT(M24,"mmm-yy") -> Allsop/CBRE Grown to Sep-24 | S9: =TEXT($D$8,0)&" BUDGET" -> 45901 BUDGET | W9: =TEXT($D$8,0)&" BUDGET Grown to "&""&TEXT($X$24, "mmm-yy") -> 45901 BUDGET Grown to Sep-22 | AA9: LAUNCH RENTS (MONTH, YEAR)
C10: ='3. GRI Pricing'!C5 -> Bedroom | D10: ='3. GRI Pricing'!D5 -> No. of Homes | E10: ='3. GRI Pricing'!E5 -> Av. Size (sqft) | H10: Monthly | I10: Annual | J10: £psf | L10: Monthly | M10: Annual | N10: £psf | P10: Unit Type | Q10: Number of units | R10: Av. Size (sqft) | S10: Monthly | T10: Annual | U10: £psf | W10: Monthly | X10: Annual | Y10: £psf | AA10: Monthly | AB10: Annual | AC10: £psf | AF10: ="Extract of latest valuation from"&TEXT(D5,0)&":" -> Extract of latest valuation fromAllsop/CBRE:
