Workbook
Name _Toc156926581: 'ROM_Analysis Estimate'!#REF!
Name _Toc156926582: 'ROM_Analysis Estimate'!#REF!
Name _Toc156926583: 'ROM_Analysis Estimate'!#REF!
Name AnalysisActuals: 'Delivery Cost Estimate'!$E$27
Name AnalysisEstimate: 'Custom Automation HLQ'!$E$25
Name AnalysisEstimate: 'Delivery Cost Estimate'!$E$26
Name AnalysisHLQ: 'Delivery Cost Estimate'!$E$25
Name BlendedRate: 'Custom Automation HLQ'!$E$11
Name BlendedRate: 'Delivery Cost Estimate'!$E$12
Name BlendedRateGBP: '2 Week Sprint'!$I$8
Name BlendedRateUSD: '2 Week Sprint'!$J$8
Name BuildActuals: 'Delivery Cost Estimate'!$E$41
Name BuildContingency_UnanticipatedComplexity: 'Delivery Cost Estimate'!$E$116
Name BuildDuration: 'Custom Automation HLQ'!$E$72
Name BuildEstimate: 'Custom Automation HLQ'!$E$37
Name BuildEstimate: 'Delivery Cost Estimate'!$E$40
Name BuildHLQ: 'Delivery Cost Estimate'!$E$39
Name BuildSprints: 'Delivery Cost Estimate'!$D$99
Name CountBA: 'Custom Automation HLQ'!$E$18
Name CountBA: 'Delivery Cost Estimate'!$E$19
Name CountDev: 'Custom Automation HLQ'!$E$19
Name CountDev: 'Delivery Cost Estimate'!$E$20
Name CountPM: 'Custom Automation HLQ'!$E$21
Name CountPM: 'Delivery Cost Estimate'!$E$22
Name CountQA: 'Custom Automation HLQ'!$E$6
Name CountQA: 'Delivery Cost Estimate'!$E$7
Name GoLiveSupportActuals: 'Delivery Cost Estimate'!$E$147
Name GoLiveSupportEstimate: 'Custom Automation HLQ'!$E$100
Name GoLiveSupportEstimate: 'Delivery Cost Estimate'!$E$146
Name GoLiveSupportHLQ: 'Delivery Cost Estimate'!$E$145
Name ProjectCostActuals: 'Delivery Cost Estimate'!$E$160
Name ProjectCostEstimate: 'Custom Automation HLQ'!$E$110
Name ProjectCostEstimate: 'Delivery Cost Estimate'!$E$159
Name ProjectCostHLQ: 'Delivery Cost Estimate'!$E$158
Name RangeDriver: 'Delivery Cost Estimate'!$E$13
Name SprintDuration: '2 Week Sprint'!$C$2
Name SumBuildOverheads: 'Custom Automation HLQ'!$E$71
Name SumBuildOverheads: 'Delivery Cost Estimate'!$E$97
Name SumFunctionalDevelopment: 'Custom Automation HLQ'!$E$45
Name SumFunctionalDevelopment: 'Delivery Cost Estimate'!$E$60
Name SumQA: 'Custom Automation HLQ'!$E$66
Name SumQA: 'Delivery Cost Estimate'!$E$91
Name SumTeamSize: 'Custom Automation HLQ'!$E$17
Name SumTeamSize: 'Delivery Cost Estimate'!$E$18
Name UserAcceptanceTestingActuals: 'Delivery Cost Estimate'!$E$121
Name UserAcceptanceTestingEstimate: 'Custom Automation HLQ'!$E$78
Name UserAcceptanceTestingEstimate: 'Delivery Cost Estimate'!$E$120
Name UserAcceptanceTestingHLQ: 'Delivery Cost Estimate'!$E$119

Sheet Automation Questionnaire
B2: High Level Description | C2: High level description of the process
F3: Risk | G3: Complexity | H3: Value
D4: Please select an option | E4: Details | F4: =IF(F$26>(F$28-$G29),5,ROUNDDOWN((F$26-F$27)/F$29+1,0)) -> 1 | G4: =IF(G$26>(G$28-$G29),5,ROUNDDOWN((G$26-G$27)/G$29+1,0)) -> 1 | H4: =IF(H$26>(H$28-$G29),5,ROUNDDOWN((H$26-H$27)/H$29+1,0)) -> 1
B5: Frequency | C5: How often is this process performed? | D5: 1. Low - quarterly or annually | H5: =IF(ISBLANK(D5),0,_xlfn.NUMBERVALUE(LEFT(D5,1))) -> 1
B6: Volume | C6: How high is the volume of records, data or iterations to be processed? E.g. ten reports per month, hundreds of invoices per day, thousands of transactions per file | D6: 1. Tens of records | G6: =IF(ISBLANK(D6),0,_xlfn.NUMBERVALUE(LEFT(D6,1))) -> 1 | H6: =IF(ISBLANK(D6),0,_xlfn.NUMBERVALUE(LEFT(D6,1))) -> 1
B7: Time | C7: How much time does the process take on average each time it's performed? | D7: 1. An hour or less | F7: =IF(ISBLANK(D7),0,_xlfn.NUMBERVALUE(LEFT(D7,1))) -> 1 | G7: =IF(ISBLANK(D7),0,_xlfn.NUMBERVALUE(LEFT(D7,1))) -> 1 | H7: =IF(ISBLANK(D7),0,_xlfn.NUMBERVALUE(LEFT(D7,1))) -> 1
B8: Headcount | C8: How many Full Time Equivalent people does this process take to execute in total? | D8: 1. 1-2 FTEs | H8: =IF(ISBLANK(D8),0,_xlfn.NUMBERVALUE(LEFT(D8,1))) -> 1
B9: Seniority | C9: What's the seniority of the typical FTE working on this process? | D9: 1. Junior | F9: =IF(ISBLANK(D9),0,_xlfn.NUMBERVALUE(LEFT(D9,1))) -> 1 | G9: =IF(ISBLANK(D9),0,_xlfn.NUMBERVALUE(LEFT(D9,1))) -> 1 | H9: =IF(ISBLANK(D9),0,_xlfn.NUMBERVALUE(LEFT(D9,1))) -> 1
B10: Scope | C10: How broad is the geographical scope of the process? | D10: 1. Country-specific | F10: =IF(ISBLANK(D10),0,_xlfn.NUMBERVALUE(LEFT(D10,1))) -> 1 | G10: =IF(ISBLANK(D10),0,_xlfn.NUMBERVALUE(LEFT(D10,1))) -> 1 | H10: =IF(ISBLANK(D10),0,_xlfn.NUMBERVALUE(LEFT(D10,1))) -> 1
B11: Cost of delays | C11: How critical is it that the process is completed accurately and on time? | D11: 1. Low - process currently completed as time allows | F11: =IF(ISBLANK(D11),0,_xlfn.NUMBERVALUE(LEFT(D11,1))) -> 1 | H11: =IF(ISBLANK(D11),0,_xlfn.NUMBERVALUE(LEFT(D11,1))) -> 1
B12: Input type | C12: What is the typical format of the data or information that forms the input into the process? | D12: 1. Fully digital/structured e.g. PDF, Excel, report | F12: =IF(ISBLANK(D12),0,_xlfn.NUMBERVALUE(LEFT(D12,1))) -> 1 | G12: =IF(ISBLANK(D12),0,_xlfn.NUMBERVALUE(LEFT(D12,1))) -> 1
B13: Document Scanning | C13: Will the input need to be read via Optical Character Recognition or AI? | D13: 1. No | G13: =IF(ISBLANK(D13),0,_xlfn.NUMBERVALUE(LEFT(D13,1))) -> 1
B14: Input quality | C14: What level of validation would need to be performed on the input data prior to use? | D14: 1. Basic - Required fields and formats | G14: =IF(ISBLANK(D14),0,_xlfn.NUMBERVALUE(LEFT(D14,1))) -> 1
B15: Process Documentation | C15: How well documented is the current process? Are there clear SOPs or does the process knowledge reside in the heads of a small number of individuals? | D15: 1. Well documented/Clear SOPs | F15: =IF(ISBLANK(D15),0,_xlfn.NUMBERVALUE(LEFT(D15,1))) -> 1 | G15: =IF(ISBLANK(D15),0,_xlfn.NUMBERVALUE(LEFT(D15,1))) -> 1
B16: Human intervention | C16: How likely is it for the process to include decision points that cannot be mapped and need to be handed off to a human to make a judgement call? E.g. free text that can't be mapped to a code | D16: 1. Unlikely | F16: =IF(ISBLANK(D16),0,_xlfn.NUMBERVALUE(LEFT(D16,1))) -> 1 | G16: =IF(ISBLANK(D16),0,_xlfn.NUMBERVALUE(LEFT(D16,1))) -> 1
B17: Number of systems | C17: How many systems or sites are involved in the end-to-end process (not counting tools like Excel). | D17: 1. 1 system | F17: =IF(ISBLANK(D17),0,_xlfn.NUMBERVALUE(LEFT(D17,1))) -> 1 | G17: =IF(ISBLANK(D17),0,_xlfn.NUMBERVALUE(LEFT(D17,1))) -> 1
B18: System access | C18: What is the nature of the systems involved and how are they accessed? | D18: 1. SaaS/External | F18: =IF(ISBLANK(D18),0,_xlfn.NUMBERVALUE(LEFT(D18,1))) -> 1 | G18: =IF(ISBLANK(D18),0,_xlfn.NUMBERVALUE(LEFT(D18,1))) -> 1
B19: Test Data Availability | C19: What sort of test data will be available? Is there a test environment that mirrors live? Any privacy or data sharing concerns that would impact the ability to use live data? | D19: 1. Test environment and/or live data | F19: =IF(ISBLANK(D19),0,_xlfn.NUMBERVALUE(LEFT(D19,1))) -> 1 | G19: =IF(ISBLANK(D19),0,_xlfn.NUMBERVALUE(LEFT(D19,1))) -> 1
B20: System Change Landscape | C20: How frequently are the applications involved in the process undergoing change? | D20: 1. System is essentially stable | F20: =IF(ISBLANK(D20),0,_xlfn.NUMBERVALUE(LEFT(D20,1))) -> 1
B21: Stakeholder Availability | C21: How available are service leads, process owners and SMEs likely to be? Consider other commitments like ongoing high priority projects in their service line. | D21: 1. Time has been committed | F21: =IF(ISBLANK(D21),0,_xlfn.NUMBERVALUE(LEFT(D21,1))) -> 1
B22: Client Impact | C22: What is the likely positive impact this automation will have on client satisfaction, retention or new client acquisition? | D22: 1. Low | H22: =IF(ISBLANK(D22),0,_xlfn.NUMBERVALUE(LEFT(D22,1))) -> 1
B23: Staff Retention | C23: What is the likely positive impact this automation will have on staff satisfaction or staff retention? | D23: 1. Low | H23: =IF(ISBLANK(D23),0,_xlfn.NUMBERVALUE(LEFT(D23,1))) -> 1
B24: Risk Reduction | C24: What is the likely positive impact this automation will have on reducing operational risk, fraud loss, regulatory risk or penalties and fees? | D24: 1. Low | H24: =IF(ISBLANK(D24),0,_xlfn.NUMBERVALUE(LEFT(D24,1))) -> 1
B25: Other Considerations | C25: Any other considerations that would affect scoring
E26: Score | F26: =SUM(F5:F25) -> 12 | G26: =SUM(G5:G25) -> 12 | H26: =SUM(H5:H25) -> 10
E27: Minimum (Excl Other) | F27: =COUNTA(F5:F24) -> 12 | G27: =COUNTA(G5:G24) -> 12 | H27: =COUNTA(H5:H24) -> 10
E28: Max (Excl Other) | F28: =COUNTA(F5:F24)*3 -> 36 | G28: =COUNTA(G5:G24)*3 -> 36 | H28: =COUNTA(H5:H24)*3 -> 30
E29: Bucket size | F29: =ROUNDDOWN((F28-F27+1)/5,0) -> 5 | G29: =ROUNDDOWN((G28-G27+1)/5,0) -> 5 | H29: =ROUNDDOWN((H28-H27+1)/5,0) -> 4

Sheet HLQ
C3: High Level Quote | G3: Currency | H3: USD
C5: Complexity: | E5: ='Automation Questionnaire'!G4 -> 1 | G5: Risk: | H5: ='Automation Questionnaire'!F4 -> 1
C7: Phase | E7: Recommended Duration (w) | F7: Quoted Duration (w) | G7: Cost From | H7: Cost To
C8: Analysis | E8: =VLOOKUP($E$5,'2 Week Sprint'!$B$24:$F$29,2,FALSE)+VLOOKUP($H$5,'2 Week Sprint'!$B$32:$G$37,2,FALSE) -> 2 | F8: =E8 -> 2 | G8: =IF($H$3="GBP",$F8*'2 Week Sprint'!$P15,$F8*'2 Week Sprint'!$Q15) -> 5200 | H8: =ROUND(IF($H$3="GBP",$F8*'2 Week Sprint'!$P15,$F8*'2 Week Sprint'!$Q15)*(1+VLOOKUP($H$5,'2 Week Sprint'!$B$32:$G$37,6,FALSE)),-2) -> 6200
C9: Build | E9: =VLOOKUP($E$5,'2 Week Sprint'!$B$24:$F$29,3,FALSE)+VLOOKUP($H$5,'2 Week Sprint'!$B$32:$G$37,3,FALSE) -> 2 | F9: =E9 -> 2 | G9: =IF($H$3="GBP",$F9*'2 Week Sprint'!$P16,$F9*'2 Week Sprint'!$Q16) -> 13400 | H9: =ROUND(IF($H$3="GBP",$F9*'2 Week Sprint'!$P16,$F9*'2 Week Sprint'!$Q16)*(1+VLOOKUP($H$5,'2 Week Sprint'!$B$32:$G$37,6,FALSE)),-2) -> 16100
C10: UAT | E10: =VLOOKUP($E$5,'2 Week Sprint'!$B$24:$F$29,4,FALSE)+VLOOKUP($H$5,'2 Week Sprint'!$B$32:$G$37,4,FALSE) -> 2 | F10: =E10 -> 2 | G10: =IF($H$3="GBP",$F10*'2 Week Sprint'!$P18,$F10*'2 Week Sprint'!$Q18) -> 7200 | H10: =ROUND(IF($H$3="GBP",$F10*'2 Week Sprint'!$P18,$F10*'2 Week Sprint'!$Q18)*(1+VLOOKUP($H$5,'2 Week Sprint'!$B$32:$G$37,6,FALSE)),-2) -> 8600
C11: Support | E11: =VLOOKUP($E$5,'2 Week Sprint'!$B$24:$F$29,5,FALSE)+VLOOKUP($H$5,'2 Week Sprint'!$B$32:$G$37,5,FALSE) -> 0 | F11: =E11 -> 0 | G11: =IF($H$3="GBP",$F11*'2 Week Sprint'!$P19,$F11*'2 Week Sprint'!$Q19) -> 0 | H11: =ROUND(IF($H$3="GBP",$F11*'2 Week Sprint'!$P19,$F11*'2 Week Sprint'!$Q19)*(1+VLOOKUP($H$5,'2 Week Sprint'!$B$32:$G$37,6,FALSE)),-2) -> 0
C12: Total | G12: =SUM(G8:G11) -> 25800 | H12: =SUM(H8:H11) -> 30900
C15: High Level Scope
B17: Item | D17: Name | G17: Description
B18: 1
B19: 2
B20: 3
B21: 4
B22: 5
B23: 6
B24: 7
C27: Assumptions
C29: Item | E29: Name | G29: Description
B30: 1 | D30: Frequency & Volume
B31: 2 | D31: Scope
B32: 3 | D32: Pre-requisites
B33: 4 | D33: Dependencies
B34: 5 | D34: Risks
B35: 6 | D35: Exclusions

Sheet ROI
C3: Cost Benefit Analysis | H3: Currency | I3: USD | P3: Benefit Calculations
C5: Year 1 Benefit | H5: Year 1 Costs | P5: Process Hours Recovered
C6: Bottom Line Savings | F6: =R32 -> 25000 | H6: Total Capital Cost | K6: =HLQ!H12 -> 30900 | P6: Current Process Effort (h) | R6: 8 | S6: (average hours to run the process each time)
C7: Reinvested Capacity | F7: =R38 -> 27000 | H7: Year 1 Operating Cost | K7: =1200*12 -> 14400 | P7: Volume p.m. | R7: 20 | S7: (average times per month the process is run)
C8: Increased Revenue | F8: =R41 -> 0 | H8: Other Annual Costs | K8: 0 | P8: Automation Coverage | R8: 0.7 | S8: (percentage of the process that can be automated)
C9: Total Annual Benefit | F9: =SUM(F6:F8) -> 52000 | H9: Total Year 1 Cost | K9: =SUM(K6:K8) -> 45300 | P9: Hours Recovered p.m. | R9: =R6*R7*R8 -> 112 | S9: (total hours recovered by automation per month)
P10: Hours Recovered p.a. | R10: =R9*12 -> 1344 | S10: (total hours recovered by automation per annum)
C11: Years of Operation | F11: 0 | P11: FTEs Recovered p.a. | R11: =R10/R20 -> 1.1061728 | S11: (=hours recovered / effective hours p.a.)
C13: Ongoing Benefit | H13: Ongoing Costs | P13: Current FTE Costs
C14: Ongoing Annual Benefit | F14: =R33+F7+F8 -> 47000 | H14: Ongoing Annual Cost | K14: =K7+K8 -> 14400 | P14: Annual Salary | R14: 30000 | S14: (average salary of FTE currently performing process)
C15: Total Benefit | F15: =F9+F14*F11 -> 52000 | H15: Total Cost of Ownership | K15: =K9+K14*F11 -> 45300 | P15: Overhead multiplier | R15: 1.5 | S15: (estimate of overheads - benefits, infrastructure, etc.)
P16: Annual Cost to Company | R16: =R14*R15 -> 45000
C17: Return on Investment | P17: Effective working days p.a. | R17: 216 | S17: (accounting for leave, illness, holidays, etc.)
C18: ROI vs Capital Investment | F18: =F15-K6 -> 21100 | H18: =F18/K6 -> 0.6828479 | P18: Working hours per day | R18: 7.5
C19: Capital Payback Month | F19: =K6/F9*12 -> 7.1307692 | P19: Efficiency multiplier | R19: 0.75 | S19: (accounting for admin, meetings, breaks, etc.)
C20: ROI vs Total Cost of Ownership | F20: =F15-K15 -> 6700 | H20: =F20/K15 -> 0.14790287 | P20: Effective hours p.a. | R20: =R17*R18*R19 -> 1215 | S20: (total hours of effective processing per FTE)
P21: Cost per effective hour | R21: =R16/R20 -> 37.037037
P23: Bottom Line Savings
P24: Number of FTEs to be reduced | R24: 0 | S24: (if objective is to reduce headcount)
P25: FTE cost reduction | R25: =R24*R16 -> 0 | S25: (=FTE reduction x annual cost to company)
P26: Avoided penalty costs | R26: 0 | S26: (if objective includes improving accuracy/reducing operational risk)
P27: New Hires avoided | R27: 1 | S27: (if automation avoids cost of hiring additional FTEs)
P28: Recruitment cost - new hire | R28: 5000
P29: Annual salary - new hire | R29: 20000 | S29: (may be different from FTE as new hire could be part time)
P30: Licensing or Software Savings | R30: 0 | S30: (if objective includes removing current technical solution or reducing licenses)
P31: Any other savings | R31: 0
P32: Bottom Line Savings - Year 1 | R32: =R25+R26+R27*(R28+R29)+R30+R31 -> 25000
P33: Annual Savings thereafter | R33: =R25+R26+R27*R29+R30+R31 -> 20000 | S33: (excluding one-off recruitment cost)
P35: Reinvested Capacity
P36: Number of FTEs to be reinvested | R36: 0.6 | S36: (if objective is to free up capacity for other value add work)
P37: Effective hours reinvested p.a. | R37: =R36*R20 -> 729 | S37: (FTEs x annual effective hours)
P38: Value of reinvested capacity | R38: =R37*R21 -> 27000 | S38: (hours x cost per effective hour)
P40: Increased Revenue
P41: Estimated annual revenue increase | R41: 0 | S41: (if objective includes increasing fee income, sales, etc.)

Sheet 2 Week Sprint
B2: Sprint Duration | C2: 2 | D2: weeks | G2: Team Composition | I2: Hourly Rate | J2: Hourly Rate
B3: FTE Hours per Sprint | C3: =40*$C$2 -> 80 | D3: hours | G3: BA | H3: 1 | I3: 83 | J3: 107
B4: Standups | C4: =Lookups!H3*5*C2/60 -> 2.5 | D4: hours | G4: PM | H4: 1 | I4: 104 | J4: 135
B5: Planning | C5: =Lookups!H4*C2/4 -> 0.5 | D5: hours | G5: DEV | H5: 1 | I5: 70 | J5: 90
B6: Review | C6: =Lookups!H5*C2/4 -> 0 | D6: hours | G6: QA | H6: 1 | I6: 70 | J6: 90
B7: Retro | C7: =Lookups!H6*C2/4 -> 0.5 | D7: hours | G7: Weighted AVG | I7: =SUMPRODUCT(H3:H6,I3:I6)/SUM(H3:H6) -> 81.75 | J7: =SUMPRODUCT(H3:H6,J3:J6)/SUM(H3:H6) -> 105.5
B8: Deployments | C8: 0 | D8: hours | G8: Blended Rate | I8: 76 | J8: 100 | L8: Review blended rate with role specific rates when we carry out the next few estimates
B9: Total overheads | C9: =SUM(C4:C8) -> 3.5 | D9: hours
B10: Overhead % | C10: =C9/C3 -> 0.04375
B13: Model Project | D13: DEV | F13: QA | H13: BA | J13: PM | L13: Grand Total | P13: Weekly Cost
B14: Phase | C14: Duration (w) | D14: % Allocation | E14: Total Hours | F14: % Allocation | G14: Total Hours | H14: % Allocation | I14: Total Hours | J14: % Allocation | K14: Total Hours | L14: % Allocation | M14: Total Hours | N14: GBP | O14: USD | P14: GBP | Q14: USD
B15: Analysis | C15: 2 | D15: 0.1 | E15: =$C15/SprintDuration*$C$3*$H$5*D15 -> 8 | F15: 0 | G15: =$C15/SprintDuration*$C$3*$H$6*F15 -> 0 | H15: 0.5 | I15: =$C15/SprintDuration*$C$3*$H$3*H15 -> 40 | J15: 0.05 | K15: =$C15/SprintDuration*$C$3*$H$4*J15 -> 4 | L15: =M15/$M$20 -> 0.17808219 | M15: =E15+G15+I15+K15 -> 52 | N15: =M15*BlendedRateGBP -> 3952 | O15: =M15*BlendedRateUSD -> 5200 | P15: =N15/$C15 -> 1976 | Q15: =O15/$C15 -> 2600
B16: Build | C16: 2 | D16: 0.8 | E16: =$C16/SprintDuration*$C$3*$H$5*D16 -> 64 | F16: 0.4 | G16: =$C16/SprintDuration*$C$3*$H$6*F16 -> 32 | H16: 0.2 | I16: =$C16/SprintDuration*$C$3*$H$3*H16 -> 16 | J16: 0.1 | K16: =$C16/SprintDuration*$C$3*$H$4*J16 -> 8 | L16: =M16/$M$20 -> 0.4109589 | M16: =E16+G16+I16+K16 -> 120 | N16: =M16*BlendedRateGBP -> 9120 | O16: =M16*BlendedRateUSD -> 12000 | P16: =SUM(N16:N17)/$C16 -> 5092 | Q16: =SUM(O16:O17)/$C16 -> 6700
B17: Sprint Overheads | D17: =$C$10 -> 0.04375 | E17: =$C16/SprintDuration*$C$3*$H$5*D17 -> 3.5 | F17: =$C$10 -> 0.04375 | G17: =$C16/SprintDuration*$C$3*$H$6*F17 -> 3.5 | H17: =$C$10 -> 0.04375 | I17: =$C16/SprintDuration*$C$3*$H$3*H17 -> 3.5 | J17: =$C$10 -> 0.04375 | K17: =$C16/SprintDuration*$C$3*$H$4*J17 -> 3.5 | L17: =M17/$M$20 -> 0.047945205 | M17: =E17+G17+I17+K17 -> 14 | N17: =M17*BlendedRateGBP -> 1064 | O17: =M17*BlendedRateUSD -> 1400 | P17: Included in Build Phase
B18: UAT | C18: 2 | D18: 0.4 | E18: =$C18/SprintDuration*$C$3*$H$5*D18 -> 32 | F18: 0.2 | G18: =$C18/SprintDuration*$C$3*$H$6*F18 -> 16 | H18: 0.2 | I18: =$C18/SprintDuration*$C$3*$H$3*H18 -> 16 | J18: 0.1 | K18: =$C18/SprintDuration*$C$3*$H$4*J18 -> 8 | L18: =M18/$M$20 -> 0.24657534 | M18: =E18+G18+I18+K18 -> 72 | N18: =M18*BlendedRateGBP -> 5472 | O18: =M18*BlendedRateUSD -> 7200 | P18: =N18/$C18 -> 2736 | Q18: =O18/$C18 -> 3600
B19: Support | C19: 1 | D19: 0.4 | E19: =$C19/SprintDuration*$C$3*$H$5*D19 -> 16 | F19: 0.2 | G19: =$C19/SprintDuration*$C$3*$H$6*F19 -> 8 | H19: 0.2 | I19: =$C19/SprintDuration*$C$3*$H$3*H19 -> 8 | J19: 0.05 | K19: =$C19/SprintDuration*$C$3*$H$4*J19 -> 2 | L19: =M19/$M$20 -> 0.11643836 | M19: =E19+G19+I19+K19 -> 34 | N19: =M19*BlendedRateGBP -> 2584 | O19: =M19*BlendedRateUSD -> 3400 | P19: =N19/$C19 -> 2584 | Q19: =O19/$C19 -> 3400
B20: Total | C20: =SUM(C15:C19) -> 7 | E20: =SUM(E15:E19) -> 123.5 | G20: =SUM(G15:G19) -> 59.5 | I20: =SUM(I15:I19) -> 83.5 | K20: =SUM(K15:K19) -> 25.5 | L20: =SUM(L15:L19) -> 1 | M20: =SUM(M15:M19) -> 292 | N20: =SUM(N15:N19) -> 22192 | O20: =SUM(O15:O19) -> 29200
C23: Duration (w)
B24: Complexity | C24: Analysis | D24: Build & Test | E24: UAT | F24: Support
B25: 1 | C25: 4 | D25: 2 | E25: 2 | F25: 2
B26: 2 | C26: 4 | D26: 4 | E26: 2 | F26: 2
B27: 3 | C27: 6 | D27: 6 | E27: 2 | F27: 2
B28: 4 | C28: 6 | D28: 8 | E28: 2 | F28: 2
B29: 5 | C29: 8 | D29: 10 | E29: 2 | F29: 2
C31: Duration (w)
B32: Risk Modifier | C32: Analysis | D32: Build & Test | E32: UAT | F32: Support | G32: Contingency
B33: 1 | C33: -2 | D33: 0 | E33: 0 | F33: -2 | G33: 0.2
B34: 2 | C34: -1 | D34: 0 | E34: 0 | F34: -1 | G34: 0.25
B35: 3 | C35: 0 | D35: 0 | E35: 0 | F35: 0 | G35: 0.3
B36: 4 | C36: 1 | D36: 0 | E36: 1 | F36: 1 | G36: 0.35
B37: 5 | C37: 2 | D37: 0 | E37: 1 | F37: 2 | G37: 0.4

Sheet Lookups
A1: ='Automation Questionnaire'!B5 -> Frequency
A2: 1. Low - quarterly or annually | G2: Sprint Timeboxing (SCRUM recommended maximum)
A3: 2. Medium - monthly or weekly | G3: Standups | H3: 15 | I3: mins per day
A4: 3. High - daily | G4: Planning | H4: 1 | I4: hours per 4 weeks
G5: Review | H5: 0 | I5: hours per 4 weeks
A6: ='Automation Questionnaire'!B6 -> Volume | G6: Retro | H6: 1 | I6: hours per 4 weeks
A7: 1. Tens of records
A8: 2. Hundreds of records
A9: 3. Thousands of records
A11: ='Automation Questionnaire'!B7 -> Time
A12: 1. An hour or less
A13: 2. Several hours
A14: 3. Several days
A16: ='Automation Questionnaire'!B10 -> Scope
A17: 1. Country-specific
A18: 2. Region-specific (e.g. EMEA/APAC/NA)
A19: 3. Global
A21: ='Automation Questionnaire'!B8 -> Headcount
A22: 1. 1-2 FTEs
A23: 2. 2-5 FTEs
A24: 3. 6+ FTEs
A26: ='Automation Questionnaire'!B9 -> Seniority
A27: 1. Junior
A28: 2. Mid-Level
A29: 3. Senior
A31: ='Automation Questionnaire'!B11 -> Cost of delays
A32: 1. Low - process currently completed as time allows
A33: 2. Medium - business impact increases with delays
A34: 3. High - process is time sensitive/business critical
A36: ='Automation Questionnaire'!B12 -> Input type
A37: 1. Fully digital/structured e.g. PDF, Excel, report
A38: 2. Somewhat structured or digital but needs work
A39: 3. Paper-based or in unstructured/unstandardised
A41: ='Automation Questionnaire'!B13 -> Document Scanning
A42: 1. No
A43: 2. Yes, with only one layout
A44: 3. Yes, with multiple layouts
A46: ='Automation Questionnaire'!B14 -> Input quality
A47: 1. Basic - Required fields and formats
A48: 2. Medium - Simple logic or lookups
A49: 3. High - Complex logic or lookups
A51: ='Automation Questionnaire'!B15 -> Process Documentation
A52: 1. Well documented/Clear SOPs
A53: 2. Documented with some gaps
A54: 3. Poorly or un-documented
A56: ='Automation Questionnaire'!B16 -> Human intervention
A57: 1. Unlikely
A58: 2. Somewhat likely
A59: 3. Highly likely
A61: ='Automation Questionnaire'!B21 -> Stakeholder Availability
A62: 1. Time has been committed
A63: 2. Somewhat available with notice
A64: 3. Limited Availability
A66: ='Automation Questionnaire'!B17 -> Number of systems
A67: 1. 1 system
A68: 2. 2-3 systems
A69: 3. 4+ systems
A71: ='Automation Questionnaire'!B18 -> System access
A72: 1. SaaS/External
A73: 2. VPN/Inside Network
A74: 3. Citrix
A76: Test Data Availability
A77: 1. Test environment and/or live data
A78: 2. Test environment and/or live-like data
A79: 3. No test environment/test data only
A81: ='Automation Questionnaire'!B20 -> System Change Landscape
A82: 1. System is essentially stable
A83: 2. System undergoes regular maintenance
A84: 3. Enhancements are in progress
A86: Client Impact/Staff Retention/Risk Reduction
A87: 1. Low
A88: 2. Medium
A89: 3. High

Sheet Custom Automation HLQ
B1: Instructions
B2: 1. This template should only be used to calculate a high level quote (HLQ) for an automation solution that does not utilise Blue Prism / UiPath.
B3: 2. Review HLQ variables, notably the Blended Project Rate/Hour.
B4: Project Contingency is applied to all phases.
B5: 3. Only white cells should be edited.
B7: > High Level Quote Variables
B9: Billing
B10: Currency | E10: USD
B11: Blended Project Rate/Hour | E11: =IF(E10="USD",BlendedRateUSD,BlendedRateGBP) -> 100
B13: Team Assumptions
B14: Projected Work Output
B15: Analysis Hours/BA/Week | E15: 32 | F15: =E15/40*100&"% allocation to project during analysis phase" -> 80% allocation to project during analysis phase
B16: Functional Development Hours/Dev/Week | E16: 32 | F16: =E16/40*100&"% allocation to project during build phase" -> 80% allocation to project during build phase
B17: Team Composition | E17: =SUM(E18:E21) -> 4
B18: BA | E18: 1
B19: Developer | E19: 1
B20: QA | E20: 1
B21: PM | E21: 1
B22: Project Contingency (Range Driver) | E22: 0.25 | F22: Applied to all project phases
B24: 1. Analysis | E24: Hours | F24: Cost
B25: High Level Quote | E25: =SUBTOTAL(9,E28:E34) -> 40 | F25: =AnalysisEstimate*BlendedRate -> 4000
B27: Analysis Tasks
B28: Documentation | E28: =SUBTOTAL(9,E29:E34) -> 40
B29: Analysis Documentation | E29: 36
B30: Client Communication | E30: 4
B36: 2. Development and Testing | E36: Hours | F36: Cost
B37: High Level Quote | E37: =SUBTOTAL(9,E40:E71) -> 114 | F37: =BuildEstimate*BlendedRate -> 11400
B39: Build Tasks
B40: Project Onboarding | E40: 8 | F40: Team familiarization (BA Handover Session, Documentation review), Application Access Testing & Troubleshooting, etc.
B41: Framework & Foundation | E41: 8
B42: Client Demo (Mid Projet) | E42: 8
B43: QA Planning | E43: 8 | F43: Test Plan/Cases, Scenario Analysis
B44: Creation of Test Data | E44: 8
B45: Functional Development | E45: =SUBTOTAL(9,E46:E65) -> 30
B46: Process 1
B47: Tasks | E47: 2
B48: Tasks | E48: 2
B49: Tasks | E49: 2
B50: Tasks | E50: 2
B51: Tasks | E51: 2
B52: Tasks | E52: 2
B53: Tasks | E53: 2
B56: Process 2 | E56: 2
B57: Tasks | E57: 2
B58: Tasks | E58: 2
B59: Tasks | E59: 2
B60: Tasks | E60: 2
... B63: Tasks | E63: 2
B66: Quality Assurance | E66: =SUBTOTAL(9,E67:E70) -> 16 | F66: =ROUND(SumQA/SumFunctionalDevelopment*100,0)&"% Dev/QA ratio" -> 53% Dev/QA ratio
B67: Process 1 Testing | E67: 8
B68: Process 2 Testing | E68: 8
B71: Build Overheads | E71: =SUM(E73:E75) -> 28
B72: Calculated Build Duration (Weeks) | E72: =CEILING(SUM(SumFunctionalDevelopment,SumQA)/(E16*CountDev),0.2) -> 1.6
B73: Team Meetings (Hours/Person/Day) | D73: 0.5 | E73: =D73*SumTeamSize*BuildDuration*5 -> 16
B74: BA Support | D74: 0.15 | E74: =ROUND(D74*SUM(SumFunctionalDevelopment,SumQA),0) -> 7
B75: Project Management | D75: 0.1 | E75: =ROUND(D75*SUM(SumFunctionalDevelopment,SumQA),0) -> 5
B77: 3. User Acceptance Testing | E77: Hours | F77: Cost
B78: High Level Quote | E78: =SUBTOTAL(9,E81:E97) -> 72.5 | F78: =UserAcceptanceTestingEstimate*BlendedRate -> 7250
B80: UAT Tasks | D80: Variables
B81: Staging | E81: =SUBTOTAL(9,E83:E91) -> 69.5
B82: UAT Duration (weeks) | D82: 2
B83: Environment Configuration | E83: 2
B84: Deployments & Smoke Test | E84: 2
B85: UAT User Guide | E85: 4
B86: UAT User Guide Walkthrough | E86: 1
B87: UAT Register | E87: 0.5
B88: Issue Investigation & Resolution | E88: 40
B89: Client and Internal Management | E89: 20
B92: Production | E92: =SUBTOTAL(9,E93:E97) -> 3
B93: Environment Configuration | E93: 1
B94: Deployments & Smoke Test | E94: 1
B95: User Guide | E95: 1
B99: 4. Go Live Support | E99: Hours | F99: Cost
B100: High Level Quote | E100: =SUBTOTAL(9,E103:E107) -> 30 | F100: =GoLiveSupportEstimate*BlendedRate -> 3000
B102: Go Live Support Tasks | D102: Variables
B103: Support Duration (weeks) | D103: 1
B104: Issue Resolution | E104: 20
B105: Client Management | E105: 10
B109: Total Project Cost | E109: Hours | F109: Cost
B110: High Level Quote | E110: =SUM(E25,E37,E78,E100) -> 256.5 | F110: =SUM(F25,F37,F78,F100) -> 25650
B112: Phase Cost and Timelines
B114: Phase | E114: Recommended Duration (w) | F114: Quoted Duration (w) | G114: Cost From | H114: Cost To
B115: Analysis | E115: =CEILING(E28/(E15*'Custom Automation HLQ'!CountBA),0.2) -> 1.4 | F115: =E115 -> 1.4 | G115: =F25 -> 4000 | H115: =G115*(1+$E$22) -> 5000
B116: Build | E116: =E72 -> 1.6 | F116: =E116 -> 1.6 | G116: =F37 -> 11400 | H116: =G116*(1+$E$22) -> 14250
B117: UAT | E117: =D82 -> 2 | F117: =E117 -> 2 | G117: =F78 -> 7250 | H117: =G117*(1+$E$22) -> 9062.5
B118: Support | E118: =D103 -> 1 | F118: =E118 -> 1 | G118: =F100 -> 3000 | H118: =G118*(1+$E$22) -> 3750
B119: Total | E119: =SUM(E115:E118) -> 6 | F119: =SUM(F115:F118) -> 6 | G119: =SUM(G115:G118) -> 25650 | H119: =SUM(H115:H118) -> 32062.5
H121: Lower | I121: =MROUND($H$119*(1-E22/2),250) -> 28000 | J121: =E22*100&"% range driver" -> 25% range driver
H122: Upper | I122: =MROUND($H$119*(1+E22/2),250) -> 36000
H123: Mid | I123: =AVERAGE(I121:I122) -> 32000
H124: Mid vs. Cost To | I124: =I123-H119 -> -62.5

Sheet Delivery Cost Estimate
B1: Instructions
B2: 1. This template should be used to calculate a final delivery cost for an automation solution.
B3: 2. By default, all High Level Quote lines will be populated with the upper bound hours estimate from the HLQ sheet.
B4: Where the Custom Automation HLQ sheet was used, all High Level Quote lines will need to be manually updated.
B5: 3. Review Project variables, notably the Blended Project Rate/Hour which should match that used for the HLQ.
B6: 4. Only white cells should be edited.
B8: > Project Variables
B10: Billing
B11: Currency | E11: USD
B12: Blended Project Rate/Hour | E12: =IF(E11="USD",BlendedRateUSD,BlendedRateGBP) -> 100
B13: Range Driver | E13: 0.25 | F13: Only required when using this template to calculate delivery cost during sales phase (e.g. Statement of Work)
B15: Team Assumptions
B16: Projected Work Output
B17: Functional Development Hours/Dev/Week | E17: 32 | F17: =E17/40*100&"% allocation to project during build phase" -> 80% allocation to project during build phase
B18: Team Composition | E18: =SUM(E19:E22) -> 4
B19: BA | E19: 1
B20: Developer | E20: 1
B21: QA | E21: 1
B22: PM | E22: 1
B24: 1. Analysis | E24: Hours | F24: Cost | G24: Difference | H24: Util %
B25: High Level Quote | E25: =CEILING(HLQ!H8/BlendedRate,0.5) -> 62 | F25: =AnalysisHLQ*BlendedRate -> 6200
B26: Estimate | E26: =SUBTOTAL(9,E30:E36) -> 80 | F26: =AnalysisEstimate*BlendedRate -> 8000 | G26: =F26-F25 -> 1800 | H26: =IFERROR(E26/E25,0) -> 1.2903226
B27: Actuals | F27: =AnalysisActuals*BlendedRate -> 0 | G27: =F27-F26 -> -8000 | H27: =IFERROR(E27/E26,0) -> 0
B29: Analysis Tasks
B30: Documentation | E30: =SUBTOTAL(9,E31:E36) -> 80
B31: Business Process Definition | E31: 20
B32: Functional Requirements Definition | E32: 20
B33: Solution Design Document | E33: 30
B34: Client Communication | E34: 10
B38: 2. Build | E38: Hours | F38: Cost | G38: Difference | H38: Util %
B39: High Level Quote | E39: =CEILING(HLQ!H9/BlendedRate,0.5) -> 161 | F39: =BuildHLQ*BlendedRate -> 16100
B40: Estimate | E40: =SUBTOTAL(9,E44:E97) -> 179 | F40: =BuildEstimate*BlendedRate -> 17900 | G40: =F40-F39 -> 1800 | H40: =IFERROR(E40/E39,0) -> 1.1118012
B41: Actuals | F41: =BuildActuals*BlendedRate -> 0 | G41: =F41-F40 -> -17900 | H41: =IFERROR(E41/E40,0) -> 0
B43: Build Tasks
B44: Project Onboarding | E44: =SUBTOTAL(9,E45:E49) -> 29
B45: Team Familiarization (Hours/Person) | D45: 4 | E45: =D45*SumTeamSize -> 16 | F45: BA Handover Session, Documentation review, etc.
B46: DevOps Setup | E46: 1
B47: Application Access Testing & Troubleshooting | E47: 4
B48: Client Demonstration (Mid Project) | E48: 8
B50: Framework & Foundation | E50: =SUBTOTAL(9,E51:E54) -> 3
B51: Technical Consulting (Consultant / Infra / Lead Dev) | E51: 1
B52: Process Setup | E52: 1
B53: Environment Setup/Configuration | E53: 1
B55: QA Planning | E55: =SUBTOTAL(9,E56:E59) -> 20
B56: Test Plan/Cases | E56: 8
B57: Creation of test data | E57: 8
B58: Preparation of production ready data | E58: 4
B60: Functional Development | E60: =SUBTOTAL(9,E61:E90) -> 31
B61: Process 1
B62: Process Design Document | E62: 1
B63: Object Design Document | E63: 1
B64: Initiation | E64: 10
B65: Step 1 | E65: 1
B66: Step 2 | E66: 1
B67: Completion | E67: 1
B68: Alerts | E68: 1
B71: Process 2 | E71: 1
B72: Process Design Document | E72: 1
B73: Object Design Document | E73: 1
B74: Initiation | E74: 1
B75: Step 1 | E75: 1
... B78: Alerts | E78: 1
B81: Process 3
B82: Process Design Document | E82: 1
B83: Object Design Document | E83: 1
B84: Initiation | E84: 1
B85: Step 1 | E85: 1
B86: Step 2 | E86: 1
B87: Completion | E87: 1
B88: Alerts | E88: 1
B91: Quality Assurance | E91: =SUBTOTAL(9,E92:E96) -> 35 | F91: =ROUND(SumQA/SumFunctionalDevelopment*100,0)&"% Dev/QA ratio" -> 113% Dev/QA ratio
B92: Process 1 Testing | E92: 5
B93: Process 2 Testing | E93: 25
B94: Process 3 Testing | E94: 5
B97: Build Overheads | E97: =SUM(E100*E99,E106,E115) -> 61
B98: Calculated Build Duration (Weeks) | E98: =CEILING(SUM(SumFunctionalDevelopment,SumQA,BuildContingency_UnanticipatedComplexity)/(E17*CountDev),0.2) -> 2.2
B99: Number of Sprints | C99: Calculated | D99: =CEILING(E98,SprintDuration)/SprintDuration -> 2 | E99: =BuildSprints -> 2 | F99: Override calculated number of sprints if required
B100: Per Sprint Overheads | E100: =SUBTOTAL(9,E101:E105) -> 14
B101: Standups (Hours/Person/Day) | D101: 0.25 | E101: =D101*SumTeamSize*SprintDuration*5 -> 10
B102: Planning (Hours/Person) | D102: 0.5 | E102: =D102*SumTeamSize -> 2
B103: Retro (Hours/Person) | D103: 0.5 | E103: =D103*SumTeamSize -> 2
B106: General Overheads | E106: =SUBTOTAL(9,E107:E114) -> 30 | F106: Affects build cost, not duration
B107: Bug Fixing (% Functional Dev) | D107: 0.1 | E107: =ROUND(D107*SumFunctionalDevelopment,0) -> 3
B108: Bug Fixing (% QA) | D108: 0.1 | E108: =ROUND(D108*SumQA,0) -> 4
B109: BA Support | D109: 0.15 | E109: =ROUND(D109*SUM(SumFunctionalDevelopment,SumQA),0) -> 10
B110: Client Reporting (PM Reviews, Other Reporting) | D110: 0.05 | E110: =ROUND(D110*SUM(SumFunctionalDevelopment,SumQA),0) -> 3
B111: General Team Management | D111: 0.1 | E111: =ROUND(D111*SUM(SumFunctionalDevelopment,SumQA),0) -> 7
B112: Code Reviews, Mentorship & Developer Leadership (% Functional Dev) | D112: 0.1 | E112: =ROUND(D112*SumFunctionalDevelopment,0) -> 3
B115: Contingencies | E115: =SUBTOTAL(9,E116:E116) -> 3 | F115: Affects build cost and duration
B116: Unanticipated Complexity | D116: 0.05 | E116: =ROUND(D116*SUM(SumFunctionalDevelopment,SumQA),0) -> 3
B118: 3. UAT | E118: Hours | F118: Cost | G118: Difference | H118: Util %
B119: High Level Quote | E119: =CEILING(HLQ!H10/BlendedRate,0.5) -> 86 | F119: =UserAcceptanceTestingHLQ*BlendedRate -> 8600
B120: Estimate | E120: =SUBTOTAL(9,E124:E142) -> 93.5 | F120: =UserAcceptanceTestingEstimate*BlendedRate -> 9350 | G120: =F120-F119 -> 750 | H120: =IFERROR(E120/E119,0) -> 1.0872093
B121: Actuals | F121: =UserAcceptanceTestingActuals*BlendedRate -> 0 | G121: =F121-F120 -> -9350 | H121: =IFERROR(E121/E120,0) -> 0
B123: UAT Tasks | D123: Variables
B124: Staging | E124: =SUBTOTAL(9,E125:E129) -> 25.5
B125: Environment Configuration | E125: 16 | F125: Including Application Access Testing & Troubleshooting
B126: Deployments & Smoke Test (multiple deployments) | E126: 4
B127: UAT User Guide | E127: 4
B128: User Guide walkthrough | E128: 1
...

Sheet ROM_Analysis Estimate
A2: Phase | B2: Task | D2: Hours | E2: % | F2: Notes | H2: Rate | I2: 120
A3: Analysis Phase | D3: =SUM(C4:C6) -> 40 | F3: 1 week | H3: Contingency | I3: 0
B4: Initial Analysis, Solution Architecture & Backlog creation | C4: 40 | H4: Range Driver | I4: 0.3
P6: Dev Hours | Q6: Lower Bound | R6: Upper Bound
I7: Lower bound | J7: Upper Bound | O7: Email Alerts - Logic Apps | P7: 8 | Q7: =(P7/P$10)*$I$11 -> 10280 | R7: =(P7/P$10)*$J$11 -> 13666.667
A8: Build Phase | B8: 3 weeks | D8: =SUM(C9:C11) -> 180 | F8: 3 weeks | H8: Hours | I8: =D32*(I3+1) -> 257 | J8: =I8*(I4+1) -> 334.1 | O8: Default Tags - Custom Web | P8: 12 | Q8: =(P8/P$10)*$I$11 -> 15420 | R8: =(P8/P$10)*$J$11 -> 20500
B9: Dev | C9: =40*3 -> 120 | H9: Cost | I9: =I8*I2 -> 30840 | J9: =J8*I2 -> 40092 | O9: Wachlist - Custom Web | P9: 4 | Q9: =(P9/P$10)*$I$11 -> 5140 | R9: =(P9/P$10)*$J$11 -> 6833.3333
B10: BA | C10: =40*0.25*3 -> 30 | P10: =SUM(P7:P9) -> 24 | Q10: =SUM(Q7:Q9) -> 30840 | R10: =SUM(R7:R9) -> 41000
B11: QA | C11: =40*0.25*3 -> 30 | H11: Communicated Costs | I11: 30840 | J11: 41000
B12: Bug Fixing - included above | C12: 0
B13: Testing - included above | C13: 0
A15: Project Admin Phase | D15: =SUM(C16:C17) -> 12 | H15: EoT | I15: 150000
B16: Team familiarization | C16: 0 | H16: Homelet | I16: =20900+4000 -> 24900
B17: Project Management | C17: =4*3 -> 12
A19: Implementation Phase
B20: UAT | D20: =SUM(C21:C24) -> 20
B21: Deployments - included above
B22: Smoke Test - included above
B23: Support / Training Manual
B24: UAT Support | C24: =4*5 -> 20 | F24: 1 week
B26: Production | D26: =SUM(C27:C29) -> 5
B27: Deployments | C27: 2 | H27: SOW
B28: Smoke Test | C28: 1 | H28: Phase | I28: Hours | J28: Lower Bound | K28: Upper Bound
B29: Prod Support | C29: 2 | F29: 2 week | H29: Analysis | I29: 40 - 52 | J29: =D3*I2 -> 4800 | K29: =J29*1.3 -> 6240
H30: Build | I30: 180 - 234 | J30: =D8*I2 -> 21600 | K30: =J30*1.3 -> 28080
B31: Project Review | D31: 0 | H31: Project Management | I31: 12 - 15.6 | J31: =D15*I2 -> 1440 | K31: =J31*1.3 -> 1872
D32: =SUM(D3:D31) -> 257 | H32: UAT | I32: 20 - 26 | J32: =D20*I2 -> 2400 | K32: =J32*1.3 -> 3120
H33: Production | I33: 5 - 6.5 | J33: =D26*I2 -> 600 | K33: =J33*1.3 -> 780
I34: =SUM(J29:J33) -> 30840 | J34: =SUM(K25:K27) -> 0
E35: =SUM(E34:E34) -> 0 | I35: =SUM(I26:I30) -> 0
B37: Assupmtions
B40: Exclusions | H40: Total | I40: 257 - 334 | J40: =SUM(J29:J33) -> 30840 | K40: =SUM(K29:K33) -> 40092

Sheet Actuals 18 March
P1: Client Hierarchy - Client | Q1: Client Hierarchy - Project | R1: Client Hierarchy - Section | S1: Client Hierarchy - Task | T1: Sum of Hours | U1: Employee
P2: Grainger PLC | Q2: Website Integration (T&M) | R2: Analysis & Build | S2: Delivery | T2: 99 | U2: Anjali Salecha
P3: Grainger PLC | Q3: Website Integration (T&M) | R3: Analysis & Build | S3: Delivery | T3: 36 | U3: Khonani Davhana
P4: Grainger PLC | Q4: Website Integration (T&M) | R4: Analysis & Build | S4: Delivery | T4: 71 | U4: Matthew Cornfield
P5: Grainger PLC | Q5: Website Integration (T&M) | R5: Analysis & Build | S5: Delivery | T5: 53.25 | U5: Nikki Papenfus
P6: Grainger PLC | Q6: Website Integration (T&M) | R6: Analysis & Build | S6: Delivery | T6: 89.5 | U6: Sachin Deshmukh
P7: Grainger PLC | Q7: Website Integration (T&M) | R7: Analysis & Build | S7: Delivery | T7: 11.75 | U7: Sam Duncan
P8: Grainger PLC | Q8: Website Integration (T&M) | R8: Analysis & Build | S8: Delivery | T8: 3.75 | U8: Shaun Barrett
P12: Sum of Sum of Hours | Q12: Column Labels
P13: Row Labels | Q13: Anjali Salecha | R13: Khonani Davhana | S13: Matthew Cornfield | T13: Nikki Papenfus | U13: Sachin Deshmukh | V13: Sam Duncan | W13: Shaun Barrett | X13: Grand Total
P14: Delivery | Q14: 99 | R14: 36 | S14: 71 | T14: 53.25 | U14: 89.5 | V14: 11.75 | W14: 3.75 | X14: 364.25
P15: Grand Total | Q15: 99 | R15: 36 | S15: 71 | T15: 53.25 | U15: 89.5 | V15: 11.75 | W15: 3.75 | X15: 364.25
P18: Less Matts time | Q18: =GETPIVOTDATA("Sum of Hours",$P$12)-GETPIVOTDATA("Sum of Hours",$P$12,"Employee","Matthew Cornfield") -> 293.25
P23: SOW | T23: Actuals/Forecast | U23: Notes
P24: Phase | Q24: Hours | R24: Lower Bound | S24: Upper Bound | T24: Hours | U24: As at 18 March
P25: Analysis | Q25: 40 - 52 | R25: 4800 | S25: 6240 | T25: =GETPIVOTDATA("Sum of Hours",$P$12,"Employee","Nikki Papenfus") -> 53.25
P26: Build | Q26: 180 - 234 | R26: 21600 | S26: 28080 | T26: =GETPIVOTDATA("Sum of Hours",$P$12,"Employee","Anjali Salecha")+GETPIVOTDATA("Sum of Hours",$P$12,"Employee","Khonani Davhana")+GETPIVOTDATA("Sum of Hours",$P$12,"Employee","Sachin Deshmukh")+GETPIVOTDATA("Sum of Hours",$P$12,"Employee","Sam Duncan")+12 -> 248.25 | U26: + 12 hours Sachine has not logged - Matts time
P27: Project Management | Q27: 12 - 15.6 | R27: 1440 | S27: 1872 | T27: =GETPIVOTDATA("Sum of Hours",$P$12,"Employee","Shaun Barrett") -> 3.75
P28: UAT | Q28: 20 - 26 | R28: 2400 | S28: 3120 | T28: 26 | U28: Estimate
P29: Production | Q29: 5 - 6.5 | R29: 600 | S29: 780 | T29: 6 | U29: Estimate
P30: Total | Q30: 257 - 334 | R30: =SUM(R25:R29) -> 30840 | S30: =SUM(S25:S29) -> 40092 | T30: =SUM(T25:T29) -> 337.25
S31: Estimated remaining effort | T31: =3*8*2 -> 48 | U31: 2 days for 3 people
S32: Reforecasted Total | T32: =T30+T31 -> 385.25
S33: Reforecasted Cost | T33: =T32*'ROM_Analysis Estimate'!I2 -> 46230
Q34: =4800/40 -> 120
Q35: =21600/180 -> 120 | S35: Delta from upper bound | T35: =T33-S30 -> 6138
S36: % | T36: =T33/S30 -> 1.1530979

Sheet Project PTA Tasks
B2: Phase | C2: Section | D2: Task
B3: Delivery | C3: Definition | D3: BPD
D4: FRD
D5: SDD
C6: Pre-Build | D6: Onboarding (BA & Dev handovers etc)
D7: Framework & Foundation
D8: QA Planning
C9: Build | D9: BA Assistance
D10: Deployments
D11: Development
D12: Code Reviews
D13: Documentation
D14: Testing
D15: UAT Feedback
C16: Go Live Support / Hypercare | D16: Investigation
D17: Issue Resolution
B18: Program Management | C18: Client Reporting | D18: Weekly PM Review
D19: Other Reporting
C20: Team Management | D20: Standup
D21: Spring Planning
D22: Sprint Retro
D23: Backlog Grooming
D24: General Project Management
