Workbook

Sheet Revision History
B2: Version | C2: Updated By | D2: Methods Affected by Change | E2: Revision Description
B3: V r1.0 | C3: - | E3: Initial release
B4: V r1.1 | C4: Lee Williams | D4: None - Documentation update | E4: Added Outcome status enum list and changed linkedApplicant ID description
B5: V r1.2 | C5: Lee Williams | D5: None - Documentation update | E5: Ameded Outcome Status enum and added applicant Status enum
B6: V r1.3 | C6: Lee Williams | D6: None - Documentation update | E6: Extended description of Cancel Tenancy
B7: V r1.4 | C7: Lee Williams | D7: None - Documentation update | E7: Extended descriptions and minor wording change
B8: V r1.5 | C8: Lee Williams | D8: None - Documentation update | E8: updated response for addApplicant and updated description to cancellation reason enum

Sheet API Services
B3: API Method Name (Link to Request & Response Examples with Data Structure) | C3: Method Version | D3: Method Description | E3: Method URL
B4: Get Authentication Token | C4: 0.1 | D4: Method to acquire an authentication (bearer) token, using the scope (always "standardapiaccess"), along with the provided clientID and Client secret | E4: Swagger - /standardapi/v1/ Postman - https://preprod-auth-service.letalliance.dev/connect/token
B5: CheckConnection | C5: 0.1 | D5: Simple ping method used to check connectivity between Vision+ API server and client with no parameters. As with all methods, if authentication token is missing or invalid, an error will be returned. If the authentication token is valid and the connection is successful, a success true will be returned. | E5: /standardapi/v1/CheckConnection
B6: CreateReferenceWithAllData | C6: 0.1 | D6: As one of the base methods of the Vision+ API, this method is used to create a property, create tenancy on property and add one or more applicants to be referenced in that property, for systems that gather and provide all required applicant data up front. | E6: /standardapi/v1/CreateReferenceWithAllData
B7: CreateReferenceWithInputFromApplicant | C7: 0.1 | D7: As another base methods of the Vision+ API, this method is used to create a property, create tenancy on property and add one or more applicants to be referenced in that property, for systems that require the applicant to fill in their own data. On submission, an email will be sent to any Applicant in the application, with details on how to log on to the Vision+ Portal and complete the required referencing data. | E7: /standardapi/v1/CreateReferenceWithInputFromApplicant
B8: GetApplicantReferenceStatus | C8: 0.1 | D8: This method is used to check the Applicant referencing status of one or more Applicants. | E8: /standardapi/v1/GetApplicantReferenceStatus/{ApplicantID}
B9: GetAgentActiveProducts | C9: 0.1 | D9: This method is used to get the list of products currently available to the agent to use in referencing applications. Using an invalid product code or a product the agent is not authorised for will cause the reference application request to fail and return an error. | E9: /standardapi/v1/GetAgentActiveProducts/{AgentCode}
B10: GetApplicantReferenceReports | C10: 0.1 | D10: This method provides the applicant available assessment reports as a base64 encoded string, which must be saved as PDF file. An interim report will be available if the appliants referencing application is in progress, and a final report will be avaible when the applicants reference application status is completed. | E10: /standardapi/v1/GetApplicantReferenceReports/{ApplicantID}
B11: PostApplicantReferenceDocument | C11: 0.1 | D11: This method is used to upload documents to support the applicant assessment process. Such as identification, proof of income, rent receipts etc. | E11: /standardapi/v1/PostApplicantReferenceDocument
B12: ResendApplicantReferenceLink | C12: 0.1 | D12: Used in conjunction with the references created with the CreateReferenceWithInputFromApplicant call, This method is used to resend the applicant referencing link to the applicant, to complete the required referencing data. This is not required for reference applications started with the CreateReferenceWithAllData call. | E12: ​/api​/workflow​/StandardIntegration​/ResendApplicantReferenceLink
B13: PostApplicantReferenceNote | C13: 0.1 | D13: This method is used to add notes to the applicant assessment. The note field supports free text and can be used to record additional data. | E13: ​/api​/workflow​/StandardIntegration​/PostApplicantReferenceNote
B14: AddApplicantToTenancy | C14: 0.1 | D14: This method is used to add an additional applicant to a tenancy application. It has a applicant type parameter that denotes whether the applicant will be sent a link to fill out the data themselves or that the data will be provided by the client system. | E14: ​/api​/workflow​/StandardIntegration​/AddApplicantToTenancy
B15: CancelApplicantFromTenancy | C15: 0.1 | D15: This method is used to get cancel a specific applicant from a tenancy application associated with the authenticated agent. | E15: ​/api​/workflow​/StandardIntegration​/CancelApplicantFromTenancy
... B20: CreateCompanyReferenceWithInputFromApplicant | C20: 0.1 | D20: As another base methods of the Vision+ API, this method is used to create a company reference with a property, create tenancy on property and add one or more applicants to be referenced in that property, for systems that require the applicant to fill in their own data. On submission, an email will be sent to any Applicant in the application, with details on how to log on to the Vision+ Portal and complete the required referencing data. | E20: ​/api​/workflow​/StandardIntegration​/CreateCompanyReferenceWithInputFromApplicant

Sheet Entity Relationship Model
A1: Entity Relationship Model

Sheet API Data Dictionary
H1: Methods Used
H2: CheckConnection | J2: CreateReferenceWithAllData | L2: CreateReferenceWithInputFromApplicant | N2: GetApplicantReferenceStatus | P2: GetAgentActiveProducts | R2: GetApplicantReferenceReports | T2: PostApplicantReferenceDocument | V2: ResendApplicantReferenceLink | X2: PostApplicantReferenceNote | Z2: AddApplicantToTenancy | AB2: AmendApplicantType | AD2: CancelApplicantFromTenancy | AF2: CancelTenancy | AH2: AmendTenancyDetails | AJ2: AmendApplicantProductType | AL2: CreateCompanyReferenceWithAllData | AN2: CreateCompanyReferenceWithInputFromApplicant
A3: ID | C3: Vision+ API Field Name | D3: Field Type | E3: API Max Field Length | F3: Field Validations | G3: Field Description | H3: Request | I3: Response | J3: Request | K3: Response | L3: Request | M3: Response | N3: Request | O3: Response | P3: Request | Q3: Response | R3: Request | S3: Response | T3: Request | U3: Response | V3: Request | W3: Response | X3: Request | Y3: Response | Z3: Request | AA3: Response | AB3: Request | AC3: Response | AD3: Request | AE3: Response | AF3: Request | AG3: Response | AH3: Request | AI3: Response | AJ3: Request | AK3: Response | AL3: Request | AM3: Response | AN3: Request | AO3: Response
A4: Agent and Tenancy Data
A5: 1 | B5: Agent and Tenancy Data | C5: tenancyID | D5: string | E5: 50 | G5: TenancyID is a unique key value for an Agent Property with Active referencing requests linked to one or more Applicants. An Agent Property may have one or more TenancyID's with simultaneous Applicant reference requests. TenancyID is created through API methods: CreateReferenceWithAllData CreateReferenceWithInputFromApplicant CreateCompanyReferenceWithAllData CreateCompanyReferenceWithInputFromApplicant | K5: X | M5: X | AM5: X
A6: 2 | C6: applicantID | D6: string | E6: 50 | G6: ApplicantID is a unique identifier for a person / Company to be referenced. ApplicantID may be linked to one or more TenancyID's executing in parallel. ApplicantID is created through API Methods: CreateReferenceWithAllData CreateReferenceWithInputFromApplicant CreateCompanyReferenceWithAllData CreateCompanyReferenceWithInputFromApplicant AddApplicantToTenancy | K6: X | M6: X | N6: M | O6: X | R6: M | T6: M | V6: M | X6: M | AM6: X
A7: 3 | C7: agentCode | D7: string | E7: 50 | G7: AgentCode is the Unique Key provided to the Agent when onboarding as a Barbon Customer. An AgentID may be linked to many Properties being managed by that Agent and Each property may be linked to 1 or more TenancyID's. | J7: M | K7: X | L7: M | P7: M | Q7: X | AL7: M | AM7: X
A8: 4 | C8: Product | D8: string | E8: 200 | G8: Product is a return value for Product description for product(s) available and enabled for the API Authenticated Agent. This includes Referencing Products (Ultimate, Express etc..) and Other services such as Insurance products (Rent on Time, Rent Guarantee etc…) and Media and Utilities. | Q8: X | AL8: M
A9: 5 | C9: rentGuarantee | D9: enum - Rent Guarantee | F9: Valid Values 1-4 (See enum definition) | G9: Rent guarantee is an indicator that determines which RG option if any the agent requires | J9: M | L9: M | AL9: M
A10: 6 | C10: tenancyTermMonths | D10: integer | G10: The term of the Tenancy in months (whole months only) | J10: M | L10: M | AL10: M
A11: 7 | C11: monthlyRental | D11: number (double) | F11: number($double) pattern: ^\d*.\d{0,2}$ | G11: The monthly rental cost | J11: M | L11: M | AL11: M
A12: 8 | C12: lettingType | D12: enum - Letting Type | F12: Valid Values 1-3 (See enum definition) | G12: The type of the letting, i.e. rent only or fully managed | J12: M | L12: M | AL12: M
A13: 9 | C13: estimatedMoveInDate | D13: string ($date-time) | F13: DD/MM/YYYY | G13: Estimated date of tenancy start (move in) | J13: M | L13: M | AL13: M
A14: 10 | C14: propertyType | D14: enum - Property Type | F14: Valid Values 1-6 (See enum definition) | G14: The Type of property | J14: M | L14: M | AL14: X
A15: 11 | C15: propertyConstructionPeriod | D15: enum - Property Construction Period | F15: Valid Values 1-9 (See enum definition) | G15: The time period in which the property was built | J15: X | L15: X | AL15: X
A16: 12 | C16: numberOfBedrooms | D16: integer | G16: The count of bedrooms in the property | J16: X | L16: X | AL16: X
A17: 13 | C17: noOfAdultOccupants | D17: integer | G17: Number of Adult occupants (18 or over) | J17: X | L17: X | AL17: X
A18: 14 | C18: noOfChildOccupants | D18: integer | G18: Number of Child Occupants (under 18) | J18: X | L18: X | AL18: X
A19: 15 | B19: Tenancy Address | C19: houseNumber | D19: string | E19: 100 | G19: The number of the property | J19: X | L19: X | AL19: X
A20: 16 | C20: houseName | D20: string | E20: 100 | G20: The name of the property | J20: X | L20: X | AL20: M
A21: 17 | C21: addressLine1 | D21: string | E21: 100 | G21: The first line of the property address | J21: M | L21: M | AL21: M
A22: 18 | C22: addressLine2 | D22: string | E22: 100 | G22: The second line of the property address | J22: x | L22: x | AL22: x
A23: 19 | C23: town | D23: string | E23: 50 | G23: The town in which the property exists | J23: M | L23: M | AL23: M
A24: 20 | C24: postcode | D24: string | E24: 50 | G24: the postcode of the property | J24: M | L24: M | AL24: M
A25: 21 | C25: ukCountryCode | D25: enum - UK Country List | F25: Valid Values 1-4 (See enum definition) | G25: The UK country Code | J25: M | L25: M | AL25: M
A26: Applicant Data (Tenant / Guarantor)
A27: 22 | B27: Tenant Name and Contact Data | C27: ApplicantStatus | D27: enum - Applicant Status | G27: A return value for the tenant's status (using method GetApplicantReferenceStatus) | O27: X
A28: 23 | C28: OutcomeStatus | D28: enum - outcome | G28: A return value for the reference grading status (using method GetApplicantReferenceStatus) | O28: X
A29: 24 | C29: tenantTypeId | D29: enum - Tenant Type | F29: Valid Values 1-4 (See enum definition) | G29: The Type of the Tenant, e.g. lead or Guarantor | J29: M | L29: M | AL29: M
A30: 25 | C30: referenceType | D30: enum - Reference Type | F30: Valid Values 1-2 (See enum definition) | G30: The Type of reference, e.g Full or Express | J30: M | L30: M | AL30: M
A31: 26 | C31: rightToRent | D31: boolean | G31: Use Right to rent product for this reference | J31: M | L31: M | AL31: M
A32: 27 | C32: title | D32: enum - Title | F32: Valid Values 1-7 (See enum definition) | G32: The persons title, e.g. Mr, Mrs, etc. | J32: M | L32: M
A33: 28 | C33: otherTitle | D33: string | E33: 100 | G33: If other is chosen for title, this is a text field to enter the specific title | J33: X | L33: X
A34: 29 | C34: firstName | D34: string | E34: 100 | F34: pattern: ^[a-zA-Z0-9\-' ]*$ | G34: First name, validated against the RegEx pattern | J34: M | L34: M
A35: 30 | C35: middleName | D35: string | E35: 50 | F35: pattern: ^[a-zA-Z0-9\-' ]*$ | G35: Middle name, validated against the RegEx pattern | J35: X | L35: X
A36: 31 | C36: surname | D36: string | E36: 100 | F36: pattern: ^[a-zA-Z0-9\-' ]*$ | G36: Surname name, validated against the RegEx pattern | J36: M | L36: M
A37: 32 | C37: shareOfRent | D37: number (double) | F37: pattern: ^\d*.\d{0,2}$ | G37: GBP value of the applicants share of the rent | J37: M | L37: M | AL37: M
A38: 33 | C38: dateOfBirth | D38: string ($date-time) | F38: DD/MM/YYYY | G38: The date of birth, formatted DD-MM-YYYY | J38: M
A39: 34 | C39: companyName | D39: string | E39: 100 | G39: Name of the company | J39: X | AL39: M
A40: 35 | C40: companyRegistrationNumber | D40: string | E40: 100 | G40: Registration number of the company | J40: X | AL40: M
A41: 36 | C41: incorporationDate | D41: string ($date-time) | F41: DD/MM/YYYY | G41: Incorperation date of the company, formatted DD-MM-YYYY | J41: X | AL41: M
A42: 37 | C42: telephoneCountryID | D42: enum -Country/Location Code | F42: Valid Values 1-239 (See enum definition) | G42: The country/location code of the phone number | J42: M | L42: M | AL42: M
A43: 38 | C43: contactTelephoneNo | D43: string | E43: 15 | F43: pattern: ^(\d{11})$ | G43: The telephone number | J43: M | L43: M | AL43: M
A44: 39 | C44: emailAddress | D44: string ($email) | E44: 200 | F44: pattern: ^(?!.*\.\.)(?!.*\\_\\_)(?!.*\-\-)[a-zA-Z0-9][-a-zA-Z0-9._]+[a-zA-Z0-9]@([-a-zA-Z0-9]+.)+[a-zA-Z]{2,5}$ | G44: The email address | J44: M | L44: M | AL44: M
A45: 40 | C45: mobileCountryId | D45: enum -Country/Location Code | F45: Valid Values 1-239 (See enum definition) | G45: The country/location code of the mobile phone number | J45: M | AL45: M
A46: 41 | C46: mobileNumber | D46: string | E46: 15 | F46: pattern: ^(\d{11})$ | G46: The mobile phone number | J46: X | AL46: X
A47: 42 | C47: companyPositionId | D47: enum - Company Position | G47: The position / role at the company
A48: 43 | C48: position | D48: string | E48: 200 | G48: If Other is chosen for position, this is a text field to enter the specific position
A49: 44 | C49: isCompanyEmployee | D49: boolean | G49: Is a company employee
A50: 45 | C50: nationality | D50: enum - Nationality | F50: Valid Values 1-231 (See enum definition) | G50: The nationality, from the nationality enum list | J50: M
A51: 46 | C51: niNumber | D51: string | E51: 100 | F51: pattern: ^[a-zA-Z]{2}(?:\d){6}[a-zA-Z]{1}$ | G51: NI Number, matched to RegEx pattern | J51: X
A52: 47 | C52: residentStatus | D52: enum - resident Status | F52: Valid Values 1-2 (See enum definition) | G52: Denotes the resident status e.g. UK resident | J52: M
A53: 48 | C53: additionalInformation | D53: string | E53: 65535 | G53: Free text field for additional information | J53: X | AL53: X
A54: 49 | C54: isAdvanceRent | D54: boolean | G54: Denotes whether rent is paid in advance | J54: M
A55: 50 | B55: Alias Data | C55: firstName | D55: string | E55: 100 | F55: pattern: ^[a-zA-Z0-9\-' ]*$ | G55: First name, validated against the RegEx pattern | J55: X
A56: 51 | C56: middleName | D56: string | E56: 50 | F56: pattern: ^[a-zA-Z0-9\-' ]*$ | G56: Middle name, validated against the RegEx pattern | J56: X
A57: 52 | C57: lastName | D57: string | E57: 100 | F57: pattern: ^[a-zA-Z0-9\-' ]*$ | G57: Surname name, validated against the RegEx pattern | J57: X
A58: 53 | C58: nameChangeDate | D58: string ($date-time) | F58: DD/MM/YYYY | G58: Date the name was changed, formatted DD/MM/YYYY | J58: X
A59: 54 | B59: Tenant Address Data | C59: houseNumber | D59: string | E59: 100 | G59: The number of the property | J59: X
A60: 55 | C60: houseName | D60: string | E60: 100 | G60: The name of the property | J60: X
A61: 56 | C61: addressLine1 | D61: string | E61: 100 | G61: The first line of the property address | J61: M
A62: 57 | C62: addressLine2 | D62: string | E62: 100 | G62: The second line of the property address | J62: x
A63: 58 | C63: town | D63: string | E63: 100 | G63: The town in which the property exists | J63: M
A64: 59 | C64: postcode | D64: string | E64: 50 | G64: the postcode of the property | J64: M
A65: 60 | C65: country | D65: enum -Country/Location Code | F65: Valid Values 1-239 (See enum definition) | G65: The Country code from the enum list, e.g. France | J65: M
A66: 61 | C66: isUKAddress | D66: boolean | G66: Denotes if the address is in the UK | J66: M
A67: 62 | C67: addressTypeId | D67: enum - address Type | F67: Valid Values 1-2 (See enum definition) | G67: Whether the address is current or previous, chosen from enum list | J67: M
A68: 63 | C68: monthMovedIn | D68: enum - month | F68: Valid Values 1-12 (Jan - Dec) | G68: Month the property was moved into, chosen from enum list | J68: M
A69: 64 | C69: yearMovedIn | D69: integer | E69: 4 | F69: Valid Values 1900 - Current Year | G69: Year the property was moved into, formatted YYYY | J69: M
A70: 65 | B70: Tenant Residential Data | C70: currentResidentialStatus | D70: enum - residentStatus | F70: Valid Values 1-3 (See enum definition) | G70: The current residential status, e.g. UK Resident | J70: M
A71: 66 | C71: currentRentAmount | D71: number (double) | F71: pattern: ^\d*.\d{0,2}$ | G71: The current rent amount in GBP | J71: X
A72: 67 | C72: landlordName | D72: string | E72: 500 | G72: Full name of the Landlord | J72: X
A73: 68 | C73: landlordContactCountryId | D73: enum -Country/Location Code | F73: Valid Values 1-239 (See enum definition) | G73: The country/location code of the landlord contact phone number | J73: M
A74: 69 | C74: landlordContactNumber | D74: string | E74: 15 | F74: pattern: ^(\d{11})$ | G74: The Landlords contact Telephone number | J74: X
A75: 70 | C75: landlordMobileCountryId | D75: enum -Country/Location Code | F75: Valid Values 1-239 (See enum definition) | G75: The country/location code of the landlord mobile phone number | J75: M
A76: 71 | C76: landlordMobileNumber | D76: string | E76: 15 | F76: pattern: ^(\d{11})$ | G76: the landlords mobile Telephone number | J76: X
A77: 72 | C77: landlordEmail | D77: string ($email) | E77: 200 | F77: pattern: ^(?!.*\.\.)(?!.*\\_\\_)(?!.*\-\-)[a-zA-Z0-9][-a-zA-Z0-9._]+[a-zA-Z0-9]@([-a-zA-Z0-9]+.)+[a-zA-Z]{2,5}$ | G77: The landlords email address | J77: X
A78: 73 | C78: House Number | D78: string | E78: 100 | G78: The number of the property | J78: X
A79: 74 | C79: House Name | D79: string | E79: 100 | G79: The name of the property | J79: X
A80: 75 | C80: addressLine1 | D80: string | E80: 100 | G80: The first line of the property address | J80: X
A81: 76 | C81: addressLine2 | D81: string | E81: 100 | G81: The second line of the property address | J81: X
A82: 77 | C82: town | D82: string | E82: 50 | G82: The town in which the property exists | J82: X
A83: 78 | C83: country | D83: enum -Country/Location Code | F83: Valid Values 1-239 (See enum definition) | G83: The Country code from the enum list, e.g. France | J83: M
A84: 79 | C84: postcode | D84: string | E84: 50 | G84: the postcode of the property | J84: X
A85: 80 | B85: Adverse Data | C85: submittedisAdverseCredit | D85: boolean | G85: Boolean for is adverse credit | J85: M
A86: 81 | C86: submittedisCCJ | D86: boolean | G86: Boolean for is County court judgment | J86: M
A87: 82 | C87: submittedisBankruptcy | D87: boolean | G87: Boolean for is bankruptcy | J87: M
A88: 83 | C88: SubmittedisInsolvency | D88: boolean | G88: Boolean for is Insolvency | J88: M
A89: 84 | C89: submittedisOtherAdverseCredit | D89: boolean | G89: Boolean for is other Adverse credit | J89: M
A90: 85 | C90: submittedOtherAdverseCreditDesc | D90: string | E90: 1000 | G90: If submittedisOtherAdverseCredit is True, the free text field for adverse credit | J90: M
A91: Applicant Income Data (Tenant / Guarantor)
A92: 86 | B92: Income Type | C92: incomeTypeID | D92: enum - Income Type | F92: Valid Values 1,2,3,5,6,7,8 (See enum definition) | G92: The Income Type, e.g savings or employed | J92: M
A93: 87 | C93: incomeTermID | D93: enum - Income Term | F93: Valid Values 1-4 (See enum definition) | G93: Income term, e.g monthly or weekly | J93: M
A94: 88 | B94: Employed | C94: countryOfEmployment | D94: enum -Country/Location Code | F94: Valid Values 1-239 (See enum definition) | G94: The Country of employment, from the enum list, e.g. France | J94: X
A95: 89 | C95: employersName | D95: string | E95: 100 | F95: pattern: ^[a-zA-Z0-9\-' ]*$ | G95: Name of the company the person is employed by | J95: X
A96: 90 | C96: jobTitle | D96: string | E96: 100 | F96: pattern: ^[A-Za-z ']+$ | G96: Job title at the company the person is employed by | J96: X
A97: 91 | C97: startDateofEmployment | D97: string ($date-time) | F97: DD/MM/YYYY | G97: Start date of employment, formatted DD/MM/YYYY | J97: X
A98: 92 | C98: employmentGrossAnnualIncome | D98: number (double) | F98: pattern: ^\d*.\d{0,2}$ | G98: Gross annual income in GBP | J98: X
A99: 93 | C99: employmentBonuses | D99: boolean | G99: Denotes if bonuses are recieved from the company the person is employed by | J99: X
A100: 94 | C100: employmentOvertimeReceived | D100: boolean | G100: Denotes if overtime is recieved from the company the person is employed by | J100: X
...

Sheet Enum Countries
B2: Enum Field | C2: Country/Location Code
B3: Description | C3: The country or location - NB. includes legacy options Fields mapped to this enum list include: telephoneCountryID mobileCountryId country landlordContactCountryId landlordMobileCountryId countryOfEmployment employmentRefereeContactCountryID employmentRefereeMobileCountryID accountantContactNoCountryId accountantMobileNoCountryId
B4: Value ID | C4: Value Name | D4: Value Description
B5: 1 | C5: Cyprus
B6: 2 | C6: United Kingdom
B7: 3 | C7: India
B8: 4 | C8: USA
B9: 5 | C9: Andorra
B10: 6 | C10: United Arab Emirates
B11: 7 | C11: Afghanistan
B12: 8 | C12: Antigua and Barbuda
B13: 9 | C13: Anguilla
B14: 10 | C14: Albania
B15: 11 | C15: Armenia
B16: 12 | C16: Netherlands Antilles
... B238: 239 | C238: Zimbabwe

Sheet Enum Short Lists
B3: Enum Field | C3: RentGuarantee
B4: Description | C4: Rent guarantee is a product option in Vision+ that provides a guaranteed payment of rent. The options for the rent guarantee are in the table
B5: Value ID | C5: Value Name | D5: Value Description
B6: 1 | C6: Yes, Annual
B7: 2 | C7: Yes, Monthly
B8: 3 | C8: Tenant Evict Only
B9: 4 | C9: No
B12: Enum Field | C12: Title
B13: Description | C13: This is the name prefix for the tenant. If Other is chosen, a free text field is required to be filled in
B14: Value ID | C14: Value Name | D14: Value Description
B15: 1 | C15: Mr
B16: 2 | C16: Mrs
B17: 3 | C17: Miss
B18: 4 | C18: Dr
B19: 5 | C19: Ms
B20: 6 | C20: Other | D20: Free text field become mandatory
B21: 7 | C21: Mx
B24: Enum Field | C24: PropertyConstructionPeriod
B25: Description | C25: This is a range of years denoting the period in which the property was built
B26: Value ID | C26: Value Name | D26: Value Description
B27: 1 | C27: Pre 1850
B28: 2 | C28: 1850 – 1899
B29: 3 | C29: 1900 – 1919
B30: 4 | C30: 1920 – 1945
B31: 5 | C31: 1946 – 1979
B32: 6 | C32: 1980 – 1990
B33: 7 | C33: 1991 – 2000
B34: 8 | C34: 2001 – 2010
B35: 9 | C35: 2011 +
B38: Enum Field | C38: ? Which field is this in the Create Request
B39: Description | C39: Other name that the tenant has been known by
B40: Value ID | C40: Value Name | D40: Value Description
B41: 1 | C41: Other Name
B42: 2 | C42: Another Name
B45: Enum Field | C45: monthMovedIn
B46: Description | C46: The standard month options
B47: Value ID | C47: Value Name | D47: Value Description
B48: 1 | C48: January
B49: 2 | C49: February
B50: 3 | C50: March
B51: 4 | C51: April
B52: 5 | C52: May
B53: 6 | C53: June
B54: 7 | C54: July
B55: 8 | C55: August
B56: 9 | C56: September
B57: 10 | C57: October
B58: 11 | C58: November
B59: 12 | C59: December
B62: Enum Field | C62: TermType
B63: Description | C63: Term type details the period length of term for multiple uses such as dividend term. Fields mapped to this enum list include: employmentBonusTerm employmentOvertimeTerm, taxCreditTerm, carerAllowanceTerm childBenefitTerm disabilityBenefitTerm fosterAllowanceTerm guardianAllowanceTerm childMaintenanceTerm housingBenefitTerm universalCreditTerm
B64: Value ID | C64: Value Name | D64: Value Description
B65: 1 | C65: Daily
B66: 2 | C66: Weekly
B67: 3 | C67: Two Weekly
B68: 4 | C68: Four Weekly
B69: 5 | C69: Monthly
B70: 6 | C70: Quarterly
B71: 7 | C71: Annually
B74: Enum Field | C74: incomeTermID
B75: Description | C75: Payment schedule details the period length of term for payment schedule
B76: Value ID | C76: Value Name | D76: Value Description
B77: 1 | C77: Monthly
B78: 2 | C78: Weekly
B79: 3 | C79: Quarterly
B80: 4 | C80: Yearly
B83: Enum Field | C83: lettingType
B84: Description | C84: The type of property let
B85: Value ID | C85: Value Name | D85: Value Description
B86: 1 | C86: Let Only
B87: 2 | C87: Fully Managed
B88: 3 | C88: Rent Collect
B91: Enum Field | C91: tenantTypeId | I91: OCR ROle
B92: Description | C92: The type of tenant | I92: Lead Tenant | J92: LeadTenant
B93: Value ID | C93: Value Name | D93: Value Description | I93: Tenant | J93: Tenant
B94: 1 | C94: LeadTenant | I94: Permitted Occupier
B95: 2 | C95: Tenant | I95: Guarantor | J95: Guarantor
B96: 3 | C96: Guarantor | I96: Relevant Person | J96: Tenant - Company
B97: 4 | C97: Tenant - Company
B100: Enum Field | C100: employmentTypeId
B101: Description | C101: The type of employment the tenant has
B102: Value ID | C102: Value Name | D102: Value Description
B103: 1 | C103: Permanent-Full Time
B104: 2 | C104: Permanent-Part Time
B105: 3 | C105: Temporary-Full Time
B106: 4 | C106: Temporary -Part Time
B109: Enum Field | C109: tradingTypeId
B110: Description | C110: The trading type of the tenants company
B111: Value ID | C111: Value Name | D111: Value Description
B112: 1 | C112: Sole Trader/Partner
B113: 2 | C113: Limited Company
B114: 3 | C114: N/A | D114: Not valid outside internal testing
B115: 4 | C115: N/A | D115: Not valid outside internal testing
B118: Enum Field | C118: referenceType
B119: Description | C119: The type of tenant reference available to the agent.
B120: Value ID | C120: Value Name | D120: Value Description
B121: 1 | C121: Full Reference
B122: 2 | C122: Express Reference
B123: 3 | C123: Nonreference | D123: Not valid outside internal testing
B126: Enum Field | C126: residentStatus
...

Sheet Enum Nationalities
B2: Enum Field | C2: nationality
B3: Description | C3: The country or location - NB includes legacy options
B4: Value ID | C4: Value Name | D4: Value Description
B5: 1 | C5: Afghan
B6: 2 | C6: Albanian
B7: 3 | C7: Algerian
B8: 4 | C8: American
B9: 5 | C9: Andorran
B10: 6 | C10: Angolan
B11: 7 | C11: Anguillan
B12: 8 | C12: Citizen of Antigua and Barbuda
B13: 9 | C13: Argentine
B14: 10 | C14: Armenian
B15: 11 | C15: Australian
B16: 12 | C16: Austrian
... B235: 231 | C235: Zairian

Sheet CreateReferenceWithInputFromApp
A1: SF Mapping Details | B1: SF Field Mapping | C1: CreateReferenceWithInputFromApplicant Example JSON | D1: Vision+ API Field Name | E1: Mandatory Field | F1: Field Type | G1: API Max Field Length | H1: Field Validations | I1: Field Description
C2: Request Example
C3: { | D3: =IF(OR(ISNUMBER(SEARCH("{", C3)),ISNUMBER(SEARCH("[", C3))), "", IFERROR(MID(C3, SEARCH("""", C3) +1, SEARCH("""", C3, SEARCH("""",C3) +1) - SEARCH("""", C3) -1), "")) | E3: =IF(D3="", "", VLOOKUP(D3,'API Data Dictionary'!C:L,10,FALSE)) | F3: =IF(D3="", "", VLOOKUP(D3,'API Data Dictionary'!C:D,2,FALSE)) | G3: =IF(IF(D3="", "", VLOOKUP(D3,'API Data Dictionary'!C:E,3,FALSE))=0, "", IF(D3="", "", VLOOKUP(D3,'API Data Dictionary'!C:E,3,FALSE))) | H3: =IF(IF(D3="", "", VLOOKUP(D3,'API Data Dictionary'!C:F,4,FALSE))=0, "", IF(D3="", "", VLOOKUP(D3,'API Data Dictionary'!C:F,4,FALSE))) | I3: =IF(IF(D3="", "", VLOOKUP(D3,'API Data Dictionary'!C:G,5,FALSE))=0, "", IF(D3="", "", VLOOKUP(D3,'API Data Dictionary'!C:G,5,FALSE)))
B4: Referencing_HL_Auth_Setting__mdt.Agent_Code__c; | C4: "agentCode": "9999", | D4: =IF(OR(ISNUMBER(SEARCH("{", C4)),ISNUMBER(SEARCH("[", C4))), "", IFERROR(MID(C4, SEARCH("""", C4) +1, SEARCH("""", C4, SEARCH("""",C4) +1) - SEARCH("""", C4) -1), "")) -> agentCode | E4: =IF(D4="", "", VLOOKUP(D4,'API Data Dictionary'!C:L,10,FALSE)) -> M | F4: =IF(D4="", "", VLOOKUP(D4,'API Data Dictionary'!C:D,2,FALSE)) -> string | G4: =IF(IF(D4="", "", VLOOKUP(D4,'API Data Dictionary'!C:E,3,FALSE))=0, "", IF(D4="", "", VLOOKUP(D4,'API Data Dictionary'!C:E,3,FALSE))) -> 50 | H4: =IF(IF(D4="", "", VLOOKUP(D4,'API Data Dictionary'!C:F,4,FALSE))=0, "", IF(D4="", "", VLOOKUP(D4,'API Data Dictionary'!C:F,4,FALSE))) | I4: =IF(IF(D4="", "", VLOOKUP(D4,'API Data Dictionary'!C:G,5,FALSE))=0, "", IF(D4="", "", VLOOKUP(D4,'API Data Dictionary'!C:G,5,FALSE))) -> AgentCode is the Unique Key provided to the Agent when onboarding as a Barbon Customer. An AgentID may be linked to many Properties being managed by that Agent and Each property may be linked to 1 or more TenancyID's.
B5: <hard code to 4> | C5: "rentGuarantee": 4, | D5: =IF(OR(ISNUMBER(SEARCH("{", C5)),ISNUMBER(SEARCH("[", C5))), "", IFERROR(MID(C5, SEARCH("""", C5) +1, SEARCH("""", C5, SEARCH("""",C5) +1) - SEARCH("""", C5) -1), "")) -> rentGuarantee | E5: =IF(D5="", "", VLOOKUP(D5,'API Data Dictionary'!C:L,10,FALSE)) -> M | F5: =IF(D5="", "", VLOOKUP(D5,'API Data Dictionary'!C:D,2,FALSE)) -> enum - Rent Guarantee | G5: =IF(IF(D5="", "", VLOOKUP(D5,'API Data Dictionary'!C:E,3,FALSE))=0, "", IF(D5="", "", VLOOKUP(D5,'API Data Dictionary'!C:E,3,FALSE))) | H5: =IF(IF(D5="", "", VLOOKUP(D5,'API Data Dictionary'!C:F,4,FALSE))=0, "", IF(D5="", "", VLOOKUP(D5,'API Data Dictionary'!C:F,4,FALSE))) -> Valid Values 1-4 (See enum definition) | I5: =IF(IF(D5="", "", VLOOKUP(D5,'API Data Dictionary'!C:G,5,FALSE))=0, "", IF(D5="", "", VLOOKUP(D5,'API Data Dictionary'!C:G,5,FALSE))) -> Rent guarantee is an indicator that determines which RG option if any the agent requires
B6: opp.Agreed_Terms__c | C6: "tenancyTermMonths": 12, | D6: =IF(OR(ISNUMBER(SEARCH("{", C6)),ISNUMBER(SEARCH("[", C6))), "", IFERROR(MID(C6, SEARCH("""", C6) +1, SEARCH("""", C6, SEARCH("""",C6) +1) - SEARCH("""", C6) -1), "")) -> tenancyTermMonths | E6: =IF(D6="", "", VLOOKUP(D6,'API Data Dictionary'!C:L,10,FALSE)) -> M | F6: =IF(D6="", "", VLOOKUP(D6,'API Data Dictionary'!C:D,2,FALSE)) -> integer | G6: =IF(IF(D6="", "", VLOOKUP(D6,'API Data Dictionary'!C:E,3,FALSE))=0, "", IF(D6="", "", VLOOKUP(D6,'API Data Dictionary'!C:E,3,FALSE))) | H6: =IF(IF(D6="", "", VLOOKUP(D6,'API Data Dictionary'!C:F,4,FALSE))=0, "", IF(D6="", "", VLOOKUP(D6,'API Data Dictionary'!C:F,4,FALSE))) | I6: =IF(IF(D6="", "", VLOOKUP(D6,'API Data Dictionary'!C:G,5,FALSE))=0, "", IF(D6="", "", VLOOKUP(D6,'API Data Dictionary'!C:G,5,FALSE))) -> The term of the Tenancy in months (whole months only)
B7: opp.Monthly_Price__c | C7: "monthlyRental": 2000, | D7: =IF(OR(ISNUMBER(SEARCH("{", C7)),ISNUMBER(SEARCH("[", C7))), "", IFERROR(MID(C7, SEARCH("""", C7) +1, SEARCH("""", C7, SEARCH("""",C7) +1) - SEARCH("""", C7) -1), "")) -> monthlyRental | E7: =IF(D7="", "", VLOOKUP(D7,'API Data Dictionary'!C:L,10,FALSE)) -> M | F7: =IF(D7="", "", VLOOKUP(D7,'API Data Dictionary'!C:D,2,FALSE)) -> number (double) | G7: =IF(IF(D7="", "", VLOOKUP(D7,'API Data Dictionary'!C:E,3,FALSE))=0, "", IF(D7="", "", VLOOKUP(D7,'API Data Dictionary'!C:E,3,FALSE))) | H7: =IF(IF(D7="", "", VLOOKUP(D7,'API Data Dictionary'!C:F,4,FALSE))=0, "", IF(D7="", "", VLOOKUP(D7,'API Data Dictionary'!C:F,4,FALSE))) -> number($double) pattern: ^\d*.\d{0,2}$ | I7: =IF(IF(D7="", "", VLOOKUP(D7,'API Data Dictionary'!C:G,5,FALSE))=0, "", IF(D7="", "", VLOOKUP(D7,'API Data Dictionary'!C:G,5,FALSE))) -> The monthly rental cost
B8: <hard code to 2> | C8: "lettingType": 1, | D8: =IF(OR(ISNUMBER(SEARCH("{", C8)),ISNUMBER(SEARCH("[", C8))), "", IFERROR(MID(C8, SEARCH("""", C8) +1, SEARCH("""", C8, SEARCH("""",C8) +1) - SEARCH("""", C8) -1), "")) -> lettingType | E8: =IF(D8="", "", VLOOKUP(D8,'API Data Dictionary'!C:L,10,FALSE)) -> M | F8: =IF(D8="", "", VLOOKUP(D8,'API Data Dictionary'!C:D,2,FALSE)) -> enum - Letting Type | G8: =IF(IF(D8="", "", VLOOKUP(D8,'API Data Dictionary'!C:E,3,FALSE))=0, "", IF(D8="", "", VLOOKUP(D8,'API Data Dictionary'!C:E,3,FALSE))) | H8: =IF(IF(D8="", "", VLOOKUP(D8,'API Data Dictionary'!C:F,4,FALSE))=0, "", IF(D8="", "", VLOOKUP(D8,'API Data Dictionary'!C:F,4,FALSE))) -> Valid Values 1-3 (See enum definition) | I8: =IF(IF(D8="", "", VLOOKUP(D8,'API Data Dictionary'!C:G,5,FALSE))=0, "", IF(D8="", "", VLOOKUP(D8,'API Data Dictionary'!C:G,5,FALSE))) -> The type of the letting, i.e. rent only or fully managed
B9: opp.Move_In_Date__c | C9: "estimatedMoveInDate": "2023-04-01T10:55:02.383Z", | D9: =IF(OR(ISNUMBER(SEARCH("{", C9)),ISNUMBER(SEARCH("[", C9))), "", IFERROR(MID(C9, SEARCH("""", C9) +1, SEARCH("""", C9, SEARCH("""",C9) +1) - SEARCH("""", C9) -1), "")) -> estimatedMoveInDate | E9: =IF(D9="", "", VLOOKUP(D9,'API Data Dictionary'!C:L,10,FALSE)) -> M | F9: =IF(D9="", "", VLOOKUP(D9,'API Data Dictionary'!C:D,2,FALSE)) -> string ($date-time) | G9: =IF(IF(D9="", "", VLOOKUP(D9,'API Data Dictionary'!C:E,3,FALSE))=0, "", IF(D9="", "", VLOOKUP(D9,'API Data Dictionary'!C:E,3,FALSE))) | H9: =IF(IF(D9="", "", VLOOKUP(D9,'API Data Dictionary'!C:F,4,FALSE))=0, "", IF(D9="", "", VLOOKUP(D9,'API Data Dictionary'!C:F,4,FALSE))) -> DD/MM/YYYY | I9: =IF(IF(D9="", "", VLOOKUP(D9,'API Data Dictionary'!C:G,5,FALSE))=0, "", IF(D9="", "", VLOOKUP(D9,'API Data Dictionary'!C:G,5,FALSE))) -> Estimated date of tenancy start (move in)
A10: SF Picklist vs Homelet Enums //TODO | B10: <check with HomeLet if we can hard code to "Other"> Referencing_HL_Mapping_Constant__mdt.propertyType = 6 | C10: "propertyType": 1, | D10: =IF(OR(ISNUMBER(SEARCH("{", C10)),ISNUMBER(SEARCH("[", C10))), "", IFERROR(MID(C10, SEARCH("""", C10) +1, SEARCH("""", C10, SEARCH("""",C10) +1) - SEARCH("""", C10) -1), "")) -> propertyType | E10: =IF(D10="", "", VLOOKUP(D10,'API Data Dictionary'!C:L,10,FALSE)) -> M | F10: =IF(D10="", "", VLOOKUP(D10,'API Data Dictionary'!C:D,2,FALSE)) -> enum - Property Type | G10: =IF(IF(D10="", "", VLOOKUP(D10,'API Data Dictionary'!C:E,3,FALSE))=0, "", IF(D10="", "", VLOOKUP(D10,'API Data Dictionary'!C:E,3,FALSE))) | H10: =IF(IF(D10="", "", VLOOKUP(D10,'API Data Dictionary'!C:F,4,FALSE))=0, "", IF(D10="", "", VLOOKUP(D10,'API Data Dictionary'!C:F,4,FALSE))) -> Valid Values 1-6 (See enum definition) | I10: =IF(IF(D10="", "", VLOOKUP(D10,'API Data Dictionary'!C:G,5,FALSE))=0, "", IF(D10="", "", VLOOKUP(D10,'API Data Dictionary'!C:G,5,FALSE))) -> The Type of property
C11: "propertyConstructionPeriod": 4, | D11: =IF(OR(ISNUMBER(SEARCH("{", C11)),ISNUMBER(SEARCH("[", C11))), "", IFERROR(MID(C11, SEARCH("""", C11) +1, SEARCH("""", C11, SEARCH("""",C11) +1) - SEARCH("""", C11) -1), "")) -> propertyConstructionPeriod | E11: =IF(D11="", "", VLOOKUP(D11,'API Data Dictionary'!C:L,10,FALSE)) -> X | F11: =IF(D11="", "", VLOOKUP(D11,'API Data Dictionary'!C:D,2,FALSE)) -> enum - Property Construction Period | G11: =IF(IF(D11="", "", VLOOKUP(D11,'API Data Dictionary'!C:E,3,FALSE))=0, "", IF(D11="", "", VLOOKUP(D11,'API Data Dictionary'!C:E,3,FALSE))) | H11: =IF(IF(D11="", "", VLOOKUP(D11,'API Data Dictionary'!C:F,4,FALSE))=0, "", IF(D11="", "", VLOOKUP(D11,'API Data Dictionary'!C:F,4,FALSE))) -> Valid Values 1-9 (See enum definition) | I11: =IF(IF(D11="", "", VLOOKUP(D11,'API Data Dictionary'!C:G,5,FALSE))=0, "", IF(D11="", "", VLOOKUP(D11,'API Data Dictionary'!C:G,5,FALSE))) -> The time period in which the property was built
B12: opp.Primary_Offer__r.Unit__r.Bedrooms__c | C12: "numberOfBedrooms": 4, | D12: =IF(OR(ISNUMBER(SEARCH("{", C12)),ISNUMBER(SEARCH("[", C12))), "", IFERROR(MID(C12, SEARCH("""", C12) +1, SEARCH("""", C12, SEARCH("""",C12) +1) - SEARCH("""", C12) -1), "")) -> numberOfBedrooms | E12: x | F12: =IF(D12="", "", VLOOKUP(D12,'API Data Dictionary'!C:D,2,FALSE)) -> integer | G12: =IF(IF(D12="", "", VLOOKUP(D12,'API Data Dictionary'!C:E,3,FALSE))=0, "", IF(D12="", "", VLOOKUP(D12,'API Data Dictionary'!C:E,3,FALSE))) | H12: =IF(IF(D12="", "", VLOOKUP(D12,'API Data Dictionary'!C:F,4,FALSE))=0, "", IF(D12="", "", VLOOKUP(D12,'API Data Dictionary'!C:F,4,FALSE))) | I12: =IF(IF(D12="", "", VLOOKUP(D12,'API Data Dictionary'!C:G,5,FALSE))=0, "", IF(D12="", "", VLOOKUP(D12,'API Data Dictionary'!C:G,5,FALSE))) -> The count of bedrooms in the property
B13: opp.Number_of_occupants__c count number of OpportunityContactRole records where role in (Lead Tenant,Tenant,Permitted Occupier) and OpportunityContactRole.Active__c = true | C13: "noOfAdultOccupants": 2, | D13: =IF(OR(ISNUMBER(SEARCH("{", C13)),ISNUMBER(SEARCH("[", C13))), "", IFERROR(MID(C13, SEARCH("""", C13) +1, SEARCH("""", C13, SEARCH("""",C13) +1) - SEARCH("""", C13) -1), "")) -> noOfAdultOccupants | E13: =IF(D13="", "", VLOOKUP(D13,'API Data Dictionary'!C:L,10,FALSE)) -> X | F13: =IF(D13="", "", VLOOKUP(D13,'API Data Dictionary'!C:D,2,FALSE)) -> integer | G13: =IF(IF(D13="", "", VLOOKUP(D13,'API Data Dictionary'!C:E,3,FALSE))=0, "", IF(D13="", "", VLOOKUP(D13,'API Data Dictionary'!C:E,3,FALSE))) | H13: =IF(IF(D13="", "", VLOOKUP(D13,'API Data Dictionary'!C:F,4,FALSE))=0, "", IF(D13="", "", VLOOKUP(D13,'API Data Dictionary'!C:F,4,FALSE))) | I13: =IF(IF(D13="", "", VLOOKUP(D13,'API Data Dictionary'!C:G,5,FALSE))=0, "", IF(D13="", "", VLOOKUP(D13,'API Data Dictionary'!C:G,5,FALSE))) -> Number of Adult occupants (18 or over)
C14: "noOfChildOccupants": 2, | D14: =IF(OR(ISNUMBER(SEARCH("{", C14)),ISNUMBER(SEARCH("[", C14))), "", IFERROR(MID(C14, SEARCH("""", C14) +1, SEARCH("""", C14, SEARCH("""",C14) +1) - SEARCH("""", C14) -1), "")) -> noOfChildOccupants | E14: =IF(D14="", "", VLOOKUP(D14,'API Data Dictionary'!C:L,10,FALSE)) -> X | F14: =IF(D14="", "", VLOOKUP(D14,'API Data Dictionary'!C:D,2,FALSE)) -> integer | G14: =IF(IF(D14="", "", VLOOKUP(D14,'API Data Dictionary'!C:E,3,FALSE))=0, "", IF(D14="", "", VLOOKUP(D14,'API Data Dictionary'!C:E,3,FALSE))) | H14: =IF(IF(D14="", "", VLOOKUP(D14,'API Data Dictionary'!C:F,4,FALSE))=0, "", IF(D14="", "", VLOOKUP(D14,'API Data Dictionary'!C:F,4,FALSE))) | I14: =IF(IF(D14="", "", VLOOKUP(D14,'API Data Dictionary'!C:G,5,FALSE))=0, "", IF(D14="", "", VLOOKUP(D14,'API Data Dictionary'!C:G,5,FALSE))) -> Number of Child Occupants (under 18)
B15: opp.Advance_Paid__c | C15: "isAdvanceRent": false, | D15: =IF(OR(ISNUMBER(SEARCH("{", C15)),ISNUMBER(SEARCH("[", C15))), "", IFERROR(MID(C15, SEARCH("""", C15) +1, SEARCH("""", C15, SEARCH("""",C15) +1) - SEARCH("""", C15) -1), "")) -> isAdvanceRent | E15: x | F15: =IF(D15="", "", VLOOKUP(D15,'API Data Dictionary'!C:D,2,FALSE)) -> boolean | G15: =IF(IF(D15="", "", VLOOKUP(D15,'API Data Dictionary'!C:E,3,FALSE))=0, "", IF(D15="", "", VLOOKUP(D15,'API Data Dictionary'!C:E,3,FALSE))) | H15: =IF(IF(D15="", "", VLOOKUP(D15,'API Data Dictionary'!C:F,4,FALSE))=0, "", IF(D15="", "", VLOOKUP(D15,'API Data Dictionary'!C:F,4,FALSE))) | I15: =IF(IF(D15="", "", VLOOKUP(D15,'API Data Dictionary'!C:G,5,FALSE))=0, "", IF(D15="", "", VLOOKUP(D15,'API Data Dictionary'!C:G,5,FALSE))) -> Denotes whether rent is paid in advance
C16: "propertyAddress": { | D16: =IF(OR(ISNUMBER(SEARCH("{", C16)),ISNUMBER(SEARCH("[", C16))), "", IFERROR(MID(C16, SEARCH("""", C16) +1, SEARCH("""", C16, SEARCH("""",C16) +1) - SEARCH("""", C16) -1), "")) | E16: =IF(D16="", "", VLOOKUP(D16,'API Data Dictionary'!C:L,10,FALSE)) | F16: =IF(D16="", "", VLOOKUP(D16,'API Data Dictionary'!C:D,2,FALSE)) | G16: =IF(IF(D16="", "", VLOOKUP(D16,'API Data Dictionary'!C:E,3,FALSE))=0, "", IF(D16="", "", VLOOKUP(D16,'API Data Dictionary'!C:E,3,FALSE))) | H16: =IF(IF(D16="", "", VLOOKUP(D16,'API Data Dictionary'!C:F,4,FALSE))=0, "", IF(D16="", "", VLOOKUP(D16,'API Data Dictionary'!C:F,4,FALSE))) | I16: =IF(IF(D16="", "", VLOOKUP(D16,'API Data Dictionary'!C:G,5,FALSE))=0, "", IF(D16="", "", VLOOKUP(D16,'API Data Dictionary'!C:G,5,FALSE)))
B17: <Split Primary_Offer__r.Unit__r.Street_Name__c on comma>[2][1][0] | C17: "houseNumber": "Apartment 42", | D17: =IF(OR(ISNUMBER(SEARCH("{", C17)),ISNUMBER(SEARCH("[", C17))), "", IFERROR(MID(C17, SEARCH("""", C17) +1, SEARCH("""", C17, SEARCH("""",C17) +1) - SEARCH("""", C17) -1), "")) -> houseNumber | E17: =IF(D17="", "", VLOOKUP(D17,'API Data Dictionary'!C:L,10,FALSE)) -> X | F17: =IF(D17="", "", VLOOKUP(D17,'API Data Dictionary'!C:D,2,FALSE)) -> string | G17: =IF(IF(D17="", "", VLOOKUP(D17,'API Data Dictionary'!C:E,3,FALSE))=0, "", IF(D17="", "", VLOOKUP(D17,'API Data Dictionary'!C:E,3,FALSE))) -> 100 | H17: =IF(IF(D17="", "", VLOOKUP(D17,'API Data Dictionary'!C:F,4,FALSE))=0, "", IF(D17="", "", VLOOKUP(D17,'API Data Dictionary'!C:F,4,FALSE))) | I17: =IF(IF(D17="", "", VLOOKUP(D17,'API Data Dictionary'!C:G,5,FALSE))=0, "", IF(D17="", "", VLOOKUP(D17,'API Data Dictionary'!C:G,5,FALSE))) -> The number of the property
B18: <Split Primary_Offer__r.Unit__r.Street_Name__c on comma>[1][0] | C18: "houseName": "3 Millet Place", | D18: =IF(OR(ISNUMBER(SEARCH("{", C18)),ISNUMBER(SEARCH("[", C18))), "", IFERROR(MID(C18, SEARCH("""", C18) +1, SEARCH("""", C18, SEARCH("""",C18) +1) - SEARCH("""", C18) -1), "")) -> houseName | E18: =IF(D18="", "", VLOOKUP(D18,'API Data Dictionary'!C:L,10,FALSE)) -> X | F18: =IF(D18="", "", VLOOKUP(D18,'API Data Dictionary'!C:D,2,FALSE)) -> string | G18: =IF(IF(D18="", "", VLOOKUP(D18,'API Data Dictionary'!C:E,3,FALSE))=0, "", IF(D18="", "", VLOOKUP(D18,'API Data Dictionary'!C:E,3,FALSE))) -> 100 | H18: =IF(IF(D18="", "", VLOOKUP(D18,'API Data Dictionary'!C:F,4,FALSE))=0, "", IF(D18="", "", VLOOKUP(D18,'API Data Dictionary'!C:F,4,FALSE))) | I18: =IF(IF(D18="", "", VLOOKUP(D18,'API Data Dictionary'!C:G,5,FALSE))=0, "", IF(D18="", "", VLOOKUP(D18,'API Data Dictionary'!C:G,5,FALSE))) -> The name of the property
B19: <Split Primary_Offer__r.Unit__r.Street_Name__c on comma>[0][0][0] | C19: "addressLine1": "Adlay Apartments", | D19: =IF(OR(ISNUMBER(SEARCH("{", C19)),ISNUMBER(SEARCH("[", C19))), "", IFERROR(MID(C19, SEARCH("""", C19) +1, SEARCH("""", C19, SEARCH("""",C19) +1) - SEARCH("""", C19) -1), "")) -> addressLine1 | E19: =IF(D19="", "", VLOOKUP(D19,'API Data Dictionary'!C:L,10,FALSE)) -> M | F19: =IF(D19="", "", VLOOKUP(D19,'API Data Dictionary'!C:D,2,FALSE)) -> string | G19: =IF(IF(D19="", "", VLOOKUP(D19,'API Data Dictionary'!C:E,3,FALSE))=0, "", IF(D19="", "", VLOOKUP(D19,'API Data Dictionary'!C:E,3,FALSE))) -> 100 | H19: =IF(IF(D19="", "", VLOOKUP(D19,'API Data Dictionary'!C:F,4,FALSE))=0, "", IF(D19="", "", VLOOKUP(D19,'API Data Dictionary'!C:F,4,FALSE))) | I19: =IF(IF(D19="", "", VLOOKUP(D19,'API Data Dictionary'!C:G,5,FALSE))=0, "", IF(D19="", "", VLOOKUP(D19,'API Data Dictionary'!C:G,5,FALSE))) -> The first line of the property address
C20: "addressLine2": "Parkway", | D20: =IF(OR(ISNUMBER(SEARCH("{", C20)),ISNUMBER(SEARCH("[", C20))), "", IFERROR(MID(C20, SEARCH("""", C20) +1, SEARCH("""", C20, SEARCH("""",C20) +1) - SEARCH("""", C20) -1), "")) -> addressLine2 | E20: =IF(D20="", "", VLOOKUP(D20,'API Data Dictionary'!C:L,10,FALSE)) -> x | F20: =IF(D20="", "", VLOOKUP(D20,'API Data Dictionary'!C:D,2,FALSE)) -> string | G20: =IF(IF(D20="", "", VLOOKUP(D20,'API Data Dictionary'!C:E,3,FALSE))=0, "", IF(D20="", "", VLOOKUP(D20,'API Data Dictionary'!C:E,3,FALSE))) -> 100 | H20: =IF(IF(D20="", "", VLOOKUP(D20,'API Data Dictionary'!C:F,4,FALSE))=0, "", IF(D20="", "", VLOOKUP(D20,'API Data Dictionary'!C:F,4,FALSE))) | I20: =IF(IF(D20="", "", VLOOKUP(D20,'API Data Dictionary'!C:G,5,FALSE))=0, "", IF(D20="", "", VLOOKUP(D20,'API Data Dictionary'!C:G,5,FALSE))) -> The second line of the property address
B21: Primary_Offer__r.Unit__r.City__c | C21: "town": "Aberdare", | D21: =IF(OR(ISNUMBER(SEARCH("{", C21)),ISNUMBER(SEARCH("[", C21))), "", IFERROR(MID(C21, SEARCH("""", C21) +1, SEARCH("""", C21, SEARCH("""",C21) +1) - SEARCH("""", C21) -1), "")) -> town | E21: =IF(D21="", "", VLOOKUP(D21,'API Data Dictionary'!C:L,10,FALSE)) -> M | F21: =IF(D21="", "", VLOOKUP(D21,'API Data Dictionary'!C:D,2,FALSE)) -> string | G21: =IF(IF(D21="", "", VLOOKUP(D21,'API Data Dictionary'!C:E,3,FALSE))=0, "", IF(D21="", "", VLOOKUP(D21,'API Data Dictionary'!C:E,3,FALSE))) -> 50 | H21: =IF(IF(D21="", "", VLOOKUP(D21,'API Data Dictionary'!C:F,4,FALSE))=0, "", IF(D21="", "", VLOOKUP(D21,'API Data Dictionary'!C:F,4,FALSE))) | I21: =IF(IF(D21="", "", VLOOKUP(D21,'API Data Dictionary'!C:G,5,FALSE))=0, "", IF(D21="", "", VLOOKUP(D21,'API Data Dictionary'!C:G,5,FALSE))) -> The town in which the property exists
B22: Primary_Offer__r.Unit__r.Post_Code__c | C22: "postcode": "CF44 8BE", | D22: =IF(OR(ISNUMBER(SEARCH("{", C22)),ISNUMBER(SEARCH("[", C22))), "", IFERROR(MID(C22, SEARCH("""", C22) +1, SEARCH("""", C22, SEARCH("""",C22) +1) - SEARCH("""", C22) -1), "")) -> postcode | E22: =IF(D22="", "", VLOOKUP(D22,'API Data Dictionary'!C:L,10,FALSE)) -> M | F22: =IF(D22="", "", VLOOKUP(D22,'API Data Dictionary'!C:D,2,FALSE)) -> string | G22: =IF(IF(D22="", "", VLOOKUP(D22,'API Data Dictionary'!C:E,3,FALSE))=0, "", IF(D22="", "", VLOOKUP(D22,'API Data Dictionary'!C:E,3,FALSE))) -> 50 | H22: =IF(IF(D22="", "", VLOOKUP(D22,'API Data Dictionary'!C:F,4,FALSE))=0, "", IF(D22="", "", VLOOKUP(D22,'API Data Dictionary'!C:F,4,FALSE))) | I22: =IF(IF(D22="", "", VLOOKUP(D22,'API Data Dictionary'!C:G,5,FALSE))=0, "", IF(D22="", "", VLOOKUP(D22,'API Data Dictionary'!C:G,5,FALSE))) -> the postcode of the property
A23: SF Picklist vs Homelet Enums //TODO | B23: <Hard code to 1 for now - will need to address for later when building in Wales goes live> | C23: "ukCountryCode": 3 | D23: =IF(OR(ISNUMBER(SEARCH("{", C23)),ISNUMBER(SEARCH("[", C23))), "", IFERROR(MID(C23, SEARCH("""", C23) +1, SEARCH("""", C23, SEARCH("""",C23) +1) - SEARCH("""", C23) -1), "")) -> ukCountryCode | E23: =IF(D23="", "", VLOOKUP(D23,'API Data Dictionary'!C:L,10,FALSE)) -> M | F23: =IF(D23="", "", VLOOKUP(D23,'API Data Dictionary'!C:D,2,FALSE)) -> enum - UK Country List | G23: =IF(IF(D23="", "", VLOOKUP(D23,'API Data Dictionary'!C:E,3,FALSE))=0, "", IF(D23="", "", VLOOKUP(D23,'API Data Dictionary'!C:E,3,FALSE))) | H23: =IF(IF(D23="", "", VLOOKUP(D23,'API Data Dictionary'!C:F,4,FALSE))=0, "", IF(D23="", "", VLOOKUP(D23,'API Data Dictionary'!C:F,4,FALSE))) -> Valid Values 1-4 (See enum definition) | I23: =IF(IF(D23="", "", VLOOKUP(D23,'API Data Dictionary'!C:G,5,FALSE))=0, "", IF(D23="", "", VLOOKUP(D23,'API Data Dictionary'!C:G,5,FALSE))) -> The UK country Code
C24: }, | D24: =IF(OR(ISNUMBER(SEARCH("{", C24)),ISNUMBER(SEARCH("[", C24))), "", IFERROR(MID(C24, SEARCH("""", C24) +1, SEARCH("""", C24, SEARCH("""",C24) +1) - SEARCH("""", C24) -1), "")) | E24: =IF(D24="", "", VLOOKUP(D24,'API Data Dictionary'!C:L,10,FALSE)) | F24: =IF(D24="", "", VLOOKUP(D24,'API Data Dictionary'!C:D,2,FALSE)) | G24: =IF(IF(D24="", "", VLOOKUP(D24,'API Data Dictionary'!C:E,3,FALSE))=0, "", IF(D24="", "", VLOOKUP(D24,'API Data Dictionary'!C:E,3,FALSE))) | H24: =IF(IF(D24="", "", VLOOKUP(D24,'API Data Dictionary'!C:F,4,FALSE))=0, "", IF(D24="", "", VLOOKUP(D24,'API Data Dictionary'!C:F,4,FALSE))) | I24: =IF(IF(D24="", "", VLOOKUP(D24,'API Data Dictionary'!C:G,5,FALSE))=0, "", IF(D24="", "", VLOOKUP(D24,'API Data Dictionary'!C:G,5,FALSE)))
C25: "tenants": [ | D25: =IF(OR(ISNUMBER(SEARCH("{", C25)),ISNUMBER(SEARCH("[", C25))), "", IFERROR(MID(C25, SEARCH("""", C25) +1, SEARCH("""", C25, SEARCH("""",C25) +1) - SEARCH("""", C25) -1), "")) | E25: =IF(D25="", "", VLOOKUP(D25,'API Data Dictionary'!C:L,10,FALSE)) | F25: =IF(D25="", "", VLOOKUP(D25,'API Data Dictionary'!C:D,2,FALSE)) | G25: =IF(IF(D25="", "", VLOOKUP(D25,'API Data Dictionary'!C:E,3,FALSE))=0, "", IF(D25="", "", VLOOKUP(D25,'API Data Dictionary'!C:E,3,FALSE))) | H25: =IF(IF(D25="", "", VLOOKUP(D25,'API Data Dictionary'!C:F,4,FALSE))=0, "", IF(D25="", "", VLOOKUP(D25,'API Data Dictionary'!C:F,4,FALSE))) | I25: =IF(IF(D25="", "", VLOOKUP(D25,'API Data Dictionary'!C:G,5,FALSE))=0, "", IF(D25="", "", VLOOKUP(D25,'API Data Dictionary'!C:G,5,FALSE)))
C26: { | D26: =IF(OR(ISNUMBER(SEARCH("{", C26)),ISNUMBER(SEARCH("[", C26))), "", IFERROR(MID(C26, SEARCH("""", C26) +1, SEARCH("""", C26, SEARCH("""",C26) +1) - SEARCH("""", C26) -1), "")) | E26: =IF(D26="", "", VLOOKUP(D26,'API Data Dictionary'!C:L,10,FALSE)) | F26: =IF(D26="", "", VLOOKUP(D26,'API Data Dictionary'!C:D,2,FALSE)) | G26: =IF(IF(D26="", "", VLOOKUP(D26,'API Data Dictionary'!C:E,3,FALSE))=0, "", IF(D26="", "", VLOOKUP(D26,'API Data Dictionary'!C:E,3,FALSE))) | H26: =IF(IF(D26="", "", VLOOKUP(D26,'API Data Dictionary'!C:F,4,FALSE))=0, "", IF(D26="", "", VLOOKUP(D26,'API Data Dictionary'!C:F,4,FALSE))) | I26: =IF(IF(D26="", "", VLOOKUP(D26,'API Data Dictionary'!C:G,5,FALSE))=0, "", IF(D26="", "", VLOOKUP(D26,'API Data Dictionary'!C:G,5,FALSE)))
B27: OpportunityContactRole.Role | C27: "tenantTypeId": 1, | D27: =IF(OR(ISNUMBER(SEARCH("{", C27)),ISNUMBER(SEARCH("[", C27))), "", IFERROR(MID(C27, SEARCH("""", C27) +1, SEARCH("""", C27, SEARCH("""",C27) +1) - SEARCH("""", C27) -1), "")) -> tenantTypeId | E27: =IF(D27="", "", VLOOKUP(D27,'API Data Dictionary'!C:L,10,FALSE)) -> M | F27: =IF(D27="", "", VLOOKUP(D27,'API Data Dictionary'!C:D,2,FALSE)) -> enum - Tenant Type | G27: =IF(IF(D27="", "", VLOOKUP(D27,'API Data Dictionary'!C:E,3,FALSE))=0, "", IF(D27="", "", VLOOKUP(D27,'API Data Dictionary'!C:E,3,FALSE))) | H27: =IF(IF(D27="", "", VLOOKUP(D27,'API Data Dictionary'!C:F,4,FALSE))=0, "", IF(D27="", "", VLOOKUP(D27,'API Data Dictionary'!C:F,4,FALSE))) -> Valid Values 1-4 (See enum definition) | I27: =IF(IF(D27="", "", VLOOKUP(D27,'API Data Dictionary'!C:G,5,FALSE))=0, "", IF(D27="", "", VLOOKUP(D27,'API Data Dictionary'!C:G,5,FALSE))) -> The Type of the Tenant, e.g. lead or Guarantor
B28: <hard code to 1> | C28: "referenceType": 1, | D28: =IF(OR(ISNUMBER(SEARCH("{", C28)),ISNUMBER(SEARCH("[", C28))), "", IFERROR(MID(C28, SEARCH("""", C28) +1, SEARCH("""", C28, SEARCH("""",C28) +1) - SEARCH("""", C28) -1), "")) -> referenceType | E28: =IF(D28="", "", VLOOKUP(D28,'API Data Dictionary'!C:L,10,FALSE)) -> M | F28: =IF(D28="", "", VLOOKUP(D28,'API Data Dictionary'!C:D,2,FALSE)) -> enum - Reference Type | G28: =IF(IF(D28="", "", VLOOKUP(D28,'API Data Dictionary'!C:E,3,FALSE))=0, "", IF(D28="", "", VLOOKUP(D28,'API Data Dictionary'!C:E,3,FALSE))) | H28: =IF(IF(D28="", "", VLOOKUP(D28,'API Data Dictionary'!C:F,4,FALSE))=0, "", IF(D28="", "", VLOOKUP(D28,'API Data Dictionary'!C:F,4,FALSE))) -> Valid Values 1-2 (See enum definition) | I28: =IF(IF(D28="", "", VLOOKUP(D28,'API Data Dictionary'!C:G,5,FALSE))=0, "", IF(D28="", "", VLOOKUP(D28,'API Data Dictionary'!C:G,5,FALSE))) -> The Type of reference, e.g Full or Express
B29: contactRole.Right_to_Rent__c | C29: "rightToRent": true, | D29: =IF(OR(ISNUMBER(SEARCH("{", C29)),ISNUMBER(SEARCH("[", C29))), "", IFERROR(MID(C29, SEARCH("""", C29) +1, SEARCH("""", C29, SEARCH("""",C29) +1) - SEARCH("""", C29) -1), "")) -> rightToRent | E29: =IF(D29="", "", VLOOKUP(D29,'API Data Dictionary'!C:L,10,FALSE)) -> M | F29: =IF(D29="", "", VLOOKUP(D29,'API Data Dictionary'!C:D,2,FALSE)) -> boolean | G29: =IF(IF(D29="", "", VLOOKUP(D29,'API Data Dictionary'!C:E,3,FALSE))=0, "", IF(D29="", "", VLOOKUP(D29,'API Data Dictionary'!C:E,3,FALSE))) | H29: =IF(IF(D29="", "", VLOOKUP(D29,'API Data Dictionary'!C:F,4,FALSE))=0, "", IF(D29="", "", VLOOKUP(D29,'API Data Dictionary'!C:F,4,FALSE))) | I29: =IF(IF(D29="", "", VLOOKUP(D29,'API Data Dictionary'!C:G,5,FALSE))=0, "", IF(D29="", "", VLOOKUP(D29,'API Data Dictionary'!C:G,5,FALSE))) -> Use Right to rent product for this reference
B30: contactRole.Contact.Salutation [CMDT to map]. If Salutation is not populated in Salesforce, pass default enum of 6 (other) to HomeLet API. This default should be stored in CMDT. | C30: "title": 1, | D30: =IF(OR(ISNUMBER(SEARCH("{", C30)),ISNUMBER(SEARCH("[", C30))), "", IFERROR(MID(C30, SEARCH("""", C30) +1, SEARCH("""", C30, SEARCH("""",C30) +1) - SEARCH("""", C30) -1), "")) -> title | E30: =IF(D30="", "", VLOOKUP(D30,'API Data Dictionary'!C:L,10,FALSE)) -> M | F30: =IF(D30="", "", VLOOKUP(D30,'API Data Dictionary'!C:D,2,FALSE)) -> enum - Title | G30: =IF(IF(D30="", "", VLOOKUP(D30,'API Data Dictionary'!C:E,3,FALSE))=0, "", IF(D30="", "", VLOOKUP(D30,'API Data Dictionary'!C:E,3,FALSE))) | H30: =IF(IF(D30="", "", VLOOKUP(D30,'API Data Dictionary'!C:F,4,FALSE))=0, "", IF(D30="", "", VLOOKUP(D30,'API Data Dictionary'!C:F,4,FALSE))) -> Valid Values 1-7 (See enum definition) | I30: =IF(IF(D30="", "", VLOOKUP(D30,'API Data Dictionary'!C:G,5,FALSE))=0, "", IF(D30="", "", VLOOKUP(D30,'API Data Dictionary'!C:G,5,FALSE))) -> The persons title, e.g. Mr, Mrs, etc.
B31: If contactRole.Contact.Salutation is null, default to "Please Specify" via CMDT | C31: "otherTitle": "", | D31: =IF(OR(ISNUMBER(SEARCH("{", C31)),ISNUMBER(SEARCH("[", C31))), "", IFERROR(MID(C31, SEARCH("""", C31) +1, SEARCH("""", C31, SEARCH("""",C31) +1) - SEARCH("""", C31) -1), "")) -> otherTitle | E31: =IF(D31="", "", VLOOKUP(D31,'API Data Dictionary'!C:L,10,FALSE)) -> X | F31: =IF(D31="", "", VLOOKUP(D31,'API Data Dictionary'!C:D,2,FALSE)) -> string | G31: =IF(IF(D31="", "", VLOOKUP(D31,'API Data Dictionary'!C:E,3,FALSE))=0, "", IF(D31="", "", VLOOKUP(D31,'API Data Dictionary'!C:E,3,FALSE))) -> 100 | H31: =IF(IF(D31="", "", VLOOKUP(D31,'API Data Dictionary'!C:F,4,FALSE))=0, "", IF(D31="", "", VLOOKUP(D31,'API Data Dictionary'!C:F,4,FALSE))) | I31: =IF(IF(D31="", "", VLOOKUP(D31,'API Data Dictionary'!C:G,5,FALSE))=0, "", IF(D31="", "", VLOOKUP(D31,'API Data Dictionary'!C:G,5,FALSE))) -> If other is chosen for title, this is a text field to enter the specific title
B32: contactRole.Contact.FirstName | C32: "firstName": "Berty", | D32: =IF(OR(ISNUMBER(SEARCH("{", C32)),ISNUMBER(SEARCH("[", C32))), "", IFERROR(MID(C32, SEARCH("""", C32) +1, SEARCH("""", C32, SEARCH("""",C32) +1) - SEARCH("""", C32) -1), "")) -> firstName | E32: =IF(D32="", "", VLOOKUP(D32,'API Data Dictionary'!C:L,10,FALSE)) -> M | F32: =IF(D32="", "", VLOOKUP(D32,'API Data Dictionary'!C:D,2,FALSE)) -> string | G32: =IF(IF(D32="", "", VLOOKUP(D32,'API Data Dictionary'!C:E,3,FALSE))=0, "", IF(D32="", "", VLOOKUP(D32,'API Data Dictionary'!C:E,3,FALSE))) -> 100 | H32: =IF(IF(D32="", "", VLOOKUP(D32,'API Data Dictionary'!C:F,4,FALSE))=0, "", IF(D32="", "", VLOOKUP(D32,'API Data Dictionary'!C:F,4,FALSE))) -> pattern: ^[a-zA-Z0-9\-' ]*$ | I32: =IF(IF(D32="", "", VLOOKUP(D32,'API Data Dictionary'!C:G,5,FALSE))=0, "", IF(D32="", "", VLOOKUP(D32,'API Data Dictionary'!C:G,5,FALSE))) -> First name, validated against the RegEx pattern
C33: "middleName": "Boo", | D33: =IF(OR(ISNUMBER(SEARCH("{", C33)),ISNUMBER(SEARCH("[", C33))), "", IFERROR(MID(C33, SEARCH("""", C33) +1, SEARCH("""", C33, SEARCH("""",C33) +1) - SEARCH("""", C33) -1), "")) -> middleName | E33: =IF(D33="", "", VLOOKUP(D33,'API Data Dictionary'!C:L,10,FALSE)) -> X | F33: =IF(D33="", "", VLOOKUP(D33,'API Data Dictionary'!C:D,2,FALSE)) -> string | G33: =IF(IF(D33="", "", VLOOKUP(D33,'API Data Dictionary'!C:E,3,FALSE))=0, "", IF(D33="", "", VLOOKUP(D33,'API Data Dictionary'!C:E,3,FALSE))) -> 50 | H33: =IF(IF(D33="", "", VLOOKUP(D33,'API Data Dictionary'!C:F,4,FALSE))=0, "", IF(D33="", "", VLOOKUP(D33,'API Data Dictionary'!C:F,4,FALSE))) -> pattern: ^[a-zA-Z0-9\-' ]*$ | I33: =IF(IF(D33="", "", VLOOKUP(D33,'API Data Dictionary'!C:G,5,FALSE))=0, "", IF(D33="", "", VLOOKUP(D33,'API Data Dictionary'!C:G,5,FALSE))) -> Middle name, validated against the RegEx pattern
B34: contactRole.Contact.LastName | C34: "surname": "Basset", | D34: =IF(OR(ISNUMBER(SEARCH("{", C34)),ISNUMBER(SEARCH("[", C34))), "", IFERROR(MID(C34, SEARCH("""", C34) +1, SEARCH("""", C34, SEARCH("""",C34) +1) - SEARCH("""", C34) -1), "")) -> surname | E34: =IF(D34="", "", VLOOKUP(D34,'API Data Dictionary'!C:L,10,FALSE)) -> M | F34: =IF(D34="", "", VLOOKUP(D34,'API Data Dictionary'!C:D,2,FALSE)) -> string | G34: =IF(IF(D34="", "", VLOOKUP(D34,'API Data Dictionary'!C:E,3,FALSE))=0, "", IF(D34="", "", VLOOKUP(D34,'API Data Dictionary'!C:E,3,FALSE))) -> 100 | H34: =IF(IF(D34="", "", VLOOKUP(D34,'API Data Dictionary'!C:F,4,FALSE))=0, "", IF(D34="", "", VLOOKUP(D34,'API Data Dictionary'!C:F,4,FALSE))) -> pattern: ^[a-zA-Z0-9\-' ]*$ | I34: =IF(IF(D34="", "", VLOOKUP(D34,'API Data Dictionary'!C:G,5,FALSE))=0, "", IF(D34="", "", VLOOKUP(D34,'API Data Dictionary'!C:G,5,FALSE))) -> Surname name, validated against the RegEx pattern
B35: contactRole.Direct_Debit_Amount__c | C35: "shareOfRent": 600, | D35: =IF(OR(ISNUMBER(SEARCH("{", C35)),ISNUMBER(SEARCH("[", C35))), "", IFERROR(MID(C35, SEARCH("""", C35) +1, SEARCH("""", C35, SEARCH("""",C35) +1) - SEARCH("""", C35) -1), "")) -> shareOfRent | E35: =IF(D35="", "", VLOOKUP(D35,'API Data Dictionary'!C:L,10,FALSE)) -> M | F35: =IF(D35="", "", VLOOKUP(D35,'API Data Dictionary'!C:D,2,FALSE)) -> number (double) | G35: =IF(IF(D35="", "", VLOOKUP(D35,'API Data Dictionary'!C:E,3,FALSE))=0, "", IF(D35="", "", VLOOKUP(D35,'API Data Dictionary'!C:E,3,FALSE))) | H35: =IF(IF(D35="", "", VLOOKUP(D35,'API Data Dictionary'!C:F,4,FALSE))=0, "", IF(D35="", "", VLOOKUP(D35,'API Data Dictionary'!C:F,4,FALSE))) -> pattern: ^\d*.\d{0,2}$ | I35: =IF(IF(D35="", "", VLOOKUP(D35,'API Data Dictionary'!C:G,5,FALSE))=0, "", IF(D35="", "", VLOOKUP(D35,'API Data Dictionary'!C:G,5,FALSE))) -> GBP value of the applicants share of the rent
B36: <hard code to 2> Referencing_HL_Mapping_Constant__mdt.telephoneCountryID = 2 | C36: "telephoneCountryID": 2, | D36: =IF(OR(ISNUMBER(SEARCH("{", C36)),ISNUMBER(SEARCH("[", C36))), "", IFERROR(MID(C36, SEARCH("""", C36) +1, SEARCH("""", C36, SEARCH("""",C36) +1) - SEARCH("""", C36) -1), "")) -> telephoneCountryID | E36: =IF(D36="", "", VLOOKUP(D36,'API Data Dictionary'!C:L,10,FALSE)) -> M | F36: =IF(D36="", "", VLOOKUP(D36,'API Data Dictionary'!C:D,2,FALSE)) -> enum -Country/Location Code | G36: =IF(IF(D36="", "", VLOOKUP(D36,'API Data Dictionary'!C:E,3,FALSE))=0, "", IF(D36="", "", VLOOKUP(D36,'API Data Dictionary'!C:E,3,FALSE))) | H36: =IF(IF(D36="", "", VLOOKUP(D36,'API Data Dictionary'!C:F,4,FALSE))=0, "", IF(D36="", "", VLOOKUP(D36,'API Data Dictionary'!C:F,4,FALSE))) -> Valid Values 1-239 (See enum definition) | I36: =IF(IF(D36="", "", VLOOKUP(D36,'API Data Dictionary'!C:G,5,FALSE))=0, "", IF(D36="", "", VLOOKUP(D36,'API Data Dictionary'!C:G,5,FALSE))) -> The country/location code of the phone number
B37: contactRole.Contact.MobilePhone | C37: "contactTelephoneNo": "01234567891", | D37: =IF(OR(ISNUMBER(SEARCH("{", C37)),ISNUMBER(SEARCH("[", C37))), "", IFERROR(MID(C37, SEARCH("""", C37) +1, SEARCH("""", C37, SEARCH("""",C37) +1) - SEARCH("""", C37) -1), "")) -> contactTelephoneNo | E37: =IF(D37="", "", VLOOKUP(D37,'API Data Dictionary'!C:L,10,FALSE)) -> M | F37: =IF(D37="", "", VLOOKUP(D37,'API Data Dictionary'!C:D,2,FALSE)) -> string | G37: =IF(IF(D37="", "", VLOOKUP(D37,'API Data Dictionary'!C:E,3,FALSE))=0, "", IF(D37="", "", VLOOKUP(D37,'API Data Dictionary'!C:E,3,FALSE))) -> 15 | H37: =IF(IF(D37="", "", VLOOKUP(D37,'API Data Dictionary'!C:F,4,FALSE))=0, "", IF(D37="", "", VLOOKUP(D37,'API Data Dictionary'!C:F,4,FALSE))) -> pattern: ^(\d{11})$ | I37: =IF(IF(D37="", "", VLOOKUP(D37,'API Data Dictionary'!C:G,5,FALSE))=0, "", IF(D37="", "", VLOOKUP(D37,'API Data Dictionary'!C:G,5,FALSE))) -> The telephone number
B38: contactRole.Contact.Email | C38: "emailAddress": "test@testtesttest.test" | D38: =IF(OR(ISNUMBER(SEARCH("{", C38)),ISNUMBER(SEARCH("[", C38))), "", IFERROR(MID(C38, SEARCH("""", C38) +1, SEARCH("""", C38, SEARCH("""",C38) +1) - SEARCH("""", C38) -1), "")) -> emailAddress | E38: =IF(D38="", "", VLOOKUP(D38,'API Data Dictionary'!C:L,10,FALSE)) -> M | F38: =IF(D38="", "", VLOOKUP(D38,'API Data Dictionary'!C:D,2,FALSE)) -> string ($email) | G38: =IF(IF(D38="", "", VLOOKUP(D38,'API Data Dictionary'!C:E,3,FALSE))=0, "", IF(D38="", "", VLOOKUP(D38,'API Data Dictionary'!C:E,3,FALSE))) -> 200 | H38: =IF(IF(D38="", "", VLOOKUP(D38,'API Data Dictionary'!C:F,4,FALSE))=0, "", IF(D38="", "", VLOOKUP(D38,'API Data Dictionary'!C:F,4,FALSE))) -> pattern: ^(?!.*\.\.)(?!.*\\_\\_)(?!.*\-\-)[a-zA-Z0-9][-a-zA-Z0-9._]+[a-zA-Z0-9]@([-a-zA-Z0-9]+.)+[a-zA-Z]{2,5}$ | I38: =IF(IF(D38="", "", VLOOKUP(D38,'API Data Dictionary'!C:G,5,FALSE))=0, "", IF(D38="", "", VLOOKUP(D38,'API Data Dictionary'!C:G,5,FALSE))) -> The email address
C39: } | D39: =IF(OR(ISNUMBER(SEARCH("{", C39)),ISNUMBER(SEARCH("[", C39))), "", IFERROR(MID(C39, SEARCH("""", C39) +1, SEARCH("""", C39, SEARCH("""",C39) +1) - SEARCH("""", C39) -1), "")) | E39: =IF(D39="", "", VLOOKUP(D39,'API Data Dictionary'!C:L,10,FALSE)) | F39: =IF(D39="", "", VLOOKUP(D39,'API Data Dictionary'!C:D,2,FALSE)) | G39: =IF(IF(D39="", "", VLOOKUP(D39,'API Data Dictionary'!C:E,3,FALSE))=0, "", IF(D39="", "", VLOOKUP(D39,'API Data Dictionary'!C:E,3,FALSE))) | H39: =IF(IF(D39="", "", VLOOKUP(D39,'API Data Dictionary'!C:F,4,FALSE))=0, "", IF(D39="", "", VLOOKUP(D39,'API Data Dictionary'!C:F,4,FALSE))) | I39: =IF(IF(D39="", "", VLOOKUP(D39,'API Data Dictionary'!C:G,5,FALSE))=0, "", IF(D39="", "", VLOOKUP(D39,'API Data Dictionary'!C:G,5,FALSE)))
C40: ] | D40: =IF(OR(ISNUMBER(SEARCH("{", C40)),ISNUMBER(SEARCH("[", C40))), "", IFERROR(MID(C40, SEARCH("""", C40) +1, SEARCH("""", C40, SEARCH("""",C40) +1) - SEARCH("""", C40) -1), "")) | E40: =IF(D40="", "", VLOOKUP(D40,'API Data Dictionary'!C:L,10,FALSE)) | F40: =IF(D40="", "", VLOOKUP(D40,'API Data Dictionary'!C:D,2,FALSE)) | G40: =IF(IF(D40="", "", VLOOKUP(D40,'API Data Dictionary'!C:E,3,FALSE))=0, "", IF(D40="", "", VLOOKUP(D40,'API Data Dictionary'!C:E,3,FALSE))) | H40: =IF(IF(D40="", "", VLOOKUP(D40,'API Data Dictionary'!C:F,4,FALSE))=0, "", IF(D40="", "", VLOOKUP(D40,'API Data Dictionary'!C:F,4,FALSE))) | I40: =IF(IF(D40="", "", VLOOKUP(D40,'API Data Dictionary'!C:G,5,FALSE))=0, "", IF(D40="", "", VLOOKUP(D40,'API Data Dictionary'!C:G,5,FALSE)))
C41: } | D41: =IF(OR(ISNUMBER(SEARCH("{", C41)),ISNUMBER(SEARCH("[", C41))), "", IFERROR(MID(C41, SEARCH("""", C41) +1, SEARCH("""", C41, SEARCH("""",C41) +1) - SEARCH("""", C41) -1), "")) | E41: =IF(D41="", "", VLOOKUP(D41,'API Data Dictionary'!C:L,10,FALSE)) | F41: =IF(D41="", "", VLOOKUP(D41,'API Data Dictionary'!C:D,2,FALSE)) | G41: =IF(IF(D41="", "", VLOOKUP(D41,'API Data Dictionary'!C:E,3,FALSE))=0, "", IF(D41="", "", VLOOKUP(D41,'API Data Dictionary'!C:E,3,FALSE))) | H41: =IF(IF(D41="", "", VLOOKUP(D41,'API Data Dictionary'!C:F,4,FALSE))=0, "", IF(D41="", "", VLOOKUP(D41,'API Data Dictionary'!C:F,4,FALSE))) | I41: =IF(IF(D41="", "", VLOOKUP(D41,'API Data Dictionary'!C:G,5,FALSE))=0, "", IF(D41="", "", VLOOKUP(D41,'API Data Dictionary'!C:G,5,FALSE)))
C42: Response Example
C43: { | D43: =IF(OR(ISNUMBER(SEARCH("{", C43)),ISNUMBER(SEARCH("[", C43))), "", IFERROR(MID(C43, SEARCH("""", C43) +1, SEARCH("""", C43, SEARCH("""",C43) +1) - SEARCH("""", C43) -1), "")) | E43: =IF(D43="", "", VLOOKUP(D43,'API Data Dictionary'!C:L,10,FALSE)) | F43: =IF(D43="", "", VLOOKUP(D43,'API Data Dictionary'!C:D,2,FALSE)) | G43: =IF(IF(D43="", "", VLOOKUP(D43,'API Data Dictionary'!C:E,3,FALSE))=0, "", IF(D43="", "", VLOOKUP(D43,'API Data Dictionary'!C:E,3,FALSE))) | H43: =IF(IF(D43="", "", VLOOKUP(D43,'API Data Dictionary'!C:F,4,FALSE))=0, "", IF(D43="", "", VLOOKUP(D43,'API Data Dictionary'!C:F,4,FALSE))) | I43: =IF(IF(D43="", "", VLOOKUP(D43,'API Data Dictionary'!C:G,5,FALSE))=0, "", IF(D43="", "", VLOOKUP(D43,'API Data Dictionary'!C:G,5,FALSE)))
C44: "success": true, | D44: =IF(OR(ISNUMBER(SEARCH("{", C44)),ISNUMBER(SEARCH("[", C44))), "", IFERROR(MID(C44, SEARCH("""", C44) +1, SEARCH("""", C44, SEARCH("""",C44) +1) - SEARCH("""", C44) -1), "")) -> success | E44: x | F44: =IF(D44="", "", VLOOKUP(D44,'API Data Dictionary'!C:D,2,FALSE)) -> string - Boolean | G44: =IF(IF(D44="", "", VLOOKUP(D44,'API Data Dictionary'!C:E,3,FALSE))=0, "", IF(D44="", "", VLOOKUP(D44,'API Data Dictionary'!C:E,3,FALSE))) -> 100 | H44: =IF(IF(D44="", "", VLOOKUP(D44,'API Data Dictionary'!C:F,4,FALSE))=0, "", IF(D44="", "", VLOOKUP(D44,'API Data Dictionary'!C:F,4,FALSE))) | I44: =IF(IF(D44="", "", VLOOKUP(D44,'API Data Dictionary'!C:G,5,FALSE))=0, "", IF(D44="", "", VLOOKUP(D44,'API Data Dictionary'!C:G,5,FALSE))) -> Returns true when successful connection
C45: "payload": { | D45: =IF(OR(ISNUMBER(SEARCH("{", C45)),ISNUMBER(SEARCH("[", C45))), "", IFERROR(MID(C45, SEARCH("""", C45) +1, SEARCH("""", C45, SEARCH("""",C45) +1) - SEARCH("""", C45) -1), "")) | E45: =IF(D45="", "", VLOOKUP(D45,'API Data Dictionary'!C:L,10,FALSE)) | F45: =IF(D45="", "", VLOOKUP(D45,'API Data Dictionary'!C:D,2,FALSE)) | G45: =IF(IF(D45="", "", VLOOKUP(D45,'API Data Dictionary'!C:E,3,FALSE))=0, "", IF(D45="", "", VLOOKUP(D45,'API Data Dictionary'!C:E,3,FALSE))) | H45: =IF(IF(D45="", "", VLOOKUP(D45,'API Data Dictionary'!C:F,4,FALSE))=0, "", IF(D45="", "", VLOOKUP(D45,'API Data Dictionary'!C:F,4,FALSE))) | I45: =IF(IF(D45="", "", VLOOKUP(D45,'API Data Dictionary'!C:G,5,FALSE))=0, "", IF(D45="", "", VLOOKUP(D45,'API Data Dictionary'!C:G,5,FALSE)))
C46: "agentCode": "9999", | D46: =IF(OR(ISNUMBER(SEARCH("{", C46)),ISNUMBER(SEARCH("[", C46))), "", IFERROR(MID(C46, SEARCH("""", C46) +1, SEARCH("""", C46, SEARCH("""",C46) +1) - SEARCH("""", C46) -1), "")) -> agentCode | E46: =IF(D46="", "", VLOOKUP(D46,'API Data Dictionary'!C:L,10,FALSE)) -> M | F46: =IF(D46="", "", VLOOKUP(D46,'API Data Dictionary'!C:D,2,FALSE)) -> string | G46: =IF(IF(D46="", "", VLOOKUP(D46,'API Data Dictionary'!C:E,3,FALSE))=0, "", IF(D46="", "", VLOOKUP(D46,'API Data Dictionary'!C:E,3,FALSE))) -> 50 | H46: =IF(IF(D46="", "", VLOOKUP(D46,'API Data Dictionary'!C:F,4,FALSE))=0, "", IF(D46="", "", VLOOKUP(D46,'API Data Dictionary'!C:F,4,FALSE))) | I46: =IF(IF(D46="", "", VLOOKUP(D46,'API Data Dictionary'!C:G,5,FALSE))=0, "", IF(D46="", "", VLOOKUP(D46,'API Data Dictionary'!C:G,5,FALSE))) -> AgentCode is the Unique Key provided to the Agent when onboarding as a Barbon Customer. An AgentID may be linked to many Properties being managed by that Agent and Each property may be linked to 1 or more TenancyID's.
C47: "propertyTenancyId": 85670, | D47: =IF(OR(ISNUMBER(SEARCH("{", C47)),ISNUMBER(SEARCH("[", C47))), "", IFERROR(MID(C47, SEARCH("""", C47) +1, SEARCH("""", C47, SEARCH("""",C47) +1) - SEARCH("""", C47) -1), "")) -> propertyTenancyId | E47: x | F47: =IF(D47="", "", VLOOKUP(D47,'API Data Dictionary'!C:D,2,FALSE)) -> integer | G47: =IF(IF(D47="", "", VLOOKUP(D47,'API Data Dictionary'!C:E,3,FALSE))=0, "", IF(D47="", "", VLOOKUP(D47,'API Data Dictionary'!C:E,3,FALSE))) | H47: =IF(IF(D47="", "", VLOOKUP(D47,'API Data Dictionary'!C:F,4,FALSE))=0, "", IF(D47="", "", VLOOKUP(D47,'API Data Dictionary'!C:F,4,FALSE))) | I47: =IF(IF(D47="", "", VLOOKUP(D47,'API Data Dictionary'!C:G,5,FALSE))=0, "", IF(D47="", "", VLOOKUP(D47,'API Data Dictionary'!C:G,5,FALSE))) -> The ID of the property tenancy
C48: "ReferencingApplicantList": [ | D48: =IF(OR(ISNUMBER(SEARCH("{", C48)),ISNUMBER(SEARCH("[", C48))), "", IFERROR(MID(C48, SEARCH("""", C48) +1, SEARCH("""", C48, SEARCH("""",C48) +1) - SEARCH("""", C48) -1), "")) | E48: =IF(D48="", "", VLOOKUP(D48,'API Data Dictionary'!C:L,10,FALSE)) | F48: =IF(D48="", "", VLOOKUP(D48,'API Data Dictionary'!C:D,2,FALSE)) | G48: =IF(IF(D48="", "", VLOOKUP(D48,'API Data Dictionary'!C:E,3,FALSE))=0, "", IF(D48="", "", VLOOKUP(D48,'API Data Dictionary'!C:E,3,FALSE))) | H48: =IF(IF(D48="", "", VLOOKUP(D48,'API Data Dictionary'!C:F,4,FALSE))=0, "", IF(D48="", "", VLOOKUP(D48,'API Data Dictionary'!C:F,4,FALSE))) | I48: =IF(IF(D48="", "", VLOOKUP(D48,'API Data Dictionary'!C:G,5,FALSE))=0, "", IF(D48="", "", VLOOKUP(D48,'API Data Dictionary'!C:G,5,FALSE)))
C49: { | D49: =IF(OR(ISNUMBER(SEARCH("{", C49)),ISNUMBER(SEARCH("[", C49))), "", IFERROR(MID(C49, SEARCH("""", C49) +1, SEARCH("""", C49, SEARCH("""",C49) +1) - SEARCH("""", C49) -1), "")) | E49: =IF(D49="", "", VLOOKUP(D49,'API Data Dictionary'!C:L,10,FALSE)) | F49: =IF(D49="", "", VLOOKUP(D49,'API Data Dictionary'!C:D,2,FALSE)) | G49: =IF(IF(D49="", "", VLOOKUP(D49,'API Data Dictionary'!C:E,3,FALSE))=0, "", IF(D49="", "", VLOOKUP(D49,'API Data Dictionary'!C:E,3,FALSE))) | H49: =IF(IF(D49="", "", VLOOKUP(D49,'API Data Dictionary'!C:F,4,FALSE))=0, "", IF(D49="", "", VLOOKUP(D49,'API Data Dictionary'!C:F,4,FALSE))) | I49: =IF(IF(D49="", "", VLOOKUP(D49,'API Data Dictionary'!C:G,5,FALSE))=0, "", IF(D49="", "", VLOOKUP(D49,'API Data Dictionary'!C:G,5,FALSE)))
C50: "applicantID": 678007, | D50: =IF(OR(ISNUMBER(SEARCH("{", C50)),ISNUMBER(SEARCH("[", C50))), "", IFERROR(MID(C50, SEARCH("""", C50) +1, SEARCH("""", C50, SEARCH("""",C50) +1) - SEARCH("""", C50) -1), "")) -> applicantID | E50: x | F50: =IF(D50="", "", VLOOKUP(D50,'API Data Dictionary'!C:D,2,FALSE)) -> string | G50: =IF(IF(D50="", "", VLOOKUP(D50,'API Data Dictionary'!C:E,3,FALSE))=0, "", IF(D50="", "", VLOOKUP(D50,'API Data Dictionary'!C:E,3,FALSE))) -> 50 | H50: =IF(IF(D50="", "", VLOOKUP(D50,'API Data Dictionary'!C:F,4,FALSE))=0, "", IF(D50="", "", VLOOKUP(D50,'API Data Dictionary'!C:F,4,FALSE))) | I50: =IF(IF(D50="", "", VLOOKUP(D50,'API Data Dictionary'!C:G,5,FALSE))=0, "", IF(D50="", "", VLOOKUP(D50,'API Data Dictionary'!C:G,5,FALSE))) -> ApplicantID is a unique identifier for a person / Company to be referenced. ApplicantID may be linked to one or more TenancyID's executing in parallel. ApplicantID is created through API Methods: CreateReferenceWithAllData CreateReferenceWithInputFromApplicant CreateCompanyReferenceWithAllData CreateCompanyReferenceWithInputFromApplicant AddApplicantToTenancy
C51: "applicantName": "Mr Berty Boo Basset" | D51: =IF(OR(ISNUMBER(SEARCH("{", C51)),ISNUMBER(SEARCH("[", C51))), "", IFERROR(MID(C51, SEARCH("""", C51) +1, SEARCH("""", C51, SEARCH("""",C51) +1) - SEARCH("""", C51) -1), "")) -> applicantName | E51: x | F51: string | G51: 50 | I51: The Applicants name, made up of title, firstname, middlename and surname
C52: } | D52: =IF(OR(ISNUMBER(SEARCH("{", C52)),ISNUMBER(SEARCH("[", C52))), "", IFERROR(MID(C52, SEARCH("""", C52) +1, SEARCH("""", C52, SEARCH("""",C52) +1) - SEARCH("""", C52) -1), "")) | E52: =IF(D52="", "", VLOOKUP(D52,'API Data Dictionary'!C:L,10,FALSE)) | F52: =IF(D52="", "", VLOOKUP(D52,'API Data Dictionary'!C:D,2,FALSE)) | G52: =IF(IF(D52="", "", VLOOKUP(D52,'API Data Dictionary'!C:E,3,FALSE))=0, "", IF(D52="", "", VLOOKUP(D52,'API Data Dictionary'!C:E,3,FALSE))) | H52: =IF(IF(D52="", "", VLOOKUP(D52,'API Data Dictionary'!C:F,4,FALSE))=0, "", IF(D52="", "", VLOOKUP(D52,'API Data Dictionary'!C:F,4,FALSE))) | I52: =IF(IF(D52="", "", VLOOKUP(D52,'API Data Dictionary'!C:G,5,FALSE))=0, "", IF(D52="", "", VLOOKUP(D52,'API Data Dictionary'!C:G,5,FALSE)))
C53: ] | D53: =IF(OR(ISNUMBER(SEARCH("{", C53)),ISNUMBER(SEARCH("[", C53))), "", IFERROR(MID(C53, SEARCH("""", C53) +1, SEARCH("""", C53, SEARCH("""",C53) +1) - SEARCH("""", C53) -1), "")) | E53: =IF(D53="", "", VLOOKUP(D53,'API Data Dictionary'!C:L,10,FALSE)) | F53: =IF(D53="", "", VLOOKUP(D53,'API Data Dictionary'!C:D,2,FALSE)) | G53: =IF(IF(D53="", "", VLOOKUP(D53,'API Data Dictionary'!C:E,3,FALSE))=0, "", IF(D53="", "", VLOOKUP(D53,'API Data Dictionary'!C:E,3,FALSE))) | H53: =IF(IF(D53="", "", VLOOKUP(D53,'API Data Dictionary'!C:F,4,FALSE))=0, "", IF(D53="", "", VLOOKUP(D53,'API Data Dictionary'!C:F,4,FALSE))) | I53: =IF(IF(D53="", "", VLOOKUP(D53,'API Data Dictionary'!C:G,5,FALSE))=0, "", IF(D53="", "", VLOOKUP(D53,'API Data Dictionary'!C:G,5,FALSE)))
C54: }, | D54: =IF(OR(ISNUMBER(SEARCH("{", C54)),ISNUMBER(SEARCH("[", C54))), "", IFERROR(MID(C54, SEARCH("""", C54) +1, SEARCH("""", C54, SEARCH("""",C54) +1) - SEARCH("""", C54) -1), "")) | E54: =IF(D54="", "", VLOOKUP(D54,'API Data Dictionary'!C:L,10,FALSE)) | F54: =IF(D54="", "", VLOOKUP(D54,'API Data Dictionary'!C:D,2,FALSE)) | G54: =IF(IF(D54="", "", VLOOKUP(D54,'API Data Dictionary'!C:E,3,FALSE))=0, "", IF(D54="", "", VLOOKUP(D54,'API Data Dictionary'!C:E,3,FALSE))) | H54: =IF(IF(D54="", "", VLOOKUP(D54,'API Data Dictionary'!C:F,4,FALSE))=0, "", IF(D54="", "", VLOOKUP(D54,'API Data Dictionary'!C:F,4,FALSE))) | I54: =IF(IF(D54="", "", VLOOKUP(D54,'API Data Dictionary'!C:G,5,FALSE))=0, "", IF(D54="", "", VLOOKUP(D54,'API Data Dictionary'!C:G,5,FALSE)))
C55: "message": "Applicant link sent successfully." | D55: =IF(OR(ISNUMBER(SEARCH("{", C55)),ISNUMBER(SEARCH("[", C55))), "", IFERROR(MID(C55, SEARCH("""", C55) +1, SEARCH("""", C55, SEARCH("""",C55) +1) - SEARCH("""", C55) -1), "")) -> message | E55: x | F55: =IF(D55="", "", VLOOKUP(D55,'API Data Dictionary'!C:D,2,FALSE)) -> string | G55: =IF(IF(D55="", "", VLOOKUP(D55,'API Data Dictionary'!C:E,3,FALSE))=0, "", IF(D55="", "", VLOOKUP(D55,'API Data Dictionary'!C:E,3,FALSE))) -> 100 | H55: =IF(IF(D55="", "", VLOOKUP(D55,'API Data Dictionary'!C:F,4,FALSE))=0, "", IF(D55="", "", VLOOKUP(D55,'API Data Dictionary'!C:F,4,FALSE))) | I55: =IF(IF(D55="", "", VLOOKUP(D55,'API Data Dictionary'!C:G,5,FALSE))=0, "", IF(D55="", "", VLOOKUP(D55,'API Data Dictionary'!C:G,5,FALSE))) -> return value, null unless there has been error in connection
C56: } | D56: =IF(OR(ISNUMBER(SEARCH("{", C56)),ISNUMBER(SEARCH("[", C56))), "", IFERROR(MID(C56, SEARCH("""", C56) +1, SEARCH("""", C56, SEARCH("""",C56) +1) - SEARCH("""", C56) -1), "")) | E56: =IF(D56="", "", VLOOKUP(D56,'API Data Dictionary'!C:L,10,FALSE)) | F56: =IF(D56="", "", VLOOKUP(D56,'API Data Dictionary'!C:D,2,FALSE)) | G56: =IF(IF(D56="", "", VLOOKUP(D56,'API Data Dictionary'!C:E,3,FALSE))=0, "", IF(D56="", "", VLOOKUP(D56,'API Data Dictionary'!C:E,3,FALSE))) | H56: =IF(IF(D56="", "", VLOOKUP(D56,'API Data Dictionary'!C:F,4,FALSE))=0, "", IF(D56="", "", VLOOKUP(D56,'API Data Dictionary'!C:F,4,FALSE))) | I56: =IF(IF(D56="", "", VLOOKUP(D56,'API Data Dictionary'!C:G,5,FALSE))=0, "", IF(D56="", "", VLOOKUP(D56,'API Data Dictionary'!C:G,5,FALSE)))
A59: tenantTypeId Mapping | B59: HomeLet Type | C59: SF Contact.Role Values
A60: 1 | B60: LeadTenant | C60: 1 Lead Tenant
A61: 2 | B61: Tenant | C61: 2 Tenant
A62: 3 | B62: Guarantor | C62: 3 Guarantor
A63: 4 | B63: Tenant - Company | C63: 5 Relevant Person
C64: 4 Permitted Occupier

Sheet AddApplicantToTenancy
A1: Mapping Details | B1: SF Field Mapping | C1: AddApplicantToTenancy Example JSON | D1: Vision+ API Field Name | E1: Mandatory Field | F1: Field Type | G1: API Max Field Length | H1: Field Validations | I1: Field Description
C3: With Applicant Input Link Example Request | D3: =IF(OR(ISNUMBER(SEARCH("{", C3)),ISNUMBER(SEARCH("[", C3))), "", IFERROR(MID(C3, SEARCH("""", C3) +1, SEARCH("""", C3, SEARCH("""",C3) +1) - SEARCH("""", C3) -1), "")) | E3: =IF(D3="", "", VLOOKUP(D3,'API Data Dictionary'!C:L,10,FALSE)) | F3: =IF(D3="", "", VLOOKUP(D3,'API Data Dictionary'!C:D,2,FALSE)) | G3: =IF(IF(D3="", "", VLOOKUP(D3,'API Data Dictionary'!C:E,3,FALSE))=0, "", IF(D3="", "", VLOOKUP(D3,'API Data Dictionary'!C:E,3,FALSE))) | H3: =IF(IF(D3="", "", VLOOKUP(D3,'API Data Dictionary'!C:F,4,FALSE))=0, "", IF(D3="", "", VLOOKUP(D3,'API Data Dictionary'!C:F,4,FALSE))) | I3: =IF(IF(D3="", "", VLOOKUP(D3,'API Data Dictionary'!C:G,5,FALSE))=0, "", IF(D3="", "", VLOOKUP(D3,'API Data Dictionary'!C:G,5,FALSE)))
C4: { | D4: =IF(OR(ISNUMBER(SEARCH("{", C4)),ISNUMBER(SEARCH("[", C4))), "", IFERROR(MID(C4, SEARCH("""", C4) +1, SEARCH("""", C4, SEARCH("""",C4) +1) - SEARCH("""", C4) -1), "")) | E4: =IF(D4="", "", VLOOKUP(D4,'API Data Dictionary'!C:L,10,FALSE)) | F4: =IF(D4="", "", VLOOKUP(D4,'API Data Dictionary'!C:D,2,FALSE)) | G4: =IF(IF(D4="", "", VLOOKUP(D4,'API Data Dictionary'!C:E,3,FALSE))=0, "", IF(D4="", "", VLOOKUP(D4,'API Data Dictionary'!C:E,3,FALSE))) | H4: =IF(IF(D4="", "", VLOOKUP(D4,'API Data Dictionary'!C:F,4,FALSE))=0, "", IF(D4="", "", VLOOKUP(D4,'API Data Dictionary'!C:F,4,FALSE))) | I4: =IF(IF(D4="", "", VLOOKUP(D4,'API Data Dictionary'!C:G,5,FALSE))=0, "", IF(D4="", "", VLOOKUP(D4,'API Data Dictionary'!C:G,5,FALSE)))
B5: Referencing_HL_Auth_Setting__mdt.Agent_Code__c; | C5: "agentCode": "string", | D5: =IF(OR(ISNUMBER(SEARCH("{", C5)),ISNUMBER(SEARCH("[", C5))), "", IFERROR(MID(C5, SEARCH("""", C5) +1, SEARCH("""", C5, SEARCH("""",C5) +1) - SEARCH("""", C5) -1), "")) -> agentCode | E5: =IF(D5="", "", VLOOKUP(D5,'API Data Dictionary'!C:L,10,FALSE)) -> M | F5: =IF(D5="", "", VLOOKUP(D5,'API Data Dictionary'!C:D,2,FALSE)) -> string | G5: =IF(IF(D5="", "", VLOOKUP(D5,'API Data Dictionary'!C:E,3,FALSE))=0, "", IF(D5="", "", VLOOKUP(D5,'API Data Dictionary'!C:E,3,FALSE))) -> 50 | H5: =IF(IF(D5="", "", VLOOKUP(D5,'API Data Dictionary'!C:F,4,FALSE))=0, "", IF(D5="", "", VLOOKUP(D5,'API Data Dictionary'!C:F,4,FALSE))) | I5: =IF(IF(D5="", "", VLOOKUP(D5,'API Data Dictionary'!C:G,5,FALSE))=0, "", IF(D5="", "", VLOOKUP(D5,'API Data Dictionary'!C:G,5,FALSE))) -> AgentCode is the Unique Key provided to the Agent when onboarding as a Barbon Customer. An AgentID may be linked to many Properties being managed by that Agent and Each property may be linked to 1 or more TenancyID's.
B6: opp.Referencing_Property_Tenancy_Id__c | C6: "propertyTenancyId": 0, | D6: =IF(OR(ISNUMBER(SEARCH("{", C6)),ISNUMBER(SEARCH("[", C6))), "", IFERROR(MID(C6, SEARCH("""", C6) +1, SEARCH("""", C6, SEARCH("""",C6) +1) - SEARCH("""", C6) -1), "")) -> propertyTenancyId | E6: M | F6: =IF(D6="", "", VLOOKUP(D6,'API Data Dictionary'!C:D,2,FALSE)) -> integer | G6: =IF(IF(D6="", "", VLOOKUP(D6,'API Data Dictionary'!C:E,3,FALSE))=0, "", IF(D6="", "", VLOOKUP(D6,'API Data Dictionary'!C:E,3,FALSE))) | H6: =IF(IF(D6="", "", VLOOKUP(D6,'API Data Dictionary'!C:F,4,FALSE))=0, "", IF(D6="", "", VLOOKUP(D6,'API Data Dictionary'!C:F,4,FALSE))) | I6: =IF(IF(D6="", "", VLOOKUP(D6,'API Data Dictionary'!C:G,5,FALSE))=0, "", IF(D6="", "", VLOOKUP(D6,'API Data Dictionary'!C:G,5,FALSE))) -> The ID of the property tenancy
B7: <hard code to false> Referencing_HL_Mapping_Constant__mdt.isSentTenantLink | C7: "isSentTenantLink": true, | D7: =IF(OR(ISNUMBER(SEARCH("{", C7)),ISNUMBER(SEARCH("[", C7))), "", IFERROR(MID(C7, SEARCH("""", C7) +1, SEARCH("""", C7, SEARCH("""",C7) +1) - SEARCH("""", C7) -1), "")) -> isSentTenantLink | E7: M | F7: =IF(D7="", "", VLOOKUP(D7,'API Data Dictionary'!C:D,2,FALSE)) -> boolean | G7: =IF(IF(D7="", "", VLOOKUP(D7,'API Data Dictionary'!C:E,3,FALSE))=0, "", IF(D7="", "", VLOOKUP(D7,'API Data Dictionary'!C:E,3,FALSE))) | H7: =IF(IF(D7="", "", VLOOKUP(D7,'API Data Dictionary'!C:F,4,FALSE))=0, "", IF(D7="", "", VLOOKUP(D7,'API Data Dictionary'!C:F,4,FALSE))) | I7: =IF(IF(D7="", "", VLOOKUP(D7,'API Data Dictionary'!C:G,5,FALSE))=0, "", IF(D7="", "", VLOOKUP(D7,'API Data Dictionary'!C:G,5,FALSE))) -> Denotes whether the Tentant link is sent
C8: "linkedApplicantID": [ | D8: linkedApplicantID | E8: x | F8: =IF(D8="", "", VLOOKUP(D8,'API Data Dictionary'!C:D,2,FALSE)) -> integer | G8: =IF(IF(D8="", "", VLOOKUP(D8,'API Data Dictionary'!C:E,3,FALSE))=0, "", IF(D8="", "", VLOOKUP(D8,'API Data Dictionary'!C:E,3,FALSE))) | H8: =IF(IF(D8="", "", VLOOKUP(D8,'API Data Dictionary'!C:F,4,FALSE))=0, "", IF(D8="", "", VLOOKUP(D8,'API Data Dictionary'!C:F,4,FALSE))) | I8: =IF(IF(D8="", "", VLOOKUP(D8,'API Data Dictionary'!C:G,5,FALSE))=0, "", IF(D8="", "", VLOOKUP(D8,'API Data Dictionary'!C:G,5,FALSE))) -> The ID of the linked applicant
B9: <hard code to leave blank> | C9: 0 | D9: =IF(OR(ISNUMBER(SEARCH("{", C9)),ISNUMBER(SEARCH("[", C9))), "", IFERROR(MID(C9, SEARCH("""", C9) +1, SEARCH("""", C9, SEARCH("""",C9) +1) - SEARCH("""", C9) -1), "")) | E9: =IF(D9="", "", VLOOKUP(D9,'API Data Dictionary'!C:L,10,FALSE)) | F9: =IF(D9="", "", VLOOKUP(D9,'API Data Dictionary'!C:D,2,FALSE)) | G9: =IF(IF(D9="", "", VLOOKUP(D9,'API Data Dictionary'!C:E,3,FALSE))=0, "", IF(D9="", "", VLOOKUP(D9,'API Data Dictionary'!C:E,3,FALSE))) | H9: =IF(IF(D9="", "", VLOOKUP(D9,'API Data Dictionary'!C:F,4,FALSE))=0, "", IF(D9="", "", VLOOKUP(D9,'API Data Dictionary'!C:F,4,FALSE))) | I9: Can be blank
C10: ], | D10: =IF(OR(ISNUMBER(SEARCH("{", C10)),ISNUMBER(SEARCH("[", C10))), "", IFERROR(MID(C10, SEARCH("""", C10) +1, SEARCH("""", C10, SEARCH("""",C10) +1) - SEARCH("""", C10) -1), "")) | E10: =IF(D10="", "", VLOOKUP(D10,'API Data Dictionary'!C:L,10,FALSE)) | F10: =IF(D10="", "", VLOOKUP(D10,'API Data Dictionary'!C:D,2,FALSE)) | G10: =IF(IF(D10="", "", VLOOKUP(D10,'API Data Dictionary'!C:E,3,FALSE))=0, "", IF(D10="", "", VLOOKUP(D10,'API Data Dictionary'!C:E,3,FALSE))) | H10: =IF(IF(D10="", "", VLOOKUP(D10,'API Data Dictionary'!C:F,4,FALSE))=0, "", IF(D10="", "", VLOOKUP(D10,'API Data Dictionary'!C:F,4,FALSE))) | I10: =IF(IF(D10="", "", VLOOKUP(D10,'API Data Dictionary'!C:G,5,FALSE))=0, "", IF(D10="", "", VLOOKUP(D10,'API Data Dictionary'!C:G,5,FALSE)))
C11: "tenantTypeId": 1, | D11: =IF(OR(ISNUMBER(SEARCH("{", C11)),ISNUMBER(SEARCH("[", C11))), "", IFERROR(MID(C11, SEARCH("""", C11) +1, SEARCH("""", C11, SEARCH("""",C11) +1) - SEARCH("""", C11) -1), "")) -> tenantTypeId | E11: =IF(D11="", "", VLOOKUP(D11,'API Data Dictionary'!C:L,10,FALSE)) -> M | F11: =IF(D11="", "", VLOOKUP(D11,'API Data Dictionary'!C:D,2,FALSE)) -> enum - Tenant Type | G11: =IF(IF(D11="", "", VLOOKUP(D11,'API Data Dictionary'!C:E,3,FALSE))=0, "", IF(D11="", "", VLOOKUP(D11,'API Data Dictionary'!C:E,3,FALSE))) | H11: =IF(IF(D11="", "", VLOOKUP(D11,'API Data Dictionary'!C:F,4,FALSE))=0, "", IF(D11="", "", VLOOKUP(D11,'API Data Dictionary'!C:F,4,FALSE))) -> Valid Values 1-4 (See enum definition) | I11: =IF(IF(D11="", "", VLOOKUP(D11,'API Data Dictionary'!C:G,5,FALSE))=0, "", IF(D11="", "", VLOOKUP(D11,'API Data Dictionary'!C:G,5,FALSE))) -> The Type of the Tenant, e.g. lead or Guarantor
C12: "referenceType": 1, | D12: =IF(OR(ISNUMBER(SEARCH("{", C12)),ISNUMBER(SEARCH("[", C12))), "", IFERROR(MID(C12, SEARCH("""", C12) +1, SEARCH("""", C12, SEARCH("""",C12) +1) - SEARCH("""", C12) -1), "")) -> referenceType | E12: =IF(D12="", "", VLOOKUP(D12,'API Data Dictionary'!C:L,10,FALSE)) -> M | F12: =IF(D12="", "", VLOOKUP(D12,'API Data Dictionary'!C:D,2,FALSE)) -> enum - Reference Type | G12: =IF(IF(D12="", "", VLOOKUP(D12,'API Data Dictionary'!C:E,3,FALSE))=0, "", IF(D12="", "", VLOOKUP(D12,'API Data Dictionary'!C:E,3,FALSE))) | H12: =IF(IF(D12="", "", VLOOKUP(D12,'API Data Dictionary'!C:F,4,FALSE))=0, "", IF(D12="", "", VLOOKUP(D12,'API Data Dictionary'!C:F,4,FALSE))) -> Valid Values 1-2 (See enum definition) | I12: =IF(IF(D12="", "", VLOOKUP(D12,'API Data Dictionary'!C:G,5,FALSE))=0, "", IF(D12="", "", VLOOKUP(D12,'API Data Dictionary'!C:G,5,FALSE))) -> The Type of reference, e.g Full or Express
B13: contactRole.Right_to_Rent__c | C13: "rightToRent": true, | D13: =IF(OR(ISNUMBER(SEARCH("{", C13)),ISNUMBER(SEARCH("[", C13))), "", IFERROR(MID(C13, SEARCH("""", C13) +1, SEARCH("""", C13, SEARCH("""",C13) +1) - SEARCH("""", C13) -1), "")) -> rightToRent | E13: =IF(D13="", "", VLOOKUP(D13,'API Data Dictionary'!C:L,10,FALSE)) -> M | F13: =IF(D13="", "", VLOOKUP(D13,'API Data Dictionary'!C:D,2,FALSE)) -> boolean | G13: =IF(IF(D13="", "", VLOOKUP(D13,'API Data Dictionary'!C:E,3,FALSE))=0, "", IF(D13="", "", VLOOKUP(D13,'API Data Dictionary'!C:E,3,FALSE))) | H13: =IF(IF(D13="", "", VLOOKUP(D13,'API Data Dictionary'!C:F,4,FALSE))=0, "", IF(D13="", "", VLOOKUP(D13,'API Data Dictionary'!C:F,4,FALSE))) | I13: =IF(IF(D13="", "", VLOOKUP(D13,'API Data Dictionary'!C:G,5,FALSE))=0, "", IF(D13="", "", VLOOKUP(D13,'API Data Dictionary'!C:G,5,FALSE))) -> Use Right to rent product for this reference
B14: contactRole.Contact.Salutation [CMDT to map to enum] | C14: "title": 1, | D14: =IF(OR(ISNUMBER(SEARCH("{", C14)),ISNUMBER(SEARCH("[", C14))), "", IFERROR(MID(C14, SEARCH("""", C14) +1, SEARCH("""", C14, SEARCH("""",C14) +1) - SEARCH("""", C14) -1), "")) -> title | E14: =IF(D14="", "", VLOOKUP(D14,'API Data Dictionary'!C:L,10,FALSE)) -> M | F14: =IF(D14="", "", VLOOKUP(D14,'API Data Dictionary'!C:D,2,FALSE)) -> enum - Title | G14: =IF(IF(D14="", "", VLOOKUP(D14,'API Data Dictionary'!C:E,3,FALSE))=0, "", IF(D14="", "", VLOOKUP(D14,'API Data Dictionary'!C:E,3,FALSE))) | H14: =IF(IF(D14="", "", VLOOKUP(D14,'API Data Dictionary'!C:F,4,FALSE))=0, "", IF(D14="", "", VLOOKUP(D14,'API Data Dictionary'!C:F,4,FALSE))) -> Valid Values 1-7 (See enum definition) | I14: =IF(IF(D14="", "", VLOOKUP(D14,'API Data Dictionary'!C:G,5,FALSE))=0, "", IF(D14="", "", VLOOKUP(D14,'API Data Dictionary'!C:G,5,FALSE))) -> The persons title, e.g. Mr, Mrs, etc.
C15: "otherTitle": "string", | D15: =IF(OR(ISNUMBER(SEARCH("{", C15)),ISNUMBER(SEARCH("[", C15))), "", IFERROR(MID(C15, SEARCH("""", C15) +1, SEARCH("""", C15, SEARCH("""",C15) +1) - SEARCH("""", C15) -1), "")) -> otherTitle | E15: =IF(D15="", "", VLOOKUP(D15,'API Data Dictionary'!C:L,10,FALSE)) -> X | F15: =IF(D15="", "", VLOOKUP(D15,'API Data Dictionary'!C:D,2,FALSE)) -> string | G15: =IF(IF(D15="", "", VLOOKUP(D15,'API Data Dictionary'!C:E,3,FALSE))=0, "", IF(D15="", "", VLOOKUP(D15,'API Data Dictionary'!C:E,3,FALSE))) -> 100 | H15: =IF(IF(D15="", "", VLOOKUP(D15,'API Data Dictionary'!C:F,4,FALSE))=0, "", IF(D15="", "", VLOOKUP(D15,'API Data Dictionary'!C:F,4,FALSE))) | I15: =IF(IF(D15="", "", VLOOKUP(D15,'API Data Dictionary'!C:G,5,FALSE))=0, "", IF(D15="", "", VLOOKUP(D15,'API Data Dictionary'!C:G,5,FALSE))) -> If other is chosen for title, this is a text field to enter the specific title
B16: contactRole.Contact.FirstName | C16: "firstName": "string", | D16: =IF(OR(ISNUMBER(SEARCH("{", C16)),ISNUMBER(SEARCH("[", C16))), "", IFERROR(MID(C16, SEARCH("""", C16) +1, SEARCH("""", C16, SEARCH("""",C16) +1) - SEARCH("""", C16) -1), "")) -> firstName | E16: =IF(D16="", "", VLOOKUP(D16,'API Data Dictionary'!C:L,10,FALSE)) -> M | F16: =IF(D16="", "", VLOOKUP(D16,'API Data Dictionary'!C:D,2,FALSE)) -> string | G16: =IF(IF(D16="", "", VLOOKUP(D16,'API Data Dictionary'!C:E,3,FALSE))=0, "", IF(D16="", "", VLOOKUP(D16,'API Data Dictionary'!C:E,3,FALSE))) -> 100 | H16: =IF(IF(D16="", "", VLOOKUP(D16,'API Data Dictionary'!C:F,4,FALSE))=0, "", IF(D16="", "", VLOOKUP(D16,'API Data Dictionary'!C:F,4,FALSE))) -> pattern: ^[a-zA-Z0-9\-' ]*$ | I16: =IF(IF(D16="", "", VLOOKUP(D16,'API Data Dictionary'!C:G,5,FALSE))=0, "", IF(D16="", "", VLOOKUP(D16,'API Data Dictionary'!C:G,5,FALSE))) -> First name, validated against the RegEx pattern
C17: "middleName": "string", | D17: =IF(OR(ISNUMBER(SEARCH("{", C17)),ISNUMBER(SEARCH("[", C17))), "", IFERROR(MID(C17, SEARCH("""", C17) +1, SEARCH("""", C17, SEARCH("""",C17) +1) - SEARCH("""", C17) -1), "")) -> middleName | E17: =IF(D17="", "", VLOOKUP(D17,'API Data Dictionary'!C:L,10,FALSE)) -> X | F17: =IF(D17="", "", VLOOKUP(D17,'API Data Dictionary'!C:D,2,FALSE)) -> string | G17: =IF(IF(D17="", "", VLOOKUP(D17,'API Data Dictionary'!C:E,3,FALSE))=0, "", IF(D17="", "", VLOOKUP(D17,'API Data Dictionary'!C:E,3,FALSE))) -> 50 | H17: =IF(IF(D17="", "", VLOOKUP(D17,'API Data Dictionary'!C:F,4,FALSE))=0, "", IF(D17="", "", VLOOKUP(D17,'API Data Dictionary'!C:F,4,FALSE))) -> pattern: ^[a-zA-Z0-9\-' ]*$ | I17: =IF(IF(D17="", "", VLOOKUP(D17,'API Data Dictionary'!C:G,5,FALSE))=0, "", IF(D17="", "", VLOOKUP(D17,'API Data Dictionary'!C:G,5,FALSE))) -> Middle name, validated against the RegEx pattern
B18: contactRole.Contact.LastName | C18: "surname": "string", | D18: =IF(OR(ISNUMBER(SEARCH("{", C18)),ISNUMBER(SEARCH("[", C18))), "", IFERROR(MID(C18, SEARCH("""", C18) +1, SEARCH("""", C18, SEARCH("""",C18) +1) - SEARCH("""", C18) -1), "")) -> surname | E18: =IF(D18="", "", VLOOKUP(D18,'API Data Dictionary'!C:L,10,FALSE)) -> M | F18: =IF(D18="", "", VLOOKUP(D18,'API Data Dictionary'!C:D,2,FALSE)) -> string | G18: =IF(IF(D18="", "", VLOOKUP(D18,'API Data Dictionary'!C:E,3,FALSE))=0, "", IF(D18="", "", VLOOKUP(D18,'API Data Dictionary'!C:E,3,FALSE))) -> 100 | H18: =IF(IF(D18="", "", VLOOKUP(D18,'API Data Dictionary'!C:F,4,FALSE))=0, "", IF(D18="", "", VLOOKUP(D18,'API Data Dictionary'!C:F,4,FALSE))) -> pattern: ^[a-zA-Z0-9\-' ]*$ | I18: =IF(IF(D18="", "", VLOOKUP(D18,'API Data Dictionary'!C:G,5,FALSE))=0, "", IF(D18="", "", VLOOKUP(D18,'API Data Dictionary'!C:G,5,FALSE))) -> Surname name, validated against the RegEx pattern
B19: contactRole.Direct_Debit_Amount__c | C19: "shareOfRent": 0, | D19: =IF(OR(ISNUMBER(SEARCH("{", C19)),ISNUMBER(SEARCH("[", C19))), "", IFERROR(MID(C19, SEARCH("""", C19) +1, SEARCH("""", C19, SEARCH("""",C19) +1) - SEARCH("""", C19) -1), "")) -> shareOfRent | E19: =IF(D19="", "", VLOOKUP(D19,'API Data Dictionary'!C:L,10,FALSE)) -> M | F19: =IF(D19="", "", VLOOKUP(D19,'API Data Dictionary'!C:D,2,FALSE)) -> number (double) | G19: =IF(IF(D19="", "", VLOOKUP(D19,'API Data Dictionary'!C:E,3,FALSE))=0, "", IF(D19="", "", VLOOKUP(D19,'API Data Dictionary'!C:E,3,FALSE))) | H19: =IF(IF(D19="", "", VLOOKUP(D19,'API Data Dictionary'!C:F,4,FALSE))=0, "", IF(D19="", "", VLOOKUP(D19,'API Data Dictionary'!C:F,4,FALSE))) -> pattern: ^\d*.\d{0,2}$ | I19: =IF(IF(D19="", "", VLOOKUP(D19,'API Data Dictionary'!C:G,5,FALSE))=0, "", IF(D19="", "", VLOOKUP(D19,'API Data Dictionary'!C:G,5,FALSE))) -> GBP value of the applicants share of the rent
C20: "telephoneCountryID": 1, | D20: =IF(OR(ISNUMBER(SEARCH("{", C20)),ISNUMBER(SEARCH("[", C20))), "", IFERROR(MID(C20, SEARCH("""", C20) +1, SEARCH("""", C20, SEARCH("""",C20) +1) - SEARCH("""", C20) -1), "")) -> telephoneCountryID | E20: =IF(D20="", "", VLOOKUP(D20,'API Data Dictionary'!C:L,10,FALSE)) -> M | F20: =IF(D20="", "", VLOOKUP(D20,'API Data Dictionary'!C:D,2,FALSE)) -> enum -Country/Location Code | G20: =IF(IF(D20="", "", VLOOKUP(D20,'API Data Dictionary'!C:E,3,FALSE))=0, "", IF(D20="", "", VLOOKUP(D20,'API Data Dictionary'!C:E,3,FALSE))) | H20: =IF(IF(D20="", "", VLOOKUP(D20,'API Data Dictionary'!C:F,4,FALSE))=0, "", IF(D20="", "", VLOOKUP(D20,'API Data Dictionary'!C:F,4,FALSE))) -> Valid Values 1-239 (See enum definition) | I20: =IF(IF(D20="", "", VLOOKUP(D20,'API Data Dictionary'!C:G,5,FALSE))=0, "", IF(D20="", "", VLOOKUP(D20,'API Data Dictionary'!C:G,5,FALSE))) -> The country/location code of the phone number
B21: contactRole.Contact.MobilePhone | C21: "contactTelephoneNo": "string", | D21: =IF(OR(ISNUMBER(SEARCH("{", C21)),ISNUMBER(SEARCH("[", C21))), "", IFERROR(MID(C21, SEARCH("""", C21) +1, SEARCH("""", C21, SEARCH("""",C21) +1) - SEARCH("""", C21) -1), "")) -> contactTelephoneNo | E21: =IF(D21="", "", VLOOKUP(D21,'API Data Dictionary'!C:L,10,FALSE)) -> M | F21: =IF(D21="", "", VLOOKUP(D21,'API Data Dictionary'!C:D,2,FALSE)) -> string | G21: =IF(IF(D21="", "", VLOOKUP(D21,'API Data Dictionary'!C:E,3,FALSE))=0, "", IF(D21="", "", VLOOKUP(D21,'API Data Dictionary'!C:E,3,FALSE))) -> 15 | H21: =IF(IF(D21="", "", VLOOKUP(D21,'API Data Dictionary'!C:F,4,FALSE))=0, "", IF(D21="", "", VLOOKUP(D21,'API Data Dictionary'!C:F,4,FALSE))) -> pattern: ^(\d{11})$ | I21: =IF(IF(D21="", "", VLOOKUP(D21,'API Data Dictionary'!C:G,5,FALSE))=0, "", IF(D21="", "", VLOOKUP(D21,'API Data Dictionary'!C:G,5,FALSE))) -> The telephone number
B22: contactRole.Contact.Email | C22: "emailAddress": "string" | D22: =IF(OR(ISNUMBER(SEARCH("{", C22)),ISNUMBER(SEARCH("[", C22))), "", IFERROR(MID(C22, SEARCH("""", C22) +1, SEARCH("""", C22, SEARCH("""",C22) +1) - SEARCH("""", C22) -1), "")) -> emailAddress | E22: =IF(D22="", "", VLOOKUP(D22,'API Data Dictionary'!C:L,10,FALSE)) -> M | F22: =IF(D22="", "", VLOOKUP(D22,'API Data Dictionary'!C:D,2,FALSE)) -> string ($email) | G22: =IF(IF(D22="", "", VLOOKUP(D22,'API Data Dictionary'!C:E,3,FALSE))=0, "", IF(D22="", "", VLOOKUP(D22,'API Data Dictionary'!C:E,3,FALSE))) -> 200 | H22: =IF(IF(D22="", "", VLOOKUP(D22,'API Data Dictionary'!C:F,4,FALSE))=0, "", IF(D22="", "", VLOOKUP(D22,'API Data Dictionary'!C:F,4,FALSE))) -> pattern: ^(?!.*\.\.)(?!.*\\_\\_)(?!.*\-\-)[a-zA-Z0-9][-a-zA-Z0-9._]+[a-zA-Z0-9]@([-a-zA-Z0-9]+.)+[a-zA-Z]{2,5}$ | I22: =IF(IF(D22="", "", VLOOKUP(D22,'API Data Dictionary'!C:G,5,FALSE))=0, "", IF(D22="", "", VLOOKUP(D22,'API Data Dictionary'!C:G,5,FALSE))) -> The email address
C23: } | D23: =IF(OR(ISNUMBER(SEARCH("{", C23)),ISNUMBER(SEARCH("[", C23))), "", IFERROR(MID(C23, SEARCH("""", C23) +1, SEARCH("""", C23, SEARCH("""",C23) +1) - SEARCH("""", C23) -1), "")) | E23: =IF(D23="", "", VLOOKUP(D23,'API Data Dictionary'!C:L,10,FALSE)) | F23: =IF(D23="", "", VLOOKUP(D23,'API Data Dictionary'!C:D,2,FALSE)) | G23: =IF(IF(D23="", "", VLOOKUP(D23,'API Data Dictionary'!C:E,3,FALSE))=0, "", IF(D23="", "", VLOOKUP(D23,'API Data Dictionary'!C:E,3,FALSE))) | H23: =IF(IF(D23="", "", VLOOKUP(D23,'API Data Dictionary'!C:F,4,FALSE))=0, "", IF(D23="", "", VLOOKUP(D23,'API Data Dictionary'!C:F,4,FALSE))) | I23: =IF(IF(D23="", "", VLOOKUP(D23,'API Data Dictionary'!C:G,5,FALSE))=0, "", IF(D23="", "", VLOOKUP(D23,'API Data Dictionary'!C:G,5,FALSE)))
C24: } | D24: =IF(OR(ISNUMBER(SEARCH("{", C24)),ISNUMBER(SEARCH("[", C24))), "", IFERROR(MID(C24, SEARCH("""", C24) +1, SEARCH("""", C24, SEARCH("""",C24) +1) - SEARCH("""", C24) -1), "")) | E24: =IF(D24="", "", VLOOKUP(D24,'API Data Dictionary'!C:L,10,FALSE)) | F24: =IF(D24="", "", VLOOKUP(D24,'API Data Dictionary'!C:D,2,FALSE)) | G24: =IF(IF(D24="", "", VLOOKUP(D24,'API Data Dictionary'!C:E,3,FALSE))=0, "", IF(D24="", "", VLOOKUP(D24,'API Data Dictionary'!C:E,3,FALSE))) | H24: =IF(IF(D24="", "", VLOOKUP(D24,'API Data Dictionary'!C:F,4,FALSE))=0, "", IF(D24="", "", VLOOKUP(D24,'API Data Dictionary'!C:F,4,FALSE))) | I24: =IF(IF(D24="", "", VLOOKUP(D24,'API Data Dictionary'!C:G,5,FALSE))=0, "", IF(D24="", "", VLOOKUP(D24,'API Data Dictionary'!C:G,5,FALSE)))
D25: =IF(OR(ISNUMBER(SEARCH("{", C25)),ISNUMBER(SEARCH("[", C25))), "", IFERROR(MID(C25, SEARCH("""", C25) +1, SEARCH("""", C25, SEARCH("""",C25) +1) - SEARCH("""", C25) -1), "")) | E25: =IF(D25="", "", VLOOKUP(D25,'API Data Dictionary'!C:L,10,FALSE)) | F25: =IF(D25="", "", VLOOKUP(D25,'API Data Dictionary'!C:D,2,FALSE)) | G25: =IF(IF(D25="", "", VLOOKUP(D25,'API Data Dictionary'!C:E,3,FALSE))=0, "", IF(D25="", "", VLOOKUP(D25,'API Data Dictionary'!C:E,3,FALSE))) | H25: =IF(IF(D25="", "", VLOOKUP(D25,'API Data Dictionary'!C:F,4,FALSE))=0, "", IF(D25="", "", VLOOKUP(D25,'API Data Dictionary'!C:F,4,FALSE))) | I25: =IF(IF(D25="", "", VLOOKUP(D25,'API Data Dictionary'!C:G,5,FALSE))=0, "", IF(D25="", "", VLOOKUP(D25,'API Data Dictionary'!C:G,5,FALSE)))
C26: With All data Example Request | D26: =IF(OR(ISNUMBER(SEARCH("{", C26)),ISNUMBER(SEARCH("[", C26))), "", IFERROR(MID(C26, SEARCH("""", C26) +1, SEARCH("""", C26, SEARCH("""",C26) +1) - SEARCH("""", C26) -1), "")) | E26: =IF(D26="", "", VLOOKUP(D26,'API Data Dictionary'!C:L,10,FALSE)) | F26: =IF(D26="", "", VLOOKUP(D26,'API Data Dictionary'!C:D,2,FALSE)) | G26: =IF(IF(D26="", "", VLOOKUP(D26,'API Data Dictionary'!C:E,3,FALSE))=0, "", IF(D26="", "", VLOOKUP(D26,'API Data Dictionary'!C:E,3,FALSE))) | H26: =IF(IF(D26="", "", VLOOKUP(D26,'API Data Dictionary'!C:F,4,FALSE))=0, "", IF(D26="", "", VLOOKUP(D26,'API Data Dictionary'!C:F,4,FALSE))) | I26: =IF(IF(D26="", "", VLOOKUP(D26,'API Data Dictionary'!C:G,5,FALSE))=0, "", IF(D26="", "", VLOOKUP(D26,'API Data Dictionary'!C:G,5,FALSE)))
C27: { | D27: =IF(OR(ISNUMBER(SEARCH("{", C27)),ISNUMBER(SEARCH("[", C27))), "", IFERROR(MID(C27, SEARCH("""", C27) +1, SEARCH("""", C27, SEARCH("""",C27) +1) - SEARCH("""", C27) -1), "")) | E27: =IF(D27="", "", VLOOKUP(D27,'API Data Dictionary'!C:L,10,FALSE)) | F27: =IF(D27="", "", VLOOKUP(D27,'API Data Dictionary'!C:D,2,FALSE)) | G27: =IF(IF(D27="", "", VLOOKUP(D27,'API Data Dictionary'!C:E,3,FALSE))=0, "", IF(D27="", "", VLOOKUP(D27,'API Data Dictionary'!C:E,3,FALSE))) | H27: =IF(IF(D27="", "", VLOOKUP(D27,'API Data Dictionary'!C:F,4,FALSE))=0, "", IF(D27="", "", VLOOKUP(D27,'API Data Dictionary'!C:F,4,FALSE))) | I27: =IF(IF(D27="", "", VLOOKUP(D27,'API Data Dictionary'!C:G,5,FALSE))=0, "", IF(D27="", "", VLOOKUP(D27,'API Data Dictionary'!C:G,5,FALSE)))
B28: Referencing_HL_Auth_Setting__mdt.Agent_Code__c; | C28: "agentCode": "string", | D28: =IF(OR(ISNUMBER(SEARCH("{", C28)),ISNUMBER(SEARCH("[", C28))), "", IFERROR(MID(C28, SEARCH("""", C28) +1, SEARCH("""", C28, SEARCH("""",C28) +1) - SEARCH("""", C28) -1), "")) -> agentCode | E28: =IF(D28="", "", VLOOKUP(D28,'API Data Dictionary'!C:L,10,FALSE)) -> M | F28: =IF(D28="", "", VLOOKUP(D28,'API Data Dictionary'!C:D,2,FALSE)) -> string | G28: =IF(IF(D28="", "", VLOOKUP(D28,'API Data Dictionary'!C:E,3,FALSE))=0, "", IF(D28="", "", VLOOKUP(D28,'API Data Dictionary'!C:E,3,FALSE))) -> 50 | H28: =IF(IF(D28="", "", VLOOKUP(D28,'API Data Dictionary'!C:F,4,FALSE))=0, "", IF(D28="", "", VLOOKUP(D28,'API Data Dictionary'!C:F,4,FALSE))) | I28: =IF(IF(D28="", "", VLOOKUP(D28,'API Data Dictionary'!C:G,5,FALSE))=0, "", IF(D28="", "", VLOOKUP(D28,'API Data Dictionary'!C:G,5,FALSE))) -> AgentCode is the Unique Key provided to the Agent when onboarding as a Barbon Customer. An AgentID may be linked to many Properties being managed by that Agent and Each property may be linked to 1 or more TenancyID's.
B29: opp.Referencing_Property_Tenancy_Id__c | C29: "propertyTenancyId": 0, | D29: =IF(OR(ISNUMBER(SEARCH("{", C29)),ISNUMBER(SEARCH("[", C29))), "", IFERROR(MID(C29, SEARCH("""", C29) +1, SEARCH("""", C29, SEARCH("""",C29) +1) - SEARCH("""", C29) -1), "")) -> propertyTenancyId | E29: =IF(D29="", "", VLOOKUP(D29,'API Data Dictionary'!C:L,10,FALSE)) -> 0 | F29: =IF(D29="", "", VLOOKUP(D29,'API Data Dictionary'!C:D,2,FALSE)) -> integer | G29: =IF(IF(D29="", "", VLOOKUP(D29,'API Data Dictionary'!C:E,3,FALSE))=0, "", IF(D29="", "", VLOOKUP(D29,'API Data Dictionary'!C:E,3,FALSE))) | H29: =IF(IF(D29="", "", VLOOKUP(D29,'API Data Dictionary'!C:F,4,FALSE))=0, "", IF(D29="", "", VLOOKUP(D29,'API Data Dictionary'!C:F,4,FALSE))) | I29: =IF(IF(D29="", "", VLOOKUP(D29,'API Data Dictionary'!C:G,5,FALSE))=0, "", IF(D29="", "", VLOOKUP(D29,'API Data Dictionary'!C:G,5,FALSE))) -> The ID of the property tenancy
B30: <hard code to false> | C30: "isSentTenantLink": false, | D30: =IF(OR(ISNUMBER(SEARCH("{", C30)),ISNUMBER(SEARCH("[", C30))), "", IFERROR(MID(C30, SEARCH("""", C30) +1, SEARCH("""", C30, SEARCH("""",C30) +1) - SEARCH("""", C30) -1), "")) -> isSentTenantLink | E30: =IF(D30="", "", VLOOKUP(D30,'API Data Dictionary'!C:L,10,FALSE)) -> 0 | F30: =IF(D30="", "", VLOOKUP(D30,'API Data Dictionary'!C:D,2,FALSE)) -> boolean | G30: =IF(IF(D30="", "", VLOOKUP(D30,'API Data Dictionary'!C:E,3,FALSE))=0, "", IF(D30="", "", VLOOKUP(D30,'API Data Dictionary'!C:E,3,FALSE))) | H30: =IF(IF(D30="", "", VLOOKUP(D30,'API Data Dictionary'!C:F,4,FALSE))=0, "", IF(D30="", "", VLOOKUP(D30,'API Data Dictionary'!C:F,4,FALSE))) | I30: =IF(IF(D30="", "", VLOOKUP(D30,'API Data Dictionary'!C:G,5,FALSE))=0, "", IF(D30="", "", VLOOKUP(D30,'API Data Dictionary'!C:G,5,FALSE))) -> Denotes whether the Tentant link is sent
C31: "linkedApplicantID": | D31: =IF(OR(ISNUMBER(SEARCH("{", C31)),ISNUMBER(SEARCH("[", C31))), "", IFERROR(MID(C31, SEARCH("""", C31) +1, SEARCH("""", C31, SEARCH("""",C31) +1) - SEARCH("""", C31) -1), "")) -> linkedApplicantID | E31: =IF(D31="", "", VLOOKUP(D31,'API Data Dictionary'!C:L,10,FALSE)) -> 0 | F31: =IF(D31="", "", VLOOKUP(D31,'API Data Dictionary'!C:D,2,FALSE)) -> integer | G31: =IF(IF(D31="", "", VLOOKUP(D31,'API Data Dictionary'!C:E,3,FALSE))=0, "", IF(D31="", "", VLOOKUP(D31,'API Data Dictionary'!C:E,3,FALSE))) | H31: =IF(IF(D31="", "", VLOOKUP(D31,'API Data Dictionary'!C:F,4,FALSE))=0, "", IF(D31="", "", VLOOKUP(D31,'API Data Dictionary'!C:F,4,FALSE))) | I31: =IF(IF(D31="", "", VLOOKUP(D31,'API Data Dictionary'!C:G,5,FALSE))=0, "", IF(D31="", "", VLOOKUP(D31,'API Data Dictionary'!C:G,5,FALSE))) -> The ID of the linked applicant
B32: <hard code to leave blank> | C32: [0 | D32: =IF(OR(ISNUMBER(SEARCH("{", C32)),ISNUMBER(SEARCH("[", C32))), "", IFERROR(MID(C32, SEARCH("""", C32) +1, SEARCH("""", C32, SEARCH("""",C32) +1) - SEARCH("""", C32) -1), "")) | E32: =IF(D32="", "", VLOOKUP(D32,'API Data Dictionary'!C:L,10,FALSE)) | F32: =IF(D32="", "", VLOOKUP(D32,'API Data Dictionary'!C:D,2,FALSE)) | G32: =IF(IF(D32="", "", VLOOKUP(D32,'API Data Dictionary'!C:E,3,FALSE))=0, "", IF(D32="", "", VLOOKUP(D32,'API Data Dictionary'!C:E,3,FALSE))) | H32: =IF(IF(D32="", "", VLOOKUP(D32,'API Data Dictionary'!C:F,4,FALSE))=0, "", IF(D32="", "", VLOOKUP(D32,'API Data Dictionary'!C:F,4,FALSE))) | I32: =IF(IF(D32="", "", VLOOKUP(D32,'API Data Dictionary'!C:G,5,FALSE))=0, "", IF(D32="", "", VLOOKUP(D32,'API Data Dictionary'!C:G,5,FALSE)))
C33: ], | D33: =IF(OR(ISNUMBER(SEARCH("{", C33)),ISNUMBER(SEARCH("[", C33))), "", IFERROR(MID(C33, SEARCH("""", C33) +1, SEARCH("""", C33, SEARCH("""",C33) +1) - SEARCH("""", C33) -1), "")) | E33: =IF(D33="", "", VLOOKUP(D33,'API Data Dictionary'!C:L,10,FALSE)) | F33: =IF(D33="", "", VLOOKUP(D33,'API Data Dictionary'!C:D,2,FALSE)) | G33: =IF(IF(D33="", "", VLOOKUP(D33,'API Data Dictionary'!C:E,3,FALSE))=0, "", IF(D33="", "", VLOOKUP(D33,'API Data Dictionary'!C:E,3,FALSE))) | H33: =IF(IF(D33="", "", VLOOKUP(D33,'API Data Dictionary'!C:F,4,FALSE))=0, "", IF(D33="", "", VLOOKUP(D33,'API Data Dictionary'!C:F,4,FALSE))) | I33: =IF(IF(D33="", "", VLOOKUP(D33,'API Data Dictionary'!C:G,5,FALSE))=0, "", IF(D33="", "", VLOOKUP(D33,'API Data Dictionary'!C:G,5,FALSE)))
C34: "tenantTypeId": 1, | D34: =IF(OR(ISNUMBER(SEARCH("{", C34)),ISNUMBER(SEARCH("[", C34))), "", IFERROR(MID(C34, SEARCH("""", C34) +1, SEARCH("""", C34, SEARCH("""",C34) +1) - SEARCH("""", C34) -1), "")) -> tenantTypeId | E34: =IF(D34="", "", VLOOKUP(D34,'API Data Dictionary'!C:L,10,FALSE)) -> M | F34: =IF(D34="", "", VLOOKUP(D34,'API Data Dictionary'!C:D,2,FALSE)) -> enum - Tenant Type | G34: =IF(IF(D34="", "", VLOOKUP(D34,'API Data Dictionary'!C:E,3,FALSE))=0, "", IF(D34="", "", VLOOKUP(D34,'API Data Dictionary'!C:E,3,FALSE))) | H34: =IF(IF(D34="", "", VLOOKUP(D34,'API Data Dictionary'!C:F,4,FALSE))=0, "", IF(D34="", "", VLOOKUP(D34,'API Data Dictionary'!C:F,4,FALSE))) -> Valid Values 1-4 (See enum definition) | I34: =IF(IF(D34="", "", VLOOKUP(D34,'API Data Dictionary'!C:G,5,FALSE))=0, "", IF(D34="", "", VLOOKUP(D34,'API Data Dictionary'!C:G,5,FALSE))) -> The Type of the Tenant, e.g. lead or Guarantor
C35: "referenceType": 1, | D35: =IF(OR(ISNUMBER(SEARCH("{", C35)),ISNUMBER(SEARCH("[", C35))), "", IFERROR(MID(C35, SEARCH("""", C35) +1, SEARCH("""", C35, SEARCH("""",C35) +1) - SEARCH("""", C35) -1), "")) -> referenceType | E35: =IF(D35="", "", VLOOKUP(D35,'API Data Dictionary'!C:L,10,FALSE)) -> M | F35: =IF(D35="", "", VLOOKUP(D35,'API Data Dictionary'!C:D,2,FALSE)) -> enum - Reference Type | G35: =IF(IF(D35="", "", VLOOKUP(D35,'API Data Dictionary'!C:E,3,FALSE))=0, "", IF(D35="", "", VLOOKUP(D35,'API Data Dictionary'!C:E,3,FALSE))) | H35: =IF(IF(D35="", "", VLOOKUP(D35,'API Data Dictionary'!C:F,4,FALSE))=0, "", IF(D35="", "", VLOOKUP(D35,'API Data Dictionary'!C:F,4,FALSE))) -> Valid Values 1-2 (See enum definition) | I35: =IF(IF(D35="", "", VLOOKUP(D35,'API Data Dictionary'!C:G,5,FALSE))=0, "", IF(D35="", "", VLOOKUP(D35,'API Data Dictionary'!C:G,5,FALSE))) -> The Type of reference, e.g Full or Express
B36: contactRole.Right_to_Rent__c | C36: "rightToRent": true, | D36: =IF(OR(ISNUMBER(SEARCH("{", C36)),ISNUMBER(SEARCH("[", C36))), "", IFERROR(MID(C36, SEARCH("""", C36) +1, SEARCH("""", C36, SEARCH("""",C36) +1) - SEARCH("""", C36) -1), "")) -> rightToRent | E36: =IF(D36="", "", VLOOKUP(D36,'API Data Dictionary'!C:L,10,FALSE)) -> M | F36: =IF(D36="", "", VLOOKUP(D36,'API Data Dictionary'!C:D,2,FALSE)) -> boolean | G36: =IF(IF(D36="", "", VLOOKUP(D36,'API Data Dictionary'!C:E,3,FALSE))=0, "", IF(D36="", "", VLOOKUP(D36,'API Data Dictionary'!C:E,3,FALSE))) | H36: =IF(IF(D36="", "", VLOOKUP(D36,'API Data Dictionary'!C:F,4,FALSE))=0, "", IF(D36="", "", VLOOKUP(D36,'API Data Dictionary'!C:F,4,FALSE))) | I36: =IF(IF(D36="", "", VLOOKUP(D36,'API Data Dictionary'!C:G,5,FALSE))=0, "", IF(D36="", "", VLOOKUP(D36,'API Data Dictionary'!C:G,5,FALSE))) -> Use Right to rent product for this reference
B37: contactRole.Contact.Salutation | C37: "title": 1, | D37: =IF(OR(ISNUMBER(SEARCH("{", C37)),ISNUMBER(SEARCH("[", C37))), "", IFERROR(MID(C37, SEARCH("""", C37) +1, SEARCH("""", C37, SEARCH("""",C37) +1) - SEARCH("""", C37) -1), "")) -> title | E37: =IF(D37="", "", VLOOKUP(D37,'API Data Dictionary'!C:L,10,FALSE)) -> M | F37: =IF(D37="", "", VLOOKUP(D37,'API Data Dictionary'!C:D,2,FALSE)) -> enum - Title | G37: =IF(IF(D37="", "", VLOOKUP(D37,'API Data Dictionary'!C:E,3,FALSE))=0, "", IF(D37="", "", VLOOKUP(D37,'API Data Dictionary'!C:E,3,FALSE))) | H37: =IF(IF(D37="", "", VLOOKUP(D37,'API Data Dictionary'!C:F,4,FALSE))=0, "", IF(D37="", "", VLOOKUP(D37,'API Data Dictionary'!C:F,4,FALSE))) -> Valid Values 1-7 (See enum definition) | I37: =IF(IF(D37="", "", VLOOKUP(D37,'API Data Dictionary'!C:G,5,FALSE))=0, "", IF(D37="", "", VLOOKUP(D37,'API Data Dictionary'!C:G,5,FALSE))) -> The persons title, e.g. Mr, Mrs, etc.
C38: "otherTitle": "string", | D38: =IF(OR(ISNUMBER(SEARCH("{", C38)),ISNUMBER(SEARCH("[", C38))), "", IFERROR(MID(C38, SEARCH("""", C38) +1, SEARCH("""", C38, SEARCH("""",C38) +1) - SEARCH("""", C38) -1), "")) -> otherTitle | E38: =IF(D38="", "", VLOOKUP(D38,'API Data Dictionary'!C:L,10,FALSE)) -> X | F38: =IF(D38="", "", VLOOKUP(D38,'API Data Dictionary'!C:D,2,FALSE)) -> string | G38: =IF(IF(D38="", "", VLOOKUP(D38,'API Data Dictionary'!C:E,3,FALSE))=0, "", IF(D38="", "", VLOOKUP(D38,'API Data Dictionary'!C:E,3,FALSE))) -> 100 | H38: =IF(IF(D38="", "", VLOOKUP(D38,'API Data Dictionary'!C:F,4,FALSE))=0, "", IF(D38="", "", VLOOKUP(D38,'API Data Dictionary'!C:F,4,FALSE))) | I38: =IF(IF(D38="", "", VLOOKUP(D38,'API Data Dictionary'!C:G,5,FALSE))=0, "", IF(D38="", "", VLOOKUP(D38,'API Data Dictionary'!C:G,5,FALSE))) -> If other is chosen for title, this is a text field to enter the specific title
B39: contactRole.Contact.FirstName | C39: "firstName": "string", | D39: =IF(OR(ISNUMBER(SEARCH("{", C39)),ISNUMBER(SEARCH("[", C39))), "", IFERROR(MID(C39, SEARCH("""", C39) +1, SEARCH("""", C39, SEARCH("""",C39) +1) - SEARCH("""", C39) -1), "")) -> firstName | E39: =IF(D39="", "", VLOOKUP(D39,'API Data Dictionary'!C:L,10,FALSE)) -> M | F39: =IF(D39="", "", VLOOKUP(D39,'API Data Dictionary'!C:D,2,FALSE)) -> string | G39: =IF(IF(D39="", "", VLOOKUP(D39,'API Data Dictionary'!C:E,3,FALSE))=0, "", IF(D39="", "", VLOOKUP(D39,'API Data Dictionary'!C:E,3,FALSE))) -> 100 | H39: =IF(IF(D39="", "", VLOOKUP(D39,'API Data Dictionary'!C:F,4,FALSE))=0, "", IF(D39="", "", VLOOKUP(D39,'API Data Dictionary'!C:F,4,FALSE))) -> pattern: ^[a-zA-Z0-9\-' ]*$ | I39: =IF(IF(D39="", "", VLOOKUP(D39,'API Data Dictionary'!C:G,5,FALSE))=0, "", IF(D39="", "", VLOOKUP(D39,'API Data Dictionary'!C:G,5,FALSE))) -> First name, validated against the RegEx pattern
C40: "middleName": "string", | D40: =IF(OR(ISNUMBER(SEARCH("{", C40)),ISNUMBER(SEARCH("[", C40))), "", IFERROR(MID(C40, SEARCH("""", C40) +1, SEARCH("""", C40, SEARCH("""",C40) +1) - SEARCH("""", C40) -1), "")) -> middleName | E40: =IF(D40="", "", VLOOKUP(D40,'API Data Dictionary'!C:L,10,FALSE)) -> X | F40: =IF(D40="", "", VLOOKUP(D40,'API Data Dictionary'!C:D,2,FALSE)) -> string | G40: =IF(IF(D40="", "", VLOOKUP(D40,'API Data Dictionary'!C:E,3,FALSE))=0, "", IF(D40="", "", VLOOKUP(D40,'API Data Dictionary'!C:E,3,FALSE))) -> 50 | H40: =IF(IF(D40="", "", VLOOKUP(D40,'API Data Dictionary'!C:F,4,FALSE))=0, "", IF(D40="", "", VLOOKUP(D40,'API Data Dictionary'!C:F,4,FALSE))) -> pattern: ^[a-zA-Z0-9\-' ]*$ | I40: =IF(IF(D40="", "", VLOOKUP(D40,'API Data Dictionary'!C:G,5,FALSE))=0, "", IF(D40="", "", VLOOKUP(D40,'API Data Dictionary'!C:G,5,FALSE))) -> Middle name, validated against the RegEx pattern
B41: contactRole.Contact.LastName | C41: "surname": "string", | D41: =IF(OR(ISNUMBER(SEARCH("{", C41)),ISNUMBER(SEARCH("[", C41))), "", IFERROR(MID(C41, SEARCH("""", C41) +1, SEARCH("""", C41, SEARCH("""",C41) +1) - SEARCH("""", C41) -1), "")) -> surname | E41: =IF(D41="", "", VLOOKUP(D41,'API Data Dictionary'!C:L,10,FALSE)) -> M | F41: =IF(D41="", "", VLOOKUP(D41,'API Data Dictionary'!C:D,2,FALSE)) -> string | G41: =IF(IF(D41="", "", VLOOKUP(D41,'API Data Dictionary'!C:E,3,FALSE))=0, "", IF(D41="", "", VLOOKUP(D41,'API Data Dictionary'!C:E,3,FALSE))) -> 100 | H41: =IF(IF(D41="", "", VLOOKUP(D41,'API Data Dictionary'!C:F,4,FALSE))=0, "", IF(D41="", "", VLOOKUP(D41,'API Data Dictionary'!C:F,4,FALSE))) -> pattern: ^[a-zA-Z0-9\-' ]*$ | I41: =IF(IF(D41="", "", VLOOKUP(D41,'API Data Dictionary'!C:G,5,FALSE))=0, "", IF(D41="", "", VLOOKUP(D41,'API Data Dictionary'!C:G,5,FALSE))) -> Surname name, validated against the RegEx pattern
B42: contactRole.Direct_Debit_Amount__c | C42: "shareOfRent": 0, | D42: =IF(OR(ISNUMBER(SEARCH("{", C42)),ISNUMBER(SEARCH("[", C42))), "", IFERROR(MID(C42, SEARCH("""", C42) +1, SEARCH("""", C42, SEARCH("""",C42) +1) - SEARCH("""", C42) -1), "")) -> shareOfRent | E42: =IF(D42="", "", VLOOKUP(D42,'API Data Dictionary'!C:L,10,FALSE)) -> M | F42: =IF(D42="", "", VLOOKUP(D42,'API Data Dictionary'!C:D,2,FALSE)) -> number (double) | G42: =IF(IF(D42="", "", VLOOKUP(D42,'API Data Dictionary'!C:E,3,FALSE))=0, "", IF(D42="", "", VLOOKUP(D42,'API Data Dictionary'!C:E,3,FALSE))) | H42: =IF(IF(D42="", "", VLOOKUP(D42,'API Data Dictionary'!C:F,4,FALSE))=0, "", IF(D42="", "", VLOOKUP(D42,'API Data Dictionary'!C:F,4,FALSE))) -> pattern: ^\d*.\d{0,2}$ | I42: =IF(IF(D42="", "", VLOOKUP(D42,'API Data Dictionary'!C:G,5,FALSE))=0, "", IF(D42="", "", VLOOKUP(D42,'API Data Dictionary'!C:G,5,FALSE))) -> GBP value of the applicants share of the rent
C43: "telephoneCountryID": 1, | D43: =IF(OR(ISNUMBER(SEARCH("{", C43)),ISNUMBER(SEARCH("[", C43))), "", IFERROR(MID(C43, SEARCH("""", C43) +1, SEARCH("""", C43, SEARCH("""",C43) +1) - SEARCH("""", C43) -1), "")) -> telephoneCountryID | E43: =IF(D43="", "", VLOOKUP(D43,'API Data Dictionary'!C:L,10,FALSE)) -> M | F43: =IF(D43="", "", VLOOKUP(D43,'API Data Dictionary'!C:D,2,FALSE)) -> enum -Country/Location Code | G43: =IF(IF(D43="", "", VLOOKUP(D43,'API Data Dictionary'!C:E,3,FALSE))=0, "", IF(D43="", "", VLOOKUP(D43,'API Data Dictionary'!C:E,3,FALSE))) | H43: =IF(IF(D43="", "", VLOOKUP(D43,'API Data Dictionary'!C:F,4,FALSE))=0, "", IF(D43="", "", VLOOKUP(D43,'API Data Dictionary'!C:F,4,FALSE))) -> Valid Values 1-239 (See enum definition) | I43: =IF(IF(D43="", "", VLOOKUP(D43,'API Data Dictionary'!C:G,5,FALSE))=0, "", IF(D43="", "", VLOOKUP(D43,'API Data Dictionary'!C:G,5,FALSE))) -> The country/location code of the phone number
B44: contactRole.Contact.MobilePhone | C44: "contactTelephoneNo": "string", | D44: =IF(OR(ISNUMBER(SEARCH("{", C44)),ISNUMBER(SEARCH("[", C44))), "", IFERROR(MID(C44, SEARCH("""", C44) +1, SEARCH("""", C44, SEARCH("""",C44) +1) - SEARCH("""", C44) -1), "")) -> contactTelephoneNo | E44: =IF(D44="", "", VLOOKUP(D44,'API Data Dictionary'!C:L,10,FALSE)) -> M | F44: =IF(D44="", "", VLOOKUP(D44,'API Data Dictionary'!C:D,2,FALSE)) -> string | G44: =IF(IF(D44="", "", VLOOKUP(D44,'API Data Dictionary'!C:E,3,FALSE))=0, "", IF(D44="", "", VLOOKUP(D44,'API Data Dictionary'!C:E,3,FALSE))) -> 15 | H44: =IF(IF(D44="", "", VLOOKUP(D44,'API Data Dictionary'!C:F,4,FALSE))=0, "", IF(D44="", "", VLOOKUP(D44,'API Data Dictionary'!C:F,4,FALSE))) -> pattern: ^(\d{11})$ | I44: =IF(IF(D44="", "", VLOOKUP(D44,'API Data Dictionary'!C:G,5,FALSE))=0, "", IF(D44="", "", VLOOKUP(D44,'API Data Dictionary'!C:G,5,FALSE))) -> The telephone number
B45: contactRole.Contact.Email | C45: "emailAddress": "string", | D45: =IF(OR(ISNUMBER(SEARCH("{", C45)),ISNUMBER(SEARCH("[", C45))), "", IFERROR(MID(C45, SEARCH("""", C45) +1, SEARCH("""", C45, SEARCH("""",C45) +1) - SEARCH("""", C45) -1), "")) -> emailAddress | E45: =IF(D45="", "", VLOOKUP(D45,'API Data Dictionary'!C:L,10,FALSE)) -> M | F45: =IF(D45="", "", VLOOKUP(D45,'API Data Dictionary'!C:D,2,FALSE)) -> string ($email) | G45: =IF(IF(D45="", "", VLOOKUP(D45,'API Data Dictionary'!C:E,3,FALSE))=0, "", IF(D45="", "", VLOOKUP(D45,'API Data Dictionary'!C:E,3,FALSE))) -> 200 | H45: =IF(IF(D45="", "", VLOOKUP(D45,'API Data Dictionary'!C:F,4,FALSE))=0, "", IF(D45="", "", VLOOKUP(D45,'API Data Dictionary'!C:F,4,FALSE))) -> pattern: ^(?!.*\.\.)(?!.*\\_\\_)(?!.*\-\-)[a-zA-Z0-9][-a-zA-Z0-9._]+[a-zA-Z0-9]@([-a-zA-Z0-9]+.)+[a-zA-Z]{2,5}$ | I45: =IF(IF(D45="", "", VLOOKUP(D45,'API Data Dictionary'!C:G,5,FALSE))=0, "", IF(D45="", "", VLOOKUP(D45,'API Data Dictionary'!C:G,5,FALSE))) -> The email address
C46: "dateOfBirth": "2023-01-03T14:03:12.243Z", | D46: =IF(OR(ISNUMBER(SEARCH("{", C46)),ISNUMBER(SEARCH("[", C46))), "", IFERROR(MID(C46, SEARCH("""", C46) +1, SEARCH("""", C46, SEARCH("""",C46) +1) - SEARCH("""", C46) -1), "")) -> dateOfBirth | E46: x | F46: =IF(D46="", "", VLOOKUP(D46,'API Data Dictionary'!C:D,2,FALSE)) -> string ($date-time) | G46: =IF(IF(D46="", "", VLOOKUP(D46,'API Data Dictionary'!C:E,3,FALSE))=0, "", IF(D46="", "", VLOOKUP(D46,'API Data Dictionary'!C:E,3,FALSE))) | H46: =IF(IF(D46="", "", VLOOKUP(D46,'API Data Dictionary'!C:F,4,FALSE))=0, "", IF(D46="", "", VLOOKUP(D46,'API Data Dictionary'!C:F,4,FALSE))) -> DD/MM/YYYY | I46: =IF(IF(D46="", "", VLOOKUP(D46,'API Data Dictionary'!C:G,5,FALSE))=0, "", IF(D46="", "", VLOOKUP(D46,'API Data Dictionary'!C:G,5,FALSE))) -> The date of birth, formatted DD-MM-YYYY
C47: "mobileCountryId": 1, | D47: =IF(OR(ISNUMBER(SEARCH("{", C47)),ISNUMBER(SEARCH("[", C47))), "", IFERROR(MID(C47, SEARCH("""", C47) +1, SEARCH("""", C47, SEARCH("""",C47) +1) - SEARCH("""", C47) -1), "")) -> mobileCountryId | E47: x | F47: =IF(D47="", "", VLOOKUP(D47,'API Data Dictionary'!C:D,2,FALSE)) -> enum -Country/Location Code | G47: =IF(IF(D47="", "", VLOOKUP(D47,'API Data Dictionary'!C:E,3,FALSE))=0, "", IF(D47="", "", VLOOKUP(D47,'API Data Dictionary'!C:E,3,FALSE))) | H47: =IF(IF(D47="", "", VLOOKUP(D47,'API Data Dictionary'!C:F,4,FALSE))=0, "", IF(D47="", "", VLOOKUP(D47,'API Data Dictionary'!C:F,4,FALSE))) -> Valid Values 1-239 (See enum definition) | I47: =IF(IF(D47="", "", VLOOKUP(D47,'API Data Dictionary'!C:G,5,FALSE))=0, "", IF(D47="", "", VLOOKUP(D47,'API Data Dictionary'!C:G,5,FALSE))) -> The country/location code of the mobile phone number
C48: "mobileNumber": "string", | D48: =IF(OR(ISNUMBER(SEARCH("{", C48)),ISNUMBER(SEARCH("[", C48))), "", IFERROR(MID(C48, SEARCH("""", C48) +1, SEARCH("""", C48, SEARCH("""",C48) +1) - SEARCH("""", C48) -1), "")) -> mobileNumber | E48: x | F48: =IF(D48="", "", VLOOKUP(D48,'API Data Dictionary'!C:D,2,FALSE)) -> string | G48: =IF(IF(D48="", "", VLOOKUP(D48,'API Data Dictionary'!C:E,3,FALSE))=0, "", IF(D48="", "", VLOOKUP(D48,'API Data Dictionary'!C:E,3,FALSE))) -> 15 | H48: =IF(IF(D48="", "", VLOOKUP(D48,'API Data Dictionary'!C:F,4,FALSE))=0, "", IF(D48="", "", VLOOKUP(D48,'API Data Dictionary'!C:F,4,FALSE))) -> pattern: ^(\d{11})$ | I48: =IF(IF(D48="", "", VLOOKUP(D48,'API Data Dictionary'!C:G,5,FALSE))=0, "", IF(D48="", "", VLOOKUP(D48,'API Data Dictionary'!C:G,5,FALSE))) -> The mobile phone number
C49: "nationality": 1, | D49: =IF(OR(ISNUMBER(SEARCH("{", C49)),ISNUMBER(SEARCH("[", C49))), "", IFERROR(MID(C49, SEARCH("""", C49) +1, SEARCH("""", C49, SEARCH("""",C49) +1) - SEARCH("""", C49) -1), "")) -> nationality | E49: x | F49: =IF(D49="", "", VLOOKUP(D49,'API Data Dictionary'!C:D,2,FALSE)) -> enum - Nationality | G49: =IF(IF(D49="", "", VLOOKUP(D49,'API Data Dictionary'!C:E,3,FALSE))=0, "", IF(D49="", "", VLOOKUP(D49,'API Data Dictionary'!C:E,3,FALSE))) | H49: =IF(IF(D49="", "", VLOOKUP(D49,'API Data Dictionary'!C:F,4,FALSE))=0, "", IF(D49="", "", VLOOKUP(D49,'API Data Dictionary'!C:F,4,FALSE))) -> Valid Values 1-231 (See enum definition) | I49: =IF(IF(D49="", "", VLOOKUP(D49,'API Data Dictionary'!C:G,5,FALSE))=0, "", IF(D49="", "", VLOOKUP(D49,'API Data Dictionary'!C:G,5,FALSE))) -> The nationality, from the nationality enum list
C50: "niNumber": "string", | D50: =IF(OR(ISNUMBER(SEARCH("{", C50)),ISNUMBER(SEARCH("[", C50))), "", IFERROR(MID(C50, SEARCH("""", C50) +1, SEARCH("""", C50, SEARCH("""",C50) +1) - SEARCH("""", C50) -1), "")) -> niNumber | E50: x | F50: =IF(D50="", "", VLOOKUP(D50,'API Data Dictionary'!C:D,2,FALSE)) -> string | G50: =IF(IF(D50="", "", VLOOKUP(D50,'API Data Dictionary'!C:E,3,FALSE))=0, "", IF(D50="", "", VLOOKUP(D50,'API Data Dictionary'!C:E,3,FALSE))) -> 100 | H50: =IF(IF(D50="", "", VLOOKUP(D50,'API Data Dictionary'!C:F,4,FALSE))=0, "", IF(D50="", "", VLOOKUP(D50,'API Data Dictionary'!C:F,4,FALSE))) -> pattern: ^[a-zA-Z]{2}(?:\d){6}[a-zA-Z]{1}$ | I50: =IF(IF(D50="", "", VLOOKUP(D50,'API Data Dictionary'!C:G,5,FALSE))=0, "", IF(D50="", "", VLOOKUP(D50,'API Data Dictionary'!C:G,5,FALSE))) -> NI Number, matched to RegEx pattern
C51: "residentStatus": 1, | D51: =IF(OR(ISNUMBER(SEARCH("{", C51)),ISNUMBER(SEARCH("[", C51))), "", IFERROR(MID(C51, SEARCH("""", C51) +1, SEARCH("""", C51, SEARCH("""",C51) +1) - SEARCH("""", C51) -1), "")) -> residentStatus | E51: x | F51: =IF(D51="", "", VLOOKUP(D51,'API Data Dictionary'!C:D,2,FALSE)) -> enum - resident Status | G51: =IF(IF(D51="", "", VLOOKUP(D51,'API Data Dictionary'!C:E,3,FALSE))=0, "", IF(D51="", "", VLOOKUP(D51,'API Data Dictionary'!C:E,3,FALSE))) | H51: =IF(IF(D51="", "", VLOOKUP(D51,'API Data Dictionary'!C:F,4,FALSE))=0, "", IF(D51="", "", VLOOKUP(D51,'API Data Dictionary'!C:F,4,FALSE))) -> Valid Values 1-2 (See enum definition) | I51: =IF(IF(D51="", "", VLOOKUP(D51,'API Data Dictionary'!C:G,5,FALSE))=0, "", IF(D51="", "", VLOOKUP(D51,'API Data Dictionary'!C:G,5,FALSE))) -> Denotes the resident status e.g. UK resident
C52: "additionalInformation": "string", | D52: =IF(OR(ISNUMBER(SEARCH("{", C52)),ISNUMBER(SEARCH("[", C52))), "", IFERROR(MID(C52, SEARCH("""", C52) +1, SEARCH("""", C52, SEARCH("""",C52) +1) - SEARCH("""", C52) -1), "")) -> additionalInformation | E52: x | F52: =IF(D52="", "", VLOOKUP(D52,'API Data Dictionary'!C:D,2,FALSE)) -> string | G52: =IF(IF(D52="", "", VLOOKUP(D52,'API Data Dictionary'!C:E,3,FALSE))=0, "", IF(D52="", "", VLOOKUP(D52,'API Data Dictionary'!C:E,3,FALSE))) -> 65535 | H52: =IF(IF(D52="", "", VLOOKUP(D52,'API Data Dictionary'!C:F,4,FALSE))=0, "", IF(D52="", "", VLOOKUP(D52,'API Data Dictionary'!C:F,4,FALSE))) | I52: =IF(IF(D52="", "", VLOOKUP(D52,'API Data Dictionary'!C:G,5,FALSE))=0, "", IF(D52="", "", VLOOKUP(D52,'API Data Dictionary'!C:G,5,FALSE))) -> Free text field for additional information
C53: "isAdvanceRent": true, | D53: =IF(OR(ISNUMBER(SEARCH("{", C53)),ISNUMBER(SEARCH("[", C53))), "", IFERROR(MID(C53, SEARCH("""", C53) +1, SEARCH("""", C53, SEARCH("""",C53) +1) - SEARCH("""", C53) -1), "")) -> isAdvanceRent | E53: x | F53: =IF(D53="", "", VLOOKUP(D53,'API Data Dictionary'!C:D,2,FALSE)) -> boolean | G53: =IF(IF(D53="", "", VLOOKUP(D53,'API Data Dictionary'!C:E,3,FALSE))=0, "", IF(D53="", "", VLOOKUP(D53,'API Data Dictionary'!C:E,3,FALSE))) | H53: =IF(IF(D53="", "", VLOOKUP(D53,'API Data Dictionary'!C:F,4,FALSE))=0, "", IF(D53="", "", VLOOKUP(D53,'API Data Dictionary'!C:F,4,FALSE))) | I53: =IF(IF(D53="", "", VLOOKUP(D53,'API Data Dictionary'!C:G,5,FALSE))=0, "", IF(D53="", "", VLOOKUP(D53,'API Data Dictionary'!C:G,5,FALSE))) -> Denotes whether rent is paid in advance
C54: "otherNames": [ | D54: =IF(OR(ISNUMBER(SEARCH("{", C54)),ISNUMBER(SEARCH("[", C54))), "", IFERROR(MID(C54, SEARCH("""", C54) +1, SEARCH("""", C54, SEARCH("""",C54) +1) - SEARCH("""", C54) -1), "")) | E54: =IF(D54="", "", VLOOKUP(D54,'API Data Dictionary'!C:L,10,FALSE)) | F54: =IF(D54="", "", VLOOKUP(D54,'API Data Dictionary'!C:D,2,FALSE)) | G54: =IF(IF(D54="", "", VLOOKUP(D54,'API Data Dictionary'!C:E,3,FALSE))=0, "", IF(D54="", "", VLOOKUP(D54,'API Data Dictionary'!C:E,3,FALSE))) | H54: =IF(IF(D54="", "", VLOOKUP(D54,'API Data Dictionary'!C:F,4,FALSE))=0, "", IF(D54="", "", VLOOKUP(D54,'API Data Dictionary'!C:F,4,FALSE))) | I54: =IF(IF(D54="", "", VLOOKUP(D54,'API Data Dictionary'!C:G,5,FALSE))=0, "", IF(D54="", "", VLOOKUP(D54,'API Data Dictionary'!C:G,5,FALSE)))
C55: { | D55: =IF(OR(ISNUMBER(SEARCH("{", C55)),ISNUMBER(SEARCH("[", C55))), "", IFERROR(MID(C55, SEARCH("""", C55) +1, SEARCH("""", C55, SEARCH("""",C55) +1) - SEARCH("""", C55) -1), "")) | E55: =IF(D55="", "", VLOOKUP(D55,'API Data Dictionary'!C:L,10,FALSE)) | F55: =IF(D55="", "", VLOOKUP(D55,'API Data Dictionary'!C:D,2,FALSE)) | G55: =IF(IF(D55="", "", VLOOKUP(D55,'API Data Dictionary'!C:E,3,FALSE))=0, "", IF(D55="", "", VLOOKUP(D55,'API Data Dictionary'!C:E,3,FALSE))) | H55: =IF(IF(D55="", "", VLOOKUP(D55,'API Data Dictionary'!C:F,4,FALSE))=0, "", IF(D55="", "", VLOOKUP(D55,'API Data Dictionary'!C:F,4,FALSE))) | I55: =IF(IF(D55="", "", VLOOKUP(D55,'API Data Dictionary'!C:G,5,FALSE))=0, "", IF(D55="", "", VLOOKUP(D55,'API Data Dictionary'!C:G,5,FALSE)))
C56: "firstName": "string", | D56: =IF(OR(ISNUMBER(SEARCH("{", C56)),ISNUMBER(SEARCH("[", C56))), "", IFERROR(MID(C56, SEARCH("""", C56) +1, SEARCH("""", C56, SEARCH("""",C56) +1) - SEARCH("""", C56) -1), "")) -> firstName | E56: =IF(D56="", "", VLOOKUP(D56,'API Data Dictionary'!C:L,10,FALSE)) -> M | F56: =IF(D56="", "", VLOOKUP(D56,'API Data Dictionary'!C:D,2,FALSE)) -> string | G56: =IF(IF(D56="", "", VLOOKUP(D56,'API Data Dictionary'!C:E,3,FALSE))=0, "", IF(D56="", "", VLOOKUP(D56,'API Data Dictionary'!C:E,3,FALSE))) -> 100 | H56: =IF(IF(D56="", "", VLOOKUP(D56,'API Data Dictionary'!C:F,4,FALSE))=0, "", IF(D56="", "", VLOOKUP(D56,'API Data Dictionary'!C:F,4,FALSE))) -> pattern: ^[a-zA-Z0-9\-' ]*$ | I56: =IF(IF(D56="", "", VLOOKUP(D56,'API Data Dictionary'!C:G,5,FALSE))=0, "", IF(D56="", "", VLOOKUP(D56,'API Data Dictionary'!C:G,5,FALSE))) -> First name, validated against the RegEx pattern
C57: "middleName": "string", | D57: =IF(OR(ISNUMBER(SEARCH("{", C57)),ISNUMBER(SEARCH("[", C57))), "", IFERROR(MID(C57, SEARCH("""", C57) +1, SEARCH("""", C57, SEARCH("""",C57) +1) - SEARCH("""", C57) -1), "")) -> middleName | E57: =IF(D57="", "", VLOOKUP(D57,'API Data Dictionary'!C:L,10,FALSE)) -> X | F57: =IF(D57="", "", VLOOKUP(D57,'API Data Dictionary'!C:D,2,FALSE)) -> string | G57: =IF(IF(D57="", "", VLOOKUP(D57,'API Data Dictionary'!C:E,3,FALSE))=0, "", IF(D57="", "", VLOOKUP(D57,'API Data Dictionary'!C:E,3,FALSE))) -> 50 | H57: =IF(IF(D57="", "", VLOOKUP(D57,'API Data Dictionary'!C:F,4,FALSE))=0, "", IF(D57="", "", VLOOKUP(D57,'API Data Dictionary'!C:F,4,FALSE))) -> pattern: ^[a-zA-Z0-9\-' ]*$ | I57: =IF(IF(D57="", "", VLOOKUP(D57,'API Data Dictionary'!C:G,5,FALSE))=0, "", IF(D57="", "", VLOOKUP(D57,'API Data Dictionary'!C:G,5,FALSE))) -> Middle name, validated against the RegEx pattern
C58: "lastName": "string", | D58: =IF(OR(ISNUMBER(SEARCH("{", C58)),ISNUMBER(SEARCH("[", C58))), "", IFERROR(MID(C58, SEARCH("""", C58) +1, SEARCH("""", C58, SEARCH("""",C58) +1) - SEARCH("""", C58) -1), "")) -> lastName | E58: x | F58: =IF(D58="", "", VLOOKUP(D58,'API Data Dictionary'!C:D,2,FALSE)) -> string | G58: =IF(IF(D58="", "", VLOOKUP(D58,'API Data Dictionary'!C:E,3,FALSE))=0, "", IF(D58="", "", VLOOKUP(D58,'API Data Dictionary'!C:E,3,FALSE))) -> 100 | H58: =IF(IF(D58="", "", VLOOKUP(D58,'API Data Dictionary'!C:F,4,FALSE))=0, "", IF(D58="", "", VLOOKUP(D58,'API Data Dictionary'!C:F,4,FALSE))) -> pattern: ^[a-zA-Z0-9\-' ]*$ | I58: =IF(IF(D58="", "", VLOOKUP(D58,'API Data Dictionary'!C:G,5,FALSE))=0, "", IF(D58="", "", VLOOKUP(D58,'API Data Dictionary'!C:G,5,FALSE))) -> Surname name, validated against the RegEx pattern
C59: "nameChangeDate": "2023-01-03T14:03:12.243Z" | D59: =IF(OR(ISNUMBER(SEARCH("{", C59)),ISNUMBER(SEARCH("[", C59))), "", IFERROR(MID(C59, SEARCH("""", C59) +1, SEARCH("""", C59, SEARCH("""",C59) +1) - SEARCH("""", C59) -1), "")) -> nameChangeDate | E59: x | F59: =IF(D59="", "", VLOOKUP(D59,'API Data Dictionary'!C:D,2,FALSE)) -> string ($date-time) | G59: =IF(IF(D59="", "", VLOOKUP(D59,'API Data Dictionary'!C:E,3,FALSE))=0, "", IF(D59="", "", VLOOKUP(D59,'API Data Dictionary'!C:E,3,FALSE))) | H59: =IF(IF(D59="", "", VLOOKUP(D59,'API Data Dictionary'!C:F,4,FALSE))=0, "", IF(D59="", "", VLOOKUP(D59,'API Data Dictionary'!C:F,4,FALSE))) -> DD/MM/YYYY | I59: =IF(IF(D59="", "", VLOOKUP(D59,'API Data Dictionary'!C:G,5,FALSE))=0, "", IF(D59="", "", VLOOKUP(D59,'API Data Dictionary'!C:G,5,FALSE))) -> Date the name was changed, formatted DD/MM/YYYY
C60: } | D60: =IF(OR(ISNUMBER(SEARCH("{", C60)),ISNUMBER(SEARCH("[", C60))), "", IFERROR(MID(C60, SEARCH("""", C60) +1, SEARCH("""", C60, SEARCH("""",C60) +1) - SEARCH("""", C60) -1), "")) | E60: =IF(D60="", "", VLOOKUP(D60,'API Data Dictionary'!C:L,10,FALSE)) | F60: =IF(D60="", "", VLOOKUP(D60,'API Data Dictionary'!C:D,2,FALSE)) | G60: =IF(IF(D60="", "", VLOOKUP(D60,'API Data Dictionary'!C:E,3,FALSE))=0, "", IF(D60="", "", VLOOKUP(D60,'API Data Dictionary'!C:E,3,FALSE))) | H60: =IF(IF(D60="", "", VLOOKUP(D60,'API Data Dictionary'!C:F,4,FALSE))=0, "", IF(D60="", "", VLOOKUP(D60,'API Data Dictionary'!C:F,4,FALSE))) | I60: =IF(IF(D60="", "", VLOOKUP(D60,'API Data Dictionary'!C:G,5,FALSE))=0, "", IF(D60="", "", VLOOKUP(D60,'API Data Dictionary'!C:G,5,FALSE)))
C61: ], | D61: =IF(OR(ISNUMBER(SEARCH("{", C61)),ISNUMBER(SEARCH("[", C61))), "", IFERROR(MID(C61, SEARCH("""", C61) +1, SEARCH("""", C61, SEARCH("""",C61) +1) - SEARCH("""", C61) -1), "")) | E61: =IF(D61="", "", VLOOKUP(D61,'API Data Dictionary'!C:L,10,FALSE)) | F61: =IF(D61="", "", VLOOKUP(D61,'API Data Dictionary'!C:D,2,FALSE)) | G61: =IF(IF(D61="", "", VLOOKUP(D61,'API Data Dictionary'!C:E,3,FALSE))=0, "", IF(D61="", "", VLOOKUP(D61,'API Data Dictionary'!C:E,3,FALSE))) | H61: =IF(IF(D61="", "", VLOOKUP(D61,'API Data Dictionary'!C:F,4,FALSE))=0, "", IF(D61="", "", VLOOKUP(D61,'API Data Dictionary'!C:F,4,FALSE))) | I61: =IF(IF(D61="", "", VLOOKUP(D61,'API Data Dictionary'!C:G,5,FALSE))=0, "", IF(D61="", "", VLOOKUP(D61,'API Data Dictionary'!C:G,5,FALSE)))
C62: "addressOtherDetailsViewModel": [ | D62: =IF(OR(ISNUMBER(SEARCH("{", C62)),ISNUMBER(SEARCH("[", C62))), "", IFERROR(MID(C62, SEARCH("""", C62) +1, SEARCH("""", C62, SEARCH("""",C62) +1) - SEARCH("""", C62) -1), "")) | E62: =IF(D62="", "", VLOOKUP(D62,'API Data Dictionary'!C:L,10,FALSE)) | F62: =IF(D62="", "", VLOOKUP(D62,'API Data Dictionary'!C:D,2,FALSE)) | G62: =IF(IF(D62="", "", VLOOKUP(D62,'API Data Dictionary'!C:E,3,FALSE))=0, "", IF(D62="", "", VLOOKUP(D62,'API Data Dictionary'!C:E,3,FALSE))) | H62: =IF(IF(D62="", "", VLOOKUP(D62,'API Data Dictionary'!C:F,4,FALSE))=0, "", IF(D62="", "", VLOOKUP(D62,'API Data Dictionary'!C:F,4,FALSE))) | I62: =IF(IF(D62="", "", VLOOKUP(D62,'API Data Dictionary'!C:G,5,FALSE))=0, "", IF(D62="", "", VLOOKUP(D62,'API Data Dictionary'!C:G,5,FALSE)))
C63: { | D63: =IF(OR(ISNUMBER(SEARCH("{", C63)),ISNUMBER(SEARCH("[", C63))), "", IFERROR(MID(C63, SEARCH("""", C63) +1, SEARCH("""", C63, SEARCH("""",C63) +1) - SEARCH("""", C63) -1), "")) | E63: =IF(D63="", "", VLOOKUP(D63,'API Data Dictionary'!C:L,10,FALSE)) | F63: =IF(D63="", "", VLOOKUP(D63,'API Data Dictionary'!C:D,2,FALSE)) | G63: =IF(IF(D63="", "", VLOOKUP(D63,'API Data Dictionary'!C:E,3,FALSE))=0, "", IF(D63="", "", VLOOKUP(D63,'API Data Dictionary'!C:E,3,FALSE))) | H63: =IF(IF(D63="", "", VLOOKUP(D63,'API Data Dictionary'!C:F,4,FALSE))=0, "", IF(D63="", "", VLOOKUP(D63,'API Data Dictionary'!C:F,4,FALSE))) | I63: =IF(IF(D63="", "", VLOOKUP(D63,'API Data Dictionary'!C:G,5,FALSE))=0, "", IF(D63="", "", VLOOKUP(D63,'API Data Dictionary'!C:G,5,FALSE)))
C64: "addresses": [ | D64: =IF(OR(ISNUMBER(SEARCH("{", C64)),ISNUMBER(SEARCH("[", C64))), "", IFERROR(MID(C64, SEARCH("""", C64) +1, SEARCH("""", C64, SEARCH("""",C64) +1) - SEARCH("""", C64) -1), "")) | E64: =IF(D64="", "", VLOOKUP(D64,'API Data Dictionary'!C:L,10,FALSE)) | F64: =IF(D64="", "", VLOOKUP(D64,'API Data Dictionary'!C:D,2,FALSE)) | G64: =IF(IF(D64="", "", VLOOKUP(D64,'API Data Dictionary'!C:E,3,FALSE))=0, "", IF(D64="", "", VLOOKUP(D64,'API Data Dictionary'!C:E,3,FALSE))) | H64: =IF(IF(D64="", "", VLOOKUP(D64,'API Data Dictionary'!C:F,4,FALSE))=0, "", IF(D64="", "", VLOOKUP(D64,'API Data Dictionary'!C:F,4,FALSE))) | I64: =IF(IF(D64="", "", VLOOKUP(D64,'API Data Dictionary'!C:G,5,FALSE))=0, "", IF(D64="", "", VLOOKUP(D64,'API Data Dictionary'!C:G,5,FALSE)))
C65: { | D65: =IF(OR(ISNUMBER(SEARCH("{", C65)),ISNUMBER(SEARCH("[", C65))), "", IFERROR(MID(C65, SEARCH("""", C65) +1, SEARCH("""", C65, SEARCH("""",C65) +1) - SEARCH("""", C65) -1), "")) | E65: =IF(D65="", "", VLOOKUP(D65,'API Data Dictionary'!C:L,10,FALSE)) | F65: =IF(D65="", "", VLOOKUP(D65,'API Data Dictionary'!C:D,2,FALSE)) | G65: =IF(IF(D65="", "", VLOOKUP(D65,'API Data Dictionary'!C:E,3,FALSE))=0, "", IF(D65="", "", VLOOKUP(D65,'API Data Dictionary'!C:E,3,FALSE))) | H65: =IF(IF(D65="", "", VLOOKUP(D65,'API Data Dictionary'!C:F,4,FALSE))=0, "", IF(D65="", "", VLOOKUP(D65,'API Data Dictionary'!C:F,4,FALSE))) | I65: =IF(IF(D65="", "", VLOOKUP(D65,'API Data Dictionary'!C:G,5,FALSE))=0, "", IF(D65="", "", VLOOKUP(D65,'API Data Dictionary'!C:G,5,FALSE)))
C66: "houseNumber": "string", | D66: =IF(OR(ISNUMBER(SEARCH("{", C66)),ISNUMBER(SEARCH("[", C66))), "", IFERROR(MID(C66, SEARCH("""", C66) +1, SEARCH("""", C66, SEARCH("""",C66) +1) - SEARCH("""", C66) -1), "")) -> houseNumber | E66: =IF(D66="", "", VLOOKUP(D66,'API Data Dictionary'!C:L,10,FALSE)) -> X | F66: =IF(D66="", "", VLOOKUP(D66,'API Data Dictionary'!C:D,2,FALSE)) -> string | G66: =IF(IF(D66="", "", VLOOKUP(D66,'API Data Dictionary'!C:E,3,FALSE))=0, "", IF(D66="", "", VLOOKUP(D66,'API Data Dictionary'!C:E,3,FALSE))) -> 100 | H66: =IF(IF(D66="", "", VLOOKUP(D66,'API Data Dictionary'!C:F,4,FALSE))=0, "", IF(D66="", "", VLOOKUP(D66,'API Data Dictionary'!C:F,4,FALSE))) | I66: =IF(IF(D66="", "", VLOOKUP(D66,'API Data Dictionary'!C:G,5,FALSE))=0, "", IF(D66="", "", VLOOKUP(D66,'API Data Dictionary'!C:G,5,FALSE))) -> The number of the property
C67: "houseName": "string", | D67: =IF(OR(ISNUMBER(SEARCH("{", C67)),ISNUMBER(SEARCH("[", C67))), "", IFERROR(MID(C67, SEARCH("""", C67) +1, SEARCH("""", C67, SEARCH("""",C67) +1) - SEARCH("""", C67) -1), "")) -> houseName | E67: =IF(D67="", "", VLOOKUP(D67,'API Data Dictionary'!C:L,10,FALSE)) -> X | F67: =IF(D67="", "", VLOOKUP(D67,'API Data Dictionary'!C:D,2,FALSE)) -> string | G67: =IF(IF(D67="", "", VLOOKUP(D67,'API Data Dictionary'!C:E,3,FALSE))=0, "", IF(D67="", "", VLOOKUP(D67,'API Data Dictionary'!C:E,3,FALSE))) -> 100 | H67: =IF(IF(D67="", "", VLOOKUP(D67,'API Data Dictionary'!C:F,4,FALSE))=0, "", IF(D67="", "", VLOOKUP(D67,'API Data Dictionary'!C:F,4,FALSE))) | I67: =IF(IF(D67="", "", VLOOKUP(D67,'API Data Dictionary'!C:G,5,FALSE))=0, "", IF(D67="", "", VLOOKUP(D67,'API Data Dictionary'!C:G,5,FALSE))) -> The name of the property
C68: "addressLine1": "string", | D68: =IF(OR(ISNUMBER(SEARCH("{", C68)),ISNUMBER(SEARCH("[", C68))), "", IFERROR(MID(C68, SEARCH("""", C68) +1, SEARCH("""", C68, SEARCH("""",C68) +1) - SEARCH("""", C68) -1), "")) -> addressLine1 | E68: =IF(D68="", "", VLOOKUP(D68,'API Data Dictionary'!C:L,10,FALSE)) -> M | F68: =IF(D68="", "", VLOOKUP(D68,'API Data Dictionary'!C:D,2,FALSE)) -> string | G68: =IF(IF(D68="", "", VLOOKUP(D68,'API Data Dictionary'!C:E,3,FALSE))=0, "", IF(D68="", "", VLOOKUP(D68,'API Data Dictionary'!C:E,3,FALSE))) -> 100 | H68: =IF(IF(D68="", "", VLOOKUP(D68,'API Data Dictionary'!C:F,4,FALSE))=0, "", IF(D68="", "", VLOOKUP(D68,'API Data Dictionary'!C:F,4,FALSE))) | I68: =IF(IF(D68="", "", VLOOKUP(D68,'API Data Dictionary'!C:G,5,FALSE))=0, "", IF(D68="", "", VLOOKUP(D68,'API Data Dictionary'!C:G,5,FALSE))) -> The first line of the property address
C69: "addressLine2": "string", | D69: =IF(OR(ISNUMBER(SEARCH("{", C69)),ISNUMBER(SEARCH("[", C69))), "", IFERROR(MID(C69, SEARCH("""", C69) +1, SEARCH("""", C69, SEARCH("""",C69) +1) - SEARCH("""", C69) -1), "")) -> addressLine2 | E69: =IF(D69="", "", VLOOKUP(D69,'API Data Dictionary'!C:L,10,FALSE)) -> x | F69: =IF(D69="", "", VLOOKUP(D69,'API Data Dictionary'!C:D,2,FALSE)) -> string | G69: =IF(IF(D69="", "", VLOOKUP(D69,'API Data Dictionary'!C:E,3,FALSE))=0, "", IF(D69="", "", VLOOKUP(D69,'API Data Dictionary'!C:E,3,FALSE))) -> 100 | H69: =IF(IF(D69="", "", VLOOKUP(D69,'API Data Dictionary'!C:F,4,FALSE))=0, "", IF(D69="", "", VLOOKUP(D69,'API Data Dictionary'!C:F,4,FALSE))) | I69: =IF(IF(D69="", "", VLOOKUP(D69,'API Data Dictionary'!C:G,5,FALSE))=0, "", IF(D69="", "", VLOOKUP(D69,'API Data Dictionary'!C:G,5,FALSE))) -> The second line of the property address
C70: "town": "string", | D70: =IF(OR(ISNUMBER(SEARCH("{", C70)),ISNUMBER(SEARCH("[", C70))), "", IFERROR(MID(C70, SEARCH("""", C70) +1, SEARCH("""", C70, SEARCH("""",C70) +1) - SEARCH("""", C70) -1), "")) -> town | E70: =IF(D70="", "", VLOOKUP(D70,'API Data Dictionary'!C:L,10,FALSE)) -> M | F70: =IF(D70="", "", VLOOKUP(D70,'API Data Dictionary'!C:D,2,FALSE)) -> string | G70: =IF(IF(D70="", "", VLOOKUP(D70,'API Data Dictionary'!C:E,3,FALSE))=0, "", IF(D70="", "", VLOOKUP(D70,'API Data Dictionary'!C:E,3,FALSE))) -> 50 | H70: =IF(IF(D70="", "", VLOOKUP(D70,'API Data Dictionary'!C:F,4,FALSE))=0, "", IF(D70="", "", VLOOKUP(D70,'API Data Dictionary'!C:F,4,FALSE))) | I70: =IF(IF(D70="", "", VLOOKUP(D70,'API Data Dictionary'!C:G,5,FALSE))=0, "", IF(D70="", "", VLOOKUP(D70,'API Data Dictionary'!C:G,5,FALSE))) -> The town in which the property exists
C71: "postcode": "string", | D71: =IF(OR(ISNUMBER(SEARCH("{", C71)),ISNUMBER(SEARCH("[", C71))), "", IFERROR(MID(C71, SEARCH("""", C71) +1, SEARCH("""", C71, SEARCH("""",C71) +1) - SEARCH("""", C71) -1), "")) -> postcode | E71: =IF(D71="", "", VLOOKUP(D71,'API Data Dictionary'!C:L,10,FALSE)) -> M | F71: =IF(D71="", "", VLOOKUP(D71,'API Data Dictionary'!C:D,2,FALSE)) -> string | G71: =IF(IF(D71="", "", VLOOKUP(D71,'API Data Dictionary'!C:E,3,FALSE))=0, "", IF(D71="", "", VLOOKUP(D71,'API Data Dictionary'!C:E,3,FALSE))) -> 50 | H71: =IF(IF(D71="", "", VLOOKUP(D71,'API Data Dictionary'!C:F,4,FALSE))=0, "", IF(D71="", "", VLOOKUP(D71,'API Data Dictionary'!C:F,4,FALSE))) | I71: =IF(IF(D71="", "", VLOOKUP(D71,'API Data Dictionary'!C:G,5,FALSE))=0, "", IF(D71="", "", VLOOKUP(D71,'API Data Dictionary'!C:G,5,FALSE))) -> the postcode of the property
C72: "country": 1, | D72: =IF(OR(ISNUMBER(SEARCH("{", C72)),ISNUMBER(SEARCH("[", C72))), "", IFERROR(MID(C72, SEARCH("""", C72) +1, SEARCH("""", C72, SEARCH("""",C72) +1) - SEARCH("""", C72) -1), "")) -> country | E72: x | F72: =IF(D72="", "", VLOOKUP(D72,'API Data Dictionary'!C:D,2,FALSE)) -> enum -Country/Location Code | G72: =IF(IF(D72="", "", VLOOKUP(D72,'API Data Dictionary'!C:E,3,FALSE))=0, "", IF(D72="", "", VLOOKUP(D72,'API Data Dictionary'!C:E,3,FALSE))) | H72: =IF(IF(D72="", "", VLOOKUP(D72,'API Data Dictionary'!C:F,4,FALSE))=0, "", IF(D72="", "", VLOOKUP(D72,'API Data Dictionary'!C:F,4,FALSE))) -> Valid Values 1-239 (See enum definition) | I72: =IF(IF(D72="", "", VLOOKUP(D72,'API Data Dictionary'!C:G,5,FALSE))=0, "", IF(D72="", "", VLOOKUP(D72,'API Data Dictionary'!C:G,5,FALSE))) -> The Country code from the enum list, e.g. France
C73: "isUKAddress": true, | D73: =IF(OR(ISNUMBER(SEARCH("{", C73)),ISNUMBER(SEARCH("[", C73))), "", IFERROR(MID(C73, SEARCH("""", C73) +1, SEARCH("""", C73, SEARCH("""",C73) +1) - SEARCH("""", C73) -1), "")) -> isUKAddress | E73: x | F73: =IF(D73="", "", VLOOKUP(D73,'API Data Dictionary'!C:D,2,FALSE)) -> boolean | G73: =IF(IF(D73="", "", VLOOKUP(D73,'API Data Dictionary'!C:E,3,FALSE))=0, "", IF(D73="", "", VLOOKUP(D73,'API Data Dictionary'!C:E,3,FALSE))) | H73: =IF(IF(D73="", "", VLOOKUP(D73,'API Data Dictionary'!C:F,4,FALSE))=0, "", IF(D73="", "", VLOOKUP(D73,'API Data Dictionary'!C:F,4,FALSE))) | I73: =IF(IF(D73="", "", VLOOKUP(D73,'API Data Dictionary'!C:G,5,FALSE))=0, "", IF(D73="", "", VLOOKUP(D73,'API Data Dictionary'!C:G,5,FALSE))) -> Denotes if the address is in the UK
C74: "addressTypeId": 1, | D74: =IF(OR(ISNUMBER(SEARCH("{", C74)),ISNUMBER(SEARCH("[", C74))), "", IFERROR(MID(C74, SEARCH("""", C74) +1, SEARCH("""", C74, SEARCH("""",C74) +1) - SEARCH("""", C74) -1), "")) -> addressTypeId | E74: x | F74: =IF(D74="", "", VLOOKUP(D74,'API Data Dictionary'!C:D,2,FALSE)) -> enum - address Type | G74: =IF(IF(D74="", "", VLOOKUP(D74,'API Data Dictionary'!C:E,3,FALSE))=0, "", IF(D74="", "", VLOOKUP(D74,'API Data Dictionary'!C:E,3,FALSE))) | H74: =IF(IF(D74="", "", VLOOKUP(D74,'API Data Dictionary'!C:F,4,FALSE))=0, "", IF(D74="", "", VLOOKUP(D74,'API Data Dictionary'!C:F,4,FALSE))) -> Valid Values 1-2 (See enum definition) | I74: =IF(IF(D74="", "", VLOOKUP(D74,'API Data Dictionary'!C:G,5,FALSE))=0, "", IF(D74="", "", VLOOKUP(D74,'API Data Dictionary'!C:G,5,FALSE))) -> Whether the address is current or previous, chosen from enum list
C75: "monthMovedIn": 1, | D75: =IF(OR(ISNUMBER(SEARCH("{", C75)),ISNUMBER(SEARCH("[", C75))), "", IFERROR(MID(C75, SEARCH("""", C75) +1, SEARCH("""", C75, SEARCH("""",C75) +1) - SEARCH("""", C75) -1), "")) -> monthMovedIn | E75: x | F75: =IF(D75="", "", VLOOKUP(D75,'API Data Dictionary'!C:D,2,FALSE)) -> enum - month | G75: =IF(IF(D75="", "", VLOOKUP(D75,'API Data Dictionary'!C:E,3,FALSE))=0, "", IF(D75="", "", VLOOKUP(D75,'API Data Dictionary'!C:E,3,FALSE))) | H75: =IF(IF(D75="", "", VLOOKUP(D75,'API Data Dictionary'!C:F,4,FALSE))=0, "", IF(D75="", "", VLOOKUP(D75,'API Data Dictionary'!C:F,4,FALSE))) -> Valid Values 1-12 (Jan - Dec) | I75: =IF(IF(D75="", "", VLOOKUP(D75,'API Data Dictionary'!C:G,5,FALSE))=0, "", IF(D75="", "", VLOOKUP(D75,'API Data Dictionary'!C:G,5,FALSE))) -> Month the property was moved into, chosen from enum list
C76: "yearMovedIn": 0 | D76: =IF(OR(ISNUMBER(SEARCH("{", C76)),ISNUMBER(SEARCH("[", C76))), "", IFERROR(MID(C76, SEARCH("""", C76) +1, SEARCH("""", C76, SEARCH("""",C76) +1) - SEARCH("""", C76) -1), "")) -> yearMovedIn | E76: x | F76: =IF(D76="", "", VLOOKUP(D76,'API Data Dictionary'!C:D,2,FALSE)) -> integer | G76: =IF(IF(D76="", "", VLOOKUP(D76,'API Data Dictionary'!C:E,3,FALSE))=0, "", IF(D76="", "", VLOOKUP(D76,'API Data Dictionary'!C:E,3,FALSE))) -> 4 | H76: =IF(IF(D76="", "", VLOOKUP(D76,'API Data Dictionary'!C:F,4,FALSE))=0, "", IF(D76="", "", VLOOKUP(D76,'API Data Dictionary'!C:F,4,FALSE))) -> Valid Values 1900 - Current Year | I76: =IF(IF(D76="", "", VLOOKUP(D76,'API Data Dictionary'!C:G,5,FALSE))=0, "", IF(D76="", "", VLOOKUP(D76,'API Data Dictionary'!C:G,5,FALSE))) -> Year the property was moved into, formatted YYYY
C77: } | D77: =IF(OR(ISNUMBER(SEARCH("{", C77)),ISNUMBER(SEARCH("[", C77))), "", IFERROR(MID(C77, SEARCH("""", C77) +1, SEARCH("""", C77, SEARCH("""",C77) +1) - SEARCH("""", C77) -1), "")) | E77: =IF(D77="", "", VLOOKUP(D77,'API Data Dictionary'!C:L,10,FALSE)) | F77: =IF(D77="", "", VLOOKUP(D77,'API Data Dictionary'!C:D,2,FALSE)) | G77: =IF(IF(D77="", "", VLOOKUP(D77,'API Data Dictionary'!C:E,3,FALSE))=0, "", IF(D77="", "", VLOOKUP(D77,'API Data Dictionary'!C:E,3,FALSE))) | H77: =IF(IF(D77="", "", VLOOKUP(D77,'API Data Dictionary'!C:F,4,FALSE))=0, "", IF(D77="", "", VLOOKUP(D77,'API Data Dictionary'!C:F,4,FALSE))) | I77: =IF(IF(D77="", "", VLOOKUP(D77,'API Data Dictionary'!C:G,5,FALSE))=0, "", IF(D77="", "", VLOOKUP(D77,'API Data Dictionary'!C:G,5,FALSE)))
C78: ], | D78: =IF(OR(ISNUMBER(SEARCH("{", C78)),ISNUMBER(SEARCH("[", C78))), "", IFERROR(MID(C78, SEARCH("""", C78) +1, SEARCH("""", C78, SEARCH("""",C78) +1) - SEARCH("""", C78) -1), "")) | E78: =IF(D78="", "", VLOOKUP(D78,'API Data Dictionary'!C:L,10,FALSE)) | F78: =IF(D78="", "", VLOOKUP(D78,'API Data Dictionary'!C:D,2,FALSE)) | G78: =IF(IF(D78="", "", VLOOKUP(D78,'API Data Dictionary'!C:E,3,FALSE))=0, "", IF(D78="", "", VLOOKUP(D78,'API Data Dictionary'!C:E,3,FALSE))) | H78: =IF(IF(D78="", "", VLOOKUP(D78,'API Data Dictionary'!C:F,4,FALSE))=0, "", IF(D78="", "", VLOOKUP(D78,'API Data Dictionary'!C:F,4,FALSE))) | I78: =IF(IF(D78="", "", VLOOKUP(D78,'API Data Dictionary'!C:G,5,FALSE))=0, "", IF(D78="", "", VLOOKUP(D78,'API Data Dictionary'!C:G,5,FALSE)))
C79: "residentialDetails": { | D79: =IF(OR(ISNUMBER(SEARCH("{", C79)),ISNUMBER(SEARCH("[", C79))), "", IFERROR(MID(C79, SEARCH("""", C79) +1, SEARCH("""", C79, SEARCH("""",C79) +1) - SEARCH("""", C79) -1), "")) | E79: =IF(D79="", "", VLOOKUP(D79,'API Data Dictionary'!C:L,10,FALSE)) | F79: =IF(D79="", "", VLOOKUP(D79,'API Data Dictionary'!C:D,2,FALSE)) | G79: =IF(IF(D79="", "", VLOOKUP(D79,'API Data Dictionary'!C:E,3,FALSE))=0, "", IF(D79="", "", VLOOKUP(D79,'API Data Dictionary'!C:E,3,FALSE))) | H79: =IF(IF(D79="", "", VLOOKUP(D79,'API Data Dictionary'!C:F,4,FALSE))=0, "", IF(D79="", "", VLOOKUP(D79,'API Data Dictionary'!C:F,4,FALSE))) | I79: =IF(IF(D79="", "", VLOOKUP(D79,'API Data Dictionary'!C:G,5,FALSE))=0, "", IF(D79="", "", VLOOKUP(D79,'API Data Dictionary'!C:G,5,FALSE)))
C80: "currentResidentialStatus": 1, | D80: =IF(OR(ISNUMBER(SEARCH("{", C80)),ISNUMBER(SEARCH("[", C80))), "", IFERROR(MID(C80, SEARCH("""", C80) +1, SEARCH("""", C80, SEARCH("""",C80) +1) - SEARCH("""", C80) -1), "")) -> currentResidentialStatus | E80: x | F80: =IF(D80="", "", VLOOKUP(D80,'API Data Dictionary'!C:D,2,FALSE)) -> enum - residentStatus | G80: =IF(IF(D80="", "", VLOOKUP(D80,'API Data Dictionary'!C:E,3,FALSE))=0, "", IF(D80="", "", VLOOKUP(D80,'API Data Dictionary'!C:E,3,FALSE))) | H80: =IF(IF(D80="", "", VLOOKUP(D80,'API Data Dictionary'!C:F,4,FALSE))=0, "", IF(D80="", "", VLOOKUP(D80,'API Data Dictionary'!C:F,4,FALSE))) -> Valid Values 1-3 (See enum definition) | I80: =IF(IF(D80="", "", VLOOKUP(D80,'API Data Dictionary'!C:G,5,FALSE))=0, "", IF(D80="", "", VLOOKUP(D80,'API Data Dictionary'!C:G,5,FALSE))) -> The current residential status, e.g. UK Resident
C81: "currentRentAmount": 0, | D81: =IF(OR(ISNUMBER(SEARCH("{", C81)),ISNUMBER(SEARCH("[", C81))), "", IFERROR(MID(C81, SEARCH("""", C81) +1, SEARCH("""", C81, SEARCH("""",C81) +1) - SEARCH("""", C81) -1), "")) -> currentRentAmount | E81: x | F81: =IF(D81="", "", VLOOKUP(D81,'API Data Dictionary'!C:D,2,FALSE)) -> number (double) | G81: =IF(IF(D81="", "", VLOOKUP(D81,'API Data Dictionary'!C:E,3,FALSE))=0, "", IF(D81="", "", VLOOKUP(D81,'API Data Dictionary'!C:E,3,FALSE))) | H81: =IF(IF(D81="", "", VLOOKUP(D81,'API Data Dictionary'!C:F,4,FALSE))=0, "", IF(D81="", "", VLOOKUP(D81,'API Data Dictionary'!C:F,4,FALSE))) -> pattern: ^\d*.\d{0,2}$ | I81: =IF(IF(D81="", "", VLOOKUP(D81,'API Data Dictionary'!C:G,5,FALSE))=0, "", IF(D81="", "", VLOOKUP(D81,'API Data Dictionary'!C:G,5,FALSE))) -> The current rent amount in GBP
C82: "landlordName": "string", | D82: =IF(OR(ISNUMBER(SEARCH("{", C82)),ISNUMBER(SEARCH("[", C82))), "", IFERROR(MID(C82, SEARCH("""", C82) +1, SEARCH("""", C82, SEARCH("""",C82) +1) - SEARCH("""", C82) -1), "")) -> landlordName | E82: x | F82: =IF(D82="", "", VLOOKUP(D82,'API Data Dictionary'!C:D,2,FALSE)) -> string | G82: =IF(IF(D82="", "", VLOOKUP(D82,'API Data Dictionary'!C:E,3,FALSE))=0, "", IF(D82="", "", VLOOKUP(D82,'API Data Dictionary'!C:E,3,FALSE))) -> 500 | H82: =IF(IF(D82="", "", VLOOKUP(D82,'API Data Dictionary'!C:F,4,FALSE))=0, "", IF(D82="", "", VLOOKUP(D82,'API Data Dictionary'!C:F,4,FALSE))) | I82: =IF(IF(D82="", "", VLOOKUP(D82,'API Data Dictionary'!C:G,5,FALSE))=0, "", IF(D82="", "", VLOOKUP(D82,'API Data Dictionary'!C:G,5,FALSE))) -> Full name of the Landlord
C83: "landlordContactCountryId": 1, | D83: =IF(OR(ISNUMBER(SEARCH("{", C83)),ISNUMBER(SEARCH("[", C83))), "", IFERROR(MID(C83, SEARCH("""", C83) +1, SEARCH("""", C83, SEARCH("""",C83) +1) - SEARCH("""", C83) -1), "")) -> landlordContactCountryId | E83: x | F83: =IF(D83="", "", VLOOKUP(D83,'API Data Dictionary'!C:D,2,FALSE)) -> enum -Country/Location Code | G83: =IF(IF(D83="", "", VLOOKUP(D83,'API Data Dictionary'!C:E,3,FALSE))=0, "", IF(D83="", "", VLOOKUP(D83,'API Data Dictionary'!C:E,3,FALSE))) | H83: =IF(IF(D83="", "", VLOOKUP(D83,'API Data Dictionary'!C:F,4,FALSE))=0, "", IF(D83="", "", VLOOKUP(D83,'API Data Dictionary'!C:F,4,FALSE))) -> Valid Values 1-239 (See enum definition) | I83: =IF(IF(D83="", "", VLOOKUP(D83,'API Data Dictionary'!C:G,5,FALSE))=0, "", IF(D83="", "", VLOOKUP(D83,'API Data Dictionary'!C:G,5,FALSE))) -> The country/location code of the landlord contact phone number
C84: "landlordContactNumber": "string", | D84: =IF(OR(ISNUMBER(SEARCH("{", C84)),ISNUMBER(SEARCH("[", C84))), "", IFERROR(MID(C84, SEARCH("""", C84) +1, SEARCH("""", C84, SEARCH("""",C84) +1) - SEARCH("""", C84) -1), "")) -> landlordContactNumber | E84: x | F84: =IF(D84="", "", VLOOKUP(D84,'API Data Dictionary'!C:D,2,FALSE)) -> string | G84: =IF(IF(D84="", "", VLOOKUP(D84,'API Data Dictionary'!C:E,3,FALSE))=0, "", IF(D84="", "", VLOOKUP(D84,'API Data Dictionary'!C:E,3,FALSE))) -> 15 | H84: =IF(IF(D84="", "", VLOOKUP(D84,'API Data Dictionary'!C:F,4,FALSE))=0, "", IF(D84="", "", VLOOKUP(D84,'API Data Dictionary'!C:F,4,FALSE))) -> pattern: ^(\d{11})$ | I84: =IF(IF(D84="", "", VLOOKUP(D84,'API Data Dictionary'!C:G,5,FALSE))=0, "", IF(D84="", "", VLOOKUP(D84,'API Data Dictionary'!C:G,5,FALSE))) -> The Landlords contact Telephone number
C85: "landlordMobileCountryId": 1, | D85: =IF(OR(ISNUMBER(SEARCH("{", C85)),ISNUMBER(SEARCH("[", C85))), "", IFERROR(MID(C85, SEARCH("""", C85) +1, SEARCH("""", C85, SEARCH("""",C85) +1) - SEARCH("""", C85) -1), "")) -> landlordMobileCountryId | E85: x | F85: =IF(D85="", "", VLOOKUP(D85,'API Data Dictionary'!C:D,2,FALSE)) -> enum -Country/Location Code | G85: =IF(IF(D85="", "", VLOOKUP(D85,'API Data Dictionary'!C:E,3,FALSE))=0, "", IF(D85="", "", VLOOKUP(D85,'API Data Dictionary'!C:E,3,FALSE))) | H85: =IF(IF(D85="", "", VLOOKUP(D85,'API Data Dictionary'!C:F,4,FALSE))=0, "", IF(D85="", "", VLOOKUP(D85,'API Data Dictionary'!C:F,4,FALSE))) -> Valid Values 1-239 (See enum definition) | I85: =IF(IF(D85="", "", VLOOKUP(D85,'API Data Dictionary'!C:G,5,FALSE))=0, "", IF(D85="", "", VLOOKUP(D85,'API Data Dictionary'!C:G,5,FALSE))) -> The country/location code of the landlord mobile phone number
C86: "landlordMobileNumber": "string", | D86: =IF(OR(ISNUMBER(SEARCH("{", C86)),ISNUMBER(SEARCH("[", C86))), "", IFERROR(MID(C86, SEARCH("""", C86) +1, SEARCH("""", C86, SEARCH("""",C86) +1) - SEARCH("""", C86) -1), "")) -> landlordMobileNumber | E86: x | F86: =IF(D86="", "", VLOOKUP(D86,'API Data Dictionary'!C:D,2,FALSE)) -> string | G86: =IF(IF(D86="", "", VLOOKUP(D86,'API Data Dictionary'!C:E,3,FALSE))=0, "", IF(D86="", "", VLOOKUP(D86,'API Data Dictionary'!C:E,3,FALSE))) -> 15 | H86: =IF(IF(D86="", "", VLOOKUP(D86,'API Data Dictionary'!C:F,4,FALSE))=0, "", IF(D86="", "", VLOOKUP(D86,'API Data Dictionary'!C:F,4,FALSE))) -> pattern: ^(\d{11})$ | I86: =IF(IF(D86="", "", VLOOKUP(D86,'API Data Dictionary'!C:G,5,FALSE))=0, "", IF(D86="", "", VLOOKUP(D86,'API Data Dictionary'!C:G,5,FALSE))) -> the landlords mobile Telephone number
C87: "landlordEmail": "string", | D87: =IF(OR(ISNUMBER(SEARCH("{", C87)),ISNUMBER(SEARCH("[", C87))), "", IFERROR(MID(C87, SEARCH("""", C87) +1, SEARCH("""", C87, SEARCH("""",C87) +1) - SEARCH("""", C87) -1), "")) -> landlordEmail | E87: x | F87: =IF(D87="", "", VLOOKUP(D87,'API Data Dictionary'!C:D,2,FALSE)) -> string ($email) | G87: =IF(IF(D87="", "", VLOOKUP(D87,'API Data Dictionary'!C:E,3,FALSE))=0, "", IF(D87="", "", VLOOKUP(D87,'API Data Dictionary'!C:E,3,FALSE))) -> 200 | H87: =IF(IF(D87="", "", VLOOKUP(D87,'API Data Dictionary'!C:F,4,FALSE))=0, "", IF(D87="", "", VLOOKUP(D87,'API Data Dictionary'!C:F,4,FALSE))) -> pattern: ^(?!.*\.\.)(?!.*\\_\\_)(?!.*\-\-)[a-zA-Z0-9][-a-zA-Z0-9._]+[a-zA-Z0-9]@([-a-zA-Z0-9]+.)+[a-zA-Z]{2,5}$ | I87: =IF(IF(D87="", "", VLOOKUP(D87,'API Data Dictionary'!C:G,5,FALSE))=0, "", IF(D87="", "", VLOOKUP(D87,'API Data Dictionary'!C:G,5,FALSE))) -> The landlords email address
C88: "landlordAddress": { | D88: =IF(OR(ISNUMBER(SEARCH("{", C88)),ISNUMBER(SEARCH("[", C88))), "", IFERROR(MID(C88, SEARCH("""", C88) +1, SEARCH("""", C88, SEARCH("""",C88) +1) - SEARCH("""", C88) -1), "")) | E88: =IF(D88="", "", VLOOKUP(D88,'API Data Dictionary'!C:L,10,FALSE)) | F88: =IF(D88="", "", VLOOKUP(D88,'API Data Dictionary'!C:D,2,FALSE)) | G88: =IF(IF(D88="", "", VLOOKUP(D88,'API Data Dictionary'!C:E,3,FALSE))=0, "", IF(D88="", "", VLOOKUP(D88,'API Data Dictionary'!C:E,3,FALSE))) | H88: =IF(IF(D88="", "", VLOOKUP(D88,'API Data Dictionary'!C:F,4,FALSE))=0, "", IF(D88="", "", VLOOKUP(D88,'API Data Dictionary'!C:F,4,FALSE))) | I88: =IF(IF(D88="", "", VLOOKUP(D88,'API Data Dictionary'!C:G,5,FALSE))=0, "", IF(D88="", "", VLOOKUP(D88,'API Data Dictionary'!C:G,5,FALSE)))
C89: "houseNumber": "string", | D89: =IF(OR(ISNUMBER(SEARCH("{", C89)),ISNUMBER(SEARCH("[", C89))), "", IFERROR(MID(C89, SEARCH("""", C89) +1, SEARCH("""", C89, SEARCH("""",C89) +1) - SEARCH("""", C89) -1), "")) -> houseNumber | E89: =IF(D89="", "", VLOOKUP(D89,'API Data Dictionary'!C:L,10,FALSE)) -> X | F89: =IF(D89="", "", VLOOKUP(D89,'API Data Dictionary'!C:D,2,FALSE)) -> string | G89: =IF(IF(D89="", "", VLOOKUP(D89,'API Data Dictionary'!C:E,3,FALSE))=0, "", IF(D89="", "", VLOOKUP(D89,'API Data Dictionary'!C:E,3,FALSE))) -> 100 | H89: =IF(IF(D89="", "", VLOOKUP(D89,'API Data Dictionary'!C:F,4,FALSE))=0, "", IF(D89="", "", VLOOKUP(D89,'API Data Dictionary'!C:F,4,FALSE))) | I89: =IF(IF(D89="", "", VLOOKUP(D89,'API Data Dictionary'!C:G,5,FALSE))=0, "", IF(D89="", "", VLOOKUP(D89,'API Data Dictionary'!C:G,5,FALSE))) -> The number of the property
C90: "houseName": "string", | D90: =IF(OR(ISNUMBER(SEARCH("{", C90)),ISNUMBER(SEARCH("[", C90))), "", IFERROR(MID(C90, SEARCH("""", C90) +1, SEARCH("""", C90, SEARCH("""",C90) +1) - SEARCH("""", C90) -1), "")) -> houseName | E90: =IF(D90="", "", VLOOKUP(D90,'API Data Dictionary'!C:L,10,FALSE)) -> X | F90: =IF(D90="", "", VLOOKUP(D90,'API Data Dictionary'!C:D,2,FALSE)) -> string | G90: =IF(IF(D90="", "", VLOOKUP(D90,'API Data Dictionary'!C:E,3,FALSE))=0, "", IF(D90="", "", VLOOKUP(D90,'API Data Dictionary'!C:E,3,FALSE))) -> 100 | H90: =IF(IF(D90="", "", VLOOKUP(D90,'API Data Dictionary'!C:F,4,FALSE))=0, "", IF(D90="", "", VLOOKUP(D90,'API Data Dictionary'!C:F,4,FALSE))) | I90: =IF(IF(D90="", "", VLOOKUP(D90,'API Data Dictionary'!C:G,5,FALSE))=0, "", IF(D90="", "", VLOOKUP(D90,'API Data Dictionary'!C:G,5,FALSE))) -> The name of the property
C91: "addressLine1": "string", | D91: =IF(OR(ISNUMBER(SEARCH("{", C91)),ISNUMBER(SEARCH("[", C91))), "", IFERROR(MID(C91, SEARCH("""", C91) +1, SEARCH("""", C91, SEARCH("""",C91) +1) - SEARCH("""", C91) -1), "")) -> addressLine1 | E91: =IF(D91="", "", VLOOKUP(D91,'API Data Dictionary'!C:L,10,FALSE)) -> M | F91: =IF(D91="", "", VLOOKUP(D91,'API Data Dictionary'!C:D,2,FALSE)) -> string | G91: =IF(IF(D91="", "", VLOOKUP(D91,'API Data Dictionary'!C:E,3,FALSE))=0, "", IF(D91="", "", VLOOKUP(D91,'API Data Dictionary'!C:E,3,FALSE))) -> 100 | H91: =IF(IF(D91="", "", VLOOKUP(D91,'API Data Dictionary'!C:F,4,FALSE))=0, "", IF(D91="", "", VLOOKUP(D91,'API Data Dictionary'!C:F,4,FALSE))) | I91: =IF(IF(D91="", "", VLOOKUP(D91,'API Data Dictionary'!C:G,5,FALSE))=0, "", IF(D91="", "", VLOOKUP(D91,'API Data Dictionary'!C:G,5,FALSE))) -> The first line of the property address
C92: "addressLine2": "string", | D92: =IF(OR(ISNUMBER(SEARCH("{", C92)),ISNUMBER(SEARCH("[", C92))), "", IFERROR(MID(C92, SEARCH("""", C92) +1, SEARCH("""", C92, SEARCH("""",C92) +1) - SEARCH("""", C92) -1), "")) -> addressLine2 | E92: x | F92: =IF(D92="", "", VLOOKUP(D92,'API Data Dictionary'!C:D,2,FALSE)) -> string | G92: =IF(IF(D92="", "", VLOOKUP(D92,'API Data Dictionary'!C:E,3,FALSE))=0, "", IF(D92="", "", VLOOKUP(D92,'API Data Dictionary'!C:E,3,FALSE))) -> 100 | H92: =IF(IF(D92="", "", VLOOKUP(D92,'API Data Dictionary'!C:F,4,FALSE))=0, "", IF(D92="", "", VLOOKUP(D92,'API Data Dictionary'!C:F,4,FALSE))) | I92: =IF(IF(D92="", "", VLOOKUP(D92,'API Data Dictionary'!C:G,5,FALSE))=0, "", IF(D92="", "", VLOOKUP(D92,'API Data Dictionary'!C:G,5,FALSE))) -> The second line of the property address
C93: "town": "string", | D93: =IF(OR(ISNUMBER(SEARCH("{", C93)),ISNUMBER(SEARCH("[", C93))), "", IFERROR(MID(C93, SEARCH("""", C93) +1, SEARCH("""", C93, SEARCH("""",C93) +1) - SEARCH("""", C93) -1), "")) -> town | E93: =IF(D93="", "", VLOOKUP(D93,'API Data Dictionary'!C:L,10,FALSE)) -> M | F93: =IF(D93="", "", VLOOKUP(D93,'API Data Dictionary'!C:D,2,FALSE)) -> string | G93: =IF(IF(D93="", "", VLOOKUP(D93,'API Data Dictionary'!C:E,3,FALSE))=0, "", IF(D93="", "", VLOOKUP(D93,'API Data Dictionary'!C:E,3,FALSE))) -> 50 | H93: =IF(IF(D93="", "", VLOOKUP(D93,'API Data Dictionary'!C:F,4,FALSE))=0, "", IF(D93="", "", VLOOKUP(D93,'API Data Dictionary'!C:F,4,FALSE))) | I93: =IF(IF(D93="", "", VLOOKUP(D93,'API Data Dictionary'!C:G,5,FALSE))=0, "", IF(D93="", "", VLOOKUP(D93,'API Data Dictionary'!C:G,5,FALSE))) -> The town in which the property exists
C94: "country": 1, | D94: =IF(OR(ISNUMBER(SEARCH("{", C94)),ISNUMBER(SEARCH("[", C94))), "", IFERROR(MID(C94, SEARCH("""", C94) +1, SEARCH("""", C94, SEARCH("""",C94) +1) - SEARCH("""", C94) -1), "")) -> country | E94: x | F94: =IF(D94="", "", VLOOKUP(D94,'API Data Dictionary'!C:D,2,FALSE)) -> enum -Country/Location Code | G94: =IF(IF(D94="", "", VLOOKUP(D94,'API Data Dictionary'!C:E,3,FALSE))=0, "", IF(D94="", "", VLOOKUP(D94,'API Data Dictionary'!C:E,3,FALSE))) | H94: =IF(IF(D94="", "", VLOOKUP(D94,'API Data Dictionary'!C:F,4,FALSE))=0, "", IF(D94="", "", VLOOKUP(D94,'API Data Dictionary'!C:F,4,FALSE))) -> Valid Values 1-239 (See enum definition) | I94: =IF(IF(D94="", "", VLOOKUP(D94,'API Data Dictionary'!C:G,5,FALSE))=0, "", IF(D94="", "", VLOOKUP(D94,'API Data Dictionary'!C:G,5,FALSE))) -> The Country code from the enum list, e.g. France
C95: "postcode": "string" | D95: =IF(OR(ISNUMBER(SEARCH("{", C95)),ISNUMBER(SEARCH("[", C95))), "", IFERROR(MID(C95, SEARCH("""", C95) +1, SEARCH("""", C95, SEARCH("""",C95) +1) - SEARCH("""", C95) -1), "")) -> postcode | E95: =IF(D95="", "", VLOOKUP(D95,'API Data Dictionary'!C:L,10,FALSE)) -> M | F95: =IF(D95="", "", VLOOKUP(D95,'API Data Dictionary'!C:D,2,FALSE)) -> string | G95: =IF(IF(D95="", "", VLOOKUP(D95,'API Data Dictionary'!C:E,3,FALSE))=0, "", IF(D95="", "", VLOOKUP(D95,'API Data Dictionary'!C:E,3,FALSE))) -> 50 | H95: =IF(IF(D95="", "", VLOOKUP(D95,'API Data Dictionary'!C:F,4,FALSE))=0, "", IF(D95="", "", VLOOKUP(D95,'API Data Dictionary'!C:F,4,FALSE))) | I95: =IF(IF(D95="", "", VLOOKUP(D95,'API Data Dictionary'!C:G,5,FALSE))=0, "", IF(D95="", "", VLOOKUP(D95,'API Data Dictionary'!C:G,5,FALSE))) -> the postcode of the property
C96: } | D96: =IF(OR(ISNUMBER(SEARCH("{", C96)),ISNUMBER(SEARCH("[", C96))), "", IFERROR(MID(C96, SEARCH("""", C96) +1, SEARCH("""", C96, SEARCH("""",C96) +1) - SEARCH("""", C96) -1), "")) | E96: =IF(D96="", "", VLOOKUP(D96,'API Data Dictionary'!C:L,10,FALSE)) | F96: =IF(D96="", "", VLOOKUP(D96,'API Data Dictionary'!C:D,2,FALSE)) | G96: =IF(IF(D96="", "", VLOOKUP(D96,'API Data Dictionary'!C:E,3,FALSE))=0, "", IF(D96="", "", VLOOKUP(D96,'API Data Dictionary'!C:E,3,FALSE))) | H96: =IF(IF(D96="", "", VLOOKUP(D96,'API Data Dictionary'!C:F,4,FALSE))=0, "", IF(D96="", "", VLOOKUP(D96,'API Data Dictionary'!C:F,4,FALSE))) | I96: =IF(IF(D96="", "", VLOOKUP(D96,'API Data Dictionary'!C:G,5,FALSE))=0, "", IF(D96="", "", VLOOKUP(D96,'API Data Dictionary'!C:G,5,FALSE)))
C97: }, | D97: =IF(OR(ISNUMBER(SEARCH("{", C97)),ISNUMBER(SEARCH("[", C97))), "", IFERROR(MID(C97, SEARCH("""", C97) +1, SEARCH("""", C97, SEARCH("""",C97) +1) - SEARCH("""", C97) -1), "")) | E97: =IF(D97="", "", VLOOKUP(D97,'API Data Dictionary'!C:L,10,FALSE)) | F97: =IF(D97="", "", VLOOKUP(D97,'API Data Dictionary'!C:D,2,FALSE)) | G97: =IF(IF(D97="", "", VLOOKUP(D97,'API Data Dictionary'!C:E,3,FALSE))=0, "", IF(D97="", "", VLOOKUP(D97,'API Data Dictionary'!C:E,3,FALSE))) | H97: =IF(IF(D97="", "", VLOOKUP(D97,'API Data Dictionary'!C:F,4,FALSE))=0, "", IF(D97="", "", VLOOKUP(D97,'API Data Dictionary'!C:F,4,FALSE))) | I97: =IF(IF(D97="", "", VLOOKUP(D97,'API Data Dictionary'!C:G,5,FALSE))=0, "", IF(D97="", "", VLOOKUP(D97,'API Data Dictionary'!C:G,5,FALSE)))
C98: "adverseCreditDetails": { | D98: =IF(OR(ISNUMBER(SEARCH("{", C98)),ISNUMBER(SEARCH("[", C98))), "", IFERROR(MID(C98, SEARCH("""", C98) +1, SEARCH("""", C98, SEARCH("""",C98) +1) - SEARCH("""", C98) -1), "")) | E98: =IF(D98="", "", VLOOKUP(D98,'API Data Dictionary'!C:L,10,FALSE)) | F98: =IF(D98="", "", VLOOKUP(D98,'API Data Dictionary'!C:D,2,FALSE)) | G98: =IF(IF(D98="", "", VLOOKUP(D98,'API Data Dictionary'!C:E,3,FALSE))=0, "", IF(D98="", "", VLOOKUP(D98,'API Data Dictionary'!C:E,3,FALSE))) | H98: =IF(IF(D98="", "", VLOOKUP(D98,'API Data Dictionary'!C:F,4,FALSE))=0, "", IF(D98="", "", VLOOKUP(D98,'API Data Dictionary'!C:F,4,FALSE))) | I98: =IF(IF(D98="", "", VLOOKUP(D98,'API Data Dictionary'!C:G,5,FALSE))=0, "", IF(D98="", "", VLOOKUP(D98,'API Data Dictionary'!C:G,5,FALSE)))
C99: "submittedisAdverseCredit": true, | D99: =IF(OR(ISNUMBER(SEARCH("{", C99)),ISNUMBER(SEARCH("[", C99))), "", IFERROR(MID(C99, SEARCH("""", C99) +1, SEARCH("""", C99, SEARCH("""",C99) +1) - SEARCH("""", C99) -1), "")) -> submittedisAdverseCredit | E99: =IF(D99="", "", VLOOKUP(D99,'API Data Dictionary'!C:L,10,FALSE)) -> 0 | F99: =IF(D99="", "", VLOOKUP(D99,'API Data Dictionary'!C:D,2,FALSE)) -> boolean | G99: =IF(IF(D99="", "", VLOOKUP(D99,'API Data Dictionary'!C:E,3,FALSE))=0, "", IF(D99="", "", VLOOKUP(D99,'API Data Dictionary'!C:E,3,FALSE))) | H99: =IF(IF(D99="", "", VLOOKUP(D99,'API Data Dictionary'!C:F,4,FALSE))=0, "", IF(D99="", "", VLOOKUP(D99,'API Data Dictionary'!C:F,4,FALSE))) | I99: =IF(IF(D99="", "", VLOOKUP(D99,'API Data Dictionary'!C:G,5,FALSE))=0, "", IF(D99="", "", VLOOKUP(D99,'API Data Dictionary'!C:G,5,FALSE))) -> Boolean for is adverse credit
C100: "submittedisCCJ": true, | D100: =IF(OR(ISNUMBER(SEARCH("{", C100)),ISNUMBER(SEARCH("[", C100))), "", IFERROR(MID(C100, SEARCH("""", C100) +1, SEARCH("""", C100, SEARCH("""",C100) +1) - SEARCH("""", C100) -1), "")) -> submittedisCCJ | E100: =IF(D100="", "", VLOOKUP(D100,'API Data Dictionary'!C:L,10,FALSE)) -> 0 | F100: =IF(D100="", "", VLOOKUP(D100,'API Data Dictionary'!C:D,2,FALSE)) -> boolean | G100: =IF(IF(D100="", "", VLOOKUP(D100,'API Data Dictionary'!C:E,3,FALSE))=0, "", IF(D100="", "", VLOOKUP(D100,'API Data Dictionary'!C:E,3,FALSE))) | H100: =IF(IF(D100="", "", VLOOKUP(D100,'API Data Dictionary'!C:F,4,FALSE))=0, "", IF(D100="", "", VLOOKUP(D100,'API Data Dictionary'!C:F,4,FALSE))) | I100: =IF(IF(D100="", "", VLOOKUP(D100,'API Data Dictionary'!C:G,5,FALSE))=0, "", IF(D100="", "", VLOOKUP(D100,'API Data Dictionary'!C:G,5,FALSE))) -> Boolean for is County court judgment
C101: "submittedisBankruptcy": true, | D101: =IF(OR(ISNUMBER(SEARCH("{", C101)),ISNUMBER(SEARCH("[", C101))), "", IFERROR(MID(C101, SEARCH("""", C101) +1, SEARCH("""", C101, SEARCH("""",C101) +1) - SEARCH("""", C101) -1), "")) -> submittedisBankruptcy | E101: =IF(D101="", "", VLOOKUP(D101,'API Data Dictionary'!C:L,10,FALSE)) -> 0 | F101: =IF(D101="", "", VLOOKUP(D101,'API Data Dictionary'!C:D,2,FALSE)) -> boolean | G101: =IF(IF(D101="", "", VLOOKUP(D101,'API Data Dictionary'!C:E,3,FALSE))=0, "", IF(D101="", "", VLOOKUP(D101,'API Data Dictionary'!C:E,3,FALSE))) | H101: =IF(IF(D101="", "", VLOOKUP(D101,'API Data Dictionary'!C:F,4,FALSE))=0, "", IF(D101="", "", VLOOKUP(D101,'API Data Dictionary'!C:F,4,FALSE))) | I101: =IF(IF(D101="", "", VLOOKUP(D101,'API Data Dictionary'!C:G,5,FALSE))=0, "", IF(D101="", "", VLOOKUP(D101,'API Data Dictionary'!C:G,5,FALSE))) -> Boolean for is bankruptcy
...

Sheet CancelApplicantFromTenancy
B1: CancelApplicantFromTenancy Example JSON | C1: Vision+ API Field Name | D1: Mandatory Field | E1: Field Type | F1: API Max Field Length | G1: Field Validations | H1: Field Description
B2: Request Example
B3: { | C3: =IF(OR(ISNUMBER(SEARCH("{", B3)),ISNUMBER(SEARCH("[", B3))), "", IFERROR(MID(B3, SEARCH("""", B3) +1, SEARCH("""", B3, SEARCH("""",B3) +1) - SEARCH("""", B3) -1), "")) | D3: =IF(C3="", "", VLOOKUP(C3,'API Data Dictionary'!C:X,22,FALSE)) | E3: =IF(C3="", "", VLOOKUP(C3,'API Data Dictionary'!C:D,2,FALSE)) | F3: =IF(IF(C3="", "", VLOOKUP(C3,'API Data Dictionary'!C:E,3,FALSE))=0, "", IF(C3="", "", VLOOKUP(C3,'API Data Dictionary'!C:E,3,FALSE))) | G3: =IF(IF(C3="", "", VLOOKUP(C3,'API Data Dictionary'!C:F,4,FALSE))=0, "", IF(C3="", "", VLOOKUP(C3,'API Data Dictionary'!C:F,4,FALSE))) | H3: =IF(IF(C3="", "", VLOOKUP(C3,'API Data Dictionary'!C:G,5,FALSE))=0, "", IF(C3="", "", VLOOKUP(C3,'API Data Dictionary'!C:G,5,FALSE)))
A4: Referencing_HL_Auth_Setting__mdt.Agent_Code__c; | B4: "agentCode": "9999", | C4: =IF(OR(ISNUMBER(SEARCH("{", B4)),ISNUMBER(SEARCH("[", B4))), "", IFERROR(MID(B4, SEARCH("""", B4) +1, SEARCH("""", B4, SEARCH("""",B4) +1) - SEARCH("""", B4) -1), "")) -> agentCode | D4: =IF(C4="", "", VLOOKUP(C4,'API Data Dictionary'!C:X,22,FALSE)) -> 0 | E4: =IF(C4="", "", VLOOKUP(C4,'API Data Dictionary'!C:D,2,FALSE)) -> string | F4: =IF(IF(C4="", "", VLOOKUP(C4,'API Data Dictionary'!C:E,3,FALSE))=0, "", IF(C4="", "", VLOOKUP(C4,'API Data Dictionary'!C:E,3,FALSE))) -> 50 | G4: =IF(IF(C4="", "", VLOOKUP(C4,'API Data Dictionary'!C:F,4,FALSE))=0, "", IF(C4="", "", VLOOKUP(C4,'API Data Dictionary'!C:F,4,FALSE))) | H4: =IF(IF(C4="", "", VLOOKUP(C4,'API Data Dictionary'!C:G,5,FALSE))=0, "", IF(C4="", "", VLOOKUP(C4,'API Data Dictionary'!C:G,5,FALSE))) -> AgentCode is the Unique Key provided to the Agent when onboarding as a Barbon Customer. An AgentID may be linked to many Properties being managed by that Agent and Each property may be linked to 1 or more TenancyID's.
A5: opp.Referencing_Property_Tenancy_Id__c | B5: "propertyTenancyId": 1, | C5: =IF(OR(ISNUMBER(SEARCH("{", B5)),ISNUMBER(SEARCH("[", B5))), "", IFERROR(MID(B5, SEARCH("""", B5) +1, SEARCH("""", B5, SEARCH("""",B5) +1) - SEARCH("""", B5) -1), "")) -> propertyTenancyId | D5: =IF(C5="", "", VLOOKUP(C5,'API Data Dictionary'!C:X,22,FALSE)) -> 0 | E5: =IF(C5="", "", VLOOKUP(C5,'API Data Dictionary'!C:D,2,FALSE)) -> integer | F5: =IF(IF(C5="", "", VLOOKUP(C5,'API Data Dictionary'!C:E,3,FALSE))=0, "", IF(C5="", "", VLOOKUP(C5,'API Data Dictionary'!C:E,3,FALSE))) | G5: =IF(IF(C5="", "", VLOOKUP(C5,'API Data Dictionary'!C:F,4,FALSE))=0, "", IF(C5="", "", VLOOKUP(C5,'API Data Dictionary'!C:F,4,FALSE))) | H5: =IF(IF(C5="", "", VLOOKUP(C5,'API Data Dictionary'!C:G,5,FALSE))=0, "", IF(C5="", "", VLOOKUP(C5,'API Data Dictionary'!C:G,5,FALSE))) -> The ID of the property tenancy
A6: ContactRole.Referencing_Applicant_Id__c | B6: "applicantID": 1 | C6: =IF(OR(ISNUMBER(SEARCH("{", B6)),ISNUMBER(SEARCH("[", B6))), "", IFERROR(MID(B6, SEARCH("""", B6) +1, SEARCH("""", B6, SEARCH("""",B6) +1) - SEARCH("""", B6) -1), "")) -> applicantID | D6: =IF(C6="", "", VLOOKUP(C6,'API Data Dictionary'!C:X,22,FALSE)) -> M | E6: =IF(C6="", "", VLOOKUP(C6,'API Data Dictionary'!C:D,2,FALSE)) -> string | F6: =IF(IF(C6="", "", VLOOKUP(C6,'API Data Dictionary'!C:E,3,FALSE))=0, "", IF(C6="", "", VLOOKUP(C6,'API Data Dictionary'!C:E,3,FALSE))) -> 50 | G6: =IF(IF(C6="", "", VLOOKUP(C6,'API Data Dictionary'!C:F,4,FALSE))=0, "", IF(C6="", "", VLOOKUP(C6,'API Data Dictionary'!C:F,4,FALSE))) | H6: =IF(IF(C6="", "", VLOOKUP(C6,'API Data Dictionary'!C:G,5,FALSE))=0, "", IF(C6="", "", VLOOKUP(C6,'API Data Dictionary'!C:G,5,FALSE))) -> ApplicantID is a unique identifier for a person / Company to be referenced. ApplicantID may be linked to one or more TenancyID's executing in parallel. ApplicantID is created through API Methods: CreateReferenceWithAllData CreateReferenceWithInputFromApplicant CreateCompanyReferenceWithAllData CreateCompanyReferenceWithInputFromApplicant AddApplicantToTenancy
B7: } | C7: =IF(OR(ISNUMBER(SEARCH("{", B7)),ISNUMBER(SEARCH("[", B7))), "", IFERROR(MID(B7, SEARCH("""", B7) +1, SEARCH("""", B7, SEARCH("""",B7) +1) - SEARCH("""", B7) -1), "")) | D7: =IF(C7="", "", VLOOKUP(C7,'API Data Dictionary'!C:X,22,FALSE)) | E7: =IF(C7="", "", VLOOKUP(C7,'API Data Dictionary'!C:D,2,FALSE)) | F7: =IF(IF(C7="", "", VLOOKUP(C7,'API Data Dictionary'!C:E,3,FALSE))=0, "", IF(C7="", "", VLOOKUP(C7,'API Data Dictionary'!C:E,3,FALSE))) | G7: =IF(IF(C7="", "", VLOOKUP(C7,'API Data Dictionary'!C:F,4,FALSE))=0, "", IF(C7="", "", VLOOKUP(C7,'API Data Dictionary'!C:F,4,FALSE))) | H7: =IF(IF(C7="", "", VLOOKUP(C7,'API Data Dictionary'!C:G,5,FALSE))=0, "", IF(C7="", "", VLOOKUP(C7,'API Data Dictionary'!C:G,5,FALSE)))
B8: Response Example
C9: =IF(OR(ISNUMBER(SEARCH("{", B9)),ISNUMBER(SEARCH("[", B9))), "", IFERROR(MID(B9, SEARCH("""", B9) +1, SEARCH("""", B9, SEARCH("""",B9) +1) - SEARCH("""", B9) -1), "")) | D9: =IF(C9="", "", VLOOKUP(C9,'API Data Dictionary'!C:X,22,FALSE)) | E9: =IF(C9="", "", VLOOKUP(C9,'API Data Dictionary'!C:D,2,FALSE)) | F9: =IF(IF(C9="", "", VLOOKUP(C9,'API Data Dictionary'!C:E,3,FALSE))=0, "", IF(C9="", "", VLOOKUP(C9,'API Data Dictionary'!C:E,3,FALSE))) | G9: =IF(IF(C9="", "", VLOOKUP(C9,'API Data Dictionary'!C:F,4,FALSE))=0, "", IF(C9="", "", VLOOKUP(C9,'API Data Dictionary'!C:F,4,FALSE))) | H9: =IF(IF(C9="", "", VLOOKUP(C9,'API Data Dictionary'!C:G,5,FALSE))=0, "", IF(C9="", "", VLOOKUP(C9,'API Data Dictionary'!C:G,5,FALSE)))
B10: { | C10: =IF(OR(ISNUMBER(SEARCH("{", B10)),ISNUMBER(SEARCH("[", B10))), "", IFERROR(MID(B10, SEARCH("""", B10) +1, SEARCH("""", B10, SEARCH("""",B10) +1) - SEARCH("""", B10) -1), "")) | E10: =IF(C10="", "", VLOOKUP(C10,'API Data Dictionary'!C:D,2,FALSE)) | F10: =IF(IF(C10="", "", VLOOKUP(C10,'API Data Dictionary'!C:E,3,FALSE))=0, "", IF(C10="", "", VLOOKUP(C10,'API Data Dictionary'!C:E,3,FALSE))) | G10: =IF(IF(C10="", "", VLOOKUP(C10,'API Data Dictionary'!C:F,4,FALSE))=0, "", IF(C10="", "", VLOOKUP(C10,'API Data Dictionary'!C:F,4,FALSE))) | H10: =IF(IF(C10="", "", VLOOKUP(C10,'API Data Dictionary'!C:G,5,FALSE))=0, "", IF(C10="", "", VLOOKUP(C10,'API Data Dictionary'!C:G,5,FALSE)))
B11: "success": true, | C11: =IF(OR(ISNUMBER(SEARCH("{", B11)),ISNUMBER(SEARCH("[", B11))), "", IFERROR(MID(B11, SEARCH("""", B11) +1, SEARCH("""", B11, SEARCH("""",B11) +1) - SEARCH("""", B11) -1), "")) -> success | D11: x | E11: =IF(C11="", "", VLOOKUP(C11,'API Data Dictionary'!C:D,2,FALSE)) -> string - Boolean | F11: =IF(IF(C11="", "", VLOOKUP(C11,'API Data Dictionary'!C:E,3,FALSE))=0, "", IF(C11="", "", VLOOKUP(C11,'API Data Dictionary'!C:E,3,FALSE))) -> 100 | G11: =IF(IF(C11="", "", VLOOKUP(C11,'API Data Dictionary'!C:F,4,FALSE))=0, "", IF(C11="", "", VLOOKUP(C11,'API Data Dictionary'!C:F,4,FALSE))) | H11: =IF(IF(C11="", "", VLOOKUP(C11,'API Data Dictionary'!C:G,5,FALSE))=0, "", IF(C11="", "", VLOOKUP(C11,'API Data Dictionary'!C:G,5,FALSE))) -> Returns true when successful connection
B12: "payload": "Success", | C12: =IF(OR(ISNUMBER(SEARCH("{", B12)),ISNUMBER(SEARCH("[", B12))), "", IFERROR(MID(B12, SEARCH("""", B12) +1, SEARCH("""", B12, SEARCH("""",B12) +1) - SEARCH("""", B12) -1), "")) -> payload | D12: x | E12: =IF(C12="", "", VLOOKUP(C12,'API Data Dictionary'!C:D,2,FALSE)) -> string | F12: =IF(IF(C12="", "", VLOOKUP(C12,'API Data Dictionary'!C:E,3,FALSE))=0, "", IF(C12="", "", VLOOKUP(C12,'API Data Dictionary'!C:E,3,FALSE))) -> 100 | G12: =IF(IF(C12="", "", VLOOKUP(C12,'API Data Dictionary'!C:F,4,FALSE))=0, "", IF(C12="", "", VLOOKUP(C12,'API Data Dictionary'!C:F,4,FALSE))) | H12: =IF(IF(C12="", "", VLOOKUP(C12,'API Data Dictionary'!C:G,5,FALSE))=0, "", IF(C12="", "", VLOOKUP(C12,'API Data Dictionary'!C:G,5,FALSE))) -> Returns healthy when connection has worked properly
B13: "message": "Applicant Cancelled successfully." | C13: =IF(OR(ISNUMBER(SEARCH("{", B13)),ISNUMBER(SEARCH("[", B13))), "", IFERROR(MID(B13, SEARCH("""", B13) +1, SEARCH("""", B13, SEARCH("""",B13) +1) - SEARCH("""", B13) -1), "")) -> message | D13: x | E13: =IF(C13="", "", VLOOKUP(C13,'API Data Dictionary'!C:D,2,FALSE)) -> string | F13: =IF(IF(C13="", "", VLOOKUP(C13,'API Data Dictionary'!C:E,3,FALSE))=0, "", IF(C13="", "", VLOOKUP(C13,'API Data Dictionary'!C:E,3,FALSE))) -> 100 | G13: =IF(IF(C13="", "", VLOOKUP(C13,'API Data Dictionary'!C:F,4,FALSE))=0, "", IF(C13="", "", VLOOKUP(C13,'API Data Dictionary'!C:F,4,FALSE))) | H13: =IF(IF(C13="", "", VLOOKUP(C13,'API Data Dictionary'!C:G,5,FALSE))=0, "", IF(C13="", "", VLOOKUP(C13,'API Data Dictionary'!C:G,5,FALSE))) -> return value, null unless there has been error in connection
B14: } | C14: =IF(OR(ISNUMBER(SEARCH("{", B14)),ISNUMBER(SEARCH("[", B14))), "", IFERROR(MID(B14, SEARCH("""", B14) +1, SEARCH("""", B14, SEARCH("""",B14) +1) - SEARCH("""", B14) -1), "")) | D14: =IF(C14="", "", VLOOKUP(C14,'API Data Dictionary'!C:X,22,FALSE)) | E14: =IF(C14="", "", VLOOKUP(C14,'API Data Dictionary'!C:D,2,FALSE)) | F14: =IF(IF(C14="", "", VLOOKUP(C14,'API Data Dictionary'!C:E,3,FALSE))=0, "", IF(C14="", "", VLOOKUP(C14,'API Data Dictionary'!C:E,3,FALSE))) | G14: =IF(IF(C14="", "", VLOOKUP(C14,'API Data Dictionary'!C:F,4,FALSE))=0, "", IF(C14="", "", VLOOKUP(C14,'API Data Dictionary'!C:F,4,FALSE))) | H14: =IF(IF(C14="", "", VLOOKUP(C14,'API Data Dictionary'!C:G,5,FALSE))=0, "", IF(C14="", "", VLOOKUP(C14,'API Data Dictionary'!C:G,5,FALSE)))

Sheet CancelTenancy
A1: SF Field | B1: CancelTenancy Example JSON | C1: Vision+ API Field Name | D1: Mandatory Field | E1: Field Type | F1: API Max Field Length | G1: Field Validations | H1: Field Description
B2: Request Example
B3: { | C3: =IF(OR(ISNUMBER(SEARCH("{", B3)),ISNUMBER(SEARCH("[", B3))), "", IFERROR(MID(B3, SEARCH("""", B3) +1, SEARCH("""", B3, SEARCH("""",B3) +1) - SEARCH("""", B3) -1), "")) | D3: =IF(C3="", "", VLOOKUP(C3,'API Data Dictionary'!C:X,22,FALSE)) | E3: =IF(C3="", "", VLOOKUP(C3,'API Data Dictionary'!C:D,2,FALSE)) | F3: =IF(IF(C3="", "", VLOOKUP(C3,'API Data Dictionary'!C:E,3,FALSE))=0, "", IF(C3="", "", VLOOKUP(C3,'API Data Dictionary'!C:E,3,FALSE))) | G3: =IF(IF(C3="", "", VLOOKUP(C3,'API Data Dictionary'!C:F,4,FALSE))=0, "", IF(C3="", "", VLOOKUP(C3,'API Data Dictionary'!C:F,4,FALSE))) | H3: =IF(IF(C3="", "", VLOOKUP(C3,'API Data Dictionary'!C:G,5,FALSE))=0, "", IF(C3="", "", VLOOKUP(C3,'API Data Dictionary'!C:G,5,FALSE)))
A4: Referencing_HL_Auth_Setting__mdt.Agent_Code__c; | B4: "agentCode": "9999", | C4: =IF(OR(ISNUMBER(SEARCH("{", B4)),ISNUMBER(SEARCH("[", B4))), "", IFERROR(MID(B4, SEARCH("""", B4) +1, SEARCH("""", B4, SEARCH("""",B4) +1) - SEARCH("""", B4) -1), "")) -> agentCode | D4: x | E4: =IF(C4="", "", VLOOKUP(C4,'API Data Dictionary'!C:D,2,FALSE)) -> string | F4: =IF(IF(C4="", "", VLOOKUP(C4,'API Data Dictionary'!C:E,3,FALSE))=0, "", IF(C4="", "", VLOOKUP(C4,'API Data Dictionary'!C:E,3,FALSE))) -> 50 | G4: =IF(IF(C4="", "", VLOOKUP(C4,'API Data Dictionary'!C:F,4,FALSE))=0, "", IF(C4="", "", VLOOKUP(C4,'API Data Dictionary'!C:F,4,FALSE))) | H4: =IF(IF(C4="", "", VLOOKUP(C4,'API Data Dictionary'!C:G,5,FALSE))=0, "", IF(C4="", "", VLOOKUP(C4,'API Data Dictionary'!C:G,5,FALSE))) -> AgentCode is the Unique Key provided to the Agent when onboarding as a Barbon Customer. An AgentID may be linked to many Properties being managed by that Agent and Each property may be linked to 1 or more TenancyID's.
A5: opp.Referencing_Property_Tenancy_Id__c | B5: "propertyTenancyId": 1, | C5: =IF(OR(ISNUMBER(SEARCH("{", B5)),ISNUMBER(SEARCH("[", B5))), "", IFERROR(MID(B5, SEARCH("""", B5) +1, SEARCH("""", B5, SEARCH("""",B5) +1) - SEARCH("""", B5) -1), "")) -> propertyTenancyId | D5: x | E5: =IF(C5="", "", VLOOKUP(C5,'API Data Dictionary'!C:D,2,FALSE)) -> integer | F5: =IF(IF(C5="", "", VLOOKUP(C5,'API Data Dictionary'!C:E,3,FALSE))=0, "", IF(C5="", "", VLOOKUP(C5,'API Data Dictionary'!C:E,3,FALSE))) | G5: =IF(IF(C5="", "", VLOOKUP(C5,'API Data Dictionary'!C:F,4,FALSE))=0, "", IF(C5="", "", VLOOKUP(C5,'API Data Dictionary'!C:F,4,FALSE))) | H5: =IF(IF(C5="", "", VLOOKUP(C5,'API Data Dictionary'!C:G,5,FALSE))=0, "", IF(C5="", "", VLOOKUP(C5,'API Data Dictionary'!C:G,5,FALSE))) -> The ID of the property tenancy
B6: "possessionDate": "2023-02-21T01:02:21.955Z" | C6: =IF(OR(ISNUMBER(SEARCH("{", B6)),ISNUMBER(SEARCH("[", B6))), "", IFERROR(MID(B6, SEARCH("""", B6) +1, SEARCH("""", B6, SEARCH("""",B6) +1) - SEARCH("""", B6) -1), "")) -> possessionDate | D6: x | E6: string datetime | H6: confirmation of the possesion date of the property
B7: "cancellationReason": 1 | C7: =IF(OR(ISNUMBER(SEARCH("{", B7)),ISNUMBER(SEARCH("[", B7))), "", IFERROR(MID(B7, SEARCH("""", B7) +1, SEARCH("""", B7, SEARCH("""",B7) +1) - SEARCH("""", B7) -1), "")) -> cancellationReason
B8: } | C8: =IF(OR(ISNUMBER(SEARCH("{", B8)),ISNUMBER(SEARCH("[", B8))), "", IFERROR(MID(B8, SEARCH("""", B8) +1, SEARCH("""", B8, SEARCH("""",B8) +1) - SEARCH("""", B8) -1), "")) | D8: =IF(C8="", "", VLOOKUP(C8,'API Data Dictionary'!C:X,22,FALSE)) | E8: =IF(C8="", "", VLOOKUP(C8,'API Data Dictionary'!C:D,2,FALSE)) | F8: =IF(IF(C8="", "", VLOOKUP(C8,'API Data Dictionary'!C:E,3,FALSE))=0, "", IF(C8="", "", VLOOKUP(C8,'API Data Dictionary'!C:E,3,FALSE))) | G8: =IF(IF(C8="", "", VLOOKUP(C8,'API Data Dictionary'!C:F,4,FALSE))=0, "", IF(C8="", "", VLOOKUP(C8,'API Data Dictionary'!C:F,4,FALSE))) | H8: =IF(IF(C8="", "", VLOOKUP(C8,'API Data Dictionary'!C:G,5,FALSE))=0, "", IF(C8="", "", VLOOKUP(C8,'API Data Dictionary'!C:G,5,FALSE)))
B9: Response Example
C10: =IF(OR(ISNUMBER(SEARCH("{", B10)),ISNUMBER(SEARCH("[", B10))), "", IFERROR(MID(B10, SEARCH("""", B10) +1, SEARCH("""", B10, SEARCH("""",B10) +1) - SEARCH("""", B10) -1), "")) | D10: =IF(C10="", "", VLOOKUP(C10,'API Data Dictionary'!C:X,22,FALSE)) | E10: =IF(C10="", "", VLOOKUP(C10,'API Data Dictionary'!C:D,2,FALSE)) | F10: =IF(IF(C10="", "", VLOOKUP(C10,'API Data Dictionary'!C:E,3,FALSE))=0, "", IF(C10="", "", VLOOKUP(C10,'API Data Dictionary'!C:E,3,FALSE))) | G10: =IF(IF(C10="", "", VLOOKUP(C10,'API Data Dictionary'!C:F,4,FALSE))=0, "", IF(C10="", "", VLOOKUP(C10,'API Data Dictionary'!C:F,4,FALSE))) | H10: =IF(IF(C10="", "", VLOOKUP(C10,'API Data Dictionary'!C:G,5,FALSE))=0, "", IF(C10="", "", VLOOKUP(C10,'API Data Dictionary'!C:G,5,FALSE)))
B11: { | C11: =IF(OR(ISNUMBER(SEARCH("{", B11)),ISNUMBER(SEARCH("[", B11))), "", IFERROR(MID(B11, SEARCH("""", B11) +1, SEARCH("""", B11, SEARCH("""",B11) +1) - SEARCH("""", B11) -1), "")) | E11: =IF(C11="", "", VLOOKUP(C11,'API Data Dictionary'!C:D,2,FALSE)) | F11: =IF(IF(C11="", "", VLOOKUP(C11,'API Data Dictionary'!C:E,3,FALSE))=0, "", IF(C11="", "", VLOOKUP(C11,'API Data Dictionary'!C:E,3,FALSE))) | G11: =IF(IF(C11="", "", VLOOKUP(C11,'API Data Dictionary'!C:F,4,FALSE))=0, "", IF(C11="", "", VLOOKUP(C11,'API Data Dictionary'!C:F,4,FALSE))) | H11: =IF(IF(C11="", "", VLOOKUP(C11,'API Data Dictionary'!C:G,5,FALSE))=0, "", IF(C11="", "", VLOOKUP(C11,'API Data Dictionary'!C:G,5,FALSE)))
B12: "success": true, | C12: =IF(OR(ISNUMBER(SEARCH("{", B12)),ISNUMBER(SEARCH("[", B12))), "", IFERROR(MID(B12, SEARCH("""", B12) +1, SEARCH("""", B12, SEARCH("""",B12) +1) - SEARCH("""", B12) -1), "")) -> success | D12: x | E12: =IF(C12="", "", VLOOKUP(C12,'API Data Dictionary'!C:D,2,FALSE)) -> string - Boolean | F12: =IF(IF(C12="", "", VLOOKUP(C12,'API Data Dictionary'!C:E,3,FALSE))=0, "", IF(C12="", "", VLOOKUP(C12,'API Data Dictionary'!C:E,3,FALSE))) -> 100 | G12: =IF(IF(C12="", "", VLOOKUP(C12,'API Data Dictionary'!C:F,4,FALSE))=0, "", IF(C12="", "", VLOOKUP(C12,'API Data Dictionary'!C:F,4,FALSE))) | H12: =IF(IF(C12="", "", VLOOKUP(C12,'API Data Dictionary'!C:G,5,FALSE))=0, "", IF(C12="", "", VLOOKUP(C12,'API Data Dictionary'!C:G,5,FALSE))) -> Returns true when successful connection
B13: "payload": "Success", | C13: =IF(OR(ISNUMBER(SEARCH("{", B13)),ISNUMBER(SEARCH("[", B13))), "", IFERROR(MID(B13, SEARCH("""", B13) +1, SEARCH("""", B13, SEARCH("""",B13) +1) - SEARCH("""", B13) -1), "")) -> payload | D13: x | E13: =IF(C13="", "", VLOOKUP(C13,'API Data Dictionary'!C:D,2,FALSE)) -> string | F13: =IF(IF(C13="", "", VLOOKUP(C13,'API Data Dictionary'!C:E,3,FALSE))=0, "", IF(C13="", "", VLOOKUP(C13,'API Data Dictionary'!C:E,3,FALSE))) -> 100 | G13: =IF(IF(C13="", "", VLOOKUP(C13,'API Data Dictionary'!C:F,4,FALSE))=0, "", IF(C13="", "", VLOOKUP(C13,'API Data Dictionary'!C:F,4,FALSE))) | H13: =IF(IF(C13="", "", VLOOKUP(C13,'API Data Dictionary'!C:G,5,FALSE))=0, "", IF(C13="", "", VLOOKUP(C13,'API Data Dictionary'!C:G,5,FALSE))) -> Returns healthy when connection has worked properly
B14: "message": "Tenancy Cancelled successfully." | C14: =IF(OR(ISNUMBER(SEARCH("{", B14)),ISNUMBER(SEARCH("[", B14))), "", IFERROR(MID(B14, SEARCH("""", B14) +1, SEARCH("""", B14, SEARCH("""",B14) +1) - SEARCH("""", B14) -1), "")) -> message | D14: x | E14: =IF(C14="", "", VLOOKUP(C14,'API Data Dictionary'!C:D,2,FALSE)) -> string | F14: =IF(IF(C14="", "", VLOOKUP(C14,'API Data Dictionary'!C:E,3,FALSE))=0, "", IF(C14="", "", VLOOKUP(C14,'API Data Dictionary'!C:E,3,FALSE))) -> 100 | G14: =IF(IF(C14="", "", VLOOKUP(C14,'API Data Dictionary'!C:F,4,FALSE))=0, "", IF(C14="", "", VLOOKUP(C14,'API Data Dictionary'!C:F,4,FALSE))) | H14: =IF(IF(C14="", "", VLOOKUP(C14,'API Data Dictionary'!C:G,5,FALSE))=0, "", IF(C14="", "", VLOOKUP(C14,'API Data Dictionary'!C:G,5,FALSE))) -> return value, null unless there has been error in connection
B15: } | C15: =IF(OR(ISNUMBER(SEARCH("{", B15)),ISNUMBER(SEARCH("[", B15))), "", IFERROR(MID(B15, SEARCH("""", B15) +1, SEARCH("""", B15, SEARCH("""",B15) +1) - SEARCH("""", B15) -1), "")) | D15: =IF(C15="", "", VLOOKUP(C15,'API Data Dictionary'!C:X,22,FALSE)) | E15: =IF(C15="", "", VLOOKUP(C15,'API Data Dictionary'!C:D,2,FALSE)) | F15: =IF(IF(C15="", "", VLOOKUP(C15,'API Data Dictionary'!C:E,3,FALSE))=0, "", IF(C15="", "", VLOOKUP(C15,'API Data Dictionary'!C:E,3,FALSE))) | G15: =IF(IF(C15="", "", VLOOKUP(C15,'API Data Dictionary'!C:F,4,FALSE))=0, "", IF(C15="", "", VLOOKUP(C15,'API Data Dictionary'!C:F,4,FALSE))) | H15: =IF(IF(C15="", "", VLOOKUP(C15,'API Data Dictionary'!C:G,5,FALSE))=0, "", IF(C15="", "", VLOOKUP(C15,'API Data Dictionary'!C:G,5,FALSE)))
