Workbook

Sheet Version History
A1: Date | B1: Version | C1: Author | D1: Comments
A2: 44645 | B2: 1.0 | C2: Phil Cullum | D2: Created based on mapping doc CP-CORE-02_NominalCodeUpserted_CP-CORE-04 EntityUpserted_Mapping v1.29 (3.10).xlsx and review of current GREP implementation
A3: 44649 | B3: 1.1 | C3: Phil Cullum | D3: Corrected mapping logic around creation of Accounts for commercial and residential tenants

Sheet Qube to Salesforce
A1: Data Mapping | B1: CP-CORE-02/CP-CORE-04
A2: Sending Interface system | B2: MRI
A3: Outbound Data Structure | B3: XML
A4: Receiving Interface system 2 | B4: Concept Evolution
A5: Inbound Data Structure 2 | B5: XML
A6: Title | B6: ChartsOfAccountsUpserted/NominalUpserted
A8: Source -Qube | C8: XML Element / Attribute | D8: Mandatory/Optional | E8: Type | F8: Size | G8: Sample Data | H8: Transformation rule/logic | I8: Canonical | J8: Destination - Salesforce | L8: JSON Element | M8: Transformation rule/logic
A9: Table | B9: Source API | J9: Table | K9: Destination Object
K10: Call order: 1.UpsertEstate 2.UpsertBuilding 3.UpsertUnit 4.Upsert Account 5.Upsert Contact (commercial tenants) 6.Upsert Opportunity 7.Upsert OpportunityContactRole
B11: Qube Buildings, Units and Tenants | C11: <building><reference> | E11: String | F11: 12 | G11: 222485 | H11: Direct | I11: <EntityListing><EntityID> | K11: Building | L11: Id | M11: Look up Salesforce Building ID from GREP XREF using <EntityListing><EntityID>
K12: Unit | L12: Building__c
K13: Building | L13: Estate__c | M13: Look up Salesforce Estate ID from GREP XREF using <EntityListing><EntityID>
B14: Qube Buildings, Units and Tenants | C14: <building><name> | E14: String | F14: 30 | H14: Direct | I14: <EntityListing><EntityName> | K14: Building | L14: Building/Name | M14: Direct
B15: Qube Buildings, Units and Tenants | C15: <building><legalowner><reference> | H15: Direct | I15: <EntityListing><LegalOwner><entry><OwnerID> | K15: Unit | L15: SUN__c | M15: Refer to the Owner ID table and match <EntityListing><LegalOwner><entry><OwnerID> with the Salesforce value. Note: Values configured in QuickConnect ref data SalesforceData list, key Mapping|MRIOwnerId|[OwnerID]
B16: Qube Buildings, Units and Tenants | C16: <building><legalowner><name> | H16: Direct | I16: <EntityListing><LegalOwner><entry><OwnerName> | K16: Unit | L16: Landlord_Name__c | M16: Direct
B17: Qube Buildings, Units and Tenants | C17: <building><legalowner><address1> | H17: Direct | I17: <EntityListing><LegalOwner><entry><OwnerAddress1> | K17: Unit | L17: Landlord_Street__c | M17: Direct
B18: Qube Buildings, Units and Tenants | C18: <building><legalowner><city> | H18: Direct | I18: <EntityListing><LegalOwner><entry><OwnerCity> | K18: Unit | L18: Landlord_City__c | M18: Direct
H19: NOT MAPPED | I19: <EntityListing><LegalOwner><entry><OwnerState> | K19: Unit | L19: Landlord_County__c | M19: Direct
B20: Qube Buildings, Units and Tenants | C20: <building><legalowner><postcode> | H20: Direct | I20: <EntityListing><LegalOwner><entry><OwnerZip> | K20: Unit | L20: Landlord_Zip_Postal_Code__c | M20: Direct
B21: Qube Buildings, Units and Tenants | C21: <building><property-status> | E21: String | G21: Active | H21: If <property-status> = Active Send Y else send N | I21: <EntityListing><ACTIVE> | J21: NOT MAPPED
B22: Qube Buildings, Units and Tenants | C22: <building><building-tenure> | E22: String | G22: AST | H22: Direct | I22: <EntityListing><TenureTypeDesc> | J22: NOT MAPPED
B23: Qube Buildings, Units and Tenants | C23: <building><purchase-date> | D23: Optional | E23: date | H23: Send as dd-mm-yyyy | I23: <EntityListing><DateAquired> | J23: NOT MAPPED
B24: Qube Buildings, Units and Tenants | C24: <building><asset><code> | E24: String | H24: If code = 1 Investment then send Y, else if code = 2 then Send N for Trading otherwise send blank NOTE: If InvestmentOnly is blank do NOT send Building, Units or Tenants to any downstream system (FSI, Proactis, Salesforce, Customer Portal) | I24: <EntityListing><InvestmentOnly> | J24: NOT MAPPED
B25: Qube Buildings, Units and Tenants | C25: <building><asset><region> | D25: Optional | E25: String | F25: 49 | H25: Direct | I25: <EntityListing><RegionDesc>
B26: Qube Buildings, Units and Tenants | C26: <building><asset><fund> | D26: Optional | E26: String | F26: 49 | H26: Direct | I26: <EntityListing><ClientDesc> | K26: Unit | L26: Unit/Fund__c | M26: Direct
B27: Qube Buildings, Units and Tenants | C27: <building><estate><name> | H27: Direct | I27: <EntityListing><ProjectName> | K27: Estate | L27: Estate/Name | M27: Direct
B28: Qube Buildings, Units and Tenants | C28: <building><asset><portfolio-id> | E28: String | F28: 49 | H28: Direct | I28: <EntityListing><PortfolioID> | K28: Unit | L28: Portfolio__c | M28: Direct
B29: Qube Buildings, Units and Tenants | C29: <building><address1> | E29: String | F29: 45 | H29: Direct | I29: <EntityListing><SHIPADR1> | J29: NOT MAPPED
B30: Qube Buildings, Units and Tenants | C30: <building><address2> | E30: String | F30: 45 | H30: Direct | I30: <EntityListing><SHIPADR2> | J30: NOT MAPPED
B31: Qube Buildings, Units and Tenants | C31: <building><address3> | E31: String | F31: 45 | H31: Direct | I31: <EntityListing><SHIPADR3> | J31: NOT MAPPED
B32: Qube Buildings, Units and Tenants | C32: <building><address4> <building><city> | E32: String | F32: 45 | H32: If address4 is specified map address4 otherwise map city | I32: <EntityListing><SHIPCITY> | K32: Building | L32: City__c | M32: Direct
B33: Qube Buildings, Units and Tenants | C33: <building><address5> | E33: String | F33: 45 | H33: Direct | I33: <EntityListing><SHIPST> | J33: NOT MAPPED
B34: Qube Buildings, Units and Tenants | C34: <building><postcode> | E34: String | F34: 45 | H34: Direct | I34: <EntityListing><SHIPZIP> | J34: NOT MAPPED
B35: Qube Buildings, Units and Tenants | C35: <building><prop-type> | E35: String | H35: If specified then map direct otherwise send MIXED USE | I35: <EntityListing><PropertyType> | J35: NOT MAPPED
H36: Refer to the Property Type table and match <building><prop-type> with the canonical code. Note: Values configured in QuickConnect ref data QubeCOA list, key Mapping|PropertyType|[prop-type] | I36: <EntityListing><EntityType> | J36: NOT MAPPED
B37: Qube Buildings, Units and Tenants | C37: <units><unit><reference> | D37: Mandatory | E37: String | F37: 30 | G37: 222485035 | H37: Parse the first 6 digits and add an hypen and send i.e. convert 222485035 to 222485-035 | I37: <EntityListing><UnitReference><entry><UnitRef> | K37: Contract | L37: Unit__c | M37: Use the UnitRef to find the Salesforce Unit id value from the XREF.
K38: Unit | L38: Id | M38: Use the UnitRef to find the Salesforce Unit id value from the XREF.
B39: Qube Buildings, Units and Tenants | C39: <units><unit><description> | D39: Mandatory | E39: String | F39: 50 | G39: Flat 602, Indigoblu | H39: Direct | I39: <EntityListing><UnitReference><entry><Description> | K39: Unit | L39: Name | M39: Direct
B40: Qube Buildings, Units and Tenants | C40: <units><unit><address1> | H40: Direct | I40: <EntityListing><UnitReference><entry><AddressLine1> | K40: Unit | L40: Street_Name__c | M40: Direct
B41: Qube Buildings, Units and Tenants | C41: <units><unit><postcode> | H41: Direct | I41: <EntityListing><UnitReference><entry><UnitPostCode> | K41: Unit | L41: Post_Code__c | M41: Direct
B42: Qube Buildings, Units and Tenants | C42: <units><unit><unitsize><area> | H42: Direct | I42: <EntityListing><UnitReference><entry><SQFT> | K42: Unit | L42: Internal_Space_GIA_ft__c | M42: Direct
K43: Unit | L43: Internal_Space_GIA_m__c | M43: Multiply <EntityListing><UnitReference><entry><SQFT> * 0.092903
B44: Qube Buildings, Units and Tenants | C44: <units><unit><unittype> | H44: Refer to the Unit Type table and match <units><unit><unittype> with the canonical code. Note: Values configured in QuickConnect ref data QubeCOA list, key Mapping|UnitType|[unittype] | I44: <EntityListing><UnitReference><entry><UNITTYPE> | K44: Unit | L44: Bedrooms__c | M44: If (<EntityListing><UnitReference><entry><NMBRBED> = 0 or not specified) and <EntityListing><UnitReference><entry><UNITKIND> = "BE" then send "Bedsit" Otherwise If (<EntityListing><UnitReference><entry><NMBRBED> = 0 or not specified) and <EntityListing><UnitReference><entry><UNITKIND> <> "BE" then send "Studio" Otherwise Refer to the Bedrooms table and match <EntityListing><UnitReference><entry><NMBRBED> with the Salesforce value. Note: Values configured in QuickConnect ref data SalesforceData list, key Mapping|[NMBRBED]
I45: <EntityListing><UnitReference><entry><UNITKIND>
B46: Qube Buildings, Units and Tenants | C46: <units><unit><bedrooms> | D46: Optional | E46: String | F46: 2 | H46: Direct | I46: <EntityListing><UnitReference><entry><NMBRBED>
B47: Qube Buildings, Units and Tenants | C47: <units><unit><bathrooms> | D47: Optional | E47: String | H47: Direct | I47: <EntityListing><UnitReference><entry><NMBRBATH> | K47: Unit | L47: Bathrooms__c | M47: If <EntityListing><UnitReference><entry><NMBRBATH> not specified or not a number send empty string Otherwise If <EntityListing><UnitReference><entry><NMBRBATH> >= 1 and <EntityListing><UnitReference><entry><NMBRBATH> <= 4 then send <UnitReference><entry><NMBRBATH> Otherwise Send default maximum number of baths. Note: Default maximum number of baths configured in QuickConnect ref data SalesforceData list, key Mapping|MaxNumberOfBaths
B48: Qube Buildings, Units and Tenants | C48: <units><unit><balconies> | H48: Direct | I48: <EntityListing><UnitReference><entry><BALPAT> | K48: Unit | L48: Outdoor_Space__c | M48: Direct
B49: Qube Buildings, Units and Tenants | C49: <units><unit><unitstatus> | D49: Mandatory | E49: String | F49: 8 | H49: Direct | I49: <EntityListing><UnitReference><entry><StatusIDDirect>
H50: Refer to the Unit Status Code table and match <units> <unit> <unittype> with the canonical code. Note: Values configured in QuickConnect ref data QubeCOA list, key Mapping|UnitStatusCode|[unitstatus] | I50: <EntityListing><UnitReference><entry><StatusID> | K50: Unit | L50: Unit_Status__c | M50: Refer to the Unit Status Code table and match <EntityListing> <UnitReference> <entry> <StatusID> with the Salesforce value. If no match found, do NOT send Building, Units or Tenants to Salesforce Note: Values configured in QuickConnect ref data SalesforceData list, key Mapping|MRILiveUnitStatusCode|[StatusID]
H51: Refer to the Unit Status Description table and match <units><unit><unittype> with the canonical code. Note: Values configured in QuickConnect ref data QubeCOA list, key Mapping|UnitStatusDescription|[unitstatus] | I51: <EntityListing><UnitReference><entry><StatusDesc> | K51: Unit | L51: MRI_Unit_Status__c | M51: Direct
B52: Qube Buildings, Units and Tenants | D52: Optional | H52: Direct | I52: <EntityListing><UnitReference><entry><TenureTypeDirect>
H53: Refer to the Tenure Type table and match <units><unit><tenure> with the canonical code. Note: Values configured in QuickConnect ref data QubeCOA list, key Mapping|UnitTenureType|[tenure] | I53: <EntityListing><UnitReference><entry><TenureType> | M53: If <EntityListing><UnitReference><entry><TenureType> is any of the following: XXX then do NOT send Building, Units or Tenants to Salesforce Note: Filter values configured in QuickConnect ref data MRISupplier list, key Mapping|ExcludedTenure
K54: Unit | L54: RecordType | M54: Refer to the Tenure Type table and match <EntityListing><UnitReference><entry><TenureType> with the Salesforce value. If no match found do NOT send Building or Units to Salesforce Note: Values configured in QuickConnect ref data SalesforceData list, key Mapping|TenureType|[TenureType]
M55: Refer to the CM Tenure Type table and match <EntityListing><UnitReference><entry><TenureType> with the Salesforce value. If tenure type not specified or no match found do NOT send Tenants to Salesforce Note: Values configured in QuickConnect ref data SalesforceData list, key Mapping|CMTenureType|[TenureType]
K56: Opportunity | L56: Agreement_Type__c | M56: Refer to the Agreement Type table and match <EntityListing><UnitReference><entry><TenureType> with the Salesforce value. If no match found, send default value from table Note: Values configured in QuickConnect ref data SalesforceData list, key Mapping|AgreementType|[TenureType]
K57: Contract | L57: Agreement_Type__c
B58: Qube Buildings, Units and Tenants | C58: <units><unit><userroles><unitmanager><email> | H58: Direct | I58: <EntityListing><UserRoles><UnitManager><Email> | K58: Unit | L58: Unit_Manager__c | M58: Use <EntityListing><UserRoles><UnitManager><Email> to look up Salesforce ID from Salesforce Users
B59: Qube Buildings, Units and Tenants | C59: <units><unit><userroles><assetmanager><email> | H59: Direct | I59: <EntityListing><UserRoles><AssetManager><Email> | K59: Unit | L59: Asset_Manager__c | M59: Use <EntityListing><UserRoles><AssetManager><Email> to look up Salesforce ID from Salesforce Users
B60: Qube Buildings, Units and Tenants | C60: <units><unit><userroles><blockmanager><email> | H60: Direct | I60: <EntityListing><UserRoles><BlockManager><Email> | K60: Unit | L60: Block_Manager__c | M60: Use <EntityListing><UserRoles><BlockManager><Email> to look up Salesforce ID from Salesforce Users
B61: Qube Buildings, Units and Tenants | C61: <units><unit><userroles><seniopropertymanager><email> | H61: Direct | I61: <EntityListing><UserRoles><SeniorPropertyManager><Email> | K61: Unit | L61: General_Manager__c | M61: Use <EntityListing><UserRoles><SeniorPropertyManager><Email> to look up Salesforce ID from Salesforce Users
B62: Qube Buildings, Units and Tenants | C62: <units><unit><userroles><adminassistant><email> | H62: Direct | I62: <EntityListing><UserRoles><AdminAssistant><Email> | K62: Unit | L62: Property_Manager_Assistant__c | M62: Use <EntityListing><UserRoles><AdminAssistant><Email> to look up Salesforce ID from Salesforce Users
B63: Qube Buildings, Units and Tenants | C63: <building><units><unit><tenant><clients><client><honorific> | E63: Choice of custom | H63: Direct | I63: <CMResidents><entry><CMContacts><entry><Title> | J63: NOT MAPPED
B64: Qube Buildings, Units and Tenants | C64: <building><units><unit><tenant><clients><client><first-name> | E64: String | F64: 20 | H64: Direct | I64: <CMResidents><entry><CMContacts><entry><FirstName> | K64: Account | L64: FirstName | M64: Direct
K65: Contact | L65: FisrtName | M65: Direct Commercial tenants only
B66: Qube Buildings, Units and Tenants | C66: <building><units><unit><tenant><clients><client><surname> | E66: String | F66: 20 | H66: Direct | I66: <CMResidents><entry><CMContacts><entry><LastName> | K66: Account | L66: LastName | M66: Direct
K67: Contact | L67: LastName | M67: Direct Commercial tenants only
K68: Account | L68: RecordType | M68: If residential tenant, send "Person Account" If commercial tenant send "Company" Note: Values configured in QuickConnect ref data SalesforceData list, keys Mapping|ResidentialRecordTypeId and Mapping|CommercialRecordTypeId respectively
B69: Qube Buildings, Units and Tenants | C69: <building><units><unit><tenant><clients><client><phonenumber> | E69: String | F69: 30 | H69: Direct | I69: <CMResidents><entry><CMContacts><entry><Phone> | K69: Account | L69: Phone | M69: Direct
K70: Contact | L70: Phone | M70: Direct Commercial tenants only
I71: <CMResidents><entry><CMContacts><entry><MobilePhone> | K71: Account | L71: MobilePhone | M71: Direct
K72: Contact | L72: MobilePhone | M72: Direct Commercial tenants only
K73: Account | L73: AccountSource | M73: Send "Qube" Note: Value configured in QuickConnect ref data SalesforceData list, key Mapping|AccountSource
B74: Qube Buildings, Units and Tenants | C74: <building><units><unit><tenant><telephone1> | E74: String | F74: 30 | H74: Direct | I74: <CMResidents><entry><Telephone1> | J74: NOT MAPPED
B75: Qube Buildings, Units and Tenants | C75: <building><units><unit><tenant><telephone2> | E75: String | F75: 30 | H75: Direct | I75: <CMResidents><entry><Telephone2> | J75: NOT MAPPED
B76: Qube Buildings, Units and Tenants | C76: <building><units><unit><tenant><clients><client><email> | E76: String | F76: 50 | H76: If email is blank then generrate a dummy email value in the form <tenant><reference>_<client><subreference>@[missing email path ref data] Note: Missing email patch value configured in QuickConnect ref data QubeCOA list, key Mapping|MissingEmailPatch with default value "grainger-qubemissing.org" If the "AnonymisedEmailFlag" system setting is set true then modify the email address by replacing the "@" symbol with -g@g- otherwise map direct | I76: <CMResidents><entry><CMContacts><entry><Email> | K76: Account | L76: PersonEmail | M76: Check email string against QuickConnect entry which represents regex string to identify dummy email addresses in the system. If there is a regex match then do not send anything in this field, otherwise send the email directly. Note: Value configured in QuickConnect ref data MRIEmail list, key MRIDummyEmail
B77: Qube Buildings, Units and Tenants | C77: <building><units><unit><tenant><reference> | G77: 222521047006 | H77: Send <building><units><unit><tenant><reference> concatenated with <building><units><unit><tenant><clients><client><subreference> e.g. 2225210470061 | I77: <CMResidents><entry><CMContacts><entry><ContactID> | J77: NOT MAPPED
B78: Qube Buildings, Units and Tenants | C78: <building><units><unit><tenant><clients><client><subreference> | G78: 1
B79: Qube Buildings, Units and Tenants | C79: <building><units><unit><tenant><clients><client><client-status> | H79: Refer to the Contact Status Table and map the relevant canonical status Note: Values configured in QuickConnect ref data QubeCOA list, key Mapping|ContactStatus|[client-status] | I79: <CMResidents><entry><CMContacts><entry><ContactStatus> | K79: OpportunityContactRole | L79: Active__c | M79: If <CMResidents><entry><CMContacts><entry><ContactStatus> = "C" send true otherwise send false Note: Active__c Values configured in QuickConnect ref data SalesforceData list, key Mapping|[ContactStatus]
B80: Qube Buildings, Units and Tenants | C80: <building><units><unit><tenant><clients><client><date-of-death> | H80: Direct | I80: <CMResidents><entry><CMContacts><entry><DateOfDeath> | K80: OpportunityContactRole | L80: Reason_for_Removal__c | M80: If <CMResidents><entry><CMContacts><entry><DateOfDeath> specified and <CMResidents><entry><CMContacts><entry><ContactStatus> = I, send "Deceased" otherwise send "Reason not known" Note: Reason for Removal Values configured in QuickConnect ref data SalesforceData list, key Mapping|Reason_for_Removal__c
B81: Qube Buildings, Units and Tenants | C81: <building><units><unit><tenant><status> | G81: Current | H81: Refer to the Tenant Status Sheet and map the relevant canonical status. Note: Values configured in QuickConnect ref data QubeCOA list, key Mapping|TenantStatus|[status] | I81: <CMResidents><entry><Status> | M81: If Status = "N" (future tenant) then find the latest Opportunity for the tenant unit and add the Opportunity ID to the Future Tenant XRef Tenancy record. This allows the tenancy to be updated from the Opportunity details when it has reached the audut stage Otherwise Process the tenancy normally
B82: Qube Buildings, Units and Tenants | C82: <building><units><unit><tenant><clients><client><occupier-type> | G82: Current | H82: When <building><units><unit><tenant><clients><client><subreference> = 1 and <occupier-type> = "Tenant" OR blank, send "Lead Tenant" otherwise When <building><units><unit><tenant><clients><client><subreference> <> 1 and <occupier-type> = "Tenant" OR blank, send "Sub Tenant" otherwise send direct | I82: <CMResidents><entry><CMContacts><entry><ContactType> | K82: OpportunityContactRole | L82: Role | M82: Refer to the Contact Role table and match <CMResidents><entry><CMContacts><entry><ContactType> with the Salesforce value. If no match found send null to Salesforce Note: Values configured in QuickConnect ref data SalesforceData list, key Mapping|ContactRole|[ContactType]
B83: Qube Buildings, Units and Tenants | C83: <building><units><unit><tenant><LeaseStartDate> | E83: date | H83: Format as dd-MM-yyyy | I83: <CMResidents><entry><OccupyDate> | J83: NOT MAPPED
B84: Qube Buildings, Units and Tenants | C84: <building><units><unit><tenant><LeaseEndDate> | E84: date | H84: Format as dd-MM-yyyy | I84: <CMResidents><entry><VoidDate> | J84: NOT MAPPED
B85: Qube Buildings, Units and Tenants | C85: <building><units><unit><tenure> | G85: AST | H85: Refer to the Tenure Type Description type table and match <building><units><unit><tenure> with the canonical code. Note: Values configured in QuickConnect ref data QubeCOA list, key Mapping|UnitTenureTypeDescription|[tenure] | I85: <CMResidents><entry><TenureTypeDesc> | J85: NOT MAPPED
B86: Qube Buildings, Units and Tenants | C86: <building><units><unit><tenant><name> | H86: Direct | I86: <CMResidents><entry><OccupantName> | K86: Opportunity | L86: Name | M86: Send [GREP User Title] + OccupantName + <EntityListing><UnitReference><entry><Description> Truncate to max 119 characters Note: [GREP User Title] default value ("GREP-CoA") configured in QuickConnect ref data SalesforceData list, key Mapping|GrepUserTitle
K87: Opportunity | L87: CloseDate | M87: Send current UK local date/time
K88: Opportunity | L88: MRI_Opportunity | M88: Send true
K89: Contract | L89: Status | M89: Send "Draft" Note: Value above configured in QuickConnect ref data SalesforceData list, key Mapping|StatusDraft

Sheet Unit Type
A1: Qube | B1: Canonical
A2: Advertising | B2: AD
A3: Allotment | B3: AL
A4: Bedsit | B4: BE
A5: Choose Type | B5: DU
A6: Commercial | B6: CM
A7: COMMERCIAL | B7: CM
A8: Det House | B8: DH
A9: DetBungalow | B9: DB
A10: DEVELOPMENT | B10: DEV
A11: Dummy | B11: DU
A12: End Terrace | B12: EH
... A49: Woodland | B49: WO

Sheet Unit Status Code
A1: Qube Unit Status Code | B1: Canonical | C1: Salesforce Live Unit Status Code | D1: Canonical Description
A2: UnderConstr | B2: OTUC | C2: Awaiting handover | D2: =VLOOKUP(A2,'Unit Status Description'!A:B,2,FALSE) -> Under Construction
A3: For Let | B3: OTFL | C3: Future Vacant | D3: =VLOOKUP(A3,'Unit Status Description'!A:B,2,FALSE) -> For Let
A4: Potent Vacant | B4: OTPV | C4: Future Vacant | D4: =VLOOKUP(A4,'Unit Status Description'!A:B,2,FALSE) -> Potentially Vacant
A5: Refresh | B5: OTRE | C5: Future Vacant | D5: =VLOOKUP(A5,'Unit Status Description'!A:B,2,FALSE) -> Refresh
A6: Tenanted | B6: OTTE | C6: Leased | D6: =VLOOKUP(A6,'Unit Status Description'!A:B,2,FALSE) -> Tenanted
A7: AwaitDecision | B7: SAWD | C7: Property to be sold | D7: =VLOOKUP(A7,'Unit Status Description'!A:B,2,FALSE) -> Sales - Await Decision
A8: Awaiting Rpt | B8: SFOR | C8: Property to be sold | D8: =VLOOKUP(A8,'Unit Status Description'!A:B,2,FALSE) -> For Sale
A9: AwaitingOffer | B9: SFOR | C9: Property to be sold | D9: =VLOOKUP(A9,'Unit Status Description'!A:B,2,FALSE) -> For Sale
A10: Completed | B10: SSEX | C10: Property to be sold | D10: =VLOOKUP(A10,'Unit Status Description'!A:B,2,FALSE) -> Sales-Contracts Exchanged
A11: Contracts Xch | B11: SSEX | C11: Property to be sold | D11: =VLOOKUP(A11,'Unit Status Description'!A:B,2,FALSE) -> Sales-Contracts Exchanged
A12: For Sale | B12: SFOR | C12: Property to be sold | D12: =VLOOKUP(A12,'Unit Status Description'!A:B,2,FALSE) -> For Sale
A13: GRIPSALE | B13: SOLD | C13: Property to be sold | D13: =VLOOKUP(A13,'Unit Status Description'!A:B,2,FALSE) -> Sales-Sold
... A25: Vacant | B25: OTNL | C25: Void | D25: =VLOOKUP(A25,'Unit Status Description'!A:B,2,FALSE) -> Not Lettable
A26: Dummy | B26: OTDU | D26: =VLOOKUP(A26,'Unit Status Description'!A:B,2,FALSE) -> Dummy
A27: NTU | B27: NTU | D27: =VLOOKUP(A27,'Unit Status Description'!A:B,2,FALSE) -> NTU

Sheet Unit Status Description
A1: Qube Unit Status Code | B1: Canonical Description
A2: AwaitDecision | B2: Sales - Await Decision
A3: Awaiting Rpt | B3: For Sale
A4: AwaitingOffer | B4: For Sale
A5: Completed | B5: Sales-Contracts Exchanged
A6: Contracts Xch | B6: Sales-Contracts Exchanged
A7: Dummy | B7: Dummy
A8: For Let | B8: For Let
A9: For Sale | B9: For Sale
A10: GRIPSALE | B10: Sales-Sold
A11: Insurance | B11: Not Lettable
A12: Negotiation | B12: Sales-Solicitor Instruction
... A27: Valuation | B27: For Sale

Sheet Tenant Status
A2: Tenant Status from Qube | B2: Canonical | C2: Tenant Status to FSI
A3: At Legal-Curr | B3: C | C3: ACTIVE
A4: At Legal-Prev | B4: O | C4: INACTIVE
A5: Current | B5: C | C5: ACTIVE
A6: FallThrough | B6: I | C6: INACTIVE
A7: Future | B7: N | C7: INACTIVE
A8: Holding Over | B8: O | C8: ACTIVE
A9: In Breach | B9: O | C9: ACTIVE
A10: Insurance | B10: I | C10: ACTIVE
A11: Negotiation | B11: A | C11: INACTIVE
A12: ntu | B12: I | C12: INACTIVE
A13: Payment Plan | B13: C | C13: ACTIVE
... A17: Transfer | B17: O | C17: INACTIVE

Sheet Tenure Type
A1: Qube Unit Tenure Type | B1: Canonical MRI Tenure Type | C1: Salesforce Tenure Type | D1: Canonical Description
A2: Aff Rent | B2: AFF | C2: Live Unit | D2: =VLOOKUP(A2,'Tenure Type Description'!A:B,2,FALSE) -> AST Affordable
A3: AHA (Agr) | B3: AGP | C3: Live Unit | D3: =VLOOKUP(A3,'Tenure Type Description'!A:B,2,FALSE) -> Agricultural Protected Statutory
A4: Assd PHA | B4: ASH | C4: Live Unit | D4: =VLOOKUP(A4,'Tenure Type Description'!A:B,2,FALSE) -> Assured-Paignton Housing Association
A5: Assd.Per | B5: ASS | C5: Live Unit | D5: =VLOOKUP(A5,'Tenure Type Description'!A:B,2,FALSE) -> ASSURED- Statutory Periodic
A6: Assured | B6: ASS | C6: Live Unit | D6: =VLOOKUP(A6,'Tenure Type Description'!A:B,2,FALSE) -> Assured
A7: AST | B7: AST | C7: Live Unit | D7: =VLOOKUP(A7,'Tenure Type Description'!A:B,2,FALSE) -> Assured Shorthold Tenancy
A8: AST Chc | B8: ACC | C8: Live Unit | D8: =VLOOKUP(A8,'Tenure Type Description'!A:B,2,FALSE) -> AST Church Commissioners
A9: AST KW | B9: ASK | C9: Live Unit | D9: =VLOOKUP(A9,'Tenure Type Description'!A:B,2,FALSE) -> AST-Keyworkers
A10: AST Per | B10: ASP | C10: Live Unit | D10: =VLOOKUP(A10,'Tenure Type Description'!A:B,2,FALSE) -> AST- Statutory Periodic
A11: AST-REF | B11: APH | C11: Live Unit | D11: =VLOOKUP(A11,'Tenure Type Description'!A:B,2,FALSE) -> AST-Paignton Housing Association
A12: ChiefRent | B12: CHR | C12: Live Unit | D12: =VLOOKUP(A12,'Tenure Type Description'!A:B,2,FALSE) -> Chief Rent
A13: CommLease | B13: COM | C13: Commercial Unit | D13: =VLOOKUP(A13,'Tenure Type Description'!A:B,2,FALSE) -> Commercial Lease
... A51: VAC-SR | B51: VAC | C51: Live Unit | D51: =VLOOKUP(A51,'Tenure Type Description'!A:B,2,FALSE) -> Vacant

Sheet Tenure Type Description
A1: Qube Unit Tenure Type | B1: Canonical Description
A2: Aff Rent | B2: AST Affordable
A3: AHA (Agr) | B3: Agricultural Protected Statutory
A4: Assd PHA | B4: Assured-Paignton Housing Association
A5: Assd.Per | B5: ASSURED- Statutory Periodic
A6: Assured | B6: Assured
A7: AST | B7: Assured Shorthold Tenancy
A8: AST Chc | B8: AST Church Commissioners
A9: AST KW | B9: AST-Keyworkers
A10: AST Per | B10: AST- Statutory Periodic
A11: AST-REF | B11: AST-Paignton Housing Association
A12: ChiefRent | B12: Chief Rent
... A52: VAC-SR | B52: Vacant

Sheet CM Tenure Type
A1: Qube Unit Tenure Type | B1: Canonical MRI Tenure Type | C1: Salesforce CM Tenure Type
A2: Aff Rent | B2: AFF | C2: Residential
A3: AHA (Agr) | B3: AGP | C3: Residential
A4: Assd PHA | B4: ASH | C4: Residential
A5: Assd.Per | B5: ASS | C5: Residential
A6: Assured | B6: ASS | C6: Residential
A7: AST | B7: AST | C7: Residential
A8: AST Chc | B8: ACC | C8: Residential
A9: AST KW | B9: ASK | C9: Residential
A10: AST Per | B10: ASP | C10: Residential
A11: AST-REF | B11: APH | C11: Residential
A12: ChiefRent | B12: CHR | C12: Residential
... A51: VAC-SR | B51: VAC | C51: Commercial

Sheet Contact Status
A1: Tenant Status from Qube | B1: Canonical | C1: Tenant Status to FSI
A2: Active | B2: C | C2: ACTIVE
A3: Not Active | B3: I | C3: INACTIVE
A4: Future | B4: F | C4: Not sent to FSI

Sheet Property Type
A1: Property Type | B1: Canonical Entity Type
A2: RESIDENTIAL | B2: PRO
A3: AGRICULT. | B3: PRO
A4: COMMERCIAL | B4: PRO
A5: MIXED USE | B5: PRO
A6: Mid Terrace | B6: PRO
A7: Det House | B7: PRO
A8: S/D House | B8: PRO
A9: End Terrace | B9: PRO
A10: Flat PB | B10: PRO
A11: Flat Conv | B11: PRO
A12: SOCIALHOUSE | B12: PRO
... A20: No prop_type | B20: COR

Sheet Agreement Type
A1: Qube Unit Tenure Type | B1: Canonical MRI Tenure Type | C1: Salesforce Agreement Type
A2: Aff Rent | B2: AFF | C2: AST (Affordable)
A3: AHA (Agr) | B3: AGP | C3: Occupation Licence
A4: Assd PHA | B4: ASH | C4: AST (Affordable)
A5: Assd.Per | B5: ASS | C5: AST (Affordable)
A6: Assured | B6: ASS | C6: AST (Affordable)
A7: AST | B7: AST | C7: AST
A8: AST Chc | B8: ACC | C8: AST
A9: AST KW | B9: ASK | C9: AST
A10: AST Per | B10: ASP | C10: AST
A11: AST-REF | B11: APH | C11: AST (Affordable)
A12: ChiefRent | B12: CHR
A13: CommLease | B13: COM | C13: Other
A14: Comm-Let | B14: CML | C14: Other
A15: CommLic | B15: CLI | C15: Other
A16: Comp-Let | B16: COL | C16: Non-Housing (Company)
A17: CT SerLic | B17: SLC | C17: Occupation Licence
A18: CT SerTen | B18: STC | C18: Occupation Licence
A19: DMR-AST | B19: DMR | C19: AST (Affordable)
A20: Dummy | B20: DUM
A21: EstateChg | B21: EST
A22: FBT(Farm) | B22: AGA
A23: FixedRent | B23: FIX | C23: Other
A24: FREEHOLD | B24: VAC
A25: Gr Lets | B25: IMR | C25: AST (Affordable)
A26: GRIPSALE | B26: GRI
A27: Grnd Rent | B27: GRT | C27: Other
A28: Insurance | B28: APH | C28: AST (Affordable)
A29: Land | B29: LIC | C29: Other
A30: LEASEHOLD | B30: VAC
A31: Licence | B31: LIC | C31: Other
A32: Live Work | B32: ALW | C32: Live Work
A33: MOD | B33: TRI | C33: Other
A34: MORTGAGE | B34: MRT
A35: NHA | B35: NHA | C35: Non-Housing (Company)
A36: Nil GR | B36: NGR | C36: Other
A37: No Tenure | B37: DUM
A38: Regulated | B38: REG | C38: AST (Affordable)
A39: Reversion | B39: CHA | C39: AST (Affordable)
A40: Services | B40: SER
A41: Sh Owner | B41: SHO | C41: Other
A42: Sold | B42: SOL | C42: Other
A43: Unregd | B43: UNR | C43: Other
A44: Vac-A | B44: VAC
A45: Vacant | B45: VAC
A46: Vac-C | B46: VAC
A47: Vac-F | B47: VAC
A48: VAC-MW | B48: VAC
A49: Vac-R | B49: VAC
A50: Vac-S | B50: VAC
A51: VAC-SR | B51: VAC
B52: Default | C52: Other

Sheet Bedrooms
A1: Canonical Value | B1: Salesforce Value
A2: 1 | B2: 1 Bedroom
A3: 2 | B3: 2 Bedrooms
A4: 3 | B4: 3 Bedrooms
A5: 4 | B5: 4 Bedrooms
A6: 5 | B6: 5 Bedrooms
A7: 6 | B7: 6 Bedrooms
A8: 7 | B8: 7 Bedrooms

Sheet Owner ID
A1: Qube Legal Owner Reference | B1: Canonical Owner ID | C1: Salesforce Owner ID
A2: [not specified] | B2: [not specified] | C2: GRML
A3: BEK | B3: BEK | C3: GTRUST
A4: BJN | B4: BJN | C4: PEARL
A5: BJT | B5: BJT | C5: PEARL
A6: BQG | B6: BQG | C6: GRML
A7: HAD | B7: HAD | C7: PEARL
A8: TAB | B8: TAB | C8: VESTA
A9: URE | B9: URE | C9: GRIPU

Sheet Contact Role
A1: Qube | B1: Canonical | C1: Salesforce
A2: <client><occupiertype> = "Tenant" and <client><subreference> =1 | B2: Lead Tenant | C2: 1 Lead Tenant
A3: <client><occupiertype> = "Tenant" and <client><subreference> <>1 | B3: Sub Tenant | C3: 2 Tenant
A4: Guarantor | B4: Guarantor | C4: 3 Guarantor
A5: Relevant Person | B5: Relevant Person | C5: 5 Relevant Person
A6: Permitted Occupier | B6: Permitted Occupier | C6: 4 Permitted Occupier

Sheet MRI to Salesforce - Update
A1: Data Mapping | B1: CP-CORE-02/CP-CORE-04
A2: Sending Interface system | B2: MRI
A3: Outbound Data Structure | B3: XML
A4: Receiving Interface system 1 | B4: Salesforce
A5: Inbound Data Structure 1 | B5: JSON
A6: Title | B6: ChartsOfAccountsUpserted/NominalUpserted - Update Customer
A7: Source - MRI | C7: Global/Entity | D7: Mandatory/Optional | E7: XML Element / Attribute | F7: Mandatory/Optional | G7: Type | H7: Size | I7: Sample Darta | J7: Transformation rule/logic | K7: Destination 1 - Salesforce | M7: Mandatory/Optional | N7: Data Type | O7: Length
A8: Table | B8: Source API | K8: Destination API | L8: Field Name
A9: Tenant Data - CM
M16: Mandatory
A19: Tenant Data - RM
M26: Mandatory
