Workbook

Sheet IL to HORIZON
A2: Interface code | D2: 1.1.2 & 1.2.2
A3: Destination system | D3: HORIZON
A4: Message Name
A5: Input Type (File/XML/Idoc/Others)?
A6: Fixed, Delimited or Tagged?
A7: Level | B7: Table Name | C7: Field Name | D7: Parent Table | E7: Mandatory / Optional | F7: Data Type / Size | G7: Format | H7: Description
C9: TNNT_REF | E9: Mandatory | F9: String(8) | H9: Tenant Ref | I9: y
C10: TNNT_LEVEL | E10: Mandatory | F10: String(3) | H10: Level | I10: y
C11: TNNT_GROUP_TNNT_REF | E11: Optional | F11: String(8) | H11: Group Tenant Ref | I11: Parent tenant id | J11: Need to be restricted to 3 levels in NAV
C12: TNNT_TRADE_NAME | E12: Optional | F12: String(60) | H12: Trade Name | I12: y
C13: TNNT_ADDR_REF | E13: Mandatory | F13: String(8) | H13: Address Ref | I13: default to customer ref
C14: TNNT_VALID_DEMANDS | E14: Mandatory | F14: String(1) | H14: Valid Demands | I14: Default Always B
C15: TNNT_TYPE_CODE | E15: Optional | F15: String(3) | H15: Type Code | I15: y
C16: TNNT_STATUS_CODE | E16: Optional | F16: String(3) | H16: Status Code | I16: y
C17: TNNT_USER_CODE | E17: Optional | F17: String(3) | H17: User Code | I17: not used
C18: TNNT_CUR_CODE | E18: Mandatory | F18: String(3) | H18: Currency Code | I18: y
C19: TNNT_LEGAL_NAME | E19: Optional | F19: String(60) | H19: Legal Name | I19: not used
C20: TNNT_EMAIL_INVOICE_FLAG | E20: Optional | F20: String(1) | H20: Email Invoice Flag | I20: defaulted based on email address
C21: TNNT_AGENT_CODE | E21: Optional | F21: String(3) | H21: Agent Code | I21: not used
C22: TNNT_DOC_LAN_CODE | E22: Optional | F22: String(3) | H22: Doc Lan Code | I22: default to English
C23: TNNT_TERI_CODE | E23: Optional | F23: String(3) | H23: Teri Code | I23: not used
... C52: TNNT_PRINT_RCPT | E52: Optional | F52: String(1) | H52: Print Rcpt | I52: not used
E53: Optional | F53: 256 | H53: Full legal name | I53: new field
C54: ADDR_REF | E54: Mandatory | F54: String(8) | H54: Address Ref | I54: default to customer ref
C55: ADDR_NAME | E55: Mandatory | F55: String(60) | H55: Name | I55: y
C56: ADDR_PROP_NAME | E56: Optional | F56: String(60) | H56: Property Name | I56: y
C57: ADDR_L1 | E57: Optional | F57: String(30) | H57: Address L1 | I57: y
C58: ADDR_L2 | E58: Optional | F58: String(30) | H58: Address L2 | I58: y
C59: ADDR_TOWN | E59: Optional | F59: String(30) | H59: Town | I59: y
C60: ADDR_COUNTY | E60: Optional | F60: String(30) | H60: County | I60: y
C61: ADDR_POSTCODE | E61: Optional | F61: String(12) | H61: Postcode | I61: y
C62: ADDR_COUNTRY | E62: Optional | F62: String(30) | H62: Country | I62: y
C63: ADDR_PHONE | E63: Optional | F63: String(20) | H63: Phone | I63: y
C64: ADDR_EMAIL | E64: Optional | F64: String(60) | H64: Email | I64: y
C65: ADDR_FAX | E65: Optional | F65: String(20) | H65: Address Fax | I65: not used
... C71: ADDR_COMP_REG_NUM | E71: Optional | F71: String(25) | H71: Operation Reg Num | I71: not used
E72: Optional | H72: Address L3 | I72: Add new 4th line of address
C73: TNAC_TNNT_REF | E73: Mandatory | F73: String(8) | H73: Tenant Ref | I73: y
C74: TNAC_REF | E74: Mandatory | F74: String(8) | H74: Tnac Ref | I74: HZN autogenerate
C75: TNAC_DESC | E75: Optional | F75: String(30) | H75: Description | I75: y
C76: TNAC_DEB_STATUS_CODE | E76: Mandatory | F76: String(3) | H76: Deb Status Code | I76: auto Creation with 001, Manual update in Horizon?
C77: TNAC_AC_NUM | E77: Optional | F77: String(36) | H77: Account Num | I77: y
C78: TNAC_AC_NAME | E78: Optional | F78: String(30) | H78: Account Name | I78: y
C79: TNAC_BANK_SORT_CODE | E79: Optional | F79: String(15) | H79: Bank Sort Code | I79: y
C80: TNAC_EFT_CODE | E80: Optional | F80: String(3) | H80: EFT Collection Code | J80: need to identify where data to be stored in NAV?
C81: TNAC_BANK_NAME | E81: Optional | F81: String(60) | H81: Bank Name | I81: y
C82: TNAC_BANK_ADDR_L1 | E82: Optional | F82: String(30) | H82: Bank Address L1 | I82: y
C83: TNAC_BANK_ADDR_L2 | E83: Optional | F83: String(30) | H83: Bank Address L2 | I83: y
C84: TNAC_BANK_TOWN | E84: Optional | F84: String(30) | H84: Bank Town | I84: y
C85: TNAC_BANK_COUNTY | E85: Optional | F85: String(30) | H85: Bank County | I85: y
C86: TNAC_BANK_POSTCODE | E86: Optional | F86: String(12) | H86: Bank Postcode | I86: y
C87: TNAC_COUNTRY | E87: Optional | F87: String(30) | H87: Country | I87: y
C88: TNAC_SWIFT_BIC_NUMBER | E88: Optional | F88: String(30) | H88: Swift Bic Number | I88: y
C89: TNAC_IBAN_NUMBER | E89: Optional | F89: String(34) | H89: Iban Number | I89: y
C90: TNAC_EFT_REFUND_CODE | E90: Optional | F90: String(3) | H90: EFT Refund Code | J90: need to identify where data to be stored in NAV?
C91: ADUS_CODE | E91: Mandatory | F91: String(3) | H91: Code | I91: y
C92: ADUS_REF | E92: Mandatory | F92: String(8) | H92: Adus Ref
C93: ADUS_ADDR_REF | E93: Mandatory | F93: String(8) | H93: Address Ref | I93: y

Sheet IL Data Mapping #WORKING#
A1: Data Mapping
A2: Sending Interface system | B2: NAV
A3: Outbound Data Structure
A4: Receiving Interface system | B4: HORIZON
A5: Inbound Data Structure
A6: Title
A7: Source | D7: Transformation rule/logic | E7: Destination
A8: Table | B8: Field Name | E8: Table | F8: Field Name
A9: Customer | B9: No. | C9: Code20 | D9: Direct | F9: TNNT_REF | H9: =IF(F9="","",VLOOKUP(F9,'IL to HORIZON'!$C$9:$F$93,4,FALSE)) -> String(8)
A10: Customer | B10: Name | C10: Text50 | D10: direct | F10: TNNT_TRADE_NAME | G10: ADDR_NAME | H10: =IF(F10="","",VLOOKUP(F10,'IL to HORIZON'!$C$9:$F$93,4,FALSE)) -> String(60) | I10: =IF(G10="","",VLOOKUP(G10,'IL to HORIZON'!$C$9:$F$93,4,FALSE)) -> String(60)
A11: Customer | B11: Search Name | C11: Code50 | H11: =IF(F11="","",VLOOKUP(F11,'IL to HORIZON'!$C$9:$F$93,4,FALSE))
A12: Customer | B12: Name 2 | C12: Text50 | H12: =IF(F12="","",VLOOKUP(F12,'IL to HORIZON'!$C$9:$F$93,4,FALSE))
A13: Customer | B13: Address | C13: Text50 | D13: Direct | F13: ADDR_PROP_NAME | H13: =IF(F13="","",VLOOKUP(F13,'IL to HORIZON'!$C$9:$F$93,4,FALSE)) -> String(60)
A14: Customer | B14: Address 2 | C14: Text50 | D14: Direct | F14: ADDR_L1 | H14: =IF(F14="","",VLOOKUP(F14,'IL to HORIZON'!$C$9:$F$93,4,FALSE)) -> String(30)
A15: Customer | B15: City | C15: Text30 | D15: Direct | F15: ADDR_TOWN | H15: =IF(F15="","",VLOOKUP(F15,'IL to HORIZON'!$C$9:$F$93,4,FALSE)) -> String(30)
A16: Customer | B16: Contact | C16: Text50 | H16: =IF(F16="","",VLOOKUP(F16,'IL to HORIZON'!$C$9:$F$93,4,FALSE))
A17: Customer | B17: Phone No. | C17: Text30 | D17: direct | F17: ADDR_PHONE | H17: =IF(F17="","",VLOOKUP(F17,'IL to HORIZON'!$C$9:$F$93,4,FALSE)) -> String(20)
A18: Customer | B18: Telex No. | C18: Text20 | H18: =IF(F18="","",VLOOKUP(F18,'IL to HORIZON'!$C$9:$F$93,4,FALSE))
A19: Customer | B19: Document Sending Profile | C19: Code20 | H19: =IF(F19="","",VLOOKUP(F19,'IL to HORIZON'!$C$9:$F$93,4,FALSE))
A20: Customer | B20: Our Account No. | C20: Text20 | H20: =IF(F20="","",VLOOKUP(F20,'IL to HORIZON'!$C$9:$F$93,4,FALSE))
A21: Customer | B21: Territory Code | C21: Code10 | H21: =IF(F21="","",VLOOKUP(F21,'IL to HORIZON'!$C$9:$F$93,4,FALSE))
A22: Customer | B22: Global Dimension 1 Code | C22: Code20 | H22: =IF(F22="","",VLOOKUP(F22,'IL to HORIZON'!$C$9:$F$93,4,FALSE))
A23: Customer | B23: Global Dimension 2 Code | C23: Code20 | H23: =IF(F23="","",VLOOKUP(F23,'IL to HORIZON'!$C$9:$F$93,4,FALSE))
A24: Customer | B24: Chain Name | C24: Code10 | H24: =IF(F24="","",VLOOKUP(F24,'IL to HORIZON'!$C$9:$F$93,4,FALSE))
A25: Customer | B25: Budgeted Amount | C25: Decimal | H25: =IF(F25="","",VLOOKUP(F25,'IL to HORIZON'!$C$9:$F$93,4,FALSE))
A26: Customer | B26: Credit Limit (LCY) | C26: Decimal | H26: =IF(F26="","",VLOOKUP(F26,'IL to HORIZON'!$C$9:$F$93,4,FALSE))
A27: Customer | B27: Customer Posting Group | C27: Code10 | D27: mapping code(10) to code(3) | F27: TNNT_TYPE_CODE | H27: =IF(F27="","",VLOOKUP(F27,'IL to HORIZON'!$C$9:$F$93,4,FALSE)) -> String(3) | I27: do these NAV codes align to HZN codes??
A28: Customer | B28: Currency Code | C28: Code10 | D28: map NULL = GBP otherwise direct if same 3 char code | F28: TNNT_CUR_CODE | H28: =IF(F28="","",VLOOKUP(F28,'IL to HORIZON'!$C$9:$F$93,4,FALSE)) -> String(3)
A29: Customer | B29: Customer Price Group | C29: Code10 | H29: =IF(F29="","",VLOOKUP(F29,'IL to HORIZON'!$C$9:$F$93,4,FALSE))
A30: Customer | B30: Language Code | C30: Code10 | H30: =IF(F30="","",VLOOKUP(F30,'IL to HORIZON'!$C$9:$F$93,4,FALSE))
A31: Customer | B31: Statistics Group | C31: Integer | H31: =IF(F31="","",VLOOKUP(F31,'IL to HORIZON'!$C$9:$F$93,4,FALSE))
A32: Customer | B32: Payment Terms Code | C32: Code10 | D32: map Code 10 to number of days | F32: TNNT_INV_DUE_DAYS | H32: =IF(F32="","",VLOOKUP(F32,'IL to HORIZON'!$C$9:$F$93,4,FALSE)) -> Number(3)
A33: Customer | B33: Fin. Charge Terms Code | C33: Code10 | H33: =IF(F33="","",VLOOKUP(F33,'IL to HORIZON'!$C$9:$F$93,4,FALSE))
A34: Customer | B34: Salesperson Code | C34: Code10 | H34: =IF(F34="","",VLOOKUP(F34,'IL to HORIZON'!$C$9:$F$93,4,FALSE))
A35: Customer | B35: Shipment Method Code | C35: Code10 | H35: =IF(F35="","",VLOOKUP(F35,'IL to HORIZON'!$C$9:$F$93,4,FALSE))
A36: Customer | B36: Shipping Agent Code | C36: Code10 | H36: =IF(F36="","",VLOOKUP(F36,'IL to HORIZON'!$C$9:$F$93,4,FALSE))
A37: Customer | B37: Place of Export | C37: Code20 | H37: =IF(F37="","",VLOOKUP(F37,'IL to HORIZON'!$C$9:$F$93,4,FALSE))
A38: Customer | B38: Invoice Disc. Code | C38: Code20 | H38: =IF(F38="","",VLOOKUP(F38,'IL to HORIZON'!$C$9:$F$93,4,FALSE))
A39: Customer | B39: Customer Disc. Group | C39: Code20 | H39: =IF(F39="","",VLOOKUP(F39,'IL to HORIZON'!$C$9:$F$93,4,FALSE))
A40: Customer | B40: Country/Region Code | C40: Code10 | D40: both using ISO 2 char code | F40: ADDR_COUNTRY | H40: =IF(F40="","",VLOOKUP(F40,'IL to HORIZON'!$C$9:$F$93,4,FALSE)) -> String(30)
A41: Customer | B41: Collection Method | C41: Code20 | H41: =IF(F41="","",VLOOKUP(F41,'IL to HORIZON'!$C$9:$F$93,4,FALSE))
A42: Customer | B42: Amount | C42: Decimal | H42: =IF(F42="","",VLOOKUP(F42,'IL to HORIZON'!$C$9:$F$93,4,FALSE))
A43: Customer | B43: Comment | C43: Boolean | H43: =IF(F43="","",VLOOKUP(F43,'IL to HORIZON'!$C$9:$F$93,4,FALSE))
A44: Customer | B44: Blocked | C44: Option | D44: Blocked/not blocked | H44: =IF(F44="","",VLOOKUP(F44,'IL to HORIZON'!$C$9:$F$93,4,FALSE))
A45: Customer | B45: Invoice Copies | C45: Integer | H45: =IF(F45="","",VLOOKUP(F45,'IL to HORIZON'!$C$9:$F$93,4,FALSE)) | I45: Question for JA
A46: Customer | B46: Last Statement No. | C46: Integer | H46: =IF(F46="","",VLOOKUP(F46,'IL to HORIZON'!$C$9:$F$93,4,FALSE))
A47: Customer | B47: Print Statements | C47: Boolean | H47: =IF(F47="","",VLOOKUP(F47,'IL to HORIZON'!$C$9:$F$93,4,FALSE))
A48: Customer | B48: Bill-to Customer No. | C48: Code20 | H48: =IF(F48="","",VLOOKUP(F48,'IL to HORIZON'!$C$9:$F$93,4,FALSE))
A49: Customer | B49: Priority | C49: Integer | H49: =IF(F49="","",VLOOKUP(F49,'IL to HORIZON'!$C$9:$F$93,4,FALSE))
A50: Customer | B50: Payment Method Code | C50: Code10 | H50: =IF(F50="","",VLOOKUP(F50,'IL to HORIZON'!$C$9:$F$93,4,FALSE))
A51: Customer | B51: Last Date Modified | C51: Date | H51: =IF(F51="","",VLOOKUP(F51,'IL to HORIZON'!$C$9:$F$93,4,FALSE))
A52: Customer | B52: Date Filter | C52: Date | H52: =IF(F52="","",VLOOKUP(F52,'IL to HORIZON'!$C$9:$F$93,4,FALSE))
A53: Customer | B53: Global Dimension 1 Filter | C53: Code20 | H53: =IF(F53="","",VLOOKUP(F53,'IL to HORIZON'!$C$9:$F$93,4,FALSE))
A54: Customer | B54: Global Dimension 2 Filter | C54: Code20 | H54: =IF(F54="","",VLOOKUP(F54,'IL to HORIZON'!$C$9:$F$93,4,FALSE))
A55: Customer | B55: Balance | C55: Decimal | H55: =IF(F55="","",VLOOKUP(F55,'IL to HORIZON'!$C$9:$F$93,4,FALSE))
A56: Customer | B56: Balance (LCY) | C56: Decimal | H56: =IF(F56="","",VLOOKUP(F56,'IL to HORIZON'!$C$9:$F$93,4,FALSE))
A57: Customer | B57: Net Change | C57: Decimal | H57: =IF(F57="","",VLOOKUP(F57,'IL to HORIZON'!$C$9:$F$93,4,FALSE))
... A79: Customer | B79: Telex Answer Back | C79: Text20 | H79: =IF(F79="","",VLOOKUP(F79,'IL to HORIZON'!$C$9:$F$93,4,FALSE))
A80: Customer | B80: VAT Registration No. | C80: Text20 | D80: Direct | F80: ADDR_VAT_NUM | H80: =IF(F80="","",VLOOKUP(F80,'IL to HORIZON'!$C$9:$F$93,4,FALSE)) -> String(25)
A81: Customer | B81: Combine Shipments | C81: Boolean | H81: =IF(F81="","",VLOOKUP(F81,'IL to HORIZON'!$C$9:$F$93,4,FALSE))
A82: Customer | B82: Gen. Bus. Posting Group | C82: Code10 | H82: =IF(F82="","",VLOOKUP(F82,'IL to HORIZON'!$C$9:$F$93,4,FALSE))
A83: Customer | B83: Picture | C83: BLOB | H83: =IF(F83="","",VLOOKUP(F83,'IL to HORIZON'!$C$9:$F$93,4,FALSE))
A84: Customer | B84: GLN | C84: Code13 | H84: =IF(F84="","",VLOOKUP(F84,'IL to HORIZON'!$C$9:$F$93,4,FALSE))
A85: Customer | B85: Post Code | C85: Code20 | D85: Direct | F85: ADDR_POSTCODE | H85: =IF(F85="","",VLOOKUP(F85,'IL to HORIZON'!$C$9:$F$93,4,FALSE)) -> String(12)
A86: Customer | B86: County | C86: Text30 | D86: NAV free text to be validated, needs to match value list from HZN | F86: ADDR_COUNTY | H86: =IF(F86="","",VLOOKUP(F86,'IL to HORIZON'!$C$9:$F$93,4,FALSE)) -> String(30)
A87: Customer | B87: Debit Amount | C87: Decimal | H87: =IF(F87="","",VLOOKUP(F87,'IL to HORIZON'!$C$9:$F$93,4,FALSE))
A88: Customer | B88: Credit Amount | C88: Decimal | H88: =IF(F88="","",VLOOKUP(F88,'IL to HORIZON'!$C$9:$F$93,4,FALSE))
A89: Customer | B89: Debit Amount (LCY) | C89: Decimal | H89: =IF(F89="","",VLOOKUP(F89,'IL to HORIZON'!$C$9:$F$93,4,FALSE))
A90: Customer | B90: Credit Amount (LCY) | C90: Decimal | H90: =IF(F90="","",VLOOKUP(F90,'IL to HORIZON'!$C$9:$F$93,4,FALSE))
A91: Customer | B91: E-Mail | C91: Text80 | D91: direct | F91: ADDR_EMAIL | H91: =IF(F91="","",VLOOKUP(F91,'IL to HORIZON'!$C$9:$F$93,4,FALSE)) -> String(60)
A92: Customer | B92: Home Page | C92: Text80 | D92: Direct | F92: ADDR_WEB | H92: =IF(F92="","",VLOOKUP(F92,'IL to HORIZON'!$C$9:$F$93,4,FALSE)) -> String(60)
A93: Customer | B93: Reminder Terms Code | C93: Code10 | H93: =IF(F93="","",VLOOKUP(F93,'IL to HORIZON'!$C$9:$F$93,4,FALSE))
A94: Customer | B94: Reminder Amounts | C94: Decimal | H94: =IF(F94="","",VLOOKUP(F94,'IL to HORIZON'!$C$9:$F$93,4,FALSE))
A95: Customer | B95: Reminder Amounts (LCY) | C95: Decimal | H95: =IF(F95="","",VLOOKUP(F95,'IL to HORIZON'!$C$9:$F$93,4,FALSE))
A96: Customer | B96: No. Series | C96: Code10 | H96: =IF(F96="","",VLOOKUP(F96,'IL to HORIZON'!$C$9:$F$93,4,FALSE))
A97: Customer | B97: Tax Area Code | C97: Code20 | H97: =IF(F97="","",VLOOKUP(F97,'IL to HORIZON'!$C$9:$F$93,4,FALSE))
A98: Customer | B98: Tax Liable | C98: Boolean | H98: =IF(F98="","",VLOOKUP(F98,'IL to HORIZON'!$C$9:$F$93,4,FALSE))
A99: Customer | B99: VAT Bus. Posting Group | C99: Code10 | H99: =IF(F99="","",VLOOKUP(F99,'IL to HORIZON'!$C$9:$F$93,4,FALSE))
A100: Customer | B100: Currency Filter | C100: Code10 | H100: =IF(F100="","",VLOOKUP(F100,'IL to HORIZON'!$C$9:$F$93,4,FALSE))
A101: Customer | B101: Outstanding Orders (LCY) | C101: Decimal | H101: =IF(F101="","",VLOOKUP(F101,'IL to HORIZON'!$C$9:$F$93,4,FALSE))
A102: Customer | B102: Shipped Not Invoiced (LCY) | C102: Decimal | H102: =IF(F102="","",VLOOKUP(F102,'IL to HORIZON'!$C$9:$F$93,4,FALSE))
A103: Customer | B103: Reserve | C103: Option | H103: =IF(F103="","",VLOOKUP(F103,'IL to HORIZON'!$C$9:$F$93,4,FALSE))
A104: Customer | B104: Block Payment Tolerance | C104: Boolean | H104: =IF(F104="","",VLOOKUP(F104,'IL to HORIZON'!$C$9:$F$93,4,FALSE))
... A156: Customer | B156: Oracle Account No. | C156: Code20 | H156: =IF(F156="","",VLOOKUP(F156,'IL to HORIZON'!$C$9:$F$93,4,FALSE))
A157: Customer | B157: Address 3 | C157: Text30 | D157: direct | F157: ADDR_L2 | H157: =IF(F157="","",VLOOKUP(F157,'IL to HORIZON'!$C$9:$F$93,4,FALSE)) -> String(30)
A158: Customer | B158: Address 4 | C158: Text30 | D158: direct | F158: Address line 4 | H158: =IF(F158="","",VLOOKUP(F158,'IL to HORIZON'!$C$9:$F$93,4,FALSE)) -> #N/A | I158: to be created
A159: Customer | B159: Status | C159: Option | D159: Active/non active map to TNC/TFS (current/Former) | F159: TNNT_STATUS_CODE | H159: =IF(F159="","",VLOOKUP(F159,'IL to HORIZON'!$C$9:$F$93,4,FALSE)) -> String(3)
A160: Customer | B160: Billing Frequency | C160: Code20 | F160: NEW FIELD | H160: =IF(F160="","",VLOOKUP(F160,'IL to HORIZON'!$C$9:$F$93,4,FALSE)) -> #N/A | I160: Need new field in Horizon for this
A161: Customer | B161: Hierarchy Type | C161: Option | H161: =IF(F161="","",VLOOKUP(F161,'IL to HORIZON'!$C$9:$F$93,4,FALSE))
A162: Customer | B162: Parent Customer No. | C162: Code20 | D162: direct | F162: TNNT_GROUP_TNNT_REF | H162: =IF(F162="","",VLOOKUP(F162,'IL to HORIZON'!$C$9:$F$93,4,FALSE)) -> String(8)
A163: Customer | B163: Required Credit Check | C163: Boolean | H163: =IF(F163="","",VLOOKUP(F163,'IL to HORIZON'!$C$9:$F$93,4,FALSE))
A164: Customer | B164: Debt Provision Level | C164: Option | H164: =IF(F164="","",VLOOKUP(F164,'IL to HORIZON'!$C$9:$F$93,4,FALSE))
A165: Customer | B165: Vendor No. | C165: Code20 | H165: =IF(F165="","",VLOOKUP(F165,'IL to HORIZON'!$C$9:$F$93,4,FALSE))
D166: direct | F166: TNNT_LEVEL | H166: =IF(F166="","",VLOOKUP(F166,'IL to HORIZON'!$C$9:$F$93,4,FALSE)) -> String(3) | I166: new field to be created in nav
A167: Customer Bank Account | B167: Customer No. | C167: Code20 | D167: direct | F167: TNAC_TNNT_REF | H167: =IF(F167="","",VLOOKUP(F167,'IL to HORIZON'!$C$9:$F$93,4,FALSE)) -> String(8)
A168: Customer Bank Account | B168: Code | C168: Code20 | H168: =IF(F168="","",VLOOKUP(F168,'IL to HORIZON'!$C$9:$F$93,4,FALSE))
A169: Customer Bank Account | B169: Name | C169: Text50 | D169: direct | F169: TNAC_AC_NAME | H169: =IF(F169="","",VLOOKUP(F169,'IL to HORIZON'!$C$9:$F$93,4,FALSE)) -> String(30)
A170: Customer Bank Account | B170: Name 2 | C170: Text50 | D170: direct | F170: TNAC_BANK_NAME | H170: =IF(F170="","",VLOOKUP(F170,'IL to HORIZON'!$C$9:$F$93,4,FALSE)) -> String(60)
A171: Customer Bank Account | B171: Address | C171: Text50 | D171: direct | F171: TNAC_BANK_ADDR_L1 | H171: =IF(F171="","",VLOOKUP(F171,'IL to HORIZON'!$C$9:$F$93,4,FALSE)) -> String(30)
A172: Customer Bank Account | B172: Address 2 | C172: Text50 | D172: direct | F172: TNAC_BANK_ADDR_L2 | H172: =IF(F172="","",VLOOKUP(F172,'IL to HORIZON'!$C$9:$F$93,4,FALSE)) -> String(30)
...

Sheet Sheet1
A1: Field | B1: Description/Usage | C1: Comment
A2: Info_1 | B2: Trading as | C2: This would seem to be the logical place to store Commercial company number. 300 active child records (tenants) have been populated with data in Qube but very little of it seems to relate to "Trading As" reference so I am sure if we needed to we could leave this data on the non- commercial units or move it to one of the other fields mentioned below
A3: Info_2 | B3: Guarantor | C3: Indicates if a guarantor exists-avoiding the need for users to drill down into tenant data tab to obtain this information
A4: info_s1 | B4: Fixed increase | C4: Holds details of fixed increase and date. This data should come over from Salesforce for the commercial leases if possible but at the moment the integration is not designed to pass this data -therefore for now it would have to be input into Qube manually if required to be held there
A5: Info_s2 | B5: Rent concessions | C5: Used in the past to hold details of any rent concessions. Probably not being used now that the information is held on Salesforce other than for leases that do not pass through Salesforce. This would be another field where the information could feed from Salesforce but where the current integration does not cater for this
A6: Info_s3 | B6: Payment Plans | C6: Indicates if a tenant account is subject to a Payment Plan. Used by Credit Control Team and for Finance Reporting
A7: Info_s4 | B7: Prepaid Rent | C7: Indicates whether a tenant account includes any pre paid rent. Used for finance reporting.
A8: Info_s5 | B8: No of occupants | C8: Stores the number of occupants. Not really used now but holds legacy data.
A9: Info_s6 | B9: Salesforce Contact id | C9: Stores the Salesforce 18 digit contact id to link the Salesforce contact with the Qube child tenant

Sheet Version History
A1: Date | B1: Version | C1: Author | D1: Comments
A2: 44503 | B2: 1.0 | C2: Phil Cullum | D2: Created
A3: 11/112021 | B3: 1.0 | C3: Phil Cullum | D3: Updated to match Tenancy, Unit and Client APIs provided by Qube
A4: 44523 | B4: 1.1 | C4: Phil Cullum | D4: Added canonical message fields
A5: 44568 | B5: 1.2 | C5: Phil Cullum | D5: Added missing transformation logic for client phone numbers
A6: 44580 | B6: 1.3 | C6: Phil Cullum | D6: Removed transformation logic for client phone numbers, no longer required
B7: 1.4 | C7: Phil Cullum | D7: Removed tenancy end date mapping as requested by Anita/Scott
B8: 1.5 | C8: Phil Cullum | D8: Changed Salesforce move in date to map to tenancy start date
A9: 45042 | B9: 1.6 | C9: Phil Cullum | D9: Updated to match updated Qube v12 API and new Unit update requirements
A10: 45204 | B10: 1.7 | C10: Phil Cullum | D10: Update after review by Deb Stein
A11: 45070 | B11: 1.8 | C11: Phil Cullum | D11: Updated with lease-percentage mapping
A12: 45082 | B12: 1.9 | C12: Phil Cullum | D12: Agreement type and tenant-type mapping changes
A13: 45092 | B13: 1.10 | C13: Phil Cullum | D13: Added tenant-type mapping to child tenant elements
A14: 45104 | B14: 1.11 | C14: Phil Cullum | D14: Updated with Opportunity filter rules
A15: 45251 | B15: 1.12 | C15: Phil Cullum | D15: Updated Opportunity Filtering Logic tab to include "Closed Won"
A16: 45253 | B16: 1.13 | C16: Phil Cullum | D16: Corrected agreement type mappings
A17: 45261 | B17: 1.14 | C17: Phil Cullum | D17: Mapped Salesforce contact mobile number to Qube Tenant Telephone3 field. See https://graingerplc.atlassian.net/browse/QUP-923

Sheet Salesforce to Qube  - Units
A1: Data Mapping | B1: CP-LJ-01
A2: Sending Interface system | B2: Salesforce
A3: Outbound Data Structure | B3: JSON
A4: Receiving Interface system | B4: Qube
A5: Inbound Data Structure | B5: XML
A6: Title | B6: TenancyCreated
A7: Method | B7: POST
A8: Source - Salesforce | C8: JSON Element | D8: Mandatory/Optional | E8: Data Type | F8: Field Length | G8: Sample Data | H8: Transformation rule/logic | I8: ChartOfAccounts | K8: Target - Qube | M8: XML Element | N8: Mandatory/Optional | O8: Data Type | P8: Field Length | Q8: Notes
A9: Table | B9: Field Name | I9: Canonical field | J9: Source API | K9: Table | L9: Field
D10: string | H10: See Opportunity Filtering Logic tab for details of which Opportunities should be processed Only send update when tenancy start date is today or in the past
H11: Set to "false" | M11: lookup | O11: boolean
H12: Set to "true" | M12: update-if-exists | O12: boolean
H13: Set to "true" | M13: clear-empty-fields | O13: boolean
A14: Opportunity | C14: Id | H14: Read from XRef | I14: EntityListing/UnitReference/entry/EntityID | M14: unit-reference
H15: NOT MAPPED | M15: property-reference
H16: NOT MAPPED | M16: desc
A17: Opportunity | C17: Tenancy_Start_Date | H17: Convert to yyyy-mm-dd format | I17: EntityListing/UnitReference/entry/CMResidents/entry/LeaseStartDate | K17: units | L17: leasedate5 | M17: lease-start
A18: Opportunity | C18: Tenancy_End_Date__c | H18: Convert to yyyy-mm-dd format | I18: EntityListing/UnitReference/entry/CMResidents/entry/LeaseEndDate | K18: units | L18: leasedate6 | M18: lease-end | N18: M
H19: NOT MAPPED | K19: units | L19: leaseterm1 | M19: lease-term-years | Q19: Need to test this is set by default
H20: NOT MAPPED | K20: units | L20: leaseterm2 | M20: lease-term-months | Q20: Need to test this is set by default
H21: NOT MAPPED | K21: units | L21: leaseterm3 | M21: lease-term-days | Q21: Need to test this is set by default
A22: Opportunity | C22: Agreement_Type__c | H22: If current Qube Unit status value is "Tenanted" do not update. See Agreement Type Mappings tab - ref data | I22: EntityListing/UnitReference/entry/Tenure | K22: units | L22: tenure | M22: tenure
H23: NOT MAPPED | K23: units | L23: TBA | M23: rent-review-date
H24: NOT MAPPED | K24: units | L24: TBA | M24: rent-review-notice
H25: NOT MAPPED | K25: units | L25: TBA | M25: rent-review- frequency
C26: Primary_Offer_Break_Clause__c | H26: See Break Clause Rules | K26: units | L26: TBA | M26: break-date | Q26: See Primary Offer Break Clause and email from Jaic
C27: Primary_Offer_Break_Clause__c | H27: See Break Clause Rules | K27: units | L27: TBA | M27: break-notice
C28: Primary_Offer_Break_Clause__c | H28: See Break Clause Rules | K28: units | L28: TBA | M28: break-frequency
H29: Set to Tenanted - store in QuickConnect reference data | K29: units | L29: unit_stat | M29: status
Q30: New field: % rent increase field TBC Tenancy.Uplift
A32: Foreign Keys
A33: None
M36: ?
M48: <detail><nett> | N48: Mandatory | O48: Number | P48: 13,2
M49: <detail><gross> | N49: Mandatory | O49: Number | P49: 13,2
M50: <detail><vat-code> | N50: Optional | O50: string | P50: 1
M51: <detail><vat> | N51: Mandatory | O51: Number | P51: 13,2
M52: <detail><line-type> | N52: Mandatory | O52: string | P52: 45
M53: <detail><line-type> | N53: Mandatory | O53: string | P53: 45
M54: <detail><property-reference> | N54: Mandatory | O54: string | P54: 12
M55: <detail><unit-reference> | N55: Mandatory | O55: string | P55: 12
M56: <detail><tenant-reference> | N56: Mandatory | O56: string | P56: 12
M57: <detail><heading-unique-id> | N57: Mandatory | O57: long integer
M58: <detail><heading-unique-id> | N58: Mandatory | O58: long integer
M59: <detail><in-cis> | O59: boolean
I62: Not Mapped
M63: <detail><materials> | N63: Optional | O63: Number | P63: 13,2
M64: <detail><labour> | N64: Optional | O64: Number | P64: 13,2

Sheet Salesforce to Qube  - Tenancy
A1: Data Mapping | B1: CP-LJ-01
A2: Sending Interface system | B2: Salesforce
A3: Outbound Data Structure | B3: JSON
A4: Receiving Interface system | B4: Qube
A5: Inbound Data Structure | B5: XML
A6: Title | B6: TenancyCreated
A7: Method | B7: POST
A8: Source - Salesforce | C8: Mandatory/Optional | D8: Data Type | E8: Field Length | G8: Transformation rule/logic | H8: ChartOfAccounts | J8: Target - Qube | M8: XML Element | N8: Mandatory/Optional | O8: Data Type | P8: Field Length | Q8: Notes
A9: Table | B9: JSON Element | F9: Sample Data | H9: Canonical field | I9: Source API | J9: Table | K9: Field | L9: Xpath
C10: Mandatory | G10: See Opportunity Filtering Logic tab for details of which Opportunities should be processed
C11: Mandatory | G11: Set to "false" | L11: [root] | M11: lookup | O11: boolean
G12: Set to "true" | L12: tenant | M12: update-if-exists | O12: boolean
G13: Set to "true" | L13: tenant | M13: clear-empty-fields | O13: boolean
B14: x | G14: The following mappings are for the parent tenancy
A15: Opportunity | B15: Primary_Offer_Live_Unit__c | G15: Read from XRef | H15: EntityListing/UnitReference/entry/EntityID | J15: units | K15: reference | L15: tenant | M15: unit-reference | O15: string | P15: 12
A16: Opportunity | B16: Id | C16: Mandatory | G16: Direct | H16: EntityListing/UnitReference/entry/OccupantReference | J16: tenant | K16: reference | L16: tenant | M16: tenant-reference | N16: M | O16: string | P16: 12 forced
G17: Direct - set to same value as tenant-reference | H17: EntityListing/UnitReference/entry/OccupantReference | L17: tenant | M17: parent-tenant
A18: Account | B18: Name | C18: Mandatory | G18: Direct | H18: EntityListing/UnitReference/entry/CMResidents/entry/OccupantName | J18: tenant | K18: name | L18: tenant | M18: name | N18: M | O18: string | P18: 45
G19: NOT MAPPED | J19: tenant | M19: lease-percentage
A20: Unit | B20: Street_Name__c | C20: Mandatory | G20: Only map if no address1 set. Truncate to 45 | H20: EntityListing/UnitReference/entry/AddressLine1 | J20: tenant | K20: address[1] | L20: tenant/address | M20: address1 | O20: string | P20: 45
G21: NOT MAPPED | J21: tenant | K21: address[2] | L21: tenant/address | M21: address2 | O21: string | P21: 45
G22: NOT MAPPED | J22: tenant | K22: address[3] | L22: tenant/address | M22: address3 | O22: string | P22: 45
G23: NOT MAPPED | J23: tenant | K23: address[4] | L23: tenant/address | M23: address4 | O23: string | P23: 45
G24: NOT MAPPED | J24: tenant | K24: address[5] | L24: tenant/address | M24: address5 | O24: string | P24: 45
G25: NOT MAPPED | J25: tenant | K25: address[6] | L25: tenant/address | M25: address6 | O25: string | P25: 45
A26: Unit | B26: Post_Code__c | G26: Direct | H26: EntityListing/UnitReference/entry/UnitPostCode | J26: tenant | K26: postcode | L26: tenant/address | M26: postcode | O26: string | P26: 11
A27: Account | B27: Phone | G27: Direct | H27: EntityListing/UnitReference/entry/CMResidents/entry/Phone1 | J27: tenant | K27: telephone[1] | L27: tenant/telephone | M27: telephone1 | O27: string | P27: 21
G28: NOT MAPPED | J28: tenant | K28: telephone[2] | L28: tenant/telephone | M28: telephone2 | O28: string | P28: 21
A29: Account | B29: PersonMobilePhone | G29: Direct | H29: EntityListing/UnitReference/entry/CMResidents/entry/Phone2 | J29: tenant | K29: telephone[3] | L29: tenant/telephone | M29: telephone3 | O29: string | P29: 21
G30: NOT MAPPED | J30: tenant | K30: telephone[4] | L30: tenant/telephone | M30: telephone4 | O30: string | P30: 21
A31: Account | B31: PersonEmail | G31: Direct | H31: EntityListing/UnitReference/entry/CMResidents/entry/Email | J31: tenant | K31: email[1] | L31: tenant/email | M31: email1 | O31: string | P31: 71
G32: NOT MAPPED | J32: tenant | K32: email[2] | L32: tenant/email | M32: email2 | O32: string | P32: 71
G33: NOT MAPPED | J33: tenant | K33: email[3] | L33: tenant/email | M33: email3 | O33: string | P33: 71
A34: Opportunity | B34: Tenancy_Start_Date__c | C34: Mandatory | G34: yyyy-mm-dd | H34: EntityListing/UnitReference/entry/CMResidents/entry/LeaseStartDate | J34: tenant | K34: ten_begin | L34: tenant | M34: start-date | O34: date
A35: Opportunity | B35: Removed | G35: NOT MAPPED | H35: EntityListing/UnitReference/entry/CMResidents/entry/LeaseEndDate | L35: tenant | M35: end-date
A36: Account | B36: Name | C36: Optional | G36: Direct | H36: EntityListing/UnitReference/entry/CMResidents/entry/OccupantName | J36: tenant | K36: dear | M36: dear | O36: string | P36: 45
C37: Optional | G37: Set to "Sincerely" - store in QuickConnect reference data | J37: tenant | K37: yours | L37: tenant | M37: yours | O37: choice
G38: NOT MAPPED | J38: tenant | K38: info-_[1] | L38: tenant | M38: info-l1 | O38: string | P38: 45
G39: NOT MAPPED | J39: tenant | K39: info-_[2] | L39: tenant | M39: info-l2 | O39: string | P39: 45
G40: NOT MAPPED | J40: tenant | K40: info_s[1] | L40: tenant | M40: info-s1 | O40: string | P40: 25
G41: NOT MAPPED | J41: tenant | K41: info_s[2] | L41: tenant | M41: info-s2 | O41: string | P41: 25
G42: NOT MAPPED | J42: tenant | K42: info_s[3] | L42: tenant | M42: info-s3 | O42: string | P42: 25
G43: NOT MAPPED | J43: tenant | K43: info_s[4] | L43: tenant | M43: info-s4 | O43: string | P43: 25
G44: NOT MAPPED | J44: tenant | K44: info_s[5] | L44: tenant | M44: info-s5 | O44: string | P44: 25
G45: NOT MAPPED | J45: tenant | K45: info_s[6] | L45: tenant | M45: info-s6 | O45: string | P45: 25
G46: Set to "DD" - store in QuickConnect reference data | J46: tenant | K46: paymethod | L46: tenant | M46: paymethod | O46: string | P46: 3
G47: Set to "GBP" - store in QuickConnect reference data | J47: tenant | K47: currency | L47: tenant | M47: currency | O47: string | P47: 3
G48: NOT MAPPED | J48: tenant | K48: scOmit | L48: tenant | M48: sc-omit | O48: boolean
G49: NOT MAPPED | J49: tenant | K49: scPeriod[1] | L49: tenant | M49: sc-period-start | O49: date
G50: NOT MAPPED | J50: tenant | K50: scPeriod[2] | L50: tenant | M50: sc-period-end | O50: date
G51: NOT MAPPED | J51: tenant | K51: scFreq | L51: tenant | M51: sc-frequency | O51: string | P51: 11
C52: Optional | G52: Set to "GRML" - store in QuickConnect reference data | J52: tenant | K52: demsuite | L52: tenant | M52: demand-suite | O52: refString | P52: 12
C53: Mandatory | G53: Set to blank | J53: tenant | K53: sta_code | L53: tenant | M53: sta-code | O53: refString | P53: 7flagged
C54: Mandatory | G54: Set to "Yes" - store in QuickConnect reference data | J54: tenant | K54: supdemand | L54: tenant | M54: supdemand | O54: boolean
C55: Optional | G55: Set to "No" - store in QuickConnect reference data | J55: tenant | K55: supletter | L55: tenant | M55: suppress-letters | O55: boolean
C56: Optional | G56: Set to "Emailed and printed" - store in QuickConnect reference data | J56: tenant | K56: demletby | L56: tenant | M56: correspondence-by | O56: string | P56: 25
G57: Set to "Email1" | J57: tenant | L57: tenant | M57: email-to | O57: string | P57: 6
G58: Set to "Telephone3" | J58: tenant | L58: tenant | M58: phone-for-sms | O58: string | P58: 10
G59: NOT MAPPED | J59: tenant | K59: tunorent | L59: tenant | M59: turnover-rent | O59: boolean
G60: NOT MAPPED | J60: tenant | K60: trading | L60: tenant | M60: trading | O60: string | P60: 45
G61: NOT MAPPED | J61: tenant | K61: vatnum | L61: tenant | M61: vat-number | O61: string | P61: 20
G62: NOT MAPPED | J62: tenant | K62: landtact | L62: tenant | M62: l-and-t-act | O62: boolean
G63: NOT MAPPED | J63: tenant | K63: ltaType | L63: tenant | M63: l-t-act-type | O63: string | P63: 45
G64: Set to "Multi-party lease" - store in QuickConnect | J64: tenant | K64: contran | L64: tenant | M64: tenant-type | O64: string | P64: 1
C65: Mandatory | D65: datetime | G65: If Tenancy_Start_Date__c is in the future, set to "Future" If Tenancy_Start_Date__c is today or in the past, set to "Current" Values stored in QuickConnect reference data | J65: tenant | K65: ten_stat | L65: tenant | M65: status | O65: choice
G66: Set to "Allow all" - store in QuickConnect reference data | J66: tenant | K66: stoppost | L66: tenant | M66: stop-posting | O66: string | P66: 25
C67: Optional | D67: string | G67: Set to "No" - store in QuickConnect reference data | J67: tenant | K67: tpalldocs | O67: choice | P67: no_yesflagged
C68: Optional | D68: float | G68: NOT MAPPED | J68: tenant | K68: bill_per | O68: choice | P68: periods
C69: Mandatory | D69: string
B70: x | G70: The following mappings are for the child tenancies (clients)
A71: Opportunity | B71: Primary_Offer_Live_Unit__c | G71: Read from XRef | H71: EntityListing/UnitReference/entry/EntityID | J71: units | K71: reference | L71: tenant | M71: unit-reference | O71: string | P71: 12
A72: Contact | B72: Id | C72: Mandatory | G72: Read from Xref if available, otherwise fetch a list of previous clients for the Unit from Qube and find the last used to calculate next value | H72: EntityListing/UnitReference/entry/CMResidents/entry/CMResidents/entry/CMContacts/entry/ContactID | J72: tenant | K72: reference | L72: tenant | M72: tenant-reference | N72: M | O72: string | P72: 12 forced
G73: Set to reference of parent tenancy | H73: EntityListing/UnitReference/entry/OccupantRef | L73: tenant | M73: parent-tenant
A74: Contact | B74: Name | G74: Direct | H74: EntityListing/UnitReference/entry/CMResidents/entry/CMContacts/entry/Name | J74: tenant | K74: name | L74: tenant | M74: name | N74: M | O74: string | P74: 45
A75: OpportunityContactRole | B75: Role | G75: Tenant (from ref data), see Client Role Mappngs. Set lease-percentage to 100 if ContatctType = "Lead Tenant" otherwise set to zero | H75: EntityListing/UnitReference/entry/CMResidents/entry/CMContacts/entry/ContactType | J75: tenant | L75: tenant | M75: lease-percentage | O75: Decimal
A76: Unit | B76: Street_Name__c | C76: Mandatory | G76: Only map if no address1 set. Truncate to 45 | H76: EntityListing/UnitReference/entry/AddressLine1 | J76: tenant | K76: address[1] | L76: tenant/address | M76: address1 | O76: string | P76: 45
G77: NOT MAPPED | J77: tenant | K77: address[2] | L77: tenant/address | M77: address2 | O77: string | P77: 45
G78: NOT MAPPED | J78: tenant | K78: address[3] | L78: tenant/address | M78: address3 | O78: string | P78: 45
G79: NOT MAPPED | J79: tenant | K79: address[4] | L79: tenant/address | M79: address4 | O79: string | P79: 45
G80: NOT MAPPED | J80: tenant | K80: address[5] | L80: tenant/address | M80: address5 | O80: string | P80: 45
G81: NOT MAPPED | J81: tenant | K81: address[6] | L81: tenant/address | M81: address6 | O81: string | P81: 45
A82: Unit | B82: Post_Code__c | G82: Direct | H82: EntityListing/UnitReference/entry/UnitPostCode | J82: tenant | K82: postcode | L82: tenant/address | M82: postcode | O82: string | P82: 11
A83: Contact | B83: Phone | G83: Direct | H83: EntityListing/UnitReference/entry/CMResidents/entry/CMContacts/entry/Phone | J83: tenant | K83: telephone[1] | L83: tenant/telephone | M83: telephone1 | O83: string | P83: 21
A84: Contact | B84: PersonMobilePhone | G84: Direct | H84: EntityListing/UnitReference/entry/CMResidents/entry/CMContacts/entry/MobilePhone | J84: tenant | K84: telephone[2] | L84: tenant/telephone | M84: telephone2 | O84: string | P84: 21
G85: NOT MAPPED | J85: tenant | K85: telephone[3] | L85: tenant/telephone | M85: telephone3 | O85: string | P85: 21
G86: NOT MAPPED | J86: tenant | K86: telephone[4] | L86: tenant/telephone | M86: telephone4 | O86: string | P86: 21
A87: Contact | B87: PersonEmail | G87: Direct | H87: EntityListing/UnitReference/entry/CMResidents/entry/CMContacts/entry/Email | J87: tenant | K87: email[1] | L87: tenant/email | M87: email1 | O87: string | P87: 71
G88: NOT MAPPED | J88: tenant | K88: email[2] | L88: tenant/email | M88: email2 | O88: string | P88: 71
G89: NOT MAPPED | J89: tenant | K89: email[3] | L89: tenant/email | M89: email3 | O89: string | P89: 71
A90: Opportunity | B90: Move_In_Date__c | C90: Mandatory | G90: yyyy-mm-dd | H90: EntityListing/UnitReference/entry/CMResidents/entry/LeaseStartDate | J90: tenant | K90: ten_begin | L90: tenant | M90: start-date | O90: date
G91: NOT MAPPED | L91: tenant | M91: end-date
A92: Contact | B92: Name | G92: Direct | H92: EntityListing/UnitReference/entry/CMResidents/entry/CMContacts/entry/Name | J92: tenant | K92: dear | M92: dear | O92: string | P92: 45
C93: Optional | G93: Set to "Sincerely" - store in QuickConnect reference data | J93: tenant | K93: yours | L93: tenant | M93: yours | O93: choice
G94: NOT MAPPED | J94: tenant | K94: info-_[1] | L94: tenant | M94: info-l1 | O94: string | P94: 45
G95: NOT MAPPED | J95: tenant | K95: info-_[2] | L95: tenant | M95: info-l2 | O95: string | P95: 45
G96: NOT MAPPED | J96: tenant | K96: info_s[1] | L96: tenant | M96: info-s1 | O96: string | P96: 25
G97: NOT MAPPED | J97: tenant | K97: info_s[2] | L97: tenant | M97: info-s2 | O97: string | P97: 25
G98: NOT MAPPED | J98: tenant | K98: info_s[3] | L98: tenant | M98: info-s3 | O98: string | P98: 25
G99: NOT MAPPED | J99: tenant | K99: info_s[4] | L99: tenant | M99: info-s4 | O99: string | P99: 25
G100: NOT MAPPED | J100: tenant | K100: info_s[5] | L100: tenant | M100: info-s5 | O100: string | P100: 25
...

Sheet Salesforce to Qube  - Clients
A1: Data Mapping | B1: CP-LJ-01
A2: Sending Interface system | B2: Salesforce
A3: Outbound Data Structure | B3: JSON
A4: Receiving Interface system | B4: Qube
A5: Inbound Data Structure | B5: XML
A6: Title | B6: TenancyCreated
A7: Method | B7: POST
A8: Source - Salesforce | C8: Mandatory/Optional | D8: Data Type | E8: Field Length | G8: Transformation rule/logic | H8: ChartOfAccounts | J8: Target - Qube | M8: XML Element | N8: Mandatory/Optional | O8: Data Type | P8: Field Length | Q8: Notes
A9: Table | B9: JSON Element | F9: Sample Data | H9: Canonical field | I9: Source API | J9: Table | K9: Field | L9: Path
C10: Mandatory | G10: See Opportunity Filtering Logic tab for details of which Opportunities should be processed
C11: Mandatory | G11: Set to "false" | L11: [root] | M11: lookup | O11: boolean
G12: Set to "true" | L12: tenantsdata | M12: update-if-exists | O12: boolean
G13: Set to "true" | L13: tenantsdata | M13: clear-empty-fields | O13: boolean
C14: Mandatory | L14: tenantsdata | M14: tenant-reference | O14: string | P14: 12 forced
A15: Contact | B15: Name | H15: EntityListing/UnitReference/entry/CMResidents/entry/CMContacts/entry/Name | L15: tenantsdata | M15: name | O15: string | P15: 45
G16: NOT MAPPED | L16: tenantsdata | M16: title | O16: string | P16: 45
A17: Contact | B17: FirstName | G17: Direct | H17: EntityListing/UnitReference/entry/CMResidents/entry/CMContacts/entry/FirstName | L17: tenantsdata | M17: first-name | O17: string | P17: 20
G18: NOT MAPPED | L18: tenantsdata | M18: middle-name | O18: string | P18: 19
A19: Contact | B19: LastName | G19: Direct | H19: EntityListing/UnitReference/entry/CMResidents/entry/CMContacts/entry/LastName | L19: tenantsdata | M19: surname | O19: string | P19: 20
A20: OpportunityContactRole | B20: Role | G20: Tenant (from ref data), see Client Role Mappngs | H20: EntityListing/UnitReference/entry/CMResidents/entry/CMContacts/entry/ContactType | L20: tenantsdata | M20: occupier-type | O20: string | P20: 45
G21: NOT MAPPED | L21: tenantsdata | M21: method-of-contact | O21: string | P21: 45
A22: Contact | B22: Birthdate | G22: Direct | L22: tenantsdata | M22: date-of-birth | O22: date
G23: NOT MAPPED | L23: tenantsdata | M23: date-of-death | O23: date
G24: NOT MAPPED | L24: tenantsdata | M24: spouse-date-of-birth
G25: NOT MAPPED | L25: tenantsdata | M25: gender
G26: NOT MAPPED | L26: tenantsdata | M26: country-of-origin
G27: NOT MAPPED | L27: tenantsdata | M27: marital-status
G28: NOT MAPPED | L28: tenantsdata | M28: benefit-received
G29: NOT MAPPED | L29: tenantsdata | M29: benefit-provider
G30: NOT MAPPED | L30: tenantsdata | M30: ni-number
G31: NOT MAPPED | L31: tenantsdata | M31: benefit-refnumber
G32: NOT MAPPED | L32: tenantsdata | M32: reason-for-vacancy
G33: NOT MAPPED | L33: tenantsdata | M33: vip
A40: Salesforce Foreign Keys
A41: OpportunityContactRole.ContactId
A42: OpportunityContactRole.OpportunityId

Sheet Opportunity Filtering Logic
A1: Only send Salesforce Opportunities to Qube where:
A3: Opportunity Agreement Type is specified
A4: Opportunity Agreement Type <> AST (Affordable)
A5: Opportunity Tenancy Type = New
A6: Opportunity PMS Reference specified
A7: Opportunity Stage = "Audit" or "Closed Won"
A8: (Processed By GREP = Not Processed OR (Processed By GREP <> Processed - Current Tenancy AND Move In Date is today or in the past)
A10: Note: All conditions must be met for Opportunity to be processed

Sheet Break Clause Rules
A1: Salesforce Primary Offer Break Clause | B1: Meaning | C1: Break Date | D1: Break Notice | E1: Break Frequency
A2: 2 at 4 to expire at 6 | B2: 2 months notice after min 4 months to expire at 6 months | C2: Move in date + 6 months | D2: 2 | E2: Do not map
A3: 2 at 6 to expire at 8 | B3: 2 months notice after min 6 months to expire at 8 months | C3: Move in date + 8 months | D3: 2 | E3: Do not map
A4: 2 at 8 to expire at 10 | B4: 2 months notice after min 8 months to expire at 10 months | C4: Move in date + 10 months | D4: 2 | E4: Do not map
A5: 2 at 10 to expire at 12 | B5: 2 months notice after min 10 months to expire at 12 months | C5: Move in date + 12 months | D5: 2 | E5: Do not map
A6: Halfway on an 18 | B6: Expire after min 9 months | C6: Move in date + 9 months | D6: 2 | E6: Do not map
A7: Halfway on an 24 | B7: Expire after min 12 months | C7: Move in date + 12 months | D7: 2 | E7: Do not map
A8: Halfway on an 36 | B8: Expire after min 18 months | C8: Move in date + 18 months | D8: 2 | E8: Do not map
A9: No break | B9: Break not permitted | C9: Do not map | D9: Do not map | E9: Do not map
A10: Live work | B10: TBA | C10: Do not map | D10: Do not map | E10: Do not map
A11: Check Contract | B11: Old tenancy and so not listed in Salesforce | C11: Do not map | D11: Do not map | E11: Do not map
A12: Renewal 1 month | B12: 1m renewal, then tenant will leave | C12: Do not map | D12: Do not map | E12: Do not map
A13: Renewal 2 month | B13: 2m renewal and then tenant will leave | C13: Do not map | D13: Do not map | E13: Do not map
A14: LW Renewal 1 month | B14: 1m renewal, then tenant will leave | C14: Do not map | D14: Do not map | E14: Do not map
A15: LW Renewal 2 month | B15: 2m renewal and then tenant will leave | C15: Do not map | D15: Do not map | E15: Do not map

Sheet Client Role Mappings
A1: Salesforce Opportunity Contact Role | B1: Canonical | C1: Qube Occupier Type
A2: Lead Tenant | B2: Lead Tenant | C2: Lead Tenant
A3: Tenant | B3: Sub Tenant | C3: Tenant
A4: Permitted Occupier | B4: Permitted Occupier | C4: Additional occupier
A5: Guarantor | B5: Guarantor | C5: Guarantor
A6: Relevant Person | B6: Relevant Person | C6: Alternative contact

Sheet Agreement Type Mappings
A1: Salesforce | B1: Canonical | C1: Qube
A2: AST | B2: AST | C2: AST
A3: Non-Housing (Company) | B3: COL | C3: Comp-Let
A4: Live Work | B4: ALW | C4: Live Work
A5: Parking Licence | B5: LIC | C5: Licence
A6: Shed Licence | B6: LIC | C6: Licence
A7: Occupation Licence | B7: LIC | C7: Licence
