Workbook

Sheet ERV file for SAji
A1: X18_digit_ID__c | B1: Name | C1: ERV | D1: Monthly ERV | E1: ERV Date
A2: a1G4J0000025tShUAI | B2: 38, Riplingham, Leamington Spa, Warwickshire | C2: =VLOOKUP(B2,'Qube Data_source data'!$B$2:$E$19707,3,0) -> #N/A | D2: =Table1[[#This Row],[ERV]]/12 -> #N/A | E2: =VLOOKUP(B2,'Qube Data_source data'!$B$2:$E$19707,4,0) -> #N/A
A3: a1G4J0000025tSmUAI | B3: 39, Galveston Road, London | C3: =VLOOKUP(B3,'Qube Data_source data'!$B$2:$E$19707,3,0) -> #N/A | D3: =Table1[[#This Row],[ERV]]/12 -> #N/A | E3: =VLOOKUP(B3,'Qube Data_source data'!$B$2:$E$19707,4,0) -> #N/A
A4: a1G4J0000025tSnUAI | B4: 20, Perth Avenue, Chadderton, Oldham | C4: =VLOOKUP(B4,'Qube Data_source data'!$B$2:$E$19707,3,0) -> 5 | D4: =Table1[[#This Row],[ERV]]/12 -> 0.41666667 | E4: =VLOOKUP(B4,'Qube Data_source data'!$B$2:$E$19707,4,0) -> 44834
A5: a1G4J0000025tSrUAI | B5: 8, Barham House, Westminster, London | C5: =VLOOKUP(B5,'Qube Data_source data'!$B$2:$E$19707,3,0) -> #N/A | D5: =Table1[[#This Row],[ERV]]/12 -> #N/A | E5: =VLOOKUP(B5,'Qube Data_source data'!$B$2:$E$19707,4,0) -> #N/A
A6: a1G4J0000025tSsUAI | B6: 30, Henshaw Street, Walworth, London | C6: =VLOOKUP(B6,'Qube Data_source data'!$B$2:$E$19707,3,0) -> #N/A | D6: =Table1[[#This Row],[ERV]]/12 -> #N/A | E6: =VLOOKUP(B6,'Qube Data_source data'!$B$2:$E$19707,4,0) -> #N/A
A7: a1G4J0000025tStUAI | B7: 42, Rosendale Road, GF, Lambeth, London | C7: =VLOOKUP(B7,'Qube Data_source data'!$B$2:$E$19707,3,0) -> #N/A | D7: =Table1[[#This Row],[ERV]]/12 -> #N/A | E7: =VLOOKUP(B7,'Qube Data_source data'!$B$2:$E$19707,4,0) -> #N/A
A8: a1G4J0000025tSwUAI | B8: 6, Barham House, Westminster, London | C8: =VLOOKUP(B8,'Qube Data_source data'!$B$2:$E$19707,3,0) -> #N/A | D8: =Table1[[#This Row],[ERV]]/12 -> #N/A | E8: =VLOOKUP(B8,'Qube Data_source data'!$B$2:$E$19707,4,0) -> #N/A
A9: a1G4J0000025tSxUAI | B9: Barham House, Westminster, INSURANCE ONLY | C9: =VLOOKUP(B9,'Qube Data_source data'!$B$2:$E$19707,3,0) -> #N/A | D9: =Table1[[#This Row],[ERV]]/12 -> #N/A | E9: =VLOOKUP(B9,'Qube Data_source data'!$B$2:$E$19707,4,0) -> #N/A
A10: a1G4J0000025tSyUAI | B10: Flat 2, 15-16 Picton Place, London W1U | C10: =VLOOKUP(B10,'Qube Data_source data'!$B$2:$E$19707,3,0) -> 13185 | D10: =Table1[[#This Row],[ERV]]/12 -> 1098.75 | E10: =VLOOKUP(B10,'Qube Data_source data'!$B$2:$E$19707,4,0) -> 44834
A11: a1G4J0000025tSzUAI | B11: 5/9, Lamont Road, Flat F, Chelsea, London | C11: =VLOOKUP(B11,'Qube Data_source data'!$B$2:$E$19707,3,0) -> #N/A | D11: =Table1[[#This Row],[ERV]]/12 -> #N/A | E11: =VLOOKUP(B11,'Qube Data_source data'!$B$2:$E$19707,4,0) -> #N/A
A12: a1G4J0000025tT0UAI | B12: 16a, Vale Drive, Chatham, Kent | C12: =VLOOKUP(B12,'Qube Data_source data'!$B$2:$E$19707,3,0) -> 150 | D12: =Table1[[#This Row],[ERV]]/12 -> 12.5 | E12: =VLOOKUP(B12,'Qube Data_source data'!$B$2:$E$19707,4,0) -> 44834
A13: a1G4J0000025tT1UAI | B13: 3, Barham House, Westminster, London | C13: =VLOOKUP(B13,'Qube Data_source data'!$B$2:$E$19707,3,0) -> #N/A | D13: =Table1[[#This Row],[ERV]]/12 -> #N/A | E13: =VLOOKUP(B13,'Qube Data_source data'!$B$2:$E$19707,4,0) -> #N/A
... A27373: a1G8d0000006VdHEAU | B27373: Tanhouse Estate 4 Bed Detached/gge, Solihull | C27373: =VLOOKUP(B27373,'Qube Data_source data'!$B$2:$E$19707,3,0) -> #N/A | D27373: =Table1[[#This Row],[ERV]]/12 -> #N/A | E27373: =VLOOKUP(B27373,'Qube Data_source data'!$B$2:$E$19707,4,0) -> #N/A
A27374: a1G8d0000006VkDEAU | B27374: 7 | C27374: =VLOOKUP(B27374,'Qube Data_source data'!$B$2:$E$19707,3,0) -> #N/A | D27374: =Table1[[#This Row],[ERV]]/12 -> #N/A | E27374: =VLOOKUP(B27374,'Qube Data_source data'!$B$2:$E$19707,4,0) -> #N/A
A27375: a1G8d0000006VxgEAE | B27375: 166, Montagu Mansions, Crawford St, W1U 6LE | C27375: =VLOOKUP(B27375,'Qube Data_source data'!$B$2:$E$19707,3,0) -> #N/A | D27375: =Table1[[#This Row],[ERV]]/12 -> #N/A | E27375: =VLOOKUP(B27375,'Qube Data_source data'!$B$2:$E$19707,4,0) -> #N/A
A27376: a1G8d0000006XUqEAM | B27376: 68 Church Path, FF, London W4 5BJ | C27376: =VLOOKUP(B27376,'Qube Data_source data'!$B$2:$E$19707,3,0) -> 0 | D27376: =Table1[[#This Row],[ERV]]/12 -> 0 | E27376: =VLOOKUP(B27376,'Qube Data_source data'!$B$2:$E$19707,4,0) -> 44834
A27377: a1G8d0000006XV5EAM | B27377: 92, Seymour Road, Leyton, London | C27377: =VLOOKUP(B27377,'Qube Data_source data'!$B$2:$E$19707,3,0) -> 5 | D27377: =Table1[[#This Row],[ERV]]/12 -> 0.41666667 | E27377: =VLOOKUP(B27377,'Qube Data_source data'!$B$2:$E$19707,4,0) -> 44834
A27378: a1G8d0000006dmcEAA | B27378: 33, Fitzroy Road INSURANCE ONLY | C27378: =VLOOKUP(B27378,'Qube Data_source data'!$B$2:$E$19707,3,0) -> #N/A | D27378: =Table1[[#This Row],[ERV]]/12 -> #N/A | E27378: =VLOOKUP(B27378,'Qube Data_source data'!$B$2:$E$19707,4,0) -> #N/A
A27379: a1G8d0000006peMEAQ | B27379: 10 Hatt Street Wellesley, Aldershot GU11 4AQ | C27379: =VLOOKUP(B27379,'Qube Data_source data'!$B$2:$E$19707,3,0) -> #N/A | D27379: =Table1[[#This Row],[ERV]]/12 -> #N/A | E27379: =VLOOKUP(B27379,'Qube Data_source data'!$B$2:$E$19707,4,0) -> #N/A
A27380: a1G8d0000006pevEAA | B27380: 6 Hortensia Road , London, SW10 0FU | C27380: =VLOOKUP(B27380,'Qube Data_source data'!$B$2:$E$19707,3,0) -> #N/A | D27380: =Table1[[#This Row],[ERV]]/12 -> #N/A | E27380: =VLOOKUP(B27380,'Qube Data_source data'!$B$2:$E$19707,4,0) -> #N/A
A27381: a1G8d0000006pf0EAA | B27381: 8 Hortensia Road , London, SW10 0FU | C27381: =VLOOKUP(B27381,'Qube Data_source data'!$B$2:$E$19707,3,0) -> #N/A | D27381: =Table1[[#This Row],[ERV]]/12 -> #N/A | E27381: =VLOOKUP(B27381,'Qube Data_source data'!$B$2:$E$19707,4,0) -> #N/A
A27382: a1G8d0000006pfAEAQ | B27382: 10 Hortensia Road , London, SW10 0FU | C27382: =VLOOKUP(B27382,'Qube Data_source data'!$B$2:$E$19707,3,0) -> #N/A | D27382: =Table1[[#This Row],[ERV]]/12 -> #N/A | E27382: =VLOOKUP(B27382,'Qube Data_source data'!$B$2:$E$19707,4,0) -> #N/A
A27383: a1G8d0000006pfFEAQ | B27383: 12 Hortensia Road , London, SW10 0FU | C27383: =VLOOKUP(B27383,'Qube Data_source data'!$B$2:$E$19707,3,0) -> #N/A | D27383: =Table1[[#This Row],[ERV]]/12 -> #N/A | E27383: =VLOOKUP(B27383,'Qube Data_source data'!$B$2:$E$19707,4,0) -> #N/A
A27384: a1G8d0000006pfKEAQ | B27384: 14 Hortensia Road , London, SW10 0FU | C27384: =VLOOKUP(B27384,'Qube Data_source data'!$B$2:$E$19707,3,0) -> #N/A | D27384: =Table1[[#This Row],[ERV]]/12 -> #N/A | E27384: =VLOOKUP(B27384,'Qube Data_source data'!$B$2:$E$19707,4,0) -> #N/A
A27385: a1G8d0000006pfPEAQ | B27385: 16 Hortensia Road , London, SW10 0FU | C27385: =VLOOKUP(B27385,'Qube Data_source data'!$B$2:$E$19707,3,0) -> #N/A | D27385: =Table1[[#This Row],[ERV]]/12 -> #N/A | E27385: =VLOOKUP(B27385,'Qube Data_source data'!$B$2:$E$19707,4,0) -> #N/A
A27386: a1G8d0000006pfUEAQ | B27386: 18 Hortensia Road , London, SW10 0FU | C27386: =VLOOKUP(B27386,'Qube Data_source data'!$B$2:$E$19707,3,0) -> #N/A | D27386: =Table1[[#This Row],[ERV]]/12 -> #N/A | E27386: =VLOOKUP(B27386,'Qube Data_source data'!$B$2:$E$19707,4,0) -> #N/A
... A27400: a1G8d0000007oMDEAY | B27400: Cavendish House INSURANCE Twickenham | C27400: =VLOOKUP(B27400,'Qube Data_source data'!$B$2:$E$19707,3,0) -> #N/A | D27400: =Table1[[#This Row],[ERV]]/12 -> #N/A | E27400: =VLOOKUP(B27400,'Qube Data_source data'!$B$2:$E$19707,4,0) -> #N/A

Sheet Qube Data_source data
A1: Reference | B1: Desc | C1: Tenure | D1: Current ERV | E1: ERV As at
A2: 103057001 | B2: 135, Trentham Street, Southfields, London | C2: Assd.Per | D2: 19020 | E2: 44834
A3: 103058001 | B3: 67, Heythorp Street, Southfields, London | C3: Regulated | D3: 13390 | E3: 44834
A4: 103062001 | B4: 100, Great Portland Street, Flat A, Marylebon | C4: Regulated | D4: 10910 | E4: 44834
A5: 103065001 | B5: 13, Rutland Street, Knightsbridge, London | C5: Regulated | D5: 14700 | E5: 44834
A6: 103066001 | B6: 43, Burnthwaite Road, London | C6: Regulated | D6: 13494 | E6: 44834
A7: 103067002 | B7: 3, Nottingham Street, Flat 4, Marlyebone, Lon | C7: Regulated | D7: 10464 | E7: 44834
A8: 103070001 | B8: 70, Elborough Street, Southfields, London | C8: Regulated | D8: 12516 | E8: 44834
A9: 103071001 | B9: 57, Pirbright Road, Southfields, London | C9: Regulated | D9: 16236 | E9: 44834
A10: 103075001 | B10: 34, St Marys Gardens, Kennington, London | C10: Regulated | D10: 8230 | E10: 44834
A11: 103078001 | B11: 10, Avalon Road, London | C11: Regulated | D11: 14950 | E11: 44834
A12: 103082001 | B12: 2, Walton Court, Richmond, Surrey | C12: Regulated | D12: 12672 | E12: 44834
A13: 103082002 | B13: 6, Walton Court, Richmond, Surrey | C13: Regulated | D13: 12672 | E13: 44834
... A19707: 900005004 | B19707: Unit 4, 9 Millet Place, London E16 2YJ | C19707: Vac-C | D19707: 19649 | E19707: 44834
