Workbook

Sheet Apartments
A1: Diary Status | B1: Event month | C1: Event Date | D1: Portfolio | E1: Estate | F1: Unit Manager | G1: Unit Description | H1: Current Tenant Name | I1: PM Details | J1: Tenancy Status | K1: Tenancy Start Date | L1: Lease Start Date | M1: Lease End Date | N1: Action Type | O1: Unit Tenure | P1: September 23 Annual ERV | Q1: September 23 Monthly ERV | R1: March 24 Annual ERV | S1: March 24 Monthly ERV | T1: Current Annual Rent | U1: Current Monthly Rent | V1: Previous Rent | W1: Price Book Rent | X1: NEW PRICE BOOK RENT | Y1: NEW Price book rent /current rent % | Z1: Price Book / Current Rent % | AA1: Price Book / March 24 ERV % | AB1: AM Offering | AC1: AM Offering / Current Rent % | AD1: AM Offering / March 24 ERV % | AE1: AM Minimum | AF1: AM Minimum / Current Rent % | AG1: AM Minimum / March ERV % | AH1: AM Comments | AI1: Tenant Balance Status | AJ1: Unit Size | AK1: Beds | AL1: Baths | AM1: Description of Unit | AN1: rent acheived | AO1: Rent Acheived % | AP1: Renewal Neg | AQ1: Renewal Status | AR1: Renewal notes
A2: Active | B2: =TEXT(C2,"mmmm") -> August | C2: 45520 | D2: BTR-London & SE | E2: Abbeville Apartments | F2: Fatma Azakli | G2: Apt 308, Abbeville Apts, 37 London Rd, Barkin | H2: Mr Mayank Jha and Mrs Tanisha Prasad | I2: N/A | J2: Current | K2: 44790 | L2: 45155 | M2: 45520 | N2: Renewal | O2: AST | P2: 17880 | Q2: 2024 | R2: 18480 | S2: 2025 | T2: 18000 | U2: 1950 | V2: 0 | W2: 2058 | Z2: =(W2-U2)/U2 -> 0.055384615 | AA2: =(W2-S2)/S2 -> 0.016296296 | AB2: 2058 | AC2: =(AB2-U2)/U2 -> 0.055384615 | AD2: =(AB2-S2)/S2 -> 0.016296296 | AE2: 1900 | AF2: =(AE2-U2)/U2 -> -0.025641026 | AG2: =(AE2-S2)/S2 -> -0.061728395 | AI2: Cleared | AJ2: 574 | AK2: 1 | AL2: 1 | AM2: 1 Bed, Third Floor, Furnished1 Bathrooms | AO2: =SUM(AN2-U2)/U2 -> -1 | AP2: Jemma | AQ2: Sent
A3: Active | B3: =TEXT(C3,"mmmm") -> August | C3: 45527 | D3: BTR-London & SE | E3: Abbeville Apartments | F3: Fatma Azakli | G3: Apt 207, Abbeville Apts, 37 London Rd, Barkin | H3: Mr Edavalath Binesh & Mrs Sangeetha Binesh | I3: N/A | J3: Current | K3: 43701 | L3: 45162 | M3: 45527 | N3: Renewal | O3: AST | P3: 17796 | Q3: 1483 | R3: 18180 | S3: =R3/12 -> 1515 | T3: 17040 | U3: =T3/12 -> 1420 | V3: 15780 | W3: 1600 | Z3: =(W3-U3)/U3 -> 0.12676056 | AA3: =(W3-S3)/S3 -> 0.056105611 | AB3: 1540 | AC3: =(AB3-U3)/U3 -> 0.084507042 | AD3: =(AB3-S3)/S3 -> 0.01650165 | AE3: 1515 | AF3: =(AE3-U3)/U3 -> 0.066901408 | AG3: =(AE3-S3)/S3 -> 0 | AI3: Arrears | AJ3: 538 | AK3: 1 | AL3: 1 | AM3: 1 Bed, Second Floor, Furnished1 Bathrooms | AO3: =SUM(AN3-U3)/U3 -> -1 | AP3: Jemma | AQ3: NTQ
A4: Active | B4: =TEXT(C4,"mmmm") -> July | C4: 45479 | D4: BTR-London & SE | E4: Abbeville Apartments | F4: Fatma Azakli | G4: Apt 113, Abbeville Apts, 37 London Rd, Barkin | H4: Nishat Anjum & Khawaja Hassan Munir | I4: N/A | J4: Current | K4: 45114 | L4: 45114 | M4: 45479 | N4: New Let | O4: AST | P4: 17796 | Q4: 1483 | R4: 18180 | S4: =R4/12 -> 1515 | T4: 18120 | U4: =T4/12 -> 1510 | V4: 16680 | W4: 1640 | Z4: =(W4-U4)/U4 -> 0.086092715 | AA4: =(W4-S4)/S4 -> 0.082508251 | AB4: 1625 | AC4: =(AB4-U4)/U4 -> 0.07615894 | AD4: =(AB4-S4)/S4 -> 0.072607261 | AE4: 1600 | AF4: =(AE4-U4)/U4 -> 0.059602649 | AG4: =(AE4-S4)/S4 -> 0.056105611 | AI4: Cleared | AJ4: 538 | AK4: 1 | AL4: 1 | AM4: 1 Bed, First Floor, Furnished1 Bathrooms | AN4: 1600 | AO4: =SUM(AN4-U4)/U4 -> 0.059602649 | AP4: Jemma | AQ4: Sent
A5: Active | B5: =TEXT(C5,"mmmm") -> July | C5: 45482 | D5: BTR-London & SE | E5: Abbeville Apartments | F5: Fatma Azakli | G5: Apt 208, Abbeville Apts, 37 London Rd, Barkin | H5: Miss Batul Abbas & Mr Durani Prasonna Vijayan | I5: N/A | J5: Current | K5: 43291 | L5: 45117 | M5: 45482 | N5: Renewal | O5: AST | P5: 17880 | Q5: 1490 | R5: 18480 | S5: =R5/12 -> 1540 | T5: 17100 | U5: =T5/12 -> 1425 | V5: 15759 | W5: 1600 | Z5: =(W5-U5)/U5 -> 0.12280702 | AA5: =(W5-S5)/S5 -> 0.038961039 | AB5: 1575 | AC5: =(AB5-U5)/U5 -> 0.10526316 | AD5: =(AB5-S5)/S5 -> 0.022727273 | AE5: 1540 | AF5: =(AE5-U5)/U5 -> 0.080701754 | AG5: =(AE5-S5)/S5 -> 0 | AI5: Cleared | AJ5: 574 | AK5: 1 | AL5: 1 | AM5: 1 Bed, Second Floor, Furnished1 Bathrooms | AN5: 1540 | AO5: =SUM(AN5-U5)/U5 -> 0.080701754 | AP5: Jemma | AQ5: Sent
A6: Active | B6: =TEXT(C6,"mmmm") -> July | C6: 45490 | D6: BTR-London & SE | E6: Abbeville Apartments | F6: Fatma Azakli | G6: Apt 313, Abbeville Apts, 37 London Rd, Barkin | H6: Mohamed Khelloufi & Assia Al Jerrari | I6: N/A | J6: Current | K6: 45125 | L6: 45125 | M6: 45490 | N6: New Let | O6: AST | P6: 17796 | Q6: 1483 | R6: 18180 | S6: =R6/12 -> 1515 | T6: 18600 | U6: =T6/12 -> 1550 | V6: 17100 | W6: 1630 | Z6: =(W6-U6)/U6 -> 0.051612903 | AA6: =(W6-S6)/S6 -> 0.075907591 | AB6: 1650 | AC6: =(AB6-U6)/U6 -> 0.064516129 | AD6: =(AB6-S6)/S6 -> 0.089108911 | AE6: 1625 | AF6: =(AE6-U6)/U6 -> 0.048387097 | AG6: =(AE6-S6)/S6 -> 0.072607261 | AI6: Cleared | AJ6: 538 | AK6: 1 | AL6: 1 | AM6: 1 Bed, Third Floor, Furnished1 Bathrooms | AO6: =SUM(AN6-U6)/U6 -> -1 | AP6: Jemma | AQ6: Sent
A7: Active | B7: =TEXT(C7,"mmmm") -> July | C7: 45474 | D7: BTR-London & SE | E7: Abbeville Apartments | F7: Fatma Azakli | G7: Apt 402, Abbeville Apts, 37 London Rd, Barkin | H7: Mandy-Liza Lehnert,J Sowah,Elletina Mekkaoui | I7: N/A | J7: Current | K7: 44014 | L7: 45109 | M7: 45474 | N7: Renewal | O7: AST | P7: 24000 | Q7: 2000 | R7: 25656 | S7: =R7/12 -> 2138 | T7: 23700 | U7: =T7/12 -> 1975 | V7: 22740 | W7: 2150 | Z7: =(W7-U7)/U7 -> 0.088607595 | AA7: =(W7-S7)/S7 -> 0.0056127222 | AB7: 2150 | AC7: =(AB7-U7)/U7 -> 0.088607595 | AD7: =(AB7-S7)/S7 -> 0.0056127222 | AE7: 2140 | AF7: =(AE7-U7)/U7 -> 0.083544304 | AG7: =(AE7-S7)/S7 -> 0.0009354537 | AI7: Credit | AJ7: 958 | AK7: 3 | AL7: 2 | AM7: 3 Bed, Forth Floor, Furnished2 Bathrooms | AO7: =SUM(AN7-U7)/U7 -> -1 | AP7: Jemma | AQ7: Sent
A8: Active | B8: =TEXT(C8,"mmmm") -> July | C8: 45497 | D8: BTR-London & SE | E8: Abbeville Apartments | F8: Fatma Azakli | G8: Apt 405, Abbeville Apts, 37 London Rd, Barkin | H8: Dr Anusuya Rajendran | I8: N/A | J8: Current | K8: 43671 | L8: 45132 | M8: 45497 | N8: Renewal | O8: AST | P8: 17796 | Q8: 1483 | R8: 18180 | S8: =R8/12 -> 1515 | T8: 17280 | U8: =T8/12 -> 1440 | V8: 15840 | W8: 1620 | Z8: =(W8-U8)/U8 -> 0.125 | AA8: =(W8-S8)/S8 -> 0.069306931 | AB8: 1575 | AC8: =(AB8-U8)/U8 -> 0.09375 | AD8: =(AB8-S8)/S8 -> 0.03960396 | AE8: 1540 | AF8: =(AE8-U8)/U8 -> 0.069444444 | AG8: =(AE8-S8)/S8 -> 0.01650165 | AI8: Cleared | AJ8: 538 | AK8: 1 | AL8: 1 | AM8: 1 Bed, Forth Floor, Furnished1 Bathrooms | AN8: 1540 | AO8: =SUM(AN8-U8)/U8 -> 0.069444444 | AP8: Jemma | AQ8: Sent
A9: Active | B9: =TEXT(C9,"mmmm") -> July | C9: 45499 | D9: BTR-London & SE | E9: Abbeville Apartments | F9: Fatma Azakli | G9: Apt 409, Abbeville Apts, 37 London Rd, Barkin | H9: Amrita Poojari and Raghavendra Poojari | I9: N/A | J9: Current | K9: 44769 | L9: 45134 | M9: 45499 | N9: Renewal | O9: AST | P9: 17796 | Q9: 1483 | R9: 18180 | S9: =R9/12 -> 1515 | T9: 17400 | U9: =T9/12 -> 1450 | V9: 16080 | W9: 1600 | Z9: =(W9-U9)/U9 -> 0.10344828 | AA9: =(W9-S9)/S9 -> 0.056105611 | AB9: 1575 | AC9: =(AB9-U9)/U9 -> 0.086206897 | AD9: =(AB9-S9)/S9 -> 0.03960396 | AE9: 1535 | AF9: =(AE9-U9)/U9 -> 0.05862069 | AG9: =(AE9-S9)/S9 -> 0.01320132 | AI9: Cleared | AJ9: 538 | AK9: 1 | AL9: 1 | AM9: 1 Bed, Forth Floor, Furnished1 Bathrooms | AN9: 1535 | AO9: =SUM(AN9-U9)/U9 -> 0.05862069 | AP9: Jemma | AQ9: Sent
A10: Active | B10: =TEXT(C10,"mmmm") -> July | C10: 45487 | D10: BTR-London & SE | E10: Abbeville Apartments | F10: Fatma Azakli | G10: Apt 412, Abbeville Apts, 37 London Rd, Barkin | H10: Rakesh Singh & Rekha Kumari | I10: N/A | J10: Current | K10: 44392 | L10: 45122 | M10: 45487 | N10: Renewal | O10: AST | P10: 20100 | Q10: 1675 | R10: 21480 | S10: =R10/12 -> 1790 | T10: 19560 | U10: =T10/12 -> 1630 | V10: 17940 | W10: 1890 | Z10: =(W10-U10)/U10 -> 0.1595092 | AA10: =(W10-S10)/S10 -> 0.055865922 | AB10: 1835 | AC10: =(AB10-U10)/U10 -> 0.12576687 | AD10: =(AB10-S10)/S10 -> 0.025139665 | AE10: 1800 | AF10: =(AE10-U10)/U10 -> 0.10429448 | AG10: =(AE10-S10)/S10 -> 0.0055865922 | AI10: Cleared | AJ10: 661 | AK10: 2 | AL10: 1 | AM10: 2 Bed, Forth Floor, Furnished1 Bathrooms | AO10: =SUM(AN10-U10)/U10 -> -1 | AP10: Jemma | AQ10: Sent
A11: Active | B11: =TEXT(C11,"mmmm") -> July | C11: 45485 | D11: BTR-London & SE | E11: Abbeville Apartments | F11: Fatma Azakli | G11: Apt 509, Abbeville Apts, 37 London Rd, Barkin | H11: Ms Sarah Gifford & Mr Wayne Brown | I11: N/A | J11: Current | K11: 42198 | L11: 45120 | M11: 45485 | N11: Renewal | O11: AST | P11: 17916 | Q11: 1493 | R11: 18180 | S11: =R11/12 -> 1515 | T11: 17580 | U11: =T11/12 -> 1465 | V11: 15744 | W11: 1610 | Z11: =(W11-U11)/U11 -> 0.098976109 | AA11: =(W11-S11)/S11 -> 0.062706271 | AB11: 1575 | AC11: =(AB11-U11)/U11 -> 0.075085324 | AD11: =(AB11-S11)/S11 -> 0.03960396 | AE11: 1540 | AF11: =(AE11-U11)/U11 -> 0.051194539 | AG11: =(AE11-S11)/S11 -> 0.01650165 | AI11: Cleared | AJ11: 538 | AK11: 1 | AL11: 1 | AM11: 1 Bed, Fifth Floor, Furnished1 Bathrooms | AN11: 1540 | AO11: =SUM(AN11-U11)/U11 -> 0.051194539 | AP11: Jemma | AQ11: Sent
A12: Active | B12: =TEXT(C12,"mmmm") -> August | C12: 45528 | D12: BTR-London & SE | E12: Abbeville Apartments | F12: Fatma Azakli | G12: Apt 609, Abbeville Apts, 37 London Rd, Barkin | H12: Arinze Sunday Ogbonna & Adriana Roccalumera | I12: N/A | J12: Current | K12: 45163 | L12: 45163 | M12: 45528 | N12: New Let | O12: AST | P12: 18000 | Q12: 1500 | R12: 18180 | S12: =R12/12 -> 1515 | T12: 18600 | U12: =T12/12 -> 1550 | V12: 16680 | W12: 1620 | Z12: =(W12-U12)/U12 -> 0.04516129 | AA12: =(W12-S12)/S12 -> 0.069306931 | AB12: 1630 | AC12: =(AB12-U12)/U12 -> 0.051612903 | AD12: =(AB12-S12)/S12 -> 0.075907591 | AE12: 1595 | AF12: =(AE12-U12)/U12 -> 0.029032258 | AG12: =(AE12-S12)/S12 -> 0.052805281 | AI12: Cleared | AJ12: 538 | AK12: 1 | AL12: 1 | AM12: 1 Bed, Sixth Floor, Furnished1 Bathrooms | AO12: =SUM(AN12-U12)/U12 -> -1 | AP12: Jemma | AQ12: Sent
A13: Pending | B13: =TEXT(C13,"mmmm") -> August | C13: 45530 | D13: BTR-London & SE | E13: Abbeville Apartments | F13: Fatma Azakli | G13: Apt 505, Abbeville Apts, 37 London Rd, Barkin | H13: Aanand Natarajan Rajahsekharun & Aditi Ravichandran | I13: N/A | J13: Current | K13: 45349 | L13: 45349 | M13: 45530 | N13: New Let | O13: AST | P13: 17916 | Q13: 1493 | R13: 18180 | S13: =R13/12 -> 1515 | T13: 18300 | U13: =T13/12 -> 1525 | V13: 16740 | W13: 1630 | Z13: =(W13-U13)/U13 -> 0.068852459 | AA13: =(W13-S13)/S13 -> 0.075907591 | AB13: 1605 | AC13: =(AB13-U13)/U13 -> 0.052459016 | AD13: =(AB13-S13)/S13 -> 0.059405941 | AE13: 1585 | AF13: =(AE13-U13)/U13 -> 0.039344262 | AG13: =(AE13-S13)/S13 -> 0.04620462 | AI13: Cleared | AJ13: 538 | AK13: 1 | AL13: 1 | AM13: 1 Bed, Fifth Floor, Furnished1 Bathrooms | AO13: =SUM(AN13-U13)/U13 -> -1 | AP13: Jemma | AQ13: Sent
A14: Active | B14: =TEXT(C14,"mmmm") -> August | C14: 45535 | D14: BTR-London & SE | E14: Abbeville Apartments | F14: Fatma Azakli | G14: Apt 104, Abbeville Apts, 37 London Rd, Barkin | H14: Mrs Durgesh Rattan Mehta | I14: This resident is our only venerable elderly woman. We deal with her daughter Veena and her details are in Qube. Happy to renew. | J14: Current | K14: 42244 | L14: 45170 | M14: 45535 | N14: Renewal | O14: AST | P14: 17796 | Q14: 1483 | R14: 18180 | S14: =R14/12 -> 1515 | T14: 17220 | U14: =T14/12 -> 1435 | V14: 15780 | W14: 1630 | Z14: =(W14-U14)/U14 -> 0.1358885 | AA14: =(W14-S14)/S14 -> 0.075907591 | AB14: 1540 | AC14: =(AB14-U14)/U14 -> 0.073170732 | AD14: =(AB14-S14)/S14 -> 0.01650165 | AE14: 1515 | AF14: =(AE14-U14)/U14 -> 0.055749129 | AG14: =(AE14-S14)/S14 -> 0 | AI14: Cleared | AJ14: 538 | AK14: 1 | AL14: 1 | AM14: 1 Bed, First Floor, Furnished1 Bathrooms | AN14: 1515 | AO14: =SUM(AN14-U14)/U14 -> 0.055749129 | AP14: Jemma | AQ14: Sent
A15: Active | B15: =TEXT(C15,"mmmm") -> August | C15: 45511 | D15: BTR-London & SE | E15: Abbeville Apartments | F15: Fatma Azakli | G15: Apt 501, Abbeville Apts, 37 London Rd, Barkin | H15: Mr Raees Patel | I15: N/A | J15: Current | K15: 44051 | L15: 45146 | M15: 45511 | N15: Renewal | O15: AST | P15: 20436 | Q15: 1703 | R15: 21696 | S15: =R15/12 -> 1808 | T15: 20160 | U15: =T15/12 -> 1680 | V15: 18840 | W15: 1890 | Z15: =(W15-U15)/U15 -> 0.125 | AA15: =(W15-S15)/S15 -> 0.045353982 | AB15: 1875 | AC15: =(AB15-U15)/U15 -> 0.11607143 | AD15: =(AB15-S15)/S15 -> 0.037057522 | AE15: 1810 | AF15: =(AE15-U15)/U15 -> 0.077380952 | AG15: =(AE15-S15)/S15 -> 0.0011061947 | AI15: Arrears | AJ15: 756 | AK15: 2 | AL15: 1 | AM15: 2 Bed, Fifth Floor, Furnished1 Bathrooms | AN15: 1810 | AO15: =SUM(AN15-U15)/U15 -> 0.077380952 | AP15: Jemma | AQ15: Sent
A16: Active | B16: =TEXT(C16,"mmmm") -> August | C16: 45524 | D16: BTR-London & SE | E16: Abbeville Apartments | F16: Fatma Azakli | G16: Apt 612, Abbeville Apts, 37 London Rd, Barkin | H16: Reece Ballett and Charlotte Hardy | I16: N/A | J16: Current | K16: 44733 | L16: 45098 | M16: 45524 | N16: Renewal | O16: AST | P16: 20280 | Q16: 1690 | R16: 21480 | S16: =R16/12 -> 1790 | T16: 20220 | U16: =T16/12 -> 1685 | V16: 19020 | W16: 1910 | Z16: =(W16-U16)/U16 -> 0.13353116 | AA16: =(W16-S16)/S16 -> 0.067039106 | AB16: 1825 | AC16: =(AB16-U16)/U16 -> 0.083086053 | AD16: =(AB16-S16)/S16 -> 0.019553073 | AE16: 1795 | AF16: =(AE16-U16)/U16 -> 0.065281899 | AG16: =(AE16-S16)/S16 -> 0.0027932961 | AI16: Cleared | AJ16: 661 | AK16: 2 | AL16: 1 | AM16: 2 Bed, Sixth Floor, Furnished1 Bathrooms | AO16: =SUM(AN16-U16)/U16 -> -1 | AP16: Jemma | AQ16: NTQ
A17: Active | B17: =TEXT(C17,"mmmm") -> August | C17: 45531 | D17: BTR-London & SE | E17: Abbeville Apartments | F17: Fatma Azakli | G17: Apt 506, Abbeville Apts, 37 London Rd, Barkin | H17: Giacomo Mazza & Angelica Mazza | I17: N/A | J17: Current | K17: 45166 | L17: 45166 | M17: 45531 | N17: New Let | O17: AST | P17: 20220 | Q17: 1685 | R17: 21480 | S17: =R17/12 -> 1790 | T17: 21420 | U17: =T17/12 -> 1785 | V17: 19800 | W17: 1890 | Z17: =(W17-U17)/U17 -> 0.058823529 | AA17: =(W17-S17)/S17 -> 0.055865922 | AB17: 1885 | AC17: =(AB17-U17)/U17 -> 0.056022409 | AD17: =(AB17-S17)/S17 -> 0.053072626 | AE17: 1860 | AF17: =(AE17-U17)/U17 -> 0.042016807 | AG17: =(AE17-S17)/S17 -> 0.039106145 | AI17: Cleared | AJ17: 660 | AK17: 2 | AL17: 1 | AM17: 2 Bed, Fifth Floor, Furnished1 Bathrooms | AN17: 1890 | AO17: =SUM(AN17-U17)/U17 -> 0.058823529 | AP17: Jemma | AQ17: signing
A18: Active | B18: =TEXT(C18,"mmmm") -> August | C18: 45535 | D18: BTR-London & SE | E18: Abbeville Apartments | F18: Fatma Azakli | G18: Apt 210, Abbeville Apts, 37 London Rd, Barkin | H18: Sateesh Mani and Gayathri Raman | I18: N/A | J18: Current | K18: 45170 | L18: 45170 | M18: 45535 | N18: New Let | O18: AST | P18: 20376 | Q18: 1698 | R18: 21756 | S18: =R18/12 -> 1813 | T18: 21000 | U18: =T18/12 -> 1750 | V18: 19440 | W18: 1920 | Z18: =(W18-U18)/U18 -> 0.097142857 | AA18: =(W18-S18)/S18 -> 0.059018202 | AB18: 1875 | AC18: =(AB18-U18)/U18 -> 0.071428571 | AD18: =(AB18-S18)/S18 -> 0.034197463 | AE18: 1850 | AF18: =(AE18-U18)/U18 -> 0.057142857 | AG18: =(AE18-S18)/S18 -> 0.020408163 | AI18: Cleared | AJ18: 778 | AK18: 2 | AL18: 1 | AM18: 2 Bed, Second Floor, Furnished1 Bathrooms | AO18: =SUM(AN18-U18)/U18 -> -1 | AP18: Jemma | AQ18: Sent | AR18: r2r required
A19: Active | B19: =TEXT(C19,"mmmm") -> August | C19: 45510 | D19: BTR-London & SE | E19: Abbeville Apartments | F19: Fatma Azakli | G19: Apt 317, Abbeville Apts, 37 London Rd, Barkin | H19: Eoin Mullan, Felix Price & Ewan Orton | I19: N/A | J19: Current | K19: 45145 | L19: 45145 | M19: 45510 | N19: New Let | O19: AST | P19: 24000 | Q19: 2000 | R19: 25680 | S19: =R19/12 -> 2140 | T19: 25200 | U19: =T19/12 -> 2100 | V19: 22740 | W19: 2170 | Z19: =(W19-U19)/U19 -> 0.033333333 | AA19: =(W19-S19)/S19 -> 0.014018692 | AB19: 2200 | AC19: =(AB19-U19)/U19 -> 0.047619048 | AD19: =(AB19-S19)/S19 -> 0.028037383 | AE19: 2165 | AF19: =(AE19-U19)/U19 -> 0.030952381 | AG19: =(AE19-S19)/S19 -> 0.011682243 | AI19: Arrears | AJ19: 987 | AK19: 3 | AL19: 2 | AM19: 3 Bed, Third Floor, Furnished2 Bathrooms | AO19: =SUM(AN19-U19)/U19 -> -1 | AP19: Jemma | AQ19: Denied
A20: Active | B20: =TEXT(C20,"mmmm") -> July | C20: 45487 | D20: PRS-London & SE | E20: Ability Plaza | F20: Younis Miho | G20: Flat 16 Ability Plaza, London, E8 | H20: Mr Justin Georges Guy Seghers | I20: N/A | J20: Current | K20: 44392 | L20: 45122 | M20: 45487 | N20: Renewal | O20: Live Work | P20: 23920 | Q20: 1993.3333 | R20: 25220 | S20: =R20/12 -> 2101.6667 | T20: 20700 | U20: =T20/12 -> 1725 | V20: 19020 | W20: NPB | Z20: =(W20-U20)/U20 -> #VALUE! | AA20: =(W20-S20)/S20 -> #VALUE! | AB20: 2150 | AC20: =(AB20-U20)/U20 -> 0.24637681 | AD20: =(AB20-S20)/S20 -> 0.022997621 | AE20: 2125 | AF20: =(AE20-U20)/U20 -> 0.23188406 | AG20: =(AE20-S20)/S20 -> 0.0111023 | AH20: The passing rent is incredibly low on this. Please offer but the increase will be high to bring in line with the wider market | AI20: Arrears | AJ20: 471.39 | AK20: 1 | AL20: 1 | AM20: S/C 1 bed/1 bath w/balcony, o/p kit/livingFF | AO20: =SUM(AN20-U20)/U20 -> -1 | AP20: Jemma | AQ20: Sent
A21: Active | B21: =TEXT(C21,"mmmm") -> July | C21: 45496 | D21: PRS-London & SE | E21: Ability Plaza | F21: Younis Miho | G21: EX 7 Ability Plaza, 310 Kingsland Rd, Lon E8 | H21: Alfred Adeoye | I21: N/A | J21: Current | K21: 44401 | L21: 45131 | M21: 45496 | N21: Renewal | O21: Live Work | P21: 24076 | Q21: 2006.3333 | R21: 25324 | S21: =R21/12 -> 2110.3333 | T21: 25140 | U21: =T21/12 -> 2095 | V21: 23411.76 | W21: NPB | Z21: =(W21-U21)/U21 -> #VALUE! | AA21: =(W21-S21)/S21 -> #VALUE! | AB21: 2225 | AC21: =(AB21-U21)/U21 -> 0.062052506 | AD21: =(AB21-S21)/S21 -> 0.054335808 | AE21: 2200 | AF21: =(AE21-U21)/U21 -> 0.050119332 | AG21: =(AE21-S21)/S21 -> 0.042489338 | AI21: Cleared | AJ21: 524.72 | AK21: 1 | AL21: 1 | AM21: S/C 1 bed/1 bath, o/p kitchen/living rm Rfb21FF | AN21: 2225 | AO21: =SUM(AN21-U21)/U21 -> 0.062052506 | AP21: Jemma | AQ21: Sent
A22: Active | B22: =TEXT(C22,"mmmm") -> July | C22: 45484 | D22: PRS-London & SE | E22: Ability Plaza | F22: Younis Miho | G22: EX 16 Ability Plaza, 310 Kingsland Rd, Lon E8 | H22: Anne Lancaster | I22: N/A | J22: Current | K22: 45119 | L22: 45119 | M22: 45484 | N22: New Let | O22: Live Work | P22: 25272 | Q22: 2106 | R22: 26520 | S22: =R22/12 -> 2210 | T22: 25800 | U22: =T22/12 -> 2150 | V22: 24000 | W22: NPB | Z22: =(W22-U22)/U22 -> #VALUE! | AA22: =(W22-S22)/S22 -> #VALUE! | AB22: 2275 | AC22: =(AB22-U22)/U22 -> 0.058139535 | AD22: =(AB22-S22)/S22 -> 0.029411765 | AE22: 2250 | AF22: =(AE22-U22)/U22 -> 0.046511628 | AG22: =(AE22-S22)/S22 -> 0.018099548 | AI22: Cleared | AJ22: 558.82 | AK22: 1 | AL22: 1 | AM22: S/C 1 bed/1 bath, o/p kit/liv, Rfrb 2014TF | AN22: 2275 | AO22: =SUM(AN22-U22)/U22 -> 0.058139535 | AP22: Jemma | AQ22: Sent
A23: Active | B23: =TEXT(C23,"mmmm") -> July | C23: 45503 | D23: PRS-London & SE | E23: Ability Plaza | F23: Younis Miho | G23: EX 19 Ability Plaza, 310 Kingsland Rd, Lon E8 | H23: Mr David Ralph & Miss Prudence Bond | I23: N/A | J23: Current | K23: 43677 | L23: 45138 | M23: 45503 | N23: Renewal | O23: Live Work | P23: 26000 | Q23: 2166.6667 | R23: 27248 | S23: =R23/12 -> 2270.6667 | T23: 24300 | U23: =T23/12 -> 2025 | V23: 22680 | W23: NPB | Z23: =(W23-U23)/U23 -> #VALUE! | AA23: =(W23-S23)/S23 -> #VALUE! | AB23: 2235 | AC23: =(AB23-U23)/U23 -> 0.1037037 | AD23: =(AB23-S23)/S23 -> -0.015707575 | AE23: 2215 | AF23: =(AE23-U23)/U23 -> 0.09382716 | AG23: =(AE23-S23)/S23 -> -0.024515561 | AI23: Cleared | AJ23: 609.17 | AK23: 1 | AL23: 1 | AM23: S/C 1 bed/1 bath, o/p kitchen/liv, Rfrb 20144F | AN23: 2215 | AO23: =SUM(AN23-U23)/U23 -> 0.09382716 | AP23: Jemma | AQ23: Sent
A24: Active | B24: =TEXT(C24,"mmmm") -> July | C24: 45492 | D24: PRS-London & SE | E24: Ability Plaza | F24: Younis Miho | G24: Flat 76 Ability Plaza, London, E8 | H24: Mr Jesse Laitinen | I24: N/A | J24: Current | K24: 43456 | L24: 45127 | M24: 45492 | N24: Renewal | O24: Live Work | P24: 24700 | Q24: 2058.3333 | R24: 25480 | S24: =R24/12 -> 2123.3333 | T24: 24780 | U24: =T24/12 -> 2065 | V24: 22800 | W24: NPB | Z24: =(W24-U24)/U24 -> #VALUE! | AA24: =(W24-S24)/S24 -> #VALUE! | AB24: 2275 | AC24: =(AB24-U24)/U24 -> 0.10169492 | AD24: =(AB24-S24)/S24 -> 0.071428571 | AE24: 2250 | AF24: =(AE24-U24)/U24 -> 0.089588378 | AG24: =(AE24-S24)/S24 -> 0.059654631 | AI24: Arrears | AJ24: 705.53 | AK24: 1 | AL24: 1 | AM24: studio/mezz/bathroom - PRfb '176F/6FA | AO24: =SUM(AN24-U24)/U24 -> -1 | AP24: Jemma | AQ24: Sent
A25: Active | B25: =TEXT(C25,"mmmm") -> July | C25: 45476 | D25: PRS-London & SE | E25: Ability Plaza | F25: Younis Miho | G25: Flat 75 Ability Plaza, London, E8 | H25: My Taylan Aygun | I25: N/A | J25: Current | K25: 44016 | L25: 45111 | M25: 45476 | N25: Renewal | O25: Live Work | P25: 27248 | Q25: 2270.6667 | R25: 28028 | S25: =R25/12 -> 2335.6667 | T25: 25020 | U25: =T25/12 -> 2085 | V25: 23160 | W25: NPB | Z25: =(W25-U25)/U25 -> #VALUE! | AA25: =(W25-S25)/S25 -> #VALUE! | AB25: 2350 | AC25: =(AB25-U25)/U25 -> 0.12709832 | AD25: =(AB25-S25)/S25 -> 0.0061367204 | AE25: 2300 | AF25: =(AE25-U25)/U25 -> 0.10311751 | AG25: =(AE25-S25)/S25 -> -0.015270444 | AI25: Cleared | AJ25: 746.18 | AK25: 1 | AL25: 1 | AM25: studio/mezz/bathroom/balcony, PRfb 206F/6FA | AN25: 2300 | AO25: =SUM(AN25-U25)/U25 -> 0.10311751 | AP25: Jemma | AQ25: Sent
A26: Active | B26: =TEXT(C26,"mmmm") -> July | C26: 45490 | D26: PRS-London & SE | E26: Ability Plaza | F26: Younis Miho | G26: Flat 64 Ability Plaza, London, E8 | H26: Peter Booth | I26: N/A | J26: Current | K26: 44394 | L26: 45125 | M26: 45490 | N26: Renewal | O26: Live Work | P26: 27144 | Q26: 2262 | R26: 29328 | S26: =R26/12 -> 2444 | T26: 25200 | U26: =T26/12 -> 2100 | V26: 22920 | W26: NPB | Z26: =(W26-U26)/U26 -> #VALUE! | AA26: =(W26-S26)/S26 -> #VALUE! | AB26: 2375 | AC26: =(AB26-U26)/U26 -> 0.13095238 | AD26: =(AB26-S26)/S26 -> -0.028232406 | AE26: 2325 | AF26: =(AE26-U26)/U26 -> 0.10714286 | AG26: =(AE26-S26)/S26 -> -0.048690671 | AH26: Passing rent is low copared to ERV and other 2 bed rents | AI26: Cleared | AJ26: 678.18 | AK26: 2 | AL26: 1 | AM26: S/C 2 bed/1 bath, kitchen, living room4FA | AO26: =SUM(AN26-U26)/U26 -> -1 | AP26: Jemma | AQ26: Sent
A27: Active | B27: =TEXT(C27,"mmmm") -> July | C27: 45489 | D27: PRS-London & SE | E27: Ability Plaza | F27: Younis Miho | G27: Flat 67 Ability Plaza, London, E8 | H27: Mr S van Oossanen, Ms S Lee & Mr D Cutler | I27: N/A | J27: Current | K27: 44394 | L27: 45124 | M27: 45489 | N27: Renewal | O27: Live Work | P27: 28392 | Q27: 2366 | R27: 30576 | S27: =R27/12 -> 2548 | T27: 26100 | U27: =T27/12 -> 2175 | V27: 24000 | W27: NPB | Z27: =(W27-U27)/U27 -> #VALUE! | AA27: =(W27-S27)/S27 -> #VALUE! | AB27: 2400 | AC27: =(AB27-U27)/U27 -> 0.10344828 | AD27: =(AB27-S27)/S27 -> -0.058084772 | AE27: 2350 | AF27: =(AE27-U27)/U27 -> 0.08045977 | AG27: =(AE27-S27)/S27 -> -0.077708006 | AI27: Cleared | AJ27: 690.25 | AK27: 2 | AL27: 1 | AM27: 2 bed/1 bath flat, kitchen, living rm PRfb205F | AN27: 2350 | AO27: =SUM(AN27-U27)/U27 -> 0.08045977 | AP27: Jemma | AQ27: Sent
A28: Active | B28: =TEXT(C28,"mmmm") -> July | C28: 45500 | D28: PRS-London & SE | E28: Ability Plaza | F28: Younis Miho | G28: Flat 85 Ability Plaza, London, E8 | H28: Theo Quarendon & Amaechi Obasi | I28: N/A | J28: Current | K28: 44770 | L28: 44770 | M28: 45500 | N28: Renewal | O28: Live Work | P28: 28600 | Q28: 2383.3333 | R28: 30836 | S28: =R28/12 -> 2569.6667 | T28: 25800 | U28: =T28/12 -> 2150 | V28: 25800 | W28: NPB | Z28: =(W28-U28)/U28 -> #VALUE! | AA28: =(W28-S28)/S28 -> #VALUE! | AB28: 2425 | AC28: =(AB28-U28)/U28 -> 0.12790698 | AD28: =(AB28-S28)/S28 -> -0.056297834 | AE28: 2375 | AF28: =(AE28-U28)/U28 -> 0.10465116 | AG28: =(AE28-S28)/S28 -> -0.07575561 | AH28: Passing rent is low compared to ERV and other 2 bed rents | AI28: Cleared | AJ28: 737.02 | AK28: 2 | AL28: 1 | AM28: 2 bed/1 bath, kitch, liv rm - P Refurb '176FA | AO28: =SUM(AN28-U28)/U28 -> -1 | AP28: Jemma | AQ28: Sent
A29: Active | B29: =TEXT(C29,"mmmm") -> August | C29: 45527 | D29: PRS-London & SE | E29: Ability Plaza | F29: Younis Miho | G29: Flat 47 Ability Plaza, London, E8 | H29: Sarah Yazouri & Austin Bly | I29: N/A | J29: Current | K29: 45162 | L29: 45162 | M29: 45527 | N29: New Let | O29: Live Work | P29: 27040 | Q29: 2253.3333 | R29: 27820 | S29: =R29/12 -> 2318.3333 | T29: 26400 | U29: =T29/12 -> 2200 | V29: 23340 | W29: NPB | Z29: =(W29-U29)/U29 -> #VALUE! | AA29: =(W29-S29)/S29 -> #VALUE! | AB29: 2350 | AC29: =(AB29-U29)/U29 -> 0.068181818 | AD29: =(AB29-S29)/S29 -> 0.013659238 | AE29: 2325 | AF29: =(AE29-U29)/U29 -> 0.056818182 | AG29: =(AE29-S29)/S29 -> 0.002875629 | AI29: Arrears | AJ29: 727.97 | AK29: 1 | AL29: 1 | AM29: studio/mezz/bathroom/balcony - PRefurb'17TF/TFA | AO29: =SUM(AN29-U29)/U29 -> -1 | AP29: Jemma | AQ29: Sent
A30: Active | B30: =TEXT(C30,"mmmm") -> August | C30: 45527 | D30: PRS-London & SE | E30: Ability Plaza | F30: Younis Miho | G30: Flat 53 Ability Plaza, London, E8 | H30: Mr Nicholas Derewlany | I30: N/A | J30: Current | K30: 44432 | L30: 45162 | M30: 45527 | N30: Renewal | O30: Live Work | P30: 30316 | Q30: 2526.3333 | R30: 31564 | S30: =R30/12 -> 2630.3333 | T30: 28380 | U30: =T30/12 -> 2365 | V30: 26160 | W30: NPB | Z30: =(W30-U30)/U30 -> #VALUE! | AA30: =(W30-S30)/S30 -> #VALUE! | AB30: 2550 | AC30: =(AB30-U30)/U30 -> 0.078224101 | AD30: =(AB30-S30)/S30 -> -0.030541123 | AE30: 2500 | AF30: =(AE30-U30)/U30 -> 0.057082452 | AG30: =(AE30-S30)/S30 -> -0.04955012 | AH30: ERV is high due to size of this unit | AI30: Cleared | AJ30: 1099.81 | AK30: 1 | AL30: 1 | AM30: 1 bed/1 bath w/mezz,o/p kit/liv,balc.-PRfb'174F/4FA | AO30: =SUM(AN30-U30)/U30 -> -1 | AP30: Jemma | AQ30: NTQ
A31: Active | B31: =TEXT(C31,"mmmm") -> August | C31: 45533 | D31: PRS-London & SE | E31: Ability Plaza | F31: Younis Miho | G31: EX 12 Ability Plaza, 310 Kingsland Rd, Lon E8 | H31: Sajani Sagar & Alice Thomson | I31: N/A | J31: Current | K31: 45168 | L31: 45168 | M31: 45533 | N31: New Let | O31: Live Work | P31: 25376 | Q31: 2114.6667 | R31: 26624 | S31: =R31/12 -> 2218.6667 | T31: 27000 | U31: =T31/12 -> 2250 | V31: 21960 | W31: NPB | Z31: =(W31-U31)/U31 -> #VALUE! | AA31: =(W31-S31)/S31 -> #VALUE! | AB31: 2300 | AC31: =(AB31-U31)/U31 -> 0.022222222 | AD31: =(AB31-S31)/S31 -> 0.036658654 | AE31: 2300 | AF31: =(AE31-U31)/U31 -> 0.022222222 | AG31: =(AE31-S31)/S31 -> 0.036658654 | AI31: Cleared | AJ31: 561.53 | AK31: 1 | AL31: 1 | AM31: S/C 1 bed/1 bath, o/p kit/liv, balc-Rfrb 2015SF | AO31: =SUM(AN31-U31)/U31 -> -1 | AP31: Jemma | AQ31: Sent
A32: Active | B32: =TEXT(C32,"mmmm") -> August | C32: 45505 | D32: PRS-London & SE | E32: Ability View | F32: Younis Miho | G32: Unit 5 Ability view, 218 Kingsland Road, Lond | H32: Sérgio Takahata & Suelen Neri Frazzato | I32: N/A | J32: Current | K32: 44775 | L32: 45140 | M32: 45505 | N32: Renewal | O32: Live Work | P32: 25740 | Q32: 2145 | R32: 27248 | S32: =R32/12 -> 2270.6667 | T32: 24780 | U32: =T32/12 -> 2065 | V32: 22920 | W32: NPB | Z32: =(W32-U32)/U32 -> #VALUE! | AA32: =(W32-S32)/S32 -> #VALUE! | AB32: 2285 | AC32: =(AB32-U32)/U32 -> 0.10653753 | AD32: =(AB32-S32)/S32 -> 0.0063123899 | AE32: 2275 | AF32: =(AE32-U32)/U32 -> 0.10169492 | AG32: =(AE32-S32)/S32 -> 0.0019083969 | AI32: Cleared | AJ32: 734.52 | AK32: 1 | AL32: 1 | AM32: S/C 1 bed/1 bath flat, o/p kitchen/living rm- | AO32: =SUM(AN32-U32)/U32 -> -1 | AP32: Jemma | AQ32: Sent
A33: Active | B33: =TEXT(C33,"mmmm") -> August | C33: 45505 | D33: PRS-London & SE | E33: Ability View | F33: Younis Miho | G33: Flat 17 Ability View, 220 Kingsland Road, Lon | H33: Mr Tristan Kinloch Hallis | I33: N/A | J33: Current | K33: 44410 | L33: 45140 | M33: 45505 | N33: Renewal | O33: Live Work | P33: 29172 | Q33: 2431 | R33: 29172 | S33: =R33/12 -> 2431 | T33: 28920 | U33: =T33/12 -> 2410 | V33: 26760 | W33: NPB | Z33: =(W33-U33)/U33 -> #VALUE! | AA33: =(W33-S33)/S33 -> #VALUE! | AB33: 2550 | AC33: =(AB33-U33)/U33 -> 0.058091286 | AD33: =(AB33-S33)/S33 -> 0.048951049 | AE33: 2525 | AF33: =(AE33-U33)/U33 -> 0.047717842 | AG33: =(AE33-S33)/S33 -> 0.038667215 | AI33: Cleared | AJ33: 813.54 | AK33: 2 | AL33: 1 | AM33: S/C 2 bed/1 bath, o/p kitchen/living rm Rfb217F | AO33: =SUM(AN33-U33)/U33 -> -1 | AP33: Jemma | AQ33: Sent
A34: Active | B34: =TEXT(C34,"mmmm") -> August | C34: 45506 | D34: PRS-London & SE | E34: Ability View | F34: Younis Miho | G34: Unit 3 Ability view, 218 Kingsland Road, Lond | H34: Henry McLean & Maria Kontorravdis | I34: N/A | J34: Current | K34: 45141 | L34: 45141 | M34: 45506 | N34: New Let | O34: Live Work | P34: 28496 | Q34: 2374.6667 | R34: 29328 | S34: =R34/12 -> 2444 | T34: 29400 | U34: =T34/12 -> 2450 | V34: 27120 | W34: NPB | Z34: =(W34-U34)/U34 -> #VALUE! | AA34: =(W34-S34)/S34 -> #VALUE! | AB34: 2575 | AC34: =(AB34-U34)/U34 -> 0.051020408 | AD34: =(AB34-S34)/S34 -> 0.053600655 | AE34: 2550 | AF34: =(AE34-U34)/U34 -> 0.040816327 | AG34: =(AE34-S34)/S34 -> 0.043371522 | AI34: Cleared | AJ34: 1165 | AK34: 1 | AL34: 1 | AM34: Studio (w/partition,o/p kit/liv - PRfb'19- | AO34: =SUM(AN34-U34)/U34 -> -1 | AP34: Jemma | AQ34: Sent
A35: Active | B35: =TEXT(C35,"mmmm") -> July | C35: 45495 | D35: PRS-London & SE | E35: Ability View | F35: Younis Miho | G35: Flat 7 Ability view, 220 Kingsland Road, Lond | H35: Mr Tamas Koloti | I35: N/A | J35: Current | K35: 43304 | L35: 45130 | M35: 45495 | N35: Renewal | O35: Live Work | P35: 26052 | Q35: 2171 | R35: 27560 | S35: =R35/12 -> 2296.6667 | T35: 25200 | U35: =T35/12 -> 2100 | V35: 23580 | W35: NPB | Z35: =(W35-U35)/U35 -> #VALUE! | AA35: =(W35-S35)/S35 -> #VALUE! | AB35: 2295 | AC35: =(AB35-U35)/U35 -> 0.092857143 | AD35: =(AB35-S35)/S35 -> -0.0007256894 | AE35: 2265 | AF35: =(AE35-U35)/U35 -> 0.078571429 | AG35: =(AE35-S35)/S35 -> -0.013788099 | AI35: Cleared | AJ35: 850.13 | AK35: 1 | AL35: 1 | AM35: 1 bed/1 bath, o/p kitch/liv rm - P Refurb '184F | AN35: 2265 | AO35: =SUM(AN35-U35)/U35 -> 0.078571429 | AP35: Jemma | AQ35: Sent
A36: Active | B36: =TEXT(C36,"mmmm") -> July | C36: 45504 | D36: PRS-London & SE | E36: Ability View | F36: Younis Miho | G36: Flat 13 Ability view, 220 Kingsland Road, Lon | H36: Miss Rachael Valters & Mr Samuel Thomas | I36: N/A | J36: Current | K36: 43301 | L36: 45139 | M36: 45504 | N36: Renewal | O36: Live Work | P36: 27924 | Q36: 2327 | R36: 29380 | S36: =R36/12 -> 2448.3333 | T36: 25500 | U36: =T36/12 -> 2125 | V36: 23493 | W36: NPB | Z36: =(W36-U36)/U36 -> #VALUE! | AA36: =(W36-S36)/S36 -> #VALUE! | AB36: 2450 | AC36: =(AB36-U36)/U36 -> 0.15294118 | AD36: =(AB36-S36)/S36 -> 0.00068073519 | AE36: 2375 | AF36: =(AE36-U36)/U36 -> 0.11764706 | AG36: =(AE36-S36)/S36 -> -0.029952349 | AH36: Passing rent is low copared to ERV and other 2 bed rents | AI36: Arrears | AJ36: 1052.92 | AK36: 1 | AL36: 1 | AM36: 1 bed / 1 bath/ opne plan kitchen/living room5F | AN36: 2450 | AO36: =SUM(AN36-U36)/U36 -> 0.15294118 | AP36: Jemma | AQ36: Sent
A37: Active | B37: =TEXT(C37,"mmmm") -> August | C37: 45521 | D37: PRS-London & SE | E37: Ability View | F37: Younis Miho | G37: Flat 6 Ability view, 220 Kingsland Road, Lond | H37: Emma Morton & Ben Rubinsztein | I37: N/A | J37: Current | K37: 45156 | L37: 45156 | M37: 45521 | N37: New Let | O37: Live Work | P37: 25844 | Q37: 2153.6667 | R37: 27352 | S37: =R37/12 -> 2279.3333 | T37: 27000 | U37: =T37/12 -> 2250 | V37: 24600 | W37: NPB | Z37: =(W37-U37)/U37 -> #VALUE! | AA37: =(W37-S37)/S37 -> #VALUE! | AB37: 2375 | AC37: =(AB37-U37)/U37 -> 0.055555556 | AD37: =(AB37-S37)/S37 -> 0.041971337 | AE37: 2350 | AF37: =(AE37-U37)/U37 -> 0.044444444 | AG37: =(AE37-S37)/S37 -> 0.031003217 | AI37: Cleared | AJ37: 796.08 | AK37: 1 | AL37: 1 | AM37: 1 bed/1 bath, kitch, liv rm - P Refurb '184F | AO37: =SUM(AN37-U37)/U37 -> -1 | AP37: Jemma | AQ37: Sent
A38: Active | B38: =TEXT(C38,"mmmm") -> August | C38: 45528 | D38: PRS-London & SE | E38: Ability View | F38: Younis Miho | G38: Flat 4 Ability view, 220 Kingsland Road, Lond | H38: Jacob Hill-Anderson | I38: N/A | J38: Current | K38: 45163 | L38: 45163 | M38: 45528 | N38: New Let | O38: Live Work | P38: 26000 | Q38: 2166.6667 | R38: 27456 | S38: =R38/12 -> 2288 | T38: 27600 | U38: =T38/12 -> 2300 | V38: 24960 | W38: NPB | Z38: =(W38-U38)/U38 -> #VALUE! | AA38: =(W38-S38)/S38 -> #VALUE! | AB38: 2425 | AC38: =(AB38-U38)/U38 -> 0.054347826 | AD38: =(AB38-S38)/S38 -> 0.059877622 | AE38: 2400 | AF38: =(AE38-U38)/U38 -> 0.043478261 | AG38: =(AE38-S38)/S38 -> 0.048951049 | AI38: Cleared | AJ38: 847.26 | AK38: 1 | AL38: 1 | AM38: S/C 1 bed/1 bath, o/p kitchen/living rm Rfb21TF | AO38: =SUM(AN38-U38)/U38 -> -1 | AP38: Jemma | AQ38: Sent
A39: Active | B39: =TEXT(C39,"mmmm") -> August | C39: 45517 | D39: BTR-London & SE | E39: Apex Gardens | F39: Nicole Freeman | G39: 1802 Aster Apts 822 Seven Sisters Rd London N | H39: Miao Ju and Daniel Kelshaw | I39: N/A | J39: Current | K39: 45152 | L39: 45152 | M39: 45517 | N39: New Let | O39: AST | P39: 24180 | Q39: 2015 | R39: 25584 | S39: =R39/12 -> 2132 | T39: 23880 | U39: =T39/12 -> 1990 | V39: 22560 | W39: 2165 | Z39: =(W39-U39)/U39 -> 0.087939698 | AA39: =(W39-S39)/S39 -> 0.015478424 | AB39: 2150 | AC39: =(AB39-U39)/U39 -> 0.08040201 | AD39: =(AB39-S39)/S39 -> 0.0084427767 | AE39: 2130 | AF39: =(AE39-U39)/U39 -> 0.070351759 | AG39: =(AE39-S39)/S39 -> -0.0009380863 | AI39: Cleared | AJ39: 548.964 | AK39: 1 | AL39: 1 | AM39: 1 bedroomWest | AN39: 2100 | AO39: =SUM(AN39-U39)/U39 -> 0.055276382 | AP39: Jemma | AQ39: Sent
A40: Active | B40: =TEXT(C40,"mmmm") -> August | C40: 45534 | D40: BTR-London & SE | E40: Apex Gardens | F40: Nicole Freeman | G40: 1105 Aster Apts 822 Seven Sisters Rd London N | H40: Mr Runjia Chen | I40: N/A | J40: Current | K40: 45169 | L40: 45169 | M40: 45534 | N40: New Let | O40: AST | P40: 23608 | Q40: 1967.3333 | R40: 25012 | S40: =R40/12 -> 2084.3333 | T40: 24600 | U40: =T40/12 -> 2050 | V40: 22560 | W40: 2045 | Z40: =(W40-U40)/U40 -> -0.0024390244 | AA40: =(W40-S40)/S40 -> -0.018870942 | AB40: 2150 | AC40: =(AB40-U40)/U40 -> 0.048780488 | AD40: =(AB40-S40)/S40 -> 0.031504878 | AE40: 2100 | AF40: =(AE40-U40)/U40 -> 0.024390244 | AG40: =(AE40-S40)/S40 -> 0.0075163921 | AI40: Cleared | AJ40: 548.964 | AK40: 1 | AL40: 1 | AM40: 1 bedroomEast | AO40: =SUM(AN40-U40)/U40 -> -1 | AP40: Jemma | AQ40: Sent
A41: Active | B41: =TEXT(C41,"mmmm") -> August | C41: 45534 | D41: BTR-London & SE | E41: Apex Gardens | F41: Nicole Freeman | G41: 1902 Aster Apts 822 Seven Sisters Rd London N | H41: Momoko Otsuka | I41: N/A | J41: Current | K41: 44835 | L41: 45169 | M41: 45534 | N41: Renewal | O41: AST | P41: 24180 | Q41: 2015 | R41: 25584 | S41: =R41/12 -> 2132 | T41: 24780 | U41: =T41/12 -> 2065 | V41: 22560 | W41: 2170 | Z41: =(W41-U41)/U41 -> 0.050847458 | AA41: =(W41-S41)/S41 -> 0.01782364 | AB41: 2175 | AC41: =(AB41-U41)/U41 -> 0.053268765 | AD41: =(AB41-S41)/S41 -> 0.020168856 | AE41: 2150 | AF41: =(AE41-U41)/U41 -> 0.041162228 | AG41: =(AE41-S41)/S41 -> 0.0084427767 | AI41: Cleared | AJ41: 548.964 | AK41: 1 | AL41: 1 | AM41: 1 bedroomWest | AO41: =SUM(AN41-U41)/U41 -> -1 | AP41: Jemma | AQ41: Sent | AR41: r2r required
A42: Active | B42: =TEXT(C42,"mmmm") -> August | C42: 45535 | D42: BTR-London & SE | E42: Apex Gardens | F42: Nicole Freeman | G42: 802 Aster Apts 822 Seven Sisters Rd London N1 | H42: Mr Grzegorz Telejko, Ms Flora Bihari-Kiss | I42: N/A | J42: Current | K42: 45170 | L42: 45170 | M42: 45535 | N42: New Let | O42: AST | P42: 23088 | Q42: 1924 | R42: 24440 | S42: =R42/12 -> 2036.6667 | T42: 23340 | U42: =T42/12 -> 1945 | V42: 21735 | W42: 2000 | Z42: =(W42-U42)/U42 -> 0.028277635 | AA42: =(W42-S42)/S42 -> -0.018003273 | AB42: 2075 | AC42: =(AB42-U42)/U42 -> 0.066838046 | AD42: =(AB42-S42)/S42 -> 0.018821604 | AE42: 2050 | AF42: =(AE42-U42)/U42 -> 0.053984576 | AG42: =(AE42-S42)/S42 -> 0.0065466448 | AI42: Cleared | AJ42: 548.964 | AK42: 1 | AL42: 1 | AM42: 1 bedroomWest | AO42: =SUM(AN42-U42)/U42 -> -1 | AP42: Jemma | AQ42: NTQ
A43: Pending | B43: =TEXT(C43,"mmmm") -> July | C43: 45491 | D43: BTR-London & SE | E43: Apex Gardens | F43: Nicole Freeman | G43: 1002 Aster Apts 822 Seven Sisters Rd London N | H43: Pedro Lins Conceição de Medeiros | I43: N/A | J43: Current | K43: 45310 | L43: 45310 | M43: 45491 | N43: New Let | O43: AST | P43: 23088 | Q43: 1924 | R43: 24440 | S43: =R43/12 -> 2036.6667 | T43: 24900 | U43: =T43/12 -> 2075 | V43: 21900 | W43: 2070 | Z43: =(W43-U43)/U43 -> -0.0024096386 | AA43: =(W43-S43)/S43 -> 0.016366612 | AB43: 2150 | AC43: =(AB43-U43)/U43 -> 0.036144578 | AD43: =(AB43-S43)/S43 -> 0.055646481 | AE43: 2135 | AF43: =(AE43-U43)/U43 -> 0.028915663 | AG43: =(AE43-S43)/S43 -> 0.048281506 | AI43: Cleared | AJ43: 548.964 | AK43: 1 | AL43: 1 | AM43: 1 bedroomWest | AO43: =SUM(AN43-U43)/U43 -> -1 | AP43: Jemma | AQ43: NTQ
A44: Active | B44: =TEXT(C44,"mmmm") -> July | C44: 45482 | D44: BTR-London & SE | E44: Apex Gardens | F44: Nicole Freeman | G44: 1103 Aster Apts 822 Seven Sisters Rd London N | H44: Selin Paeck & Jiyoon Sung | I44: N/A | J44: Current | K44: 44449 | L44: 45179 | M44: 45482 | N44: Renewal | O44: AST | P44: 29588 | Q44: 2465.6667 | R44: 30316 | S44: =R44/12 -> 2526.3333 | T44: 28980 | U44: =T44/12 -> 2415 | V44: 26760 | W44: 2625 | Z44: =(W44-U44)/U44 -> 0.086956522 | AA44: =(W44-S44)/S44 -> 0.039055284 | AB44: 2550 | AC44: =(AB44-U44)/U44 -> 0.055900621 | AD44: =(AB44-S44)/S44 -> 0.0093679905 | AE44: 2525 | AF44: =(AE44-U44)/U44 -> 0.045548654 | AG44: =(AE44-S44)/S44 -> -0.00052777411 | AI44: Cleared | AJ44: 839.592 | AK44: 2 | AL44: 2 | AM44: 2 bedroomSouth West | AO44: =SUM(AN44-U44)/U44 -> -1 | AP44: Jemma | AQ44: Sent
A45: Active | B45: =TEXT(C45,"mmmm") -> July | C45: 45504 | D45: BTR-London & SE | E45: Apex Gardens | F45: Nicole Freeman | G45: 2001 Aster Apts 822 Seven Sisters Rd London N | H45: A Jessa, L Longstreet, I Cavicchi | I45: N/A | J45: Current | K45: 44774 | L45: 45139 | M45: 45504 | N45: Renewal | O45: AST | P45: 39000 | Q45: 3250 | R45: 40456 | S45: =R45/12 -> 3371.3333 | T45: 37440 | U45: =T45/12 -> 3120 | V45: 35640 | W45: 3320 | Z45: =(W45-U45)/U45 -> 0.064102564 | AA45: =(W45-S45)/S45 -> -0.015226419 | AB45: 3300 | AC45: =(AB45-U45)/U45 -> 0.057692308 | AD45: =(AB45-S45)/S45 -> -0.02115879 | AE45: 3275 | AF45: =(AE45-U45)/U45 -> 0.049679487 | AG45: =(AE45-S45)/S45 -> -0.028574254 | AI45: Cleared | AJ45: 1130.22 | AK45: 3 | AL45: 2 | AM45: 3 bedroomNorth West | AN45: 3300 | AO45: =SUM(AN45-U45)/U45 -> 0.057692308 | AP45: Jemma | AQ45: Sent
A46: Active | B46: =TEXT(C46,"mmmm") -> July | C46: 45479 | D46: BTR-London & SE | E46: Apex Gardens | F46: Nicole Freeman | G46: 806 Aster Apts 822 Seven Sisters Rd London N1 | H46: Craig Burgess & Lauren Jade Zonneveld | I46: N/A | J46: Current | K46: 45114 | L46: 45114 | M46: 45479 | N46: New Let | O46: AST | P46: 27924 | Q46: 2327 | R46: 28652 | S46: =R46/12 -> 2387.6667 | T46: 28440 | U46: =T46/12 -> 2370 | V46: 24096 | W46: 2530 | Z46: =(W46-U46)/U46 -> 0.067510549 | AA46: =(W46-S46)/S46 -> 0.059611894 | AB46: 2550 | AC46: =(AB46-U46)/U46 -> 0.075949367 | AD46: =(AB46-S46)/S46 -> 0.067988273 | AE46: 2500 | AF46: =(AE46-U46)/U46 -> 0.054852321 | AG46: =(AE46-S46)/S46 -> 0.047047327 | AI46: Cleared | AJ46: 828.828 | AK46: 2 | AL46: 2 | AM46: 2 bedroomNorth East | AO46: =SUM(AN46-U46)/U46 -> -1 | AP46: Jemma | AQ46: Sent
A47: Active | B47: =TEXT(C47,"mmmm") -> August | C47: 45509 | D47: BTR-London & SE | E47: Apex Gardens | F47: Nicole Freeman | G47: 1904 Aster Apts 822 Seven Sisters Rd London N | H47: Miss Anna Kuforiji and Miss Esther Kuforiji | I47: N/A | J47: Current | K47: 44414 | L47: 45144 | M47: 45509 | N47: Renewal | O47: AST | P47: 31252 | Q47: 2604.3333 | R47: 32032 | S47: =R47/12 -> 2669.3333 | T47: 28800 | U47: =T47/12 -> 2400 | V47: 27075.6 | W47: 2590 | Z47: =(W47-U47)/U47 -> 0.079166667 | AA47: =(W47-S47)/S47 -> -0.02972028 | AB47: 2625 | AC47: =(AB47-U47)/U47 -> 0.09375 | AD47: =(AB47-S47)/S47 -> -0.016608392 | AE47: 2600 | AF47: =(AE47-U47)/U47 -> 0.083333333 | AG47: =(AE47-S47)/S47 -> -0.025974026 | AI47: Cleared | AJ47: 968.76 | AK47: 2 | AL47: 2 | AM47: 2 bedroomNorth East | AN47: 2600 | AO47: =SUM(AN47-U47)/U47 -> 0.083333333 | AP47: Jemma | AQ47: Sent
A48: Active | B48: =TEXT(C48,"mmmm") -> August | C48: 45530 | D48: BTR-London & SE | E48: Apex Gardens | F48: Nicole Freeman | G48: 108 Aster Apts 822 Seven Sisters Rd London N1 | H48: Sean Innes and Jamie Hyde Willis | I48: N/A | J48: Current | K48: 44435 | L48: 45165 | M48: 45530 | N48: Renewal | O48: AST | P48: 27248 | Q48: 2270.6667 | R48: 27976 | S48: =R48/12 -> 2331.3333 | T48: 27000 | U48: =T48/12 -> 2250 | V48: 23940 | W48: 2520 | Z48: =(W48-U48)/U48 -> 0.12 | AA48: =(W48-S48)/S48 -> 0.080926508 | AB48: 2365 | AC48: =(AB48-U48)/U48 -> 0.051111111 | AD48: =(AB48-S48)/S48 -> 0.014440949 | AE48: 2340 | AF48: =(AE48-U48)/U48 -> 0.04 | AG48: =(AE48-S48)/S48 -> 0.0037174721 | AI48: Cleared | AJ48: 828.828 | AK48: 2 | AL48: 2 | AM48: 2 bedroomNorth East | AO48: =SUM(AN48-U48)/U48 -> -1 | AP48: Jemma | AQ48: Sent
A49: Active | B49: =TEXT(C49,"mmmm") -> August | C49: 45534 | D49: BTR-London & SE | E49: Apex Gardens | F49: Nicole Freeman | G49: 605 Aster Apts 822 Seven Sisters Rd London N1 | H49: Mr Seng Poh Lee, Mr Qingshan Wen | I49: N/A | J49: Current | K49: 45169 | L49: 45169 | M49: 45534 | N49: New Let | O49: AST | P49: 27300 | Q49: 2275 | R49: 28028 | S49: =R49/12 -> 2335.6667 | T49: 28980 | U49: =T49/12 -> 2415 | V49: 27000 | W49: 2560 | Z49: =(W49-U49)/U49 -> 0.060041408 | AA49: =(W49-S49)/S49 -> 0.09604681 | AB49: 2550 | AC49: =(AB49-U49)/U49 -> 0.055900621 | AD49: =(AB49-S49)/S49 -> 0.091765377 | AE49: 2515 | AF49: =(AE49-U49)/U49 -> 0.041407867 | AG49: =(AE49-S49)/S49 -> 0.076780362 | AI49: Cleared | AJ49: 775.008 | AK49: 2 | AL49: 2 | AM49: 2 bedroomSouth East | AO49: =SUM(AN49-U49)/U49 -> -1 | AP49: Jemma | AQ49: Sent
A50: Active | B50: =TEXT(C50,"mmmm") -> August | C50: 45517 | D50: BTR-London & SE | E50: Apex Gardens | F50: Nicole Freeman | G50: 1401 Aster Apts 822 Seven Sisters Rd London N | H50: T Ranjan, K Doshi, K N Quang & I G Garrido | I50: N/A | J50: Current | K50: 45152 | L50: 45152 | M50: 45517 | N50: New Let | O50: AST | P50: 37544 | Q50: 3128.6667 | R50: 38948 | S50: =R50/12 -> 3245.6667 | T50: 37320 | U50: =T50/12 -> 3110 | V50: 35940 | W50: 3320 | Z50: =(W50-U50)/U50 -> 0.067524116 | AA50: =(W50-S50)/S50 -> 0.022902331 | AB50: 3265 | AC50: =(AB50-U50)/U50 -> 0.049839228 | AD50: =(AB50-S50)/S50 -> 0.0059566602 | AE50: 3245 | AF50: =(AE50-U50)/U50 -> 0.04340836 | AG50: =(AE50-S50)/S50 -> -0.00020540207 | AI50: Cleared | AJ50: 1119.456 | AK50: 3 | AL50: 2 | AM50: 3 bedroomNorth West | AO50: =SUM(AN50-U50)/U50 -> -1 | AP50: Jemma | AQ50: Sent
A51: Active | B51: =TEXT(C51,"mmmm") -> August | C51: 45517 | D51: BTR-London & SE | E51: Apex Gardens | F51: Nicole Freeman | G51: 1801 Aster Apts 822 Seven Sisters Rd London N | H51: P Airon, A Das & K A Liljequist | I51: N/A | J51: Current | K51: 45152 | L51: 45152 | M51: 45517 | N51: New Let | O51: AST | P51: 38428 | Q51: 3202.3333 | R51: 39884 | S51: =R51/12 -> 3323.6667 | T51: 37020 | U51: =T51/12 -> 3085 | V51: 35640 | W51: 3295 | Z51: =(W51-U51)/U51 -> 0.068071313 | AA51: =(W51-S51)/S51 -> -0.0086250125 | AB51: 3325 | AC51: =(AB51-U51)/U51 -> 0.077795786 | AD51: =(AB51-S51)/S51 -> 0.00040116337 | AE51: 3300 | AF51: =(AE51-U51)/U51 -> 0.069692058 | AG51: =(AE51-S51)/S51 -> -0.0071206499 | AI51: Cleared | AJ51: 1119.456 | AK51: 3 | AL51: 2 | AM51: 3 bedroomNorth West | AO51: =SUM(AN51-U51)/U51 -> -1 | AP51: Jemma | AQ51: Sent
A52: Active | B52: =TEXT(C52,"mmmm") -> August | C52: 45527 | D52: BTR-London & SE | E52: Apex Gardens | F52: Nicole Freeman | G52: 101 Aster Apts 822 Seven Sisters Rd London N1 | H52: Mr Rodriguez, Mr Thomas, Ms Qiu | I52: N/A | J52: Current | K52: 44797 | L52: 45162 | M52: 45527 | N52: Renewal | O52: AST | P52: 35776 | Q52: 2981.3333 | R52: 37076 | S52: =R52/12 -> 3089.6667 | T52: 36480 | U52: =T52/12 -> 3040 | V52: 34500 | W52: 3230 | Z52: =(W52-U52)/U52 -> 0.0625 | AA52: =(W52-S52)/S52 -> 0.045420218 | AB52: 3150 | AC52: =(AB52-U52)/U52 -> 0.036184211 | AD52: =(AB52-S52)/S52 -> 0.019527457 | AE52: 3095 | AF52: =(AE52-U52)/U52 -> 0.018092105 | AG52: =(AE52-S52)/S52 -> 0.0017261841 | AI52: Cleared | AJ52: 1124 | AK52: 3 | AL52: 2 | AM52: 3 bedroomNorth West | AO52: =SUM(AN52-U52)/U52 -> -1 | AP52: Jemma | AQ52: Sent
A53: Active | B53: =TEXT(C53,"mmmm") -> August | C53: 45530 | D53: BTR-London & SE | E53: Apex Gardens | F53: Nicole Freeman | G53: 501 Aster Apts 822 Seven Sisters Rd London N1 | H53: Luke Elliot, Damien Lynch & Cal Elliott | I53: N/A | J53: Current | K53: 44435 | L53: 45165 | M53: 45530 | N53: Renewal | O53: AST | P53: 35776 | Q53: 2981.3333 | R53: 37076 | S53: =R53/12 -> 3089.6667 | T53: 36540 | U53: =T53/12 -> 3045 | V53: 34080 | W53: 3240 | Z53: =(W53-U53)/U53 -> 0.064039409 | AA53: =(W53-S53)/S53 -> 0.048656813 | AB53: 3150 | AC53: =(AB53-U53)/U53 -> 0.034482759 | AD53: =(AB53-S53)/S53 -> 0.019527457 | AE53: 3095 | AF53: =(AE53-U53)/U53 -> 0.016420361 | AG53: =(AE53-S53)/S53 -> 0.0017261841 | AI53: Cleared | AJ53: 1119.456 | AK53: 3 | AL53: 2 | AM53: 3 bedroomNorth West | AO53: =SUM(AN53-U53)/U53 -> -1 | AP53: Jemma | AQ53: Sent
A54: Active | B54: =TEXT(C54,"mmmm") -> August | C54: 45531 | D54: BTR-London & SE | E54: Apex Gardens | F54: Nicole Freeman | G54: 601 Aster Apts 822 Seven Sisters Rd London N1 | H54: P Soni, N N Kumar & M Muralidhar | I54: N/A | J54: Current | K54: 45166 | L54: 45166 | M54: 45531 | N54: New Let | O54: AST | P54: 36660 | Q54: 3055 | R54: 38012 | S54: =R54/12 -> 3167.6667 | T54: 37200 | U54: =T54/12 -> 3100 | V54: 35460 | W54: 3275 | Z54: =(W54-U54)/U54 -> 0.056451613 | AA54: =(W54-S54)/S54 -> 0.033884037 | AB54: 3225 | AC54: =(AB54-U54)/U54 -> 0.040322581 | AD54: =(AB54-S54)/S54 -> 0.018099548 | AE54: 3175 | AF54: =(AE54-U54)/U54 -> 0.024193548 | AG54: =(AE54-S54)/S54 -> 0.0023150584 | AI54: Cleared | AJ54: 1119.456 | AK54: 3 | AL54: 2 | AM54: 3 bedroomNorth West | AN54: 3175 | AO54: =SUM(AN54-U54)/U54 -> 0.024193548 | AP54: Jemma | AQ54: Sent | AR54: r2r required
A55: Active | B55: =TEXT(C55,"mmmm") -> August | C55: 45517 | D55: BTR-London & SE | E55: Argo Apartments | F55: Fatma Azakli | G55: 69 Argo Apts, 4 Silvertown Way,London,E16 1ED | H55: Blake Max & Mared Parry | I55: These residents can be very rude and threaten to go on social media for rent increases etc. | J55: Current | K55: 44422 | L55: 45152 | M55: 45517 | N55: Renewal | O55: AST | P55: 22980 | Q55: 1915 | R55: 23820 | S55: =R55/12 -> 1985 | T55: 21000 | U55: =T55/12 -> 1750 | V55: 19200 | W55: 2110 | Z55: =(W55-U55)/U55 -> 0.20571429 | AA55: =(W55-S55)/S55 -> 0.062972292 | AB55: 1995 | AC55: =(AB55-U55)/U55 -> 0.14 | AD55: =(AB55-S55)/S55 -> 0.0050377834 | AE55: =$S55 -> 1985 | AF55: =(AE55-U55)/U55 -> 0.13428571 | AG55: =(AE55-S55)/S55 -> 0 | AH55: Please do not offer yet. | AI55: Cleared | AJ55: 572 | AK55: 1 | AL55: 1 | AM55: 1 bed & 1 bath South-West Right9th floor | AO55: =SUM(AN55-U55)/U55 -> -1 | AP55: Jemma | AQ55: Sent
A56: Active | B56: =TEXT(C56,"mmmm") -> August | C56: 45522 | D56: BTR-London & SE | E56: Argo Apartments | F56: Fatma Azakli | G56: 98 Argo Apts, 4 Silvertown Way,London,E16 1YD | H56: Mr Suparno Guha | I56: N/A | J56: Current | K56: 44427 | L56: 45157 | M56: 45522 | N56: Renewal | O56: AST | P56: 23640 | Q56: 1970 | R56: 23820 | S56: =R56/12 -> 1985 | T56: 21600 | U56: =T56/12 -> 1800 | V56: 20100 | W56: 2120 | Z56: =(W56-U56)/U56 -> 0.17777778 | AA56: =(W56-S56)/S56 -> 0.068010076 | AB56: 1985 | AC56: =(AB56-U56)/U56 -> 0.10277778 | AD56: =(AB56-S56)/S56 -> 0 | AE56: =$S56 -> 1985 | AF56: =(AE56-U56)/U56 -> 0.10277778 | AG56: =(AE56-S56)/S56 -> 0 | AI56: Cleared | AJ56: 572 | AK56: 1 | AL56: 1 | AM56: 1 bed & 1 bath South-West Right12th floor | AN56: 1985 | AO56: =SUM(AN56-U56)/U56 -> 0.10277778 | AP56: Jemma | AQ56: Sent
A57: Active | B57: =TEXT(C57,"mmmm") -> August | C57: 45526 | D57: BTR-London & SE | E57: Argo Apartments | F57: Fatma Azakli | G57: 58 Argo Apts, 4 Silvertown Way,London,E16 1ED | H57: Reema Sohanlal Bohara and Rohit Prakash Jain | I57: N/A | J57: Current | K57: 44431 | L57: 45161 | M57: 45526 | N57: Renewal | O57: AST | P57: 22980 | Q57: 1915 | R57: 23820 | S57: =R57/12 -> 1985 | T57: 21540 | U57: =T57/12 -> 1795 | V57: 19800 | W57: 2050 | Z57: =(W57-U57)/U57 -> 0.14206128 | AA57: =(W57-S57)/S57 -> 0.032745592 | AB57: 1985 | AC57: =(AB57-U57)/U57 -> 0.10584958 | AD57: =(AB57-S57)/S57 -> 0 | AE57: =$S57 -> 1985 | AF57: =(AE57-U57)/U57 -> 0.10584958 | AG57: =(AE57-S57)/S57 -> 0 | AI57: Cleared | AJ57: 572 | AK57: 1 | AL57: 1 | AM57: 1 bed & 1 bath South-West Right8th floor | AO57: =SUM(AN57-U57)/U57 -> -1 | AP57: Jemma | AQ57: Sent | AR57: r2r reqiured
A58: Active | B58: =TEXT(C58,"mmmm") -> August | C58: 45531 | D58: BTR-London & SE | E58: Argo Apartments | F58: Fatma Azakli | G58: 22 Argo Apts, 4 Silvertown Way,London,E16 1ED | H58: AGUSTIN PALAZON HERNANDEZ | I58: N/A | J58: Current | K58: 45166 | L58: 45166 | M58: 45531 | N58: New Let | O58: AST | P58: 22500 | Q58: 1875 | R58: 23700 | S58: =R58/12 -> 1975 | T58: 23100 | U58: =T58/12 -> 1925 | V58: 19800 | W58: 2050 | Z58: =(W58-U58)/U58 -> 0.064935065 | AA58: =(W58-S58)/S58 -> 0.037974684 | AB58: 2000 | AC58: =(AB58-U58)/U58 -> 0.038961039 | AD58: =(AB58-S58)/S58 -> 0.012658228 | AE58: =$S58 -> 1975 | AF58: =(AE58-U58)/U58 -> 0.025974026 | AG58: =(AE58-S58)/S58 -> 0 | AI58: Cleared | AJ58: 564 | AK58: 1 | AL58: 1 | AM58: 1 bed & 1 bath North-West4th floor | AO58: =SUM(AN58-U58)/U58 -> -1 | AP58: Jemma | AQ58: Sent
A59: Active | B59: =TEXT(C59,"mmmm") -> August | C59: 45534 | D59: BTR-London & SE | E59: Argo Apartments | F59: Fatma Azakli | G59: 132 Argo Apts,4 Silvertown Way,London,E16 1YD | H59: Martin Walter | I59: Nice resident, but hard to get hold of sometimes. Please let the team know if any issues contacting. | J59: Current | K59: 44439 | L59: 45169 | M59: 45534 | N59: Renewal | O59: AST | P59: 24600 | Q59: 2050 | R59: 23700 | S59: =R59/12 -> 1975 | T59: 22800 | U59: =T59/12 -> 1900 | V59: 20400 | W59: 2095 | Z59: =(W59-U59)/U59 -> 0.10263158 | AA59: =(W59-S59)/S59 -> 0.060759494 | AB59: 2000 | AC59: =(AB59-U59)/U59 -> 0.052631579 | AD59: =(AB59-S59)/S59 -> 0.012658228 | AE59: =$S59 -> 1975 | AF59: =(AE59-U59)/U59 -> 0.039473684 | AG59: =(AE59-S59)/S59 -> 0 | AI59: Cleared | AJ59: 564 | AK59: 1 | AL59: 1 | AM59: 1 bed & 1 bath North-West15th floor | AO59: =SUM(AN59-U59)/U59 -> -1 | AP59: Jemma | AQ59: Sent
A60: Active | B60: =TEXT(C60,"mmmm") -> August | C60: 45535 | D60: BTR-London & SE | E60: Argo Apartments | F60: Fatma Azakli | G60: 109 Argo Apts,4 Silvertown Way,London,E16 1YD | H60: Mears Ltd | I60: N/A | J60: Current | K60: 44440 | L60: 45170 | M60: 45535 | N60: Renewal | O60: Comp-Let | P60: 23640 | Q60: 1970 | R60: 23820 | S60: =R60/12 -> 1985 | T60: 21960 | U60: =T60/12 -> 1830 | V60: 20700 | W60: 2130 | Z60: =(W60-U60)/U60 -> 0.16393443 | AA60: =(W60-S60)/S60 -> 0.073047859 | AB60: 2000 | AC60: =(AB60-U60)/U60 -> 0.092896175 | AD60: =(AB60-S60)/S60 -> 0.0075566751 | AE60: =$S60 -> 1985 | AF60: =(AE60-U60)/U60 -> 0.084699454 | AG60: =(AE60-S60)/S60 -> 0 | AI60: Credit | AJ60: 572 | AK60: 1 | AL60: 1 | AM60: 1 bed & 1 bath South-West Right13th floor | AO60: =SUM(AN60-U60)/U60 -> -1 | AP60: Sophie
A61: Pending | B61: =TEXT(C61,"mmmm") -> July | C61: 45480 | D61: BTR-London & SE | E61: Argo Apartments | F61: Fatma Azakli | G61: 106 Argo Apts,4 Silvertown Way,London,E16 1YD | H61: Tien Tu & Tam Minh Tu | I61: N/A | J61: Current | K61: 45299 | L61: 45299 | M61: 45480 | N61: New Let | O61: AST | P61: 29400 | Q61: 2450 | R61: 29340 | S61: =R61/12 -> 2445 | T61: 29820 | U61: =T61/12 -> 2485 | V61: 25980 | W61: 2620 | Z61: =(W61-U61)/U61 -> 0.054325956 | AA61: =(W61-S61)/S61 -> 0.071574642 | AB61: 2585 | AC61: =(AB61-U61)/U61 -> 0.040241449 | AD61: =(AB61-S61)/S61 -> 0.057259714 | AE61: 2525 | AF61: =(AE61-U61)/U61 -> 0.016096579 | AG61: =(AE61-S61)/S61 -> 0.032719836 | AI61: Cleared | AJ61: 808 | AK61: 2 | AL61: 2 | AM61: 2 bed & 2 bath South-West13th floor | AN61: 2585 | AO61: =SUM(AN61-U61)/U61 -> 0.040241449 | AP61: Jemma | AQ61: Sent
A62: Active | B62: =TEXT(C62,"mmmm") -> July | C62: 45480 | D62: BTR-London & SE | E62: Argo Apartments | F62: Fatma Azakli | G62: 112 Argo Apts,4 Silvertown Way,London,E16 1YD | H62: Mears Ltd | I62: N/A | J62: Current | K62: 44385 | L62: 45115 | M62: 45480 | N62: Renewal | O62: Comp-Let | P62: 23520 | Q62: 1960 | R62: 23700 | S62: =R62/12 -> 1975 | T62: 22320 | U62: =T62/12 -> 1860 | V62: 21012 | W62: 2070 | Z62: =(W62-U62)/U62 -> 0.11290323 | AA62: =(W62-S62)/S62 -> 0.048101266 | AB62: 1995 | AC62: =(AB62-U62)/U62 -> 0.072580645 | AD62: =(AB62-S62)/S62 -> 0.010126582 | AE62: 1975 | AF62: =(AE62-U62)/U62 -> 0.061827957 | AG62: =(AE62-S62)/S62 -> 0 | AI62: Credit | AJ62: 564 | AK62: 1 | AL62: 1 | AM62: 1 bed & 1 bath North-West13th floor | AN62: 1995 | AO62: =SUM(AN62-U62)/U62 -> 0.072580645 | AP62: Sophie | AQ62: processed | AR62: agreed
A63: Active | B63: =TEXT(C63,"mmmm") -> July | C63: 45491 | D63: BTR-London & SE | E63: Argo Apartments | F63: Fatma Azakli | G63: 19 Argo Apts, 4 Silvertown Way,London,E16 1ED | H63: Lauren Neill & Yida Zhang | I63: N/A | J63: Current | K63: 44761 | L63: 45126 | M63: 45491 | N63: Renewal | O63: AST | P63: 22560 | Q63: 1880 | R63: 23820 | S63: =R63/12 -> 1985 | T63: 22500 | U63: =T63/12 -> 1875 | V63: 21000 | W63: 2090 | Z63: =(W63-U63)/U63 -> 0.11466667 | AA63: =(W63-S63)/S63 -> 0.052896725 | AB63: 1995 | AC63: =(AB63-U63)/U63 -> 0.064 | AD63: =(AB63-S63)/S63 -> 0.0050377834 | AE63: 1985 | AF63: =(AE63-U63)/U63 -> 0.058666667 | AG63: =(AE63-S63)/S63 -> 0 | AI63: Cleared | AJ63: 572 | AK63: 1 | AL63: 1 | AM63: 1 bed & 1 bath South-West Right4th floor | AN63: 1985 | AO63: =SUM(AN63-U63)/U63 -> 0.058666667 | AP63: Jemma | AQ63: Sent
A64: Active | B64: =TEXT(C64,"mmmm") -> July | C64: 45482 | D64: BTR-London & SE | E64: Argo Apartments | F64: Fatma Azakli | G64: 27 Argo Apts, 4 Silvertown Way,London,E16 1ED | H64: Mears Ltd | I64: N/A | J64: Current | K64: 45117 | L64: 45117 | M64: 45482 | N64: New Let | O64: Comp-Let | P64: 22620 | Q64: 1885 | R64: 23700 | S64: =R64/12 -> 1975 | T64: 22020 | U64: =T64/12 -> 1835 | V64: 20760 | W64: 2030 | Z64: =(W64-U64)/U64 -> 0.10626703 | AA64: =(W64-S64)/S64 -> 0.027848101 | AB64: 1995 | AC64: =(AB64-U64)/U64 -> 0.08719346 | AD64: =(AB64-S64)/S64 -> 0.010126582 | AE64: 1975 | AF64: =(AE64-U64)/U64 -> 0.076294278 | AG64: =(AE64-S64)/S64 -> 0 | AI64: Credit | AJ64: 564 | AK64: 1 | AL64: 1 | AM64: 1 bed & 1 bath South-West Left5th floor | AN64: 1995 | AO64: =SUM(AN64-U64)/U64 -> 0.08719346 | AP64: Sophie | AQ64: processed | AR64: agreed
A65: Active | B65: =TEXT(C65,"mmmm") -> July | C65: 45499 | D65: BTR-London & SE | E65: Argo Apartments | F65: Fatma Azakli | G65: 4 Argo Apts, 4 Silvertown Way, London,E16 1ED | H65: Matthew Smith & Thu Huong Dao | I65: N/A | J65: Current | K65: 45134 | L65: 45134 | M65: 45499 | N65: New Let | O65: AST | P65: 28140 | Q65: 2345 | R65: 29100 | S65: =R65/12 -> 2425 | T65: 28020 | U65: =T65/12 -> 2335 | V65: 23400 | W65: 2480 | Z65: =(W65-U65)/U65 -> 0.062098501 | AA65: =(W65-S65)/S65 -> 0.022680412 | AB65: 2460 | AC65: =(AB65-U65)/U65 -> 0.053533191 | AD65: =(AB65-S65)/S65 -> 0.01443299 | AE65: 2425 | AF65: =(AE65-U65)/U65 -> 0.038543897 | AG65: =(AE65-S65)/S65 -> 0 | AI65: Cleared | AJ65: 794 | AK65: 2 | AL65: 2 | AM65: 2 bed & 2 bath North-West2nd floor | AO65: =SUM(AN65-U65)/U65 -> -1 | AP65: Jemma | AQ65: Sent
A66: Active | B66: =TEXT(C66,"mmmm") -> July | C66: 45491 | D66: BTR-London & SE | E66: Argo Apartments | F66: Fatma Azakli | G66: 44 Argo Apts, 4 Silvertown Way,London,E16 1ED | H66: Wei Jin & shan li | I66: N/A | J66: Current | K66: 45310 | L66: 45310 | M66: 45491 | N66: New Let | O66: AST | P66: 28560 | Q66: 2380 | R66: 29220 | S66: =R66/12 -> 2435 | T66: 29640 | U66: =T66/12 -> 2470 | V66: 28140 | W66: 2530 | Z66: =(W66-U66)/U66 -> 0.024291498 | AA66: =(W66-S66)/S66 -> 0.039014374 | AB66: 2565 | AC66: =(AB66-U66)/U66 -> 0.038461538 | AD66: =(AB66-S66)/S66 -> 0.05338809 | AE66: 2500 | AF66: =(AE66-U66)/U66 -> 0.012145749 | AG66: =(AE66-S66)/S66 -> 0.026694045 | AI66: Cleared | AJ66: 799 | AK66: 2 | AL66: 2 | AM66: 2 bed & 2 bath East Left6th floor | AO66: =SUM(AN66-U66)/U66 -> -1 | AP66: Jemma | AQ66: Sent
A67: Pending | B67: =TEXT(C67,"mmmm") -> July | C67: 45495 | D67: BTR-London & SE | E67: Argo Apartments | F67: Fatma Azakli | G67: 97 Argo Apts, 4 Silvertown Way,London,E16 1YD | H67: Mr E Katsampouris & Miss A E Bakou | I67: N/A | J67: Current | K67: 44400 | L67: 45130 | M67: 45495 | N67: Renewal | O67: AST | P67: 23520 | Q67: 1960 | R67: 23700 | S67: =R67/12 -> 1975 | T67: 22200 | U67: =T67/12 -> 1850 | V67: 20100 | W67: 2115 | Z67: =(W67-U67)/U67 -> 0.14324324 | AA67: =(W67-S67)/S67 -> 0.070886076 | AB67: 1995 | AC67: =(AB67-U67)/U67 -> 0.078378378 | AD67: =(AB67-S67)/S67 -> 0.010126582 | AE67: 1975 | AF67: =(AE67-U67)/U67 -> 0.067567568 | AG67: =(AE67-S67)/S67 -> 0 | AI67: Cleared | AJ67: 564 | AK67: 1 | AL67: 1 | AM67: 1 bed & 1 bath South-West Left12th floor | AN67: 1975 | AO67: =SUM(AN67-U67)/U67 -> 0.067567568 | AP67: Jemma | AQ67: Sent
A68: Active | B68: =TEXT(C68,"mmmm") -> August | C68: 45535 | D68: BTR-London & SE | E68: Argo Apartments | F68: Fatma Azakli | G68: 50 Argo Apts, 4 Silvertown Way,London,E16 1ED | H68: Mr Ioannis Arampatzis | I68: N/A | J68: Current | K68: 44440 | L68: 45170 | M68: 45535 | N68: Renewal | O68: AST | P68: 24000 | Q68: 2000 | R68: 24840 | S68: =R68/12 -> 2070 | T68: 23100 | U68: =T68/12 -> 1925 | V68: 20700 | W68: 2180 | Z68: =(W68-U68)/U68 -> 0.13246753 | AA68: =(W68-S68)/S68 -> 0.053140097 | AB68: 2070 | AC68: =(AB68-U68)/U68 -> 0.075324675 | AD68: =(AB68-S68)/S68 -> 0 | AE68: =$S68 -> 2070 | AF68: =(AE68-U68)/U68 -> 0.075324675 | AG68: =(AE68-S68)/S68 -> 0 | AI68: Cleared | AJ68: 728 | AK68: 1 | AL68: 1 | AM68: 1 bed & 1 bath West7th floor | AO68: =SUM(AN68-U68)/U68 -> -1 | AP68: Jemma | AQ68: Sent
A69: Active | B69: =TEXT(C69,"mmmm") -> August | C69: 45508 | D69: BTR-London & SE | E69: Argo Apartments | F69: Fatma Azakli | G69: 46 Argo Apts, 4 Silvertown Way,London,E16 1ED | H69: Mears Ltd | I69: N/A | J69: Current | K69: 43195 | L69: 45143 | M69: 45508 | N69: Renewal | O69: Comp-Let | P69: 28740 | Q69: 2395 | R69: 29340 | S69: =R69/12 -> 2445 | T69: 23940 | U69: =T69/12 -> 1995 | V69: 22570.08 | W69: 2540 | Z69: =(W69-U69)/U69 -> 0.27318296 | AA69: =(W69-S69)/S69 -> 0.038854806 | AB69: 2450 | AC69: =(AB69-U69)/U69 -> 0.22807018 | AD69: =(AB69-S69)/S69 -> 0.0020449898 | AE69: =$S69 -> 2445 | AF69: =(AE69-U69)/U69 -> 0.22556391 | AG69: =(AE69-S69)/S69 -> 0 | AI69: Credit | AJ69: 808 | AK69: 2 | AL69: 2 | AM69: 2 bed & 2 bath South-West7th floor | AN69: 2445 | AO69: =SUM(AN69-U69)/U69 -> 0.22556391 | AP69: Sophie | AQ69: signing | AR69: agreed
A70: Active | B70: =TEXT(C70,"mmmm") -> August | C70: 45512 | D70: BTR-London & SE | E70: Argo Apartments | F70: Fatma Azakli | G70: 113 Argo Apts,4 Silvertown Way,London,E16 1YD | H70: Ms Aysha Choudhry & Miss Shriya Prasad | I70: N/A | J70: Current | K70: 44417 | L70: 45147 | M70: 45512 | N70: Renewal | O70: AST | P70: 29400 | Q70: 2450 | R70: 29340 | S70: =R70/12 -> 2445 | T70: 26100 | U70: =T70/12 -> 2175 | V70: 23722.2 | W70: 2575 | Z70: =(W70-U70)/U70 -> 0.18390805 | AA70: =(W70-S70)/S70 -> 0.053169734 | AB70: 2450 | AC70: =(AB70-U70)/U70 -> 0.12643678 | AD70: =(AB70-S70)/S70 -> 0.0020449898 | AE70: =$S70 -> 2445 | AF70: =(AE70-U70)/U70 -> 0.12413793 | AG70: =(AE70-S70)/S70 -> 0 | AI70: Cleared | AJ70: 808 | AK70: 2 | AL70: 2 | AM70: 2 bed & 2 bath North-West Dual13th floor | AO70: =SUM(AN70-U70)/U70 -> -1 | AP70: Jemma | AQ70: Sent
A71: Active | B71: =TEXT(C71,"mmmm") -> August | C71: 45512 | D71: BTR-London & SE | E71: Argo Apartments | F71: Fatma Azakli | G71: 81 Argo Apts, 4 Silvertown Way,London,E16 1YD | H71: Mears Ltd | I71: N/A | J71: Current | K71: 44386 | L71: 45147 | M71: 45512 | N71: Renewal | O71: Comp-Let | P71: 28620 | Q71: 2385 | R71: 29100 | S71: =R71/12 -> 2425 | T71: 26040 | U71: =T71/12 -> 2170 | V71: 24550.2 | W71: 2535 | Z71: =(W71-U71)/U71 -> 0.16820276 | AA71: =(W71-S71)/S71 -> 0.045360825 | AB71: 2450 | AC71: =(AB71-U71)/U71 -> 0.12903226 | AD71: =(AB71-S71)/S71 -> 0.010309278 | AE71: =$S71 -> 2425 | AF71: =(AE71-U71)/U71 -> 0.11751152 | AG71: =(AE71-S71)/S71 -> 0 | AI71: Credit | AJ71: 794 | AK71: 2 | AL71: 2 | AM71: 2 bed & 2 bath North-West10th floor | AN71: 2425 | AO71: =SUM(AN71-U71)/U71 -> 0.11751152 | AP71: Sophie | AQ71: signing | AR71: agreed
A72: Pending | B72: =TEXT(C72,"mmmm") -> July | C72: 45503 | D72: BTR-London & SE | E72: Argo Apartments | F72: Fatma Azakli | G72: 35 Argo Apts, 4 Silvertown Way,London,E16 1ED | H72: Owen Buchan and Harry Sivills | I72: They will complaing about Virgin TV since the change over from Glide and will challenge any increase. | J72: Current | K72: 44408 | L72: 45138 | M72: 45503 | N72: Renewal | O72: AST | P72: 28560 | Q72: 2380 | R72: 29220 | S72: =R72/12 -> 2435 | T72: 25320 | U72: =T72/12 -> 2110 | V72: 22980 | W72: 2530 | Z72: =(W72-U72)/U72 -> 0.19905213 | AA72: =(W72-S72)/S72 -> 0.039014374 | AB72: 2430 | AC72: =(AB72-U72)/U72 -> 0.15165877 | AD72: =(AB72-S72)/S72 -> -0.0020533881 | AE72: 2415 | AF72: =(AE72-U72)/U72 -> 0.14454976 | AG72: =(AE72-S72)/S72 -> -0.0082135524 | AH72: Please do not offer yet. | AI72: Cleared | AJ72: 799 | AK72: 2 | AL72: 2 | AM72: 2 bed & 2 bath East Right5th floor | AO72: =SUM(AN72-U72)/U72 -> -1 | AP72: Jemma | AQ72: On Hold
A73: Active | B73: =TEXT(C73,"mmmm") -> August | C73: 45513 | D73: BTR-London & SE | E73: Argo Apartments | F73: Fatma Azakli | G73: 14 Argo Apts, 4 Silvertown Way,London,E16 1ED | H73: Advait Abhay Vaidya & Shaun Homiar Poonawala | I73: N/A | J73: Current | K73: 44418 | L73: 45148 | M73: 45513 | N73: Renewal | O73: AST | P73: 28260 | Q73: 2355 | R73: 29220 | S73: =R73/12 -> 2435 | T73: 25200 | U73: =T73/12 -> 2100 | V73: 23100 | W73: 2530 | Z73: =(W73-U73)/U73 -> 0.2047619 | AA73: =(W73-S73)/S73 -> 0.039014374 | AB73: 2425 | AC73: =(AB73-U73)/U73 -> 0.1547619 | AD73: =(AB73-S73)/S73 -> -0.0041067762 | AE73: =$S73 -> 2435 | AF73: =(AE73-U73)/U73 -> 0.15952381 | AG73: =(AE73-S73)/S73 -> 0 | AI73: Cleared | AJ73: 799 | AK73: 2 | AL73: 2 | AM73: 2 bed & 2 bath East Left3rd floor | AO73: =SUM(AN73-U73)/U73 -> -1 | AP73: Jemma | AQ73: Sent
A74: Active | B74: =TEXT(C74,"mmmm") -> August | C74: 45514 | D74: BTR-London & SE | E74: Argo Apartments | F74: Fatma Azakli | G74: 36 Argo Apts, 4 Silvertown Way,London,E16 1ED | H74: Chi Cheung & Sui Chang | I74: N/A | J74: Current | K74: 45149 | L74: 45149 | M74: 45514 | N74: New Let | O74: AST | P74: 28620 | Q74: 2385 | R74: 29340 | S74: =R74/12 -> 2445 | T74: 29400 | U74: =T74/12 -> 2450 | V74: 23340 | W74: 2550 | Z74: =(W74-U74)/U74 -> 0.040816327 | AA74: =(W74-S74)/S74 -> 0.042944785 | AB74: 2550 | AC74: =(AB74-U74)/U74 -> 0.040816327 | AD74: =(AB74-S74)/S74 -> 0.042944785 | AE74: =$S74 -> 2445 | AF74: =(AE74-U74)/U74 -> -0.0020408163 | AG74: =(AE74-S74)/S74 -> 0 | AI74: Cleared | AJ74: 808 | AK74: 2 | AL74: 2 | AM74: 2 bed & 2 bath South-West6th floor | AO74: =SUM(AN74-U74)/U74 -> -1 | AP74: Jemma | AQ74: Sent
A75: Active | B75: =TEXT(C75,"mmmm") -> August | C75: 45528 | D75: BTR-London & SE | E75: Argo Apartments | F75: Fatma Azakli | G75: 26 Argo Apts, 4 Silvertown Way,London,E16 1ED | H75: Allan Souza, Merlyn Souza & Jenny Thomas | I75: N/A | J75: Current | K75: 44433 | L75: 45163 | M75: 45528 | N75: Renewal | O75: AST | P75: 28620 | Q75: 2385 | R75: 29340 | S75: =R75/12 -> 2445 | T75: 25800 | U75: =T75/12 -> 2150 | V75: 23400 | W75: 2535 | Z75: =(W75-U75)/U75 -> 0.17906977 | AA75: =(W75-S75)/S75 -> 0.036809816 | AB75: 2450 | AC75: =(AB75-U75)/U75 -> 0.13953488 | AD75: =(AB75-S75)/S75 -> 0.0020449898 | AE75: =$S75 -> 2445 | AF75: =(AE75-U75)/U75 -> 0.1372093 | AG75: =(AE75-S75)/S75 -> 0 | AI75: Cleared | AJ75: 808 | AK75: 2 | AL75: 2 | AM75: 2 bed & 2 bath South-West5th floor | AO75: =SUM(AN75-U75)/U75 -> -1 | AP75: Jemma | AQ75: Sent
A76: Active | B76: =TEXT(C76,"mmmm") -> August | C76: 45534 | D76: BTR-London & SE | E76: Argo Apartments | F76: Fatma Azakli | G76: 115 Argo Apts,4 Silvertown Way,London,E16 1YD | H76: Ms Ziyi Chen, Ms Yue Zhao | I76: N/A | J76: Current | K76: 44804 | L76: 45169 | M76: 45534 | N76: Renewal | O76: AST | P76: 29340 | Q76: 2445 | R76: 29220 | S76: =R76/12 -> 2435 | T76: 27000 | U76: =T76/12 -> 2250 | V76: 25200 | W76: 2570 | Z76: =(W76-U76)/U76 -> 0.14222222 | AA76: =(W76-S76)/S76 -> 0.055441478 | AB76: 2450 | AC76: =(AB76-U76)/U76 -> 0.088888889 | AD76: =(AB76-S76)/S76 -> 0.0061601643 | AE76: =$S76 -> 2435 | AF76: =(AE76-U76)/U76 -> 0.082222222 | AG76: =(AE76-S76)/S76 -> 0 | AI76: Cleared | AJ76: 799 | AK76: 2 | AL76: 2 | AM76: 2 bed & 2 bath East Right13th floor | AO76: =SUM(AN76-U76)/U76 -> -1 | AP76: Jemma | AQ76: Sent
A77: Active | B77: =TEXT(C77,"mmmm") -> August | C77: 45535 | D77: BTR-London & SE | E77: Argo Apartments | F77: Fatma Azakli | G77: 121 Argo Apts,4 Silvertown Way,London,E16 1YD | H77: Raeesa A G Ossman & Muhammad Y A G Ossman | I77: Nice residents, but please note everyone has a wahts app chat in Argo and will check all other renewal prices etc. | J77: Current | K77: 44805 | M77: 45535 | N77: Renewal | O77: AST | P77: 29700 | Q77: 2475 | R77: 29100 | S77: =R77/12 -> 2425 | T77: 27000 | U77: =T77/12 -> 2250 | V77: 24900 | W77: 2555 | Z77: =(W77-U77)/U77 -> 0.13555556 | AA77: =(W77-S77)/S77 -> 0.053608247 | AB77: 2435 | AC77: =(AB77-U77)/U77 -> 0.082222222 | AD77: =(AB77-S77)/S77 -> 0.0041237113 | AE77: =$S77 -> 2425 | AF77: =(AE77-U77)/U77 -> 0.077777778 | AG77: =(AE77-S77)/S77 -> 0 | AI77: Cleared | AJ77: 794 | AK77: 2 | AL77: 2 | AM77: 2 bed & 2 bath North-West14th floor | AO77: =SUM(AN77-U77)/U77 -> -1 | AP77: Jemma | AQ77: Sent
A78: Active | B78: =TEXT(C78,"mmmm") -> July | C78: 45479 | D78: BTR-London & SE | E78: Berewood PRS | F78: Megan Fleming | G78: 6, Houghton Avenue, Waterlooville, Hampshire, | H78: Owen Dowse & Georgina Rollingson | I78: N/A | J78: Current | K78: 45114 | L78: 45114 | M78: 45479 | N78: New Let | O78: AST | P78: 16634 | Q78: 1386.1667 | R78: 17400 | S78: =R78/12 -> 1450 | T78: 16500 | U78: =T78/12 -> 1375 | V78: 15232.82 | W78: NPB | Z78: =(W78-U78)/U78 -> #VALUE! | AA78: =(W78-S78)/S78 -> #VALUE! | AB78: 1460 | AC78: =(AB78-U78)/U78 -> 0.061818182 | AD78: =(AB78-S78)/S78 -> 0.0068965517 | AE78: 1450 | AF78: =(AE78-U78)/U78 -> 0.054545455 | AG78: =(AE78-S78)/S78 -> 0 | AI78: Cleared | AJ78: 889 | AK78: 3 | AL78: 2 | AM78: Mid Terrace3 Bed 5 Person | AN78: 1430 | AO78: =SUM(AN78-U78)/U78 -> 0.04 | AP78: Sophie | AQ78: signing | AR78: re-offered
A79: Active | B79: =TEXT(C79,"mmmm") -> July | C79: 45495 | D79: BTR-London & SE | E79: Berewood PRS | F79: Megan Fleming | G79: 7 Woodward House, Waterlooville, PO7 3BP | H79: Mr Rob Jeffery | I79: N/A | J79: Current | K79: 44400 | L79: 45130 | M79: 45495 | N79: Renewal | O79: AST | P79: 14006 | Q79: 1167.1667 | R79: 13500 | S79: =R79/12 -> 1125 | T79: 12720 | U79: =T79/12 -> 1060 | V79: 12000 | W79: NPB | Z79: =(W79-U79)/U79 -> #VALUE! | AA79: =(W79-S79)/S79 -> #VALUE! | AB79: 1150 | AC79: =(AB79-U79)/U79 -> 0.08490566 | AD79: =(AB79-S79)/S79 -> 0.022222222 | AE79: 1125 | AF79: =(AE79-U79)/U79 -> 0.061320755 | AG79: =(AE79-S79)/S79 -> 0 | AI79: Cleared | AJ79: 758 | AK79: 2 | AL79: 1 | AM79: 2Bed 4Person | AN79: 1125 | AO79: =SUM(AN79-U79)/U79 -> 0.061320755 | AP79: Sophie | AQ79: signing | AR79: min
A80: Active | B80: =TEXT(C80,"mmmm") -> August | C80: 45510 | D80: BTR-London & SE | E80: Berewood PRS | F80: Megan Fleming | G80: 5 Langford House, Carey Lane, Waterlooville P | H80: Ms Vivian Ha & Shyun Ping Tiong | I80: N/A | J80: Current | K80: 44415 | L80: 45145 | M80: 45510 | N80: Renewal | O80: AST | P80: 13465 | Q80: 1122.0833 | R80: 13500 | S80: =R80/12 -> 1125 | T80: 12900 | U80: =T80/12 -> 1075 | V80: 12300 | W80: NPB | Z80: =(W80-U80)/U80 -> #VALUE! | AA80: =(W80-S80)/S80 -> #VALUE! | AB80: 1150 | AC80: =(AB80-U80)/U80 -> 0.069767442 | AD80: =(AB80-S80)/S80 -> 0.022222222 | AE80: 1125 | AF80: =(AE80-U80)/U80 -> 0.046511628 | AG80: =(AE80-S80)/S80 -> 0 | AI80: Cleared | AJ80: 728.7 | AK80: 2 | AL80: 2 | AM80: 1st Floor2 Bed 4 Person | AN80: 1150 | AO80: =SUM(AN80-U80)/U80 -> 0.069767442 | AP80: Sophie | AQ80: signing | AR80: accepted
A81: Active | B81: =TEXT(C81,"mmmm") -> July | C81: 45499 | D81: BTR-London & SE | E81: Berewood PRS | F81: Megan Fleming | G81: 1 Langford House, Carey Lane, Waterlooville P | H81: Kathryn Lee | I81: N/A | J81: Current | K81: 45134 | L81: 45134 | M81: 45499 | N81: New Let | O81: AST | P81: 13561 | Q81: 1130.0833 | R81: 13500 | S81: =R81/12 -> 1125 | T81: 13740 | U81: =T81/12 -> 1145 | V81: 11940 | W81: NPB | Z81: =(W81-U81)/U81 -> #VALUE! | AA81: =(W81-S81)/S81 -> #VALUE! | AB81: 1225 | AC81: =(AB81-U81)/U81 -> 0.069868996 | AD81: =(AB81-S81)/S81 -> 0.088888889 | AE81: 1200 | AF81: =(AE81-U81)/U81 -> 0.048034934 | AG81: =(AE81-S81)/S81 -> 0.066666667 | AI81: Cleared | AJ81: 733.9 | AK81: 2 | AL81: 2 | AM81: Ground Floor2 Bed 4 Person | AN81: 1225 | AO81: =SUM(AN81-U81)/U81 -> 0.069868996 | AP81: Sophie | AQ81: signing | AR81: discussing bc
A82: Active | B82: =TEXT(C82,"mmmm") -> July | C82: 45496 | D82: BTR-London & SE | E82: Berewood PRS | F82: Megan Fleming | G82: 16 Orchard Mead, Waterlooville, PO7 | H82: Lee McGrath & Rebecca Pay | I82: N/A | J82: Current | K82: 45131 | L82: 45131 | M82: 45496 | N82: New Let | O82: AST | P82: 16634 | Q82: 1386.1667 | R82: 17400 | S82: =R82/12 -> 1450 | T82: 16800 | U82: =T82/12 -> 1400 | V82: 15780 | W82: NPB | Z82: =(W82-U82)/U82 -> #VALUE! | AA82: =(W82-S82)/S82 -> #VALUE! | AB82: 1475 | AC82: =(AB82-U82)/U82 -> 0.053571429 | AD82: =(AB82-S82)/S82 -> 0.017241379 | AE82: 1450 | AF82: =(AE82-U82)/U82 -> 0.035714286 | AG82: =(AE82-S82)/S82 -> 0 | AI82: Cleared | AJ82: 889 | AK82: 3 | AL82: 2 | AM82: End Terrace3 Bed 5 Person | AN82: 1475 | AO82: =SUM(AN82-U82)/U82 -> 0.053571429 | AP82: Sophie | AQ82: signing | AR82: 24 months
A83: Active | B83: =TEXT(C83,"mmmm") -> July | C83: 45479 | D83: BTR-London & SE | E83: Berewood PRS | F83: Megan Fleming | G83: 2 Woodward House, Waterlooville, PO7 3BP | H83: Mr Joshua Legg | I83: N/A | J83: Current | K83: 44019 | L83: 45114 | M83: 45479 | N83: Renewal | O83: AST | P83: 13987 | Q83: 1165.5833 | R83: 13500 | S83: =R83/12 -> 1125 | T83: 12720 | U83: =T83/12 -> 1060 | V83: 11940 | W83: NPB | Z83: =(W83-U83)/U83 -> #VALUE! | AA83: =(W83-S83)/S83 -> #VALUE! | AB83: 1150 | AC83: =(AB83-U83)/U83 -> 0.08490566 | AD83: =(AB83-S83)/S83 -> 0.022222222 | AE83: 1125 | AF83: =(AE83-U83)/U83 -> 0.061320755 | AG83: =(AE83-S83)/S83 -> 0 | AI83: Cleared | AJ83: 757 | AK83: 2 | AL83: 2 | AM83: 2Bed 4Person | AN83: 1125 | AO83: =SUM(AN83-U83)/U83 -> 0.061320755 | AP83: Sophie | AQ83: signing | AR83: same 2months' anytime bc
A84: Active | B84: =TEXT(C84,"mmmm") -> July | C84: 45500 | D84: BTR-London & SE | E84: Berewood PRS | F84: Megan Fleming | G84: 23 Orchard Mead, Waterlooville, PO7 | H84: Samantha Coombs | I84: N/A | J84: Current | K84: 45135 | L84: 45135 | M84: 45500 | N84: New Let | O84: AST | P84: 14117 | Q84: 1176.4167 | R84: 15300 | S84: =R84/12 -> 1275 | T84: 15300 | U84: =T84/12 -> 1275 | V84: 14655.6 | W84: NPB | Z84: =(W84-U84)/U84 -> #VALUE! | AA84: =(W84-S84)/S84 -> #VALUE! | AB84: 1350 | AC84: =(AB84-U84)/U84 -> 0.058823529 | AD84: =(AB84-S84)/S84 -> 0.058823529 | AE84: 1310 | AF84: =(AE84-U84)/U84 -> 0.02745098 | AG84: =(AE84-S84)/S84 -> 0.02745098 | AI84: Cleared | AJ84: 764 | AK84: 2 | AL84: 1 | AM84: End Terrace2 Bed 4 Person | AN84: 1350 | AO84: =SUM(AN84-U84)/U84 -> 0.058823529 | AP84: Sophie | AQ84: signing | AR84: accepted - 24 month
A85: Active | B85: =TEXT(C85,"mmmm") -> July | C85: 45495 | D85: BTR-London & SE | E85: Berewood PRS | F85: Megan Fleming | G85: 34 Houghton Avenue, Waterlooville, PO7 3AA | H85: Laura Hassanyeh & Nawal Hassanyeh | I85: N/A | J85: Current | K85: 43304 | L85: 44400 | M85: 45495 | N85: Renewal | O85: AST | P85: 16765 | Q85: 1397.0833 | R85: 17400 | S85: =R85/12 -> 1450 | T85: 16326.72 | U85: =T85/12 -> 1360.56 | V85: 15928.56 | W85: NPB | Z85: =(W85-U85)/U85 -> #VALUE! | AA85: =(W85-S85)/S85 -> #VALUE! | AB85: 1460 | AC85: =(AB85-U85)/U85 -> 0.073087552 | AD85: =(AB85-S85)/S85 -> 0.0068965517 | AE85: 1450 | AF85: =(AE85-U85)/U85 -> 0.065737637 | AG85: =(AE85-S85)/S85 -> 0 | AI85: Cleared | AJ85: 889 | AK85: 3 | AL85: 2 | AM85: End Terrace3 Bed 5 Person | AN85: 1460 | AO85: =SUM(AN85-U85)/U85 -> 0.073087552 | AP85: Sophie | AQ85: signing | AR85: 36 months
A86: Active | B86: =TEXT(C86,"mmmm") -> July | C86: 45484 | D86: BTR-London & SE | E86: Berewood PRS | F86: Megan Fleming | G86: 14 Lauder Hs, Watson Ln, Waterlooville, Hants | H86: Mears Ltd | I86: Mears tenancies do not renew | J86: Current | K86: 44754 | L86: 45119 | M86: 45484 | N86: Renewal | O86: Comp-Let | P86: 11216 | Q86: 934.66667 | R86: 12600 | S86: =R86/12 -> 1050 | T86: 11820 | U86: =T86/12 -> 985 | V86: 11100 | W86: NPB | Z86: =(W86-U86)/U86 -> #VALUE! | AA86: =(W86-S86)/S86 -> #VALUE! | AB86: 1075 | AC86: =(AB86-U86)/U86 -> 0.091370558 | AD86: =(AB86-S86)/S86 -> 0.023809524 | AE86: 1050 | AF86: =(AE86-U86)/U86 -> 0.065989848 | AG86: =(AE86-S86)/S86 -> 0 | AI86: Credit | AJ86: 486.5 | AK86: 1 | AL86: 1 | AM86: 1 bed 2 person | AN86: 1075 | AO86: =SUM(AN86-U86)/U86 -> 0.091370558 | AP86: Sophie | AQ86: processed | AR86: agreed
A87: Active | B87: =TEXT(C87,"mmmm") -> August | C87: 45517 | D87: BTR-London & SE | E87: Berewood PRS | F87: Megan Fleming | G87: 17 Orchard Mead, Waterlooville, PO7 | H87: Hayley Elizabeth Bentley | I87: N/A | J87: Current | K87: 44057 | L87: 45152 | M87: 45517 | N87: Renewal | O87: AST | P87: 16634 | Q87: 1386.1667 | R87: 17400 | S87: =R87/12 -> 1450 | T87: 16740 | U87: =T87/12 -> 1395 | V87: 15900 | W87: NPB | Z87: =(W87-U87)/U87 -> #VALUE! | AA87: =(W87-S87)/S87 -> #VALUE! | AB87: 1475 | AC87: =(AB87-U87)/U87 -> 0.05734767 | AD87: =(AB87-S87)/S87 -> 0.017241379 | AE87: 1450 | AF87: =(AE87-U87)/U87 -> 0.039426523 | AG87: =(AE87-S87)/S87 -> 0 | AI87: Cleared | AJ87: 889 | AK87: 3 | AL87: 2 | AM87: 3 bed 5 person | AN87: 1475 | AO87: =SUM(AN87-U87)/U87 -> 0.05734767 | AP87: Sophie | AQ87: signing | AR87: accepted
A88: Active | B88: =TEXT(C88,"mmmm") -> August | C88: 45518 | D88: BTR-London & SE | E88: Berewood PRS | F88: Megan Fleming | G88: 9 Rosemary Lane, Waterlooville, Hants, PO7 3A | H88: Stevie Figgins & Gary Youngs | I88: N/A | J88: Current | K88: 45153 | L88: 45153 | M88: 45518 | N88: New Let | O88: AST | P88: 19200 | Q88: 1600 | R88: 19800 | S88: =R88/12 -> 1650 | T88: 19200 | U88: =T88/12 -> 1600 | V88: 17100 | W88: NPB | Z88: =(W88-U88)/U88 -> #VALUE! | AA88: =(W88-S88)/S88 -> #VALUE! | AB88: 1675 | AC88: =(AB88-U88)/U88 -> 0.046875 | AD88: =(AB88-S88)/S88 -> 0.015151515 | AE88: 1650 | AF88: =(AE88-U88)/U88 -> 0.03125 | AG88: =(AE88-S88)/S88 -> 0 | AI88: Cleared | AJ88: 1297 | AK88: 4 | AL88: 2 | AM88: 4 Bed 7 person | AO88: =SUM(AN88-U88)/U88 -> -1 | AP88: Sophie | AQ88: in neg | AR88: min
A89: Active | B89: =TEXT(C89,"mmmm") -> August | C89: 45521 | D89: BTR-London & SE | E89: Berewood PRS | F89: Megan Fleming | G89: 4 Carey Lane, Waterlooville PO7 3BG | H89: Thomas Dickson & Natalie Thomas | I89: N/A | J89: Current | K89: 45156 | L89: 45156 | M89: 45521 | N89: New Let | O89: AST | P89: 15276 | Q89: 1273 | R89: 15300 | S89: =R89/12 -> 1275 | T89: 15120 | U89: =T89/12 -> 1260 | V89: 14400 | W89: NPB | Z89: =(W89-U89)/U89 -> #VALUE! | AA89: =(W89-S89)/S89 -> #VALUE! | AB89: 1350 | AC89: =(AB89-U89)/U89 -> 0.071428571 | AD89: =(AB89-S89)/S89 -> 0.058823529 | AE89: 1310 | AF89: =(AE89-U89)/U89 -> 0.03968254 | AG89: =(AE89-S89)/S89 -> 0.02745098 | AI89: Cleared | AJ89: 762.1 | AK89: 2 | AL89: 1 | AM89: Flat of garage2 Bed 4 Person | AN89: 1350 | AO89: =SUM(AN89-U89)/U89 -> 0.071428571 | AP89: Sophie | AQ89: signing | AR89: accepted - 24 month
A90: Active | B90: =TEXT(C90,"mmmm") -> August | C90: 45524 | D90: BTR-London & SE | E90: Berewood PRS | F90: Megan Fleming | G90: 30 Orchard Mead, Waterlooville Hampshire, PO7 | H90: Chadley Cadman & Sophie-Lauren Hamilton | I90: N/A | J90: Current | K90: 45159 | L90: 45159 | M90: 45524 | N90: New Let | O90: AST | P90: 14117 | Q90: 1176.4167 | R90: 15300 | S90: =R90/12 -> 1275 | T90: 15300 | U90: =T90/12 -> 1275 | V90: 15300 | W90: NPB | Z90: =(W90-U90)/U90 -> #VALUE! | AA90: =(W90-S90)/S90 -> #VALUE! | AB90: 1350 | AC90: =(AB90-U90)/U90 -> 0.058823529 | AD90: =(AB90-S90)/S90 -> 0.058823529 | AE90: 1325 | AF90: =(AE90-U90)/U90 -> 0.039215686 | AG90: =(AE90-S90)/S90 -> 0.039215686 | AI90: Cleared | AJ90: 764 | AK90: 3 | AL90: 2 | AM90: End Terrace2 Bed 4 Person | AN90: 1350 | AO90: =SUM(AN90-U90)/U90 -> 0.058823529 | AP90: Sophie | AQ90: Signing | AR90: agreed - 24 month
A91: Active | B91: =TEXT(C91,"mmmm") -> August | C91: 45528 | D91: BTR-London & SE | E91: Berewood PRS | F91: Megan Fleming | G91: 4 Langford House, Carey Lane, Waterlooville P | H91: Mr Dune Grimsell | I91: Happy to renew, likely to not accept any increase | J91: Current | K91: 44798 | L91: 45163 | M91: 45528 | N91: Renewal | O91: AST | P91: 11887 | Q91: 990.58333 | R91: 12600 | S91: =R91/12 -> 1050 | T91: 11280 | U91: =T91/12 -> 940 | V91: 10500 | W91: NPB | Z91: =(W91-U91)/U91 -> #VALUE! | AA91: =(W91-S91)/S91 -> #VALUE! | AB91: 1050 | AC91: =(AB91-U91)/U91 -> 0.11702128 | AD91: =(AB91-S91)/S91 -> 0 | AE91: 1040 | AF91: =(AE91-U91)/U91 -> 0.10638298 | AG91: =(AE91-S91)/S91 -> -0.0095238095 | AI91: Cleared | AJ91: 515.6 | AK91: 1 | AL91: 1 | AM91: Ground Floor1 Bed 2 Person | AO91: =SUM(AN91-U91)/U91 -> -1 | AP91: Sophie | AQ91: in neg | AR91: rent to high - outstandig repairs
A92: Active | B92: =TEXT(C92,"mmmm") -> August | C92: 45535 | D92: BTR-London & SE | E92: Berewood PRS | F92: Megan Fleming | G92: 6 Theobald House, Carey Lane, Waterlooville P | H92: Mr Adam Yarnold | I92: N/A | J92: Current | K92: 44440 | L92: 45170 | M92: 45535 | N92: Renewal | O92: AST | P92: 11975 | Q92: 997.91667 | R92: 12600 | S92: =R92/12 -> 1050 | T92: 11700 | U92: =T92/12 -> 975 | V92: 11100 | W92: NPB | Z92: =(W92-U92)/U92 -> #VALUE! | AA92: =(W92-S92)/S92 -> #VALUE! | AB92: 1075 | AC92: =(AB92-U92)/U92 -> 0.1025641 | AD92: =(AB92-S92)/S92 -> 0.023809524 | AE92: 1050 | AF92: =(AE92-U92)/U92 -> 0.076923077 | AG92: =(AE92-S92)/S92 -> 0 | AI92: Cleared | AJ92: 498.4 | AK92: 1 | AL92: 1 | AM92: 1st Floor1 Bed 2 Person | AN92: 1050 | AO92: =SUM(AN92-U92)/U92 -> 0.076923077 | AP92: Sophie | AQ92: signing | AR92: reduced to min
B93: =TEXT(C93,"mmmm") -> 21/07/2024 | C93: 21/07/2024 | D93: BTR-London & SE | E93: Berewood PRS | G93: 42 Houghton Avenue | I93: - | O93: AST | P93: 14117 | Q93: 1176 | R93: 15300 | S93: =R93/12 -> 1275 | U93: £1,270.00 | W93: NPB | Z93: =(W93-U93)/U93 -> #VALUE! | AA93: =(W93-S93)/S93 -> #VALUE! | AB93: 1350 | AC93: =(AB93-U93)/U93 -> #VALUE! | AD93: =(AB93-S93)/S93 -> 0.058823529 | AE93: 1325 | AF93: =(AE93-U93)/U93 -> #VALUE! | AG93: =(AE93-S93)/S93 -> 0.039215686 | AJ93: 764 sq.ft | AK93: 2 | AL93: 1 | AN93: 1350 | AO93: =SUM(AN93-U93)/U93 -> #VALUE! | AP93: Sophie | AQ93: signing | AR93: agreed
A94: Active | B94: =TEXT(C94,"mmmm") -> July | C94: 45497 | D94: PRS-London & SE | E94: Berry Street | F94: Nicolette McRae | G94: Apartment 5, 6 Berry Street | H94: Adalet Idil Argun, Asaria Lisa Foeh | I94: AM tbc re: renewal offer or not / strategy. flat is in good condition. no known issues. | J94: Current | K94: 43671 | L94: 45132 | M94: 45497 | N94: Renewal | O94: AST | P94: 31320 | Q94: 2610 | R94: 31320 | T94: 31140 | V94: 31140 | W94: NPB | Z94: =(W94-U94)/U94 -> #VALUE! | AA94: =(W94-S94)/S94 -> #VALUE! | AC94: =(AB94-U94)/U94 -> #DIV/0! | AD94: =(AB94-S94)/S94 -> #DIV/0! | AF94: =(AE94-U94)/U94 -> #DIV/0! | AG94: =(AE94-S94)/S94 -> #DIV/0! | AH94: Hold for now | AI94: Cleared | AJ94: 670 | AK94: 2 | AL94: 1 | AM94: 2 bed/1 bath, Kitchen, Living rm Rfrb 2015SFF | AO94: =SUM(AN94-U94)/U94 -> #DIV/0! | AP94: Jemma | AQ94: On Hold
A95: Active | B95: =TEXT(C95,"mmmm") -> July | C95: 45487 | D95: PRS-London & SE | E95: Berry Street | F95: Nicolette McRae | G95: Apartment 7, 6 Berry Street | H95: Olivia Robertson & Kimberly F Mcpherson | I95: AM tbc re: renewal offer or not / strategy. flat is in good condition. no known issues. | J95: Current | K95: 45122 | L95: 45122 | M95: 45487 | N95: New Let | O95: AST | P95: 39660 | Q95: 3305 | R95: 40800 | T95: 40800 | V95: 37728.54 | W95: NPB | Z95: =(W95-U95)/U95 -> #VALUE! | AA95: =(W95-S95)/S95 -> #VALUE! | AC95: =(AB95-U95)/U95 -> #DIV/0! | AD95: =(AB95-S95)/S95 -> #DIV/0! | AF95: =(AE95-U95)/U95 -> #DIV/0! | AG95: =(AE95-S95)/S95 -> #DIV/0! | AH95: Hold for now | AI95: Cleared | AJ95: 872.31 | AK95: 2 | AL95: 2 | AM95: 2 bed/2 bath flat w/balcony, Rfrb 2014TFF | AO95: =SUM(AN95-U95)/U95 -> #DIV/0! | AP95: Jemma | AQ95: On Hold
A96: Active | B96: =TEXT(C96,"mmmm") -> July | C96: 45492 | D96: PRS-London & SE | E96: Berry Street | F96: Nicolette McRae | G96: Jn | H96: N Hughes, O McGregor & O Lanzalaco | I96: AM tbc re: renewal offer or not / strategy. flat is in good condition. no known issues. | J96: Current | K96: 45127 | L96: 45127 | M96: 45492 | N96: New Let | O96: AST | P96: 52200 | Q96: 4350 | R96: 52200 | T96: 52200 | V96: 49920 | W96: NPB | Z96: =(W96-U96)/U96 -> #VALUE! | AA96: =(W96-S96)/S96 -> #VALUE! | AC96: =(AB96-U96)/U96 -> #DIV/0! | AD96: =(AB96-S96)/S96 -> #DIV/0! | AF96: =(AE96-U96)/U96 -> #DIV/0! | AG96: =(AE96-S96)/S96 -> #DIV/0! | AH96: Hold for now | AI96: Arrears | AJ96: 1055 | AK96: 3 | AL96: 2 | AM96: 3 bed flat/2 bath/rf trrce, Rfrb 2015FFF | AO96: =SUM(AN96-U96)/U96 -> #DIV/0! | AP96: Jemma | AQ96: On Hold
A97: Active | B97: =TEXT(C97,"mmmm") -> August | C97: 45533 | D97: PRS-London & SE | E97: Berry Street | F97: Nicolette McRae | G97: Flat 1a, 6 Berry Street | H97: Yunhao Yao | I97: AM tbc re: renewal offer or not / strategy. flat is needs full redecs but rest is in average condition. no known issues. | J97: Current | K97: 45168 | L97: 45168 | M97: 45533 | N97: New Let | O97: AST | P97: 24000 | Q97: 2000 | R97: 24000 | T97: 23700 | V97: 22776 | Z97: =(W97-U97)/U97 -> #DIV/0! | AA97: =(W97-S97)/S97 -> #DIV/0! | AC97: =(AB97-U97)/U97 -> #DIV/0! | AD97: =(AB97-S97)/S97 -> #DIV/0! | AF97: =(AE97-U97)/U97 -> #DIV/0! | AG97: =(AE97-S97)/S97 -> #DIV/0! | AH97: Hold on offering | AI97: Cleared | AJ97: 503.65 | AK97: 0 | AL97: 1 | AM97: Studio flat w/kit, bath, Rfb'15GFF | AO97: =SUM(AN97-U97)/U97 -> #DIV/0! | AP97: Jemma | AQ97: On Hold
A98: Active | B98: =TEXT(C98,"mmmm") -> August | C98: 45515 | D98: PRS-London & SE | E98: Bethnal Green | F98: Robert Steel | G98: 22, Temple Dwellings, London, E2 6QG | H98: Youssef Hadire and Athos Croce | I98: No Issues, ensure we have a 6 month break clause | J98: Current | K98: 44785 | L98: 45150 | M98: 45515 | N98: Renewal | O98: AST | P98: 19200 | Q98: 1600 | R98: 21000 | S98: =R98/12 -> 1750 | T98: 21000 | U98: =T98/12 -> 1750 | V98: 19140 | W98: NPB | Z98: =(W98-U98)/U98 -> #VALUE! | AA98: =(W98-#REF!)/#REF! -> #VALUE! | AB98: 1825 | AC98: =(AB98-U98)/U98 -> 0.042857143 | AD98: =(AB98-#REF!)/#REF! -> #REF! | AE98: 1815 | AF98: =(AE98-U98)/U98 -> 0.037142857 | AG98: =(AE98-#REF!)/#REF! -> #REF! | AI98: Cleared | AJ98: 457.15 | AK98: 1 | AL98: 1 | AM98: 1 bed/1 bath, kitch, liv rm - PRfrb '17FF | AO98: =SUM(AN98-U98)/U98 -> -1 | AP98: Jemma | AQ98: Sent
A99: Active | B99: =TEXT(C99,"mmmm") -> August | C99: 45518 | D99: PRS-London & SE | E99: Bethnal Green | F99: Robert Steel | G99: 7, Temple Dwellings, London, E2 6QG | H99: Sam Killick & Chloe Smith | I99: some damp issues which we are sorting however no issues with tenants, offer new TA ensuring we have a 6 month break clause | J99: Current | K99: 44788 | L99: 45153 | M99: 45518 | N99: Renewal | O99: AST | P99: 19200 | Q99: 1600 | R99: 20520 | S99: =R99/12 -> 1710 | T99: 20520 | U99: =T99/12 -> 1710 | V99: 18900 | W99: NPB | Z99: =(W99-U99)/U99 -> #VALUE! | AA99: =(W99-S99)/S99 -> #VALUE! | AB99: 1825 | AC99: =(AB99-U99)/U99 -> 0.067251462 | AD99: =(AB99-S99)/S99 -> 0.067251462 | AE99: 1785 | AF99: =(AE99-U99)/U99 -> 0.043859649 | AG99: =(AE99-S99)/S99 -> 0.043859649 | AI99: Cleared | AJ99: 439.17 | AK99: 1 | AL99: 1 | AM99: 1 bed/1 bath, kitch, liv rm - PRfrb '17SF | AN99: 1785 | AO99: =SUM(AN99-U99)/U99 -> 0.043859649 | AP99: Jemma | AQ99: Sent
A100: Active | B100: =TEXT(C100,"mmmm") -> July | C100: 45486 | D100: PRS-London & SE | E100: Bethnal Green | F100: Robert Steel | G100: 33a, Temple Street, Flat 2 London, E2 6QQ | H100: Amadea Strassnig | I100: No Issues, ensure we have a 6 month break clause | J100: Current | K100: 45091 | L100: 45091 | M100: 45486 | N100: New Let | O100: AST | P100: 16800 | Q100: 1400 | R100: 16800 | S100: =R100/12 -> 1400 | T100: 16800 | U100: =T100/12 -> 1400 | V100: 14700 | W100: NPB | Z100: =(W100-U100)/U100 -> #VALUE! | AA100: =(W100-S101)/S101 -> #VALUE! | AB100: 1500 | AC100: =(AB100-U100)/U100 -> 0.071428571 | AD100: =(AB100-S101)/S101 -> 0.071428571 | AE100: 1475 | AF100: =(AE100-U100)/U100 -> 0.053571429 | AG100: =(AE100-S101)/S101 -> 0.053571429 | AI100: Arrears | AJ100: 244.45 | AK100: 0 | AL100: 1 | AM100: Studio flat w/kitchen & bath, one reception rFF right | AO100: =SUM(AN100-U100)/U100 -> -1 | AP100: Jemma | AQ100: Sent
...

Sheet Licences
A1: Diary Status | B1: Event Date | C1: Portfolio | D1: Estate | E1: Unit Manager | F1: Unit Description | G1: Current Tenant Name | H1: PM Details | I1: Tenancy Status | J1: Tenancy Start Date | K1: Tenancy End Date | L1: Lease Start Date | M1: Lease End Date | N1: Action Type | O1: Unit Tenure | P1: ERV | Q1: Monthly ERV | R1: March ERV | S1: Annual Rent | T1: Passing Rent | U1: Passing Rent -1 | V1: Tenant Balance Status | W1: Unit Size | X1: Number of Beds | Y1: Number of Baths | Z1: Description of Unit | AA1: Renewal Neg | AB1: Renewal Notes Date | AC1: Renewal Notes
A2: Active | B2: 45481 | C2: BTR-London & SE | D2: Argo Apartments | E2: Raihana Parveen | F2: Car Space 80 Argo Apartments,4 Silvertown Way | G2: Mears Ltd | I2: Current | J2: 44751 | L2: 45116 | M2: 45481 | N2: Renewal | O2: Licence | P2: 1200 | Q2: 100 | R2: 1440 | S2: 1440 | T2: 1440 | U2: 1200 | V2: Credit | W2: 0 | X2: 0 | Y2: 0 | AA2: RP3 | AB2: 45481
A3: Active | B3: 45481 | C3: BTR-London & SE | D3: Argo Apartments | E3: Raihana Parveen | F3: Car Space 81 Argo Apartments,4 Silvertown Way | G3: Mears Ltd | I3: Current | J3: 44751 | L3: 45116 | M3: 45481 | N3: Renewal | O3: Licence | P3: 1200 | Q3: 100 | R3: 1440 | S3: 1440 | T3: 1440 | U3: 1200 | V3: Arrears | W3: 0 | X3: 0 | Y3: 0 | AA3: RP3 | AB3: 45481
A4: Active | B4: 45482 | C4: BTR-London & SE | D4: Argo Apartments | E4: Raihana Parveen | F4: Car Space 63 Argo Apartments,4 Silvertown Way | G4: Mears Ltd | I4: Current | J4: 45117 | L4: 45117 | M4: 45482 | N4: New Let | O4: Licence | P4: 1200 | Q4: 100 | R4: 1200 | S4: 1440 | T4: 1260 | U4: 1200 | V4: Cleared | W4: 0 | X4: 0 | Y4: 0 | AA4: RP3 | AB4: 45482
A5: Active | B5: 45508 | C5: BTR-London & SE | D5: Argo Apartments | E5: Raihana Parveen | F5: Car Space 71 Argo Apartments,4 Silvertown Way | G5: Mears Ltd | I5: Current | J5: 43217 | L5: 45143 | M5: 45508 | N5: Renewal | O5: Licence | P5: 1200 | Q5: 100 | R5: 1200 | S5: 1440 | T5: 1200 | U5: 1200 | V5: Cleared | W5: 0 | X5: 0 | Y5: 0 | AA5: RP3 | AB5: 45508
A6: Active | B6: 45508 | C6: BTR-London & SE | D6: Argo Apartments | E6: Raihana Parveen | F6: Car Space 74 Argo Apartments,4 Silvertown Way | G6: Mears Ltd | I6: Current | J6: 43217 | L6: 45143 | M6: 45508 | N6: Renewal | O6: Licence | P6: 1200 | Q6: 100 | R6: 1200 | S6: 1440 | T6: 1200 | U6: 1200 | V6: Cleared | W6: 0 | X6: 0 | Y6: 0 | AA6: RP3 | AB6: 45508
A7: Active | B7: 45485 | C7: BTR-London & SE | D7: Berewood PRS | E7: Megan Fleming | F7: Car Park Bay 9, Langford House, Carey Lane, | G7: Mr Benjo Balolong, Mrs Vanessa Kae Jose | I7: Current | J7: 44939 | L7: 44939 | M7: 45485 | N7: New Let | O7: Licence | P7: 0 | Q7: 0 | R7: 0 | S7: 0 | T7: 0 | U7: 0 | V7: Cleared | W7: 0 | X7: 0 | Y7: 0 | Z7: Car Park space | AA7: AG4 | AB7: 45485
A8: Active | B8: 45495 | C8: BTR-London & SE | D8: Berewood PRS | E8: Megan Fleming | F8: Car Park Bay 17, Fielding House, Carey Lane, | G8: Miss Hajnalka Fogarasi | I8: Current | J8: 44949 | L8: 44949 | M8: 45495 | N8: New Let | O8: Licence | P8: 0 | Q8: 0 | S8: 0 | T8: 0 | U8: 0 | V8: Cleared | W8: 0 | X8: 0 | Y8: 0 | Z8: Car Park space | AA8: AG4 | AB8: 45495
A9: Active | B9: 45483 | C9: BTR-Regions | D9: Brook Place | E9: Emma Cramer- Mitchell | F9: Parking 24 Brook Place Apts, Sheffield, S11 | G9: Frances McGee | H9: Linked to 503- no issues | I9: Current | J9: 45118 | L9: 45118 | M9: 45483 | N9: New Let | O9: Licence | P9: 1500 | Q9: 125 | R9: 1560 | S9: 1560 | T9: 1560 | U9: 1500 | V9: Cleared | W9: 0 | X9: 0 | Y9: 0 | AA9: MC2 | AB9: 45483
A10: Active | B10: 45489 | C10: BTR-Regions | D10: Brook Place | E10: Emma Cramer- Mitchell | F10: Parking 43 Brook Place Apts, Sheffield, S11 | G10: Oliver Rathbone | H10: Linked to 725- no issues | I10: Current | J10: 45124 | L10: 45124 | M10: 45489 | N10: New Let | O10: Licence | P10: 1500 | Q10: 125 | R10: 1440 | S10: 1560 | T10: 1440 | U10: 1500 | V10: Cleared | W10: 0 | X10: 0 | Y10: 0 | AA10: MC2 | AB10: 45489
A11: Active | B11: 45490 | C11: BTR-Regions | D11: Brook Place | E11: Emma Cramer- Mitchell | F11: Parking 42 Brook Place Apts, Sheffield, S11 | G11: Harshit Kondapally | H11: Linked to 418- no issues | I11: Current | J11: 44760 | L11: 45125 | M11: 45490 | N11: Renewal | O11: Licence | P11: 1500 | Q11: 125 | R11: 1440 | S11: 1560 | T11: 1440 | U11: 1500 | V11: Cleared | W11: 0 | X11: 0 | Y11: 0 | AA11: MC2 | AB11: 45490
A12: Active | B12: 45492 | C12: BTR-Regions | D12: Brook Place | E12: Emma Cramer- Mitchell | F12: Parking 23 Brook Place Apts, Sheffield, S11 | G12: James Warrington | H12: Linked to 703- no issues | I12: Current | J12: 45127 | L12: 45127 | M12: 45492 | N12: New Let | O12: Licence | P12: 1500 | Q12: 125 | R12: 1440 | S12: 1560 | T12: 1440 | U12: 1500 | V12: Cleared | W12: 0 | X12: 0 | Y12: 0 | AA12: MC2 | AB12: 45492
A13: Active | B13: 45497 | C13: BTR-Regions | D13: Brook Place | E13: Emma Cramer- Mitchell | F13: Parking 04 Brook Place Apts, Sheffield, S11 | G13: Dina Ibrahim | H13: Linked to 529- no issues | I13: Current | J13: 45132 | L13: 45132 | M13: 45497 | N13: New Let | O13: Licence | P13: 1500 | Q13: 125 | R13: 1440 | S13: 1560 | T13: 1440 | U13: 1500 | V13: Cleared | W13: 0 | X13: 0 | Y13: 0 | AA13: MC2 | AB13: 45497
A14: Active | B14: 45504 | C14: BTR-Regions | D14: Brook Place | E14: Emma Cramer- Mitchell | F14: Parking 31 Brook Place Apts, Sheffield, S11 | G14: Asha Wright | H14: Linked to 324- no issues | I14: Current | J14: 45139 | L14: 45139 | M14: 45504 | N14: New Let | O14: Licence | P14: 1500 | Q14: 125 | R14: 1440 | S14: 1560 | T14: 1560 | U14: 1500 | V14: Cleared | W14: 0 | X14: 0 | Y14: 0 | AA14: MC2 | AB14: 45504
A15: Active | B15: 45516 | C15: BTR-Regions | D15: Brook Place | E15: Emma Cramer- Mitchell | F15: Parking 01 Brook Place Apts, Sheffield, S11 | G15: Amrit Jani | H15: Linked to 422- no issues | I15: Current | J15: 44694 | L15: 45059 | M15: 45516 | N15: Renewal | O15: Licence | P15: 1500 | Q15: 125 | R15: 1440 | S15: 1500 | T15: 1440 | U15: 1500 | V15: Cleared | W15: 0 | X15: 0 | Y15: 0 | AA15: MC2 | AB15: 45516
A16: Active | B16: 45535 | C16: BTR-Regions | D16: Brook Place | E16: Emma Cramer- Mitchell | F16: Parking 44 Brook Place Apts, Sheffield, S11 | G16: Bojian Li | H16: Linked to 411- DDM needs setting up- rent not being paid automatically | I16: Current | J16: 45170 | K16: 45535 | L16: 45170 | M16: 45535 | N16: New Let | O16: Licence | P16: 1500 | Q16: 125 | R16: 1440 | S16: 1560 | T16: 1440 | U16: 1500 | V16: Arrears | W16: 0 | X16: 0 | Y16: 0 | AA16: MC2 | AB16: 45535
A17: Pending | B17: 45531 | C17: BTR-Regions | D17: Brook Place | E17: Emma Cramer- Mitchell | F17: Parking 19 Brook Place Apts, Sheffield, S11 | G17: Aydin Can | H17: Linked to 303- no issues | I17: Current | J17: 44985 | L17: 45350 | M17: 45531 | N17: Renewal | O17: Licence | P17: 1500 | Q17: 125 | R17: 1560 | S17: 1560 | T17: 1560 | U17: 1500 | V17: Cleared | W17: 0 | X17: 0 | Y17: 0 | AA17: EC1 | AB17: 45531
A18: Active | B18: 45507 | C18: PRS-London & SE | D18: Churston Close | E18: Nadia Rogers | F18: Garage O,Churston Cl,162-164Tulse Hill,SW23BX | G18: Abir The Colour Of Life | I18: Current | J18: 45142 | L18: 45142 | M18: 45507 | N18: New Let | O18: Licence | P18: 600 | Q18: 50 | R18: 1440 | S18: 1800 | T18: 1440 | U18: 600 | V18: Cleared | W18: 0 | Z18: Garage | AA18: NRX | AB18: 45507
A19: Active | B19: 45478 | C19: BTR-Regions | D19: Clippers Quay | E19: Helen Bowers | F19: Parking D35 Torrens Apt, Salford M50 | G19: Wendy Moneke | I19: Current | J19: 45113 | L19: 45113 | M19: 45478 | N19: New Let | O19: Licence | P19: 1380 | Q19: 115 | R19: 1200 | S19: 1380 | T19: 1200 | U19: 1380 | V19: Cleared | W19: 0 | X19: 0 | Y19: 0 | AA19: HB2 | AB19: 45478
A20: Active | B20: 45482 | C20: BTR-Regions | D20: Clippers Quay | E20: Helen Bowers | F20: Parking D39 Torrens Apt, Salford M50 | G20: Max Walters | I20: Current | J20: 45117 | L20: 45117 | M20: 45482 | N20: New Let | O20: Licence | P20: 1380 | Q20: 115 | R20: 1380 | S20: 1500 | T20: 1380 | U20: 1380 | V20: Cleared | W20: 0 | X20: 0 | Y20: 0 | AA20: HB2 | AB20: 45482
A21: Active | B21: 45484 | C21: BTR-Regions | D21: Clippers Quay | E21: Helen Bowers | F21: Parking D32 Torrens Apt, Salford M50 | G21: Rakeeb Patel | I21: Current | J21: 44069 | L21: 45119 | M21: 45484 | N21: Renewal | O21: Licence | P21: 1380 | Q21: 115 | R21: 1260 | S21: 1500 | T21: 1260 | U21: 1380 | V21: Cleared | W21: 0 | X21: 0 | Y21: 0 | AA21: HB2 | AB21: 45484
A22: Active | B22: 45486 | C22: BTR-Regions | D22: Clippers Quay | E22: Helen Bowers | F22: Parking D6 Torrens Apt, Salford M50 | G22: Tsz Fung Lo | I22: Current | J22: 45121 | L22: 45121 | M22: 45486 | N22: New Let | O22: Licence | P22: 1380 | Q22: 115 | R22: 1380 | S22: 1500 | T22: 1380 | U22: 1380 | V22: Cleared | W22: 0 | X22: 0 | Y22: 0 | AA22: HB2 | AB22: 45486
A23: Active | B23: 45486 | C23: BTR-Regions | D23: Clippers Quay | E23: Helen Bowers | F23: Parking E9 Ambassador Apt , Salford M50 | G23: Nick Overd | I23: Current | J23: 45121 | L23: 45121 | M23: 45486 | N23: New Let | O23: Licence | P23: 1380 | Q23: 115 | R23: 1200 | S23: 1500 | T23: 1200 | U23: 1380 | V23: Cleared | W23: 0 | X23: 0 | Y23: 0 | AA23: HB2 | AB23: 45486
A24: Active | B24: 45492 | C24: BTR-Regions | D24: Clippers Quay | E24: Helen Bowers | F24: Parking B25 Syren Apt , Salford M50 | G24: Chung Yee Fung | I24: Current | J24: 45127 | L24: 45127 | M24: 45492 | N24: New Let | O24: Licence | P24: 1380 | Q24: 115 | R24: 1380 | S24: 1500 | T24: 1380 | U24: 1380 | V24: Arrears | W24: 0 | X24: 0 | Y24: 0 | AA24: HB2 | AB24: 45492
A25: Active | B25: 45492 | C25: BTR-Regions | D25: Clippers Quay | E25: Helen Bowers | F25: Parking E36 Ambassador Apt , Salford M50 | G25: Madi Eastham | I25: Current | J25: 45127 | L25: 45127 | M25: 45492 | N25: New Let | O25: Licence | P25: 1380 | Q25: 115 | R25: 1200 | S25: 1500 | T25: 1200 | U25: 1380 | V25: Cleared | W25: 0 | X25: 0 | Y25: 0 | AA25: HB2 | AB25: 45492
A26: Active | B26: 45494 | C26: BTR-Regions | D26: Clippers Quay | E26: Helen Bowers | F26: Parking C18 Tayleur Apt, Salford M50 | G26: Eduardo De la Cotera Morales | I26: Current | J26: 44764 | L26: 45129 | M26: 45494 | N26: Renewal | O26: Licence | P26: 1380 | Q26: 115 | R26: 1200 | S26: 1500 | T26: 1200 | U26: 1380 | V26: Cleared | W26: 0 | X26: 1 | Y26: 0 | Z26: Car Parking Space | AA26: HB2 | AB26: 45494
A27: Active | B27: 45494 | C27: BTR-Regions | D27: Clippers Quay | E27: Helen Bowers | F27: Parking C28 Tayleur Apt, Salford M50 | G27: Rosie Boyer | I27: Current | J27: 44948 | L27: 45129 | M27: 45494 | N27: Renewal | O27: Licence | P27: 1380 | Q27: 115 | R27: 1200 | S27: 1500 | T27: 1200 | U27: 1380 | V27: Cleared | W27: 0 | X27: 3 | Y27: 0 | Z27: Car Parking Space | AA27: HB2 | AB27: 45494
A28: Active | B28: 45496 | C28: BTR-Regions | D28: Clippers Quay | E28: Helen Bowers | F28: Parking D7 Torrens Apt, Salford M50 | G28: Cheuk Kin Lee | I28: Current | J28: 45131 | L28: 45131 | M28: 45496 | N28: New Let | O28: Licence | P28: 1380 | Q28: 115 | R28: 1200 | S28: 1500 | T28: 1200 | U28: 1380 | V28: Cleared | W28: 0 | X28: 0 | Y28: 0 | AA28: HB2 | AB28: 45496
A29: Active | B29: 45501 | C29: BTR-Regions | D29: Clippers Quay | E29: Helen Bowers | F29: Parking B33 Syren Apt , Salford M50 | G29: James Lancaster | I29: Current | J29: 45136 | L29: 45136 | M29: 45501 | N29: New Let | O29: Licence | P29: 1380 | Q29: 115 | R29: 1200 | S29: 1500 | T29: 1200 | U29: 1380 | V29: Cleared | W29: 0 | X29: 0 | Y29: 0 | AA29: HB2 | AB29: 45501
A30: Active | B30: 45501 | C30: BTR-Regions | D30: Clippers Quay | E30: Helen Bowers | F30: Parking B4 Syren Apt , Salford M50 | G30: Tsz Tsun Lam | I30: Current | J30: 45136 | L30: 45136 | M30: 45501 | N30: New Let | O30: Licence | P30: 1380 | Q30: 115 | R30: 1200 | S30: 1500 | T30: 1200 | U30: 1380 | V30: Cleared | W30: 0 | X30: 0 | Y30: 0 | AA30: HB2 | AB30: 45501
A31: Active | B31: 45504 | C31: BTR-Regions | D31: Clippers Quay | E31: Helen Bowers | F31: Parking C24 Tayleur Apt, Salford M50 | G31: Yik Lau | I31: Current | J31: 45362 | L31: 45362 | M31: 45726 | N31: New Let | O31: Licence | P31: 1380 | Q31: 115 | R31: 1200 | S31: 1500 | T31: 1500 | U31: 1380 | V31: Arrears | W31: 0 | X31: 2 | Y31: 0 | Z31: Car Parking Space | AA31: HB2 | AB31: 45726
A32: Active | B32: 45504 | C32: BTR-Regions | D32: Clippers Quay | E32: Helen Bowers | F32: Parking C29 Tayleur Apt, Salford M50 | G32: Victoria Quinn | I32: Current | J32: 44043 | L32: 45139 | M32: 45504 | N32: Renewal | O32: Licence | P32: 1380 | Q32: 115 | R32: 1260 | S32: 1500 | T32: 1260 | U32: 1380 | V32: Cleared | W32: 0 | X32: 2 | Y32: 0 | Z32: Car Parking Space | AA32: HB2 | AB32: 45504
A33: Active | B33: 45504 | C33: BTR-Regions | D33: Clippers Quay | E33: Helen Bowers | F33: Parking C33 Tayleur Apt, Salford M50 | G33: Dimitra Maniakdaki | I33: Current | J33: 44378 | L33: 45139 | M33: 45504 | N33: Renewal | O33: Licence | P33: 1380 | Q33: 115 | R33: 1200 | S33: 1500 | T33: 1200 | U33: 1380 | V33: Cleared | W33: 0 | X33: 2 | Y33: 0 | Z33: Car Parking Space | AA33: HB2 | AB33: 45504
A34: Active | B34: 45504 | C34: BTR-Regions | D34: Clippers Quay | E34: Helen Bowers | F34: Parking D18 Torrens Apt, Salford M50 | G34: Francis D'Sa | I34: Current | J34: 45139 | L34: 45139 | M34: 45504 | N34: New Let | O34: Licence | P34: 1380 | Q34: 115 | R34: 1200 | S34: 1500 | T34: 1200 | U34: 1380 | V34: Cleared | W34: 0 | X34: 0 | Y34: 0 | AA34: HB2 | AB34: 45504
A35: Active | B35: 45504 | C35: BTR-Regions | D35: Clippers Quay | E35: Helen Bowers | F35: Parking E38 Ambassador Apt , Salford M50 | G35: Kate Stafford | I35: Current | J35: 45139 | L35: 45139 | M35: 45504 | N35: New Let | O35: Licence | P35: 1380 | Q35: 115 | R35: 1200 | S35: 1500 | T35: 1200 | U35: 1380 | V35: Cleared | W35: 0 | X35: 0 | Y35: 0 | AA35: HB2 | AB35: 45504
A36: Active | B36: 45511 | C36: BTR-Regions | D36: Clippers Quay | E36: Helen Bowers | F36: Parking C20 Tayleur Apt, Salford M50 | G36: Long Cheng | I36: Current | J36: 45146 | L36: 45146 | M36: 45511 | N36: New Let | O36: Licence | P36: 1380 | Q36: 115 | R36: 1260 | S36: 1500 | T36: 1260 | U36: 1380 | V36: Cleared | W36: 0 | X36: 3 | Y36: 0 | Z36: Car Parking Space | AA36: HB2 | AB36: 45511
A37: Active | B37: 45511 | C37: BTR-Regions | D37: Clippers Quay | E37: Helen Bowers | F37: Parking D41 Torrens Apt, Salford M50 | G37: Cheung Kit Danny | I37: Current | J37: 45146 | L37: 45146 | M37: 45511 | N37: New Let | O37: Licence | P37: 1380 | Q37: 115 | R37: 1200 | S37: 1500 | T37: 1200 | U37: 1380 | V37: Cleared | W37: 0 | X37: 0 | Y37: 0 | AA37: HB2 | AB37: 45511
A38: Active | B38: 45513 | C38: BTR-Regions | D38: Clippers Quay | E38: Helen Bowers | F38: Parking E10 Ambassador Apt , Salford M50 | G38: Chung Kong Tse | I38: Current | J38: 45148 | L38: 45148 | M38: 45513 | N38: New Let | O38: Licence | P38: 1380 | Q38: 115 | R38: 1260 | S38: 1500 | T38: 1260 | U38: 1380 | V38: Cleared | W38: 0 | X38: 0 | Y38: 0 | AA38: HB2 | AB38: 45513
A39: Active | B39: 45513 | C39: BTR-Regions | D39: Clippers Quay | E39: Helen Bowers | F39: Parking E19 Ambassador Apt , Salford M50 | G39: Dr Sunil Anirudhprasad Jayaswal | I39: Current | J39: 44067 | L39: 45148 | M39: 45513 | N39: Renewal | O39: Licence | P39: 1380 | Q39: 115 | R39: 1260 | S39: 1500 | T39: 1260 | U39: 1380 | V39: Cleared | W39: 0 | X39: 0 | Y39: 0 | AA39: HB2 | AB39: 45513
A40: Active | B40: 45515 | C40: BTR-Regions | D40: Clippers Quay | E40: Helen Bowers | F40: Parking E28 Ambassador Apt , Salford M50 | G40: Ruby Fisher | I40: Current | J40: 44785 | L40: 45150 | M40: 45515 | N40: Renewal | O40: Licence | P40: 1380 | Q40: 115 | R40: 1200 | S40: 1500 | T40: 1200 | U40: 1380 | V40: Cleared | W40: 0 | X40: 0 | Y40: 0 | AA40: HB2 | AB40: 45515
A41: Active | B41: 45516 | C41: BTR-Regions | D41: Clippers Quay | E41: Helen Bowers | F41: Parking D13 Torrens Apt, Salford M50 | G41: Harriet Scott Worthington | I41: Current | J41: 44421 | L41: 45151 | M41: 45516 | N41: Renewal | O41: Licence | P41: 1380 | Q41: 115 | R41: 1260 | S41: 1500 | T41: 1260 | U41: 1380 | V41: Cleared | W41: 0 | X41: 0 | Y41: 0 | AA41: HB2 | AB41: 45516
A42: Active | B42: 45520 | C42: BTR-Regions | D42: Clippers Quay | E42: Helen Bowers | F42: Parking B11 Syren Apt , Salford M50 | G42: Adeola Eribake | I42: Current | J42: 45155 | L42: 45155 | M42: 45520 | N42: New Let | O42: Licence | P42: 1380 | Q42: 115 | R42: 1200 | S42: 1260 | T42: 1200 | U42: 1380 | V42: Cleared | W42: 0 | X42: 0 | Y42: 0 | AA42: HB2 | AB42: 45520
A43: Active | B43: 45524 | C43: BTR-Regions | D43: Clippers Quay | E43: Helen Bowers | F43: Parking E42 Ambassador Apt , Salford M50 | G43: Animesh Jayaswal | I43: Current | J43: 45159 | L43: 45159 | M43: 45524 | N43: New Let | O43: Licence | P43: 1380 | Q43: 115 | R43: 1200 | S43: 1500 | T43: 1200 | U43: 1380 | V43: Cleared | W43: 0 | X43: 0 | Y43: 0 | AA43: HB2 | AB43: 45524
A44: Active | B44: 45528 | C44: BTR-Regions | D44: Clippers Quay | E44: Helen Bowers | F44: Parking C27 Tayleur Apt, Salford M50 | G44: Yuen Ching Janet Chow | I44: Current | J44: 45163 | L44: 45163 | M44: 45528 | N44: New Let | O44: Licence | P44: 1380 | Q44: 115 | R44: 1380 | S44: 1500 | T44: 1380 | U44: 1380 | V44: Cleared | W44: 0 | X44: 2 | Y44: 0 | Z44: Car Parking Space | AA44: HB2 | AB44: 45528
A45: Active | B45: 45528 | C45: BTR-Regions | D45: Clippers Quay | E45: Helen Bowers | F45: Parking D15 Torrens Apt, Salford M50 | G45: Neema Paul & Micky Joe Thomas Palekkudy | I45: Current | J45: 45163 | L45: 45163 | M45: 45528 | N45: New Let | O45: Licence | P45: 1380 | Q45: 115 | R45: 1200 | S45: 1500 | T45: 1200 | U45: 1380 | V45: Cleared | W45: 0 | X45: 0 | Y45: 0 | AA45: HB2 | AB45: 45528
A46: Active | B46: 45528 | C46: BTR-Regions | D46: Clippers Quay | E46: Helen Bowers | F46: Parking E11 Ambassador Apt , Salford M50 | G46: Kris Green | I46: Current | J46: 45163 | L46: 45163 | M46: 45528 | N46: New Let | O46: Licence | P46: 1380 | Q46: 115 | R46: 1200 | S46: 1500 | T46: 1200 | U46: 1380 | V46: Cleared | W46: 0 | X46: 0 | Y46: 0 | AA46: HB2 | AB46: 45528
A47: Active | B47: 45529 | C47: BTR-Regions | D47: Clippers Quay | E47: Helen Bowers | F47: Parking D20 Torrens Apt, Salford M50 | G47: Emily Rees | I47: Current | J47: 45164 | L47: 45164 | M47: 45529 | N47: New Let | O47: Licence | P47: 1380 | Q47: 115 | R47: 1200 | S47: 1500 | T47: 1200 | U47: 1380 | V47: Cleared | W47: 0 | X47: 0 | Y47: 0 | AA47: HB2 | AB47: 45529
A48: Active | B48: 45535 | C48: BTR-Regions | D48: Clippers Quay | E48: Helen Bowers | F48: Parking E6 Ambassador Apt , Salford M50 | G48: Vishnu Madhusoodanan | I48: Current | J48: 45170 | L48: 45170 | M48: 45535 | N48: New Let | O48: Licence | P48: 1380 | Q48: 115 | R48: 1260 | S48: 1500 | T48: 1260 | U48: 1380 | V48: Cleared | W48: 0 | X48: 0 | Y48: 0 | AA48: HB2 | AB48: 45535
A49: Active | B49: 45481 | C49: Rev-London & SE | D49: Denman (Rev) | E49: Darin Solomon | F49: Shed 17, Denman House, Lordship Terrace, N16 | G49: Melody Barlett | I49: Current | J49: 44721 | L49: 45116 | M49: 45481 | N49: Renewal | O49: Licence | P49: 300 | Q49: 25 | R49: 273 | S49: 300 | T49: 273 | U49: 300 | V49: Cleared | W49: 0 | AA49: DSX | AB49: 45481
A50: Active | B50: 45504 | C50: Rev-London & SE | D50: Dibdin (Rev) | E50: Darin Solomon | F50: Shed 68, Dibdin Hse , Andover Place, W9 1QE | G50: Ashraf Al-Ansari | I50: Current | J50: 45139 | L50: 45139 | M50: 45504 | N50: New Let | O50: Licence | P50: 300 | Q50: 25 | R50: 1200 | S50: 300 | T50: 100 | U50: 300 | V50: Credit | W50: 0 | AA50: DSX | AB50: 45504
A51: Active | B51: 45517 | C51: Rev-London & SE | D51: Dibdin (Rev) | E51: Darin Solomon | F51: Shed 87, Dibdin Hse , Andover Place, W9 1QE | G51: Maria Virto | I51: Current | J51: 45152 | L51: 45152 | M51: 45517 | N51: New Let | O51: Licence | P51: 300 | Q51: 25 | R51: 80.04 | S51: 300 | T51: 80 | U51: 300 | V51: Cleared | W51: 0 | AA51: DSX | AB51: 45517
A52: Pending | B52: 45504 | C52: Rev-London & SE | D52: Dibdin (Rev) | E52: Darin Solomon | F52: Shed 61, Dibdin Hse , Andover Place, W9 1QE | G52: Miss Alison Brown | I52: Current | J52: 39713 | L52: 45323 | M52: 45504 | N52: Renewal | O52: Licence | P52: 80 | Q52: 6.6666667 | R52: 80 | S52: 360 | T52: 80 | U52: 80 | V52: Cleared | W52: 0 | AA52: DSX | AB52: 45504
A53: Active | B53: 45479 | C53: BTR-Regions | D53: Enigma Square | E53: Tina Viragh | F53: Parking 106 Enigma Square | G53: Jamie Patel | I53: Current | J53: 45114 | L53: 45114 | M53: 45479 | N53: New Let | O53: Licence | P53: 360 | Q53: 30 | R53: 360 | S53: 480 | T53: 360 | U53: 360 | V53: Cleared | W53: 0 | AA53: JBE | AB53: 45479
A54: Active | B54: 45485 | C54: BTR-Regions | D54: Enigma Square | E54: Tina Viragh | F54: Parking 119 Enigma Square | G54: Alex Meade | I54: Current | J54: 45120 | L54: 45120 | M54: 45485 | N54: New Let | O54: Licence | P54: 360 | Q54: 30 | R54: 360 | S54: 600 | T54: 360 | U54: 360 | V54: Cleared | W54: 0 | AA54: JBE | AB54: 45485
A55: Active | B55: 45489 | C55: BTR-Regions | D55: Enigma Square | E55: Tina Viragh | F55: Parking 154 Enigma Square | G55: Ting Chan | I55: Current | J55: 45124 | L55: 45155 | M55: 45489 | N55: Renewal | O55: Licence | P55: 360 | Q55: 30 | R55: 360 | S55: 600 | T55: 600 | U55: 360 | V55: Cleared | W55: 0 | AA55: JBE | AB55: 45489
A56: Active | B56: 45489 | C56: BTR-Regions | D56: Enigma Square | E56: Tina Viragh | F56: Parking 23 Enigma Square | G56: Michael Hollis | I56: Current | J56: 45124 | L56: 45124 | M56: 45489 | N56: New Let | O56: Licence | P56: 360 | Q56: 30 | R56: 360 | S56: 600 | T56: 360 | U56: 360 | V56: Cleared | W56: 0 | AA56: JBE | AB56: 45489
A57: Active | B57: 45493 | C57: BTR-Regions | D57: Enigma Square | E57: Tina Viragh | F57: Parking 96 Enigma Square | G57: Cephas Kang | I57: Current | J57: 45128 | L57: 45128 | M57: 45493 | N57: New Let | O57: Licence | P57: 360 | Q57: 30 | R57: 360 | S57: 600 | T57: 360 | U57: 360 | V57: Cleared | W57: 0 | AA57: JBE | AB57: 45493
A58: Active | B58: 45508 | C58: BTR-Regions | D58: Enigma Square | E58: Tina Viragh | F58: Parking 26 Enigma Square | G58: Stephen Burch | I58: Current | J58: 45143 | L58: 45143 | M58: 45508 | N58: New Let | O58: Licence | P58: 360 | Q58: 30 | R58: 360 | S58: 600 | T58: 360 | U58: 360 | V58: Cleared | W58: 0 | AA58: JBE | AB58: 45508
A59: Active | B59: 45510 | C59: BTR-Regions | D59: Enigma Square | E59: Tina Viragh | F59: Parking 107 Enigma Square | G59: Marc Leonard | I59: Current | J59: 45145 | L59: 45145 | M59: 45510 | N59: New Let | O59: Licence | P59: 360 | Q59: 30 | R59: 360 | S59: 480 | T59: 360 | U59: 360 | V59: Arrears | W59: 0 | AA59: JBE | AB59: 45510
A60: Active | B60: 45510 | C60: BTR-Regions | D60: Enigma Square | E60: Tina Viragh | F60: Parking 108 Enigma Square | G60: Carly McGill | I60: Current | J60: 45145 | L60: 45145 | M60: 45510 | N60: New Let | O60: Licence | P60: 360 | Q60: 30 | R60: 360 | S60: 480 | T60: 360 | U60: 360 | V60: Cleared | W60: 0 | AA60: JBE | AB60: 45510
... A85: Pending | B85: 45535 | C85: BTR-Regions | D85: Enigma Square | E85: Tina Viragh | F85: Parking 136 Enigma Square | G85: Peter Murphy | I85: Current | J85: 45352 | L85: 45352 | M85: 45535 | N85: New Let | O85: Licence | P85: 360 | Q85: 30 | R85: 600 | S85: 600 | T85: 636 | U85: 360 | V85: Cleared | W85: 0 | AA85: TVX | AB85: 45992
A86: Active | B86: 45477 | C86: BTR-London & SE | D86: Gatehouse Apartments | E86: Alice Shaw | F86: Parking 44 - Level 0 | G86: Stephen Doran | I86: Current | J86: 44382 | L86: 45112 | M86: 45477 | N86: Renewal | O86: Licence | P86: 1200 | Q86: 100 | R86: 1200 | S86: 1200 | T86: 1200 | U86: 1200 | V86: Cleared | W86: 0 | Z86: Car Parking Space | AA86: AS2 | AB86: 45477
A87: Active | B87: 45480 | C87: BTR-London & SE | D87: Gatehouse Apartments | E87: Alice Shaw | F87: Parking 13 - Level 0 | G87: Stephanie Roberta Clark | I87: Current | J87: 44355 | L87: 45115 | M87: 45480 | N87: Renewal | O87: Licence | P87: 1200 | Q87: 100 | R87: 1200 | S87: 1200 | T87: 1200 | U87: 1200 | V87: Cleared | W87: 0 | Z87: Car Parking Space | AA87: AS2 | AB87: 45480
A88: Active | B88: 45483 | C88: BTR-London & SE | D88: Gatehouse Apartments | E88: Alice Shaw | F88: Parking 11 - Level 0 | G88: Ravikumar Abbigeri | I88: Current | J88: 45118 | L88: 45118 | M88: 45483 | N88: New Let | O88: Licence | P88: 1200 | Q88: 100 | R88: 1200 | S88: 1260 | T88: 1200 | U88: 1200 | V88: Cleared | W88: 0 | Z88: Car Parking Space | AA88: AS2 | AB88: 45483
A89: Active | B89: 45485 | C89: BTR-London & SE | D89: Gatehouse Apartments | E89: Alice Shaw | F89: Parking 21 - Level 0 | G89: Katerina Kgorila | I89: Current | J89: 44390 | L89: 45120 | M89: 45485 | N89: Renewal | O89: Licence | P89: 1200 | Q89: 100 | R89: 1260 | S89: 1260 | T89: 1260 | U89: 1200 | V89: Arrears | W89: 0 | Z89: Car Parking Space | AA89: AS2 | AB89: 45485
A90: Active | B90: 45503 | C90: BTR-London & SE | D90: Gatehouse Apartments | E90: Alice Shaw | F90: Parking 24 - Level 0 | G90: Harry Peacock | I90: Current | J90: 45138 | L90: 45138 | M90: 45503 | N90: New Let | O90: Licence | P90: 1200 | Q90: 100 | R90: 1200 | S90: 1260 | T90: 1200 | U90: 1200 | V90: Cleared | W90: 0 | Z90: Car Parking Space | AA90: AS2 | AB90: 45503
A91: Active | B91: 45511 | C91: BTR-London & SE | D91: Gatehouse Apartments | E91: Alice Shaw | F91: Parking 7 - Level 0 | G91: Valentina Palmini | I91: Current | J91: 44750 | L91: 45115 | M91: 45511 | N91: Renewal | O91: Licence | P91: 1200 | Q91: 100 | R91: 1200 | S91: 1200 | T91: 1200 | U91: 1200 | V91: Cleared | W91: 0 | Z91: Car Parking Space | AA91: AS2 | AB91: 45511
A92: Active | B92: 45513 | C92: BTR-London & SE | D92: Gatehouse Apartments | E92: Alice Shaw | F92: Parking 33 - Level 0 | G92: Anna Patricia Simonds | I92: Current | J92: 44783 | L92: 45148 | M92: 45513 | N92: Renewal | O92: Licence | P92: 1200 | Q92: 100 | R92: 1200 | S92: 1200 | T92: 1200 | U92: 1200 | V92: Cleared | W92: 0 | Z92: Car Parking Space | AA92: AS2 | AB92: 45513
A93: Active | B93: 45515 | C93: BTR-London & SE | D93: Gatehouse Apartments | E93: Alice Shaw | F93: Parking 43 - Level 0 | G93: Frederick Newbury | I93: Current | J93: 44785 | L93: 45150 | M93: 45515 | N93: Renewal | O93: Licence | P93: 1200 | Q93: 100 | R93: 1200 | S93: 1200 | T93: 1200 | U93: 1200 | V93: Cleared | W93: 0 | Z93: Car Parking Space | AA93: AS2 | AB93: 45515
A94: Active | B94: 45524 | C94: BTR-London & SE | D94: Gatehouse Apartments | E94: Alice Shaw | F94: Parking 8 - Level 0 | G94: Adam Else | I94: Current | J94: 45159 | L94: 45159 | M94: 45524 | N94: New Let | O94: Licence | P94: 1200 | Q94: 100 | R94: 1200 | S94: 1260 | T94: 1200 | U94: 1200 | V94: Cleared | W94: 0 | Z94: Car Parking Space | AA94: AS2 | AB94: 45524
A95: Active | B95: 45529 | C95: BTR-London & SE | D95: Gatehouse Apartments | E95: Alice Shaw | F95: Parking 47 - Level 0 | G95: Ross Eldridge | I95: Current | J95: 45352 | L95: 45352 | M95: 45351 | N95: New Let | O95: Licence | P95: 1200 | Q95: 100 | R95: 1200 | S95: 1260 | T95: 1200 | U95: 1200 | V95: Cleared | W95: 0 | Z95: Car Parking Space | AA95: AS2 | AB95: 45716
A96: Active | B96: 45535 | C96: BTR-London & SE | D96: Gatehouse Apartments | E96: Alice Shaw | F96: Parking 4 - Level 0 | G96: Raymond Felton | I96: Current | J96: 44805 | L96: 45170 | M96: 45535 | N96: Renewal | O96: Licence | P96: 1200 | Q96: 100 | R96: 1260 | S96: 1260 | T96: 1260 | U96: 1200 | V96: Cleared | W96: 0 | Z96: Car Parking Space | AA96: AS2 | AB96: 45535
A97: Active | B97: 45493 | C97: BTR-Regions | D97: Gilders Yard | E97: James Bell | F97: Parking 27 & 41 | G97: Mears Ltd | I97: Current | J97: 45128 | L97: 45128 | M97: 45493 | N97: New Let | O97: Licence | P97: 1728 | Q97: 144 | R97: 2100 | S97: 2100 | T97: 2100 | U97: 1728 | V97: Arrears | W97: 0 | AA97: JBE | AB97: 45493
A98: Active | B98: 45497 | C98: BTR-Regions | D98: Gilders Yard | E98: James Bell | F98: Parking 1 | G98: Sarah Will | I98: Current | J98: 45132 | L98: 45132 | M98: 45497 | N98: New Let | O98: Licence | P98: 1728 | Q98: 144 | R98: 1500 | S98: 1500 | T98: 1500 | U98: 1728 | V98: Cleared | W98: 0 | AA98: JBE | AB98: 45497
A99: Active | B99: 45503 | C99: BTR-Regions | D99: Gilders Yard | E99: James Bell | F99: Parking 4 | G99: Mears Ltd | I99: Current | J99: 45138 | L99: 45138 | M99: 45503 | N99: New Let | O99: Licence | P99: 1728 | Q99: 144 | R99: 1500 | S99: 1500 | T99: 1500 | U99: 1728 | V99: Arrears | W99: 0 | AA99: JBE | AB99: 45503
A100: Pending | B100: 45525 | C100: BTR-Regions | D100: Gilders Yard | E100: James Bell | F100: Parking 12 | G100: Maggie Grogan | I100: Current | J100: 45282 | L100: 45282 | M100: 45525 | N100: New Let | O100: Licence | P100: 1728 | Q100: 144 | R100: 1500 | S100: 1500 | T100: 1500 | U100: 1728 | V100: Cleared | W100: 0 | AA100: JBE | AB100: 45525
A101: Active | B101: 45478 | C101: Grainger Trust | D101: GT - Millet Place | E101: Kaycee Cooper | F101: Parking bay 8, Poppy Apartments, E16 2YH | G101: Jake Howler | I101: Current | J101: 45113 | L101: 45113 | M101: 45478 | N101: New Let | O101: Licence | P101: 1560 | Q101: 130 | R101: 0 | S101: 1560 | T101: 1560 | U101: 1560 | V101: Cleared | W101: 0 | X101: 0 | Y101: 0 | Z101: PARKING BAYLower ground | AA101: KC2 | AB101: 45478
A102: Active | B102: 45513 | C102: Grainger Trust | D102: GT - Millet Place | E102: Kaycee Cooper | F102: Parking bay 7, Poppy Apartments, E16 2YH | G102: Nagina Rehman | I102: Current | J102: 44691 | L102: 45148 | M102: 45513 | N102: Renewal | O102: Licence | P102: 1320 | Q102: 110 | R102: 1320 | S102: 1320 | T102: 1320 | U102: 1320 | V102: Cleared | W102: 0 | X102: 0 | Y102: 0 | Z102: PARKING BAYLower ground | AA102: KC2 | AB102: 45513
A103: Active | B103: 45521 | C103: Grainger Trust | D103: GT - Millet Place | E103: Kaycee Cooper | F103: Parking bay 10, Poppy Apartments, E16 2YH | G103: Ziaul Haque | I103: Current | J103: 45156 | L103: 45156 | M103: 45521 | N103: New Let | O103: Licence | P103: 1320 | Q103: 110 | R103: 1560 | S103: 1320 | T103: 1560 | U103: 1320 | V103: Cleared | W103: 0 | X103: 0 | Y103: 0 | Z103: PARKING BAYDisabled; Wheelchair | AA103: KC2 | AB103: 45521
A104: Active | B104: 45535 | C104: Grainger Trust | D104: GT - Millet Place | E104: Kaycee Cooper | F104: Parking bay 3, Poppy Apartments, E16 2YH | G104: Jose Vargas | I104: Current | J104: 45170 | L104: 45170 | M104: 45535 | N104: New Let | O104: Licence | P104: 1560 | Q104: 130 | R104: 0 | S104: 1560 | T104: 1560 | U104: 1560 | V104: Cleared | W104: 0 | X104: 0 | Y104: 0 | Z104: PARKING BAYLower ground | AA104: SOX | AB104: 45535
A105: Pending | B105: 45496 | C105: Grainger Trust | D105: GT - Millet Place | E105: Kaycee Cooper | F105: Parking bay 36, Poppy Apartments, E16 2YH | G105: Hamsa Yusuf | I105: Current | J105: 45131 | L105: 45315 | M105: 45496 | N105: Renewal | O105: Licence | P105: 1560 | Q105: 130 | R105: 0 | S105: 1560 | T105: 1560 | U105: 1560 | V105: Cleared | W105: 0 | X105: 0 | Y105: 0 | Z105: PARKING BAYElectric; Wheelchair Access | AA105: KC2 | AB105: 45496
A106: Active | B106: 45482 | C106: BTR-London & SE | D106: Gunhill | E106: Megan Fleming | F106: Parking 2, 2 Bradbury Apts, Aldershot GU11 | G106: Harjit Karir & Stephanie Alonzo | I106: Current | J106: 44752 | L106: 44752 | M106: 45482 | N106: New Let | O106: Licence | P106: 0 | Q106: 0 | R106: 0 | S106: 0 | T106: 0 | U106: 0 | V106: Cleared | W106: 0 | X106: 0 | Y106: 0 | Z106: car park | AA106: AG4 | AB106: 45482
A107: Active | B107: 45486 | C107: BTR-London & SE | D107: Gunhill | E107: Megan Fleming | F107: Parking 103(D), 1 Mundy Place, Aldershot GU11 | G107: Scott West & Natasha Fotheringham | I107: Current | J107: 44756 | L107: 44756 | M107: 45486 | N107: New Let | O107: Licence | P107: 0 | Q107: 0 | R107: 0 | S107: 0 | T107: 0 | U107: 0 | V107: Cleared | W107: 0 | X107: 0 | Y107: 0 | Z107: car park | AA107: AG4 | AB107: 45486
A108: Active | B108: 45486 | C108: BTR-London & SE | D108: Gunhill | E108: Megan Fleming | F108: Parking 103, 1 Mundy Place, Aldershot GU11 | G108: Scott West & Natasha Fotheringham | I108: Current | J108: 44756 | L108: 44756 | M108: 45486 | N108: New Let | O108: Licence | P108: 0 | Q108: 0 | R108: 0 | S108: 0 | T108: 0 | U108: 0 | V108: Cleared | W108: 0 | X108: 0 | Y108: 0 | Z108: car park | AA108: AG4 | AB108: 45486
A109: Active | B109: 45479 | C109: BTR-Regions | D109: Hawkins & George | E109: Sarah Regan | F109: Parking 22, Hawkins and George, Bristol BS1 | G109: Metin Gerceker | I109: Current | J109: 45206 | K109: 45481 | L109: 45206 | M109: 45479 | N109: New Let | O109: Licence | P109: 1500 | Q109: 125 | R109: 1200 | S109: 1260 | T109: 1260 | U109: 1500 | V109: Cleared | W109: 0 | X109: 0 | Y109: 0 | AA109: SR5 | AB109: 45479
A110: Active | B110: 45480 | C110: BTR-Regions | D110: Hawkins & George | E110: Sarah Regan | F110: Parking 75, Hawkins and George, Bristol BS1 | G110: Wai Kwan Kwok | I110: Current | J110: 44750 | L110: 45115 | M110: 45480 | N110: Renewal | O110: Licence | P110: 1500 | Q110: 125 | R110: 1200 | S110: 1500 | T110: 1200 | U110: 1500 | V110: Cleared | W110: 0 | X110: 0 | Y110: 0 | AA110: SR5 | AB110: 45480
A111: Active | B111: 45483 | C111: BTR-Regions | D111: Hawkins & George | E111: Sarah Regan | F111: Parking 198, Hawkins and George, Bristol BS1 | G111: Tsoi Tung Hiu | I111: Current | J111: 45118 | L111: 45118 | M111: 45483 | N111: New Let | O111: Licence | P111: 900 | Q111: 75 | R111: 600 | S111: 1500 | T111: 1200 | U111: 900 | V111: Cleared | W111: 0 | X111: 0 | Y111: 0 | AA111: SR5 | AB111: 45483
A112: Active | B112: 45487 | C112: BTR-Regions | D112: Hawkins & George | E112: Sarah Regan | F112: Parking 190, Hawkins and George, Bristol BS1 | G112: Simon Griffiths | I112: Current | J112: 44026 | L112: 45122 | M112: 45487 | N112: Renewal | O112: Licence | P112: 900 | Q112: 75 | R112: 1200 | S112: 1500 | T112: 1200 | U112: 900 | V112: Cleared | W112: 0 | X112: 0 | Y112: 0 | AA112: SR5 | AB112: 45487
A113: Active | B113: 45488 | C113: BTR-Regions | D113: Hawkins & George | E113: Sarah Regan | F113: Parking 44, Hawkins and George, Bristol BS1 | G113: Mr Luis Oliveira | I113: Current | J113: 44275 | L113: 45123 | M113: 45488 | N113: Renewal | O113: Licence | P113: 1500 | Q113: 125 | R113: 1200 | S113: 1500 | T113: 1200 | U113: 1500 | V113: Cleared | W113: 0 | X113: 0 | Y113: 0 | AA113: SR5 | AB113: 45488
A114: Active | B114: 45490 | C114: BTR-Regions | D114: Hawkins & George | E114: Sarah Regan | F114: Parking 268, Hawkins and George, Bristol BS1 | G114: Charlie Hirst | I114: Current | J114: 44698 | L114: 45125 | M114: 45490 | N114: Renewal | O114: Licence | P114: 900 | Q114: 75 | R114: 1200 | S114: 1500 | T114: 1200 | U114: 900 | V114: Arrears | W114: 0 | X114: 0 | Y114: 0 | AA114: SR5 | AB114: 45490
A115: Active | B115: 45497 | C115: BTR-Regions | D115: Hawkins & George | E115: Sarah Regan | F115: Parking 84, Hawkins and George, Bristol BS1 | G115: Aimie Grant | I115: Current | J115: 45132 | L115: 45132 | M115: 45497 | N115: New Let | O115: Licence | P115: 1500 | Q115: 125 | R115: 1200 | S115: 1500 | T115: 1200 | U115: 1500 | V115: Cleared | W115: 0 | X115: 0 | Y115: 0 | AA115: SR5 | AB115: 45497
A116: Active | B116: 45500 | C116: BTR-Regions | D116: Hawkins & George | E116: Sarah Regan | F116: Parking 110, Hawkins and George, Bristol BS1 | G116: Emily Wass | I116: Current | J116: 44405 | L116: 45135 | M116: 45500 | N116: Renewal | O116: Licence | P116: 1500 | Q116: 125 | R116: 1260 | S116: 1500 | T116: 1260 | U116: 1500 | V116: Cleared | W116: 0 | X116: 0 | Y116: 0 | AA116: SR5 | AB116: 45500
A117: Active | B117: 45500 | C117: BTR-Regions | D117: Hawkins & George | E117: Sarah Regan | F117: Parking 192, Hawkins and George, Bristol BS1 | G117: Richard Lovatt | I117: Current | J117: 45135 | L117: 45135 | M117: 45500 | N117: New Let | O117: Licence | P117: 900 | Q117: 75 | R117: 1200 | S117: 1500 | T117: 1200 | U117: 900 | V117: Cleared | W117: 0 | X117: 0 | Y117: 0 | AA117: SR5 | AB117: 45500
A118: Active | B118: 45503 | C118: BTR-Regions | D118: Hawkins & George | E118: Sarah Regan | F118: Parking 199, Hawkins and George, Bristol BS1 | G118: Lihan Jiang | I118: Current | J118: 45138 | L118: 45138 | M118: 45503 | N118: New Let | O118: Licence | P118: 900 | Q118: 75 | R118: 1200 | S118: 1500 | T118: 1260 | U118: 900 | V118: Cleared | W118: 0 | X118: 0 | Y118: 0 | AA118: SR5 | AB118: 45503
A119: Active | B119: 45504 | C119: BTR-Regions | D119: Hawkins & George | E119: Sarah Regan | F119: Parking 100, Hawkins and George, Bristol BS1 | G119: Aaditya Sonah Ori | I119: Current | J119: 45139 | K119: 45504 | L119: 45139 | M119: 45504 | N119: New Let | O119: Licence | P119: 1500 | Q119: 125 | R119: 1260 | S119: 1500 | T119: 1260 | U119: 1500 | V119: Cleared | W119: 0 | X119: 0 | Y119: 0 | AA119: SR5 | AB119: 45504
A120: Active | B120: 45504 | C120: BTR-Regions | D120: Hawkins & George | E120: Sarah Regan | F120: Parking 83, Hawkins and George, Bristol BS1 | G120: Ciara Halpin | I120: Current | J120: 44774 | L120: 45139 | M120: 45504 | N120: Renewal | O120: Licence | P120: 1500 | Q120: 125 | R120: 1200 | S120: 1500 | T120: 1200 | U120: 1500 | V120: Cleared | W120: 0 | X120: 0 | Y120: 0 | AA120: SR5 | AB120: 45504
A121: Active | B121: 45504 | C121: BTR-Regions | D121: Hawkins & George | E121: Sarah Regan | F121: Parking 98, Hawkins and George, Bristol BS1 | G121: Alena Vakulich & Yuriy Voronkov | I121: Current | J121: 45139 | L121: 45139 | M121: 45504 | N121: New Let | O121: Licence | P121: 1500 | Q121: 125 | R121: 1200 | S121: 1500 | T121: 1200 | U121: 1500 | V121: Cleared | W121: 0 | X121: 0 | Y121: 0 | AA121: SR5 | AB121: 45504
A122: Active | B122: 45505 | C122: BTR-Regions | D122: Hawkins & George | E122: Sarah Regan | F122: Parking 73, Hawkins and George, Bristol BS1 | G122: Huan Jiang | I122: Current | J122: 45140 | L122: 45140 | M122: 45505 | N122: New Let | O122: Licence | P122: 1500 | Q122: 125 | R122: 1260 | S122: 1500 | T122: 1260 | U122: 1500 | V122: Cleared | W122: 0 | X122: 0 | Y122: 0 | AA122: SR5 | AB122: 45505
A123: Active | B123: 45513 | C123: BTR-Regions | D123: Hawkins & George | E123: Sarah Regan | F123: Parking 197, Hawkins and George, Bristol BS1 | G123: Adam Newton | I123: Current | J123: 45148 | L123: 45148 | M123: 45513 | N123: New Let | O123: Licence | P123: 900 | Q123: 75 | R123: 1200 | S123: 1500 | T123: 1200 | U123: 900 | V123: Cleared | W123: 0 | X123: 0 | Y123: 0 | AA123: SR5 | AB123: 45513
A124: Active | B124: 45515 | C124: BTR-Regions | D124: Hawkins & George | E124: Sarah Regan | F124: Parking 95, Hawkins and George, Bristol BS1 | G124: Joshua Campden-Alexander | I124: Current | J124: 45352 | L124: 45352 | M124: 45716 | N124: New Let | O124: Licence | P124: 1500 | Q124: 125 | R124: 1200 | S124: 1500 | T124: 1500 | U124: 1500 | V124: Cleared | W124: 0 | X124: 0 | Y124: 0 | AA124: SR5 | AB124: 45716
...

Sheet DO NOT APPROACH
A1: Diary Status | B1: Event Date | C1: Portfolio | D1: Estate | E1: Unit Manager | F1: Unit Description | G1: Current Tenant Name | H1: PM Details | I1: Tenancy Status | J1: Tenancy Start Date | K1: Lease Start Date | L1: Lease End Date | M1: Action Type | N1: Unit Tenure | O1: September 23 Annual ERV | P1: September 23 Monthly ERV | Q1: March 24 Annual ERV | R1: March 24 Monthly ERV | S1: Current Annual Rent | T1: Current Monthly Rent | U1: Previous Rent | V1: Price Book Rent | W1: Price Book / Current Rent % | X1: Price Book / March 24 ERV % | Y1: AM Offering | Z1: AM Offering / Current Rent % | AA1: AM Offering / March 24 ERV % | AB1: AM Minimum | AC1: AM Minimum / Current Rent % | AD1: AM Minimum / Sept ERV % | AE1: AM Comments | AF1: Tenant Balance Status | AG1: Unit Size | AH1: Number of Beds | AI1: Number of Baths | AJ1: Description of Unit | AK1: Renewal Neg | AL1: Renewal Notes Date | AM1: Renewal Notes
A2: denied | B2: 45521 | C2: BTR-Regions | D2: Clippers Quay | E2: Helen Bowers | F2: 808 Syren Apt , Ottinger Close, Salford M50 | G2: Revanth Challa, Venjata Chebiam, Sreeja Balne | H2: do not renew - residents have fallen out/wont agree to change of sharer. | I2: Current | J2: 44791 | K2: 45156 | L2: 45521 | M2: Renewal | N2: AST | O2: 16020 | P2: 1335 | Q2: 16560 | R2: =Q2/12 -> 1380 | S2: 15720 | T2: =S2/12 -> 1310 | U2: 14340 | V2: 1410 | W2: =(V2-T2)/T2 -> 0.076335878 | X2: =(V2-R2)/R2 -> 0.02173913 | Z2: =(Y2-T2)/T2 -> -1 | AA2: =(Y2-R2)/R2 -> -1 | AC2: =(AB2-T2)/T2 -> -1 | AD2: =(AB2-R2)/R2 -> -1 | AF2: Cleared | AG2: 668 | AH2: 2 | AI2: 2 | AJ2: 2 BedValencia | AK2: Lacey | AL2: 45521
A3: denied | B3: 45490 | C3: BTR-Regions | D3: Enigma Square | E3: Tina Viragh | F3: 506 Enigma Square, 414 North Row, MK9 2FU | G3: Akanksha Mehta & Ayush Jain | H3: Do not offer renewal - problematic towards site team | I3: Current | J3: 45125 | K3: 45125 | L3: 45490 | M3: New Let | N3: AST | O3: 15912 | P3: 1326 | Q3: 17316 | R3: =Q3/12 -> 1443 | S3: 15600 | T3: =S3/12 -> 1300 | U3: 15912 | V3: 1470 | W3: =(V3-T3)/T3 -> 0.13076923 | X3: =(V3-R3)/R3 -> 0.018711019 | Z3: =(Y3-T3)/T3 -> -1 | AA3: =(Y3-R3)/R3 -> -1 | AC3: =(AB3-T3)/T3 -> -1 | AD3: =(AB3-R3)/R3 -> -1 | AF3: Cleared | AG3: 528.6 | AH3: 1 | AI3: 1 | AJ3: 1B2P, 01D(J)North East, Balcony | AK3: Sophie | AL3: 45490
A4: denied | B4: 45486 | C4: BTR-Regions | D4: Enigma Square | E4: Tina Viragh | F4: 708 Enigma Square, 414 North Row, MK9 2FU | G4: S Bedre, R Patil, S Amin and S Chavan | H4: Do not offer renewal. Residents have been verbally abusive to site team and caused lots of issues | I4: Current | J4: 45121 | K4: 45121 | L4: 45486 | M4: New Let | N4: AST | O4: 20540 | P4: 1711.6667 | Q4: 21320 | R4: =Q4/12 -> 1776.6667 | S4: 21240 | T4: =S4/12 -> 1770 | U4: 20540 | V4: 1890 | W4: =(V4-T4)/T4 -> 0.06779661 | X4: =(V4-R4)/R4 -> 0.063789869 | Z4: =(Y4-T4)/T4 -> -1 | AA4: =(Y4-R4)/R4 -> -1 | AC4: =(AB4-T4)/T4 -> -1 | AD4: =(AB4-R4)/R4 -> -1 | AF4: Cleared | AG4: 664.3 | AH4: 2 | AI4: 2 | AJ4: 2B4P, 02D(M)North East, Balcony | AK4: Sophie | AL4: 45486
A5: denied | B5: 45521 | C5: BTR-Regions | D5: The Filaments | E5: Samantha Lancaster | F5: 804, Halogen House, 217 Chapel St, Salford, M | G5: Okikioluwa Fagbemi & Khalid Adeleke | H5: No - Do not offer, too many noise disturbances - check with PM | I5: Current | J5: 45156 | K5: 45156 | L5: 45521 | M5: New Let | N5: AST | O5: 24600 | P5: 2050 | Q5: 25200 | R5: =Q5/12 -> 2100 | S5: 24600 | T5: =S5/12 -> 2050 | U5: 21540 | V5: 2195 | W5: =(V5-T5)/T5 -> 0.070731707 | X5: =(V5-R5)/R5 -> 0.045238095 | Z5: =(Y5-T5)/T5 -> -1 | AA5: =(Y5-R5)/R5 -> -1 | AC5: =(AB5-T5)/T5 -> -1 | AD5: =(AB5-R5)/R5 -> -1 | AF5: Arrears | AG5: 874 | AH5: 3 | AI5: 2 | AJ5: Balcony, ESE3 Bed - TYPE A | AK5: Lacey | AL5: 45521
A6: denied | B6: 45533 | C6: BTR-London & SE | D6: The Mint | E6: Kimberley Pope | F6: 315 Assay Apartments, Station View, Guildford | G6: Khaled Alalawi | H6: Resident has had final warnings relating to smoke on apartment balcony. Reports this is ongoing. Therefore, no renewal will be offered. | I6: Current | J6: 45168 | K6: 45168 | L6: 45533 | M6: New Let | N6: AST | O6: 19920 | P6: 1660 | Q6: 20040 | R6: =Q6/12 -> 1670 | S6: 19740 | T6: =S6/12 -> 1645 | U6: 19920 | V6: 1750 | W6: =(V6-T6)/T6 -> 0.063829787 | X6: =(V6-R6)/R6 -> 0.047904192 | Z6: =(Y6-T6)/T6 -> -1 | AA6: =(Y6-R6)/R6 -> -1 | AC6: =(AB6-T6)/T6 -> -1 | AD6: =(AB6-R6)/R6 -> -1 | AF6: Cleared | AG6: 586.97 | AH6: 1 | AI6: 1 | AJ6: 1b2p, 1DNorth, Balcony | AK6: Jemma | AL6: 45533
A7: Aborted | B7: 45530 | C7: BTR-London & SE | D7: Argo Apartments | E7: Fatma Azakli | F7: 108 Argo Apts,4 Silvertown Way,London,E16 1YD | G7: Zitong Zhao & Oliver Firth | H7: They have vacated. | I7: Current | J7: 44435 | K7: 45165 | L7: 45530 | M7: Renewal | N7: AST | O7: 23640 | P7: 1970 | Q7: 23820 | R7: =Q7/12 -> 1985 | S7: 22140 | T7: =S7/12 -> 1845 | U7: 20400 | V7: 2130 | W7: =(V7-T7)/T7 -> 0.15447154 | X7: =(V7-R7)/R7 -> 0.073047859 | Z7: =(Y7-T7)/T7 -> -1 | AA7: =(Y7-R7)/R7 -> -1 | AC7: =(AB7-T7)/T7 -> -1 | AD7: =(AB7-R7)/R7 -> -1 | AF7: Cleared | AG7: 572 | AH7: 1 | AI7: 1 | AJ7: 1 bed & 1 bath South-West Right13th floor | AK7: Jemma | AL7: 45530
A8: ntq | B8: 45534 | C8: BTR-Regions | D8: Enigma Square | E8: Tina Viragh | F8: 719 Enigma Square, 414 North Row, MK9 2GE | G8: Mr Radhakrishnan, Miss Khambete, Mr Sundarraj | H8: Wants early release - do not offer renewal if they change their mind | I8: Current | J8: 45169 | K8: 45169 | L8: 45534 | M8: New Let | N8: AST | O8: 23504 | P8: 1958.6667 | Q8: 25168 | R8: =Q8/12 -> 2097.3333 | S8: 23940 | T8: =S8/12 -> 1995 | U8: 22620 | V8: 2020 | W8: =(V8-T8)/T8 -> 0.012531328 | X8: =(V8-R8)/R8 -> -0.036872219 | Z8: =(Y8-T8)/T8 -> -1 | AA8: =(Y8-R8)/R8 -> -1 | AC8: =(AB8-T8)/T8 -> -1 | AD8: =(AB8-R8)/R8 -> -1 | AF8: Cleared | AG8: 1065.8 | AH8: 3 | AI8: 1 | AJ8: 3B6P, 03BSouth East, Balcony | AK8: Sophie | AL8: 45534
A9: ntq | B9: 45510 | C9: BTR-Regions | D9: Enigma Square | E9: Tina Viragh | F9: 809 Enigma Square, 414 North Row, MK9 2GE | G9: Carly McGill and Marc Leonard | H9: Has requested early release - will not be renewing | I9: Current | J9: 45145 | K9: 45145 | L9: 45510 | M9: New Let | N9: AST | O9: 15288 | P9: 1274 | Q9: 16848 | R9: =Q9/12 -> 1404 | S9: 15600 | T9: =S9/12 -> 1300 | U9: 15288 | V9: 1445 | W9: =(V9-T9)/T9 -> 0.11153846 | X9: =(V9-R9)/R9 -> 0.029202279 | Z9: =(Y9-T9)/T9 -> -1 | AA9: =(Y9-R9)/R9 -> -1 | AC9: =(AB9-T9)/T9 -> -1 | AD9: =(AB9-R9)/R9 -> -1 | AF9: Credit | AG9: 437.2 | AH9: 1 | AI9: 1 | AJ9: 1B2P, 01E(M)South West, Balcony | AK9: Sophie | AL9: 45510
A10: aborted | B10: 45533 | C10: BTR-London & SE | D10: Gatehouse Apartments | E10: Alice Shaw | F10: 103 Gatehouse Apts, 86 East St, Southampton | G10: Miss Keri Cooper, Miss Frances Phillis | H10: Leaving - already on market | I10: Current | J10: 45168 | K10: 45168 | L10: 45533 | M10: New Let | N10: AST | O10: 18600 | P10: 1550 | Q10: 18600 | R10: =Q10/12 -> 1550 | S10: 18600 | T10: =S10/12 -> 1550 | U10: 17820 | V10: 1575 | W10: =(V10-T10)/T10 -> 0.016129032 | X10: =(V10-R10)/R10 -> 0.016129032 | Z10: =(Y10-T10)/T10 -> -1 | AA10: =(Y10-R10)/R10 -> -1 | AC10: =(AB10-T10)/T10 -> -1 | AD10: =(AB10-R10)/R10 -> -1 | AF10: Cleared | AG10: 777 | AH10: 2 | AI10: 2 | AJ10: L7, Encl. balcony, River Itchen/Cruise ship2Bed 4P, Type 2B | AK10: Jemma | AL10: 45533
A11: aborted | B11: 45513 | C11: BTR-London & SE | D11: Gatehouse Apartments | E11: Alice Shaw | F11: 126 Gatehouse Apts, 86 East St, Southampton | G11: Chi Kong Cheung & Wai Man Lee | H11: Leaving - already on market | I11: Current | J11: 44783 | K11: 45148 | L11: 45513 | M11: Renewal | N11: AST | O11: 18600 | P11: 1550 | Q11: 19740 | R11: =Q11/12 -> 1645 | S11: 18540 | T11: =S11/12 -> 1545 | U11: 17280 | V11: 1750 | W11: =(V11-T11)/T11 -> 0.13268608 | X11: =(V11-R11)/R11 -> 0.063829787 | Z11: =(Y11-T11)/T11 -> -1 | AA11: =(Y11-R11)/R11 -> -1 | AC11: =(AB11-T11)/T11 -> -1 | AD11: =(AB11-R11)/R11 -> -1 | AF11: Cleared | AG11: 742 | AH11: 2 | AI11: 2 | AJ11: L13, Encl. balcony, Town Hall/River Itchen2Bed 4P, Type 2A | AK11: Jemma | AL11: 45513
A12: ntq | B12: 45503 | C12: BTR-Regions | D12: Enigma Square | E12: Tina Viragh | F12: 814 Enigma Square, 414 North Row, MK9 2GE | G12: Owen and Tamara Lane | H12: Has requested early release - will not be renewing | I12: Current | J12: 45138 | K12: 45138 | L12: 45503 | M12: New Let | N12: AST | O12: 15600 | P12: 1300 | Q12: 17108 | R12: =Q12/12 -> 1425.6667 | S12: 15720 | T12: =S12/12 -> 1310 | U12: 15600 | V12: 1470 | W12: =(V12-T12)/T12 -> 0.1221374 | X12: =(V12-R12)/R12 -> 0.031096563 | Z12: =(Y12-T12)/T12 -> -1 | AA12: =(Y12-R12)/R12 -> -1 | AC12: =(AB12-T12)/T12 -> -1 | AD12: =(AB12-R12)/R12 -> -1 | AF12: Cleared | AG12: 486 | AH12: 1 | AI12: 1 | AJ12: 1B2P, 01C_S(MJ)North East, Balcony | AK12: Sophie | AL12: 45503
A13: completed | B13: 45504 | C13: Rev-London & SE | D13: Outer London | E13: Robert Steel | F13: 52, Morieux Road, Leyton, London | G13: Mr Harold George Doy | H13: Issue section 13 notice to increase rent to £800 PCM with effect from 1st August 2024. | I13: Current | J13: 45139 | M13: New Let | N13: Assured | O13: 7200 | P13: 600 | R13: =Q13/12 -> 0 | S13: 7200 | T13: =S13/12 -> 600 | U13: 175 | W13: =(V13-T13)/T13 -> -1 | X13: =(V13-R13)/R13 -> #DIV/0! | Z13: =(Y13-T13)/T13 -> -1 | AA13: =(Y13-R13)/R13 -> #DIV/0! | AC13: =(AB13-T13)/T13 -> -1 | AD13: =(AB13-R13)/R13 -> #DIV/0! | AF13: Cleared | AG13: 0 | AJ13: Purpose-built flat ground floor1 bedroom, 1 reception | AK13: Jemma | AL13: 45504
A14: denied | B14: 45534 | C14: BTR-Regions | D14: The Filaments | E14: Samantha Lancaster | F14: 1106, Halogen House, 217 Chapel St, Salford, | G14: Roy Alexander Weise | H14: In arrears - do not offer, notice served | I14: Current | J14: 44439 | K14: 45169 | L14: 45534 | M14: Renewal | N14: AST | O14: 13980 | P14: 1165 | Q14: 14400 | R14: =Q14/12 -> 1200 | S14: 14400 | T14: =S14/12 -> 1200 | U14: 12984 | V14: 1300 | W14: =(V14-T14)/T14 -> 0.083333333 | X14: =(V14-R14)/R14 -> 0.083333333 | Z14: =(Y14-T14)/T14 -> -1 | AA14: =(Y14-R14)/R14 -> -1 | AC14: =(AB14-T14)/T14 -> -1 | AD14: =(AB14-R14)/R14 -> -1 | AF14: Arrears | AG14: 459 | AH14: 1 | AI14: 1 | AJ14: Balcony, ESE1 Bed - TYPE A | AK14: Lacey | AL14: 45534
A15: ntq | B15: 45487 | C15: BTR-Regions | D15: The Filaments | E15: Samantha Lancaster | F15: 406, Halogen House, 217 Chapel St, Salford, M | G15: Henry Swales & Maria Lacerda de Castro | H15: Moving to another unit in Neon House | I15: Current | J15: 44392 | K15: 45122 | L15: 45487 | M15: Renewal | N15: AST | O15: 14100 | P15: 1175 | Q15: 14520 | R15: =Q15/12 -> 1210 | S15: 13620 | T15: =S15/12 -> 1135 | U15: 11880 | V15: 1240 | W15: =(V15-T15)/T15 -> 0.092511013 | X15: =(V15-R15)/R15 -> 0.024793388 | Z15: =(Y15-T15)/T15 -> -1 | AA15: =(Y15-R15)/R15 -> -1 | AC15: =(AB15-T15)/T15 -> -1 | AD15: =(AB15-R15)/R15 -> -1 | AF15: Cleared | AG15: 459 | AH15: 1 | AI15: 1 | AJ15: Balcony, ESE1 Bed - TYPE A | AK15: Lacey | AL15: 45487
A16: ntq | B16: 45502 | C16: BTR-Regions | D16: The Filaments | E16: Samantha Lancaster | F16: 607, Halogen House, 217 Chapel St, Salford, M | G16: Mr Kristian Smith and Mr Toby Gheysen | H16: Bought a house | I16: Current | J16: 44408 | K16: 45137 | L16: 45502 | M16: Renewal | N16: AST | O16: 16920 | P16: 1410 | Q16: 17400 | R16: =Q16/12 -> 1450 | S16: 16680 | T16: =S16/12 -> 1390 | U16: 15180 | V16: 1515 | W16: =(V16-T16)/T16 -> 0.089928058 | X16: =(V16-R16)/R16 -> 0.044827586 | Z16: =(Y16-T16)/T16 -> -1 | AA16: =(Y16-R16)/R16 -> -1 | AC16: =(AB16-T16)/T16 -> -1 | AD16: =(AB16-R16)/R16 -> -1 | AF16: Cleared | AG16: 673 | AH16: 2 | AI16: 2 | AJ16: Balcony, Dual - ESE / SSW2 Bed - TYPE B | AK16: Lacey | AL16: 45502
A17: aborted | B17: 45526 | C17: PRS-London & SE | D17: Bethnal Green | E17: Robert Steel | F17: 6, Temple Dwellings, London, E2 6QG | G17: Lewis White & Giulio Bajona | H17: Tenants vacated 17th March, property now for sale | I17: Current | J17: 44795 | K17: 44795 | L17: 45159 | M17: Renewal | N17: AST | O17: 19200 | P17: 1600 | S17: 20400 | T17: =S17/12 -> 1700 | U17: 19140 | W17: =(V17-T17)/T17 -> -1 | X17: =(V17-R17)/R17 -> #DIV/0! | Z17: =(Y17-T17)/T17 -> -1 | AA17: =(Y17-R17)/R17 -> #DIV/0! | AC17: =(AB17-T17)/T17 -> -1 | AD17: =(AB17-R17)/R17 -> #DIV/0! | AF17: Arrears | AG17: 422.49 | AH17: 1 | AI17: 1 | AJ17: 1 bed/1 bath, kitch, liv rm - PRfrb '17FF | AK17: Jemma | AL17: 45526 | AM17: Section 13 Notice served 6.7.23 to commence 22nd August 2023
A18: Denied | B18: 45517 | C18: PRS-London & SE | D18: Bethnal Green | E18: Robert Steel | F18: 10, Temple Dwellings, London, E2 6QG | G18: Kieran Dawson & Jessica Brassington | H18: 4/4 advised by Asset management to serve a S21 notice | I18: Current | J18: 45152 | K18: 45152 | L18: 45517 | M18: New Let | N18: AST | O18: 19200 | P18: 1600 | S18: 21600 | T18: =S18/12 -> 1800 | U18: 19200 | W18: =(V18-T18)/T18 -> -1 | X18: =(V18-R18)/R18 -> #DIV/0! | Z18: =(Y18-T18)/T18 -> -1 | AA18: =(Y18-R18)/R18 -> #DIV/0! | AC18: =(AB18-T18)/T18 -> -1 | AD18: =(AB18-R18)/R18 -> #DIV/0! | AF18: Cleared | AG18: 433.9 | AH18: 1 | AI18: 1 | AJ18: 1bed / 1bath, kitch, liv, grdn - Refurb '18LGF | AK18: Jemma | AL18: 45517
A19: aborted | B19: 45486 | C19: BTR-Regions | D19: The Headline | E19: Joseph Scarrott | F19: 316, The Headline, Wellington Park Way, Leeds | G19: Rebecca Hall and Edward James | H19: Due to move out 31st March 2024 | I19: Current | J19: 45121 | K19: 45121 | L19: 45486 | M19: New Let | N19: AST | O19: 15300 | P19: 1275 | Q19: 15840 | R19: =Q19/12 -> 1320 | S19: 15300 | T19: =S19/12 -> 1275 | U19: 13740 | V19: 1345 | W19: =(V19-T19)/T19 -> 0.054901961 | X19: =(V19-R19)/R19 -> 0.018939394 | Z19: =(Y19-T19)/T19 -> -1 | AA19: =(Y19-R19)/R19 -> -1 | AC19: =(AB19-T19)/T19 -> -1 | AD19: =(AB19-R19)/R19 -> -1 | AF19: Credit | AG19: 695.3 | AH19: 2 | AI19: 1 | AJ19: 2 Bed, 1 Bath, Type BL3, West | AK19: Lacey | AL19: 45486
A20: Denied | B20: 45487 | C20: BTR-Regions | D20: The Headline | E20: Joseph Scarrott | F20: 501, The Headline, Wellington Park Way, Leeds | G20: F Pennacchieti, G Mugione & C Oliver | H20: Please section 21 | I20: Current | J20: 44758 | K20: 45122 | L20: 45487 | M20: Renewal | N20: AST | O20: 16440 | P20: 1370 | Q20: 17040 | R20: =Q20/12 -> 1420 | S20: 16440 | T20: =S20/12 -> 1370 | U20: 14880 | V20: 1435 | W20: =(V20-T20)/T20 -> 0.047445255 | X20: =(V20-R20)/R20 -> 0.01056338 | Z20: =(Y20-T20)/T20 -> -1 | AA20: =(Y20-R20)/R20 -> -1 | AC20: =(AB20-T20)/T20 -> -1 | AD20: =(AB20-R20)/R20 -> -1 | AF20: Cleared | AG20: 678.1 | AH20: 2 | AI20: 2 | AJ20: 2 Bed, 2 Bath, Type CL5, balcony, East | AK20: Lacey | AL20: 45487
A21: ntq | B21: 45489 | C21: PRS-London & SE | D21: Tilt Core | E21: Yvonne Leggett | F21: Flat 7,Dominic Court,43 The Gardens, SE22 9QR | G21: Jessica Louise Oppong | H21: has served notice ot vacate on 1st September? | I21: Current | J21: 44302 | K21: 45124 | L21: 45489 | M21: Renewal | N21: AST | O21: 17580 | P21: 1465 | R21: =Q21/12 -> 0 | S21: 17700 | T21: =S21/12 -> 1475 | U21: 16740 | W21: =(V21-T21)/T21 -> -1 | X21: =(V21-R21)/R21 -> #DIV/0! | Z21: =(Y21-T21)/T21 -> -1 | AA21: =(Y21-R21)/R21 -> #DIV/0! | AC21: =(AB21-T21)/T21 -> -1 | AD21: =(AB21-R21)/R21 -> #DIV/0! | AF21: Cleared | AG21: 486 | AH21: 1 | AI21: 1 | AJ21: 2 Rooms, Kitchen, Bath Flat - Rfrb 21First floor | AK21: Jemma | AL21: 45489
A22: Aborted | B22: 45487 | C22: PRS-London & SE | D22: Waterloo Estate | E22: Miranda Rowe | F22: 4D Mitre Road, London, SE1 8PY | G22: Alice Harwood & Rosie Moore | H22: Vacating, please abort LE Diary | I22: Current | J22: 44758 | K22: 45122 | L22: 45487 | M22: Renewal | N22: AST | O22: 29400 | P22: 2450 | R22: =Q22/12 -> 0 | S22: 29400 | T22: =S22/12 -> 2450 | U22: 27600 | W22: =(V22-T22)/T22 -> -1 | X22: =(V22-R22)/R22 -> #DIV/0! | Z22: =(Y22-T22)/T22 -> -1 | AA22: =(Y22-R22)/R22 -> #DIV/0! | AC22: =(AB22-T22)/T22 -> -1 | AD22: =(AB22-R22)/R22 -> #DIV/0! | AF22: Credit | AG22: 592.02 | AH22: 2 | AI22: 1 | AK22: Jemma | AL22: 45487
A23: Aborted | B23: 45483 | C23: PRS-Regions | D23: The Rock | E23: David Hancock | F23: 17, 110 The Rock, Bury, BL9 | G23: Imranuddin Khan & Mehak Fathima Khan | H23: Vacating 05.04.24 | I23: Current | J23: 45118 | K23: 45118 | L23: 45483 | M23: New Let | N23: AST | O23: 9660 | P23: 805 | S23: 9360 | T23: =S23/12 -> 780 | U23: 8400 | V23: 825 | W23: =(V23-T23)/T23 -> 0.057692308 | X23: =(P23-T23)/T23 -> 0.032051282 | Z23: =(Y23-T23)/T23 -> -1 | AA23: =(Y23-P23)/P23 -> -1 | AC23: =(AB23-T23)/T23 -> -1 | AD23: =(AB23-P23)/P23 -> -1 | AE23: Think this is either void or FV | AF23: Cleared | AG23: 548.96 | AH23: 1 | AI23: 1 | AJ23: 1 Bedroom Type 1B3/Balcony | AK23: Lacey | AL23: 45483
A24: NTQ | B24: 45534 | C24: PRS-Regions | D24: The Rock | E24: David Hancock | F24: 48, 124 The Rock, Bury, BL9 | G24: Ahmed Esmael & Aya Abdelmoneam | H24: Vacating 17.05.24 | I24: Current | J24: 44804 | K24: 45169 | L24: 45534 | M24: Renewal | N24: AST | O24: 6900 | P24: 575 | S24: 7500 | T24: =S24/12 -> 625 | U24: 6900 | V24: 680 | W24: =(V24-T24)/T24 -> 0.088 | X24: =(P24-T24)/T24 -> -0.08 | Z24: =(Y24-T24)/T24 -> -1 | AA24: =(Y24-P24)/P24 -> -1 | AC24: =(AB24-T24)/T24 -> -1 | AD24: =(AB24-P24)/P24 -> -1 | AE24: Think this is either void or FV | AF24: Cleared | AG24: 344.44 | AH24: 0 | AI24: 1 | AJ24: Studio Type A4/No Balcony | AK24: Lacey | AL24: 45534
A25: ntq | B25: 45486 | C25: PRS-Regions | D25: Kings Dock Mill | E25: Luke Pollard | F25: Apt 165, Kings Dock Mill, Liverpool, L1 | G25: Amber Sardinha & Andrew Harbinson | H25: Residents have served notice to leave - no need to renew | I25: Current | J25: 44757 | K25: 45121 | L25: 45486 | M25: Renewal | N25: AST | O25: 11280 | P25: 940 | S25: 11520 | T25: =S25/12 -> 960 | U25: 10560 | V25: 1030 | W25: =(V25-T25)/T25 -> 0.072916667 | X25: =(P25-T25)/T25 -> -0.020833333 | Z25: =(Y25-T25)/T25 -> -1 | AA25: =(Y25-P25)/P25 -> -1 | AC25: =(AB25-T25)/T25 -> -1 | AD25: =(AB25-P25)/P25 -> -1 | AE25: Think this is either void or FV | AF25: Cleared | AG25: 602.779 | AH25: 2 | AI25: 1 | AJ25: 2 Bedroom | AK25: Lacey | AL25: 45486
A26: denied | B26: 45478 | C26: PRS-Regions | D26: Indigoblu | E26: Ruth Friend | F26: Flat 303, Indigoblu, 14 Crown Point Rd, Leeds | G26: Helen Singleton | H26: No issues, happy for renewal. Being sold so need to chekc with AM first before offering | I26: Current | J26: 45113 | K26: 45113 | L26: 45478 | M26: New Let | N26: AST | O26: 10740 | P26: 895 | S26: 10560 | T26: =S26/12 -> 880 | U26: 9660 | V26: 915 | W26: =(V26-T26)/T26 -> 0.039772727 | X26: =(P26-T26)/T26 -> 0.017045455 | Z26: =(Y26-T26)/T26 -> -1 | AA26: =(Y26-P26)/P26 -> -1 | AC26: =(AB26-T26)/T26 -> -1 | AD26: =(AB26-P26)/P26 -> -1 | AE26: Keep on hold re sale | AF26: Cleared | AG26: 559.72 | AH26: 1 | AI26: 1 | AJ26: 1 Bedroom PB FlatFurnished | AK26: Lacey | AL26: 45478
A27: denied | B27: 45479 | C27: PRS-Regions | D27: Indigoblu | E27: Ruth Friend | F27: Flat 404, Indigoblu, 14 Crown Point Rd, Leeds | G27: Faraaz Memon & Ishita Naik | H27: No issues, happy for renewal. Being sold so need to chekc with AM first before offering | I27: Current | J27: 45114 | K27: 45114 | L27: 45479 | M27: New Let | N27: AST | O27: 10740 | P27: 895 | S27: 10440 | T27: =S27/12 -> 870 | U27: 9600 | V27: 925 | W27: =(V27-T27)/T27 -> 0.063218391 | X27: =(P27-T27)/T27 -> 0.028735632 | Z27: =(Y27-T27)/T27 -> -1 | AA27: =(Y27-P27)/P27 -> -1 | AC27: =(AB27-T27)/T27 -> -1 | AD27: =(AB27-P27)/P27 -> -1 | AE27: Keep on hold re sale | AF27: Cleared | AG27: 559.72 | AH27: 1 | AI27: 1 | AJ27: 1 Bedroom PB FlatFurnished | AK27: Lacey | AL27: 45479
A28: denied | B28: 45480 | C28: PRS-Regions | D28: Indigoblu | E28: Ruth Friend | F28: Flat 209, Indigoblu, 14 Crown Point Rd, Leeds | G28: Cameron Brown | H28: No issues, happy for renewal. Being sold so need to chekc with AM first before offering | I28: Current | J28: 45115 | K28: 45115 | L28: 45480 | M28: New Let | N28: AST | O28: 10740 | P28: 895 | S28: 10440 | T28: =S28/12 -> 870 | U28: 9300 | V28: 905 | W28: =(V28-T28)/T28 -> 0.040229885 | X28: =(P28-T28)/T28 -> 0.028735632 | Z28: =(Y28-T28)/T28 -> -1 | AA28: =(Y28-P28)/P28 -> -1 | AC28: =(AB28-T28)/T28 -> -1 | AD28: =(AB28-P28)/P28 -> -1 | AE28: Keep on hold re sale | AF28: Cleared | AG28: 548.96 | AH28: 1 | AI28: 1 | AJ28: 1 Bedroom PB FlatFurnished | AK28: Lacey | AL28: 45480
A29: denied | B29: 45480 | C29: PRS-Regions | D29: Indigoblu | E29: Ruth Friend | F29: Flat 402, Indigoblu, 14 Crown Point Rd, Leeds | G29: Deaglan Samuel O'Hare & Chris Middleton | H29: No issues, happy for renewal. Being sold so need to chekc with AM first before offering | I29: Current | J29: 44750 | K29: 45115 | L29: 45480 | M29: Renewal | N29: AST | O29: 13020 | P29: 1085 | S29: 12900 | T29: =S29/12 -> 1075 | U29: 11520 | V29: 1115 | W29: =(V29-T29)/T29 -> 0.037209302 | X29: =(P29-T29)/T29 -> 0.0093023256 | Z29: =(Y29-T29)/T29 -> -1 | AA29: =(Y29-P29)/P29 -> -1 | AC29: =(AB29-T29)/T29 -> -1 | AD29: =(AB29-P29)/P29 -> -1 | AE29: Keep on hold re sale | AF29: Cleared | AG29: 753.47 | AH29: 2 | AI29: 2 | AJ29: 2 Bedroom PB Flat - EnsuiteFurnished | AK29: Lacey | AL29: 45480
A30: denied | B30: 45487 | C30: PRS-Regions | D30: Indigoblu | E30: Ruth Friend | F30: Flat 705, Indigoblu, 14 Crown Point Rd, Leeds | G30: Tadas Mazeika, Nhi Thao Do & Thanh Nga Do | H30: No issues, happy for renewal. Being sold so need to chekc with AM first before offering | I30: Current | J30: 44757 | K30: 45122 | L30: 45487 | M30: Renewal | N30: AST | O30: 13020 | P30: 1085 | S30: 13140 | T30: =S30/12 -> 1095 | U30: 11820 | V30: 1140 | W30: =(V30-T30)/T30 -> 0.04109589 | X30: =(P30-T30)/T30 -> -0.0091324201 | Z30: =(Y30-T30)/T30 -> -1 | AA30: =(Y30-P30)/P30 -> -1 | AC30: =(AB30-T30)/T30 -> -1 | AD30: =(AB30-P30)/P30 -> -1 | AE30: Keep on hold re sale | AF30: Cleared | AG30: 807.29 | AH30: 2 | AI30: 2 | AJ30: 2 Bedroom PB Flat - EnsuiteFurnished | AK30: Lacey | AL30: 45487
A31: denied | B31: 45502 | C31: PRS-Regions | D31: Indigoblu | E31: Ruth Friend | F31: Flat 702, Indigoblu, 14 Crown Point Rd, Leeds | G31: Sultan Alsubaie & Abduallah Almugharrid | H31: No issues, happy for renewal. Being sold so need to chekc with AM first before offering | I31: Current | J31: 44957 | K31: 45137 | L31: 45502 | M31: Renewal | N31: AST | O31: 13020 | P31: 1085 | S31: 13140 | T31: =S31/12 -> 1095 | U31: 11760 | V31: 1140 | W31: =(V31-T31)/T31 -> 0.04109589 | X31: =(P31-T31)/T31 -> -0.0091324201 | Z31: =(Y31-T31)/T31 -> -1 | AA31: =(Y31-P31)/P31 -> -1 | AC31: =(AB31-T31)/T31 -> -1 | AD31: =(AB31-P31)/P31 -> -1 | AE31: Keep on hold re sale | AF31: Arrears | AG31: 753.47 | AH31: 2 | AI31: 2 | AJ31: 2 Bedroom PB Flat - EnsuiteFurnished | AK31: Lacey | AL31: 45502
A32: denied | B32: 45514 | C32: PRS-Regions | D32: Indigoblu | E32: Ruth Friend | F32: Flat 202, Indigoblu, 14 Crown Point Rd, Leeds | G32: Murali Manohar & Amrit Priya | H32: No issues, happy for renewal. Being sold so need to chekc with AM first before offering | I32: Current | J32: 45149 | K32: 45149 | L32: 45514 | M32: New Let | N32: AST | O32: 13020 | P32: 1085 | S32: 12600 | T32: =S32/12 -> 1050 | U32: 11220 | V32: 1100 | W32: =(V32-T32)/T32 -> 0.047619048 | X32: =(P32-T32)/T32 -> 0.033333333 | Z32: =(Y32-T32)/T32 -> -1 | AA32: =(Y32-P32)/P32 -> -1 | AC32: =(AB32-T32)/T32 -> -1 | AD32: =(AB32-P32)/P32 -> -1 | AE32: Keep on hold re sale | AF32: Cleared | AG32: 753.47 | AH32: 2 | AI32: 2 | AJ32: 2 Bedroom PB Flat - 1 ensuiteFurnished | AK32: Lacey | AL32: 45514
A33: denied | B33: 45481 | C33: PRS-Regions | D33: North Star Jesmond | E33: Sam Robson | F33: 13, Jesmond Place, Newcastle upon Tyne, NE2 | G33: Majed Alasaly & Maissae Drissennek | H33: N/A | I33: Current | J33: 44935 | K33: 44935 | L33: 45481 | M33: Renewal | N33: AST | O33: 10200 | P33: 850 | S33: 10939.2 | T33: =S33/12 -> 911.6 | U33: 10320 | V33: NPB | X33: =(P33-T33)/T33 -> -0.067573497 | Z33: =(Y33-T33)/T33 -> -1 | AA33: N/A | AC33: =(AB33-T33)/T33 -> -1 | AD33: N/A | AE33: Keep on hold re sale | AF33: Cleared | AG33: 559.72 | AH33: 2 | AI33: 1 | AJ33: 2 Bedroom, FF, Modernised 2017 | AK33: Lacey | AL33: 45481
A34: denied | B34: 45482 | C34: PRS-Regions | D34: North Star Jesmond | E34: Sam Robson | F34: 21, Jesmond Place, Newcastle upon Tyne, NE2 | G34: Ashvina Shegobin & Philip Leese | H34: N/A | I34: Current | J34: 45117 | K34: 45117 | L34: 45482 | M34: New Let | N34: AST | O34: 10200 | P34: 850 | S34: 10620 | T34: =S34/12 -> 885 | U34: 10080 | V34: NPB | X34: =(P34-T34)/T34 -> -0.039548023 | Z34: =(Y34-T34)/T34 -> -1 | AA34: N/A | AC34: =(AB34-T34)/T34 -> -1 | AD34: N/A | AE34: Keep on hold re sale | AF34: Cleared | AG34: 559.72 | AH34: 2 | AI34: 1 | AJ34: 2 Bedroom, TF, Modernised 2020 | AK34: Lacey | AL34: 45482
A35: denied | B35: 45500 | C35: PRS-Regions | D35: North Star Jesmond | E35: Sam Robson | F35: 5, Jesmond Place, Newcastle upon Tyne, NE2 | G35: Paul Gibbons & Rebecca Forster | H35: N/A | I35: Current | J35: 45135 | K35: 45135 | L35: 45500 | M35: New Let | N35: AST | O35: 8520 | P35: 710 | S35: 8880 | T35: =S35/12 -> 740 | U35: 8460 | V35: NPB | X35: =(P35-T35)/T35 -> -0.040540541 | Z35: =(Y35-T35)/T35 -> -1 | AA35: N/A | AC35: =(AB35-T35)/T35 -> -1 | AD35: N/A | AE35: Keep on hold re sale | AF35: Cleared | AG35: 387.5 | AH35: 1 | AI35: 1 | AJ35: 1 Bedroom, FF, Modernised 2018Furnished 2019 | AK35: Lacey | AL35: 45500
A36: denied | B36: 45504 | C36: PRS-Regions | D36: North Star Jesmond | E36: Sam Robson | F36: 4, Jesmond Place, Newcastle upon Tyne, NE2 | G36: Mia Bucklow & Jonty Hanwell | H36: Had a couple of issues with condensation mould, Have helped out quite a bit and havent heard from them in a while. | I36: Current | J36: 45139 | K36: 45139 | L36: 45504 | M36: New Let | N36: AST | O36: 10200 | P36: 850 | S36: 10860 | T36: =S36/12 -> 905 | U36: 9780 | V36: NPB | X36: =(P36-T36)/T36 -> -0.060773481 | Z36: =(Y36-T36)/T36 -> -1 | AA36: N/A | AC36: =(AB36-T36)/T36 -> -1 | AD36: N/A | AE36: Keep on hold re sale | AF36: Cleared | AG36: 559.72 | AH36: 2 | AI36: 1 | AJ36: 2 Bedroom, FF, Modernised & Furnished 2018 | AK36: Lacey | AL36: 45504
A37: ntq | B37: 45512 | C37: PRS-Regions | D37: North Star Jesmond | E37: Sam Robson | F37: 16, Jesmond Place, Newcastle upon Tyne, NE2 | G37: Grace Fryer | H37: N/A | I37: Current | J37: 45147 | K37: 45147 | L37: 45512 | M37: New Let | N37: AST | O37: 10200 | P37: 850 | S37: 10440 | T37: =S37/12 -> 870 | U37: 9840 | V37: NPB | X37: =(P37-T37)/T37 -> -0.022988506 | Z37: =(Y37-T37)/T37 -> -1 | AA37: N/A | AC37: =(AB37-T37)/T37 -> -1 | AD37: N/A | AE37: Keep on hold re sale | AF37: Cleared | AG37: 559.72 | AH37: 2 | AI37: 1 | AJ37: 2 Bedroom, SF, Modernised & Furnished 2017 | AK37: Lacey | AL37: 45512
A38: ntq | B38: 45476 | C38: PRS-Regions | D38: North Star Jesmond | E38: Sam Robson | F38: 19, Jesmond Place, Newcastle upon Tyne, NE2 | G38: Amy Bryce | H38: N/A | I38: Current | J38: 44746 | K38: 45111 | L38: 45476 | M38: Renewal | N38: AST | O38: 10200 | P38: 850 | S38: 10500 | T38: =S38/12 -> 875 | U38: 10020 | V38: NPB | X38: =(P38-T38)/T38 -> -0.028571429 | Z38: =(Y38-T38)/T38 -> -1 | AA38: N/A | AC38: =(AB38-T38)/T38 -> -1 | AD38: N/A | AE38: Keep on hold re sale | AF38: Cleared | AG38: 559.72 | AH38: 2 | AI38: 1 | AJ38: 2 Bedroom, TF, Modernised & Furnished 2017 | AK38: Lacey | AL38: 45476
A39: denied | B39: 45497 | C39: PRS-Regions | D39: North Star Sandown | E39: Sam Robson | F39: 55, Sandown, Whitley Bay, NE25 | G39: Dr Semande Ayihongbe | H39: N/A | I39: Current | J39: 43304 | K39: 45132 | L39: 45497 | M39: Renewal | N39: AST | O39: 7620 | P39: 635 | S39: 7200 | T39: =S39/12 -> 600 | U39: 6600 | V39: NPB | X39: =(P39-T39)/T39 -> 0.058333333 | Z39: =(Y39-T39)/T39 -> -1 | AA39: N/A | AC39: =(AB39-T39)/T39 -> -1 | AD39: N/A | AE39: Keep on hold re sale | AF39: Cleared | AG39: 495.14 | AH39: 1 | AI39: 1 | AJ39: 1 Bedroom, FF, Modernised 2018 | AK39: Lacey | AL39: 45497
A40: denied | B40: 45504 | C40: PRS-Regions | D40: North Star Sandown | E40: Sam Robson | F40: 51, Sandown, Whitley Bay, NE25 | G40: Mr Daniel Slater | H40: N/A | I40: Current | J40: 42462 | K40: 45139 | L40: 45504 | M40: Renewal | N40: AST | O40: 7980 | P40: 665 | S40: 7140 | T40: =S40/12 -> 595 | U40: 6900 | V40: NPB | X40: =(P40-T40)/T40 -> 0.11764706 | Z40: =(Y40-T40)/T40 -> -1 | AA40: N/A | AC40: =(AB40-T40)/T40 -> -1 | AD40: N/A | AE40: Keep on hold re sale | AF40: Arrears | AG40: 495.14 | AH40: 2 | AI40: 1 | AJ40: 2 Bedroom, GF, UnmodernisedModern Bathroom 2021 | AK40: Lacey | AL40: 45504
A41: denied | B41: 45507 | C41: PRS-Regions | D41: North Star Sandown | E41: Sam Robson | F41: 60, Sandown, Whitley Bay, NE25 | G41: Lee Matthewson | H41: N/A | I41: Current | J41: 45142 | K41: 45142 | L41: 45507 | M41: New Let | N41: AST | O41: 7620 | P41: 635 | S41: 7080 | T41: =S41/12 -> 590 | U41: 6660 | V41: NPB | X41: =(P41-T41)/T41 -> 0.076271186 | Z41: =(Y41-T41)/T41 -> -1 | AA41: N/A | AC41: =(AB41-T41)/T41 -> -1 | AD41: N/A | AE41: Keep on hold re sale | AF41: Cleared | AG41: 495.14 | AH41: 1 | AI41: 1 | AJ41: 1 Bedroom, FF, Modernised 2018 | AK41: Lacey | AL41: 45507
A42: denied | B42: 45524 | C42: PRS-Regions | D42: North Star Sandown | E42: Sam Robson | F42: 59, Sandown, Whitley Bay, NE25 | G42: Mr James McCallum and Kim McCallum | H42: N/A | I42: Current | J42: 44429 | K42: 45159 | L42: 45524 | M42: Renewal | N42: AST | O42: 7980 | P42: 665 | S42: 7800 | T42: =S42/12 -> 650 | U42: 7620 | V42: NPB | X42: =(P42-T42)/T42 -> 0.023076923 | Z42: =(Y42-T42)/T42 -> -1 | AA42: N/A | AC42: =(AB42-T42)/T42 -> -1 | AD42: N/A | AE42: Keep on hold re sale | AF42: Cleared | AG42: 495.14 | AH42: 2 | AI42: 1 | AJ42: 2 Bedroom, FF, Modernised 2018 | AK42: Lacey | AL42: 45524
A43: denied | B43: 45532 | C43: PRS-Regions | D43: North Star Sandown | E43: Sam Robson | F43: 63, Sandown, Whitley Bay, NE25 | G43: Maryana Kachynska | H43: N/A | I43: Current | J43: 44802 | K43: 45167 | L43: 45532 | M43: Renewal | N43: AST | O43: 7980 | P43: 665 | S43: 7800 | T43: =S43/12 -> 650 | U43: 7380 | V43: NPB | X43: =(P43-T43)/T43 -> 0.023076923 | Z43: =(Y43-T43)/T43 -> -1 | AA43: N/A | AC43: =(AB43-T43)/T43 -> -1 | AD43: N/A | AE43: Keep on hold re sale | AF43: Cleared | AG43: 495.14 | AH43: 2 | AI43: 1 | AJ43: 2 Bedroom, GF, Modernised 2021 | AK43: Lacey | AL43: 45532
A44: ntq | B44: 45483 | C44: PRS-Regions | D44: Oystercatcher Foundry | E44: Sam Robson | F44: 23 Foundry Court, Newcastle upon Tyne, NE6 | G44: Isabel Dobinson | H44: N/A | I44: Current | J44: 44754 | K44: 45118 | L44: 45483 | M44: Renewal | N44: AST | O44: 7620 | P44: 635 | S44: 8100 | T44: =S44/12 -> 675 | U44: 7620 | V44: NPB | X44: =(P44-T44)/T44 -> -0.059259259 | Z44: =(Y44-T44)/T44 -> -1 | AA44: N/A | AC44: =(AB44-T44)/T44 -> -1 | AD44: N/A | AE44: Keep on hold re sale | AF44: Cleared | AG44: 548.96 | AH44: 2 | AI44: 1 | AJ44: 2 Bedroom, TF, Modernised 2020, GCH 2019 | AK44: Lacey | AL44: 45483
... A46: ntq | B46: 45525 | C46: PRS-Regions | D46: Oystercatcher Foundry | E46: Sam Robson | F46: 13 Foundry Court, Newcastle upon Tyne, NE6 | G46: Julian Wyton | H46: N/A | I46: Current | J46: 44673 | K46: 45160 | L46: 45525 | M46: Renewal | N46: AST | O46: 6840 | P46: 570 | S46: 7560 | T46: =S46/12 -> 630 | U46: 7560 | V46: NPB | X46: =(P46-T46)/T46 -> -0.095238095 | Z46: =(Y46-T46)/T46 -> -1 | AA46: N/A | AC46: =(AB46-T46)/T46 -> -1 | AD46: N/A | AE46: Keep on hold re sale | AF46: Cleared | AG46: 409.03 | AH46: 1 | AI46: 1 | AJ46: 1 Bedroom, SF, Modernised 2017, GCH 2019 | AK46: Lacey | AL46: 45525
A47: denied | B47: 45474 | C47: PRS-Regions | D47: Resi Heysmoor | E47: Luke Pollard | F47: Flat 81, Heysmoor Heights, Liverpool, L8 | G47: Mateus Tchilimba | H47: No issues with the resident or property - we are looking to sell the property in April so best to check with AM if we are looking to renew | I47: Current | J47: 44744 | K47: 45109 | L47: 45474 | M47: Renewal | N47: AST | O47: 8940 | P47: 745 | S47: 9180 | T47: =S47/12 -> 765 | U47: 8520 | V47: 800 | W47: =(V47-T47)/T47 -> 0.045751634 | X47: =(P47-T47)/T47 -> -0.026143791 | Z47: =(Y47-T47)/T47 -> -1 | AA47: N/A | AC47: =(AB47-T47)/T47 -> -1 | AD47: N/A | AE47: Keep on hold re sale | AF47: Cleared | AG47: 613.54 | AH47: 2 | AI47: 1 | AJ47: 2 Bedroom-13FFurnished | AK47: Lacey | AL47: 45474
A48: denied | B48: 45478 | C48: PRS-Regions | D48: Resi Heysmoor | E48: Luke Pollard | F48: Flat 85, Heysmoor Heights, Liverpool, L8 | G48: Milena Wlodarska | H48: No issues with the resident or property - we are looking to sell the property in April so best to check with AM if we are looking to renew | I48: Current | J48: 45113 | K48: 45113 | L48: 45478 | M48: New Let | N48: AST | O48: 8100 | P48: 675 | S48: 8040 | T48: =S48/12 -> 670 | U48: 7920 | V48: 695 | W48: =(V48-T48)/T48 -> 0.037313433 | X48: =(P48-T48)/T48 -> 0.0074626866 | Z48: =(Y48-T48)/T48 -> -1 | AA48: N/A | AC48: =(AB48-T48)/T48 -> -1 | AD48: N/A | AE48: Keep on hold re sale | AF48: Cleared | AG48: 516.67 | AH48: 1 | AI48: 1 | AJ48: 1 Bedroom-14FUnfurnished | AK48: Lacey | AL48: 45478
A49: denied | B49: 45483 | C49: PRS-Regions | D49: Resi Heysmoor | E49: Luke Pollard | F49: Flat 70, Heysmoor Heights, Liverpool, L8 | G49: Eimear Keatings | H49: No issues with the resident or property - we are looking to sell the property in April so best to check with AM if we are looking to renew | I49: Current | J49: 45118 | K49: 45118 | L49: 45483 | M49: New Let | N49: AST | O49: 8100 | P49: 675 | S49: 7920 | T49: =S49/12 -> 660 | U49: 7680 | V49: 685 | W49: =(V49-T49)/T49 -> 0.037878788 | X49: =(P49-T49)/T49 -> 0.022727273 | Z49: =(Y49-T49)/T49 -> -1 | AA49: N/A | AC49: =(AB49-T49)/T49 -> -1 | AD49: N/A | AE49: Keep on hold re sale | AF49: Cleared | AG49: 516.67 | AH49: 1 | AI49: 1 | AJ49: 1 Bedroom-12FFurnished | AK49: Lacey | AL49: 45483
A50: denied | B50: 45490 | C50: PRS-Regions | D50: Resi Heysmoor | E50: Luke Pollard | F50: Flat 66, Heysmoor Heights, Liverpool, L8 | G50: Betina Sajimon & Joel Joseph | H50: No issues with the resident or property - we are looking to sell the property in April so best to check with AM if we are looking to renew | I50: Current | J50: 44760 | K50: 45125 | L50: 45490 | M50: Renewal | N50: AST | O50: 8940 | P50: 745 | S50: 9060 | T50: =S50/12 -> 755 | U50: 8400 | V50: 790 | W50: =(V50-T50)/T50 -> 0.046357616 | X50: =(P50-T50)/T50 -> -0.013245033 | Z50: =(Y50-T50)/T50 -> -1 | AA50: N/A | AC50: =(AB50-T50)/T50 -> -1 | AD50: N/A | AE50: Keep on hold re sale | AF50: Cleared | AG50: 635.07 | AH50: 2 | AI50: 1 | AJ50: 2 Bedroom-11FFurnished | AK50: Lacey | AL50: 45490
A51: denied | B51: 45504 | C51: PRS-Regions | D51: Resi Heysmoor | E51: Luke Pollard | F51: Flat 52, Heysmoor Heights, Liverpool, L8 | G51: Chanel Kalemba | H51: No issues with the resident or property - we are looking to sell the property in April so best to check with AM if we are looking to renew | I51: Current | J51: 44774 | K51: 45139 | L51: 45504 | M51: Renewal | N51: AST | O51: 8100 | P51: 675 | S51: 7740 | T51: =S51/12 -> 645 | U51: 7200 | V51: 670 | W51: =(V51-T51)/T51 -> 0.03875969 | X51: =(P51-T51)/T51 -> 0.046511628 | Z51: =(Y51-T51)/T51 -> -1 | AA51: N/A | AC51: =(AB51-T51)/T51 -> -1 | AD51: N/A | AE51: Keep on hold re sale | AF51: Cleared | AG51: 516.67 | AH51: 1 | AI51: 1 | AJ51: 1 Bedroom- 9th FFurnished | AK51: Lacey | AL51: 45504
A52: denied | B52: 45510 | C52: PRS-Regions | D52: Resi Heysmoor | E52: Luke Pollard | F52: Flat 74, Heysmoor Heights, Liverpool, L8 | G52: Louis Hopkins & Hannah Fowler | H52: No issues with the resident or property - we are looking to sell the property in April so best to check with AM if we are looking to renew | I52: Current | J52: 45145 | K52: 45145 | L52: 45510 | M52: New Let | N52: AST | O52: 8940 | P52: 745 | S52: 9120 | T52: =S52/12 -> 760 | U52: 9120 | V52: 980 | W52: =(V52-T52)/T52 -> 0.28947368 | X52: =(P52-T52)/T52 -> -0.019736842 | Z52: =(Y52-T52)/T52 -> -1 | AA52: N/A | AC52: =(AB52-T52)/T52 -> -1 | AD52: N/A | AE52: Keep on hold re sale | AF52: Cleared | AG52: 613.54 | AH52: 2 | AI52: 1 | AJ52: 2 Bedroom-12FFurnished | AK52: Lacey | AL52: 45510
A53: denied | B53: 45513 | C53: PRS-Regions | D53: Resi Heysmoor | E53: Luke Pollard | F53: Flat 28, Heysmoor Heights, Liverpool, L8 | G53: Tiffany Rogan & Matthew Quarrell | H53: No issues with the resident or property - we are looking to sell the property in April so best to check with AM if we are looking to renew | I53: Current | J53: 45148 | K53: 45148 | L53: 45513 | M53: New Let | N53: AST | O53: 8100 | P53: 675 | S53: 7500 | T53: =S53/12 -> 625 | U53: 7416 | W53: =(V53-T53)/T53 -> -1 | X53: =(P53-T53)/T53 -> 0.08 | Z53: =(Y53-T53)/T53 -> -1 | AA53: N/A | AC53: =(AB53-T53)/T53 -> -1 | AD53: N/A | AE53: Keep on hold re sale | AF53: Cleared | AG53: 516.67 | AH53: 1 | AI53: 1 | AJ53: 1 bedroom- 5th floorFurnished | AK53: Lacey | AL53: 45513
A54: denied | B54: 45517 | C54: PRS-Regions | D54: Resi Heysmoor | E54: Luke Pollard | F54: Flat 54, Heysmoor Heights, Liverpool, L8 | G54: Martyn Lyness | H54: No issues with the resident or property - we are looking to sell the property in April so best to check with AM if we are looking to renew | I54: Current | J54: 45152 | K54: 45152 | L54: 45517 | M54: New Let | N54: AST | O54: 8940 | P54: 745 | S54: 8940 | T54: =S54/12 -> 745 | U54: 8520 | W54: =(V54-T54)/T54 -> -1 | X54: =(P54-T54)/T54 -> 0 | Z54: =(Y54-T54)/T54 -> -1 | AA54: N/A | AC54: =(AB54-T54)/T54 -> -1 | AD54: N/A | AE54: Keep on hold re sale | AF54: Arrears | AG54: 635.07 | AH54: 2 | AI54: 1 | AJ54: 2 Bedroom- 9FUnfurnished | AK54: Lacey | AL54: 45517
A55: denied | B55: 45519 | C55: PRS-Regions | D55: Resi Heysmoor | E55: Luke Pollard | F55: Flat 38, Heysmoor Heights, Liverpool, L8 | G55: Miss Sioned Williams | H55: No issues with the resident or property - we are looking to sell the property in April so best to check with AM if we are looking to renew | I55: Current | J55: 43600 | K55: 45154 | L55: 45519 | M55: Renewal | N55: AST | O55: 8940 | P55: 745 | S55: 8760 | T55: =S55/12 -> 730 | U55: 8100 | W55: =(V55-T55)/T55 -> -1 | X55: =(P55-T55)/T55 -> 0.020547945 | Z55: =(Y55-T55)/T55 -> -1 | AA55: N/A | AC55: =(AB55-T55)/T55 -> -1 | AD55: N/A | AE55: Keep on hold re sale | AF55: Cleared | AG55: 613.54 | AH55: 2 | AI55: 1 | AJ55: 2 Bedroom-6th floorFurnished | AK55: Lacey | AL55: 45519
A56: denied | B56: 45527 | C56: PRS-Regions | D56: Resi Heysmoor | E56: Luke Pollard | F56: Flat 73, Heysmoor Heights, Liverpool, L8 | G56: Ceryce Collie | H56: No issues with the resident or property - we are looking to sell the property in April so best to check with AM if we are looking to renew | I56: Current | J56: 45162 | K56: 45162 | L56: 45527 | M56: New Let | N56: AST | O56: 8100 | P56: 675 | S56: 7980 | T56: =S56/12 -> 665 | U56: 7620 | W56: =(V56-T56)/T56 -> -1 | X56: =(P56-T56)/T56 -> 0.015037594 | Z56: =(Y56-T56)/T56 -> -1 | AA56: N/A | AC56: =(AB56-T56)/T56 -> -1 | AD56: N/A | AE56: Keep on hold re sale | AF56: Cleared | AG56: 516.67 | AH56: 1 | AI56: 1 | AJ56: 1 Bedroom-12FFurnished | AK56: Lacey | AL56: 45527
A57: denied | B57: 45528 | C57: PRS-Regions | D57: Resi Heysmoor | E57: Luke Pollard | F57: Flat 57, Heysmoor Heights, Liverpool, L8 | G57: Jack McAlister & Conor Kernohan | H57: No issues with the resident or property - we are looking to sell the property in April so best to check with AM if we are looking to renew | I57: Current | J57: 44433 | K57: 45163 | L57: 45528 | M57: Renewal | N57: AST | O57: 8940 | P57: 745 | S57: 9000 | T57: =S57/12 -> 750 | U57: 8400 | W57: =(V57-T57)/T57 -> -1 | X57: =(P57-T57)/T57 -> -0.0066666667 | Z57: =(Y57-T57)/T57 -> -1 | AA57: N/A | AC57: =(AB57-T57)/T57 -> -1 | AD57: N/A | AE57: Keep on hold re sale | AF57: Cleared | AG57: 613.54 | AH57: 2 | AI57: 1 | AJ57: 2 Bedroom-9FFurnished | AK57: Lacey | AL57: 45528

Sheet Neg Requests
A1: Date Added | B1: AM | C1: Neg | D1: Estate | E1: Address | F1: Beds | G1: ERV | H1: Current Monthly | I1: Offered Price | J1: Offered/ Current % | K1: Tenants Counter Offer | L1: Counter Offer % | M1: Renewal Suggested Price | N1: Suggested/ Current % | O1: Suggested/ ERV % | P1: Reasoning | Q1: AM Decision | R1: AM Notes | S1: Re-Offered | T1: Outcome
A2: 13/05/2024 | B2: Daisy | C2: Jem | D2: Ability Plaza | E2: Flat 75 Ability Plaza | F2: 1 | G2: 2336 | H2: 2085 | I2: 2350 | J2: =SUM(I2-H2)/H2 -> 0.12709832 | K2: 2200 | L2: =SUM(K2-H2)/H2 -> 0.055155875 | M2: 2295 | N2: =SUM(M2-H2)/H2 -> 0.10071942 | O2: =SUM(M2-G2)/G2 -> -0.01755137 | P2: Tenant has been in 4 years | Q2: no | R2: Needs to be in line with ERV at least | S2: Re-Offered
A3: 13/05/2024 | B3: Vicki | C3: Jem | D3: Brook Place | E3: 316 Brook Place | F3: 2 | G3: 1260 | H3: 1210 | I3: 1265 | J3: =SUM(I3-H3)/H3 -> 0.045454545 | K3: 1210 | L3: =SUM(K3-H3)/H3 -> 0 | M3: 1240 | N3: =SUM(M3-H3)/H3 -> 0.024793388 | O3: =SUM(M3-G3)/G3 -> -0.015873016 | P3: 8 x 2 beds due on market | Q3: £1235 | R3: Come back to me if still an issue - do not want a avoid | S3: Re-Offered
A4: 14/05/2024 | B4: Vicki | C4: Lacey | D4: Pin Yard | E4: 402 Pin Yard | F4: 1 | G4: 980 | H4: 980 | I4: 1045 | J4: =SUM(I4-H4)/H4 -> 0.066326531 | K4: 1000 | L4: =SUM(K4-H4)/H4 -> 0.020408163 | M4: 1010 | N4: =SUM(M4-H4)/H4 -> 0.030612245 | O4: =SUM(M4-G4)/G4 -> 0.030612245 | P4: June Renewal Think we can try for a bit more but aware of issues here & dont want to lose anyone- can we accept counter or push for more? he is requesting to sign a 36 month contract too | Q4: £1000 | R4: Try for more but would accept counter offer | S4: Re-Offered | T4: Accepted
A5: 14/05/2025 | B5: Vicki | C5: Lacey | D5: Pin Yard | E5: 801 Pin Yard | F5: 1 | G5: 1090 | H5: 1035 | I5: 1100 | J5: =SUM(I5-H5)/H5 -> 0.062801932 | K5: 1060 | L5: =SUM(K5-H5)/H5 -> 0.024154589 | M5: 1070 | N5: =SUM(M5-H5)/H5 -> 0.033816425 | O5: =SUM(M5-G5)/G5 -> -0.018348624 | P5: TT is aware of market & what is available, as we do not want void suggest a smaller increase on his or accept counter | Q5: £1060 | R5: Accept counter offer | S5: Re-Offered | T5: Accepted
A6: 14/05/2026 | B6: Vicki | C6: Lacey | D6: KDM | E6: 116 Kings Dock Mill | F6: 1 | G6: 745 | H6: 710 | I6: 770 | J6: =SUM(I6-H6)/H6 -> 0.084507042 | K6: 0 | L6: =SUM(K6-H6)/H6 -> -1 | M6: 770 | N6: =SUM(M6-H6)/H6 -> 0.084507042 | O6: =SUM(M6-G6)/G6 -> 0.033557047 | P6: TT is travelling around Christmas so wants a 6 month break clause to end in January- can we grant this? Fear is she may not then sign a renewal with increase and it will roll | Q6: Yes | R6: Yes - give break clause | S6: Re-Offered | T6: Accepted
A7: 14/05/2027 | B7: Sarah | C7: Lacey | D7: Barnum | E7: 835 The Barnum | F7: 1 | G7: 1210 | H7: 1210 | I7: 1215 | J7: =SUM(I7-H7)/H7 -> 0.0041322314 | K7: 1215 | L7: =SUM(K7-H7)/H7 -> 0.0041322314 | M7: 1215 | N7: =SUM(M7-H7)/H7 -> 0.0041322314 | O7: =SUM(M7-G7)/G7 -> 0.0041322314 | P7: TT pays RIA & wants a 6 month contract, cannot pass for monthly cannot provide GT, wants to stay beyond the 6 months happy to pay the rent but cannot pay anymore than 6 months at a time. Suggest offering x2 6 months RIA at this time but would mean inputting a 6 month break clause however still not sure he can pay the 6 months in month 4.
A8: 15/05/52024 | B8: Vicki | C8: Lacey | D8: Pin Yard | E8: 620 Pin Yard | F8: 2 | G8: 1410 | H8: 1360 | I8: 1430 | J8: =SUM(I8-H8)/H8 -> 0.051470588 | K8: 1380 | L8: =SUM(K8-H8)/H8 -> 0.014705882 | M8: 1400 | N8: =SUM(M8-H8)/H8 -> 0.029411765 | O8: =SUM(M8-G8)/G8 -> -0.0070921986 | P8: high voids in Pin suggest either accepting or try for a little more uplift | Q8: £1400 | R8: Try for £1,400 but would accept counter offer rather than lose them | S8: Re-Offered | T8: Accepted
A9: 15/05/52025 | B9: Vicki | C9: Lacey | D9: The Rock | E9: 54 15 SJG | F9: 1 | G9: 805 | H9: 785 | I9: 845 | J9: =SUM(I9-H9)/H9 -> 0.076433121 | K9: 800 | L9: =SUM(K9-H9)/H9 -> 0.01910828 | M9: 835 | N9: =SUM(M9-H9)/H9 -> 0.063694268 | O9: =SUM(M9-G9)/G9 -> 0.037267081 | P9: Small decrease to try to keep tenants | Q9: No | R9: No neg | S9: Re-Offered
A10: 15/05/52026 | B10: Vicki | C10: Lacey | D10: Pin Yard | E10: 610 Pin Yard | F10: 1 | G10: 1060 | H10: 1005 | I10: 1065 | J10: =SUM(I10-H10)/H10 -> 0.059701493 | K10: 1000 | L10: =SUM(K10-H10)/H10 -> -0.0049751244 | M10: 1045 | N10: =SUM(M10-H10)/H10 -> 0.039800995 | O10: =SUM(M10-G10)/G10 -> -0.014150943 | P10: Whats the best price here to try to keep? | Q10: £1025 | R10: £1025 is lowest | S10: Re-Offered | T10: Accepted
A11: 15/05/52027 | B11: Vicki | C11: Lacey | D11: Clippers | E11: 804 Tayleur | F11: 2 | G11: 1410 | H11: 1360 | I11: 1440 | J11: =SUM(I11-H11)/H11 -> 0.058823529 | K11: 1410 | L11: =SUM(K11-H11)/H11 -> 0.036764706 | M11: 1425 | N11: =SUM(M11-H11)/H11 -> 0.047794118 | O11: =SUM(M11-G11)/G11 -> 0.010638298 | P11: a few 2 beds on the market dont think we want one of the more expensive ones on the market as struggling to shift the less expensive 2 beds, suggest a smaller increase | Q11: Yes | R11: Accept counter offer | S11: Re-Offered | T11: Accepted
A12: 17/05/2024 | B12: Vicki | C12: Lacey | D12: Clippers | E12: 1010 Tayleur | F12: 2 | G12: 1385 | H12: 1300 | I12: 1415 | J12: =SUM(I12-H12)/H12 -> 0.088461538 | K12: 1350 | L12: =SUM(K12-H12)/H12 -> 0.038461538 | M12: 1385 | N12: =SUM(M12-H12)/H12 -> 0.065384615 | O12: =SUM(M12-G12)/G12 -> 0 | P12: to try to keep them | Q12: £1365 | R12: Try for £1385 but would accept £1365 | S12: Re-Offered | T12: Accepted
A13: 17/05/2024 | B13: Vicki | C13: Lacey | D13: Filaments | E13: 1207 Halogen | F13: 2 | G13: 1555 | H13: 1490 | I13: 1570 | J13: =SUM(I13-H13)/H13 -> 0.053691275 | K13: 1500 | L13: =SUM(K13-H13)/H13 -> 0.0067114094 | M13: 1540 | N13: =SUM(M13-H13)/H13 -> 0.033557047 | O13: =SUM(M13-G13)/G13 -> -0.0096463023 | P13: slight reduction to try to keep them | Q13: £1540 | R13: No lower than £1540 | S13: Re-Offered | T13: Accepted
A14: 17/05/2024 | B14: Vicki | C14: Lacey | D14: Filaments | E14: 611 Neon | F14: 2 | G14: 1395 | H14: 1335 | I14: 1485 | J14: =SUM(I14-H14)/H14 -> 0.11235955 | K14: 1356 | L14: =SUM(K14-H14)/H14 -> 0.015730337 | M14: 1420 | N14: =SUM(M14-H14)/H14 -> 0.063670412 | O14: =SUM(M14-G14)/G14 -> 0.017921147 | P14: Tenants are asking for less than the minimum which is £1430 here if they sign a longer contract- can we go any lower than the minimum £1430? | Q14: Yes | R14: £1420 for longer contract | S14: Re-Offered | T14: Accepted
A15: 27/07/2024 | B15: Vicki | C15: Sophie | D15: Enigma | E15: 817 Enigma Squ | F15: 1 | G15: 1309 | H15: 1320 | I15: 1470 | J15: =SUM(I15-H15)/H15 -> 0.11363636 | K15: =H15/100*3+H15 -> 1359.6 | L15: =SUM(K15-H15)/H15 -> 0.03 | M15: suggest to come doen to 6% - tenants interested in 36 months term incl 14 months break clause. | N15: =(1360-H15)/H15 -> 0.03030303 | O15: =(1360-G15)/G15 -> 0.038961039 | P15: does not want to pay more than 3% - cheaper apts in and around the building. | Q15: Yes | R15: Try for 4% uplift but woudl accept 3% uplift | S15: yes | T15: vacting
A16: 17/05/2024 | B16: Harriet | C16: Jemma | D16: Millet Place | E16: 97 Adlay Apartments | F16: 2 | G16: n/a | H16: 2150 | I16: 2295 | J16: =SUM(I16-H16)/H16 -> 0.06744186 | K16: 2250 | L16: =SUM(K16-H16)/H16 -> 0.046511628 | M16: 2265 | N16: =SUM(M16-H16)/H16 -> 0.053488372 | O16: =SUM(M16-G16)/G16 -> #VALUE! | Q16: Accept £2265 | S16: Re-Offered
A17: 17/05/2024 | B17: Vicki | C17: Lacey | D17: Pin Yard | E17: 516 Pin Yard | F17: 1 | G17: 1040 | H17: 980 | I17: 1040 | J17: =SUM(I17-H17)/H17 -> 0.06122449 | K17: 1000 | L17: =SUM(K17-H17)/H17 -> 0.020408163 | M17: 1020 | N17: =SUM(M17-H17)/H17 -> 0.040816327 | O17: =SUM(M17-G17)/G17 -> -0.019230769 | P17: tenants struggling with rent whats best price here? | Q17: Yes | R17: £1020 but come back tome if still an issue as do not want a void | S17: Re-Offered
A18: 17/05/2025 | B18: Vicki | C18: Lacey | D18: Kings Dock Mill | E18: 43 Kings Dock Mill | F18: 1 | G18: 745 | H18: 700 | I18: 765 | J18: =SUM(I18-H18)/H18 -> 0.092857143 | K18: 740 | L18: =SUM(K18-H18)/H18 -> 0.057142857 | M18: 750 | N18: =SUM(M18-H18)/H18 -> 0.071428571 | O18: =SUM(M18-G18)/G18 -> 0.0067114094 | P18: suggest slightly more than ERV to keep | Q18: No | R18: No neg | S18: Re-Offered | T18: Accepted
A19: 17/05/2026 | B19: Vicki | C19: Lacey | D19: Pin Yard | E19: 409 Pin Yard | F19: 1 | G19: 1075 | H19: 1015 | I19: 1075 | J19: =SUM(I19-H19)/H19 -> 0.0591133 | K19: 1045 | L19: =SUM(K19-H19)/H19 -> 0.02955665 | M19: 1050 | N19: =SUM(M19-H19)/H19 -> 0.034482759 | O19: =SUM(M19-G19)/G19 -> -0.023255814 | P19: suggest accepting or offer slightly higher the retain | Q19: £1050 | R19: Try for £1050 but I would accept resident counter offer | S19: Re-Offered
A20: 17/05/2024 | B20: Daisy | C20: Jemma | D20: Great Sutton | E20: Apartment 7, 46-47 | F20: 3 | G20: N/A | H20: N/A | I20: N/A | J20: =SUM(I20-H20)/H20 -> #VALUE! | K20: N/A | L20: =SUM(K20-H20)/H20 -> #VALUE! | M20: tenant happy with price | N20: =SUM(M20-H20)/H20 -> #VALUE! | O20: =SUM(M20-G20)/G20 -> #VALUE! | P20: Tenant wants a 2 month break clause because her mum, who lives in Australia requires 24 hour care. Her dad currently provides this, but should something happen where he can't look after her mum, they would need to move back home. They previously had a 2 month bc in their current contract. | Q20: Yes | R20: That's fine, please renew | S20: Re-Offered | T20: Accepted
A21: 21/05/2024 | B21: Vicki | C21: Lacey | D21: Filaments | E21: 407 Neon House | F21: 3 | G21: 2050 | H21: 1935 | I21: 2100 | J21: =SUM(I21-H21)/H21 -> 0.085271318 | K21: 2000 | L21: =SUM(K21-H21)/H21 -> 0.033591731 | M21: 2060 | N21: =SUM(M21-H21)/H21 -> 0.064599483 | O21: =SUM(M21-G21)/G21 -> 0.0048780488 | P21: Whats best price? | Q21: 2050 | R21: Let me know if still an issue. Do not want void | S21: Re-Offered | T21: Accepted
A22: 21/05/2024 | B22: Vicki | C22: Lacey | D22: Pin Yard | E22: 1106 Pin Yard | F22: 1 | J22: =SUM(I22-H22)/H22 -> #DIV/0! | L22: =SUM(K22-H22)/H22 -> #DIV/0! | N22: =SUM(M22-H22)/H22 -> #DIV/0! | O22: =SUM(M22-G22)/G22 -> #DIV/0! | P22: no mention of rent reduction- wants a 6 month break clause as moving in with boyfriend after this, can we accept | Q22: Yes | R22: Yes - give the break clause | S22: Re-Offered | T22: Accepted
A23: 21/05/2024 | B23: Vicki | C23: Lacey | D23: Filaments | E23: 307 Neon | F23: 3 | G23: 2050 | H23: 1930 | I23: 2090 | J23: =SUM(I23-H23)/H23 -> 0.082901554 | K23: 2030 | L23: =SUM(K23-H23)/H23 -> 0.051813472 | M23: 2060 | N23: =SUM(M23-H23)/H23 -> 0.067357513 | O23: =SUM(M23-G23)/G23 -> 0.0048780488 | P23: to try to keep them as 3 beds are tough to let currently | Q23: 2050 | R23: Let me know if still an issue. Do not want void | S23: Re-Offered | T23: Accepted
A24: 21/05/2025 | B24: Vicki | C24: Lacey | D24: Filaments | E24: 409 Neon | F24: 2 | G24: 1455 | H24: 1395 | I24: 1485 | J24: =SUM(I24-H24)/H24 -> 0.064516129 | K24: 1445 | L24: =SUM(K24-H24)/H24 -> 0.035842294 | M24: 1455 | N24: =SUM(M24-H24)/H24 -> 0.043010753 | O24: =SUM(M24-G24)/G24 -> 0 | P24: not happy at all been here for 3 years- whats best price? | Q24: 1455 | R24: No more neg after £1,455 | S24: Re-Offered | T24: Accepted
A25: 22/05/2024 | B25: Vicki | C25: Sophie | D25: Gilders | E25: 15, Gilders Yard, | F25: 1 | G25: 1090 | H25: 1070 | I25: 115 | J25: =SUM(I25-H25)/H25 -> -0.89252336 | K25: 1080 | L25: =SUM(K25-H25)/H25 -> 0.0093457944 | M25: 1095 | N25: =SUM(M25-H25)/H25 -> 0.023364486 | O25: =SUM(M25-G25)/G25 -> 0.004587156 | P25: 1080 a month this would be more on the increase I would be able to budget and manage within. Also, I would still be able to pay this in two 6-month installments | Q25: No | R25: No neg | S25: yes
A26: 23/5/24 | B26: Vicki | C26: Jemma | D26: Brook Place | E26: 114 Brook | F26: 2 | G26: 1255 | H26: 1205 | I26: 1260 | J26: =SUM(I26-H26)/H26 -> 0.045643154 | K26: 1235 | L26: =SUM(K26-H26)/H26 -> 0.024896266 | N26: =SUM(M26-H26)/H26 -> -1 | O26: =SUM(M26-G26)/G26 -> -1 | Q26: 1240 | R26: No more neg after £1,240 | S26: Re-Offered
A27: 20/05/2024 | B27: Harriet | C27: Jemma | D27: abbevville | E27: Apt 402, Abbeville Apts, | F27: 3 | G27: 2138 | H27: 1975 | I27: 2150 | J27: =SUM(I27-H27)/H27 -> 0.088607595 | K27: 2000 | L27: =SUM(K27-H27)/H27 -> 0.012658228 | M27: 2075 | N27: =SUM(M27-H27)/H27 -> 0.050632911 | O27: =SUM(M27-G27)/G27 -> -0.029466791 | P27: did not budget for larger increase | Q27: £2,100 minimum | S27: Re-Offered
A28: 20/07/2024 | B28: vicki | C28: sophie | D28: Enigma | E28: 810 Enigma Sq | F28: 1 | G28: 1426 | H28: 1295 | I28: 1470 | J28: =SUM(I28-H28)/H28 -> 0.13513514 | K28: 1350 | L28: =SUM(K28-H28)/H28 -> 0.042471042 | M28: 1400 | N28: =SUM(M28-H28)/H28 -> 0.081081081 | O28: =SUM(M28-G28)/G28 -> -0.018232819 | P28: This is way above any cost of living increase and totally unacceptable. | Q28: 1430 | R28: No more neg after £1,430 | S28: yes
A29: 20/07/2025 | B29: vicki | C29: sophie | D29: Enigma | E29: 729 Enigma | F29: 1 | G29: 1426 | H29: 1319 | I29: 1460 | J29: =SUM(I29-H29)/H29 -> 0.10689917 | K29: 1380 | L29: =SUM(K29-H29)/H29 -> 0.046247157 | M29: 1400 | N29: =SUM(M29-H29)/H29 -> 0.061410159 | O29: =SUM(M29-G29)/G29 -> -0.018232819 | P29: comparable enigma units listed at 1370-1380 | Q29: 1430 | R29: No more neg after £1,430 | S29: yes
A30: 24/05/2024 | B30: Vicki | C30: Lacey | D30: Filaments | E30: 407 Halogen | F30: 2 | J30: =SUM(I30-H30)/H30 -> #DIV/0! | L30: =SUM(K30-H30)/H30 -> #DIV/0! | N30: =SUM(M30-H30)/H30 -> #DIV/0! | O30: =SUM(M30-G30)/G30 -> #DIV/0! | P30: Mum is very ill in Australia and if she worsens she will need to go back. She is having heart surgery in a few months time so it would be around October/November time she may want to vacate Have offered the 2 month any time break but cannot leave in Nov-March but in this case can we shorten this to just Dec & Jan? | Q30: Yes | R30: Yes as per your comments | S30: Re-Offered | T30: Accepted
A31: 24/05/2024 | B31: Vicki | C31: Lacey | D31: Headline | E31: 1401 The Headline | F31: 2 | J31: =SUM(I31-H31)/H31 -> #DIV/0! | L31: =SUM(K31-H31)/H31 -> #DIV/0! | N31: =SUM(M31-H31)/H31 -> #DIV/0! | O31: =SUM(M31-G31)/G31 -> #DIV/0! | P31: Wants a 6 month contract to leave in Jan as will definitely be vacating can we accept? | Q31: No | R31: Would rather have void now than January | S31: Re-Offered | T31: Accepted
A32: 27/07/2024 | B32: Vicki | C32: Sophie | D32: Enigma | E32: 706 Enigma S | F32: 1 | G32: 1404 | H32: 1300 | I32: 1470 | J32: =SUM(I32-H32)/H32 -> 0.13076923 | K32: 1405 | L32: =SUM(K32-H32)/H32 -> 0.080769231 | M32: offer new price book rent first (1420) with the option to reduce to 8% | N32: =SUM(M32-H32)/H32 -> #VALUE! | O32: =SUM(M32-G32)/G32 -> #VALUE! | P32: budgetted for the 8% increase stated in the agreement which applied to the longer term contracts - informed that will be the renewal price | Q32: 1410 | R32: No more neg after £1,410 | S32: yes | T32: Accepted
A33: 24/05/2024 | B33: Harriet | C33: Jemma | D33: Argo | E33: 97 Argo | F33: 1 | G33: 1975 | H33: 1850 | I33: 2000 | J33: =SUM(I33-H33)/H33 -> 0.081081081 | K33: 1900 | L33: =SUM(K33-H33)/H33 -> 0.027027027 | M33: 1975 | N33: =SUM(M33-H33)/H33 -> 0.067567568 | O33: =SUM(M33-G33)/G33 -> 0 | P33: TTs cannot afford and have been looking elsewhere | Q33: accept - £1,975 min | S33: Re-Offered
A34: 24/05/2024 | B34: Vicki | C34: Lacey | D34: Headline | E34: 213 The Headline | F34: 1 | G34: 1120 | H34: 1080 | I34: 1130 | J34: =SUM(I34-H34)/H34 -> 0.046296296 | K34: 1080 | L34: =SUM(K34-H34)/H34 -> 0 | M34: 1090 | N34: =SUM(M34-H34)/H34 -> 0.0092592593 | O34: =SUM(M34-G34)/G34 -> -0.026785714 | P34: 104 is on the market for £1065 and tenant is aware of this, whats our best price? new PB is £1085 | Q34: 1120 | S34: Re-Offered | T34: Accepted
A35: 24/05/2024 | B35: Vicki | C35: Lacey | D35: KDM | E35: 162 KDM | F35: 2 | G35: 940 | H35: 930 | I35: 1050 | J35: =SUM(I35-H35)/H35 -> 0.12903226 | K35: 930 | L35: =SUM(K35-H35)/H35 -> 0 | M35: 995 | N35: =SUM(M35-H35)/H35 -> 0.069892473 | O35: =SUM(M35-G35)/G35 -> 0.058510638 | P35: Whats best price? most 2 beds on the market are B2R in this area at similar price | Q35: 950 | S35: Re-Offered | T35: Accepted
A36: 28/05/2024 | B36: Vicki | C36: Lacey | D36: KDM | E36: 130 KDM | F36: 1 | G36: 745 | H36: 800 | I36: 870 | J36: =SUM(I36-H36)/H36 -> 0.0875 | K36: 800 | L36: =SUM(K36-H36)/H36 -> 0 | M36: 850 | N36: =SUM(M36-H36)/H36 -> 0.0625 | O36: =SUM(M36-G36)/G36 -> 0.1409396 | P36: whats best price? | Q36: 825 | S36: Re-Offered | T36: Accepted
A37: 28/05/2024 | B37: Vicki | C37: Lacey | D37: KDM | E37: 108 KDM | F37: 2 | G37: 940 | H37: 960 | I37: 1005 | J37: =SUM(I37-H37)/H37 -> 0.046875 | K37: 960 | L37: =SUM(K37-H37)/H37 -> 0 | M37: 990 | N37: =SUM(M37-H37)/H37 -> 0.03125 | O37: =SUM(M37-G37)/G37 -> 0.053191489 | P37: They have served notice but want to see what best price is to try to keep | Q37: 975 | S37: Re-Offered | T37: Vacating
A38: 14/07/2024 | B38: Vicki | C38: Sophie | D38: H&G | E38: FLAT 23, Hawkins L | F38: 2 | G38: 1924 | H38: 1770 | I38: 1950 | J38: =SUM(I38-H38)/H38 -> 0.10169492 | L38: =SUM(K38-H38)/H38 -> -1 | M38: 1900 | N38: =SUM(M38-H38)/H38 -> 0.073446328 | O38: =SUM(M38-G38)/G38 -> -0.012474012 | P38: We're currently at £1925- are we able to reduce to £1900 (1.2% below ERV) to try and tie? | Q38: 1925 | R38: Offer longer TA | S38: yes
A39: 31/07/2024 | B39: Vicki | C39: Sophie | D39: Enigma | E39: 334 Enigm | F39: 1 | G39: 1426 | H39: 1270 | I39: 1430 | J39: =SUM(I39-H39)/H39 -> 0.12598425 | K39: 1350 | L39: =SUM(K39-H39)/H39 -> 0.062992126 | M39: 1370 | N39: =SUM(M39-H39)/H39 -> 0.078740157 | O39: =SUM(M39-G39)/G39 -> -0.039270687 | P39: I would have loved to renew my rent with enigma bcos I love the service you provide but the prize increase is ridiculous for 1 bedroom flat excluding all bills, the prize increase was too much I must say. + on the phone seen comparable unit not far away for 100 less | Q39: No neg | R39: No neg - sorry | S39: yes | T39: Vacating
A40: 29/05/2024 | B40: Daisy | C40: Jemma | D40: Eagle House | E40: Flat 9 Eagle House | F40: 1 | G40: 2240 | H40: 2250 | I40: 2375 | J40: =SUM(I40-H40)/H40 -> 0.055555556 | K40: 2250 | L40: =SUM(K40-H40)/H40 -> 0 | M40: 2275 | N40: =SUM(M40-H40)/H40 -> 0.011111111 | O40: =SUM(M40-G40)/G40 -> 0.015625 | P40: tenant has seen an identical flat on for £2150 although not sure what flat this is | Q40: No | R40: Please stick with offer | S40: Re-Offered
A41: 29/05/2024 | B41: Daisy | C41: Jemma | D41: Mitre Road | E41: 95 Mitre Road | F41: 2 | G41: 2140 | H41: 2140 | I41: 2350 | J41: =SUM(I41-H41)/H41 -> 0.098130841 | K41: 2260 | L41: =SUM(K41-H41)/H41 -> 0.056074766 | M41: 2260 | N41: =SUM(M41-H41)/H41 -> 0.056074766 | O41: =SUM(M41-G41)/G41 -> 0.056074766 | P41: This figure is based on comparable furnished properties the tenant found in the same vicinity currently listed at £2,200 on Zoopla. They have been tenants for 7 years. | Q41: Yes | R41: That's fine, please renew at suggested price | S41: Re-Offered | T41: Accepted
A42: 29/05/2024 | B42: Daisy | C42: Jemma | D42: The Gardens | E42: 32, Flat FFF | F42: Studio | G42: 1310 | H42: 1175 | I42: 1285 | J42: =SUM(I42-H42)/H42 -> 0.093617021 | K42: 1275 | L42: =SUM(K42-H42)/H42 -> 0.085106383 | M42: 1275 | N42: =SUM(M42-H42)/H42 -> 0.085106383 | O42: =SUM(M42-G42)/G42 -> -0.026717557 | P42: tenant wants a £10pcm reduction on offer | Q42: Yes | R42: That's fine, please renew at suggested price | S42: Re-Offered | T42: Accepted
A43: 45358 | B43: Vicki | C43: Sophie | D43: Enigma | E43: 305 Enigma S | F43: 2 | G43: 1798 | H43: 1825 | I43: 1890 | J43: =SUM(I43-H43)/H43 -> 0.035616438 | K43: 1875 | L43: =SUM(K43-H43)/H43 -> 0.02739726 | M43: 1875 | N43: =SUM(M43-H43)/H43 -> 0.02739726 | O43: =SUM(M43-G43)/G43 -> 0.042825362 | P43: Since moving in January 2023, the proposed rent of £1890 per calendar month represents an 18.5% increase over a span of just 1.5 years. Arbour and Park Square, which are offering 2-bedroom apartments at significantly lower rates. Multiple complaints of nouse & intrcom issues | Q43: 1875 | R43: Would accept £1,855 if they agree to longer TA | S43: yes
A44: 30/05/2024 | B44: Daisy | C44: Jemma | D44: Dibdin House | E44: Flat 165 | F44: 1 | G44: 1875 | H44: 1875 | I44: 1950 | J44: =SUM(I44-H44)/H44 -> 0.04 | K44: 1875 | L44: =SUM(K44-H44)/H44 -> 0 | M44: 1900 | N44: =SUM(M44-H44)/H44 -> 0.013333333 | O44: =SUM(M44-G44)/G44 -> 0.013333333 | P44: tenant said he's seen other flats in the same building for much lower | Q44: No | R44: This flat is recently refurbished, please stick to original offer | S44: Re-Offered
A45: 30/05/2024 | B45: Daisy | C45: Jemma | D45: Grove House | E45: Flat 3 Grove House | F45: 2 | G45: 2625 | H45: 2460 | I45: 2675 | J45: =SUM(I45-H45)/H45 -> 0.087398374 | K45: 2500 | L45: =SUM(K45-H45)/H45 -> 0.016260163 | M45: 2635 | N45: =SUM(M45-H45)/H45 -> 0.071138211 | O45: =SUM(M45-G45)/G45 -> 0.0038095238 | P45: they feel they're being pushed out which is unfair considering the difficult circumstances they have endured (relentless drilling, unusable terrace, loud gym noises) | Q45: Yes | R45: Works are due to be completed here soon. Happy to agree with suggested renewal price | S45: Re-Offered
A46: 30/05/2024 | B46: Daisy | C46: Jemma | D46: Grove House | E46: Flat 11 Grove House | F46: 3 | G46: 3085 | H46: 3010 | I46: 3150 | J46: =SUM(I46-H46)/H46 -> 0.046511628 | K46: 3010 | L46: =SUM(K46-H46)/H46 -> 0 | M46: 3125 | N46: =SUM(M46-H46)/H46 -> 0.03820598 | O46: =SUM(M46-G46)/G46 -> 0.012965964 | P46: tenants think the flat is not currently in a state to be re-let due to the damage that needs replacing and that the market price does not include these factors
A47: 30/05/2024 | B47: Daisy | C47: Jemma | D47: Shillington | E47: 2Y Shillington Old School | F47: bedsit | G47: 990 | H47: 975 | I47: 1035 | J47: =SUM(I47-H47)/H47 -> 0.061538462 | K47: 1030 | L47: =SUM(K47-H47)/H47 -> 0.056410256 | M47: 1030 | N47: =SUM(M47-H47)/H47 -> 0.056410256 | O47: =SUM(M47-G47)/G47 -> 0.04040404 | P47: suggest accept counteroffer as £5pcm | Q47: Yes | R47: Please renew at suggested price | S47: Re-Offered | T47: Accepted
A48: 30/05/2024 | B48: Daisy | C48: Jemma | D48: Kew Bridge | E48: 83 Kew Bridge Court | F48: 2 | G48: 2162 | H48: 2110 | I48: 2225 | J48: =SUM(I48-H48)/H48 -> 0.05450237 | K48: 2210 | L48: =SUM(K48-H48)/H48 -> 0.047393365 | M48: 2210 | N48: =SUM(M48-H48)/H48 -> 0.047393365 | O48: =SUM(M48-G48)/G48 -> 0.022201665 | P48: suggest accept counteroffer | Q48: Yes | R48: Please renew at suggested price | S48: Re-Offered | T48: Accepted
A49: 30/05/2024 | B49: Daisy | C49: Jemma | D49: Ability Plaza | E49: Ex 19 Ability Plaza | F49: 1 | G49: 2271 | H49: 2025 | I49: 2235 | J49: =SUM(I49-H49)/H49 -> 0.1037037 | K49: 2146.5 | L49: =SUM(K49-H49)/H49 -> 0.06 | M49: 2200 | N49: =SUM(M49-H49)/H49 -> 0.086419753 | O49: =SUM(M49-G49)/G49 -> -0.03126376 | Q49: No | R49: The resident is paying a very low rent for the property. Please can we push a little higher here. Offered rent is already below ERV | S49: Re-Offered
A50: 45479 | B50: Harriet | C50: Sophie | D50: Berewood | E50: 6, Houghton Avenue | F50: 3 | G50: 1450 | H50: 1375 | I50: 1460 | J50: =SUM(I50-H50)/H50 -> 0.061818182 | K50: 1400 | L50: =SUM(K50-H50)/H50 -> 0.018181818 | N50: =SUM(M50-H50)/H50 -> -1 | O50: =SUM(M50-G50)/G50 -> -1 | P50: will sign another 24 months term for 1400pcm - had numerous issues with flat | Q50: £1430 min | S50: yes
A51: 45329 | B51: Vicki | C51: Sophie | D51: Enigma | E51: 730 Enigma | F51: 1 | G51: 1404 | H51: 1325 | I51: 1505 | J51: =SUM(I51-H51)/H51 -> 0.13584906 | K51: 1440 | L51: =SUM(K51-H51)/H51 -> 0.086792453 | N51: =SUM(M51-H51)/H51 -> -1 | O51: =SUM(M51-G51)/G51 -> -1 | P51: req a capped increase at 9% (1440) | Q51: 1440 | S51: yes
A52: 15/07/2024 | B52: Vicki | C52: Sophie | D52: Enigma | E52: 816 Enigma | F52: 1 | G52: 1404 | H52: 1300 | I52: 1480 | J52: =SUM(I52-H52)/H52 -> 0.13846154 | K52: 1360 | L52: =SUM(K52-H52)/H52 -> 0.046153846 | M52: 1400 | N52: =SUM(M52-H52)/H52 -> 0.076923077 | O52: =SUM(M52-G52)/G52 -> -0.0028490028 | P52: I checked the rightmove website, and it seems that prices for the identical apartments in Enigma Square vary from 1360 to 1400 there, which is less than what you provided me in the renewal offer: | Q52: 1405 | S52: yes | T52: Accepted
A53: 24/07/2024 | B53: Vicki | C53: Sophie | D53: H&G | E53: Flat 97 Hawkins | F53: 2 | G53: 1972 | H53: 1880 | I53: 1995 | J53: =SUM(I53-H53)/H53 -> 0.061170213 | K53: 1880 | L53: =SUM(K53-H53)/H53 -> 0 | M53: 1955 | N53: =SUM(M53-H53)/H53 -> 0.039893617 | O53: =SUM(M53-G53)/G53 -> -0.0086206897 | P53: A | Q53: 1975 | S53: yes
A54: 45357 | B54: Vicki | C54: Lacey | D54: Clippers | E54: 1006 Tayleur | F54: 1 | G54: 1115 | H54: 1070 | I54: 1160 | J54: =SUM(I54-H54)/H54 -> 0.08411215 | K54: 1110 | L54: =SUM(K54-H54)/H54 -> 0.037383178 | M54: 1120 | N54: =SUM(M54-H54)/H54 -> 0.046728972 | O54: =SUM(M54-G54)/G54 -> 0.0044843049 | P54: What price can we agree? | Q54: 1120 | S54: Re-Offered
A55: 45358 | B55: Vicki | C55: Lacey | D55: Clippers | E55: 705 Ambassador | F55: 3 | G55: 1905 | H55: 1815 | I55: 1920 | J55: =SUM(I55-H55)/H55 -> 0.05785124 | K55: 1870 | L55: =SUM(K55-H55)/H55 -> 0.03030303 | M55: 1905 | N55: =SUM(M55-H55)/H55 -> 0.049586777 | O55: =SUM(M55-G55)/G55 -> 0 | P55: New PB £1865 Can we reduce a small amount to keep? | Q55: 1905 | S55: Re-Offered
A56: 45481 | B56: Vicki | C56: Sophie | D56: Solstice | E56: 225 Solsricr | F56: 2 | G56: 1638 | H56: 1620 | I56: 1710 | J56: =SUM(I56-H56)/H56 -> 0.055555556 | K56: 1650 | L56: =SUM(K56-H56)/H56 -> 0.018518519 | M56: 1685 | N56: =SUM(M56-H56)/H56 -> 0.040123457 | O56: =SUM(M56-G56)/G56 -> 0.028693529 | P56: will be happy to agree to 4% for a 24 or 36 month term including 15 month break clause. | Q56: 1685 | S56: yes
A57: 45358 | B57: Vicki | C57: Sophie | D57: Enigma | E57: 516 Enigma | F57: 1 | G57: 1443 | H57: 1290 | I57: 1450 | J57: =SUM(I57-H57)/H57 -> 0.12403101 | K57: 1390 | L57: =SUM(K57-H57)/H57 -> 0.07751938 | M57: 1400 | N57: =SUM(M57-H57)/H57 -> 0.085271318 | O57: =SUM(M57-G57)/G57 -> -0.02979903 | P57: TT counter offered with £1390- complaining as they're aware of other renewals and have offered in line with these - suggest we accept counter offer | Q57: 1410
A58: 45357 | B58: Vicki | C58: Lacey | D58: filaments | E58: 1004 Halogen | F58: 3 | G58: 2145 | H58: 2095 | I58: 2205 | J58: =SUM(I58-H58)/H58 -> 0.052505967 | K58: 1800 | L58: =SUM(K58-H58)/H58 -> -0.14081146 | M58: 2150 | N58: =SUM(M58-H58)/H58 -> 0.026252983 | O58: =SUM(M58-G58)/G58 -> 0.0023310023 | P58: More than likely will lose this as have countered at £1800- whats best price? | Q58: 2150 | S58: Re-Offered
A59: 45357 | B59: Vicki | C59: Lacey | D59: filaments | E59: 1009 Halogen | F59: 2 | G59: 1540 | H59: 1475 | I59: 1600 | J59: =SUM(I59-H59)/H59 -> 0.084745763 | K59: 1475 | L59: =SUM(K59-H59)/H59 -> 0 | M59: 1540 | N59: =SUM(M59-H59)/H59 -> 0.044067797 | O59: =SUM(M59-G59)/G59 -> 0 | P59: the minimum states £1560 but is there any more room? they want current rent as the lower floors are going for this- we may lose | Q59: 1545 | S59: Re-Offered
A60: 45357 | B60: Vicki | C60: Sophie | D60: Solstice | E60: 224 Solstice | F60: 2 | G60: 1638 | H60: 1540 | I60: 1675 | J60: =SUM(I60-H60)/H60 -> 0.087662338 | K60: 1600 | L60: =SUM(K60-H60)/H60 -> 0.038961039 | M60: 1640 | N60: =SUM(M60-H60)/H60 -> 0.064935065 | O60: =SUM(M60-G60)/G60 -> 0.0012210012 | Q60: 1640 | S60: yes
B61: Vicki | C61: Sophie | D61: H&G | E61: FLAT 56, Hawkins L | F61: 2 | G61: 1924 | H61: 1855 | I61: 1960 | J61: =SUM(I61-H61)/H61 -> 0.056603774 | K61: 1900 | L61: =SUM(K61-H61)/H61 -> 0.02425876 | M61: 1920 | N61: =SUM(M61-H61)/H61 -> 0.035040431 | O61: =SUM(M61-G61)/G61 -> -0.0020790021 | P61: tenant is interrested in 24 months term - would recommend new price book rent for longer term | Q61: 1930
A62: 45450 | B62: Harriet | C62: Sophie | D62: Gunhill | E62: 6 Mundy | F62: 3 | G62: 1751 | H62: 1885 | I62: 1980 | J62: =SUM(I62-H62)/H62 -> 0.050397878 | K62: 1885 | L62: =SUM(K62-H62)/H62 -> 0 | M62: 1935 | N62: =SUM(M62-H62)/H62 -> 0.026525199 | O62: =SUM(M62-G62)/G62 -> 0.10508281 | P62: informed by the agent at move in there would be no increase, also would be rolling - i think we could agree to meet mid-way with 6months BC | Q62: can accept £1935 | R62: I think the ERV is wrong | S62: yes | T62: accepted
A63: 45388 | B63: Daisy | C63: Jemma | D63: Springfield House | E63: Flat 66 Springfield | F63: 2 | G63: 2769 | H63: 2685 | I63: 2830 | J63: =SUM(I63-H63)/H63 -> 0.054003724 | K63: 2780 | L63: =SUM(K63-H63)/H63 -> 0.03538175 | M63: 2800 | N63: =SUM(M63-H63)/H63 -> 0.04283054 | O63: =SUM(M63-G63)/G63 -> 0.011195377 | P63: tenant wants a longer term. maybe £2800 for first year and 4% uplift in 2nd year? | Q63: agreed | S63: Re-Offered
A64: 13/08/2024 | B64: Vicki | C64: Sophie | D64: Enigma | E64: 408 Enigma S | F64: 1 | G64: 1426 | H64: 1290 | I64: 1430 | J64: =SUM(I64-H64)/H64 -> 0.10852713 | K64: 1390 | L64: =SUM(K64-H64)/H64 -> 0.07751938 | M64: 1400 | N64: =SUM(M64-H64)/H64 -> 0.085271318 | O64: =SUM(M64-G64)/G64 -> -0.018232819 | P64: Max bugjet is less than 1400pcm. | Q64: No neg | S64: yes
A65: 45388 | B65: Harriet | C65: Jemma | D65: Nautilus | E65: 31 Nautilus | F65: 1 | G65: 2132 | H65: 2080 | I65: 2150 | J65: =SUM(I65-H65)/H65 -> 0.033653846 | K65: 2150 | L65: =SUM(K65-H65)/H65 -> 0.033653846 | M65: 2150 | N65: =SUM(M65-H65)/H65 -> 0.033653846 | O65: =SUM(M65-G65)/G65 -> 0.0084427767 | P65: tenant has requested a 3 month term due to masters. she pays RIA - would suggest accepting 3 month term to re-let in October, or a break clause holiday. | R65: discussed over email | S65: Re-Offered
A66: 45418 | B66: Vicki | C66: Lacey | D66: Headline | E66: 805 The Headline | F66: 2 | G66: 1435 | H66: 1385 | I66: 1450 | J66: =SUM(I66-H66)/H66 -> 0.046931408 | K66: 1400 | L66: =SUM(K66-H66)/H66 -> 0.010830325 | M66: 1395 | N66: =SUM(M66-H66)/H66 -> 0.0072202166 | O66: =SUM(M66-G66)/G66 -> -0.027874564 | P66: 815 the headline is on market for £1330- TT knows and wants to view this- he has countered at £1400 however do believe we will lose to other apartment as cheaper than current rent | Q66: 1440 | S66: Re-Offered
A67: 45418 | B67: Vicki | C67: Lacey | D67: Filaments | E67: 702 Halogen | F67: 2 | G67: 1485 | H67: 1420 | I67: 1565 | J67: =SUM(I67-H67)/H67 -> 0.10211268 | K67: 1435 | L67: =SUM(K67-H67)/H67 -> 0.01056338 | M67: 1485 | N67: =SUM(M67-H67)/H67 -> 0.045774648 | O67: =SUM(M67-G67)/G67 -> 0 | P67: not sure if we will keep- whats best price | Q67: 1500 | S67: Re-Offered
A68: 45449 | B68: Vicki | C68: Lacey | D68: Clippers | E68: 801 Tayleur | F68: 2 | G68: 1360 | H68: 1295 | I68: 1390 | J68: =SUM(I68-H68)/H68 -> 0.073359073 | L68: =SUM(K68-H68)/H68 -> -1 | M68: 1370 | N68: =SUM(M68-H68)/H68 -> 0.057915058 | O68: =SUM(M68-G68)/G68 -> 0.0073529412 | P68: tenants have served notice but asking to see if theres any neg toom to try to keep | Q68: 1370 | R68: £1,370 best and final | S68: Re-Offered
A69: 45449 | B69: Vicki | C69: Lacey | D69: Filaments | E69: 1504 Lamp House | F69: 2 | G69: 1585 | H69: 1520 | I69: 1600 | J69: =SUM(I69-H69)/H69 -> 0.052631579 | K69: 1570 | L69: =SUM(K69-H69)/H69 -> 0.032894737 | M69: 1570 | N69: =SUM(M69-H69)/H69 -> 0.032894737 | O69: =SUM(M69-G69)/G69 -> -0.0094637224 | P69: to try to keep | Q69: 1585 | R69: £1,585 best and final | S69: Re-Offered
A70: 45449 | B70: Vicki | C70: Lacey | D70: Clippers | E70: 804 Torrens | F70: 2 | G70: 1410 | H70: 1300 | I70: 1400 | J70: =SUM(I70-H70)/H70 -> 0.076923077 | K70: 1350 | L70: =SUM(K70-H70)/H70 -> 0.038461538 | M70: 1370 | N70: =SUM(M70-H70)/H70 -> 0.053846154 | O70: =SUM(M70-G70)/G70 -> -0.028368794 | P70: to try to keep | Q70: No | R70: No neg on offered price | S70: Re-Offered
A71: 27/07/2024 | B71: Vicki | C71: Sophie | D71: Enigma | E71: 811 Enigma | F71: 1 | G71: 1404 | H71: 1300 | I71: 1440 | J71: =SUM(I71-H71)/H71 -> 0.10769231 | K71: 1380 | L71: =SUM(K71-H71)/H71 -> 0.061538462 | M71: 1400 | N71: =SUM(M71-H71)/H71 -> 0.076923077 | O71: =SUM(M71-G71)/G71 -> -0.0028490028 | P71: TTs req max increase of 6%, 11% is unacceptable price increase | Q71: 1400 | R71: £1,400 best and final | S71: yes
A72: 45479 | B72: Vicki | C72: Lacey | D72: Clippers | E72: 704 Ambassador | F72: 2 | G72: 1475 | H72: 1425 | I72: 1505 | J72: =SUM(I72-H72)/H72 -> 0.056140351 | K72: 1485 | L72: =SUM(K72-H72)/H72 -> 0.042105263 | M72: 1485 | N72: =SUM(M72-H72)/H72 -> 0.042105263 | O72: =SUM(M72-G72)/G72 -> 0.006779661 | P72: suggest agree to their counter | Q72: Yes | R72: Accept counter offer | S72: Re-Offered
A73: 45603 | B73: Vicki | C73: Sophie | D73: Enigma | E73: 635 Enigma | F73: 1 | G73: 1443 | H73: 1360 | I73: 1515 | J73: =SUM(I73-H73)/H73 -> 0.11397059 | K73: 1480 incl pl | L73: =SUM(K73-H73)/H73 -> #VALUE! | M73: 1465 | N73: =SUM(M73-H73)/H73 -> 0.077205882 | O73: =SUM(M73-G73)/G73 -> 0.015246015 | P73: Offered min at £1465 - TT is asking for 1480 including parking - would suggest Rental Level: £1465.00 + Parking fee: £25.00 = 1490 in total. | Q73: Yes | R73: As per renewals team suggestion | S73: yes
A74: 45571 | B74: Vicki | C74: Lacey | D74: KDM | E74: 73 Kings Dock Mill | F74: 2 | G74: 960 | H74: 905 | I74: 1010 | J74: =SUM(I74-H74)/H74 -> 0.1160221 | K74: 910 | L74: =SUM(K74-H74)/H74 -> 0.0055248619 | M74: 970 | N74: =SUM(M74-H74)/H74 -> 0.071823204 | O74: =SUM(M74-G74)/G74 -> 0.010416667 | Q74: No | R74: No neg | S74: Re-Offered
A75: 45571 | B75: Daisy | C75: Jemma | D75: Mitre Road | E75: 86 Mitre Road | F75: 2 | H75: 2440 | I75: 2650 | J75: =SUM(I75-H75)/H75 -> 0.086065574 | K75: Short term | L75: N/A | M75: 2650 | N75: =SUM(M75-H75)/H75 -> 0.086065574 | O75: =SUM(M75-G75)/G75 -> #DIV/0! | P75: tenant can only commit to a tenancy ending in December due to VISA issues. Did offer a work relocation clause but was rejected. | Q75: no | R75: Cannot agree to a contract ending in December | S75: Re-Offered
A76: 45571 | B76: Daisy | C76: Jemma | D76: Ability Plaza | E76: Flat 16 Ability | F76: 1 | G76: 2102 | H76: 1725 | I76: 2125 | J76: =SUM(I76-H76)/H76 -> 0.23188406 | K76: 2000 | L76: =SUM(K76-H76)/H76 -> 0.15942029 | M76: 2105 | N76: =SUM(M76-H76)/H76 -> 0.22028986 | O76: =SUM(M76-G76)/G76 -> 0.0014272122 | P76: suggest offering just above ERV | Q76: agreed | S76: Re-Offered
A77: 45602 | B77: Harriet | C77: Jemma | D77: Millet Place | E77: 104 Adlay Apartments | F77: 2 | G77: 2340 | H77: 2095 | I77: 2295 | J77: =SUM(I77-H77)/H77 -> 0.095465394 | K77: 2150 | L77: =SUM(K77-H77)/H77 -> 0.026252983 | M77: 2250 | N77: =SUM(M77-H77)/H77 -> 0.07398568 | O77: =SUM(M77-G77)/G77 -> -0.038461538 | Q77: cannot accept below £2275 | R77: HS added ERV | S77: Re-Offered
A78: 45604 | B78: Harriet | C78: Sophie | D78: Wellesley | E78: 16 Nelson | F78: 2 | G78: 1322 | H78: 1242 | I78: 1330 | J78: =SUM(I78-H78)/H78 -> 0.070853462 | K78: 1300 | L78: =SUM(K78-H78)/H78 -> 0.046698873 | M78: 1300 | N78: =SUM(M78-H78)/H78 -> 0.046698873 | O78: =SUM(M78-G78)/G78 -> -0.016641452 | P78: happy to proceed with a 24 month term - req 1300pcm | Q78: Cannot accept below ERV - £1325 min | R78: no more neg | S78: yes
A79: 45602 | B79: Daisy | C79: Jemma | D79: Grove HOUSE | E79: Flat 3 Grove House | F79: 2 | G79: 2625 | H79: 2460 | I79: 2635 | J79: =SUM(I79-H79)/H79 -> 0.071138211 | K79: 2555 | L79: =SUM(K79-H79)/H79 -> 0.038617886 | M79: 2600 | N79: =SUM(M79-H79)/H79 -> 0.056910569 | O79: =SUM(M79-G79)/G79 -> -0.0095238095 | P79: Second time they have requested a neg. Can we go below ERV? Currently a Future Vacant | Q79: agreed | S79: Re-Offered
