Workbook
Name aspectpremium: '2. GRI Pricing Inputs'!$C$53:$E$55
Name balcony: '2. GRI Pricing Inputs'!$C$67:$E$69
Name baseprice: '2. GRI Pricing Inputs'!$C$15:$F$17
Name bathpremium: '2. GRI Pricing Inputs'!$C$21:$E$24
Name floorpremium: '2. GRI Pricing Inputs'!$C$45:$E$47
Name other: '2. GRI Pricing Inputs'!$O$32:$P$47
Name phasedrelease: '2. GRI Pricing Inputs'!$I$54
Name sizepremium: '2. GRI Pricing Inputs'!$C$28:$E$31

Sheet Cover
C3: BTR PRICING WORKBOOK
K5: ACQ | L5: CFT | M5: ONB | N5: AM | O5: LET
C6: Project: | E6: The Forge, Newcastle | J6: Project Team | K6: [Name] | L6: [Name] | M6: [Name] | N6: [Name] | O6: [Name]
C7: Pricing Date: | E7: 44538 | J7: Reviewer | K7: [Name] | L7: [Name] | M7: [Name] | N7: [Name] | O7: [Name]
C9: INSTRUCTIONS
C11: Key: | E11: Light blue = input | G11: White = calculation
C13: Tab | D13: Process
C14: 1. Accomodation tab | D14: 1 | E14: Input accomodation to be constructed, as per the Development agreement, in columns D-F (request final DA from the acquistions manager)
D15: 2 | E15: Update Qube for Qube location data (fund/portfolio/estate) as per BTR example provided (check with asset manager if unsure)
D16: 3 | E16: Create Grainger schedule as required in the format provided (Col L-AA)
D17: 4 | E17: Input Grainger required accomodation attributes (Col S-AA)
C19: 2. GRI Pricing inputs | D19: 5 | E19: Input premium values and growth inputs (Number 1-15)
D20: 6 | E20: Describe methodology for each inputs
C22: 3. GRI Pricing | D22: 7 | E22: Review and sense check pricing framework unit by unit
D23: 8 | E23: Add any manual adjustment and provide rationale for adjustments
D24: 9 | E24: Review and sense check overall and average pricing
C26: 4. CBRE ERV's | D26: 10 | E26: CFT to provide i) approved underwritten rents ii) market ERV per the latest CBRE valuation
D27: 11 | E27: Communication expected launch date to CFT in order to grow benchmarks to same point in time.
D28: 12 | E28: All rents must be compared at the same point in time, on a like for like basis.
D29: 13 | E29: If appraising the current market rent today, we must grow both the underwriting and CBRE from their respective points in time to today.
D30: 14 | E30: Grainger underwrite rental growth for each project and CBRE assume rental growth in their valuation (check growth % for each specific project).
C32: 5. Dashboard | D32: 15 | E32: Review dashboard, ensure current pricing are in line as expected of the current view of the market
D33: 16 | E33: Aim to launch at and outperform the higher of i) ‘grown underwritten ERV’ and ii) ‘CBRE Est. Forecast' ERV
D34: 17 | E34: Append the table within leasing and marketing report
C36: 6. IC Appendix | D36: 18 | E36: Append the full master schedule within leasing and marketing report.
C38: 7. Archive Pricing | D38: 19 | E38: To allow tracking of previously approved prices for each unit.

Sheet 1. Accomodation
H3: 1. ACCOMODATION SCHEDULE | Y3: ='4. Valuation'!$D$6 -> 45199
H5: Project | I5: =Cover!E6 -> The Forge, Newcastle
H7: Qube Location Data | L7: Grainger Accomodation
H8: Qube Field | I8: Inputs | J8: Example | L8: Bedroom | M8: No. of Homes | N8: Av. Size (sqft) | O8: Notes
H9: Fund | I9: BTR-Regions | L9: 1 Bed | M9: =IFERROR(COUNTIF($P$21:$P$622,$L9),"-") -> 78 | N9: =IFERROR(AVERAGEIF($P$21:$P$622,$L9,$O$21:$O$622),"-") -> 503.5641
H10: Portfolio | I10: The Forge | L10: 2 Bed | M10: =IFERROR(COUNTIF($P$21:$P$622,$L10),"-") -> 179 | N10: =IFERROR(AVERAGEIF($P$21:$P$622,$L10,$O$21:$O$622),"-") -> 652.34637
H11: Estate | I11: The Forge - Apts | J11: XXXX - Apartments | L11: 3 Bed | M11: =IFERROR(COUNTIF($P$21:$P$622,$L11),"-") -> 26 | N11: =IFERROR(AVERAGEIF($P$21:$P$622,$L11,$O$21:$O$622),"-") -> 823.19231
J12: XXXX - XXX Apts | M12: =IFERROR(COUNTIF($P$21:$P$622,$L12),"-") -> 0 | N12: =IFERROR(AVERAGEIF($P$21:$P$622,$L12,$O$21:$O$622),"-") -> -
J13: XXXX - Amenity | M13: =IFERROR(COUNTIF($P$21:$P$622,$L13),"-") -> 0 | N13: =IFERROR(AVERAGEIF($P$21:$P$622,$L13,$O$21:$O$622),"-") -> -
J14: XXXX - Commercial | M14: =IFERROR(COUNTIF($P$21:$P$622,$L14),"-") -> 0 | N14: =IFERROR(AVERAGEIF($P$21:$P$622,$L14,$O$21:$O$622),"-") -> -
L15: Total | M15: =SUM(M9:M13) -> 283 | N15: =IFERROR(SUM(O21:O620)/M15,0) -> 627.03534
J16: XXXX - Car Parking | L16: Car Park
D19: DA ACCOMODATION | H19: Qube Property Location Inputs | L19: GRAINGER ACCOMODATION
C20: Plot Number | D20: Home type | E20: Size (sq.ft) | F20: Bedroom | H20: Fund | I20: Portfolio | J20: Estate | L20: Block Name | M20: =D20 -> Home type | N20: Door Number | O20: =E20 -> Size (sq.ft) | P20: ='2. GRI Pricing Inputs'!C15 -> Bedroom | Q20: ='2. GRI Pricing Inputs'!C22 -> Bath | R20: ='2. GRI Pricing Inputs'!C45 -> Floor | S20: ='2. GRI Pricing Inputs'!C53 -> Aspect | T20: ='2. GRI Pricing Inputs'!C60 -> Storage | U20: ='2. GRI Pricing Inputs'!C67 -> Balcony | V20: ='2. GRI Pricing Inputs'!C83 -> Window Premium | W20: ='2. GRI Pricing Inputs'!C90 -> Restricted Light | X20: ='2. GRI Pricing Inputs'!C98 -> 0 | Y20: ='2. GRI Pricing Inputs'!C105 -> Character premium #4
D21: [Select] | H21: =$I$9 -> BTR-Regions | I21: =$I$10 -> The Forge | J21: The Forge - Apts | L21: North | M21: Apartment | N21: 101N | O21: 484 | P21: 1 Bed | Q21: 1 | R21: Ground | S21: Courtyard | T21: [Select] | U21: No | V21: External Access | W21: No | X21: No | Y21: [A-4]
D22: [Select] | H22: =$I$9 -> BTR-Regions | I22: =$I$10 -> The Forge | J22: The Forge - Apts | L22: North | M22: Apartment | N22: 102N | O22: 678 | P22: 2 Bed | Q22: 2 | R22: Ground | S22: Courtyard | T22: [Select] | U22: No | V22: External Access | W22: No | X22: No | Y22: [Select]
D23: [Select] | H23: =$I$9 -> BTR-Regions | I23: =$I$10 -> The Forge | J23: The Forge - Apts | L23: North | M23: Apartment | N23: 103N | O23: 657 | P23: 2 Bed | Q23: 2 | R23: Ground | S23: Courtyard | T23: [Select] | U23: No | V23: Normal | W23: No | X23: No | Y23: [Select]
D24: [Select] | H24: =$I$9 -> BTR-Regions | I24: =$I$10 -> The Forge | J24: The Forge - Apts | L24: North | M24: Apartment | N24: 104N | O24: 818 | P24: 3 Bed | Q24: 2 | R24: 1 | S24: Pottery Lane | T24: [Select] | U24: No | V24: Normal | W24: No | X24: No | Y24: [Select]
D25: [Select] | H25: =$I$9 -> BTR-Regions | I25: =$I$10 -> The Forge | J25: The Forge - Apts | L25: North | M25: Apartment | N25: 105N | O25: 667 | P25: 2 Bed | Q25: 2 | R25: 1 | S25: Forth Banks/Pottery Lane | T25: [Select] | U25: No | V25: Normal | W25: No | X25: No | Y25: [Select]
D26: [Select] | H26: =$I$9 -> BTR-Regions | I26: =$I$10 -> The Forge | J26: The Forge - Apts | L26: North | M26: Apartment | N26: 106N | O26: 441 | P26: 1 Bed | Q26: 1 | R26: 1 | S26: Forth Banks | T26: [Select] | U26: No | V26: Normal | W26: No | X26: Adjustment - 15 | Y26: [Select]
D27: [Select] | H27: =$I$9 -> BTR-Regions | I27: =$I$10 -> The Forge | J27: The Forge - Apts | L27: North | M27: Apartment | N27: 107N | O27: 624 | P27: 2 Bed | Q27: 2 | R27: 1 | S27: Forth Banks | T27: [Select] | U27: No | V27: Normal | W27: No | X27: No | Y27: [Select]
D28: [Select] | H28: =$I$9 -> BTR-Regions | I28: =$I$10 -> The Forge | J28: The Forge - Apts | L28: North | M28: Apartment | N28: 108N | O28: 624 | P28: 2 Bed | Q28: 2 | R28: 1 | S28: Forth Banks | T28: [Select] | U28: No | V28: Normal | W28: No | X28: No | Y28: [Select]
D29: [Select] | H29: =$I$9 -> BTR-Regions | I29: =$I$10 -> The Forge | J29: The Forge - Apts | L29: North | M29: Apartment | N29: 109N | O29: 657 | P29: 2 Bed | Q29: 2 | R29: 1 | S29: River - Partial | T29: [Select] | U29: No | V29: Normal | W29: No | X29: No | Y29: [Select]
D30: [Select] | H30: =$I$9 -> BTR-Regions | I30: =$I$10 -> The Forge | J30: The Forge - Apts | L30: North | M30: Apartment | N30: 110N | O30: 700 | P30: 2 Bed | Q30: 2 | R30: 1 | S30: Forth Banks - Partial | T30: [Select] | U30: No | V30: Normal | W30: No | X30: No | Y30: [Select]
D31: [Select] | H31: =$I$9 -> BTR-Regions | I31: =$I$10 -> The Forge | J31: The Forge - Apts | L31: North | M31: Apartment | N31: 111N | O31: 689 | P31: 2 Bed | Q31: 2 | R31: 1 | S31: Courtyard - dual | T31: [Select] | U31: Yes | V31: Normal | W31: No | X31: No | Y31: [Select]
D32: [Select] | H32: =$I$9 -> BTR-Regions | I32: =$I$10 -> The Forge | J32: The Forge - Apts | L32: North | M32: Apartment | N32: 112N | O32: 506 | P32: 1 Bed | Q32: 1 | R32: Ground | S32: Courtyard | T32: [Select] | U32: No | V32: External Access | W32: No | X32: No | Y32: [Select]
D33: [Select] | H33: =$I$9 -> BTR-Regions | I33: =$I$10 -> The Forge | J33: The Forge - Apts | L33: North | M33: Apartment | N33: 113N | O33: 538 | P33: 1 Bed | Q33: 1 | R33: Ground | S33: Courtyard | T33: [Select] | U33: No | V33: External Access | W33: No | X33: No | Y33: [Select]
D34: [Select] | H34: =$I$9 -> BTR-Regions | I34: =$I$10 -> The Forge | J34: The Forge - Apts | L34: North | M34: Apartment | N34: 114N | O34: 560 | P34: 1 Bed | Q34: 1 | R34: Ground | S34: Courtyard | T34: [Select] | U34: No | V34: External Access | W34: Resticted - 25 | X34: No | Y34: [Select]
D35: [Select] | H35: =$I$9 -> BTR-Regions | I35: =$I$10 -> The Forge | J35: The Forge - Apts | L35: North | M35: Apartment | N35: 115N | O35: 624 | P35: 2 Bed | Q35: 2 | R35: Ground | S35: Courtyard | T35: [Select] | U35: No | V35: External Access | W35: No | X35: No | Y35: [Select]
D36: [Select] | H36: =$I$9 -> BTR-Regions | I36: =$I$10 -> The Forge | J36: The Forge - Apts | L36: North | M36: Apartment | N36: 116N | O36: 624 | P36: 2 Bed | Q36: 2 | R36: Ground | S36: Courtyard | T36: [Select] | U36: No | V36: External Access | W36: No | X36: No | Y36: [Select]
D37: [Select] | H37: =$I$9 -> BTR-Regions | I37: =$I$10 -> The Forge | J37: The Forge - Apts | L37: North | M37: Apartment | N37: 201N | O37: 484 | P37: 1 Bed | Q37: 1 | R37: 2 | S37: Courtyard | T37: [Select] | U37: No | V37: Normal | W37: No | X37: No | Y37: [Select]
D38: [Select] | H38: =$I$9 -> BTR-Regions | I38: =$I$10 -> The Forge | J38: The Forge - Apts | L38: North | M38: Apartment | N38: 202N | O38: 678 | P38: 2 Bed | Q38: 2 | R38: 2 | S38: Courtyard | T38: [Select] | U38: No | V38: Normal | W38: No | X38: No | Y38: [Select]
D39: [Select] | H39: =$I$9 -> BTR-Regions | I39: =$I$10 -> The Forge | J39: The Forge - Apts | L39: North | M39: Apartment | N39: 203N | O39: 657 | P39: 2 Bed | Q39: 2 | R39: 2 | S39: Courtyard | T39: [Select] | U39: No | V39: Normal | W39: No | X39: No | Y39: [Select]
D40: [Select] | H40: =$I$9 -> BTR-Regions | I40: =$I$10 -> The Forge | J40: The Forge - Apts | L40: North | M40: Apartment | N40: 204N | O40: 818 | P40: 3 Bed | Q40: 2 | R40: 2 | S40: Pottery Lane | T40: [Select] | U40: No | V40: Normal | W40: No | X40: No | Y40: [Select]
D41: [Select] | H41: =$I$9 -> BTR-Regions | I41: =$I$10 -> The Forge | J41: The Forge - Apts | L41: North | M41: Apartment | N41: 205N | O41: 667 | P41: 2 Bed | Q41: 2 | R41: 2 | S41: Forth Banks/Pottery Lane | T41: [Select] | U41: No | V41: Normal | W41: No | X41: No | Y41: [Select]
D42: [Select] | H42: =$I$9 -> BTR-Regions | I42: =$I$10 -> The Forge | J42: The Forge - Apts | L42: North | M42: Apartment | N42: 206N | O42: 441 | P42: 1 Bed | Q42: 1 | R42: 2 | S42: Forth Banks | T42: [Select] | U42: No | V42: Normal | W42: No | X42: Adjustment - 15 | Y42: [Select]
D43: [Select] | H43: =$I$9 -> BTR-Regions | I43: =$I$10 -> The Forge | J43: The Forge - Apts | L43: North | M43: Apartment | N43: 207N | O43: 624 | P43: 2 Bed | Q43: 2 | R43: 2 | S43: Forth Banks | T43: [Select] | U43: No | V43: Normal | W43: No | X43: No | Y43: [Select]
D44: [Select] | H44: =$I$9 -> BTR-Regions | I44: =$I$10 -> The Forge | J44: The Forge - Apts | L44: North | M44: Apartment | N44: 208N | O44: 624 | P44: 2 Bed | Q44: 2 | R44: 2 | S44: Forth Banks | T44: [Select] | U44: No | V44: Normal | W44: No | X44: No | Y44: [Select]
D45: [Select] | H45: =$I$9 -> BTR-Regions | I45: =$I$10 -> The Forge | J45: The Forge - Apts | L45: North | M45: Apartment | N45: 209N | O45: 657 | P45: 2 Bed | Q45: 2 | R45: 2 | S45: River - Partial | T45: [Select] | U45: No | V45: Normal | W45: No | X45: No | Y45: [Select]
D46: [Select] | H46: =$I$9 -> BTR-Regions | I46: =$I$10 -> The Forge | J46: The Forge - Apts | L46: North | M46: Apartment | N46: 210N | O46: 700 | P46: 2 Bed | Q46: 2 | R46: 2 | S46: Forth Banks - Partial | T46: [Select] | U46: No | V46: Normal | W46: No | X46: No | Y46: [Select]
D47: [Select] | H47: =$I$9 -> BTR-Regions | I47: =$I$10 -> The Forge | J47: The Forge - Apts | L47: North | M47: Apartment | N47: 211N | O47: 689 | P47: 2 Bed | Q47: 2 | R47: 2 | S47: Courtyard - dual | T47: [Select] | U47: No | V47: Normal | W47: No | X47: No | Y47: [Select]
D48: [Select] | H48: =$I$9 -> BTR-Regions | I48: =$I$10 -> The Forge | J48: The Forge - Apts | L48: North | M48: Apartment | N48: 212N | O48: 517 | P48: 1 Bed | Q48: 1 | R48: 2 | S48: Courtyard - dual | T48: [Select] | U48: No | V48: Normal | W48: No | X48: No | Y48: [Select]
... D131: [Select] | H131: =$I$9 -> BTR-Regions | I131: =$I$10 -> The Forge | J131: The Forge - Apts | L131: North | M131: Apartment | N131: 715N | O131: 624 | P131: 2 Bed | Q131: 2 | R131: 7 | S131: Courtyard | T131: [Select] | U131: No | V131: Normal | W131: No | X131: No | Y131: [Select]
D132: [Select] | H132: =$I$9 -> BTR-Regions | I132: =$I$10 -> The Forge | J132: The Forge - Apts | L132: South | M132: Apartment | N132: 1S | O132: 757 | P132: 2 Bed | Q132: 2 | R132: Ground | S132: Courtyard | T132: [Select] | U132: No | V132: External Access | W132: Restricted - 75 | X132: No | Y132: [Select]
D133: [Select] | H133: =$I$9 -> BTR-Regions | I133: =$I$10 -> The Forge | J133: The Forge - Apts | L133: South | M133: Apartment | N133: 2S | O133: 553 | P133: 1 Bed | Q133: 1 | R133: Ground | S133: Courtyard | T133: [Select] | U133: No | V133: External Access | W133: Restricted - 75 | X133: No | Y133: [Select]
D134: [Select] | H134: =$I$9 -> BTR-Regions | I134: =$I$10 -> The Forge | J134: The Forge - Apts | L134: South | M134: Apartment | N134: 3S | O134: 505 | P134: 1 Bed | Q134: 1 | R134: Ground | S134: Courtyard | T134: [Select] | U134: No | V134: External Access | W134: Restricted - 75 | X134: No | Y134: [Select]
D135: [Select] | H135: =$I$9 -> BTR-Regions | I135: =$I$10 -> The Forge | J135: The Forge - Apts | L135: South | M135: Apartment | N135: 101S | O135: 624 | P135: 2 Bed | Q135: 2 | R135: Ground | S135: Fence | T135: [Select] | U135: No | V135: External Access | W135: No | X135: No | Y135: [Select]
D136: [Select] | H136: =$I$9 -> BTR-Regions | I136: =$I$10 -> The Forge | J136: The Forge - Apts | L136: South | M136: Apartment | N136: 102S | O136: 603 | P136: 2 Bed | Q136: 2 | R136: Ground | S136: Fence | T136: [Select] | U136: No | V136: External Access | W136: No | X136: No | Y136: [Select]
D137: [Select] | H137: =$I$9 -> BTR-Regions | I137: =$I$10 -> The Forge | J137: The Forge - Apts | L137: South | M137: Apartment | N137: 103S | O137: 614 | P137: 2 Bed | Q137: 2 | R137: Ground | S137: Fence | T137: [Select] | U137: No | V137: External Access | W137: No | X137: No | Y137: [Select]
D138: [Select] | H138: =$I$9 -> BTR-Regions | I138: =$I$10 -> The Forge | J138: The Forge - Apts | L138: South | M138: Apartment | N138: 104S | O138: 829 | P138: 3 Bed | Q138: 3 | R138: Ground | S138: Fence | T138: [Select] | U138: No | V138: External Access | W138: No | X138: No | Y138: [Select]
D139: [Select] | H139: =$I$9 -> BTR-Regions | I139: =$I$10 -> The Forge | J139: The Forge - Apts | L139: South | M139: Apartment | N139: 105S | O139: 689 | P139: 2 Bed | Q139: 2 | R139: 1 | S139: Courtyard | T139: [Select] | U139: No | V139: Normal | W139: No | X139: No | Y139: [Select]
D140: [Select] | H140: =$I$9 -> BTR-Regions | I140: =$I$10 -> The Forge | J140: The Forge - Apts | L140: South | M140: Apartment | N140: 106S | O140: 474 | P140: 1 Bed | Q140: 1 | R140: 1 | S140: Courtyard | T140: [Select] | U140: No | V140: Normal | W140: No | X140: No | Y140: [Select]
D141: [Select] | H141: =$I$9 -> BTR-Regions | I141: =$I$10 -> The Forge | J141: The Forge - Apts | L141: South | M141: Apartment | N141: 107S | O141: 624 | P141: 2 Bed | Q141: 2 | R141: 1 | S141: Courtyard | T141: [Select] | U141: No | V141: Normal | W141: No | X141: No | Y141: [Select]
D142: [Select] | H142: =$I$9 -> BTR-Regions | I142: =$I$10 -> The Forge | J142: The Forge - Apts | L142: South | M142: Apartment | N142: 201S | O142: 624 | P142: 2 Bed | Q142: 2 | R142: 2 | S142: River- Trees | T142: [Select] | U142: Yes | V142: Normal | W142: No | X142: No | Y142: [Select]
D143: [Select] | H143: =$I$9 -> BTR-Regions | I143: =$I$10 -> The Forge | J143: The Forge - Apts | L143: South | M143: Apartment | N143: 202S | O143: 603 | P143: 2 Bed | Q143: 2 | R143: 2 | S143: River- Trees | T143: [Select] | U143: Yes | V143: Normal | W143: No | X143: No | Y143: [Select]
D144: [Select] | H144: =$I$9 -> BTR-Regions | I144: =$I$10 -> The Forge | J144: The Forge - Apts | L144: South | M144: Apartment | N144: 203S | O144: 614 | P144: 2 Bed | Q144: 2 | R144: 2 | S144: River- Trees | T144: [Select] | U144: Yes | V144: Normal | W144: No | X144: No | Y144: [Select]
D145: [Select] | H145: =$I$9 -> BTR-Regions | I145: =$I$10 -> The Forge | J145: The Forge - Apts | L145: South | M145: Apartment | N145: 204S | O145: 829 | P145: 3 Bed | Q145: 3 | R145: 2 | S145: River- Trees | T145: [Select] | U145: Yes | V145: Normal | W145: No | X145: No | Y145: [Select]
D146: [Select] | H146: =$I$9 -> BTR-Regions | I146: =$I$10 -> The Forge | J146: The Forge - Apts | L146: South | M146: Apartment | N146: 205S | O146: 689 | P146: 2 Bed | Q146: 2 | R146: 2 | S146: Courtyard | T146: [Select] | U146: No | V146: Normal | W146: No | X146: No | Y146: [Select]
D147: [Select] | H147: =$I$9 -> BTR-Regions | I147: =$I$10 -> The Forge | J147: The Forge - Apts | L147: South | M147: Apartment | N147: 206S | O147: 474 | P147: 1 Bed | Q147: 1 | R147: 2 | S147: Courtyard | T147: [Select] | U147: No | V147: Normal | W147: No | X147: No | Y147: [Select]
D148: [Select] | H148: =$I$9 -> BTR-Regions | I148: =$I$10 -> The Forge | J148: The Forge - Apts | L148: South | M148: Apartment | N148: 207S | O148: 624 | P148: 2 Bed | Q148: 2 | R148: 2 | S148: Courtyard | T148: [Select] | U148: No | V148: Normal | W148: No | X148: No | Y148: [Select]
D149: [Select] | H149: =$I$9 -> BTR-Regions | I149: =$I$10 -> The Forge | J149: The Forge - Apts | L149: South | M149: Apartment | N149: 301S | O149: 624 | P149: 2 Bed | Q149: 2 | R149: 3 | S149: River- Trees | T149: [Select] | U149: Yes | V149: Normal | W149: No | X149: No | Y149: [Select]
D150: [Select] | H150: =$I$9 -> BTR-Regions | I150: =$I$10 -> The Forge | J150: The Forge - Apts | L150: South | M150: Apartment | N150: 302S | O150: 603 | P150: 2 Bed | Q150: 2 | R150: 3 | S150: River- Trees | T150: [Select] | U150: Yes | V150: Normal | W150: No | X150: No | Y150: [Select]
... D190: [Select] | H190: =$I$9 -> BTR-Regions | I190: =$I$10 -> The Forge | J190: The Forge - Apts | L190: South | M190: Apartment | N190: 807S | O190: 624 | P190: 2 Bed | Q190: 2 | R190: 8 | S190: Cityscape | T190: [Select] | U190: No | V190: Normal | W190: No | X190: No | Y190: [Select]
D191: [Select] | H191: =$I$9 -> BTR-Regions | I191: =$I$10 -> The Forge | J191: The Forge - Apts | L191: West | M191: Apartment | N191: 1W | O191: 689 | P191: 2 Bed | Q191: 2 | R191: Ground | S191: Pottery Lane | T191: [Select] | U191: No | V191: Normal | W191: No | X191: No | Y191: [Select]
D192: [Select] | H192: =$I$9 -> BTR-Regions | I192: =$I$10 -> The Forge | J192: The Forge - Apts | L192: West | M192: Apartment | N192: 2W | O192: 463 | P192: 1 Bed | Q192: 1 | R192: Ground | S192: Courtyard | T192: [Select] | U192: No | V192: Normal | W192: Resticted - 25 | X192: No | Y192: [Select]
D193: [Select] | H193: =$I$9 -> BTR-Regions | I193: =$I$10 -> The Forge | J193: The Forge - Apts | L193: West | M193: Apartment | N193: 3W | O193: 549 | P193: 1 Bed | Q193: 1 | R193: Ground | S193: Courtyard | T193: [Select] | U193: No | V193: Normal | W193: Resticted - 25 | X193: No | Y193: [Select]
D194: [Select] | H194: =$I$9 -> BTR-Regions | I194: =$I$10 -> The Forge | J194: The Forge - Apts | L194: West | M194: Apartment | N194: 4W | O194: 484 | P194: 1 Bed | Q194: 1 | R194: Ground | S194: Fence | T194: [Select] | U194: No | V194: Normal | W194: No | X194: No | Y194: [Select]
D195: [Select] | H195: =$I$9 -> BTR-Regions | I195: =$I$10 -> The Forge | J195: The Forge - Apts | L195: West | M195: Apartment | N195: 5W | O195: 678 | P195: 2 Bed | Q195: 2 | R195: Ground | S195: Fence | T195: [Select] | U195: No | V195: External Access | W195: Resticted - 25 | X195: No | Y195: [Select]
D196: [Select] | H196: =$I$9 -> BTR-Regions | I196: =$I$10 -> The Forge | J196: The Forge - Apts | L196: West | M196: Apartment | N196: 6W | O196: 743 | P196: 2 Bed | Q196: 2 | R196: Ground | S196: Courtyard | T196: [Select] | U196: No | V196: Normal | W196: No | X196: No | Y196: [Select]
D197: [Select] | H197: =$I$9 -> BTR-Regions | I197: =$I$10 -> The Forge | J197: The Forge - Apts | L197: West | M197: Apartment | N197: 7W | O197: 710 | P197: 2 Bed | Q197: 2 | R197: Ground | S197: Courtyard | T197: [Select] | U197: No | V197: External Access | W197: No | X197: No | Y197: [Select]
D198: [Select] | H198: =$I$9 -> BTR-Regions | I198: =$I$10 -> The Forge | J198: The Forge - Apts | L198: West | M198: Apartment | N198: 8W | O198: 667 | P198: 2 Bed | Q198: 2 | R198: Ground | S198: Courtyard | T198: [Select] | U198: No | V198: External Access | W198: No | X198: No | Y198: [Select]
D199: [Select] | H199: =$I$9 -> BTR-Regions | I199: =$I$10 -> The Forge | J199: The Forge - Apts | L199: West | M199: Apartment | N199: 9W | O199: 463 | P199: 1 Bed | Q199: 1 | R199: Ground | S199: Fence | T199: [Select] | U199: No | V199: External Access | W199: Resticted - 25 | X199: No | Y199: [Select]
D200: [Select] | H200: =$I$9 -> BTR-Regions | I200: =$I$10 -> The Forge | J200: The Forge - Apts | L200: West | M200: Apartment | N200: 10W | O200: 797 | P200: 3 Bed | Q200: 2 | R200: Ground | S200: Fence | T200: [Select] | U200: No | V200: Normal | W200: Resticted - 25 | X200: No | Y200: [Select]
D201: [Select] | H201: =$I$9 -> BTR-Regions | I201: =$I$10 -> The Forge | J201: The Forge - Apts | L201: West | M201: Apartment | N201: 11W | O201: 635 | P201: 2 Bed | Q201: 2 | R201: Ground | S201: Fence | T201: [Select] | U201: No | V201: Normal | W201: No | X201: No | Y201: [Select]
D202: [Select] | H202: =$I$9 -> BTR-Regions | I202: =$I$10 -> The Forge | J202: The Forge - Apts | L202: West | M202: Apartment | N202: 101W | O202: 689 | P202: 2 Bed | Q202: 2 | R202: 1 | S202: Pottery Lane | T202: [Select] | U202: No | V202: Normal | W202: No | X202: No | Y202: [Select]
D203: [Select] | H203: =$I$9 -> BTR-Regions | I203: =$I$10 -> The Forge | J203: The Forge - Apts | L203: West | M203: Apartment | N203: 102W | O203: 495 | P203: 1 Bed | Q203: 1 | R203: 1 | S203: Courtyard | T203: [Select] | U203: No | V203: Normal | W203: No | X203: No | Y203: [Select]
D204: [Select] | H204: =$I$9 -> BTR-Regions | I204: =$I$10 -> The Forge | J204: The Forge - Apts | L204: West | M204: Apartment | N204: 103W | O204: 657 | P204: 2 Bed | Q204: 2 | R204: 1 | S204: Courtyard | T204: [Select] | U204: No | V204: Normal | W204: No | X204: No | Y204: [Select]
D205: [Select] | H205: =$I$9 -> BTR-Regions | I205: =$I$10 -> The Forge | J205: The Forge - Apts | L205: West | M205: Apartment | N205: 104W | O205: 657 | P205: 2 Bed | Q205: 2 | R205: 1 | S205: Railway Bridge | T205: [Select] | U205: No | V205: Normal | W205: No | X205: No | Y205: [Select]
D206: [Select] | H206: =$I$9 -> BTR-Regions | I206: =$I$10 -> The Forge | J206: The Forge - Apts | L206: West | M206: Apartment | N206: 105W | O206: 678 | P206: 2 Bed | Q206: 2 | R206: 1 | S206: Railway Bridge | T206: [Select] | U206: No | V206: Normal | W206: No | X206: No | Y206: [Select]
D207: [Select] | H207: =$I$9 -> BTR-Regions | I207: =$I$10 -> The Forge | J207: The Forge - Apts | L207: West | M207: Apartment | N207: 106W | O207: 506 | P207: 1 Bed | Q207: 1 | R207: 1 | S207: Railway Bridge | T207: [Select] | U207: No | V207: Normal | W207: No | X207: No | Y207: [Select]
D208: [Select] | H208: =$I$9 -> BTR-Regions | I208: =$I$10 -> The Forge | J208: The Forge - Apts | L208: West | M208: Apartment | N208: 107W | O208: 474 | P208: 1 Bed | Q208: 1 | R208: 1 | S208: Pottery Lane | T208: [Select] | U208: No | V208: Normal | W208: No | X208: No | Y208: [Select]
D209: [Select] | H209: =$I$9 -> BTR-Regions | I209: =$I$10 -> The Forge | J209: The Forge - Apts | L209: West | M209: Apartment | N209: 108W | O209: 775 | P209: 2 Bed | Q209: 2 | R209: 1 | S209: Courtyard | T209: [Select] | U209: No | V209: Normal | W209: No | X209: No | Y209: [Select]
D210: [Select] | H210: =$I$9 -> BTR-Regions | I210: =$I$10 -> The Forge | J210: The Forge - Apts | L210: West | M210: Apartment | N210: 109W | O210: 657 | P210: 2 Bed | Q210: 2 | R210: 1 | S210: Courtyard | T210: [Select] | U210: No | V210: Normal | W210: No | X210: No | Y210: [Select]
D211: [Select] | H211: =$I$9 -> BTR-Regions | I211: =$I$10 -> The Forge | J211: The Forge - Apts | L211: West | M211: Apartment | N211: 110W | O211: 689 | P211: 2 Bed | Q211: 2 | R211: 1 | S211: Courtyard | T211: [Select] | U211: No | V211: Normal | W211: No | X211: No | Y211: [Select]
D212: [Select] | H212: =$I$9 -> BTR-Regions | I212: =$I$10 -> The Forge | J212: The Forge - Apts | L212: West | M212: Apartment | N212: 111W | O212: 667 | P212: 2 Bed | Q212: 2 | R212: 1 | S212: Courtyard | T212: [Select] | U212: No | V212: Normal | W212: No | X212: No | Y212: [Select]
D213: [Select] | H213: =$I$9 -> BTR-Regions | I213: =$I$10 -> The Forge | J213: The Forge - Apts | L213: West | M213: Apartment | N213: 112W | O213: 527 | P213: 1 Bed | Q213: 1 | R213: 1 | S213: Railway Bridge | T213: [Select] | U213: No | V213: Normal | W213: No | X213: No | Y213: [Select]
... D303: [Select] | H303: =$I$9 -> BTR-Regions | I303: =$I$10 -> The Forge | J303: The Forge - Apts | L303: West | M303: Apartment | N303: 809W | O303: 840 | P303: 3 Bed | Q303: 2 | R303: 8 | S303: Railway Bridge - Higher | T303: [Select] | U303: No | V303: Normal | W303: No | X303: No | Y303: [Select]
D304: [Select] | H304: =$I$9 -> BTR-Regions | I304: =$I$10 -> The Forge
D305: [Select] | H305: =$I$9 -> BTR-Regions | I305: =$I$10 -> The Forge
D306: [Select] | H306: =$I$9 -> BTR-Regions | I306: =$I$10 -> The Forge
D307: [Select] | H307: =$I$9 -> BTR-Regions | I307: =$I$10 -> The Forge
D308: [Select] | H308: =$I$9 -> BTR-Regions | I308: =$I$10 -> The Forge
D309: [Select] | H309: =$I$9 -> BTR-Regions | I309: =$I$10 -> The Forge
D310: [Select] | H310: =$I$9 -> BTR-Regions | I310: =$I$10 -> The Forge
D311: [Select] | H311: =$I$9 -> BTR-Regions | I311: =$I$10 -> The Forge
D312: [Select] | H312: =$I$9 -> BTR-Regions | I312: =$I$10 -> The Forge
D313: [Select] | H313: =$I$9 -> BTR-Regions | I313: =$I$10 -> The Forge
D314: [Select] | H314: =$I$9 -> BTR-Regions | I314: =$I$10 -> The Forge
D315: [Select] | H315: =$I$9 -> BTR-Regions | I315: =$I$10 -> The Forge
... D620: [Select] | H620: =$I$9 -> BTR-Regions | I620: =$I$10 -> The Forge

Sheet 2. GRI Pricing Inputs
C3: 2. GRAINGER PRICING INPUTS | AL3: METHODOLOGY
C5: 0. Accomodation information
C7: Home Type | D7: [Select] | E7: Apartment
C9: Block Name | D9: [Select] | E9: North | F9: South | G9: West
C11: 1. Base price
C13: The base pricing for each bed type based on comparable evidence of the local market.
C15: Bedroom | D15: [Select] | E15: ='1. Accomodation'!L9 -> 1 Bed | F15: ='1. Accomodation'!L10 -> 2 Bed | G15: ='1. Accomodation'!L11 -> 3 Bed | H15: ='1. Accomodation'!L12 -> 0 | I15: ='1. Accomodation'!L13 -> 0 | J15: ='1. Accomodation'!M13 -> 0
C16: Base Price (£pm) | E16: 845 | F16: 1110 | G16: 1485
C18: 2. Bath premium
C20: The premium to the base pricing (assumes a standard X bed homes) to reflect either the discount for only have 1 bathroom or the premium for having two.
C22: Bath | D22: [Select] | E22: 1 | F22: 2 | G22: 3
C23: Bath Premium | E23: 0 | F23: 0 | G23: 0
C25: 3. Size premium by range
C27: The premium to the base pricing (assumes a standard X bed homes) to reflect units which are above or below the standard size.
C29: Bedroom | D29: [Select] | E29: 1 Bed | F29: 2 Bed | G29: 3 Bed | H29: [Select] | I29: [Select] | J29: [Select] | K29: [Select] | L29: [Select] | M29: [Select] | N29: [Select]
C30: Average size (sqft) | E30: =IFERROR(INDEX('1. Accomodation'!$F$9:$F$11,MATCH('2. GRI Pricing Inputs'!E$29,'1. Accomodation'!$D$9:$D$11,0)),0) -> 0 | F30: =IFERROR(INDEX('1. Accomodation'!$F$9:$F$11,MATCH('2. GRI Pricing Inputs'!F$29,'1. Accomodation'!$D$9:$D$11,0)),0) -> 0 | G30: =IFERROR(INDEX('1. Accomodation'!$F$9:$F$11,MATCH('2. GRI Pricing Inputs'!G$29,'1. Accomodation'!$D$9:$D$11,0)),0) -> 0 | H30: =IFERROR(INDEX('1. Accomodation'!$F$9:$F$11,MATCH('2. GRI Pricing Inputs'!H$29,'1. Accomodation'!$D$9:$D$11,0)),0) -> 0 | I30: =IFERROR(INDEX('1. Accomodation'!$F$9:$F$11,MATCH('2. GRI Pricing Inputs'!I$29,'1. Accomodation'!$D$9:$D$11,0)),0) -> 0 | J30: =IFERROR(INDEX('1. Accomodation'!$F$9:$F$11,MATCH('2. GRI Pricing Inputs'!J$29,'1. Accomodation'!$D$9:$D$11,0)),0) -> 0
C32: Size premium | D32: 1 | F32: 2 | H32: 3 | J32: 4 | L32: 5 | N32: 6 | P32: 7 | R32: 8 | T32: 9 | V32: 10 | X32: 11 | Z32: 12 | AB32: 13 | AD32: 14 | AF32: 15
D33: 484 | E33: 484 | F33: 495 | G33: 506 | H33: 517 | I33: 527 | J33: 538 | K33: 553 | L33: 560 | M33: 570 | N33: 603 | O33: 614 | P33: 623 | Q33: 636 | R33: 646 | S33: 657 | T33: 667 | U33: 667 | V33: 678 | W33: 678 | X33: 689 | Y33: 689 | Z33: 700 | AA33: 701 | AB33: 818 | AC33: 818 | AD33: 829 | AE33: 829 | AF33: 840 | AG33: 840
C34: 1 Bed | D34: 10 | F34: 15 | H34: 20 | J34: 25 | L34: 35
C35: 2 Bed | N35: 5 | P35: 10 | R35: 20 | T35: 30 | V35: 40 | X35: 65 | Z35: 70
C36: 3 Bed | AB36: 50 | AD36: 60 | AF36: 70
C37: [Select]
C38: [Select]
C39: [Select]
C41: 4. Floor premium
C43: A discount or premium to the base price is dependent on what floor the unit is located on (typical increments are between £5 - £20 per floor).
C45: Floor | D45: [Select] | E45: Ground | F45: 1 | G45: 2 | H45: 3 | I45: 4 | J45: 5 | K45: 6 | L45: 7 | M45: 8
C46: Floor premium | E46: 0 | F46: 30 | G46: 40 | H46: 50 | I46: 70 | J46: 70 | K46: 80 | L46: 90 | M46: 100
C49: 5. Aspect premium
C51: The premium to the base pricing is dependent on which direction the unit is facing (for e.g. south being the best).
C53: Aspect | D53: [Select] | E53: Fence | F53: Forth Banks | G53: Forth Banks/Pottery Lane | H53: Pottery Lane | I53: Railway Bridge | J53: Railway Bridge - Mid | K53: Courtyard | L53: River- Trees | M53: Railway Bridge - Higher | N53: Cityscape | O53: Forth Banks - Partial | P53: River - Partial | Q53: Courtyard - dual | R53: River- full
C54: Aspect premium | E54: 0 | F54: 5 | G54: 10 | H54: 10 | I54: 10 | J54: 20 | K54: 25 | L54: 30 | M54: 30 | N54: 35 | O54: 40 | P54: 45 | Q54: 55 | R54: 60
C56: 6. Storage premium
C58: The premium to the base pricing is dependent on the storage offered in the units.
C60: Storage | D60: [Select] | E60: Open Storage | F60: Traditional Wardrobe
C61: Storage premium | E61: 5 | F61: 0
C63: 7. Balcony premium
C65: A premium to base to reflect if there is a balcony present. Price is further broken down as below.
C67: Balcony | D67: [Select] | E67: Yes | F67: Recessed - Glass | G67: Recessed - Solid | H67: No
C68: Balcony premium | E68: 40 | F68: 20 | G68: 10 | H68: 0
C70: 8. Amenity premium
C72: The premium to the base pricing is dependent on the amenity offered in the portfolio.
C74: Amenity | D74: [Select] | E74: Gym | F74: Dining | G74: Lounge | H74: Yoga | I74: Concierge | J74: Outdoor space | K74: Internet | AI74: All
C75: Amenity premium | E75: 15 | F75: 0 | G75: 15 | H75: 0 | I75: 15 | J75: 0 | K75: 25 | AI75: =SUM(E75:AH75) -> 70
C78: 9. Character #1
C80: The premium to the base pricing is dependent on the character of the building.
C82: Character | D82: [Select] | E82: Small | F82: External Access | G82: Normal
C83: Window Premium | E83: -50 | F83: 20 | G83: 0
C85: 10. Character #2
C87: The premium to the base pricing is dependent on the character of the building.
C89: Character | D89: [Select] | E89: Resticted - 25 | F89: Restricted- 50 | G89: Restricted - 75 | H89: No
C90: Restricted Light | E90: -25 | F90: -50 | G90: -75 | H90: 0 | AJ90: =SUM(E90:J90)='1. Accomodation'!E14 -> FALSE
C93: 11. Character #3
C95: The premium to the base pricing is dependent on the character of the building.
C97: Character | D97: [Select]
C100: 12. Character #4
C102: The premium to the base pricing is dependent on the character of the building.
C104: Character | D104: [Select]
C105: Character premium #4
C108: 13. Growth rate
C110: Rents are assumed to grow at the below rate per annum stipulated by Asset Manager. | AL110: Per CBRE/ Budget assumption
D113: PRS | E113: Commercial | F113: Car Parking
C114: Business Plan Growth Rate | D114: 0.04 | E114: 0.02 | F114: 0
C116: 14. Car Park
C118: Units | D118: ='1. Accomodation'!M16 -> 0 | AL118: Per CBRE
C119: Base price | D119: 10

Sheet 3. GRI Pricing
C3: 3. GRAINGER PRICING SCHEDULE
C5: Bedroom | D5: ='1. Accomodation'!N20 -> Door Number | E5: Av. Size (sqft) | F5: Launch Rent (pcm) | G5: Launch Rent (pa) | H5: Launch Rent (psf) | AB5: =C5 -> Bedroom | AC5: =AC16 -> 45230 | AD5: =AD16 -> 45260 | AE5: =AE16 -> 45291 | AF5: =AF16 -> 45322 | AG5: =AG16 -> 45351 | AH5: =AH16 -> 45382 | AI5: =AI16 -> 45412 | AJ5: =AJ16 -> 45443 | ... AO5: =AO16 -> 45596
C6: ='1. Accomodation'!L9 -> 1 Bed | D6: ='1. Accomodation'!M9 -> 78 | E6: ='1. Accomodation'!N9 -> 503.5641 | F6: =IFERROR(AVERAGEIF($D$17:$D$616,$C6,$Y$17:$Y$616),0) -> 999.80769 | G6: =F6*12 -> 11997.692 | H6: =IFERROR(G6/E6,0) -> 23.825551 | AB6: =C6 -> 1 Bed | AC6: =IFERROR(AVERAGEIF($D$17:$D$616,$C6,AC$17:AC$616),0) -> 1003.1437 | AD6: =IFERROR(AVERAGEIF($D$17:$D$616,$C6,AD$17:AD$616),0) -> 1006.3827 | AE6: =IFERROR(AVERAGEIF($D$17:$D$616,$C6,AE$17:AE$616),0) -> 1009.7406 | AF6: =IFERROR(AVERAGEIF($D$17:$D$616,$C6,AF$17:AF$616),0) -> 1013.1097 | AG6: =IFERROR(AVERAGEIF($D$17:$D$616,$C6,AG$17:AG$616),0) -> 1016.2716 | AH6: =IFERROR(AVERAGEIF($D$17:$D$616,$C6,AH$17:AH$616),0) -> 1019.6626 | AI6: =IFERROR(AVERAGEIF($D$17:$D$616,$C6,AI$17:AI$616),0) -> 1022.9549 | AJ6: =IFERROR(AVERAGEIF($D$17:$D$616,$C6,AJ$17:AJ$616),0) -> 1026.3681 | ... AO6: =IFERROR(AVERAGEIF($D$17:$D$616,$C6,AO$17:AO$616),0) -> 1043.3815
C7: ='1. Accomodation'!L10 -> 2 Bed | D7: ='1. Accomodation'!M10 -> 179 | E7: ='1. Accomodation'!N10 -> 652.34637 | F7: =IFERROR(AVERAGEIF($D$17:$D$616,$C7,$Y$17:$Y$616),0) -> 1293.4358 | G7: =F7*12 -> 15521.229 | H7: =IFERROR(G7/E7,0) -> 23.792926 | AB7: =C7 -> 2 Bed | AC7: =IFERROR(AVERAGEIF($D$17:$D$616,$C7,AC$17:AC$616),0) -> 1297.7515 | AD7: =IFERROR(AVERAGEIF($D$17:$D$616,$C7,AD$17:AD$616),0) -> 1301.9417 | AE7: =IFERROR(AVERAGEIF($D$17:$D$616,$C7,AE$17:AE$616),0) -> 1306.2858 | AF7: =IFERROR(AVERAGEIF($D$17:$D$616,$C7,AF$17:AF$616),0) -> 1310.6444 | AG7: =IFERROR(AVERAGEIF($D$17:$D$616,$C7,AG$17:AG$616),0) -> 1314.7349 | AH7: =IFERROR(AVERAGEIF($D$17:$D$616,$C7,AH$17:AH$616),0) -> 1319.1217 | AI7: =IFERROR(AVERAGEIF($D$17:$D$616,$C7,AI$17:AI$616),0) -> 1323.3809 | AJ7: =IFERROR(AVERAGEIF($D$17:$D$616,$C7,AJ$17:AJ$616),0) -> 1327.7965 | ... AO7: =IFERROR(AVERAGEIF($D$17:$D$616,$C7,AO$17:AO$616),0) -> 1349.8066
C8: ='1. Accomodation'!L11 -> 3 Bed | D8: ='1. Accomodation'!M11 -> 26 | E8: ='1. Accomodation'!N11 -> 823.19231 | F8: =IFERROR(AVERAGEIF($D$17:$D$616,$C8,$Y$17:$Y$616),0) -> 1698.6538 | G8: =F8*12 -> 20383.846 | H8: =IFERROR(G8/E8,0) -> 24.761949 | AB8: =C8 -> 3 Bed | AC8: =IFERROR(AVERAGEIF($D$17:$D$616,$C8,AC$17:AC$616),0) -> 1704.3216 | AD8: =IFERROR(AVERAGEIF($D$17:$D$616,$C8,AD$17:AD$616),0) -> 1709.8246 | AE8: =IFERROR(AVERAGEIF($D$17:$D$616,$C8,AE$17:AE$616),0) -> 1715.5296 | AF8: =IFERROR(AVERAGEIF($D$17:$D$616,$C8,AF$17:AF$616),0) -> 1721.2537 | AG8: =IFERROR(AVERAGEIF($D$17:$D$616,$C8,AG$17:AG$616),0) -> 1726.6258 | AH8: =IFERROR(AVERAGEIF($D$17:$D$616,$C8,AH$17:AH$616),0) -> 1732.3869 | AI8: =IFERROR(AVERAGEIF($D$17:$D$616,$C8,AI$17:AI$616),0) -> 1737.9805 | AJ8: =IFERROR(AVERAGEIF($D$17:$D$616,$C8,AJ$17:AJ$616),0) -> 1743.7795 | ... AO8: =IFERROR(AVERAGEIF($D$17:$D$616,$C8,AO$17:AO$616),0) -> 1772.685
C9: ='1. Accomodation'!L12 -> 0 | D9: ='1. Accomodation'!M12 -> 0 | E9: ='1. Accomodation'!N12 -> - | F9: =IFERROR(AVERAGEIF($D$17:$D$616,$C9,$Y$17:$Y$616),0) -> 0 | G9: =F9*12 -> 0 | H9: =IFERROR(G9/E9,0) -> 0 | AB9: =C9 -> 0 | AC9: =IFERROR(AVERAGEIF($D$17:$D$616,$C9,AC$17:AC$616),0) -> 0 | AD9: =IFERROR(AVERAGEIF($D$17:$D$616,$C9,AD$17:AD$616),0) -> 0 | AE9: =IFERROR(AVERAGEIF($D$17:$D$616,$C9,AE$17:AE$616),0) -> 0 | AF9: =IFERROR(AVERAGEIF($D$17:$D$616,$C9,AF$17:AF$616),0) -> 0 | AG9: =IFERROR(AVERAGEIF($D$17:$D$616,$C9,AG$17:AG$616),0) -> 0 | AH9: =IFERROR(AVERAGEIF($D$17:$D$616,$C9,AH$17:AH$616),0) -> 0 | AI9: =IFERROR(AVERAGEIF($D$17:$D$616,$C9,AI$17:AI$616),0) -> 0 | AJ9: =IFERROR(AVERAGEIF($D$17:$D$616,$C9,AJ$17:AJ$616),0) -> 0 | ... AO9: =IFERROR(AVERAGEIF($D$17:$D$616,$C9,AO$17:AO$616),0) -> 0
C10: ='1. Accomodation'!L13 -> 0 | D10: ='1. Accomodation'!M13 -> 0 | E10: ='1. Accomodation'!N13 -> - | F10: =IFERROR(AVERAGEIF($D$17:$D$616,$C10,$Y$17:$Y$616),0) -> 0 | G10: =F10*12 -> 0 | H10: =IFERROR(G10/E10,0) -> 0 | AB10: =C10 -> 0 | AC10: =IFERROR(AVERAGEIF($D$17:$D$616,$C10,AC$17:AC$616),0) -> 0 | AD10: =IFERROR(AVERAGEIF($D$17:$D$616,$C10,AD$17:AD$616),0) -> 0 | AE10: =IFERROR(AVERAGEIF($D$17:$D$616,$C10,AE$17:AE$616),0) -> 0 | AF10: =IFERROR(AVERAGEIF($D$17:$D$616,$C10,AF$17:AF$616),0) -> 0 | AG10: =IFERROR(AVERAGEIF($D$17:$D$616,$C10,AG$17:AG$616),0) -> 0 | AH10: =IFERROR(AVERAGEIF($D$17:$D$616,$C10,AH$17:AH$616),0) -> 0 | AI10: =IFERROR(AVERAGEIF($D$17:$D$616,$C10,AI$17:AI$616),0) -> 0 | AJ10: =IFERROR(AVERAGEIF($D$17:$D$616,$C10,AJ$17:AJ$616),0) -> 0 | ... AO10: =IFERROR(AVERAGEIF($D$17:$D$616,$C10,AO$17:AO$616),0) -> 0
C11: ='1. Accomodation'!L14 -> 0 | D11: ='1. Accomodation'!M14 -> 0 | E11: ='1. Accomodation'!N14 -> - | F11: =IFERROR(AVERAGEIF($D$17:$D$616,$C11,$Y$17:$Y$616),0) -> 0 | G11: =F11*12 -> 0 | H11: =IFERROR(G11/E11,0) -> 0 | AB11: =C11 -> 0 | AC11: =IFERROR(AVERAGEIF($D$17:$D$616,$C11,AC$17:AC$616),0) -> 0 | AD11: =IFERROR(AVERAGEIF($D$17:$D$616,$C11,AD$17:AD$616),0) -> 0 | AE11: =IFERROR(AVERAGEIF($D$17:$D$616,$C11,AE$17:AE$616),0) -> 0 | AF11: =IFERROR(AVERAGEIF($D$17:$D$616,$C11,AF$17:AF$616),0) -> 0 | AG11: =IFERROR(AVERAGEIF($D$17:$D$616,$C11,AG$17:AG$616),0) -> 0 | AH11: =IFERROR(AVERAGEIF($D$17:$D$616,$C11,AH$17:AH$616),0) -> 0 | AI11: =IFERROR(AVERAGEIF($D$17:$D$616,$C11,AI$17:AI$616),0) -> 0 | AJ11: =IFERROR(AVERAGEIF($D$17:$D$616,$C11,AJ$17:AJ$616),0) -> 0 | ... AO11: =IFERROR(AVERAGEIF($D$17:$D$616,$C11,AO$17:AO$616),0) -> 0
C12: AVERAGE | D12: ='1. Accomodation'!M15 -> 283 | E12: =IFERROR('1. Accomodation'!N15,0) -> 627.03534 | F12: =IFERROR(G12/12,0) -> 1249.735 | G12: =IFERROR(Y617/$D$12,0) -> 14996.82 | H12: =IFERROR(G12/$E$12,0) -> 23.917025 | AB12: =C12 -> AVERAGE | AC12: =IFERROR(AVERAGEIF($D$17:$D$616,$C12,AC$17:AC$616),0) -> 0 | AD12: =IFERROR(AVERAGEIF($D$17:$D$616,$C12,AD$17:AD$616),0) -> 0 | AE12: =IFERROR(AVERAGEIF($D$17:$D$616,$C12,AE$17:AE$616),0) -> 0 | AF12: =IFERROR(AVERAGEIF($D$17:$D$616,$C12,AF$17:AF$616),0) -> 0 | AG12: =IFERROR(AVERAGEIF($D$17:$D$616,$C12,AG$17:AG$616),0) -> 0 | AH12: =IFERROR(AVERAGEIF($D$17:$D$616,$C12,AH$17:AH$616),0) -> 0 | AI12: =IFERROR(AVERAGEIF($D$17:$D$616,$C12,AI$17:AI$616),0) -> 0 | AJ12: =IFERROR(AVERAGEIF($D$17:$D$616,$C12,AJ$17:AJ$616),0) -> 0 | ... AO12: =IFERROR(AVERAGEIF($D$17:$D$616,$C12,AO$17:AO$616),0) -> 0
C13: Car park | D13: ='1. Accomodation'!M16 -> 0 | F13: ='2. GRI Pricing Inputs'!D119 -> 10 | G13: =F13*12 -> 120 | AB13: =C13 -> Car park | AC13: =IFERROR(AVERAGEIF($D$17:$D$616,$C13,AC$17:AC$616),0) -> 0 | AD13: =IFERROR(AVERAGEIF($D$17:$D$616,$C13,AD$17:AD$616),0) -> 0 | AE13: =IFERROR(AVERAGEIF($D$17:$D$616,$C13,AE$17:AE$616),0) -> 0 | AF13: =IFERROR(AVERAGEIF($D$17:$D$616,$C13,AF$17:AF$616),0) -> 0 | AG13: =IFERROR(AVERAGEIF($D$17:$D$616,$C13,AG$17:AG$616),0) -> 0 | AH13: =IFERROR(AVERAGEIF($D$17:$D$616,$C13,AH$17:AH$616),0) -> 0 | AI13: =IFERROR(AVERAGEIF($D$17:$D$616,$C13,AI$17:AI$616),0) -> 0 | AJ13: =IFERROR(AVERAGEIF($D$17:$D$616,$C13,AJ$17:AJ$616),0) -> 0 | ... AO13: =IFERROR(AVERAGEIF($D$17:$D$616,$C13,AO$17:AO$616),0) -> 0
C15: Accomodation Attributes | K15: GRI PRICING FRAMEWORK | AB15: 45199 | AC15: Monthly rent increase over 12 months (using Grainger growth rate)
C16: ='1. Accomodation'!N20 -> Door Number | D16: ='1. Accomodation'!P20 -> Bedroom | E16: ='1. Accomodation'!Q20 -> Bath | F16: ='1. Accomodation'!O20 -> Size (sq.ft) | G16: ='1. Accomodation'!R20 -> Floor | H16: ='1. Accomodation'!S20 -> Aspect | K16: ='2. GRI Pricing Inputs'!C16 -> Base Price (£pm) | L16: ='2. GRI Pricing Inputs'!C23 -> Bath Premium | M16: Area Range | N16: ='2. GRI Pricing Inputs'!C32 -> Size premium | O16: ='2. GRI Pricing Inputs'!C46 -> Floor premium | P16: ='2. GRI Pricing Inputs'!C54 -> Aspect premium | Q16: ='2. GRI Pricing Inputs'!C61 -> Storage premium | R16: ='2. GRI Pricing Inputs'!C68 -> Balcony premium | S16: ='2. GRI Pricing Inputs'!C75 -> Amenity premium | T16: ='2. GRI Pricing Inputs'!C83 -> Window Premium | U16: ='2. GRI Pricing Inputs'!C90 -> Restricted Light | V16: ='2. GRI Pricing Inputs'!C98 -> 0 | W16: ='2. GRI Pricing Inputs'!C105 -> Character premium #4 | X16: Manual Adjustment (must provide reason) | Y16: Proposed Rent (pcm) | AC16: =EOMONTH(AB15,1) -> 45230 | AD16: =EOMONTH(AC16,1) -> 45260 | AE16: =EOMONTH(AD16,1) -> 45291 | AF16: =EOMONTH(AE16,1) -> 45322 | AG16: =EOMONTH(AF16,1) -> 45351 | AH16: =EOMONTH(AG16,1) -> 45382 | AI16: =EOMONTH(AH16,1) -> 45412 | AJ16: =EOMONTH(AI16,1) -> 45443 | AK16: =EOMONTH(AJ16,1) -> 45473 | ... AO16: =EOMONTH(AN16,1) -> 45596
C17: ='1. Accomodation'!N21 -> 101N | D17: ='1. Accomodation'!P21 -> 1 Bed | E17: ='1. Accomodation'!Q21 -> 1 | F17: ='1. Accomodation'!O21 -> 484 | G17: ='1. Accomodation'!R21 -> Ground | H17: ='1. Accomodation'!S21 -> Courtyard | K17: =IFERROR(INDEX('2. GRI Pricing Inputs'!$C$15:$AI$16,MATCH($K$16,'2. GRI Pricing Inputs'!$C$15:$C$16,0),MATCH(D17,'2. GRI Pricing Inputs'!$C$15:$AI$15,0)),0) -> 845 | L17: =IFERROR(INDEX('2. GRI Pricing Inputs'!$C$22:$AI$23,MATCH($L$16,'2. GRI Pricing Inputs'!$C$22:$C$23,0),MATCH(E17,'2. GRI Pricing Inputs'!$C$22:$AI$22,0)),0) -> 0 | M17: =IF(AND('3. GRI Pricing'!$F17>='2. GRI Pricing Inputs'!$D$33,'3. GRI Pricing'!$F17<='2. GRI Pricing Inputs'!$E$33),'2. GRI Pricing Inputs'!$D$32,IF(AND('3. GRI Pricing'!$F17>='2. GRI Pricing Inputs'!$F$33,'3. GRI Pricing'!$F17<='2. GRI Pricing Inputs'!$G$33),'2. GRI Pricing Inputs'!$F$32,IF(AND('3. GRI Pricing'!$F17>='2. GRI Pricing Inputs'!$H$33,'3. GRI Pricing'!$F17<='2. GRI Pricing Inputs'!$I$33),'2. GRI Pricing Inputs'!$H$32,IF(AND('3. GRI Pricing'!$F17>='2. GRI Pricing Inputs'!$J$33,'3. GRI Pricing'!$F17<='2. GRI Pricing Inputs'!$K$33),'2. GRI Pricing Inputs'!$J$32,IF(AND('3. GRI Pricing'!$F17>='2. GRI Pricing Inputs'!$L$33,'3. GRI Pricing'!$F17<='2. GRI Pricing Inputs'!$M$33),'2. GRI Pricing Inputs'!$L$32,IF(AND('3. GRI Pricing'!$F17>='2. GRI Pricing Inputs'!$N$33,'3. GRI Pricing'!$F17<='2. GRI Pricing Inputs'!$O$33),'2. GRI Pricing Inputs'!$N$32,IF(AND('3. GRI Pricing'!$F17>='2. GRI Pricing Inputs'!$P$33,'3. GRI Pricing'!$F17<='2. GRI Pricing Inputs'!$Q$33),'2. GRI Pricing Inputs'!$P$32,IF(AND('3. GRI Pricing'!$F17>='2. GRI Pricing Inputs'!$R$33,'3. GRI Pricing'!$F17<='2. GRI Pricing Inputs'!$S$33),'2. GRI Pricing Inputs'!$R$32,IF(AND('3. GRI Pricing'!$F17>='2. GRI Pricing Inputs'!$T$33,'3. GRI Pricing'!$F17<='2. GRI Pricing Inputs'!$U$33),'2. GRI Pricing Inputs'!$T$32,IF(AND('3. GRI Pricing'!$F17>='2. GRI Pricing Inputs'!$V$33,'3. GRI Pricing'!$F17<='2. GRI Pricing Inputs'!$W$33),'2. GRI Pricing Inputs'!$V$32,IF(AND('3. GRI Pricing'!$F17>='2. GRI Pricing Inputs'!$X$33,'3. GRI Pricing'!$F17<='2. GRI Pricing Inputs'!$Y$33),'2. GRI Pricing Inputs'!$X$32,IF(AND('3. GRI Pricing'!$F17>='2. GRI Pricing Inputs'!$Z$33,'3. GRI Pricing'!$F17<='2. GRI Pricing Inputs'!$AA$33),'2. GRI Pricing Inputs'!$Z$32,IF(AND('3. GRI Pricing'!$F17>='2. GRI Pricing Inputs'!$AB$33,'3. GRI Pricing'!$F17<='2. GRI Pricing Inputs'!$AC$33),'2. GRI Pricing Inputs'!$AB$32,IF(AND('3. GRI Pricing'!$F17>='2. GRI Pricing Inputs'!$AD$33,'3. GRI Pricing'!$F17<='2. GRI Pricing Inputs'!$AE$33),'2. GRI Pricing Inputs'!$AD$32,IF(AND('3. GRI Pricing'!$F17>='2. GRI Pricing Inputs'!$AF$33,'3. GRI Pricing'!$F17<='2. GRI Pricing Inputs'!$AG$33),'2. GRI Pricing Inputs'!$AF$32,IF(AND('3. GRI Pricing'!$F17>='2. GRI Pricing Inputs'!$AH$33,'3. GRI Pricing'!$F17<='2. GRI Pricing Inputs'!$AI$33),'2. GRI Pricing Inputs'!$AH$32,0)))))))))))))))) -> 1 | N17: {=IFERROR(INDEX('2. GRI Pricing Inputs'!$C$32:$AI$39,MATCH('3. GRI Pricing'!D17,'2. GRI Pricing Inputs'!$C$32:$C$39,0),(MATCH('3. GRI Pricing'!M17,'2. GRI Pricing Inputs'!$D$32:$AI$32,0)+1)),0)} -> 10 | O17: =IFERROR(INDEX('2. GRI Pricing Inputs'!$C$45:$AI$46,MATCH($O$16,'2. GRI Pricing Inputs'!$C$45:$C$46,0),MATCH(G17,'2. GRI Pricing Inputs'!$C$45:$AI$45,0)),0) -> 0 | P17: =IFERROR(INDEX('2. GRI Pricing Inputs'!$C$53:$AI$54,MATCH('3. GRI Pricing'!$P$16,'2. GRI Pricing Inputs'!$C$53:$C$54,0),MATCH('3. GRI Pricing'!H17,'2. GRI Pricing Inputs'!$C$53:$AI$53,0)),0) -> 25 | Q17: =IFERROR(INDEX('2. GRI Pricing Inputs'!$C$60:$AI$61,MATCH('3. GRI Pricing'!$Q$16,'2. GRI Pricing Inputs'!$C$60:$C$61,0),MATCH('1. Accomodation'!T21,'2. GRI Pricing Inputs'!$C$60:$AI$60,0)),0) -> 0 | R17: =IFERROR(INDEX('2. GRI Pricing Inputs'!$C$67:$AI$68,MATCH('3. GRI Pricing'!$R$16,'2. GRI Pricing Inputs'!$C$67:$C$68,0),MATCH('1. Accomodation'!U21,'2. GRI Pricing Inputs'!$C$67:$AI$67,0)),0) -> 0 | S17: =IF(D17=0,0,'2. GRI Pricing Inputs'!$AI$75) -> 70 | T17: =IFERROR(INDEX('2. GRI Pricing Inputs'!$C$82:$AI$83,MATCH('3. GRI Pricing'!$T$16,'2. GRI Pricing Inputs'!$C$82:$C$83,0),MATCH('1. Accomodation'!V21,'2. GRI Pricing Inputs'!$C$82:$AI$82,0)),0) -> 20 | U17: =IFERROR(INDEX('2. GRI Pricing Inputs'!$C$89:$AI$90,MATCH('3. GRI Pricing'!$U$16,'2. GRI Pricing Inputs'!$C$89:$C$90,0),MATCH('1. Accomodation'!W21,'2. GRI Pricing Inputs'!$C$89:$AI$89,0)),0) -> 0 | V17: =IFERROR(INDEX('2. GRI Pricing Inputs'!$C$97:$AI$98,MATCH('3. GRI Pricing'!$V$16,'2. GRI Pricing Inputs'!$C$97:$C$98,0),MATCH('1. Accomodation'!X21,'2. GRI Pricing Inputs'!$C$97:$AI$97,0)),0) -> 0 | W17: =IFERROR(INDEX('2. GRI Pricing Inputs'!$C$104:$AI$105,MATCH('3. GRI Pricing'!$W$16,'2. GRI Pricing Inputs'!$C$104:$C$105,0),MATCH('1. Accomodation'!Y21,'2. GRI Pricing Inputs'!$C$104:$AI$104,0)),0) -> 0 | X17: 0 | Y17: =K17+L17+N17+O17+P17+Q17+R17+S17+T17+U17+V17+W17+X17 -> 970 | AC17: =Y17*(1+'2. GRI Pricing Inputs'!$D$114)^(($AC$16-$AB$15)/365) -> 973.23653 | AD17: =AC17*(1+'2. GRI Pricing Inputs'!$D$114)^((AD$16-AC$16)/365) -> 976.37894 | AE17: =AD17*(1+'2. GRI Pricing Inputs'!$D$114)^((AE$16-AD$16)/365) -> 979.63675 | AF17: =AE17*(1+'2. GRI Pricing Inputs'!$D$114)^((AF$16-AE$16)/365) -> 982.90543 | AG17: =AF17*(1+'2. GRI Pricing Inputs'!$D$114)^((AG$16-AF$16)/365) -> 985.97311 | AH17: =AG17*(1+'2. GRI Pricing Inputs'!$D$114)^((AH$16-AG$16)/365) -> 989.26293 | AI17: =AH17*(1+'2. GRI Pricing Inputs'!$D$114)^((AI$16-AH$16)/365) -> 992.45709 | AJ17: =AI17*(1+'2. GRI Pricing Inputs'!$D$114)^((AJ$16-AI$16)/365) -> 995.76855 | AK17: =AJ17*(1+'2. GRI Pricing Inputs'!$D$114)^((AK$16-AJ$16)/365) -> 998.98371 | ... AO17: =AN17*(1+'2. GRI Pricing Inputs'!$D$114)^((AO$16-AN$16)/365) -> 1012.2748
C18: ='1. Accomodation'!N22 -> 102N | D18: ='1. Accomodation'!P22 -> 2 Bed | E18: ='1. Accomodation'!Q22 -> 2 | F18: ='1. Accomodation'!O22 -> 678 | G18: ='1. Accomodation'!R22 -> Ground | H18: ='1. Accomodation'!S22 -> Courtyard | K18: =IFERROR(INDEX('2. GRI Pricing Inputs'!$C$15:$AI$16,MATCH($K$16,'2. GRI Pricing Inputs'!$C$15:$C$16,0),MATCH(D18,'2. GRI Pricing Inputs'!$C$15:$AI$15,0)),0) -> 1110 | L18: =IFERROR(INDEX('2. GRI Pricing Inputs'!$C$22:$AI$23,MATCH($L$16,'2. GRI Pricing Inputs'!$C$22:$C$23,0),MATCH(E18,'2. GRI Pricing Inputs'!$C$22:$AI$22,0)),0) -> 0 | M18: =IF(AND('3. GRI Pricing'!$F18>='2. GRI Pricing Inputs'!$D$33,'3. GRI Pricing'!$F18<='2. GRI Pricing Inputs'!$E$33),'2. GRI Pricing Inputs'!$D$32,IF(AND('3. GRI Pricing'!$F18>='2. GRI Pricing Inputs'!$F$33,'3. GRI Pricing'!$F18<='2. GRI Pricing Inputs'!$G$33),'2. GRI Pricing Inputs'!$F$32,IF(AND('3. GRI Pricing'!$F18>='2. GRI Pricing Inputs'!$H$33,'3. GRI Pricing'!$F18<='2. GRI Pricing Inputs'!$I$33),'2. GRI Pricing Inputs'!$H$32,IF(AND('3. GRI Pricing'!$F18>='2. GRI Pricing Inputs'!$J$33,'3. GRI Pricing'!$F18<='2. GRI Pricing Inputs'!$K$33),'2. GRI Pricing Inputs'!$J$32,IF(AND('3. GRI Pricing'!$F18>='2. GRI Pricing Inputs'!$L$33,'3. GRI Pricing'!$F18<='2. GRI Pricing Inputs'!$M$33),'2. GRI Pricing Inputs'!$L$32,IF(AND('3. GRI Pricing'!$F18>='2. GRI Pricing Inputs'!$N$33,'3. GRI Pricing'!$F18<='2. GRI Pricing Inputs'!$O$33),'2. GRI Pricing Inputs'!$N$32,IF(AND('3. GRI Pricing'!$F18>='2. GRI Pricing Inputs'!$P$33,'3. GRI Pricing'!$F18<='2. GRI Pricing Inputs'!$Q$33),'2. GRI Pricing Inputs'!$P$32,IF(AND('3. GRI Pricing'!$F18>='2. GRI Pricing Inputs'!$R$33,'3. GRI Pricing'!$F18<='2. GRI Pricing Inputs'!$S$33),'2. GRI Pricing Inputs'!$R$32,IF(AND('3. GRI Pricing'!$F18>='2. GRI Pricing Inputs'!$T$33,'3. GRI Pricing'!$F18<='2. GRI Pricing Inputs'!$U$33),'2. GRI Pricing Inputs'!$T$32,IF(AND('3. GRI Pricing'!$F18>='2. GRI Pricing Inputs'!$V$33,'3. GRI Pricing'!$F18<='2. GRI Pricing Inputs'!$W$33),'2. GRI Pricing Inputs'!$V$32,IF(AND('3. GRI Pricing'!$F18>='2. GRI Pricing Inputs'!$X$33,'3. GRI Pricing'!$F18<='2. GRI Pricing Inputs'!$Y$33),'2. GRI Pricing Inputs'!$X$32,IF(AND('3. GRI Pricing'!$F18>='2. GRI Pricing Inputs'!$Z$33,'3. GRI Pricing'!$F18<='2. GRI Pricing Inputs'!$AA$33),'2. GRI Pricing Inputs'!$Z$32,IF(AND('3. GRI Pricing'!$F18>='2. GRI Pricing Inputs'!$AB$33,'3. GRI Pricing'!$F18<='2. GRI Pricing Inputs'!$AC$33),'2. GRI Pricing Inputs'!$AB$32,IF(AND('3. GRI Pricing'!$F18>='2. GRI Pricing Inputs'!$AD$33,'3. GRI Pricing'!$F18<='2. GRI Pricing Inputs'!$AE$33),'2. GRI Pricing Inputs'!$AD$32,IF(AND('3. GRI Pricing'!$F18>='2. GRI Pricing Inputs'!$AF$33,'3. GRI Pricing'!$F18<='2. GRI Pricing Inputs'!$AG$33),'2. GRI Pricing Inputs'!$AF$32,IF(AND('3. GRI Pricing'!$F18>='2. GRI Pricing Inputs'!$AH$33,'3. GRI Pricing'!$F18<='2. GRI Pricing Inputs'!$AI$33),'2. GRI Pricing Inputs'!$AH$32,0)))))))))))))))) -> 10 | N18: {=IFERROR(INDEX('2. GRI Pricing Inputs'!$C$32:$AI$39,MATCH('3. GRI Pricing'!D18,'2. GRI Pricing Inputs'!$C$32:$C$39,0),(MATCH('3. GRI Pricing'!M18,'2. GRI Pricing Inputs'!$D$32:$AI$32,0)+1)),0)} -> 40 | O18: =IFERROR(INDEX('2. GRI Pricing Inputs'!$C$45:$AI$46,MATCH($O$16,'2. GRI Pricing Inputs'!$C$45:$C$46,0),MATCH(G18,'2. GRI Pricing Inputs'!$C$45:$AI$45,0)),0) -> 0 | P18: =IFERROR(INDEX('2. GRI Pricing Inputs'!$C$53:$AI$54,MATCH('3. GRI Pricing'!$P$16,'2. GRI Pricing Inputs'!$C$53:$C$54,0),MATCH('3. GRI Pricing'!H18,'2. GRI Pricing Inputs'!$C$53:$AI$53,0)),0) -> 25 | Q18: =IFERROR(INDEX('2. GRI Pricing Inputs'!$C$60:$AI$61,MATCH('3. GRI Pricing'!$Q$16,'2. GRI Pricing Inputs'!$C$60:$C$61,0),MATCH('1. Accomodation'!T22,'2. GRI Pricing Inputs'!$C$60:$AI$60,0)),0) -> 0 | R18: =IFERROR(INDEX('2. GRI Pricing Inputs'!$C$67:$AI$68,MATCH('3. GRI Pricing'!$R$16,'2. GRI Pricing Inputs'!$C$67:$C$68,0),MATCH('1. Accomodation'!U22,'2. GRI Pricing Inputs'!$C$67:$AI$67,0)),0) -> 0 | S18: =IF(D18=0,0,'2. GRI Pricing Inputs'!$AI$75) -> 70 | T18: =IFERROR(INDEX('2. GRI Pricing Inputs'!$C$82:$AI$83,MATCH('3. GRI Pricing'!$T$16,'2. GRI Pricing Inputs'!$C$82:$C$83,0),MATCH('1. Accomodation'!V22,'2. GRI Pricing Inputs'!$C$82:$AI$82,0)),0) -> 20 | U18: =IFERROR(INDEX('2. GRI Pricing Inputs'!$C$89:$AI$90,MATCH('3. GRI Pricing'!$U$16,'2. GRI Pricing Inputs'!$C$89:$C$90,0),MATCH('1. Accomodation'!W22,'2. GRI Pricing Inputs'!$C$89:$AI$89,0)),0) -> 0 | V18: =IFERROR(INDEX('2. GRI Pricing Inputs'!$C$97:$AI$98,MATCH('3. GRI Pricing'!$V$16,'2. GRI Pricing Inputs'!$C$97:$C$98,0),MATCH('1. Accomodation'!X22,'2. GRI Pricing Inputs'!$C$97:$AI$97,0)),0) -> 0 | W18: =IFERROR(INDEX('2. GRI Pricing Inputs'!$C$104:$AI$105,MATCH('3. GRI Pricing'!$W$16,'2. GRI Pricing Inputs'!$C$104:$C$105,0),MATCH('1. Accomodation'!Y22,'2. GRI Pricing Inputs'!$C$104:$AI$104,0)),0) -> 0 | X18: 0 | Y18: =K18+L18+N18+O18+P18+Q18+R18+S18+T18+U18+V18+W18+X18 -> 1265 | AC18: =Y18*(1+'2. GRI Pricing Inputs'!$D$114)^(($AC$16-$AB$15)/365) -> 1269.2208 | AD18: =AC18*(1+'2. GRI Pricing Inputs'!$D$114)^((AD$16-AC$16)/365) -> 1273.3189 | AE18: =AD18*(1+'2. GRI Pricing Inputs'!$D$114)^((AE$16-AD$16)/365) -> 1277.5675 | AF18: =AE18*(1+'2. GRI Pricing Inputs'!$D$114)^((AF$16-AE$16)/365) -> 1281.8303 | AG18: =AF18*(1+'2. GRI Pricing Inputs'!$D$114)^((AG$16-AF$16)/365) -> 1285.8309 | AH18: =AG18*(1+'2. GRI Pricing Inputs'!$D$114)^((AH$16-AG$16)/365) -> 1290.1212 | AI18: =AH18*(1+'2. GRI Pricing Inputs'!$D$114)^((AI$16-AH$16)/365) -> 1294.2868 | AJ18: =AI18*(1+'2. GRI Pricing Inputs'!$D$114)^((AJ$16-AI$16)/365) -> 1298.6054 | AK18: =AJ18*(1+'2. GRI Pricing Inputs'!$D$114)^((AK$16-AJ$16)/365) -> 1302.7983 | ... AO18: =AN18*(1+'2. GRI Pricing Inputs'!$D$114)^((AO$16-AN$16)/365) -> 1320.1315
C19: ='1. Accomodation'!N23 -> 103N | D19: ='1. Accomodation'!P23 -> 2 Bed | E19: ='1. Accomodation'!Q23 -> 2 | F19: ='1. Accomodation'!O23 -> 657 | G19: ='1. Accomodation'!R23 -> Ground | H19: ='1. Accomodation'!S23 -> Courtyard | K19: =IFERROR(INDEX('2. GRI Pricing Inputs'!$C$15:$AI$16,MATCH($K$16,'2. GRI Pricing Inputs'!$C$15:$C$16,0),MATCH(D19,'2. GRI Pricing Inputs'!$C$15:$AI$15,0)),0) -> 1110 | L19: =IFERROR(INDEX('2. GRI Pricing Inputs'!$C$22:$AI$23,MATCH($L$16,'2. GRI Pricing Inputs'!$C$22:$C$23,0),MATCH(E19,'2. GRI Pricing Inputs'!$C$22:$AI$22,0)),0) -> 0 | M19: =IF(AND('3. GRI Pricing'!$F19>='2. GRI Pricing Inputs'!$D$33,'3. GRI Pricing'!$F19<='2. GRI Pricing Inputs'!$E$33),'2. GRI Pricing Inputs'!$D$32,IF(AND('3. GRI Pricing'!$F19>='2. GRI Pricing Inputs'!$F$33,'3. GRI Pricing'!$F19<='2. GRI Pricing Inputs'!$G$33),'2. GRI Pricing Inputs'!$F$32,IF(AND('3. GRI Pricing'!$F19>='2. GRI Pricing Inputs'!$H$33,'3. GRI Pricing'!$F19<='2. GRI Pricing Inputs'!$I$33),'2. GRI Pricing Inputs'!$H$32,IF(AND('3. GRI Pricing'!$F19>='2. GRI Pricing Inputs'!$J$33,'3. GRI Pricing'!$F19<='2. GRI Pricing Inputs'!$K$33),'2. GRI Pricing Inputs'!$J$32,IF(AND('3. GRI Pricing'!$F19>='2. GRI Pricing Inputs'!$L$33,'3. GRI Pricing'!$F19<='2. GRI Pricing Inputs'!$M$33),'2. GRI Pricing Inputs'!$L$32,IF(AND('3. GRI Pricing'!$F19>='2. GRI Pricing Inputs'!$N$33,'3. GRI Pricing'!$F19<='2. GRI Pricing Inputs'!$O$33),'2. GRI Pricing Inputs'!$N$32,IF(AND('3. GRI Pricing'!$F19>='2. GRI Pricing Inputs'!$P$33,'3. GRI Pricing'!$F19<='2. GRI Pricing Inputs'!$Q$33),'2. GRI Pricing Inputs'!$P$32,IF(AND('3. GRI Pricing'!$F19>='2. GRI Pricing Inputs'!$R$33,'3. GRI Pricing'!$F19<='2. GRI Pricing Inputs'!$S$33),'2. GRI Pricing Inputs'!$R$32,IF(AND('3. GRI Pricing'!$F19>='2. GRI Pricing Inputs'!$T$33,'3. GRI Pricing'!$F19<='2. GRI Pricing Inputs'!$U$33),'2. GRI Pricing Inputs'!$T$32,IF(AND('3. GRI Pricing'!$F19>='2. GRI Pricing Inputs'!$V$33,'3. GRI Pricing'!$F19<='2. GRI Pricing Inputs'!$W$33),'2. GRI Pricing Inputs'!$V$32,IF(AND('3. GRI Pricing'!$F19>='2. GRI Pricing Inputs'!$X$33,'3. GRI Pricing'!$F19<='2. GRI Pricing Inputs'!$Y$33),'2. GRI Pricing Inputs'!$X$32,IF(AND('3. GRI Pricing'!$F19>='2. GRI Pricing Inputs'!$Z$33,'3. GRI Pricing'!$F19<='2. GRI Pricing Inputs'!$AA$33),'2. GRI Pricing Inputs'!$Z$32,IF(AND('3. GRI Pricing'!$F19>='2. GRI Pricing Inputs'!$AB$33,'3. GRI Pricing'!$F19<='2. GRI Pricing Inputs'!$AC$33),'2. GRI Pricing Inputs'!$AB$32,IF(AND('3. GRI Pricing'!$F19>='2. GRI Pricing Inputs'!$AD$33,'3. GRI Pricing'!$F19<='2. GRI Pricing Inputs'!$AE$33),'2. GRI Pricing Inputs'!$AD$32,IF(AND('3. GRI Pricing'!$F19>='2. GRI Pricing Inputs'!$AF$33,'3. GRI Pricing'!$F19<='2. GRI Pricing Inputs'!$AG$33),'2. GRI Pricing Inputs'!$AF$32,IF(AND('3. GRI Pricing'!$F19>='2. GRI Pricing Inputs'!$AH$33,'3. GRI Pricing'!$F19<='2. GRI Pricing Inputs'!$AI$33),'2. GRI Pricing Inputs'!$AH$32,0)))))))))))))))) -> 8 | N19: {=IFERROR(INDEX('2. GRI Pricing Inputs'!$C$32:$AI$39,MATCH('3. GRI Pricing'!D19,'2. GRI Pricing Inputs'!$C$32:$C$39,0),(MATCH('3. GRI Pricing'!M19,'2. GRI Pricing Inputs'!$D$32:$AI$32,0)+1)),0)} -> 20 | O19: =IFERROR(INDEX('2. GRI Pricing Inputs'!$C$45:$AI$46,MATCH($O$16,'2. GRI Pricing Inputs'!$C$45:$C$46,0),MATCH(G19,'2. GRI Pricing Inputs'!$C$45:$AI$45,0)),0) -> 0 | P19: =IFERROR(INDEX('2. GRI Pricing Inputs'!$C$53:$AI$54,MATCH('3. GRI Pricing'!$P$16,'2. GRI Pricing Inputs'!$C$53:$C$54,0),MATCH('3. GRI Pricing'!H19,'2. GRI Pricing Inputs'!$C$53:$AI$53,0)),0) -> 25 | Q19: =IFERROR(INDEX('2. GRI Pricing Inputs'!$C$60:$AI$61,MATCH('3. GRI Pricing'!$Q$16,'2. GRI Pricing Inputs'!$C$60:$C$61,0),MATCH('1. Accomodation'!T23,'2. GRI Pricing Inputs'!$C$60:$AI$60,0)),0) -> 0 | R19: =IFERROR(INDEX('2. GRI Pricing Inputs'!$C$67:$AI$68,MATCH('3. GRI Pricing'!$R$16,'2. GRI Pricing Inputs'!$C$67:$C$68,0),MATCH('1. Accomodation'!U23,'2. GRI Pricing Inputs'!$C$67:$AI$67,0)),0) -> 0 | S19: =IF(D19=0,0,'2. GRI Pricing Inputs'!$AI$75) -> 70 | T19: =IFERROR(INDEX('2. GRI Pricing Inputs'!$C$82:$AI$83,MATCH('3. GRI Pricing'!$T$16,'2. GRI Pricing Inputs'!$C$82:$C$83,0),MATCH('1. Accomodation'!V23,'2. GRI Pricing Inputs'!$C$82:$AI$82,0)),0) -> 0 | U19: =IFERROR(INDEX('2. GRI Pricing Inputs'!$C$89:$AI$90,MATCH('3. GRI Pricing'!$U$16,'2. GRI Pricing Inputs'!$C$89:$C$90,0),MATCH('1. Accomodation'!W23,'2. GRI Pricing Inputs'!$C$89:$AI$89,0)),0) -> 0 | V19: =IFERROR(INDEX('2. GRI Pricing Inputs'!$C$97:$AI$98,MATCH('3. GRI Pricing'!$V$16,'2. GRI Pricing Inputs'!$C$97:$C$98,0),MATCH('1. Accomodation'!X23,'2. GRI Pricing Inputs'!$C$97:$AI$97,0)),0) -> 0 | W19: =IFERROR(INDEX('2. GRI Pricing Inputs'!$C$104:$AI$105,MATCH('3. GRI Pricing'!$W$16,'2. GRI Pricing Inputs'!$C$104:$C$105,0),MATCH('1. Accomodation'!Y23,'2. GRI Pricing Inputs'!$C$104:$AI$104,0)),0) -> 0 | X19: 0 | Y19: =K19+L19+N19+O19+P19+Q19+R19+S19+T19+U19+V19+W19+X19 -> 1225 | AC19: =Y19*(1+'2. GRI Pricing Inputs'!$D$114)^(($AC$16-$AB$15)/365) -> 1229.0874 | AD19: =AC19*(1+'2. GRI Pricing Inputs'!$D$114)^((AD$16-AC$16)/365) -> 1233.0559 | AE19: =AD19*(1+'2. GRI Pricing Inputs'!$D$114)^((AE$16-AD$16)/365) -> 1237.1701 | AF19: =AE19*(1+'2. GRI Pricing Inputs'!$D$114)^((AF$16-AE$16)/365) -> 1241.2981 | AG19: =AF19*(1+'2. GRI Pricing Inputs'!$D$114)^((AG$16-AF$16)/365) -> 1245.1722 | AH19: =AG19*(1+'2. GRI Pricing Inputs'!$D$114)^((AH$16-AG$16)/365) -> 1249.3269 | AI19: =AH19*(1+'2. GRI Pricing Inputs'!$D$114)^((AI$16-AH$16)/365) -> 1253.3608 | AJ19: =AI19*(1+'2. GRI Pricing Inputs'!$D$114)^((AJ$16-AI$16)/365) -> 1257.5428 | AK19: =AJ19*(1+'2. GRI Pricing Inputs'!$D$114)^((AK$16-AJ$16)/365) -> 1261.6031 | ... AO19: =AN19*(1+'2. GRI Pricing Inputs'!$D$114)^((AO$16-AN$16)/365) -> 1278.3882
C20: ='1. Accomodation'!N24 -> 104N | D20: ='1. Accomodation'!P24 -> 3 Bed | E20: ='1. Accomodation'!Q24 -> 2 | F20: ='1. Accomodation'!O24 -> 818 | G20: ='1. Accomodation'!R24 -> 1 | H20: ='1. Accomodation'!S24 -> Pottery Lane | K20: =IFERROR(INDEX('2. GRI Pricing Inputs'!$C$15:$AI$16,MATCH($K$16,'2. GRI Pricing Inputs'!$C$15:$C$16,0),MATCH(D20,'2. GRI Pricing Inputs'!$C$15:$AI$15,0)),0) -> 1485 | L20: =IFERROR(INDEX('2. GRI Pricing Inputs'!$C$22:$AI$23,MATCH($L$16,'2. GRI Pricing Inputs'!$C$22:$C$23,0),MATCH(E20,'2. GRI Pricing Inputs'!$C$22:$AI$22,0)),0) -> 0 | M20: =IF(AND('3. GRI Pricing'!$F20>='2. GRI Pricing Inputs'!$D$33,'3. GRI Pricing'!$F20<='2. GRI Pricing Inputs'!$E$33),'2. GRI Pricing Inputs'!$D$32,IF(AND('3. GRI Pricing'!$F20>='2. GRI Pricing Inputs'!$F$33,'3. GRI Pricing'!$F20<='2. GRI Pricing Inputs'!$G$33),'2. GRI Pricing Inputs'!$F$32,IF(AND('3. GRI Pricing'!$F20>='2. GRI Pricing Inputs'!$H$33,'3. GRI Pricing'!$F20<='2. GRI Pricing Inputs'!$I$33),'2. GRI Pricing Inputs'!$H$32,IF(AND('3. GRI Pricing'!$F20>='2. GRI Pricing Inputs'!$J$33,'3. GRI Pricing'!$F20<='2. GRI Pricing Inputs'!$K$33),'2. GRI Pricing Inputs'!$J$32,IF(AND('3. GRI Pricing'!$F20>='2. GRI Pricing Inputs'!$L$33,'3. GRI Pricing'!$F20<='2. GRI Pricing Inputs'!$M$33),'2. GRI Pricing Inputs'!$L$32,IF(AND('3. GRI Pricing'!$F20>='2. GRI Pricing Inputs'!$N$33,'3. GRI Pricing'!$F20<='2. GRI Pricing Inputs'!$O$33),'2. GRI Pricing Inputs'!$N$32,IF(AND('3. GRI Pricing'!$F20>='2. GRI Pricing Inputs'!$P$33,'3. GRI Pricing'!$F20<='2. GRI Pricing Inputs'!$Q$33),'2. GRI Pricing Inputs'!$P$32,IF(AND('3. GRI Pricing'!$F20>='2. GRI Pricing Inputs'!$R$33,'3. GRI Pricing'!$F20<='2. GRI Pricing Inputs'!$S$33),'2. GRI Pricing Inputs'!$R$32,IF(AND('3. GRI Pricing'!$F20>='2. GRI Pricing Inputs'!$T$33,'3. GRI Pricing'!$F20<='2. GRI Pricing Inputs'!$U$33),'2. GRI Pricing Inputs'!$T$32,IF(AND('3. GRI Pricing'!$F20>='2. GRI Pricing Inputs'!$V$33,'3. GRI Pricing'!$F20<='2. GRI Pricing Inputs'!$W$33),'2. GRI Pricing Inputs'!$V$32,IF(AND('3. GRI Pricing'!$F20>='2. GRI Pricing Inputs'!$X$33,'3. GRI Pricing'!$F20<='2. GRI Pricing Inputs'!$Y$33),'2. GRI Pricing Inputs'!$X$32,IF(AND('3. GRI Pricing'!$F20>='2. GRI Pricing Inputs'!$Z$33,'3. GRI Pricing'!$F20<='2. GRI Pricing Inputs'!$AA$33),'2. GRI Pricing Inputs'!$Z$32,IF(AND('3. GRI Pricing'!$F20>='2. GRI Pricing Inputs'!$AB$33,'3. GRI Pricing'!$F20<='2. GRI Pricing Inputs'!$AC$33),'2. GRI Pricing Inputs'!$AB$32,IF(AND('3. GRI Pricing'!$F20>='2. GRI Pricing Inputs'!$AD$33,'3. GRI Pricing'!$F20<='2. GRI Pricing Inputs'!$AE$33),'2. GRI Pricing Inputs'!$AD$32,IF(AND('3. GRI Pricing'!$F20>='2. GRI Pricing Inputs'!$AF$33,'3. GRI Pricing'!$F20<='2. GRI Pricing Inputs'!$AG$33),'2. GRI Pricing Inputs'!$AF$32,IF(AND('3. GRI Pricing'!$F20>='2. GRI Pricing Inputs'!$AH$33,'3. GRI Pricing'!$F20<='2. GRI Pricing Inputs'!$AI$33),'2. GRI Pricing Inputs'!$AH$32,0)))))))))))))))) -> 13 | N20: {=IFERROR(INDEX('2. GRI Pricing Inputs'!$C$32:$AI$39,MATCH('3. GRI Pricing'!D20,'2. GRI Pricing Inputs'!$C$32:$C$39,0),(MATCH('3. GRI Pricing'!M20,'2. GRI Pricing Inputs'!$D$32:$AI$32,0)+1)),0)} -> 50 | O20: =IFERROR(INDEX('2. GRI Pricing Inputs'!$C$45:$AI$46,MATCH($O$16,'2. GRI Pricing Inputs'!$C$45:$C$46,0),MATCH(G20,'2. GRI Pricing Inputs'!$C$45:$AI$45,0)),0) -> 30 | P20: =IFERROR(INDEX('2. GRI Pricing Inputs'!$C$53:$AI$54,MATCH('3. GRI Pricing'!$P$16,'2. GRI Pricing Inputs'!$C$53:$C$54,0),MATCH('3. GRI Pricing'!H20,'2. GRI Pricing Inputs'!$C$53:$AI$53,0)),0) -> 10 | Q20: =IFERROR(INDEX('2. GRI Pricing Inputs'!$C$60:$AI$61,MATCH('3. GRI Pricing'!$Q$16,'2. GRI Pricing Inputs'!$C$60:$C$61,0),MATCH('1. Accomodation'!T24,'2. GRI Pricing Inputs'!$C$60:$AI$60,0)),0) -> 0 | R20: =IFERROR(INDEX('2. GRI Pricing Inputs'!$C$67:$AI$68,MATCH('3. GRI Pricing'!$R$16,'2. GRI Pricing Inputs'!$C$67:$C$68,0),MATCH('1. Accomodation'!U24,'2. GRI Pricing Inputs'!$C$67:$AI$67,0)),0) -> 0 | S20: =IF(D20=0,0,'2. GRI Pricing Inputs'!$AI$75) -> 70 | T20: =IFERROR(INDEX('2. GRI Pricing Inputs'!$C$82:$AI$83,MATCH('3. GRI Pricing'!$T$16,'2. GRI Pricing Inputs'!$C$82:$C$83,0),MATCH('1. Accomodation'!V24,'2. GRI Pricing Inputs'!$C$82:$AI$82,0)),0) -> 0 | U20: =IFERROR(INDEX('2. GRI Pricing Inputs'!$C$89:$AI$90,MATCH('3. GRI Pricing'!$U$16,'2. GRI Pricing Inputs'!$C$89:$C$90,0),MATCH('1. Accomodation'!W24,'2. GRI Pricing Inputs'!$C$89:$AI$89,0)),0) -> 0 | V20: =IFERROR(INDEX('2. GRI Pricing Inputs'!$C$97:$AI$98,MATCH('3. GRI Pricing'!$V$16,'2. GRI Pricing Inputs'!$C$97:$C$98,0),MATCH('1. Accomodation'!X24,'2. GRI Pricing Inputs'!$C$97:$AI$97,0)),0) -> 0 | W20: =IFERROR(INDEX('2. GRI Pricing Inputs'!$C$104:$AI$105,MATCH('3. GRI Pricing'!$W$16,'2. GRI Pricing Inputs'!$C$104:$C$105,0),MATCH('1. Accomodation'!Y24,'2. GRI Pricing Inputs'!$C$104:$AI$104,0)),0) -> 0 | X20: 0 | Y20: =K20+L20+N20+O20+P20+Q20+R20+S20+T20+U20+V20+W20+X20 -> 1645 | AC20: =Y20*(1+'2. GRI Pricing Inputs'!$D$114)^(($AC$16-$AB$15)/365) -> 1650.4888 | AD20: =AC20*(1+'2. GRI Pricing Inputs'!$D$114)^((AD$16-AC$16)/365) -> 1655.8179 | AE20: =AD20*(1+'2. GRI Pricing Inputs'!$D$114)^((AE$16-AD$16)/365) -> 1661.3427 | AF20: =AE20*(1+'2. GRI Pricing Inputs'!$D$114)^((AF$16-AE$16)/365) -> 1666.886 | AG20: =AF20*(1+'2. GRI Pricing Inputs'!$D$114)^((AG$16-AF$16)/365) -> 1672.0884 | AH20: =AG20*(1+'2. GRI Pricing Inputs'!$D$114)^((AH$16-AG$16)/365) -> 1677.6676 | AI20: =AH20*(1+'2. GRI Pricing Inputs'!$D$114)^((AI$16-AH$16)/365) -> 1683.0844 | AJ20: =AI20*(1+'2. GRI Pricing Inputs'!$D$114)^((AJ$16-AI$16)/365) -> 1688.7003 | AK20: =AJ20*(1+'2. GRI Pricing Inputs'!$D$114)^((AK$16-AJ$16)/365) -> 1694.1528 | ... AO20: =AN20*(1+'2. GRI Pricing Inputs'!$D$114)^((AO$16-AN$16)/365) -> 1716.6928
C21: ='1. Accomodation'!N25 -> 105N | D21: ='1. Accomodation'!P25 -> 2 Bed | E21: ='1. Accomodation'!Q25 -> 2 | F21: ='1. Accomodation'!O25 -> 667 | G21: ='1. Accomodation'!R25 -> 1 | H21: ='1. Accomodation'!S25 -> Forth Banks/Pottery Lane | K21: =IFERROR(INDEX('2. GRI Pricing Inputs'!$C$15:$AI$16,MATCH($K$16,'2. GRI Pricing Inputs'!$C$15:$C$16,0),MATCH(D21,'2. GRI Pricing Inputs'!$C$15:$AI$15,0)),0) -> 1110 | L21: =IFERROR(INDEX('2. GRI Pricing Inputs'!$C$22:$AI$23,MATCH($L$16,'2. GRI Pricing Inputs'!$C$22:$C$23,0),MATCH(E21,'2. GRI Pricing Inputs'!$C$22:$AI$22,0)),0) -> 0 | M21: =IF(AND('3. GRI Pricing'!$F21>='2. GRI Pricing Inputs'!$D$33,'3. GRI Pricing'!$F21<='2. GRI Pricing Inputs'!$E$33),'2. GRI Pricing Inputs'!$D$32,IF(AND('3. GRI Pricing'!$F21>='2. GRI Pricing Inputs'!$F$33,'3. GRI Pricing'!$F21<='2. GRI Pricing Inputs'!$G$33),'2. GRI Pricing Inputs'!$F$32,IF(AND('3. GRI Pricing'!$F21>='2. GRI Pricing Inputs'!$H$33,'3. GRI Pricing'!$F21<='2. GRI Pricing Inputs'!$I$33),'2. GRI Pricing Inputs'!$H$32,IF(AND('3. GRI Pricing'!$F21>='2. GRI Pricing Inputs'!$J$33,'3. GRI Pricing'!$F21<='2. GRI Pricing Inputs'!$K$33),'2. GRI Pricing Inputs'!$J$32,IF(AND('3. GRI Pricing'!$F21>='2. GRI Pricing Inputs'!$L$33,'3. GRI Pricing'!$F21<='2. GRI Pricing Inputs'!$M$33),'2. GRI Pricing Inputs'!$L$32,IF(AND('3. GRI Pricing'!$F21>='2. GRI Pricing Inputs'!$N$33,'3. GRI Pricing'!$F21<='2. GRI Pricing Inputs'!$O$33),'2. GRI Pricing Inputs'!$N$32,IF(AND('3. GRI Pricing'!$F21>='2. GRI Pricing Inputs'!$P$33,'3. GRI Pricing'!$F21<='2. GRI Pricing Inputs'!$Q$33),'2. GRI Pricing Inputs'!$P$32,IF(AND('3. GRI Pricing'!$F21>='2. GRI Pricing Inputs'!$R$33,'3. GRI Pricing'!$F21<='2. GRI Pricing Inputs'!$S$33),'2. GRI Pricing Inputs'!$R$32,IF(AND('3. GRI Pricing'!$F21>='2. GRI Pricing Inputs'!$T$33,'3. GRI Pricing'!$F21<='2. GRI Pricing Inputs'!$U$33),'2. GRI Pricing Inputs'!$T$32,IF(AND('3. GRI Pricing'!$F21>='2. GRI Pricing Inputs'!$V$33,'3. GRI Pricing'!$F21<='2. GRI Pricing Inputs'!$W$33),'2. GRI Pricing Inputs'!$V$32,IF(AND('3. GRI Pricing'!$F21>='2. GRI Pricing Inputs'!$X$33,'3. GRI Pricing'!$F21<='2. GRI Pricing Inputs'!$Y$33),'2. GRI Pricing Inputs'!$X$32,IF(AND('3. GRI Pricing'!$F21>='2. GRI Pricing Inputs'!$Z$33,'3. GRI Pricing'!$F21<='2. GRI Pricing Inputs'!$AA$33),'2. GRI Pricing Inputs'!$Z$32,IF(AND('3. GRI Pricing'!$F21>='2. GRI Pricing Inputs'!$AB$33,'3. GRI Pricing'!$F21<='2. GRI Pricing Inputs'!$AC$33),'2. GRI Pricing Inputs'!$AB$32,IF(AND('3. GRI Pricing'!$F21>='2. GRI Pricing Inputs'!$AD$33,'3. GRI Pricing'!$F21<='2. GRI Pricing Inputs'!$AE$33),'2. GRI Pricing Inputs'!$AD$32,IF(AND('3. GRI Pricing'!$F21>='2. GRI Pricing Inputs'!$AF$33,'3. GRI Pricing'!$F21<='2. GRI Pricing Inputs'!$AG$33),'2. GRI Pricing Inputs'!$AF$32,IF(AND('3. GRI Pricing'!$F21>='2. GRI Pricing Inputs'!$AH$33,'3. GRI Pricing'!$F21<='2. GRI Pricing Inputs'!$AI$33),'2. GRI Pricing Inputs'!$AH$32,0)))))))))))))))) -> 9 | N21: {=IFERROR(INDEX('2. GRI Pricing Inputs'!$C$32:$AI$39,MATCH('3. GRI Pricing'!D21,'2. GRI Pricing Inputs'!$C$32:$C$39,0),(MATCH('3. GRI Pricing'!M21,'2. GRI Pricing Inputs'!$D$32:$AI$32,0)+1)),0)} -> 30 | O21: =IFERROR(INDEX('2. GRI Pricing Inputs'!$C$45:$AI$46,MATCH($O$16,'2. GRI Pricing Inputs'!$C$45:$C$46,0),MATCH(G21,'2. GRI Pricing Inputs'!$C$45:$AI$45,0)),0) -> 30 | P21: =IFERROR(INDEX('2. GRI Pricing Inputs'!$C$53:$AI$54,MATCH('3. GRI Pricing'!$P$16,'2. GRI Pricing Inputs'!$C$53:$C$54,0),MATCH('3. GRI Pricing'!H21,'2. GRI Pricing Inputs'!$C$53:$AI$53,0)),0) -> 10 | Q21: =IFERROR(INDEX('2. GRI Pricing Inputs'!$C$60:$AI$61,MATCH('3. GRI Pricing'!$Q$16,'2. GRI Pricing Inputs'!$C$60:$C$61,0),MATCH('1. Accomodation'!T25,'2. GRI Pricing Inputs'!$C$60:$AI$60,0)),0) -> 0 | R21: =IFERROR(INDEX('2. GRI Pricing Inputs'!$C$67:$AI$68,MATCH('3. GRI Pricing'!$R$16,'2. GRI Pricing Inputs'!$C$67:$C$68,0),MATCH('1. Accomodation'!U25,'2. GRI Pricing Inputs'!$C$67:$AI$67,0)),0) -> 0 | S21: =IF(D21=0,0,'2. GRI Pricing Inputs'!$AI$75) -> 70 | T21: =IFERROR(INDEX('2. GRI Pricing Inputs'!$C$82:$AI$83,MATCH('3. GRI Pricing'!$T$16,'2. GRI Pricing Inputs'!$C$82:$C$83,0),MATCH('1. Accomodation'!V25,'2. GRI Pricing Inputs'!$C$82:$AI$82,0)),0) -> 0 | U21: =IFERROR(INDEX('2. GRI Pricing Inputs'!$C$89:$AI$90,MATCH('3. GRI Pricing'!$U$16,'2. GRI Pricing Inputs'!$C$89:$C$90,0),MATCH('1. Accomodation'!W25,'2. GRI Pricing Inputs'!$C$89:$AI$89,0)),0) -> 0 | V21: =IFERROR(INDEX('2. GRI Pricing Inputs'!$C$97:$AI$98,MATCH('3. GRI Pricing'!$V$16,'2. GRI Pricing Inputs'!$C$97:$C$98,0),MATCH('1. Accomodation'!X25,'2. GRI Pricing Inputs'!$C$97:$AI$97,0)),0) -> 0 | W21: =IFERROR(INDEX('2. GRI Pricing Inputs'!$C$104:$AI$105,MATCH('3. GRI Pricing'!$W$16,'2. GRI Pricing Inputs'!$C$104:$C$105,0),MATCH('1. Accomodation'!Y25,'2. GRI Pricing Inputs'!$C$104:$AI$104,0)),0) -> 0 | X21: 0 | Y21: =K21+L21+N21+O21+P21+Q21+R21+S21+T21+U21+V21+W21+X21 -> 1250 | AC21: =Y21*(1+'2. GRI Pricing Inputs'!$D$114)^(($AC$16-$AB$15)/365) -> 1254.1708 | AD21: =AC21*(1+'2. GRI Pricing Inputs'!$D$114)^((AD$16-AC$16)/365) -> 1258.2203 | AE21: =AD21*(1+'2. GRI Pricing Inputs'!$D$114)^((AE$16-AD$16)/365) -> 1262.4185 | AF21: =AE21*(1+'2. GRI Pricing Inputs'!$D$114)^((AF$16-AE$16)/365) -> 1266.6307 | AG21: =AF21*(1+'2. GRI Pricing Inputs'!$D$114)^((AG$16-AF$16)/365) -> 1270.5839 | AH21: =AG21*(1+'2. GRI Pricing Inputs'!$D$114)^((AH$16-AG$16)/365) -> 1274.8234 | AI21: =AH21*(1+'2. GRI Pricing Inputs'!$D$114)^((AI$16-AH$16)/365) -> 1278.9395 | AJ21: =AI21*(1+'2. GRI Pricing Inputs'!$D$114)^((AJ$16-AI$16)/365) -> 1283.2069 | AK21: =AJ21*(1+'2. GRI Pricing Inputs'!$D$114)^((AK$16-AJ$16)/365) -> 1287.3501 | ... AO21: =AN21*(1+'2. GRI Pricing Inputs'!$D$114)^((AO$16-AN$16)/365) -> 1304.4778
C22: ='1. Accomodation'!N26 -> 106N | D22: ='1. Accomodation'!P26 -> 1 Bed | E22: ='1. Accomodation'!Q26 -> 1 | F22: ='1. Accomodation'!O26 -> 441 | G22: ='1. Accomodation'!R26 -> 1 | H22: ='1. Accomodation'!S26 -> Forth Banks | K22: =IFERROR(INDEX('2. GRI Pricing Inputs'!$C$15:$AI$16,MATCH($K$16,'2. GRI Pricing Inputs'!$C$15:$C$16,0),MATCH(D22,'2. GRI Pricing Inputs'!$C$15:$AI$15,0)),0) -> 845 | L22: =IFERROR(INDEX('2. GRI Pricing Inputs'!$C$22:$AI$23,MATCH($L$16,'2. GRI Pricing Inputs'!$C$22:$C$23,0),MATCH(E22,'2. GRI Pricing Inputs'!$C$22:$AI$22,0)),0) -> 0 | M22: =IF(AND('3. GRI Pricing'!$F22>='2. GRI Pricing Inputs'!$D$33,'3. GRI Pricing'!$F22<='2. GRI Pricing Inputs'!$E$33),'2. GRI Pricing Inputs'!$D$32,IF(AND('3. GRI Pricing'!$F22>='2. GRI Pricing Inputs'!$F$33,'3. GRI Pricing'!$F22<='2. GRI Pricing Inputs'!$G$33),'2. GRI Pricing Inputs'!$F$32,IF(AND('3. GRI Pricing'!$F22>='2. GRI Pricing Inputs'!$H$33,'3. GRI Pricing'!$F22<='2. GRI Pricing Inputs'!$I$33),'2. GRI Pricing Inputs'!$H$32,IF(AND('3. GRI Pricing'!$F22>='2. GRI Pricing Inputs'!$J$33,'3. GRI Pricing'!$F22<='2. GRI Pricing Inputs'!$K$33),'2. GRI Pricing Inputs'!$J$32,IF(AND('3. GRI Pricing'!$F22>='2. GRI Pricing Inputs'!$L$33,'3. GRI Pricing'!$F22<='2. GRI Pricing Inputs'!$M$33),'2. GRI Pricing Inputs'!$L$32,IF(AND('3. GRI Pricing'!$F22>='2. GRI Pricing Inputs'!$N$33,'3. GRI Pricing'!$F22<='2. GRI Pricing Inputs'!$O$33),'2. GRI Pricing Inputs'!$N$32,IF(AND('3. GRI Pricing'!$F22>='2. GRI Pricing Inputs'!$P$33,'3. GRI Pricing'!$F22<='2. GRI Pricing Inputs'!$Q$33),'2. GRI Pricing Inputs'!$P$32,IF(AND('3. GRI Pricing'!$F22>='2. GRI Pricing Inputs'!$R$33,'3. GRI Pricing'!$F22<='2. GRI Pricing Inputs'!$S$33),'2. GRI Pricing Inputs'!$R$32,IF(AND('3. GRI Pricing'!$F22>='2. GRI Pricing Inputs'!$T$33,'3. GRI Pricing'!$F22<='2. GRI Pricing Inputs'!$U$33),'2. GRI Pricing Inputs'!$T$32,IF(AND('3. GRI Pricing'!$F22>='2. GRI Pricing Inputs'!$V$33,'3. GRI Pricing'!$F22<='2. GRI Pricing Inputs'!$W$33),'2. GRI Pricing Inputs'!$V$32,IF(AND('3. GRI Pricing'!$F22>='2. GRI Pricing Inputs'!$X$33,'3. GRI Pricing'!$F22<='2. GRI Pricing Inputs'!$Y$33),'2. GRI Pricing Inputs'!$X$32,IF(AND('3. GRI Pricing'!$F22>='2. GRI Pricing Inputs'!$Z$33,'3. GRI Pricing'!$F22<='2. GRI Pricing Inputs'!$AA$33),'2. GRI Pricing Inputs'!$Z$32,IF(AND('3. GRI Pricing'!$F22>='2. GRI Pricing Inputs'!$AB$33,'3. GRI Pricing'!$F22<='2. GRI Pricing Inputs'!$AC$33),'2. GRI Pricing Inputs'!$AB$32,IF(AND('3. GRI Pricing'!$F22>='2. GRI Pricing Inputs'!$AD$33,'3. GRI Pricing'!$F22<='2. GRI Pricing Inputs'!$AE$33),'2. GRI Pricing Inputs'!$AD$32,IF(AND('3. GRI Pricing'!$F22>='2. GRI Pricing Inputs'!$AF$33,'3. GRI Pricing'!$F22<='2. GRI Pricing Inputs'!$AG$33),'2. GRI Pricing Inputs'!$AF$32,IF(AND('3. GRI Pricing'!$F22>='2. GRI Pricing Inputs'!$AH$33,'3. GRI Pricing'!$F22<='2. GRI Pricing Inputs'!$AI$33),'2. GRI Pricing Inputs'!$AH$32,0)))))))))))))))) -> 0 | N22: {=IFERROR(INDEX('2. GRI Pricing Inputs'!$C$32:$AI$39,MATCH('3. GRI Pricing'!D22,'2. GRI Pricing Inputs'!$C$32:$C$39,0),(MATCH('3. GRI Pricing'!M22,'2. GRI Pricing Inputs'!$D$32:$AI$32,0)+1)),0)} -> 0 | O22: =IFERROR(INDEX('2. GRI Pricing Inputs'!$C$45:$AI$46,MATCH($O$16,'2. GRI Pricing Inputs'!$C$45:$C$46,0),MATCH(G22,'2. GRI Pricing Inputs'!$C$45:$AI$45,0)),0) -> 30 | P22: =IFERROR(INDEX('2. GRI Pricing Inputs'!$C$53:$AI$54,MATCH('3. GRI Pricing'!$P$16,'2. GRI Pricing Inputs'!$C$53:$C$54,0),MATCH('3. GRI Pricing'!H22,'2. GRI Pricing Inputs'!$C$53:$AI$53,0)),0) -> 5 | Q22: =IFERROR(INDEX('2. GRI Pricing Inputs'!$C$60:$AI$61,MATCH('3. GRI Pricing'!$Q$16,'2. GRI Pricing Inputs'!$C$60:$C$61,0),MATCH('1. Accomodation'!T26,'2. GRI Pricing Inputs'!$C$60:$AI$60,0)),0) -> 0 | R22: =IFERROR(INDEX('2. GRI Pricing Inputs'!$C$67:$AI$68,MATCH('3. GRI Pricing'!$R$16,'2. GRI Pricing Inputs'!$C$67:$C$68,0),MATCH('1. Accomodation'!U26,'2. GRI Pricing Inputs'!$C$67:$AI$67,0)),0) -> 0 | S22: =IF(D22=0,0,'2. GRI Pricing Inputs'!$AI$75) -> 70 | T22: =IFERROR(INDEX('2. GRI Pricing Inputs'!$C$82:$AI$83,MATCH('3. GRI Pricing'!$T$16,'2. GRI Pricing Inputs'!$C$82:$C$83,0),MATCH('1. Accomodation'!V26,'2. GRI Pricing Inputs'!$C$82:$AI$82,0)),0) -> 0 | U22: =IFERROR(INDEX('2. GRI Pricing Inputs'!$C$89:$AI$90,MATCH('3. GRI Pricing'!$U$16,'2. GRI Pricing Inputs'!$C$89:$C$90,0),MATCH('1. Accomodation'!W26,'2. GRI Pricing Inputs'!$C$89:$AI$89,0)),0) -> 0 | V22: =IFERROR(INDEX('2. GRI Pricing Inputs'!$C$97:$AI$98,MATCH('3. GRI Pricing'!$V$16,'2. GRI Pricing Inputs'!$C$97:$C$98,0),MATCH('1. Accomodation'!X26,'2. GRI Pricing Inputs'!$C$97:$AI$97,0)),0) -> 0 | W22: =IFERROR(INDEX('2. GRI Pricing Inputs'!$C$104:$AI$105,MATCH('3. GRI Pricing'!$W$16,'2. GRI Pricing Inputs'!$C$104:$C$105,0),MATCH('1. Accomodation'!Y26,'2. GRI Pricing Inputs'!$C$104:$AI$104,0)),0) -> 0 | X22: 0 | Y22: =K22+L22+N22+O22+P22+Q22+R22+S22+T22+U22+V22+W22+X22 -> 950 | AC22: =Y22*(1+'2. GRI Pricing Inputs'!$D$114)^(($AC$16-$AB$15)/365) -> 953.1698 | AD22: =AC22*(1+'2. GRI Pricing Inputs'!$D$114)^((AD$16-AC$16)/365) -> 956.24741 | AE22: =AD22*(1+'2. GRI Pricing Inputs'!$D$114)^((AE$16-AD$16)/365) -> 959.43805 | AF22: =AE22*(1+'2. GRI Pricing Inputs'!$D$114)^((AF$16-AE$16)/365) -> 962.63934 | AG22: =AF22*(1+'2. GRI Pricing Inputs'!$D$114)^((AG$16-AF$16)/365) -> 965.64377 | AH22: =AG22*(1+'2. GRI Pricing Inputs'!$D$114)^((AH$16-AG$16)/365) -> 968.86576 | AI22: =AH22*(1+'2. GRI Pricing Inputs'!$D$114)^((AI$16-AH$16)/365) -> 971.99406 | AJ22: =AI22*(1+'2. GRI Pricing Inputs'!$D$114)^((AJ$16-AI$16)/365) -> 975.23724 | AK22: =AJ22*(1+'2. GRI Pricing Inputs'!$D$114)^((AK$16-AJ$16)/365) -> 978.38611 | ... AO22: =AN22*(1+'2. GRI Pricing Inputs'!$D$114)^((AO$16-AN$16)/365) -> 991.40311
C23: ='1. Accomodation'!N27 -> 107N | D23: ='1. Accomodation'!P27 -> 2 Bed | E23: ='1. Accomodation'!Q27 -> 2 | F23: ='1. Accomodation'!O27 -> 624 | G23: ='1. Accomodation'!R27 -> 1 | H23: ='1. Accomodation'!S27 -> Forth Banks | K23: =IFERROR(INDEX('2. GRI Pricing Inputs'!$C$15:$AI$16,MATCH($K$16,'2. GRI Pricing Inputs'!$C$15:$C$16,0),MATCH(D23,'2. GRI Pricing Inputs'!$C$15:$AI$15,0)),0) -> 1110 | L23: =IFERROR(INDEX('2. GRI Pricing Inputs'!$C$22:$AI$23,MATCH($L$16,'2. GRI Pricing Inputs'!$C$22:$C$23,0),MATCH(E23,'2. GRI Pricing Inputs'!$C$22:$AI$22,0)),0) -> 0 | M23: =IF(AND('3. GRI Pricing'!$F23>='2. GRI Pricing Inputs'!$D$33,'3. GRI Pricing'!$F23<='2. GRI Pricing Inputs'!$E$33),'2. GRI Pricing Inputs'!$D$32,IF(AND('3. GRI Pricing'!$F23>='2. GRI Pricing Inputs'!$F$33,'3. GRI Pricing'!$F23<='2. GRI Pricing Inputs'!$G$33),'2. GRI Pricing Inputs'!$F$32,IF(AND('3. GRI Pricing'!$F23>='2. GRI Pricing Inputs'!$H$33,'3. GRI Pricing'!$F23<='2. GRI Pricing Inputs'!$I$33),'2. GRI Pricing Inputs'!$H$32,IF(AND('3. GRI Pricing'!$F23>='2. GRI Pricing Inputs'!$J$33,'3. GRI Pricing'!$F23<='2. GRI Pricing Inputs'!$K$33),'2. GRI Pricing Inputs'!$J$32,IF(AND('3. GRI Pricing'!$F23>='2. GRI Pricing Inputs'!$L$33,'3. GRI Pricing'!$F23<='2. GRI Pricing Inputs'!$M$33),'2. GRI Pricing Inputs'!$L$32,IF(AND('3. GRI Pricing'!$F23>='2. GRI Pricing Inputs'!$N$33,'3. GRI Pricing'!$F23<='2. GRI Pricing Inputs'!$O$33),'2. GRI Pricing Inputs'!$N$32,IF(AND('3. GRI Pricing'!$F23>='2. GRI Pricing Inputs'!$P$33,'3. GRI Pricing'!$F23<='2. GRI Pricing Inputs'!$Q$33),'2. GRI Pricing Inputs'!$P$32,IF(AND('3. GRI Pricing'!$F23>='2. GRI Pricing Inputs'!$R$33,'3. GRI Pricing'!$F23<='2. GRI Pricing Inputs'!$S$33),'2. GRI Pricing Inputs'!$R$32,IF(AND('3. GRI Pricing'!$F23>='2. GRI Pricing Inputs'!$T$33,'3. GRI Pricing'!$F23<='2. GRI Pricing Inputs'!$U$33),'2. GRI Pricing Inputs'!$T$32,IF(AND('3. GRI Pricing'!$F23>='2. GRI Pricing Inputs'!$V$33,'3. GRI Pricing'!$F23<='2. GRI Pricing Inputs'!$W$33),'2. GRI Pricing Inputs'!$V$32,IF(AND('3. GRI Pricing'!$F23>='2. GRI Pricing Inputs'!$X$33,'3. GRI Pricing'!$F23<='2. GRI Pricing Inputs'!$Y$33),'2. GRI Pricing Inputs'!$X$32,IF(AND('3. GRI Pricing'!$F23>='2. GRI Pricing Inputs'!$Z$33,'3. GRI Pricing'!$F23<='2. GRI Pricing Inputs'!$AA$33),'2. GRI Pricing Inputs'!$Z$32,IF(AND('3. GRI Pricing'!$F23>='2. GRI Pricing Inputs'!$AB$33,'3. GRI Pricing'!$F23<='2. GRI Pricing Inputs'!$AC$33),'2. GRI Pricing Inputs'!$AB$32,IF(AND('3. GRI Pricing'!$F23>='2. GRI Pricing Inputs'!$AD$33,'3. GRI Pricing'!$F23<='2. GRI Pricing Inputs'!$AE$33),'2. GRI Pricing Inputs'!$AD$32,IF(AND('3. GRI Pricing'!$F23>='2. GRI Pricing Inputs'!$AF$33,'3. GRI Pricing'!$F23<='2. GRI Pricing Inputs'!$AG$33),'2. GRI Pricing Inputs'!$AF$32,IF(AND('3. GRI Pricing'!$F23>='2. GRI Pricing Inputs'!$AH$33,'3. GRI Pricing'!$F23<='2. GRI Pricing Inputs'!$AI$33),'2. GRI Pricing Inputs'!$AH$32,0)))))))))))))))) -> 7 | N23: {=IFERROR(INDEX('2. GRI Pricing Inputs'!$C$32:$AI$39,MATCH('3. GRI Pricing'!D23,'2. GRI Pricing Inputs'!$C$32:$C$39,0),(MATCH('3. GRI Pricing'!M23,'2. GRI Pricing Inputs'!$D$32:$AI$32,0)+1)),0)} -> 10 | O23: =IFERROR(INDEX('2. GRI Pricing Inputs'!$C$45:$AI$46,MATCH($O$16,'2. GRI Pricing Inputs'!$C$45:$C$46,0),MATCH(G23,'2. GRI Pricing Inputs'!$C$45:$AI$45,0)),0) -> 30 | P23: =IFERROR(INDEX('2. GRI Pricing Inputs'!$C$53:$AI$54,MATCH('3. GRI Pricing'!$P$16,'2. GRI Pricing Inputs'!$C$53:$C$54,0),MATCH('3. GRI Pricing'!H23,'2. GRI Pricing Inputs'!$C$53:$AI$53,0)),0) -> 5 | Q23: =IFERROR(INDEX('2. GRI Pricing Inputs'!$C$60:$AI$61,MATCH('3. GRI Pricing'!$Q$16,'2. GRI Pricing Inputs'!$C$60:$C$61,0),MATCH('1. Accomodation'!T27,'2. GRI Pricing Inputs'!$C$60:$AI$60,0)),0) -> 0 | R23: =IFERROR(INDEX('2. GRI Pricing Inputs'!$C$67:$AI$68,MATCH('3. GRI Pricing'!$R$16,'2. GRI Pricing Inputs'!$C$67:$C$68,0),MATCH('1. Accomodation'!U27,'2. GRI Pricing Inputs'!$C$67:$AI$67,0)),0) -> 0 | S23: =IF(D23=0,0,'2. GRI Pricing Inputs'!$AI$75) -> 70 | T23: =IFERROR(INDEX('2. GRI Pricing Inputs'!$C$82:$AI$83,MATCH('3. GRI Pricing'!$T$16,'2. GRI Pricing Inputs'!$C$82:$C$83,0),MATCH('1. Accomodation'!V27,'2. GRI Pricing Inputs'!$C$82:$AI$82,0)),0) -> 0 | U23: =IFERROR(INDEX('2. GRI Pricing Inputs'!$C$89:$AI$90,MATCH('3. GRI Pricing'!$U$16,'2. GRI Pricing Inputs'!$C$89:$C$90,0),MATCH('1. Accomodation'!W27,'2. GRI Pricing Inputs'!$C$89:$AI$89,0)),0) -> 0 | V23: =IFERROR(INDEX('2. GRI Pricing Inputs'!$C$97:$AI$98,MATCH('3. GRI Pricing'!$V$16,'2. GRI Pricing Inputs'!$C$97:$C$98,0),MATCH('1. Accomodation'!X27,'2. GRI Pricing Inputs'!$C$97:$AI$97,0)),0) -> 0 | W23: =IFERROR(INDEX('2. GRI Pricing Inputs'!$C$104:$AI$105,MATCH('3. GRI Pricing'!$W$16,'2. GRI Pricing Inputs'!$C$104:$C$105,0),MATCH('1. Accomodation'!Y27,'2. GRI Pricing Inputs'!$C$104:$AI$104,0)),0) -> 0 | X23: 0 | Y23: =K23+L23+N23+O23+P23+Q23+R23+S23+T23+U23+V23+W23+X23 -> 1225 | AC23: =Y23*(1+'2. GRI Pricing Inputs'!$D$114)^(($AC$16-$AB$15)/365) -> 1229.0874 | AD23: =AC23*(1+'2. GRI Pricing Inputs'!$D$114)^((AD$16-AC$16)/365) -> 1233.0559 | AE23: =AD23*(1+'2. GRI Pricing Inputs'!$D$114)^((AE$16-AD$16)/365) -> 1237.1701 | AF23: =AE23*(1+'2. GRI Pricing Inputs'!$D$114)^((AF$16-AE$16)/365) -> 1241.2981 | AG23: =AF23*(1+'2. GRI Pricing Inputs'!$D$114)^((AG$16-AF$16)/365) -> 1245.1722 | AH23: =AG23*(1+'2. GRI Pricing Inputs'!$D$114)^((AH$16-AG$16)/365) -> 1249.3269 | AI23: =AH23*(1+'2. GRI Pricing Inputs'!$D$114)^((AI$16-AH$16)/365) -> 1253.3608 | AJ23: =AI23*(1+'2. GRI Pricing Inputs'!$D$114)^((AJ$16-AI$16)/365) -> 1257.5428 | AK23: =AJ23*(1+'2. GRI Pricing Inputs'!$D$114)^((AK$16-AJ$16)/365) -> 1261.6031 | ... AO23: =AN23*(1+'2. GRI Pricing Inputs'!$D$114)^((AO$16-AN$16)/365) -> 1278.3882
C24: ='1. Accomodation'!N28 -> 108N | D24: ='1. Accomodation'!P28 -> 2 Bed | E24: ='1. Accomodation'!Q28 -> 2 | F24: ='1. Accomodation'!O28 -> 624 | G24: ='1. Accomodation'!R28 -> 1 | H24: ='1. Accomodation'!S28 -> Forth Banks | K24: =IFERROR(INDEX('2. GRI Pricing Inputs'!$C$15:$AI$16,MATCH($K$16,'2. GRI Pricing Inputs'!$C$15:$C$16,0),MATCH(D24,'2. GRI Pricing Inputs'!$C$15:$AI$15,0)),0) -> 1110 | L24: =IFERROR(INDEX('2. GRI Pricing Inputs'!$C$22:$AI$23,MATCH($L$16,'2. GRI Pricing Inputs'!$C$22:$C$23,0),MATCH(E24,'2. GRI Pricing Inputs'!$C$22:$AI$22,0)),0) -> 0 | M24: =IF(AND('3. GRI Pricing'!$F24>='2. GRI Pricing Inputs'!$D$33,'3. GRI Pricing'!$F24<='2. GRI Pricing Inputs'!$E$33),'2. GRI Pricing Inputs'!$D$32,IF(AND('3. GRI Pricing'!$F24>='2. GRI Pricing Inputs'!$F$33,'3. GRI Pricing'!$F24<='2. GRI Pricing Inputs'!$G$33),'2. GRI Pricing Inputs'!$F$32,IF(AND('3. GRI Pricing'!$F24>='2. GRI Pricing Inputs'!$H$33,'3. GRI Pricing'!$F24<='2. GRI Pricing Inputs'!$I$33),'2. GRI Pricing Inputs'!$H$32,IF(AND('3. GRI Pricing'!$F24>='2. GRI Pricing Inputs'!$J$33,'3. GRI Pricing'!$F24<='2. GRI Pricing Inputs'!$K$33),'2. GRI Pricing Inputs'!$J$32,IF(AND('3. GRI Pricing'!$F24>='2. GRI Pricing Inputs'!$L$33,'3. GRI Pricing'!$F24<='2. GRI Pricing Inputs'!$M$33),'2. GRI Pricing Inputs'!$L$32,IF(AND('3. GRI Pricing'!$F24>='2. GRI Pricing Inputs'!$N$33,'3. GRI Pricing'!$F24<='2. GRI Pricing Inputs'!$O$33),'2. GRI Pricing Inputs'!$N$32,IF(AND('3. GRI Pricing'!$F24>='2. GRI Pricing Inputs'!$P$33,'3. GRI Pricing'!$F24<='2. GRI Pricing Inputs'!$Q$33),'2. GRI Pricing Inputs'!$P$32,IF(AND('3. GRI Pricing'!$F24>='2. GRI Pricing Inputs'!$R$33,'3. GRI Pricing'!$F24<='2. GRI Pricing Inputs'!$S$33),'2. GRI Pricing Inputs'!$R$32,IF(AND('3. GRI Pricing'!$F24>='2. GRI Pricing Inputs'!$T$33,'3. GRI Pricing'!$F24<='2. GRI Pricing Inputs'!$U$33),'2. GRI Pricing Inputs'!$T$32,IF(AND('3. GRI Pricing'!$F24>='2. GRI Pricing Inputs'!$V$33,'3. GRI Pricing'!$F24<='2. GRI Pricing Inputs'!$W$33),'2. GRI Pricing Inputs'!$V$32,IF(AND('3. GRI Pricing'!$F24>='2. GRI Pricing Inputs'!$X$33,'3. GRI Pricing'!$F24<='2. GRI Pricing Inputs'!$Y$33),'2. GRI Pricing Inputs'!$X$32,IF(AND('3. GRI Pricing'!$F24>='2. GRI Pricing Inputs'!$Z$33,'3. GRI Pricing'!$F24<='2. GRI Pricing Inputs'!$AA$33),'2. GRI Pricing Inputs'!$Z$32,IF(AND('3. GRI Pricing'!$F24>='2. GRI Pricing Inputs'!$AB$33,'3. GRI Pricing'!$F24<='2. GRI Pricing Inputs'!$AC$33),'2. GRI Pricing Inputs'!$AB$32,IF(AND('3. GRI Pricing'!$F24>='2. GRI Pricing Inputs'!$AD$33,'3. GRI Pricing'!$F24<='2. GRI Pricing Inputs'!$AE$33),'2. GRI Pricing Inputs'!$AD$32,IF(AND('3. GRI Pricing'!$F24>='2. GRI Pricing Inputs'!$AF$33,'3. GRI Pricing'!$F24<='2. GRI Pricing Inputs'!$AG$33),'2. GRI Pricing Inputs'!$AF$32,IF(AND('3. GRI Pricing'!$F24>='2. GRI Pricing Inputs'!$AH$33,'3. GRI Pricing'!$F24<='2. GRI Pricing Inputs'!$AI$33),'2. GRI Pricing Inputs'!$AH$32,0)))))))))))))))) -> 7 | N24: {=IFERROR(INDEX('2. GRI Pricing Inputs'!$C$32:$AI$39,MATCH('3. GRI Pricing'!D24,'2. GRI Pricing Inputs'!$C$32:$C$39,0),(MATCH('3. GRI Pricing'!M24,'2. GRI Pricing Inputs'!$D$32:$AI$32,0)+1)),0)} -> 10 | O24: =IFERROR(INDEX('2. GRI Pricing Inputs'!$C$45:$AI$46,MATCH($O$16,'2. GRI Pricing Inputs'!$C$45:$C$46,0),MATCH(G24,'2. GRI Pricing Inputs'!$C$45:$AI$45,0)),0) -> 30 | P24: =IFERROR(INDEX('2. GRI Pricing Inputs'!$C$53:$AI$54,MATCH('3. GRI Pricing'!$P$16,'2. GRI Pricing Inputs'!$C$53:$C$54,0),MATCH('3. GRI Pricing'!H24,'2. GRI Pricing Inputs'!$C$53:$AI$53,0)),0) -> 5 | Q24: =IFERROR(INDEX('2. GRI Pricing Inputs'!$C$60:$AI$61,MATCH('3. GRI Pricing'!$Q$16,'2. GRI Pricing Inputs'!$C$60:$C$61,0),MATCH('1. Accomodation'!T28,'2. GRI Pricing Inputs'!$C$60:$AI$60,0)),0) -> 0 | R24: =IFERROR(INDEX('2. GRI Pricing Inputs'!$C$67:$AI$68,MATCH('3. GRI Pricing'!$R$16,'2. GRI Pricing Inputs'!$C$67:$C$68,0),MATCH('1. Accomodation'!U28,'2. GRI Pricing Inputs'!$C$67:$AI$67,0)),0) -> 0 | S24: =IF(D24=0,0,'2. GRI Pricing Inputs'!$AI$75) -> 70 | T24: =IFERROR(INDEX('2. GRI Pricing Inputs'!$C$82:$AI$83,MATCH('3. GRI Pricing'!$T$16,'2. GRI Pricing Inputs'!$C$82:$C$83,0),MATCH('1. Accomodation'!V28,'2. GRI Pricing Inputs'!$C$82:$AI$82,0)),0) -> 0 | U24: =IFERROR(INDEX('2. GRI Pricing Inputs'!$C$89:$AI$90,MATCH('3. GRI Pricing'!$U$16,'2. GRI Pricing Inputs'!$C$89:$C$90,0),MATCH('1. Accomodation'!W28,'2. GRI Pricing Inputs'!$C$89:$AI$89,0)),0) -> 0 | V24: =IFERROR(INDEX('2. GRI Pricing Inputs'!$C$97:$AI$98,MATCH('3. GRI Pricing'!$V$16,'2. GRI Pricing Inputs'!$C$97:$C$98,0),MATCH('1. Accomodation'!X28,'2. GRI Pricing Inputs'!$C$97:$AI$97,0)),0) -> 0 | W24: =IFERROR(INDEX('2. GRI Pricing Inputs'!$C$104:$AI$105,MATCH('3. GRI Pricing'!$W$16,'2. GRI Pricing Inputs'!$C$104:$C$105,0),MATCH('1. Accomodation'!Y28,'2. GRI Pricing Inputs'!$C$104:$AI$104,0)),0) -> 0 | X24: 0 | Y24: =K24+L24+N24+O24+P24+Q24+R24+S24+T24+U24+V24+W24+X24 -> 1225 | AC24: =Y24*(1+'2. GRI Pricing Inputs'!$D$114)^(($AC$16-$AB$15)/365) -> 1229.0874 | AD24: =AC24*(1+'2. GRI Pricing Inputs'!$D$114)^((AD$16-AC$16)/365) -> 1233.0559 | AE24: =AD24*(1+'2. GRI Pricing Inputs'!$D$114)^((AE$16-AD$16)/365) -> 1237.1701 | AF24: =AE24*(1+'2. GRI Pricing Inputs'!$D$114)^((AF$16-AE$16)/365) -> 1241.2981 | AG24: =AF24*(1+'2. GRI Pricing Inputs'!$D$114)^((AG$16-AF$16)/365) -> 1245.1722 | AH24: =AG24*(1+'2. GRI Pricing Inputs'!$D$114)^((AH$16-AG$16)/365) -> 1249.3269 | AI24: =AH24*(1+'2. GRI Pricing Inputs'!$D$114)^((AI$16-AH$16)/365) -> 1253.3608 | AJ24: =AI24*(1+'2. GRI Pricing Inputs'!$D$114)^((AJ$16-AI$16)/365) -> 1257.5428 | AK24: =AJ24*(1+'2. GRI Pricing Inputs'!$D$114)^((AK$16-AJ$16)/365) -> 1261.6031 | ... AO24: =AN24*(1+'2. GRI Pricing Inputs'!$D$114)^((AO$16-AN$16)/365) -> 1278.3882
C25: ='1. Accomodation'!N29 -> 109N | D25: ='1. Accomodation'!P29 -> 2 Bed | E25: ='1. Accomodation'!Q29 -> 2 | F25: ='1. Accomodation'!O29 -> 657 | G25: ='1. Accomodation'!R29 -> 1 | H25: ='1. Accomodation'!S29 -> River - Partial | K25: =IFERROR(INDEX('2. GRI Pricing Inputs'!$C$15:$AI$16,MATCH($K$16,'2. GRI Pricing Inputs'!$C$15:$C$16,0),MATCH(D25,'2. GRI Pricing Inputs'!$C$15:$AI$15,0)),0) -> 1110 | L25: =IFERROR(INDEX('2. GRI Pricing Inputs'!$C$22:$AI$23,MATCH($L$16,'2. GRI Pricing Inputs'!$C$22:$C$23,0),MATCH(E25,'2. GRI Pricing Inputs'!$C$22:$AI$22,0)),0) -> 0 | M25: =IF(AND('3. GRI Pricing'!$F25>='2. GRI Pricing Inputs'!$D$33,'3. GRI Pricing'!$F25<='2. GRI Pricing Inputs'!$E$33),'2. GRI Pricing Inputs'!$D$32,IF(AND('3. GRI Pricing'!$F25>='2. GRI Pricing Inputs'!$F$33,'3. GRI Pricing'!$F25<='2. GRI Pricing Inputs'!$G$33),'2. GRI Pricing Inputs'!$F$32,IF(AND('3. GRI Pricing'!$F25>='2. GRI Pricing Inputs'!$H$33,'3. GRI Pricing'!$F25<='2. GRI Pricing Inputs'!$I$33),'2. GRI Pricing Inputs'!$H$32,IF(AND('3. GRI Pricing'!$F25>='2. GRI Pricing Inputs'!$J$33,'3. GRI Pricing'!$F25<='2. GRI Pricing Inputs'!$K$33),'2. GRI Pricing Inputs'!$J$32,IF(AND('3. GRI Pricing'!$F25>='2. GRI Pricing Inputs'!$L$33,'3. GRI Pricing'!$F25<='2. GRI Pricing Inputs'!$M$33),'2. GRI Pricing Inputs'!$L$32,IF(AND('3. GRI Pricing'!$F25>='2. GRI Pricing Inputs'!$N$33,'3. GRI Pricing'!$F25<='2. GRI Pricing Inputs'!$O$33),'2. GRI Pricing Inputs'!$N$32,IF(AND('3. GRI Pricing'!$F25>='2. GRI Pricing Inputs'!$P$33,'3. GRI Pricing'!$F25<='2. GRI Pricing Inputs'!$Q$33),'2. GRI Pricing Inputs'!$P$32,IF(AND('3. GRI Pricing'!$F25>='2. GRI Pricing Inputs'!$R$33,'3. GRI Pricing'!$F25<='2. GRI Pricing Inputs'!$S$33),'2. GRI Pricing Inputs'!$R$32,IF(AND('3. GRI Pricing'!$F25>='2. GRI Pricing Inputs'!$T$33,'3. GRI Pricing'!$F25<='2. GRI Pricing Inputs'!$U$33),'2. GRI Pricing Inputs'!$T$32,IF(AND('3. GRI Pricing'!$F25>='2. GRI Pricing Inputs'!$V$33,'3. GRI Pricing'!$F25<='2. GRI Pricing Inputs'!$W$33),'2. GRI Pricing Inputs'!$V$32,IF(AND('3. GRI Pricing'!$F25>='2. GRI Pricing Inputs'!$X$33,'3. GRI Pricing'!$F25<='2. GRI Pricing Inputs'!$Y$33),'2. GRI Pricing Inputs'!$X$32,IF(AND('3. GRI Pricing'!$F25>='2. GRI Pricing Inputs'!$Z$33,'3. GRI Pricing'!$F25<='2. GRI Pricing Inputs'!$AA$33),'2. GRI Pricing Inputs'!$Z$32,IF(AND('3. GRI Pricing'!$F25>='2. GRI Pricing Inputs'!$AB$33,'3. GRI Pricing'!$F25<='2. GRI Pricing Inputs'!$AC$33),'2. GRI Pricing Inputs'!$AB$32,IF(AND('3. GRI Pricing'!$F25>='2. GRI Pricing Inputs'!$AD$33,'3. GRI Pricing'!$F25<='2. GRI Pricing Inputs'!$AE$33),'2. GRI Pricing Inputs'!$AD$32,IF(AND('3. GRI Pricing'!$F25>='2. GRI Pricing Inputs'!$AF$33,'3. GRI Pricing'!$F25<='2. GRI Pricing Inputs'!$AG$33),'2. GRI Pricing Inputs'!$AF$32,IF(AND('3. GRI Pricing'!$F25>='2. GRI Pricing Inputs'!$AH$33,'3. GRI Pricing'!$F25<='2. GRI Pricing Inputs'!$AI$33),'2. GRI Pricing Inputs'!$AH$32,0)))))))))))))))) -> 8 | N25: {=IFERROR(INDEX('2. GRI Pricing Inputs'!$C$32:$AI$39,MATCH('3. GRI Pricing'!D25,'2. GRI Pricing Inputs'!$C$32:$C$39,0),(MATCH('3. GRI Pricing'!M25,'2. GRI Pricing Inputs'!$D$32:$AI$32,0)+1)),0)} -> 20 | O25: =IFERROR(INDEX('2. GRI Pricing Inputs'!$C$45:$AI$46,MATCH($O$16,'2. GRI Pricing Inputs'!$C$45:$C$46,0),MATCH(G25,'2. GRI Pricing Inputs'!$C$45:$AI$45,0)),0) -> 30 | P25: =IFERROR(INDEX('2. GRI Pricing Inputs'!$C$53:$AI$54,MATCH('3. GRI Pricing'!$P$16,'2. GRI Pricing Inputs'!$C$53:$C$54,0),MATCH('3. GRI Pricing'!H25,'2. GRI Pricing Inputs'!$C$53:$AI$53,0)),0) -> 45 | Q25: =IFERROR(INDEX('2. GRI Pricing Inputs'!$C$60:$AI$61,MATCH('3. GRI Pricing'!$Q$16,'2. GRI Pricing Inputs'!$C$60:$C$61,0),MATCH('1. Accomodation'!T29,'2. GRI Pricing Inputs'!$C$60:$AI$60,0)),0) -> 0 | R25: =IFERROR(INDEX('2. GRI Pricing Inputs'!$C$67:$AI$68,MATCH('3. GRI Pricing'!$R$16,'2. GRI Pricing Inputs'!$C$67:$C$68,0),MATCH('1. Accomodation'!U29,'2. GRI Pricing Inputs'!$C$67:$AI$67,0)),0) -> 0 | S25: =IF(D25=0,0,'2. GRI Pricing Inputs'!$AI$75) -> 70 | T25: =IFERROR(INDEX('2. GRI Pricing Inputs'!$C$82:$AI$83,MATCH('3. GRI Pricing'!$T$16,'2. GRI Pricing Inputs'!$C$82:$C$83,0),MATCH('1. Accomodation'!V29,'2. GRI Pricing Inputs'!$C$82:$AI$82,0)),0) -> 0 | U25: =IFERROR(INDEX('2. GRI Pricing Inputs'!$C$89:$AI$90,MATCH('3. GRI Pricing'!$U$16,'2. GRI Pricing Inputs'!$C$89:$C$90,0),MATCH('1. Accomodation'!W29,'2. GRI Pricing Inputs'!$C$89:$AI$89,0)),0) -> 0 | V25: =IFERROR(INDEX('2. GRI Pricing Inputs'!$C$97:$AI$98,MATCH('3. GRI Pricing'!$V$16,'2. GRI Pricing Inputs'!$C$97:$C$98,0),MATCH('1. Accomodation'!X29,'2. GRI Pricing Inputs'!$C$97:$AI$97,0)),0) -> 0 | W25: =IFERROR(INDEX('2. GRI Pricing Inputs'!$C$104:$AI$105,MATCH('3. GRI Pricing'!$W$16,'2. GRI Pricing Inputs'!$C$104:$C$105,0),MATCH('1. Accomodation'!Y29,'2. GRI Pricing Inputs'!$C$104:$AI$104,0)),0) -> 0 | X25: 0 | Y25: =K25+L25+N25+O25+P25+Q25+R25+S25+T25+U25+V25+W25+X25 -> 1275 | AC25: =Y25*(1+'2. GRI Pricing Inputs'!$D$114)^(($AC$16-$AB$15)/365) -> 1279.2542 | AD25: =AC25*(1+'2. GRI Pricing Inputs'!$D$114)^((AD$16-AC$16)/365) -> 1283.3847 | AE25: =AD25*(1+'2. GRI Pricing Inputs'!$D$114)^((AE$16-AD$16)/365) -> 1287.6669 | AF25: =AE25*(1+'2. GRI Pricing Inputs'!$D$114)^((AF$16-AE$16)/365) -> 1291.9633 | AG25: =AF25*(1+'2. GRI Pricing Inputs'!$D$114)^((AG$16-AF$16)/365) -> 1295.9956 | AH25: =AG25*(1+'2. GRI Pricing Inputs'!$D$114)^((AH$16-AG$16)/365) -> 1300.3198 | AI25: =AH25*(1+'2. GRI Pricing Inputs'!$D$114)^((AI$16-AH$16)/365) -> 1304.5183 | AJ25: =AI25*(1+'2. GRI Pricing Inputs'!$D$114)^((AJ$16-AI$16)/365) -> 1308.871 | AK25: =AJ25*(1+'2. GRI Pricing Inputs'!$D$114)^((AK$16-AJ$16)/365) -> 1313.0971 | ... AO25: =AN25*(1+'2. GRI Pricing Inputs'!$D$114)^((AO$16-AN$16)/365) -> 1330.5673
C26: ='1. Accomodation'!N30 -> 110N | D26: ='1. Accomodation'!P30 -> 2 Bed | E26: ='1. Accomodation'!Q30 -> 2 | F26: ='1. Accomodation'!O30 -> 700 | G26: ='1. Accomodation'!R30 -> 1 | H26: ='1. Accomodation'!S30 -> Forth Banks - Partial | K26: =IFERROR(INDEX('2. GRI Pricing Inputs'!$C$15:$AI$16,MATCH($K$16,'2. GRI Pricing Inputs'!$C$15:$C$16,0),MATCH(D26,'2. GRI Pricing Inputs'!$C$15:$AI$15,0)),0) -> 1110 | L26: =IFERROR(INDEX('2. GRI Pricing Inputs'!$C$22:$AI$23,MATCH($L$16,'2. GRI Pricing Inputs'!$C$22:$C$23,0),MATCH(E26,'2. GRI Pricing Inputs'!$C$22:$AI$22,0)),0) -> 0 | M26: =IF(AND('3. GRI Pricing'!$F26>='2. GRI Pricing Inputs'!$D$33,'3. GRI Pricing'!$F26<='2. GRI Pricing Inputs'!$E$33),'2. GRI Pricing Inputs'!$D$32,IF(AND('3. GRI Pricing'!$F26>='2. GRI Pricing Inputs'!$F$33,'3. GRI Pricing'!$F26<='2. GRI Pricing Inputs'!$G$33),'2. GRI Pricing Inputs'!$F$32,IF(AND('3. GRI Pricing'!$F26>='2. GRI Pricing Inputs'!$H$33,'3. GRI Pricing'!$F26<='2. GRI Pricing Inputs'!$I$33),'2. GRI Pricing Inputs'!$H$32,IF(AND('3. GRI Pricing'!$F26>='2. GRI Pricing Inputs'!$J$33,'3. GRI Pricing'!$F26<='2. GRI Pricing Inputs'!$K$33),'2. GRI Pricing Inputs'!$J$32,IF(AND('3. GRI Pricing'!$F26>='2. GRI Pricing Inputs'!$L$33,'3. GRI Pricing'!$F26<='2. GRI Pricing Inputs'!$M$33),'2. GRI Pricing Inputs'!$L$32,IF(AND('3. GRI Pricing'!$F26>='2. GRI Pricing Inputs'!$N$33,'3. GRI Pricing'!$F26<='2. GRI Pricing Inputs'!$O$33),'2. GRI Pricing Inputs'!$N$32,IF(AND('3. GRI Pricing'!$F26>='2. GRI Pricing Inputs'!$P$33,'3. GRI Pricing'!$F26<='2. GRI Pricing Inputs'!$Q$33),'2. GRI Pricing Inputs'!$P$32,IF(AND('3. GRI Pricing'!$F26>='2. GRI Pricing Inputs'!$R$33,'3. GRI Pricing'!$F26<='2. GRI Pricing Inputs'!$S$33),'2. GRI Pricing Inputs'!$R$32,IF(AND('3. GRI Pricing'!$F26>='2. GRI Pricing Inputs'!$T$33,'3. GRI Pricing'!$F26<='2. GRI Pricing Inputs'!$U$33),'2. GRI Pricing Inputs'!$T$32,IF(AND('3. GRI Pricing'!$F26>='2. GRI Pricing Inputs'!$V$33,'3. GRI Pricing'!$F26<='2. GRI Pricing Inputs'!$W$33),'2. GRI Pricing Inputs'!$V$32,IF(AND('3. GRI Pricing'!$F26>='2. GRI Pricing Inputs'!$X$33,'3. GRI Pricing'!$F26<='2. GRI Pricing Inputs'!$Y$33),'2. GRI Pricing Inputs'!$X$32,IF(AND('3. GRI Pricing'!$F26>='2. GRI Pricing Inputs'!$Z$33,'3. GRI Pricing'!$F26<='2. GRI Pricing Inputs'!$AA$33),'2. GRI Pricing Inputs'!$Z$32,IF(AND('3. GRI Pricing'!$F26>='2. GRI Pricing Inputs'!$AB$33,'3. GRI Pricing'!$F26<='2. GRI Pricing Inputs'!$AC$33),'2. GRI Pricing Inputs'!$AB$32,IF(AND('3. GRI Pricing'!$F26>='2. GRI Pricing Inputs'!$AD$33,'3. GRI Pricing'!$F26<='2. GRI Pricing Inputs'!$AE$33),'2. GRI Pricing Inputs'!$AD$32,IF(AND('3. GRI Pricing'!$F26>='2. GRI Pricing Inputs'!$AF$33,'3. GRI Pricing'!$F26<='2. GRI Pricing Inputs'!$AG$33),'2. GRI Pricing Inputs'!$AF$32,IF(AND('3. GRI Pricing'!$F26>='2. GRI Pricing Inputs'!$AH$33,'3. GRI Pricing'!$F26<='2. GRI Pricing Inputs'!$AI$33),'2. GRI Pricing Inputs'!$AH$32,0)))))))))))))))) -> 12 | N26: {=IFERROR(INDEX('2. GRI Pricing Inputs'!$C$32:$AI$39,MATCH('3. GRI Pricing'!D26,'2. GRI Pricing Inputs'!$C$32:$C$39,0),(MATCH('3. GRI Pricing'!M26,'2. GRI Pricing Inputs'!$D$32:$AI$32,0)+1)),0)} -> 70 | O26: =IFERROR(INDEX('2. GRI Pricing Inputs'!$C$45:$AI$46,MATCH($O$16,'2. GRI Pricing Inputs'!$C$45:$C$46,0),MATCH(G26,'2. GRI Pricing Inputs'!$C$45:$AI$45,0)),0) -> 30 | P26: =IFERROR(INDEX('2. GRI Pricing Inputs'!$C$53:$AI$54,MATCH('3. GRI Pricing'!$P$16,'2. GRI Pricing Inputs'!$C$53:$C$54,0),MATCH('3. GRI Pricing'!H26,'2. GRI Pricing Inputs'!$C$53:$AI$53,0)),0) -> 40 | Q26: =IFERROR(INDEX('2. GRI Pricing Inputs'!$C$60:$AI$61,MATCH('3. GRI Pricing'!$Q$16,'2. GRI Pricing Inputs'!$C$60:$C$61,0),MATCH('1. Accomodation'!T30,'2. GRI Pricing Inputs'!$C$60:$AI$60,0)),0) -> 0 | R26: =IFERROR(INDEX('2. GRI Pricing Inputs'!$C$67:$AI$68,MATCH('3. GRI Pricing'!$R$16,'2. GRI Pricing Inputs'!$C$67:$C$68,0),MATCH('1. Accomodation'!U30,'2. GRI Pricing Inputs'!$C$67:$AI$67,0)),0) -> 0 | S26: =IF(D26=0,0,'2. GRI Pricing Inputs'!$AI$75) -> 70 | T26: =IFERROR(INDEX('2. GRI Pricing Inputs'!$C$82:$AI$83,MATCH('3. GRI Pricing'!$T$16,'2. GRI Pricing Inputs'!$C$82:$C$83,0),MATCH('1. Accomodation'!V30,'2. GRI Pricing Inputs'!$C$82:$AI$82,0)),0) -> 0 | U26: =IFERROR(INDEX('2. GRI Pricing Inputs'!$C$89:$AI$90,MATCH('3. GRI Pricing'!$U$16,'2. GRI Pricing Inputs'!$C$89:$C$90,0),MATCH('1. Accomodation'!W30,'2. GRI Pricing Inputs'!$C$89:$AI$89,0)),0) -> 0 | V26: =IFERROR(INDEX('2. GRI Pricing Inputs'!$C$97:$AI$98,MATCH('3. GRI Pricing'!$V$16,'2. GRI Pricing Inputs'!$C$97:$C$98,0),MATCH('1. Accomodation'!X30,'2. GRI Pricing Inputs'!$C$97:$AI$97,0)),0) -> 0 | W26: =IFERROR(INDEX('2. GRI Pricing Inputs'!$C$104:$AI$105,MATCH('3. GRI Pricing'!$W$16,'2. GRI Pricing Inputs'!$C$104:$C$105,0),MATCH('1. Accomodation'!Y30,'2. GRI Pricing Inputs'!$C$104:$AI$104,0)),0) -> 0 | X26: 0 | Y26: =K26+L26+N26+O26+P26+Q26+R26+S26+T26+U26+V26+W26+X26 -> 1320 | AC26: =Y26*(1+'2. GRI Pricing Inputs'!$D$114)^(($AC$16-$AB$15)/365) -> 1324.4043 | AD26: =AC26*(1+'2. GRI Pricing Inputs'!$D$114)^((AD$16-AC$16)/365) -> 1328.6806 | AE26: =AD26*(1+'2. GRI Pricing Inputs'!$D$114)^((AE$16-AD$16)/365) -> 1333.1139 | AF26: =AE26*(1+'2. GRI Pricing Inputs'!$D$114)^((AF$16-AE$16)/365) -> 1337.562 | AG26: =AF26*(1+'2. GRI Pricing Inputs'!$D$114)^((AG$16-AF$16)/365) -> 1341.7366 | AH26: =AG26*(1+'2. GRI Pricing Inputs'!$D$114)^((AH$16-AG$16)/365) -> 1346.2135 | AI26: =AH26*(1+'2. GRI Pricing Inputs'!$D$114)^((AI$16-AH$16)/365) -> 1350.5602 | AJ26: =AI26*(1+'2. GRI Pricing Inputs'!$D$114)^((AJ$16-AI$16)/365) -> 1355.0665 | AK26: =AJ26*(1+'2. GRI Pricing Inputs'!$D$114)^((AK$16-AJ$16)/365) -> 1359.4417 | ... AO26: =AN26*(1+'2. GRI Pricing Inputs'!$D$114)^((AO$16-AN$16)/365) -> 1377.5285
C27: ='1. Accomodation'!N31 -> 111N | D27: ='1. Accomodation'!P31 -> 2 Bed | E27: ='1. Accomodation'!Q31 -> 2 | F27: ='1. Accomodation'!O31 -> 689 | G27: ='1. Accomodation'!R31 -> 1 | H27: ='1. Accomodation'!S31 -> Courtyard - dual | K27: =IFERROR(INDEX('2. GRI Pricing Inputs'!$C$15:$AI$16,MATCH($K$16,'2. GRI Pricing Inputs'!$C$15:$C$16,0),MATCH(D27,'2. GRI Pricing Inputs'!$C$15:$AI$15,0)),0) -> 1110 | L27: =IFERROR(INDEX('2. GRI Pricing Inputs'!$C$22:$AI$23,MATCH($L$16,'2. GRI Pricing Inputs'!$C$22:$C$23,0),MATCH(E27,'2. GRI Pricing Inputs'!$C$22:$AI$22,0)),0) -> 0 | M27: =IF(AND('3. GRI Pricing'!$F27>='2. GRI Pricing Inputs'!$D$33,'3. GRI Pricing'!$F27<='2. GRI Pricing Inputs'!$E$33),'2. GRI Pricing Inputs'!$D$32,IF(AND('3. GRI Pricing'!$F27>='2. GRI Pricing Inputs'!$F$33,'3. GRI Pricing'!$F27<='2. GRI Pricing Inputs'!$G$33),'2. GRI Pricing Inputs'!$F$32,IF(AND('3. GRI Pricing'!$F27>='2. GRI Pricing Inputs'!$H$33,'3. GRI Pricing'!$F27<='2. GRI Pricing Inputs'!$I$33),'2. GRI Pricing Inputs'!$H$32,IF(AND('3. GRI Pricing'!$F27>='2. GRI Pricing Inputs'!$J$33,'3. GRI Pricing'!$F27<='2. GRI Pricing Inputs'!$K$33),'2. GRI Pricing Inputs'!$J$32,IF(AND('3. GRI Pricing'!$F27>='2. GRI Pricing Inputs'!$L$33,'3. GRI Pricing'!$F27<='2. GRI Pricing Inputs'!$M$33),'2. GRI Pricing Inputs'!$L$32,IF(AND('3. GRI Pricing'!$F27>='2. GRI Pricing Inputs'!$N$33,'3. GRI Pricing'!$F27<='2. GRI Pricing Inputs'!$O$33),'2. GRI Pricing Inputs'!$N$32,IF(AND('3. GRI Pricing'!$F27>='2. GRI Pricing Inputs'!$P$33,'3. GRI Pricing'!$F27<='2. GRI Pricing Inputs'!$Q$33),'2. GRI Pricing Inputs'!$P$32,IF(AND('3. GRI Pricing'!$F27>='2. GRI Pricing Inputs'!$R$33,'3. GRI Pricing'!$F27<='2. GRI Pricing Inputs'!$S$33),'2. GRI Pricing Inputs'!$R$32,IF(AND('3. GRI Pricing'!$F27>='2. GRI Pricing Inputs'!$T$33,'3. GRI Pricing'!$F27<='2. GRI Pricing Inputs'!$U$33),'2. GRI Pricing Inputs'!$T$32,IF(AND('3. GRI Pricing'!$F27>='2. GRI Pricing Inputs'!$V$33,'3. GRI Pricing'!$F27<='2. GRI Pricing Inputs'!$W$33),'2. GRI Pricing Inputs'!$V$32,IF(AND('3. GRI Pricing'!$F27>='2. GRI Pricing Inputs'!$X$33,'3. GRI Pricing'!$F27<='2. GRI Pricing Inputs'!$Y$33),'2. GRI Pricing Inputs'!$X$32,IF(AND('3. GRI Pricing'!$F27>='2. GRI Pricing Inputs'!$Z$33,'3. GRI Pricing'!$F27<='2. GRI Pricing Inputs'!$AA$33),'2. GRI Pricing Inputs'!$Z$32,IF(AND('3. GRI Pricing'!$F27>='2. GRI Pricing Inputs'!$AB$33,'3. GRI Pricing'!$F27<='2. GRI Pricing Inputs'!$AC$33),'2. GRI Pricing Inputs'!$AB$32,IF(AND('3. GRI Pricing'!$F27>='2. GRI Pricing Inputs'!$AD$33,'3. GRI Pricing'!$F27<='2. GRI Pricing Inputs'!$AE$33),'2. GRI Pricing Inputs'!$AD$32,IF(AND('3. GRI Pricing'!$F27>='2. GRI Pricing Inputs'!$AF$33,'3. GRI Pricing'!$F27<='2. GRI Pricing Inputs'!$AG$33),'2. GRI Pricing Inputs'!$AF$32,IF(AND('3. GRI Pricing'!$F27>='2. GRI Pricing Inputs'!$AH$33,'3. GRI Pricing'!$F27<='2. GRI Pricing Inputs'!$AI$33),'2. GRI Pricing Inputs'!$AH$32,0)))))))))))))))) -> 11 | N27: {=IFERROR(INDEX('2. GRI Pricing Inputs'!$C$32:$AI$39,MATCH('3. GRI Pricing'!D27,'2. GRI Pricing Inputs'!$C$32:$C$39,0),(MATCH('3. GRI Pricing'!M27,'2. GRI Pricing Inputs'!$D$32:$AI$32,0)+1)),0)} -> 65 | O27: =IFERROR(INDEX('2. GRI Pricing Inputs'!$C$45:$AI$46,MATCH($O$16,'2. GRI Pricing Inputs'!$C$45:$C$46,0),MATCH(G27,'2. GRI Pricing Inputs'!$C$45:$AI$45,0)),0) -> 30 | P27: =IFERROR(INDEX('2. GRI Pricing Inputs'!$C$53:$AI$54,MATCH('3. GRI Pricing'!$P$16,'2. GRI Pricing Inputs'!$C$53:$C$54,0),MATCH('3. GRI Pricing'!H27,'2. GRI Pricing Inputs'!$C$53:$AI$53,0)),0) -> 55 | Q27: =IFERROR(INDEX('2. GRI Pricing Inputs'!$C$60:$AI$61,MATCH('3. GRI Pricing'!$Q$16,'2. GRI Pricing Inputs'!$C$60:$C$61,0),MATCH('1. Accomodation'!T31,'2. GRI Pricing Inputs'!$C$60:$AI$60,0)),0) -> 0 | R27: =IFERROR(INDEX('2. GRI Pricing Inputs'!$C$67:$AI$68,MATCH('3. GRI Pricing'!$R$16,'2. GRI Pricing Inputs'!$C$67:$C$68,0),MATCH('1. Accomodation'!U31,'2. GRI Pricing Inputs'!$C$67:$AI$67,0)),0) -> 40 | S27: =IF(D27=0,0,'2. GRI Pricing Inputs'!$AI$75) -> 70 | T27: =IFERROR(INDEX('2. GRI Pricing Inputs'!$C$82:$AI$83,MATCH('3. GRI Pricing'!$T$16,'2. GRI Pricing Inputs'!$C$82:$C$83,0),MATCH('1. Accomodation'!V31,'2. GRI Pricing Inputs'!$C$82:$AI$82,0)),0) -> 0 | U27: =IFERROR(INDEX('2. GRI Pricing Inputs'!$C$89:$AI$90,MATCH('3. GRI Pricing'!$U$16,'2. GRI Pricing Inputs'!$C$89:$C$90,0),MATCH('1. Accomodation'!W31,'2. GRI Pricing Inputs'!$C$89:$AI$89,0)),0) -> 0 | V27: =IFERROR(INDEX('2. GRI Pricing Inputs'!$C$97:$AI$98,MATCH('3. GRI Pricing'!$V$16,'2. GRI Pricing Inputs'!$C$97:$C$98,0),MATCH('1. Accomodation'!X31,'2. GRI Pricing Inputs'!$C$97:$AI$97,0)),0) -> 0 | W27: =IFERROR(INDEX('2. GRI Pricing Inputs'!$C$104:$AI$105,MATCH('3. GRI Pricing'!$W$16,'2. GRI Pricing Inputs'!$C$104:$C$105,0),MATCH('1. Accomodation'!Y31,'2. GRI Pricing Inputs'!$C$104:$AI$104,0)),0) -> 0 | X27: 0 | Y27: =K27+L27+N27+O27+P27+Q27+R27+S27+T27+U27+V27+W27+X27 -> 1370 | AC27: =Y27*(1+'2. GRI Pricing Inputs'!$D$114)^(($AC$16-$AB$15)/365) -> 1374.5712 | AD27: =AC27*(1+'2. GRI Pricing Inputs'!$D$114)^((AD$16-AC$16)/365) -> 1379.0094 | AE27: =AD27*(1+'2. GRI Pricing Inputs'!$D$114)^((AE$16-AD$16)/365) -> 1383.6107 | AF27: =AE27*(1+'2. GRI Pricing Inputs'!$D$114)^((AF$16-AE$16)/365) -> 1388.2273 | AG27: =AF27*(1+'2. GRI Pricing Inputs'!$D$114)^((AG$16-AF$16)/365) -> 1392.56 | AH27: =AG27*(1+'2. GRI Pricing Inputs'!$D$114)^((AH$16-AG$16)/365) -> 1397.2064 | AI27: =AH27*(1+'2. GRI Pricing Inputs'!$D$114)^((AI$16-AH$16)/365) -> 1401.7177 | AJ27: =AI27*(1+'2. GRI Pricing Inputs'!$D$114)^((AJ$16-AI$16)/365) -> 1406.3948 | AK27: =AJ27*(1+'2. GRI Pricing Inputs'!$D$114)^((AK$16-AJ$16)/365) -> 1410.9358 | ... AO27: =AN27*(1+'2. GRI Pricing Inputs'!$D$114)^((AO$16-AN$16)/365) -> 1429.7076
C28: ='1. Accomodation'!N32 -> 112N | D28: ='1. Accomodation'!P32 -> 1 Bed | E28: ='1. Accomodation'!Q32 -> 1 | F28: ='1. Accomodation'!O32 -> 506 | G28: ='1. Accomodation'!R32 -> Ground | H28: ='1. Accomodation'!S32 -> Courtyard | K28: =IFERROR(INDEX('2. GRI Pricing Inputs'!$C$15:$AI$16,MATCH($K$16,'2. GRI Pricing Inputs'!$C$15:$C$16,0),MATCH(D28,'2. GRI Pricing Inputs'!$C$15:$AI$15,0)),0) -> 845 | L28: =IFERROR(INDEX('2. GRI Pricing Inputs'!$C$22:$AI$23,MATCH($L$16,'2. GRI Pricing Inputs'!$C$22:$C$23,0),MATCH(E28,'2. GRI Pricing Inputs'!$C$22:$AI$22,0)),0) -> 0 | M28: =IF(AND('3. GRI Pricing'!$F28>='2. GRI Pricing Inputs'!$D$33,'3. GRI Pricing'!$F28<='2. GRI Pricing Inputs'!$E$33),'2. GRI Pricing Inputs'!$D$32,IF(AND('3. GRI Pricing'!$F28>='2. GRI Pricing Inputs'!$F$33,'3. GRI Pricing'!$F28<='2. GRI Pricing Inputs'!$G$33),'2. GRI Pricing Inputs'!$F$32,IF(AND('3. GRI Pricing'!$F28>='2. GRI Pricing Inputs'!$H$33,'3. GRI Pricing'!$F28<='2. GRI Pricing Inputs'!$I$33),'2. GRI Pricing Inputs'!$H$32,IF(AND('3. GRI Pricing'!$F28>='2. GRI Pricing Inputs'!$J$33,'3. GRI Pricing'!$F28<='2. GRI Pricing Inputs'!$K$33),'2. GRI Pricing Inputs'!$J$32,IF(AND('3. GRI Pricing'!$F28>='2. GRI Pricing Inputs'!$L$33,'3. GRI Pricing'!$F28<='2. GRI Pricing Inputs'!$M$33),'2. GRI Pricing Inputs'!$L$32,IF(AND('3. GRI Pricing'!$F28>='2. GRI Pricing Inputs'!$N$33,'3. GRI Pricing'!$F28<='2. GRI Pricing Inputs'!$O$33),'2. GRI Pricing Inputs'!$N$32,IF(AND('3. GRI Pricing'!$F28>='2. GRI Pricing Inputs'!$P$33,'3. GRI Pricing'!$F28<='2. GRI Pricing Inputs'!$Q$33),'2. GRI Pricing Inputs'!$P$32,IF(AND('3. GRI Pricing'!$F28>='2. GRI Pricing Inputs'!$R$33,'3. GRI Pricing'!$F28<='2. GRI Pricing Inputs'!$S$33),'2. GRI Pricing Inputs'!$R$32,IF(AND('3. GRI Pricing'!$F28>='2. GRI Pricing Inputs'!$T$33,'3. GRI Pricing'!$F28<='2. GRI Pricing Inputs'!$U$33),'2. GRI Pricing Inputs'!$T$32,IF(AND('3. GRI Pricing'!$F28>='2. GRI Pricing Inputs'!$V$33,'3. GRI Pricing'!$F28<='2. GRI Pricing Inputs'!$W$33),'2. GRI Pricing Inputs'!$V$32,IF(AND('3. GRI Pricing'!$F28>='2. GRI Pricing Inputs'!$X$33,'3. GRI Pricing'!$F28<='2. GRI Pricing Inputs'!$Y$33),'2. GRI Pricing Inputs'!$X$32,IF(AND('3. GRI Pricing'!$F28>='2. GRI Pricing Inputs'!$Z$33,'3. GRI Pricing'!$F28<='2. GRI Pricing Inputs'!$AA$33),'2. GRI Pricing Inputs'!$Z$32,IF(AND('3. GRI Pricing'!$F28>='2. GRI Pricing Inputs'!$AB$33,'3. GRI Pricing'!$F28<='2. GRI Pricing Inputs'!$AC$33),'2. GRI Pricing Inputs'!$AB$32,IF(AND('3. GRI Pricing'!$F28>='2. GRI Pricing Inputs'!$AD$33,'3. GRI Pricing'!$F28<='2. GRI Pricing Inputs'!$AE$33),'2. GRI Pricing Inputs'!$AD$32,IF(AND('3. GRI Pricing'!$F28>='2. GRI Pricing Inputs'!$AF$33,'3. GRI Pricing'!$F28<='2. GRI Pricing Inputs'!$AG$33),'2. GRI Pricing Inputs'!$AF$32,IF(AND('3. GRI Pricing'!$F28>='2. GRI Pricing Inputs'!$AH$33,'3. GRI Pricing'!$F28<='2. GRI Pricing Inputs'!$AI$33),'2. GRI Pricing Inputs'!$AH$32,0)))))))))))))))) -> 2 | N28: {=IFERROR(INDEX('2. GRI Pricing Inputs'!$C$32:$AI$39,MATCH('3. GRI Pricing'!D28,'2. GRI Pricing Inputs'!$C$32:$C$39,0),(MATCH('3. GRI Pricing'!M28,'2. GRI Pricing Inputs'!$D$32:$AI$32,0)+1)),0)} -> 15 | O28: =IFERROR(INDEX('2. GRI Pricing Inputs'!$C$45:$AI$46,MATCH($O$16,'2. GRI Pricing Inputs'!$C$45:$C$46,0),MATCH(G28,'2. GRI Pricing Inputs'!$C$45:$AI$45,0)),0) -> 0 | P28: =IFERROR(INDEX('2. GRI Pricing Inputs'!$C$53:$AI$54,MATCH('3. GRI Pricing'!$P$16,'2. GRI Pricing Inputs'!$C$53:$C$54,0),MATCH('3. GRI Pricing'!H28,'2. GRI Pricing Inputs'!$C$53:$AI$53,0)),0) -> 25 | Q28: =IFERROR(INDEX('2. GRI Pricing Inputs'!$C$60:$AI$61,MATCH('3. GRI Pricing'!$Q$16,'2. GRI Pricing Inputs'!$C$60:$C$61,0),MATCH('1. Accomodation'!T32,'2. GRI Pricing Inputs'!$C$60:$AI$60,0)),0) -> 0 | R28: =IFERROR(INDEX('2. GRI Pricing Inputs'!$C$67:$AI$68,MATCH('3. GRI Pricing'!$R$16,'2. GRI Pricing Inputs'!$C$67:$C$68,0),MATCH('1. Accomodation'!U32,'2. GRI Pricing Inputs'!$C$67:$AI$67,0)),0) -> 0 | S28: =IF(D28=0,0,'2. GRI Pricing Inputs'!$AI$75) -> 70 | T28: =IFERROR(INDEX('2. GRI Pricing Inputs'!$C$82:$AI$83,MATCH('3. GRI Pricing'!$T$16,'2. GRI Pricing Inputs'!$C$82:$C$83,0),MATCH('1. Accomodation'!V32,'2. GRI Pricing Inputs'!$C$82:$AI$82,0)),0) -> 20 | U28: =IFERROR(INDEX('2. GRI Pricing Inputs'!$C$89:$AI$90,MATCH('3. GRI Pricing'!$U$16,'2. GRI Pricing Inputs'!$C$89:$C$90,0),MATCH('1. Accomodation'!W32,'2. GRI Pricing Inputs'!$C$89:$AI$89,0)),0) -> 0 | V28: =IFERROR(INDEX('2. GRI Pricing Inputs'!$C$97:$AI$98,MATCH('3. GRI Pricing'!$V$16,'2. GRI Pricing Inputs'!$C$97:$C$98,0),MATCH('1. Accomodation'!X32,'2. GRI Pricing Inputs'!$C$97:$AI$97,0)),0) -> 0 | W28: =IFERROR(INDEX('2. GRI Pricing Inputs'!$C$104:$AI$105,MATCH('3. GRI Pricing'!$W$16,'2. GRI Pricing Inputs'!$C$104:$C$105,0),MATCH('1. Accomodation'!Y32,'2. GRI Pricing Inputs'!$C$104:$AI$104,0)),0) -> 0 | X28: 0 | Y28: =K28+L28+N28+O28+P28+Q28+R28+S28+T28+U28+V28+W28+X28 -> 975 | AC28: =Y28*(1+'2. GRI Pricing Inputs'!$D$114)^(($AC$16-$AB$15)/365) -> 978.25321 | AD28: =AC28*(1+'2. GRI Pricing Inputs'!$D$114)^((AD$16-AC$16)/365) -> 981.41182 | AE28: =AD28*(1+'2. GRI Pricing Inputs'!$D$114)^((AE$16-AD$16)/365) -> 984.68642 | AF28: =AE28*(1+'2. GRI Pricing Inputs'!$D$114)^((AF$16-AE$16)/365) -> 987.97196 | AG28: =AF28*(1+'2. GRI Pricing Inputs'!$D$114)^((AG$16-AF$16)/365) -> 991.05544 | AH28: =AG28*(1+'2. GRI Pricing Inputs'!$D$114)^((AH$16-AG$16)/365) -> 994.36223 | AI28: =AH28*(1+'2. GRI Pricing Inputs'!$D$114)^((AI$16-AH$16)/365) -> 997.57285 | AJ28: =AI28*(1+'2. GRI Pricing Inputs'!$D$114)^((AJ$16-AI$16)/365) -> 1000.9014 | AK28: =AJ28*(1+'2. GRI Pricing Inputs'!$D$114)^((AK$16-AJ$16)/365) -> 1004.1331 | ... AO28: =AN28*(1+'2. GRI Pricing Inputs'!$D$114)^((AO$16-AN$16)/365) -> 1017.4927
... C299: ='1. Accomodation'!N303 -> 809W | D299: ='1. Accomodation'!P303 -> 3 Bed | E299: ='1. Accomodation'!Q303 -> 2 | F299: ='1. Accomodation'!O303 -> 840 | G299: ='1. Accomodation'!R303 -> 8 | H299: ='1. Accomodation'!S303 -> Railway Bridge - Higher | K299: =IFERROR(INDEX('2. GRI Pricing Inputs'!$C$15:$AI$16,MATCH($K$16,'2. GRI Pricing Inputs'!$C$15:$C$16,0),MATCH(D299,'2. GRI Pricing Inputs'!$C$15:$AI$15,0)),0) -> 1485 | L299: =IFERROR(INDEX('2. GRI Pricing Inputs'!$C$22:$AI$23,MATCH($L$16,'2. GRI Pricing Inputs'!$C$22:$C$23,0),MATCH(E299,'2. GRI Pricing Inputs'!$C$22:$AI$22,0)),0) -> 0 | M299: =IF(AND('3. GRI Pricing'!$F299>='2. GRI Pricing Inputs'!$D$33,'3. GRI Pricing'!$F299<='2. GRI Pricing Inputs'!$E$33),'2. GRI Pricing Inputs'!$D$32,IF(AND('3. GRI Pricing'!$F299>='2. GRI Pricing Inputs'!$F$33,'3. GRI Pricing'!$F299<='2. GRI Pricing Inputs'!$G$33),'2. GRI Pricing Inputs'!$F$32,IF(AND('3. GRI Pricing'!$F299>='2. GRI Pricing Inputs'!$H$33,'3. GRI Pricing'!$F299<='2. GRI Pricing Inputs'!$I$33),'2. GRI Pricing Inputs'!$H$32,IF(AND('3. GRI Pricing'!$F299>='2. GRI Pricing Inputs'!$J$33,'3. GRI Pricing'!$F299<='2. GRI Pricing Inputs'!$K$33),'2. GRI Pricing Inputs'!$J$32,IF(AND('3. GRI Pricing'!$F299>='2. GRI Pricing Inputs'!$L$33,'3. GRI Pricing'!$F299<='2. GRI Pricing Inputs'!$M$33),'2. GRI Pricing Inputs'!$L$32,IF(AND('3. GRI Pricing'!$F299>='2. GRI Pricing Inputs'!$N$33,'3. GRI Pricing'!$F299<='2. GRI Pricing Inputs'!$O$33),'2. GRI Pricing Inputs'!$N$32,IF(AND('3. GRI Pricing'!$F299>='2. GRI Pricing Inputs'!$P$33,'3. GRI Pricing'!$F299<='2. GRI Pricing Inputs'!$Q$33),'2. GRI Pricing Inputs'!$P$32,IF(AND('3. GRI Pricing'!$F299>='2. GRI Pricing Inputs'!$R$33,'3. GRI Pricing'!$F299<='2. GRI Pricing Inputs'!$S$33),'2. GRI Pricing Inputs'!$R$32,IF(AND('3. GRI Pricing'!$F299>='2. GRI Pricing Inputs'!$T$33,'3. GRI Pricing'!$F299<='2. GRI Pricing Inputs'!$U$33),'2. GRI Pricing Inputs'!$T$32,IF(AND('3. GRI Pricing'!$F299>='2. GRI Pricing Inputs'!$V$33,'3. GRI Pricing'!$F299<='2. GRI Pricing Inputs'!$W$33),'2. GRI Pricing Inputs'!$V$32,IF(AND('3. GRI Pricing'!$F299>='2. GRI Pricing Inputs'!$X$33,'3. GRI Pricing'!$F299<='2. GRI Pricing Inputs'!$Y$33),'2. GRI Pricing Inputs'!$X$32,IF(AND('3. GRI Pricing'!$F299>='2. GRI Pricing Inputs'!$Z$33,'3. GRI Pricing'!$F299<='2. GRI Pricing Inputs'!$AA$33),'2. GRI Pricing Inputs'!$Z$32,IF(AND('3. GRI Pricing'!$F299>='2. GRI Pricing Inputs'!$AB$33,'3. GRI Pricing'!$F299<='2. GRI Pricing Inputs'!$AC$33),'2. GRI Pricing Inputs'!$AB$32,IF(AND('3. GRI Pricing'!$F299>='2. GRI Pricing Inputs'!$AD$33,'3. GRI Pricing'!$F299<='2. GRI Pricing Inputs'!$AE$33),'2. GRI Pricing Inputs'!$AD$32,IF(AND('3. GRI Pricing'!$F299>='2. GRI Pricing Inputs'!$AF$33,'3. GRI Pricing'!$F299<='2. GRI Pricing Inputs'!$AG$33),'2. GRI Pricing Inputs'!$AF$32,IF(AND('3. GRI Pricing'!$F299>='2. GRI Pricing Inputs'!$AH$33,'3. GRI Pricing'!$F299<='2. GRI Pricing Inputs'!$AI$33),'2. GRI Pricing Inputs'!$AH$32,0)))))))))))))))) -> 15 | N299: {=IFERROR(INDEX('2. GRI Pricing Inputs'!$C$32:$AI$39,MATCH('3. GRI Pricing'!D299,'2. GRI Pricing Inputs'!$C$32:$C$39,0),(MATCH('3. GRI Pricing'!M299,'2. GRI Pricing Inputs'!$D$32:$AI$32,0)+1)),0)} -> 70 | O299: =IFERROR(INDEX('2. GRI Pricing Inputs'!$C$45:$AI$46,MATCH($O$16,'2. GRI Pricing Inputs'!$C$45:$C$46,0),MATCH(G299,'2. GRI Pricing Inputs'!$C$45:$AI$45,0)),0) -> 100 | P299: =IFERROR(INDEX('2. GRI Pricing Inputs'!$C$53:$AI$54,MATCH('3. GRI Pricing'!$P$16,'2. GRI Pricing Inputs'!$C$53:$C$54,0),MATCH('3. GRI Pricing'!H299,'2. GRI Pricing Inputs'!$C$53:$AI$53,0)),0) -> 30 | Q299: =IFERROR(INDEX('2. GRI Pricing Inputs'!$C$60:$AI$61,MATCH('3. GRI Pricing'!$Q$16,'2. GRI Pricing Inputs'!$C$60:$C$61,0),MATCH('1. Accomodation'!T303,'2. GRI Pricing Inputs'!$C$60:$AI$60,0)),0) -> 0 | R299: =IFERROR(INDEX('2. GRI Pricing Inputs'!$C$67:$AI$68,MATCH('3. GRI Pricing'!$R$16,'2. GRI Pricing Inputs'!$C$67:$C$68,0),MATCH('1. Accomodation'!U303,'2. GRI Pricing Inputs'!$C$67:$AI$67,0)),0) -> 0 | S299: =IF(D299=0,0,'2. GRI Pricing Inputs'!$AI$75) -> 70 | T299: =IFERROR(INDEX('2. GRI Pricing Inputs'!$C$82:$AI$83,MATCH('3. GRI Pricing'!$T$16,'2. GRI Pricing Inputs'!$C$82:$C$83,0),MATCH('1. Accomodation'!V303,'2. GRI Pricing Inputs'!$C$82:$AI$82,0)),0) -> 0 | U299: =IFERROR(INDEX('2. GRI Pricing Inputs'!$C$89:$AI$90,MATCH('3. GRI Pricing'!$U$16,'2. GRI Pricing Inputs'!$C$89:$C$90,0),MATCH('1. Accomodation'!W303,'2. GRI Pricing Inputs'!$C$89:$AI$89,0)),0) -> 0 | V299: =IFERROR(INDEX('2. GRI Pricing Inputs'!$C$97:$AI$98,MATCH('3. GRI Pricing'!$V$16,'2. GRI Pricing Inputs'!$C$97:$C$98,0),MATCH('1. Accomodation'!X303,'2. GRI Pricing Inputs'!$C$97:$AI$97,0)),0) -> 0 | W299: =IFERROR(INDEX('2. GRI Pricing Inputs'!$C$104:$AI$105,MATCH('3. GRI Pricing'!$W$16,'2. GRI Pricing Inputs'!$C$104:$C$105,0),MATCH('1. Accomodation'!Y303,'2. GRI Pricing Inputs'!$C$104:$AI$104,0)),0) -> 0 | X299: 0 | Y299: =K299+L299+N299+O299+P299+Q299+R299+S299+T299+U299+V299+W299+X299 -> 1755 | AC299: =Y299*(1+'2. GRI Pricing Inputs'!$D$114)^(($AC$16-$AB$15)/365) -> 1760.8558 | AD299: =AC299*(1+'2. GRI Pricing Inputs'!$D$114)^((AD$16-AC$16)/365) -> 1766.5413 | AE299: =AD299*(1+'2. GRI Pricing Inputs'!$D$114)^((AE$16-AD$16)/365) -> 1772.4356 | AF299: =AE299*(1+'2. GRI Pricing Inputs'!$D$114)^((AF$16-AE$16)/365) -> 1778.3495 | AG299: =AF299*(1+'2. GRI Pricing Inputs'!$D$114)^((AG$16-AF$16)/365) -> 1783.8998 | AH299: =AG299*(1+'2. GRI Pricing Inputs'!$D$114)^((AH$16-AG$16)/365) -> 1789.852 | AI299: =AH299*(1+'2. GRI Pricing Inputs'!$D$114)^((AI$16-AH$16)/365) -> 1795.6311 | AJ299: =AI299*(1+'2. GRI Pricing Inputs'!$D$114)^((AJ$16-AI$16)/365) -> 1801.6225 | AK299: =AJ299*(1+'2. GRI Pricing Inputs'!$D$114)^((AK$16-AJ$16)/365) -> 1807.4396 | ... AO299: =AN299*(1+'2. GRI Pricing Inputs'!$D$114)^((AO$16-AN$16)/365) -> 1831.4868
C300: ='1. Accomodation'!N304 -> 0 | D300: ='1. Accomodation'!P304 -> 0 | E300: ='1. Accomodation'!Q304 -> 0 | F300: ='1. Accomodation'!O304 -> 0 | G300: ='1. Accomodation'!R304 -> 0 | H300: ='1. Accomodation'!S304 -> 0 | K300: =IFERROR(INDEX('2. GRI Pricing Inputs'!$C$15:$AI$16,MATCH($K$16,'2. GRI Pricing Inputs'!$C$15:$C$16,0),MATCH(D300,'2. GRI Pricing Inputs'!$C$15:$AI$15,0)),0) -> 0 | L300: =IFERROR(INDEX('2. GRI Pricing Inputs'!$C$22:$AI$23,MATCH($L$16,'2. GRI Pricing Inputs'!$C$22:$C$23,0),MATCH(E300,'2. GRI Pricing Inputs'!$C$22:$AI$22,0)),0) -> 0 | M300: =IF(AND('3. GRI Pricing'!$F300>='2. GRI Pricing Inputs'!$D$33,'3. GRI Pricing'!$F300<='2. GRI Pricing Inputs'!$E$33),'2. GRI Pricing Inputs'!$D$32,IF(AND('3. GRI Pricing'!$F300>='2. GRI Pricing Inputs'!$F$33,'3. GRI Pricing'!$F300<='2. GRI Pricing Inputs'!$G$33),'2. GRI Pricing Inputs'!$F$32,IF(AND('3. GRI Pricing'!$F300>='2. GRI Pricing Inputs'!$H$33,'3. GRI Pricing'!$F300<='2. GRI Pricing Inputs'!$I$33),'2. GRI Pricing Inputs'!$H$32,IF(AND('3. GRI Pricing'!$F300>='2. GRI Pricing Inputs'!$J$33,'3. GRI Pricing'!$F300<='2. GRI Pricing Inputs'!$K$33),'2. GRI Pricing Inputs'!$J$32,IF(AND('3. GRI Pricing'!$F300>='2. GRI Pricing Inputs'!$L$33,'3. GRI Pricing'!$F300<='2. GRI Pricing Inputs'!$M$33),'2. GRI Pricing Inputs'!$L$32,IF(AND('3. GRI Pricing'!$F300>='2. GRI Pricing Inputs'!$N$33,'3. GRI Pricing'!$F300<='2. GRI Pricing Inputs'!$O$33),'2. GRI Pricing Inputs'!$N$32,IF(AND('3. GRI Pricing'!$F300>='2. GRI Pricing Inputs'!$P$33,'3. GRI Pricing'!$F300<='2. GRI Pricing Inputs'!$Q$33),'2. GRI Pricing Inputs'!$P$32,IF(AND('3. GRI Pricing'!$F300>='2. GRI Pricing Inputs'!$R$33,'3. GRI Pricing'!$F300<='2. GRI Pricing Inputs'!$S$33),'2. GRI Pricing Inputs'!$R$32,IF(AND('3. GRI Pricing'!$F300>='2. GRI Pricing Inputs'!$T$33,'3. GRI Pricing'!$F300<='2. GRI Pricing Inputs'!$U$33),'2. GRI Pricing Inputs'!$T$32,IF(AND('3. GRI Pricing'!$F300>='2. GRI Pricing Inputs'!$V$33,'3. GRI Pricing'!$F300<='2. GRI Pricing Inputs'!$W$33),'2. GRI Pricing Inputs'!$V$32,IF(AND('3. GRI Pricing'!$F300>='2. GRI Pricing Inputs'!$X$33,'3. GRI Pricing'!$F300<='2. GRI Pricing Inputs'!$Y$33),'2. GRI Pricing Inputs'!$X$32,IF(AND('3. GRI Pricing'!$F300>='2. GRI Pricing Inputs'!$Z$33,'3. GRI Pricing'!$F300<='2. GRI Pricing Inputs'!$AA$33),'2. GRI Pricing Inputs'!$Z$32,IF(AND('3. GRI Pricing'!$F300>='2. GRI Pricing Inputs'!$AB$33,'3. GRI Pricing'!$F300<='2. GRI Pricing Inputs'!$AC$33),'2. GRI Pricing Inputs'!$AB$32,IF(AND('3. GRI Pricing'!$F300>='2. GRI Pricing Inputs'!$AD$33,'3. GRI Pricing'!$F300<='2. GRI Pricing Inputs'!$AE$33),'2. GRI Pricing Inputs'!$AD$32,IF(AND('3. GRI Pricing'!$F300>='2. GRI Pricing Inputs'!$AF$33,'3. GRI Pricing'!$F300<='2. GRI Pricing Inputs'!$AG$33),'2. GRI Pricing Inputs'!$AF$32,IF(AND('3. GRI Pricing'!$F300>='2. GRI Pricing Inputs'!$AH$33,'3. GRI Pricing'!$F300<='2. GRI Pricing Inputs'!$AI$33),'2. GRI Pricing Inputs'!$AH$32,0)))))))))))))))) -> 0 | N300: {=IFERROR(INDEX('2. GRI Pricing Inputs'!$C$32:$AI$39,MATCH('3. GRI Pricing'!D300,'2. GRI Pricing Inputs'!$C$32:$C$39,0),(MATCH('3. GRI Pricing'!M300,'2. GRI Pricing Inputs'!$D$32:$AI$32,0)+1)),0)} -> 0 | O300: =IFERROR(INDEX('2. GRI Pricing Inputs'!$C$45:$AI$46,MATCH($O$16,'2. GRI Pricing Inputs'!$C$45:$C$46,0),MATCH(G300,'2. GRI Pricing Inputs'!$C$45:$AI$45,0)),0) -> 0 | P300: =IFERROR(INDEX('2. GRI Pricing Inputs'!$C$53:$AI$54,MATCH('3. GRI Pricing'!$P$16,'2. GRI Pricing Inputs'!$C$53:$C$54,0),MATCH('3. GRI Pricing'!H300,'2. GRI Pricing Inputs'!$C$53:$AI$53,0)),0) -> 0 | Q300: =IFERROR(INDEX('2. GRI Pricing Inputs'!$C$60:$AI$61,MATCH('3. GRI Pricing'!$Q$16,'2. GRI Pricing Inputs'!$C$60:$C$61,0),MATCH('1. Accomodation'!T304,'2. GRI Pricing Inputs'!$C$60:$AI$60,0)),0) -> 0 | R300: =IFERROR(INDEX('2. GRI Pricing Inputs'!$C$67:$AI$68,MATCH('3. GRI Pricing'!$R$16,'2. GRI Pricing Inputs'!$C$67:$C$68,0),MATCH('1. Accomodation'!U304,'2. GRI Pricing Inputs'!$C$67:$AI$67,0)),0) -> 0 | S300: =IF(D300=0,0,'2. GRI Pricing Inputs'!$AI$75) -> 0 | T300: =IFERROR(INDEX('2. GRI Pricing Inputs'!$C$82:$AI$83,MATCH('3. GRI Pricing'!$T$16,'2. GRI Pricing Inputs'!$C$82:$C$83,0),MATCH('1. Accomodation'!V304,'2. GRI Pricing Inputs'!$C$82:$AI$82,0)),0) -> 0 | U300: =IFERROR(INDEX('2. GRI Pricing Inputs'!$C$89:$AI$90,MATCH('3. GRI Pricing'!$U$16,'2. GRI Pricing Inputs'!$C$89:$C$90,0),MATCH('1. Accomodation'!W304,'2. GRI Pricing Inputs'!$C$89:$AI$89,0)),0) -> 0 | V300: =IFERROR(INDEX('2. GRI Pricing Inputs'!$C$97:$AI$98,MATCH('3. GRI Pricing'!$V$16,'2. GRI Pricing Inputs'!$C$97:$C$98,0),MATCH('1. Accomodation'!X304,'2. GRI Pricing Inputs'!$C$97:$AI$97,0)),0) -> 0 | W300: =IFERROR(INDEX('2. GRI Pricing Inputs'!$C$104:$AI$105,MATCH('3. GRI Pricing'!$W$16,'2. GRI Pricing Inputs'!$C$104:$C$105,0),MATCH('1. Accomodation'!Y304,'2. GRI Pricing Inputs'!$C$104:$AI$104,0)),0) -> 0 | Y300: =K300+L300+N300+O300+P300+Q300+R300+S300+T300+U300+V300+W300+X300 -> 0 | AC300: =Y300*(1+'2. GRI Pricing Inputs'!$D$114)^(($AC$16-$AB$15)/365) -> 0 | AD300: =AC300*(1+'2. GRI Pricing Inputs'!$D$114)^((AD$16-AC$16)/365) -> 0 | AE300: =AD300*(1+'2. GRI Pricing Inputs'!$D$114)^((AE$16-AD$16)/365) -> 0 | AF300: =AE300*(1+'2. GRI Pricing Inputs'!$D$114)^((AF$16-AE$16)/365) -> 0 | AG300: =AF300*(1+'2. GRI Pricing Inputs'!$D$114)^((AG$16-AF$16)/365) -> 0 | AH300: =AG300*(1+'2. GRI Pricing Inputs'!$D$114)^((AH$16-AG$16)/365) -> 0 | AI300: =AH300*(1+'2. GRI Pricing Inputs'!$D$114)^((AI$16-AH$16)/365) -> 0 | AJ300: =AI300*(1+'2. GRI Pricing Inputs'!$D$114)^((AJ$16-AI$16)/365) -> 0 | AK300: =AJ300*(1+'2. GRI Pricing Inputs'!$D$114)^((AK$16-AJ$16)/365) -> 0 | ... AO300: =AN300*(1+'2. GRI Pricing Inputs'!$D$114)^((AO$16-AN$16)/365) -> 0
C301: ='1. Accomodation'!N305 -> 0 | D301: ='1. Accomodation'!P305 -> 0 | E301: ='1. Accomodation'!Q305 -> 0 | F301: ='1. Accomodation'!O305 -> 0 | G301: ='1. Accomodation'!R305 -> 0 | H301: ='1. Accomodation'!S305 -> 0 | K301: =IFERROR(INDEX('2. GRI Pricing Inputs'!$C$15:$AI$16,MATCH($K$16,'2. GRI Pricing Inputs'!$C$15:$C$16,0),MATCH(D301,'2. GRI Pricing Inputs'!$C$15:$AI$15,0)),0) -> 0 | L301: =IFERROR(INDEX('2. GRI Pricing Inputs'!$C$22:$AI$23,MATCH($L$16,'2. GRI Pricing Inputs'!$C$22:$C$23,0),MATCH(E301,'2. GRI Pricing Inputs'!$C$22:$AI$22,0)),0) -> 0 | M301: =IF(AND('3. GRI Pricing'!$F301>='2. GRI Pricing Inputs'!$D$33,'3. GRI Pricing'!$F301<='2. GRI Pricing Inputs'!$E$33),'2. GRI Pricing Inputs'!$D$32,IF(AND('3. GRI Pricing'!$F301>='2. GRI Pricing Inputs'!$F$33,'3. GRI Pricing'!$F301<='2. GRI Pricing Inputs'!$G$33),'2. GRI Pricing Inputs'!$F$32,IF(AND('3. GRI Pricing'!$F301>='2. GRI Pricing Inputs'!$H$33,'3. GRI Pricing'!$F301<='2. GRI Pricing Inputs'!$I$33),'2. GRI Pricing Inputs'!$H$32,IF(AND('3. GRI Pricing'!$F301>='2. GRI Pricing Inputs'!$J$33,'3. GRI Pricing'!$F301<='2. GRI Pricing Inputs'!$K$33),'2. GRI Pricing Inputs'!$J$32,IF(AND('3. GRI Pricing'!$F301>='2. GRI Pricing Inputs'!$L$33,'3. GRI Pricing'!$F301<='2. GRI Pricing Inputs'!$M$33),'2. GRI Pricing Inputs'!$L$32,IF(AND('3. GRI Pricing'!$F301>='2. GRI Pricing Inputs'!$N$33,'3. GRI Pricing'!$F301<='2. GRI Pricing Inputs'!$O$33),'2. GRI Pricing Inputs'!$N$32,IF(AND('3. GRI Pricing'!$F301>='2. GRI Pricing Inputs'!$P$33,'3. GRI Pricing'!$F301<='2. GRI Pricing Inputs'!$Q$33),'2. GRI Pricing Inputs'!$P$32,IF(AND('3. GRI Pricing'!$F301>='2. GRI Pricing Inputs'!$R$33,'3. GRI Pricing'!$F301<='2. GRI Pricing Inputs'!$S$33),'2. GRI Pricing Inputs'!$R$32,IF(AND('3. GRI Pricing'!$F301>='2. GRI Pricing Inputs'!$T$33,'3. GRI Pricing'!$F301<='2. GRI Pricing Inputs'!$U$33),'2. GRI Pricing Inputs'!$T$32,IF(AND('3. GRI Pricing'!$F301>='2. GRI Pricing Inputs'!$V$33,'3. GRI Pricing'!$F301<='2. GRI Pricing Inputs'!$W$33),'2. GRI Pricing Inputs'!$V$32,IF(AND('3. GRI Pricing'!$F301>='2. GRI Pricing Inputs'!$X$33,'3. GRI Pricing'!$F301<='2. GRI Pricing Inputs'!$Y$33),'2. GRI Pricing Inputs'!$X$32,IF(AND('3. GRI Pricing'!$F301>='2. GRI Pricing Inputs'!$Z$33,'3. GRI Pricing'!$F301<='2. GRI Pricing Inputs'!$AA$33),'2. GRI Pricing Inputs'!$Z$32,IF(AND('3. GRI Pricing'!$F301>='2. GRI Pricing Inputs'!$AB$33,'3. GRI Pricing'!$F301<='2. GRI Pricing Inputs'!$AC$33),'2. GRI Pricing Inputs'!$AB$32,IF(AND('3. GRI Pricing'!$F301>='2. GRI Pricing Inputs'!$AD$33,'3. GRI Pricing'!$F301<='2. GRI Pricing Inputs'!$AE$33),'2. GRI Pricing Inputs'!$AD$32,IF(AND('3. GRI Pricing'!$F301>='2. GRI Pricing Inputs'!$AF$33,'3. GRI Pricing'!$F301<='2. GRI Pricing Inputs'!$AG$33),'2. GRI Pricing Inputs'!$AF$32,IF(AND('3. GRI Pricing'!$F301>='2. GRI Pricing Inputs'!$AH$33,'3. GRI Pricing'!$F301<='2. GRI Pricing Inputs'!$AI$33),'2. GRI Pricing Inputs'!$AH$32,0)))))))))))))))) -> 0 | N301: {=IFERROR(INDEX('2. GRI Pricing Inputs'!$C$32:$AI$39,MATCH('3. GRI Pricing'!D301,'2. GRI Pricing Inputs'!$C$32:$C$39,0),(MATCH('3. GRI Pricing'!M301,'2. GRI Pricing Inputs'!$D$32:$AI$32,0)+1)),0)} -> 0 | O301: =IFERROR(INDEX('2. GRI Pricing Inputs'!$C$45:$AI$46,MATCH($O$16,'2. GRI Pricing Inputs'!$C$45:$C$46,0),MATCH(G301,'2. GRI Pricing Inputs'!$C$45:$AI$45,0)),0) -> 0 | P301: =IFERROR(INDEX('2. GRI Pricing Inputs'!$C$53:$AI$54,MATCH('3. GRI Pricing'!$P$16,'2. GRI Pricing Inputs'!$C$53:$C$54,0),MATCH('3. GRI Pricing'!H301,'2. GRI Pricing Inputs'!$C$53:$AI$53,0)),0) -> 0 | Q301: =IFERROR(INDEX('2. GRI Pricing Inputs'!$C$60:$AI$61,MATCH('3. GRI Pricing'!$Q$16,'2. GRI Pricing Inputs'!$C$60:$C$61,0),MATCH('1. Accomodation'!T305,'2. GRI Pricing Inputs'!$C$60:$AI$60,0)),0) -> 0 | R301: =IFERROR(INDEX('2. GRI Pricing Inputs'!$C$67:$AI$68,MATCH('3. GRI Pricing'!$R$16,'2. GRI Pricing Inputs'!$C$67:$C$68,0),MATCH('1. Accomodation'!U305,'2. GRI Pricing Inputs'!$C$67:$AI$67,0)),0) -> 0 | S301: =IF(D301=0,0,'2. GRI Pricing Inputs'!$AI$75) -> 0 | T301: =IFERROR(INDEX('2. GRI Pricing Inputs'!$C$82:$AI$83,MATCH('3. GRI Pricing'!$T$16,'2. GRI Pricing Inputs'!$C$82:$C$83,0),MATCH('1. Accomodation'!V305,'2. GRI Pricing Inputs'!$C$82:$AI$82,0)),0) -> 0 | U301: =IFERROR(INDEX('2. GRI Pricing Inputs'!$C$89:$AI$90,MATCH('3. GRI Pricing'!$U$16,'2. GRI Pricing Inputs'!$C$89:$C$90,0),MATCH('1. Accomodation'!W305,'2. GRI Pricing Inputs'!$C$89:$AI$89,0)),0) -> 0 | V301: =IFERROR(INDEX('2. GRI Pricing Inputs'!$C$97:$AI$98,MATCH('3. GRI Pricing'!$V$16,'2. GRI Pricing Inputs'!$C$97:$C$98,0),MATCH('1. Accomodation'!X305,'2. GRI Pricing Inputs'!$C$97:$AI$97,0)),0) -> 0 | W301: =IFERROR(INDEX('2. GRI Pricing Inputs'!$C$104:$AI$105,MATCH('3. GRI Pricing'!$W$16,'2. GRI Pricing Inputs'!$C$104:$C$105,0),MATCH('1. Accomodation'!Y305,'2. GRI Pricing Inputs'!$C$104:$AI$104,0)),0) -> 0 | Y301: =K301+L301+N301+O301+P301+Q301+R301+S301+T301+U301+V301+W301+X301 -> 0 | AC301: =Y301*(1+'2. GRI Pricing Inputs'!$D$114)^(($AC$16-$AB$15)/365) -> 0 | AD301: =AC301*(1+'2. GRI Pricing Inputs'!$D$114)^((AD$16-AC$16)/365) -> 0 | AE301: =AD301*(1+'2. GRI Pricing Inputs'!$D$114)^((AE$16-AD$16)/365) -> 0 | AF301: =AE301*(1+'2. GRI Pricing Inputs'!$D$114)^((AF$16-AE$16)/365) -> 0 | AG301: =AF301*(1+'2. GRI Pricing Inputs'!$D$114)^((AG$16-AF$16)/365) -> 0 | AH301: =AG301*(1+'2. GRI Pricing Inputs'!$D$114)^((AH$16-AG$16)/365) -> 0 | AI301: =AH301*(1+'2. GRI Pricing Inputs'!$D$114)^((AI$16-AH$16)/365) -> 0 | AJ301: =AI301*(1+'2. GRI Pricing Inputs'!$D$114)^((AJ$16-AI$16)/365) -> 0 | AK301: =AJ301*(1+'2. GRI Pricing Inputs'!$D$114)^((AK$16-AJ$16)/365) -> 0 | ... AO301: =AN301*(1+'2. GRI Pricing Inputs'!$D$114)^((AO$16-AN$16)/365) -> 0
C302: ='1. Accomodation'!N306 -> 0 | D302: ='1. Accomodation'!P306 -> 0 | E302: ='1. Accomodation'!Q306 -> 0 | F302: ='1. Accomodation'!O306 -> 0 | G302: ='1. Accomodation'!R306 -> 0 | H302: ='1. Accomodation'!S306 -> 0 | K302: =IFERROR(INDEX('2. GRI Pricing Inputs'!$C$15:$AI$16,MATCH($K$16,'2. GRI Pricing Inputs'!$C$15:$C$16,0),MATCH(D302,'2. GRI Pricing Inputs'!$C$15:$AI$15,0)),0) -> 0 | L302: =IFERROR(INDEX('2. GRI Pricing Inputs'!$C$22:$AI$23,MATCH($L$16,'2. GRI Pricing Inputs'!$C$22:$C$23,0),MATCH(E302,'2. GRI Pricing Inputs'!$C$22:$AI$22,0)),0) -> 0 | M302: =IF(AND('3. GRI Pricing'!$F302>='2. GRI Pricing Inputs'!$D$33,'3. GRI Pricing'!$F302<='2. GRI Pricing Inputs'!$E$33),'2. GRI Pricing Inputs'!$D$32,IF(AND('3. GRI Pricing'!$F302>='2. GRI Pricing Inputs'!$F$33,'3. GRI Pricing'!$F302<='2. GRI Pricing Inputs'!$G$33),'2. GRI Pricing Inputs'!$F$32,IF(AND('3. GRI Pricing'!$F302>='2. GRI Pricing Inputs'!$H$33,'3. GRI Pricing'!$F302<='2. GRI Pricing Inputs'!$I$33),'2. GRI Pricing Inputs'!$H$32,IF(AND('3. GRI Pricing'!$F302>='2. GRI Pricing Inputs'!$J$33,'3. GRI Pricing'!$F302<='2. GRI Pricing Inputs'!$K$33),'2. GRI Pricing Inputs'!$J$32,IF(AND('3. GRI Pricing'!$F302>='2. GRI Pricing Inputs'!$L$33,'3. GRI Pricing'!$F302<='2. GRI Pricing Inputs'!$M$33),'2. GRI Pricing Inputs'!$L$32,IF(AND('3. GRI Pricing'!$F302>='2. GRI Pricing Inputs'!$N$33,'3. GRI Pricing'!$F302<='2. GRI Pricing Inputs'!$O$33),'2. GRI Pricing Inputs'!$N$32,IF(AND('3. GRI Pricing'!$F302>='2. GRI Pricing Inputs'!$P$33,'3. GRI Pricing'!$F302<='2. GRI Pricing Inputs'!$Q$33),'2. GRI Pricing Inputs'!$P$32,IF(AND('3. GRI Pricing'!$F302>='2. GRI Pricing Inputs'!$R$33,'3. GRI Pricing'!$F302<='2. GRI Pricing Inputs'!$S$33),'2. GRI Pricing Inputs'!$R$32,IF(AND('3. GRI Pricing'!$F302>='2. GRI Pricing Inputs'!$T$33,'3. GRI Pricing'!$F302<='2. GRI Pricing Inputs'!$U$33),'2. GRI Pricing Inputs'!$T$32,IF(AND('3. GRI Pricing'!$F302>='2. GRI Pricing Inputs'!$V$33,'3. GRI Pricing'!$F302<='2. GRI Pricing Inputs'!$W$33),'2. GRI Pricing Inputs'!$V$32,IF(AND('3. GRI Pricing'!$F302>='2. GRI Pricing Inputs'!$X$33,'3. GRI Pricing'!$F302<='2. GRI Pricing Inputs'!$Y$33),'2. GRI Pricing Inputs'!$X$32,IF(AND('3. GRI Pricing'!$F302>='2. GRI Pricing Inputs'!$Z$33,'3. GRI Pricing'!$F302<='2. GRI Pricing Inputs'!$AA$33),'2. GRI Pricing Inputs'!$Z$32,IF(AND('3. GRI Pricing'!$F302>='2. GRI Pricing Inputs'!$AB$33,'3. GRI Pricing'!$F302<='2. GRI Pricing Inputs'!$AC$33),'2. GRI Pricing Inputs'!$AB$32,IF(AND('3. GRI Pricing'!$F302>='2. GRI Pricing Inputs'!$AD$33,'3. GRI Pricing'!$F302<='2. GRI Pricing Inputs'!$AE$33),'2. GRI Pricing Inputs'!$AD$32,IF(AND('3. GRI Pricing'!$F302>='2. GRI Pricing Inputs'!$AF$33,'3. GRI Pricing'!$F302<='2. GRI Pricing Inputs'!$AG$33),'2. GRI Pricing Inputs'!$AF$32,IF(AND('3. GRI Pricing'!$F302>='2. GRI Pricing Inputs'!$AH$33,'3. GRI Pricing'!$F302<='2. GRI Pricing Inputs'!$AI$33),'2. GRI Pricing Inputs'!$AH$32,0)))))))))))))))) -> 0 | N302: {=IFERROR(INDEX('2. GRI Pricing Inputs'!$C$32:$AI$39,MATCH('3. GRI Pricing'!D302,'2. GRI Pricing Inputs'!$C$32:$C$39,0),(MATCH('3. GRI Pricing'!M302,'2. GRI Pricing Inputs'!$D$32:$AI$32,0)+1)),0)} -> 0 | O302: =IFERROR(INDEX('2. GRI Pricing Inputs'!$C$45:$AI$46,MATCH($O$16,'2. GRI Pricing Inputs'!$C$45:$C$46,0),MATCH(G302,'2. GRI Pricing Inputs'!$C$45:$AI$45,0)),0) -> 0 | P302: =IFERROR(INDEX('2. GRI Pricing Inputs'!$C$53:$AI$54,MATCH('3. GRI Pricing'!$P$16,'2. GRI Pricing Inputs'!$C$53:$C$54,0),MATCH('3. GRI Pricing'!H302,'2. GRI Pricing Inputs'!$C$53:$AI$53,0)),0) -> 0 | Q302: =IFERROR(INDEX('2. GRI Pricing Inputs'!$C$60:$AI$61,MATCH('3. GRI Pricing'!$Q$16,'2. GRI Pricing Inputs'!$C$60:$C$61,0),MATCH('1. Accomodation'!T306,'2. GRI Pricing Inputs'!$C$60:$AI$60,0)),0) -> 0 | R302: =IFERROR(INDEX('2. GRI Pricing Inputs'!$C$67:$AI$68,MATCH('3. GRI Pricing'!$R$16,'2. GRI Pricing Inputs'!$C$67:$C$68,0),MATCH('1. Accomodation'!U306,'2. GRI Pricing Inputs'!$C$67:$AI$67,0)),0) -> 0 | S302: =IF(D302=0,0,'2. GRI Pricing Inputs'!$AI$75) -> 0 | T302: =IFERROR(INDEX('2. GRI Pricing Inputs'!$C$82:$AI$83,MATCH('3. GRI Pricing'!$T$16,'2. GRI Pricing Inputs'!$C$82:$C$83,0),MATCH('1. Accomodation'!V306,'2. GRI Pricing Inputs'!$C$82:$AI$82,0)),0) -> 0 | U302: =IFERROR(INDEX('2. GRI Pricing Inputs'!$C$89:$AI$90,MATCH('3. GRI Pricing'!$U$16,'2. GRI Pricing Inputs'!$C$89:$C$90,0),MATCH('1. Accomodation'!W306,'2. GRI Pricing Inputs'!$C$89:$AI$89,0)),0) -> 0 | V302: =IFERROR(INDEX('2. GRI Pricing Inputs'!$C$97:$AI$98,MATCH('3. GRI Pricing'!$V$16,'2. GRI Pricing Inputs'!$C$97:$C$98,0),MATCH('1. Accomodation'!X306,'2. GRI Pricing Inputs'!$C$97:$AI$97,0)),0) -> 0 | W302: =IFERROR(INDEX('2. GRI Pricing Inputs'!$C$104:$AI$105,MATCH('3. GRI Pricing'!$W$16,'2. GRI Pricing Inputs'!$C$104:$C$105,0),MATCH('1. Accomodation'!Y306,'2. GRI Pricing Inputs'!$C$104:$AI$104,0)),0) -> 0 | Y302: =K302+L302+N302+O302+P302+Q302+R302+S302+T302+U302+V302+W302+X302 -> 0 | AC302: =Y302*(1+'2. GRI Pricing Inputs'!$D$114)^(($AC$16-$AB$15)/365) -> 0 | AD302: =AC302*(1+'2. GRI Pricing Inputs'!$D$114)^((AD$16-AC$16)/365) -> 0 | AE302: =AD302*(1+'2. GRI Pricing Inputs'!$D$114)^((AE$16-AD$16)/365) -> 0 | AF302: =AE302*(1+'2. GRI Pricing Inputs'!$D$114)^((AF$16-AE$16)/365) -> 0 | AG302: =AF302*(1+'2. GRI Pricing Inputs'!$D$114)^((AG$16-AF$16)/365) -> 0 | AH302: =AG302*(1+'2. GRI Pricing Inputs'!$D$114)^((AH$16-AG$16)/365) -> 0 | AI302: =AH302*(1+'2. GRI Pricing Inputs'!$D$114)^((AI$16-AH$16)/365) -> 0 | AJ302: =AI302*(1+'2. GRI Pricing Inputs'!$D$114)^((AJ$16-AI$16)/365) -> 0 | AK302: =AJ302*(1+'2. GRI Pricing Inputs'!$D$114)^((AK$16-AJ$16)/365) -> 0 | ... AO302: =AN302*(1+'2. GRI Pricing Inputs'!$D$114)^((AO$16-AN$16)/365) -> 0
C303: ='1. Accomodation'!N307 -> 0 | D303: ='1. Accomodation'!P307 -> 0 | E303: ='1. Accomodation'!Q307 -> 0 | F303: ='1. Accomodation'!O307 -> 0 | G303: ='1. Accomodation'!R307 -> 0 | H303: ='1. Accomodation'!S307 -> 0 | K303: =IFERROR(INDEX('2. GRI Pricing Inputs'!$C$15:$AI$16,MATCH($K$16,'2. GRI Pricing Inputs'!$C$15:$C$16,0),MATCH(D303,'2. GRI Pricing Inputs'!$C$15:$AI$15,0)),0) -> 0 | L303: =IFERROR(INDEX('2. GRI Pricing Inputs'!$C$22:$AI$23,MATCH($L$16,'2. GRI Pricing Inputs'!$C$22:$C$23,0),MATCH(E303,'2. GRI Pricing Inputs'!$C$22:$AI$22,0)),0) -> 0 | M303: =IF(AND('3. GRI Pricing'!$F303>='2. GRI Pricing Inputs'!$D$33,'3. GRI Pricing'!$F303<='2. GRI Pricing Inputs'!$E$33),'2. GRI Pricing Inputs'!$D$32,IF(AND('3. GRI Pricing'!$F303>='2. GRI Pricing Inputs'!$F$33,'3. GRI Pricing'!$F303<='2. GRI Pricing Inputs'!$G$33),'2. GRI Pricing Inputs'!$F$32,IF(AND('3. GRI Pricing'!$F303>='2. GRI Pricing Inputs'!$H$33,'3. GRI Pricing'!$F303<='2. GRI Pricing Inputs'!$I$33),'2. GRI Pricing Inputs'!$H$32,IF(AND('3. GRI Pricing'!$F303>='2. GRI Pricing Inputs'!$J$33,'3. GRI Pricing'!$F303<='2. GRI Pricing Inputs'!$K$33),'2. GRI Pricing Inputs'!$J$32,IF(AND('3. GRI Pricing'!$F303>='2. GRI Pricing Inputs'!$L$33,'3. GRI Pricing'!$F303<='2. GRI Pricing Inputs'!$M$33),'2. GRI Pricing Inputs'!$L$32,IF(AND('3. GRI Pricing'!$F303>='2. GRI Pricing Inputs'!$N$33,'3. GRI Pricing'!$F303<='2. GRI Pricing Inputs'!$O$33),'2. GRI Pricing Inputs'!$N$32,IF(AND('3. GRI Pricing'!$F303>='2. GRI Pricing Inputs'!$P$33,'3. GRI Pricing'!$F303<='2. GRI Pricing Inputs'!$Q$33),'2. GRI Pricing Inputs'!$P$32,IF(AND('3. GRI Pricing'!$F303>='2. GRI Pricing Inputs'!$R$33,'3. GRI Pricing'!$F303<='2. GRI Pricing Inputs'!$S$33),'2. GRI Pricing Inputs'!$R$32,IF(AND('3. GRI Pricing'!$F303>='2. GRI Pricing Inputs'!$T$33,'3. GRI Pricing'!$F303<='2. GRI Pricing Inputs'!$U$33),'2. GRI Pricing Inputs'!$T$32,IF(AND('3. GRI Pricing'!$F303>='2. GRI Pricing Inputs'!$V$33,'3. GRI Pricing'!$F303<='2. GRI Pricing Inputs'!$W$33),'2. GRI Pricing Inputs'!$V$32,IF(AND('3. GRI Pricing'!$F303>='2. GRI Pricing Inputs'!$X$33,'3. GRI Pricing'!$F303<='2. GRI Pricing Inputs'!$Y$33),'2. GRI Pricing Inputs'!$X$32,IF(AND('3. GRI Pricing'!$F303>='2. GRI Pricing Inputs'!$Z$33,'3. GRI Pricing'!$F303<='2. GRI Pricing Inputs'!$AA$33),'2. GRI Pricing Inputs'!$Z$32,IF(AND('3. GRI Pricing'!$F303>='2. GRI Pricing Inputs'!$AB$33,'3. GRI Pricing'!$F303<='2. GRI Pricing Inputs'!$AC$33),'2. GRI Pricing Inputs'!$AB$32,IF(AND('3. GRI Pricing'!$F303>='2. GRI Pricing Inputs'!$AD$33,'3. GRI Pricing'!$F303<='2. GRI Pricing Inputs'!$AE$33),'2. GRI Pricing Inputs'!$AD$32,IF(AND('3. GRI Pricing'!$F303>='2. GRI Pricing Inputs'!$AF$33,'3. GRI Pricing'!$F303<='2. GRI Pricing Inputs'!$AG$33),'2. GRI Pricing Inputs'!$AF$32,IF(AND('3. GRI Pricing'!$F303>='2. GRI Pricing Inputs'!$AH$33,'3. GRI Pricing'!$F303<='2. GRI Pricing Inputs'!$AI$33),'2. GRI Pricing Inputs'!$AH$32,0)))))))))))))))) -> 0 | N303: {=IFERROR(INDEX('2. GRI Pricing Inputs'!$C$32:$AI$39,MATCH('3. GRI Pricing'!D303,'2. GRI Pricing Inputs'!$C$32:$C$39,0),(MATCH('3. GRI Pricing'!M303,'2. GRI Pricing Inputs'!$D$32:$AI$32,0)+1)),0)} -> 0 | O303: =IFERROR(INDEX('2. GRI Pricing Inputs'!$C$45:$AI$46,MATCH($O$16,'2. GRI Pricing Inputs'!$C$45:$C$46,0),MATCH(G303,'2. GRI Pricing Inputs'!$C$45:$AI$45,0)),0) -> 0 | P303: =IFERROR(INDEX('2. GRI Pricing Inputs'!$C$53:$AI$54,MATCH('3. GRI Pricing'!$P$16,'2. GRI Pricing Inputs'!$C$53:$C$54,0),MATCH('3. GRI Pricing'!H303,'2. GRI Pricing Inputs'!$C$53:$AI$53,0)),0) -> 0 | Q303: =IFERROR(INDEX('2. GRI Pricing Inputs'!$C$60:$AI$61,MATCH('3. GRI Pricing'!$Q$16,'2. GRI Pricing Inputs'!$C$60:$C$61,0),MATCH('1. Accomodation'!T307,'2. GRI Pricing Inputs'!$C$60:$AI$60,0)),0) -> 0 | R303: =IFERROR(INDEX('2. GRI Pricing Inputs'!$C$67:$AI$68,MATCH('3. GRI Pricing'!$R$16,'2. GRI Pricing Inputs'!$C$67:$C$68,0),MATCH('1. Accomodation'!U307,'2. GRI Pricing Inputs'!$C$67:$AI$67,0)),0) -> 0 | S303: =IF(D303=0,0,'2. GRI Pricing Inputs'!$AI$75) -> 0 | T303: =IFERROR(INDEX('2. GRI Pricing Inputs'!$C$82:$AI$83,MATCH('3. GRI Pricing'!$T$16,'2. GRI Pricing Inputs'!$C$82:$C$83,0),MATCH('1. Accomodation'!V307,'2. GRI Pricing Inputs'!$C$82:$AI$82,0)),0) -> 0 | U303: =IFERROR(INDEX('2. GRI Pricing Inputs'!$C$89:$AI$90,MATCH('3. GRI Pricing'!$U$16,'2. GRI Pricing Inputs'!$C$89:$C$90,0),MATCH('1. Accomodation'!W307,'2. GRI Pricing Inputs'!$C$89:$AI$89,0)),0) -> 0 | V303: =IFERROR(INDEX('2. GRI Pricing Inputs'!$C$97:$AI$98,MATCH('3. GRI Pricing'!$V$16,'2. GRI Pricing Inputs'!$C$97:$C$98,0),MATCH('1. Accomodation'!X307,'2. GRI Pricing Inputs'!$C$97:$AI$97,0)),0) -> 0 | W303: =IFERROR(INDEX('2. GRI Pricing Inputs'!$C$104:$AI$105,MATCH('3. GRI Pricing'!$W$16,'2. GRI Pricing Inputs'!$C$104:$C$105,0),MATCH('1. Accomodation'!Y307,'2. GRI Pricing Inputs'!$C$104:$AI$104,0)),0) -> 0 | Y303: =K303+L303+N303+O303+P303+Q303+R303+S303+T303+U303+V303+W303+X303 -> 0 | AC303: =Y303*(1+'2. GRI Pricing Inputs'!$D$114)^(($AC$16-$AB$15)/365) -> 0 | AD303: =AC303*(1+'2. GRI Pricing Inputs'!$D$114)^((AD$16-AC$16)/365) -> 0 | AE303: =AD303*(1+'2. GRI Pricing Inputs'!$D$114)^((AE$16-AD$16)/365) -> 0 | AF303: =AE303*(1+'2. GRI Pricing Inputs'!$D$114)^((AF$16-AE$16)/365) -> 0 | AG303: =AF303*(1+'2. GRI Pricing Inputs'!$D$114)^((AG$16-AF$16)/365) -> 0 | AH303: =AG303*(1+'2. GRI Pricing Inputs'!$D$114)^((AH$16-AG$16)/365) -> 0 | AI303: =AH303*(1+'2. GRI Pricing Inputs'!$D$114)^((AI$16-AH$16)/365) -> 0 | AJ303: =AI303*(1+'2. GRI Pricing Inputs'!$D$114)^((AJ$16-AI$16)/365) -> 0 | AK303: =AJ303*(1+'2. GRI Pricing Inputs'!$D$114)^((AK$16-AJ$16)/365) -> 0 | ... AO303: =AN303*(1+'2. GRI Pricing Inputs'!$D$114)^((AO$16-AN$16)/365) -> 0
C304: ='1. Accomodation'!N308 -> 0 | D304: ='1. Accomodation'!P308 -> 0 | E304: ='1. Accomodation'!Q308 -> 0 | F304: ='1. Accomodation'!O308 -> 0 | G304: ='1. Accomodation'!R308 -> 0 | H304: ='1. Accomodation'!S308 -> 0 | K304: =IFERROR(INDEX('2. GRI Pricing Inputs'!$C$15:$AI$16,MATCH($K$16,'2. GRI Pricing Inputs'!$C$15:$C$16,0),MATCH(D304,'2. GRI Pricing Inputs'!$C$15:$AI$15,0)),0) -> 0 | L304: =IFERROR(INDEX('2. GRI Pricing Inputs'!$C$22:$AI$23,MATCH($L$16,'2. GRI Pricing Inputs'!$C$22:$C$23,0),MATCH(E304,'2. GRI Pricing Inputs'!$C$22:$AI$22,0)),0) -> 0 | M304: =IF(AND('3. GRI Pricing'!$F304>='2. GRI Pricing Inputs'!$D$33,'3. GRI Pricing'!$F304<='2. GRI Pricing Inputs'!$E$33),'2. GRI Pricing Inputs'!$D$32,IF(AND('3. GRI Pricing'!$F304>='2. GRI Pricing Inputs'!$F$33,'3. GRI Pricing'!$F304<='2. GRI Pricing Inputs'!$G$33),'2. GRI Pricing Inputs'!$F$32,IF(AND('3. GRI Pricing'!$F304>='2. GRI Pricing Inputs'!$H$33,'3. GRI Pricing'!$F304<='2. GRI Pricing Inputs'!$I$33),'2. GRI Pricing Inputs'!$H$32,IF(AND('3. GRI Pricing'!$F304>='2. GRI Pricing Inputs'!$J$33,'3. GRI Pricing'!$F304<='2. GRI Pricing Inputs'!$K$33),'2. GRI Pricing Inputs'!$J$32,IF(AND('3. GRI Pricing'!$F304>='2. GRI Pricing Inputs'!$L$33,'3. GRI Pricing'!$F304<='2. GRI Pricing Inputs'!$M$33),'2. GRI Pricing Inputs'!$L$32,IF(AND('3. GRI Pricing'!$F304>='2. GRI Pricing Inputs'!$N$33,'3. GRI Pricing'!$F304<='2. GRI Pricing Inputs'!$O$33),'2. GRI Pricing Inputs'!$N$32,IF(AND('3. GRI Pricing'!$F304>='2. GRI Pricing Inputs'!$P$33,'3. GRI Pricing'!$F304<='2. GRI Pricing Inputs'!$Q$33),'2. GRI Pricing Inputs'!$P$32,IF(AND('3. GRI Pricing'!$F304>='2. GRI Pricing Inputs'!$R$33,'3. GRI Pricing'!$F304<='2. GRI Pricing Inputs'!$S$33),'2. GRI Pricing Inputs'!$R$32,IF(AND('3. GRI Pricing'!$F304>='2. GRI Pricing Inputs'!$T$33,'3. GRI Pricing'!$F304<='2. GRI Pricing Inputs'!$U$33),'2. GRI Pricing Inputs'!$T$32,IF(AND('3. GRI Pricing'!$F304>='2. GRI Pricing Inputs'!$V$33,'3. GRI Pricing'!$F304<='2. GRI Pricing Inputs'!$W$33),'2. GRI Pricing Inputs'!$V$32,IF(AND('3. GRI Pricing'!$F304>='2. GRI Pricing Inputs'!$X$33,'3. GRI Pricing'!$F304<='2. GRI Pricing Inputs'!$Y$33),'2. GRI Pricing Inputs'!$X$32,IF(AND('3. GRI Pricing'!$F304>='2. GRI Pricing Inputs'!$Z$33,'3. GRI Pricing'!$F304<='2. GRI Pricing Inputs'!$AA$33),'2. GRI Pricing Inputs'!$Z$32,IF(AND('3. GRI Pricing'!$F304>='2. GRI Pricing Inputs'!$AB$33,'3. GRI Pricing'!$F304<='2. GRI Pricing Inputs'!$AC$33),'2. GRI Pricing Inputs'!$AB$32,IF(AND('3. GRI Pricing'!$F304>='2. GRI Pricing Inputs'!$AD$33,'3. GRI Pricing'!$F304<='2. GRI Pricing Inputs'!$AE$33),'2. GRI Pricing Inputs'!$AD$32,IF(AND('3. GRI Pricing'!$F304>='2. GRI Pricing Inputs'!$AF$33,'3. GRI Pricing'!$F304<='2. GRI Pricing Inputs'!$AG$33),'2. GRI Pricing Inputs'!$AF$32,IF(AND('3. GRI Pricing'!$F304>='2. GRI Pricing Inputs'!$AH$33,'3. GRI Pricing'!$F304<='2. GRI Pricing Inputs'!$AI$33),'2. GRI Pricing Inputs'!$AH$32,0)))))))))))))))) -> 0 | N304: {=IFERROR(INDEX('2. GRI Pricing Inputs'!$C$32:$AI$39,MATCH('3. GRI Pricing'!D304,'2. GRI Pricing Inputs'!$C$32:$C$39,0),(MATCH('3. GRI Pricing'!M304,'2. GRI Pricing Inputs'!$D$32:$AI$32,0)+1)),0)} -> 0 | O304: =IFERROR(INDEX('2. GRI Pricing Inputs'!$C$45:$AI$46,MATCH($O$16,'2. GRI Pricing Inputs'!$C$45:$C$46,0),MATCH(G304,'2. GRI Pricing Inputs'!$C$45:$AI$45,0)),0) -> 0 | P304: =IFERROR(INDEX('2. GRI Pricing Inputs'!$C$53:$AI$54,MATCH('3. GRI Pricing'!$P$16,'2. GRI Pricing Inputs'!$C$53:$C$54,0),MATCH('3. GRI Pricing'!H304,'2. GRI Pricing Inputs'!$C$53:$AI$53,0)),0) -> 0 | Q304: =IFERROR(INDEX('2. GRI Pricing Inputs'!$C$60:$AI$61,MATCH('3. GRI Pricing'!$Q$16,'2. GRI Pricing Inputs'!$C$60:$C$61,0),MATCH('1. Accomodation'!T308,'2. GRI Pricing Inputs'!$C$60:$AI$60,0)),0) -> 0 | R304: =IFERROR(INDEX('2. GRI Pricing Inputs'!$C$67:$AI$68,MATCH('3. GRI Pricing'!$R$16,'2. GRI Pricing Inputs'!$C$67:$C$68,0),MATCH('1. Accomodation'!U308,'2. GRI Pricing Inputs'!$C$67:$AI$67,0)),0) -> 0 | S304: =IF(D304=0,0,'2. GRI Pricing Inputs'!$AI$75) -> 0 | T304: =IFERROR(INDEX('2. GRI Pricing Inputs'!$C$82:$AI$83,MATCH('3. GRI Pricing'!$T$16,'2. GRI Pricing Inputs'!$C$82:$C$83,0),MATCH('1. Accomodation'!V308,'2. GRI Pricing Inputs'!$C$82:$AI$82,0)),0) -> 0 | U304: =IFERROR(INDEX('2. GRI Pricing Inputs'!$C$89:$AI$90,MATCH('3. GRI Pricing'!$U$16,'2. GRI Pricing Inputs'!$C$89:$C$90,0),MATCH('1. Accomodation'!W308,'2. GRI Pricing Inputs'!$C$89:$AI$89,0)),0) -> 0 | V304: =IFERROR(INDEX('2. GRI Pricing Inputs'!$C$97:$AI$98,MATCH('3. GRI Pricing'!$V$16,'2. GRI Pricing Inputs'!$C$97:$C$98,0),MATCH('1. Accomodation'!X308,'2. GRI Pricing Inputs'!$C$97:$AI$97,0)),0) -> 0 | W304: =IFERROR(INDEX('2. GRI Pricing Inputs'!$C$104:$AI$105,MATCH('3. GRI Pricing'!$W$16,'2. GRI Pricing Inputs'!$C$104:$C$105,0),MATCH('1. Accomodation'!Y308,'2. GRI Pricing Inputs'!$C$104:$AI$104,0)),0) -> 0 | Y304: =K304+L304+N304+O304+P304+Q304+R304+S304+T304+U304+V304+W304+X304 -> 0 | AC304: =Y304*(1+'2. GRI Pricing Inputs'!$D$114)^(($AC$16-$AB$15)/365) -> 0 | AD304: =AC304*(1+'2. GRI Pricing Inputs'!$D$114)^((AD$16-AC$16)/365) -> 0 | AE304: =AD304*(1+'2. GRI Pricing Inputs'!$D$114)^((AE$16-AD$16)/365) -> 0 | AF304: =AE304*(1+'2. GRI Pricing Inputs'!$D$114)^((AF$16-AE$16)/365) -> 0 | AG304: =AF304*(1+'2. GRI Pricing Inputs'!$D$114)^((AG$16-AF$16)/365) -> 0 | AH304: =AG304*(1+'2. GRI Pricing Inputs'!$D$114)^((AH$16-AG$16)/365) -> 0 | AI304: =AH304*(1+'2. GRI Pricing Inputs'!$D$114)^((AI$16-AH$16)/365) -> 0 | AJ304: =AI304*(1+'2. GRI Pricing Inputs'!$D$114)^((AJ$16-AI$16)/365) -> 0 | AK304: =AJ304*(1+'2. GRI Pricing Inputs'!$D$114)^((AK$16-AJ$16)/365) -> 0 | ... AO304: =AN304*(1+'2. GRI Pricing Inputs'!$D$114)^((AO$16-AN$16)/365) -> 0
C305: ='1. Accomodation'!N309 -> 0 | D305: ='1. Accomodation'!P309 -> 0 | E305: ='1. Accomodation'!Q309 -> 0 | F305: ='1. Accomodation'!O309 -> 0 | G305: ='1. Accomodation'!R309 -> 0 | H305: ='1. Accomodation'!S309 -> 0 | K305: =IFERROR(INDEX('2. GRI Pricing Inputs'!$C$15:$AI$16,MATCH($K$16,'2. GRI Pricing Inputs'!$C$15:$C$16,0),MATCH(D305,'2. GRI Pricing Inputs'!$C$15:$AI$15,0)),0) -> 0 | L305: =IFERROR(INDEX('2. GRI Pricing Inputs'!$C$22:$AI$23,MATCH($L$16,'2. GRI Pricing Inputs'!$C$22:$C$23,0),MATCH(E305,'2. GRI Pricing Inputs'!$C$22:$AI$22,0)),0) -> 0 | M305: =IF(AND('3. GRI Pricing'!$F305>='2. GRI Pricing Inputs'!$D$33,'3. GRI Pricing'!$F305<='2. GRI Pricing Inputs'!$E$33),'2. GRI Pricing Inputs'!$D$32,IF(AND('3. GRI Pricing'!$F305>='2. GRI Pricing Inputs'!$F$33,'3. GRI Pricing'!$F305<='2. GRI Pricing Inputs'!$G$33),'2. GRI Pricing Inputs'!$F$32,IF(AND('3. GRI Pricing'!$F305>='2. GRI Pricing Inputs'!$H$33,'3. GRI Pricing'!$F305<='2. GRI Pricing Inputs'!$I$33),'2. GRI Pricing Inputs'!$H$32,IF(AND('3. GRI Pricing'!$F305>='2. GRI Pricing Inputs'!$J$33,'3. GRI Pricing'!$F305<='2. GRI Pricing Inputs'!$K$33),'2. GRI Pricing Inputs'!$J$32,IF(AND('3. GRI Pricing'!$F305>='2. GRI Pricing Inputs'!$L$33,'3. GRI Pricing'!$F305<='2. GRI Pricing Inputs'!$M$33),'2. GRI Pricing Inputs'!$L$32,IF(AND('3. GRI Pricing'!$F305>='2. GRI Pricing Inputs'!$N$33,'3. GRI Pricing'!$F305<='2. GRI Pricing Inputs'!$O$33),'2. GRI Pricing Inputs'!$N$32,IF(AND('3. GRI Pricing'!$F305>='2. GRI Pricing Inputs'!$P$33,'3. GRI Pricing'!$F305<='2. GRI Pricing Inputs'!$Q$33),'2. GRI Pricing Inputs'!$P$32,IF(AND('3. GRI Pricing'!$F305>='2. GRI Pricing Inputs'!$R$33,'3. GRI Pricing'!$F305<='2. GRI Pricing Inputs'!$S$33),'2. GRI Pricing Inputs'!$R$32,IF(AND('3. GRI Pricing'!$F305>='2. GRI Pricing Inputs'!$T$33,'3. GRI Pricing'!$F305<='2. GRI Pricing Inputs'!$U$33),'2. GRI Pricing Inputs'!$T$32,IF(AND('3. GRI Pricing'!$F305>='2. GRI Pricing Inputs'!$V$33,'3. GRI Pricing'!$F305<='2. GRI Pricing Inputs'!$W$33),'2. GRI Pricing Inputs'!$V$32,IF(AND('3. GRI Pricing'!$F305>='2. GRI Pricing Inputs'!$X$33,'3. GRI Pricing'!$F305<='2. GRI Pricing Inputs'!$Y$33),'2. GRI Pricing Inputs'!$X$32,IF(AND('3. GRI Pricing'!$F305>='2. GRI Pricing Inputs'!$Z$33,'3. GRI Pricing'!$F305<='2. GRI Pricing Inputs'!$AA$33),'2. GRI Pricing Inputs'!$Z$32,IF(AND('3. GRI Pricing'!$F305>='2. GRI Pricing Inputs'!$AB$33,'3. GRI Pricing'!$F305<='2. GRI Pricing Inputs'!$AC$33),'2. GRI Pricing Inputs'!$AB$32,IF(AND('3. GRI Pricing'!$F305>='2. GRI Pricing Inputs'!$AD$33,'3. GRI Pricing'!$F305<='2. GRI Pricing Inputs'!$AE$33),'2. GRI Pricing Inputs'!$AD$32,IF(AND('3. GRI Pricing'!$F305>='2. GRI Pricing Inputs'!$AF$33,'3. GRI Pricing'!$F305<='2. GRI Pricing Inputs'!$AG$33),'2. GRI Pricing Inputs'!$AF$32,IF(AND('3. GRI Pricing'!$F305>='2. GRI Pricing Inputs'!$AH$33,'3. GRI Pricing'!$F305<='2. GRI Pricing Inputs'!$AI$33),'2. GRI Pricing Inputs'!$AH$32,0)))))))))))))))) -> 0 | N305: {=IFERROR(INDEX('2. GRI Pricing Inputs'!$C$32:$AI$39,MATCH('3. GRI Pricing'!D305,'2. GRI Pricing Inputs'!$C$32:$C$39,0),(MATCH('3. GRI Pricing'!M305,'2. GRI Pricing Inputs'!$D$32:$AI$32,0)+1)),0)} -> 0 | O305: =IFERROR(INDEX('2. GRI Pricing Inputs'!$C$45:$AI$46,MATCH($O$16,'2. GRI Pricing Inputs'!$C$45:$C$46,0),MATCH(G305,'2. GRI Pricing Inputs'!$C$45:$AI$45,0)),0) -> 0 | P305: =IFERROR(INDEX('2. GRI Pricing Inputs'!$C$53:$AI$54,MATCH('3. GRI Pricing'!$P$16,'2. GRI Pricing Inputs'!$C$53:$C$54,0),MATCH('3. GRI Pricing'!H305,'2. GRI Pricing Inputs'!$C$53:$AI$53,0)),0) -> 0 | Q305: =IFERROR(INDEX('2. GRI Pricing Inputs'!$C$60:$AI$61,MATCH('3. GRI Pricing'!$Q$16,'2. GRI Pricing Inputs'!$C$60:$C$61,0),MATCH('1. Accomodation'!T309,'2. GRI Pricing Inputs'!$C$60:$AI$60,0)),0) -> 0 | R305: =IFERROR(INDEX('2. GRI Pricing Inputs'!$C$67:$AI$68,MATCH('3. GRI Pricing'!$R$16,'2. GRI Pricing Inputs'!$C$67:$C$68,0),MATCH('1. Accomodation'!U309,'2. GRI Pricing Inputs'!$C$67:$AI$67,0)),0) -> 0 | S305: =IF(D305=0,0,'2. GRI Pricing Inputs'!$AI$75) -> 0 | T305: =IFERROR(INDEX('2. GRI Pricing Inputs'!$C$82:$AI$83,MATCH('3. GRI Pricing'!$T$16,'2. GRI Pricing Inputs'!$C$82:$C$83,0),MATCH('1. Accomodation'!V309,'2. GRI Pricing Inputs'!$C$82:$AI$82,0)),0) -> 0 | U305: =IFERROR(INDEX('2. GRI Pricing Inputs'!$C$89:$AI$90,MATCH('3. GRI Pricing'!$U$16,'2. GRI Pricing Inputs'!$C$89:$C$90,0),MATCH('1. Accomodation'!W309,'2. GRI Pricing Inputs'!$C$89:$AI$89,0)),0) -> 0 | V305: =IFERROR(INDEX('2. GRI Pricing Inputs'!$C$97:$AI$98,MATCH('3. GRI Pricing'!$V$16,'2. GRI Pricing Inputs'!$C$97:$C$98,0),MATCH('1. Accomodation'!X309,'2. GRI Pricing Inputs'!$C$97:$AI$97,0)),0) -> 0 | W305: =IFERROR(INDEX('2. GRI Pricing Inputs'!$C$104:$AI$105,MATCH('3. GRI Pricing'!$W$16,'2. GRI Pricing Inputs'!$C$104:$C$105,0),MATCH('1. Accomodation'!Y309,'2. GRI Pricing Inputs'!$C$104:$AI$104,0)),0) -> 0 | Y305: =K305+L305+N305+O305+P305+Q305+R305+S305+T305+U305+V305+W305+X305 -> 0 | AC305: =Y305*(1+'2. GRI Pricing Inputs'!$D$114)^(($AC$16-$AB$15)/365) -> 0 | AD305: =AC305*(1+'2. GRI Pricing Inputs'!$D$114)^((AD$16-AC$16)/365) -> 0 | AE305: =AD305*(1+'2. GRI Pricing Inputs'!$D$114)^((AE$16-AD$16)/365) -> 0 | AF305: =AE305*(1+'2. GRI Pricing Inputs'!$D$114)^((AF$16-AE$16)/365) -> 0 | AG305: =AF305*(1+'2. GRI Pricing Inputs'!$D$114)^((AG$16-AF$16)/365) -> 0 | AH305: =AG305*(1+'2. GRI Pricing Inputs'!$D$114)^((AH$16-AG$16)/365) -> 0 | AI305: =AH305*(1+'2. GRI Pricing Inputs'!$D$114)^((AI$16-AH$16)/365) -> 0 | AJ305: =AI305*(1+'2. GRI Pricing Inputs'!$D$114)^((AJ$16-AI$16)/365) -> 0 | AK305: =AJ305*(1+'2. GRI Pricing Inputs'!$D$114)^((AK$16-AJ$16)/365) -> 0 | ... AO305: =AN305*(1+'2. GRI Pricing Inputs'!$D$114)^((AO$16-AN$16)/365) -> 0
C306: ='1. Accomodation'!N310 -> 0 | D306: ='1. Accomodation'!P310 -> 0 | E306: ='1. Accomodation'!Q310 -> 0 | F306: ='1. Accomodation'!O310 -> 0 | G306: ='1. Accomodation'!R310 -> 0 | H306: ='1. Accomodation'!S310 -> 0 | K306: =IFERROR(INDEX('2. GRI Pricing Inputs'!$C$15:$AI$16,MATCH($K$16,'2. GRI Pricing Inputs'!$C$15:$C$16,0),MATCH(D306,'2. GRI Pricing Inputs'!$C$15:$AI$15,0)),0) -> 0 | L306: =IFERROR(INDEX('2. GRI Pricing Inputs'!$C$22:$AI$23,MATCH($L$16,'2. GRI Pricing Inputs'!$C$22:$C$23,0),MATCH(E306,'2. GRI Pricing Inputs'!$C$22:$AI$22,0)),0) -> 0 | M306: =IF(AND('3. GRI Pricing'!$F306>='2. GRI Pricing Inputs'!$D$33,'3. GRI Pricing'!$F306<='2. GRI Pricing Inputs'!$E$33),'2. GRI Pricing Inputs'!$D$32,IF(AND('3. GRI Pricing'!$F306>='2. GRI Pricing Inputs'!$F$33,'3. GRI Pricing'!$F306<='2. GRI Pricing Inputs'!$G$33),'2. GRI Pricing Inputs'!$F$32,IF(AND('3. GRI Pricing'!$F306>='2. GRI Pricing Inputs'!$H$33,'3. GRI Pricing'!$F306<='2. GRI Pricing Inputs'!$I$33),'2. GRI Pricing Inputs'!$H$32,IF(AND('3. GRI Pricing'!$F306>='2. GRI Pricing Inputs'!$J$33,'3. GRI Pricing'!$F306<='2. GRI Pricing Inputs'!$K$33),'2. GRI Pricing Inputs'!$J$32,IF(AND('3. GRI Pricing'!$F306>='2. GRI Pricing Inputs'!$L$33,'3. GRI Pricing'!$F306<='2. GRI Pricing Inputs'!$M$33),'2. GRI Pricing Inputs'!$L$32,IF(AND('3. GRI Pricing'!$F306>='2. GRI Pricing Inputs'!$N$33,'3. GRI Pricing'!$F306<='2. GRI Pricing Inputs'!$O$33),'2. GRI Pricing Inputs'!$N$32,IF(AND('3. GRI Pricing'!$F306>='2. GRI Pricing Inputs'!$P$33,'3. GRI Pricing'!$F306<='2. GRI Pricing Inputs'!$Q$33),'2. GRI Pricing Inputs'!$P$32,IF(AND('3. GRI Pricing'!$F306>='2. GRI Pricing Inputs'!$R$33,'3. GRI Pricing'!$F306<='2. GRI Pricing Inputs'!$S$33),'2. GRI Pricing Inputs'!$R$32,IF(AND('3. GRI Pricing'!$F306>='2. GRI Pricing Inputs'!$T$33,'3. GRI Pricing'!$F306<='2. GRI Pricing Inputs'!$U$33),'2. GRI Pricing Inputs'!$T$32,IF(AND('3. GRI Pricing'!$F306>='2. GRI Pricing Inputs'!$V$33,'3. GRI Pricing'!$F306<='2. GRI Pricing Inputs'!$W$33),'2. GRI Pricing Inputs'!$V$32,IF(AND('3. GRI Pricing'!$F306>='2. GRI Pricing Inputs'!$X$33,'3. GRI Pricing'!$F306<='2. GRI Pricing Inputs'!$Y$33),'2. GRI Pricing Inputs'!$X$32,IF(AND('3. GRI Pricing'!$F306>='2. GRI Pricing Inputs'!$Z$33,'3. GRI Pricing'!$F306<='2. GRI Pricing Inputs'!$AA$33),'2. GRI Pricing Inputs'!$Z$32,IF(AND('3. GRI Pricing'!$F306>='2. GRI Pricing Inputs'!$AB$33,'3. GRI Pricing'!$F306<='2. GRI Pricing Inputs'!$AC$33),'2. GRI Pricing Inputs'!$AB$32,IF(AND('3. GRI Pricing'!$F306>='2. GRI Pricing Inputs'!$AD$33,'3. GRI Pricing'!$F306<='2. GRI Pricing Inputs'!$AE$33),'2. GRI Pricing Inputs'!$AD$32,IF(AND('3. GRI Pricing'!$F306>='2. GRI Pricing Inputs'!$AF$33,'3. GRI Pricing'!$F306<='2. GRI Pricing Inputs'!$AG$33),'2. GRI Pricing Inputs'!$AF$32,IF(AND('3. GRI Pricing'!$F306>='2. GRI Pricing Inputs'!$AH$33,'3. GRI Pricing'!$F306<='2. GRI Pricing Inputs'!$AI$33),'2. GRI Pricing Inputs'!$AH$32,0)))))))))))))))) -> 0 | N306: {=IFERROR(INDEX('2. GRI Pricing Inputs'!$C$32:$AI$39,MATCH('3. GRI Pricing'!D306,'2. GRI Pricing Inputs'!$C$32:$C$39,0),(MATCH('3. GRI Pricing'!M306,'2. GRI Pricing Inputs'!$D$32:$AI$32,0)+1)),0)} -> 0 | O306: =IFERROR(INDEX('2. GRI Pricing Inputs'!$C$45:$AI$46,MATCH($O$16,'2. GRI Pricing Inputs'!$C$45:$C$46,0),MATCH(G306,'2. GRI Pricing Inputs'!$C$45:$AI$45,0)),0) -> 0 | P306: =IFERROR(INDEX('2. GRI Pricing Inputs'!$C$53:$AI$54,MATCH('3. GRI Pricing'!$P$16,'2. GRI Pricing Inputs'!$C$53:$C$54,0),MATCH('3. GRI Pricing'!H306,'2. GRI Pricing Inputs'!$C$53:$AI$53,0)),0) -> 0 | Q306: =IFERROR(INDEX('2. GRI Pricing Inputs'!$C$60:$AI$61,MATCH('3. GRI Pricing'!$Q$16,'2. GRI Pricing Inputs'!$C$60:$C$61,0),MATCH('1. Accomodation'!T310,'2. GRI Pricing Inputs'!$C$60:$AI$60,0)),0) -> 0 | R306: =IFERROR(INDEX('2. GRI Pricing Inputs'!$C$67:$AI$68,MATCH('3. GRI Pricing'!$R$16,'2. GRI Pricing Inputs'!$C$67:$C$68,0),MATCH('1. Accomodation'!U310,'2. GRI Pricing Inputs'!$C$67:$AI$67,0)),0) -> 0 | S306: =IF(D306=0,0,'2. GRI Pricing Inputs'!$AI$75) -> 0 | T306: =IFERROR(INDEX('2. GRI Pricing Inputs'!$C$82:$AI$83,MATCH('3. GRI Pricing'!$T$16,'2. GRI Pricing Inputs'!$C$82:$C$83,0),MATCH('1. Accomodation'!V310,'2. GRI Pricing Inputs'!$C$82:$AI$82,0)),0) -> 0 | U306: =IFERROR(INDEX('2. GRI Pricing Inputs'!$C$89:$AI$90,MATCH('3. GRI Pricing'!$U$16,'2. GRI Pricing Inputs'!$C$89:$C$90,0),MATCH('1. Accomodation'!W310,'2. GRI Pricing Inputs'!$C$89:$AI$89,0)),0) -> 0 | V306: =IFERROR(INDEX('2. GRI Pricing Inputs'!$C$97:$AI$98,MATCH('3. GRI Pricing'!$V$16,'2. GRI Pricing Inputs'!$C$97:$C$98,0),MATCH('1. Accomodation'!X310,'2. GRI Pricing Inputs'!$C$97:$AI$97,0)),0) -> 0 | W306: =IFERROR(INDEX('2. GRI Pricing Inputs'!$C$104:$AI$105,MATCH('3. GRI Pricing'!$W$16,'2. GRI Pricing Inputs'!$C$104:$C$105,0),MATCH('1. Accomodation'!Y310,'2. GRI Pricing Inputs'!$C$104:$AI$104,0)),0) -> 0 | Y306: =K306+L306+N306+O306+P306+Q306+R306+S306+T306+U306+V306+W306+X306 -> 0 | AC306: =Y306*(1+'2. GRI Pricing Inputs'!$D$114)^(($AC$16-$AB$15)/365) -> 0 | AD306: =AC306*(1+'2. GRI Pricing Inputs'!$D$114)^((AD$16-AC$16)/365) -> 0 | AE306: =AD306*(1+'2. GRI Pricing Inputs'!$D$114)^((AE$16-AD$16)/365) -> 0 | AF306: =AE306*(1+'2. GRI Pricing Inputs'!$D$114)^((AF$16-AE$16)/365) -> 0 | AG306: =AF306*(1+'2. GRI Pricing Inputs'!$D$114)^((AG$16-AF$16)/365) -> 0 | AH306: =AG306*(1+'2. GRI Pricing Inputs'!$D$114)^((AH$16-AG$16)/365) -> 0 | AI306: =AH306*(1+'2. GRI Pricing Inputs'!$D$114)^((AI$16-AH$16)/365) -> 0 | AJ306: =AI306*(1+'2. GRI Pricing Inputs'!$D$114)^((AJ$16-AI$16)/365) -> 0 | AK306: =AJ306*(1+'2. GRI Pricing Inputs'!$D$114)^((AK$16-AJ$16)/365) -> 0 | ... AO306: =AN306*(1+'2. GRI Pricing Inputs'!$D$114)^((AO$16-AN$16)/365) -> 0
C307: ='1. Accomodation'!N311 -> 0 | D307: ='1. Accomodation'!P311 -> 0 | E307: ='1. Accomodation'!Q311 -> 0 | F307: ='1. Accomodation'!O311 -> 0 | G307: ='1. Accomodation'!R311 -> 0 | H307: ='1. Accomodation'!S311 -> 0 | K307: =IFERROR(INDEX('2. GRI Pricing Inputs'!$C$15:$AI$16,MATCH($K$16,'2. GRI Pricing Inputs'!$C$15:$C$16,0),MATCH(D307,'2. GRI Pricing Inputs'!$C$15:$AI$15,0)),0) -> 0 | L307: =IFERROR(INDEX('2. GRI Pricing Inputs'!$C$22:$AI$23,MATCH($L$16,'2. GRI Pricing Inputs'!$C$22:$C$23,0),MATCH(E307,'2. GRI Pricing Inputs'!$C$22:$AI$22,0)),0) -> 0 | M307: =IF(AND('3. GRI Pricing'!$F307>='2. GRI Pricing Inputs'!$D$33,'3. GRI Pricing'!$F307<='2. GRI Pricing Inputs'!$E$33),'2. GRI Pricing Inputs'!$D$32,IF(AND('3. GRI Pricing'!$F307>='2. GRI Pricing Inputs'!$F$33,'3. GRI Pricing'!$F307<='2. GRI Pricing Inputs'!$G$33),'2. GRI Pricing Inputs'!$F$32,IF(AND('3. GRI Pricing'!$F307>='2. GRI Pricing Inputs'!$H$33,'3. GRI Pricing'!$F307<='2. GRI Pricing Inputs'!$I$33),'2. GRI Pricing Inputs'!$H$32,IF(AND('3. GRI Pricing'!$F307>='2. GRI Pricing Inputs'!$J$33,'3. GRI Pricing'!$F307<='2. GRI Pricing Inputs'!$K$33),'2. GRI Pricing Inputs'!$J$32,IF(AND('3. GRI Pricing'!$F307>='2. GRI Pricing Inputs'!$L$33,'3. GRI Pricing'!$F307<='2. GRI Pricing Inputs'!$M$33),'2. GRI Pricing Inputs'!$L$32,IF(AND('3. GRI Pricing'!$F307>='2. GRI Pricing Inputs'!$N$33,'3. GRI Pricing'!$F307<='2. GRI Pricing Inputs'!$O$33),'2. GRI Pricing Inputs'!$N$32,IF(AND('3. GRI Pricing'!$F307>='2. GRI Pricing Inputs'!$P$33,'3. GRI Pricing'!$F307<='2. GRI Pricing Inputs'!$Q$33),'2. GRI Pricing Inputs'!$P$32,IF(AND('3. GRI Pricing'!$F307>='2. GRI Pricing Inputs'!$R$33,'3. GRI Pricing'!$F307<='2. GRI Pricing Inputs'!$S$33),'2. GRI Pricing Inputs'!$R$32,IF(AND('3. GRI Pricing'!$F307>='2. GRI Pricing Inputs'!$T$33,'3. GRI Pricing'!$F307<='2. GRI Pricing Inputs'!$U$33),'2. GRI Pricing Inputs'!$T$32,IF(AND('3. GRI Pricing'!$F307>='2. GRI Pricing Inputs'!$V$33,'3. GRI Pricing'!$F307<='2. GRI Pricing Inputs'!$W$33),'2. GRI Pricing Inputs'!$V$32,IF(AND('3. GRI Pricing'!$F307>='2. GRI Pricing Inputs'!$X$33,'3. GRI Pricing'!$F307<='2. GRI Pricing Inputs'!$Y$33),'2. GRI Pricing Inputs'!$X$32,IF(AND('3. GRI Pricing'!$F307>='2. GRI Pricing Inputs'!$Z$33,'3. GRI Pricing'!$F307<='2. GRI Pricing Inputs'!$AA$33),'2. GRI Pricing Inputs'!$Z$32,IF(AND('3. GRI Pricing'!$F307>='2. GRI Pricing Inputs'!$AB$33,'3. GRI Pricing'!$F307<='2. GRI Pricing Inputs'!$AC$33),'2. GRI Pricing Inputs'!$AB$32,IF(AND('3. GRI Pricing'!$F307>='2. GRI Pricing Inputs'!$AD$33,'3. GRI Pricing'!$F307<='2. GRI Pricing Inputs'!$AE$33),'2. GRI Pricing Inputs'!$AD$32,IF(AND('3. GRI Pricing'!$F307>='2. GRI Pricing Inputs'!$AF$33,'3. GRI Pricing'!$F307<='2. GRI Pricing Inputs'!$AG$33),'2. GRI Pricing Inputs'!$AF$32,IF(AND('3. GRI Pricing'!$F307>='2. GRI Pricing Inputs'!$AH$33,'3. GRI Pricing'!$F307<='2. GRI Pricing Inputs'!$AI$33),'2. GRI Pricing Inputs'!$AH$32,0)))))))))))))))) -> 0 | N307: {=IFERROR(INDEX('2. GRI Pricing Inputs'!$C$32:$AI$39,MATCH('3. GRI Pricing'!D307,'2. GRI Pricing Inputs'!$C$32:$C$39,0),(MATCH('3. GRI Pricing'!M307,'2. GRI Pricing Inputs'!$D$32:$AI$32,0)+1)),0)} -> 0 | O307: =IFERROR(INDEX('2. GRI Pricing Inputs'!$C$45:$AI$46,MATCH($O$16,'2. GRI Pricing Inputs'!$C$45:$C$46,0),MATCH(G307,'2. GRI Pricing Inputs'!$C$45:$AI$45,0)),0) -> 0 | P307: =IFERROR(INDEX('2. GRI Pricing Inputs'!$C$53:$AI$54,MATCH('3. GRI Pricing'!$P$16,'2. GRI Pricing Inputs'!$C$53:$C$54,0),MATCH('3. GRI Pricing'!H307,'2. GRI Pricing Inputs'!$C$53:$AI$53,0)),0) -> 0 | Q307: =IFERROR(INDEX('2. GRI Pricing Inputs'!$C$60:$AI$61,MATCH('3. GRI Pricing'!$Q$16,'2. GRI Pricing Inputs'!$C$60:$C$61,0),MATCH('1. Accomodation'!T311,'2. GRI Pricing Inputs'!$C$60:$AI$60,0)),0) -> 0 | R307: =IFERROR(INDEX('2. GRI Pricing Inputs'!$C$67:$AI$68,MATCH('3. GRI Pricing'!$R$16,'2. GRI Pricing Inputs'!$C$67:$C$68,0),MATCH('1. Accomodation'!U311,'2. GRI Pricing Inputs'!$C$67:$AI$67,0)),0) -> 0 | S307: =IF(D307=0,0,'2. GRI Pricing Inputs'!$AI$75) -> 0 | T307: =IFERROR(INDEX('2. GRI Pricing Inputs'!$C$82:$AI$83,MATCH('3. GRI Pricing'!$T$16,'2. GRI Pricing Inputs'!$C$82:$C$83,0),MATCH('1. Accomodation'!V311,'2. GRI Pricing Inputs'!$C$82:$AI$82,0)),0) -> 0 | U307: =IFERROR(INDEX('2. GRI Pricing Inputs'!$C$89:$AI$90,MATCH('3. GRI Pricing'!$U$16,'2. GRI Pricing Inputs'!$C$89:$C$90,0),MATCH('1. Accomodation'!W311,'2. GRI Pricing Inputs'!$C$89:$AI$89,0)),0) -> 0 | V307: =IFERROR(INDEX('2. GRI Pricing Inputs'!$C$97:$AI$98,MATCH('3. GRI Pricing'!$V$16,'2. GRI Pricing Inputs'!$C$97:$C$98,0),MATCH('1. Accomodation'!X311,'2. GRI Pricing Inputs'!$C$97:$AI$97,0)),0) -> 0 | W307: =IFERROR(INDEX('2. GRI Pricing Inputs'!$C$104:$AI$105,MATCH('3. GRI Pricing'!$W$16,'2. GRI Pricing Inputs'!$C$104:$C$105,0),MATCH('1. Accomodation'!Y311,'2. GRI Pricing Inputs'!$C$104:$AI$104,0)),0) -> 0 | Y307: =K307+L307+N307+O307+P307+Q307+R307+S307+T307+U307+V307+W307+X307 -> 0 | AC307: =Y307*(1+'2. GRI Pricing Inputs'!$D$114)^(($AC$16-$AB$15)/365) -> 0 | AD307: =AC307*(1+'2. GRI Pricing Inputs'!$D$114)^((AD$16-AC$16)/365) -> 0 | AE307: =AD307*(1+'2. GRI Pricing Inputs'!$D$114)^((AE$16-AD$16)/365) -> 0 | AF307: =AE307*(1+'2. GRI Pricing Inputs'!$D$114)^((AF$16-AE$16)/365) -> 0 | AG307: =AF307*(1+'2. GRI Pricing Inputs'!$D$114)^((AG$16-AF$16)/365) -> 0 | AH307: =AG307*(1+'2. GRI Pricing Inputs'!$D$114)^((AH$16-AG$16)/365) -> 0 | AI307: =AH307*(1+'2. GRI Pricing Inputs'!$D$114)^((AI$16-AH$16)/365) -> 0 | AJ307: =AI307*(1+'2. GRI Pricing Inputs'!$D$114)^((AJ$16-AI$16)/365) -> 0 | AK307: =AJ307*(1+'2. GRI Pricing Inputs'!$D$114)^((AK$16-AJ$16)/365) -> 0 | ... AO307: =AN307*(1+'2. GRI Pricing Inputs'!$D$114)^((AO$16-AN$16)/365) -> 0
C308: ='1. Accomodation'!N312 -> 0 | D308: ='1. Accomodation'!P312 -> 0 | E308: ='1. Accomodation'!Q312 -> 0 | F308: ='1. Accomodation'!O312 -> 0 | G308: ='1. Accomodation'!R312 -> 0 | H308: ='1. Accomodation'!S312 -> 0 | K308: =IFERROR(INDEX('2. GRI Pricing Inputs'!$C$15:$AI$16,MATCH($K$16,'2. GRI Pricing Inputs'!$C$15:$C$16,0),MATCH(D308,'2. GRI Pricing Inputs'!$C$15:$AI$15,0)),0) -> 0 | L308: =IFERROR(INDEX('2. GRI Pricing Inputs'!$C$22:$AI$23,MATCH($L$16,'2. GRI Pricing Inputs'!$C$22:$C$23,0),MATCH(E308,'2. GRI Pricing Inputs'!$C$22:$AI$22,0)),0) -> 0 | M308: =IF(AND('3. GRI Pricing'!$F308>='2. GRI Pricing Inputs'!$D$33,'3. GRI Pricing'!$F308<='2. GRI Pricing Inputs'!$E$33),'2. GRI Pricing Inputs'!$D$32,IF(AND('3. GRI Pricing'!$F308>='2. GRI Pricing Inputs'!$F$33,'3. GRI Pricing'!$F308<='2. GRI Pricing Inputs'!$G$33),'2. GRI Pricing Inputs'!$F$32,IF(AND('3. GRI Pricing'!$F308>='2. GRI Pricing Inputs'!$H$33,'3. GRI Pricing'!$F308<='2. GRI Pricing Inputs'!$I$33),'2. GRI Pricing Inputs'!$H$32,IF(AND('3. GRI Pricing'!$F308>='2. GRI Pricing Inputs'!$J$33,'3. GRI Pricing'!$F308<='2. GRI Pricing Inputs'!$K$33),'2. GRI Pricing Inputs'!$J$32,IF(AND('3. GRI Pricing'!$F308>='2. GRI Pricing Inputs'!$L$33,'3. GRI Pricing'!$F308<='2. GRI Pricing Inputs'!$M$33),'2. GRI Pricing Inputs'!$L$32,IF(AND('3. GRI Pricing'!$F308>='2. GRI Pricing Inputs'!$N$33,'3. GRI Pricing'!$F308<='2. GRI Pricing Inputs'!$O$33),'2. GRI Pricing Inputs'!$N$32,IF(AND('3. GRI Pricing'!$F308>='2. GRI Pricing Inputs'!$P$33,'3. GRI Pricing'!$F308<='2. GRI Pricing Inputs'!$Q$33),'2. GRI Pricing Inputs'!$P$32,IF(AND('3. GRI Pricing'!$F308>='2. GRI Pricing Inputs'!$R$33,'3. GRI Pricing'!$F308<='2. GRI Pricing Inputs'!$S$33),'2. GRI Pricing Inputs'!$R$32,IF(AND('3. GRI Pricing'!$F308>='2. GRI Pricing Inputs'!$T$33,'3. GRI Pricing'!$F308<='2. GRI Pricing Inputs'!$U$33),'2. GRI Pricing Inputs'!$T$32,IF(AND('3. GRI Pricing'!$F308>='2. GRI Pricing Inputs'!$V$33,'3. GRI Pricing'!$F308<='2. GRI Pricing Inputs'!$W$33),'2. GRI Pricing Inputs'!$V$32,IF(AND('3. GRI Pricing'!$F308>='2. GRI Pricing Inputs'!$X$33,'3. GRI Pricing'!$F308<='2. GRI Pricing Inputs'!$Y$33),'2. GRI Pricing Inputs'!$X$32,IF(AND('3. GRI Pricing'!$F308>='2. GRI Pricing Inputs'!$Z$33,'3. GRI Pricing'!$F308<='2. GRI Pricing Inputs'!$AA$33),'2. GRI Pricing Inputs'!$Z$32,IF(AND('3. GRI Pricing'!$F308>='2. GRI Pricing Inputs'!$AB$33,'3. GRI Pricing'!$F308<='2. GRI Pricing Inputs'!$AC$33),'2. GRI Pricing Inputs'!$AB$32,IF(AND('3. GRI Pricing'!$F308>='2. GRI Pricing Inputs'!$AD$33,'3. GRI Pricing'!$F308<='2. GRI Pricing Inputs'!$AE$33),'2. GRI Pricing Inputs'!$AD$32,IF(AND('3. GRI Pricing'!$F308>='2. GRI Pricing Inputs'!$AF$33,'3. GRI Pricing'!$F308<='2. GRI Pricing Inputs'!$AG$33),'2. GRI Pricing Inputs'!$AF$32,IF(AND('3. GRI Pricing'!$F308>='2. GRI Pricing Inputs'!$AH$33,'3. GRI Pricing'!$F308<='2. GRI Pricing Inputs'!$AI$33),'2. GRI Pricing Inputs'!$AH$32,0)))))))))))))))) -> 0 | N308: {=IFERROR(INDEX('2. GRI Pricing Inputs'!$C$32:$AI$39,MATCH('3. GRI Pricing'!D308,'2. GRI Pricing Inputs'!$C$32:$C$39,0),(MATCH('3. GRI Pricing'!M308,'2. GRI Pricing Inputs'!$D$32:$AI$32,0)+1)),0)} -> 0 | O308: =IFERROR(INDEX('2. GRI Pricing Inputs'!$C$45:$AI$46,MATCH($O$16,'2. GRI Pricing Inputs'!$C$45:$C$46,0),MATCH(G308,'2. GRI Pricing Inputs'!$C$45:$AI$45,0)),0) -> 0 | P308: =IFERROR(INDEX('2. GRI Pricing Inputs'!$C$53:$AI$54,MATCH('3. GRI Pricing'!$P$16,'2. GRI Pricing Inputs'!$C$53:$C$54,0),MATCH('3. GRI Pricing'!H308,'2. GRI Pricing Inputs'!$C$53:$AI$53,0)),0) -> 0 | Q308: =IFERROR(INDEX('2. GRI Pricing Inputs'!$C$60:$AI$61,MATCH('3. GRI Pricing'!$Q$16,'2. GRI Pricing Inputs'!$C$60:$C$61,0),MATCH('1. Accomodation'!T312,'2. GRI Pricing Inputs'!$C$60:$AI$60,0)),0) -> 0 | R308: =IFERROR(INDEX('2. GRI Pricing Inputs'!$C$67:$AI$68,MATCH('3. GRI Pricing'!$R$16,'2. GRI Pricing Inputs'!$C$67:$C$68,0),MATCH('1. Accomodation'!U312,'2. GRI Pricing Inputs'!$C$67:$AI$67,0)),0) -> 0 | S308: =IF(D308=0,0,'2. GRI Pricing Inputs'!$AI$75) -> 0 | T308: =IFERROR(INDEX('2. GRI Pricing Inputs'!$C$82:$AI$83,MATCH('3. GRI Pricing'!$T$16,'2. GRI Pricing Inputs'!$C$82:$C$83,0),MATCH('1. Accomodation'!V312,'2. GRI Pricing Inputs'!$C$82:$AI$82,0)),0) -> 0 | U308: =IFERROR(INDEX('2. GRI Pricing Inputs'!$C$89:$AI$90,MATCH('3. GRI Pricing'!$U$16,'2. GRI Pricing Inputs'!$C$89:$C$90,0),MATCH('1. Accomodation'!W312,'2. GRI Pricing Inputs'!$C$89:$AI$89,0)),0) -> 0 | V308: =IFERROR(INDEX('2. GRI Pricing Inputs'!$C$97:$AI$98,MATCH('3. GRI Pricing'!$V$16,'2. GRI Pricing Inputs'!$C$97:$C$98,0),MATCH('1. Accomodation'!X312,'2. GRI Pricing Inputs'!$C$97:$AI$97,0)),0) -> 0 | W308: =IFERROR(INDEX('2. GRI Pricing Inputs'!$C$104:$AI$105,MATCH('3. GRI Pricing'!$W$16,'2. GRI Pricing Inputs'!$C$104:$C$105,0),MATCH('1. Accomodation'!Y312,'2. GRI Pricing Inputs'!$C$104:$AI$104,0)),0) -> 0 | Y308: =K308+L308+N308+O308+P308+Q308+R308+S308+T308+U308+V308+W308+X308 -> 0 | AC308: =Y308*(1+'2. GRI Pricing Inputs'!$D$114)^(($AC$16-$AB$15)/365) -> 0 | AD308: =AC308*(1+'2. GRI Pricing Inputs'!$D$114)^((AD$16-AC$16)/365) -> 0 | AE308: =AD308*(1+'2. GRI Pricing Inputs'!$D$114)^((AE$16-AD$16)/365) -> 0 | AF308: =AE308*(1+'2. GRI Pricing Inputs'!$D$114)^((AF$16-AE$16)/365) -> 0 | AG308: =AF308*(1+'2. GRI Pricing Inputs'!$D$114)^((AG$16-AF$16)/365) -> 0 | AH308: =AG308*(1+'2. GRI Pricing Inputs'!$D$114)^((AH$16-AG$16)/365) -> 0 | AI308: =AH308*(1+'2. GRI Pricing Inputs'!$D$114)^((AI$16-AH$16)/365) -> 0 | AJ308: =AI308*(1+'2. GRI Pricing Inputs'!$D$114)^((AJ$16-AI$16)/365) -> 0 | AK308: =AJ308*(1+'2. GRI Pricing Inputs'!$D$114)^((AK$16-AJ$16)/365) -> 0 | ... AO308: =AN308*(1+'2. GRI Pricing Inputs'!$D$114)^((AO$16-AN$16)/365) -> 0
C309: ='1. Accomodation'!N313 -> 0 | D309: ='1. Accomodation'!P313 -> 0 | E309: ='1. Accomodation'!Q313 -> 0 | F309: ='1. Accomodation'!O313 -> 0 | G309: ='1. Accomodation'!R313 -> 0 | H309: ='1. Accomodation'!S313 -> 0 | K309: =IFERROR(INDEX('2. GRI Pricing Inputs'!$C$15:$AI$16,MATCH($K$16,'2. GRI Pricing Inputs'!$C$15:$C$16,0),MATCH(D309,'2. GRI Pricing Inputs'!$C$15:$AI$15,0)),0) -> 0 | L309: =IFERROR(INDEX('2. GRI Pricing Inputs'!$C$22:$AI$23,MATCH($L$16,'2. GRI Pricing Inputs'!$C$22:$C$23,0),MATCH(E309,'2. GRI Pricing Inputs'!$C$22:$AI$22,0)),0) -> 0 | M309: =IF(AND('3. GRI Pricing'!$F309>='2. GRI Pricing Inputs'!$D$33,'3. GRI Pricing'!$F309<='2. GRI Pricing Inputs'!$E$33),'2. GRI Pricing Inputs'!$D$32,IF(AND('3. GRI Pricing'!$F309>='2. GRI Pricing Inputs'!$F$33,'3. GRI Pricing'!$F309<='2. GRI Pricing Inputs'!$G$33),'2. GRI Pricing Inputs'!$F$32,IF(AND('3. GRI Pricing'!$F309>='2. GRI Pricing Inputs'!$H$33,'3. GRI Pricing'!$F309<='2. GRI Pricing Inputs'!$I$33),'2. GRI Pricing Inputs'!$H$32,IF(AND('3. GRI Pricing'!$F309>='2. GRI Pricing Inputs'!$J$33,'3. GRI Pricing'!$F309<='2. GRI Pricing Inputs'!$K$33),'2. GRI Pricing Inputs'!$J$32,IF(AND('3. GRI Pricing'!$F309>='2. GRI Pricing Inputs'!$L$33,'3. GRI Pricing'!$F309<='2. GRI Pricing Inputs'!$M$33),'2. GRI Pricing Inputs'!$L$32,IF(AND('3. GRI Pricing'!$F309>='2. GRI Pricing Inputs'!$N$33,'3. GRI Pricing'!$F309<='2. GRI Pricing Inputs'!$O$33),'2. GRI Pricing Inputs'!$N$32,IF(AND('3. GRI Pricing'!$F309>='2. GRI Pricing Inputs'!$P$33,'3. GRI Pricing'!$F309<='2. GRI Pricing Inputs'!$Q$33),'2. GRI Pricing Inputs'!$P$32,IF(AND('3. GRI Pricing'!$F309>='2. GRI Pricing Inputs'!$R$33,'3. GRI Pricing'!$F309<='2. GRI Pricing Inputs'!$S$33),'2. GRI Pricing Inputs'!$R$32,IF(AND('3. GRI Pricing'!$F309>='2. GRI Pricing Inputs'!$T$33,'3. GRI Pricing'!$F309<='2. GRI Pricing Inputs'!$U$33),'2. GRI Pricing Inputs'!$T$32,IF(AND('3. GRI Pricing'!$F309>='2. GRI Pricing Inputs'!$V$33,'3. GRI Pricing'!$F309<='2. GRI Pricing Inputs'!$W$33),'2. GRI Pricing Inputs'!$V$32,IF(AND('3. GRI Pricing'!$F309>='2. GRI Pricing Inputs'!$X$33,'3. GRI Pricing'!$F309<='2. GRI Pricing Inputs'!$Y$33),'2. GRI Pricing Inputs'!$X$32,IF(AND('3. GRI Pricing'!$F309>='2. GRI Pricing Inputs'!$Z$33,'3. GRI Pricing'!$F309<='2. GRI Pricing Inputs'!$AA$33),'2. GRI Pricing Inputs'!$Z$32,IF(AND('3. GRI Pricing'!$F309>='2. GRI Pricing Inputs'!$AB$33,'3. GRI Pricing'!$F309<='2. GRI Pricing Inputs'!$AC$33),'2. GRI Pricing Inputs'!$AB$32,IF(AND('3. GRI Pricing'!$F309>='2. GRI Pricing Inputs'!$AD$33,'3. GRI Pricing'!$F309<='2. GRI Pricing Inputs'!$AE$33),'2. GRI Pricing Inputs'!$AD$32,IF(AND('3. GRI Pricing'!$F309>='2. GRI Pricing Inputs'!$AF$33,'3. GRI Pricing'!$F309<='2. GRI Pricing Inputs'!$AG$33),'2. GRI Pricing Inputs'!$AF$32,IF(AND('3. GRI Pricing'!$F309>='2. GRI Pricing Inputs'!$AH$33,'3. GRI Pricing'!$F309<='2. GRI Pricing Inputs'!$AI$33),'2. GRI Pricing Inputs'!$AH$32,0)))))))))))))))) -> 0 | N309: {=IFERROR(INDEX('2. GRI Pricing Inputs'!$C$32:$AI$39,MATCH('3. GRI Pricing'!D309,'2. GRI Pricing Inputs'!$C$32:$C$39,0),(MATCH('3. GRI Pricing'!M309,'2. GRI Pricing Inputs'!$D$32:$AI$32,0)+1)),0)} -> 0 | O309: =IFERROR(INDEX('2. GRI Pricing Inputs'!$C$45:$AI$46,MATCH($O$16,'2. GRI Pricing Inputs'!$C$45:$C$46,0),MATCH(G309,'2. GRI Pricing Inputs'!$C$45:$AI$45,0)),0) -> 0 | P309: =IFERROR(INDEX('2. GRI Pricing Inputs'!$C$53:$AI$54,MATCH('3. GRI Pricing'!$P$16,'2. GRI Pricing Inputs'!$C$53:$C$54,0),MATCH('3. GRI Pricing'!H309,'2. GRI Pricing Inputs'!$C$53:$AI$53,0)),0) -> 0 | Q309: =IFERROR(INDEX('2. GRI Pricing Inputs'!$C$60:$AI$61,MATCH('3. GRI Pricing'!$Q$16,'2. GRI Pricing Inputs'!$C$60:$C$61,0),MATCH('1. Accomodation'!T313,'2. GRI Pricing Inputs'!$C$60:$AI$60,0)),0) -> 0 | R309: =IFERROR(INDEX('2. GRI Pricing Inputs'!$C$67:$AI$68,MATCH('3. GRI Pricing'!$R$16,'2. GRI Pricing Inputs'!$C$67:$C$68,0),MATCH('1. Accomodation'!U313,'2. GRI Pricing Inputs'!$C$67:$AI$67,0)),0) -> 0 | S309: =IF(D309=0,0,'2. GRI Pricing Inputs'!$AI$75) -> 0 | T309: =IFERROR(INDEX('2. GRI Pricing Inputs'!$C$82:$AI$83,MATCH('3. GRI Pricing'!$T$16,'2. GRI Pricing Inputs'!$C$82:$C$83,0),MATCH('1. Accomodation'!V313,'2. GRI Pricing Inputs'!$C$82:$AI$82,0)),0) -> 0 | U309: =IFERROR(INDEX('2. GRI Pricing Inputs'!$C$89:$AI$90,MATCH('3. GRI Pricing'!$U$16,'2. GRI Pricing Inputs'!$C$89:$C$90,0),MATCH('1. Accomodation'!W313,'2. GRI Pricing Inputs'!$C$89:$AI$89,0)),0) -> 0 | V309: =IFERROR(INDEX('2. GRI Pricing Inputs'!$C$97:$AI$98,MATCH('3. GRI Pricing'!$V$16,'2. GRI Pricing Inputs'!$C$97:$C$98,0),MATCH('1. Accomodation'!X313,'2. GRI Pricing Inputs'!$C$97:$AI$97,0)),0) -> 0 | W309: =IFERROR(INDEX('2. GRI Pricing Inputs'!$C$104:$AI$105,MATCH('3. GRI Pricing'!$W$16,'2. GRI Pricing Inputs'!$C$104:$C$105,0),MATCH('1. Accomodation'!Y313,'2. GRI Pricing Inputs'!$C$104:$AI$104,0)),0) -> 0 | Y309: =K309+L309+N309+O309+P309+Q309+R309+S309+T309+U309+V309+W309+X309 -> 0 | AC309: =Y309*(1+'2. GRI Pricing Inputs'!$D$114)^(($AC$16-$AB$15)/365) -> 0 | AD309: =AC309*(1+'2. GRI Pricing Inputs'!$D$114)^((AD$16-AC$16)/365) -> 0 | AE309: =AD309*(1+'2. GRI Pricing Inputs'!$D$114)^((AE$16-AD$16)/365) -> 0 | AF309: =AE309*(1+'2. GRI Pricing Inputs'!$D$114)^((AF$16-AE$16)/365) -> 0 | AG309: =AF309*(1+'2. GRI Pricing Inputs'!$D$114)^((AG$16-AF$16)/365) -> 0 | AH309: =AG309*(1+'2. GRI Pricing Inputs'!$D$114)^((AH$16-AG$16)/365) -> 0 | AI309: =AH309*(1+'2. GRI Pricing Inputs'!$D$114)^((AI$16-AH$16)/365) -> 0 | AJ309: =AI309*(1+'2. GRI Pricing Inputs'!$D$114)^((AJ$16-AI$16)/365) -> 0 | AK309: =AJ309*(1+'2. GRI Pricing Inputs'!$D$114)^((AK$16-AJ$16)/365) -> 0 | ... AO309: =AN309*(1+'2. GRI Pricing Inputs'!$D$114)^((AO$16-AN$16)/365) -> 0
C310: ='1. Accomodation'!N314 -> 0 | D310: ='1. Accomodation'!P314 -> 0 | E310: ='1. Accomodation'!Q314 -> 0 | F310: ='1. Accomodation'!O314 -> 0 | G310: ='1. Accomodation'!R314 -> 0 | H310: ='1. Accomodation'!S314 -> 0 | K310: =IFERROR(INDEX('2. GRI Pricing Inputs'!$C$15:$AI$16,MATCH($K$16,'2. GRI Pricing Inputs'!$C$15:$C$16,0),MATCH(D310,'2. GRI Pricing Inputs'!$C$15:$AI$15,0)),0) -> 0 | L310: =IFERROR(INDEX('2. GRI Pricing Inputs'!$C$22:$AI$23,MATCH($L$16,'2. GRI Pricing Inputs'!$C$22:$C$23,0),MATCH(E310,'2. GRI Pricing Inputs'!$C$22:$AI$22,0)),0) -> 0 | M310: =IF(AND('3. GRI Pricing'!$F310>='2. GRI Pricing Inputs'!$D$33,'3. GRI Pricing'!$F310<='2. GRI Pricing Inputs'!$E$33),'2. GRI Pricing Inputs'!$D$32,IF(AND('3. GRI Pricing'!$F310>='2. GRI Pricing Inputs'!$F$33,'3. GRI Pricing'!$F310<='2. GRI Pricing Inputs'!$G$33),'2. GRI Pricing Inputs'!$F$32,IF(AND('3. GRI Pricing'!$F310>='2. GRI Pricing Inputs'!$H$33,'3. GRI Pricing'!$F310<='2. GRI Pricing Inputs'!$I$33),'2. GRI Pricing Inputs'!$H$32,IF(AND('3. GRI Pricing'!$F310>='2. GRI Pricing Inputs'!$J$33,'3. GRI Pricing'!$F310<='2. GRI Pricing Inputs'!$K$33),'2. GRI Pricing Inputs'!$J$32,IF(AND('3. GRI Pricing'!$F310>='2. GRI Pricing Inputs'!$L$33,'3. GRI Pricing'!$F310<='2. GRI Pricing Inputs'!$M$33),'2. GRI Pricing Inputs'!$L$32,IF(AND('3. GRI Pricing'!$F310>='2. GRI Pricing Inputs'!$N$33,'3. GRI Pricing'!$F310<='2. GRI Pricing Inputs'!$O$33),'2. GRI Pricing Inputs'!$N$32,IF(AND('3. GRI Pricing'!$F310>='2. GRI Pricing Inputs'!$P$33,'3. GRI Pricing'!$F310<='2. GRI Pricing Inputs'!$Q$33),'2. GRI Pricing Inputs'!$P$32,IF(AND('3. GRI Pricing'!$F310>='2. GRI Pricing Inputs'!$R$33,'3. GRI Pricing'!$F310<='2. GRI Pricing Inputs'!$S$33),'2. GRI Pricing Inputs'!$R$32,IF(AND('3. GRI Pricing'!$F310>='2. GRI Pricing Inputs'!$T$33,'3. GRI Pricing'!$F310<='2. GRI Pricing Inputs'!$U$33),'2. GRI Pricing Inputs'!$T$32,IF(AND('3. GRI Pricing'!$F310>='2. GRI Pricing Inputs'!$V$33,'3. GRI Pricing'!$F310<='2. GRI Pricing Inputs'!$W$33),'2. GRI Pricing Inputs'!$V$32,IF(AND('3. GRI Pricing'!$F310>='2. GRI Pricing Inputs'!$X$33,'3. GRI Pricing'!$F310<='2. GRI Pricing Inputs'!$Y$33),'2. GRI Pricing Inputs'!$X$32,IF(AND('3. GRI Pricing'!$F310>='2. GRI Pricing Inputs'!$Z$33,'3. GRI Pricing'!$F310<='2. GRI Pricing Inputs'!$AA$33),'2. GRI Pricing Inputs'!$Z$32,IF(AND('3. GRI Pricing'!$F310>='2. GRI Pricing Inputs'!$AB$33,'3. GRI Pricing'!$F310<='2. GRI Pricing Inputs'!$AC$33),'2. GRI Pricing Inputs'!$AB$32,IF(AND('3. GRI Pricing'!$F310>='2. GRI Pricing Inputs'!$AD$33,'3. GRI Pricing'!$F310<='2. GRI Pricing Inputs'!$AE$33),'2. GRI Pricing Inputs'!$AD$32,IF(AND('3. GRI Pricing'!$F310>='2. GRI Pricing Inputs'!$AF$33,'3. GRI Pricing'!$F310<='2. GRI Pricing Inputs'!$AG$33),'2. GRI Pricing Inputs'!$AF$32,IF(AND('3. GRI Pricing'!$F310>='2. GRI Pricing Inputs'!$AH$33,'3. GRI Pricing'!$F310<='2. GRI Pricing Inputs'!$AI$33),'2. GRI Pricing Inputs'!$AH$32,0)))))))))))))))) -> 0 | N310: {=IFERROR(INDEX('2. GRI Pricing Inputs'!$C$32:$AI$39,MATCH('3. GRI Pricing'!D310,'2. GRI Pricing Inputs'!$C$32:$C$39,0),(MATCH('3. GRI Pricing'!M310,'2. GRI Pricing Inputs'!$D$32:$AI$32,0)+1)),0)} -> 0 | O310: =IFERROR(INDEX('2. GRI Pricing Inputs'!$C$45:$AI$46,MATCH($O$16,'2. GRI Pricing Inputs'!$C$45:$C$46,0),MATCH(G310,'2. GRI Pricing Inputs'!$C$45:$AI$45,0)),0) -> 0 | P310: =IFERROR(INDEX('2. GRI Pricing Inputs'!$C$53:$AI$54,MATCH('3. GRI Pricing'!$P$16,'2. GRI Pricing Inputs'!$C$53:$C$54,0),MATCH('3. GRI Pricing'!H310,'2. GRI Pricing Inputs'!$C$53:$AI$53,0)),0) -> 0 | Q310: =IFERROR(INDEX('2. GRI Pricing Inputs'!$C$60:$AI$61,MATCH('3. GRI Pricing'!$Q$16,'2. GRI Pricing Inputs'!$C$60:$C$61,0),MATCH('1. Accomodation'!T314,'2. GRI Pricing Inputs'!$C$60:$AI$60,0)),0) -> 0 | R310: =IFERROR(INDEX('2. GRI Pricing Inputs'!$C$67:$AI$68,MATCH('3. GRI Pricing'!$R$16,'2. GRI Pricing Inputs'!$C$67:$C$68,0),MATCH('1. Accomodation'!U314,'2. GRI Pricing Inputs'!$C$67:$AI$67,0)),0) -> 0 | S310: =IF(D310=0,0,'2. GRI Pricing Inputs'!$AI$75) -> 0 | T310: =IFERROR(INDEX('2. GRI Pricing Inputs'!$C$82:$AI$83,MATCH('3. GRI Pricing'!$T$16,'2. GRI Pricing Inputs'!$C$82:$C$83,0),MATCH('1. Accomodation'!V314,'2. GRI Pricing Inputs'!$C$82:$AI$82,0)),0) -> 0 | U310: =IFERROR(INDEX('2. GRI Pricing Inputs'!$C$89:$AI$90,MATCH('3. GRI Pricing'!$U$16,'2. GRI Pricing Inputs'!$C$89:$C$90,0),MATCH('1. Accomodation'!W314,'2. GRI Pricing Inputs'!$C$89:$AI$89,0)),0) -> 0 | V310: =IFERROR(INDEX('2. GRI Pricing Inputs'!$C$97:$AI$98,MATCH('3. GRI Pricing'!$V$16,'2. GRI Pricing Inputs'!$C$97:$C$98,0),MATCH('1. Accomodation'!X314,'2. GRI Pricing Inputs'!$C$97:$AI$97,0)),0) -> 0 | W310: =IFERROR(INDEX('2. GRI Pricing Inputs'!$C$104:$AI$105,MATCH('3. GRI Pricing'!$W$16,'2. GRI Pricing Inputs'!$C$104:$C$105,0),MATCH('1. Accomodation'!Y314,'2. GRI Pricing Inputs'!$C$104:$AI$104,0)),0) -> 0 | Y310: =K310+L310+N310+O310+P310+Q310+R310+S310+T310+U310+V310+W310+X310 -> 0 | AC310: =Y310*(1+'2. GRI Pricing Inputs'!$D$114)^(($AC$16-$AB$15)/365) -> 0 | AD310: =AC310*(1+'2. GRI Pricing Inputs'!$D$114)^((AD$16-AC$16)/365) -> 0 | AE310: =AD310*(1+'2. GRI Pricing Inputs'!$D$114)^((AE$16-AD$16)/365) -> 0 | AF310: =AE310*(1+'2. GRI Pricing Inputs'!$D$114)^((AF$16-AE$16)/365) -> 0 | AG310: =AF310*(1+'2. GRI Pricing Inputs'!$D$114)^((AG$16-AF$16)/365) -> 0 | AH310: =AG310*(1+'2. GRI Pricing Inputs'!$D$114)^((AH$16-AG$16)/365) -> 0 | AI310: =AH310*(1+'2. GRI Pricing Inputs'!$D$114)^((AI$16-AH$16)/365) -> 0 | AJ310: =AI310*(1+'2. GRI Pricing Inputs'!$D$114)^((AJ$16-AI$16)/365) -> 0 | AK310: =AJ310*(1+'2. GRI Pricing Inputs'!$D$114)^((AK$16-AJ$16)/365) -> 0 | ... AO310: =AN310*(1+'2. GRI Pricing Inputs'!$D$114)^((AO$16-AN$16)/365) -> 0
C311: ='1. Accomodation'!N315 -> 0 | D311: ='1. Accomodation'!P315 -> 0 | E311: ='1. Accomodation'!Q315 -> 0 | F311: ='1. Accomodation'!O315 -> 0 | G311: ='1. Accomodation'!R315 -> 0 | H311: ='1. Accomodation'!S315 -> 0 | K311: =IFERROR(INDEX('2. GRI Pricing Inputs'!$C$15:$AI$16,MATCH($K$16,'2. GRI Pricing Inputs'!$C$15:$C$16,0),MATCH(D311,'2. GRI Pricing Inputs'!$C$15:$AI$15,0)),0) -> 0 | L311: =IFERROR(INDEX('2. GRI Pricing Inputs'!$C$22:$AI$23,MATCH($L$16,'2. GRI Pricing Inputs'!$C$22:$C$23,0),MATCH(E311,'2. GRI Pricing Inputs'!$C$22:$AI$22,0)),0) -> 0 | M311: =IF(AND('3. GRI Pricing'!$F311>='2. GRI Pricing Inputs'!$D$33,'3. GRI Pricing'!$F311<='2. GRI Pricing Inputs'!$E$33),'2. GRI Pricing Inputs'!$D$32,IF(AND('3. GRI Pricing'!$F311>='2. GRI Pricing Inputs'!$F$33,'3. GRI Pricing'!$F311<='2. GRI Pricing Inputs'!$G$33),'2. GRI Pricing Inputs'!$F$32,IF(AND('3. GRI Pricing'!$F311>='2. GRI Pricing Inputs'!$H$33,'3. GRI Pricing'!$F311<='2. GRI Pricing Inputs'!$I$33),'2. GRI Pricing Inputs'!$H$32,IF(AND('3. GRI Pricing'!$F311>='2. GRI Pricing Inputs'!$J$33,'3. GRI Pricing'!$F311<='2. GRI Pricing Inputs'!$K$33),'2. GRI Pricing Inputs'!$J$32,IF(AND('3. GRI Pricing'!$F311>='2. GRI Pricing Inputs'!$L$33,'3. GRI Pricing'!$F311<='2. GRI Pricing Inputs'!$M$33),'2. GRI Pricing Inputs'!$L$32,IF(AND('3. GRI Pricing'!$F311>='2. GRI Pricing Inputs'!$N$33,'3. GRI Pricing'!$F311<='2. GRI Pricing Inputs'!$O$33),'2. GRI Pricing Inputs'!$N$32,IF(AND('3. GRI Pricing'!$F311>='2. GRI Pricing Inputs'!$P$33,'3. GRI Pricing'!$F311<='2. GRI Pricing Inputs'!$Q$33),'2. GRI Pricing Inputs'!$P$32,IF(AND('3. GRI Pricing'!$F311>='2. GRI Pricing Inputs'!$R$33,'3. GRI Pricing'!$F311<='2. GRI Pricing Inputs'!$S$33),'2. GRI Pricing Inputs'!$R$32,IF(AND('3. GRI Pricing'!$F311>='2. GRI Pricing Inputs'!$T$33,'3. GRI Pricing'!$F311<='2. GRI Pricing Inputs'!$U$33),'2. GRI Pricing Inputs'!$T$32,IF(AND('3. GRI Pricing'!$F311>='2. GRI Pricing Inputs'!$V$33,'3. GRI Pricing'!$F311<='2. GRI Pricing Inputs'!$W$33),'2. GRI Pricing Inputs'!$V$32,IF(AND('3. GRI Pricing'!$F311>='2. GRI Pricing Inputs'!$X$33,'3. GRI Pricing'!$F311<='2. GRI Pricing Inputs'!$Y$33),'2. GRI Pricing Inputs'!$X$32,IF(AND('3. GRI Pricing'!$F311>='2. GRI Pricing Inputs'!$Z$33,'3. GRI Pricing'!$F311<='2. GRI Pricing Inputs'!$AA$33),'2. GRI Pricing Inputs'!$Z$32,IF(AND('3. GRI Pricing'!$F311>='2. GRI Pricing Inputs'!$AB$33,'3. GRI Pricing'!$F311<='2. GRI Pricing Inputs'!$AC$33),'2. GRI Pricing Inputs'!$AB$32,IF(AND('3. GRI Pricing'!$F311>='2. GRI Pricing Inputs'!$AD$33,'3. GRI Pricing'!$F311<='2. GRI Pricing Inputs'!$AE$33),'2. GRI Pricing Inputs'!$AD$32,IF(AND('3. GRI Pricing'!$F311>='2. GRI Pricing Inputs'!$AF$33,'3. GRI Pricing'!$F311<='2. GRI Pricing Inputs'!$AG$33),'2. GRI Pricing Inputs'!$AF$32,IF(AND('3. GRI Pricing'!$F311>='2. GRI Pricing Inputs'!$AH$33,'3. GRI Pricing'!$F311<='2. GRI Pricing Inputs'!$AI$33),'2. GRI Pricing Inputs'!$AH$32,0)))))))))))))))) -> 0 | N311: {=IFERROR(INDEX('2. GRI Pricing Inputs'!$C$32:$AI$39,MATCH('3. GRI Pricing'!D311,'2. GRI Pricing Inputs'!$C$32:$C$39,0),(MATCH('3. GRI Pricing'!M311,'2. GRI Pricing Inputs'!$D$32:$AI$32,0)+1)),0)} -> 0 | O311: =IFERROR(INDEX('2. GRI Pricing Inputs'!$C$45:$AI$46,MATCH($O$16,'2. GRI Pricing Inputs'!$C$45:$C$46,0),MATCH(G311,'2. GRI Pricing Inputs'!$C$45:$AI$45,0)),0) -> 0 | P311: =IFERROR(INDEX('2. GRI Pricing Inputs'!$C$53:$AI$54,MATCH('3. GRI Pricing'!$P$16,'2. GRI Pricing Inputs'!$C$53:$C$54,0),MATCH('3. GRI Pricing'!H311,'2. GRI Pricing Inputs'!$C$53:$AI$53,0)),0) -> 0 | Q311: =IFERROR(INDEX('2. GRI Pricing Inputs'!$C$60:$AI$61,MATCH('3. GRI Pricing'!$Q$16,'2. GRI Pricing Inputs'!$C$60:$C$61,0),MATCH('1. Accomodation'!T315,'2. GRI Pricing Inputs'!$C$60:$AI$60,0)),0) -> 0 | R311: =IFERROR(INDEX('2. GRI Pricing Inputs'!$C$67:$AI$68,MATCH('3. GRI Pricing'!$R$16,'2. GRI Pricing Inputs'!$C$67:$C$68,0),MATCH('1. Accomodation'!U315,'2. GRI Pricing Inputs'!$C$67:$AI$67,0)),0) -> 0 | S311: =IF(D311=0,0,'2. GRI Pricing Inputs'!$AI$75) -> 0 | T311: =IFERROR(INDEX('2. GRI Pricing Inputs'!$C$82:$AI$83,MATCH('3. GRI Pricing'!$T$16,'2. GRI Pricing Inputs'!$C$82:$C$83,0),MATCH('1. Accomodation'!V315,'2. GRI Pricing Inputs'!$C$82:$AI$82,0)),0) -> 0 | U311: =IFERROR(INDEX('2. GRI Pricing Inputs'!$C$89:$AI$90,MATCH('3. GRI Pricing'!$U$16,'2. GRI Pricing Inputs'!$C$89:$C$90,0),MATCH('1. Accomodation'!W315,'2. GRI Pricing Inputs'!$C$89:$AI$89,0)),0) -> 0 | V311: =IFERROR(INDEX('2. GRI Pricing Inputs'!$C$97:$AI$98,MATCH('3. GRI Pricing'!$V$16,'2. GRI Pricing Inputs'!$C$97:$C$98,0),MATCH('1. Accomodation'!X315,'2. GRI Pricing Inputs'!$C$97:$AI$97,0)),0) -> 0 | W311: =IFERROR(INDEX('2. GRI Pricing Inputs'!$C$104:$AI$105,MATCH('3. GRI Pricing'!$W$16,'2. GRI Pricing Inputs'!$C$104:$C$105,0),MATCH('1. Accomodation'!Y315,'2. GRI Pricing Inputs'!$C$104:$AI$104,0)),0) -> 0 | Y311: =K311+L311+N311+O311+P311+Q311+R311+S311+T311+U311+V311+W311+X311 -> 0 | AC311: =Y311*(1+'2. GRI Pricing Inputs'!$D$114)^(($AC$16-$AB$15)/365) -> 0 | AD311: =AC311*(1+'2. GRI Pricing Inputs'!$D$114)^((AD$16-AC$16)/365) -> 0 | AE311: =AD311*(1+'2. GRI Pricing Inputs'!$D$114)^((AE$16-AD$16)/365) -> 0 | AF311: =AE311*(1+'2. GRI Pricing Inputs'!$D$114)^((AF$16-AE$16)/365) -> 0 | AG311: =AF311*(1+'2. GRI Pricing Inputs'!$D$114)^((AG$16-AF$16)/365) -> 0 | AH311: =AG311*(1+'2. GRI Pricing Inputs'!$D$114)^((AH$16-AG$16)/365) -> 0 | AI311: =AH311*(1+'2. GRI Pricing Inputs'!$D$114)^((AI$16-AH$16)/365) -> 0 | AJ311: =AI311*(1+'2. GRI Pricing Inputs'!$D$114)^((AJ$16-AI$16)/365) -> 0 | AK311: =AJ311*(1+'2. GRI Pricing Inputs'!$D$114)^((AK$16-AJ$16)/365) -> 0 | ... AO311: =AN311*(1+'2. GRI Pricing Inputs'!$D$114)^((AO$16-AN$16)/365) -> 0
... C616: ='1. Accomodation'!N620 -> 0 | D616: ='1. Accomodation'!P620 -> 0 | E616: ='1. Accomodation'!Q620 -> 0 | F616: ='1. Accomodation'!O620 -> 0 | G616: ='1. Accomodation'!R620 -> 0 | H616: ='1. Accomodation'!S620 -> 0 | K616: =IFERROR(INDEX('2. GRI Pricing Inputs'!$C$15:$AI$16,MATCH($K$16,'2. GRI Pricing Inputs'!$C$15:$C$16,0),MATCH(D616,'2. GRI Pricing Inputs'!$C$15:$AI$15,0)),0) -> 0 | L616: =IFERROR(INDEX('2. GRI Pricing Inputs'!$C$22:$AI$23,MATCH($L$16,'2. GRI Pricing Inputs'!$C$22:$C$23,0),MATCH(E616,'2. GRI Pricing Inputs'!$C$22:$AI$22,0)),0) -> 0 | M616: =IF(AND('3. GRI Pricing'!$F616>='2. GRI Pricing Inputs'!$D$33,'3. GRI Pricing'!$F616<='2. GRI Pricing Inputs'!$E$33),'2. GRI Pricing Inputs'!$D$32,IF(AND('3. GRI Pricing'!$F616>='2. GRI Pricing Inputs'!$F$33,'3. GRI Pricing'!$F616<='2. GRI Pricing Inputs'!$G$33),'2. GRI Pricing Inputs'!$F$32,IF(AND('3. GRI Pricing'!$F616>='2. GRI Pricing Inputs'!$H$33,'3. GRI Pricing'!$F616<='2. GRI Pricing Inputs'!$I$33),'2. GRI Pricing Inputs'!$H$32,IF(AND('3. GRI Pricing'!$F616>='2. GRI Pricing Inputs'!$J$33,'3. GRI Pricing'!$F616<='2. GRI Pricing Inputs'!$K$33),'2. GRI Pricing Inputs'!$J$32,IF(AND('3. GRI Pricing'!$F616>='2. GRI Pricing Inputs'!$L$33,'3. GRI Pricing'!$F616<='2. GRI Pricing Inputs'!$M$33),'2. GRI Pricing Inputs'!$L$32,IF(AND('3. GRI Pricing'!$F616>='2. GRI Pricing Inputs'!$N$33,'3. GRI Pricing'!$F616<='2. GRI Pricing Inputs'!$O$33),'2. GRI Pricing Inputs'!$N$32,IF(AND('3. GRI Pricing'!$F616>='2. GRI Pricing Inputs'!$P$33,'3. GRI Pricing'!$F616<='2. GRI Pricing Inputs'!$Q$33),'2. GRI Pricing Inputs'!$P$32,IF(AND('3. GRI Pricing'!$F616>='2. GRI Pricing Inputs'!$R$33,'3. GRI Pricing'!$F616<='2. GRI Pricing Inputs'!$S$33),'2. GRI Pricing Inputs'!$R$32,IF(AND('3. GRI Pricing'!$F616>='2. GRI Pricing Inputs'!$T$33,'3. GRI Pricing'!$F616<='2. GRI Pricing Inputs'!$U$33),'2. GRI Pricing Inputs'!$T$32,IF(AND('3. GRI Pricing'!$F616>='2. GRI Pricing Inputs'!$V$33,'3. GRI Pricing'!$F616<='2. GRI Pricing Inputs'!$W$33),'2. GRI Pricing Inputs'!$V$32,IF(AND('3. GRI Pricing'!$F616>='2. GRI Pricing Inputs'!$X$33,'3. GRI Pricing'!$F616<='2. GRI Pricing Inputs'!$Y$33),'2. GRI Pricing Inputs'!$X$32,IF(AND('3. GRI Pricing'!$F616>='2. GRI Pricing Inputs'!$Z$33,'3. GRI Pricing'!$F616<='2. GRI Pricing Inputs'!$AA$33),'2. GRI Pricing Inputs'!$Z$32,IF(AND('3. GRI Pricing'!$F616>='2. GRI Pricing Inputs'!$AB$33,'3. GRI Pricing'!$F616<='2. GRI Pricing Inputs'!$AC$33),'2. GRI Pricing Inputs'!$AB$32,IF(AND('3. GRI Pricing'!$F616>='2. GRI Pricing Inputs'!$AD$33,'3. GRI Pricing'!$F616<='2. GRI Pricing Inputs'!$AE$33),'2. GRI Pricing Inputs'!$AD$32,IF(AND('3. GRI Pricing'!$F616>='2. GRI Pricing Inputs'!$AF$33,'3. GRI Pricing'!$F616<='2. GRI Pricing Inputs'!$AG$33),'2. GRI Pricing Inputs'!$AF$32,IF(AND('3. GRI Pricing'!$F616>='2. GRI Pricing Inputs'!$AH$33,'3. GRI Pricing'!$F616<='2. GRI Pricing Inputs'!$AI$33),'2. GRI Pricing Inputs'!$AH$32,0)))))))))))))))) -> 0 | N616: {=IFERROR(INDEX('2. GRI Pricing Inputs'!$C$32:$AI$39,MATCH('3. GRI Pricing'!D616,'2. GRI Pricing Inputs'!$C$32:$C$39,0),(MATCH('3. GRI Pricing'!M616,'2. GRI Pricing Inputs'!$D$32:$AI$32,0)+1)),0)} -> 0 | O616: =IFERROR(INDEX('2. GRI Pricing Inputs'!$C$45:$AI$46,MATCH($O$16,'2. GRI Pricing Inputs'!$C$45:$C$46,0),MATCH(G616,'2. GRI Pricing Inputs'!$C$45:$AI$45,0)),0) -> 0 | P616: =IFERROR(INDEX('2. GRI Pricing Inputs'!$C$53:$AI$54,MATCH('3. GRI Pricing'!$P$16,'2. GRI Pricing Inputs'!$C$53:$C$54,0),MATCH('3. GRI Pricing'!H616,'2. GRI Pricing Inputs'!$C$53:$AI$53,0)),0) -> 0 | Q616: =IFERROR(INDEX('2. GRI Pricing Inputs'!$C$60:$AI$61,MATCH('3. GRI Pricing'!$Q$16,'2. GRI Pricing Inputs'!$C$60:$C$61,0),MATCH('1. Accomodation'!T620,'2. GRI Pricing Inputs'!$C$60:$AI$60,0)),0) -> 0 | R616: =IFERROR(INDEX('2. GRI Pricing Inputs'!$C$67:$AI$68,MATCH('3. GRI Pricing'!$R$16,'2. GRI Pricing Inputs'!$C$67:$C$68,0),MATCH('1. Accomodation'!U620,'2. GRI Pricing Inputs'!$C$67:$AI$67,0)),0) -> 0 | S616: =IF(D616=0,0,'2. GRI Pricing Inputs'!$AI$75) -> 0 | T616: =IFERROR(INDEX('2. GRI Pricing Inputs'!$C$82:$AI$83,MATCH('3. GRI Pricing'!$T$16,'2. GRI Pricing Inputs'!$C$82:$C$83,0),MATCH('1. Accomodation'!V620,'2. GRI Pricing Inputs'!$C$82:$AI$82,0)),0) -> 0 | U616: =IFERROR(INDEX('2. GRI Pricing Inputs'!$C$89:$AI$90,MATCH('3. GRI Pricing'!$U$16,'2. GRI Pricing Inputs'!$C$89:$C$90,0),MATCH('1. Accomodation'!W620,'2. GRI Pricing Inputs'!$C$89:$AI$89,0)),0) -> 0 | V616: =IFERROR(INDEX('2. GRI Pricing Inputs'!$C$97:$AI$98,MATCH('3. GRI Pricing'!$V$16,'2. GRI Pricing Inputs'!$C$97:$C$98,0),MATCH('1. Accomodation'!X620,'2. GRI Pricing Inputs'!$C$97:$AI$97,0)),0) -> 0 | W616: =IFERROR(INDEX('2. GRI Pricing Inputs'!$C$104:$AI$105,MATCH('3. GRI Pricing'!$W$16,'2. GRI Pricing Inputs'!$C$104:$C$105,0),MATCH('1. Accomodation'!Y620,'2. GRI Pricing Inputs'!$C$104:$AI$104,0)),0) -> 0 | Y616: =K616+L616+N616+O616+P616+Q616+R616+S616+T616+U616+V616+W616+X616 -> 0 | AC616: =Y616*(1+'2. GRI Pricing Inputs'!$D$114)^(($AC$16-$AB$15)/365) -> 0 | AD616: =AC616*(1+'2. GRI Pricing Inputs'!$D$114)^((AD$16-AC$16)/365) -> 0 | AE616: =AD616*(1+'2. GRI Pricing Inputs'!$D$114)^((AE$16-AD$16)/365) -> 0 | AF616: =AE616*(1+'2. GRI Pricing Inputs'!$D$114)^((AF$16-AE$16)/365) -> 0 | AG616: =AF616*(1+'2. GRI Pricing Inputs'!$D$114)^((AG$16-AF$16)/365) -> 0 | AH616: =AG616*(1+'2. GRI Pricing Inputs'!$D$114)^((AH$16-AG$16)/365) -> 0 | AI616: =AH616*(1+'2. GRI Pricing Inputs'!$D$114)^((AI$16-AH$16)/365) -> 0 | AJ616: =AI616*(1+'2. GRI Pricing Inputs'!$D$114)^((AJ$16-AI$16)/365) -> 0 | AK616: =AJ616*(1+'2. GRI Pricing Inputs'!$D$114)^((AK$16-AJ$16)/365) -> 0 | ... AO616: =AN616*(1+'2. GRI Pricing Inputs'!$D$114)^((AO$16-AN$16)/365) -> 0
X617: Total ERV | Y617: =SUM(Y17:Y616)*12 -> 4244100 | AC617: =SUM(AC17:AC616)*12 -> 4258261 | AD617: =SUM(AD17:AD616)*12 -> 4272010.2 | AE617: =SUM(AE17:AE616)*12 -> 4286264.3 | AF617: =SUM(AF17:AF616)*12 -> 4300565.9 | AG617: =SUM(AG17:AG616)*12 -> 4313988.1 | AH617: =SUM(AH17:AH616)*12 -> 4328382.3 | AI617: =SUM(AI17:AI616)*12 -> 4342357.9 | AJ617: =SUM(AJ17:AJ616)*12 -> 4356846.7 | ... AO617: =SUM(AO17:AO616)*12 -> 4429067.3
C621: =COUNT(C17:C616) -> 317

Sheet 4. Valuation
C3: 4. ERV COMPARISON AGAINST VALUER
C5: Valuer | D5: CBRE
C6: Pricing Update Date | D6: 45199 | H6: PRS | I6: Car Parking | W6: PRS | X6: Car Parking
C7: Last Valuation Date | D7: 45199 | G7: =TEXT(D5,0)&" Growth Rate" -> CBRE Growth Rate | H7: 0.03 | I7: 0 | V7: Budget Growth Rate | W7: 0.03 | X7: 0
C8: Budget period: 12m up to | D8: 45199 | K8: Check dates as hardcoded | R8: Check dates as hardcoded | V8: Check dates as hardcoded | Z8: Check dates as hardcoded
G9: =TEXT($D$5,0)&" "&TEXT($D$7,"mmm-yy") -> CBRE Sep-23 | K9: =TEXT($D$5,0)&" Grown to "&TEXT(L24,"mmm-yy") -> CBRE Grown to Sep-23 | R9: =TEXT($D$8,0)&" BUDGET" -> 45199 BUDGET | V9: =TEXT($D$8,0)&" BUDGET Grown to "&""&TEXT($W$24, "mmm-yy") -> 45199 BUDGET Grown to Sep-22 | Z9: LAUNCH RENTS (MONTH, YEAR)
C10: ='3. GRI Pricing'!C5 -> Bedroom | D10: ='3. GRI Pricing'!D5 -> Door Number | E10: ='3. GRI Pricing'!E5 -> Av. Size (sqft) | G10: Monthly | H10: Annual | I10: £psf | K10: Monthly | L10: Annual | M10: £psf | O10: Unit Type | P10: Number of units | Q10: Av. Size (sqft) | R10: Monthly | S10: Annual | T10: £psf | V10: Monthly | W10: Annual | X10: £psf | Z10: Monthly | AA10: Annual | AB10: £psf | AE10: ="Extract of latest valuation from"&TEXT(D5,0)&":" -> Extract of latest valuation fromCBRE:
C11: ='1. Accomodation'!L9 -> 1 Bed | D11: ='1. Accomodation'!M9 -> 78 | E11: ='1. Accomodation'!N9 -> 503.5641 | G11: 867 | H11: =IFERROR(G11*12,"-") -> 10404 | I11: =IFERROR(H11/$E11,"-") -> 20.660726 | K11: =IFERROR(AVERAGEIF($D$26:$L$625,C11,$L$26:$L$625),0) -> 867 | L11: =IFERROR(K11*12,"-") -> 10404 | M11: =IFERROR(L11/$E11,"-") -> 20.660726 | O11: =C11 -> 1 Bed | P11: =D11 -> 78 | Q11: =E11 -> 503.5641 | S11: =IFERROR(R11*12,"-") -> 0 | T11: =IFERROR(S11/$E11,"-") -> 0 | V11: =IFERROR(AVERAGEIF(C26:$X$625,C11,V25:$V$625),0) -> 0 | W11: =IFERROR(V11*12,"-") -> 0 | X11: =IFERROR(W11/$E11,"-") -> 0 | Z11: =IFERROR(AVERAGEIF(D26:$AB$625,C11,$AA26:AA$625),0) -> 999.80769 | AA11: =IFERROR(Z11*12,"-") -> 11997.692 | AB11: =IFERROR(AA11/$E11,"-") -> 23.825551
C12: ='1. Accomodation'!L10 -> 2 Bed | D12: ='1. Accomodation'!M10 -> 179 | E12: ='1. Accomodation'!N10 -> 652.34637 | G12: 1166 | H12: =IFERROR(G12*12,"-") -> 13992 | I12: =IFERROR(H12/$E12,"-") -> 21.448728 | K12: =IFERROR(AVERAGEIF($D$26:$L$625,C12,$L$26:$L$625),0) -> 1166 | L12: =IFERROR(K12*12,"-") -> 13992 | M12: =IFERROR(L12/$E12,"-") -> 21.448728 | O12: =C12 -> 2 Bed | P12: =D12 -> 179 | Q12: =E12 -> 652.34637 | S12: =IFERROR(R12*12,"-") -> 0 | T12: =IFERROR(S12/$E12,"-") -> 0 | V12: =IFERROR(AVERAGEIF(C27:$X$625,C12,V26:$V$625),0) -> 0 | W12: =IFERROR(V12*12,"-") -> 0 | X12: =IFERROR(W12/$E12,"-") -> 0 | Z12: =IFERROR(AVERAGEIF(D27:$AB$625,C12,$AA27:AA$625),0) -> 1293.4358 | AA12: =IFERROR(Z12*12,"-") -> 15521.229 | AB12: =IFERROR(AA12/$E12,"-") -> 23.792926
C13: ='1. Accomodation'!L11 -> 3 Bed | D13: ='1. Accomodation'!M11 -> 26 | E13: ='1. Accomodation'!N11 -> 823.19231 | G13: 1511 | H13: =IFERROR(G13*12,"-") -> 18132 | I13: =IFERROR(H13/$E13,"-") -> 22.026445 | K13: =IFERROR(AVERAGEIF($D$26:$L$625,C13,$L$26:$L$625),0) -> 1511 | L13: =IFERROR(K13*12,"-") -> 18132 | M13: =IFERROR(L13/$E13,"-") -> 22.026445 | O13: =C13 -> 3 Bed | P13: =D13 -> 26 | Q13: =E13 -> 823.19231 | S13: =IFERROR(R13*12,"-") -> 0 | T13: =IFERROR(S13/$E13,"-") -> 0 | V13: =IFERROR(AVERAGEIF(C28:$X$625,C13,V27:$V$625),0) -> 0 | W13: =IFERROR(V13*12,"-") -> 0 | X13: =IFERROR(W13/$E13,"-") -> 0 | Z13: =IFERROR(AVERAGEIF(D28:$AB$625,C13,$AA28:AA$625),0) -> 1698.6538 | AA13: =IFERROR(Z13*12,"-") -> 20383.846 | AB13: =IFERROR(AA13/$E13,"-") -> 24.761949
C14: ='1. Accomodation'!L12 -> 0 | D14: ='1. Accomodation'!M12 -> 0 | E14: ='1. Accomodation'!N12 -> - | H14: =IFERROR(G14*12,"-") -> 0 | I14: =IFERROR(H14/$E14,"-") -> - | K14: =IFERROR(AVERAGEIF($D$26:$L$625,C14,$L$26:$L$625),0) -> 0 | L14: =IFERROR(K14*12,"-") -> 0 | M14: =IFERROR(L14/$E14,"-") -> - | O14: =C14 -> 0 | P14: =D14 -> 0 | Q14: =E14 -> - | S14: =IFERROR(R14*12,"-") -> 0 | T14: =IFERROR(S14/$E14,"-") -> - | V14: =IFERROR(AVERAGEIF(C29:$X$625,C14,V28:$V$625),0) -> 14.394322 | W14: =IFERROR(V14*12,"-") -> 172.73186 | X14: =IFERROR(W14/$E14,"-") -> - | Z14: =IFERROR(AVERAGEIF(D29:$AB$625,C14,$AA29:AA$625),0) -> 0 | AA14: =IFERROR(Z14*12,"-") -> 0 | AB14: =IFERROR(AA14/$E14,"-") -> -
C15: ='1. Accomodation'!L13 -> 0 | D15: ='1. Accomodation'!M13 -> 0 | E15: ='1. Accomodation'!N13 -> - | H15: =IFERROR(G15*12,"-") -> 0 | I15: =IFERROR(H15/$E15,"-") -> - | K15: =IFERROR(AVERAGEIF($D$26:$L$625,C15,$L$26:$L$625),0) -> 0 | L15: =IFERROR(K15*12,"-") -> 0 | M15: =IFERROR(L15/$E15,"-") -> - | O15: =C15 -> 0 | P15: =D15 -> 0 | Q15: =E15 -> - | S15: =IFERROR(R15*12,"-") -> 0 | T15: =IFERROR(S15/$E15,"-") -> - | V15: =IFERROR(AVERAGEIF(C30:$X$625,C15,V29:$V$625),0) -> 14.394322 | W15: =IFERROR(V15*12,"-") -> 172.73186 | X15: =IFERROR(W15/$E15,"-") -> - | Z15: =IFERROR(AVERAGEIF(D30:$AB$625,C15,$AA30:AA$625),0) -> 0 | AA15: =IFERROR(Z15*12,"-") -> 0 | AB15: =IFERROR(AA15/$E15,"-") -> -
C16: ='1. Accomodation'!L14 -> 0 | D16: ='1. Accomodation'!M14 -> 0 | E16: ='1. Accomodation'!N14 -> - | H16: =IFERROR(G16*12,"-") -> 0 | I16: =IFERROR(H16/$E16,"-") -> - | K16: =IFERROR(AVERAGEIF($D$26:$L$625,C16,$L$26:$L$625),0) -> 0 | L16: =IFERROR(K16*12,"-") -> 0 | M16: =IFERROR(L16/$E16,"-") -> - | O16: =C16 -> 0 | P16: =D16 -> 0 | Q16: =E16 -> - | S16: =IFERROR(R16*12,"-") -> 0 | T16: =IFERROR(S16/$E16,"-") -> - | V16: =IFERROR(AVERAGEIF(C31:$X$625,C16,V30:$V$625),0) -> 14.394322 | W16: =IFERROR(V16*12,"-") -> 172.73186 | X16: =IFERROR(W16/$E16,"-") -> - | Z16: =IFERROR(AVERAGEIF(D31:$AB$625,C16,$AA31:AA$625),0) -> 0 | AA16: =IFERROR(Z16*12,"-") -> 0 | AB16: =IFERROR(AA16/$E16,"-") -> -
C17: AVERAGE | D17: ='1. Accomodation'!M15 -> 283 | E17: ='1. Accomodation'!N15 -> 627.03534 | H17: =IFERROR(G17*12,"-") -> 0 | I17: =IFERROR(H17/E17,"-") -> 0 | K17: =L17/12 -> 1115.2862 | L17: =IFERROR(K627/D17,0) -> 13383.435 | M17: =IFERROR(L17/E17,"-") -> 21.343988 | O17: AVERAGE | P17: =D17 -> 283 | Q17: =E17 -> 627.03534 | S17: =IFERROR(R627/K17,0) -> 0 | T17: =IFERROR(S17/$E$17,"-") -> 0 | V17: =W17/12 -> 0 | W17: =IFERROR(V627/P17,0) -> 0 | X17: =IFERROR(W17/$E$17,"-") -> 0 | Z17: =AA17/12 -> 1249.735 | AA17: =IFERROR(Z627/D17,0) -> 14996.82 | AB17: =IFERROR(AA17/$E$17,"-") -> 23.917025
C18: ='1. Accomodation'!L16 -> Car Park | D18: ='1. Accomodation'!M16 -> 0 | H18: =G18*12 -> 0 | K18: =G18*(1+$H$7)^((L$24-K$24)/365) -> 0 | L18: =K18*12 -> 0 | O18: AVERAGE | P18: =D18 -> 0 | Q18: =E18 -> 0 | S18: =R18*12 -> 0 | V18: =R18*(1+'2. GRI Pricing Inputs'!$F$114)^((W$24-V$24)/365) -> 0 | W18: =V18*12 -> 0 | Z18: =V18*(1+'2. GRI Pricing Inputs'!$F$114)^((AA$24-Z$24)/365) -> 0 | AA18: =Z18*12 -> 0
C20: RENT GROWTH WORKINGS
G22: =G9 -> CBRE Sep-23 | K22: =K9 -> CBRE Grown to Sep-23 | R22: =R9 -> 45199 BUDGET | V22: =V9 -> 45199 BUDGET Grown to Sep-22 | Z22: =Z9 -> LAUNCH RENTS (MONTH, YEAR)
K23: Date From | L23: Date to: | M23: Growth (pa) | V23: Date From | W23: Date to: | X23: Growth (pa)
K24: =$D$7 -> 45199 | L24: =D6 -> 45199 | M24: =H7 -> 0.03 | V24: =D7 -> 45199 | W24: 44834 | X24: =$W$7 -> 0.03
C25: =D10 -> Door Number | D25: =C10 -> Bedroom | E25: =E10 -> Av. Size (sqft) | G25: Annual | H25: Monthly | I25: £psf | K25: Annual | L25: Monthly | M25: £psf | R25: Annual | S25: Monthly | T25: £psf | V25: Annual | W25: Monthly | X25: £psf | Z25: Annual | AA25: Monthly | AB25: £psf
C26: ='1. Accomodation'!N21 -> 101N | D26: ='1. Accomodation'!P21 -> 1 Bed | E26: ='1. Accomodation'!O21 -> 484 | G26: 11340 | H26: =IFERROR(INDEX('4. Valuation'!$C$10:$I$17,MATCH($D26,'4. Valuation'!$C$10:$C$17,0),MATCH($H$25,'4. Valuation'!$C$10:$I$10,0)),0) -> 867 | I26: =IFERROR(INDEX('4. Valuation'!$C$10:$I$17,MATCH($D26,'4. Valuation'!$C$10:$C$17,0),MATCH($I$25,'4. Valuation'!$C$10:$I$10,0)),0) -> 20.660726 | K26: =L26*12 -> 10404 | L26: =H26*(1+$M$24)^((L$24-K$24)/365) -> 867 | M26: =IFERROR(K26/E26,0) -> 21.495868 | R26: =IFERROR(INDEX('4. Valuation'!$O$10:$X$17,MATCH($D26,'4. Valuation'!$O$10:$O$17,0),MATCH($R$25,'4. Valuation'!$O$10:$X$10,0)),0) -> 0 | S26: =IFERROR(INDEX('4. Valuation'!$O$10:$X$17,MATCH($D26,'4. Valuation'!$O$10:$O$17,0),MATCH($S$25,'4. Valuation'!$O$10:$X$10,0)),0) -> 0 | T26: =IFERROR(INDEX('4. Valuation'!$O$10:$X$17,MATCH($D26,'4. Valuation'!$O$10:$O$17,0),MATCH($T$25,'4. Valuation'!$O$10:$X$10,0)),0) -> 0 | V26: =W26*12 -> 0 | W26: =S26*(1+$M$24)^((W$24-V$24)/365) -> 0 | X26: =IFERROR(V26/E26,0) -> 0 | Z26: =AA26*12 -> 11640 | AA26: ='3. GRI Pricing'!Y17 -> 970 | AB26: =IFERROR(Z26/E26,0) -> 24.049587
C27: ='1. Accomodation'!N22 -> 102N | D27: ='1. Accomodation'!P22 -> 2 Bed | E27: ='1. Accomodation'!O22 -> 678 | G27: 15900 | H27: =IFERROR(INDEX('4. Valuation'!$C$10:$I$17,MATCH($D27,'4. Valuation'!$C$10:$C$17,0),MATCH($H$25,'4. Valuation'!$C$10:$I$10,0)),0) -> 1166 | I27: =IFERROR(INDEX('4. Valuation'!$C$10:$I$17,MATCH($D27,'4. Valuation'!$C$10:$C$17,0),MATCH($I$25,'4. Valuation'!$C$10:$I$10,0)),0) -> 21.448728 | K27: =L27*12 -> 13992 | L27: =H27*(1+$M$24)^((L$24-K$24)/365) -> 1166 | M27: =IFERROR(K27/E27,0) -> 20.637168 | R27: =IFERROR(INDEX('4. Valuation'!$O$10:$X$17,MATCH($D27,'4. Valuation'!$O$10:$O$17,0),MATCH($R$25,'4. Valuation'!$O$10:$X$10,0)),0) -> 0 | S27: =IFERROR(INDEX('4. Valuation'!$O$10:$X$17,MATCH($D27,'4. Valuation'!$O$10:$O$17,0),MATCH($S$25,'4. Valuation'!$O$10:$X$10,0)),0) -> 0 | T27: =IFERROR(INDEX('4. Valuation'!$O$10:$X$17,MATCH($D27,'4. Valuation'!$O$10:$O$17,0),MATCH($T$25,'4. Valuation'!$O$10:$X$10,0)),0) -> 0 | V27: =W27*12 -> 0 | W27: =S27*(1+$M$24)^((W$24-V$24)/365) -> 0 | X27: =IFERROR(V27/E27,0) -> 0 | Z27: =AA27*12 -> 15180 | AA27: ='3. GRI Pricing'!Y18 -> 1265 | AB27: =IFERROR(Z27/E27,0) -> 22.389381
