Workbook

Sheet ROI Calcs
A1: ROI Calcs
B3: 800 | C3: Renewals per month | E3: Improving Tenant Retention
B4: =B3*12 -> 9600 | C4: Renewals p.a. | E4: 0.01 | F4: Goal: Improvement in retention rate | H4: Ave cost per refresh / refurb / clean
B5: 0.4 | C5: Current renewals lost | E5: =B5-E4 -> 0.39 | F5: Goal: Renewals lost | I5: Ave Cost | J5: % of Voids | K5: Annual # Voids
B6: =B4*B5 -> 3840 | C6: Voids p.a. | E6: =B4*E5 -> 3744 | F6: New total voids p.a. | H6: Refurb | I6: 18000 | J6: 0.02 | K6: =J6*$B$6 -> 76.8
B7: =B6/12 -> 320 | C7: Voids p.m. | E7: =B6-E6 -> 96 | F7: Fewer voids p.a. | H7: Refresh | I7: 3000 | J7: 0.66 | K7: =J7*$B$6 -> 2534.4
E8: =B13 -> 7 | F8: Days rent gained if tenant retained | H8: Clean | I8: 250 | J8: 0.32 | K8: =J8*$B$6 -> 1228.8
E9: =E7*B11*E8 -> 36960 | F9: Additional rental income p.a. from improved retention | H9: Average | I9: =(I6*J6)+(I7*J7)+(I8*J8) -> 2420 | J9: =SUM(J6:J8) -> 1 | K9: =SUM(K6:K8) -> 3840
B10: Improving Turnaround Times | E10: =I9 -> 2420 | F10: Ave cost per refresh / refurb / clean
B11: 55 | C11: Ave unit rent per day | E11: =E10*E7 -> 232320 | F11: Refresh costs saved p.a.
B12: =B11*30 -> 1650 | C12: Ave unit rent per month
B13: 7 | C13: Current average void turn around time (days) | E13: 20 | F13: Employee hours spent on: Move out + marketing + leasing + move in activities for 1 void
B14: 5 | C14: Goal: Target turnaround days | E14: 18 | F14: Average hourly salary
B15: 2 | C15: Reduction in void turnaround days | E15: =E14*40*4*12 -> 34560 | F15: Average annual salary
B16: =B6*B11*B15 -> 422400 | C16: Rent gained from faster void turnaround p.a. | E16: 0 | F16: Additional costs per void e.g. marketing a unit
E17: =E13*E7 -> 1920 | F17: Employee hours saved p.a.
E18: =E17*E14+E16*E7 -> 34560 | F18: Equivalent value p.a.
B19: Improving Speed & Efficiency | E19: =E17/(40*4*12) -> 1 | F19: # FTE'S
B20: 20 | C20: # Portfolio managers
B21: 0.3 | C21: Time spent on voids
B22: =B7/B20 -> 16 | C22: Per Ptf Mgr: Voids to be completed per month
B23: =4*40*B21 -> 48 | C23: Per Ptf Mgr: Hours spent on voids per month
B24: =B23/B22 -> 3 | C24: Hours per void | E24: Future Gains
B25: =B21*B20 -> 6 | C25: FTEs (full time equivalent) working on voids | E25: =B24*(1-B26) -> 2 | F25: Goal: hours per void
B26: 0.33333333 | C26: Goal = Reduction in human effort (hours) to complete a void | E26: =B23/E25 -> 24 | F26: # Voids Ptf Mgrs can now complete in the same time
E27: =(E26-B22)/B22 -> 0.5 | F27: Increase in # voids Ptf Mgrs are able to process
B28: Immediate Gains
B29: =B26*B25 -> 2 | C29: FTEs gained | E29: 1 | F29: Target Portfolio / Unit increase over next 3-4 years
B30: 2000 | C30: Monthly cost per temp | E30: =B7*(1+E29) -> 640 | F30: New # voids per month
B31: =B30*12 -> 24000 | C31: Annual cost per temp | E31: =E30*E25/(40*4) -> 8 | F31: FTEs required to process increased number of voids p.m.
B32: =B30*B29 -> 4000 | C32: Monthly temp cost savings | E32: =(E31-B25)/B25 -> 0.33333333 | F32: % increase in number of FTEs required
B33: 4 | C33: Months per year temps are hired

Sheet ROI Summary
A1: Summary
B3: Increased Annual Revenue
B4: ='ROI Calcs'!B16 -> 422400 | C4: Rent gained from faster void turnaround
B5: ='ROI Calcs'!E9 -> 36960 | C5: Additional rental income from improved retention
B6: =SUM(B4:B5) -> 459360 | C6: TOTAL
B8: Annual Cost Savings
B9: ='ROI Calcs'!E11 -> 232320 | C9: Refresh/ refurb / cleaning costs saved
B10: ='ROI Calcs'!B33*'ROI Calcs'!B32 -> 16000 | C10: Temp cost savings
B11: ='ROI Calcs'!E18 -> 34560 | C11: FTE savings from improved retention
B12: =SUM(B9:B11) -> 282880 | C12: TOTAL
B14: =B6+B12 -> 742240 | C14: OVERALL ANNUAL ESTIMATED BENEFIT
B16: Support for Grainger's Growth Plans
B17: ='ROI Calcs'!E32 -> 0.33333333 | C17: ="Headcount increase required for "&'ROI Calcs'!E29*100&"% "&'ROI Calcs'!F29 -> Headcount increase required for 100% Target Portfolio / Unit increase over next 3-4 years

Sheet Other Stats
