Workbook

Sheet Revision History
B2: Version | C2: Updated By | D2: Methods Affected by Change | E2: Revision Description
B3: V r1.0 | C3: - | E3: Initial release
B4: V r1.1 | C4: Lee Williams | D4: None - Documentation update | E4: Added Outcome status enum list and changed linkedApplicant ID description
B5: V r1.2 | C5: Lee Williams | D5: None - Documentation update | E5: Ameded Outcome Status enum and added applicant Status enum
B6: V r1.3 | C6: Lee Williams | D6: None - Documentation update | E6: Extended description of Cancel Tenancy
B7: V r1.4 | C7: Lee Williams | D7: None - Documentation update | E7: Extended descriptions and minor wording change
B8: V r1.5 | C8: Lee Williams | D8: None - Documentation update | E8: Updated response for addApplicant and updated description to cancellation reason enum
B9: V r1.5 | C9: Lee Williams | D9: None - Documentation update | E9: Updated ApplicantID description
B10: V r1.6 | C10: Lee Williams | D10: Error Response Normalisation | E10: Document QA review and error responses added
B11: V r1.7 | C11: Lee Williams | D11: 2 Iframe Calls added | E11: Create reference and add applicant for iframe added
B12: V r1.8 | C12: Lee Williams | D12: GetReferenceStatus | E12: Granular task status added to GetReferenceStatusCall, more detailed error keys added, Pending GetApplicantNotes call added
B13: V r1.9 | C13: Lee Williams | D13: None - Documentation update | E13: Additional report types added to enum list
B14: V r2.0 | C14: Lee Williams | D14: Added GetApplicantNotes call | E14: GetApplicantNotes Call added, PostApplicantReferenceNote responses updated

Sheet API Services
B3: API Method Name (Link to Request & Response Examples with Data Structure) | C3: Method Version | D3: Method Description | E3: Method URL
B4: Get Authentication Token | C4: 0.1 | D4: Method to acquire an authentication (bearer) token, using the scope (always "standardapiaccess"), along with the provided clientID and Client secret | E4: Swagger - /standardapi/v1/ Postman - https://preprod-auth-service.letalliance.dev/connect/token
B5: CheckConnection | C5: 0.1 | D5: Simple ping method used to check connectivity between Vision+ API server and client with no parameters. As with all methods, if authentication token is missing or invalid, an error will be returned. If the authentication token is valid and the connection is successful, a success true will be returned. | E5: /standardapi/v1/CheckConnection
B6: CreateReferenceWithAllData | C6: 0.1 | D6: As one of the base methods of the Vision+ API, this method is used to create a property, create tenancy on property and add one or more applicants to be referenced in that property, for systems that gather and provide all required applicant data up front. | E6: /standardapi/v1/CreateReferenceWithAllData
B7: CreateReferenceWithInputFromApplicant | C7: 0.1 | D7: As another base methods of the Vision+ API, this method is used to create a property, create tenancy on property and add one or more applicants to be referenced in that property, for systems that require the applicant to fill in their own data. On submission, an email will be sent to any Applicant in the application, with details on how to log on to the Vision+ Portal and complete the required referencing data. | E7: /standardapi/v1/CreateReferenceWithInputFromApplicant
B8: CreateReferenceWithApplicantIframe | C8: 0.1 | D8: As another base methods of the Vision+ API, this method is used to create a property, create tenancy on property and add one or more applicants to be referenced in that property, for systems that require the applicant to fill in their own data. On submission, an email will be sent to any Applicant in the application, with details on how to log on to the Vision+ Portal and complete the required referencing data. | E8: /standardapi/v1/CreateReferenceWithApplicantIframe
B9: GetApplicantReferenceStatus | C9: 0.1 | D9: This method is used to check the Applicant referencing status of one or more Applicants. | E9: /standardapi/v1/GetApplicantReferenceStatus/{ApplicantID}
B10: GetAgentActiveProducts | C10: 0.1 | D10: This method is used to get the list of products currently available to the agent to use in referencing applications. Using an invalid product code or a product the agent is not authorised for will cause the reference application request to fail and return an error. | E10: /standardapi/v1/GetAgentActiveProducts/{AgentCode}
B11: GetApplicantReferenceReports | C11: 0.1 | D11: This method provides the applicant available assessment reports as a base64 encoded string, which must be saved as PDF file. An interim report will be available if the appliants referencing application is in progress, and a final report will be avaible when the applicants reference application status is completed. | E11: /standardapi/v1/GetApplicantReferenceReports/{ApplicantID}
B12: PostApplicantReferenceDocument | C12: 0.1 | D12: This method is used to upload documents to support the applicant assessment process. Such as identification, proof of income, rent receipts etc. | E12: /standardapi/v1/PostApplicantReferenceDocument
B13: ResendApplicantReferenceLink | C13: 0.1 | D13: Used in conjunction with the references created with the CreateReferenceWithInputFromApplicant call, This method is used to resend the applicant referencing link to the applicant, to complete the required referencing data. This is not required for reference applications started with the CreateReferenceWithAllData call. | E13: ​/api​/workflow​/StandardIntegration​/ResendApplicantReferenceLink
B14: PostApplicantReferenceNote | C14: 0.1 | D14: This method is used to add notes to the applicant assessment. The note field supports free text and can be used to record additional data. | E14: ​/api​/workflow​/StandardIntegration​/PostApplicantReferenceNote
B15: AddApplicantToTenancy | C15: 0.1 | D15: This method is used to add an additional applicant to a tenancy application. It has a applicant type parameter that denotes whether the applicant will be sent a link to fill out the data themselves or that the data will be provided by the client system. | E15: ​/api​/workflow​/StandardIntegration​/AddApplicantToTenancy
... B23: GetApplicantNotes | C23: 0.1 | D23: Used to retrieve notes attached to applicant, by applicant ID | E23: ​/api​/workflow​/StandardIntegration​/GetApplicantNotes

Sheet Entity Relationship Model
A1: Entity Relationship Model

Sheet API Data Dictionary
H1: Methods Used
H2: CheckConnection | J2: CreateReferenceWithAllData | L2: CreateReferenceWithInputFromApplicant | N2: GetApplicantReferenceStatus | P2: GetAgentActiveProducts | R2: GetApplicantReferenceReports | T2: PostApplicantReferenceDocument | V2: ResendApplicantReferenceLink | X2: PostApplicantReferenceNote | Z2: AddApplicantToTenancy | AB2: AmendApplicantType | AD2: CancelApplicantFromTenancy | AF2: CancelTenancy | AH2: AmendTenancyDetails | AJ2: AmendApplicantProductType | AL2: CreateCompanyReferenceWithAllData | AN2: CreateCompanyReferenceWithInputFromApplicant
A3: ID | C3: Vision+ API Field Name | D3: Field Type | E3: API Max Field Length | F3: Field Validations | G3: Field Description | H3: Request | I3: Response | J3: Request | K3: Response | L3: Request | M3: Response | N3: Request | O3: Response | P3: Request | Q3: Response | R3: Request | S3: Response | T3: Request | U3: Response | V3: Request | W3: Response | X3: Request | Y3: Response | Z3: Request | AA3: Response | AB3: Request | AC3: Response | AD3: Request | AE3: Response | AF3: Request | AG3: Response | AH3: Request | AI3: Response | AJ3: Request | AK3: Response | AL3: Request | AM3: Response | AN3: Request | AO3: Response
A4: Agent and Tenancy Data
A5: 1 | B5: Agent and Tenancy Data | C5: tenancyID | D5: string | E5: 50 | G5: TenancyID is a unique key value for an Agent Property with Active referencing requests linked to one or more Applicants. An Agent Property may have one or more TenancyID's with simultaneous Applicant reference requests. TenancyID is created through API methods: CreateReferenceWithAllData CreateReferenceWithInputFromApplicant CreateCompanyReferenceWithAllData CreateCompanyReferenceWithInputFromApplicant | K5: X | M5: X | AM5: X
A6: 2 | C6: applicantID | D6: integer | G6: ApplicantID is a unique identifier for a person / Company to be referenced. ApplicantID is created through API Methods: CreateReferenceWithAllData CreateReferenceWithInputFromApplicant CreateCompanyReferenceWithAllData CreateCompanyReferenceWithInputFromApplicant AddApplicantToTenancy | K6: X | M6: X | N6: M | O6: X | R6: M | T6: M | V6: M | X6: M | AM6: X
A7: 3 | C7: agentCode | D7: string | E7: 50 | G7: AgentCode is the Unique Key provided to the Agent when onboarding as a Barbon Customer. An AgentID may be linked to many Properties being managed by that Agent and Each property may be linked to 1 or more TenancyID's. | J7: M | K7: X | L7: M | P7: M | Q7: X | AL7: M | AM7: X
A8: 4 | C8: Product | D8: string | E8: 200 | G8: Product is a return value for Product description for product(s) available and enabled for the API Authenticated Agent. This includes Referencing Products (Ultimate, Express etc..) and Other services such as Insurance products (Rent on Time, Rent Guarantee etc…) and Media and Utilities. | Q8: X | AL8: M
A9: 5 | C9: rentGuarantee | D9: enum - Rent Guarantee | F9: Valid Values 1-4 (See enum definition) | G9: Rent guarantee is an indicator that determines which RG option if any the agent requires | J9: M | L9: M | AL9: M
A10: 6 | C10: tenancyTermMonths | D10: integer | G10: The term of the Tenancy in months (whole months only) | J10: M | L10: M | AL10: M
A11: 7 | C11: monthlyRental | D11: number (double) | F11: number($double) pattern: ^\d*.\d{0,2}$ | G11: The monthly rental cost | J11: M | L11: M | AL11: M
A12: 8 | C12: lettingType | D12: enum - Letting Type | F12: Valid Values 1-3 (See enum definition) | G12: The type of the letting, i.e. rent only or fully managed | J12: M | L12: M | AL12: M
A13: 9 | C13: estimatedMoveInDate | D13: string ($date-time) | F13: DD/MM/YYYY | G13: Estimated date of tenancy start (move in) | J13: M | L13: M | AL13: M
A14: 10 | C14: propertyType | D14: enum - Property Type | F14: Valid Values 1-6 (See enum definition) | G14: The Type of property | J14: M | L14: M | AL14: X
A15: 11 | C15: propertyConstructionPeriod | D15: enum - Property Construction Period | F15: Valid Values 1-9 (See enum definition) | G15: The time period in which the property was built | J15: X | L15: X | AL15: X
A16: 12 | C16: numberOfBedrooms | D16: integer | G16: The count of bedrooms in the property | J16: X | L16: X | AL16: X
A17: 13 | C17: noOfAdultOccupants | D17: integer | G17: Number of Adult occupants (18 or over) | J17: X | L17: X | AL17: X
A18: 14 | C18: noOfChildOccupants | D18: integer | G18: Number of Child Occupants (under 18) | J18: X | L18: X | AL18: X
A19: 15 | B19: Tenancy Address | C19: houseNumber | D19: string | E19: 100 | G19: The number of the property, mandatory OR pair with House name field | J19: X | L19: X | AL19: X
A20: 16 | C20: houseName | D20: string | E20: 100 | G20: The name of the property, mandatory OR pair with House number field | J20: X | L20: X | AL20: M
A21: 17 | C21: addressLine1 | D21: string | E21: 100 | G21: The first line of the property address | J21: M | L21: M | AL21: M
A22: 18 | C22: addressLine2 | D22: string | E22: 100 | G22: The second line of the property address | J22: X | L22: X | AL22: X
A23: 19 | C23: town | D23: string | E23: 50 | G23: The town in which the property exists | J23: M | L23: M | AL23: M
A24: 20 | C24: postcode | D24: string | E24: 50 | G24: the postcode of the property | J24: M | L24: M | AL24: M
A25: 21 | C25: ukCountryCode | D25: enum - UK Country List | F25: Valid Values 1-4 (See enum definition) | G25: The UK country Code | J25: M | L25: M | AL25: M
A26: Applicant Data (Tenant / Guarantor)
A27: 22 | B27: Tenant Name and Contact Data | C27: ApplicantStatus | D27: enum - Applicant Status | G27: A return value for the tenant's status (using method GetApplicantReferenceStatus) | O27: X
A28: 23 | C28: OutcomeStatus | D28: enum - outcome | G28: A return value for the reference grading status (using method GetApplicantReferenceStatus) | O28: X
A29: 24 | C29: tenantTypeId | D29: enum - Tenant Type | F29: Valid Values 1-4 (See enum definition) | G29: The Type of the Tenant, e.g. lead or Guarantor | J29: M | L29: M | AL29: M
A30: 25 | C30: referenceType | D30: enum - Reference Type | F30: Valid Values 1-2 (See enum definition) | G30: The Type of reference, e.g Full or Express | J30: M | L30: M | AL30: M
A31: 26 | C31: rightToRent | D31: boolean | G31: Use Right to rent product for this reference | J31: M | L31: M | AL31: M
A32: 27 | C32: title | D32: enum - Title | F32: Valid Values 1-7 (See enum definition) | G32: The persons title, e.g. Mr, Mrs, etc. | J32: M | L32: M
A33: 28 | C33: otherTitle | D33: string | E33: 100 | G33: If other is chosen for title, this is a text field to enter the specific title | J33: X | L33: X
A34: 29 | C34: firstName | D34: string | E34: 100 | F34: pattern: ^[a-zA-Z0-9\-' ]*$ | G34: First name, validated against the RegEx pattern | J34: M | L34: M
A35: 30 | C35: middleName | D35: string | E35: 50 | F35: pattern: ^[a-zA-Z0-9\-' ]*$ | G35: Middle name, validated against the RegEx pattern | J35: X | L35: X
A36: 31 | C36: surname | D36: string | E36: 100 | F36: pattern: ^[a-zA-Z0-9\-' ]*$ | G36: Surname name, validated against the RegEx pattern | J36: M | L36: M
A37: 32 | C37: shareOfRent | D37: number (double) | F37: pattern: ^\d*.\d{0,2}$ | G37: GBP value of the applicants share of the rent | J37: M | L37: M | AL37: M
A38: 33 | C38: dateOfBirth | D38: string ($date-time) | F38: DD/MM/YYYY | G38: The date of birth, formatted DD-MM-YYYY | J38: M
A39: 34 | C39: companyName | D39: string | E39: 100 | G39: Name of the company | J39: X | AL39: M
A40: 35 | C40: companyRegistrationNumber | D40: string | E40: 100 | G40: Registration number of the company | J40: X | AL40: M
A41: 36 | C41: incorporationDate | D41: string ($date-time) | F41: DD/MM/YYYY | G41: Incorperation date of the company, formatted DD-MM-YYYY | J41: X | AL41: M
A42: 37 | C42: telephoneCountryID | D42: enum -Country/Location Code | F42: Valid Values 1-239 (See enum definition) | G42: The country/location code of the phone number | J42: M | L42: M | AL42: M
A43: 38 | C43: contactTelephoneNo | D43: string | E43: 15 | F43: pattern: ^(\d{11})$ | G43: The telephone number | J43: M | L43: M | AL43: M
A44: 39 | C44: emailAddress | D44: string ($email) | E44: 200 | F44: pattern: ^(?!.*\.\.)(?!.*\\_\\_)(?!.*\-\-)[a-zA-Z0-9][-a-zA-Z0-9._]+[a-zA-Z0-9]@([-a-zA-Z0-9]+.)+[a-zA-Z]{2,5}$ | G44: The email address | J44: M | L44: M | AL44: M
A45: 40 | C45: mobileCountryId | D45: enum -Country/Location Code | F45: Valid Values 1-239 (See enum definition) | G45: The country/location code of the mobile phone number | J45: M | AL45: M
A46: 41 | C46: mobileNumber | D46: string | E46: 15 | F46: pattern: ^(\d{11})$ | G46: The mobile phone number | J46: X | AL46: X
A47: 42 | C47: companyPositionId | D47: enum - Company Position | G47: The position / role at the company
A48: 43 | C48: position | D48: string | E48: 200 | G48: If Other is chosen for position, this is a text field to enter the specific position
A49: 44 | C49: isCompanyEmployee | D49: boolean | G49: Is a company employee
A50: 45 | C50: nationality | D50: enum - Nationality | F50: Valid Values 1-231 (See enum definition) | G50: The nationality, from the nationality enum list | J50: M
A51: 46 | C51: niNumber | D51: string | E51: 100 | F51: pattern: ^[a-zA-Z]{2}(?:\d){6}[a-zA-Z]{1}$ | G51: NI Number, matched to RegEx pattern | J51: X
A52: 47 | C52: residentStatus | D52: enum - resident Status | F52: Valid Values 1-2 (See enum definition) | G52: Denotes the resident status e.g. UK resident | J52: M
A53: 48 | C53: additionalInformation | D53: string | E53: 65535 | G53: Free text field for additional information | J53: X | AL53: X
A54: 49 | C54: isAdvanceRent | D54: boolean | G54: Denotes whether rent is paid in advance | J54: M
A55: 50 | B55: Alias Data | C55: firstName | D55: string | E55: 100 | F55: pattern: ^[a-zA-Z0-9\-' ]*$ | G55: First name, validated against the RegEx pattern | J55: X
A56: 51 | C56: middleName | D56: string | E56: 50 | F56: pattern: ^[a-zA-Z0-9\-' ]*$ | G56: Middle name, validated against the RegEx pattern | J56: X
A57: 52 | C57: lastName | D57: string | E57: 100 | F57: pattern: ^[a-zA-Z0-9\-' ]*$ | G57: Surname name, validated against the RegEx pattern | J57: X
A58: 53 | C58: nameChangeDate | D58: string ($date-time) | F58: DD/MM/YYYY | G58: Date the name was changed, formatted DD/MM/YYYY | J58: X
A59: 54 | B59: Tenant Address Data | C59: houseNumber | D59: string | E59: 100 | G59: The number of the property | J59: X
A60: 55 | C60: houseName | D60: string | E60: 100 | G60: The name of the property | J60: X
A61: 56 | C61: addressLine1 | D61: string | E61: 100 | G61: The first line of the property address | J61: M
A62: 57 | C62: addressLine2 | D62: string | E62: 100 | G62: The second line of the property address | J62: X
A63: 58 | C63: town | D63: string | E63: 100 | G63: The town in which the property exists | J63: M
A64: 59 | C64: postcode | D64: string | E64: 50 | G64: the postcode of the property | J64: M
A65: 60 | C65: country | D65: enum -Country/Location Code | F65: Valid Values 1-239 (See enum definition) | G65: The Country code from the enum list, e.g. France | J65: M
A66: 61 | C66: isUKAddress | D66: boolean | G66: Denotes if the address is in the UK | J66: M
A67: 62 | C67: addressTypeId | D67: enum - address Type | F67: Valid Values 1-2 (See enum definition) | G67: Whether the address is current or previous, chosen from enum list | J67: M
A68: 63 | C68: monthMovedIn | D68: enum - month | F68: Valid Values 1-12 (Jan - Dec) | G68: Month the property was moved into, chosen from enum list | J68: M
A69: 64 | C69: yearMovedIn | D69: integer | E69: 4 | F69: Valid Values 1900 - Current Year | G69: Year the property was moved into, formatted YYYY | J69: M
A70: 65 | B70: Tenant Residential Data | C70: currentResidentialStatus | D70: enum - residentStatus | F70: Valid Values 1-3 (See enum definition) | G70: The current residential status, e.g. UK Resident | J70: M
A71: 66 | C71: currentRentAmount | D71: number (double) | F71: pattern: ^\d*.\d{0,2}$ | G71: The current rent amount in GBP | J71: X
A72: 67 | C72: landlordName | D72: string | E72: 500 | G72: Full name of the Landlord | J72: X
A73: 68 | C73: landlordContactCountryId | D73: enum -Country/Location Code | F73: Valid Values 1-239 (See enum definition) | G73: The country/location code of the landlord contact phone number | J73: M
A74: 69 | C74: landlordContactNumber | D74: string | E74: 15 | F74: pattern: ^(\d{11})$ | G74: The Landlords contact Telephone number | J74: X
A75: 70 | C75: landlordMobileCountryId | D75: enum -Country/Location Code | F75: Valid Values 1-239 (See enum definition) | G75: The country/location code of the landlord mobile phone number | J75: M
A76: 71 | C76: landlordMobileNumber | D76: string | E76: 15 | F76: pattern: ^(\d{11})$ | G76: the landlords mobile Telephone number | J76: X
A77: 72 | C77: landlordEmail | D77: string ($email) | E77: 200 | F77: pattern: ^(?!.*\.\.)(?!.*\\_\\_)(?!.*\-\-)[a-zA-Z0-9][-a-zA-Z0-9._]+[a-zA-Z0-9]@([-a-zA-Z0-9]+.)+[a-zA-Z]{2,5}$ | G77: The landlords email address | J77: X
A78: 73 | C78: House Number | D78: string | E78: 100 | G78: The number of the property | J78: X
A79: 74 | C79: House Name | D79: string | E79: 100 | G79: The name of the property | J79: X
A80: 75 | C80: addressLine1 | D80: string | E80: 100 | G80: The first line of the property address | J80: X
A81: 76 | C81: addressLine2 | D81: string | E81: 100 | G81: The second line of the property address | J81: X
A82: 77 | C82: town | D82: string | E82: 50 | G82: The town in which the property exists | J82: X
A83: 78 | C83: country | D83: enum -Country/Location Code | F83: Valid Values 1-239 (See enum definition) | G83: The Country code from the enum list, e.g. France | J83: M
A84: 79 | C84: postcode | D84: string | E84: 50 | G84: the postcode of the property | J84: X
A85: 80 | B85: Adverse Data | C85: submittedisAdverseCredit | D85: boolean | G85: Boolean for is adverse credit | J85: M
A86: 81 | C86: submittedisCCJ | D86: boolean | G86: Boolean for is County court judgment | J86: M
A87: 82 | C87: submittedisBankruptcy | D87: boolean | G87: Boolean for is bankruptcy | J87: M
A88: 83 | C88: SubmittedisInsolvency | D88: boolean | G88: Boolean for is Insolvency | J88: M
A89: 84 | C89: submittedisOtherAdverseCredit | D89: boolean | G89: Boolean for is other Adverse credit | J89: M
A90: 85 | C90: submittedOtherAdverseCreditDesc | D90: string | E90: 1000 | G90: If submittedisOtherAdverseCredit is True, the free text field for adverse credit | J90: M
A91: Applicant Income Data (Tenant / Guarantor)
A92: 86 | B92: Income Type | C92: incomeTypeID | D92: enum - Income Type | F92: Valid Values 1,2,3,5,6,7,8 (See enum definition) | G92: The Income Type, e.g savings or employed | J92: M
A93: 87 | C93: incomeTermID | D93: enum - Income Term | F93: Valid Values 1-4 (See enum definition) | G93: Income term, e.g monthly or weekly | J93: M
A94: 88 | B94: Employed | C94: countryOfEmployment | D94: enum -Country/Location Code | F94: Valid Values 1-239 (See enum definition) | G94: The Country of employment, from the enum list, e.g. France | J94: X
A95: 89 | C95: employersName | D95: string | E95: 100 | F95: pattern: ^[a-zA-Z0-9\-' ]*$ | G95: Name of the company the person is employed by | J95: X
A96: 90 | C96: jobTitle | D96: string | E96: 100 | F96: pattern: ^[A-Za-z ']+$ | G96: Job title at the company the person is employed by | J96: X
A97: 91 | C97: startDateofEmployment | D97: string ($date-time) | F97: DD/MM/YYYY | G97: Start date of employment, formatted DD/MM/YYYY | J97: X
A98: 92 | C98: employmentGrossAnnualIncome | D98: number (double) | F98: pattern: ^\d*.\d{0,2}$ | G98: Gross annual income in GBP | J98: X
A99: 93 | C99: employmentBonuses | D99: boolean | G99: Denotes if bonuses are recieved from the company the person is employed by | J99: X
A100: 94 | C100: employmentOvertimeReceived | D100: boolean | G100: Denotes if overtime is recieved from the company the person is employed by | J100: X
...

Sheet Enum Short Lists
B3: Enum Field | C3: RentGuarantee
B4: Description | C4: Rent guarantee is a product option in Vision+ that provides a guaranteed payment of rent. The options for the rent guarantee are in the table
B5: Value ID | C5: Value Name | D5: Value Description
B6: 1 | C6: Yes, Annual
B7: 2 | C7: Yes, Monthly
B8: 3 | C8: Tenant Evict Only
B9: 4 | C9: No
B12: Enum Field | C12: Title
B13: Description | C13: This is the name prefix for the tenant. If Other is chosen, a free text field is required to be filled in
B14: Value ID | C14: Value Name | D14: Value Description
B15: 1 | C15: Mr
B16: 2 | C16: Mrs
B17: 3 | C17: Miss
B18: 4 | C18: Dr
B19: 5 | C19: Ms
B20: 6 | C20: Other | D20: Free text field become mandatory
B21: 7 | C21: Mx
B24: Enum Field | C24: PropertyConstructionPeriod
B25: Description | C25: This is a range of years denoting the period in which the property was built
B26: Value ID | C26: Value Name | D26: Value Description
B27: 1 | C27: Pre 1850
B28: 2 | C28: 1850 – 1899
B29: 3 | C29: 1900 – 1919
B30: 4 | C30: 1920 – 1945
B31: 5 | C31: 1946 – 1979
B32: 6 | C32: 1980 – 1990
B33: 7 | C33: 1991 – 2000
B34: 8 | C34: 2001 – 2010
B35: 9 | C35: 2011 +
B38: Enum Field | C38: Name Type
B39: Description | C39: Other name that the tenant has been known by
B40: Value ID | C40: Value Name | D40: Value Description
B41: 1 | C41: Other Name
B42: 2 | C42: Another Name
B45: Enum Field | C45: monthMovedIn
B46: Description | C46: The standard month options
B47: Value ID | C47: Value Name | D47: Value Description
B48: 1 | C48: January
B49: 2 | C49: February
B50: 3 | C50: March
B51: 4 | C51: April
B52: 5 | C52: May
B53: 6 | C53: June
B54: 7 | C54: July
B55: 8 | C55: August
B56: 9 | C56: September
B57: 10 | C57: October
B58: 11 | C58: November
B59: 12 | C59: December
B62: Enum Field | C62: TermType
B63: Description | C63: Term type details the period length of term for multiple uses such as dividend term. Fields mapped to this enum list include: employmentBonusTerm employmentOvertimeTerm, taxCreditTerm, carerAllowanceTerm childBenefitTerm disabilityBenefitTerm fosterAllowanceTerm guardianAllowanceTerm childMaintenanceTerm housingBenefitTerm universalCreditTerm
B64: Value ID | C64: Value Name | D64: Value Description
B65: 1 | C65: Daily
B66: 2 | C66: Weekly
B67: 3 | C67: Two Weekly
B68: 4 | C68: Four Weekly
B69: 5 | C69: Monthly
B70: 6 | C70: Quarterly
B71: 7 | C71: Annually
B74: Enum Field | C74: incomeTermID
B75: Description | C75: Payment schedule details the period length of term for payment schedule
B76: Value ID | C76: Value Name | D76: Value Description
B77: 1 | C77: Monthly
B78: 2 | C78: Weekly
B79: 3 | C79: Quarterly
B80: 4 | C80: Yearly
B83: Enum Field | C83: lettingType
B84: Description | C84: The type of property let
B85: Value ID | C85: Value Name | D85: Value Description
B86: 1 | C86: Let Only
B87: 2 | C87: Fully Managed
B88: 3 | C88: Rent Collect
B91: Enum Field | C91: tenantTypeId
B92: Description | C92: The type of tenant
B93: Value ID | C93: Value Name | D93: Value Description
B94: 1 | C94: LeadTenant
B95: 2 | C95: Tenant
B96: 3 | C96: Guarantor
B97: 4 | C97: Tenant - Company
B100: Enum Field | C100: employmentTypeId
B101: Description | C101: The type of employment the tenant has
B102: Value ID | C102: Value Name | D102: Value Description
B103: 1 | C103: Permanent-Full Time
B104: 2 | C104: Permanent-Part Time
B105: 3 | C105: Temporary-Full Time
B106: 4 | C106: Temporary -Part Time
B109: Enum Field | C109: tradingTypeId
B110: Description | C110: The trading type of the tenants company
B111: Value ID | C111: Value Name | D111: Value Description
B112: 1 | C112: Sole Trader/Partner
B113: 2 | C113: Limited Company
B114: 3 | C114: N/A | D114: Not valid outside internal testing
B115: 4 | C115: N/A | D115: Not valid outside internal testing
B118: Enum Field | C118: referenceType
B119: Description | C119: The type of tenant reference available to the agent.
B120: Value ID | C120: Value Name | D120: Value Description
B121: 1 | C121: Full Reference
B122: 2 | C122: Express Reference
B123: 3 | C123: Nonreference | D123: Not valid outside internal testing
B126: Enum Field | C126: residentStatus
...

Sheet Enum Countries
B2: Enum Field | C2: Country/Location Code
B3: Description | C3: The country or location - NB. includes legacy options Fields mapped to this enum list include: telephoneCountryID mobileCountryId country landlordContactCountryId landlordMobileCountryId countryOfEmployment employmentRefereeContactCountryID employmentRefereeMobileCountryID accountantContactNoCountryId accountantMobileNoCountryId
B4: Value ID | C4: Value Name | D4: Value Description
B5: 1 | C5: Cyprus
B6: 2 | C6: United Kingdom
B7: 3 | C7: India
B8: 4 | C8: USA
B9: 5 | C9: Andorra
B10: 6 | C10: United Arab Emirates
B11: 7 | C11: Afghanistan
B12: 8 | C12: Antigua and Barbuda
B13: 9 | C13: Anguilla
B14: 10 | C14: Albania
B15: 11 | C15: Armenia
B16: 12 | C16: Netherlands Antilles
... B239: 240 | C239: Serbia

Sheet Enum Nationalities
B2: Enum Field | C2: nationality
B3: Description | C3: The country or location - NB includes legacy options
B4: Value ID | C4: Value Name | D4: Value Description
B5: 1 | C5: Afghan
B6: 2 | C6: Albanian
B7: 3 | C7: Algerian
B8: 4 | C8: American
B9: 5 | C9: Andorran
B10: 6 | C10: Angolan
B11: 7 | C11: Anguillan
B12: 8 | C12: Citizen of Antigua and Barbuda
B13: 9 | C13: Argentine
B14: 10 | C14: Armenian
B15: 11 | C15: Australian
B16: 12 | C16: Austrian
... B235: 231 | C235: Zairian

Sheet CheckConnection
A1: GetApplicantReferenceStatus Example JSON | B1: Vision+ API Field Name | C1: Mandatory Field | D1: Field Type | E1: API Max Field Length | F1: Field Validations | G1: Field Description
A2: Request Example
A3: { | B3: =IF(OR(ISNUMBER(SEARCH("{", A3)),ISNUMBER(SEARCH("[", A3))), "", IFERROR(MID(A3, SEARCH("""", A3) +1, SEARCH("""", A3, SEARCH("""",A3) +1) - SEARCH("""", A3) -1), "")) | C3: =IF(B3="", "", VLOOKUP(B3,'API Data Dictionary'!C:N,12,FALSE)) | D3: =IF(B3="", "", VLOOKUP(B3,'API Data Dictionary'!C:D,2,FALSE)) | E3: =IF(IF(B3="", "", VLOOKUP(B3,'API Data Dictionary'!C:E,3,FALSE))=0, "", IF(B3="", "", VLOOKUP(B3,'API Data Dictionary'!C:E,3,FALSE))) | F3: =IF(IF(B3="", "", VLOOKUP(B3,'API Data Dictionary'!C:F,4,FALSE))=0, "", IF(B3="", "", VLOOKUP(B3,'API Data Dictionary'!C:F,4,FALSE))) | G3: =IF(IF(B3="", "", VLOOKUP(B3,'API Data Dictionary'!C:G,5,FALSE))=0, "", IF(B3="", "", VLOOKUP(B3,'API Data Dictionary'!C:G,5,FALSE)))
A4: N/A - No parameters | B4: N/A | C4: N/A | D4: N/A | E4: N/A | F4: N/A | G4: N/A
A5: } | B5: =IF(OR(ISNUMBER(SEARCH("{", A5)),ISNUMBER(SEARCH("[", A5))), "", IFERROR(MID(A5, SEARCH("""", A5) +1, SEARCH("""", A5, SEARCH("""",A5) +1) - SEARCH("""", A5) -1), "")) | C5: =IF(B5="", "", VLOOKUP(B5,'API Data Dictionary'!C:N,12,FALSE)) | D5: =IF(B5="", "", VLOOKUP(B5,'API Data Dictionary'!C:D,2,FALSE)) | E5: =IF(IF(B5="", "", VLOOKUP(B5,'API Data Dictionary'!C:E,3,FALSE))=0, "", IF(B5="", "", VLOOKUP(B5,'API Data Dictionary'!C:E,3,FALSE))) | F5: =IF(IF(B5="", "", VLOOKUP(B5,'API Data Dictionary'!C:F,4,FALSE))=0, "", IF(B5="", "", VLOOKUP(B5,'API Data Dictionary'!C:F,4,FALSE))) | G5: =IF(IF(B5="", "", VLOOKUP(B5,'API Data Dictionary'!C:G,5,FALSE))=0, "", IF(B5="", "", VLOOKUP(B5,'API Data Dictionary'!C:G,5,FALSE)))
A7: Response Example: Success
A8: { | B8: =IF(OR(ISNUMBER(SEARCH("{", A8)),ISNUMBER(SEARCH("[", A8))), "", IFERROR(MID(A8, SEARCH("""", A8) +1, SEARCH("""", A8, SEARCH("""",A8) +1) - SEARCH("""", A8) -1), "")) | C8: =IF(B8="", "", VLOOKUP(B8,'API Data Dictionary'!C:N,12,FALSE)) | D8: =IF(B8="", "", VLOOKUP(B8,'API Data Dictionary'!C:D,2,FALSE)) | E8: =IF(IF(B8="", "", VLOOKUP(B8,'API Data Dictionary'!C:E,3,FALSE))=0, "", IF(B8="", "", VLOOKUP(B8,'API Data Dictionary'!C:E,3,FALSE))) | F8: =IF(IF(B8="", "", VLOOKUP(B8,'API Data Dictionary'!C:F,4,FALSE))=0, "", IF(B8="", "", VLOOKUP(B8,'API Data Dictionary'!C:F,4,FALSE))) | G8: =IF(IF(B8="", "", VLOOKUP(B8,'API Data Dictionary'!C:G,5,FALSE))=0, "", IF(B8="", "", VLOOKUP(B8,'API Data Dictionary'!C:G,5,FALSE)))
A9: "success": true, | B9: =IF(OR(ISNUMBER(SEARCH("{", A9)),ISNUMBER(SEARCH("[", A9))), "", IFERROR(MID(A9, SEARCH("""", A9) +1, SEARCH("""", A9, SEARCH("""",A9) +1) - SEARCH("""", A9) -1), "")) -> success | C9: M | D9: =IF(B9="", "", VLOOKUP(B9,'API Data Dictionary'!C:D,2,FALSE)) -> string - Boolean | E9: =IF(IF(B9="", "", VLOOKUP(B9,'API Data Dictionary'!C:E,3,FALSE))=0, "", IF(B9="", "", VLOOKUP(B9,'API Data Dictionary'!C:E,3,FALSE))) -> 100 | F9: =IF(IF(B9="", "", VLOOKUP(B9,'API Data Dictionary'!C:F,4,FALSE))=0, "", IF(B9="", "", VLOOKUP(B9,'API Data Dictionary'!C:F,4,FALSE))) | G9: =IF(IF(B9="", "", VLOOKUP(B9,'API Data Dictionary'!C:G,5,FALSE))=0, "", IF(B9="", "", VLOOKUP(B9,'API Data Dictionary'!C:G,5,FALSE))) -> Returns true when successful call/connection
A10: "payload": "Healthy", | B10: =IF(OR(ISNUMBER(SEARCH("{", A10)),ISNUMBER(SEARCH("[", A10))), "", IFERROR(MID(A10, SEARCH("""", A10) +1, SEARCH("""", A10, SEARCH("""",A10) +1) - SEARCH("""", A10) -1), "")) -> payload | C10: M | D10: =IF(B10="", "", VLOOKUP(B10,'API Data Dictionary'!C:D,2,FALSE)) -> string | E10: =IF(IF(B10="", "", VLOOKUP(B10,'API Data Dictionary'!C:E,3,FALSE))=0, "", IF(B10="", "", VLOOKUP(B10,'API Data Dictionary'!C:E,3,FALSE))) -> 100 | F10: =IF(IF(B10="", "", VLOOKUP(B10,'API Data Dictionary'!C:F,4,FALSE))=0, "", IF(B10="", "", VLOOKUP(B10,'API Data Dictionary'!C:F,4,FALSE))) | G10: =IF(IF(B10="", "", VLOOKUP(B10,'API Data Dictionary'!C:G,5,FALSE))=0, "", IF(B10="", "", VLOOKUP(B10,'API Data Dictionary'!C:G,5,FALSE))) -> Returns healthy when connection has worked properly
A11: "message": null | B11: =IF(OR(ISNUMBER(SEARCH("{", A11)),ISNUMBER(SEARCH("[", A11))), "", IFERROR(MID(A11, SEARCH("""", A11) +1, SEARCH("""", A11, SEARCH("""",A11) +1) - SEARCH("""", A11) -1), "")) -> message | C11: M | D11: =IF(B11="", "", VLOOKUP(B11,'API Data Dictionary'!C:D,2,FALSE)) -> string | E11: =IF(IF(B11="", "", VLOOKUP(B11,'API Data Dictionary'!C:E,3,FALSE))=0, "", IF(B11="", "", VLOOKUP(B11,'API Data Dictionary'!C:E,3,FALSE))) -> 100 | F11: =IF(IF(B11="", "", VLOOKUP(B11,'API Data Dictionary'!C:F,4,FALSE))=0, "", IF(B11="", "", VLOOKUP(B11,'API Data Dictionary'!C:F,4,FALSE))) | G11: =IF(IF(B11="", "", VLOOKUP(B11,'API Data Dictionary'!C:G,5,FALSE))=0, "", IF(B11="", "", VLOOKUP(B11,'API Data Dictionary'!C:G,5,FALSE))) -> return value, null or success, unless there has been error
A12: }
A14: Response Example: Fail - 401 Unauthorised Error
A15: 401 Error: Unauthorized | B15: N/A | C15: N/A | D15: string | E15: 100 | G15: Returns a 401 error if not authorised
A17: Response Example: Fail - 403 Forbidden
A18: 403 Error: Forbidden | B18: N/A | C18: N/A | D18: string | E18: 100 | G18: Returns a 403 error if foribidden
A20: Response Example: Fail - 500 internal Error (post validation)
A21: { | B21: =IF(OR(ISNUMBER(SEARCH("{", A21)),ISNUMBER(SEARCH("[", A21))), "", IFERROR(MID(A21, SEARCH("""", A21) +1, SEARCH("""", A21, SEARCH("""",A21) +1) - SEARCH("""", A21) -1), "")) | C21: =IF(B21="", "", VLOOKUP(B21,'API Data Dictionary'!C:J,8,FALSE)) | D21: =IF(B21="", "", VLOOKUP(B21,'API Data Dictionary'!C:D,2,FALSE)) | E21: =IF(IF(B21="", "", VLOOKUP(B21,'API Data Dictionary'!C:E,3,FALSE))=0, "", IF(B21="", "", VLOOKUP(B21,'API Data Dictionary'!C:E,3,FALSE))) | F21: =IF(IF(B21="", "", VLOOKUP(B21,'API Data Dictionary'!C:F,4,FALSE))=0, "", IF(B21="", "", VLOOKUP(B21,'API Data Dictionary'!C:F,4,FALSE))) | G21: =IF(IF(B21="", "", VLOOKUP(B21,'API Data Dictionary'!C:G,5,FALSE))=0, "", IF(B21="", "", VLOOKUP(B21,'API Data Dictionary'!C:G,5,FALSE)))
A22: "success": false, | B22: =IF(OR(ISNUMBER(SEARCH("{", A22)),ISNUMBER(SEARCH("[", A22))), "", IFERROR(MID(A22, SEARCH("""", A22) +1, SEARCH("""", A22, SEARCH("""",A22) +1) - SEARCH("""", A22) -1), "")) -> success | C22: M | D22: =IF(B22="", "", VLOOKUP(B22,'API Data Dictionary'!C:D,2,FALSE)) -> string - Boolean | E22: =IF(IF(B22="", "", VLOOKUP(B22,'API Data Dictionary'!C:E,3,FALSE))=0, "", IF(B22="", "", VLOOKUP(B22,'API Data Dictionary'!C:E,3,FALSE))) -> 100 | F22: =IF(IF(B22="", "", VLOOKUP(B22,'API Data Dictionary'!C:F,4,FALSE))=0, "", IF(B22="", "", VLOOKUP(B22,'API Data Dictionary'!C:F,4,FALSE))) | G22: =IF(IF(B22="", "", VLOOKUP(B22,'API Data Dictionary'!C:G,5,FALSE))=0, "", IF(B22="", "", VLOOKUP(B22,'API Data Dictionary'!C:G,5,FALSE))) -> Returns true when successful call/connection
A23: "payload": null | B23: =IF(OR(ISNUMBER(SEARCH("{", A23)),ISNUMBER(SEARCH("[", A23))), "", IFERROR(MID(A23, SEARCH("""", A23) +1, SEARCH("""", A23, SEARCH("""",A23) +1) - SEARCH("""", A23) -1), "")) -> payload | C23: M | D23: =IF(B23="", "", VLOOKUP(B23,'API Data Dictionary'!C:D,2,FALSE)) -> string | E23: =IF(IF(B23="", "", VLOOKUP(B23,'API Data Dictionary'!C:E,3,FALSE))=0, "", IF(B23="", "", VLOOKUP(B23,'API Data Dictionary'!C:E,3,FALSE))) -> 100 | F23: =IF(IF(B23="", "", VLOOKUP(B23,'API Data Dictionary'!C:F,4,FALSE))=0, "", IF(B23="", "", VLOOKUP(B23,'API Data Dictionary'!C:F,4,FALSE))) | G23: =IF(IF(B23="", "", VLOOKUP(B23,'API Data Dictionary'!C:G,5,FALSE))=0, "", IF(B23="", "", VLOOKUP(B23,'API Data Dictionary'!C:G,5,FALSE))) -> Returns healthy when connection has worked properly
A24: "message": "Internal error" | B24: =IF(OR(ISNUMBER(SEARCH("{", A24)),ISNUMBER(SEARCH("[", A24))), "", IFERROR(MID(A24, SEARCH("""", A24) +1, SEARCH("""", A24, SEARCH("""",A24) +1) - SEARCH("""", A24) -1), "")) -> message | C24: M | D24: =IF(B24="", "", VLOOKUP(B24,'API Data Dictionary'!C:D,2,FALSE)) -> string | E24: =IF(IF(B24="", "", VLOOKUP(B24,'API Data Dictionary'!C:E,3,FALSE))=0, "", IF(B24="", "", VLOOKUP(B24,'API Data Dictionary'!C:E,3,FALSE))) -> 100 | F24: =IF(IF(B24="", "", VLOOKUP(B24,'API Data Dictionary'!C:F,4,FALSE))=0, "", IF(B24="", "", VLOOKUP(B24,'API Data Dictionary'!C:F,4,FALSE))) | G24: =IF(IF(B24="", "", VLOOKUP(B24,'API Data Dictionary'!C:G,5,FALSE))=0, "", IF(B24="", "", VLOOKUP(B24,'API Data Dictionary'!C:G,5,FALSE))) -> return value, null or success, unless there has been error
A25: } | B25: =IF(OR(ISNUMBER(SEARCH("{", A25)),ISNUMBER(SEARCH("[", A25))), "", IFERROR(MID(A25, SEARCH("""", A25) +1, SEARCH("""", A25, SEARCH("""",A25) +1) - SEARCH("""", A25) -1), "")) | C25: =IF(B25="", "", VLOOKUP(B25,'API Data Dictionary'!C:J,8,FALSE)) | D25: =IF(B25="", "", VLOOKUP(B25,'API Data Dictionary'!C:D,2,FALSE)) | E25: =IF(IF(B25="", "", VLOOKUP(B25,'API Data Dictionary'!C:E,3,FALSE))=0, "", IF(B25="", "", VLOOKUP(B25,'API Data Dictionary'!C:E,3,FALSE))) | F25: =IF(IF(B25="", "", VLOOKUP(B25,'API Data Dictionary'!C:F,4,FALSE))=0, "", IF(B25="", "", VLOOKUP(B25,'API Data Dictionary'!C:F,4,FALSE))) | G25: =IF(IF(B25="", "", VLOOKUP(B25,'API Data Dictionary'!C:G,5,FALSE))=0, "", IF(B25="", "", VLOOKUP(B25,'API Data Dictionary'!C:G,5,FALSE)))

Sheet GetAuthenticationToken
A1: GetApplicantReferenceStatus Example JSON | B1: Vision+ API Field Name | C1: Mandatory Field | D1: Field Type | E1: API Max Field Length | F1: Field Validations | G1: Field Description
A2: Request Example
A3: { | B3: =IF(OR(ISNUMBER(SEARCH("{", A3)),ISNUMBER(SEARCH("[", A3))), "", IFERROR(MID(A3, SEARCH("""", A3) +1, SEARCH("""", A3, SEARCH("""",A3) +1) - SEARCH("""", A3) -1), "")) | C3: =IF(B3="", "", VLOOKUP(B3,'API Data Dictionary'!C:N,12,FALSE)) | D3: =IF(B3="", "", VLOOKUP(B3,'API Data Dictionary'!C:D,2,FALSE)) | E3: =IF(IF(B3="", "", VLOOKUP(B3,'API Data Dictionary'!C:E,3,FALSE))=0, "", IF(B3="", "", VLOOKUP(B3,'API Data Dictionary'!C:E,3,FALSE))) | F3: =IF(IF(B3="", "", VLOOKUP(B3,'API Data Dictionary'!C:F,4,FALSE))=0, "", IF(B3="", "", VLOOKUP(B3,'API Data Dictionary'!C:F,4,FALSE))) | G3: =IF(IF(B3="", "", VLOOKUP(B3,'API Data Dictionary'!C:G,5,FALSE))=0, "", IF(B3="", "", VLOOKUP(B3,'API Data Dictionary'!C:G,5,FALSE)))
A4: "scope": "standardapiaccess", | B4: =IF(OR(ISNUMBER(SEARCH("{", A4)),ISNUMBER(SEARCH("[", A4))), "", IFERROR(MID(A4, SEARCH("""", A4) +1, SEARCH("""", A4, SEARCH("""",A4) +1) - SEARCH("""", A4) -1), "")) -> scope | C4: M | D4: =IF(B4="", "", VLOOKUP(B4,'API Data Dictionary'!C:D,2,FALSE)) -> string - constant | E4: =IF(IF(B4="", "", VLOOKUP(B4,'API Data Dictionary'!C:E,3,FALSE))=0, "", IF(B4="", "", VLOOKUP(B4,'API Data Dictionary'!C:E,3,FALSE))) -> 100 | F4: =IF(IF(B4="", "", VLOOKUP(B4,'API Data Dictionary'!C:F,4,FALSE))=0, "", IF(B4="", "", VLOOKUP(B4,'API Data Dictionary'!C:F,4,FALSE))) | G4: =IF(IF(B4="", "", VLOOKUP(B4,'API Data Dictionary'!C:G,5,FALSE))=0, "", IF(B4="", "", VLOOKUP(B4,'API Data Dictionary'!C:G,5,FALSE))) -> Scope of the API Authentication, must always be: "standardapiaccess"
A5: "client_id": "1234-clientID", | B5: =IF(OR(ISNUMBER(SEARCH("{", A5)),ISNUMBER(SEARCH("[", A5))), "", IFERROR(MID(A5, SEARCH("""", A5) +1, SEARCH("""", A5, SEARCH("""",A5) +1) - SEARCH("""", A5) -1), "")) -> client_id | C5: M | D5: =IF(B5="", "", VLOOKUP(B5,'API Data Dictionary'!C:D,2,FALSE)) -> string | E5: =IF(IF(B5="", "", VLOOKUP(B5,'API Data Dictionary'!C:E,3,FALSE))=0, "", IF(B5="", "", VLOOKUP(B5,'API Data Dictionary'!C:E,3,FALSE))) -> 100 | F5: =IF(IF(B5="", "", VLOOKUP(B5,'API Data Dictionary'!C:F,4,FALSE))=0, "", IF(B5="", "", VLOOKUP(B5,'API Data Dictionary'!C:F,4,FALSE))) | G5: =IF(IF(B5="", "", VLOOKUP(B5,'API Data Dictionary'!C:G,5,FALSE))=0, "", IF(B5="", "", VLOOKUP(B5,'API Data Dictionary'!C:G,5,FALSE))) -> Client ID Authentication credentials provided to you on customer setup
A6: "client_secret": "xxxxxxxxxxxxxxxxxxx" | B6: =IF(OR(ISNUMBER(SEARCH("{", A6)),ISNUMBER(SEARCH("[", A6))), "", IFERROR(MID(A6, SEARCH("""", A6) +1, SEARCH("""", A6, SEARCH("""",A6) +1) - SEARCH("""", A6) -1), "")) -> client_secret | C6: M | D6: =IF(B6="", "", VLOOKUP(B6,'API Data Dictionary'!C:D,2,FALSE)) -> string | E6: =IF(IF(B6="", "", VLOOKUP(B6,'API Data Dictionary'!C:E,3,FALSE))=0, "", IF(B6="", "", VLOOKUP(B6,'API Data Dictionary'!C:E,3,FALSE))) -> 100 | F6: =IF(IF(B6="", "", VLOOKUP(B6,'API Data Dictionary'!C:F,4,FALSE))=0, "", IF(B6="", "", VLOOKUP(B6,'API Data Dictionary'!C:F,4,FALSE))) | G6: =IF(IF(B6="", "", VLOOKUP(B6,'API Data Dictionary'!C:G,5,FALSE))=0, "", IF(B6="", "", VLOOKUP(B6,'API Data Dictionary'!C:G,5,FALSE))) -> Client Secret Authentication credentials provided to you on customer setup
A7: } | B7: =IF(OR(ISNUMBER(SEARCH("{", A7)),ISNUMBER(SEARCH("[", A7))), "", IFERROR(MID(A7, SEARCH("""", A7) +1, SEARCH("""", A7, SEARCH("""",A7) +1) - SEARCH("""", A7) -1), "")) | C7: =IF(B7="", "", VLOOKUP(B7,'API Data Dictionary'!C:N,12,FALSE)) | D7: =IF(B7="", "", VLOOKUP(B7,'API Data Dictionary'!C:D,2,FALSE)) | E7: =IF(IF(B7="", "", VLOOKUP(B7,'API Data Dictionary'!C:E,3,FALSE))=0, "", IF(B7="", "", VLOOKUP(B7,'API Data Dictionary'!C:E,3,FALSE))) | F7: =IF(IF(B7="", "", VLOOKUP(B7,'API Data Dictionary'!C:F,4,FALSE))=0, "", IF(B7="", "", VLOOKUP(B7,'API Data Dictionary'!C:F,4,FALSE))) | G7: =IF(IF(B7="", "", VLOOKUP(B7,'API Data Dictionary'!C:G,5,FALSE))=0, "", IF(B7="", "", VLOOKUP(B7,'API Data Dictionary'!C:G,5,FALSE)))
A9: Response Example: Success - 200
A10: { | B10: =IF(OR(ISNUMBER(SEARCH("{", A10)),ISNUMBER(SEARCH("[", A10))), "", IFERROR(MID(A10, SEARCH("""", A10) +1, SEARCH("""", A10, SEARCH("""",A10) +1) - SEARCH("""", A10) -1), "")) | C10: =IF(B10="", "", VLOOKUP(B10,'API Data Dictionary'!C:N,12,FALSE)) | D10: =IF(B10="", "", VLOOKUP(B10,'API Data Dictionary'!C:D,2,FALSE)) | E10: =IF(IF(B10="", "", VLOOKUP(B10,'API Data Dictionary'!C:E,3,FALSE))=0, "", IF(B10="", "", VLOOKUP(B10,'API Data Dictionary'!C:E,3,FALSE))) | F10: =IF(IF(B10="", "", VLOOKUP(B10,'API Data Dictionary'!C:F,4,FALSE))=0, "", IF(B10="", "", VLOOKUP(B10,'API Data Dictionary'!C:F,4,FALSE))) | G10: =IF(IF(B10="", "", VLOOKUP(B10,'API Data Dictionary'!C:G,5,FALSE))=0, "", IF(B10="", "", VLOOKUP(B10,'API Data Dictionary'!C:G,5,FALSE)))
A11: eyJhbGciOiJSUzI1NiIsImtpZCI6IjIzNDBFOTVDMDU1M0VGNUM1Mzc0ODNBMjUyMTU1RTkyRDFGRTM3MThSUzI1NiIsInR5cCI6ImF0K2p3dCIsIng1dCI6IkkwRHBYQVZUNzF4VGRJT2lVaFZla3RILU54ZyJ9.eyJuYmYiOjE2ODU5NjExMDcsImV4cCI6MTY4NjA0NzUwNywiaXNzIjoiaHR0cHM6Ly9wcmVwcm9kLWF1dGgtc2VydmljZS5iYXJib25kZXYuY28udWsiLCJjbGllbnRfaWQiOiI0NDQyNDFfRm94dG9ucy1XZW1ibGV5IiwianRpIjoiREIwRjhGMkQwOEUyQzEwNDBCMjA1N0Y0ODg1NkRGNDciLCJpYXQiOjE2ODU5NjExMDcsInNjb3BlIjpbInN0YW5kYXJkYXBpYWNjZXNzIl19.z9phqgSvjwsbU2LeZMFmJvnDQ5fTIdhOyPZzLxJY59uJmE8ALZNEFjIrJFpQwIeBuuw8uHY8BS8czxZpW7AZtBps-Lh0qEW4GRXANWJi0rmU-Z1eEuqbmbF1z-9MSILP-OcyZeVPac8LleTh5gfHK0ycD6ioY3f-ZlsGQu7DqE7g68xMZ3UpbN617T8X93fDT67enC67m39B1-b3XrVFcIcROvIoqYQS4o8qexqLCBSgGHM726HlNWwtfSBe7gcRBU5Seij_GjtwQB9HcZf_Jwu3loElI7joJkycc2AxxyxitBrU1FFe9ZnGBAwmxY4Hiam5PsXWhR-qO1kh3M0c2Q | B11: Bearer Token | C11: M | D11: string | E11: 1000 | G11: Returned bearer authentication Token, to be used as "bearer XYZ" where XYZ is the token. Note Microsoft .NET6 systems (or others that stringify JSON responses) are required to Trim the bearer token of double quotes, e.g. client.DefaultRequestHeaders.Authorization = new AuthenticationHeaderValue("Bearer", token.Trim('"'));
A12: } | B12: =IF(OR(ISNUMBER(SEARCH("{", A12)),ISNUMBER(SEARCH("[", A12))), "", IFERROR(MID(A12, SEARCH("""", A12) +1, SEARCH("""", A12, SEARCH("""",A12) +1) - SEARCH("""", A12) -1), "")) | C12: =IF(B12="", "", VLOOKUP(B12,'API Data Dictionary'!C:N,12,FALSE)) | D12: =IF(B12="", "", VLOOKUP(B12,'API Data Dictionary'!C:D,2,FALSE)) | E12: =IF(IF(B12="", "", VLOOKUP(B12,'API Data Dictionary'!C:E,3,FALSE))=0, "", IF(B12="", "", VLOOKUP(B12,'API Data Dictionary'!C:E,3,FALSE))) | F12: =IF(IF(B12="", "", VLOOKUP(B12,'API Data Dictionary'!C:F,4,FALSE))=0, "", IF(B12="", "", VLOOKUP(B12,'API Data Dictionary'!C:F,4,FALSE))) | G12: =IF(IF(B12="", "", VLOOKUP(B12,'API Data Dictionary'!C:G,5,FALSE))=0, "", IF(B12="", "", VLOOKUP(B12,'API Data Dictionary'!C:G,5,FALSE)))
A14: Response Example: Fail - 401 Client Credentials Error
A15: invalid_client | B15: N/A | C15: N/A | D15: string | E15: 100 | G15: Invalid client will be returned if there are any issues with the combination of client_id and client_secret.
A17: Response Example: Fail - 401 Invalid Scope Error
A18: invalid_scope | B18: N/A | C18: N/A | D18: string | E18: 100 | G18: Invalid scope will be returned if there are any issues with the scope - Should always be "standardapiaccess"
A20: Response Example: Fail - 403 Forbidden
A21: 403 Error: Forbidden | B21: N/A | C21: N/A | D21: string | E21: 100 | G21: Returns a 403 error if foribidden
A23: Response Example: Fail - 500 internal Error (post validation)
A24: { | B24: =IF(OR(ISNUMBER(SEARCH("{", A24)),ISNUMBER(SEARCH("[", A24))), "", IFERROR(MID(A24, SEARCH("""", A24) +1, SEARCH("""", A24, SEARCH("""",A24) +1) - SEARCH("""", A24) -1), "")) | C24: =IF(B24="", "", VLOOKUP(B24,'API Data Dictionary'!C:J,8,FALSE)) | D24: =IF(B24="", "", VLOOKUP(B24,'API Data Dictionary'!C:D,2,FALSE)) | E24: =IF(IF(B24="", "", VLOOKUP(B24,'API Data Dictionary'!C:E,3,FALSE))=0, "", IF(B24="", "", VLOOKUP(B24,'API Data Dictionary'!C:E,3,FALSE))) | F24: =IF(IF(B24="", "", VLOOKUP(B24,'API Data Dictionary'!C:F,4,FALSE))=0, "", IF(B24="", "", VLOOKUP(B24,'API Data Dictionary'!C:F,4,FALSE))) | G24: =IF(IF(B24="", "", VLOOKUP(B24,'API Data Dictionary'!C:G,5,FALSE))=0, "", IF(B24="", "", VLOOKUP(B24,'API Data Dictionary'!C:G,5,FALSE)))
A25: "success": false, | B25: =IF(OR(ISNUMBER(SEARCH("{", A25)),ISNUMBER(SEARCH("[", A25))), "", IFERROR(MID(A25, SEARCH("""", A25) +1, SEARCH("""", A25, SEARCH("""",A25) +1) - SEARCH("""", A25) -1), "")) -> success | C25: M | D25: =IF(B25="", "", VLOOKUP(B25,'API Data Dictionary'!C:D,2,FALSE)) -> string - Boolean | E25: =IF(IF(B25="", "", VLOOKUP(B25,'API Data Dictionary'!C:E,3,FALSE))=0, "", IF(B25="", "", VLOOKUP(B25,'API Data Dictionary'!C:E,3,FALSE))) -> 100 | F25: =IF(IF(B25="", "", VLOOKUP(B25,'API Data Dictionary'!C:F,4,FALSE))=0, "", IF(B25="", "", VLOOKUP(B25,'API Data Dictionary'!C:F,4,FALSE))) | G25: =IF(IF(B25="", "", VLOOKUP(B25,'API Data Dictionary'!C:G,5,FALSE))=0, "", IF(B25="", "", VLOOKUP(B25,'API Data Dictionary'!C:G,5,FALSE))) -> Returns true when successful call/connection
A26: "payload": null | B26: =IF(OR(ISNUMBER(SEARCH("{", A26)),ISNUMBER(SEARCH("[", A26))), "", IFERROR(MID(A26, SEARCH("""", A26) +1, SEARCH("""", A26, SEARCH("""",A26) +1) - SEARCH("""", A26) -1), "")) -> payload | C26: M | D26: =IF(B26="", "", VLOOKUP(B26,'API Data Dictionary'!C:D,2,FALSE)) -> string | E26: =IF(IF(B26="", "", VLOOKUP(B26,'API Data Dictionary'!C:E,3,FALSE))=0, "", IF(B26="", "", VLOOKUP(B26,'API Data Dictionary'!C:E,3,FALSE))) -> 100 | F26: =IF(IF(B26="", "", VLOOKUP(B26,'API Data Dictionary'!C:F,4,FALSE))=0, "", IF(B26="", "", VLOOKUP(B26,'API Data Dictionary'!C:F,4,FALSE))) | G26: =IF(IF(B26="", "", VLOOKUP(B26,'API Data Dictionary'!C:G,5,FALSE))=0, "", IF(B26="", "", VLOOKUP(B26,'API Data Dictionary'!C:G,5,FALSE))) -> Returns healthy when connection has worked properly
A27: "message": "Internal error" | B27: =IF(OR(ISNUMBER(SEARCH("{", A27)),ISNUMBER(SEARCH("[", A27))), "", IFERROR(MID(A27, SEARCH("""", A27) +1, SEARCH("""", A27, SEARCH("""",A27) +1) - SEARCH("""", A27) -1), "")) -> message | C27: M | D27: =IF(B27="", "", VLOOKUP(B27,'API Data Dictionary'!C:D,2,FALSE)) -> string | E27: =IF(IF(B27="", "", VLOOKUP(B27,'API Data Dictionary'!C:E,3,FALSE))=0, "", IF(B27="", "", VLOOKUP(B27,'API Data Dictionary'!C:E,3,FALSE))) -> 100 | F27: =IF(IF(B27="", "", VLOOKUP(B27,'API Data Dictionary'!C:F,4,FALSE))=0, "", IF(B27="", "", VLOOKUP(B27,'API Data Dictionary'!C:F,4,FALSE))) | G27: =IF(IF(B27="", "", VLOOKUP(B27,'API Data Dictionary'!C:G,5,FALSE))=0, "", IF(B27="", "", VLOOKUP(B27,'API Data Dictionary'!C:G,5,FALSE))) -> return value, null or success, unless there has been error
A28: } | B28: =IF(OR(ISNUMBER(SEARCH("{", A28)),ISNUMBER(SEARCH("[", A28))), "", IFERROR(MID(A28, SEARCH("""", A28) +1, SEARCH("""", A28, SEARCH("""",A28) +1) - SEARCH("""", A28) -1), "")) | C28: =IF(B28="", "", VLOOKUP(B28,'API Data Dictionary'!C:J,8,FALSE)) | D28: =IF(B28="", "", VLOOKUP(B28,'API Data Dictionary'!C:D,2,FALSE)) | E28: =IF(IF(B28="", "", VLOOKUP(B28,'API Data Dictionary'!C:E,3,FALSE))=0, "", IF(B28="", "", VLOOKUP(B28,'API Data Dictionary'!C:E,3,FALSE))) | F28: =IF(IF(B28="", "", VLOOKUP(B28,'API Data Dictionary'!C:F,4,FALSE))=0, "", IF(B28="", "", VLOOKUP(B28,'API Data Dictionary'!C:F,4,FALSE))) | G28: =IF(IF(B28="", "", VLOOKUP(B28,'API Data Dictionary'!C:G,5,FALSE))=0, "", IF(B28="", "", VLOOKUP(B28,'API Data Dictionary'!C:G,5,FALSE)))

Sheet CreateReferenceWithAllData
A1: CreateReferenceWithAllData Example JSON | B1: Vision+ API Field Name | C1: Mandatory Field | D1: Field Type | E1: API Max Field Length | F1: Field Validations | G1: Field Description
A2: Request Example
A3: { | B3: =IF(OR(ISNUMBER(SEARCH("{", A3)),ISNUMBER(SEARCH("[", A3))), "", IFERROR(MID(A3, SEARCH("""", A3) +1, SEARCH("""", A3, SEARCH("""",A3) +1) - SEARCH("""", A3) -1), "")) | C3: =IF(B3="", "", VLOOKUP(B3,'API Data Dictionary'!C:J,8,FALSE)) | D3: =IF(B3="", "", VLOOKUP(B3,'API Data Dictionary'!C:D,2,FALSE)) | E3: =IF(IF(B3="", "", VLOOKUP(B3,'API Data Dictionary'!C:E,3,FALSE))=0, "", IF(B3="", "", VLOOKUP(B3,'API Data Dictionary'!C:E,3,FALSE))) | F3: =IF(IF(B3="", "", VLOOKUP(B3,'API Data Dictionary'!C:F,4,FALSE))=0, "", IF(B3="", "", VLOOKUP(B3,'API Data Dictionary'!C:F,4,FALSE))) | G3: =IF(IF(B3="", "", VLOOKUP(B3,'API Data Dictionary'!C:G,5,FALSE))=0, "", IF(B3="", "", VLOOKUP(B3,'API Data Dictionary'!C:G,5,FALSE)))
A4: "agentCode": "9999", | B4: =IF(OR(ISNUMBER(SEARCH("{", A4)),ISNUMBER(SEARCH("[", A4))), "", IFERROR(MID(A4, SEARCH("""", A4) +1, SEARCH("""", A4, SEARCH("""",A4) +1) - SEARCH("""", A4) -1), "")) -> agentCode | C4: =IF(B4="", "", VLOOKUP(B4,'API Data Dictionary'!C:J,8,FALSE)) -> M | D4: =IF(B4="", "", VLOOKUP(B4,'API Data Dictionary'!C:D,2,FALSE)) -> string | E4: =IF(IF(B4="", "", VLOOKUP(B4,'API Data Dictionary'!C:E,3,FALSE))=0, "", IF(B4="", "", VLOOKUP(B4,'API Data Dictionary'!C:E,3,FALSE))) -> 50 | F4: =IF(IF(B4="", "", VLOOKUP(B4,'API Data Dictionary'!C:F,4,FALSE))=0, "", IF(B4="", "", VLOOKUP(B4,'API Data Dictionary'!C:F,4,FALSE))) | G4: =IF(IF(B4="", "", VLOOKUP(B4,'API Data Dictionary'!C:G,5,FALSE))=0, "", IF(B4="", "", VLOOKUP(B4,'API Data Dictionary'!C:G,5,FALSE))) -> AgentCode is the Unique Key provided to the Agent when onboarding as a Barbon Customer. An AgentID may be linked to many Properties being managed by that Agent and Each property may be linked to 1 or more TenancyID's.
A5: "rentGuarantee": 1, | B5: =IF(OR(ISNUMBER(SEARCH("{", A5)),ISNUMBER(SEARCH("[", A5))), "", IFERROR(MID(A5, SEARCH("""", A5) +1, SEARCH("""", A5, SEARCH("""",A5) +1) - SEARCH("""", A5) -1), "")) -> rentGuarantee | C5: =IF(B5="", "", VLOOKUP(B5,'API Data Dictionary'!C:J,8,FALSE)) -> M | D5: =IF(B5="", "", VLOOKUP(B5,'API Data Dictionary'!C:D,2,FALSE)) -> enum - Rent Guarantee | E5: =IF(IF(B5="", "", VLOOKUP(B5,'API Data Dictionary'!C:E,3,FALSE))=0, "", IF(B5="", "", VLOOKUP(B5,'API Data Dictionary'!C:E,3,FALSE))) | F5: =IF(IF(B5="", "", VLOOKUP(B5,'API Data Dictionary'!C:F,4,FALSE))=0, "", IF(B5="", "", VLOOKUP(B5,'API Data Dictionary'!C:F,4,FALSE))) -> Valid Values 1-4 (See enum definition) | G5: =IF(IF(B5="", "", VLOOKUP(B5,'API Data Dictionary'!C:G,5,FALSE))=0, "", IF(B5="", "", VLOOKUP(B5,'API Data Dictionary'!C:G,5,FALSE))) -> Rent guarantee is an indicator that determines which RG option if any the agent requires
A6: "tenancyTermMonths": 12, | B6: =IF(OR(ISNUMBER(SEARCH("{", A6)),ISNUMBER(SEARCH("[", A6))), "", IFERROR(MID(A6, SEARCH("""", A6) +1, SEARCH("""", A6, SEARCH("""",A6) +1) - SEARCH("""", A6) -1), "")) -> tenancyTermMonths | C6: =IF(B6="", "", VLOOKUP(B6,'API Data Dictionary'!C:J,8,FALSE)) -> M | D6: =IF(B6="", "", VLOOKUP(B6,'API Data Dictionary'!C:D,2,FALSE)) -> integer | E6: =IF(IF(B6="", "", VLOOKUP(B6,'API Data Dictionary'!C:E,3,FALSE))=0, "", IF(B6="", "", VLOOKUP(B6,'API Data Dictionary'!C:E,3,FALSE))) | F6: =IF(IF(B6="", "", VLOOKUP(B6,'API Data Dictionary'!C:F,4,FALSE))=0, "", IF(B6="", "", VLOOKUP(B6,'API Data Dictionary'!C:F,4,FALSE))) | G6: =IF(IF(B6="", "", VLOOKUP(B6,'API Data Dictionary'!C:G,5,FALSE))=0, "", IF(B6="", "", VLOOKUP(B6,'API Data Dictionary'!C:G,5,FALSE))) -> The term of the Tenancy in months (whole months only)
A7: "monthlyRental": 12, | B7: =IF(OR(ISNUMBER(SEARCH("{", A7)),ISNUMBER(SEARCH("[", A7))), "", IFERROR(MID(A7, SEARCH("""", A7) +1, SEARCH("""", A7, SEARCH("""",A7) +1) - SEARCH("""", A7) -1), "")) -> monthlyRental | C7: =IF(B7="", "", VLOOKUP(B7,'API Data Dictionary'!C:J,8,FALSE)) -> M | D7: =IF(B7="", "", VLOOKUP(B7,'API Data Dictionary'!C:D,2,FALSE)) -> number (double) | E7: =IF(IF(B7="", "", VLOOKUP(B7,'API Data Dictionary'!C:E,3,FALSE))=0, "", IF(B7="", "", VLOOKUP(B7,'API Data Dictionary'!C:E,3,FALSE))) | F7: =IF(IF(B7="", "", VLOOKUP(B7,'API Data Dictionary'!C:F,4,FALSE))=0, "", IF(B7="", "", VLOOKUP(B7,'API Data Dictionary'!C:F,4,FALSE))) -> number($double) pattern: ^\d*.\d{0,2}$ | G7: =IF(IF(B7="", "", VLOOKUP(B7,'API Data Dictionary'!C:G,5,FALSE))=0, "", IF(B7="", "", VLOOKUP(B7,'API Data Dictionary'!C:G,5,FALSE))) -> The monthly rental cost
A8: "lettingType": 1, | B8: =IF(OR(ISNUMBER(SEARCH("{", A8)),ISNUMBER(SEARCH("[", A8))), "", IFERROR(MID(A8, SEARCH("""", A8) +1, SEARCH("""", A8, SEARCH("""",A8) +1) - SEARCH("""", A8) -1), "")) -> lettingType | C8: =IF(B8="", "", VLOOKUP(B8,'API Data Dictionary'!C:J,8,FALSE)) -> M | D8: =IF(B8="", "", VLOOKUP(B8,'API Data Dictionary'!C:D,2,FALSE)) -> enum - Letting Type | E8: =IF(IF(B8="", "", VLOOKUP(B8,'API Data Dictionary'!C:E,3,FALSE))=0, "", IF(B8="", "", VLOOKUP(B8,'API Data Dictionary'!C:E,3,FALSE))) | F8: =IF(IF(B8="", "", VLOOKUP(B8,'API Data Dictionary'!C:F,4,FALSE))=0, "", IF(B8="", "", VLOOKUP(B8,'API Data Dictionary'!C:F,4,FALSE))) -> Valid Values 1-3 (See enum definition) | G8: =IF(IF(B8="", "", VLOOKUP(B8,'API Data Dictionary'!C:G,5,FALSE))=0, "", IF(B8="", "", VLOOKUP(B8,'API Data Dictionary'!C:G,5,FALSE))) -> The type of the letting, i.e. rent only or fully managed
A9: "estimatedMoveInDate": "2023-07-20T09:57:50.515Z", | B9: =IF(OR(ISNUMBER(SEARCH("{", A9)),ISNUMBER(SEARCH("[", A9))), "", IFERROR(MID(A9, SEARCH("""", A9) +1, SEARCH("""", A9, SEARCH("""",A9) +1) - SEARCH("""", A9) -1), "")) -> estimatedMoveInDate | C9: =IF(B9="", "", VLOOKUP(B9,'API Data Dictionary'!C:J,8,FALSE)) -> M | D9: =IF(B9="", "", VLOOKUP(B9,'API Data Dictionary'!C:D,2,FALSE)) -> string ($date-time) | E9: =IF(IF(B9="", "", VLOOKUP(B9,'API Data Dictionary'!C:E,3,FALSE))=0, "", IF(B9="", "", VLOOKUP(B9,'API Data Dictionary'!C:E,3,FALSE))) | F9: =IF(IF(B9="", "", VLOOKUP(B9,'API Data Dictionary'!C:F,4,FALSE))=0, "", IF(B9="", "", VLOOKUP(B9,'API Data Dictionary'!C:F,4,FALSE))) -> DD/MM/YYYY | G9: =IF(IF(B9="", "", VLOOKUP(B9,'API Data Dictionary'!C:G,5,FALSE))=0, "", IF(B9="", "", VLOOKUP(B9,'API Data Dictionary'!C:G,5,FALSE))) -> Estimated date of tenancy start (move in)
A10: "propertyType": 1, | B10: =IF(OR(ISNUMBER(SEARCH("{", A10)),ISNUMBER(SEARCH("[", A10))), "", IFERROR(MID(A10, SEARCH("""", A10) +1, SEARCH("""", A10, SEARCH("""",A10) +1) - SEARCH("""", A10) -1), "")) -> propertyType | C10: =IF(B10="", "", VLOOKUP(B10,'API Data Dictionary'!C:J,8,FALSE)) -> M | D10: =IF(B10="", "", VLOOKUP(B10,'API Data Dictionary'!C:D,2,FALSE)) -> enum - Property Type | E10: =IF(IF(B10="", "", VLOOKUP(B10,'API Data Dictionary'!C:E,3,FALSE))=0, "", IF(B10="", "", VLOOKUP(B10,'API Data Dictionary'!C:E,3,FALSE))) | F10: =IF(IF(B10="", "", VLOOKUP(B10,'API Data Dictionary'!C:F,4,FALSE))=0, "", IF(B10="", "", VLOOKUP(B10,'API Data Dictionary'!C:F,4,FALSE))) -> Valid Values 1-6 (See enum definition) | G10: =IF(IF(B10="", "", VLOOKUP(B10,'API Data Dictionary'!C:G,5,FALSE))=0, "", IF(B10="", "", VLOOKUP(B10,'API Data Dictionary'!C:G,5,FALSE))) -> The Type of property
A11: "propertyConstructionPeriod": 4, | B11: =IF(OR(ISNUMBER(SEARCH("{", A11)),ISNUMBER(SEARCH("[", A11))), "", IFERROR(MID(A11, SEARCH("""", A11) +1, SEARCH("""", A11, SEARCH("""",A11) +1) - SEARCH("""", A11) -1), "")) -> propertyConstructionPeriod | C11: =IF(B11="", "", VLOOKUP(B11,'API Data Dictionary'!C:J,8,FALSE)) -> X | D11: =IF(B11="", "", VLOOKUP(B11,'API Data Dictionary'!C:D,2,FALSE)) -> enum - Property Construction Period | E11: =IF(IF(B11="", "", VLOOKUP(B11,'API Data Dictionary'!C:E,3,FALSE))=0, "", IF(B11="", "", VLOOKUP(B11,'API Data Dictionary'!C:E,3,FALSE))) | F11: =IF(IF(B11="", "", VLOOKUP(B11,'API Data Dictionary'!C:F,4,FALSE))=0, "", IF(B11="", "", VLOOKUP(B11,'API Data Dictionary'!C:F,4,FALSE))) -> Valid Values 1-9 (See enum definition) | G11: =IF(IF(B11="", "", VLOOKUP(B11,'API Data Dictionary'!C:G,5,FALSE))=0, "", IF(B11="", "", VLOOKUP(B11,'API Data Dictionary'!C:G,5,FALSE))) -> The time period in which the property was built
A12: "numberOfBedrooms": 3, | B12: =IF(OR(ISNUMBER(SEARCH("{", A12)),ISNUMBER(SEARCH("[", A12))), "", IFERROR(MID(A12, SEARCH("""", A12) +1, SEARCH("""", A12, SEARCH("""",A12) +1) - SEARCH("""", A12) -1), "")) -> numberOfBedrooms | C12: =IF(B12="", "", VLOOKUP(B12,'API Data Dictionary'!C:J,8,FALSE)) -> X | D12: =IF(B12="", "", VLOOKUP(B12,'API Data Dictionary'!C:D,2,FALSE)) -> integer | E12: =IF(IF(B12="", "", VLOOKUP(B12,'API Data Dictionary'!C:E,3,FALSE))=0, "", IF(B12="", "", VLOOKUP(B12,'API Data Dictionary'!C:E,3,FALSE))) | F12: =IF(IF(B12="", "", VLOOKUP(B12,'API Data Dictionary'!C:F,4,FALSE))=0, "", IF(B12="", "", VLOOKUP(B12,'API Data Dictionary'!C:F,4,FALSE))) | G12: =IF(IF(B12="", "", VLOOKUP(B12,'API Data Dictionary'!C:G,5,FALSE))=0, "", IF(B12="", "", VLOOKUP(B12,'API Data Dictionary'!C:G,5,FALSE))) -> The count of bedrooms in the property
A13: "noOfAdultOccupants": 2, | B13: =IF(OR(ISNUMBER(SEARCH("{", A13)),ISNUMBER(SEARCH("[", A13))), "", IFERROR(MID(A13, SEARCH("""", A13) +1, SEARCH("""", A13, SEARCH("""",A13) +1) - SEARCH("""", A13) -1), "")) -> noOfAdultOccupants | C13: =IF(B13="", "", VLOOKUP(B13,'API Data Dictionary'!C:J,8,FALSE)) -> X | D13: =IF(B13="", "", VLOOKUP(B13,'API Data Dictionary'!C:D,2,FALSE)) -> integer | E13: =IF(IF(B13="", "", VLOOKUP(B13,'API Data Dictionary'!C:E,3,FALSE))=0, "", IF(B13="", "", VLOOKUP(B13,'API Data Dictionary'!C:E,3,FALSE))) | F13: =IF(IF(B13="", "", VLOOKUP(B13,'API Data Dictionary'!C:F,4,FALSE))=0, "", IF(B13="", "", VLOOKUP(B13,'API Data Dictionary'!C:F,4,FALSE))) | G13: =IF(IF(B13="", "", VLOOKUP(B13,'API Data Dictionary'!C:G,5,FALSE))=0, "", IF(B13="", "", VLOOKUP(B13,'API Data Dictionary'!C:G,5,FALSE))) -> Number of Adult occupants (18 or over)
A14: "noOfChildOccupants": 1, | B14: =IF(OR(ISNUMBER(SEARCH("{", A14)),ISNUMBER(SEARCH("[", A14))), "", IFERROR(MID(A14, SEARCH("""", A14) +1, SEARCH("""", A14, SEARCH("""",A14) +1) - SEARCH("""", A14) -1), "")) -> noOfChildOccupants | C14: =IF(B14="", "", VLOOKUP(B14,'API Data Dictionary'!C:J,8,FALSE)) -> X | D14: =IF(B14="", "", VLOOKUP(B14,'API Data Dictionary'!C:D,2,FALSE)) -> integer | E14: =IF(IF(B14="", "", VLOOKUP(B14,'API Data Dictionary'!C:E,3,FALSE))=0, "", IF(B14="", "", VLOOKUP(B14,'API Data Dictionary'!C:E,3,FALSE))) | F14: =IF(IF(B14="", "", VLOOKUP(B14,'API Data Dictionary'!C:F,4,FALSE))=0, "", IF(B14="", "", VLOOKUP(B14,'API Data Dictionary'!C:F,4,FALSE))) | G14: =IF(IF(B14="", "", VLOOKUP(B14,'API Data Dictionary'!C:G,5,FALSE))=0, "", IF(B14="", "", VLOOKUP(B14,'API Data Dictionary'!C:G,5,FALSE))) -> Number of Child Occupants (under 18)
... A32: "firstName": "Juliet", | B32: =IF(OR(ISNUMBER(SEARCH("{", A32)),ISNUMBER(SEARCH("[", A32))), "", IFERROR(MID(A32, SEARCH("""", A32) +1, SEARCH("""", A32, SEARCH("""",A32) +1) - SEARCH("""", A32) -1), "")) -> firstName | C32: =IF(B32="", "", VLOOKUP(B32,'API Data Dictionary'!C:J,8,FALSE)) -> M | D32: =IF(B32="", "", VLOOKUP(B32,'API Data Dictionary'!C:D,2,FALSE)) -> string | E32: =IF(IF(B32="", "", VLOOKUP(B32,'API Data Dictionary'!C:E,3,FALSE))=0, "", IF(B32="", "", VLOOKUP(B32,'API Data Dictionary'!C:E,3,FALSE))) -> 100 | F32: =IF(IF(B32="", "", VLOOKUP(B32,'API Data Dictionary'!C:F,4,FALSE))=0, "", IF(B32="", "", VLOOKUP(B32,'API Data Dictionary'!C:F,4,FALSE))) -> pattern: ^[a-zA-Z0-9\-' ]*$ | G32: =IF(IF(B32="", "", VLOOKUP(B32,'API Data Dictionary'!C:G,5,FALSE))=0, "", IF(B32="", "", VLOOKUP(B32,'API Data Dictionary'!C:G,5,FALSE))) -> First name, validated against the RegEx pattern
A33: "middleName": "Barney", | B33: =IF(OR(ISNUMBER(SEARCH("{", A33)),ISNUMBER(SEARCH("[", A33))), "", IFERROR(MID(A33, SEARCH("""", A33) +1, SEARCH("""", A33, SEARCH("""",A33) +1) - SEARCH("""", A33) -1), "")) -> middleName | C33: M | D33: =IF(B33="", "", VLOOKUP(B33,'API Data Dictionary'!C:D,2,FALSE)) -> string | E33: =IF(IF(B33="", "", VLOOKUP(B33,'API Data Dictionary'!C:E,3,FALSE))=0, "", IF(B33="", "", VLOOKUP(B33,'API Data Dictionary'!C:E,3,FALSE))) -> 50 | F33: =IF(IF(B33="", "", VLOOKUP(B33,'API Data Dictionary'!C:F,4,FALSE))=0, "", IF(B33="", "", VLOOKUP(B33,'API Data Dictionary'!C:F,4,FALSE))) -> pattern: ^[a-zA-Z0-9\-' ]*$ | G33: =IF(IF(B33="", "", VLOOKUP(B33,'API Data Dictionary'!C:G,5,FALSE))=0, "", IF(B33="", "", VLOOKUP(B33,'API Data Dictionary'!C:G,5,FALSE))) -> Middle name, validated against the RegEx pattern
A34: "surname": "Clarke", | B34: =IF(OR(ISNUMBER(SEARCH("{", A34)),ISNUMBER(SEARCH("[", A34))), "", IFERROR(MID(A34, SEARCH("""", A34) +1, SEARCH("""", A34, SEARCH("""",A34) +1) - SEARCH("""", A34) -1), "")) -> surname | C34: =IF(B34="", "", VLOOKUP(B34,'API Data Dictionary'!C:J,8,FALSE)) -> M | D34: =IF(B34="", "", VLOOKUP(B34,'API Data Dictionary'!C:D,2,FALSE)) -> string | E34: =IF(IF(B34="", "", VLOOKUP(B34,'API Data Dictionary'!C:E,3,FALSE))=0, "", IF(B34="", "", VLOOKUP(B34,'API Data Dictionary'!C:E,3,FALSE))) -> 100 | F34: =IF(IF(B34="", "", VLOOKUP(B34,'API Data Dictionary'!C:F,4,FALSE))=0, "", IF(B34="", "", VLOOKUP(B34,'API Data Dictionary'!C:F,4,FALSE))) -> pattern: ^[a-zA-Z0-9\-' ]*$ | G34: =IF(IF(B34="", "", VLOOKUP(B34,'API Data Dictionary'!C:G,5,FALSE))=0, "", IF(B34="", "", VLOOKUP(B34,'API Data Dictionary'!C:G,5,FALSE))) -> Surname name, validated against the RegEx pattern
A35: "shareOfRent": 525.26, | B35: =IF(OR(ISNUMBER(SEARCH("{", A35)),ISNUMBER(SEARCH("[", A35))), "", IFERROR(MID(A35, SEARCH("""", A35) +1, SEARCH("""", A35, SEARCH("""",A35) +1) - SEARCH("""", A35) -1), "")) -> shareOfRent | C35: =IF(B35="", "", VLOOKUP(B35,'API Data Dictionary'!C:J,8,FALSE)) -> M | D35: =IF(B35="", "", VLOOKUP(B35,'API Data Dictionary'!C:D,2,FALSE)) -> number (double) | E35: =IF(IF(B35="", "", VLOOKUP(B35,'API Data Dictionary'!C:E,3,FALSE))=0, "", IF(B35="", "", VLOOKUP(B35,'API Data Dictionary'!C:E,3,FALSE))) | F35: =IF(IF(B35="", "", VLOOKUP(B35,'API Data Dictionary'!C:F,4,FALSE))=0, "", IF(B35="", "", VLOOKUP(B35,'API Data Dictionary'!C:F,4,FALSE))) -> pattern: ^\d*.\d{0,2}$ | G35: =IF(IF(B35="", "", VLOOKUP(B35,'API Data Dictionary'!C:G,5,FALSE))=0, "", IF(B35="", "", VLOOKUP(B35,'API Data Dictionary'!C:G,5,FALSE))) -> GBP value of the applicants share of the rent
A36: "telephoneCountryID": 1, | B36: =IF(OR(ISNUMBER(SEARCH("{", A36)),ISNUMBER(SEARCH("[", A36))), "", IFERROR(MID(A36, SEARCH("""", A36) +1, SEARCH("""", A36, SEARCH("""",A36) +1) - SEARCH("""", A36) -1), "")) -> telephoneCountryID | C36: =IF(B36="", "", VLOOKUP(B36,'API Data Dictionary'!C:J,8,FALSE)) -> M | D36: =IF(B36="", "", VLOOKUP(B36,'API Data Dictionary'!C:D,2,FALSE)) -> enum -Country/Location Code | E36: =IF(IF(B36="", "", VLOOKUP(B36,'API Data Dictionary'!C:E,3,FALSE))=0, "", IF(B36="", "", VLOOKUP(B36,'API Data Dictionary'!C:E,3,FALSE))) | F36: =IF(IF(B36="", "", VLOOKUP(B36,'API Data Dictionary'!C:F,4,FALSE))=0, "", IF(B36="", "", VLOOKUP(B36,'API Data Dictionary'!C:F,4,FALSE))) -> Valid Values 1-239 (See enum definition) | G36: =IF(IF(B36="", "", VLOOKUP(B36,'API Data Dictionary'!C:G,5,FALSE))=0, "", IF(B36="", "", VLOOKUP(B36,'API Data Dictionary'!C:G,5,FALSE))) -> The country/location code of the phone number
A37: "contactTelephoneNo": "01234567891", | B37: =IF(OR(ISNUMBER(SEARCH("{", A37)),ISNUMBER(SEARCH("[", A37))), "", IFERROR(MID(A37, SEARCH("""", A37) +1, SEARCH("""", A37, SEARCH("""",A37) +1) - SEARCH("""", A37) -1), "")) -> contactTelephoneNo | C37: =IF(B37="", "", VLOOKUP(B37,'API Data Dictionary'!C:J,8,FALSE)) -> M | D37: =IF(B37="", "", VLOOKUP(B37,'API Data Dictionary'!C:D,2,FALSE)) -> string | E37: =IF(IF(B37="", "", VLOOKUP(B37,'API Data Dictionary'!C:E,3,FALSE))=0, "", IF(B37="", "", VLOOKUP(B37,'API Data Dictionary'!C:E,3,FALSE))) -> 15 | F37: =IF(IF(B37="", "", VLOOKUP(B37,'API Data Dictionary'!C:F,4,FALSE))=0, "", IF(B37="", "", VLOOKUP(B37,'API Data Dictionary'!C:F,4,FALSE))) -> pattern: ^(\d{11})$ | G37: =IF(IF(B37="", "", VLOOKUP(B37,'API Data Dictionary'!C:G,5,FALSE))=0, "", IF(B37="", "", VLOOKUP(B37,'API Data Dictionary'!C:G,5,FALSE))) -> The telephone number
A38: "emailAddress": "gajodal609@cnxcoin.com", | B38: =IF(OR(ISNUMBER(SEARCH("{", A38)),ISNUMBER(SEARCH("[", A38))), "", IFERROR(MID(A38, SEARCH("""", A38) +1, SEARCH("""", A38, SEARCH("""",A38) +1) - SEARCH("""", A38) -1), "")) -> emailAddress | C38: =IF(B38="", "", VLOOKUP(B38,'API Data Dictionary'!C:J,8,FALSE)) -> M | D38: =IF(B38="", "", VLOOKUP(B38,'API Data Dictionary'!C:D,2,FALSE)) -> string ($email) | E38: =IF(IF(B38="", "", VLOOKUP(B38,'API Data Dictionary'!C:E,3,FALSE))=0, "", IF(B38="", "", VLOOKUP(B38,'API Data Dictionary'!C:E,3,FALSE))) -> 200 | F38: =IF(IF(B38="", "", VLOOKUP(B38,'API Data Dictionary'!C:F,4,FALSE))=0, "", IF(B38="", "", VLOOKUP(B38,'API Data Dictionary'!C:F,4,FALSE))) -> pattern: ^(?!.*\.\.)(?!.*\\_\\_)(?!.*\-\-)[a-zA-Z0-9][-a-zA-Z0-9._]+[a-zA-Z0-9]@([-a-zA-Z0-9]+.)+[a-zA-Z]{2,5}$ | G38: =IF(IF(B38="", "", VLOOKUP(B38,'API Data Dictionary'!C:G,5,FALSE))=0, "", IF(B38="", "", VLOOKUP(B38,'API Data Dictionary'!C:G,5,FALSE))) -> The email address
A39: "dateOfBirth": "1986-10-12T00:00:00.0000000", | B39: =IF(OR(ISNUMBER(SEARCH("{", A39)),ISNUMBER(SEARCH("[", A39))), "", IFERROR(MID(A39, SEARCH("""", A39) +1, SEARCH("""", A39, SEARCH("""",A39) +1) - SEARCH("""", A39) -1), "")) -> dateOfBirth | C39: M | D39: =IF(B39="", "", VLOOKUP(B39,'API Data Dictionary'!C:D,2,FALSE)) -> string ($date-time) | E39: =IF(IF(B39="", "", VLOOKUP(B39,'API Data Dictionary'!C:E,3,FALSE))=0, "", IF(B39="", "", VLOOKUP(B39,'API Data Dictionary'!C:E,3,FALSE))) | F39: =IF(IF(B39="", "", VLOOKUP(B39,'API Data Dictionary'!C:F,4,FALSE))=0, "", IF(B39="", "", VLOOKUP(B39,'API Data Dictionary'!C:F,4,FALSE))) -> DD/MM/YYYY | G39: =IF(IF(B39="", "", VLOOKUP(B39,'API Data Dictionary'!C:G,5,FALSE))=0, "", IF(B39="", "", VLOOKUP(B39,'API Data Dictionary'!C:G,5,FALSE))) -> The date of birth, formatted DD-MM-YYYY
A40: "nationality": 1, | B40: =IF(OR(ISNUMBER(SEARCH("{", A40)),ISNUMBER(SEARCH("[", A40))), "", IFERROR(MID(A40, SEARCH("""", A40) +1, SEARCH("""", A40, SEARCH("""",A40) +1) - SEARCH("""", A40) -1), "")) -> nationality | C40: =IF(B40="", "", VLOOKUP(B40,'API Data Dictionary'!C:J,8,FALSE)) -> M | D40: =IF(B40="", "", VLOOKUP(B40,'API Data Dictionary'!C:D,2,FALSE)) -> enum - Nationality | E40: =IF(IF(B40="", "", VLOOKUP(B40,'API Data Dictionary'!C:E,3,FALSE))=0, "", IF(B40="", "", VLOOKUP(B40,'API Data Dictionary'!C:E,3,FALSE))) | F40: =IF(IF(B40="", "", VLOOKUP(B40,'API Data Dictionary'!C:F,4,FALSE))=0, "", IF(B40="", "", VLOOKUP(B40,'API Data Dictionary'!C:F,4,FALSE))) -> Valid Values 1-231 (See enum definition) | G40: =IF(IF(B40="", "", VLOOKUP(B40,'API Data Dictionary'!C:G,5,FALSE))=0, "", IF(B40="", "", VLOOKUP(B40,'API Data Dictionary'!C:G,5,FALSE))) -> The nationality, from the nationality enum list
A41: "niNumber": "AB123456D", | B41: =IF(OR(ISNUMBER(SEARCH("{", A41)),ISNUMBER(SEARCH("[", A41))), "", IFERROR(MID(A41, SEARCH("""", A41) +1, SEARCH("""", A41, SEARCH("""",A41) +1) - SEARCH("""", A41) -1), "")) -> niNumber | C41: =IF(B41="", "", VLOOKUP(B41,'API Data Dictionary'!C:J,8,FALSE)) -> X | D41: =IF(B41="", "", VLOOKUP(B41,'API Data Dictionary'!C:D,2,FALSE)) -> string | E41: =IF(IF(B41="", "", VLOOKUP(B41,'API Data Dictionary'!C:E,3,FALSE))=0, "", IF(B41="", "", VLOOKUP(B41,'API Data Dictionary'!C:E,3,FALSE))) -> 100 | F41: =IF(IF(B41="", "", VLOOKUP(B41,'API Data Dictionary'!C:F,4,FALSE))=0, "", IF(B41="", "", VLOOKUP(B41,'API Data Dictionary'!C:F,4,FALSE))) -> pattern: ^[a-zA-Z]{2}(?:\d){6}[a-zA-Z]{1}$ | G41: =IF(IF(B41="", "", VLOOKUP(B41,'API Data Dictionary'!C:G,5,FALSE))=0, "", IF(B41="", "", VLOOKUP(B41,'API Data Dictionary'!C:G,5,FALSE))) -> NI Number, matched to RegEx pattern
A42: "residentStatus": 1, | B42: =IF(OR(ISNUMBER(SEARCH("{", A42)),ISNUMBER(SEARCH("[", A42))), "", IFERROR(MID(A42, SEARCH("""", A42) +1, SEARCH("""", A42, SEARCH("""",A42) +1) - SEARCH("""", A42) -1), "")) -> residentStatus | C42: =IF(B42="", "", VLOOKUP(B42,'API Data Dictionary'!C:J,8,FALSE)) -> M | D42: =IF(B42="", "", VLOOKUP(B42,'API Data Dictionary'!C:D,2,FALSE)) -> enum - resident Status | E42: =IF(IF(B42="", "", VLOOKUP(B42,'API Data Dictionary'!C:E,3,FALSE))=0, "", IF(B42="", "", VLOOKUP(B42,'API Data Dictionary'!C:E,3,FALSE))) | F42: =IF(IF(B42="", "", VLOOKUP(B42,'API Data Dictionary'!C:F,4,FALSE))=0, "", IF(B42="", "", VLOOKUP(B42,'API Data Dictionary'!C:F,4,FALSE))) -> Valid Values 1-2 (See enum definition) | G42: =IF(IF(B42="", "", VLOOKUP(B42,'API Data Dictionary'!C:G,5,FALSE))=0, "", IF(B42="", "", VLOOKUP(B42,'API Data Dictionary'!C:G,5,FALSE))) -> Denotes the resident status e.g. UK resident
A43: "additionalInformation": "Additional information for the tenancy of tenant", | B43: =IF(OR(ISNUMBER(SEARCH("{", A43)),ISNUMBER(SEARCH("[", A43))), "", IFERROR(MID(A43, SEARCH("""", A43) +1, SEARCH("""", A43, SEARCH("""",A43) +1) - SEARCH("""", A43) -1), "")) -> additionalInformation | C43: =IF(B43="", "", VLOOKUP(B43,'API Data Dictionary'!C:J,8,FALSE)) -> X | D43: =IF(B43="", "", VLOOKUP(B43,'API Data Dictionary'!C:D,2,FALSE)) -> string | E43: =IF(IF(B43="", "", VLOOKUP(B43,'API Data Dictionary'!C:E,3,FALSE))=0, "", IF(B43="", "", VLOOKUP(B43,'API Data Dictionary'!C:E,3,FALSE))) -> 65535 | F43: =IF(IF(B43="", "", VLOOKUP(B43,'API Data Dictionary'!C:F,4,FALSE))=0, "", IF(B43="", "", VLOOKUP(B43,'API Data Dictionary'!C:F,4,FALSE))) | G43: =IF(IF(B43="", "", VLOOKUP(B43,'API Data Dictionary'!C:G,5,FALSE))=0, "", IF(B43="", "", VLOOKUP(B43,'API Data Dictionary'!C:G,5,FALSE))) -> Free text field for additional information
A44: "otherNames": [ | B44: =IF(OR(ISNUMBER(SEARCH("{", A44)),ISNUMBER(SEARCH("[", A44))), "", IFERROR(MID(A44, SEARCH("""", A44) +1, SEARCH("""", A44, SEARCH("""",A44) +1) - SEARCH("""", A44) -1), "")) | C44: =IF(B44="", "", VLOOKUP(B44,'API Data Dictionary'!C:J,8,FALSE)) | D44: =IF(B44="", "", VLOOKUP(B44,'API Data Dictionary'!C:D,2,FALSE)) | E44: =IF(IF(B44="", "", VLOOKUP(B44,'API Data Dictionary'!C:E,3,FALSE))=0, "", IF(B44="", "", VLOOKUP(B44,'API Data Dictionary'!C:E,3,FALSE))) | F44: =IF(IF(B44="", "", VLOOKUP(B44,'API Data Dictionary'!C:F,4,FALSE))=0, "", IF(B44="", "", VLOOKUP(B44,'API Data Dictionary'!C:F,4,FALSE))) | G44: =IF(IF(B44="", "", VLOOKUP(B44,'API Data Dictionary'!C:G,5,FALSE))=0, "", IF(B44="", "", VLOOKUP(B44,'API Data Dictionary'!C:G,5,FALSE)))
A45: { | B45: =IF(OR(ISNUMBER(SEARCH("{", A45)),ISNUMBER(SEARCH("[", A45))), "", IFERROR(MID(A45, SEARCH("""", A45) +1, SEARCH("""", A45, SEARCH("""",A45) +1) - SEARCH("""", A45) -1), "")) | C45: =IF(B45="", "", VLOOKUP(B45,'API Data Dictionary'!C:J,8,FALSE)) | D45: =IF(B45="", "", VLOOKUP(B45,'API Data Dictionary'!C:D,2,FALSE)) | E45: =IF(IF(B45="", "", VLOOKUP(B45,'API Data Dictionary'!C:E,3,FALSE))=0, "", IF(B45="", "", VLOOKUP(B45,'API Data Dictionary'!C:E,3,FALSE))) | F45: =IF(IF(B45="", "", VLOOKUP(B45,'API Data Dictionary'!C:F,4,FALSE))=0, "", IF(B45="", "", VLOOKUP(B45,'API Data Dictionary'!C:F,4,FALSE))) | G45: =IF(IF(B45="", "", VLOOKUP(B45,'API Data Dictionary'!C:G,5,FALSE))=0, "", IF(B45="", "", VLOOKUP(B45,'API Data Dictionary'!C:G,5,FALSE)))
A46: "firstName": "Chelsea", | B46: =IF(OR(ISNUMBER(SEARCH("{", A46)),ISNUMBER(SEARCH("[", A46))), "", IFERROR(MID(A46, SEARCH("""", A46) +1, SEARCH("""", A46, SEARCH("""",A46) +1) - SEARCH("""", A46) -1), "")) -> firstName | C46: =IF(B46="", "", VLOOKUP(B46,'API Data Dictionary'!C:J,8,FALSE)) -> M | D46: =IF(B46="", "", VLOOKUP(B46,'API Data Dictionary'!C:D,2,FALSE)) -> string | E46: =IF(IF(B46="", "", VLOOKUP(B46,'API Data Dictionary'!C:E,3,FALSE))=0, "", IF(B46="", "", VLOOKUP(B46,'API Data Dictionary'!C:E,3,FALSE))) -> 100 | F46: =IF(IF(B46="", "", VLOOKUP(B46,'API Data Dictionary'!C:F,4,FALSE))=0, "", IF(B46="", "", VLOOKUP(B46,'API Data Dictionary'!C:F,4,FALSE))) -> pattern: ^[a-zA-Z0-9\-' ]*$ | G46: =IF(IF(B46="", "", VLOOKUP(B46,'API Data Dictionary'!C:G,5,FALSE))=0, "", IF(B46="", "", VLOOKUP(B46,'API Data Dictionary'!C:G,5,FALSE))) -> First name, validated against the RegEx pattern
A47: "middleName": "Ali", | B47: =IF(OR(ISNUMBER(SEARCH("{", A47)),ISNUMBER(SEARCH("[", A47))), "", IFERROR(MID(A47, SEARCH("""", A47) +1, SEARCH("""", A47, SEARCH("""",A47) +1) - SEARCH("""", A47) -1), "")) -> middleName | C47: =IF(B47="", "", VLOOKUP(B47,'API Data Dictionary'!C:J,8,FALSE)) -> X | D47: =IF(B47="", "", VLOOKUP(B47,'API Data Dictionary'!C:D,2,FALSE)) -> string | E47: =IF(IF(B47="", "", VLOOKUP(B47,'API Data Dictionary'!C:E,3,FALSE))=0, "", IF(B47="", "", VLOOKUP(B47,'API Data Dictionary'!C:E,3,FALSE))) -> 50 | F47: =IF(IF(B47="", "", VLOOKUP(B47,'API Data Dictionary'!C:F,4,FALSE))=0, "", IF(B47="", "", VLOOKUP(B47,'API Data Dictionary'!C:F,4,FALSE))) -> pattern: ^[a-zA-Z0-9\-' ]*$ | G47: =IF(IF(B47="", "", VLOOKUP(B47,'API Data Dictionary'!C:G,5,FALSE))=0, "", IF(B47="", "", VLOOKUP(B47,'API Data Dictionary'!C:G,5,FALSE))) -> Middle name, validated against the RegEx pattern
A48: "lastName": "Woodley", | B48: =IF(OR(ISNUMBER(SEARCH("{", A48)),ISNUMBER(SEARCH("[", A48))), "", IFERROR(MID(A48, SEARCH("""", A48) +1, SEARCH("""", A48, SEARCH("""",A48) +1) - SEARCH("""", A48) -1), "")) -> lastName | C48: =IF(B48="", "", VLOOKUP(B48,'API Data Dictionary'!C:J,8,FALSE)) -> X | D48: =IF(B48="", "", VLOOKUP(B48,'API Data Dictionary'!C:D,2,FALSE)) -> string | E48: =IF(IF(B48="", "", VLOOKUP(B48,'API Data Dictionary'!C:E,3,FALSE))=0, "", IF(B48="", "", VLOOKUP(B48,'API Data Dictionary'!C:E,3,FALSE))) -> 100 | F48: =IF(IF(B48="", "", VLOOKUP(B48,'API Data Dictionary'!C:F,4,FALSE))=0, "", IF(B48="", "", VLOOKUP(B48,'API Data Dictionary'!C:F,4,FALSE))) -> pattern: ^[a-zA-Z0-9\-' ]*$ | G48: =IF(IF(B48="", "", VLOOKUP(B48,'API Data Dictionary'!C:G,5,FALSE))=0, "", IF(B48="", "", VLOOKUP(B48,'API Data Dictionary'!C:G,5,FALSE))) -> Surname name, validated against the RegEx pattern
A49: "nameChangeDate": "2020-10-12T00:00:00.0000000" | B49: =IF(OR(ISNUMBER(SEARCH("{", A49)),ISNUMBER(SEARCH("[", A49))), "", IFERROR(MID(A49, SEARCH("""", A49) +1, SEARCH("""", A49, SEARCH("""",A49) +1) - SEARCH("""", A49) -1), "")) -> nameChangeDate | C49: =IF(B49="", "", VLOOKUP(B49,'API Data Dictionary'!C:J,8,FALSE)) -> X | D49: =IF(B49="", "", VLOOKUP(B49,'API Data Dictionary'!C:D,2,FALSE)) -> string ($date-time) | E49: =IF(IF(B49="", "", VLOOKUP(B49,'API Data Dictionary'!C:E,3,FALSE))=0, "", IF(B49="", "", VLOOKUP(B49,'API Data Dictionary'!C:E,3,FALSE))) | F49: =IF(IF(B49="", "", VLOOKUP(B49,'API Data Dictionary'!C:F,4,FALSE))=0, "", IF(B49="", "", VLOOKUP(B49,'API Data Dictionary'!C:F,4,FALSE))) -> DD/MM/YYYY | G49: =IF(IF(B49="", "", VLOOKUP(B49,'API Data Dictionary'!C:G,5,FALSE))=0, "", IF(B49="", "", VLOOKUP(B49,'API Data Dictionary'!C:G,5,FALSE))) -> Date the name was changed, formatted DD/MM/YYYY
A50: } | B50: =IF(OR(ISNUMBER(SEARCH("{", A50)),ISNUMBER(SEARCH("[", A50))), "", IFERROR(MID(A50, SEARCH("""", A50) +1, SEARCH("""", A50, SEARCH("""",A50) +1) - SEARCH("""", A50) -1), "")) | C50: =IF(B50="", "", VLOOKUP(B50,'API Data Dictionary'!C:J,8,FALSE)) | D50: =IF(B50="", "", VLOOKUP(B50,'API Data Dictionary'!C:D,2,FALSE)) | E50: =IF(IF(B50="", "", VLOOKUP(B50,'API Data Dictionary'!C:E,3,FALSE))=0, "", IF(B50="", "", VLOOKUP(B50,'API Data Dictionary'!C:E,3,FALSE))) | F50: =IF(IF(B50="", "", VLOOKUP(B50,'API Data Dictionary'!C:F,4,FALSE))=0, "", IF(B50="", "", VLOOKUP(B50,'API Data Dictionary'!C:F,4,FALSE))) | G50: =IF(IF(B50="", "", VLOOKUP(B50,'API Data Dictionary'!C:G,5,FALSE))=0, "", IF(B50="", "", VLOOKUP(B50,'API Data Dictionary'!C:G,5,FALSE)))
A51: ], | B51: =IF(OR(ISNUMBER(SEARCH("{", A51)),ISNUMBER(SEARCH("[", A51))), "", IFERROR(MID(A51, SEARCH("""", A51) +1, SEARCH("""", A51, SEARCH("""",A51) +1) - SEARCH("""", A51) -1), "")) | C51: =IF(B51="", "", VLOOKUP(B51,'API Data Dictionary'!C:J,8,FALSE)) | D51: =IF(B51="", "", VLOOKUP(B51,'API Data Dictionary'!C:D,2,FALSE)) | E51: =IF(IF(B51="", "", VLOOKUP(B51,'API Data Dictionary'!C:E,3,FALSE))=0, "", IF(B51="", "", VLOOKUP(B51,'API Data Dictionary'!C:E,3,FALSE))) | F51: =IF(IF(B51="", "", VLOOKUP(B51,'API Data Dictionary'!C:F,4,FALSE))=0, "", IF(B51="", "", VLOOKUP(B51,'API Data Dictionary'!C:F,4,FALSE))) | G51: =IF(IF(B51="", "", VLOOKUP(B51,'API Data Dictionary'!C:G,5,FALSE))=0, "", IF(B51="", "", VLOOKUP(B51,'API Data Dictionary'!C:G,5,FALSE)))
... A79: "monthMovedOut": 1, | B79: =IF(OR(ISNUMBER(SEARCH("{", A79)),ISNUMBER(SEARCH("[", A79))), "", IFERROR(MID(A79, SEARCH("""", A79) +1, SEARCH("""", A79, SEARCH("""",A79) +1) - SEARCH("""", A79) -1), "")) -> monthMovedOut | C79: =IF(B79="", "", VLOOKUP(B79,'API Data Dictionary'!C:J,8,FALSE)) -> 0 | D79: =IF(B79="", "", VLOOKUP(B79,'API Data Dictionary'!C:D,2,FALSE)) -> string ($date-time) | E79: =IF(IF(B79="", "", VLOOKUP(B79,'API Data Dictionary'!C:E,3,FALSE))=0, "", IF(B79="", "", VLOOKUP(B79,'API Data Dictionary'!C:E,3,FALSE))) | F79: =IF(IF(B79="", "", VLOOKUP(B79,'API Data Dictionary'!C:F,4,FALSE))=0, "", IF(B79="", "", VLOOKUP(B79,'API Data Dictionary'!C:F,4,FALSE))) -> DD/MM/YYYY | G79: =IF(IF(B79="", "", VLOOKUP(B79,'API Data Dictionary'!C:G,5,FALSE))=0, "", IF(B79="", "", VLOOKUP(B79,'API Data Dictionary'!C:G,5,FALSE))) -> Start date of self employment, formatted DD/MM/YYYY
A80: "yearMovedOut": 2016 | B80: =IF(OR(ISNUMBER(SEARCH("{", A80)),ISNUMBER(SEARCH("[", A80))), "", IFERROR(MID(A80, SEARCH("""", A80) +1, SEARCH("""", A80, SEARCH("""",A80) +1) - SEARCH("""", A80) -1), "")) -> yearMovedOut | C80: M | D80: =IF(B80="", "", VLOOKUP(B80,'API Data Dictionary'!C:D,2,FALSE)) -> #N/A | E80: =IF(IF(B80="", "", VLOOKUP(B80,'API Data Dictionary'!C:E,3,FALSE))=0, "", IF(B80="", "", VLOOKUP(B80,'API Data Dictionary'!C:E,3,FALSE))) -> #N/A | F80: =IF(IF(B80="", "", VLOOKUP(B80,'API Data Dictionary'!C:F,4,FALSE))=0, "", IF(B80="", "", VLOOKUP(B80,'API Data Dictionary'!C:F,4,FALSE))) -> #N/A | G80: =IF(IF(B80="", "", VLOOKUP(B80,'API Data Dictionary'!C:G,5,FALSE))=0, "", IF(B80="", "", VLOOKUP(B80,'API Data Dictionary'!C:G,5,FALSE))) -> #N/A
A81: }, | B81: =IF(OR(ISNUMBER(SEARCH("{", A81)),ISNUMBER(SEARCH("[", A81))), "", IFERROR(MID(A81, SEARCH("""", A81) +1, SEARCH("""", A81, SEARCH("""",A81) +1) - SEARCH("""", A81) -1), "")) | C81: =IF(B81="", "", VLOOKUP(B81,'API Data Dictionary'!C:J,8,FALSE)) | D81: =IF(B81="", "", VLOOKUP(B81,'API Data Dictionary'!C:D,2,FALSE)) | E81: =IF(IF(B81="", "", VLOOKUP(B81,'API Data Dictionary'!C:E,3,FALSE))=0, "", IF(B81="", "", VLOOKUP(B81,'API Data Dictionary'!C:E,3,FALSE))) | F81: =IF(IF(B81="", "", VLOOKUP(B81,'API Data Dictionary'!C:F,4,FALSE))=0, "", IF(B81="", "", VLOOKUP(B81,'API Data Dictionary'!C:F,4,FALSE))) | G81: =IF(IF(B81="", "", VLOOKUP(B81,'API Data Dictionary'!C:G,5,FALSE))=0, "", IF(B81="", "", VLOOKUP(B81,'API Data Dictionary'!C:G,5,FALSE)))
A82: "residentialDetails": { | B82: =IF(OR(ISNUMBER(SEARCH("{", A82)),ISNUMBER(SEARCH("[", A82))), "", IFERROR(MID(A82, SEARCH("""", A82) +1, SEARCH("""", A82, SEARCH("""",A82) +1) - SEARCH("""", A82) -1), "")) | C82: =IF(B82="", "", VLOOKUP(B82,'API Data Dictionary'!C:J,8,FALSE)) | D82: =IF(B82="", "", VLOOKUP(B82,'API Data Dictionary'!C:D,2,FALSE)) | E82: =IF(IF(B82="", "", VLOOKUP(B82,'API Data Dictionary'!C:E,3,FALSE))=0, "", IF(B82="", "", VLOOKUP(B82,'API Data Dictionary'!C:E,3,FALSE))) | F82: =IF(IF(B82="", "", VLOOKUP(B82,'API Data Dictionary'!C:F,4,FALSE))=0, "", IF(B82="", "", VLOOKUP(B82,'API Data Dictionary'!C:F,4,FALSE))) | G82: =IF(IF(B82="", "", VLOOKUP(B82,'API Data Dictionary'!C:G,5,FALSE))=0, "", IF(B82="", "", VLOOKUP(B82,'API Data Dictionary'!C:G,5,FALSE)))
A83: "currentResidentialStatus": 1, | B83: =IF(OR(ISNUMBER(SEARCH("{", A83)),ISNUMBER(SEARCH("[", A83))), "", IFERROR(MID(A83, SEARCH("""", A83) +1, SEARCH("""", A83, SEARCH("""",A83) +1) - SEARCH("""", A83) -1), "")) -> currentResidentialStatus | C83: =IF(B83="", "", VLOOKUP(B83,'API Data Dictionary'!C:J,8,FALSE)) -> M | D83: =IF(B83="", "", VLOOKUP(B83,'API Data Dictionary'!C:D,2,FALSE)) -> enum - residentStatus | E83: =IF(IF(B83="", "", VLOOKUP(B83,'API Data Dictionary'!C:E,3,FALSE))=0, "", IF(B83="", "", VLOOKUP(B83,'API Data Dictionary'!C:E,3,FALSE))) | F83: =IF(IF(B83="", "", VLOOKUP(B83,'API Data Dictionary'!C:F,4,FALSE))=0, "", IF(B83="", "", VLOOKUP(B83,'API Data Dictionary'!C:F,4,FALSE))) -> Valid Values 1-3 (See enum definition) | G83: =IF(IF(B83="", "", VLOOKUP(B83,'API Data Dictionary'!C:G,5,FALSE))=0, "", IF(B83="", "", VLOOKUP(B83,'API Data Dictionary'!C:G,5,FALSE))) -> The current residential status, e.g. UK Resident
A84: "currentRentAmount": 220.5, | B84: =IF(OR(ISNUMBER(SEARCH("{", A84)),ISNUMBER(SEARCH("[", A84))), "", IFERROR(MID(A84, SEARCH("""", A84) +1, SEARCH("""", A84, SEARCH("""",A84) +1) - SEARCH("""", A84) -1), "")) -> currentRentAmount | C84: =IF(B84="", "", VLOOKUP(B84,'API Data Dictionary'!C:J,8,FALSE)) -> X | D84: =IF(B84="", "", VLOOKUP(B84,'API Data Dictionary'!C:D,2,FALSE)) -> number (double) | E84: =IF(IF(B84="", "", VLOOKUP(B84,'API Data Dictionary'!C:E,3,FALSE))=0, "", IF(B84="", "", VLOOKUP(B84,'API Data Dictionary'!C:E,3,FALSE))) | F84: =IF(IF(B84="", "", VLOOKUP(B84,'API Data Dictionary'!C:F,4,FALSE))=0, "", IF(B84="", "", VLOOKUP(B84,'API Data Dictionary'!C:F,4,FALSE))) -> pattern: ^\d*.\d{0,2}$ | G84: =IF(IF(B84="", "", VLOOKUP(B84,'API Data Dictionary'!C:G,5,FALSE))=0, "", IF(B84="", "", VLOOKUP(B84,'API Data Dictionary'!C:G,5,FALSE))) -> The current rent amount in GBP
A85: "landlordName": "string", | B85: =IF(OR(ISNUMBER(SEARCH("{", A85)),ISNUMBER(SEARCH("[", A85))), "", IFERROR(MID(A85, SEARCH("""", A85) +1, SEARCH("""", A85, SEARCH("""",A85) +1) - SEARCH("""", A85) -1), "")) -> landlordName | C85: =IF(B85="", "", VLOOKUP(B85,'API Data Dictionary'!C:J,8,FALSE)) -> X | D85: =IF(B85="", "", VLOOKUP(B85,'API Data Dictionary'!C:D,2,FALSE)) -> string | E85: =IF(IF(B85="", "", VLOOKUP(B85,'API Data Dictionary'!C:E,3,FALSE))=0, "", IF(B85="", "", VLOOKUP(B85,'API Data Dictionary'!C:E,3,FALSE))) -> 500 | F85: =IF(IF(B85="", "", VLOOKUP(B85,'API Data Dictionary'!C:F,4,FALSE))=0, "", IF(B85="", "", VLOOKUP(B85,'API Data Dictionary'!C:F,4,FALSE))) | G85: =IF(IF(B85="", "", VLOOKUP(B85,'API Data Dictionary'!C:G,5,FALSE))=0, "", IF(B85="", "", VLOOKUP(B85,'API Data Dictionary'!C:G,5,FALSE))) -> Full name of the Landlord
A86: "landlordContactCountryId": 1, | B86: =IF(OR(ISNUMBER(SEARCH("{", A86)),ISNUMBER(SEARCH("[", A86))), "", IFERROR(MID(A86, SEARCH("""", A86) +1, SEARCH("""", A86, SEARCH("""",A86) +1) - SEARCH("""", A86) -1), "")) -> landlordContactCountryId | C86: M | D86: =IF(B86="", "", VLOOKUP(B86,'API Data Dictionary'!C:D,2,FALSE)) -> enum -Country/Location Code | E86: =IF(IF(B86="", "", VLOOKUP(B86,'API Data Dictionary'!C:E,3,FALSE))=0, "", IF(B86="", "", VLOOKUP(B86,'API Data Dictionary'!C:E,3,FALSE))) | F86: =IF(IF(B86="", "", VLOOKUP(B86,'API Data Dictionary'!C:F,4,FALSE))=0, "", IF(B86="", "", VLOOKUP(B86,'API Data Dictionary'!C:F,4,FALSE))) -> Valid Values 1-239 (See enum definition) | G86: =IF(IF(B86="", "", VLOOKUP(B86,'API Data Dictionary'!C:G,5,FALSE))=0, "", IF(B86="", "", VLOOKUP(B86,'API Data Dictionary'!C:G,5,FALSE))) -> The country/location code of the landlord contact phone number
A87: "landlordContactNumber": "01245367891", | B87: =IF(OR(ISNUMBER(SEARCH("{", A87)),ISNUMBER(SEARCH("[", A87))), "", IFERROR(MID(A87, SEARCH("""", A87) +1, SEARCH("""", A87, SEARCH("""",A87) +1) - SEARCH("""", A87) -1), "")) -> landlordContactNumber | C87: =IF(B87="", "", VLOOKUP(B87,'API Data Dictionary'!C:J,8,FALSE)) -> X | D87: =IF(B87="", "", VLOOKUP(B87,'API Data Dictionary'!C:D,2,FALSE)) -> string | E87: =IF(IF(B87="", "", VLOOKUP(B87,'API Data Dictionary'!C:E,3,FALSE))=0, "", IF(B87="", "", VLOOKUP(B87,'API Data Dictionary'!C:E,3,FALSE))) -> 15 | F87: =IF(IF(B87="", "", VLOOKUP(B87,'API Data Dictionary'!C:F,4,FALSE))=0, "", IF(B87="", "", VLOOKUP(B87,'API Data Dictionary'!C:F,4,FALSE))) -> pattern: ^(\d{11})$ | G87: =IF(IF(B87="", "", VLOOKUP(B87,'API Data Dictionary'!C:G,5,FALSE))=0, "", IF(B87="", "", VLOOKUP(B87,'API Data Dictionary'!C:G,5,FALSE))) -> The Landlords contact Telephone number
A88: "landlordEmail": "paxoy72496@cmeinbox.com", | B88: =IF(OR(ISNUMBER(SEARCH("{", A88)),ISNUMBER(SEARCH("[", A88))), "", IFERROR(MID(A88, SEARCH("""", A88) +1, SEARCH("""", A88, SEARCH("""",A88) +1) - SEARCH("""", A88) -1), "")) -> landlordEmail | C88: =IF(B88="", "", VLOOKUP(B88,'API Data Dictionary'!C:J,8,FALSE)) -> X | D88: =IF(B88="", "", VLOOKUP(B88,'API Data Dictionary'!C:D,2,FALSE)) -> string ($email) | E88: =IF(IF(B88="", "", VLOOKUP(B88,'API Data Dictionary'!C:E,3,FALSE))=0, "", IF(B88="", "", VLOOKUP(B88,'API Data Dictionary'!C:E,3,FALSE))) -> 200 | F88: =IF(IF(B88="", "", VLOOKUP(B88,'API Data Dictionary'!C:F,4,FALSE))=0, "", IF(B88="", "", VLOOKUP(B88,'API Data Dictionary'!C:F,4,FALSE))) -> pattern: ^(?!.*\.\.)(?!.*\\_\\_)(?!.*\-\-)[a-zA-Z0-9][-a-zA-Z0-9._]+[a-zA-Z0-9]@([-a-zA-Z0-9]+.)+[a-zA-Z]{2,5}$ | G88: =IF(IF(B88="", "", VLOOKUP(B88,'API Data Dictionary'!C:G,5,FALSE))=0, "", IF(B88="", "", VLOOKUP(B88,'API Data Dictionary'!C:G,5,FALSE))) -> The landlords email address
A89: "landlordAddress": { | B89: =IF(OR(ISNUMBER(SEARCH("{", A89)),ISNUMBER(SEARCH("[", A89))), "", IFERROR(MID(A89, SEARCH("""", A89) +1, SEARCH("""", A89, SEARCH("""",A89) +1) - SEARCH("""", A89) -1), "")) | C89: =IF(B89="", "", VLOOKUP(B89,'API Data Dictionary'!C:J,8,FALSE)) | D89: =IF(B89="", "", VLOOKUP(B89,'API Data Dictionary'!C:D,2,FALSE)) | E89: =IF(IF(B89="", "", VLOOKUP(B89,'API Data Dictionary'!C:E,3,FALSE))=0, "", IF(B89="", "", VLOOKUP(B89,'API Data Dictionary'!C:E,3,FALSE))) | F89: =IF(IF(B89="", "", VLOOKUP(B89,'API Data Dictionary'!C:F,4,FALSE))=0, "", IF(B89="", "", VLOOKUP(B89,'API Data Dictionary'!C:F,4,FALSE))) | G89: =IF(IF(B89="", "", VLOOKUP(B89,'API Data Dictionary'!C:G,5,FALSE))=0, "", IF(B89="", "", VLOOKUP(B89,'API Data Dictionary'!C:G,5,FALSE)))
A90: "houseNumber": "660", | B90: =IF(OR(ISNUMBER(SEARCH("{", A90)),ISNUMBER(SEARCH("[", A90))), "", IFERROR(MID(A90, SEARCH("""", A90) +1, SEARCH("""", A90, SEARCH("""",A90) +1) - SEARCH("""", A90) -1), "")) -> houseNumber | C90: =IF(B90="", "", VLOOKUP(B90,'API Data Dictionary'!C:J,8,FALSE)) -> X | D90: =IF(B90="", "", VLOOKUP(B90,'API Data Dictionary'!C:D,2,FALSE)) -> string | E90: =IF(IF(B90="", "", VLOOKUP(B90,'API Data Dictionary'!C:E,3,FALSE))=0, "", IF(B90="", "", VLOOKUP(B90,'API Data Dictionary'!C:E,3,FALSE))) -> 100 | F90: =IF(IF(B90="", "", VLOOKUP(B90,'API Data Dictionary'!C:F,4,FALSE))=0, "", IF(B90="", "", VLOOKUP(B90,'API Data Dictionary'!C:F,4,FALSE))) | G90: =IF(IF(B90="", "", VLOOKUP(B90,'API Data Dictionary'!C:G,5,FALSE))=0, "", IF(B90="", "", VLOOKUP(B90,'API Data Dictionary'!C:G,5,FALSE))) -> The number of the property, mandatory OR pair with House name field
A91: "houseName": "Warwick", | B91: =IF(OR(ISNUMBER(SEARCH("{", A91)),ISNUMBER(SEARCH("[", A91))), "", IFERROR(MID(A91, SEARCH("""", A91) +1, SEARCH("""", A91, SEARCH("""",A91) +1) - SEARCH("""", A91) -1), "")) -> houseName | C91: =IF(B91="", "", VLOOKUP(B91,'API Data Dictionary'!C:J,8,FALSE)) -> X | D91: =IF(B91="", "", VLOOKUP(B91,'API Data Dictionary'!C:D,2,FALSE)) -> string | E91: =IF(IF(B91="", "", VLOOKUP(B91,'API Data Dictionary'!C:E,3,FALSE))=0, "", IF(B91="", "", VLOOKUP(B91,'API Data Dictionary'!C:E,3,FALSE))) -> 100 | F91: =IF(IF(B91="", "", VLOOKUP(B91,'API Data Dictionary'!C:F,4,FALSE))=0, "", IF(B91="", "", VLOOKUP(B91,'API Data Dictionary'!C:F,4,FALSE))) | G91: =IF(IF(B91="", "", VLOOKUP(B91,'API Data Dictionary'!C:G,5,FALSE))=0, "", IF(B91="", "", VLOOKUP(B91,'API Data Dictionary'!C:G,5,FALSE))) -> The name of the property, mandatory OR pair with House number field
A92: "addressLine1": "111 Lee Crescent North", | B92: =IF(OR(ISNUMBER(SEARCH("{", A92)),ISNUMBER(SEARCH("[", A92))), "", IFERROR(MID(A92, SEARCH("""", A92) +1, SEARCH("""", A92, SEARCH("""",A92) +1) - SEARCH("""", A92) -1), "")) -> addressLine1 | C92: =IF(B92="", "", VLOOKUP(B92,'API Data Dictionary'!C:J,8,FALSE)) -> M | D92: =IF(B92="", "", VLOOKUP(B92,'API Data Dictionary'!C:D,2,FALSE)) -> string | E92: =IF(IF(B92="", "", VLOOKUP(B92,'API Data Dictionary'!C:E,3,FALSE))=0, "", IF(B92="", "", VLOOKUP(B92,'API Data Dictionary'!C:E,3,FALSE))) -> 100 | F92: =IF(IF(B92="", "", VLOOKUP(B92,'API Data Dictionary'!C:F,4,FALSE))=0, "", IF(B92="", "", VLOOKUP(B92,'API Data Dictionary'!C:F,4,FALSE))) | G92: =IF(IF(B92="", "", VLOOKUP(B92,'API Data Dictionary'!C:G,5,FALSE))=0, "", IF(B92="", "", VLOOKUP(B92,'API Data Dictionary'!C:G,5,FALSE))) -> The first line of the property address
A93: "addressLine2": "Bridge of Don", | B93: =IF(OR(ISNUMBER(SEARCH("{", A93)),ISNUMBER(SEARCH("[", A93))), "", IFERROR(MID(A93, SEARCH("""", A93) +1, SEARCH("""", A93, SEARCH("""",A93) +1) - SEARCH("""", A93) -1), "")) -> addressLine2 | C93: =IF(B93="", "", VLOOKUP(B93,'API Data Dictionary'!C:J,8,FALSE)) -> X | D93: =IF(B93="", "", VLOOKUP(B93,'API Data Dictionary'!C:D,2,FALSE)) -> string | E93: =IF(IF(B93="", "", VLOOKUP(B93,'API Data Dictionary'!C:E,3,FALSE))=0, "", IF(B93="", "", VLOOKUP(B93,'API Data Dictionary'!C:E,3,FALSE))) -> 100 | F93: =IF(IF(B93="", "", VLOOKUP(B93,'API Data Dictionary'!C:F,4,FALSE))=0, "", IF(B93="", "", VLOOKUP(B93,'API Data Dictionary'!C:F,4,FALSE))) | G93: =IF(IF(B93="", "", VLOOKUP(B93,'API Data Dictionary'!C:G,5,FALSE))=0, "", IF(B93="", "", VLOOKUP(B93,'API Data Dictionary'!C:G,5,FALSE))) -> The second line of the property address
A94: "town": "ABERDEEN", | B94: =IF(OR(ISNUMBER(SEARCH("{", A94)),ISNUMBER(SEARCH("[", A94))), "", IFERROR(MID(A94, SEARCH("""", A94) +1, SEARCH("""", A94, SEARCH("""",A94) +1) - SEARCH("""", A94) -1), "")) -> town | C94: =IF(B94="", "", VLOOKUP(B94,'API Data Dictionary'!C:J,8,FALSE)) -> M | D94: =IF(B94="", "", VLOOKUP(B94,'API Data Dictionary'!C:D,2,FALSE)) -> string | E94: =IF(IF(B94="", "", VLOOKUP(B94,'API Data Dictionary'!C:E,3,FALSE))=0, "", IF(B94="", "", VLOOKUP(B94,'API Data Dictionary'!C:E,3,FALSE))) -> 50 | F94: =IF(IF(B94="", "", VLOOKUP(B94,'API Data Dictionary'!C:F,4,FALSE))=0, "", IF(B94="", "", VLOOKUP(B94,'API Data Dictionary'!C:F,4,FALSE))) | G94: =IF(IF(B94="", "", VLOOKUP(B94,'API Data Dictionary'!C:G,5,FALSE))=0, "", IF(B94="", "", VLOOKUP(B94,'API Data Dictionary'!C:G,5,FALSE))) -> The town in which the property exists
A95: "country": 1, | B95: =IF(OR(ISNUMBER(SEARCH("{", A95)),ISNUMBER(SEARCH("[", A95))), "", IFERROR(MID(A95, SEARCH("""", A95) +1, SEARCH("""", A95, SEARCH("""",A95) +1) - SEARCH("""", A95) -1), "")) -> country | C95: =IF(B95="", "", VLOOKUP(B95,'API Data Dictionary'!C:J,8,FALSE)) -> M | D95: =IF(B95="", "", VLOOKUP(B95,'API Data Dictionary'!C:D,2,FALSE)) -> enum -Country/Location Code | E95: =IF(IF(B95="", "", VLOOKUP(B95,'API Data Dictionary'!C:E,3,FALSE))=0, "", IF(B95="", "", VLOOKUP(B95,'API Data Dictionary'!C:E,3,FALSE))) | F95: =IF(IF(B95="", "", VLOOKUP(B95,'API Data Dictionary'!C:F,4,FALSE))=0, "", IF(B95="", "", VLOOKUP(B95,'API Data Dictionary'!C:F,4,FALSE))) -> Valid Values 1-239 (See enum definition) | G95: =IF(IF(B95="", "", VLOOKUP(B95,'API Data Dictionary'!C:G,5,FALSE))=0, "", IF(B95="", "", VLOOKUP(B95,'API Data Dictionary'!C:G,5,FALSE))) -> The Country code from the enum list, e.g. France
A96: "postcode": "AB22 8FQ" | B96: =IF(OR(ISNUMBER(SEARCH("{", A96)),ISNUMBER(SEARCH("[", A96))), "", IFERROR(MID(A96, SEARCH("""", A96) +1, SEARCH("""", A96, SEARCH("""",A96) +1) - SEARCH("""", A96) -1), "")) -> postcode | C96: =IF(B96="", "", VLOOKUP(B96,'API Data Dictionary'!C:J,8,FALSE)) -> M | D96: =IF(B96="", "", VLOOKUP(B96,'API Data Dictionary'!C:D,2,FALSE)) -> string | E96: =IF(IF(B96="", "", VLOOKUP(B96,'API Data Dictionary'!C:E,3,FALSE))=0, "", IF(B96="", "", VLOOKUP(B96,'API Data Dictionary'!C:E,3,FALSE))) -> 50 | F96: =IF(IF(B96="", "", VLOOKUP(B96,'API Data Dictionary'!C:F,4,FALSE))=0, "", IF(B96="", "", VLOOKUP(B96,'API Data Dictionary'!C:F,4,FALSE))) | G96: =IF(IF(B96="", "", VLOOKUP(B96,'API Data Dictionary'!C:G,5,FALSE))=0, "", IF(B96="", "", VLOOKUP(B96,'API Data Dictionary'!C:G,5,FALSE))) -> the postcode of the property
A97: } | B97: =IF(OR(ISNUMBER(SEARCH("{", A97)),ISNUMBER(SEARCH("[", A97))), "", IFERROR(MID(A97, SEARCH("""", A97) +1, SEARCH("""", A97, SEARCH("""",A97) +1) - SEARCH("""", A97) -1), "")) | C97: =IF(B97="", "", VLOOKUP(B97,'API Data Dictionary'!C:J,8,FALSE)) | D97: =IF(B97="", "", VLOOKUP(B97,'API Data Dictionary'!C:D,2,FALSE)) | E97: =IF(IF(B97="", "", VLOOKUP(B97,'API Data Dictionary'!C:E,3,FALSE))=0, "", IF(B97="", "", VLOOKUP(B97,'API Data Dictionary'!C:E,3,FALSE))) | F97: =IF(IF(B97="", "", VLOOKUP(B97,'API Data Dictionary'!C:F,4,FALSE))=0, "", IF(B97="", "", VLOOKUP(B97,'API Data Dictionary'!C:F,4,FALSE))) | G97: =IF(IF(B97="", "", VLOOKUP(B97,'API Data Dictionary'!C:G,5,FALSE))=0, "", IF(B97="", "", VLOOKUP(B97,'API Data Dictionary'!C:G,5,FALSE)))
A98: }, | B98: =IF(OR(ISNUMBER(SEARCH("{", A98)),ISNUMBER(SEARCH("[", A98))), "", IFERROR(MID(A98, SEARCH("""", A98) +1, SEARCH("""", A98, SEARCH("""",A98) +1) - SEARCH("""", A98) -1), "")) | C98: =IF(B98="", "", VLOOKUP(B98,'API Data Dictionary'!C:J,8,FALSE)) | D98: =IF(B98="", "", VLOOKUP(B98,'API Data Dictionary'!C:D,2,FALSE)) | E98: =IF(IF(B98="", "", VLOOKUP(B98,'API Data Dictionary'!C:E,3,FALSE))=0, "", IF(B98="", "", VLOOKUP(B98,'API Data Dictionary'!C:E,3,FALSE))) | F98: =IF(IF(B98="", "", VLOOKUP(B98,'API Data Dictionary'!C:F,4,FALSE))=0, "", IF(B98="", "", VLOOKUP(B98,'API Data Dictionary'!C:F,4,FALSE))) | G98: =IF(IF(B98="", "", VLOOKUP(B98,'API Data Dictionary'!C:G,5,FALSE))=0, "", IF(B98="", "", VLOOKUP(B98,'API Data Dictionary'!C:G,5,FALSE)))
... A126: "employmentEmployeeNumber": "ABCD1234", | B126: =IF(OR(ISNUMBER(SEARCH("{", A126)),ISNUMBER(SEARCH("[", A126))), "", IFERROR(MID(A126, SEARCH("""", A126) +1, SEARCH("""", A126, SEARCH("""",A126) +1) - SEARCH("""", A126) -1), "")) -> employmentEmployeeNumber | C126: =IF(B126="", "", VLOOKUP(B126,'API Data Dictionary'!C:J,8,FALSE)) -> X | D126: =IF(B126="", "", VLOOKUP(B126,'API Data Dictionary'!C:D,2,FALSE)) -> string | E126: =IF(IF(B126="", "", VLOOKUP(B126,'API Data Dictionary'!C:E,3,FALSE))=0, "", IF(B126="", "", VLOOKUP(B126,'API Data Dictionary'!C:E,3,FALSE))) -> 100 | F126: =IF(IF(B126="", "", VLOOKUP(B126,'API Data Dictionary'!C:F,4,FALSE))=0, "", IF(B126="", "", VLOOKUP(B126,'API Data Dictionary'!C:F,4,FALSE))) | G126: =IF(IF(B126="", "", VLOOKUP(B126,'API Data Dictionary'!C:G,5,FALSE))=0, "", IF(B126="", "", VLOOKUP(B126,'API Data Dictionary'!C:G,5,FALSE))) -> Employee number from the company the person is employed by
A127: "paymentScheduleId": 1, | B127: =IF(OR(ISNUMBER(SEARCH("{", A127)),ISNUMBER(SEARCH("[", A127))), "", IFERROR(MID(A127, SEARCH("""", A127) +1, SEARCH("""", A127, SEARCH("""",A127) +1) - SEARCH("""", A127) -1), "")) -> paymentScheduleId | C127: M | D127: =IF(B127="", "", VLOOKUP(B127,'API Data Dictionary'!C:D,2,FALSE)) -> enum - Income Term | E127: =IF(IF(B127="", "", VLOOKUP(B127,'API Data Dictionary'!C:E,3,FALSE))=0, "", IF(B127="", "", VLOOKUP(B127,'API Data Dictionary'!C:E,3,FALSE))) | F127: =IF(IF(B127="", "", VLOOKUP(B127,'API Data Dictionary'!C:F,4,FALSE))=0, "", IF(B127="", "", VLOOKUP(B127,'API Data Dictionary'!C:F,4,FALSE))) -> Valid Values 1-4 (See enum definition) | G127: =IF(IF(B127="", "", VLOOKUP(B127,'API Data Dictionary'!C:G,5,FALSE))=0, "", IF(B127="", "", VLOOKUP(B127,'API Data Dictionary'!C:G,5,FALSE))) -> The schedule of the payments
A128: "employmentRefereeName": "Georgia", | B128: =IF(OR(ISNUMBER(SEARCH("{", A128)),ISNUMBER(SEARCH("[", A128))), "", IFERROR(MID(A128, SEARCH("""", A128) +1, SEARCH("""", A128, SEARCH("""",A128) +1) - SEARCH("""", A128) -1), "")) -> employmentRefereeName | C128: =IF(B128="", "", VLOOKUP(B128,'API Data Dictionary'!C:J,8,FALSE)) -> X | D128: =IF(B128="", "", VLOOKUP(B128,'API Data Dictionary'!C:D,2,FALSE)) -> string | E128: =IF(IF(B128="", "", VLOOKUP(B128,'API Data Dictionary'!C:E,3,FALSE))=0, "", IF(B128="", "", VLOOKUP(B128,'API Data Dictionary'!C:E,3,FALSE))) -> 100 | F128: =IF(IF(B128="", "", VLOOKUP(B128,'API Data Dictionary'!C:F,4,FALSE))=0, "", IF(B128="", "", VLOOKUP(B128,'API Data Dictionary'!C:F,4,FALSE))) | G128: =IF(IF(B128="", "", VLOOKUP(B128,'API Data Dictionary'!C:G,5,FALSE))=0, "", IF(B128="", "", VLOOKUP(B128,'API Data Dictionary'!C:G,5,FALSE))) -> The fulll name of the employment referee
A129: "employmentRefereeContactCountryID": 1, | B129: =IF(OR(ISNUMBER(SEARCH("{", A129)),ISNUMBER(SEARCH("[", A129))), "", IFERROR(MID(A129, SEARCH("""", A129) +1, SEARCH("""", A129, SEARCH("""",A129) +1) - SEARCH("""", A129) -1), "")) -> employmentRefereeContactCountryID | C129: =IF(B129="", "", VLOOKUP(B129,'API Data Dictionary'!C:J,8,FALSE)) -> X | D129: =IF(B129="", "", VLOOKUP(B129,'API Data Dictionary'!C:D,2,FALSE)) -> enum -Country/Location Code | E129: =IF(IF(B129="", "", VLOOKUP(B129,'API Data Dictionary'!C:E,3,FALSE))=0, "", IF(B129="", "", VLOOKUP(B129,'API Data Dictionary'!C:E,3,FALSE))) | F129: =IF(IF(B129="", "", VLOOKUP(B129,'API Data Dictionary'!C:F,4,FALSE))=0, "", IF(B129="", "", VLOOKUP(B129,'API Data Dictionary'!C:F,4,FALSE))) -> Valid Values 1-239 (See enum definition) | G129: =IF(IF(B129="", "", VLOOKUP(B129,'API Data Dictionary'!C:G,5,FALSE))=0, "", IF(B129="", "", VLOOKUP(B129,'API Data Dictionary'!C:G,5,FALSE))) -> The country/location code of the employment referee contact phone number
A130: "employmentRefereeContactNumber": "01263458971", | B130: =IF(OR(ISNUMBER(SEARCH("{", A130)),ISNUMBER(SEARCH("[", A130))), "", IFERROR(MID(A130, SEARCH("""", A130) +1, SEARCH("""", A130, SEARCH("""",A130) +1) - SEARCH("""", A130) -1), "")) -> employmentRefereeContactNumber | C130: =IF(B130="", "", VLOOKUP(B130,'API Data Dictionary'!C:J,8,FALSE)) -> X | D130: =IF(B130="", "", VLOOKUP(B130,'API Data Dictionary'!C:D,2,FALSE)) -> string | E130: =IF(IF(B130="", "", VLOOKUP(B130,'API Data Dictionary'!C:E,3,FALSE))=0, "", IF(B130="", "", VLOOKUP(B130,'API Data Dictionary'!C:E,3,FALSE))) -> 15 | F130: =IF(IF(B130="", "", VLOOKUP(B130,'API Data Dictionary'!C:F,4,FALSE))=0, "", IF(B130="", "", VLOOKUP(B130,'API Data Dictionary'!C:F,4,FALSE))) -> pattern: ^(\d{11})$ | G130: =IF(IF(B130="", "", VLOOKUP(B130,'API Data Dictionary'!C:G,5,FALSE))=0, "", IF(B130="", "", VLOOKUP(B130,'API Data Dictionary'!C:G,5,FALSE))) -> The emplyment referee contact phone number
A131: "employmentRefereeEmail": "higiso7093@themesw.com", | B131: =IF(OR(ISNUMBER(SEARCH("{", A131)),ISNUMBER(SEARCH("[", A131))), "", IFERROR(MID(A131, SEARCH("""", A131) +1, SEARCH("""", A131, SEARCH("""",A131) +1) - SEARCH("""", A131) -1), "")) -> employmentRefereeEmail | C131: =IF(B131="", "", VLOOKUP(B131,'API Data Dictionary'!C:J,8,FALSE)) -> X | D131: =IF(B131="", "", VLOOKUP(B131,'API Data Dictionary'!C:D,2,FALSE)) -> string ($email) | E131: =IF(IF(B131="", "", VLOOKUP(B131,'API Data Dictionary'!C:E,3,FALSE))=0, "", IF(B131="", "", VLOOKUP(B131,'API Data Dictionary'!C:E,3,FALSE))) -> 200 | F131: =IF(IF(B131="", "", VLOOKUP(B131,'API Data Dictionary'!C:F,4,FALSE))=0, "", IF(B131="", "", VLOOKUP(B131,'API Data Dictionary'!C:F,4,FALSE))) -> pattern: ^(?!.*\.\.)(?!.*\\_\\_)(?!.*\-\-)[a-zA-Z0-9][-a-zA-Z0-9._]+[a-zA-Z0-9]@([-a-zA-Z0-9]+.)+[a-zA-Z]{2,5}$ | G131: =IF(IF(B131="", "", VLOOKUP(B131,'API Data Dictionary'!C:G,5,FALSE))=0, "", IF(B131="", "", VLOOKUP(B131,'API Data Dictionary'!C:G,5,FALSE))) -> The email address of the referee
A132: "employmentRefereePosition": "Manager", | B132: =IF(OR(ISNUMBER(SEARCH("{", A132)),ISNUMBER(SEARCH("[", A132))), "", IFERROR(MID(A132, SEARCH("""", A132) +1, SEARCH("""", A132, SEARCH("""",A132) +1) - SEARCH("""", A132) -1), "")) -> employmentRefereePosition | C132: =IF(B132="", "", VLOOKUP(B132,'API Data Dictionary'!C:J,8,FALSE)) -> X | D132: =IF(B132="", "", VLOOKUP(B132,'API Data Dictionary'!C:D,2,FALSE)) -> string | E132: =IF(IF(B132="", "", VLOOKUP(B132,'API Data Dictionary'!C:E,3,FALSE))=0, "", IF(B132="", "", VLOOKUP(B132,'API Data Dictionary'!C:E,3,FALSE))) -> 100 | F132: =IF(IF(B132="", "", VLOOKUP(B132,'API Data Dictionary'!C:F,4,FALSE))=0, "", IF(B132="", "", VLOOKUP(B132,'API Data Dictionary'!C:F,4,FALSE))) | G132: =IF(IF(B132="", "", VLOOKUP(B132,'API Data Dictionary'!C:G,5,FALSE))=0, "", IF(B132="", "", VLOOKUP(B132,'API Data Dictionary'!C:G,5,FALSE))) -> The position of the employment referee in the company
A133: "addressLine1": "3 Broadgates Avenue", | B133: =IF(OR(ISNUMBER(SEARCH("{", A133)),ISNUMBER(SEARCH("[", A133))), "", IFERROR(MID(A133, SEARCH("""", A133) +1, SEARCH("""", A133, SEARCH("""",A133) +1) - SEARCH("""", A133) -1), "")) -> addressLine1 | C133: M | D133: =IF(B133="", "", VLOOKUP(B133,'API Data Dictionary'!C:D,2,FALSE)) -> string | E133: =IF(IF(B133="", "", VLOOKUP(B133,'API Data Dictionary'!C:E,3,FALSE))=0, "", IF(B133="", "", VLOOKUP(B133,'API Data Dictionary'!C:E,3,FALSE))) -> 100 | F133: =IF(IF(B133="", "", VLOOKUP(B133,'API Data Dictionary'!C:F,4,FALSE))=0, "", IF(B133="", "", VLOOKUP(B133,'API Data Dictionary'!C:F,4,FALSE))) | G133: =IF(IF(B133="", "", VLOOKUP(B133,'API Data Dictionary'!C:G,5,FALSE))=0, "", IF(B133="", "", VLOOKUP(B133,'API Data Dictionary'!C:G,5,FALSE))) -> The first line of the property address
A134: "addressLine2": "Acocks Green", | B134: =IF(OR(ISNUMBER(SEARCH("{", A134)),ISNUMBER(SEARCH("[", A134))), "", IFERROR(MID(A134, SEARCH("""", A134) +1, SEARCH("""", A134, SEARCH("""",A134) +1) - SEARCH("""", A134) -1), "")) -> addressLine2 | C134: =IF(B134="", "", VLOOKUP(B134,'API Data Dictionary'!C:J,8,FALSE)) -> X | D134: =IF(B134="", "", VLOOKUP(B134,'API Data Dictionary'!C:D,2,FALSE)) -> string | E134: =IF(IF(B134="", "", VLOOKUP(B134,'API Data Dictionary'!C:E,3,FALSE))=0, "", IF(B134="", "", VLOOKUP(B134,'API Data Dictionary'!C:E,3,FALSE))) -> 100 | F134: =IF(IF(B134="", "", VLOOKUP(B134,'API Data Dictionary'!C:F,4,FALSE))=0, "", IF(B134="", "", VLOOKUP(B134,'API Data Dictionary'!C:F,4,FALSE))) | G134: =IF(IF(B134="", "", VLOOKUP(B134,'API Data Dictionary'!C:G,5,FALSE))=0, "", IF(B134="", "", VLOOKUP(B134,'API Data Dictionary'!C:G,5,FALSE))) -> The second line of the property address
A135: "city": "BIRMINGHAM", | B135: =IF(OR(ISNUMBER(SEARCH("{", A135)),ISNUMBER(SEARCH("[", A135))), "", IFERROR(MID(A135, SEARCH("""", A135) +1, SEARCH("""", A135, SEARCH("""",A135) +1) - SEARCH("""", A135) -1), "")) -> city | C135: =IF(B135="", "", VLOOKUP(B135,'API Data Dictionary'!C:J,8,FALSE)) -> X | D135: =IF(B135="", "", VLOOKUP(B135,'API Data Dictionary'!C:D,2,FALSE)) -> string | E135: =IF(IF(B135="", "", VLOOKUP(B135,'API Data Dictionary'!C:E,3,FALSE))=0, "", IF(B135="", "", VLOOKUP(B135,'API Data Dictionary'!C:E,3,FALSE))) -> 100 | F135: =IF(IF(B135="", "", VLOOKUP(B135,'API Data Dictionary'!C:F,4,FALSE))=0, "", IF(B135="", "", VLOOKUP(B135,'API Data Dictionary'!C:F,4,FALSE))) | G135: =IF(IF(B135="", "", VLOOKUP(B135,'API Data Dictionary'!C:G,5,FALSE))=0, "", IF(B135="", "", VLOOKUP(B135,'API Data Dictionary'!C:G,5,FALSE))) -> The town in which the property exists
A136: "postCode": "B27 6PX", | B136: =IF(OR(ISNUMBER(SEARCH("{", A136)),ISNUMBER(SEARCH("[", A136))), "", IFERROR(MID(A136, SEARCH("""", A136) +1, SEARCH("""", A136, SEARCH("""",A136) +1) - SEARCH("""", A136) -1), "")) -> postCode | C136: =IF(B136="", "", VLOOKUP(B136,'API Data Dictionary'!C:J,8,FALSE)) -> M | D136: =IF(B136="", "", VLOOKUP(B136,'API Data Dictionary'!C:D,2,FALSE)) -> string | E136: =IF(IF(B136="", "", VLOOKUP(B136,'API Data Dictionary'!C:E,3,FALSE))=0, "", IF(B136="", "", VLOOKUP(B136,'API Data Dictionary'!C:E,3,FALSE))) -> 50 | F136: =IF(IF(B136="", "", VLOOKUP(B136,'API Data Dictionary'!C:F,4,FALSE))=0, "", IF(B136="", "", VLOOKUP(B136,'API Data Dictionary'!C:F,4,FALSE))) | G136: =IF(IF(B136="", "", VLOOKUP(B136,'API Data Dictionary'!C:G,5,FALSE))=0, "", IF(B136="", "", VLOOKUP(B136,'API Data Dictionary'!C:G,5,FALSE))) -> the postcode of the property
A137: "employmentTypeId": 1, | B137: =IF(OR(ISNUMBER(SEARCH("{", A137)),ISNUMBER(SEARCH("[", A137))), "", IFERROR(MID(A137, SEARCH("""", A137) +1, SEARCH("""", A137, SEARCH("""",A137) +1) - SEARCH("""", A137) -1), "")) -> employmentTypeId | C137: =IF(B137="", "", VLOOKUP(B137,'API Data Dictionary'!C:J,8,FALSE)) -> X | D137: =IF(B137="", "", VLOOKUP(B137,'API Data Dictionary'!C:D,2,FALSE)) -> enum - employmentTypeId | E137: =IF(IF(B137="", "", VLOOKUP(B137,'API Data Dictionary'!C:E,3,FALSE))=0, "", IF(B137="", "", VLOOKUP(B137,'API Data Dictionary'!C:E,3,FALSE))) | F137: =IF(IF(B137="", "", VLOOKUP(B137,'API Data Dictionary'!C:F,4,FALSE))=0, "", IF(B137="", "", VLOOKUP(B137,'API Data Dictionary'!C:F,4,FALSE))) -> Valid Values 1-4 (See enum definition) | G137: =IF(IF(B137="", "", VLOOKUP(B137,'API Data Dictionary'!C:G,5,FALSE))=0, "", IF(B137="", "", VLOOKUP(B137,'API Data Dictionary'!C:G,5,FALSE))) -> Employment Type from the enum lists, e.g. permenant full time
A138: "employmentZeroHourContract": false, | B138: =IF(OR(ISNUMBER(SEARCH("{", A138)),ISNUMBER(SEARCH("[", A138))), "", IFERROR(MID(A138, SEARCH("""", A138) +1, SEARCH("""", A138, SEARCH("""",A138) +1) - SEARCH("""", A138) -1), "")) -> employmentZeroHourContract | C138: =IF(B138="", "", VLOOKUP(B138,'API Data Dictionary'!C:J,8,FALSE)) -> X | D138: =IF(B138="", "", VLOOKUP(B138,'API Data Dictionary'!C:D,2,FALSE)) -> boolean | E138: =IF(IF(B138="", "", VLOOKUP(B138,'API Data Dictionary'!C:E,3,FALSE))=0, "", IF(B138="", "", VLOOKUP(B138,'API Data Dictionary'!C:E,3,FALSE))) | F138: =IF(IF(B138="", "", VLOOKUP(B138,'API Data Dictionary'!C:F,4,FALSE))=0, "", IF(B138="", "", VLOOKUP(B138,'API Data Dictionary'!C:F,4,FALSE))) | G138: =IF(IF(B138="", "", VLOOKUP(B138,'API Data Dictionary'!C:G,5,FALSE))=0, "", IF(B138="", "", VLOOKUP(B138,'API Data Dictionary'!C:G,5,FALSE))) -> Denotes if emplyed on a zero hour contract
A139: "industryType": 1 | B139: =IF(OR(ISNUMBER(SEARCH("{", A139)),ISNUMBER(SEARCH("[", A139))), "", IFERROR(MID(A139, SEARCH("""", A139) +1, SEARCH("""", A139, SEARCH("""",A139) +1) - SEARCH("""", A139) -1), "")) -> industryType | C139: =IF(B139="", "", VLOOKUP(B139,'API Data Dictionary'!C:J,8,FALSE)) -> 0 | D139: =IF(B139="", "", VLOOKUP(B139,'API Data Dictionary'!C:D,2,FALSE)) -> enum - industry type | E139: =IF(IF(B139="", "", VLOOKUP(B139,'API Data Dictionary'!C:E,3,FALSE))=0, "", IF(B139="", "", VLOOKUP(B139,'API Data Dictionary'!C:E,3,FALSE))) | F139: =IF(IF(B139="", "", VLOOKUP(B139,'API Data Dictionary'!C:F,4,FALSE))=0, "", IF(B139="", "", VLOOKUP(B139,'API Data Dictionary'!C:F,4,FALSE))) | G139: =IF(IF(B139="", "", VLOOKUP(B139,'API Data Dictionary'!C:G,5,FALSE))=0, "", IF(B139="", "", VLOOKUP(B139,'API Data Dictionary'!C:G,5,FALSE))) -> Type of industry
A140: }, | B140: =IF(OR(ISNUMBER(SEARCH("{", A140)),ISNUMBER(SEARCH("[", A140))), "", IFERROR(MID(A140, SEARCH("""", A140) +1, SEARCH("""", A140, SEARCH("""",A140) +1) - SEARCH("""", A140) -1), "")) | C140: =IF(B140="", "", VLOOKUP(B140,'API Data Dictionary'!C:J,8,FALSE)) | D140: =IF(B140="", "", VLOOKUP(B140,'API Data Dictionary'!C:D,2,FALSE)) | E140: =IF(IF(B140="", "", VLOOKUP(B140,'API Data Dictionary'!C:E,3,FALSE))=0, "", IF(B140="", "", VLOOKUP(B140,'API Data Dictionary'!C:E,3,FALSE))) | F140: =IF(IF(B140="", "", VLOOKUP(B140,'API Data Dictionary'!C:F,4,FALSE))=0, "", IF(B140="", "", VLOOKUP(B140,'API Data Dictionary'!C:F,4,FALSE))) | G140: =IF(IF(B140="", "", VLOOKUP(B140,'API Data Dictionary'!C:G,5,FALSE))=0, "", IF(B140="", "", VLOOKUP(B140,'API Data Dictionary'!C:G,5,FALSE)))
A141: "selfEmployed": { | B141: =IF(OR(ISNUMBER(SEARCH("{", A141)),ISNUMBER(SEARCH("[", A141))), "", IFERROR(MID(A141, SEARCH("""", A141) +1, SEARCH("""", A141, SEARCH("""",A141) +1) - SEARCH("""", A141) -1), "")) | C141: =IF(B141="", "", VLOOKUP(B141,'API Data Dictionary'!C:J,8,FALSE)) | D141: =IF(B141="", "", VLOOKUP(B141,'API Data Dictionary'!C:D,2,FALSE)) | E141: =IF(IF(B141="", "", VLOOKUP(B141,'API Data Dictionary'!C:E,3,FALSE))=0, "", IF(B141="", "", VLOOKUP(B141,'API Data Dictionary'!C:E,3,FALSE))) | F141: =IF(IF(B141="", "", VLOOKUP(B141,'API Data Dictionary'!C:F,4,FALSE))=0, "", IF(B141="", "", VLOOKUP(B141,'API Data Dictionary'!C:F,4,FALSE))) | G141: =IF(IF(B141="", "", VLOOKUP(B141,'API Data Dictionary'!C:G,5,FALSE))=0, "", IF(B141="", "", VLOOKUP(B141,'API Data Dictionary'!C:G,5,FALSE)))
A142: "tradingTypeId": 1, | B142: =IF(OR(ISNUMBER(SEARCH("{", A142)),ISNUMBER(SEARCH("[", A142))), "", IFERROR(MID(A142, SEARCH("""", A142) +1, SEARCH("""", A142, SEARCH("""",A142) +1) - SEARCH("""", A142) -1), "")) -> tradingTypeId | C142: =IF(B142="", "", VLOOKUP(B142,'API Data Dictionary'!C:J,8,FALSE)) -> X | D142: =IF(B142="", "", VLOOKUP(B142,'API Data Dictionary'!C:D,2,FALSE)) -> enum - tradingTypeId | E142: =IF(IF(B142="", "", VLOOKUP(B142,'API Data Dictionary'!C:E,3,FALSE))=0, "", IF(B142="", "", VLOOKUP(B142,'API Data Dictionary'!C:E,3,FALSE))) | F142: =IF(IF(B142="", "", VLOOKUP(B142,'API Data Dictionary'!C:F,4,FALSE))=0, "", IF(B142="", "", VLOOKUP(B142,'API Data Dictionary'!C:F,4,FALSE))) -> Valid Values (See enum definition) | G142: =IF(IF(B142="", "", VLOOKUP(B142,'API Data Dictionary'!C:G,5,FALSE))=0, "", IF(B142="", "", VLOOKUP(B142,'API Data Dictionary'!C:G,5,FALSE))) -> The trading type of the self employed person
A143: "startDateOfSelfEmployment": "2022-10-10T00:00:00.0000000", | B143: =IF(OR(ISNUMBER(SEARCH("{", A143)),ISNUMBER(SEARCH("[", A143))), "", IFERROR(MID(A143, SEARCH("""", A143) +1, SEARCH("""", A143, SEARCH("""",A143) +1) - SEARCH("""", A143) -1), "")) -> startDateOfSelfEmployment | C143: =IF(B143="", "", VLOOKUP(B143,'API Data Dictionary'!C:J,8,FALSE)) -> X | D143: =IF(B143="", "", VLOOKUP(B143,'API Data Dictionary'!C:D,2,FALSE)) -> string ($date-time) | E143: =IF(IF(B143="", "", VLOOKUP(B143,'API Data Dictionary'!C:E,3,FALSE))=0, "", IF(B143="", "", VLOOKUP(B143,'API Data Dictionary'!C:E,3,FALSE))) | F143: =IF(IF(B143="", "", VLOOKUP(B143,'API Data Dictionary'!C:F,4,FALSE))=0, "", IF(B143="", "", VLOOKUP(B143,'API Data Dictionary'!C:F,4,FALSE))) -> DD/MM/YYYY | G143: =IF(IF(B143="", "", VLOOKUP(B143,'API Data Dictionary'!C:G,5,FALSE))=0, "", IF(B143="", "", VLOOKUP(B143,'API Data Dictionary'!C:G,5,FALSE))) -> Start date of self employment, formatted DD/MM/YYYY
A144: "selfEmployedGrossAnnualIncome": 5000.5, | B144: =IF(OR(ISNUMBER(SEARCH("{", A144)),ISNUMBER(SEARCH("[", A144))), "", IFERROR(MID(A144, SEARCH("""", A144) +1, SEARCH("""", A144, SEARCH("""",A144) +1) - SEARCH("""", A144) -1), "")) -> selfEmployedGrossAnnualIncome | C144: =IF(B144="", "", VLOOKUP(B144,'API Data Dictionary'!C:J,8,FALSE)) -> 0 | D144: =IF(B144="", "", VLOOKUP(B144,'API Data Dictionary'!C:D,2,FALSE)) -> number ($double) | E144: =IF(IF(B144="", "", VLOOKUP(B144,'API Data Dictionary'!C:E,3,FALSE))=0, "", IF(B144="", "", VLOOKUP(B144,'API Data Dictionary'!C:E,3,FALSE))) | F144: =IF(IF(B144="", "", VLOOKUP(B144,'API Data Dictionary'!C:F,4,FALSE))=0, "", IF(B144="", "", VLOOKUP(B144,'API Data Dictionary'!C:F,4,FALSE))) -> pattern: ^\d*.\d{0,2}$ | G144: =IF(IF(B144="", "", VLOOKUP(B144,'API Data Dictionary'!C:G,5,FALSE))=0, "", IF(B144="", "", VLOOKUP(B144,'API Data Dictionary'!C:G,5,FALSE))) -> Amount of self employed gross annual income in GBP
A145: "netMonthlyIncome": 8000.5, | B145: =IF(OR(ISNUMBER(SEARCH("{", A145)),ISNUMBER(SEARCH("[", A145))), "", IFERROR(MID(A145, SEARCH("""", A145) +1, SEARCH("""", A145, SEARCH("""",A145) +1) - SEARCH("""", A145) -1), "")) -> netMonthlyIncome | C145: =IF(B145="", "", VLOOKUP(B145,'API Data Dictionary'!C:J,8,FALSE)) -> X | D145: =IF(B145="", "", VLOOKUP(B145,'API Data Dictionary'!C:D,2,FALSE)) -> number ($double) | E145: =IF(IF(B145="", "", VLOOKUP(B145,'API Data Dictionary'!C:E,3,FALSE))=0, "", IF(B145="", "", VLOOKUP(B145,'API Data Dictionary'!C:E,3,FALSE))) | F145: =IF(IF(B145="", "", VLOOKUP(B145,'API Data Dictionary'!C:F,4,FALSE))=0, "", IF(B145="", "", VLOOKUP(B145,'API Data Dictionary'!C:F,4,FALSE))) -> pattern: ^\d*.\d{0,2}$ | G145: =IF(IF(B145="", "", VLOOKUP(B145,'API Data Dictionary'!C:G,5,FALSE))=0, "", IF(B145="", "", VLOOKUP(B145,'API Data Dictionary'!C:G,5,FALSE))) -> Amount of Net monthly income in GBP
... A173: "investmentAmount": 100000 | B173: =IF(OR(ISNUMBER(SEARCH("{", A173)),ISNUMBER(SEARCH("[", A173))), "", IFERROR(MID(A173, SEARCH("""", A173) +1, SEARCH("""", A173, SEARCH("""",A173) +1) - SEARCH("""", A173) -1), "")) -> investmentAmount | C173: =IF(B173="", "", VLOOKUP(B173,'API Data Dictionary'!C:J,8,FALSE)) -> X | D173: =IF(B173="", "", VLOOKUP(B173,'API Data Dictionary'!C:D,2,FALSE)) -> number ($double) | E173: =IF(IF(B173="", "", VLOOKUP(B173,'API Data Dictionary'!C:E,3,FALSE))=0, "", IF(B173="", "", VLOOKUP(B173,'API Data Dictionary'!C:E,3,FALSE))) | F173: =IF(IF(B173="", "", VLOOKUP(B173,'API Data Dictionary'!C:F,4,FALSE))=0, "", IF(B173="", "", VLOOKUP(B173,'API Data Dictionary'!C:F,4,FALSE))) -> pattern: ^\d*.\d{0,2}$ | G173: =IF(IF(B173="", "", VLOOKUP(B173,'API Data Dictionary'!C:G,5,FALSE))=0, "", IF(B173="", "", VLOOKUP(B173,'API Data Dictionary'!C:G,5,FALSE))) -> Amount of investment in GBP
A174: }, | B174: =IF(OR(ISNUMBER(SEARCH("{", A174)),ISNUMBER(SEARCH("[", A174))), "", IFERROR(MID(A174, SEARCH("""", A174) +1, SEARCH("""", A174, SEARCH("""",A174) +1) - SEARCH("""", A174) -1), "")) | C174: M | D174: =IF(B174="", "", VLOOKUP(B174,'API Data Dictionary'!C:D,2,FALSE)) | E174: =IF(IF(B174="", "", VLOOKUP(B174,'API Data Dictionary'!C:E,3,FALSE))=0, "", IF(B174="", "", VLOOKUP(B174,'API Data Dictionary'!C:E,3,FALSE))) | F174: =IF(IF(B174="", "", VLOOKUP(B174,'API Data Dictionary'!C:F,4,FALSE))=0, "", IF(B174="", "", VLOOKUP(B174,'API Data Dictionary'!C:F,4,FALSE))) | G174: =IF(IF(B174="", "", VLOOKUP(B174,'API Data Dictionary'!C:G,5,FALSE))=0, "", IF(B174="", "", VLOOKUP(B174,'API Data Dictionary'!C:G,5,FALSE)))
A175: "saving": { | B175: =IF(OR(ISNUMBER(SEARCH("{", A175)),ISNUMBER(SEARCH("[", A175))), "", IFERROR(MID(A175, SEARCH("""", A175) +1, SEARCH("""", A175, SEARCH("""",A175) +1) - SEARCH("""", A175) -1), "")) | C175: =IF(B175="", "", VLOOKUP(B175,'API Data Dictionary'!C:J,8,FALSE)) | D175: =IF(B175="", "", VLOOKUP(B175,'API Data Dictionary'!C:D,2,FALSE)) | E175: =IF(IF(B175="", "", VLOOKUP(B175,'API Data Dictionary'!C:E,3,FALSE))=0, "", IF(B175="", "", VLOOKUP(B175,'API Data Dictionary'!C:E,3,FALSE))) | F175: =IF(IF(B175="", "", VLOOKUP(B175,'API Data Dictionary'!C:F,4,FALSE))=0, "", IF(B175="", "", VLOOKUP(B175,'API Data Dictionary'!C:F,4,FALSE))) | G175: =IF(IF(B175="", "", VLOOKUP(B175,'API Data Dictionary'!C:G,5,FALSE))=0, "", IF(B175="", "", VLOOKUP(B175,'API Data Dictionary'!C:G,5,FALSE)))
A176: "savingsAmount": 50000 | B176: =IF(OR(ISNUMBER(SEARCH("{", A176)),ISNUMBER(SEARCH("[", A176))), "", IFERROR(MID(A176, SEARCH("""", A176) +1, SEARCH("""", A176, SEARCH("""",A176) +1) - SEARCH("""", A176) -1), "")) -> savingsAmount | C176: =IF(B176="", "", VLOOKUP(B176,'API Data Dictionary'!C:J,8,FALSE)) -> X | D176: =IF(B176="", "", VLOOKUP(B176,'API Data Dictionary'!C:D,2,FALSE)) -> integer | E176: =IF(IF(B176="", "", VLOOKUP(B176,'API Data Dictionary'!C:E,3,FALSE))=0, "", IF(B176="", "", VLOOKUP(B176,'API Data Dictionary'!C:E,3,FALSE))) | F176: =IF(IF(B176="", "", VLOOKUP(B176,'API Data Dictionary'!C:F,4,FALSE))=0, "", IF(B176="", "", VLOOKUP(B176,'API Data Dictionary'!C:F,4,FALSE))) | G176: =IF(IF(B176="", "", VLOOKUP(B176,'API Data Dictionary'!C:G,5,FALSE))=0, "", IF(B176="", "", VLOOKUP(B176,'API Data Dictionary'!C:G,5,FALSE))) -> The amount of savings in GBP, to the nearest whole number
A177: }, | B177: =IF(OR(ISNUMBER(SEARCH("{", A177)),ISNUMBER(SEARCH("[", A177))), "", IFERROR(MID(A177, SEARCH("""", A177) +1, SEARCH("""", A177, SEARCH("""",A177) +1) - SEARCH("""", A177) -1), "")) | C177: =IF(B177="", "", VLOOKUP(B177,'API Data Dictionary'!C:J,8,FALSE)) | D177: =IF(B177="", "", VLOOKUP(B177,'API Data Dictionary'!C:D,2,FALSE)) | E177: =IF(IF(B177="", "", VLOOKUP(B177,'API Data Dictionary'!C:E,3,FALSE))=0, "", IF(B177="", "", VLOOKUP(B177,'API Data Dictionary'!C:E,3,FALSE))) | F177: =IF(IF(B177="", "", VLOOKUP(B177,'API Data Dictionary'!C:F,4,FALSE))=0, "", IF(B177="", "", VLOOKUP(B177,'API Data Dictionary'!C:F,4,FALSE))) | G177: =IF(IF(B177="", "", VLOOKUP(B177,'API Data Dictionary'!C:G,5,FALSE))=0, "", IF(B177="", "", VLOOKUP(B177,'API Data Dictionary'!C:G,5,FALSE)))
A178: "unemployed": { | B178: =IF(OR(ISNUMBER(SEARCH("{", A178)),ISNUMBER(SEARCH("[", A178))), "", IFERROR(MID(A178, SEARCH("""", A178) +1, SEARCH("""", A178, SEARCH("""",A178) +1) - SEARCH("""", A178) -1), "")) | C178: =IF(B178="", "", VLOOKUP(B178,'API Data Dictionary'!C:J,8,FALSE)) | D178: =IF(B178="", "", VLOOKUP(B178,'API Data Dictionary'!C:D,2,FALSE)) | E178: =IF(IF(B178="", "", VLOOKUP(B178,'API Data Dictionary'!C:E,3,FALSE))=0, "", IF(B178="", "", VLOOKUP(B178,'API Data Dictionary'!C:E,3,FALSE))) | F178: =IF(IF(B178="", "", VLOOKUP(B178,'API Data Dictionary'!C:F,4,FALSE))=0, "", IF(B178="", "", VLOOKUP(B178,'API Data Dictionary'!C:F,4,FALSE))) | G178: =IF(IF(B178="", "", VLOOKUP(B178,'API Data Dictionary'!C:G,5,FALSE))=0, "", IF(B178="", "", VLOOKUP(B178,'API Data Dictionary'!C:G,5,FALSE)))
A179: "applicantBenefitsReceived": false, | B179: =IF(OR(ISNUMBER(SEARCH("{", A179)),ISNUMBER(SEARCH("[", A179))), "", IFERROR(MID(A179, SEARCH("""", A179) +1, SEARCH("""", A179, SEARCH("""",A179) +1) - SEARCH("""", A179) -1), "")) -> applicantBenefitsReceived | C179: =IF(B179="", "", VLOOKUP(B179,'API Data Dictionary'!C:J,8,FALSE)) -> X | D179: =IF(B179="", "", VLOOKUP(B179,'API Data Dictionary'!C:D,2,FALSE)) -> boolean | E179: =IF(IF(B179="", "", VLOOKUP(B179,'API Data Dictionary'!C:E,3,FALSE))=0, "", IF(B179="", "", VLOOKUP(B179,'API Data Dictionary'!C:E,3,FALSE))) | F179: =IF(IF(B179="", "", VLOOKUP(B179,'API Data Dictionary'!C:F,4,FALSE))=0, "", IF(B179="", "", VLOOKUP(B179,'API Data Dictionary'!C:F,4,FALSE))) | G179: =IF(IF(B179="", "", VLOOKUP(B179,'API Data Dictionary'!C:G,5,FALSE))=0, "", IF(B179="", "", VLOOKUP(B179,'API Data Dictionary'!C:G,5,FALSE))) -> Denotes if benefits are recieved
A180: "netMonthlyIncome": 8000.5, | B180: =IF(OR(ISNUMBER(SEARCH("{", A180)),ISNUMBER(SEARCH("[", A180))), "", IFERROR(MID(A180, SEARCH("""", A180) +1, SEARCH("""", A180, SEARCH("""",A180) +1) - SEARCH("""", A180) -1), "")) -> netMonthlyIncome | C180: M | D180: =IF(B180="", "", VLOOKUP(B180,'API Data Dictionary'!C:D,2,FALSE)) -> number ($double) | E180: =IF(IF(B180="", "", VLOOKUP(B180,'API Data Dictionary'!C:E,3,FALSE))=0, "", IF(B180="", "", VLOOKUP(B180,'API Data Dictionary'!C:E,3,FALSE))) | F180: =IF(IF(B180="", "", VLOOKUP(B180,'API Data Dictionary'!C:F,4,FALSE))=0, "", IF(B180="", "", VLOOKUP(B180,'API Data Dictionary'!C:F,4,FALSE))) -> pattern: ^\d*.\d{0,2}$ | G180: =IF(IF(B180="", "", VLOOKUP(B180,'API Data Dictionary'!C:G,5,FALSE))=0, "", IF(B180="", "", VLOOKUP(B180,'API Data Dictionary'!C:G,5,FALSE))) -> Amount of Net monthly income in GBP
A181: "grossAnnualIncome": 8000.5, | B181: =IF(OR(ISNUMBER(SEARCH("{", A181)),ISNUMBER(SEARCH("[", A181))), "", IFERROR(MID(A181, SEARCH("""", A181) +1, SEARCH("""", A181, SEARCH("""",A181) +1) - SEARCH("""", A181) -1), "")) -> grossAnnualIncome | C181: =IF(B181="", "", VLOOKUP(B181,'API Data Dictionary'!C:J,8,FALSE)) -> 0 | D181: =IF(B181="", "", VLOOKUP(B181,'API Data Dictionary'!C:D,2,FALSE)) -> number ($double) | E181: =IF(IF(B181="", "", VLOOKUP(B181,'API Data Dictionary'!C:E,3,FALSE))=0, "", IF(B181="", "", VLOOKUP(B181,'API Data Dictionary'!C:E,3,FALSE))) | F181: =IF(IF(B181="", "", VLOOKUP(B181,'API Data Dictionary'!C:F,4,FALSE))=0, "", IF(B181="", "", VLOOKUP(B181,'API Data Dictionary'!C:F,4,FALSE))) -> pattern: ^\d*.\d{0,2}$ | G181: =IF(IF(B181="", "", VLOOKUP(B181,'API Data Dictionary'!C:G,5,FALSE))=0, "", IF(B181="", "", VLOOKUP(B181,'API Data Dictionary'!C:G,5,FALSE))) -> Amount ofgross annual income in GBP
A182: "taxCredit": true, | B182: =IF(OR(ISNUMBER(SEARCH("{", A182)),ISNUMBER(SEARCH("[", A182))), "", IFERROR(MID(A182, SEARCH("""", A182) +1, SEARCH("""", A182, SEARCH("""",A182) +1) - SEARCH("""", A182) -1), "")) -> taxCredit | C182: =IF(B182="", "", VLOOKUP(B182,'API Data Dictionary'!C:J,8,FALSE)) -> X | D182: =IF(B182="", "", VLOOKUP(B182,'API Data Dictionary'!C:D,2,FALSE)) -> boolean | E182: =IF(IF(B182="", "", VLOOKUP(B182,'API Data Dictionary'!C:E,3,FALSE))=0, "", IF(B182="", "", VLOOKUP(B182,'API Data Dictionary'!C:E,3,FALSE))) | F182: =IF(IF(B182="", "", VLOOKUP(B182,'API Data Dictionary'!C:F,4,FALSE))=0, "", IF(B182="", "", VLOOKUP(B182,'API Data Dictionary'!C:F,4,FALSE))) | G182: =IF(IF(B182="", "", VLOOKUP(B182,'API Data Dictionary'!C:G,5,FALSE))=0, "", IF(B182="", "", VLOOKUP(B182,'API Data Dictionary'!C:G,5,FALSE))) -> Denotes if is tax credit
A183: "carerAllowance": false, | B183: =IF(OR(ISNUMBER(SEARCH("{", A183)),ISNUMBER(SEARCH("[", A183))), "", IFERROR(MID(A183, SEARCH("""", A183) +1, SEARCH("""", A183, SEARCH("""",A183) +1) - SEARCH("""", A183) -1), "")) -> carerAllowance | C183: =IF(B183="", "", VLOOKUP(B183,'API Data Dictionary'!C:J,8,FALSE)) -> X | D183: =IF(B183="", "", VLOOKUP(B183,'API Data Dictionary'!C:D,2,FALSE)) -> boolean | E183: =IF(IF(B183="", "", VLOOKUP(B183,'API Data Dictionary'!C:E,3,FALSE))=0, "", IF(B183="", "", VLOOKUP(B183,'API Data Dictionary'!C:E,3,FALSE))) | F183: =IF(IF(B183="", "", VLOOKUP(B183,'API Data Dictionary'!C:F,4,FALSE))=0, "", IF(B183="", "", VLOOKUP(B183,'API Data Dictionary'!C:F,4,FALSE))) | G183: =IF(IF(B183="", "", VLOOKUP(B183,'API Data Dictionary'!C:G,5,FALSE))=0, "", IF(B183="", "", VLOOKUP(B183,'API Data Dictionary'!C:G,5,FALSE))) -> Denotes if carer allowance is received
A184: "childBenefit": true, | B184: =IF(OR(ISNUMBER(SEARCH("{", A184)),ISNUMBER(SEARCH("[", A184))), "", IFERROR(MID(A184, SEARCH("""", A184) +1, SEARCH("""", A184, SEARCH("""",A184) +1) - SEARCH("""", A184) -1), "")) -> childBenefit | C184: =IF(B184="", "", VLOOKUP(B184,'API Data Dictionary'!C:J,8,FALSE)) -> X | D184: =IF(B184="", "", VLOOKUP(B184,'API Data Dictionary'!C:D,2,FALSE)) -> boolean | E184: =IF(IF(B184="", "", VLOOKUP(B184,'API Data Dictionary'!C:E,3,FALSE))=0, "", IF(B184="", "", VLOOKUP(B184,'API Data Dictionary'!C:E,3,FALSE))) | F184: =IF(IF(B184="", "", VLOOKUP(B184,'API Data Dictionary'!C:F,4,FALSE))=0, "", IF(B184="", "", VLOOKUP(B184,'API Data Dictionary'!C:F,4,FALSE))) | G184: =IF(IF(B184="", "", VLOOKUP(B184,'API Data Dictionary'!C:G,5,FALSE))=0, "", IF(B184="", "", VLOOKUP(B184,'API Data Dictionary'!C:G,5,FALSE))) -> Denotes if child benfit is received
A185: "disabilityBenefit": false, | B185: =IF(OR(ISNUMBER(SEARCH("{", A185)),ISNUMBER(SEARCH("[", A185))), "", IFERROR(MID(A185, SEARCH("""", A185) +1, SEARCH("""", A185, SEARCH("""",A185) +1) - SEARCH("""", A185) -1), "")) -> disabilityBenefit | C185: =IF(B185="", "", VLOOKUP(B185,'API Data Dictionary'!C:J,8,FALSE)) -> X | D185: =IF(B185="", "", VLOOKUP(B185,'API Data Dictionary'!C:D,2,FALSE)) -> boolean | E185: =IF(IF(B185="", "", VLOOKUP(B185,'API Data Dictionary'!C:E,3,FALSE))=0, "", IF(B185="", "", VLOOKUP(B185,'API Data Dictionary'!C:E,3,FALSE))) | F185: =IF(IF(B185="", "", VLOOKUP(B185,'API Data Dictionary'!C:F,4,FALSE))=0, "", IF(B185="", "", VLOOKUP(B185,'API Data Dictionary'!C:F,4,FALSE))) | G185: =IF(IF(B185="", "", VLOOKUP(B185,'API Data Dictionary'!C:G,5,FALSE))=0, "", IF(B185="", "", VLOOKUP(B185,'API Data Dictionary'!C:G,5,FALSE))) -> Denotes if disablity Benefit is Recieved
A186: "fosterAllowance": true, | B186: =IF(OR(ISNUMBER(SEARCH("{", A186)),ISNUMBER(SEARCH("[", A186))), "", IFERROR(MID(A186, SEARCH("""", A186) +1, SEARCH("""", A186, SEARCH("""",A186) +1) - SEARCH("""", A186) -1), "")) -> fosterAllowance | C186: =IF(B186="", "", VLOOKUP(B186,'API Data Dictionary'!C:J,8,FALSE)) -> X | D186: =IF(B186="", "", VLOOKUP(B186,'API Data Dictionary'!C:D,2,FALSE)) -> boolean | E186: =IF(IF(B186="", "", VLOOKUP(B186,'API Data Dictionary'!C:E,3,FALSE))=0, "", IF(B186="", "", VLOOKUP(B186,'API Data Dictionary'!C:E,3,FALSE))) | F186: =IF(IF(B186="", "", VLOOKUP(B186,'API Data Dictionary'!C:F,4,FALSE))=0, "", IF(B186="", "", VLOOKUP(B186,'API Data Dictionary'!C:F,4,FALSE))) | G186: =IF(IF(B186="", "", VLOOKUP(B186,'API Data Dictionary'!C:G,5,FALSE))=0, "", IF(B186="", "", VLOOKUP(B186,'API Data Dictionary'!C:G,5,FALSE))) -> Denotes if foster allowance is recieved
A187: "guardianAllowance": true, | B187: =IF(OR(ISNUMBER(SEARCH("{", A187)),ISNUMBER(SEARCH("[", A187))), "", IFERROR(MID(A187, SEARCH("""", A187) +1, SEARCH("""", A187, SEARCH("""",A187) +1) - SEARCH("""", A187) -1), "")) -> guardianAllowance | C187: =IF(B187="", "", VLOOKUP(B187,'API Data Dictionary'!C:J,8,FALSE)) -> X | D187: =IF(B187="", "", VLOOKUP(B187,'API Data Dictionary'!C:D,2,FALSE)) -> boolean | E187: =IF(IF(B187="", "", VLOOKUP(B187,'API Data Dictionary'!C:E,3,FALSE))=0, "", IF(B187="", "", VLOOKUP(B187,'API Data Dictionary'!C:E,3,FALSE))) | F187: =IF(IF(B187="", "", VLOOKUP(B187,'API Data Dictionary'!C:F,4,FALSE))=0, "", IF(B187="", "", VLOOKUP(B187,'API Data Dictionary'!C:F,4,FALSE))) | G187: =IF(IF(B187="", "", VLOOKUP(B187,'API Data Dictionary'!C:G,5,FALSE))=0, "", IF(B187="", "", VLOOKUP(B187,'API Data Dictionary'!C:G,5,FALSE))) -> Denotes if guardian allowance is recieved
A188: "childMaintenance": true, | B188: =IF(OR(ISNUMBER(SEARCH("{", A188)),ISNUMBER(SEARCH("[", A188))), "", IFERROR(MID(A188, SEARCH("""", A188) +1, SEARCH("""", A188, SEARCH("""",A188) +1) - SEARCH("""", A188) -1), "")) -> childMaintenance | C188: =IF(B188="", "", VLOOKUP(B188,'API Data Dictionary'!C:J,8,FALSE)) -> X | D188: =IF(B188="", "", VLOOKUP(B188,'API Data Dictionary'!C:D,2,FALSE)) -> boolean | E188: =IF(IF(B188="", "", VLOOKUP(B188,'API Data Dictionary'!C:E,3,FALSE))=0, "", IF(B188="", "", VLOOKUP(B188,'API Data Dictionary'!C:E,3,FALSE))) | F188: =IF(IF(B188="", "", VLOOKUP(B188,'API Data Dictionary'!C:F,4,FALSE))=0, "", IF(B188="", "", VLOOKUP(B188,'API Data Dictionary'!C:F,4,FALSE))) | G188: =IF(IF(B188="", "", VLOOKUP(B188,'API Data Dictionary'!C:G,5,FALSE))=0, "", IF(B188="", "", VLOOKUP(B188,'API Data Dictionary'!C:G,5,FALSE))) -> Denotes if Child maintenance is received
A189: "housingBenefit": false, | B189: =IF(OR(ISNUMBER(SEARCH("{", A189)),ISNUMBER(SEARCH("[", A189))), "", IFERROR(MID(A189, SEARCH("""", A189) +1, SEARCH("""", A189, SEARCH("""",A189) +1) - SEARCH("""", A189) -1), "")) -> housingBenefit | C189: =IF(B189="", "", VLOOKUP(B189,'API Data Dictionary'!C:J,8,FALSE)) -> X | D189: =IF(B189="", "", VLOOKUP(B189,'API Data Dictionary'!C:D,2,FALSE)) -> boolean | E189: =IF(IF(B189="", "", VLOOKUP(B189,'API Data Dictionary'!C:E,3,FALSE))=0, "", IF(B189="", "", VLOOKUP(B189,'API Data Dictionary'!C:E,3,FALSE))) | F189: =IF(IF(B189="", "", VLOOKUP(B189,'API Data Dictionary'!C:F,4,FALSE))=0, "", IF(B189="", "", VLOOKUP(B189,'API Data Dictionary'!C:F,4,FALSE))) | G189: =IF(IF(B189="", "", VLOOKUP(B189,'API Data Dictionary'!C:G,5,FALSE))=0, "", IF(B189="", "", VLOOKUP(B189,'API Data Dictionary'!C:G,5,FALSE))) -> Denotes if shousing benefit is received
A190: "employmentSupport": true, | B190: =IF(OR(ISNUMBER(SEARCH("{", A190)),ISNUMBER(SEARCH("[", A190))), "", IFERROR(MID(A190, SEARCH("""", A190) +1, SEARCH("""", A190, SEARCH("""",A190) +1) - SEARCH("""", A190) -1), "")) -> employmentSupport | C190: =IF(B190="", "", VLOOKUP(B190,'API Data Dictionary'!C:J,8,FALSE)) -> X | D190: =IF(B190="", "", VLOOKUP(B190,'API Data Dictionary'!C:D,2,FALSE)) -> boolean | E190: =IF(IF(B190="", "", VLOOKUP(B190,'API Data Dictionary'!C:E,3,FALSE))=0, "", IF(B190="", "", VLOOKUP(B190,'API Data Dictionary'!C:E,3,FALSE))) | F190: =IF(IF(B190="", "", VLOOKUP(B190,'API Data Dictionary'!C:F,4,FALSE))=0, "", IF(B190="", "", VLOOKUP(B190,'API Data Dictionary'!C:F,4,FALSE))) | G190: =IF(IF(B190="", "", VLOOKUP(B190,'API Data Dictionary'!C:G,5,FALSE))=0, "", IF(B190="", "", VLOOKUP(B190,'API Data Dictionary'!C:G,5,FALSE))) -> Denotes if employment support is received
A191: "universalCredit": true, | B191: =IF(OR(ISNUMBER(SEARCH("{", A191)),ISNUMBER(SEARCH("[", A191))), "", IFERROR(MID(A191, SEARCH("""", A191) +1, SEARCH("""", A191, SEARCH("""",A191) +1) - SEARCH("""", A191) -1), "")) -> universalCredit | C191: =IF(B191="", "", VLOOKUP(B191,'API Data Dictionary'!C:J,8,FALSE)) -> X | D191: =IF(B191="", "", VLOOKUP(B191,'API Data Dictionary'!C:D,2,FALSE)) -> boolean | E191: =IF(IF(B191="", "", VLOOKUP(B191,'API Data Dictionary'!C:E,3,FALSE))=0, "", IF(B191="", "", VLOOKUP(B191,'API Data Dictionary'!C:E,3,FALSE))) | F191: =IF(IF(B191="", "", VLOOKUP(B191,'API Data Dictionary'!C:F,4,FALSE))=0, "", IF(B191="", "", VLOOKUP(B191,'API Data Dictionary'!C:F,4,FALSE))) | G191: =IF(IF(B191="", "", VLOOKUP(B191,'API Data Dictionary'!C:G,5,FALSE))=0, "", IF(B191="", "", VLOOKUP(B191,'API Data Dictionary'!C:G,5,FALSE))) -> Denotes if universal is received
A192: "startDate": "2000-06-11T00:00:00.0000000" | B192: =IF(OR(ISNUMBER(SEARCH("{", A192)),ISNUMBER(SEARCH("[", A192))), "", IFERROR(MID(A192, SEARCH("""", A192) +1, SEARCH("""", A192, SEARCH("""",A192) +1) - SEARCH("""", A192) -1), "")) -> startDate | C192: =IF(B192="", "", VLOOKUP(B192,'API Data Dictionary'!C:J,8,FALSE)) -> 0 | D192: =IF(B192="", "", VLOOKUP(B192,'API Data Dictionary'!C:D,2,FALSE)) -> 0 | E192: =IF(IF(B192="", "", VLOOKUP(B192,'API Data Dictionary'!C:E,3,FALSE))=0, "", IF(B192="", "", VLOOKUP(B192,'API Data Dictionary'!C:E,3,FALSE))) | F192: =IF(IF(B192="", "", VLOOKUP(B192,'API Data Dictionary'!C:F,4,FALSE))=0, "", IF(B192="", "", VLOOKUP(B192,'API Data Dictionary'!C:F,4,FALSE))) | G192: =IF(IF(B192="", "", VLOOKUP(B192,'API Data Dictionary'!C:G,5,FALSE))=0, "", IF(B192="", "", VLOOKUP(B192,'API Data Dictionary'!C:G,5,FALSE)))
... A202: } | B202: =IF(OR(ISNUMBER(SEARCH("{", A202)),ISNUMBER(SEARCH("[", A202))), "", IFERROR(MID(A202, SEARCH("""", A202) +1, SEARCH("""", A202, SEARCH("""",A202) +1) - SEARCH("""", A202) -1), "")) | C202: =IF(B202="", "", VLOOKUP(B202,'API Data Dictionary'!C:J,8,FALSE)) | D202: =IF(B202="", "", VLOOKUP(B202,'API Data Dictionary'!C:D,2,FALSE)) | E202: =IF(IF(B202="", "", VLOOKUP(B202,'API Data Dictionary'!C:E,3,FALSE))=0, "", IF(B202="", "", VLOOKUP(B202,'API Data Dictionary'!C:E,3,FALSE))) | F202: =IF(IF(B202="", "", VLOOKUP(B202,'API Data Dictionary'!C:F,4,FALSE))=0, "", IF(B202="", "", VLOOKUP(B202,'API Data Dictionary'!C:F,4,FALSE))) | G202: =IF(IF(B202="", "", VLOOKUP(B202,'API Data Dictionary'!C:G,5,FALSE))=0, "", IF(B202="", "", VLOOKUP(B202,'API Data Dictionary'!C:G,5,FALSE)))
A204: Response Example: Success - 200
A205: { | B205: =IF(OR(ISNUMBER(SEARCH("{", A205)),ISNUMBER(SEARCH("[", A205))), "", IFERROR(MID(A205, SEARCH("""", A205) +1, SEARCH("""", A205, SEARCH("""",A205) +1) - SEARCH("""", A205) -1), "")) | C205: =IF(B205="", "", VLOOKUP(B205,'API Data Dictionary'!C:J,8,FALSE)) | D205: =IF(B205="", "", VLOOKUP(B205,'API Data Dictionary'!C:D,2,FALSE)) | E205: =IF(IF(B205="", "", VLOOKUP(B205,'API Data Dictionary'!C:E,3,FALSE))=0, "", IF(B205="", "", VLOOKUP(B205,'API Data Dictionary'!C:E,3,FALSE))) | F205: =IF(IF(B205="", "", VLOOKUP(B205,'API Data Dictionary'!C:F,4,FALSE))=0, "", IF(B205="", "", VLOOKUP(B205,'API Data Dictionary'!C:F,4,FALSE))) | G205: =IF(IF(B205="", "", VLOOKUP(B205,'API Data Dictionary'!C:G,5,FALSE))=0, "", IF(B205="", "", VLOOKUP(B205,'API Data Dictionary'!C:G,5,FALSE)))
A206: "success": true, | B206: =IF(OR(ISNUMBER(SEARCH("{", A206)),ISNUMBER(SEARCH("[", A206))), "", IFERROR(MID(A206, SEARCH("""", A206) +1, SEARCH("""", A206, SEARCH("""",A206) +1) - SEARCH("""", A206) -1), "")) -> success | C206: M | D206: =IF(B206="", "", VLOOKUP(B206,'API Data Dictionary'!C:D,2,FALSE)) -> string - Boolean | E206: =IF(IF(B206="", "", VLOOKUP(B206,'API Data Dictionary'!C:E,3,FALSE))=0, "", IF(B206="", "", VLOOKUP(B206,'API Data Dictionary'!C:E,3,FALSE))) -> 100 | F206: =IF(IF(B206="", "", VLOOKUP(B206,'API Data Dictionary'!C:F,4,FALSE))=0, "", IF(B206="", "", VLOOKUP(B206,'API Data Dictionary'!C:F,4,FALSE))) | G206: =IF(IF(B206="", "", VLOOKUP(B206,'API Data Dictionary'!C:G,5,FALSE))=0, "", IF(B206="", "", VLOOKUP(B206,'API Data Dictionary'!C:G,5,FALSE))) -> Returns true when successful call/connection
A207: "payload": { | B207: =IF(OR(ISNUMBER(SEARCH("{", A207)),ISNUMBER(SEARCH("[", A207))), "", IFERROR(MID(A207, SEARCH("""", A207) +1, SEARCH("""", A207, SEARCH("""",A207) +1) - SEARCH("""", A207) -1), "")) | C207: =IF(B207="", "", VLOOKUP(B207,'API Data Dictionary'!C:J,8,FALSE)) | D207: =IF(B207="", "", VLOOKUP(B207,'API Data Dictionary'!C:D,2,FALSE)) | E207: =IF(IF(B207="", "", VLOOKUP(B207,'API Data Dictionary'!C:E,3,FALSE))=0, "", IF(B207="", "", VLOOKUP(B207,'API Data Dictionary'!C:E,3,FALSE))) | F207: =IF(IF(B207="", "", VLOOKUP(B207,'API Data Dictionary'!C:F,4,FALSE))=0, "", IF(B207="", "", VLOOKUP(B207,'API Data Dictionary'!C:F,4,FALSE))) | G207: =IF(IF(B207="", "", VLOOKUP(B207,'API Data Dictionary'!C:G,5,FALSE))=0, "", IF(B207="", "", VLOOKUP(B207,'API Data Dictionary'!C:G,5,FALSE)))
A208: "agentCode": "9999", | B208: =IF(OR(ISNUMBER(SEARCH("{", A208)),ISNUMBER(SEARCH("[", A208))), "", IFERROR(MID(A208, SEARCH("""", A208) +1, SEARCH("""", A208, SEARCH("""",A208) +1) - SEARCH("""", A208) -1), "")) -> agentCode | C208: M | D208: =IF(B208="", "", VLOOKUP(B208,'API Data Dictionary'!C:D,2,FALSE)) -> string | E208: =IF(IF(B208="", "", VLOOKUP(B208,'API Data Dictionary'!C:E,3,FALSE))=0, "", IF(B208="", "", VLOOKUP(B208,'API Data Dictionary'!C:E,3,FALSE))) -> 50 | F208: =IF(IF(B208="", "", VLOOKUP(B208,'API Data Dictionary'!C:F,4,FALSE))=0, "", IF(B208="", "", VLOOKUP(B208,'API Data Dictionary'!C:F,4,FALSE))) | G208: =IF(IF(B208="", "", VLOOKUP(B208,'API Data Dictionary'!C:G,5,FALSE))=0, "", IF(B208="", "", VLOOKUP(B208,'API Data Dictionary'!C:G,5,FALSE))) -> AgentCode is the Unique Key provided to the Agent when onboarding as a Barbon Customer. An AgentID may be linked to many Properties being managed by that Agent and Each property may be linked to 1 or more TenancyID's.
...

Sheet CreateReferenceWithApplicantIfr
A1: CreateReferenceWithApplicantIframe Example JSON | B1: Vision+ API Field Name | C1: Mandatory Field | D1: Field Type | E1: API Max Field Length | F1: Field Validations | G1: Field Description
A2: Request Example
A3: { | B3: =IF(OR(ISNUMBER(SEARCH("{", A3)),ISNUMBER(SEARCH("[", A3))), "", IFERROR(MID(A3, SEARCH("""", A3) +1, SEARCH("""", A3, SEARCH("""",A3) +1) - SEARCH("""", A3) -1), "")) | C3: =IF(B3="", "", VLOOKUP(B3,'API Data Dictionary'!C:L,10,FALSE)) | D3: =IF(B3="", "", VLOOKUP(B3,'API Data Dictionary'!C:D,2,FALSE)) | E3: =IF(IF(B3="", "", VLOOKUP(B3,'API Data Dictionary'!C:E,3,FALSE))=0, "", IF(B3="", "", VLOOKUP(B3,'API Data Dictionary'!C:E,3,FALSE))) | F3: =IF(IF(B3="", "", VLOOKUP(B3,'API Data Dictionary'!C:F,4,FALSE))=0, "", IF(B3="", "", VLOOKUP(B3,'API Data Dictionary'!C:F,4,FALSE))) | G3: =IF(IF(B3="", "", VLOOKUP(B3,'API Data Dictionary'!C:G,5,FALSE))=0, "", IF(B3="", "", VLOOKUP(B3,'API Data Dictionary'!C:G,5,FALSE)))
A4: "agentCode": "9999", | B4: =IF(OR(ISNUMBER(SEARCH("{", A4)),ISNUMBER(SEARCH("[", A4))), "", IFERROR(MID(A4, SEARCH("""", A4) +1, SEARCH("""", A4, SEARCH("""",A4) +1) - SEARCH("""", A4) -1), "")) -> agentCode | C4: =IF(B4="", "", VLOOKUP(B4,'API Data Dictionary'!C:L,10,FALSE)) -> M | D4: =IF(B4="", "", VLOOKUP(B4,'API Data Dictionary'!C:D,2,FALSE)) -> string | E4: =IF(IF(B4="", "", VLOOKUP(B4,'API Data Dictionary'!C:E,3,FALSE))=0, "", IF(B4="", "", VLOOKUP(B4,'API Data Dictionary'!C:E,3,FALSE))) -> 50 | F4: =IF(IF(B4="", "", VLOOKUP(B4,'API Data Dictionary'!C:F,4,FALSE))=0, "", IF(B4="", "", VLOOKUP(B4,'API Data Dictionary'!C:F,4,FALSE))) | G4: =IF(IF(B4="", "", VLOOKUP(B4,'API Data Dictionary'!C:G,5,FALSE))=0, "", IF(B4="", "", VLOOKUP(B4,'API Data Dictionary'!C:G,5,FALSE))) -> AgentCode is the Unique Key provided to the Agent when onboarding as a Barbon Customer. An AgentID may be linked to many Properties being managed by that Agent and Each property may be linked to 1 or more TenancyID's.
A5: "rentGuarantee": 4, | B5: =IF(OR(ISNUMBER(SEARCH("{", A5)),ISNUMBER(SEARCH("[", A5))), "", IFERROR(MID(A5, SEARCH("""", A5) +1, SEARCH("""", A5, SEARCH("""",A5) +1) - SEARCH("""", A5) -1), "")) -> rentGuarantee | C5: =IF(B5="", "", VLOOKUP(B5,'API Data Dictionary'!C:L,10,FALSE)) -> M | D5: =IF(B5="", "", VLOOKUP(B5,'API Data Dictionary'!C:D,2,FALSE)) -> enum - Rent Guarantee | E5: =IF(IF(B5="", "", VLOOKUP(B5,'API Data Dictionary'!C:E,3,FALSE))=0, "", IF(B5="", "", VLOOKUP(B5,'API Data Dictionary'!C:E,3,FALSE))) | F5: =IF(IF(B5="", "", VLOOKUP(B5,'API Data Dictionary'!C:F,4,FALSE))=0, "", IF(B5="", "", VLOOKUP(B5,'API Data Dictionary'!C:F,4,FALSE))) -> Valid Values 1-4 (See enum definition) | G5: =IF(IF(B5="", "", VLOOKUP(B5,'API Data Dictionary'!C:G,5,FALSE))=0, "", IF(B5="", "", VLOOKUP(B5,'API Data Dictionary'!C:G,5,FALSE))) -> Rent guarantee is an indicator that determines which RG option if any the agent requires
A6: "tenancyTermMonths": 12, | B6: =IF(OR(ISNUMBER(SEARCH("{", A6)),ISNUMBER(SEARCH("[", A6))), "", IFERROR(MID(A6, SEARCH("""", A6) +1, SEARCH("""", A6, SEARCH("""",A6) +1) - SEARCH("""", A6) -1), "")) -> tenancyTermMonths | C6: =IF(B6="", "", VLOOKUP(B6,'API Data Dictionary'!C:L,10,FALSE)) -> M | D6: =IF(B6="", "", VLOOKUP(B6,'API Data Dictionary'!C:D,2,FALSE)) -> integer | E6: =IF(IF(B6="", "", VLOOKUP(B6,'API Data Dictionary'!C:E,3,FALSE))=0, "", IF(B6="", "", VLOOKUP(B6,'API Data Dictionary'!C:E,3,FALSE))) | F6: =IF(IF(B6="", "", VLOOKUP(B6,'API Data Dictionary'!C:F,4,FALSE))=0, "", IF(B6="", "", VLOOKUP(B6,'API Data Dictionary'!C:F,4,FALSE))) | G6: =IF(IF(B6="", "", VLOOKUP(B6,'API Data Dictionary'!C:G,5,FALSE))=0, "", IF(B6="", "", VLOOKUP(B6,'API Data Dictionary'!C:G,5,FALSE))) -> The term of the Tenancy in months (whole months only)
A7: "monthlyRental": 2000, | B7: =IF(OR(ISNUMBER(SEARCH("{", A7)),ISNUMBER(SEARCH("[", A7))), "", IFERROR(MID(A7, SEARCH("""", A7) +1, SEARCH("""", A7, SEARCH("""",A7) +1) - SEARCH("""", A7) -1), "")) -> monthlyRental | C7: =IF(B7="", "", VLOOKUP(B7,'API Data Dictionary'!C:L,10,FALSE)) -> M | D7: =IF(B7="", "", VLOOKUP(B7,'API Data Dictionary'!C:D,2,FALSE)) -> number (double) | E7: =IF(IF(B7="", "", VLOOKUP(B7,'API Data Dictionary'!C:E,3,FALSE))=0, "", IF(B7="", "", VLOOKUP(B7,'API Data Dictionary'!C:E,3,FALSE))) | F7: =IF(IF(B7="", "", VLOOKUP(B7,'API Data Dictionary'!C:F,4,FALSE))=0, "", IF(B7="", "", VLOOKUP(B7,'API Data Dictionary'!C:F,4,FALSE))) -> number($double) pattern: ^\d*.\d{0,2}$ | G7: =IF(IF(B7="", "", VLOOKUP(B7,'API Data Dictionary'!C:G,5,FALSE))=0, "", IF(B7="", "", VLOOKUP(B7,'API Data Dictionary'!C:G,5,FALSE))) -> The monthly rental cost
A8: "lettingType": 1, | B8: =IF(OR(ISNUMBER(SEARCH("{", A8)),ISNUMBER(SEARCH("[", A8))), "", IFERROR(MID(A8, SEARCH("""", A8) +1, SEARCH("""", A8, SEARCH("""",A8) +1) - SEARCH("""", A8) -1), "")) -> lettingType | C8: =IF(B8="", "", VLOOKUP(B8,'API Data Dictionary'!C:L,10,FALSE)) -> M | D8: =IF(B8="", "", VLOOKUP(B8,'API Data Dictionary'!C:D,2,FALSE)) -> enum - Letting Type | E8: =IF(IF(B8="", "", VLOOKUP(B8,'API Data Dictionary'!C:E,3,FALSE))=0, "", IF(B8="", "", VLOOKUP(B8,'API Data Dictionary'!C:E,3,FALSE))) | F8: =IF(IF(B8="", "", VLOOKUP(B8,'API Data Dictionary'!C:F,4,FALSE))=0, "", IF(B8="", "", VLOOKUP(B8,'API Data Dictionary'!C:F,4,FALSE))) -> Valid Values 1-3 (See enum definition) | G8: =IF(IF(B8="", "", VLOOKUP(B8,'API Data Dictionary'!C:G,5,FALSE))=0, "", IF(B8="", "", VLOOKUP(B8,'API Data Dictionary'!C:G,5,FALSE))) -> The type of the letting, i.e. rent only or fully managed
A9: "estimatedMoveInDate": "2023-06-01T10:55:02.383Z", | B9: =IF(OR(ISNUMBER(SEARCH("{", A9)),ISNUMBER(SEARCH("[", A9))), "", IFERROR(MID(A9, SEARCH("""", A9) +1, SEARCH("""", A9, SEARCH("""",A9) +1) - SEARCH("""", A9) -1), "")) -> estimatedMoveInDate | C9: =IF(B9="", "", VLOOKUP(B9,'API Data Dictionary'!C:L,10,FALSE)) -> M | D9: =IF(B9="", "", VLOOKUP(B9,'API Data Dictionary'!C:D,2,FALSE)) -> string ($date-time) | E9: =IF(IF(B9="", "", VLOOKUP(B9,'API Data Dictionary'!C:E,3,FALSE))=0, "", IF(B9="", "", VLOOKUP(B9,'API Data Dictionary'!C:E,3,FALSE))) | F9: =IF(IF(B9="", "", VLOOKUP(B9,'API Data Dictionary'!C:F,4,FALSE))=0, "", IF(B9="", "", VLOOKUP(B9,'API Data Dictionary'!C:F,4,FALSE))) -> DD/MM/YYYY | G9: =IF(IF(B9="", "", VLOOKUP(B9,'API Data Dictionary'!C:G,5,FALSE))=0, "", IF(B9="", "", VLOOKUP(B9,'API Data Dictionary'!C:G,5,FALSE))) -> Estimated date of tenancy start (move in)
A10: "propertyType": 1, | B10: =IF(OR(ISNUMBER(SEARCH("{", A10)),ISNUMBER(SEARCH("[", A10))), "", IFERROR(MID(A10, SEARCH("""", A10) +1, SEARCH("""", A10, SEARCH("""",A10) +1) - SEARCH("""", A10) -1), "")) -> propertyType | C10: M | D10: =IF(B10="", "", VLOOKUP(B10,'API Data Dictionary'!C:D,2,FALSE)) -> enum - Property Type | E10: =IF(IF(B10="", "", VLOOKUP(B10,'API Data Dictionary'!C:E,3,FALSE))=0, "", IF(B10="", "", VLOOKUP(B10,'API Data Dictionary'!C:E,3,FALSE))) | F10: =IF(IF(B10="", "", VLOOKUP(B10,'API Data Dictionary'!C:F,4,FALSE))=0, "", IF(B10="", "", VLOOKUP(B10,'API Data Dictionary'!C:F,4,FALSE))) -> Valid Values 1-6 (See enum definition) | G10: =IF(IF(B10="", "", VLOOKUP(B10,'API Data Dictionary'!C:G,5,FALSE))=0, "", IF(B10="", "", VLOOKUP(B10,'API Data Dictionary'!C:G,5,FALSE))) -> The Type of property
A11: "propertyConstructionPeriod": 4, | B11: =IF(OR(ISNUMBER(SEARCH("{", A11)),ISNUMBER(SEARCH("[", A11))), "", IFERROR(MID(A11, SEARCH("""", A11) +1, SEARCH("""", A11, SEARCH("""",A11) +1) - SEARCH("""", A11) -1), "")) -> propertyConstructionPeriod | C11: X | D11: =IF(B11="", "", VLOOKUP(B11,'API Data Dictionary'!C:D,2,FALSE)) -> enum - Property Construction Period | E11: =IF(IF(B11="", "", VLOOKUP(B11,'API Data Dictionary'!C:E,3,FALSE))=0, "", IF(B11="", "", VLOOKUP(B11,'API Data Dictionary'!C:E,3,FALSE))) | F11: =IF(IF(B11="", "", VLOOKUP(B11,'API Data Dictionary'!C:F,4,FALSE))=0, "", IF(B11="", "", VLOOKUP(B11,'API Data Dictionary'!C:F,4,FALSE))) -> Valid Values 1-9 (See enum definition) | G11: =IF(IF(B11="", "", VLOOKUP(B11,'API Data Dictionary'!C:G,5,FALSE))=0, "", IF(B11="", "", VLOOKUP(B11,'API Data Dictionary'!C:G,5,FALSE))) -> The time period in which the property was built
A12: "numberOfBedrooms": 4, | B12: =IF(OR(ISNUMBER(SEARCH("{", A12)),ISNUMBER(SEARCH("[", A12))), "", IFERROR(MID(A12, SEARCH("""", A12) +1, SEARCH("""", A12, SEARCH("""",A12) +1) - SEARCH("""", A12) -1), "")) -> numberOfBedrooms | C12: X | D12: =IF(B12="", "", VLOOKUP(B12,'API Data Dictionary'!C:D,2,FALSE)) -> integer | E12: =IF(IF(B12="", "", VLOOKUP(B12,'API Data Dictionary'!C:E,3,FALSE))=0, "", IF(B12="", "", VLOOKUP(B12,'API Data Dictionary'!C:E,3,FALSE))) | F12: =IF(IF(B12="", "", VLOOKUP(B12,'API Data Dictionary'!C:F,4,FALSE))=0, "", IF(B12="", "", VLOOKUP(B12,'API Data Dictionary'!C:F,4,FALSE))) | G12: =IF(IF(B12="", "", VLOOKUP(B12,'API Data Dictionary'!C:G,5,FALSE))=0, "", IF(B12="", "", VLOOKUP(B12,'API Data Dictionary'!C:G,5,FALSE))) -> The count of bedrooms in the property
A13: "noOfAdultOccupants": 2, | B13: =IF(OR(ISNUMBER(SEARCH("{", A13)),ISNUMBER(SEARCH("[", A13))), "", IFERROR(MID(A13, SEARCH("""", A13) +1, SEARCH("""", A13, SEARCH("""",A13) +1) - SEARCH("""", A13) -1), "")) -> noOfAdultOccupants | C13: X | D13: =IF(B13="", "", VLOOKUP(B13,'API Data Dictionary'!C:D,2,FALSE)) -> integer | E13: =IF(IF(B13="", "", VLOOKUP(B13,'API Data Dictionary'!C:E,3,FALSE))=0, "", IF(B13="", "", VLOOKUP(B13,'API Data Dictionary'!C:E,3,FALSE))) | F13: =IF(IF(B13="", "", VLOOKUP(B13,'API Data Dictionary'!C:F,4,FALSE))=0, "", IF(B13="", "", VLOOKUP(B13,'API Data Dictionary'!C:F,4,FALSE))) | G13: =IF(IF(B13="", "", VLOOKUP(B13,'API Data Dictionary'!C:G,5,FALSE))=0, "", IF(B13="", "", VLOOKUP(B13,'API Data Dictionary'!C:G,5,FALSE))) -> Number of Adult occupants (18 or over)
A14: "noOfChildOccupants": 2, | B14: =IF(OR(ISNUMBER(SEARCH("{", A14)),ISNUMBER(SEARCH("[", A14))), "", IFERROR(MID(A14, SEARCH("""", A14) +1, SEARCH("""", A14, SEARCH("""",A14) +1) - SEARCH("""", A14) -1), "")) -> noOfChildOccupants | C14: X | D14: =IF(B14="", "", VLOOKUP(B14,'API Data Dictionary'!C:D,2,FALSE)) -> integer | E14: =IF(IF(B14="", "", VLOOKUP(B14,'API Data Dictionary'!C:E,3,FALSE))=0, "", IF(B14="", "", VLOOKUP(B14,'API Data Dictionary'!C:E,3,FALSE))) | F14: =IF(IF(B14="", "", VLOOKUP(B14,'API Data Dictionary'!C:F,4,FALSE))=0, "", IF(B14="", "", VLOOKUP(B14,'API Data Dictionary'!C:F,4,FALSE))) | G14: =IF(IF(B14="", "", VLOOKUP(B14,'API Data Dictionary'!C:G,5,FALSE))=0, "", IF(B14="", "", VLOOKUP(B14,'API Data Dictionary'!C:G,5,FALSE))) -> Number of Child Occupants (under 18)
A15: "isAdvanceRent": false, | B15: =IF(OR(ISNUMBER(SEARCH("{", A15)),ISNUMBER(SEARCH("[", A15))), "", IFERROR(MID(A15, SEARCH("""", A15) +1, SEARCH("""", A15, SEARCH("""",A15) +1) - SEARCH("""", A15) -1), "")) -> isAdvanceRent | C15: M | D15: =IF(B15="", "", VLOOKUP(B15,'API Data Dictionary'!C:D,2,FALSE)) -> boolean | E15: =IF(IF(B15="", "", VLOOKUP(B15,'API Data Dictionary'!C:E,3,FALSE))=0, "", IF(B15="", "", VLOOKUP(B15,'API Data Dictionary'!C:E,3,FALSE))) | F15: =IF(IF(B15="", "", VLOOKUP(B15,'API Data Dictionary'!C:F,4,FALSE))=0, "", IF(B15="", "", VLOOKUP(B15,'API Data Dictionary'!C:F,4,FALSE))) | G15: =IF(IF(B15="", "", VLOOKUP(B15,'API Data Dictionary'!C:G,5,FALSE))=0, "", IF(B15="", "", VLOOKUP(B15,'API Data Dictionary'!C:G,5,FALSE))) -> Denotes whether rent is paid in advance
A16: "propertyAddress": { | B16: =IF(OR(ISNUMBER(SEARCH("{", A16)),ISNUMBER(SEARCH("[", A16))), "", IFERROR(MID(A16, SEARCH("""", A16) +1, SEARCH("""", A16, SEARCH("""",A16) +1) - SEARCH("""", A16) -1), "")) | C16: =IF(B16="", "", VLOOKUP(B16,'API Data Dictionary'!C:L,10,FALSE)) | D16: =IF(B16="", "", VLOOKUP(B16,'API Data Dictionary'!C:D,2,FALSE)) | E16: =IF(IF(B16="", "", VLOOKUP(B16,'API Data Dictionary'!C:E,3,FALSE))=0, "", IF(B16="", "", VLOOKUP(B16,'API Data Dictionary'!C:E,3,FALSE))) | F16: =IF(IF(B16="", "", VLOOKUP(B16,'API Data Dictionary'!C:F,4,FALSE))=0, "", IF(B16="", "", VLOOKUP(B16,'API Data Dictionary'!C:F,4,FALSE))) | G16: =IF(IF(B16="", "", VLOOKUP(B16,'API Data Dictionary'!C:G,5,FALSE))=0, "", IF(B16="", "", VLOOKUP(B16,'API Data Dictionary'!C:G,5,FALSE)))
A17: "houseNumber": "65000", | B17: =IF(OR(ISNUMBER(SEARCH("{", A17)),ISNUMBER(SEARCH("[", A17))), "", IFERROR(MID(A17, SEARCH("""", A17) +1, SEARCH("""", A17, SEARCH("""",A17) +1) - SEARCH("""", A17) -1), "")) -> houseNumber | C17: =IF(B17="", "", VLOOKUP(B17,'API Data Dictionary'!C:L,10,FALSE)) -> X | D17: =IF(B17="", "", VLOOKUP(B17,'API Data Dictionary'!C:D,2,FALSE)) -> string | E17: =IF(IF(B17="", "", VLOOKUP(B17,'API Data Dictionary'!C:E,3,FALSE))=0, "", IF(B17="", "", VLOOKUP(B17,'API Data Dictionary'!C:E,3,FALSE))) -> 100 | F17: =IF(IF(B17="", "", VLOOKUP(B17,'API Data Dictionary'!C:F,4,FALSE))=0, "", IF(B17="", "", VLOOKUP(B17,'API Data Dictionary'!C:F,4,FALSE))) | G17: =IF(IF(B17="", "", VLOOKUP(B17,'API Data Dictionary'!C:G,5,FALSE))=0, "", IF(B17="", "", VLOOKUP(B17,'API Data Dictionary'!C:G,5,FALSE))) -> The number of the property, mandatory OR pair with House name field
A18: "houseName": "Oxford Street", | B18: =IF(OR(ISNUMBER(SEARCH("{", A18)),ISNUMBER(SEARCH("[", A18))), "", IFERROR(MID(A18, SEARCH("""", A18) +1, SEARCH("""", A18, SEARCH("""",A18) +1) - SEARCH("""", A18) -1), "")) -> houseName | C18: =IF(B18="", "", VLOOKUP(B18,'API Data Dictionary'!C:L,10,FALSE)) -> X | D18: =IF(B18="", "", VLOOKUP(B18,'API Data Dictionary'!C:D,2,FALSE)) -> string | E18: =IF(IF(B18="", "", VLOOKUP(B18,'API Data Dictionary'!C:E,3,FALSE))=0, "", IF(B18="", "", VLOOKUP(B18,'API Data Dictionary'!C:E,3,FALSE))) -> 100 | F18: =IF(IF(B18="", "", VLOOKUP(B18,'API Data Dictionary'!C:F,4,FALSE))=0, "", IF(B18="", "", VLOOKUP(B18,'API Data Dictionary'!C:F,4,FALSE))) | G18: =IF(IF(B18="", "", VLOOKUP(B18,'API Data Dictionary'!C:G,5,FALSE))=0, "", IF(B18="", "", VLOOKUP(B18,'API Data Dictionary'!C:G,5,FALSE))) -> The name of the property, mandatory OR pair with House number field
A19: "addressLine1": "Gadlys", | B19: =IF(OR(ISNUMBER(SEARCH("{", A19)),ISNUMBER(SEARCH("[", A19))), "", IFERROR(MID(A19, SEARCH("""", A19) +1, SEARCH("""", A19, SEARCH("""",A19) +1) - SEARCH("""", A19) -1), "")) -> addressLine1 | C19: =IF(B19="", "", VLOOKUP(B19,'API Data Dictionary'!C:L,10,FALSE)) -> M | D19: =IF(B19="", "", VLOOKUP(B19,'API Data Dictionary'!C:D,2,FALSE)) -> string | E19: =IF(IF(B19="", "", VLOOKUP(B19,'API Data Dictionary'!C:E,3,FALSE))=0, "", IF(B19="", "", VLOOKUP(B19,'API Data Dictionary'!C:E,3,FALSE))) -> 100 | F19: =IF(IF(B19="", "", VLOOKUP(B19,'API Data Dictionary'!C:F,4,FALSE))=0, "", IF(B19="", "", VLOOKUP(B19,'API Data Dictionary'!C:F,4,FALSE))) | G19: =IF(IF(B19="", "", VLOOKUP(B19,'API Data Dictionary'!C:G,5,FALSE))=0, "", IF(B19="", "", VLOOKUP(B19,'API Data Dictionary'!C:G,5,FALSE))) -> The first line of the property address
A20: "addressLine2": "Parkway", | B20: =IF(OR(ISNUMBER(SEARCH("{", A20)),ISNUMBER(SEARCH("[", A20))), "", IFERROR(MID(A20, SEARCH("""", A20) +1, SEARCH("""", A20, SEARCH("""",A20) +1) - SEARCH("""", A20) -1), "")) -> addressLine2 | C20: X | D20: =IF(B20="", "", VLOOKUP(B20,'API Data Dictionary'!C:D,2,FALSE)) -> string | E20: =IF(IF(B20="", "", VLOOKUP(B20,'API Data Dictionary'!C:E,3,FALSE))=0, "", IF(B20="", "", VLOOKUP(B20,'API Data Dictionary'!C:E,3,FALSE))) -> 100 | F20: =IF(IF(B20="", "", VLOOKUP(B20,'API Data Dictionary'!C:F,4,FALSE))=0, "", IF(B20="", "", VLOOKUP(B20,'API Data Dictionary'!C:F,4,FALSE))) | G20: =IF(IF(B20="", "", VLOOKUP(B20,'API Data Dictionary'!C:G,5,FALSE))=0, "", IF(B20="", "", VLOOKUP(B20,'API Data Dictionary'!C:G,5,FALSE))) -> The second line of the property address
A21: "town": "Aberdare", | B21: =IF(OR(ISNUMBER(SEARCH("{", A21)),ISNUMBER(SEARCH("[", A21))), "", IFERROR(MID(A21, SEARCH("""", A21) +1, SEARCH("""", A21, SEARCH("""",A21) +1) - SEARCH("""", A21) -1), "")) -> town | C21: =IF(B21="", "", VLOOKUP(B21,'API Data Dictionary'!C:L,10,FALSE)) -> M | D21: =IF(B21="", "", VLOOKUP(B21,'API Data Dictionary'!C:D,2,FALSE)) -> string | E21: =IF(IF(B21="", "", VLOOKUP(B21,'API Data Dictionary'!C:E,3,FALSE))=0, "", IF(B21="", "", VLOOKUP(B21,'API Data Dictionary'!C:E,3,FALSE))) -> 50 | F21: =IF(IF(B21="", "", VLOOKUP(B21,'API Data Dictionary'!C:F,4,FALSE))=0, "", IF(B21="", "", VLOOKUP(B21,'API Data Dictionary'!C:F,4,FALSE))) | G21: =IF(IF(B21="", "", VLOOKUP(B21,'API Data Dictionary'!C:G,5,FALSE))=0, "", IF(B21="", "", VLOOKUP(B21,'API Data Dictionary'!C:G,5,FALSE))) -> The town in which the property exists
A22: "postcode": "CF44 8BE", | B22: =IF(OR(ISNUMBER(SEARCH("{", A22)),ISNUMBER(SEARCH("[", A22))), "", IFERROR(MID(A22, SEARCH("""", A22) +1, SEARCH("""", A22, SEARCH("""",A22) +1) - SEARCH("""", A22) -1), "")) -> postcode | C22: =IF(B22="", "", VLOOKUP(B22,'API Data Dictionary'!C:L,10,FALSE)) -> M | D22: =IF(B22="", "", VLOOKUP(B22,'API Data Dictionary'!C:D,2,FALSE)) -> string | E22: =IF(IF(B22="", "", VLOOKUP(B22,'API Data Dictionary'!C:E,3,FALSE))=0, "", IF(B22="", "", VLOOKUP(B22,'API Data Dictionary'!C:E,3,FALSE))) -> 50 | F22: =IF(IF(B22="", "", VLOOKUP(B22,'API Data Dictionary'!C:F,4,FALSE))=0, "", IF(B22="", "", VLOOKUP(B22,'API Data Dictionary'!C:F,4,FALSE))) | G22: =IF(IF(B22="", "", VLOOKUP(B22,'API Data Dictionary'!C:G,5,FALSE))=0, "", IF(B22="", "", VLOOKUP(B22,'API Data Dictionary'!C:G,5,FALSE))) -> the postcode of the property
A23: "ukCountryCode": 3 | B23: =IF(OR(ISNUMBER(SEARCH("{", A23)),ISNUMBER(SEARCH("[", A23))), "", IFERROR(MID(A23, SEARCH("""", A23) +1, SEARCH("""", A23, SEARCH("""",A23) +1) - SEARCH("""", A23) -1), "")) -> ukCountryCode | C23: =IF(B23="", "", VLOOKUP(B23,'API Data Dictionary'!C:L,10,FALSE)) -> M | D23: =IF(B23="", "", VLOOKUP(B23,'API Data Dictionary'!C:D,2,FALSE)) -> enum - UK Country List | E23: =IF(IF(B23="", "", VLOOKUP(B23,'API Data Dictionary'!C:E,3,FALSE))=0, "", IF(B23="", "", VLOOKUP(B23,'API Data Dictionary'!C:E,3,FALSE))) | F23: =IF(IF(B23="", "", VLOOKUP(B23,'API Data Dictionary'!C:F,4,FALSE))=0, "", IF(B23="", "", VLOOKUP(B23,'API Data Dictionary'!C:F,4,FALSE))) -> Valid Values 1-4 (See enum definition) | G23: =IF(IF(B23="", "", VLOOKUP(B23,'API Data Dictionary'!C:G,5,FALSE))=0, "", IF(B23="", "", VLOOKUP(B23,'API Data Dictionary'!C:G,5,FALSE))) -> The UK country Code
A24: }, | B24: =IF(OR(ISNUMBER(SEARCH("{", A24)),ISNUMBER(SEARCH("[", A24))), "", IFERROR(MID(A24, SEARCH("""", A24) +1, SEARCH("""", A24, SEARCH("""",A24) +1) - SEARCH("""", A24) -1), "")) | C24: =IF(B24="", "", VLOOKUP(B24,'API Data Dictionary'!C:L,10,FALSE)) | D24: =IF(B24="", "", VLOOKUP(B24,'API Data Dictionary'!C:D,2,FALSE)) | E24: =IF(IF(B24="", "", VLOOKUP(B24,'API Data Dictionary'!C:E,3,FALSE))=0, "", IF(B24="", "", VLOOKUP(B24,'API Data Dictionary'!C:E,3,FALSE))) | F24: =IF(IF(B24="", "", VLOOKUP(B24,'API Data Dictionary'!C:F,4,FALSE))=0, "", IF(B24="", "", VLOOKUP(B24,'API Data Dictionary'!C:F,4,FALSE))) | G24: =IF(IF(B24="", "", VLOOKUP(B24,'API Data Dictionary'!C:G,5,FALSE))=0, "", IF(B24="", "", VLOOKUP(B24,'API Data Dictionary'!C:G,5,FALSE)))
A25: "tenants": [ | B25: =IF(OR(ISNUMBER(SEARCH("{", A25)),ISNUMBER(SEARCH("[", A25))), "", IFERROR(MID(A25, SEARCH("""", A25) +1, SEARCH("""", A25, SEARCH("""",A25) +1) - SEARCH("""", A25) -1), "")) | C25: =IF(B25="", "", VLOOKUP(B25,'API Data Dictionary'!C:L,10,FALSE)) | D25: =IF(B25="", "", VLOOKUP(B25,'API Data Dictionary'!C:D,2,FALSE)) | E25: =IF(IF(B25="", "", VLOOKUP(B25,'API Data Dictionary'!C:E,3,FALSE))=0, "", IF(B25="", "", VLOOKUP(B25,'API Data Dictionary'!C:E,3,FALSE))) | F25: =IF(IF(B25="", "", VLOOKUP(B25,'API Data Dictionary'!C:F,4,FALSE))=0, "", IF(B25="", "", VLOOKUP(B25,'API Data Dictionary'!C:F,4,FALSE))) | G25: =IF(IF(B25="", "", VLOOKUP(B25,'API Data Dictionary'!C:G,5,FALSE))=0, "", IF(B25="", "", VLOOKUP(B25,'API Data Dictionary'!C:G,5,FALSE)))
A26: { | B26: =IF(OR(ISNUMBER(SEARCH("{", A26)),ISNUMBER(SEARCH("[", A26))), "", IFERROR(MID(A26, SEARCH("""", A26) +1, SEARCH("""", A26, SEARCH("""",A26) +1) - SEARCH("""", A26) -1), "")) | C26: =IF(B26="", "", VLOOKUP(B26,'API Data Dictionary'!C:L,10,FALSE)) | D26: =IF(B26="", "", VLOOKUP(B26,'API Data Dictionary'!C:D,2,FALSE)) | E26: =IF(IF(B26="", "", VLOOKUP(B26,'API Data Dictionary'!C:E,3,FALSE))=0, "", IF(B26="", "", VLOOKUP(B26,'API Data Dictionary'!C:E,3,FALSE))) | F26: =IF(IF(B26="", "", VLOOKUP(B26,'API Data Dictionary'!C:F,4,FALSE))=0, "", IF(B26="", "", VLOOKUP(B26,'API Data Dictionary'!C:F,4,FALSE))) | G26: =IF(IF(B26="", "", VLOOKUP(B26,'API Data Dictionary'!C:G,5,FALSE))=0, "", IF(B26="", "", VLOOKUP(B26,'API Data Dictionary'!C:G,5,FALSE)))
A27: "tenantTypeId": 1, | B27: =IF(OR(ISNUMBER(SEARCH("{", A27)),ISNUMBER(SEARCH("[", A27))), "", IFERROR(MID(A27, SEARCH("""", A27) +1, SEARCH("""", A27, SEARCH("""",A27) +1) - SEARCH("""", A27) -1), "")) -> tenantTypeId | C27: =IF(B27="", "", VLOOKUP(B27,'API Data Dictionary'!C:L,10,FALSE)) -> M | D27: =IF(B27="", "", VLOOKUP(B27,'API Data Dictionary'!C:D,2,FALSE)) -> enum - Tenant Type | E27: =IF(IF(B27="", "", VLOOKUP(B27,'API Data Dictionary'!C:E,3,FALSE))=0, "", IF(B27="", "", VLOOKUP(B27,'API Data Dictionary'!C:E,3,FALSE))) | F27: =IF(IF(B27="", "", VLOOKUP(B27,'API Data Dictionary'!C:F,4,FALSE))=0, "", IF(B27="", "", VLOOKUP(B27,'API Data Dictionary'!C:F,4,FALSE))) -> Valid Values 1-4 (See enum definition) | G27: =IF(IF(B27="", "", VLOOKUP(B27,'API Data Dictionary'!C:G,5,FALSE))=0, "", IF(B27="", "", VLOOKUP(B27,'API Data Dictionary'!C:G,5,FALSE))) -> The Type of the Tenant, e.g. lead or Guarantor
A28: "referenceType": 1, | B28: =IF(OR(ISNUMBER(SEARCH("{", A28)),ISNUMBER(SEARCH("[", A28))), "", IFERROR(MID(A28, SEARCH("""", A28) +1, SEARCH("""", A28, SEARCH("""",A28) +1) - SEARCH("""", A28) -1), "")) -> referenceType | C28: =IF(B28="", "", VLOOKUP(B28,'API Data Dictionary'!C:L,10,FALSE)) -> M | D28: =IF(B28="", "", VLOOKUP(B28,'API Data Dictionary'!C:D,2,FALSE)) -> enum - Reference Type | E28: =IF(IF(B28="", "", VLOOKUP(B28,'API Data Dictionary'!C:E,3,FALSE))=0, "", IF(B28="", "", VLOOKUP(B28,'API Data Dictionary'!C:E,3,FALSE))) | F28: =IF(IF(B28="", "", VLOOKUP(B28,'API Data Dictionary'!C:F,4,FALSE))=0, "", IF(B28="", "", VLOOKUP(B28,'API Data Dictionary'!C:F,4,FALSE))) -> Valid Values 1-2 (See enum definition) | G28: =IF(IF(B28="", "", VLOOKUP(B28,'API Data Dictionary'!C:G,5,FALSE))=0, "", IF(B28="", "", VLOOKUP(B28,'API Data Dictionary'!C:G,5,FALSE))) -> The Type of reference, e.g Full or Express
A29: "rightToRent": true, | B29: =IF(OR(ISNUMBER(SEARCH("{", A29)),ISNUMBER(SEARCH("[", A29))), "", IFERROR(MID(A29, SEARCH("""", A29) +1, SEARCH("""", A29, SEARCH("""",A29) +1) - SEARCH("""", A29) -1), "")) -> rightToRent | C29: =IF(B29="", "", VLOOKUP(B29,'API Data Dictionary'!C:L,10,FALSE)) -> M | D29: =IF(B29="", "", VLOOKUP(B29,'API Data Dictionary'!C:D,2,FALSE)) -> boolean | E29: =IF(IF(B29="", "", VLOOKUP(B29,'API Data Dictionary'!C:E,3,FALSE))=0, "", IF(B29="", "", VLOOKUP(B29,'API Data Dictionary'!C:E,3,FALSE))) | F29: =IF(IF(B29="", "", VLOOKUP(B29,'API Data Dictionary'!C:F,4,FALSE))=0, "", IF(B29="", "", VLOOKUP(B29,'API Data Dictionary'!C:F,4,FALSE))) | G29: =IF(IF(B29="", "", VLOOKUP(B29,'API Data Dictionary'!C:G,5,FALSE))=0, "", IF(B29="", "", VLOOKUP(B29,'API Data Dictionary'!C:G,5,FALSE))) -> Use Right to rent product for this reference
A30: "title": 1, | B30: =IF(OR(ISNUMBER(SEARCH("{", A30)),ISNUMBER(SEARCH("[", A30))), "", IFERROR(MID(A30, SEARCH("""", A30) +1, SEARCH("""", A30, SEARCH("""",A30) +1) - SEARCH("""", A30) -1), "")) -> title | C30: =IF(B30="", "", VLOOKUP(B30,'API Data Dictionary'!C:L,10,FALSE)) -> M | D30: =IF(B30="", "", VLOOKUP(B30,'API Data Dictionary'!C:D,2,FALSE)) -> enum - Title | E30: =IF(IF(B30="", "", VLOOKUP(B30,'API Data Dictionary'!C:E,3,FALSE))=0, "", IF(B30="", "", VLOOKUP(B30,'API Data Dictionary'!C:E,3,FALSE))) | F30: =IF(IF(B30="", "", VLOOKUP(B30,'API Data Dictionary'!C:F,4,FALSE))=0, "", IF(B30="", "", VLOOKUP(B30,'API Data Dictionary'!C:F,4,FALSE))) -> Valid Values 1-7 (See enum definition) | G30: =IF(IF(B30="", "", VLOOKUP(B30,'API Data Dictionary'!C:G,5,FALSE))=0, "", IF(B30="", "", VLOOKUP(B30,'API Data Dictionary'!C:G,5,FALSE))) -> The persons title, e.g. Mr, Mrs, etc.
A31: "otherTitle": "", | B31: =IF(OR(ISNUMBER(SEARCH("{", A31)),ISNUMBER(SEARCH("[", A31))), "", IFERROR(MID(A31, SEARCH("""", A31) +1, SEARCH("""", A31, SEARCH("""",A31) +1) - SEARCH("""", A31) -1), "")) -> otherTitle | C31: =IF(B31="", "", VLOOKUP(B31,'API Data Dictionary'!C:L,10,FALSE)) -> X | D31: =IF(B31="", "", VLOOKUP(B31,'API Data Dictionary'!C:D,2,FALSE)) -> string | E31: =IF(IF(B31="", "", VLOOKUP(B31,'API Data Dictionary'!C:E,3,FALSE))=0, "", IF(B31="", "", VLOOKUP(B31,'API Data Dictionary'!C:E,3,FALSE))) -> 100 | F31: =IF(IF(B31="", "", VLOOKUP(B31,'API Data Dictionary'!C:F,4,FALSE))=0, "", IF(B31="", "", VLOOKUP(B31,'API Data Dictionary'!C:F,4,FALSE))) | G31: =IF(IF(B31="", "", VLOOKUP(B31,'API Data Dictionary'!C:G,5,FALSE))=0, "", IF(B31="", "", VLOOKUP(B31,'API Data Dictionary'!C:G,5,FALSE))) -> If other is chosen for title, this is a text field to enter the specific title
A32: "firstName": "Berty", | B32: =IF(OR(ISNUMBER(SEARCH("{", A32)),ISNUMBER(SEARCH("[", A32))), "", IFERROR(MID(A32, SEARCH("""", A32) +1, SEARCH("""", A32, SEARCH("""",A32) +1) - SEARCH("""", A32) -1), "")) -> firstName | C32: =IF(B32="", "", VLOOKUP(B32,'API Data Dictionary'!C:L,10,FALSE)) -> M | D32: =IF(B32="", "", VLOOKUP(B32,'API Data Dictionary'!C:D,2,FALSE)) -> string | E32: =IF(IF(B32="", "", VLOOKUP(B32,'API Data Dictionary'!C:E,3,FALSE))=0, "", IF(B32="", "", VLOOKUP(B32,'API Data Dictionary'!C:E,3,FALSE))) -> 100 | F32: =IF(IF(B32="", "", VLOOKUP(B32,'API Data Dictionary'!C:F,4,FALSE))=0, "", IF(B32="", "", VLOOKUP(B32,'API Data Dictionary'!C:F,4,FALSE))) -> pattern: ^[a-zA-Z0-9\-' ]*$ | G32: =IF(IF(B32="", "", VLOOKUP(B32,'API Data Dictionary'!C:G,5,FALSE))=0, "", IF(B32="", "", VLOOKUP(B32,'API Data Dictionary'!C:G,5,FALSE))) -> First name, validated against the RegEx pattern
... A41: } | B41: =IF(OR(ISNUMBER(SEARCH("{", A41)),ISNUMBER(SEARCH("[", A41))), "", IFERROR(MID(A41, SEARCH("""", A41) +1, SEARCH("""", A41, SEARCH("""",A41) +1) - SEARCH("""", A41) -1), "")) | C41: =IF(B41="", "", VLOOKUP(B41,'API Data Dictionary'!C:L,10,FALSE)) | D41: =IF(B41="", "", VLOOKUP(B41,'API Data Dictionary'!C:D,2,FALSE)) | E41: =IF(IF(B41="", "", VLOOKUP(B41,'API Data Dictionary'!C:E,3,FALSE))=0, "", IF(B41="", "", VLOOKUP(B41,'API Data Dictionary'!C:E,3,FALSE))) | F41: =IF(IF(B41="", "", VLOOKUP(B41,'API Data Dictionary'!C:F,4,FALSE))=0, "", IF(B41="", "", VLOOKUP(B41,'API Data Dictionary'!C:F,4,FALSE))) | G41: =IF(IF(B41="", "", VLOOKUP(B41,'API Data Dictionary'!C:G,5,FALSE))=0, "", IF(B41="", "", VLOOKUP(B41,'API Data Dictionary'!C:G,5,FALSE)))
A43: Response Example: Success - 200
A44: { | B44: =IF(OR(ISNUMBER(SEARCH("{", A44)),ISNUMBER(SEARCH("[", A44))), "", IFERROR(MID(A44, SEARCH("""", A44) +1, SEARCH("""", A44, SEARCH("""",A44) +1) - SEARCH("""", A44) -1), "")) | C44: =IF(B44="", "", VLOOKUP(B44,'API Data Dictionary'!C:L,10,FALSE)) | D44: =IF(B44="", "", VLOOKUP(B44,'API Data Dictionary'!C:D,2,FALSE)) | E44: =IF(IF(B44="", "", VLOOKUP(B44,'API Data Dictionary'!C:E,3,FALSE))=0, "", IF(B44="", "", VLOOKUP(B44,'API Data Dictionary'!C:E,3,FALSE))) | F44: =IF(IF(B44="", "", VLOOKUP(B44,'API Data Dictionary'!C:F,4,FALSE))=0, "", IF(B44="", "", VLOOKUP(B44,'API Data Dictionary'!C:F,4,FALSE))) | G44: =IF(IF(B44="", "", VLOOKUP(B44,'API Data Dictionary'!C:G,5,FALSE))=0, "", IF(B44="", "", VLOOKUP(B44,'API Data Dictionary'!C:G,5,FALSE)))
A45: "success": true, | B45: =IF(OR(ISNUMBER(SEARCH("{", A45)),ISNUMBER(SEARCH("[", A45))), "", IFERROR(MID(A45, SEARCH("""", A45) +1, SEARCH("""", A45, SEARCH("""",A45) +1) - SEARCH("""", A45) -1), "")) -> success | C45: M | D45: =IF(B45="", "", VLOOKUP(B45,'API Data Dictionary'!C:D,2,FALSE)) -> string - Boolean | E45: =IF(IF(B45="", "", VLOOKUP(B45,'API Data Dictionary'!C:E,3,FALSE))=0, "", IF(B45="", "", VLOOKUP(B45,'API Data Dictionary'!C:E,3,FALSE))) -> 100 | F45: =IF(IF(B45="", "", VLOOKUP(B45,'API Data Dictionary'!C:F,4,FALSE))=0, "", IF(B45="", "", VLOOKUP(B45,'API Data Dictionary'!C:F,4,FALSE))) | G45: =IF(IF(B45="", "", VLOOKUP(B45,'API Data Dictionary'!C:G,5,FALSE))=0, "", IF(B45="", "", VLOOKUP(B45,'API Data Dictionary'!C:G,5,FALSE))) -> Returns true when successful call/connection
A46: "payload": { | B46: =IF(OR(ISNUMBER(SEARCH("{", A46)),ISNUMBER(SEARCH("[", A46))), "", IFERROR(MID(A46, SEARCH("""", A46) +1, SEARCH("""", A46, SEARCH("""",A46) +1) - SEARCH("""", A46) -1), "")) | C46: =IF(B46="", "", VLOOKUP(B46,'API Data Dictionary'!C:L,10,FALSE)) | D46: =IF(B46="", "", VLOOKUP(B46,'API Data Dictionary'!C:D,2,FALSE)) | E46: =IF(IF(B46="", "", VLOOKUP(B46,'API Data Dictionary'!C:E,3,FALSE))=0, "", IF(B46="", "", VLOOKUP(B46,'API Data Dictionary'!C:E,3,FALSE))) | F46: =IF(IF(B46="", "", VLOOKUP(B46,'API Data Dictionary'!C:F,4,FALSE))=0, "", IF(B46="", "", VLOOKUP(B46,'API Data Dictionary'!C:F,4,FALSE))) | G46: =IF(IF(B46="", "", VLOOKUP(B46,'API Data Dictionary'!C:G,5,FALSE))=0, "", IF(B46="", "", VLOOKUP(B46,'API Data Dictionary'!C:G,5,FALSE)))
A47: "agentCode": "9999", | B47: =IF(OR(ISNUMBER(SEARCH("{", A47)),ISNUMBER(SEARCH("[", A47))), "", IFERROR(MID(A47, SEARCH("""", A47) +1, SEARCH("""", A47, SEARCH("""",A47) +1) - SEARCH("""", A47) -1), "")) -> agentCode | C47: =IF(B47="", "", VLOOKUP(B47,'API Data Dictionary'!C:L,10,FALSE)) -> M | D47: =IF(B47="", "", VLOOKUP(B47,'API Data Dictionary'!C:D,2,FALSE)) -> string | E47: =IF(IF(B47="", "", VLOOKUP(B47,'API Data Dictionary'!C:E,3,FALSE))=0, "", IF(B47="", "", VLOOKUP(B47,'API Data Dictionary'!C:E,3,FALSE))) -> 50 | F47: =IF(IF(B47="", "", VLOOKUP(B47,'API Data Dictionary'!C:F,4,FALSE))=0, "", IF(B47="", "", VLOOKUP(B47,'API Data Dictionary'!C:F,4,FALSE))) | G47: =IF(IF(B47="", "", VLOOKUP(B47,'API Data Dictionary'!C:G,5,FALSE))=0, "", IF(B47="", "", VLOOKUP(B47,'API Data Dictionary'!C:G,5,FALSE))) -> AgentCode is the Unique Key provided to the Agent when onboarding as a Barbon Customer. An AgentID may be linked to many Properties being managed by that Agent and Each property may be linked to 1 or more TenancyID's.
A48: "propertyTenancyId": 85670, | B48: =IF(OR(ISNUMBER(SEARCH("{", A48)),ISNUMBER(SEARCH("[", A48))), "", IFERROR(MID(A48, SEARCH("""", A48) +1, SEARCH("""", A48, SEARCH("""",A48) +1) - SEARCH("""", A48) -1), "")) -> propertyTenancyId | C48: M | D48: =IF(B48="", "", VLOOKUP(B48,'API Data Dictionary'!C:D,2,FALSE)) -> integer | E48: =IF(IF(B48="", "", VLOOKUP(B48,'API Data Dictionary'!C:E,3,FALSE))=0, "", IF(B48="", "", VLOOKUP(B48,'API Data Dictionary'!C:E,3,FALSE))) | F48: =IF(IF(B48="", "", VLOOKUP(B48,'API Data Dictionary'!C:F,4,FALSE))=0, "", IF(B48="", "", VLOOKUP(B48,'API Data Dictionary'!C:F,4,FALSE))) | G48: =IF(IF(B48="", "", VLOOKUP(B48,'API Data Dictionary'!C:G,5,FALSE))=0, "", IF(B48="", "", VLOOKUP(B48,'API Data Dictionary'!C:G,5,FALSE))) -> The ID of the property tenancy
A49: "ReferencingApplicantList": [ | B49: =IF(OR(ISNUMBER(SEARCH("{", A49)),ISNUMBER(SEARCH("[", A49))), "", IFERROR(MID(A49, SEARCH("""", A49) +1, SEARCH("""", A49, SEARCH("""",A49) +1) - SEARCH("""", A49) -1), "")) | C49: =IF(B49="", "", VLOOKUP(B49,'API Data Dictionary'!C:L,10,FALSE)) | D49: =IF(B49="", "", VLOOKUP(B49,'API Data Dictionary'!C:D,2,FALSE)) | E49: =IF(IF(B49="", "", VLOOKUP(B49,'API Data Dictionary'!C:E,3,FALSE))=0, "", IF(B49="", "", VLOOKUP(B49,'API Data Dictionary'!C:E,3,FALSE))) | F49: =IF(IF(B49="", "", VLOOKUP(B49,'API Data Dictionary'!C:F,4,FALSE))=0, "", IF(B49="", "", VLOOKUP(B49,'API Data Dictionary'!C:F,4,FALSE))) | G49: =IF(IF(B49="", "", VLOOKUP(B49,'API Data Dictionary'!C:G,5,FALSE))=0, "", IF(B49="", "", VLOOKUP(B49,'API Data Dictionary'!C:G,5,FALSE)))
A50: { | B50: =IF(OR(ISNUMBER(SEARCH("{", A50)),ISNUMBER(SEARCH("[", A50))), "", IFERROR(MID(A50, SEARCH("""", A50) +1, SEARCH("""", A50, SEARCH("""",A50) +1) - SEARCH("""", A50) -1), "")) | C50: =IF(B50="", "", VLOOKUP(B50,'API Data Dictionary'!C:L,10,FALSE)) | D50: =IF(B50="", "", VLOOKUP(B50,'API Data Dictionary'!C:D,2,FALSE)) | E50: =IF(IF(B50="", "", VLOOKUP(B50,'API Data Dictionary'!C:E,3,FALSE))=0, "", IF(B50="", "", VLOOKUP(B50,'API Data Dictionary'!C:E,3,FALSE))) | F50: =IF(IF(B50="", "", VLOOKUP(B50,'API Data Dictionary'!C:F,4,FALSE))=0, "", IF(B50="", "", VLOOKUP(B50,'API Data Dictionary'!C:F,4,FALSE))) | G50: =IF(IF(B50="", "", VLOOKUP(B50,'API Data Dictionary'!C:G,5,FALSE))=0, "", IF(B50="", "", VLOOKUP(B50,'API Data Dictionary'!C:G,5,FALSE)))
A51: "applicantID": 678007, | B51: =IF(OR(ISNUMBER(SEARCH("{", A51)),ISNUMBER(SEARCH("[", A51))), "", IFERROR(MID(A51, SEARCH("""", A51) +1, SEARCH("""", A51, SEARCH("""",A51) +1) - SEARCH("""", A51) -1), "")) -> applicantID | C51: M | D51: =IF(B51="", "", VLOOKUP(B51,'API Data Dictionary'!C:D,2,FALSE)) -> integer | E51: =IF(IF(B51="", "", VLOOKUP(B51,'API Data Dictionary'!C:E,3,FALSE))=0, "", IF(B51="", "", VLOOKUP(B51,'API Data Dictionary'!C:E,3,FALSE))) | F51: =IF(IF(B51="", "", VLOOKUP(B51,'API Data Dictionary'!C:F,4,FALSE))=0, "", IF(B51="", "", VLOOKUP(B51,'API Data Dictionary'!C:F,4,FALSE))) | G51: =IF(IF(B51="", "", VLOOKUP(B51,'API Data Dictionary'!C:G,5,FALSE))=0, "", IF(B51="", "", VLOOKUP(B51,'API Data Dictionary'!C:G,5,FALSE))) -> ApplicantID is a unique identifier for a person / Company to be referenced. ApplicantID is created through API Methods: CreateReferenceWithAllData CreateReferenceWithInputFromApplicant CreateCompanyReferenceWithAllData CreateCompanyReferenceWithInputFromApplicant AddApplicantToTenancy
A52: "applicantName": "Mr Berty Boo Basset" | B52: =IF(OR(ISNUMBER(SEARCH("{", A52)),ISNUMBER(SEARCH("[", A52))), "", IFERROR(MID(A52, SEARCH("""", A52) +1, SEARCH("""", A52, SEARCH("""",A52) +1) - SEARCH("""", A52) -1), "")) -> applicantName | C52: M | D52: string | E52: 50 | G52: The Applicants name, made up of title, firstname, middlename and surname
A53: "emailAddress": "test@testtesttest.test" | B53: emailAddress | C53: M | D53: string ($email) | E53: 200 | F53: pattern: ^(?!.*\.\.)(?!.*\\_\\_)(?!.*\-\-)[a-zA-Z0-9][-a-zA-Z0-9._]+[a-zA-Z0-9]@([-a-zA-Z0-9]+.)+[a-zA-Z]{2,5}$ | G53: The email address
A54: } | B54: =IF(OR(ISNUMBER(SEARCH("{", A54)),ISNUMBER(SEARCH("[", A54))), "", IFERROR(MID(A54, SEARCH("""", A54) +1, SEARCH("""", A54, SEARCH("""",A54) +1) - SEARCH("""", A54) -1), "")) | C54: =IF(B54="", "", VLOOKUP(B54,'API Data Dictionary'!C:L,10,FALSE)) | D54: =IF(B54="", "", VLOOKUP(B54,'API Data Dictionary'!C:D,2,FALSE)) | E54: =IF(IF(B54="", "", VLOOKUP(B54,'API Data Dictionary'!C:E,3,FALSE))=0, "", IF(B54="", "", VLOOKUP(B54,'API Data Dictionary'!C:E,3,FALSE))) | F54: =IF(IF(B54="", "", VLOOKUP(B54,'API Data Dictionary'!C:F,4,FALSE))=0, "", IF(B54="", "", VLOOKUP(B54,'API Data Dictionary'!C:F,4,FALSE))) | G54: =IF(IF(B55="", "", VLOOKUP(B55,'API Data Dictionary'!C:G,5,FALSE))=0, "", IF(B55="", "", VLOOKUP(B55,'API Data Dictionary'!C:G,5,FALSE)))
A55: ] | B55: =IF(OR(ISNUMBER(SEARCH("{", A55)),ISNUMBER(SEARCH("[", A55))), "", IFERROR(MID(A55, SEARCH("""", A55) +1, SEARCH("""", A55, SEARCH("""",A55) +1) - SEARCH("""", A55) -1), "")) | C55: =IF(B55="", "", VLOOKUP(B55,'API Data Dictionary'!C:L,10,FALSE)) | D55: =IF(B55="", "", VLOOKUP(B55,'API Data Dictionary'!C:D,2,FALSE)) | E55: =IF(IF(B55="", "", VLOOKUP(B55,'API Data Dictionary'!C:E,3,FALSE))=0, "", IF(B55="", "", VLOOKUP(B55,'API Data Dictionary'!C:E,3,FALSE))) | F55: =IF(IF(B55="", "", VLOOKUP(B55,'API Data Dictionary'!C:F,4,FALSE))=0, "", IF(B55="", "", VLOOKUP(B55,'API Data Dictionary'!C:F,4,FALSE))) | G55: =IF(IF(B56="", "", VLOOKUP(B56,'API Data Dictionary'!C:G,5,FALSE))=0, "", IF(B56="", "", VLOOKUP(B56,'API Data Dictionary'!C:G,5,FALSE)))
A56: }, | B56: =IF(OR(ISNUMBER(SEARCH("{", A56)),ISNUMBER(SEARCH("[", A56))), "", IFERROR(MID(A56, SEARCH("""", A56) +1, SEARCH("""", A56, SEARCH("""",A56) +1) - SEARCH("""", A56) -1), "")) | C56: =IF(B56="", "", VLOOKUP(B56,'API Data Dictionary'!C:L,10,FALSE)) | D56: =IF(B56="", "", VLOOKUP(B56,'API Data Dictionary'!C:D,2,FALSE)) | E56: =IF(IF(B56="", "", VLOOKUP(B56,'API Data Dictionary'!C:E,3,FALSE))=0, "", IF(B56="", "", VLOOKUP(B56,'API Data Dictionary'!C:E,3,FALSE))) | F56: =IF(IF(B56="", "", VLOOKUP(B56,'API Data Dictionary'!C:F,4,FALSE))=0, "", IF(B56="", "", VLOOKUP(B56,'API Data Dictionary'!C:F,4,FALSE))) | G56: =IF(IF(B57="", "", VLOOKUP(B57,'API Data Dictionary'!C:G,5,FALSE))=0, "", IF(B57="", "", VLOOKUP(B57,'API Data Dictionary'!C:G,5,FALSE))) -> return value, null or success, unless there has been error
A57: "message": "Applicant created successfully." | B57: =IF(OR(ISNUMBER(SEARCH("{", A57)),ISNUMBER(SEARCH("[", A57))), "", IFERROR(MID(A57, SEARCH("""", A57) +1, SEARCH("""", A57, SEARCH("""",A57) +1) - SEARCH("""", A57) -1), "")) -> message | C57: M | D57: =IF(B57="", "", VLOOKUP(B57,'API Data Dictionary'!C:D,2,FALSE)) -> string | E57: =IF(IF(B57="", "", VLOOKUP(B57,'API Data Dictionary'!C:E,3,FALSE))=0, "", IF(B57="", "", VLOOKUP(B57,'API Data Dictionary'!C:E,3,FALSE))) -> 100 | F57: =IF(IF(B57="", "", VLOOKUP(B57,'API Data Dictionary'!C:F,4,FALSE))=0, "", IF(B57="", "", VLOOKUP(B57,'API Data Dictionary'!C:F,4,FALSE))) | G57: =IF(IF(B58="", "", VLOOKUP(B58,'API Data Dictionary'!C:G,5,FALSE))=0, "", IF(B58="", "", VLOOKUP(B58,'API Data Dictionary'!C:G,5,FALSE)))
A58: } | B58: =IF(OR(ISNUMBER(SEARCH("{", A58)),ISNUMBER(SEARCH("[", A58))), "", IFERROR(MID(A58, SEARCH("""", A58) +1, SEARCH("""", A58, SEARCH("""",A58) +1) - SEARCH("""", A58) -1), "")) | C58: =IF(B58="", "", VLOOKUP(B58,'API Data Dictionary'!C:L,10,FALSE)) | D58: =IF(B58="", "", VLOOKUP(B58,'API Data Dictionary'!C:D,2,FALSE)) | E58: =IF(IF(B58="", "", VLOOKUP(B58,'API Data Dictionary'!C:E,3,FALSE))=0, "", IF(B58="", "", VLOOKUP(B58,'API Data Dictionary'!C:E,3,FALSE))) | F58: =IF(IF(B58="", "", VLOOKUP(B58,'API Data Dictionary'!C:F,4,FALSE))=0, "", IF(B58="", "", VLOOKUP(B58,'API Data Dictionary'!C:F,4,FALSE)))
A60: Response Example: Fail - 401 Unauthorised Error | G60: Returns a 401 error if not authorised
A61: 401 Error: Unauthorized | B61: N/A | C61: N/A | D61: string | E61: 100
A63: Response Example: Fail - 403 Forbidden | G63: Returns a 403 error if foribidden
A64: 403 Error: Forbidden | B64: N/A | C64: N/A | D64: string | E64: 100
A66: Response Example: Fail - 422 field Validation Error | G66: =IF(IF(B67="", "", VLOOKUP(B67,'API Data Dictionary'!C:G,5,FALSE))=0, "", IF(B67="", "", VLOOKUP(B67,'API Data Dictionary'!C:G,5,FALSE)))
A67: { | B67: =IF(OR(ISNUMBER(SEARCH("{", A67)),ISNUMBER(SEARCH("[", A67))), "", IFERROR(MID(A67, SEARCH("""", A67) +1, SEARCH("""", A67, SEARCH("""",A67) +1) - SEARCH("""", A67) -1), "")) | D67: =IF(B67="", "", VLOOKUP(B67,'API Data Dictionary'!C:D,2,FALSE)) | E67: =IF(IF(B67="", "", VLOOKUP(B67,'API Data Dictionary'!C:E,3,FALSE))=0, "", IF(B67="", "", VLOOKUP(B67,'API Data Dictionary'!C:E,3,FALSE))) | F67: =IF(IF(B67="", "", VLOOKUP(B67,'API Data Dictionary'!C:F,4,FALSE))=0, "", IF(B67="", "", VLOOKUP(B67,'API Data Dictionary'!C:F,4,FALSE))) | G67: =IF(IF(B68="", "", VLOOKUP(B68,'API Data Dictionary'!C:G,5,FALSE))=0, "", IF(B68="", "", VLOOKUP(B68,'API Data Dictionary'!C:G,5,FALSE))) -> Returns true when successful call/connection
A68: "success": false, | B68: =IF(OR(ISNUMBER(SEARCH("{", A68)),ISNUMBER(SEARCH("[", A68))), "", IFERROR(MID(A68, SEARCH("""", A68) +1, SEARCH("""", A68, SEARCH("""",A68) +1) - SEARCH("""", A68) -1), "")) -> success | C68: M | D68: =IF(B68="", "", VLOOKUP(B68,'API Data Dictionary'!C:D,2,FALSE)) -> string - Boolean | E68: =IF(IF(B68="", "", VLOOKUP(B68,'API Data Dictionary'!C:E,3,FALSE))=0, "", IF(B68="", "", VLOOKUP(B68,'API Data Dictionary'!C:E,3,FALSE))) -> 100 | F68: =IF(IF(B68="", "", VLOOKUP(B68,'API Data Dictionary'!C:F,4,FALSE))=0, "", IF(B68="", "", VLOOKUP(B68,'API Data Dictionary'!C:F,4,FALSE))) | G68: =IF(IF(B69="", "", VLOOKUP(B69,'API Data Dictionary'!C:G,5,FALSE))=0, "", IF(B69="", "", VLOOKUP(B69,'API Data Dictionary'!C:G,5,FALSE)))
A69: "payload": { | B69: =IF(OR(ISNUMBER(SEARCH("{", A69)),ISNUMBER(SEARCH("[", A69))), "", IFERROR(MID(A69, SEARCH("""", A69) +1, SEARCH("""", A69, SEARCH("""",A69) +1) - SEARCH("""", A69) -1), "")) | C69: =IF(B69="", "", VLOOKUP(B69,'API Data Dictionary'!C:L,10,FALSE)) | D69: =IF(B69="", "", VLOOKUP(B69,'API Data Dictionary'!C:D,2,FALSE)) | E69: =IF(IF(B69="", "", VLOOKUP(B69,'API Data Dictionary'!C:E,3,FALSE))=0, "", IF(B69="", "", VLOOKUP(B69,'API Data Dictionary'!C:E,3,FALSE))) | F69: =IF(IF(B69="", "", VLOOKUP(B69,'API Data Dictionary'!C:F,4,FALSE))=0, "", IF(B69="", "", VLOOKUP(B69,'API Data Dictionary'!C:F,4,FALSE)))
A70: "errors": { | B70: Error Container | C70: M | D70: collection
A71: "AgentCode": [ | B71: Error Field | C71: M | D71: string | E71: max
A72: "Error in request: Invalid AgentCode. AgentCode should be as Authenticated Agent: 99999" | B72: Error Field Message | C72: M | D72: string | E72: max
A73: ], | B73: =IF(OR(ISNUMBER(SEARCH("{", A73)),ISNUMBER(SEARCH("[", A73))), "", IFERROR(MID(A73, SEARCH("""", A73) +1, SEARCH("""", A73, SEARCH("""",A73) +1) - SEARCH("""", A73) -1), "")) | C73: =IF(B73="", "", VLOOKUP(B73,'API Data Dictionary'!C:L,10,FALSE)) | D73: =IF(B73="", "", VLOOKUP(B73,'API Data Dictionary'!C:D,2,FALSE))
A74: "EstimatedMoveInDate": [ | B74: Error Field | C74: M | D74: string | E74: max
A75: "Error in Request. Invalid: EstimatedMoveInDate must be future date." | B75: Error Field Message | C75: M | D75: string | E75: max
A76: ] | B76: =IF(OR(ISNUMBER(SEARCH("{", A76)),ISNUMBER(SEARCH("[", A76))), "", IFERROR(MID(A76, SEARCH("""", A76) +1, SEARCH("""", A76, SEARCH("""",A76) +1) - SEARCH("""", A76) -1), "")) | C76: =IF(B76="", "", VLOOKUP(B76,'API Data Dictionary'!C:L,10,FALSE)) | D76: =IF(B76="", "", VLOOKUP(B76,'API Data Dictionary'!C:D,2,FALSE))
A77: }, | B77: =IF(OR(ISNUMBER(SEARCH("{", A77)),ISNUMBER(SEARCH("[", A77))), "", IFERROR(MID(A77, SEARCH("""", A77) +1, SEARCH("""", A77, SEARCH("""",A77) +1) - SEARCH("""", A77) -1), "")) | C77: =IF(B77="", "", VLOOKUP(B77,'API Data Dictionary'!C:L,10,FALSE)) | D77: =IF(B77="", "", VLOOKUP(B77,'API Data Dictionary'!C:D,2,FALSE))
A78: "title": "2 validation errors occurred.", | B78: Error Title | C78: M | D78: string | E78: max
A79: "detail": "See the errors property for details" | B79: Error Detail | C79: M | D79: string | E79: max | G79: =IF(IF(B80="", "", VLOOKUP(B80,'API Data Dictionary'!C:G,5,FALSE))=0, "", IF(B80="", "", VLOOKUP(B80,'API Data Dictionary'!C:G,5,FALSE)))
A80: }, | B80: =IF(OR(ISNUMBER(SEARCH("{", A80)),ISNUMBER(SEARCH("[", A80))), "", IFERROR(MID(A80, SEARCH("""", A80) +1, SEARCH("""", A80, SEARCH("""",A80) +1) - SEARCH("""", A80) -1), "")) | C80: =IF(B80="", "", VLOOKUP(B80,'API Data Dictionary'!C:L,10,FALSE)) | D80: =IF(B80="", "", VLOOKUP(B80,'API Data Dictionary'!C:D,2,FALSE)) | E80: =IF(IF(B80="", "", VLOOKUP(B80,'API Data Dictionary'!C:E,3,FALSE))=0, "", IF(B80="", "", VLOOKUP(B80,'API Data Dictionary'!C:E,3,FALSE))) | F80: =IF(IF(B80="", "", VLOOKUP(B80,'API Data Dictionary'!C:F,4,FALSE))=0, "", IF(B80="", "", VLOOKUP(B80,'API Data Dictionary'!C:F,4,FALSE)))
A81: "message": "Error in Request. Invalid: AgentCode, EstimatedMoveInDate" | B81: Error Message | C81: M | D81: string | E81: max | G81: =IF(IF(B82="", "", VLOOKUP(B82,'API Data Dictionary'!C:G,5,FALSE))=0, "", IF(B82="", "", VLOOKUP(B82,'API Data Dictionary'!C:G,5,FALSE)))
A82: } | B82: =IF(OR(ISNUMBER(SEARCH("{", A82)),ISNUMBER(SEARCH("[", A82))), "", IFERROR(MID(A82, SEARCH("""", A82) +1, SEARCH("""", A82, SEARCH("""",A82) +1) - SEARCH("""", A82) -1), "")) | D82: =IF(B82="", "", VLOOKUP(B82,'API Data Dictionary'!C:D,2,FALSE)) | E82: =IF(IF(B82="", "", VLOOKUP(B82,'API Data Dictionary'!C:E,3,FALSE))=0, "", IF(B82="", "", VLOOKUP(B82,'API Data Dictionary'!C:E,3,FALSE))) | F82: =IF(IF(B82="", "", VLOOKUP(B82,'API Data Dictionary'!C:F,4,FALSE))=0, "", IF(B82="", "", VLOOKUP(B82,'API Data Dictionary'!C:F,4,FALSE)))
A84: Response Example: Fail - 500 internal Error (post validation) | G84: =IF(IF(B85="", "", VLOOKUP(B85,'API Data Dictionary'!C:G,5,FALSE))=0, "", IF(B85="", "", VLOOKUP(B85,'API Data Dictionary'!C:G,5,FALSE)))
A85: { | B85: =IF(OR(ISNUMBER(SEARCH("{", A85)),ISNUMBER(SEARCH("[", A85))), "", IFERROR(MID(A85, SEARCH("""", A85) +1, SEARCH("""", A85, SEARCH("""",A85) +1) - SEARCH("""", A85) -1), "")) | C85: =IF(B85="", "", VLOOKUP(B85,'API Data Dictionary'!C:J,8,FALSE)) | D85: =IF(B85="", "", VLOOKUP(B85,'API Data Dictionary'!C:D,2,FALSE)) | E85: =IF(IF(B85="", "", VLOOKUP(B85,'API Data Dictionary'!C:E,3,FALSE))=0, "", IF(B85="", "", VLOOKUP(B85,'API Data Dictionary'!C:E,3,FALSE))) | F85: =IF(IF(B85="", "", VLOOKUP(B85,'API Data Dictionary'!C:F,4,FALSE))=0, "", IF(B85="", "", VLOOKUP(B85,'API Data Dictionary'!C:F,4,FALSE))) | G85: =IF(IF(B86="", "", VLOOKUP(B86,'API Data Dictionary'!C:G,5,FALSE))=0, "", IF(B86="", "", VLOOKUP(B86,'API Data Dictionary'!C:G,5,FALSE))) -> Returns true when successful call/connection
A86: "success": false, | B86: =IF(OR(ISNUMBER(SEARCH("{", A86)),ISNUMBER(SEARCH("[", A86))), "", IFERROR(MID(A86, SEARCH("""", A86) +1, SEARCH("""", A86, SEARCH("""",A86) +1) - SEARCH("""", A86) -1), "")) -> success | C86: M | D86: =IF(B86="", "", VLOOKUP(B86,'API Data Dictionary'!C:D,2,FALSE)) -> string - Boolean | E86: =IF(IF(B86="", "", VLOOKUP(B86,'API Data Dictionary'!C:E,3,FALSE))=0, "", IF(B86="", "", VLOOKUP(B86,'API Data Dictionary'!C:E,3,FALSE))) -> 100 | F86: =IF(IF(B86="", "", VLOOKUP(B86,'API Data Dictionary'!C:F,4,FALSE))=0, "", IF(B86="", "", VLOOKUP(B86,'API Data Dictionary'!C:F,4,FALSE))) | G86: =IF(IF(B87="", "", VLOOKUP(B87,'API Data Dictionary'!C:G,5,FALSE))=0, "", IF(B87="", "", VLOOKUP(B87,'API Data Dictionary'!C:G,5,FALSE))) -> Returns healthy when connection has worked properly
A87: "payload": null | B87: =IF(OR(ISNUMBER(SEARCH("{", A87)),ISNUMBER(SEARCH("[", A87))), "", IFERROR(MID(A87, SEARCH("""", A87) +1, SEARCH("""", A87, SEARCH("""",A87) +1) - SEARCH("""", A87) -1), "")) -> payload | C87: M | D87: =IF(B87="", "", VLOOKUP(B87,'API Data Dictionary'!C:D,2,FALSE)) -> string | E87: =IF(IF(B87="", "", VLOOKUP(B87,'API Data Dictionary'!C:E,3,FALSE))=0, "", IF(B87="", "", VLOOKUP(B87,'API Data Dictionary'!C:E,3,FALSE))) -> 100 | F87: =IF(IF(B87="", "", VLOOKUP(B87,'API Data Dictionary'!C:F,4,FALSE))=0, "", IF(B87="", "", VLOOKUP(B87,'API Data Dictionary'!C:F,4,FALSE))) | G87: =IF(IF(B88="", "", VLOOKUP(B88,'API Data Dictionary'!C:G,5,FALSE))=0, "", IF(B88="", "", VLOOKUP(B88,'API Data Dictionary'!C:G,5,FALSE))) -> return value, null or success, unless there has been error
A88: "message": "Internal error" | B88: =IF(OR(ISNUMBER(SEARCH("{", A88)),ISNUMBER(SEARCH("[", A88))), "", IFERROR(MID(A88, SEARCH("""", A88) +1, SEARCH("""", A88, SEARCH("""",A88) +1) - SEARCH("""", A88) -1), "")) -> message | C88: M | D88: =IF(B88="", "", VLOOKUP(B88,'API Data Dictionary'!C:D,2,FALSE)) -> string | E88: =IF(IF(B88="", "", VLOOKUP(B88,'API Data Dictionary'!C:E,3,FALSE))=0, "", IF(B88="", "", VLOOKUP(B88,'API Data Dictionary'!C:E,3,FALSE))) -> 100 | F88: =IF(IF(B88="", "", VLOOKUP(B88,'API Data Dictionary'!C:F,4,FALSE))=0, "", IF(B88="", "", VLOOKUP(B88,'API Data Dictionary'!C:F,4,FALSE))) | G88: =IF(IF(B89="", "", VLOOKUP(B89,'API Data Dictionary'!C:G,5,FALSE))=0, "", IF(B89="", "", VLOOKUP(B89,'API Data Dictionary'!C:G,5,FALSE)))
A89: } | B89: =IF(OR(ISNUMBER(SEARCH("{", A89)),ISNUMBER(SEARCH("[", A89))), "", IFERROR(MID(A89, SEARCH("""", A89) +1, SEARCH("""", A89, SEARCH("""",A89) +1) - SEARCH("""", A89) -1), "")) | C89: =IF(B89="", "", VLOOKUP(B89,'API Data Dictionary'!C:J,8,FALSE)) | D89: =IF(B89="", "", VLOOKUP(B89,'API Data Dictionary'!C:D,2,FALSE)) | E89: =IF(IF(B89="", "", VLOOKUP(B89,'API Data Dictionary'!C:E,3,FALSE))=0, "", IF(B89="", "", VLOOKUP(B89,'API Data Dictionary'!C:E,3,FALSE))) | F89: =IF(IF(B89="", "", VLOOKUP(B89,'API Data Dictionary'!C:F,4,FALSE))=0, "", IF(B89="", "", VLOOKUP(B89,'API Data Dictionary'!C:F,4,FALSE)))

Sheet CreateReferenceWithInputFromApp
A1: CreateReferenceWithInputFromApplicant Example JSON | B1: Vision+ API Field Name | C1: Mandatory Field | D1: Field Type | E1: API Max Field Length | F1: Field Validations | G1: Field Description
A2: Request Example
A3: { | B3: =IF(OR(ISNUMBER(SEARCH("{", A3)),ISNUMBER(SEARCH("[", A3))), "", IFERROR(MID(A3, SEARCH("""", A3) +1, SEARCH("""", A3, SEARCH("""",A3) +1) - SEARCH("""", A3) -1), "")) | C3: =IF(B3="", "", VLOOKUP(B3,'API Data Dictionary'!C:L,10,FALSE)) | D3: =IF(B3="", "", VLOOKUP(B3,'API Data Dictionary'!C:D,2,FALSE)) | E3: =IF(IF(B3="", "", VLOOKUP(B3,'API Data Dictionary'!C:E,3,FALSE))=0, "", IF(B3="", "", VLOOKUP(B3,'API Data Dictionary'!C:E,3,FALSE))) | F3: =IF(IF(B3="", "", VLOOKUP(B3,'API Data Dictionary'!C:F,4,FALSE))=0, "", IF(B3="", "", VLOOKUP(B3,'API Data Dictionary'!C:F,4,FALSE))) | G3: =IF(IF(B3="", "", VLOOKUP(B3,'API Data Dictionary'!C:G,5,FALSE))=0, "", IF(B3="", "", VLOOKUP(B3,'API Data Dictionary'!C:G,5,FALSE)))
A4: "agentCode": "9999", | B4: =IF(OR(ISNUMBER(SEARCH("{", A4)),ISNUMBER(SEARCH("[", A4))), "", IFERROR(MID(A4, SEARCH("""", A4) +1, SEARCH("""", A4, SEARCH("""",A4) +1) - SEARCH("""", A4) -1), "")) -> agentCode | C4: =IF(B4="", "", VLOOKUP(B4,'API Data Dictionary'!C:L,10,FALSE)) -> M | D4: =IF(B4="", "", VLOOKUP(B4,'API Data Dictionary'!C:D,2,FALSE)) -> string | E4: =IF(IF(B4="", "", VLOOKUP(B4,'API Data Dictionary'!C:E,3,FALSE))=0, "", IF(B4="", "", VLOOKUP(B4,'API Data Dictionary'!C:E,3,FALSE))) -> 50 | F4: =IF(IF(B4="", "", VLOOKUP(B4,'API Data Dictionary'!C:F,4,FALSE))=0, "", IF(B4="", "", VLOOKUP(B4,'API Data Dictionary'!C:F,4,FALSE))) | G4: =IF(IF(B4="", "", VLOOKUP(B4,'API Data Dictionary'!C:G,5,FALSE))=0, "", IF(B4="", "", VLOOKUP(B4,'API Data Dictionary'!C:G,5,FALSE))) -> AgentCode is the Unique Key provided to the Agent when onboarding as a Barbon Customer. An AgentID may be linked to many Properties being managed by that Agent and Each property may be linked to 1 or more TenancyID's.
A5: "rentGuarantee": 4, | B5: =IF(OR(ISNUMBER(SEARCH("{", A5)),ISNUMBER(SEARCH("[", A5))), "", IFERROR(MID(A5, SEARCH("""", A5) +1, SEARCH("""", A5, SEARCH("""",A5) +1) - SEARCH("""", A5) -1), "")) -> rentGuarantee | C5: =IF(B5="", "", VLOOKUP(B5,'API Data Dictionary'!C:L,10,FALSE)) -> M | D5: =IF(B5="", "", VLOOKUP(B5,'API Data Dictionary'!C:D,2,FALSE)) -> enum - Rent Guarantee | E5: =IF(IF(B5="", "", VLOOKUP(B5,'API Data Dictionary'!C:E,3,FALSE))=0, "", IF(B5="", "", VLOOKUP(B5,'API Data Dictionary'!C:E,3,FALSE))) | F5: =IF(IF(B5="", "", VLOOKUP(B5,'API Data Dictionary'!C:F,4,FALSE))=0, "", IF(B5="", "", VLOOKUP(B5,'API Data Dictionary'!C:F,4,FALSE))) -> Valid Values 1-4 (See enum definition) | G5: =IF(IF(B5="", "", VLOOKUP(B5,'API Data Dictionary'!C:G,5,FALSE))=0, "", IF(B5="", "", VLOOKUP(B5,'API Data Dictionary'!C:G,5,FALSE))) -> Rent guarantee is an indicator that determines which RG option if any the agent requires
A6: "tenancyTermMonths": 12, | B6: =IF(OR(ISNUMBER(SEARCH("{", A6)),ISNUMBER(SEARCH("[", A6))), "", IFERROR(MID(A6, SEARCH("""", A6) +1, SEARCH("""", A6, SEARCH("""",A6) +1) - SEARCH("""", A6) -1), "")) -> tenancyTermMonths | C6: =IF(B6="", "", VLOOKUP(B6,'API Data Dictionary'!C:L,10,FALSE)) -> M | D6: =IF(B6="", "", VLOOKUP(B6,'API Data Dictionary'!C:D,2,FALSE)) -> integer | E6: =IF(IF(B6="", "", VLOOKUP(B6,'API Data Dictionary'!C:E,3,FALSE))=0, "", IF(B6="", "", VLOOKUP(B6,'API Data Dictionary'!C:E,3,FALSE))) | F6: =IF(IF(B6="", "", VLOOKUP(B6,'API Data Dictionary'!C:F,4,FALSE))=0, "", IF(B6="", "", VLOOKUP(B6,'API Data Dictionary'!C:F,4,FALSE))) | G6: =IF(IF(B6="", "", VLOOKUP(B6,'API Data Dictionary'!C:G,5,FALSE))=0, "", IF(B6="", "", VLOOKUP(B6,'API Data Dictionary'!C:G,5,FALSE))) -> The term of the Tenancy in months (whole months only)
A7: "monthlyRental": 2000, | B7: =IF(OR(ISNUMBER(SEARCH("{", A7)),ISNUMBER(SEARCH("[", A7))), "", IFERROR(MID(A7, SEARCH("""", A7) +1, SEARCH("""", A7, SEARCH("""",A7) +1) - SEARCH("""", A7) -1), "")) -> monthlyRental | C7: =IF(B7="", "", VLOOKUP(B7,'API Data Dictionary'!C:L,10,FALSE)) -> M | D7: =IF(B7="", "", VLOOKUP(B7,'API Data Dictionary'!C:D,2,FALSE)) -> number (double) | E7: =IF(IF(B7="", "", VLOOKUP(B7,'API Data Dictionary'!C:E,3,FALSE))=0, "", IF(B7="", "", VLOOKUP(B7,'API Data Dictionary'!C:E,3,FALSE))) | F7: =IF(IF(B7="", "", VLOOKUP(B7,'API Data Dictionary'!C:F,4,FALSE))=0, "", IF(B7="", "", VLOOKUP(B7,'API Data Dictionary'!C:F,4,FALSE))) -> number($double) pattern: ^\d*.\d{0,2}$ | G7: =IF(IF(B7="", "", VLOOKUP(B7,'API Data Dictionary'!C:G,5,FALSE))=0, "", IF(B7="", "", VLOOKUP(B7,'API Data Dictionary'!C:G,5,FALSE))) -> The monthly rental cost
A8: "lettingType": 1, | B8: =IF(OR(ISNUMBER(SEARCH("{", A8)),ISNUMBER(SEARCH("[", A8))), "", IFERROR(MID(A8, SEARCH("""", A8) +1, SEARCH("""", A8, SEARCH("""",A8) +1) - SEARCH("""", A8) -1), "")) -> lettingType | C8: =IF(B8="", "", VLOOKUP(B8,'API Data Dictionary'!C:L,10,FALSE)) -> M | D8: =IF(B8="", "", VLOOKUP(B8,'API Data Dictionary'!C:D,2,FALSE)) -> enum - Letting Type | E8: =IF(IF(B8="", "", VLOOKUP(B8,'API Data Dictionary'!C:E,3,FALSE))=0, "", IF(B8="", "", VLOOKUP(B8,'API Data Dictionary'!C:E,3,FALSE))) | F8: =IF(IF(B8="", "", VLOOKUP(B8,'API Data Dictionary'!C:F,4,FALSE))=0, "", IF(B8="", "", VLOOKUP(B8,'API Data Dictionary'!C:F,4,FALSE))) -> Valid Values 1-3 (See enum definition) | G8: =IF(IF(B8="", "", VLOOKUP(B8,'API Data Dictionary'!C:G,5,FALSE))=0, "", IF(B8="", "", VLOOKUP(B8,'API Data Dictionary'!C:G,5,FALSE))) -> The type of the letting, i.e. rent only or fully managed
A9: "estimatedMoveInDate": "2023-06-01T10:55:02.383Z", | B9: =IF(OR(ISNUMBER(SEARCH("{", A9)),ISNUMBER(SEARCH("[", A9))), "", IFERROR(MID(A9, SEARCH("""", A9) +1, SEARCH("""", A9, SEARCH("""",A9) +1) - SEARCH("""", A9) -1), "")) -> estimatedMoveInDate | C9: =IF(B9="", "", VLOOKUP(B9,'API Data Dictionary'!C:L,10,FALSE)) -> M | D9: =IF(B9="", "", VLOOKUP(B9,'API Data Dictionary'!C:D,2,FALSE)) -> string ($date-time) | E9: =IF(IF(B9="", "", VLOOKUP(B9,'API Data Dictionary'!C:E,3,FALSE))=0, "", IF(B9="", "", VLOOKUP(B9,'API Data Dictionary'!C:E,3,FALSE))) | F9: =IF(IF(B9="", "", VLOOKUP(B9,'API Data Dictionary'!C:F,4,FALSE))=0, "", IF(B9="", "", VLOOKUP(B9,'API Data Dictionary'!C:F,4,FALSE))) -> DD/MM/YYYY | G9: =IF(IF(B9="", "", VLOOKUP(B9,'API Data Dictionary'!C:G,5,FALSE))=0, "", IF(B9="", "", VLOOKUP(B9,'API Data Dictionary'!C:G,5,FALSE))) -> Estimated date of tenancy start (move in)
A10: "propertyType": 1, | B10: =IF(OR(ISNUMBER(SEARCH("{", A10)),ISNUMBER(SEARCH("[", A10))), "", IFERROR(MID(A10, SEARCH("""", A10) +1, SEARCH("""", A10, SEARCH("""",A10) +1) - SEARCH("""", A10) -1), "")) -> propertyType | C10: =IF(B10="", "", VLOOKUP(B10,'API Data Dictionary'!C:L,10,FALSE)) -> M | D10: =IF(B10="", "", VLOOKUP(B10,'API Data Dictionary'!C:D,2,FALSE)) -> enum - Property Type | E10: =IF(IF(B10="", "", VLOOKUP(B10,'API Data Dictionary'!C:E,3,FALSE))=0, "", IF(B10="", "", VLOOKUP(B10,'API Data Dictionary'!C:E,3,FALSE))) | F10: =IF(IF(B10="", "", VLOOKUP(B10,'API Data Dictionary'!C:F,4,FALSE))=0, "", IF(B10="", "", VLOOKUP(B10,'API Data Dictionary'!C:F,4,FALSE))) -> Valid Values 1-6 (See enum definition) | G10: =IF(IF(B10="", "", VLOOKUP(B10,'API Data Dictionary'!C:G,5,FALSE))=0, "", IF(B10="", "", VLOOKUP(B10,'API Data Dictionary'!C:G,5,FALSE))) -> The Type of property
A11: "propertyConstructionPeriod": 4, | B11: =IF(OR(ISNUMBER(SEARCH("{", A11)),ISNUMBER(SEARCH("[", A11))), "", IFERROR(MID(A11, SEARCH("""", A11) +1, SEARCH("""", A11, SEARCH("""",A11) +1) - SEARCH("""", A11) -1), "")) -> propertyConstructionPeriod | C11: M | D11: =IF(B11="", "", VLOOKUP(B11,'API Data Dictionary'!C:D,2,FALSE)) -> enum - Property Construction Period | E11: =IF(IF(B11="", "", VLOOKUP(B11,'API Data Dictionary'!C:E,3,FALSE))=0, "", IF(B11="", "", VLOOKUP(B11,'API Data Dictionary'!C:E,3,FALSE))) | F11: =IF(IF(B11="", "", VLOOKUP(B11,'API Data Dictionary'!C:F,4,FALSE))=0, "", IF(B11="", "", VLOOKUP(B11,'API Data Dictionary'!C:F,4,FALSE))) -> Valid Values 1-9 (See enum definition) | G11: =IF(IF(B11="", "", VLOOKUP(B11,'API Data Dictionary'!C:G,5,FALSE))=0, "", IF(B11="", "", VLOOKUP(B11,'API Data Dictionary'!C:G,5,FALSE))) -> The time period in which the property was built
A12: "numberOfBedrooms": 4, | B12: =IF(OR(ISNUMBER(SEARCH("{", A12)),ISNUMBER(SEARCH("[", A12))), "", IFERROR(MID(A12, SEARCH("""", A12) +1, SEARCH("""", A12, SEARCH("""",A12) +1) - SEARCH("""", A12) -1), "")) -> numberOfBedrooms | C12: M | D12: =IF(B12="", "", VLOOKUP(B12,'API Data Dictionary'!C:D,2,FALSE)) -> integer | E12: =IF(IF(B12="", "", VLOOKUP(B12,'API Data Dictionary'!C:E,3,FALSE))=0, "", IF(B12="", "", VLOOKUP(B12,'API Data Dictionary'!C:E,3,FALSE))) | F12: =IF(IF(B12="", "", VLOOKUP(B12,'API Data Dictionary'!C:F,4,FALSE))=0, "", IF(B12="", "", VLOOKUP(B12,'API Data Dictionary'!C:F,4,FALSE))) | G12: =IF(IF(B12="", "", VLOOKUP(B12,'API Data Dictionary'!C:G,5,FALSE))=0, "", IF(B12="", "", VLOOKUP(B12,'API Data Dictionary'!C:G,5,FALSE))) -> The count of bedrooms in the property
A13: "noOfAdultOccupants": 2, | B13: =IF(OR(ISNUMBER(SEARCH("{", A13)),ISNUMBER(SEARCH("[", A13))), "", IFERROR(MID(A13, SEARCH("""", A13) +1, SEARCH("""", A13, SEARCH("""",A13) +1) - SEARCH("""", A13) -1), "")) -> noOfAdultOccupants | C13: M | D13: =IF(B13="", "", VLOOKUP(B13,'API Data Dictionary'!C:D,2,FALSE)) -> integer | E13: =IF(IF(B13="", "", VLOOKUP(B13,'API Data Dictionary'!C:E,3,FALSE))=0, "", IF(B13="", "", VLOOKUP(B13,'API Data Dictionary'!C:E,3,FALSE))) | F13: =IF(IF(B13="", "", VLOOKUP(B13,'API Data Dictionary'!C:F,4,FALSE))=0, "", IF(B13="", "", VLOOKUP(B13,'API Data Dictionary'!C:F,4,FALSE))) | G13: =IF(IF(B13="", "", VLOOKUP(B13,'API Data Dictionary'!C:G,5,FALSE))=0, "", IF(B13="", "", VLOOKUP(B13,'API Data Dictionary'!C:G,5,FALSE))) -> Number of Adult occupants (18 or over)
A14: "noOfChildOccupants": 2, | B14: =IF(OR(ISNUMBER(SEARCH("{", A14)),ISNUMBER(SEARCH("[", A14))), "", IFERROR(MID(A14, SEARCH("""", A14) +1, SEARCH("""", A14, SEARCH("""",A14) +1) - SEARCH("""", A14) -1), "")) -> noOfChildOccupants | C14: M | D14: =IF(B14="", "", VLOOKUP(B14,'API Data Dictionary'!C:D,2,FALSE)) -> integer | E14: =IF(IF(B14="", "", VLOOKUP(B14,'API Data Dictionary'!C:E,3,FALSE))=0, "", IF(B14="", "", VLOOKUP(B14,'API Data Dictionary'!C:E,3,FALSE))) | F14: =IF(IF(B14="", "", VLOOKUP(B14,'API Data Dictionary'!C:F,4,FALSE))=0, "", IF(B14="", "", VLOOKUP(B14,'API Data Dictionary'!C:F,4,FALSE))) | G14: =IF(IF(B14="", "", VLOOKUP(B14,'API Data Dictionary'!C:G,5,FALSE))=0, "", IF(B14="", "", VLOOKUP(B14,'API Data Dictionary'!C:G,5,FALSE))) -> Number of Child Occupants (under 18)
A15: "isAdvanceRent": false, | B15: =IF(OR(ISNUMBER(SEARCH("{", A15)),ISNUMBER(SEARCH("[", A15))), "", IFERROR(MID(A15, SEARCH("""", A15) +1, SEARCH("""", A15, SEARCH("""",A15) +1) - SEARCH("""", A15) -1), "")) -> isAdvanceRent | C15: M | D15: =IF(B15="", "", VLOOKUP(B15,'API Data Dictionary'!C:D,2,FALSE)) -> boolean | E15: =IF(IF(B15="", "", VLOOKUP(B15,'API Data Dictionary'!C:E,3,FALSE))=0, "", IF(B15="", "", VLOOKUP(B15,'API Data Dictionary'!C:E,3,FALSE))) | F15: =IF(IF(B15="", "", VLOOKUP(B15,'API Data Dictionary'!C:F,4,FALSE))=0, "", IF(B15="", "", VLOOKUP(B15,'API Data Dictionary'!C:F,4,FALSE))) | G15: =IF(IF(B15="", "", VLOOKUP(B15,'API Data Dictionary'!C:G,5,FALSE))=0, "", IF(B15="", "", VLOOKUP(B15,'API Data Dictionary'!C:G,5,FALSE))) -> Denotes whether rent is paid in advance
A16: "propertyAddress": { | B16: =IF(OR(ISNUMBER(SEARCH("{", A16)),ISNUMBER(SEARCH("[", A16))), "", IFERROR(MID(A16, SEARCH("""", A16) +1, SEARCH("""", A16, SEARCH("""",A16) +1) - SEARCH("""", A16) -1), "")) | C16: =IF(B16="", "", VLOOKUP(B16,'API Data Dictionary'!C:L,10,FALSE)) | D16: =IF(B16="", "", VLOOKUP(B16,'API Data Dictionary'!C:D,2,FALSE)) | E16: =IF(IF(B16="", "", VLOOKUP(B16,'API Data Dictionary'!C:E,3,FALSE))=0, "", IF(B16="", "", VLOOKUP(B16,'API Data Dictionary'!C:E,3,FALSE))) | F16: =IF(IF(B16="", "", VLOOKUP(B16,'API Data Dictionary'!C:F,4,FALSE))=0, "", IF(B16="", "", VLOOKUP(B16,'API Data Dictionary'!C:F,4,FALSE))) | G16: =IF(IF(B16="", "", VLOOKUP(B16,'API Data Dictionary'!C:G,5,FALSE))=0, "", IF(B16="", "", VLOOKUP(B16,'API Data Dictionary'!C:G,5,FALSE)))
A17: "houseNumber": "65000", | B17: =IF(OR(ISNUMBER(SEARCH("{", A17)),ISNUMBER(SEARCH("[", A17))), "", IFERROR(MID(A17, SEARCH("""", A17) +1, SEARCH("""", A17, SEARCH("""",A17) +1) - SEARCH("""", A17) -1), "")) -> houseNumber | C17: =IF(B17="", "", VLOOKUP(B17,'API Data Dictionary'!C:L,10,FALSE)) -> X | D17: =IF(B17="", "", VLOOKUP(B17,'API Data Dictionary'!C:D,2,FALSE)) -> string | E17: =IF(IF(B17="", "", VLOOKUP(B17,'API Data Dictionary'!C:E,3,FALSE))=0, "", IF(B17="", "", VLOOKUP(B17,'API Data Dictionary'!C:E,3,FALSE))) -> 100 | F17: =IF(IF(B17="", "", VLOOKUP(B17,'API Data Dictionary'!C:F,4,FALSE))=0, "", IF(B17="", "", VLOOKUP(B17,'API Data Dictionary'!C:F,4,FALSE))) | G17: =IF(IF(B17="", "", VLOOKUP(B17,'API Data Dictionary'!C:G,5,FALSE))=0, "", IF(B17="", "", VLOOKUP(B17,'API Data Dictionary'!C:G,5,FALSE))) -> The number of the property, mandatory OR pair with House name field
A18: "houseName": "Oxford Street", | B18: =IF(OR(ISNUMBER(SEARCH("{", A18)),ISNUMBER(SEARCH("[", A18))), "", IFERROR(MID(A18, SEARCH("""", A18) +1, SEARCH("""", A18, SEARCH("""",A18) +1) - SEARCH("""", A18) -1), "")) -> houseName | C18: =IF(B18="", "", VLOOKUP(B18,'API Data Dictionary'!C:L,10,FALSE)) -> X | D18: =IF(B18="", "", VLOOKUP(B18,'API Data Dictionary'!C:D,2,FALSE)) -> string | E18: =IF(IF(B18="", "", VLOOKUP(B18,'API Data Dictionary'!C:E,3,FALSE))=0, "", IF(B18="", "", VLOOKUP(B18,'API Data Dictionary'!C:E,3,FALSE))) -> 100 | F18: =IF(IF(B18="", "", VLOOKUP(B18,'API Data Dictionary'!C:F,4,FALSE))=0, "", IF(B18="", "", VLOOKUP(B18,'API Data Dictionary'!C:F,4,FALSE))) | G18: =IF(IF(B18="", "", VLOOKUP(B18,'API Data Dictionary'!C:G,5,FALSE))=0, "", IF(B18="", "", VLOOKUP(B18,'API Data Dictionary'!C:G,5,FALSE))) -> The name of the property, mandatory OR pair with House number field
A19: "addressLine1": "Gadlys", | B19: =IF(OR(ISNUMBER(SEARCH("{", A19)),ISNUMBER(SEARCH("[", A19))), "", IFERROR(MID(A19, SEARCH("""", A19) +1, SEARCH("""", A19, SEARCH("""",A19) +1) - SEARCH("""", A19) -1), "")) -> addressLine1 | C19: =IF(B19="", "", VLOOKUP(B19,'API Data Dictionary'!C:L,10,FALSE)) -> M | D19: =IF(B19="", "", VLOOKUP(B19,'API Data Dictionary'!C:D,2,FALSE)) -> string | E19: =IF(IF(B19="", "", VLOOKUP(B19,'API Data Dictionary'!C:E,3,FALSE))=0, "", IF(B19="", "", VLOOKUP(B19,'API Data Dictionary'!C:E,3,FALSE))) -> 100 | F19: =IF(IF(B19="", "", VLOOKUP(B19,'API Data Dictionary'!C:F,4,FALSE))=0, "", IF(B19="", "", VLOOKUP(B19,'API Data Dictionary'!C:F,4,FALSE))) | G19: =IF(IF(B19="", "", VLOOKUP(B19,'API Data Dictionary'!C:G,5,FALSE))=0, "", IF(B19="", "", VLOOKUP(B19,'API Data Dictionary'!C:G,5,FALSE))) -> The first line of the property address
A20: "addressLine2": "Parkway", | B20: =IF(OR(ISNUMBER(SEARCH("{", A20)),ISNUMBER(SEARCH("[", A20))), "", IFERROR(MID(A20, SEARCH("""", A20) +1, SEARCH("""", A20, SEARCH("""",A20) +1) - SEARCH("""", A20) -1), "")) -> addressLine2 | C20: X | D20: =IF(B20="", "", VLOOKUP(B20,'API Data Dictionary'!C:D,2,FALSE)) -> string | E20: =IF(IF(B20="", "", VLOOKUP(B20,'API Data Dictionary'!C:E,3,FALSE))=0, "", IF(B20="", "", VLOOKUP(B20,'API Data Dictionary'!C:E,3,FALSE))) -> 100 | F20: =IF(IF(B20="", "", VLOOKUP(B20,'API Data Dictionary'!C:F,4,FALSE))=0, "", IF(B20="", "", VLOOKUP(B20,'API Data Dictionary'!C:F,4,FALSE))) | G20: =IF(IF(B20="", "", VLOOKUP(B20,'API Data Dictionary'!C:G,5,FALSE))=0, "", IF(B20="", "", VLOOKUP(B20,'API Data Dictionary'!C:G,5,FALSE))) -> The second line of the property address
A21: "town": "Aberdare", | B21: =IF(OR(ISNUMBER(SEARCH("{", A21)),ISNUMBER(SEARCH("[", A21))), "", IFERROR(MID(A21, SEARCH("""", A21) +1, SEARCH("""", A21, SEARCH("""",A21) +1) - SEARCH("""", A21) -1), "")) -> town | C21: =IF(B21="", "", VLOOKUP(B21,'API Data Dictionary'!C:L,10,FALSE)) -> M | D21: =IF(B21="", "", VLOOKUP(B21,'API Data Dictionary'!C:D,2,FALSE)) -> string | E21: =IF(IF(B21="", "", VLOOKUP(B21,'API Data Dictionary'!C:E,3,FALSE))=0, "", IF(B21="", "", VLOOKUP(B21,'API Data Dictionary'!C:E,3,FALSE))) -> 50 | F21: =IF(IF(B21="", "", VLOOKUP(B21,'API Data Dictionary'!C:F,4,FALSE))=0, "", IF(B21="", "", VLOOKUP(B21,'API Data Dictionary'!C:F,4,FALSE))) | G21: =IF(IF(B21="", "", VLOOKUP(B21,'API Data Dictionary'!C:G,5,FALSE))=0, "", IF(B21="", "", VLOOKUP(B21,'API Data Dictionary'!C:G,5,FALSE))) -> The town in which the property exists
