Workbook

Sheet RTR
A1: Id | B1: Tenant__r.Name | C1: Related_Opportunity__c | D1: Related_Unit__c | E1: Status__c | F1: Time_Limited__c | G1: RTR_Expiry__c | H1: Date_Next_RTR_Required__c | I1: Document_Saved__c | J1: Check_Date__c | K1: CreatedDate | L1: LastModifiedDate | M1: OwnerId | N1: Criteria | P1: _LastModifiedDate_Splited | Q1: _Check_Date__c > _Is_LastModifiedDate OR Check_Date__c is NULL ?
A2: a1zNz00000095JpIAI | B2: gVcFvfyrV8jNsHt9Vf1X MxYaNpgylHRkz9GNCnmg | C2: 006Nz000002OfSMIA0 | D2: a1G8d0000004XgtEAE | E2: Completed | F2: TRUE | G2: 46656 | I2: FALSE | J2: 45203 | K2: 2023-10-03T12:20:45.000+0000 | L2: 2023-10-03T12:20:45.000+0000 | M2: 0058d00000202rVAAQ | N2: =IF(Q2=TRUE,"BASIC_CRITERIA","") -> BASIC_CRITERIA | P2: =DATEVALUE(SUBSTITUTE(LEFT(L2,10),"-","/")) -> 45202 | Q2: =IF(J2="",TRUE,IF(J2>P2,TRUE,FALSE)) -> TRUE
A3: a1zNz000000AdUjIAK | B3: Ben McCabe | C3: 006Nz000002lChMIAU | D3: a1G4J0000025wYMUAY | E3: Completed | F3: FALSE | I3: FALSE | J3: 45206 | K3: 2023-10-05T13:39:36.000+0000 | L3: 2023-10-06T08:12:09.000+0000 | M3: 0058d0000043ssPAAQ | N3: =IF(Q3=TRUE,"BASIC_CRITERIA","") -> BASIC_CRITERIA | P3: =DATEVALUE(SUBSTITUTE(LEFT(L3,10),"-","/")) -> 45205 | Q3: =IF(J3="",TRUE,IF(J3>P3,TRUE,FALSE)) -> TRUE
A4: a1zNz000000AeSPIA0 | B4: Jess Tilley | C4: 006Nz000002n7QdIAI | D4: a1G4J0000025xkKUAQ | E4: Completed | F4: FALSE | I4: FALSE | J4: 45204 | K4: 2023-10-05T13:47:43.000+0000 | L4: 2023-10-06T08:15:46.000+0000 | M4: 0058d0000043ssPAAQ | N4: =IF(Q4=TRUE,"BASIC_CRITERIA","") | P4: =DATEVALUE(SUBSTITUTE(LEFT(L4,10),"-","/")) -> 45205 | Q4: =IF(J4="",TRUE,IF(J4>P4,TRUE,FALSE)) -> FALSE
A5: a1zNz000000AeU1IAK | B5: Matthew Birkett | C5: 006Nz000002n7QdIAI | D5: a1G4J0000025xkKUAQ | E5: Completed | F5: FALSE | I5: FALSE | J5: 45204 | K5: 2023-10-05T13:48:43.000+0000 | L5: 2023-10-06T08:16:41.000+0000 | M5: 0058d0000043ssPAAQ | N5: =IF(Q5=TRUE,"BASIC_CRITERIA","") | P5: =DATEVALUE(SUBSTITUTE(LEFT(L5,10),"-","/")) -> 45205 | Q5: =IF(J5="",TRUE,IF(J5>P5,TRUE,FALSE)) -> FALSE
A6: a1zNz000000AgIvIAK | B6: Aleena Iqbal | C6: 006Nz000002p0o2IAA | D6: a1G4J0000025y3NUAQ | E6: Completed | F6: FALSE | I6: FALSE | J6: 45204 | K6: 2023-10-05T14:10:46.000+0000 | L6: 2023-10-06T08:17:59.000+0000 | M6: 0058d0000043ssPAAQ | N6: =IF(Q6=TRUE,"BASIC_CRITERIA","") | P6: =DATEVALUE(SUBSTITUTE(LEFT(L6,10),"-","/")) -> 45205 | Q6: =IF(J6="",TRUE,IF(J6>P6,TRUE,FALSE)) -> FALSE
A7: a1zNz000000AetpIAC | B7: Sam Collins | C7: 006Nz000002oZawIAE | D7: a1G4J0000025xuQUAQ | E7: Completed | F7: FALSE | I7: FALSE | J7: 45204 | K7: 2023-10-05T13:53:46.000+0000 | L7: 2023-10-09T11:21:48.000+0000 | M7: 0058d0000043ssPAAQ | N7: =IF(Q7=TRUE,"BASIC_CRITERIA","") | P7: =DATEVALUE(SUBSTITUTE(LEFT(L7,10),"-","/")) -> 45208 | Q7: =IF(J7="",TRUE,IF(J7>P7,TRUE,FALSE)) -> FALSE
A8: a1zNz000000AesDIAS | B8: Adam McCrum | C8: 006Nz000002oZawIAE | D8: a1G4J0000025xuQUAQ | E8: Completed | F8: FALSE | I8: FALSE | J8: 45204 | K8: 2023-10-05T13:53:28.000+0000 | L8: 2023-10-10T11:16:58.000+0000 | M8: 0058d0000043ssPAAQ | N8: =IF(Q8=TRUE,"BASIC_CRITERIA","") | P8: =DATEVALUE(SUBSTITUTE(LEFT(L8,10),"-","/")) -> 45209 | Q8: =IF(J8="",TRUE,IF(J8>P8,TRUE,FALSE)) -> FALSE
A9: a1zNz000000AdWLIA0 | B9: Ema Almeida | C9: 006Nz000002lChMIAU | D9: a1G4J0000025wYMUAY | E9: Completed | F9: TRUE | G9: 45944 | I9: FALSE | J9: 45204 | K9: 2023-10-05T13:40:37.000+0000 | L9: 2023-10-10T15:26:15.000+0000 | M9: 0058d0000043ssPAAQ | N9: =IF(Q9=TRUE,"BASIC_CRITERIA","") | P9: =DATEVALUE(SUBSTITUTE(LEFT(L9,10),"-","/")) -> 45209 | Q9: =IF(J9="",TRUE,IF(J9>P9,TRUE,FALSE)) -> FALSE
A10: a1zNz000000AgVpIAK | B10: Ka Po Ngai | C10: 006Nz0000023YnEIAU | D10: a1G4J0000025zIlUAI | E10: Completed | F10: TRUE | G10: 46138 | I10: FALSE | J10: 45204 | K10: 2023-10-05T14:37:50.000+0000 | L10: 2024-08-15T16:03:46.000+0000 | M10: 0058d00000202rVAAQ | N10: =IF(Q10=TRUE,"BASIC_CRITERIA","") | P10: =DATEVALUE(SUBSTITUTE(LEFT(L10,10),"-","/")) -> 45519 | Q10: =IF(J10="",TRUE,IF(J10>P10,TRUE,FALSE)) -> FALSE
A11: a1zNz000000AgM9IAK | B11: Adnan Salah | C11: 006Nz000002p0o2IAA | D11: a1G4J0000025y3NUAQ | E11: Completed | F11: TRUE | G11: 45570 | I11: FALSE | J11: 45204 | K11: 2023-10-05T14:16:27.000+0000 | L11: 2023-10-05T14:24:03.000+0000 | M11: 0058d0000043ssPAAQ | N11: =IF(Q11=TRUE,"BASIC_CRITERIA","") | P11: =DATEVALUE(SUBSTITUTE(LEFT(L11,10),"-","/")) -> 45204 | Q11: =IF(J11="",TRUE,IF(J11>P11,TRUE,FALSE)) -> FALSE
A12: a1zNz000000CAtFIAW | B12: Muskan Singh | C12: 006Nz000002EEWkIAO | D12: a1G4J0000025xj1UAA | E12: Completed | F12: FALSE | I12: FALSE | J12: 45208 | K12: 2023-10-09T16:37:47.000+0000 | L12: 2023-10-12T10:43:52.000+0000 | M12: 0058d0000043ssPAAQ | N12: =IF(Q12=TRUE,"BASIC_CRITERIA","") | P12: =DATEVALUE(SUBSTITUTE(LEFT(L12,10),"-","/")) -> 45211 | Q12: =IF(J12="",TRUE,IF(J12>P12,TRUE,FALSE)) -> FALSE
A13: a1zNz000000CPHBIA4 | B13: Letizia Olivero | C13: 006Nz000002qXMxIAM | D13: a1G8d0000004D97EAE | E13: Completed | F13: TRUE | I13: TRUE | J13: 45209 | K13: 2023-10-10T08:06:26.000+0000 | L13: 2023-10-10T13:34:47.000+0000 | M13: 0058d000006cI6JAAU | N13: =IF(Q13=TRUE,"BASIC_CRITERIA","") | P13: =DATEVALUE(SUBSTITUTE(LEFT(L13,10),"-","/")) -> 45209 | Q13: =IF(J13="",TRUE,IF(J13>P13,TRUE,FALSE)) -> FALSE
A14: a1zNz000000DpWAIA0 | B14: Alexander Karsten | C14: 006Nz000002xve1IAA | D14: a1G8d0000004DEqEAM | E14: Completed | F14: TRUE | I14: TRUE | J14: 45211 | K14: 2023-10-12T08:38:09.000+0000 | L14: 2023-10-12T08:38:09.000+0000 | M14: 0058d000006cI6JAAU | N14: =IF(Q14=TRUE,"BASIC_CRITERIA","") | P14: =DATEVALUE(SUBSTITUTE(LEFT(L14,10),"-","/")) -> 45211 | Q14: =IF(J14="",TRUE,IF(J14>P14,TRUE,FALSE)) -> FALSE
A15: a1zNz000000E2GTIA0 | B15: Afolabi Obasa | C15: 006Nz000002y7YXIAY | D15: a1G4J0000025yx2UAA | E15: Completed | F15: TRUE | G15: 46980 | I15: FALSE | J15: 45211 | K15: 2023-10-12T10:40:23.000+0000 | L15: 2023-10-12T11:34:34.000+0000 | M15: 0058d0000043ssPAAQ | N15: =IF(Q15=TRUE,"BASIC_CRITERIA","") | P15: =DATEVALUE(SUBSTITUTE(LEFT(L15,10),"-","/")) -> 45211 | Q15: =IF(J15="",TRUE,IF(J15>P15,TRUE,FALSE)) -> FALSE
A16: a1zNz000000EdG1IAK | B16: Sobomate Princewell | C16: 006Nz000002bik7IAA | D16: a1G8d0000004c7WEAQ | E16: Completed | F16: TRUE | G16: 45321 | I16: FALSE | J16: 45212 | K16: 2023-10-14T11:35:34.000+0000 | L16: 2023-10-14T11:35:34.000+0000 | M16: 0058d000004FHK0AAO | N16: =IF(Q16=TRUE,"BASIC_CRITERIA","") | P16: =DATEVALUE(SUBSTITUTE(LEFT(L16,10),"-","/")) -> 45213 | Q16: =IF(J16="",TRUE,IF(J16>P16,TRUE,FALSE)) -> FALSE
A17: a1zNz000000Edr7IAC | B17: Elba Cardoso | C17: 006Nz000000wonhIAA | D17: a1G8d0000004cBnEAI | E17: Completed | F17: TRUE | G17: 45303 | I17: FALSE | J17: 45212 | K17: 2023-10-14T12:31:33.000+0000 | L17: 2023-10-14T12:31:33.000+0000 | M17: 0058d000004FHK0AAO | N17: =IF(Q17=TRUE,"BASIC_CRITERIA","") | P17: =DATEVALUE(SUBSTITUTE(LEFT(L17,10),"-","/")) -> 45213 | Q17: =IF(J17="",TRUE,IF(J17>P17,TRUE,FALSE)) -> FALSE
A18: a1zNz000000ERZpIAO | B18: Kit Yee Kiwi Law | C18: 006Nz0000031r5PIAQ | D18: a1GNz0000000zzZMAQ | E18: Completed | F18: TRUE | G18: 46661 | I18: FALSE | J18: 45212 | K18: 2023-10-13T10:55:06.000+0000 | L18: 2023-10-13T10:56:41.000+0000 | M18: 0058d000006chw3AAA | N18: =IF(Q18=TRUE,"BASIC_CRITERIA","") | P18: =DATEVALUE(SUBSTITUTE(LEFT(L18,10),"-","/")) -> 45212 | Q18: =IF(J18="",TRUE,IF(J18>P18,TRUE,FALSE)) -> FALSE
A19: a1zNz000000FlBVIA0 | B19: laura sanchez | C19: 006Nz0000038O6lIAE | D19: a1G4J0000025xkFUAQ | E19: Completed | F19: FALSE | I19: FALSE | J19: 45215 | K19: 2023-10-16T11:44:47.000+0000 | L19: 2023-11-07T08:47:08.000+0000 | M19: 0058d0000043ssPAAQ | N19: =IF(Q19=TRUE,"BASIC_CRITERIA","") | P19: =DATEVALUE(SUBSTITUTE(LEFT(L19,10),"-","/")) -> 45237 | Q19: =IF(J19="",TRUE,IF(J19>P19,TRUE,FALSE)) -> FALSE
A20: a1zNz000000DrHsIAK | B20: Louis Rocca | C20: 006Nz000002iwjzIAA | D20: a1G4J000004jylHUAQ | E20: Completed | F20: FALSE | I20: FALSE | J20: 45216 | K20: 2023-10-12T09:02:53.000+0000 | L20: 2023-10-17T10:23:33.000+0000 | M20: 0054J000006BkQgQAK | N20: =IF(Q20=TRUE,"BASIC_CRITERIA","") | P20: =DATEVALUE(SUBSTITUTE(LEFT(L20,10),"-","/")) -> 45216 | Q20: =IF(J20="",TRUE,IF(J20>P20,TRUE,FALSE)) -> FALSE
A21: a1zNz000000IYw5IAG | B21: Benjamin Maynard | C21: 006Nz000003Bd5yIAC | D21: a1G4J0000025y4wUAA | E21: Completed | F21: FALSE | I21: FALSE | J21: 45218 | K21: 2023-10-19T15:57:09.000+0000 | L21: 2023-10-20T08:03:35.000+0000 | M21: 0058d0000043ssPAAQ | N21: =IF(Q21=TRUE,"BASIC_CRITERIA","") | P21: =DATEVALUE(SUBSTITUTE(LEFT(L21,10),"-","/")) -> 45219 | Q21: =IF(J21="",TRUE,IF(J21>P21,TRUE,FALSE)) -> FALSE
A22: a1zNz000000IYxhIAG | B22: Hazel McDowell | C22: 006Nz000003Bd5yIAC | D22: a1G4J0000025y4wUAA | E22: Completed | F22: FALSE | I22: FALSE | J22: 45218 | K22: 2023-10-19T15:57:57.000+0000 | L22: 2023-10-23T10:04:36.000+0000 | M22: 0058d0000043ssPAAQ | N22: =IF(Q22=TRUE,"BASIC_CRITERIA","") | P22: =DATEVALUE(SUBSTITUTE(LEFT(L22,10),"-","/")) -> 45222 | Q22: =IF(J22="",TRUE,IF(J22>P22,TRUE,FALSE)) -> FALSE
A23: a1zNz000000K5oMIAS | B23: Amelia Lloyd | C23: 006Nz000003I4UvIAK | D23: a1G4J0000025zDJUAY | E23: Completed | F23: FALSE | I23: FALSE | J23: 45222 | K23: 2023-10-23T09:56:42.000+0000 | L23: 2023-10-30T09:14:14.000+0000 | M23: 0058d0000043ssPAAQ | N23: =IF(Q23=TRUE,"BASIC_CRITERIA","") | P23: =DATEVALUE(SUBSTITUTE(LEFT(L23,10),"-","/")) -> 45229 | Q23: =IF(J23="",TRUE,IF(J23>P23,TRUE,FALSE)) -> FALSE
A24: a1zNz000000Jw1tIAC | B24: Ghadah Alsharif | C24: 006Nz000002b80jIAA | D24: a1GNz0000000wGyMAI | E24: Completed | F24: TRUE | G24: 45586 | I24: FALSE | J24: 45222 | K24: 2023-10-23T08:21:08.000+0000 | L24: 2023-10-23T08:21:08.000+0000 | M24: 0054J000004wSINQA2 | N24: =IF(Q24=TRUE,"BASIC_CRITERIA","") | P24: =DATEVALUE(SUBSTITUTE(LEFT(L24,10),"-","/")) -> 45222 | Q24: =IF(J24="",TRUE,IF(J24>P24,TRUE,FALSE)) -> FALSE
A25: a1zNz000000K5unIAC | B25: Rocco Tosini | C25: 006Nz000003I4UvIAK | D25: a1G4J0000025zDJUAY | E25: Completed | F25: TRUE | G25: 45863 | I25: FALSE | J25: 45222 | K25: 2023-10-23T09:56:09.000+0000 | L25: 2023-10-23T11:39:33.000+0000 | M25: 0058d0000043ssPAAQ | N25: =IF(Q25=TRUE,"BASIC_CRITERIA","") | P25: =DATEVALUE(SUBSTITUTE(LEFT(L25,10),"-","/")) -> 45222 | Q25: =IF(J25="",TRUE,IF(J25>P25,TRUE,FALSE)) -> FALSE
A26: a1zNz000000L93VIAS | B26: Kate Johnson | C26: 006Nz000002y1MjIAI | D26: a1G8d0000004XfzEAE | E26: Completed | F26: FALSE | I26: FALSE | J26: 45223 | K26: 2023-10-24T10:04:16.000+0000 | L26: 2023-10-24T10:04:16.000+0000 | M26: 0058d00000202rVAAQ | N26: =IF(Q26=TRUE,"BASIC_CRITERIA","") | P26: =DATEVALUE(SUBSTITUTE(LEFT(L26,10),"-","/")) -> 45223 | Q26: =IF(J26="",TRUE,IF(J26>P26,TRUE,FALSE)) -> FALSE
A27: a1zNz000000Q7STIA0 | B27: Princess Asante | C27: 006Nz000002jBJAIA2 | D27: a1G8d000002QBSoEAO | E27: Completed | F27: TRUE | I27: TRUE | J27: 45227 | K27: 2023-10-31T09:40:22.000+0000 | L27: 2023-10-31T09:43:00.000+0000 | M27: 0058d00000204EOAAY | N27: =IF(Q27=TRUE,"BASIC_CRITERIA","") | P27: =DATEVALUE(SUBSTITUTE(LEFT(L27,10),"-","/")) -> 45230 | Q27: =IF(J27="",TRUE,IF(J27>P27,TRUE,FALSE)) -> FALSE
A28: a1zNz000000PeIPIA0 | B28: Scott Davies | C28: 006Nz000003YWtSIAW | E28: Completed | F28: FALSE | I28: FALSE | J28: 45229 | K28: 2023-10-30T16:54:38.000+0000 | L28: 2023-10-30T16:54:38.000+0000 | M28: 0054J000004wSINQA2 | N28: =IF(Q28=TRUE,"BASIC_CRITERIA","") | P28: =DATEVALUE(SUBSTITUTE(LEFT(L28,10),"-","/")) -> 45229 | Q28: =IF(J28="",TRUE,IF(J28>P28,TRUE,FALSE)) -> FALSE
A29: a1zNz000000RUwTIAW | B29: Oladepo Oladotun | C29: 006Nz0000039RAZIA2 | D29: a1GNz00000015vKMAQ | E29: Completed | F29: TRUE | G29: 45597 | I29: FALSE | J29: 45231 | K29: 2023-11-01T12:06:19.000+0000 | L29: 2023-11-01T14:50:40.000+0000 | M29: 0058d000006chw3AAA | N29: =IF(Q29=TRUE,"BASIC_CRITERIA","") | P29: =DATEVALUE(SUBSTITUTE(LEFT(L29,10),"-","/")) -> 45231 | Q29: =IF(J29="",TRUE,IF(J29>P29,TRUE,FALSE)) -> FALSE
A30: a1zNz000000Rh8vIAC | B30: Su Yi Sarah Ng | C30: 006Nz000001MGvCIAW | D30: a1G8d000002QBa4EAG | E30: Completed | F30: TRUE | G30: 45524 | I30: FALSE | J30: 45231 | K30: 2023-11-01T14:46:35.000+0000 | L30: 2023-11-01T14:46:35.000+0000 | M30: 0058d000006chw3AAA | N30: =IF(Q30=TRUE,"BASIC_CRITERIA","") | P30: =DATEVALUE(SUBSTITUTE(LEFT(L30,10),"-","/")) -> 45231 | Q30: =IF(J30="",TRUE,IF(J30>P30,TRUE,FALSE)) -> FALSE
A31: a1zNz000000T1jtIAC | B31: Sebastien Bouchereau | E31: Completed | F31: FALSE | I31: FALSE | J31: 45234 | K31: 2023-11-04T10:30:53.000+0000 | L31: 2023-11-04T10:30:53.000+0000 | M31: 005Nz000000kC30IAE | N31: =IF(Q31=TRUE,"BASIC_CRITERIA","") | P31: =DATEVALUE(SUBSTITUTE(LEFT(L31,10),"-","/")) -> 45234 | Q31: =IF(J31="",TRUE,IF(J31>P31,TRUE,FALSE)) -> FALSE
A32: a1zNz000000UF85IAG | B32: Evaldas Rimkus | C32: 006Nz000003G6KiIAK | D32: a1G8d000002QBLSEA4 | E32: Completed | F32: FALSE | I32: FALSE | J32: 45236 | K32: 2023-11-06T09:17:48.000+0000 | L32: 2023-11-06T09:17:48.000+0000 | M32: 0058d0000043sEOAAY | N32: =IF(Q32=TRUE,"BASIC_CRITERIA","") | P32: =DATEVALUE(SUBSTITUTE(LEFT(L32,10),"-","/")) -> 45236 | Q32: =IF(J32="",TRUE,IF(J32>P32,TRUE,FALSE)) -> FALSE
A33: a1zNz000000UXzRIAW | B33: Marius Andrei Codesc | C33: 006Nz000002jGM3IAM | D33: a1G8d000002QBLDEA4 | E33: Completed | F33: FALSE | I33: FALSE | J33: 45236 | K33: 2023-11-06T14:24:39.000+0000 | L33: 2023-11-06T14:24:39.000+0000 | M33: 0058d0000043sEOAAY | N33: =IF(Q33=TRUE,"BASIC_CRITERIA","") | P33: =DATEVALUE(SUBSTITUTE(LEFT(L33,10),"-","/")) -> 45236 | Q33: =IF(J33="",TRUE,IF(J33>P33,TRUE,FALSE)) -> FALSE
A34: a1zNz000000V00XIAS | B34: Mia Lenthall | C34: 006Nz000003S54fIAC | D34: a1G4J0000025zz9UAA | E34: Completed | F34: FALSE | I34: FALSE | J34: 45237 | K34: 2023-11-07T09:29:09.000+0000 | L34: 2023-11-07T09:29:09.000+0000 | M34: 0054J000004wZgRQAU | N34: =IF(Q34=TRUE,"BASIC_CRITERIA","") | P34: =DATEVALUE(SUBSTITUTE(LEFT(L34,10),"-","/")) -> 45237 | Q34: =IF(J34="",TRUE,IF(J34>P34,TRUE,FALSE)) -> FALSE
A35: a1zNz000000VE3VIAW | B35: Sharan Sudharshan | C35: 006Nz000003vN33IAE | E35: Completed | F35: TRUE | G35: 45311 | I35: FALSE | J35: 45238 | K35: 2023-11-08T12:29:10.000+0000 | L35: 2023-11-08T12:29:10.000+0000 | M35: 0058d0000043sEOAAY | N35: =IF(Q35=TRUE,"BASIC_CRITERIA","") | P35: =DATEVALUE(SUBSTITUTE(LEFT(L35,10),"-","/")) -> 45238 | Q35: =IF(J35="",TRUE,IF(J35>P35,TRUE,FALSE)) -> FALSE
A36: a1zNz000000VN8PIAW | B36: Mohammed Munawar Munawar Khan | C36: 006Nz0000030L1AIAU | E36: Completed | F36: TRUE | G36: 45681 | I36: FALSE | J36: 45239 | K36: 2023-11-09T09:09:08.000+0000 | L36: 2023-11-09T09:09:08.000+0000 | M36: 0058d0000043sEOAAY | N36: =IF(Q36=TRUE,"BASIC_CRITERIA","") | P36: =DATEVALUE(SUBSTITUTE(LEFT(L36,10),"-","/")) -> 45239 | Q36: =IF(J36="",TRUE,IF(J36>P36,TRUE,FALSE)) -> FALSE
A37: a1zNz000000VNoLIAW | B37: Muddassir Ahmed Khan Ahmed Khan | C37: 006Nz0000030L1AIAU | D37: a1G4J0000025x1GUAQ | E37: Completed | F37: TRUE | I37: TRUE | J37: 45239 | K37: 2023-11-09T10:18:48.000+0000 | L37: 2023-11-09T10:18:48.000+0000 | M37: 0058d0000043sEOAAY | N37: =IF(Q37=TRUE,"BASIC_CRITERIA","") | P37: =DATEVALUE(SUBSTITUTE(LEFT(L37,10),"-","/")) -> 45239 | Q37: =IF(J37="",TRUE,IF(J37>P37,TRUE,FALSE)) -> FALSE
A38: a1zNz000000W3IvIAK | B38: Mark Threlfall | C38: 006Nz00000481z9IAA | D38: a1G4J0000025xsGUAQ | E38: Completed | F38: FALSE | I38: FALSE | J38: 45243 | K38: 2023-11-13T14:24:01.000+0000 | L38: 2023-11-14T08:54:38.000+0000 | M38: 0058d0000043ssPAAQ | N38: =IF(Q38=TRUE,"BASIC_CRITERIA","") | P38: =DATEVALUE(SUBSTITUTE(LEFT(L38,10),"-","/")) -> 45244 | Q38: =IF(J38="",TRUE,IF(J38>P38,TRUE,FALSE)) -> FALSE
A39: a1zNz000000WYRZIA4 | B39: Simone Simone Rodriguez | C39: 006Nz000001QZCtIAO | D39: a1G8d0000004XiPEAU | E39: Completed | F39: TRUE | G39: 45455 | I39: FALSE | J39: 45245 | K39: 2023-11-15T09:44:57.000+0000 | L39: 2023-11-15T09:44:57.000+0000 | M39: 0058d00000202rVAAQ | N39: =IF(Q39=TRUE,"BASIC_CRITERIA","") | P39: =DATEVALUE(SUBSTITUTE(LEFT(L39,10),"-","/")) -> 45245 | Q39: =IF(J39="",TRUE,IF(J39>P39,TRUE,FALSE)) -> FALSE
A40: a1zNz000000XmHBIA0 | B40: Louie Blake | C40: 006Nz000003NtBlIAK | D40: a1G4J0000025xiJUAQ | E40: Completed | F40: TRUE | I40: TRUE | J40: 45246 | K40: 2023-11-17T09:48:18.000+0000 | L40: 2023-11-17T09:48:18.000+0000 | M40: 0058d00000204EOAAY | N40: =IF(Q40=TRUE,"BASIC_CRITERIA","") | P40: =DATEVALUE(SUBSTITUTE(LEFT(L40,10),"-","/")) -> 45247 | Q40: =IF(J40="",TRUE,IF(J40>P40,TRUE,FALSE)) -> FALSE
A41: a1zNz000000XmQrIAK | B41: Pascale Maynard | C41: 006Nz000003NtBlIAK | D41: a1G4J0000025xiJUAQ | E41: Completed | F41: TRUE | G41: 47150 | I41: FALSE | J41: 45246 | K41: 2023-11-17T09:56:03.000+0000 | L41: 2023-11-17T09:56:03.000+0000 | M41: 0058d00000204EOAAY | N41: =IF(Q41=TRUE,"BASIC_CRITERIA","") | P41: =DATEVALUE(SUBSTITUTE(LEFT(L41,10),"-","/")) -> 45247 | Q41: =IF(J41="",TRUE,IF(J41>P41,TRUE,FALSE)) -> FALSE
A42: a1zNz000000Z3SvIAK | B42: Tiago Barreira | C42: 006Nz000003x4lvIAA | D42: a1GNz0000000xHrMAI | E42: Completed | F42: TRUE | G42: 46241 | I42: FALSE | J42: 45250 | K42: 2023-11-20T12:01:57.000+0000 | L42: 2023-11-20T12:01:57.000+0000 | M42: 0058d00000202rVAAQ | N42: =IF(Q42=TRUE,"BASIC_CRITERIA","") | P42: =DATEVALUE(SUBSTITUTE(LEFT(L42,10),"-","/")) -> 45250 | Q42: =IF(J42="",TRUE,IF(J42>P42,TRUE,FALSE)) -> FALSE
A43: a1zNz000000an3pIAA | B43: Nilton Miguel | C43: 006Nz000004kRrQIAU | D43: a1G4J0000025wzaUAA | E43: Completed | F43: TRUE | G43: 45842 | I43: FALSE | J43: 45253 | K43: 2023-11-23T15:20:45.000+0000 | L43: 2023-11-23T15:20:45.000+0000 | M43: 0054J000004wSINQA2 | N43: =IF(Q43=TRUE,"BASIC_CRITERIA","") | P43: =DATEVALUE(SUBSTITUTE(LEFT(L43,10),"-","/")) -> 45253 | Q43: =IF(J43="",TRUE,IF(J43>P43,TRUE,FALSE)) -> FALSE
A44: a1zNz000000cIrxIAE | B44: Kristo Trajche | C44: 006Nz000004SrDbIAK | D44: a1GNz00000017HCMAY | E44: Completed | F44: TRUE | G44: 45552 | I44: FALSE | J44: 45257 | K44: 2023-11-27T14:18:59.000+0000 | L44: 2023-11-27T14:18:59.000+0000 | M44: 0058d000006chw3AAA | N44: =IF(Q44=TRUE,"BASIC_CRITERIA","") | P44: =DATEVALUE(SUBSTITUTE(LEFT(L44,10),"-","/")) -> 45257 | Q44: =IF(J44="",TRUE,IF(J44>P44,TRUE,FALSE)) -> FALSE
A45: a1zNz000000eFy1IAE | B45: Lakhvir lakha | C45: 006Nz000004U6dZIAS | D45: a1G4J00000260SaUAI | E45: Completed | F45: FALSE | I45: FALSE | J45: 45260 | K45: 2023-11-30T16:50:55.000+0000 | L45: 2023-11-30T16:50:55.000+0000 | M45: 0058d0000043sEOAAY | N45: =IF(Q45=TRUE,"BASIC_CRITERIA","") | P45: =DATEVALUE(SUBSTITUTE(LEFT(L45,10),"-","/")) -> 45260 | Q45: =IF(J45="",TRUE,IF(J45>P45,TRUE,FALSE)) -> FALSE
A46: a1zNz000000eFzdIAE | B46: Tyla Desnoes | C46: 006Nz000004U6dZIAS | D46: a1G4J00000260SaUAI | E46: Completed | F46: FALSE | I46: FALSE | J46: 45260 | K46: 2023-11-30T16:51:23.000+0000 | L46: 2023-11-30T16:51:23.000+0000 | M46: 0058d0000043sEOAAY | N46: =IF(Q46=TRUE,"BASIC_CRITERIA","") | P46: =DATEVALUE(SUBSTITUTE(LEFT(L46,10),"-","/")) -> 45260 | Q46: =IF(J46="",TRUE,IF(J46>P46,TRUE,FALSE)) -> FALSE
A47: a1zNz000000eNtxIAE | B47: liva samal | C47: 006Nz000004MpMaIAK | D47: a1G8d000002QBNJEA4 | E47: Completed | F47: TRUE | G47: 45654 | I47: FALSE | J47: 45261 | K47: 2023-12-01T09:26:14.000+0000 | L47: 2024-08-15T16:03:48.000+0000 | M47: 0058d0000043sEOAAY | N47: =IF(Q47=TRUE,"BASIC_CRITERIA","") | P47: =DATEVALUE(SUBSTITUTE(LEFT(L47,10),"-","/")) -> 45519 | Q47: =IF(J47="",TRUE,IF(J47>P47,TRUE,FALSE)) -> FALSE
A48: a1zNz000000eOQDIA2 | B48: Swati Agarwal | C48: 006Nz000004MpMaIAK | D48: a1G8d000002QBNJEA4 | E48: Completed | F48: TRUE | G48: 46753 | I48: FALSE | J48: 45261 | K48: 2023-12-01T10:01:26.000+0000 | L48: 2023-12-01T10:36:47.000+0000 | M48: 0058d0000043sEOAAY | N48: =IF(Q48=TRUE,"BASIC_CRITERIA","") | P48: =DATEVALUE(SUBSTITUTE(LEFT(L48,10),"-","/")) -> 45261 | Q48: =IF(J48="",TRUE,IF(J48>P48,TRUE,FALSE)) -> FALSE
A49: a1zNz000000zr2bIAA | B49: Renfei Wang | C49: 006Nz000006ItkGIAS | D49: a1G4J0000025zvOUAQ | E49: Completed | F49: TRUE | G49: 46014 | I49: FALSE | J49: 45301 | K49: 2024-01-10T17:39:48.000+0000 | L49: 2024-08-15T16:03:48.000+0000 | M49: 0058d0000043sEOAAY | N49: =IF(Q49=TRUE,"BASIC_CRITERIA","") | P49: =DATEVALUE(SUBSTITUTE(LEFT(L49,10),"-","/")) -> 45519 | Q49: =IF(J49="",TRUE,IF(J49>P49,TRUE,FALSE)) -> FALSE
A50: a1zNz000001DfETIA0 | B50: Jessica Khukhele | C50: 0068d00000BLXcuAAH | D50: a1G8d0000004c6PEAQ | E50: Completed | F50: FALSE | I50: FALSE | J50: 45320 | K50: 2024-02-02T15:59:33.000+0000 | L50: 2024-08-15T16:03:49.000+0000 | M50: 0058d0000034KZ2AAM | N50: =IF(Q50=TRUE,"BASIC_CRITERIA","") | P50: =DATEVALUE(SUBSTITUTE(LEFT(L50,10),"-","/")) -> 45519 | Q50: =IF(J50="",TRUE,IF(J50>P50,TRUE,FALSE)) -> FALSE
A51: a1zNz000001DfRNIA0 | B51: Nnana Mokhonoana | C51: 0068d00000BLXcuAAH | D51: a1G8d0000004c6PEAQ | E51: Completed | F51: FALSE | I51: FALSE | J51: 45320 | K51: 2024-02-02T16:10:21.000+0000 | L51: 2024-08-15T16:03:49.000+0000 | M51: 0058d0000034KZ2AAM | N51: =IF(Q51=TRUE,"BASIC_CRITERIA","") | P51: =DATEVALUE(SUBSTITUTE(LEFT(L51,10),"-","/")) -> 45519 | Q51: =IF(J51="",TRUE,IF(J51>P51,TRUE,FALSE)) -> FALSE
A52: a1zNz000001DgLpIAK | B52: Karishma Rathod | C52: 006Nz000001LMJXIA4 | D52: a1G8d0000004c81EAA | E52: Completed | F52: FALSE | I52: FALSE | J52: 45320 | K52: 2024-02-02T16:39:37.000+0000 | L52: 2024-08-15T16:03:49.000+0000 | M52: 0058d0000034KZ2AAM | N52: =IF(Q52=TRUE,"BASIC_CRITERIA","") | P52: =DATEVALUE(SUBSTITUTE(LEFT(L52,10),"-","/")) -> 45519 | Q52: =IF(J52="",TRUE,IF(J52>P52,TRUE,FALSE)) -> FALSE
A53: a1zNz000001DgNRIA0 | B53: Palak Rita | C53: 006Nz000001LMJXIA4 | D53: a1G8d0000004c81EAA | E53: Completed | F53: FALSE | I53: FALSE | J53: 45320 | K53: 2024-02-02T16:39:58.000+0000 | L53: 2024-08-15T16:03:49.000+0000 | M53: 0058d0000034KZ2AAM | N53: =IF(Q53=TRUE,"BASIC_CRITERIA","") | P53: =DATEVALUE(SUBSTITUTE(LEFT(L53,10),"-","/")) -> 45519 | Q53: =IF(J53="",TRUE,IF(J53>P53,TRUE,FALSE)) -> FALSE
A54: a1zNz000001BrgLIAS | B54: Liam Esders | E54: Completed | F54: FALSE | I54: FALSE | J54: 45322 | K54: 2024-01-31T09:50:15.000+0000 | L54: 2024-08-15T16:03:49.000+0000 | M54: 0058d000004DynQAAS | N54: =IF(Q54=TRUE,"BASIC_CRITERIA","") | P54: =DATEVALUE(SUBSTITUTE(LEFT(L54,10),"-","/")) -> 45519 | Q54: =IF(J54="",TRUE,IF(J54>P54,TRUE,FALSE)) -> FALSE
A55: a1zNz000001PStOIAW | B55: Aimee Hardy | C55: 006Nz000007KW7lIAG | D55: a1G4J0000025ztfUAA | E55: Completed | F55: FALSE | I55: FALSE | J55: 45337 | K55: 2024-02-15T10:19:31.000+0000 | L55: 2024-08-15T16:03:49.000+0000 | M55: 0054J000004wZgRQAU | N55: =IF(Q55=TRUE,"BASIC_CRITERIA","") | P55: =DATEVALUE(SUBSTITUTE(LEFT(L55,10),"-","/")) -> 45519 | Q55: =IF(J55="",TRUE,IF(J55>P55,TRUE,FALSE)) -> FALSE
A56: a1zNz000001X2YjIAK | B56: Rubi Cevik | C56: 006Nz0000084DwgIAE | D56: a1GNz0000000xrKMAQ | E56: Completed | F56: FALSE | I56: FALSE | J56: 45345 | K56: 2024-02-23T16:39:09.000+0000 | L56: 2024-08-15T16:03:49.000+0000 | M56: 0058d00000202rVAAQ | N56: =IF(Q56=TRUE,"BASIC_CRITERIA","") | P56: =DATEVALUE(SUBSTITUTE(LEFT(L56,10),"-","/")) -> 45519 | Q56: =IF(J56="",TRUE,IF(J56>P56,TRUE,FALSE)) -> FALSE
A57: a1zNz000001kOzdIAE | B57: Tsz Man Chiu | C57: 006Nz000008n5y1IAA | D57: a1G4J0000025zGTUAY | E57: Completed | F57: TRUE | G57: 46317 | I57: FALSE | J57: 45359 | K57: 2024-03-08T09:40:23.000+0000 | L57: 2024-08-15T16:03:50.000+0000 | M57: 0058d00000202rVAAQ | N57: =IF(Q57=TRUE,"BASIC_CRITERIA","") | P57: =DATEVALUE(SUBSTITUTE(LEFT(L57,10),"-","/")) -> 45519 | Q57: =IF(J57="",TRUE,IF(J57>P57,TRUE,FALSE)) -> FALSE
A58: a1zNz000001kP2rIAE | B58: Ho Hin Ng | C58: 006Nz000008n5y1IAA | D58: a1G4J0000025zGTUAY | E58: Completed | F58: FALSE | I58: FALSE | J58: 45359 | K58: 2024-03-08T09:44:24.000+0000 | L58: 2024-08-15T16:03:50.000+0000 | M58: 0058d00000202rVAAQ | N58: =IF(Q58=TRUE,"BASIC_CRITERIA","") | P58: =DATEVALUE(SUBSTITUTE(LEFT(L58,10),"-","/")) -> 45519 | Q58: =IF(J58="",TRUE,IF(J58>P58,TRUE,FALSE)) -> FALSE
A59: a1zNz0000027i3GIAQ | B59: Natalia Savelyeva | C59: 006Nz000009P3S9IAK | E59: Completed | F59: FALSE | I59: FALSE | J59: 45385 | K59: 2024-04-03T09:39:34.000+0000 | L59: 2024-08-15T16:03:50.000+0000 | M59: 0058d000004DynQAAS | N59: =IF(Q59=TRUE,"BASIC_CRITERIA","") | P59: =DATEVALUE(SUBSTITUTE(LEFT(L59,10),"-","/")) -> 45519 | Q59: =IF(J59="",TRUE,IF(J59>P59,TRUE,FALSE)) -> FALSE
A60: a1zNz0000027tuhIAA | B60: Alexandre Nicholas Gvozd | C60: 006Nz000009P3S9IAK | E60: Completed | F60: FALSE | I60: FALSE | J60: 45385 | K60: 2024-04-03T09:39:21.000+0000 | L60: 2024-08-15T16:03:50.000+0000 | M60: 0058d000004DynQAAS | N60: =IF(Q60=TRUE,"BASIC_CRITERIA","") | P60: =DATEVALUE(SUBSTITUTE(LEFT(L60,10),"-","/")) -> 45519 | Q60: =IF(J60="",TRUE,IF(J60>P60,TRUE,FALSE)) -> FALSE
A61: a1zNz000002DYkHIAW | B61: Sayako Kogawa | C61: 006Nz000009ocktIAA | D61: a1G4J000002606EUAQ | E61: Completed | F61: TRUE | G61: 46352 | I61: FALSE | J61: 45390 | K61: 2024-04-08T15:58:50.000+0000 | L61: 2024-08-15T16:03:50.000+0000 | M61: 0054J000004wZgRQAU | N61: =IF(Q61=TRUE,"BASIC_CRITERIA","") | P61: =DATEVALUE(SUBSTITUTE(LEFT(L61,10),"-","/")) -> 45519 | Q61: =IF(J61="",TRUE,IF(J61>P61,TRUE,FALSE)) -> FALSE
A62: a1zNz000002h48sIAA | B62: Lydia Anne Tibbet | C62: 006Nz00000AWd28IAD | D62: a1GNz0000000cZxMAI | E62: Completed | F62: FALSE | I62: FALSE | J62: 45426 | K62: 2024-05-07T10:38:44.000+0000 | L62: 2024-08-15T16:03:50.000+0000 | M62: 0054J000004vXOqQAM | N62: =IF(Q62=TRUE,"BASIC_CRITERIA","") | P62: =DATEVALUE(SUBSTITUTE(LEFT(L62,10),"-","/")) -> 45519 | Q62: =IF(J62="",TRUE,IF(J62>P62,TRUE,FALSE)) -> FALSE
A63: a1zNz000003AcWvIAK | B63: Alicia Kwan | C63: 006Nz00000BzwtaIAB | D63: a1G4J0000025yZKUAY | E63: Completed | F63: TRUE | G63: 45888 | I63: FALSE | J63: 45446 | K63: 2024-06-03T12:27:29.000+0000 | L63: 2024-08-15T16:03:50.000+0000 | M63: 0058d000004DOMXAA4 | N63: =IF(Q63=TRUE,"BASIC_CRITERIA","") | P63: =DATEVALUE(SUBSTITUTE(LEFT(L63,10),"-","/")) -> 45519 | Q63: =IF(J63="",TRUE,IF(J63>P63,TRUE,FALSE)) -> FALSE
A64: a1zNz000003F1i1IAC | B64: chi wing Wan | C64: 006Nz00000AiYZhIAN | D64: a1G4J000002608oUAA | E64: Completed | F64: TRUE | G64: 45935 | I64: FALSE | J64: 45449 | K64: 2024-06-06T11:17:42.000+0000 | L64: 2024-08-15T16:03:50.000+0000 | M64: 0058d000004DOMXAA4 | N64: =IF(Q64=TRUE,"BASIC_CRITERIA","") | P64: =DATEVALUE(SUBSTITUTE(LEFT(L64,10),"-","/")) -> 45519 | Q64: =IF(J64="",TRUE,IF(J64>P64,TRUE,FALSE)) -> FALSE
A65: a1zNz000000VZ9ZIAW | B65: Jamal Khoo | C65: 0068d000002cbgIAAQ | D65: a1G4J00000260SjUAI | E65: Completed | F65: TRUE | G65: 45210 | I65: TRUE | K65: 2023-11-10T12:14:46.000+0000 | L65: 2023-11-10T12:14:46.000+0000 | M65: 0058d000004Cx8uAAC | N65: =IF(Q65=TRUE,"BASIC_CRITERIA","") -> BASIC_CRITERIA | P65: =DATEVALUE(SUBSTITUTE(LEFT(L65,10),"-","/")) -> 45240 | Q65: =IF(J65="",TRUE,IF(J65>P65,TRUE,FALSE)) -> TRUE
A66: a1zNz000000VZKrIAO | B66: Shail Utkarshbhatt | D66: a1G4J00000260RIUAY | E66: Completed | F66: TRUE | G66: 46052 | I66: FALSE | J66: 45240 | K66: 2023-11-10T12:21:34.000+0000 | L66: 2023-11-10T12:21:34.000+0000 | M66: 0058d000004Cx8uAAC | N66: =IF(Q66=TRUE,"BASIC_CRITERIA","") | P66: =DATEVALUE(SUBSTITUTE(LEFT(L66,10),"-","/")) -> 45240 | Q66: =IF(J66="",TRUE,IF(J66>P66,TRUE,FALSE)) -> FALSE
A67: a1zNz000000gz2IIAQ | B67: Austin Rwodzi | C67: 0068d00000Cs6BVAAZ | D67: a1G4J0000025xf0UAA | E67: Completed | F67: TRUE | G67: 45505 | I67: TRUE | K67: 2023-12-07T10:58:53.000+0000 | L67: 2023-12-07T10:58:53.000+0000 | M67: 0058d000004Cx8uAAC | N67: =IF(Q67=TRUE,"BASIC_CRITERIA","") -> BASIC_CRITERIA | P67: =DATEVALUE(SUBSTITUTE(LEFT(L67,10),"-","/")) -> 45267 | Q67: =IF(J67="",TRUE,IF(J67>P67,TRUE,FALSE)) -> TRUE
A68: a1zNz000000upZJIAY | B68: Krishnanjana Jayachandran | C68: 0068d00000F4mDIAAZ | E68: Completed | F68: TRUE | G68: 45504 | I68: TRUE | K68: 2024-01-03T11:21:37.000+0000 | L68: 2024-01-03T11:21:37.000+0000 | M68: 0058d000006d4S2AAI | N68: =IF(Q68=TRUE,"BASIC_CRITERIA","") -> BASIC_CRITERIA | P68: =DATEVALUE(SUBSTITUTE(LEFT(L68,10),"-","/")) -> 45294 | Q68: =IF(J68="",TRUE,IF(J68>P68,TRUE,FALSE)) -> TRUE
A69: a1zPv000000mh97IAA | B69: Joe Pilkington | C69: 006Pv000009pWwjIAE | E69: Completed | F69: TRUE | G69: 45518 | I69: TRUE | K69: 2024-08-14T08:51:00.000+0000 | L69: 2024-08-14T09:04:15.000+0000 | M69: 00GPv000002kNznMAE | N69: =IF(Q69=TRUE,"BASIC_CRITERIA","") -> BASIC_CRITERIA | P69: =DATEVALUE(SUBSTITUTE(LEFT(L69,10),"-","/")) -> 45518 | Q69: =IF(J69="",TRUE,IF(J69>P69,TRUE,FALSE)) -> TRUE
A70: a1zNz0000000OdSIAU | B70: Ruoxi Leng | C70: 006Nz000001UfRlIAK | D70: a1G4J000004jyp9UAA | E70: Completed | F70: TRUE | G70: 45676 | I70: TRUE | K70: 2023-09-05T11:21:04.000+0000 | L70: 2024-08-15T16:03:46.000+0000 | M70: 0054J000006BkQgQAK | N70: =IF(Q70=TRUE,"BASIC_CRITERIA","") -> BASIC_CRITERIA | P70: =DATEVALUE(SUBSTITUTE(LEFT(L70,10),"-","/")) -> 45519 | Q70: =IF(J70="",TRUE,IF(J70>P70,TRUE,FALSE)) -> TRUE
A71: a1zNz000000Cm45IAC | B71: Lok Ching Wong | C71: 006Nz000002PqSGIA0 | D71: a1GNz0000000vxZMAQ | E71: Completed | F71: TRUE | G71: 46652 | I71: TRUE | K71: 2023-10-10T13:29:47.000+0000 | L71: 2024-08-15T16:03:46.000+0000 | M71: 0054J000004wSINQA2 | N71: =IF(Q71=TRUE,"BASIC_CRITERIA","") -> BASIC_CRITERIA | P71: =DATEVALUE(SUBSTITUTE(LEFT(L71,10),"-","/")) -> 45519 | Q71: =IF(J71="",TRUE,IF(J71>P71,TRUE,FALSE)) -> TRUE
A72: a1zNz000000ET5NIAW | B72: Jittrapa Phurkvimolphan | D72: a1G8d000002Q2SZEA0 | E72: Completed | F72: TRUE | G72: 45675 | I72: TRUE | K72: 2023-10-13T13:08:30.000+0000 | L72: 2024-08-15T16:03:46.000+0000 | M72: 0058d000001yXeuAAE | N72: =IF(Q72=TRUE,"BASIC_CRITERIA","") -> BASIC_CRITERIA | P72: =DATEVALUE(SUBSTITUTE(LEFT(L72,10),"-","/")) -> 45519 | Q72: =IF(J72="",TRUE,IF(J72>P72,TRUE,FALSE)) -> TRUE
A73: a1zNz000000VZG1IAO | B73: Akhil Vaswani | D73: a1G4J00000260RIUAY | E73: Completed | F73: TRUE | G73: 46233 | I73: TRUE | K73: 2023-11-10T12:18:31.000+0000 | L73: 2024-08-15T16:03:47.000+0000 | M73: 0058d000004Cx8uAAC | N73: =IF(Q73=TRUE,"BASIC_CRITERIA","") -> BASIC_CRITERIA | P73: =DATEVALUE(SUBSTITUTE(LEFT(L73,10),"-","/")) -> 45519 | Q73: =IF(J73="",TRUE,IF(J73>P73,TRUE,FALSE)) -> TRUE
A74: a1zNz000000VZHdIAO | B74: Pranav Gattani | D74: a1G4J00000260RIUAY | E74: Completed | F74: TRUE | G74: 46279 | I74: TRUE | K74: 2023-11-10T12:20:23.000+0000 | L74: 2024-08-15T16:03:47.000+0000 | M74: 0058d000004Cx8uAAC | N74: =IF(Q74=TRUE,"BASIC_CRITERIA","") -> BASIC_CRITERIA | P74: =DATEVALUE(SUBSTITUTE(LEFT(L74,10),"-","/")) -> 45519 | Q74: =IF(J74="",TRUE,IF(J74>P74,TRUE,FALSE)) -> TRUE
A75: a1zNz000000VaYfIAK | B75: Sihyun Kim | D75: a1G4J0000025xQUUAY | E75: Completed | F75: TRUE | G75: 46149 | I75: TRUE | K75: 2023-11-10T14:09:59.000+0000 | L75: 2024-08-15T16:03:47.000+0000 | M75: 0058d000004Cx8uAAC | N75: =IF(Q75=TRUE,"BASIC_CRITERIA","") -> BASIC_CRITERIA | P75: =DATEVALUE(SUBSTITUTE(LEFT(L75,10),"-","/")) -> 45519 | Q75: =IF(J75="",TRUE,IF(J75>P75,TRUE,FALSE)) -> TRUE
A76: a1zNz000000VabtIAC | B76: Yu Hong Leung | C76: 0064J00000DFU4gQAH | D76: a1G4J0000025xQUUAY | E76: Completed | F76: TRUE | G76: 46249 | I76: TRUE | K76: 2023-11-10T14:11:26.000+0000 | L76: 2024-08-15T16:03:47.000+0000 | M76: 0058d000004Cx8uAAC | N76: =IF(Q76=TRUE,"BASIC_CRITERIA","") -> BASIC_CRITERIA | P76: =DATEVALUE(SUBSTITUTE(LEFT(L76,10),"-","/")) -> 45519 | Q76: =IF(J76="",TRUE,IF(J76>P76,TRUE,FALSE)) -> TRUE
A77: a1zNz000000WCUHIA4 | B77: Rommel Dy | C77: 006Nz0000011vWjIAI | D77: a1G4J0000025zuiUAA | E77: Completed | F77: TRUE | G77: 46309 | I77: TRUE | K77: 2023-11-14T15:00:07.000+0000 | L77: 2024-08-15T16:03:47.000+0000 | M77: 0058d000004Cx8uAAC | N77: =IF(Q77=TRUE,"BASIC_CRITERIA","") -> BASIC_CRITERIA | P77: =DATEVALUE(SUBSTITUTE(LEFT(L77,10),"-","/")) -> 45519 | Q77: =IF(J77="",TRUE,IF(J77>P77,TRUE,FALSE)) -> TRUE
A78: a1zNz000000XeczIAC | B78: Charles Egbuonu | C78: 006Nz000004EGylIAG | D78: a1GNz0000000wDhMAI | E78: Completed | F78: TRUE | G78: 46183 | I78: TRUE | K78: 2023-11-16T14:37:58.000+0000 | L78: 2024-08-15T16:03:48.000+0000 | M78: 0058d00000202rVAAQ | N78: =IF(Q78=TRUE,"BASIC_CRITERIA","") -> BASIC_CRITERIA | P78: =DATEVALUE(SUBSTITUTE(LEFT(L78,10),"-","/")) -> 45519 | Q78: =IF(J78="",TRUE,IF(J78>P78,TRUE,FALSE)) -> TRUE
A79: a1zNz000000guXOIAY | B79: Tunde Ganiy | C79: 0068d000003tzz5AAA | D79: a1G4J00000260R8UAI | E79: Completed | F79: TRUE | G79: 46022 | I79: TRUE | K79: 2023-12-07T09:50:57.000+0000 | L79: 2024-08-15T16:03:48.000+0000 | M79: 0058d000004Cx8uAAC | N79: =IF(Q79=TRUE,"BASIC_CRITERIA","") -> BASIC_CRITERIA | P79: =DATEVALUE(SUBSTITUTE(LEFT(L79,10),"-","/")) -> 45519 | Q79: =IF(J79="",TRUE,IF(J79>P79,TRUE,FALSE)) -> TRUE
A80: a1zNz000000gvrVIAQ | B80: Zainab Ayodimeji | C80: 0068d000003tzz5AAA | D80: a1G4J00000260R8UAI | E80: Completed | F80: TRUE | G80: 46140 | I80: TRUE | K80: 2023-12-07T09:55:06.000+0000 | L80: 2024-08-15T16:03:48.000+0000 | M80: 0058d000004Cx8uAAC | N80: =IF(Q80=TRUE,"BASIC_CRITERIA","") -> BASIC_CRITERIA | P80: =DATEVALUE(SUBSTITUTE(LEFT(L80,10),"-","/")) -> 45519 | Q80: =IF(J80="",TRUE,IF(J80>P80,TRUE,FALSE)) -> TRUE
A81: a1zNz000000nS3BIAU | B81: Mijung Yu | C81: 006Nz000001LEnPIAW | D81: a1G8d0000005rAkEAI | E81: Completed | F81: TRUE | G81: 46226 | I81: TRUE | K81: 2023-12-19T15:48:22.000+0000 | L81: 2024-08-15T16:03:48.000+0000 | M81: 005Nz0000013xmDIAQ | N81: =IF(Q81=TRUE,"BASIC_CRITERIA","") -> BASIC_CRITERIA | P81: =DATEVALUE(SUBSTITUTE(LEFT(L81,10),"-","/")) -> 45519 | Q81: =IF(J81="",TRUE,IF(J81>P81,TRUE,FALSE)) -> TRUE
A82: a1zNz000000rdeLIAQ | B82: Andrey Kluban | C82: 006Nz000000jk1wIAA | D82: a1G8d0000005rJIEAY | E82: Completed | F82: TRUE | G82: 46310 | I82: TRUE | K82: 2023-12-28T10:22:05.000+0000 | L82: 2024-08-15T16:03:48.000+0000 | M82: 005Nz0000013xmDIAQ | N82: =IF(Q82=TRUE,"BASIC_CRITERIA","") -> BASIC_CRITERIA | P82: =DATEVALUE(SUBSTITUTE(LEFT(L82,10),"-","/")) -> 45519 | Q82: =IF(J82="",TRUE,IF(J82>P82,TRUE,FALSE)) -> TRUE
A83: a1zNz000000s8JxIAI | B83: Lin Hu | D83: a1G4J000004jyeQUAQ | E83: Completed | F83: TRUE | G83: 45687 | I83: TRUE | K83: 2023-12-29T16:05:15.000+0000 | L83: 2024-08-15T16:03:48.000+0000 | M83: 0058d0000034Kn5AAE | N83: =IF(Q83=TRUE,"BASIC_CRITERIA","") -> BASIC_CRITERIA | P83: =DATEVALUE(SUBSTITUTE(LEFT(L83,10),"-","/")) -> 45519 | Q83: =IF(J83="",TRUE,IF(J83>P83,TRUE,FALSE)) -> TRUE
A84: a1zNz000000vt6DIAQ | B84: Akshitha Gajula | C84: 006Nz000004wNoMIAU | D84: a1G4J0000025x2OUAQ | E84: Completed | F84: TRUE | G84: 45677 | I84: TRUE | K84: 2024-01-04T11:03:17.000+0000 | L84: 2024-08-15T16:03:48.000+0000 | M84: 0058d0000043sEOAAY | N84: =IF(Q84=TRUE,"BASIC_CRITERIA","") -> BASIC_CRITERIA | P84: =DATEVALUE(SUBSTITUTE(LEFT(L84,10),"-","/")) -> 45519 | Q84: =IF(J84="",TRUE,IF(J84>P84,TRUE,FALSE)) -> TRUE
A85: a1zNz000000znBtIAI | B85: Elif Eroglu | C85: 0068d00000Cs1DiAAJ | D85: a1G4J00000260NLUAY | E85: Completed | F85: TRUE | G85: 46005 | I85: TRUE | K85: 2024-01-10T14:07:55.000+0000 | L85: 2024-08-15T16:03:48.000+0000 | M85: 0058d000004Cx8uAAC | N85: =IF(Q85=TRUE,"BASIC_CRITERIA","") -> BASIC_CRITERIA | P85: =DATEVALUE(SUBSTITUTE(LEFT(L85,10),"-","/")) -> 45519 | Q85: =IF(J85="",TRUE,IF(J85>P85,TRUE,FALSE)) -> TRUE
A86: a1zNz0000014YP7IAM | B86: Ryan Carlton | D86: a1G4J0000025y4WUAQ | E86: Completed | F86: FALSE | I86: TRUE | K86: 2024-01-19T14:48:05.000+0000 | L86: 2024-08-15T16:03:49.000+0000 | M86: 0058d000004DynQAAS | N86: =IF(Q86=TRUE,"BASIC_CRITERIA","") -> BASIC_CRITERIA | P86: =DATEVALUE(SUBSTITUTE(LEFT(L86,10),"-","/")) -> 45519 | Q86: =IF(J86="",TRUE,IF(J86>P86,TRUE,FALSE)) -> TRUE
A87: a1zNz0000014YQjIAM | B87: Sophie Lee | D87: a1G4J0000025y4WUAQ | E87: Completed | F87: FALSE | I87: TRUE | K87: 2024-01-19T14:49:14.000+0000 | L87: 2024-08-15T16:03:49.000+0000 | M87: 0058d000004DynQAAS | N87: =IF(Q87=TRUE,"BASIC_CRITERIA","") -> BASIC_CRITERIA | P87: =DATEVALUE(SUBSTITUTE(LEFT(L87,10),"-","/")) -> 45519 | Q87: =IF(J87="",TRUE,IF(J87>P87,TRUE,FALSE)) -> TRUE
A88: a1zNz0000016PG7IAM | B88: Bence Cserkuti | C88: 006Nz000006hHTbIAM | D88: a1G8d0000004qaEEAQ | E88: Completed | F88: FALSE | I88: TRUE | K88: 2024-01-23T14:58:33.000+0000 | L88: 2024-08-15T16:03:49.000+0000 | M88: 005Nz000000eYuFIAU | N88: =IF(Q88=TRUE,"BASIC_CRITERIA","") -> BASIC_CRITERIA | P88: =DATEVALUE(SUBSTITUTE(LEFT(L88,10),"-","/")) -> 45519 | Q88: =IF(J88="",TRUE,IF(J88>P88,TRUE,FALSE)) -> TRUE
A89: a1zNz000001DfhVIAS | B89: Alice Belshaw | C89: 006Nz000001ba3yIAA | D89: a1G8d0000004c9mEAA | E89: Completed | F89: TRUE | G89: 45682 | I89: TRUE | K89: 2024-02-02T16:27:04.000+0000 | L89: 2024-08-15T16:03:49.000+0000 | M89: 0058d0000034KZ2AAM | N89: =IF(Q89=TRUE,"BASIC_CRITERIA","") -> BASIC_CRITERIA | P89: =DATEVALUE(SUBSTITUTE(LEFT(L89,10),"-","/")) -> 45519 | Q89: =IF(J89="",TRUE,IF(J89>P89,TRUE,FALSE)) -> TRUE
A90: a1zNz000001JSZWIA4 | B90: Xiaotian Xie | D90: a1G8d000002Q2a0EAC | E90: Completed | F90: TRUE | G90: 45657 | I90: TRUE | K90: 2024-02-09T11:00:33.000+0000 | L90: 2024-08-15T16:03:49.000+0000 | M90: 005Nz000000FVd0IAG | N90: =IF(Q90=TRUE,"BASIC_CRITERIA","") -> BASIC_CRITERIA | P90: =DATEVALUE(SUBSTITUTE(LEFT(L90,10),"-","/")) -> 45519 | Q90: =IF(J90="",TRUE,IF(J90>P90,TRUE,FALSE)) -> TRUE
A91: a1zNz000001JSzJIAW | B91: Jessica Yan | D91: a1G8d000002Q2a0EAC | E91: Completed | F91: TRUE | G91: 45657 | I91: TRUE | K91: 2024-02-09T11:02:00.000+0000 | L91: 2024-08-15T16:03:49.000+0000 | M91: 005Nz000000FVd0IAG | N91: =IF(Q91=TRUE,"BASIC_CRITERIA","") -> BASIC_CRITERIA | P91: =DATEVALUE(SUBSTITUTE(LEFT(L91,10),"-","/")) -> 45519 | Q91: =IF(J91="",TRUE,IF(J91>P91,TRUE,FALSE)) -> TRUE
A92: a1zNz000001Ta5xIAC | B92: Delna Dotivala | C92: 006Nz000007uQwgIAE | D92: a1G4J0000025wxVUAQ | E92: Completed | F92: TRUE | G92: 45995 | I92: TRUE | K92: 2024-02-20T09:48:47.000+0000 | L92: 2024-08-15T16:03:49.000+0000 | M92: 005Nz000002KcrEIAS | N92: =IF(Q92=TRUE,"BASIC_CRITERIA","") -> BASIC_CRITERIA | P92: =DATEVALUE(SUBSTITUTE(LEFT(L92,10),"-","/")) -> 45519 | Q92: =IF(J92="",TRUE,IF(J92>P92,TRUE,FALSE)) -> TRUE
A93: a1zNz000001TaPKIA0 | B93: Hamid Siddiqui | C93: 006Nz000007uQwgIAE | D93: a1G4J0000025wxVUAQ | E93: Completed | F93: TRUE | G93: 45995 | I93: TRUE | K93: 2024-02-20T09:51:56.000+0000 | L93: 2024-08-15T16:03:49.000+0000 | M93: 005Nz000002KcrEIAS | N93: =IF(Q93=TRUE,"BASIC_CRITERIA","") -> BASIC_CRITERIA | P93: =DATEVALUE(SUBSTITUTE(LEFT(L93,10),"-","/")) -> 45519 | Q93: =IF(J93="",TRUE,IF(J93>P93,TRUE,FALSE)) -> TRUE
A94: a1zNz000001UYA9IAO | B94: Teresa To | D94: a1G4J000002634bUAA | E94: Completed | F94: TRUE | G94: 46145 | I94: TRUE | K94: 2024-02-21T09:05:41.000+0000 | L94: 2024-08-15T16:03:49.000+0000 | M94: 0054J000004vm8oQAA | N94: =IF(Q94=TRUE,"BASIC_CRITERIA","") -> BASIC_CRITERIA | P94: =DATEVALUE(SUBSTITUTE(LEFT(L94,10),"-","/")) -> 45519 | Q94: =IF(J94="",TRUE,IF(J94>P94,TRUE,FALSE)) -> TRUE
A95: a1zNz000001WWiXIAW | B95: Terri Sandiford | C95: 006Nz0000089UgnIAE | D95: a1G4J0000025xhtUAA | E95: Completed | F95: FALSE | I95: TRUE | K95: 2024-02-22T13:21:57.000+0000 | L95: 2024-08-15T16:03:49.000+0000 | M95: 0054J000004vXOqQAM | N95: =IF(Q95=TRUE,"BASIC_CRITERIA","") -> BASIC_CRITERIA | P95: =DATEVALUE(SUBSTITUTE(LEFT(L95,10),"-","/")) -> 45519 | Q95: =IF(J95="",TRUE,IF(J95>P95,TRUE,FALSE)) -> TRUE
A96: a1zNz000001iVE1IAM | B96: Noor Khalid Abdelmajeed | C96: 006Nz000005MMbnIAG | E96: Completed | F96: TRUE | G96: 45923 | I96: TRUE | K96: 2024-03-06T12:23:47.000+0000 | L96: 2024-08-15T16:03:49.000+0000 | M96: 0054J000004vXP2QAM | N96: =IF(Q96=TRUE,"BASIC_CRITERIA","") -> BASIC_CRITERIA | P96: =DATEVALUE(SUBSTITUTE(LEFT(L96,10),"-","/")) -> 45519 | Q96: =IF(J96="",TRUE,IF(J96>P96,TRUE,FALSE)) -> TRUE
A97: a1zNz000001itTFIAY | B97: Amy Johnson | C97: 006Nz000007tRgLIAU | D97: a1G8d0000004cBnEAI | E97: Completed | F97: FALSE | I97: TRUE | K97: 2024-03-06T16:25:57.000+0000 | L97: 2024-08-15T16:03:49.000+0000 | M97: 0058d000006chw3AAA | N97: =IF(Q97=TRUE,"BASIC_CRITERIA","") -> BASIC_CRITERIA | P97: =DATEVALUE(SUBSTITUTE(LEFT(L97,10),"-","/")) -> 45519 | Q97: =IF(J97="",TRUE,IF(J97>P97,TRUE,FALSE)) -> TRUE
A98: a1zNz000002PXCXIA4 | B98: Callum Mccafferty | C98: 006Nz00000A7pEdIAJ | D98: a1G4J0000025zxoUAA | E98: Completed | F98: FALSE | I98: TRUE | K98: 2024-04-19T10:44:09.000+0000 | L98: 2024-08-15T16:03:50.000+0000 | M98: 0058d00000204EOAAY | N98: =IF(Q98=TRUE,"BASIC_CRITERIA","") -> BASIC_CRITERIA | P98: =DATEVALUE(SUBSTITUTE(LEFT(L98,10),"-","/")) -> 45519 | Q98: =IF(J98="",TRUE,IF(J98>P98,TRUE,FALSE)) -> TRUE
A99: a1zNz000002g4xOIAQ | B99: Baher Hanna | C99: 006Nz0000030Q8tIAE | D99: a1G8d0000005rP1EAI | E99: Completed | F99: TRUE | G99: 46021 | I99: TRUE | K99: 2024-05-06T12:03:47.000+0000 | L99: 2024-08-15T16:03:50.000+0000 | M99: 005Nz000002TJ6AIAW | N99: =IF(Q99=TRUE,"BASIC_CRITERIA","") -> BASIC_CRITERIA | P99: =DATEVALUE(SUBSTITUTE(LEFT(L99,10),"-","/")) -> 45519 | Q99: =IF(J99="",TRUE,IF(J99>P99,TRUE,FALSE)) -> TRUE
A100: a1zNz000002j44pIAA | B100: Joseph Kelly | C100: 006Nz00000B2ZJYIA3 | D100: a1G8d0000005rFzEAI | E100: Completed | F100: FALSE | I100: TRUE | K100: 2024-05-09T09:03:50.000+0000 | L100: 2024-08-15T16:03:50.000+0000 | M100: 0054J000004vXP2QAM | N100: =IF(Q100=TRUE,"BASIC_CRITERIA","") -> BASIC_CRITERIA | P100: =DATEVALUE(SUBSTITUTE(LEFT(L100,10),"-","/")) -> 45519 | Q100: =IF(J100="",TRUE,IF(J100>P100,TRUE,FALSE)) -> TRUE
...

Sheet RTR with No Document Upload
A1: Id | B1: Tenant__r.Name | C1: Related_Opportunity__c | D1: Related_Unit__c | E1: Status__c | F1: Time_Limited__c | G1: RTR_Expiry__c | H1: Date_Next_RTR_Required__c | I1: Document_Saved__c | J1: Check_Date__c | K1: CreatedDate | L1: LastModifiedDate | M1: OwnerId | N1: Criteria | P1: AttachedContentDocuments.totalSize | Q1: AttachedContentDocuments.done | R1: AttachedContentDocuments.records.0.Id | S1: AttachedContentDocuments.records.1.Id | T1: AttachedContentDocuments.records.2.Id | U1: AttachedContentDocuments.records.3.Id | V1: AttachedContentDocuments.records.4.Id | W1: AttachedContentDocuments.records.5.Id
A2: a1zNz00000001ddIAA | B2: Puja Aggarwal | C2: 006Nz000001QqYfIAK | D2: a1G4J000004jyoaUAA | E2: Completed | F2: FALSE | I2: TRUE | J2: 45154 | K2: 2023-08-16T14:52:09.000+0000 | L2: 2024-08-15T16:03:46.000+0000 | M2: 0058d00000202rVAAQ | N2: =IF(P2="","NO_DOCS_UPLOADED","") | P2: 2 | Q2: TRUE | R2: 06ANz000001BGUfMAO | S2: 06ANz000001BJF6MAO
A3: a1zNz00000003AnIAI | B3: 2MdM8M7dojhoxxGYABAj NwdLWsMpDGbakVQnWm7v | C3: 006Nz000001f3CfIAI | D3: a1G4J0000025z4AUAQ | E3: Completed | F3: FALSE | I3: TRUE | J3: 45159 | K3: 2023-08-21T14:40:42.000+0000 | L3: 2024-08-15T16:03:46.000+0000 | M3: 0054J000006BkQgQAK | N3: =IF(P3="","NO_DOCS_UPLOADED","") | P3: 1 | Q3: TRUE | R3: 06ANz000001FWEPMA4
A4: a1zNz00000003QvIAI | B4: Thendo Makgatho | D4: a1G4J000004jyeVUAQ | E4: Completed | F4: TRUE | G4: 45522 | I4: TRUE | J4: 45159 | K4: 2023-08-22T11:00:40.000+0000 | L4: 2024-08-15T16:03:46.000+0000 | M4: 0058d0000034Kn5AAE | N4: =IF(P4="","NO_DOCS_UPLOADED","") | P4: 1 | Q4: TRUE | R4: 06ANz000001JVpLMAW
A5: a1zNz00000004I9IAI | B5: Suliman Almazyad | C5: 006Nz000001QhFFIA0 | D5: a1G4J000004jycyUAA | E5: Completed | F5: TRUE | G5: 45687 | I5: TRUE | J5: 45161 | K5: 2023-08-23T13:27:20.000+0000 | L5: 2024-08-15T16:03:46.000+0000 | M5: 0058d00000202rVAAQ | N5: =IF(P5="","NO_DOCS_UPLOADED","") | P5: 1 | Q5: TRUE | R5: 06ANz000001IC9RMAW
A6: a1zNz00000004RpIAI | B6: Test Mohamed | D6: a1G4J000004jynNUAQ | E6: Completed | F6: TRUE | G6: 45960 | I6: TRUE | J6: 45138 | K6: 2023-08-23T14:33:15.000+0000 | L6: 2024-08-15T16:03:46.000+0000 | M6: 0058d0000034Kn5AAE | N6: =IF(P6="","NO_DOCS_UPLOADED","") | P6: 1 | Q6: TRUE | R6: 06ANz000001JXxQMAW
A7: a1zNz00000004hxIAA | B7: Ugochukwu Maduanusi | C7: 006Nz000001ThvUIAS | D7: a1G8d0000004DBDEA2 | E7: Completed | F7: FALSE | I7: TRUE | J7: 45162 | K7: 2023-08-24T09:27:14.000+0000 | L7: 2023-09-04T12:26:08.000+0000 | M7: 0058d00000202rVAAQ | N7: =IF(P7="","NO_DOCS_UPLOADED","") | P7: 1 | Q7: TRUE | R7: 06ANz000001JMIyMAO
A8: a1zNz00000004tFIAQ | B8: Chunjie Wu | C8: 006Nz0000018rmZIAQ | D8: a1G8d0000004DJvEAM | E8: Completed | F8: TRUE | G8: 45303 | I8: TRUE | J8: 45162 | K8: 2023-08-24T14:21:53.000+0000 | L8: 2023-09-04T12:27:05.000+0000 | M8: 0058d00000202rVAAQ | N8: =IF(P8="","NO_DOCS_UPLOADED","") | P8: 1 | Q8: TRUE | R8: 06ANz000001JqLkMAK
A9: a1zNz000000052vIAA | B9: Amani Alattas | C9: 006Nz000001pK2bIAE | D9: a1G4J000004jynJUAQ | E9: In Progress | F9: TRUE | G9: 45261 | I9: TRUE | J9: 45163 | K9: 2023-08-25T08:13:09.000+0000 | L9: 2023-09-04T12:10:01.000+0000 | M9: 0058d00000202rVAAQ | P9: 1 | Q9: TRUE | R9: 06ANz000001KenbMAC
A10: a1zNz00000005FpIAI | B10: Charmaine Kilonzo | C10: 006Nz000001nugPIAQ | D10: a1G4J000004jyekUAA | E10: Completed | F10: FALSE | I10: TRUE | J10: 45163 | K10: 2023-08-25T10:07:49.000+0000 | L10: 2024-08-15T16:03:46.000+0000 | M10: 0058d00000202rVAAQ | N10: =IF(P10="","NO_DOCS_UPLOADED","") | P10: 1 | Q10: TRUE | R10: 06ANz000001KrRaMAK
A11: a1zNz0000000AtpIAE | B11: Hanan Alhasan | C11: 006Nz000001lSWjIAM | D11: a1G4J000004jyj6UAA | E11: Completed | F11: TRUE | G11: 45882 | I11: TRUE | J11: 45168 | K11: 2023-08-30T15:19:11.000+0000 | L11: 2024-08-15T16:03:46.000+0000 | M11: 0054J000006BkQgQAK | N11: =IF(P11="","NO_DOCS_UPLOADED","") | P11: 1 | Q11: TRUE | R11: 06ANz000001RODsMAO
A12: a1zNz0000000CxFIAU | B12: Fajer Alalawi | C12: 006Nz000001lKAxIAM | D12: a1G4J000004jypjUAA | E12: Completed | F12: TRUE | G12: 47118 | I12: TRUE | J12: 45169 | K12: 2023-08-31T09:58:16.000+0000 | L12: 2024-08-15T16:03:46.000+0000 | M12: 0054J000006BkQgQAK | N12: =IF(P12="","NO_DOCS_UPLOADED","") | P12: 1 | Q12: TRUE | R12: 06ANz000001SIREMA4
A13: a1zNz0000000FjpIAE | B13: Afeke Hormeku | D13: a1G4J000004jyoWUAQ | E13: Completed | F13: TRUE | G13: 45519 | I13: TRUE | J13: 45169 | K13: 2023-09-01T12:11:29.000+0000 | L13: 2024-08-15T16:03:46.000+0000 | M13: 0058d0000034Kn5AAE | N13: =IF(P13="","NO_DOCS_UPLOADED","") | P13: 1 | Q13: TRUE | R13: 06ANz000001TyToMAK
A14: a1zNz0000000OdRIAU | B14: Jiaji Li | C14: 006Nz000001UfRlIAK | D14: a1G4J000004jyp9UAA | E14: Completed | F14: TRUE | G14: 45260 | I14: TRUE | J14: 45174 | K14: 2023-09-05T11:20:23.000+0000 | L14: 2023-09-05T11:21:25.000+0000 | M14: 0054J000006BkQgQAK | N14: =IF(P14="","NO_DOCS_UPLOADED","") | P14: 1 | Q14: TRUE | R14: 06ANz000001XnG6MAK
A15: a1zNz0000000OdSIAU | B15: Ruoxi Leng | C15: 006Nz000001UfRlIAK | D15: a1G4J000004jyp9UAA | E15: Completed | F15: TRUE | G15: 45676 | I15: TRUE | K15: 2023-09-05T11:21:04.000+0000 | L15: 2024-08-15T16:03:46.000+0000 | M15: 0054J000006BkQgQAK | N15: =IF(P15="","NO_DOCS_UPLOADED","") | P15: 1 | Q15: TRUE | R15: 06ANz000001XhXTMA0
A16: a1zNz0000000OjtIAE | B16: Abdulaziz Alkandari | C16: 006Nz000001vbbsIAA | D16: a1G4J000004jyvCUAQ | E16: Completed | F16: TRUE | G16: 45251 | I16: TRUE | J16: 45174 | K16: 2023-09-05T11:47:52.000+0000 | L16: 2023-09-05T11:48:13.000+0000 | M16: 0054J000006BkQgQAK | N16: =IF(P16="","NO_DOCS_UPLOADED","") | P16: 1 | Q16: TRUE | R16: 06ANz000001XqNhMAK
A17: a1zNz0000000Po1IAE | B17: Emilia Cole | C17: 006Nz000001mghBIAQ | D17: a1G4J000004jyu4UAA | E17: Completed | F17: FALSE | I17: TRUE | J17: 45175 | K17: 2023-09-06T11:14:58.000+0000 | L17: 2024-08-15T16:03:46.000+0000 | M17: 0054J000006BkQgQAK | N17: =IF(P17="","NO_DOCS_UPLOADED","") | P17: 1 | Q17: TRUE | R17: 06ANz000001ZGU2MAO
A18: a1zNz0000000PrFIAU | B18: Asina Kaya | C18: 006Nz000001f9oLIAQ | D18: a1G4J000004jyhFUAQ | E18: Completed | F18: TRUE | G18: 45253 | I18: TRUE | J18: 45175 | K18: 2023-09-06T12:37:46.000+0000 | L18: 2023-09-06T12:37:46.000+0000 | M18: 0054J000006BkQgQAK | N18: =IF(P18="","NO_DOCS_UPLOADED","") | P18: 1 | Q18: TRUE | R18: 06ANz000001ZMoIMAW
A19: a1zNz0000000PsrIAE | B19: Hakki Kaya | C19: 006Nz000001f9oLIAQ | D19: a1G4J000004jyhFUAQ | E19: Completed | F19: TRUE | G19: 45253 | I19: TRUE | J19: 45175 | K19: 2023-09-06T12:38:27.000+0000 | L19: 2023-09-06T12:38:27.000+0000 | M19: 0054J000006BkQgQAK | N19: =IF(P19="","NO_DOCS_UPLOADED","") | P19: 1 | Q19: TRUE | R19: 06ANz000001ZMl4MAG
A20: a1zNz0000000T5FIAU | B20: Luke Tibbetts | C20: 006Nz000001TeJGIA0 | D20: a1G4J000004jymPUAQ | E20: Completed | F20: FALSE | I20: TRUE | J20: 45177 | K20: 2023-09-08T12:02:06.000+0000 | L20: 2024-08-15T16:03:46.000+0000 | M20: 0058d00000202rVAAQ | N20: =IF(P20="","NO_DOCS_UPLOADED","") | P20: 1 | Q20: TRUE | R20: 06ANz000001c368MAA
A21: a1zNz0000000T6rIAE | B21: Richard Marshall | C21: 006Nz000001TeJGIA0 | D21: a1G4J000004jymPUAQ | E21: Completed | F21: FALSE | I21: TRUE | J21: 45177 | K21: 2023-09-08T12:03:20.000+0000 | L21: 2024-08-15T16:03:46.000+0000 | M21: 0058d00000202rVAAQ | N21: =IF(P21="","NO_DOCS_UPLOADED","") -> NO_DOCS_UPLOADED
A22: a1zNz0000000Ue1IAE | B22: Joseph Malik | D22: a1G4J000004jydcUAA | E22: Completed | F22: FALSE | I22: TRUE | J22: 45178 | K22: 2023-09-09T13:40:31.000+0000 | L22: 2024-08-15T16:03:46.000+0000 | M22: 0058d0000034Kn5AAE | N22: =IF(P22="","NO_DOCS_UPLOADED","") | P22: 1 | Q22: TRUE | R22: 06ANz000001d7ViMAI
A23: a1zNz0000000UirIAE | B23: Matthew Hughes | D23: a1G4J000004jydcUAA | E23: Completed | F23: FALSE | I23: TRUE | J23: 45178 | K23: 2023-09-09T13:45:34.000+0000 | L23: 2024-08-15T16:03:46.000+0000 | M23: 0058d0000034Kn5AAE | N23: =IF(P23="","NO_DOCS_UPLOADED","") | P23: 1 | Q23: TRUE | R23: 06ANz000001d4bAMAQ
A24: a1zNz0000000WEQIA2 | B24: Sophie Tolson | C24: 006Nz000001mghBIAQ | D24: a1G4J000004jyu4UAA | E24: Completed | F24: FALSE | I24: TRUE | J24: 45180 | K24: 2023-09-11T08:30:00.000+0000 | L24: 2024-08-15T16:03:46.000+0000 | M24: 0054J000006BkQgQAK | N24: =IF(P24="","NO_DOCS_UPLOADED","") | P24: 1 | Q24: TRUE | R24: 06ANz000001eGSXMA2
A25: a1zNz0000000WpVIAU | B25: Joseph Malik | C25: 006Nz000001Tcz1IAC | D25: a1G4J000004jydcUAA | E25: Completed | F25: FALSE | I25: TRUE | J25: 45178 | K25: 2023-09-11T10:25:52.000+0000 | L25: 2024-08-15T16:03:46.000+0000 | M25: 0058d0000034Ks6AAE | N25: =IF(P25="","NO_DOCS_UPLOADED","") | P25: 2 | Q25: TRUE | R25: 06ANz000001eVPaMAM | S25: 06ANz000002cJ7EMAU
A26: a1zNz0000000Wr7IAE | B26: Matthew Hughes | C26: 006Nz000001Tcz1IAC | D26: a1G4J000004jydcUAA | E26: Completed | F26: FALSE | I26: TRUE | J26: 45178 | K26: 2023-09-11T10:27:20.000+0000 | L26: 2024-08-15T16:03:46.000+0000 | M26: 0058d0000034Ks6AAE | N26: =IF(P26="","NO_DOCS_UPLOADED","") | P26: 1 | Q26: TRUE | R26: 06ANz000001eNdMMAU
A27: a1zNz0000000XATIA2 | B27: Fraser McKnespiey | C27: 006Nz000001TYFTIA4 | D27: a1G4J000004jyjwUAA | E27: Completed | F27: FALSE | I27: TRUE | J27: 45155 | K27: 2023-09-11T11:37:49.000+0000 | L27: 2024-08-15T16:03:46.000+0000 | M27: 0054J000006BkQgQAK | N27: =IF(P27="","NO_DOCS_UPLOADED","") | P27: 1 | Q27: TRUE | R27: 06ANz000001eY7oMAE
A28: a1zNz0000000XC5IAM | B28: Ellen Wright | C28: 006Nz000001TYFTIA4 | D28: a1G4J000004jyjwUAA | E28: Completed | F28: FALSE | I28: TRUE | J28: 45155 | K28: 2023-09-11T11:38:24.000+0000 | L28: 2024-08-15T16:03:46.000+0000 | M28: 0054J000006BkQgQAK | N28: =IF(P28="","NO_DOCS_UPLOADED","") | P28: 1 | Q28: TRUE | R28: 06ANz000001eTRIMA2
A29: a1zNz0000000ZsDIAU | B29: Cristina Ruiz de Loizaga Garcia | C29: 006Nz000001NHqqIAG | D29: a1G4J000004jyvRUAQ | E29: Completed | F29: TRUE | G29: 45595 | I29: TRUE | J29: 45181 | K29: 2023-09-12T12:12:29.000+0000 | L29: 2024-08-15T16:03:46.000+0000 | M29: 0054J000006BkQgQAK | N29: =IF(P29="","NO_DOCS_UPLOADED","") | P29: 1 | Q29: TRUE | R29: 06ANz000001g0TVMAY
A30: a1zNz0000003kxZIAQ | B30: Asmar Rzayeva | C30: 0064J00000FTju1QAD | D30: a1G4J0000025xSVUAY | E30: Completed | F30: TRUE | G30: 46107 | I30: TRUE | J30: 45191 | K30: 2023-09-22T12:01:22.000+0000 | L30: 2024-08-15T16:03:46.000+0000 | M30: 0058d0000034KskAAE | N30: =IF(P30="","NO_DOCS_UPLOADED","") | P30: 1 | Q30: TRUE | R30: 06ANz000001uZloMAE
A31: a1zNz0000003tkjIAA | B31: Jodi Meir | C31: 006Nz000001f3cUIAQ | D31: a1G4J0000025zLKUAY | E31: Completed | F31: FALSE | I31: TRUE | J31: 45192 | K31: 2023-09-23T16:56:37.000+0000 | L31: 2024-08-15T16:03:46.000+0000 | M31: 0054J000006BkQgQAK | N31: =IF(P31="","NO_DOCS_UPLOADED","") | P31: 1 | Q31: TRUE | R31: 06ANz000001w50MMAQ
A32: a1zNz0000003tmLIAQ | B32: Ella Wilcock | C32: 006Nz000001f3cUIAQ | D32: a1G4J0000025zLKUAY | E32: Completed | F32: FALSE | I32: TRUE | J32: 45192 | K32: 2023-09-23T16:56:57.000+0000 | L32: 2024-08-15T16:03:46.000+0000 | M32: 0054J000006BkQgQAK | N32: =IF(P32="","NO_DOCS_UPLOADED","") | P32: 1 | Q32: TRUE | R32: 06ANz000001w53aMAA
A33: a1zNz00000050SPIAY | B33: Xingyu Tian | C33: 006Nz000002O2CYIA0 | D33: a1G4J000004jyrzUAA | E33: Completed | F33: TRUE | G33: 46782 | I33: TRUE | J33: 45194 | K33: 2023-09-25T16:56:32.000+0000 | L33: 2024-08-15T16:03:46.000+0000 | M33: 0054J000006BkQgQAK | N33: =IF(P33="","NO_DOCS_UPLOADED","") | P33: 1 | Q33: TRUE | R33: 06ANz000001yLDuMAM
A34: a1zNz00000050U1IAI | B34: Ming Yue | C34: 006Nz000002O2CYIA0 | D34: a1G4J000004jyrzUAA | E34: Completed | F34: TRUE | G34: 46782 | I34: TRUE | J34: 45194 | K34: 2023-09-25T16:57:13.000+0000 | L34: 2024-08-15T16:03:46.000+0000 | M34: 0054J000006BkQgQAK | N34: =IF(P34="","NO_DOCS_UPLOADED","") | P34: 1 | Q34: TRUE | R34: 06ANz000001yHE5MAM
A35: a1zNz0000005L5RIAU | B35: Luke Bulmer | C35: 006Nz0000020IDjIAM | D35: a1G4J0000025zS4UAI | E35: Completed | F35: FALSE | I35: TRUE | J35: 45195 | K35: 2023-09-26T09:57:46.000+0000 | L35: 2024-08-15T16:03:46.000+0000 | M35: 0054J000006BkQgQAK | N35: =IF(P35="","NO_DOCS_UPLOADED","") | P35: 1 | Q35: TRUE | R35: 06ANz000001zMZfMAM
A36: a1zNz0000005L73IAE | B36: Erin Doughty | C36: 006Nz0000020IDjIAM | D36: a1G4J0000025zS4UAI | E36: Completed | F36: FALSE | I36: TRUE | J36: 45195 | K36: 2023-09-26T09:58:12.000+0000 | L36: 2024-08-15T16:03:46.000+0000 | M36: 0054J000006BkQgQAK | N36: =IF(P36="","NO_DOCS_UPLOADED","") | P36: 1 | Q36: TRUE | R36: 06ANz000001zaMAMAY
A37: a1zNz0000005YM2IAM | B37: Michail Athinaios | C37: 006Nz000002SKCMIA4 | D37: a1GNz0000000w8sMAA | E37: Completed | F37: TRUE | G37: 45519 | I37: TRUE | J37: 45195 | K37: 2023-09-26T12:39:54.000+0000 | L37: 2024-08-15T16:03:46.000+0000 | M37: 0058d00000202rVAAQ | N37: =IF(P37="","NO_DOCS_UPLOADED","") | P37: 1 | Q37: TRUE | R37: 06ANz00000200yCMAQ
A38: a1zNz0000005d3xIAA | B38: Rehekah Newey | C38: 006Nz000002SKCMIA4 | D38: a1GNz0000000w8sMAA | E38: Completed | F38: FALSE | I38: TRUE | J38: 45195 | K38: 2023-09-26T13:54:15.000+0000 | L38: 2024-08-15T16:03:46.000+0000 | M38: 0058d00000202rVAAQ | N38: =IF(P38="","NO_DOCS_UPLOADED","") | P38: 1 | Q38: TRUE | R38: 06ANz000001zuGFMAY
A39: a1zNz0000005eWHIAY | B39: Ian Kennedy | C39: 006Nz000002XVyOIAW | D39: a1GNz0000000vO5MAI | E39: Completed | F39: FALSE | I39: TRUE | J39: 45195 | K39: 2023-09-26T14:48:16.000+0000 | L39: 2024-08-15T16:03:46.000+0000 | M39: 0054J000006BkQgQAK | N39: =IF(P39="","NO_DOCS_UPLOADED","") | P39: 1 | Q39: TRUE | R39: 06ANz0000020H4oMAE
A40: a1zNz0000005rwXIAQ | B40: Elsie Appiah | C40: 006Nz0000012j3hIAA | D40: a1G4J0000025xZMUAY | E40: Completed | F40: TRUE | G40: 46728 | I40: TRUE | J40: 45196 | K40: 2023-09-27T07:49:50.000+0000 | L40: 2024-10-30T12:14:33.000+0000 | M40: 0058d0000020QoXAAU | N40: =IF(P40="","NO_DOCS_UPLOADED","") | P40: 1 | Q40: TRUE | R40: 06ANz0000021Y8YMAU
A41: a1zNz0000006MsHIAU | B41: Wenyu Shi | C41: 006Nz000002MZHNIA4 | D41: a1G4J000004jyokUAA | E41: Completed | F41: TRUE | G41: 45687 | I41: TRUE | J41: 45196 | K41: 2023-09-27T13:59:36.000+0000 | L41: 2024-08-15T16:03:46.000+0000 | M41: 0054J000006BkQgQAK | N41: =IF(P41="","NO_DOCS_UPLOADED","") | P41: 1 | Q41: TRUE | R41: 06ANz0000022Pm3MAE
A42: a1zNz0000006oIIIAY | B42: Malthe Winther | C42: 006Nz000002MeLqIAK | D42: a1G8d0000004XZPEA2 | E42: Completed | F42: TRUE | G42: 45563 | I42: TRUE | J42: 45197 | K42: 2023-09-28T11:39:32.000+0000 | L42: 2024-08-15T16:03:46.000+0000 | M42: 0054J000006BkQgQAK | N42: =IF(P42="","NO_DOCS_UPLOADED","") | P42: 1 | Q42: TRUE | R42: 06ANz000002468wMAA
A43: a1zNz0000006zqPIAQ | B43: Jasmine Baker | C43: 006Nz000002ZRPBIA4 | E43: Completed | F43: FALSE | I43: TRUE | J43: 45197 | K43: 2023-09-28T15:06:40.000+0000 | L43: 2024-08-15T16:03:46.000+0000 | M43: 0058d00000202rVAAQ | N43: =IF(P43="","NO_DOCS_UPLOADED","") | P43: 1 | Q43: TRUE | R43: 06ANz0000024LUlMAM
A44: a1zNz0000006zvFIAQ | B44: Alex Barker | C44: 006Nz000002Q0OGIA0 | D44: a1GNz0000000xXyMAI | E44: Completed | F44: FALSE | I44: TRUE | J44: 45197 | K44: 2023-09-28T15:13:40.000+0000 | L44: 2024-08-15T16:03:46.000+0000 | M44: 0054J000006BkQgQAK | N44: =IF(P44="","NO_DOCS_UPLOADED","") | P44: 2 | Q44: TRUE | R44: 06ANz0000024Ja1MAE | S44: 06ANz0000024MD8MAM
A45: a1zNz0000006zwrIAA | B45: Marcelo Millan | C45: 006Nz000002Q0OGIA0 | D45: a1GNz0000000xXyMAI | E45: Completed | F45: FALSE | I45: TRUE | J45: 45197 | K45: 2023-09-28T15:15:29.000+0000 | L45: 2023-09-28T15:24:31.000+0000 | M45: 0054J000006BkQgQAK | N45: =IF(P45="","NO_DOCS_UPLOADED","") | P45: 1 | Q45: TRUE | R45: 06ANz0000024TgoMAE
A46: a1zNz00000070EbIAI | B46: Maria Eduarda Claciano Donadi | C46: 006Nz000002bEULIA2 | D46: a1GNz0000000w7HMAQ | E46: Completed | F46: TRUE | G46: 46051 | I46: TRUE | J46: 45197 | K46: 2023-09-28T15:44:35.000+0000 | L46: 2024-08-15T16:03:46.000+0000 | M46: 0058d00000202rVAAQ | N46: =IF(P46="","NO_DOCS_UPLOADED","") | P46: 2 | Q46: TRUE | R46: 06ANz0000024QUQMA2 | S46: 06ANz0000024QUSMA2
A47: a1zNz00000070HpIAI | B47: Joao Gustavo Castro Vieira | C47: 006Nz000002bEULIA2 | D47: a1GNz0000000w7HMAQ | E47: Completed | F47: TRUE | G47: 46213 | I47: TRUE | J47: 45197 | K47: 2023-09-28T15:45:44.000+0000 | L47: 2024-08-15T16:03:46.000+0000 | M47: 0058d00000202rVAAQ | N47: =IF(P47="","NO_DOCS_UPLOADED","") | P47: 1 | Q47: TRUE | R47: 06ANz0000024VZLMA2
A48: a1zNz00000070T7IAI | B48: fFvo5LxykElHq0JjTewj 3mfLmPxGRI35UMmHJ1su | C48: 0068d000003s2p1AAA | D48: a1G4J0000025zFqUAI | E48: Completed | F48: TRUE | G48: 46447 | I48: TRUE | J48: 45197 | K48: 2023-09-28T15:56:55.000+0000 | L48: 2024-08-15T16:03:46.000+0000 | M48: 0058d0000034c7KAAQ | N48: =IF(P48="","NO_DOCS_UPLOADED","") | P48: 1 | Q48: TRUE | R48: 06ANz0000024RfPMAU
A49: a1zNz00000070WLIAY | B49: Antony Farid | C49: 006Nz000002QAKNIA4 | D49: a1GNz0000000ygvMAA | E49: Completed | F49: TRUE | G49: 46095 | I49: TRUE | J49: 45197 | K49: 2023-09-28T16:00:28.000+0000 | L49: 2024-08-15T16:03:46.000+0000 | M49: 0058d00000202rVAAQ | N49: =IF(P49="","NO_DOCS_UPLOADED","") | P49: 2 | Q49: TRUE | R49: 06ANz0000024ZMNMA2 | S49: 06ANz0000024dzKMAQ
A50: a1zNz00000070g1IAA | B50: Irina Guseva | C50: 0068d000009hfhtAAA | D50: a1G4J0000025zSsUAI | E50: Completed | F50: TRUE | G50: 46918 | I50: TRUE | J50: 45197 | K50: 2023-09-28T16:39:37.000+0000 | L50: 2024-08-15T16:03:46.000+0000 | M50: 0058d0000034c7KAAQ | N50: =IF(P50="","NO_DOCS_UPLOADED","") | P50: 1 | Q50: TRUE | R50: 06ANz0000024VkSMAU
A51: a1zNz00000070krIAA | B51: EuUDGQTqMHt3lgrNEWhB ImZFTjoLEMpuwxi5o2XL | C51: 006Nz000002QFyOIAW | D51: a1GNz0000000wP0MAI | E51: Completed | F51: FALSE | I51: TRUE | J51: 45197 | K51: 2023-09-28T16:42:11.000+0000 | L51: 2024-08-15T16:03:46.000+0000 | M51: 0058d00000202rVAAQ | N51: =IF(P51="","NO_DOCS_UPLOADED","") | P51: 1 | Q51: TRUE | R51: 06ANz0000024atQMAQ
A52: a1zNz00000072rVIAQ | B52: Fahad Almutairi | C52: 006Nz000002Td1mIAC | D52: a1G8d0000004DCaEAM | E52: Completed | F52: TRUE | G52: 45237 | I52: TRUE | J52: 45198 | K52: 2023-09-29T07:31:54.000+0000 | L52: 2023-09-29T07:31:54.000+0000 | M52: 0058d00000202rVAAQ | N52: =IF(P52="","NO_DOCS_UPLOADED","") | P52: 1 | Q52: TRUE | R52: 06ANz0000025UxIMAU
A53: a1zNz00000072t7IAA | B53: Mohammed Almutairi | C53: 006Nz000002Td1mIAC | D53: a1G8d0000004DCaEAM | E53: Completed | F53: TRUE | G53: 45237 | I53: TRUE | J53: 45198 | K53: 2023-09-29T07:32:56.000+0000 | L53: 2023-09-29T07:32:56.000+0000 | M53: 0058d00000202rVAAQ | N53: =IF(P53="","NO_DOCS_UPLOADED","") | P53: 1 | Q53: TRUE | R53: 06ANz0000025WuqMAE
A54: a1zNz00000073h7IAA | B54: Nadya Xintian | D54: a1G8d0000004DGhEAM | E54: Completed | F54: TRUE | G54: 45687 | I54: TRUE | J54: 45198 | K54: 2023-09-29T09:05:19.000+0000 | L54: 2024-08-15T16:03:46.000+0000 | M54: 0054J000004vm8VQAQ | N54: =IF(P54="","NO_DOCS_UPLOADED","") | P54: 1 | Q54: TRUE | R54: 06ANz0000025hjBMAQ
A55: a1zNz00000074GbIAI | B55: Nathan Stocks | C55: 006Nz000002XjJpIAK | D55: a1GNz0000000xGDMAY | E55: Completed | F55: FALSE | I55: TRUE | J55: 45198 | K55: 2023-09-29T09:50:36.000+0000 | L55: 2024-08-15T16:03:46.000+0000 | M55: 0058d00000202rVAAQ | N55: =IF(P55="","NO_DOCS_UPLOADED","") | P55: 1 | Q55: TRUE | R55: 06ANz0000025lgOMAQ
A56: a1zNz00000074jdIAA | B56: Miriam Shan | C56: 006Nz000001vKhcIAE | D56: a1GNz0000000wC5MAI | E56: Completed | F56: FALSE | I56: TRUE | J56: 45198 | K56: 2023-09-29T10:40:47.000+0000 | L56: 2024-08-15T16:03:46.000+0000 | M56: 0058d00000202rVAAQ | N56: =IF(P56="","NO_DOCS_UPLOADED","") | P56: 1 | Q56: TRUE | R56: 06ANz0000025rveMAA
A57: a1zNz00000076YXIAY | B57: Mahammad Aldaihani | C57: 006Nz000002X5O3IAK | D57: a1G8d0000004DBXEA2 | E57: Completed | F57: TRUE | G57: 45276 | I57: TRUE | J57: 45198 | K57: 2023-09-29T13:46:41.000+0000 | L57: 2023-09-29T13:46:41.000+0000 | M57: 0058d00000202rVAAQ | N57: =IF(P57="","NO_DOCS_UPLOADED","") -> NO_DOCS_UPLOADED
A58: a1zNz00000076a9IAA | B58: Abdulmalek Alsaleh | C58: 006Nz000002X5O3IAK | D58: a1G8d0000004DBXEA2 | E58: Completed | F58: TRUE | G58: 45277 | I58: TRUE | J58: 45198 | K58: 2023-09-29T13:47:36.000+0000 | L58: 2023-09-29T13:47:36.000+0000 | M58: 0058d00000202rVAAQ | N58: =IF(P58="","NO_DOCS_UPLOADED","") | P58: 1 | Q58: TRUE | R58: 06ANz0000026EwvMAE
A59: a1zNz00000076iDIAQ | B59: Fahad Alotaibi | C59: 006Nz000002ZJt3IAG | D59: a1G4J000004jyvbUAA | E59: Completed | F59: TRUE | G59: 45579 | I59: TRUE | J59: 45198 | K59: 2023-09-29T14:09:00.000+0000 | L59: 2024-08-15T16:03:46.000+0000 | M59: 0058d00000202rVAAQ | N59: =IF(P59="","NO_DOCS_UPLOADED","") | P59: 1 | Q59: TRUE | R59: 06ANz0000026H6gMAE
A60: a1zNz00000076v7IAA | B60: Abhilasha Kakkar | C60: 006Nz000002O3WfIAK | D60: a1G4J000004jyqlUAA | E60: Completed | F60: FALSE | I60: TRUE | J60: 45198 | K60: 2023-09-29T14:24:07.000+0000 | L60: 2024-08-15T16:03:46.000+0000 | M60: 0058d00000202rVAAQ | N60: =IF(P60="","NO_DOCS_UPLOADED","") | P60: 1 | Q60: TRUE | R60: 06ANz0000026BAIMA2
A61: a1zNz00000078SHIAY | B61: Adewale Adegoke | C61: 006Nz000001u4q3IAA | D61: a1GNz0000000xZZMAY | E61: Completed | F61: TRUE | G61: 45321 | I61: TRUE | J61: 45198 | K61: 2023-09-29T16:33:01.000+0000 | L61: 2023-09-29T16:38:47.000+0000 | M61: 0054J000006BkQgQAK | N61: =IF(P61="","NO_DOCS_UPLOADED","") | P61: 1 | Q61: TRUE | R61: 06ANz0000026VeIMAU
A62: a1zNz00000078TtIAI | B62: Ademide Olukoya | C62: 006Nz000001u4q3IAA | D62: a1GNz0000000xZZMAY | E62: Completed | F62: TRUE | G62: 45321 | I62: TRUE | J62: 45198 | K62: 2023-09-29T16:37:46.000+0000 | L62: 2023-10-03T16:52:02.000+0000 | M62: 0054J000006BkQgQAK | N62: =IF(P62="","NO_DOCS_UPLOADED","") | P62: 1 | Q62: TRUE | R62: 06ANz0000027EukMAE
A63: a1zNz00000078fBIAQ | B63: Gillian Muchedzi | C63: 006Nz0000021eDcIAI | D63: a1GNz0000000vuMMAQ | E63: Completed | F63: FALSE | I63: TRUE | J63: 45198 | K63: 2023-09-29T17:01:52.000+0000 | L63: 2024-08-15T16:03:46.000+0000 | M63: 0054J000006BkQgQAK | N63: =IF(P63="","NO_DOCS_UPLOADED","") | P63: 1 | Q63: TRUE | R63: 06ANz0000026TbGMAU
A64: a1zNz0000007I0DIAU | B64: Zowie King | C64: 006Nz000001TdevIAC | D64: a1G4J0000025zJMUAY | E64: Completed | F64: FALSE | I64: TRUE | J64: 45199 | K64: 2023-09-30T13:44:05.000+0000 | L64: 2024-08-15T16:03:46.000+0000 | M64: 005Nz000000R0K6IAK | N64: =IF(P64="","NO_DOCS_UPLOADED","") | P64: 1 | Q64: TRUE | R64: 06ANz0000027SkoMAE
A65: a1zNz0000008JIQIA2 | B65: Megan Gilliver | C65: 006Nz000002U0B8IAK | D65: a1GNz0000000xo5MAA | E65: Completed | F65: FALSE | I65: TRUE | J65: 45201 | K65: 2023-10-02T12:07:29.000+0000 | L65: 2024-08-15T16:03:46.000+0000 | M65: 0058d00000202rVAAQ | N65: =IF(P65="","NO_DOCS_UPLOADED","") | P65: 1 | Q65: TRUE | R65: 06ANz0000029iOsMAI
A66: a1zNz0000008JK1IAM | B66: r1Gt6gkZ0EAT6uU58YIy TGprb8rk6bfsMTR0VSD4 | C66: 006Nz000002OcCfIAK | D66: a1G4J000004jyjzUAA | E66: Completed | F66: TRUE | G66: 45772 | I66: TRUE | J66: 45201 | K66: 2023-10-02T11:14:04.000+0000 | L66: 2024-08-15T16:03:46.000+0000 | M66: 0058d00000202rVAAQ | N66: =IF(P66="","NO_DOCS_UPLOADED","") | P66: 2 | Q66: TRUE | R66: 06ANz0000029WW5MAM | S66: 06ANz0000029cGEMAY
A67: a1zNz0000009DqrIAE | B67: Saeed Arabloo | C67: 006Nz000002f09OIAQ | D67: a1G4J0000025zRHUAY | E67: Completed | F67: TRUE | G67: 47041 | I67: TRUE | J67: 45202 | K67: 2023-10-03T17:01:59.000+0000 | L67: 2024-08-15T16:03:46.000+0000 | M67: 0054J000006BkQgQAK | N67: =IF(P67="","NO_DOCS_UPLOADED","") | P67: 1 | Q67: TRUE | R67: 06ANz000002CHFTMA4
A68: a1zNz0000009DsTIAU | B68: Zahra Poorya | C68: 006Nz000002f09OIAQ | D68: a1G4J0000025zRHUAY | E68: Completed | F68: TRUE | G68: 45321 | I68: TRUE | J68: 45202 | K68: 2023-10-03T17:02:40.000+0000 | L68: 2023-10-03T17:02:40.000+0000 | M68: 0054J000006BkQgQAK | N68: =IF(P68="","NO_DOCS_UPLOADED","") | P68: 1 | Q68: TRUE | R68: 06ANz000002CIepMAG
A69: a1zNz0000009V2zIAE | B69: Mohammed Munaf | C69: 006Nz000002dJGCIA2 | D69: a1G4J0000025zT3UAI | E69: Completed | F69: FALSE | I69: TRUE | J69: 45203 | K69: 2023-10-04T08:24:18.000+0000 | L69: 2024-08-15T16:03:46.000+0000 | M69: 0054J000006BkQgQAK | N69: =IF(P69="","NO_DOCS_UPLOADED","") | P69: 1 | Q69: TRUE | R69: 06ANz000002DJaCMAW
A70: a1zNz0000009WYXIA2 | B70: Emmanouil Nektarios Kalligeris | C70: 006Nz000002mionIAA | D70: a1GNz0000000xRWMAY | E70: Completed | F70: TRUE | G70: 46315 | I70: TRUE | J70: 45203 | K70: 2023-10-04T08:57:15.000+0000 | L70: 2024-08-15T16:03:46.000+0000 | M70: 0058d00000202rVAAQ | N70: =IF(P70="","NO_DOCS_UPLOADED","") | P70: 1 | Q70: TRUE | R70: 06ANz000002DIR5MAO
A71: a1zNz0000009mtRIAQ | B71: Pooja Patel | C71: 006Nz000000rZm2IAE | D71: a1G4J0000025z24UAA | E71: Completed | F71: TRUE | G71: 46419 | I71: TRUE | J71: 45203 | K71: 2023-10-04T12:30:31.000+0000 | L71: 2024-08-15T16:03:46.000+0000 | M71: 005Nz000000R0K6IAK | N71: =IF(P71="","NO_DOCS_UPLOADED","") | P71: 1 | Q71: TRUE | R71: 06ANz000002Di2OMAS
A72: a1zNz0000009pOIIAY | B72: Mitchell Hayes | C72: 006Nz000002ZULWIA4 | D72: a1G4J0000025zF9UAI | E72: Completed | F72: FALSE | I72: TRUE | J72: 45203 | K72: 2023-10-04T13:05:48.000+0000 | L72: 2024-08-15T16:03:46.000+0000 | M72: 0054J000006BkQgQAK | N72: =IF(P72="","NO_DOCS_UPLOADED","") | P72: 1 | Q72: TRUE | R72: 06ANz000002DmImMAK
A73: a1zNz0000009pOJIAY | B73: Melissa Walpole | C73: 006Nz000002ZULWIA4 | D73: a1G4J0000025zF9UAI | E73: Completed | F73: TRUE | G73: 45884 | I73: TRUE | J73: 45203 | K73: 2023-10-04T13:06:40.000+0000 | L73: 2024-08-15T16:03:46.000+0000 | M73: 0054J000006BkQgQAK | N73: =IF(P73="","NO_DOCS_UPLOADED","") | P73: 1 | Q73: TRUE | R73: 06ANz000002Dn25MAC
A74: a1zNz000000AGZmIAO | B74: Oscar E. Mendoza | C74: 006Nz000002diwDIAQ | D74: a1G4J0000025zLxUAI | E74: Completed | F74: TRUE | G74: 45570 | I74: TRUE | J74: 45204 | K74: 2023-10-05T09:14:17.000+0000 | L74: 2024-08-15T16:03:46.000+0000 | M74: 0054J000006BkQgQAK | N74: =IF(P74="","NO_DOCS_UPLOADED","") | P74: 1 | Q74: TRUE | R74: 06ANz000002G4tZMAS
A75: a1zNz000000AIzlIAG | B75: Yuri Mejia | C75: 006Nz000002diwDIAQ | D75: a1G4J0000025zLxUAI | E75: Completed | F75: TRUE | G75: 45606 | I75: TRUE | J75: 45204 | K75: 2023-10-05T09:13:41.000+0000 | L75: 2024-08-15T16:03:46.000+0000 | M75: 0054J000006BkQgQAK | N75: =IF(P75="","NO_DOCS_UPLOADED","") | P75: 1 | Q75: TRUE | R75: 06ANz000002FIe6MAG
A76: a1zNz000000ALWGIA4 | B76: Minxuan He | C76: 006Nz0000021XbxIAE | D76: a1GNz0000000xpjMAA | E76: Completed | F76: TRUE | G76: 45317 | I76: TRUE | J76: 45204 | K76: 2023-10-05T10:31:31.000+0000 | L76: 2023-10-05T10:31:31.000+0000 | M76: 0054J000006BkQgQAK | N76: =IF(P76="","NO_DOCS_UPLOADED","") | P76: 1 | Q76: TRUE | R76: 06ANz000002FWejMAG
A77: a1zNz000000AMs6IAG | B77: Cameron Fairburn | C77: 006Nz000002XMLdIAO | D77: a1GNz0000000yfKMAQ | E77: Completed | F77: FALSE | I77: TRUE | J77: 45204 | K77: 2023-10-05T10:02:20.000+0000 | L77: 2024-08-15T16:03:46.000+0000 | M77: 0058d00000202rVAAQ | N77: =IF(P77="","NO_DOCS_UPLOADED","") | P77: 1 | Q77: TRUE | R77: 06ANz000002FNf9MAG
A78: a1zNz000000AWWUIA4 | B78: Ifeoluwa Flora Dada | C78: 006Nz000002gixyIAA | D78: a1GNz0000000vERMAY | E78: Completed | F78: TRUE | G78: 46980 | I78: TRUE | J78: 45204 | K78: 2023-10-05T12:33:11.000+0000 | L78: 2024-08-15T16:03:46.000+0000 | M78: 0054J000006BkQgQAK | N78: =IF(P78="","NO_DOCS_UPLOADED","") | P78: 1 | Q78: TRUE | R78: 06ANz000002FrsUMAS
A79: a1zNz000000AXSXIA4 | B79: Omolayo Pelumi Adetunji | C79: 006Nz000002gixyIAA | D79: a1GNz0000000vERMAY | E79: Completed | F79: TRUE | G79: 46980 | I79: TRUE | J79: 45204 | K79: 2023-10-05T12:34:48.000+0000 | L79: 2024-08-15T16:03:46.000+0000 | M79: 0054J000006BkQgQAK | N79: =IF(P79="","NO_DOCS_UPLOADED","") | P79: 1 | Q79: TRUE | R79: 06ANz000002Fk8xMAC
A80: a1zNz000000AYWfIAO | B80: Im5dZnpW0fEy6NFF8CS9 9eAhC7tr8WOSHH0S9TY4 | C80: 006Nz000002e2YEIAY | D80: a1GNz0000000w8rMAA | E80: Completed | F80: TRUE | G80: 46059 | I80: TRUE | J80: 45204 | K80: 2023-10-05T12:45:53.000+0000 | L80: 2024-08-15T16:03:46.000+0000 | M80: 0054J000006BkQgQAK | N80: =IF(P80="","NO_DOCS_UPLOADED","") | P80: 1 | Q80: TRUE | R80: 06ANz000002FjcmMAC
A81: a1zNz000000AZffIAG | B81: Lesley Young | C81: 006Nz000002XMLdIAO | D81: a1GNz0000000yfKMAQ | E81: Completed | F81: FALSE | I81: TRUE | J81: 45204 | K81: 2023-10-05T13:52:37.000+0000 | L81: 2024-08-15T16:03:46.000+0000 | M81: 0058d00000202rVAAQ | N81: =IF(P81="","NO_DOCS_UPLOADED","") | P81: 1 | Q81: TRUE | R81: 06ANz000002G4MqMAK
A82: a1zNz000000AbSxIAK | B82: Suzanne Bradley | C82: 006Nz000002lChMIAU | D82: a1G4J0000025wYMUAY | E82: Completed | F82: FALSE | I82: TRUE | J82: 45209 | K82: 2023-10-05T13:40:08.000+0000 | L82: 2024-08-15T16:03:46.000+0000 | M82: 0058d0000043ssPAAQ | N82: =IF(P82="","NO_DOCS_UPLOADED","") | P82: 1 | Q82: TRUE | R82: 06ANz000002NocaMAC
A83: a1zNz000000AgHJIA0 | B83: Jiaxuan Bi | C83: 006Nz000001yYeBIAU | D83: a1GNz0000000xsxMAA | E83: Completed | F83: FALSE | I83: TRUE | J83: 45204 | K83: 2023-10-05T14:09:43.000+0000 | L83: 2023-10-05T14:09:43.000+0000 | M83: 0058d00000202rVAAQ | N83: =IF(P83="","NO_DOCS_UPLOADED","") | P83: 1 | Q83: TRUE | R83: 06ANz000002G93FMAS
A84: a1zNz000000AhlFIAS | B84: Nikol Papageorgiou | C84: 006Nz000001zGNUIA2 | D84: a1G4J0000025z2PUAQ | E84: Completed | F84: FALSE | I84: TRUE | J84: 45204 | K84: 2023-10-05T17:10:32.000+0000 | L84: 2024-08-15T16:03:46.000+0000 | M84: 005Nz000000R0K6IAK | N84: =IF(P84="","NO_DOCS_UPLOADED","") | P84: 1 | Q84: TRUE | R84: 06ANz000002GTmUMAW
A85: a1zNz000000AlAXIA0 | B85: Irina Guseva | C85: 006Nz000002c1wRIAQ | D85: a1G4J0000025zRbUAI | E85: In Progress | F85: TRUE | G85: 46918 | I85: TRUE | J85: 45205 | K85: 2023-10-06T09:44:06.000+0000 | L85: 2024-08-15T16:03:46.000+0000 | M85: 0058d00000202rVAAQ | P85: 1 | Q85: TRUE | R85: 06ANz000002HdoeMAC
A86: a1zNz000000AlTtIAK | B86: Amy Austin | C86: 006Nz000002kxojIAA | D86: a1G4J0000025ynNUAQ | E86: Completed | F86: FALSE | I86: TRUE | J86: 45205 | K86: 2023-10-06T10:21:57.000+0000 | L86: 2024-08-15T16:03:46.000+0000 | M86: 0054J000004vXOWQA2 | N86: =IF(P86="","NO_DOCS_UPLOADED","") | P86: 1 | Q86: TRUE | R86: 06ANz000002HZh0MAG
A87: a1zNz000000AliPIAS | B87: Sn0oVMBc0XWfzEDYFuqJ dnv9Vyar6Jq3HpzVsIMb | C87: 006Nz000002TrHZIA0 | D87: a1G8d0000004D8YEAU | E87: Completed | F87: FALSE | I87: TRUE | J87: 45205 | K87: 2023-10-06T11:00:50.000+0000 | L87: 2024-08-15T16:03:46.000+0000 | M87: 0058d000006cI6JAAU | N87: =IF(P87="","NO_DOCS_UPLOADED","") | P87: 1 | Q87: TRUE | R87: 06ANz000002HlBBMA0
A88: a1zNz000000Alk1IAC | B88: e1seX09zx0WnHzUYWbeB fVg7gSWdNam0gnf4pWlg | C88: 006Nz000002TrHZIA0 | D88: a1G8d0000004D8YEAU | E88: Completed | F88: FALSE | I88: TRUE | J88: 45205 | K88: 2023-10-06T11:01:54.000+0000 | L88: 2024-08-15T16:03:46.000+0000 | M88: 0058d000006cI6JAAU | N88: =IF(P88="","NO_DOCS_UPLOADED","") | P88: 1 | Q88: TRUE | R88: 06ANz000002HiSSMA0
A89: a1zNz000000Am9pIAC | B89: Charles Craddock | C89: 006Nz000002jYcNIAU | D89: a1GNz0000000xGFMAY | E89: Completed | F89: FALSE | I89: TRUE | J89: 45205 | K89: 2023-10-06T11:55:45.000+0000 | L89: 2024-08-15T16:03:46.000+0000 | M89: 0054J000006BkQgQAK | N89: =IF(P89="","NO_DOCS_UPLOADED","") | P89: 1 | Q89: TRUE | R89: 06ANz000002HuPhMAK
A90: a1zNz000000AmmXIAS | B90: Michael Booth | C90: 006Nz000002kxojIAA | D90: a1G4J0000025yz0UAA | E90: Completed | F90: FALSE | I90: TRUE | J90: 45205 | K90: 2023-10-06T12:55:36.000+0000 | L90: 2024-08-15T16:03:46.000+0000 | M90: 0054J000004vXOWQA2 | N90: =IF(P90="","NO_DOCS_UPLOADED","") | P90: 1 | Q90: TRUE | R90: 06ANz000002Htx4MAC
A91: a1zNz000000BZTuIAO | B91: Chris Freeman | C91: 006Nz000002f3gmIAA | D91: a1GNz0000000vr7MAA | E91: Completed | F91: FALSE | I91: TRUE | J91: 45208 | K91: 2023-10-09T07:43:00.000+0000 | L91: 2024-08-15T16:03:46.000+0000 | M91: 0058d00000202rVAAQ | N91: =IF(P91="","NO_DOCS_UPLOADED","") | P91: 1 | Q91: TRUE | R91: 06ANz000002KtfCMAS
A92: a1zNz000000Ba4zIAC | B92: Emi-Rose Albeer | C92: 006Nz000002f3gmIAA | D92: a1GNz0000000vr7MAA | E92: Completed | F92: FALSE | I92: TRUE | J92: 45208 | K92: 2023-10-09T07:43:48.000+0000 | L92: 2024-08-15T16:03:46.000+0000 | M92: 0058d00000202rVAAQ | N92: =IF(P92="","NO_DOCS_UPLOADED","") | P92: 1 | Q92: TRUE | R92: 06ANz000002KiZcMAK
A93: a1zNz000000Bb2fIAC | B93: Jamie Wood | C93: 006Nz000002lgsHIAQ | D93: a1GNz0000000wk0MAA | E93: Completed | F93: FALSE | I93: TRUE | J93: 45208 | K93: 2023-10-09T07:48:29.000+0000 | L93: 2024-08-15T16:03:46.000+0000 | M93: 0058d00000202rVAAQ | N93: =IF(P93="","NO_DOCS_UPLOADED","") | P93: 1 | Q93: TRUE | R93: 06ANz000002KjmQMAS
A94: a1zNz000000Bb5tIAC | B94: Jamie Boyde | C94: 006Nz000002XBd4IAG | D94: a1G8d0000004XcCEAU | E94: Completed | F94: FALSE | I94: TRUE | J94: 45208 | K94: 2023-10-09T07:50:15.000+0000 | L94: 2024-08-15T16:03:46.000+0000 | M94: 0058d00000202rVAAQ | N94: =IF(P94="","NO_DOCS_UPLOADED","") | P94: 1 | Q94: TRUE | R94: 06ANz000002KnOhMAK
A95: a1zNz000000C27iIAC | B95: Faisal Alshorafa | C95: 006Nz000001Skc1IAC | D95: a1G4J000004jympUAA | E95: Completed | F95: FALSE | I95: TRUE | J95: 45208 | K95: 2023-10-09T13:32:48.000+0000 | L95: 2023-10-09T13:32:48.000+0000 | M95: 0058d000005RQ1sAAG | N95: =IF(P95="","NO_DOCS_UPLOADED","") | P95: 1 | Q95: TRUE | R95: 06ANz000002LVOmMAO
A96: a1zNz000000CADJIA4 | B96: Louise Oddy | C96: 006Nz000001eof5IAA | D96: a1G8d0000004XbsEAE | E96: Completed | F96: FALSE | I96: TRUE | J96: 45208 | K96: 2023-10-09T14:56:37.000+0000 | L96: 2024-08-15T16:03:46.000+0000 | M96: 0058d00000202rVAAQ | N96: =IF(P96="","NO_DOCS_UPLOADED","") | P96: 1 | Q96: TRUE | R96: 06ANz000002LsM4MAK
A97: a1zNz000000CAEvIAO | B97: James Hopwood | C97: 006Nz000001eof5IAA | D97: a1G8d0000004XbsEAE | E97: Completed | F97: FALSE | I97: TRUE | J97: 45208 | K97: 2023-10-09T14:58:00.000+0000 | L97: 2024-08-15T16:03:46.000+0000 | M97: 0058d00000202rVAAQ | N97: =IF(P97="","NO_DOCS_UPLOADED","") | P97: 2 | Q97: TRUE | R97: 06ANz000002LeO9MAK | S97: 06ANz000002LpWkMAK
A98: a1zNz000000CAurIAG | B98: Yash Maindola | C98: 006Nz000002EEWkIAO | D98: a1G4J0000025xj1UAA | E98: Completed | F98: TRUE | G98: 45304 | I98: TRUE | J98: 45208 | K98: 2023-10-09T16:38:23.000+0000 | L98: 2023-10-10T11:23:16.000+0000 | M98: 0058d0000043ssPAAQ | N98: =IF(P98="","NO_DOCS_UPLOADED","") | P98: 1 | Q98: TRUE | R98: 06ANz000002NJZ4MAO
A99: a1zNz000000CPHBIA4 | B99: Letizia Olivero | C99: 006Nz000002qXMxIAM | D99: a1G8d0000004D97EAE | E99: Completed | F99: TRUE | I99: TRUE | J99: 45209 | K99: 2023-10-10T08:06:26.000+0000 | L99: 2023-10-10T13:34:47.000+0000 | M99: 0058d000006cI6JAAU | N99: =IF(P99="","NO_DOCS_UPLOADED","") | P99: 1 | Q99: TRUE | R99: 06ANz000002MzGcMAK
A100: a1zNz000000CPVjIAO | B100: Ziwen Qin | C100: 006Nz000000pfkHIAQ | D100: a1G4J0000025yolUAA | E100: Completed | F100: TRUE | G100: 45676 | I100: TRUE | J100: 45208 | K100: 2023-10-10T09:22:27.000+0000 | L100: 2024-08-15T16:03:46.000+0000 | M100: 0054J000005JMoGQAW | N100: =IF(P100="","NO_DOCS_UPLOADED","") | P100: 1 | Q100: TRUE | R100: 06ANz000002UPZNMA4
...

Sheet 1. RTR with Tenant >1 "Compltd"
A1: Id | B1: Right_to_Rents__r.totalSize | C1: Right_to_Rents__r.done | D1: Right_to_Rents__r.records.0.Status__c | E1: Right_to_Rents__r.records.1.Status__c | F1: Right_to_Rents__r.records.2.Status__c | G1: Right_to_Rents__r.records.3.Status__c | H1: Right_to_Rents__r.records.4.Status__c | I1: Right_to_Rents__r.records.5.Status__c | J1: Right_to_Rents__r.records.6.Status__c | K1: Right_to_Rents__r.records.7.Status__c | L1: Right_to_Rents__r.records.8.Status__c | M1: Right_to_Rents__r.records.9.Status__c | N1: Right_to_Rents__r.records.10.Status__c | O1: Right_to_Rents__r.records.11.Status__c | P1: Right_to_Rents__r.records.12.Status__c | Q1: Right_to_Rents__r.records.13.Status__c | R1: Right_to_Rents__r.records.14.Status__c | S1: Right_to_Rents__r.records.15.Status__c | U1: _Count of Status ="Completed" > 1
A2: 0014J00000VvTtbQAF | B2: 16 | C2: TRUE | D2: Completed | E2: Completed | F2: Completed | G2: Completed | H2: Completed | I2: Completed | J2: Completed | K2: Completed | L2: Completed | M2: Completed | N2: Completed | O2: Completed | P2: Completed | Q2: Completed | R2: Completed | S2: Not started | U2: =IF(COUNTIF(D2:S2,"Completed")>1,"TRUE","FALSE") -> TRUE
A3: 0018d00000JkBPhAAN | B3: 4 | C3: TRUE | D3: Completed | E3: Completed | F3: Completed | G3: Not started | U3: =IF(COUNTIF(D3:S3,"Completed")>1,"TRUE","FALSE") -> TRUE
A4: 0018d00000G0FPXAA3 | B4: 4 | C4: TRUE | D4: Completed | E4: Completed | F4: Not started | G4: Not started | U4: =IF(COUNTIF(D4:S4,"Completed")>1,"TRUE","FALSE") -> TRUE
A5: 001Nz000003LbAzIAK | B5: 4 | C5: TRUE | D5: Completed | E5: Completed | F5: Not started | G5: Not started | U5: =IF(COUNTIF(D5:S5,"Completed")>1,"TRUE","FALSE") -> TRUE
A6: 001Nz000002wbUIIAY | B6: 3 | C6: TRUE | D6: Completed | E6: Completed | F6: Not started | U6: =IF(COUNTIF(D6:S6,"Completed")>1,"TRUE","FALSE") -> TRUE
A7: 001Nz0000077RHBIA2 | B7: 3 | C7: TRUE | D7: Completed | E7: Completed | F7: Not started | U7: =IF(COUNTIF(D7:S7,"Completed")>1,"TRUE","FALSE") -> TRUE
A8: 001Nz000004YEPdIAO | B8: 3 | C8: TRUE | D8: Completed | E8: Completed | F8: Not started | U8: =IF(COUNTIF(D8:S8,"Completed")>1,"TRUE","FALSE") -> TRUE
A9: 0018d0000098mbAAAQ | B9: 3 | C9: TRUE | D9: Completed | E9: In Progress | F9: Completed | U9: =IF(COUNTIF(D9:S9,"Completed")>1,"TRUE","FALSE") -> TRUE
A10: 0014J00000ZtPDnQAN | B10: 3 | C10: TRUE | D10: Completed | E10: Completed | F10: Not started | U10: =IF(COUNTIF(D10:S10,"Completed")>1,"TRUE","FALSE") -> TRUE
A11: 001Nz000004OV5DIAW | B11: 3 | C11: TRUE | D11: Completed | E11: Completed | F11: Not started | U11: =IF(COUNTIF(D11:S11,"Completed")>1,"TRUE","FALSE") -> TRUE
A12: 001Nz000002XoGFIA0 | B12: 3 | C12: TRUE | D12: Completed | E12: Completed | F12: Not started | U12: =IF(COUNTIF(D12:S12,"Completed")>1,"TRUE","FALSE") -> TRUE
A13: 001Nz000006wFckIAE | B13: 3 | C13: TRUE | D13: Completed | E13: Completed | F13: Not started | U13: =IF(COUNTIF(D13:S13,"Completed")>1,"TRUE","FALSE") -> TRUE
A14: 001Nz000002spUIIAY | B14: 3 | C14: TRUE | D14: Completed | E14: Completed | F14: Not started | U14: =IF(COUNTIF(D14:S14,"Completed")>1,"TRUE","FALSE") -> TRUE
A15: 001Nz000003pVJNIA2 | B15: 3 | C15: TRUE | D15: Completed | E15: Completed | F15: Not started | U15: =IF(COUNTIF(D15:S15,"Completed")>1,"TRUE","FALSE") -> TRUE
A16: 0018d00000LMmMSAA1 | B16: 3 | C16: TRUE | D16: Completed | E16: Completed | F16: Not started | U16: =IF(COUNTIF(D16:S16,"Completed")>1,"TRUE","FALSE") -> TRUE
A17: 0018d00000EifdKAAR | B17: 3 | C17: TRUE | D17: Completed | E17: Completed | F17: Not started | U17: =IF(COUNTIF(D17:S17,"Completed")>1,"TRUE","FALSE") -> TRUE
... A30: 0018d00000PUAa4AAH | B30: 3 | C30: TRUE | D30: Completed | E30: Completed | F30: Not started | U30: =IF(COUNTIF(D30:S30,"Completed")>1,"TRUE","FALSE") -> TRUE
A31: 001Nz0000014ue9IAA | B31: 2 | C31: TRUE | D31: Completed | E31: Completed | U31: =IF(COUNTIF(D31:S31,"Completed")>1,"TRUE","FALSE") -> TRUE
A32: 001Nz000003oC2fIAE | B32: 2 | C32: TRUE | D32: Completed | E32: Completed | U32: =IF(COUNTIF(D32:S32,"Completed")>1,"TRUE","FALSE") -> TRUE
A33: 001Nz000008Nb3uIAC | B33: 2 | C33: TRUE | D33: Completed | E33: Completed | U33: =IF(COUNTIF(D33:S33,"Completed")>1,"TRUE","FALSE") -> TRUE
A34: 001Nz00000Ap54jIAB | B34: 2 | C34: TRUE | D34: Completed | E34: Completed | U34: =IF(COUNTIF(D34:S34,"Completed")>1,"TRUE","FALSE") -> TRUE
A35: 001Nz000002QXs4IAG | B35: 2 | C35: TRUE | D35: Completed | E35: Completed | U35: =IF(COUNTIF(D35:S35,"Completed")>1,"TRUE","FALSE") -> TRUE
A36: 001Nz000009qgHWIAY | B36: 2 | C36: TRUE | D36: Completed | E36: Completed | U36: =IF(COUNTIF(D36:S36,"Completed")>1,"TRUE","FALSE") -> TRUE
A37: 001Nz000008BxHuIAK | B37: 2 | C37: TRUE | D37: Completed | E37: Completed | U37: =IF(COUNTIF(D37:S37,"Completed")>1,"TRUE","FALSE") -> TRUE
A38: 0014J00000VvU1kQAF | B38: 2 | C38: TRUE | D38: Completed | E38: Completed | U38: =IF(COUNTIF(D38:S38,"Completed")>1,"TRUE","FALSE") -> TRUE
A39: 0018d00000FyzCuAAJ | B39: 2 | C39: TRUE | D39: Completed | E39: Completed | U39: =IF(COUNTIF(D39:S39,"Completed")>1,"TRUE","FALSE") -> TRUE
A40: 001Nz000004Z8LVIA0 | B40: 2 | C40: TRUE | D40: Completed | E40: Completed | U40: =IF(COUNTIF(D40:S40,"Completed")>1,"TRUE","FALSE") -> TRUE
A41: 001Nz0000027TnKIAU | B41: 2 | C41: TRUE | D41: Completed | E41: Completed | U41: =IF(COUNTIF(D41:S41,"Completed")>1,"TRUE","FALSE") -> TRUE
A42: 001Nz00000AkSejIAF | B42: 2 | C42: TRUE | D42: Completed | E42: Completed | U42: =IF(COUNTIF(D42:S42,"Completed")>1,"TRUE","FALSE") -> TRUE
... A90: 001Nz000006UNQRIA4 | B90: 2 | C90: TRUE | D90: Completed | E90: Completed | U90: =IF(COUNTIF(D90:S90,"Completed")>1,"TRUE","FALSE") -> TRUE
A91: 001Nz000001U4NNIA0 | B91: 1 | C91: TRUE | D91: Completed | U91: =IF(COUNTIF(D91:S91,"Completed")>1,"TRUE","FALSE") -> FALSE
A92: 001Nz000001iLszIAE | B92: 1 | C92: TRUE | D92: Completed | U92: =IF(COUNTIF(D92:S92,"Completed")>1,"TRUE","FALSE") -> FALSE
A93: 0018d000002sQaEAAU | B93: 1 | C93: TRUE | D93: Completed | U93: =IF(COUNTIF(D93:S93,"Completed")>1,"TRUE","FALSE") -> FALSE
A94: 001Nz000001TtoZIAS | B94: 1 | C94: TRUE | D94: Completed | U94: =IF(COUNTIF(D94:S94,"Completed")>1,"TRUE","FALSE") -> FALSE
A95: 0018d00000PSOIFAA5 | B95: 1 | C95: TRUE | D95: Completed | U95: =IF(COUNTIF(D95:S95,"Completed")>1,"TRUE","FALSE") -> FALSE
A96: 001Nz000001sfwrIAA | B96: 1 | C96: TRUE | D96: Completed | U96: =IF(COUNTIF(D96:S96,"Completed")>1,"TRUE","FALSE") -> FALSE
A97: 001Nz000001qr1FIAQ | B97: 1 | C97: TRUE | D97: Completed | U97: =IF(COUNTIF(D97:S97,"Completed")>1,"TRUE","FALSE") -> FALSE
A98: 001Nz000001oT7yIAE | B98: 1 | C98: TRUE | D98: Completed | U98: =IF(COUNTIF(D98:S98,"Completed")>1,"TRUE","FALSE") -> FALSE
A99: 001Nz000001oKXjIAM | B99: 1 | C99: TRUE | D99: Completed | U99: =IF(COUNTIF(D99:S99,"Completed")>1,"TRUE","FALSE") -> FALSE
A100: 0018d000006WGGzAAO | B100: 1 | C100: TRUE | D100: Completed | U100: =IF(COUNTIF(D100:S100,"Completed")>1,"TRUE","FALSE") -> FALSE
A101: 001Nz000001XuIzIAK | B101: 1 | C101: TRUE | D101: Completed | U101: =IF(COUNTIF(D101:S101,"Completed")>1,"TRUE","FALSE") -> FALSE
A102: 001Nz000001jf9kIAA | B102: 1 | C102: TRUE | D102: Completed | U102: =IF(COUNTIF(D102:S102,"Completed")>1,"TRUE","FALSE") -> FALSE
... A111: 001Nz000001WwGRIA0 | B111: 1 | C111: TRUE | D111: Completed | U111: =IF(COUNTIF(D111:S111,"Completed")>1,"TRUE","FALSE") -> FALSE
A112: 001Nz000002rHKwIAM | B112: 3 | C112: TRUE | D112: Completed | E112: Not started | F112: Not started | U112: =IF(COUNTIF(D112:S112,"Completed")>1,"TRUE","FALSE") -> FALSE
A113: 0014J00000ZR2dfQAD | B113: 1 | C113: TRUE | D113: Completed | U113: =IF(COUNTIF(D113:S113,"Completed")>1,"TRUE","FALSE") -> FALSE
A114: 001Nz000002thBKIAY | B114: 3 | C114: TRUE | D114: Completed | E114: Not started | F114: Not started | U114: =IF(COUNTIF(D114:S114,"Completed")>1,"TRUE","FALSE") -> FALSE
A115: 001Nz000001jP9oIAE | B115: 1 | C115: TRUE | D115: Completed | U115: =IF(COUNTIF(D115:S115,"Completed")>1,"TRUE","FALSE") -> FALSE
A116: 001Nz000002SyHqIAK | B116: 1 | C116: TRUE | D116: Completed | U116: =IF(COUNTIF(D116:S116,"Completed")>1,"TRUE","FALSE") -> FALSE
A117: 001Nz0000022sfwIAA | B117: 1 | C117: TRUE | D117: Completed | U117: =IF(COUNTIF(D117:S117,"Completed")>1,"TRUE","FALSE") -> FALSE
A118: 001Nz000002Al1JIAS | B118: 1 | C118: TRUE | D118: Completed | U118: =IF(COUNTIF(D118:S118,"Completed")>1,"TRUE","FALSE") -> FALSE
A119: 001Nz000002WqITIA0 | B119: 1 | C119: TRUE | D119: Completed | U119: =IF(COUNTIF(D119:S119,"Completed")>1,"TRUE","FALSE") -> FALSE
A120: 001Nz000002UzxpIAC | B120: 1 | C120: TRUE | D120: Completed | U120: =IF(COUNTIF(D120:S120,"Completed")>1,"TRUE","FALSE") -> FALSE
A121: 001Nz000002aIYPIA2 | B121: 1 | C121: TRUE | D121: Completed | U121: =IF(COUNTIF(D121:S121,"Completed")>1,"TRUE","FALSE") -> FALSE
A122: 0018d00000IHd34AAD | B122: 1 | C122: TRUE | D122: Completed | U122: =IF(COUNTIF(D122:S122,"Completed")>1,"TRUE","FALSE") -> FALSE
A123: 001Nz000002P3PpIAK | B123: 1 | C123: TRUE | D123: Completed | U123: =IF(COUNTIF(D123:S123,"Completed")>1,"TRUE","FALSE") -> FALSE
A124: 001Nz000002PBvBIAW | B124: 1 | C124: TRUE | D124: Completed | U124: =IF(COUNTIF(D124:S124,"Completed")>1,"TRUE","FALSE") -> FALSE
A125: 001Nz000002cGyfIAE | B125: 1 | C125: TRUE | D125: Completed | U125: =IF(COUNTIF(D125:S125,"Completed")>1,"TRUE","FALSE") -> FALSE
A126: 001Nz000002SXrCIAW | B126: 1 | C126: TRUE | D126: Completed | U126: =IF(COUNTIF(D126:S126,"Completed")>1,"TRUE","FALSE") -> FALSE
... A131: 0018d00000WuEmkAAF | B131: 1 | C131: TRUE | D131: Completed | U131: =IF(COUNTIF(D131:S131,"Completed")>1,"TRUE","FALSE") -> FALSE
A132: 001Nz000003C13TIAS | B132: 3 | C132: TRUE | D132: Completed | E132: Not started | F132: Not started | U132: =IF(COUNTIF(D132:S132,"Completed")>1,"TRUE","FALSE") -> FALSE
A133: 001Nz000002SpRWIA0 | B133: 1 | C133: TRUE | D133: Completed | U133: =IF(COUNTIF(D133:S133,"Completed")>1,"TRUE","FALSE") -> FALSE
A134: 001Nz000002WMnUIAW | B134: 1 | C134: TRUE | D134: Completed | U134: =IF(COUNTIF(D134:S134,"Completed")>1,"TRUE","FALSE") -> FALSE
A135: 001Nz000002d2gkIAA | B135: 1 | C135: TRUE | D135: Completed | U135: =IF(COUNTIF(D135:S135,"Completed")>1,"TRUE","FALSE") -> FALSE
A136: 001Nz000002aY0aIAE | B136: 1 | C136: TRUE | D136: Completed | U136: =IF(COUNTIF(D136:S136,"Completed")>1,"TRUE","FALSE") -> FALSE
A137: 001Nz000001y4HxIAI | B137: 1 | C137: TRUE | D137: Completed | U137: =IF(COUNTIF(D137:S137,"Completed")>1,"TRUE","FALSE") -> FALSE
A138: 001Nz000002ZvNJIA0 | B138: 1 | C138: TRUE | D138: Completed | U138: =IF(COUNTIF(D138:S138,"Completed")>1,"TRUE","FALSE") -> FALSE
A139: 001Nz000002cXuhIAE | B139: 1 | C139: TRUE | D139: Completed | U139: =IF(COUNTIF(D139:S139,"Completed")>1,"TRUE","FALSE") -> FALSE
A140: 001Nz000002c8wHIAQ | B140: 1 | C140: TRUE | D140: Completed | U140: =IF(COUNTIF(D140:S140,"Completed")>1,"TRUE","FALSE") -> FALSE
A141: 001Nz000002QZQnIAO | B141: 1 | C141: TRUE | D141: Completed | U141: =IF(COUNTIF(D141:S141,"Completed")>1,"TRUE","FALSE") -> FALSE
A142: 001Nz000001wsyjIAA | B142: 1 | C142: TRUE | D142: Completed | U142: =IF(COUNTIF(D142:S142,"Completed")>1,"TRUE","FALSE") -> FALSE
A143: 001Nz000002gvK8IAI | B143: 1 | C143: TRUE | D143: Completed | U143: =IF(COUNTIF(D143:S143,"Completed")>1,"TRUE","FALSE") -> FALSE
A144: 001Nz0000024AEBIA2 | B144: 1 | C144: TRUE | D144: Completed | U144: =IF(COUNTIF(D144:S144,"Completed")>1,"TRUE","FALSE") -> FALSE
... A166: 001Nz000002pXKAIA2 | B166: 1 | C166: TRUE | D166: Completed | U166: =IF(COUNTIF(D166:S166,"Completed")>1,"TRUE","FALSE") -> FALSE
A167: 001Nz000003CRIrIAO | B167: 3 | C167: TRUE | D167: Completed | E167: Not started | F167: Not started | U167: =IF(COUNTIF(D167:S167,"Completed")>1,"TRUE","FALSE") -> FALSE
A168: 001Nz000003D6IoIAK | B168: 3 | C168: TRUE | D168: Completed | E168: Not started | F168: Not started | U168: =IF(COUNTIF(D168:S168,"Completed")>1,"TRUE","FALSE") -> FALSE
A169: 001Nz000002tRzMIAU | B169: 1 | C169: TRUE | D169: Completed | U169: =IF(COUNTIF(D169:S169,"Completed")>1,"TRUE","FALSE") -> FALSE
A170: 001Nz000002k7q9IAA | B170: 1 | C170: TRUE | D170: Completed | U170: =IF(COUNTIF(D170:S170,"Completed")>1,"TRUE","FALSE") -> FALSE
A171: 001Nz0000021Bl4IAE | B171: 1 | C171: TRUE | D171: Completed | U171: =IF(COUNTIF(D171:S171,"Completed")>1,"TRUE","FALSE") -> FALSE
A172: 001Nz000002tU4MIAU | B172: 1 | C172: TRUE | D172: Completed | U172: =IF(COUNTIF(D172:S172,"Completed")>1,"TRUE","FALSE") -> FALSE
A173: 001Nz000002tKucIAE | B173: 1 | C173: TRUE | D173: Completed | U173: =IF(COUNTIF(D173:S173,"Completed")>1,"TRUE","FALSE") -> FALSE
A174: 001Nz000001yBmVIAU | B174: 1 | C174: TRUE | D174: Completed | U174: =IF(COUNTIF(D174:S174,"Completed")>1,"TRUE","FALSE") -> FALSE
A175: 001Nz0000021qwIIAQ | B175: 1 | C175: TRUE | D175: Completed | U175: =IF(COUNTIF(D175:S175,"Completed")>1,"TRUE","FALSE") -> FALSE
A176: 001Nz000002oqezIAA | B176: 1 | C176: TRUE | D176: Completed | U176: =IF(COUNTIF(D176:S176,"Completed")>1,"TRUE","FALSE") -> FALSE
A177: 001Nz000002WYdPIAW | B177: 1 | C177: TRUE | D177: Completed | U177: =IF(COUNTIF(D177:S177,"Completed")>1,"TRUE","FALSE") -> FALSE
A178: 001Nz000002gvGsIAI | B178: 1 | C178: TRUE | D178: Completed | U178: =IF(COUNTIF(D178:S178,"Completed")>1,"TRUE","FALSE") -> FALSE
A179: 001Nz000002nEOyIAM | B179: 1 | C179: TRUE | D179: Completed | U179: =IF(COUNTIF(D179:S179,"Completed")>1,"TRUE","FALSE") -> FALSE
A180: 001Nz000002okOIIAY | B180: 1 | C180: TRUE | D180: Completed | U180: =IF(COUNTIF(D180:S180,"Completed")>1,"TRUE","FALSE") -> FALSE
... A184: 001Nz000002a1PTIAY | B184: 1 | C184: TRUE | D184: Completed | U184: =IF(COUNTIF(D184:S184,"Completed")>1,"TRUE","FALSE") -> FALSE
A185: 001Nz000000ghOjIAI | B185: 3 | C185: TRUE | D185: Completed | E185: Not started | F185: Not started | U185: =IF(COUNTIF(D185:S185,"Completed")>1,"TRUE","FALSE") -> FALSE
A186: 001Nz000003VePGIA0 | B186: 3 | C186: TRUE | D186: Completed | E186: Not started | F186: Not started | U186: =IF(COUNTIF(D186:S186,"Completed")>1,"TRUE","FALSE") -> FALSE
A187: 001Nz0000037mJCIAY | B187: 3 | C187: TRUE | D187: Completed | E187: Not started | F187: Not started | U187: =IF(COUNTIF(D187:S187,"Completed")>1,"TRUE","FALSE") -> FALSE
A188: 0018d00000G043zAAB | B188: 3 | C188: TRUE | D188: Completed | E188: Not started | F188: Not started | U188: =IF(COUNTIF(D188:S188,"Completed")>1,"TRUE","FALSE") -> FALSE
A189: 001Nz00000378tZIAQ | B189: 3 | C189: TRUE | D189: Completed | E189: Not started | F189: Not started | U189: =IF(COUNTIF(D189:S189,"Completed")>1,"TRUE","FALSE") -> FALSE
A190: 001Nz000002v1z8IAA | B190: 1 | C190: TRUE | D190: Completed | U190: =IF(COUNTIF(D190:S190,"Completed")>1,"TRUE","FALSE") -> FALSE
A191: 001Nz000003LNPiIAO | B191: 3 | C191: TRUE | D191: Completed | E191: Not started | F191: Not started | U191: =IF(COUNTIF(D191:S191,"Completed")>1,"TRUE","FALSE") -> FALSE
A192: 0018d00000aEq96AAC | B192: 1 | C192: TRUE | D192: Completed | U192: =IF(COUNTIF(D192:S192,"Completed")>1,"TRUE","FALSE") -> FALSE
A193: 001Nz000002pYUpIAM | B193: 1 | C193: TRUE | D193: Completed | U193: =IF(COUNTIF(D193:S193,"Completed")>1,"TRUE","FALSE") -> FALSE
A194: 001Nz000001NMVZIA4 | B194: 1 | C194: TRUE | D194: Completed | U194: =IF(COUNTIF(D194:S194,"Completed")>1,"TRUE","FALSE") -> FALSE
A195: 0018d0000095Ph7AAE | B195: 1 | C195: TRUE | D195: Completed | U195: =IF(COUNTIF(D195:S195,"Completed")>1,"TRUE","FALSE") -> FALSE
...

Sheet 2. RTR with Tenant >1 "Compltd"
A1: Id
A2: 001Nz000002wbUIIAY
A3: 001Nz0000077RHBIA2
A4: 001Nz0000014ue9IAA
A5: 001Nz000003oC2fIAE
A6: 001Nz000008Nb3uIAC
A7: 001Nz000004YEPdIAO
A8: 001Nz00000Ap54jIAB
A9: 0018d0000098mbAAAQ
A10: 001Nz000002QXs4IAG
A11: 001Nz000009qgHWIAY
A12: 001Nz000008BxHuIAK
... A94: 001Nz000006dIBJIA2

Sheet 3. RTR with Tenant >1 "Compltd"
A1: Id | B1: Tenant__c | C1: Tenant__r.Name | D1: Related_Opportunity__c | E1: Related_Unit__c | F1: Status__c | G1: Time_Limited__c | H1: RTR_Expiry__c | I1: Document_Saved__c | J1: Check_Date__c | K1: CreatedDate | L1: LastModifiedDate | M1: OwnerId | N1: Criteria | P1: _Pass Criteria?
A2: a1zPv0000018MikIAE | B2: 0014J00000VvNS1QAN | C2: . Barber | D2: 006Pv00000CPBm9IAH | F2: Not started | G2: FALSE | I2: FALSE | K2: 2024-11-14T22:08:24.000+0000 | L2: 2024-11-14T22:08:24.000+0000 | M2: 00GPv000002kNznMAE | P2: =NOT(ISERROR(VLOOKUP(B2,'2. RTR with Tenant >1 "Compltd"'!A:A,1,FALSE))) -> FALSE
A3: a1zNz000001djEPIAY | B3: 001Nz000008jzCZIAY | C3: ?Jingyao Chen | D3: 006Nz000008VWVGIA4 | E3: a1G4J0000025ynlUAA | F3: Completed | G3: TRUE | H3: 46059 | I3: TRUE | J3: 45352 | K3: 2024-03-01T14:52:24.000+0000 | L3: 2024-08-15T16:03:49.000+0000 | M3: 0058d000006aqUrAAI | P3: =NOT(ISERROR(VLOOKUP(B3,'2. RTR with Tenant >1 "Compltd"'!A:A,1,FALSE))) -> FALSE
A4: a1zPv000000vegfIAA | C4: 006Pv00000B94ckIAB | E4: Not started | F4: FALSE | H4: FALSE | J4: 2024-09-19T09:36:23.000+0000 | K4: 2024-09-19T09:36:23.000+0000 | L4: 00GPv000002kNznMAE | P4: =NOT(ISERROR(VLOOKUP(B4,'2. RTR with Tenant >1 "Compltd"'!A:A,1,FALSE))) -> FALSE
A5: a1zPv000000vebpIAA | C5: 006Pv00000B99grIAB | E5: Not started | F5: FALSE | H5: FALSE | J5: 2024-09-19T09:22:21.000+0000 | K5: 2024-09-19T09:22:21.000+0000 | L5: 00GPv000002kNznMAE | P5: =NOT(ISERROR(VLOOKUP(B5,'2. RTR with Tenant >1 "Compltd"'!A:A,1,FALSE))) -> FALSE
A6: a1zPv00000118FuIAI | C6: 006Pv00000Bc7BpIAJ | E6: Not started | F6: FALSE | H6: FALSE | J6: 2024-10-16T16:27:10.000+0000 | K6: 2024-10-16T16:27:10.000+0000 | L6: 00GPv000002kNznMAE | P6: =NOT(ISERROR(VLOOKUP(B6,'2. RTR with Tenant >1 "Compltd"'!A:A,1,FALSE))) -> FALSE
A7: a1zNz000000UIFeIAO | B7: 001Nz0000037crdIAA | C7: 0C6qXnFQiTEyPnsIKq62 KwJRGmqaKV9wEP8KMYgG | D7: 006Nz00000347FjIAI | F7: Completed | G7: FALSE | I7: TRUE | J7: 45236 | K7: 2023-11-06T09:58:45.000+0000 | L7: 2024-08-15T16:03:47.000+0000 | M7: 0058d0000043ssPAAQ | P7: =NOT(ISERROR(VLOOKUP(B7,'2. RTR with Tenant >1 "Compltd"'!A:A,1,FALSE))) -> FALSE
A8: a1zNz000000V2rxIAC | B8: 001Nz000003ssXzIAI | C8: 0Qce73SkNtmjUBe3uDk1 9qOeWaPWHSsfIW3g4Bhg | D8: 006Nz000003TzUlIAK | E8: a1G4J0000025zKnUAI | F8: Completed | G8: TRUE | H8: 45474 | I8: TRUE | J8: 45237 | K8: 2023-11-07T11:49:29.000+0000 | L8: 2023-11-07T11:49:29.000+0000 | M8: 0054J000004wZgRQAU | P8: =NOT(ISERROR(VLOOKUP(B8,'2. RTR with Tenant >1 "Compltd"'!A:A,1,FALSE))) -> FALSE
A9: a1zNz000003OHveIAG | B9: 001Nz000000VDQoIAO | C9: 1gNhjJnB1ks3CACYmUlK teIhOuSnagmwp8f9BrXq | D9: 006Nz00000AsbRYIAZ | E9: a1G4J0000025yVWUAY | F9: Completed | G9: FALSE | I9: TRUE | J9: 45456 | K9: 2024-06-13T13:59:38.000+0000 | L9: 2024-08-15T16:03:50.000+0000 | M9: 0054J000004vXOaQAM | P9: =NOT(ISERROR(VLOOKUP(B9,'2. RTR with Tenant >1 "Compltd"'!A:A,1,FALSE))) -> FALSE
A10: a1zNz0000022USIIA2 | B10: 0018d00000JjBl0AAF | C10: 1QZtgrjblkd4nCCZbnzg 5ggn9bOUA83W9V9OqlOP | D10: 006Nz000008LS7yIAG | E10: a1G4J0000025y00UAA | F10: Completed | G10: TRUE | H10: 45894 | I10: TRUE | J10: 45379 | K10: 2024-03-28T09:03:48.000+0000 | L10: 2024-08-15T16:03:50.000+0000 | M10: 0058d00000202rVAAQ | P10: =NOT(ISERROR(VLOOKUP(B10,'2. RTR with Tenant >1 "Compltd"'!A:A,1,FALSE))) -> FALSE
A11: a1zNz000002oVvWIAU | B11: 0018d00000RGQTFAA5 | C11: 2ESBl7VxuaG8dG4Noago WzDxQ0J7KzFtyuT0Jbi1 | D11: 006Nz00000B30oNIAR | E11: a1G8d0000004cBxEAI | F11: Completed | G11: TRUE | H11: 46502 | I11: TRUE | J11: 45426 | K11: 2024-05-14T13:42:19.000+0000 | L11: 2024-08-15T16:03:50.000+0000 | M11: 005Nz000003Ka0oIAC | P11: =NOT(ISERROR(VLOOKUP(B11,'2. RTR with Tenant >1 "Compltd"'!A:A,1,FALSE))) -> FALSE
A12: a1zNz000001QUxxIAG | B12: 0018d000006X2cxAAC | C12: 2I97XkY7BvRMU9TINOyD xOiuMvFSmvWwJbK2ITRC | E12: a1G4J000002609mUAA | F12: Completed | G12: TRUE | H12: 47515 | I12: TRUE | J12: 45338 | K12: 2024-02-16T14:38:47.000+0000 | L12: 2024-08-15T16:03:49.000+0000 | M12: 0058d000001yXevAAE | P12: =NOT(ISERROR(VLOOKUP(B12,'2. RTR with Tenant >1 "Compltd"'!A:A,1,FALSE))) -> FALSE
A13: a1zNz00000003AnIAI | B13: 001Nz000001iLszIAE | C13: 2MdM8M7dojhoxxGYABAj NwdLWsMpDGbakVQnWm7v | D13: 006Nz000001f3CfIAI | E13: a1G4J0000025z4AUAQ | F13: Completed | G13: FALSE | I13: TRUE | J13: 45159 | K13: 2023-08-21T14:40:42.000+0000 | L13: 2024-08-15T16:03:46.000+0000 | M13: 0054J000006BkQgQAK | P13: =NOT(ISERROR(VLOOKUP(B13,'2. RTR with Tenant >1 "Compltd"'!A:A,1,FALSE))) -> FALSE
A14: a1zNz000001X3GHIA0 | B14: 001Nz000002rQL1IAM | C14: 8jWcYnnW7AdjgM1KUcPf SxfunkUavXYxFgSvfXt4 | D14: 006Nz000000TQn7IAG | E14: a1G8d0000004c7EEAQ | F14: Completed | G14: TRUE | H14: 46122 | I14: TRUE | J14: 45345 | K14: 2024-02-23T17:46:37.000+0000 | L14: 2024-08-15T16:03:49.000+0000 | M14: 0058d0000034KZ2AAM | P14: =NOT(ISERROR(VLOOKUP(B14,'2. RTR with Tenant >1 "Compltd"'!A:A,1,FALSE))) -> FALSE
A15: a1zPv000000z5M9IAI | B15: 001Pv00000XV1B9IAL | C15: A BC | D15: 006Pv00000BR5wXIAT | F15: Not started | G15: FALSE | I15: FALSE | K15: 2024-10-07T11:44:36.000+0000 | L15: 2024-10-07T11:44:36.000+0000 | M15: 00GPv000002kNznMAE | P15: =NOT(ISERROR(VLOOKUP(B15,'2. RTR with Tenant >1 "Compltd"'!A:A,1,FALSE))) -> FALSE
A16: a1zPv000000zx3BIAQ | B16: 001Pv00000XV1B9IAL | C16: A BC | D16: 006Pv00000BR5wXIAT | F16: Not started | G16: FALSE | I16: FALSE | K16: 2024-10-11T13:34:56.000+0000 | L16: 2024-10-11T13:34:56.000+0000 | M16: 00GPv000002kNznMAE | P16: =NOT(ISERROR(VLOOKUP(B16,'2. RTR with Tenant >1 "Compltd"'!A:A,1,FALSE))) -> FALSE
A17: a1zPv0000017GcBIAU | B17: 0018d000006WChGAAW | C17: Aakaash Sankar | D17: 006Pv00000CKGL5IAP | F17: Not started | G17: FALSE | I17: FALSE | K17: 2024-11-11T08:00:24.000+0000 | L17: 2024-11-11T08:00:24.000+0000 | M17: 00GPv000002kNzmMAE | P17: =NOT(ISERROR(VLOOKUP(B17,'2. RTR with Tenant >1 "Compltd"'!A:A,1,FALSE))) -> FALSE
A18: a1zNz000003AIMyIAO | B18: 001Nz000000vnDiIAI | C18: Aakanksha Lowlekar | D18: 006Nz000000qkd6IAA | E18: a1G4J0000025zLEUAY | F18: Completed | G18: TRUE | H18: 45883 | I18: TRUE | J18: 45446 | K18: 2024-06-03T09:22:39.000+0000 | L18: 2024-08-15T16:03:50.000+0000 | M18: 005Nz000002mlzaIAA | P18: =NOT(ISERROR(VLOOKUP(B18,'2. RTR with Tenant >1 "Compltd"'!A:A,1,FALSE))) -> FALSE
A19: a1zPv000000rXsIIAU | B19: 001Nz000004bo5JIAQ | C19: Aalaa Seidahmed | D19: 006Pv00000AqpVJIAZ | F19: Not started | G19: FALSE | I19: FALSE | K19: 2024-09-04T07:01:47.000+0000 | L19: 2024-09-04T07:01:47.000+0000 | M19: 00GPv000002kNzmMAE | P19: =NOT(ISERROR(VLOOKUP(B19,'2. RTR with Tenant >1 "Compltd"'!A:A,1,FALSE))) -> FALSE
A20: a1zNz000001whTpIAI | B20: 0018d00000V8IGwAAN | C20: Aaliyah Naseem | D20: 006Nz000009JCLHIA4 | E20: a1G4J0000025xBnUAI | F20: Completed | G20: FALSE | I20: TRUE | J20: 45029 | K20: 2024-03-21T14:44:33.000+0000 | L20: 2024-08-15T16:03:50.000+0000 | M20: 0054J000004vXOqQAM | P20: =NOT(ISERROR(VLOOKUP(B20,'2. RTR with Tenant >1 "Compltd"'!A:A,1,FALSE))) -> FALSE
A21: a1zNz000001NIOfIAO | B21: 001Nz000007ezwqIAA | C21: Aanand Natarajan Rajahsekha | D21: 006Nz000007RzwHIAS | E21: a1G4J0000025x4jUAA | F21: Completed | G21: TRUE | H21: 46058 | I21: TRUE | J21: 45335 | K21: 2024-02-13T18:59:45.000+0000 | L21: 2024-08-15T16:03:49.000+0000 | M21: 0058d0000043sEOAAY | P21: =NOT(ISERROR(VLOOKUP(B21,'2. RTR with Tenant >1 "Compltd"'!A:A,1,FALSE))) -> FALSE
A22: a1zNz000000SsqHIAS | B22: 001Nz000003U1kvIAC | C22: Aanandita Gupta | D22: 006Nz000003QsB8IAK | E22: a1G4J000004jylDUAQ | F22: Completed | G22: TRUE | H22: 46283 | I22: TRUE | J22: 45239 | K22: 2023-11-03T15:49:33.000+0000 | L22: 2024-08-15T16:03:47.000+0000 | M22: 0058d00000202rVAAQ | P22: =NOT(ISERROR(VLOOKUP(B22,'2. RTR with Tenant >1 "Compltd"'!A:A,1,FALSE))) -> FALSE
A23: a1zNz000000Me5FIAS | B23: 001Nz000003YLI1IAO | C23: Aaron Bamford | D23: 006Nz000003QxfWIAS | E23: a1G8d0000004DFkEAM | F23: Completed | G23: FALSE | I23: TRUE | J23: 45224 | K23: 2023-10-25T16:36:17.000+0000 | L23: 2024-08-15T16:03:47.000+0000 | M23: 0058d000006cI6JAAU | P23: =NOT(ISERROR(VLOOKUP(B23,'2. RTR with Tenant >1 "Compltd"'!A:A,1,FALSE))) -> FALSE
A24: a1zPv000000ziliIAA | B24: 0018d000005ja1SAAQ | C24: Aaron Cordey | D24: 006Pv00000BUJlFIAX | F24: Not started | G24: FALSE | I24: FALSE | K24: 2024-10-10T07:01:11.000+0000 | L24: 2024-10-10T07:01:11.000+0000 | M24: 00GPv000002kNzmMAE | P24: =NOT(ISERROR(VLOOKUP(B24,'2. RTR with Tenant >1 "Compltd"'!A:A,1,FALSE))) -> FALSE
A25: a1zNz000001VGhRIAW | B25: 001Nz000008QrqVIAS | C25: Aaron Doyle | D25: 006Nz000008AiftIAC | E25: a1G4J0000025yIHUAY | F25: Completed | G25: FALSE | I25: TRUE | J25: 45343 | K25: 2024-02-21T15:49:41.000+0000 | L25: 2024-08-15T16:03:49.000+0000 | M25: 0054J000004wSINQA2 | P25: =NOT(ISERROR(VLOOKUP(B25,'2. RTR with Tenant >1 "Compltd"'!A:A,1,FALSE))) -> FALSE
A26: a1zNz000002YffXIAS | B26: 001Nz00000AWzQuIAL | C26: Aaron Grew | D26: 006Nz00000AJDFEIA5 | E26: a1G4J0000025zr2UAA | F26: Completed | G26: FALSE | I26: TRUE | J26: 45407 | K26: 2024-04-29T09:43:30.000+0000 | L26: 2024-08-15T16:03:50.000+0000 | M26: 0058d00000204EOAAY | P26: =NOT(ISERROR(VLOOKUP(B26,'2. RTR with Tenant >1 "Compltd"'!A:A,1,FALSE))) -> FALSE
A27: a1zNz000003MpgTIAS | B27: 001Nz000001chctIAA | C27: Aarshika Singh | D27: 0068d00000CsUdmAAF | E27: a1G4J00000260McUAI | F27: Completed | G27: TRUE | H27: 45932 | I27: TRUE | J27: 45138 | K27: 2024-06-12T14:23:29.000+0000 | L27: 2024-08-15T16:03:50.000+0000 | M27: 0054J000004vXOnQAM | P27: =NOT(ISERROR(VLOOKUP(B27,'2. RTR with Tenant >1 "Compltd"'!A:A,1,FALSE))) -> FALSE
A28: a1zNz000002uOrJIAU | B28: 001Nz00000BMhEVIA1 | C28: Aarti Aarti | D28: 006Nz00000B2avbIAB | E28: a1GNz000000126EMAQ | F28: Completed | G28: TRUE | H28: 47164 | I28: TRUE | J28: 45432 | K28: 2024-05-20T12:13:21.000+0000 | L28: 2024-08-15T16:03:50.000+0000 | M28: 0054J000005JWtDQAW | P28: =NOT(ISERROR(VLOOKUP(B28,'2. RTR with Tenant >1 "Compltd"'!A:A,1,FALSE))) -> FALSE
A29: a1zNz000000VCOHIA4 | B29: 001Nz000003rDodIAE | C29: Aarti DCruz | D29: 006Nz000003noV3IAI | E29: a1G4J0000025yCEUAY | F29: Completed | G29: TRUE | H29: 45590 | I29: TRUE | J29: 45238 | K29: 2023-11-08T10:29:56.000+0000 | L29: 2024-08-15T16:03:47.000+0000 | M29: 0054J000004wZgRQAU | P29: =NOT(ISERROR(VLOOKUP(B29,'2. RTR with Tenant >1 "Compltd"'!A:A,1,FALSE))) -> FALSE
A30: a1zPv000000sbCPIAY | B30: 001Nz000003rDodIAE | C30: Aarti DCruz | D30: 006Pv00000AvnPkIAJ | F30: Not started | G30: FALSE | I30: FALSE | K30: 2024-09-09T07:00:33.000+0000 | L30: 2024-09-09T07:00:33.000+0000 | M30: 00GPv000002kNzmMAE | P30: =NOT(ISERROR(VLOOKUP(B30,'2. RTR with Tenant >1 "Compltd"'!A:A,1,FALSE))) -> FALSE
A31: a1zNz000003M7FdIAK | B31: 001Nz00000CikbJIAR | C31: Aarushi Dureja | D31: 006Nz00000CRNRRIA5 | E31: a1G4J0000025zaFUAQ | F31: Completed | G31: TRUE | H31: 45687 | I31: TRUE | J31: 45455 | K31: 2024-06-12T10:46:37.000+0000 | L31: 2024-08-15T16:03:50.000+0000 | M31: 0054J000004vXPBQA2 | P31: =NOT(ISERROR(VLOOKUP(B31,'2. RTR with Tenant >1 "Compltd"'!A:A,1,FALSE))) -> FALSE
A32: a1zNz000001nKkzIAE | B32: 001Nz000008nm28IAA | C32: Aarushi Gupta | D32: 006Nz000008YptCIAS | E32: a1G4J0000025zsAUAQ | F32: Completed | G32: TRUE | H32: 46055 | I32: TRUE | J32: 45363 | K32: 2024-03-12T10:43:35.000+0000 | L32: 2024-08-15T16:03:50.000+0000 | M32: 005Nz000002KcrEIAS | P32: =NOT(ISERROR(VLOOKUP(B32,'2. RTR with Tenant >1 "Compltd"'!A:A,1,FALSE))) -> FALSE
A33: a1zNz000002SGALIA4 | B33: 001Nz00000A0fn5IAB | C33: Aaryaman Gandotra | D33: 006Nz000009kndGIAQ | E33: a1G4J00000262uRUAQ | F33: Completed | G33: TRUE | H33: 46184 | I33: TRUE | J33: 45405 | K33: 2024-04-23T05:30:13.000+0000 | L33: 2024-08-15T16:03:50.000+0000 | M33: 0058d0000034c7LAAQ | P33: =NOT(ISERROR(VLOOKUP(B33,'2. RTR with Tenant >1 "Compltd"'!A:A,1,FALSE))) -> FALSE
A34: a1zNz000003OUeNIAW | B34: 001Nz00000CFtVCIA1 | C34: Aaryaman Saini | D34: 006Nz00000BzHlbIAF | E34: a1G4J0000025y1JUAQ | F34: Completed | G34: TRUE | H34: 45925 | I34: TRUE | J34: 45456 | K34: 2024-06-13T15:13:05.000+0000 | L34: 2024-08-15T16:03:50.000+0000 | M34: 0054J000004vXOaQAM | P34: =NOT(ISERROR(VLOOKUP(B34,'2. RTR with Tenant >1 "Compltd"'!A:A,1,FALSE))) -> FALSE
A35: a1zNz000000LS4XIAW | B35: 001Nz000002aYlDIAU | C35: Aashna Grewal | D35: 006Nz000002XkMIIA0 | E35: a1G8d000002QBa3EAG | F35: Completed | G35: TRUE | H35: 45514 | I35: TRUE | J35: 45223 | K35: 2023-10-24T12:17:14.000+0000 | L35: 2023-10-24T12:17:14.000+0000 | M35: 0058d000006chw3AAA | P35: =NOT(ISERROR(VLOOKUP(B35,'2. RTR with Tenant >1 "Compltd"'!A:A,1,FALSE))) -> FALSE
A36: a1zPv000000pggYIAQ | B36: 001Nz000002aYlDIAU | C36: Aashna Grewal | D36: 006Pv00000Af1vOIAR | F36: Not started | G36: FALSE | I36: FALSE | K36: 2024-08-27T07:00:45.000+0000 | L36: 2024-08-27T07:00:45.000+0000 | M36: 00GPv000002kNzmMAE | P36: =NOT(ISERROR(VLOOKUP(B36,'2. RTR with Tenant >1 "Compltd"'!A:A,1,FALSE))) -> FALSE
A37: a1zNz000002w0PtIAI | B37: 001Nz00000BV0VGIA1 | C37: Aasrit Kappagantu | D37: 006Nz00000BEaJqIAL | E37: a1G4J0000025xhdUAA | F37: Completed | G37: TRUE | H37: 46420 | I37: TRUE | J37: 45433 | K37: 2024-05-21T13:02:33.000+0000 | L37: 2024-08-15T16:03:50.000+0000 | M37: 0054J000004vXOaQAM | P37: =NOT(ISERROR(VLOOKUP(B37,'2. RTR with Tenant >1 "Compltd"'!A:A,1,FALSE))) -> FALSE
A38: a1zNz000000RhYjIAK | B38: 001Nz0000010cvxIAA | C38: Abaan Kachkar | E38: a1G8d0000004XbiEAE | F38: Completed | G38: TRUE | H38: 45611 | I38: TRUE | J38: 45231 | K38: 2023-11-01T15:08:19.000+0000 | L38: 2024-08-15T16:03:47.000+0000 | M38: 0058d0000020QoXAAU | P38: =NOT(ISERROR(VLOOKUP(B38,'2. RTR with Tenant >1 "Compltd"'!A:A,1,FALSE))) -> FALSE
A39: a1zNz000001JcyfIAC | B39: 001Nz000007uYhKIAU | C39: Abantika Saha | D39: 006Nz000007dbS3IAI | E39: a1G8d000002QBKyEAO | F39: Completed | G39: TRUE | H39: 45697 | I39: TRUE | J39: 45331 | K39: 2024-02-09T15:17:05.000+0000 | L39: 2024-08-15T16:03:49.000+0000 | M39: 0054J000004vXOnQAM | P39: =NOT(ISERROR(VLOOKUP(B39,'2. RTR with Tenant >1 "Compltd"'!A:A,1,FALSE))) -> FALSE
A40: a1zNz000002GzfxIAC | B40: 001Nz00000AK9vtIAD | C40: Abasiama Inyang | D40: 006Nz00000A3qFgIAJ | E40: a1G4J0000025xz5UAA | F40: Completed | G40: TRUE | H40: 46299 | I40: TRUE | J40: 45393 | K40: 2024-04-11T10:44:23.000+0000 | L40: 2024-08-15T16:03:50.000+0000 | M40: 0058d000006aqUrAAI | P40: =NOT(ISERROR(VLOOKUP(B40,'2. RTR with Tenant >1 "Compltd"'!A:A,1,FALSE))) -> FALSE
A41: a1zNz000000zq3JIAQ | B41: 001Nz000000eKsrIAE | C41: Abayomi Elkanah | D41: 006Nz000000ZZqvIAG | F41: Completed | G41: TRUE | H41: 45666 | I41: TRUE | J41: 45300 | K41: 2024-01-10T16:08:14.000+0000 | L41: 2024-08-15T16:03:48.000+0000 | M41: 0058d0000034KtEAAU | P41: =NOT(ISERROR(VLOOKUP(B41,'2. RTR with Tenant >1 "Compltd"'!A:A,1,FALSE))) -> FALSE
A42: a1zNz000001UQZCIA4 | B42: 001Nz000008Cl0DIAS | C42: Abbas Ali Khan | D42: 006Nz000007nXi2IAE | E42: a1G4J00000262rSUAQ | F42: Completed | G42: FALSE | I42: TRUE | J42: 45342 | K42: 2024-02-21T08:46:48.000+0000 | L42: 2024-08-15T16:03:49.000+0000 | M42: 0058d00000204EOAAY | P42: =NOT(ISERROR(VLOOKUP(B42,'2. RTR with Tenant >1 "Compltd"'!A:A,1,FALSE))) -> FALSE
A43: a1zNz000000c3CzIAI | B43: 001Nz000004mYegIAE | C43: Abbas Ali Shah | D43: 006Nz000004eEgLIAU | E43: a1GNz000000177VMAQ | F43: Completed | G43: TRUE | H43: 45298 | I43: TRUE | J43: 45257 | K43: 2023-11-27T12:14:19.000+0000 | L43: 2023-11-28T10:48:21.000+0000 | M43: 0058d000006chw3AAA | P43: =NOT(ISERROR(VLOOKUP(B43,'2. RTR with Tenant >1 "Compltd"'!A:A,1,FALSE))) -> FALSE
A44: a1zPv000000sDukIAE | B44: 001Nz000004mduQIAQ | C44: Abbas Ali Shah | D44: 006Pv00000AuMT7IAN | F44: Not started | G44: FALSE | I44: FALSE | K44: 2024-09-07T07:02:48.000+0000 | L44: 2024-09-07T07:02:48.000+0000 | M44: 00GPv000002kNzmMAE | P44: =NOT(ISERROR(VLOOKUP(B44,'2. RTR with Tenant >1 "Compltd"'!A:A,1,FALSE))) -> FALSE
A45: a1zNz000001SnA5IAK | B45: 001Nz000004sdwZIAQ | C45: Abbas Miski | D45: 006Nz0000089JwTIAU | E45: a1G4J0000025yHwUAI | F45: Completed | G45: TRUE | H45: 45605 | I45: TRUE | J45: 45341 | K45: 2024-02-19T16:49:24.000+0000 | L45: 2024-08-15T16:03:49.000+0000 | M45: 0058d0000043ssPAAQ | P45: =NOT(ISERROR(VLOOKUP(B45,'2. RTR with Tenant >1 "Compltd"'!A:A,1,FALSE))) -> FALSE
A46: a1zNz000002Zyt2IAC | B46: 001Nz00000AYiLqIAL | C46: Abbas saleh | D46: 006Nz00000AIx0iIAD | E46: a1G4J000002603BUAQ | F46: Completed | G46: FALSE | I46: TRUE | J46: 45412 | K46: 2024-04-30T09:18:43.000+0000 | L46: 2024-08-15T16:03:50.000+0000 | M46: 0054J000004wZgRQAU | P46: =NOT(ISERROR(VLOOKUP(B46,'2. RTR with Tenant >1 "Compltd"'!A:A,1,FALSE))) -> FALSE
A47: a1zNz000002tud7IAA | B47: 001Nz00000Amxo3IAB | C47: Abbie Fish | D47: 006Nz00000AWgXpIAL | E47: a1G4J0000025z8cUAA | F47: Completed | G47: FALSE | I47: TRUE | J47: 45432 | K47: 2024-05-20T09:43:38.000+0000 | L47: 2024-08-15T16:03:50.000+0000 | M47: 0058d0000034SvqAAE | P47: =NOT(ISERROR(VLOOKUP(B47,'2. RTR with Tenant >1 "Compltd"'!A:A,1,FALSE))) -> FALSE
A48: a1zNz000001x7CzIAI | B48: 001Nz000009GsSLIA0 | C48: Abbie Foxton | D48: 006Nz0000090zxcIAA | E48: a1G4J0000025zV3UAI | F48: Completed | G48: FALSE | I48: TRUE | J48: 45376 | K48: 2024-03-22T10:07:25.000+0000 | L48: 2024-08-15T16:03:50.000+0000 | M48: 0058d000006cI6JAAU | P48: =NOT(ISERROR(VLOOKUP(B48,'2. RTR with Tenant >1 "Compltd"'!A:A,1,FALSE))) -> FALSE
A49: a1zNz000001OB1lIAG | B49: 001Nz000007fB6mIAE | C49: Abbie Watts | E49: a1GNz0000000aWZMAY | F49: Completed | G49: FALSE | I49: TRUE | J49: 45336 | K49: 2024-02-14T11:18:36.000+0000 | L49: 2024-11-07T16:34:50.000+0000 | M49: 005Nz0000004fixIAA | P49: =NOT(ISERROR(VLOOKUP(B49,'2. RTR with Tenant >1 "Compltd"'!A:A,1,FALSE))) -> FALSE
A50: a1zNz00000131v3IAA | B50: 001Nz000006TfysIAC | C50: Abby Cook | D50: 006Nz000006JpmdIAC | E50: a1G4J0000025xsdUAA | F50: Completed | G50: FALSE | I50: TRUE | J50: 45309 | K50: 2024-01-18T10:28:58.000+0000 | L50: 2024-08-15T16:03:49.000+0000 | M50: 0054J000004wSINQA2 | P50: =NOT(ISERROR(VLOOKUP(B50,'2. RTR with Tenant >1 "Compltd"'!A:A,1,FALSE))) -> FALSE
A51: a1zPv0000013J2WIAU | B51: 001Nz000006TfysIAC | C51: Abby Cook | D51: 006Pv00000C1S1vIAF | F51: Not started | G51: FALSE | I51: FALSE | K51: 2024-10-26T07:00:27.000+0000 | L51: 2024-10-26T07:00:27.000+0000 | M51: 00GPv000002kNzmMAE | P51: =NOT(ISERROR(VLOOKUP(B51,'2. RTR with Tenant >1 "Compltd"'!A:A,1,FALSE))) -> FALSE
A52: a1zNz000001ABMcIAO | B52: 001Nz000001Dpc5IAC | C52: Abby McMaster | D52: 006Nz0000078FkEIAU | E52: a1G4J0000025xzTUAQ | F52: Completed | G52: FALSE | I52: TRUE | J52: 45320 | K52: 2024-01-29T16:44:56.000+0000 | L52: 2024-08-15T16:03:49.000+0000 | M52: 0054J000004wSINQA2 | P52: =NOT(ISERROR(VLOOKUP(B52,'2. RTR with Tenant >1 "Compltd"'!A:A,1,FALSE))) -> FALSE
A53: a1zPv000001AoCkIAK | B53: 0014J00000athY5QAI | C53: Abdelsalam (Noah) Gaddafi | D53: 006Pv00000CYav8IAD | F53: Not started | G53: FALSE | I53: FALSE | K53: 2024-11-22T08:00:37.000+0000 | L53: 2024-11-22T08:00:37.000+0000 | M53: 00GPv000002kNzmMAE | P53: =NOT(ISERROR(VLOOKUP(B53,'2. RTR with Tenant >1 "Compltd"'!A:A,1,FALSE))) -> FALSE
A54: a1zNz000000gjdRIAQ | B54: 001Nz000005KNNQIA4 | C54: Abduallah Almugharrid | D54: 006Nz000003p1l9IAA | E54: a1G4J0000025xzjUAA | F54: Completed | G54: TRUE | H54: 46690 | I54: TRUE | J54: 45264 | K54: 2023-12-06T15:39:29.000+0000 | L54: 2024-08-15T16:03:48.000+0000 | M54: 0054J000004vXOiQAM | P54: =NOT(ISERROR(VLOOKUP(B54,'2. RTR with Tenant >1 "Compltd"'!A:A,1,FALSE))) -> FALSE
A55: a1zNz0000036H65IAE | B55: 001Nz00000Bv4jhIAB | C55: Abdul Ghani | D55: 006Nz00000BdpM6IAJ | E55: a1G8d0000005rE3EAI | F55: Completed | G55: FALSE | I55: TRUE | J55: 45442 | K55: 2024-05-30T09:18:14.000+0000 | L55: 2024-08-15T16:03:50.000+0000 | M55: 0058d0000034SvqAAE | P55: =NOT(ISERROR(VLOOKUP(B55,'2. RTR with Tenant >1 "Compltd"'!A:A,1,FALSE))) -> FALSE
A56: a1zNz000001q0L7IAI | B56: 001Nz000009L21nIAC | C56: Abdul Hamid Ahmed | D56: 006Nz000008yoBsIAI | E56: a1G8d0000005r6OEAQ | F56: Completed | G56: FALSE | I56: TRUE | J56: 45369 | K56: 2024-03-14T10:47:22.000+0000 | L56: 2024-08-15T16:03:50.000+0000 | M56: 0054J000004vXOhQAM | P56: =NOT(ISERROR(VLOOKUP(B56,'2. RTR with Tenant >1 "Compltd"'!A:A,1,FALSE))) -> FALSE
A57: a1zNz000000VNd3IAG | B57: 001Nz00000344zPIAQ | C57: Abdul Mohammed | D57: 006Nz0000030L1AIAU | F57: Completed | G57: TRUE | H57: 45828 | I57: TRUE | J57: 45239 | K57: 2023-11-09T10:15:13.000+0000 | L57: 2024-08-15T16:03:47.000+0000 | M57: 0058d0000043sEOAAY | P57: =NOT(ISERROR(VLOOKUP(B57,'2. RTR with Tenant >1 "Compltd"'!A:A,1,FALSE))) -> FALSE
A58: a1zNz000002vT5oIAE | B58: 001Nz00000BUhKYIA1 | C58: Abdul Sallam Sajid | D58: 006Nz00000BEFiSIAX | E58: a1G8d0000004Xc7EAE | F58: Completed | G58: TRUE | H58: 45800 | I58: TRUE | J58: 45433 | K58: 2024-05-21T10:40:40.000+0000 | L58: 2024-08-15T16:03:50.000+0000 | M58: 0058d0000034SvqAAE | P58: =NOT(ISERROR(VLOOKUP(B58,'2. RTR with Tenant >1 "Compltd"'!A:A,1,FALSE))) -> FALSE
A59: a1zPv000000nRn5IAE | B59: 001Nz000001pKSMIA2 | C59: Abdulaziz Alabdulazi | D59: 006Pv00000AUJ6EIAX | F59: Not started | G59: FALSE | I59: FALSE | K59: 2024-08-17T07:00:27.000+0000 | L59: 2024-08-17T07:00:27.000+0000 | M59: 00GPv000002kNzmMAE | P59: =NOT(ISERROR(VLOOKUP(B59,'2. RTR with Tenant >1 "Compltd"'!A:A,1,FALSE))) -> FALSE
A60: a1zNz000001qGjHIAU | B60: 001Nz000002GnrlIAC | C60: Abdulaziz AlAskar | D60: 006Nz0000093pwsIAA | E60: a1G8d0000005r98EAA | F60: Completed | G60: TRUE | H60: 45681 | I60: TRUE | J60: 45365 | K60: 2024-03-14T12:36:02.000+0000 | L60: 2024-08-15T16:03:50.000+0000 | M60: 0054J000004vXOhQAM | P60: =NOT(ISERROR(VLOOKUP(B60,'2. RTR with Tenant >1 "Compltd"'!A:A,1,FALSE))) -> FALSE
A61: a1zNz0000000OjtIAE | B61: 001Nz000001yLfLIAU | C61: Abdulaziz Alkandari | D61: 006Nz000001vbbsIAA | E61: a1G4J000004jyvCUAQ | F61: Completed | G61: TRUE | H61: 45251 | I61: TRUE | J61: 45174 | K61: 2023-09-05T11:47:52.000+0000 | L61: 2023-09-05T11:48:13.000+0000 | M61: 0054J000006BkQgQAK | P61: =NOT(ISERROR(VLOOKUP(B61,'2. RTR with Tenant >1 "Compltd"'!A:A,1,FALSE))) -> FALSE
A62: a1zNz000001qN81IAE | B62: 001Nz000009Jc63IAC | C62: Abdulaziz Almegbel | D62: 006Nz0000093pwsIAA | E62: a1G8d0000005r98EAA | F62: Completed | G62: TRUE | H62: 45684 | I62: TRUE | J62: 45365 | K62: 2024-03-14T12:34:40.000+0000 | L62: 2024-08-15T16:03:50.000+0000 | M62: 0054J000004vXOhQAM | P62: =NOT(ISERROR(VLOOKUP(B62,'2. RTR with Tenant >1 "Compltd"'!A:A,1,FALSE))) -> FALSE
A63: a1zNz000001DhUnIAK | B63: 001Nz000001ItbmIAC | C63: Abdulaziz Alshenaifi | D63: 006Nz000001FkZqIAK | E63: a1G8d000002QBLYEA4 | F63: Completed | G63: TRUE | H63: 45900 | I63: TRUE | J63: 45324 | K63: 2024-02-02T17:28:44.000+0000 | L63: 2024-08-15T16:03:49.000+0000 | M63: 005Nz000001cfZbIAI | P63: =NOT(ISERROR(VLOOKUP(B63,'2. RTR with Tenant >1 "Compltd"'!A:A,1,FALSE))) -> FALSE
A64: a1zPv000000sPMSIA2 | B64: 001Nz000001ItbmIAC | C64: Abdulaziz Alshenaifi | D64: 006Pv00000Av4ApIAJ | F64: Not started | G64: FALSE | I64: FALSE | K64: 2024-09-08T07:00:41.000+0000 | L64: 2024-09-08T07:00:41.000+0000 | M64: 00GPv000002kNzmMAE | P64: =NOT(ISERROR(VLOOKUP(B64,'2. RTR with Tenant >1 "Compltd"'!A:A,1,FALSE))) -> FALSE
A65: a1zNz000000yY21IAE | B65: 001Nz000006XwbFIAS | C65: AbdulAziz AlZalzalah | D65: 006Nz000006NwxYIAS | E65: a1G8d0000004D5fEAE | F65: Completed | G65: TRUE | H65: 45666 | I65: TRUE | J65: 45300 | K65: 2024-01-09T09:07:39.000+0000 | L65: 2024-08-15T16:03:48.000+0000 | M65: 0058d000006cI6JAAU | P65: =NOT(ISERROR(VLOOKUP(B65,'2. RTR with Tenant >1 "Compltd"'!A:A,1,FALSE))) -> FALSE
A66: a1zNz000002jo2kIAA | B66: 001Nz00000AZGgsIAH | C66: Abdulla Adil Kolakkaden | D66: 006Nz00000AJ80zIAD | E66: a1GNz00000015X7MAI | F66: Completed | G66: TRUE | H66: 45786 | I66: TRUE | J66: 45421 | K66: 2024-05-09T12:06:59.000+0000 | L66: 2024-08-15T16:03:50.000+0000 | M66: 0054J000005JWtDQAW | P66: =NOT(ISERROR(VLOOKUP(B66,'2. RTR with Tenant >1 "Compltd"'!A:A,1,FALSE))) -> FALSE
A67: a1zNz000000E6TlIAK | B67: 001Nz0000031pYJIAY | C67: Abdulla Al-Khaja | D67: 006Nz000002yQY2IAM | E67: a1G8d0000004DKUEA2 | F67: Completed | G67: TRUE | H67: 45960 | I67: TRUE | J67: 45211 | K67: 2023-10-12T11:14:19.000+0000 | L67: 2024-08-15T16:03:46.000+0000 | M67: 0058d000006cI6JAAU | P67: =NOT(ISERROR(VLOOKUP(B67,'2. RTR with Tenant >1 "Compltd"'!A:A,1,FALSE))) -> FALSE
A68: a1zNz000000StO9IAK | B68: 0018d00000JjgbGAAR | C68: Abdulla Alsulaiti | D68: 006Nz000003lYm5IAE | E68: a1G8d0000004DL8EAM | F68: Completed | G68: TRUE | H68: 45960 | I68: TRUE | J68: 45233 | K68: 2023-11-03T16:36:40.000+0000 | L68: 2024-08-15T16:03:47.000+0000 | M68: 0058d00000202rVAAQ | P68: =NOT(ISERROR(VLOOKUP(B68,'2. RTR with Tenant >1 "Compltd"'!A:A,1,FALSE))) -> FALSE
A69: a1zNz000002cEiNIAU | B69: 0018d000002v4GtAAI | C69: Abdullah Alhamaed | D69: 006Nz000008wPhXIAU | E69: a1G8d0000004DJCEA2 | F69: Completed | G69: TRUE | H69: 45778 | I69: TRUE | J69: 45413 | K69: 2024-05-01T13:51:16.000+0000 | L69: 2024-08-15T16:03:50.000+0000 | M69: 0054J000004vXOnQAM | P69: =NOT(ISERROR(VLOOKUP(B69,'2. RTR with Tenant >1 "Compltd"'!A:A,1,FALSE))) -> FALSE
A70: a1zNz000000eT4vIAE | B70: 0014J00000bisiBQAQ | C70: Abdullah Lajam | D70: 0064J00000GyCTvQAN | E70: a1G4J000004jyw6UAA | F70: Completed | G70: TRUE | H70: 45687 | I70: TRUE | J70: 45261 | K70: 2023-12-01T18:05:47.000+0000 | L70: 2024-08-15T16:03:48.000+0000 | M70: 0058d0000034Kn5AAE | P70: =NOT(ISERROR(VLOOKUP(B70,'2. RTR with Tenant >1 "Compltd"'!A:A,1,FALSE))) -> FALSE
A71: a1zNz00000076a9IAA | B71: 001Nz000002cXuhIAE | C71: Abdulmalek Alsaleh | D71: 006Nz000002X5O3IAK | E71: a1G8d0000004DBXEA2 | F71: Completed | G71: TRUE | H71: 45277 | I71: TRUE | J71: 45198 | K71: 2023-09-29T13:47:36.000+0000 | L71: 2023-09-29T13:47:36.000+0000 | M71: 0058d00000202rVAAQ | P71: =NOT(ISERROR(VLOOKUP(B71,'2. RTR with Tenant >1 "Compltd"'!A:A,1,FALSE))) -> FALSE
A72: a1zNz000002Srg9IAC | B72: 001Nz00000AVydHIAT | C72: Abdulmohsen Alkhanbashi | D72: 006Nz00000AFtxiIAD | E72: a1GNz0000019GxpMAE | F72: Completed | G72: TRUE | H72: 46904 | I72: TRUE | J72: 45405 | K72: 2024-04-23T11:05:15.000+0000 | L72: 2024-08-15T16:03:50.000+0000 | M72: 005Nz0000004fixIAA | P72: =NOT(ISERROR(VLOOKUP(B72,'2. RTR with Tenant >1 "Compltd"'!A:A,1,FALSE))) -> FALSE
A73: a1zPv000000uQuJIAU | B73: 0014J00000VvU2sQAF | C73: Abdulrahman Al-emadi | D73: 006Pv00000B4vZHIAZ | F73: Not started | G73: FALSE | I73: FALSE | K73: 2024-09-15T07:00:40.000+0000 | L73: 2024-09-15T07:00:40.000+0000 | M73: 00GPv000002kNzmMAE | P73: =NOT(ISERROR(VLOOKUP(B73,'2. RTR with Tenant >1 "Compltd"'!A:A,1,FALSE))) -> FALSE
A74: a1zPv000000rXqjIAE | B74: 0014J00000VvT7PQAV | C74: Abdulrahman Allzahrani | D74: 006Pv00000AqpQVIAZ | F74: Not started | G74: FALSE | I74: FALSE | K74: 2024-09-04T07:01:30.000+0000 | L74: 2024-09-04T07:01:30.000+0000 | M74: 00GPv000002kNzmMAE | P74: =NOT(ISERROR(VLOOKUP(B74,'2. RTR with Tenant >1 "Compltd"'!A:A,1,FALSE))) -> FALSE
A75: a1zNz000001aFkjIAE | B75: 001Nz000008U1ACIA0 | C75: Abdulrahman Khalid M Alturki | D75: 006Nz000008GGH9IAO | E75: a1G4J000004jyhpUAA | F75: Completed | G75: TRUE | H75: 45661 | I75: TRUE | J75: 45349 | K75: 2024-02-27T13:33:01.000+0000 | L75: 2024-08-15T16:03:49.000+0000 | M75: 0058d00000202rVAAQ | P75: =NOT(ISERROR(VLOOKUP(B75,'2. RTR with Tenant >1 "Compltd"'!A:A,1,FALSE))) -> FALSE
A76: a1zNz000001QUgHIAW | B76: 001Nz000007WbOdIAK | C76: Abeer Albalawi | D76: 006Nz000007JnsGIAS | E76: a1GNz0000000y7RMAQ | F76: Completed | G76: TRUE | H76: 45807 | I76: TRUE | J76: 45338 | K76: 2024-02-16T14:47:18.000+0000 | L76: 2024-08-15T16:03:49.000+0000 | M76: 0058d00000202rVAAQ | P76: =NOT(ISERROR(VLOOKUP(B76,'2. RTR with Tenant >1 "Compltd"'!A:A,1,FALSE))) -> FALSE
A77: a1zNz0000017LS9IAM | B77: 001Nz000006VD7CIAW | C77: Abena Prah | D77: 006Nz000006LHtmIAG | E77: a1G4J0000025yAcUAI | F77: Completed | G77: TRUE | H77: 47093 | I77: TRUE | J77: 45315 | K77: 2024-01-24T15:30:48.000+0000 | L77: 2024-08-15T16:03:49.000+0000 | M77: 0058d0000043ssPAAQ | P77: =NOT(ISERROR(VLOOKUP(B77,'2. RTR with Tenant >1 "Compltd"'!A:A,1,FALSE))) -> FALSE
A78: a1zNz000001GiCbIAK | B78: 001Nz000007JWWPIA4 | C78: Abhay Desalli | D78: 006Nz0000076xW1IAI | E78: a1G4J0000025vftUAA | F78: Completed | G78: TRUE | H78: 46550 | I78: TRUE | J78: 45328 | K78: 2024-02-06T17:30:20.000+0000 | L78: 2024-08-15T16:03:49.000+0000 | M78: 0058d0000043sEOAAY | P78: =NOT(ISERROR(VLOOKUP(B78,'2. RTR with Tenant >1 "Compltd"'!A:A,1,FALSE))) -> FALSE
A79: a1zPv000000pT8CIAU | B79: 001Nz000002elzzIAA | C79: Abhay Jindal | D79: 006Pv00000AdsvkIAB | F79: Not started | G79: FALSE | I79: FALSE | K79: 2024-08-26T07:00:56.000+0000 | L79: 2024-08-26T07:00:56.000+0000 | M79: 00GPv000002kNzmMAE | P79: =NOT(ISERROR(VLOOKUP(B79,'2. RTR with Tenant >1 "Compltd"'!A:A,1,FALSE))) -> FALSE
A80: a1zNz000002UEVpIAO | B80: 001Nz000002UG4cIAG | C80: Abhijeet Adhav | D80: 006Nz000002RaW8IAK | E80: a1G8d000002QBUPEA4 | F80: Completed | G80: TRUE | H80: 45814 | I80: TRUE | J80: 45406 | K80: 2024-04-24T11:08:15.000+0000 | L80: 2024-08-15T16:03:50.000+0000 | M80: 005Nz0000013sHqIAI | P80: =NOT(ISERROR(VLOOKUP(B80,'2. RTR with Tenant >1 "Compltd"'!A:A,1,FALSE))) -> FALSE
A81: a1zNz000002VoH7IAK | B81: 001Nz000007HEqYIAW | C81: Abhilash Mohanan Panicker | D81: 006Nz0000074uh9IAA | E81: a1G8d000002Q2YYEA0 | F81: Completed | G81: TRUE | H81: 45449 | I81: TRUE | J81: 45407 | K81: 2024-04-25T12:17:11.000+0000 | L81: 2024-04-25T18:56:32.000+0000 | M81: 005Nz000000FVd0IAG | P81: =NOT(ISERROR(VLOOKUP(B81,'2. RTR with Tenant >1 "Compltd"'!A:A,1,FALSE))) -> FALSE
A82: a1zNz00000076v7IAA | B82: 001Nz000002QZQnIAO | C82: Abhilasha Kakkar | D82: 006Nz000002O3WfIAK | E82: a1G4J000004jyqlUAA | F82: Completed | G82: FALSE | I82: TRUE | J82: 45198 | K82: 2023-09-29T14:24:07.000+0000 | L82: 2024-08-15T16:03:46.000+0000 | M82: 0058d00000202rVAAQ | P82: =NOT(ISERROR(VLOOKUP(B82,'2. RTR with Tenant >1 "Compltd"'!A:A,1,FALSE))) -> FALSE
A83: a1zNz000003OFKMIA4 | B83: 001Nz000000iIcMIAU | C83: Abigail Ehrlich | D83: 006Nz00000BWzLOIA1 | E83: a1G4J0000025yQ3UAI | F83: Completed | G83: FALSE | I83: TRUE | J83: 45456 | K83: 2024-06-13T13:38:28.000+0000 | L83: 2024-08-15T16:03:50.000+0000 | M83: 0054J000004vXOaQAM | P83: =NOT(ISERROR(VLOOKUP(B83,'2. RTR with Tenant >1 "Compltd"'!A:A,1,FALSE))) -> FALSE
A84: a1zNz000000W3dtIAC | B84: 001Nz000003lvxFIAQ | C84: Abigail Linda Opoku | D84: 006Nz0000034Nh4IAE | E84: a1GNz00000010qnMAA | F84: Completed | G84: TRUE | H84: 46073 | I84: TRUE | J84: 45243 | K84: 2023-11-13T15:07:54.000+0000 | L84: 2024-08-15T16:03:47.000+0000 | M84: 005Nz000000B1bwIAC | P84: =NOT(ISERROR(VLOOKUP(B84,'2. RTR with Tenant >1 "Compltd"'!A:A,1,FALSE))) -> FALSE
A85: a1zPv000000oKQUIA2 | B85: 001Nz000003lvxFIAQ | C85: Abigail Linda Opoku | D85: 006Pv00000AYudMIAT | F85: Not started | G85: FALSE | I85: FALSE | K85: 2024-08-21T07:00:35.000+0000 | L85: 2024-08-21T07:00:35.000+0000 | M85: 00GPv000002kNzmMAE | P85: =NOT(ISERROR(VLOOKUP(B85,'2. RTR with Tenant >1 "Compltd"'!A:A,1,FALSE))) -> FALSE
A86: a1zNz000002LF1KIAW | B86: 001Nz000003K0GfIAK | C86: Abiola Afolabi | D86: 006Nz000009yNUQIA2 | E86: a1G4J0000025xw3UAA | F86: Completed | G86: TRUE | H86: 46479 | I86: TRUE | J86: 45398 | K86: 2024-04-16T09:36:19.000+0000 | L86: 2024-08-15T16:03:50.000+0000 | M86: 0058d000006aqUrAAI | P86: =NOT(ISERROR(VLOOKUP(B86,'2. RTR with Tenant >1 "Compltd"'!A:A,1,FALSE))) -> FALSE
A87: a1zPv000000pggPIAQ | B87: 0018d00000JkAEyAAN | C87: Abisolaoluwa Babasola | D87: 006Pv00000Af1vIIAR | F87: Not started | G87: FALSE | I87: FALSE | K87: 2024-08-27T07:00:45.000+0000 | L87: 2024-08-27T07:00:45.000+0000 | M87: 00GPv000002kNzmMAE | P87: =NOT(ISERROR(VLOOKUP(B87,'2. RTR with Tenant >1 "Compltd"'!A:A,1,FALSE))) -> FALSE
A88: a1zNz000000PSXNIA4 | B88: 001Nz000003QxSYIA0 | C88: Abjll Maih | D88: 006Nz000003Ng1gIAC | E88: a1G8d0000004D8AEAU | F88: Completed | G88: FALSE | I88: TRUE | J88: 45229 | K88: 2023-10-30T12:33:10.000+0000 | L88: 2024-08-15T16:03:47.000+0000 | M88: 0058d00000202rVAAQ | P88: =NOT(ISERROR(VLOOKUP(B88,'2. RTR with Tenant >1 "Compltd"'!A:A,1,FALSE))) -> FALSE
A89: a1zNz000003Nxk4IAC | B89: 001Nz00000Ced74IAB | C89: Abraham Ayomini Adekoya | D89: 006Nz00000CHgthIAD | E89: a1G4J0000025y5YUAQ | F89: Completed | G89: FALSE | I89: TRUE | J89: 45456 | K89: 2024-06-13T11:57:10.000+0000 | L89: 2024-08-15T16:03:50.000+0000 | M89: 0058d0000020feeAAA | P89: =NOT(ISERROR(VLOOKUP(B89,'2. RTR with Tenant >1 "Compltd"'!A:A,1,FALSE))) -> FALSE
A90: a1zNz000002LXKnIAO | B90: 0018d00000LKUXSAA5 | C90: Abraham Ng | D90: 006Nz000009UAG5IAO | E90: a1G4J0000025z9ZUAQ | F90: Completed | G90: TRUE | H90: 46672 | I90: TRUE | J90: 45398 | K90: 2024-04-16T10:55:08.000+0000 | L90: 2024-08-15T16:03:50.000+0000 | M90: 0054J000004wSINQA2 | P90: =NOT(ISERROR(VLOOKUP(B90,'2. RTR with Tenant >1 "Compltd"'!A:A,1,FALSE))) -> FALSE
A91: a1zNz000000ip8TIAQ | B91: 0018d00000aEi63AAC | C91: Abram Flores | D91: 006Nz000004wE5VIAU | E91: a1G4J0000025zRfUAI | F91: Completed | G91: TRUE | H91: 46128 | I91: TRUE | J91: 45271 | K91: 2023-12-11T11:41:17.000+0000 | L91: 2024-08-15T16:03:48.000+0000 | M91: 0054J000006BkQgQAK | P91: =NOT(ISERROR(VLOOKUP(B91,'2. RTR with Tenant >1 "Compltd"'!A:A,1,FALSE))) -> FALSE
A92: a1zPv000000uFCnIAM | B92: 0018d00000aEi63AAC | C92: Abram Flores | D92: 006Pv00000B34vMIAR | F92: Not started | G92: FALSE | I92: FALSE | K92: 2024-09-14T07:01:20.000+0000 | L92: 2024-09-14T07:01:20.000+0000 | M92: 00GPv000002kNzmMAE | P92: =NOT(ISERROR(VLOOKUP(B92,'2. RTR with Tenant >1 "Compltd"'!A:A,1,FALSE))) -> FALSE
A93: a1zNz000000gwPNIAY | B93: 001Nz000002zHUHIA2 | C93: Abrar Alwayel | D93: 006Nz0000052cXrIAI | E93: a1G8d0000004cBEEAY | F93: Completed | G93: TRUE | H93: 45358 | I93: TRUE | J93: 45267 | K93: 2023-12-07T10:01:46.000+0000 | L93: 2023-12-07T10:01:46.000+0000 | M93: 005Nz0000004fixIAA | P93: =NOT(ISERROR(VLOOKUP(B93,'2. RTR with Tenant >1 "Compltd"'!A:A,1,FALSE))) -> FALSE
A94: a1zNz000003B01NIAS | B94: 001Nz00000BqtzmIAB | C94: Abu Zaid Khan | D94: 006Nz00000BZdGKIA1 | E94: a1GNz0000000a9zMAA | F94: Completed | G94: TRUE | H94: 46385 | I94: TRUE | J94: 45446 | K94: 2024-06-03T15:13:21.000+0000 | L94: 2024-08-15T16:03:50.000+0000 | M94: 0054J000004vXOqQAM | P94: =NOT(ISERROR(VLOOKUP(B94,'2. RTR with Tenant >1 "Compltd"'!A:A,1,FALSE))) -> FALSE
A95: a1zNz000000cg9VIAQ | B95: 001Nz000004t0pwIAA | C95: Adam Batty | D95: 006Nz000004hIXFIA2 | E95: a1G4J0000025yI5UAI | F95: Completed | G95: FALSE | I95: TRUE | J95: 45254 | K95: 2023-11-28T10:12:34.000+0000 | L95: 2024-08-15T16:03:48.000+0000 | M95: 0058d0000043ssPAAQ | P95: =NOT(ISERROR(VLOOKUP(B95,'2. RTR with Tenant >1 "Compltd"'!A:A,1,FALSE))) -> FALSE
A96: a1zPv000000ucVrIAI | B96: 001Nz000004t0pwIAA | C96: Adam Batty | D96: 006Pv00000B5h9QIAR | F96: Not started | G96: FALSE | I96: FALSE | K96: 2024-09-16T07:00:25.000+0000 | L96: 2024-09-16T07:00:25.000+0000 | M96: 00GPv000002kNzmMAE | P96: =NOT(ISERROR(VLOOKUP(B96,'2. RTR with Tenant >1 "Compltd"'!A:A,1,FALSE))) -> FALSE
A97: a1zNz000001SDEjIAO | B97: 001Nz000008FqORIA0 | C97: Adam Byrd | D97: 006Nz0000082DSrIAM | E97: a1G4J0000025z22UAA | F97: Completed | G97: FALSE | I97: TRUE | J97: 45341 | K97: 2024-02-19T10:30:15.000+0000 | L97: 2024-08-15T16:03:49.000+0000 | M97: 0058d00000202rVAAQ | P97: =NOT(ISERROR(VLOOKUP(B97,'2. RTR with Tenant >1 "Compltd"'!A:A,1,FALSE))) -> FALSE
A98: a1zPv000000qYjyIAE | B98: 0018d000003WgTWAA0 | C98: Adam Cinelioglu | D98: 006Pv00000AlGl8IAF | F98: Not started | G98: FALSE | I98: FALSE | K98: 2024-08-30T07:00:29.000+0000 | L98: 2024-08-30T07:00:29.000+0000 | M98: 00GPv000002kNzmMAE | P98: =NOT(ISERROR(VLOOKUP(B98,'2. RTR with Tenant >1 "Compltd"'!A:A,1,FALSE))) -> FALSE
A99: a1zNz000003OOIpIAO | B99: 001Nz0000029822IAA | C99: Adam Fleiser | D99: 006Nz0000026gpvIAA | E99: a1G4J0000025yMbUAI | F99: Completed | G99: TRUE | H99: 45722 | I99: TRUE | J99: 45456 | K99: 2024-06-13T14:04:06.000+0000 | L99: 2024-08-15T16:03:50.000+0000 | M99: 0058d0000034Km2AAE | P99: =NOT(ISERROR(VLOOKUP(B99,'2. RTR with Tenant >1 "Compltd"'!A:A,1,FALSE))) -> FALSE
A100: a1zNz000002DzitIAC | B100: 001Nz00000A4aK9IAJ | C100: Adam King | D100: 006Nz000009ocktIAA | E100: a1G4J000002606EUAQ | F100: Completed | G100: FALSE | I100: TRUE | J100: 45391 | K100: 2024-04-09T08:29:40.000+0000 | L100: 2024-08-15T16:03:50.000+0000 | M100: 0054J000004wZgRQAU | P100: =NOT(ISERROR(VLOOKUP(B100,'2. RTR with Tenant >1 "Compltd"'!A:A,1,FALSE))) -> FALSE
...

Sheet 1. RTR with Tenant >1 != Vacatd
A1: Id | B1: Right_to_Rents__r.totalSize | C1: Right_to_Rents__r.done | D1: Right_to_Rents__r.records.0.Status__c | E1: Right_to_Rents__r.records.1.Status__c | F1: Right_to_Rents__r.records.2.Status__c | G1: Right_to_Rents__r.records.3.Status__c | H1: Right_to_Rents__r.records.4.Status__c | I1: Right_to_Rents__r.records.5.Status__c | J1: Right_to_Rents__r.records.6.Status__c | K1: Right_to_Rents__r.records.7.Status__c | L1: Right_to_Rents__r.records.8.Status__c | M1: Right_to_Rents__r.records.9.Status__c | N1: Right_to_Rents__r.records.10.Status__c | O1: Right_to_Rents__r.records.11.Status__c | P1: Right_to_Rents__r.records.12.Status__c | Q1: Right_to_Rents__r.records.13.Status__c | R1: Right_to_Rents__r.records.14.Status__c | S1: Right_to_Rents__r.records.15.Status__c
A2: 001Nz000001U4NNIA0 | B2: 1 | C2: TRUE | D2: Completed
A3: 001Nz000001iLszIAE | B3: 1 | C3: TRUE | D3: Completed
A4: 0018d000002sQaEAAU | B4: 1 | C4: TRUE | D4: Completed
A5: 001Nz000001TtoZIAS | B5: 1 | C5: TRUE | D5: Completed
A6: 0014J00000biT5dQAE | B6: 3 | C6: TRUE | D6: Completed | E6: Completed | F6: Not started
A7: 0018d00000PSOIFAA5 | B7: 1 | C7: TRUE | D7: Completed
A8: 001Nz000001sfwrIAA | B8: 1 | C8: TRUE | D8: Completed
A9: 001Nz000001sCWmIAM | B9: 1 | C9: TRUE | D9: In Progress
A10: 001Nz000001qr1FIAQ | B10: 1 | C10: TRUE | D10: Completed
A11: 001Nz000001oT7yIAE | B11: 1 | C11: TRUE | D11: Completed
A12: 001Nz000001oKXjIAM | B12: 1 | C12: TRUE | D12: Completed
A13: 0018d000006WGGzAAO | B13: 1 | C13: TRUE | D13: Completed
A14: 001Nz000001XuIzIAK | B14: 1 | C14: TRUE | D14: Completed
A15: 001Nz000001jf9kIAA | B15: 1 | C15: TRUE | D15: Completed
A16: 001Nz000001yLfLIAU | B16: 1 | C16: TRUE | D16: Completed
A17: 001Nz000001pg3JIAQ | B17: 1 | C17: TRUE | D17: Completed
A18: 001Nz000001iSfxIAE | B18: 1 | C18: TRUE | D18: Completed
... A21: 001Nz000001WsmHIAS | B21: 1 | C21: TRUE | D21: Completed
A22: 001Nz000001WsJGIA0 | B22: 2 | C22: TRUE | D22: Completed | E22: Completed
A23: 001Nz000001Wz30IAC | B23: 2 | C23: TRUE | D23: Completed | E23: Completed
A24: 001Nz000001rKODIA2 | B24: 1 | C24: TRUE | D24: Completed
A25: 0018d00000EjZsSAAV | B25: 1 | C25: TRUE | D25: Completed
A26: 001Nz000001WwGRIA0 | B26: 1 | C26: TRUE | D26: Completed
A27: 001Nz000001W5FKIA0 | B27: 2 | C27: TRUE | D27: Completed | E27: Not started
A28: 0014J00000ZR2dfQAD | B28: 1 | C28: TRUE | D28: Completed
A29: 001Nz000001iO7hIAE | B29: 2 | C29: TRUE | D29: Completed | E29: Not started
A30: 001Nz000001jP9oIAE | B30: 1 | C30: TRUE | D30: Completed
A31: 001Nz000002QXs4IAG | B31: 2 | C31: TRUE | D31: Completed | E31: Completed
A32: 001Nz000002SyHqIAK | B32: 1 | C32: TRUE | D32: Completed
A33: 001Nz0000022sfwIAA | B33: 1 | C33: TRUE | D33: Completed
A34: 001Nz000002Al1JIAS | B34: 1 | C34: TRUE | D34: Completed
A35: 001Nz000002WqITIA0 | B35: 1 | C35: TRUE | D35: Completed
A36: 001Nz000002UzxpIAC | B36: 1 | C36: TRUE | D36: Completed
A37: 001Nz000002aIYPIA2 | B37: 1 | C37: TRUE | D37: Completed
A38: 0018d00000IHd34AAD | B38: 1 | C38: TRUE | D38: Completed
A39: 001Nz000002P3PpIAK | B39: 1 | C39: TRUE | D39: Completed
A40: 001Nz000002PBvBIAW | B40: 1 | C40: TRUE | D40: Completed
A41: 001Nz000002cGyfIAE | B41: 1 | C41: TRUE | D41: Completed
A42: 001Nz000002SXrCIAW | B42: 1 | C42: TRUE | D42: Completed
A43: 001Nz000002WepFIAS | B43: 1 | C43: TRUE | D43: Completed
... A47: 0018d00000WuEmkAAF | B47: 1 | C47: TRUE | D47: Completed
A48: 0018d00000Jk8SEAAZ | B48: 2 | C48: TRUE | D48: Completed | E48: In Progress
A49: 001Nz000002SpRWIA0 | B49: 1 | C49: TRUE | D49: Completed
A50: 001Nz000002WMnUIAW | B50: 1 | C50: TRUE | D50: Completed
A51: 001Nz000002d2gkIAA | B51: 1 | C51: TRUE | D51: Completed
A52: 0018d00000JkBPhAAN | B52: 4 | C52: TRUE | D52: Completed | E52: Completed | F52: Completed | G52: Not started
A53: 001Nz000002aY0aIAE | B53: 1 | C53: TRUE | D53: Completed
A54: 001Nz000001y4HxIAI | B54: 1 | C54: TRUE | D54: Completed
A55: 001Nz000002ZvNJIA0 | B55: 1 | C55: TRUE | D55: Completed
A56: 001Nz000002cXuhIAE | B56: 1 | C56: TRUE | D56: Completed
A57: 001Nz000002c8wHIAQ | B57: 1 | C57: TRUE | D57: Completed
A58: 001Nz000002QZQnIAO | B58: 1 | C58: TRUE | D58: Completed
A59: 001Nz000001wsyjIAA | B59: 1 | C59: TRUE | D59: Completed
A60: 001Nz000002gvK8IAI | B60: 1 | C60: TRUE | D60: Completed
A61: 001Nz0000024AEBIA2 | B61: 1 | C61: TRUE | D61: Completed
A62: 001Nz000001WrtRIAS | B62: 1 | C62: TRUE | D62: Completed
A63: 001Nz000002WgnnIAC | B63: 1 | C63: TRUE | D63: Completed
A64: 001Nz000002R9hBIAS | B64: 1 | C64: TRUE | D64: Completed
... A83: 001Nz000002pXKAIA2 | B83: 1 | C83: TRUE | D83: Completed
A84: 001Nz000002rHKwIAM | B84: 3 | C84: TRUE | D84: Completed | E84: Not started | F84: Not started
A85: 001Nz000002rLgQIAU | B85: 2 | C85: TRUE | D85: Completed | E85: Not started
A86: 001Nz000002tRzMIAU | B86: 1 | C86: TRUE | D86: Completed
A87: 001Nz000002k7q9IAA | B87: 1 | C87: TRUE | D87: Completed
A88: 001Nz0000021Bl4IAE | B88: 1 | C88: TRUE | D88: Completed
A89: 001Nz000002tU4MIAU | B89: 1 | C89: TRUE | D89: Completed
A90: 001Nz000002tKucIAE | B90: 1 | C90: TRUE | D90: Completed
A91: 0018d00000IJvBwAAL | B91: 1 | C91: TRUE | D91: In Progress
A92: 001Nz000001yBmVIAU | B92: 1 | C92: TRUE | D92: Completed
A93: 001Nz0000021qwIIAQ | B93: 1 | C93: TRUE | D93: Completed
A94: 001Nz000002oqezIAA | B94: 1 | C94: TRUE | D94: Completed
A95: 001Nz000002WYdPIAW | B95: 1 | C95: TRUE | D95: Completed
A96: 001Nz000002gvGsIAI | B96: 1 | C96: TRUE | D96: Completed
A97: 001Nz000002nEOyIAM | B97: 1 | C97: TRUE | D97: Completed
... A102: 001Nz000002a1PTIAY | B102: 1 | C102: TRUE | D102: Completed
A103: 0018d00000IIGhQAAX | B103: 2 | C103: TRUE | D103: Completed | E103: Not started
A104: 001Nz000001i7reIAA | B104: 2 | C104: TRUE | D104: Completed | E104: Not started
A105: 0018d000006WoX1AAK | B105: 2 | C105: TRUE | D105: Completed | E105: Not started
A106: 001Nz000002GiooIAC | B106: 2 | C106: TRUE | D106: Completed | E106: Not started
A107: 001Nz000002uyV3IAI | B107: 2 | C107: TRUE | D107: Completed | E107: Not started
A108: 001Nz000002v1z8IAA | B108: 1 | C108: TRUE | D108: Completed
A109: 001Nz000000scY9IAI | B109: 2 | C109: TRUE | D109: Completed | E109: Not started
A110: 001Nz000000iNgrIAE | B110: 2 | C110: TRUE | D110: Completed | E110: Completed
A111: 0018d00000aEq96AAC | B111: 1 | C111: TRUE | D111: Completed
A112: 001Nz000002pYUpIAM | B112: 1 | C112: TRUE | D112: Completed
A113: 001Nz000001NMVZIA4 | B113: 1 | C113: TRUE | D113: Completed
A114: 0018d0000095Ph7AAE | B114: 1 | C114: TRUE | D114: Completed
A115: 0018d000006XMWtAAO | B115: 1 | C115: TRUE | D115: Completed
A116: 0018d00000aGOnsAAG | B116: 1 | C116: TRUE | D116: Completed
A117: 001Nz000002zQsUIAU | B117: 1 | C117: TRUE | D117: In Progress
A118: 001Nz000002spUIIAY | B118: 3 | C118: TRUE | D118: Completed | E118: Completed | F118: Not started
A119: 001Nz000002aYq3IAE | B119: 2 | C119: TRUE | D119: Completed | E119: Not started
A120: 001Nz000002a5GBIAY | B120: 2 | C120: TRUE | D120: Completed | E120: Not started
A121: 001Nz000002tLqiIAE | B121: 2 | C121: TRUE | D121: Completed | E121: Not started
A122: 001Nz000002SRoyIAG | B122: 2 | C122: TRUE | D122: Completed | E122: Not started
A123: 001Nz0000028sGbIAI | B123: 1 | C123: TRUE | D123: Not started
A124: 001Nz000002r5mqIAA | B124: 1 | C124: TRUE | D124: Completed
A125: 001Nz000001o0p3IAA | B125: 1 | C125: TRUE | D125: Completed
A126: 001Nz000001pbjKIAQ | B126: 1 | C126: TRUE | D126: Completed
A127: 001Nz000002RKr7IAG | B127: 1 | C127: TRUE | D127: Completed
...

Sheet 2. RTR with Tenant >1 != Vacatd
A1: Id
A2: 0014J00000biT5dQAE
A3: 001Nz000001WsJGIA0
A4: 001Nz000001Wz30IAC
A5: 001Nz000001W5FKIA0
A6: 001Nz000001iO7hIAE
A7: 001Nz000002QXs4IAG
A8: 0018d00000Jk8SEAAZ
A9: 0018d00000JkBPhAAN
A10: 001Nz000002rHKwIAM
A11: 001Nz000002rLgQIAU
A12: 0018d00000IIGhQAAX
... A958: 001Pv00000YvlQ1IAJ

Sheet 3. RTR with Tenant >1 != Vacatd
A1: Id | B1: Tenant__c | C1: Tenant__r.Name | D1: Related_Opportunity__c | E1: Related_Unit__c | F1: Status__c | G1: Time_Limited__c | H1: RTR_Expiry__c | I1: Date_Next_RTR_Required__c | J1: Document_Saved__c | K1: Check_Date__c | L1: CreatedDate | M1: LastModifiedDate | N1: Owner.Name | P1: _Date_Next_RTR_Required__c > TODAY? | Q1: _Account_Satify_Condition? | R1: _RTR To Be Considered?
A2: a1zNz00000001ddIAA | B2: 001Nz000001U4NNIA0 | C2: Puja Aggarwal | D2: 006Nz000001QqYfIAK | E2: a1G4J000004jyoaUAA | F2: Completed | G2: FALSE | I2: 45621 | J2: TRUE | K2: 45154 | L2: 2023-08-16T14:52:09.000+0000 | M2: 2024-08-15T16:03:46.000+0000 | N2: 0058d00000202rVAAQ | P2: =IF(I2>TODAY(),TRUE,FALSE) -> FALSE | Q2: =NOT(ISERROR(VLOOKUP(B2,'2. RTR with Tenant >1 != Vacatd'!A:A,1,FALSE))) -> FALSE | R2: =AND(P2=TRUE,Q2=TRUE) -> FALSE
A3: a1zNz00000003AnIAI | B3: 001Nz000001iLszIAE | C3: 2MdM8M7dojhoxxGYABAj NwdLWsMpDGbakVQnWm7v | D3: 006Nz000001f3CfIAI | E3: a1G4J0000025z4AUAQ | F3: Completed | G3: FALSE | I3: 45973 | J3: TRUE | K3: 45159 | L3: 2023-08-21T14:40:42.000+0000 | M3: 2024-08-15T16:03:46.000+0000 | N3: 0054J000006BkQgQAK | P3: =IF(I3>TODAY(),TRUE,FALSE) -> TRUE | Q3: =NOT(ISERROR(VLOOKUP(B3,'2. RTR with Tenant >1 != Vacatd'!A:A,1,FALSE))) -> TRUE | R3: =AND(P3=TRUE,Q3=TRUE) -> TRUE
A4: a1zNz00000003QvIAI | B4: 0018d000002sQaEAAU | C4: Thendo Makgatho | E4: a1G4J000004jyeVUAQ | F4: Completed | G4: TRUE | H4: 45522 | I4: 45974 | J4: TRUE | K4: 45159 | L4: 2023-08-22T11:00:40.000+0000 | M4: 2024-08-15T16:03:46.000+0000 | N4: 0058d0000034Kn5AAE | P4: =IF(I4>TODAY(),TRUE,FALSE) -> TRUE | Q4: =NOT(ISERROR(VLOOKUP(B4,'2. RTR with Tenant >1 != Vacatd'!A:A,1,FALSE))) -> FALSE | R4: =AND(P4=TRUE,Q4=TRUE) -> FALSE
A5: a1zNz00000004I9IAI | B5: 001Nz000001TtoZIAS | C5: Suliman Almazyad | D5: 006Nz000001QhFFIA0 | E5: a1G4J000004jycyUAA | F5: Completed | G5: TRUE | H5: 45687 | I5: 45975 | J5: TRUE | K5: 45161 | L5: 2023-08-23T13:27:20.000+0000 | M5: 2024-08-15T16:03:46.000+0000 | N5: 0058d00000202rVAAQ | P5: =IF(I5>TODAY(),TRUE,FALSE) -> TRUE | Q5: =NOT(ISERROR(VLOOKUP(B5,'2. RTR with Tenant >1 != Vacatd'!A:A,1,FALSE))) -> FALSE | R5: =AND(P5=TRUE,Q5=TRUE) -> FALSE
A6: a1zNz00000004RpIAI | B6: 0014J00000biT5dQAE | C6: Test Mohamed | E6: a1G4J000004jynNUAQ | F6: Completed | G6: TRUE | H6: 45960 | I6: 45976 | J6: TRUE | K6: 45138 | L6: 2023-08-23T14:33:15.000+0000 | M6: 2024-08-15T16:03:46.000+0000 | N6: 0058d0000034Kn5AAE | P6: =IF(I6>TODAY(),TRUE,FALSE) -> TRUE | Q6: =NOT(ISERROR(VLOOKUP(B6,'2. RTR with Tenant >1 != Vacatd'!A:A,1,FALSE))) -> TRUE | R6: =AND(P6=TRUE,Q6=TRUE) -> TRUE
A7: a1zNz00000004hxIAA | B7: 0018d00000PSOIFAA5 | C7: Ugochukwu Maduanusi | D7: 006Nz000001ThvUIAS | E7: a1G8d0000004DBDEA2 | F7: Completed | G7: FALSE | I7: 45977 | J7: TRUE | K7: 45162 | L7: 2023-08-24T09:27:14.000+0000 | M7: 2023-09-04T12:26:08.000+0000 | N7: 0058d00000202rVAAQ | P7: =IF(I7>TODAY(),TRUE,FALSE) -> TRUE | Q7: =NOT(ISERROR(VLOOKUP(B7,'2. RTR with Tenant >1 != Vacatd'!A:A,1,FALSE))) -> FALSE | R7: =AND(P7=TRUE,Q7=TRUE) -> FALSE
A8: a1zNz00000004tFIAQ | B8: 001Nz000001sfwrIAA | C8: Chunjie Wu | D8: 006Nz0000018rmZIAQ | E8: a1G8d0000004DJvEAM | F8: Completed | G8: TRUE | H8: 45303 | I8: 45978 | J8: TRUE | K8: 45162 | L8: 2023-08-24T14:21:53.000+0000 | M8: 2023-09-04T12:27:05.000+0000 | N8: 0058d00000202rVAAQ | P8: =IF(I8>TODAY(),TRUE,FALSE) -> TRUE | Q8: =NOT(ISERROR(VLOOKUP(B8,'2. RTR with Tenant >1 != Vacatd'!A:A,1,FALSE))) -> FALSE | R8: =AND(P8=TRUE,Q8=TRUE) -> FALSE
A9: a1zNz000000052vIAA | B9: 001Nz000001sCWmIAM | C9: Amani Alattas | D9: 006Nz000001pK2bIAE | E9: a1G4J000004jynJUAQ | F9: In Progress | G9: TRUE | H9: 45261 | I9: 45597 | J9: TRUE | K9: 45163 | L9: 2023-08-25T08:13:09.000+0000 | M9: 2023-09-04T12:10:01.000+0000 | N9: 0058d00000202rVAAQ | P9: =IF(I9>TODAY(),TRUE,FALSE) -> FALSE | Q9: =NOT(ISERROR(VLOOKUP(B9,'2. RTR with Tenant >1 != Vacatd'!A:A,1,FALSE))) -> FALSE | R9: =AND(P9=TRUE,Q9=TRUE) -> FALSE
A10: a1zNz00000005FpIAI | B10: 001Nz000001qr1FIAQ | C10: Charmaine Kilonzo | D10: 006Nz000001nugPIAQ | E10: a1G4J000004jyekUAA | F10: Completed | G10: FALSE | I10: 45598 | J10: TRUE | K10: 45163 | L10: 2023-08-25T10:07:49.000+0000 | M10: 2024-08-15T16:03:46.000+0000 | N10: 0058d00000202rVAAQ | P10: =IF(I10>TODAY(),TRUE,FALSE) -> FALSE | Q10: =NOT(ISERROR(VLOOKUP(B10,'2. RTR with Tenant >1 != Vacatd'!A:A,1,FALSE))) -> FALSE | R10: =AND(P10=TRUE,Q10=TRUE) -> FALSE
A11: a1zNz0000000AtpIAE | B11: 001Nz000001oT7yIAE | C11: Hanan Alhasan | D11: 006Nz000001lSWjIAM | E11: a1G4J000004jyj6UAA | F11: Completed | G11: TRUE | H11: 45882 | I11: 45599 | J11: TRUE | K11: 45168 | L11: 2023-08-30T15:19:11.000+0000 | M11: 2024-08-15T16:03:46.000+0000 | N11: 0054J000006BkQgQAK | P11: =IF(I11>TODAY(),TRUE,FALSE) -> FALSE | Q11: =NOT(ISERROR(VLOOKUP(B11,'2. RTR with Tenant >1 != Vacatd'!A:A,1,FALSE))) -> FALSE | R11: =AND(P11=TRUE,Q11=TRUE) -> FALSE
A12: a1zNz0000000CxFIAU | B12: 001Nz000001oKXjIAM | C12: Fajer Alalawi | D12: 006Nz000001lKAxIAM | E12: a1G4J000004jypjUAA | F12: Completed | G12: TRUE | H12: 47118 | I12: 45600 | J12: TRUE | K12: 45169 | L12: 2023-08-31T09:58:16.000+0000 | M12: 2024-08-15T16:03:46.000+0000 | N12: 0054J000006BkQgQAK | P12: =IF(I12>TODAY(),TRUE,FALSE) -> FALSE | Q12: =NOT(ISERROR(VLOOKUP(B12,'2. RTR with Tenant >1 != Vacatd'!A:A,1,FALSE))) -> FALSE | R12: =AND(P12=TRUE,Q12=TRUE) -> FALSE
A13: a1zNz0000000FjpIAE | B13: 0018d000006WGGzAAO | C13: Afeke Hormeku | E13: a1G4J000004jyoWUAQ | F13: Completed | G13: TRUE | H13: 45519 | I13: 45601 | J13: TRUE | K13: 45169 | L13: 2023-09-01T12:11:29.000+0000 | M13: 2024-08-15T16:03:46.000+0000 | N13: 0058d0000034Kn5AAE | P13: =IF(I13>TODAY(),TRUE,FALSE) -> FALSE | Q13: =NOT(ISERROR(VLOOKUP(B13,'2. RTR with Tenant >1 != Vacatd'!A:A,1,FALSE))) -> FALSE | R13: =AND(P13=TRUE,Q13=TRUE) -> FALSE
A14: a1zNz0000000OdRIAU | B14: 001Nz000001XuIzIAK | C14: Jiaji Li | D14: 006Nz000001UfRlIAK | E14: a1G4J000004jyp9UAA | F14: Completed | G14: TRUE | H14: 45260 | I14: 45602 | J14: TRUE | K14: 45174 | L14: 2023-09-05T11:20:23.000+0000 | M14: 2023-09-05T11:21:25.000+0000 | N14: 0054J000006BkQgQAK | P14: =IF(I14>TODAY(),TRUE,FALSE) -> FALSE | Q14: =NOT(ISERROR(VLOOKUP(B14,'2. RTR with Tenant >1 != Vacatd'!A:A,1,FALSE))) -> FALSE | R14: =AND(P14=TRUE,Q14=TRUE) -> FALSE
A15: a1zNz0000000OdSIAU | B15: 001Nz000001jf9kIAA | C15: Ruoxi Leng | D15: 006Nz000001UfRlIAK | E15: a1G4J000004jyp9UAA | F15: Completed | G15: TRUE | H15: 45676 | I15: 45603 | J15: TRUE | L15: 2023-09-05T11:21:04.000+0000 | M15: 2024-08-15T16:03:46.000+0000 | N15: 0054J000006BkQgQAK | P15: =IF(I15>TODAY(),TRUE,FALSE) -> FALSE | Q15: =NOT(ISERROR(VLOOKUP(B15,'2. RTR with Tenant >1 != Vacatd'!A:A,1,FALSE))) -> FALSE | R15: =AND(P15=TRUE,Q15=TRUE) -> FALSE
A16: a1zNz0000000OjtIAE | B16: 001Nz000001yLfLIAU | C16: Abdulaziz Alkandari | D16: 006Nz000001vbbsIAA | E16: a1G4J000004jyvCUAQ | F16: Completed | G16: TRUE | H16: 45251 | I16: 45604 | J16: TRUE | K16: 45174 | L16: 2023-09-05T11:47:52.000+0000 | M16: 2023-09-05T11:48:13.000+0000 | N16: 0054J000006BkQgQAK | P16: =IF(I16>TODAY(),TRUE,FALSE) -> FALSE | Q16: =NOT(ISERROR(VLOOKUP(B16,'2. RTR with Tenant >1 != Vacatd'!A:A,1,FALSE))) -> FALSE | R16: =AND(P16=TRUE,Q16=TRUE) -> FALSE
A17: a1zNz0000000Po1IAE | B17: 001Nz000001pg3JIAQ | C17: Emilia Cole | D17: 006Nz000001mghBIAQ | E17: a1G4J000004jyu4UAA | F17: Completed | G17: FALSE | I17: 45605 | J17: TRUE | K17: 45175 | L17: 2023-09-06T11:14:58.000+0000 | M17: 2024-08-15T16:03:46.000+0000 | N17: 0054J000006BkQgQAK | P17: =IF(I17>TODAY(),TRUE,FALSE) -> FALSE | Q17: =NOT(ISERROR(VLOOKUP(B17,'2. RTR with Tenant >1 != Vacatd'!A:A,1,FALSE))) -> FALSE | R17: =AND(P17=TRUE,Q17=TRUE) -> FALSE
A18: a1zNz0000000PrFIAU | B18: 001Nz000001iSfxIAE | C18: Asina Kaya | D18: 006Nz000001f9oLIAQ | E18: a1G4J000004jyhFUAQ | F18: Completed | G18: TRUE | H18: 45253 | I18: 45606 | J18: TRUE | K18: 45175 | L18: 2023-09-06T12:37:46.000+0000 | M18: 2023-09-06T12:37:46.000+0000 | N18: 0054J000006BkQgQAK | P18: =IF(I18>TODAY(),TRUE,FALSE) -> FALSE | Q18: =NOT(ISERROR(VLOOKUP(B18,'2. RTR with Tenant >1 != Vacatd'!A:A,1,FALSE))) -> FALSE | R18: =AND(P18=TRUE,Q18=TRUE) -> FALSE
A19: a1zNz0000000PsrIAE | B19: 001Nz0000022xviIAA | C19: Hakki Kaya | D19: 006Nz000001f9oLIAQ | E19: a1G4J000004jyhFUAQ | F19: Completed | G19: TRUE | H19: 45253 | I19: 45607 | J19: TRUE | K19: 45175 | L19: 2023-09-06T12:38:27.000+0000 | M19: 2023-09-06T12:38:27.000+0000 | N19: 0054J000006BkQgQAK | P19: =IF(I19>TODAY(),TRUE,FALSE) -> FALSE | Q19: =NOT(ISERROR(VLOOKUP(B19,'2. RTR with Tenant >1 != Vacatd'!A:A,1,FALSE))) -> FALSE | R19: =AND(P19=TRUE,Q19=TRUE) -> FALSE
A20: a1zNz0000000T5FIAU | B20: 001Nz000002AOO6IAO | C20: Luke Tibbetts | D20: 006Nz000001TeJGIA0 | E20: a1G4J000004jymPUAQ | F20: Completed | G20: FALSE | I20: 45608 | J20: TRUE | K20: 45177 | L20: 2023-09-08T12:02:06.000+0000 | M20: 2024-08-15T16:03:46.000+0000 | N20: 0058d00000202rVAAQ | P20: =IF(I20>TODAY(),TRUE,FALSE) -> FALSE | Q20: =NOT(ISERROR(VLOOKUP(B20,'2. RTR with Tenant >1 != Vacatd'!A:A,1,FALSE))) -> FALSE | R20: =AND(P20=TRUE,Q20=TRUE) -> FALSE
A21: a1zNz0000000T6rIAE | B21: 001Nz000001WsmHIAS | C21: Richard Marshall | D21: 006Nz000001TeJGIA0 | E21: a1G4J000004jymPUAQ | F21: Completed | G21: FALSE | I21: 45609 | J21: TRUE | K21: 45177 | L21: 2023-09-08T12:03:20.000+0000 | M21: 2024-08-15T16:03:46.000+0000 | N21: 0058d00000202rVAAQ | P21: =IF(I21>TODAY(),TRUE,FALSE) -> FALSE | Q21: =NOT(ISERROR(VLOOKUP(B21,'2. RTR with Tenant >1 != Vacatd'!A:A,1,FALSE))) -> FALSE | R21: =AND(P21=TRUE,Q21=TRUE) -> FALSE
A22: a1zNz0000000Ue1IAE | B22: 001Nz000001WsJGIA0 | C22: Joseph Malik | E22: a1G4J000004jydcUAA | F22: Completed | G22: FALSE | I22: 45610 | J22: TRUE | K22: 45178 | L22: 2023-09-09T13:40:31.000+0000 | M22: 2024-08-15T16:03:46.000+0000 | N22: 0058d0000034Kn5AAE | P22: =IF(I22>TODAY(),TRUE,FALSE) -> FALSE | Q22: =NOT(ISERROR(VLOOKUP(B22,'2. RTR with Tenant >1 != Vacatd'!A:A,1,FALSE))) -> TRUE | R22: =AND(P22=TRUE,Q22=TRUE) -> FALSE
A23: a1zNz0000000UirIAE | B23: 001Nz000001Wz30IAC | C23: Matthew Hughes | E23: a1G4J000004jydcUAA | F23: Completed | G23: FALSE | I23: 45611 | J23: TRUE | K23: 45178 | L23: 2023-09-09T13:45:34.000+0000 | M23: 2024-08-15T16:03:46.000+0000 | N23: 0058d0000034Kn5AAE | P23: =IF(I23>TODAY(),TRUE,FALSE) -> FALSE | Q23: =NOT(ISERROR(VLOOKUP(B23,'2. RTR with Tenant >1 != Vacatd'!A:A,1,FALSE))) -> TRUE | R23: =AND(P23=TRUE,Q23=TRUE) -> FALSE
A24: a1zNz0000000WEQIA2 | B24: 001Nz000001rKODIA2 | C24: Sophie Tolson | D24: 006Nz000001mghBIAQ | E24: a1G4J000004jyu4UAA | F24: Completed | G24: FALSE | I24: 45612 | J24: TRUE | K24: 45180 | L24: 2023-09-11T08:30:00.000+0000 | M24: 2024-08-15T16:03:46.000+0000 | N24: 0054J000006BkQgQAK | P24: =IF(I24>TODAY(),TRUE,FALSE) -> FALSE | Q24: =NOT(ISERROR(VLOOKUP(B24,'2. RTR with Tenant >1 != Vacatd'!A:A,1,FALSE))) -> FALSE | R24: =AND(P24=TRUE,Q24=TRUE) -> FALSE
A25: a1zNz0000000WpVIAU | B25: 001Nz000001WsJGIA0 | C25: Joseph Malik | D25: 006Nz000001Tcz1IAC | E25: a1G4J000004jydcUAA | F25: Completed | G25: FALSE | I25: 45611 | J25: TRUE | K25: 45178 | L25: 2023-09-11T10:25:52.000+0000 | M25: 2024-08-15T16:03:46.000+0000 | N25: 0058d0000034Ks6AAE | P25: =IF(I25>TODAY(),TRUE,FALSE) -> FALSE | Q25: =NOT(ISERROR(VLOOKUP(B25,'2. RTR with Tenant >1 != Vacatd'!A:A,1,FALSE))) -> TRUE | R25: =AND(P25=TRUE,Q25=TRUE) -> FALSE
A26: a1zNz0000000Wr7IAE | B26: 001Nz000001Wz30IAC | C26: Matthew Hughes | D26: 006Nz000001Tcz1IAC | E26: a1G4J000004jydcUAA | F26: Completed | G26: FALSE | I26: 45611 | J26: TRUE | K26: 45178 | L26: 2023-09-11T10:27:20.000+0000 | M26: 2024-08-15T16:03:46.000+0000 | N26: 0058d0000034Ks6AAE | P26: =IF(I26>TODAY(),TRUE,FALSE) -> FALSE | Q26: =NOT(ISERROR(VLOOKUP(B26,'2. RTR with Tenant >1 != Vacatd'!A:A,1,FALSE))) -> TRUE | R26: =AND(P26=TRUE,Q26=TRUE) -> FALSE
A27: a1zNz0000000XATIA2 | B27: 0018d00000EjZsSAAV | C27: Fraser McKnespiey | D27: 006Nz000001TYFTIA4 | E27: a1G4J000004jyjwUAA | F27: Completed | G27: FALSE | I27: 45611 | J27: TRUE | K27: 45155 | L27: 2023-09-11T11:37:49.000+0000 | M27: 2024-08-15T16:03:46.000+0000 | N27: 0054J000006BkQgQAK | P27: =IF(I27>TODAY(),TRUE,FALSE) -> FALSE | Q27: =NOT(ISERROR(VLOOKUP(B27,'2. RTR with Tenant >1 != Vacatd'!A:A,1,FALSE))) -> FALSE | R27: =AND(P27=TRUE,Q27=TRUE) -> FALSE
A28: a1zNz0000000XC5IAM | B28: 001Nz000001WwGRIA0 | C28: Ellen Wright | D28: 006Nz000001TYFTIA4 | E28: a1G4J000004jyjwUAA | F28: Completed | G28: FALSE | I28: 45611 | J28: TRUE | K28: 45155 | L28: 2023-09-11T11:38:24.000+0000 | M28: 2024-08-15T16:03:46.000+0000 | N28: 0054J000006BkQgQAK | P28: =IF(I28>TODAY(),TRUE,FALSE) -> FALSE | Q28: =NOT(ISERROR(VLOOKUP(B28,'2. RTR with Tenant >1 != Vacatd'!A:A,1,FALSE))) -> FALSE | R28: =AND(P28=TRUE,Q28=TRUE) -> FALSE
A29: a1zNz0000000ZsDIAU | B29: 001Nz000001W5FKIA0 | C29: Cristina Ruiz de Loizaga Garcia | D29: 006Nz000001NHqqIAG | E29: a1G4J000004jyvRUAQ | F29: Completed | G29: TRUE | H29: 45595 | I29: 45611 | J29: TRUE | K29: 45181 | L29: 2023-09-12T12:12:29.000+0000 | M29: 2024-08-15T16:03:46.000+0000 | N29: 0054J000006BkQgQAK | P29: =IF(I29>TODAY(),TRUE,FALSE) -> FALSE | Q29: =NOT(ISERROR(VLOOKUP(B29,'2. RTR with Tenant >1 != Vacatd'!A:A,1,FALSE))) -> TRUE | R29: =AND(P29=TRUE,Q29=TRUE) -> FALSE
A30: a1zNz0000003kxZIAQ | B30: 0014J00000ZR2dfQAD | C30: Asmar Rzayeva | D30: 0064J00000FTju1QAD | E30: a1G4J0000025xSVUAY | F30: Completed | G30: TRUE | H30: 46107 | I30: 45611 | J30: TRUE | K30: 45191 | L30: 2023-09-22T12:01:22.000+0000 | M30: 2024-08-15T16:03:46.000+0000 | N30: 0058d0000034KskAAE | P30: =IF(I30>TODAY(),TRUE,FALSE) -> FALSE | Q30: =NOT(ISERROR(VLOOKUP(B30,'2. RTR with Tenant >1 != Vacatd'!A:A,1,FALSE))) -> FALSE | R30: =AND(P30=TRUE,Q30=TRUE) -> FALSE
A31: a1zNz0000003tkjIAA | B31: 001Nz000001iO7hIAE | C31: Jodi Meir | D31: 006Nz000001f3cUIAQ | E31: a1G4J0000025zLKUAY | F31: Completed | G31: FALSE | I31: 45611 | J31: TRUE | K31: 45192 | L31: 2023-09-23T16:56:37.000+0000 | M31: 2024-08-15T16:03:46.000+0000 | N31: 0054J000006BkQgQAK | P31: =IF(I31>TODAY(),TRUE,FALSE) -> FALSE | Q31: =NOT(ISERROR(VLOOKUP(B31,'2. RTR with Tenant >1 != Vacatd'!A:A,1,FALSE))) -> TRUE | R31: =AND(P31=TRUE,Q31=TRUE) -> FALSE
A32: a1zNz0000003tmLIAQ | B32: 001Nz000001jP9oIAE | C32: Ella Wilcock | D32: 006Nz000001f3cUIAQ | E32: a1G4J0000025zLKUAY | F32: Completed | G32: FALSE | I32: 45611 | J32: TRUE | K32: 45192 | L32: 2023-09-23T16:56:57.000+0000 | M32: 2024-08-15T16:03:46.000+0000 | N32: 0054J000006BkQgQAK | P32: =IF(I32>TODAY(),TRUE,FALSE) -> FALSE | Q32: =NOT(ISERROR(VLOOKUP(B32,'2. RTR with Tenant >1 != Vacatd'!A:A,1,FALSE))) -> FALSE | R32: =AND(P32=TRUE,Q32=TRUE) -> FALSE
A33: a1zNz00000050SPIAY | B33: 001Nz000002QXs4IAG | C33: Xingyu Tian | D33: 006Nz000002O2CYIA0 | E33: a1G4J000004jyrzUAA | F33: Completed | G33: TRUE | H33: 46782 | I33: 45611 | J33: TRUE | K33: 45194 | L33: 2023-09-25T16:56:32.000+0000 | M33: 2024-08-15T16:03:46.000+0000 | N33: 0054J000006BkQgQAK | P33: =IF(I33>TODAY(),TRUE,FALSE) -> FALSE | Q33: =NOT(ISERROR(VLOOKUP(B33,'2. RTR with Tenant >1 != Vacatd'!A:A,1,FALSE))) -> TRUE | R33: =AND(P33=TRUE,Q33=TRUE) -> FALSE
A34: a1zNz00000050U1IAI | B34: 001Nz000002SyHqIAK | C34: Ming Yue | D34: 006Nz000002O2CYIA0 | E34: a1G4J000004jyrzUAA | F34: Completed | G34: TRUE | H34: 46782 | I34: 45611 | J34: TRUE | K34: 45194 | L34: 2023-09-25T16:57:13.000+0000 | M34: 2024-08-15T16:03:46.000+0000 | N34: 0054J000006BkQgQAK | P34: =IF(I34>TODAY(),TRUE,FALSE) -> FALSE | Q34: =NOT(ISERROR(VLOOKUP(B34,'2. RTR with Tenant >1 != Vacatd'!A:A,1,FALSE))) -> FALSE | R34: =AND(P34=TRUE,Q34=TRUE) -> FALSE
A35: a1zNz0000005L5RIAU | B35: 001Nz0000022sfwIAA | C35: Luke Bulmer | D35: 006Nz0000020IDjIAM | E35: a1G4J0000025zS4UAI | F35: Completed | G35: FALSE | I35: 45611 | J35: TRUE | K35: 45195 | L35: 2023-09-26T09:57:46.000+0000 | M35: 2024-08-15T16:03:46.000+0000 | N35: 0054J000006BkQgQAK | P35: =IF(I35>TODAY(),TRUE,FALSE) -> FALSE | Q35: =NOT(ISERROR(VLOOKUP(B35,'2. RTR with Tenant >1 != Vacatd'!A:A,1,FALSE))) -> FALSE | R35: =AND(P35=TRUE,Q35=TRUE) -> FALSE
A36: a1zNz0000005L73IAE | B36: 001Nz000002Al1JIAS | C36: Erin Doughty | D36: 006Nz0000020IDjIAM | E36: a1G4J0000025zS4UAI | F36: Completed | G36: FALSE | I36: 45611 | J36: TRUE | K36: 45195 | L36: 2023-09-26T09:58:12.000+0000 | M36: 2024-08-15T16:03:46.000+0000 | N36: 0054J000006BkQgQAK | P36: =IF(I36>TODAY(),TRUE,FALSE) -> FALSE | Q36: =NOT(ISERROR(VLOOKUP(B36,'2. RTR with Tenant >1 != Vacatd'!A:A,1,FALSE))) -> FALSE | R36: =AND(P36=TRUE,Q36=TRUE) -> FALSE
A37: a1zNz0000005YM2IAM | B37: 001Nz000002WqITIA0 | C37: Michail Athinaios | D37: 006Nz000002SKCMIA4 | E37: a1GNz0000000w8sMAA | F37: Completed | G37: TRUE | H37: 45519 | I37: 45611 | J37: TRUE | K37: 45195 | L37: 2023-09-26T12:39:54.000+0000 | M37: 2024-08-15T16:03:46.000+0000 | N37: 0058d00000202rVAAQ | P37: =IF(I37>TODAY(),TRUE,FALSE) -> FALSE | Q37: =NOT(ISERROR(VLOOKUP(B37,'2. RTR with Tenant >1 != Vacatd'!A:A,1,FALSE))) -> FALSE | R37: =AND(P37=TRUE,Q37=TRUE) -> FALSE
A38: a1zNz0000005d3xIAA | B38: 001Nz000002UzxpIAC | C38: Rehekah Newey | D38: 006Nz000002SKCMIA4 | E38: a1GNz0000000w8sMAA | F38: Completed | G38: FALSE | I38: 45611 | J38: TRUE | K38: 45195 | L38: 2023-09-26T13:54:15.000+0000 | M38: 2024-08-15T16:03:46.000+0000 | N38: 0058d00000202rVAAQ | P38: =IF(I38>TODAY(),TRUE,FALSE) -> FALSE | Q38: =NOT(ISERROR(VLOOKUP(B38,'2. RTR with Tenant >1 != Vacatd'!A:A,1,FALSE))) -> FALSE | R38: =AND(P38=TRUE,Q38=TRUE) -> FALSE
A39: a1zNz0000005eWHIAY | B39: 001Nz000002aIYPIA2 | C39: Ian Kennedy | D39: 006Nz000002XVyOIAW | E39: a1GNz0000000vO5MAI | F39: Completed | G39: FALSE | I39: 45611 | J39: TRUE | K39: 45195 | L39: 2023-09-26T14:48:16.000+0000 | M39: 2024-08-15T16:03:46.000+0000 | N39: 0054J000006BkQgQAK | P39: =IF(I39>TODAY(),TRUE,FALSE) -> FALSE | Q39: =NOT(ISERROR(VLOOKUP(B39,'2. RTR with Tenant >1 != Vacatd'!A:A,1,FALSE))) -> FALSE | R39: =AND(P39=TRUE,Q39=TRUE) -> FALSE
A40: a1zNz0000005rwXIAQ | B40: 0018d00000IHd34AAD | C40: Elsie Appiah | D40: 006Nz0000012j3hIAA | E40: a1G4J0000025xZMUAY | F40: Completed | G40: TRUE | H40: 46728 | I40: 45611 | J40: TRUE | K40: 45196 | L40: 2023-09-27T07:49:50.000+0000 | M40: 2024-10-30T12:14:33.000+0000 | N40: 0058d0000020QoXAAU | P40: =IF(I40>TODAY(),TRUE,FALSE) -> FALSE | Q40: =NOT(ISERROR(VLOOKUP(B40,'2. RTR with Tenant >1 != Vacatd'!A:A,1,FALSE))) -> FALSE | R40: =AND(P40=TRUE,Q40=TRUE) -> FALSE
A41: a1zNz0000006MsHIAU | B41: 001Nz000002P3PpIAK | C41: Wenyu Shi | D41: 006Nz000002MZHNIA4 | E41: a1G4J000004jyokUAA | F41: Completed | G41: TRUE | H41: 45687 | I41: 45611 | J41: TRUE | K41: 45196 | L41: 2023-09-27T13:59:36.000+0000 | M41: 2024-08-15T16:03:46.000+0000 | N41: 0054J000006BkQgQAK | P41: =IF(I41>TODAY(),TRUE,FALSE) -> FALSE | Q41: =NOT(ISERROR(VLOOKUP(B41,'2. RTR with Tenant >1 != Vacatd'!A:A,1,FALSE))) -> FALSE | R41: =AND(P41=TRUE,Q41=TRUE) -> FALSE
A42: a1zNz0000006oIIIAY | B42: 001Nz000002PBvBIAW | C42: Malthe Winther | D42: 006Nz000002MeLqIAK | E42: a1G8d0000004XZPEA2 | F42: Completed | G42: TRUE | H42: 45563 | I42: 45611 | J42: TRUE | K42: 45197 | L42: 2023-09-28T11:39:32.000+0000 | M42: 2024-08-15T16:03:46.000+0000 | N42: 0054J000006BkQgQAK | P42: =IF(I42>TODAY(),TRUE,FALSE) -> FALSE | Q42: =NOT(ISERROR(VLOOKUP(B42,'2. RTR with Tenant >1 != Vacatd'!A:A,1,FALSE))) -> FALSE | R42: =AND(P42=TRUE,Q42=TRUE) -> FALSE
A43: a1zNz0000006zqPIAQ | B43: 001Nz000002cGyfIAE | C43: Jasmine Baker | D43: 006Nz000002ZRPBIA4 | F43: Completed | G43: FALSE | I43: 45611 | J43: TRUE | K43: 45197 | L43: 2023-09-28T15:06:40.000+0000 | M43: 2024-08-15T16:03:46.000+0000 | N43: 0058d00000202rVAAQ | P43: =IF(I43>TODAY(),TRUE,FALSE) -> FALSE | Q43: =NOT(ISERROR(VLOOKUP(B43,'2. RTR with Tenant >1 != Vacatd'!A:A,1,FALSE))) -> FALSE | R43: =AND(P43=TRUE,Q43=TRUE) -> FALSE
A44: a1zNz0000006zvFIAQ | B44: 001Nz000002SXrCIAW | C44: Alex Barker | D44: 006Nz000002Q0OGIA0 | E44: a1GNz0000000xXyMAI | F44: Completed | G44: FALSE | I44: 45611 | J44: TRUE | K44: 45197 | L44: 2023-09-28T15:13:40.000+0000 | M44: 2024-08-15T16:03:46.000+0000 | N44: 0054J000006BkQgQAK | P44: =IF(I44>TODAY(),TRUE,FALSE) -> FALSE | Q44: =NOT(ISERROR(VLOOKUP(B44,'2. RTR with Tenant >1 != Vacatd'!A:A,1,FALSE))) -> FALSE | R44: =AND(P44=TRUE,Q44=TRUE) -> FALSE
A45: a1zNz0000006zwrIAA | B45: 001Nz000002WepFIAS | C45: Marcelo Millan | D45: 006Nz000002Q0OGIA0 | E45: a1GNz0000000xXyMAI | F45: Completed | G45: FALSE | I45: 45611 | J45: TRUE | K45: 45197 | L45: 2023-09-28T15:15:29.000+0000 | M45: 2023-09-28T15:24:31.000+0000 | N45: 0054J000006BkQgQAK | P45: =IF(I45>TODAY(),TRUE,FALSE) -> FALSE | Q45: =NOT(ISERROR(VLOOKUP(B45,'2. RTR with Tenant >1 != Vacatd'!A:A,1,FALSE))) -> FALSE | R45: =AND(P45=TRUE,Q45=TRUE) -> FALSE
A46: a1zNz00000070EbIAI | B46: 001Nz000002eI3dIAE | C46: Maria Eduarda Claciano Donadi | D46: 006Nz000002bEULIA2 | E46: a1GNz0000000w7HMAQ | F46: Completed | G46: TRUE | H46: 46051 | I46: 45611 | J46: TRUE | K46: 45197 | L46: 2023-09-28T15:44:35.000+0000 | M46: 2024-08-15T16:03:46.000+0000 | N46: 0058d00000202rVAAQ | P46: =IF(I46>TODAY(),TRUE,FALSE) -> FALSE | Q46: =NOT(ISERROR(VLOOKUP(B46,'2. RTR with Tenant >1 != Vacatd'!A:A,1,FALSE))) -> FALSE | R46: =AND(P46=TRUE,Q46=TRUE) -> FALSE
A47: a1zNz00000070HpIAI | B47: 001Nz000002gBPMIA2 | C47: Joao Gustavo Castro Vieira | D47: 006Nz000002bEULIA2 | E47: a1GNz0000000w7HMAQ | F47: Completed | G47: TRUE | H47: 46213 | I47: 45611 | J47: TRUE | K47: 45197 | L47: 2023-09-28T15:45:44.000+0000 | M47: 2024-08-15T16:03:46.000+0000 | N47: 0058d00000202rVAAQ | P47: =IF(I47>TODAY(),TRUE,FALSE) -> FALSE | Q47: =NOT(ISERROR(VLOOKUP(B47,'2. RTR with Tenant >1 != Vacatd'!A:A,1,FALSE))) -> FALSE | R47: =AND(P47=TRUE,Q47=TRUE) -> FALSE
A48: a1zNz00000070T7IAI | B48: 001Nz000002OQxvIAG | C48: fFvo5LxykElHq0JjTewj 3mfLmPxGRI35UMmHJ1su | D48: 0068d000003s2p1AAA | E48: a1G4J0000025zFqUAI | F48: Completed | G48: TRUE | H48: 46447 | I48: 45611 | J48: TRUE | K48: 45197 | L48: 2023-09-28T15:56:55.000+0000 | M48: 2024-08-15T16:03:46.000+0000 | N48: 0058d0000034c7KAAQ | P48: =IF(I48>TODAY(),TRUE,FALSE) -> FALSE | Q48: =NOT(ISERROR(VLOOKUP(B48,'2. RTR with Tenant >1 != Vacatd'!A:A,1,FALSE))) -> FALSE | R48: =AND(P48=TRUE,Q48=TRUE) -> FALSE
A49: a1zNz00000070WLIAY | B49: 0018d00000WuEmkAAF | C49: Antony Farid | D49: 006Nz000002QAKNIA4 | E49: a1GNz0000000ygvMAA | F49: Completed | G49: TRUE | H49: 46095 | I49: 45611 | J49: TRUE | K49: 45197 | L49: 2023-09-28T16:00:28.000+0000 | M49: 2024-08-15T16:03:46.000+0000 | N49: 0058d00000202rVAAQ | P49: =IF(I49>TODAY(),TRUE,FALSE) -> FALSE | Q49: =NOT(ISERROR(VLOOKUP(B49,'2. RTR with Tenant >1 != Vacatd'!A:A,1,FALSE))) -> FALSE | R49: =AND(P49=TRUE,Q49=TRUE) -> FALSE
A50: a1zNz00000070g1IAA | B50: 0018d00000Jk8SEAAZ | C50: Irina Guseva | D50: 0068d000009hfhtAAA | E50: a1G4J0000025zSsUAI | F50: Completed | G50: TRUE | H50: 46918 | I50: 45611 | J50: TRUE | K50: 45197 | L50: 2023-09-28T16:39:37.000+0000 | M50: 2024-08-15T16:03:46.000+0000 | N50: 0058d0000034c7KAAQ | P50: =IF(I50>TODAY(),TRUE,FALSE) -> FALSE | Q50: =NOT(ISERROR(VLOOKUP(B50,'2. RTR with Tenant >1 != Vacatd'!A:A,1,FALSE))) -> TRUE | R50: =AND(P50=TRUE,Q50=TRUE) -> FALSE
A51: a1zNz00000070krIAA | B51: 001Nz000002SpRWIA0 | C51: EuUDGQTqMHt3lgrNEWhB ImZFTjoLEMpuwxi5o2XL | D51: 006Nz000002QFyOIAW | E51: a1GNz0000000wP0MAI | F51: Completed | G51: FALSE | I51: 45611 | J51: TRUE | K51: 45197 | L51: 2023-09-28T16:42:11.000+0000 | M51: 2024-08-15T16:03:46.000+0000 | N51: 0058d00000202rVAAQ | P51: =IF(I51>TODAY(),TRUE,FALSE) -> FALSE | Q51: =NOT(ISERROR(VLOOKUP(B51,'2. RTR with Tenant >1 != Vacatd'!A:A,1,FALSE))) -> FALSE | R51: =AND(P51=TRUE,Q51=TRUE) -> FALSE
A52: a1zNz00000072rVIAQ | B52: 001Nz000002WMnUIAW | C52: Fahad Almutairi | D52: 006Nz000002Td1mIAC | E52: a1G8d0000004DCaEAM | F52: Completed | G52: TRUE | H52: 45237 | I52: 45611 | J52: TRUE | K52: 45198 | L52: 2023-09-29T07:31:54.000+0000 | M52: 2023-09-29T07:31:54.000+0000 | N52: 0058d00000202rVAAQ | P52: =IF(I52>TODAY(),TRUE,FALSE) -> FALSE | Q52: =NOT(ISERROR(VLOOKUP(B52,'2. RTR with Tenant >1 != Vacatd'!A:A,1,FALSE))) -> FALSE | R52: =AND(P52=TRUE,Q52=TRUE) -> FALSE
A53: a1zNz00000072t7IAA | B53: 001Nz000002d2gkIAA | C53: Mohammed Almutairi | D53: 006Nz000002Td1mIAC | E53: a1G8d0000004DCaEAM | F53: Completed | G53: TRUE | H53: 45237 | I53: 45611 | J53: TRUE | K53: 45198 | L53: 2023-09-29T07:32:56.000+0000 | M53: 2023-09-29T07:32:56.000+0000 | N53: 0058d00000202rVAAQ | P53: =IF(I53>TODAY(),TRUE,FALSE) -> FALSE | Q53: =NOT(ISERROR(VLOOKUP(B53,'2. RTR with Tenant >1 != Vacatd'!A:A,1,FALSE))) -> FALSE | R53: =AND(P53=TRUE,Q53=TRUE) -> FALSE
A54: a1zNz00000073h7IAA | B54: 0018d00000JkBPhAAN | C54: Nadya Xintian | E54: a1G8d0000004DGhEAM | F54: Completed | G54: TRUE | H54: 45687 | I54: 45611 | J54: TRUE | K54: 45198 | L54: 2023-09-29T09:05:19.000+0000 | M54: 2024-08-15T16:03:46.000+0000 | N54: 0054J000004vm8VQAQ | P54: =IF(I54>TODAY(),TRUE,FALSE) -> FALSE | Q54: =NOT(ISERROR(VLOOKUP(B54,'2. RTR with Tenant >1 != Vacatd'!A:A,1,FALSE))) -> TRUE | R54: =AND(P54=TRUE,Q54=TRUE) -> FALSE
A55: a1zNz00000074GbIAI | B55: 001Nz000002aY0aIAE | C55: Nathan Stocks | D55: 006Nz000002XjJpIAK | E55: a1GNz0000000xGDMAY | F55: Completed | G55: FALSE | I55: 45611 | J55: TRUE | K55: 45198 | L55: 2023-09-29T09:50:36.000+0000 | M55: 2024-08-15T16:03:46.000+0000 | N55: 0058d00000202rVAAQ | P55: =IF(I55>TODAY(),TRUE,FALSE) -> FALSE | Q55: =NOT(ISERROR(VLOOKUP(B55,'2. RTR with Tenant >1 != Vacatd'!A:A,1,FALSE))) -> FALSE | R55: =AND(P55=TRUE,Q55=TRUE) -> FALSE
A56: a1zNz00000074jdIAA | B56: 001Nz000001y4HxIAI | C56: Miriam Shan | D56: 006Nz000001vKhcIAE | E56: a1GNz0000000wC5MAI | F56: Completed | G56: FALSE | I56: 45611 | J56: TRUE | K56: 45198 | L56: 2023-09-29T10:40:47.000+0000 | M56: 2024-08-15T16:03:46.000+0000 | N56: 0058d00000202rVAAQ | P56: =IF(I56>TODAY(),TRUE,FALSE) -> FALSE | Q56: =NOT(ISERROR(VLOOKUP(B56,'2. RTR with Tenant >1 != Vacatd'!A:A,1,FALSE))) -> FALSE | R56: =AND(P56=TRUE,Q56=TRUE) -> FALSE
A57: a1zNz00000076YXIAY | B57: 001Nz000002ZvNJIA0 | C57: Mahammad Aldaihani | D57: 006Nz000002X5O3IAK | E57: a1G8d0000004DBXEA2 | F57: Completed | G57: TRUE | H57: 45276 | I57: 45611 | J57: TRUE | K57: 45198 | L57: 2023-09-29T13:46:41.000+0000 | M57: 2023-09-29T13:46:41.000+0000 | N57: 0058d00000202rVAAQ | P57: =IF(I57>TODAY(),TRUE,FALSE) -> FALSE | Q57: =NOT(ISERROR(VLOOKUP(B57,'2. RTR with Tenant >1 != Vacatd'!A:A,1,FALSE))) -> FALSE | R57: =AND(P57=TRUE,Q57=TRUE) -> FALSE
A58: a1zNz00000076a9IAA | B58: 001Nz000002cXuhIAE | C58: Abdulmalek Alsaleh | D58: 006Nz000002X5O3IAK | E58: a1G8d0000004DBXEA2 | F58: Completed | G58: TRUE | H58: 45277 | I58: 45611 | J58: TRUE | K58: 45198 | L58: 2023-09-29T13:47:36.000+0000 | M58: 2023-09-29T13:47:36.000+0000 | N58: 0058d00000202rVAAQ | P58: =IF(I58>TODAY(),TRUE,FALSE) -> FALSE | Q58: =NOT(ISERROR(VLOOKUP(B58,'2. RTR with Tenant >1 != Vacatd'!A:A,1,FALSE))) -> FALSE | R58: =AND(P58=TRUE,Q58=TRUE) -> FALSE
A59: a1zNz00000076iDIAQ | B59: 001Nz000002c8wHIAQ | C59: Fahad Alotaibi | D59: 006Nz000002ZJt3IAG | E59: a1G4J000004jyvbUAA | F59: Completed | G59: TRUE | H59: 45579 | I59: 45611 | J59: TRUE | K59: 45198 | L59: 2023-09-29T14:09:00.000+0000 | M59: 2024-08-15T16:03:46.000+0000 | N59: 0058d00000202rVAAQ | P59: =IF(I59>TODAY(),TRUE,FALSE) -> FALSE | Q59: =NOT(ISERROR(VLOOKUP(B59,'2. RTR with Tenant >1 != Vacatd'!A:A,1,FALSE))) -> FALSE | R59: =AND(P59=TRUE,Q59=TRUE) -> FALSE
A60: a1zNz00000076v7IAA | B60: 001Nz000002QZQnIAO | C60: Abhilasha Kakkar | D60: 006Nz000002O3WfIAK | E60: a1G4J000004jyqlUAA | F60: Completed | G60: FALSE | I60: 45611 | J60: TRUE | K60: 45198 | L60: 2023-09-29T14:24:07.000+0000 | M60: 2024-08-15T16:03:46.000+0000 | N60: 0058d00000202rVAAQ | P60: =IF(I60>TODAY(),TRUE,FALSE) -> FALSE | Q60: =NOT(ISERROR(VLOOKUP(B60,'2. RTR with Tenant >1 != Vacatd'!A:A,1,FALSE))) -> FALSE | R60: =AND(P60=TRUE,Q60=TRUE) -> FALSE
A61: a1zNz00000078SHIAY | B61: 001Nz000001wsyjIAA | C61: Adewale Adegoke | D61: 006Nz000001u4q3IAA | E61: a1GNz0000000xZZMAY | F61: Completed | G61: TRUE | H61: 45321 | I61: 45611 | J61: TRUE | K61: 45198 | L61: 2023-09-29T16:33:01.000+0000 | M61: 2023-09-29T16:38:47.000+0000 | N61: 0054J000006BkQgQAK | P61: =IF(I61>TODAY(),TRUE,FALSE) -> FALSE | Q61: =NOT(ISERROR(VLOOKUP(B61,'2. RTR with Tenant >1 != Vacatd'!A:A,1,FALSE))) -> FALSE | R61: =AND(P61=TRUE,Q61=TRUE) -> FALSE
A62: a1zNz00000078TtIAI | B62: 001Nz000002gvK8IAI | C62: Ademide Olukoya | D62: 006Nz000001u4q3IAA | E62: a1GNz0000000xZZMAY | F62: Completed | G62: TRUE | H62: 45321 | I62: 45611 | J62: TRUE | K62: 45198 | L62: 2023-09-29T16:37:46.000+0000 | M62: 2023-10-03T16:52:02.000+0000 | N62: 0054J000006BkQgQAK | P62: =IF(I62>TODAY(),TRUE,FALSE) -> FALSE | Q62: =NOT(ISERROR(VLOOKUP(B62,'2. RTR with Tenant >1 != Vacatd'!A:A,1,FALSE))) -> FALSE | R62: =AND(P62=TRUE,Q62=TRUE) -> FALSE
A63: a1zNz00000078fBIAQ | B63: 001Nz0000024AEBIA2 | C63: Gillian Muchedzi | D63: 006Nz0000021eDcIAI | E63: a1GNz0000000vuMMAQ | F63: Completed | G63: FALSE | I63: 45611 | J63: TRUE | K63: 45198 | L63: 2023-09-29T17:01:52.000+0000 | M63: 2024-08-15T16:03:46.000+0000 | N63: 0054J000006BkQgQAK | P63: =IF(I63>TODAY(),TRUE,FALSE) -> FALSE | Q63: =NOT(ISERROR(VLOOKUP(B63,'2. RTR with Tenant >1 != Vacatd'!A:A,1,FALSE))) -> FALSE | R63: =AND(P63=TRUE,Q63=TRUE) -> FALSE
A64: a1zNz0000007I0DIAU | B64: 001Nz000001WrtRIAS | C64: Zowie King | D64: 006Nz000001TdevIAC | E64: a1G4J0000025zJMUAY | F64: Completed | G64: FALSE | I64: 45611 | J64: TRUE | K64: 45199 | L64: 2023-09-30T13:44:05.000+0000 | M64: 2024-08-15T16:03:46.000+0000 | N64: 005Nz000000R0K6IAK | P64: =IF(I64>TODAY(),TRUE,FALSE) -> FALSE | Q64: =NOT(ISERROR(VLOOKUP(B64,'2. RTR with Tenant >1 != Vacatd'!A:A,1,FALSE))) -> FALSE | R64: =AND(P64=TRUE,Q64=TRUE) -> FALSE
A65: a1zNz0000008JIQIA2 | B65: 001Nz000002WgnnIAC | C65: Megan Gilliver | D65: 006Nz000002U0B8IAK | E65: a1GNz0000000xo5MAA | F65: Completed | G65: FALSE | I65: 45611 | J65: TRUE | K65: 45201 | L65: 2023-10-02T12:07:29.000+0000 | M65: 2024-08-15T16:03:46.000+0000 | N65: 0058d00000202rVAAQ | P65: =IF(I65>TODAY(),TRUE,FALSE) -> FALSE | Q65: =NOT(ISERROR(VLOOKUP(B65,'2. RTR with Tenant >1 != Vacatd'!A:A,1,FALSE))) -> FALSE | R65: =AND(P65=TRUE,Q65=TRUE) -> FALSE
A66: a1zNz0000008JK1IAM | B66: 001Nz000002R9hBIAS | C66: r1Gt6gkZ0EAT6uU58YIy TGprb8rk6bfsMTR0VSD4 | D66: 006Nz000002OcCfIAK | E66: a1G4J000004jyjzUAA | F66: Completed | G66: TRUE | H66: 45772 | I66: 45611 | J66: TRUE | K66: 45201 | L66: 2023-10-02T11:14:04.000+0000 | M66: 2024-08-15T16:03:46.000+0000 | N66: 0058d00000202rVAAQ | P66: =IF(I66>TODAY(),TRUE,FALSE) -> FALSE | Q66: =NOT(ISERROR(VLOOKUP(B66,'2. RTR with Tenant >1 != Vacatd'!A:A,1,FALSE))) -> FALSE | R66: =AND(P66=TRUE,Q66=TRUE) -> FALSE
A67: a1zNz00000095JpIAI | B67: 001Nz000002RDeNIAW | C67: gVcFvfyrV8jNsHt9Vf1X MxYaNpgylHRkz9GNCnmg | D67: 006Nz000002OfSMIA0 | E67: a1G8d0000004XgtEAE | F67: Completed | G67: TRUE | H67: 46656 | I67: 45611 | J67: FALSE | K67: 45202 | L67: 2023-10-03T12:20:45.000+0000 | M67: 2023-10-03T12:20:45.000+0000 | N67: 0058d00000202rVAAQ | P67: =IF(I67>TODAY(),TRUE,FALSE) -> FALSE | Q67: =NOT(ISERROR(VLOOKUP(B67,'2. RTR with Tenant >1 != Vacatd'!A:A,1,FALSE))) -> FALSE | R67: =AND(P67=TRUE,Q67=TRUE) -> FALSE
A68: a1zNz0000009DqrIAE | B68: 0018d00000G1h8uAAB | C68: Saeed Arabloo | D68: 006Nz000002f09OIAQ | E68: a1G4J0000025zRHUAY | F68: Completed | G68: TRUE | H68: 47041 | I68: 45611 | J68: TRUE | K68: 45202 | L68: 2023-10-03T17:01:59.000+0000 | M68: 2024-08-15T16:03:46.000+0000 | N68: 0054J000006BkQgQAK | P68: =IF(I68>TODAY(),TRUE,FALSE) -> FALSE | Q68: =NOT(ISERROR(VLOOKUP(B68,'2. RTR with Tenant >1 != Vacatd'!A:A,1,FALSE))) -> FALSE | R68: =AND(P68=TRUE,Q68=TRUE) -> FALSE
A69: a1zNz0000009DsTIAU | B69: 0018d00000G1ldjAAB | C69: Zahra Poorya | D69: 006Nz000002f09OIAQ | E69: a1G4J0000025zRHUAY | F69: Completed | G69: TRUE | H69: 45321 | I69: 45611 | J69: TRUE | K69: 45202 | L69: 2023-10-03T17:02:40.000+0000 | M69: 2023-10-03T17:02:40.000+0000 | N69: 0054J000006BkQgQAK | P69: =IF(I69>TODAY(),TRUE,FALSE) -> FALSE | Q69: =NOT(ISERROR(VLOOKUP(B69,'2. RTR with Tenant >1 != Vacatd'!A:A,1,FALSE))) -> FALSE | R69: =AND(P69=TRUE,Q69=TRUE) -> FALSE
A70: a1zNz0000009V2zIAE | B70: 0018d000006YjbpAAC | C70: Mohammed Munaf | D70: 006Nz000002dJGCIA2 | E70: a1G4J0000025zT3UAI | F70: Completed | G70: FALSE | I70: 45611 | J70: TRUE | K70: 45203 | L70: 2023-10-04T08:24:18.000+0000 | M70: 2024-08-15T16:03:46.000+0000 | N70: 0054J000006BkQgQAK | P70: =IF(I70>TODAY(),TRUE,FALSE) -> FALSE | Q70: =NOT(ISERROR(VLOOKUP(B70,'2. RTR with Tenant >1 != Vacatd'!A:A,1,FALSE))) -> FALSE | R70: =AND(P70=TRUE,Q70=TRUE) -> FALSE
A71: a1zNz0000009WYXIA2 | B71: 001Nz000002qoCTIAY | C71: Emmanouil Nektarios Kalligeris | D71: 006Nz000002mionIAA | E71: a1GNz0000000xRWMAY | F71: Completed | G71: TRUE | H71: 46315 | I71: 45611 | J71: TRUE | K71: 45203 | L71: 2023-10-04T08:57:15.000+0000 | M71: 2024-08-15T16:03:46.000+0000 | N71: 0058d00000202rVAAQ | P71: =IF(I71>TODAY(),TRUE,FALSE) -> FALSE | Q71: =NOT(ISERROR(VLOOKUP(B71,'2. RTR with Tenant >1 != Vacatd'!A:A,1,FALSE))) -> FALSE | R71: =AND(P71=TRUE,Q71=TRUE) -> FALSE
A72: a1zNz0000009mtRIAQ | B72: 0014J00000WrgJsQAJ | C72: Pooja Patel | D72: 006Nz000000rZm2IAE | E72: a1G4J0000025z24UAA | F72: Completed | G72: TRUE | H72: 46419 | I72: 45611 | J72: TRUE | K72: 45203 | L72: 2023-10-04T12:30:31.000+0000 | M72: 2024-08-15T16:03:46.000+0000 | N72: 005Nz000000R0K6IAK | P72: =IF(I72>TODAY(),TRUE,FALSE) -> FALSE | Q72: =NOT(ISERROR(VLOOKUP(B72,'2. RTR with Tenant >1 != Vacatd'!A:A,1,FALSE))) -> FALSE | R72: =AND(P72=TRUE,Q72=TRUE) -> FALSE
A73: a1zNz0000009pOIIAY | B73: 001Nz000002cJWoIAM | C73: Mitchell Hayes | D73: 006Nz000002ZULWIA4 | E73: a1G4J0000025zF9UAI | F73: Completed | G73: FALSE | I73: 45611 | J73: TRUE | K73: 45203 | L73: 2023-10-04T13:05:48.000+0000 | M73: 2024-08-15T16:03:46.000+0000 | N73: 0054J000006BkQgQAK | P73: =IF(I73>TODAY(),TRUE,FALSE) -> FALSE | Q73: =NOT(ISERROR(VLOOKUP(B73,'2. RTR with Tenant >1 != Vacatd'!A:A,1,FALSE))) -> FALSE | R73: =AND(P73=TRUE,Q73=TRUE) -> FALSE
A74: a1zNz0000009pOJIAY | B74: 001Nz000002gdwgIAA | C74: Melissa Walpole | D74: 006Nz000002ZULWIA4 | E74: a1G4J0000025zF9UAI | F74: Completed | G74: TRUE | H74: 45884 | I74: 45611 | J74: TRUE | K74: 45203 | L74: 2023-10-04T13:06:40.000+0000 | M74: 2024-08-15T16:03:46.000+0000 | N74: 0054J000006BkQgQAK | P74: =IF(I74>TODAY(),TRUE,FALSE) -> FALSE | Q74: =NOT(ISERROR(VLOOKUP(B74,'2. RTR with Tenant >1 != Vacatd'!A:A,1,FALSE))) -> FALSE | R74: =AND(P74=TRUE,Q74=TRUE) -> FALSE
A75: a1zNz000000AGZmIAO | B75: 001Nz000002gxk5IAA | C75: Oscar E. Mendoza | D75: 006Nz000002diwDIAQ | E75: a1G4J0000025zLxUAI | F75: Completed | G75: TRUE | H75: 45570 | I75: 45611 | J75: TRUE | K75: 45204 | L75: 2023-10-05T09:14:17.000+0000 | M75: 2024-08-15T16:03:46.000+0000 | N75: 0054J000006BkQgQAK | P75: =IF(I75>TODAY(),TRUE,FALSE) -> FALSE | Q75: =NOT(ISERROR(VLOOKUP(B75,'2. RTR with Tenant >1 != Vacatd'!A:A,1,FALSE))) -> FALSE | R75: =AND(P75=TRUE,Q75=TRUE) -> FALSE
A76: a1zNz000000AIzlIAG | B76: 0014J00000VvUXXQA3 | C76: Yuri Mejia | D76: 006Nz000002diwDIAQ | E76: a1G4J0000025zLxUAI | F76: Completed | G76: TRUE | H76: 45606 | I76: 45611 | J76: TRUE | K76: 45204 | L76: 2023-10-05T09:13:41.000+0000 | M76: 2024-08-15T16:03:46.000+0000 | N76: 0054J000006BkQgQAK | P76: =IF(I76>TODAY(),TRUE,FALSE) -> FALSE | Q76: =NOT(ISERROR(VLOOKUP(B76,'2. RTR with Tenant >1 != Vacatd'!A:A,1,FALSE))) -> FALSE | R76: =AND(P76=TRUE,Q76=TRUE) -> FALSE
A77: a1zNz000000ALWGIA4 | B77: 001Nz00000245zHIAQ | C77: Minxuan He | D77: 006Nz0000021XbxIAE | E77: a1GNz0000000xpjMAA | F77: Completed | G77: TRUE | H77: 45317 | I77: 45611 | J77: TRUE | K77: 45204 | L77: 2023-10-05T10:31:31.000+0000 | M77: 2023-10-05T10:31:31.000+0000 | N77: 0054J000006BkQgQAK | P77: =IF(I77>TODAY(),TRUE,FALSE) -> FALSE | Q77: =NOT(ISERROR(VLOOKUP(B77,'2. RTR with Tenant >1 != Vacatd'!A:A,1,FALSE))) -> FALSE | R77: =AND(P77=TRUE,Q77=TRUE) -> FALSE
A78: a1zNz000000AMs6IAG | B78: 001Nz000002aAkZIAU | C78: Cameron Fairburn | D78: 006Nz000002XMLdIAO | E78: a1GNz0000000yfKMAQ | F78: Completed | G78: FALSE | I78: 45611 | J78: TRUE | K78: 45204 | L78: 2023-10-05T10:02:20.000+0000 | M78: 2024-08-15T16:03:46.000+0000 | N78: 0058d00000202rVAAQ | P78: =IF(I78>TODAY(),TRUE,FALSE) -> FALSE | Q78: =NOT(ISERROR(VLOOKUP(B78,'2. RTR with Tenant >1 != Vacatd'!A:A,1,FALSE))) -> FALSE | R78: =AND(P78=TRUE,Q78=TRUE) -> FALSE
A79: a1zNz000000AWWUIA4 | B79: 001Nz000002k8XkIAI | C79: Ifeoluwa Flora Dada | D79: 006Nz000002gixyIAA | E79: a1GNz0000000vERMAY | F79: Completed | G79: TRUE | H79: 46980 | I79: 45611 | J79: TRUE | K79: 45204 | L79: 2023-10-05T12:33:11.000+0000 | M79: 2024-08-15T16:03:46.000+0000 | N79: 0054J000006BkQgQAK | P79: =IF(I79>TODAY(),TRUE,FALSE) -> FALSE | Q79: =NOT(ISERROR(VLOOKUP(B79,'2. RTR with Tenant >1 != Vacatd'!A:A,1,FALSE))) -> FALSE | R79: =AND(P79=TRUE,Q79=TRUE) -> FALSE
A80: a1zNz000000AXSXIA4 | B80: 001Nz000002kWi5IAE | C80: Omolayo Pelumi Adetunji | D80: 006Nz000002gixyIAA | E80: a1GNz0000000vERMAY | F80: Completed | G80: TRUE | H80: 46980 | I80: 45611 | J80: TRUE | K80: 45204 | L80: 2023-10-05T12:34:48.000+0000 | M80: 2024-08-15T16:03:46.000+0000 | N80: 0054J000006BkQgQAK | P80: =IF(I80>TODAY(),TRUE,FALSE) -> FALSE | Q80: =NOT(ISERROR(VLOOKUP(B80,'2. RTR with Tenant >1 != Vacatd'!A:A,1,FALSE))) -> FALSE | R80: =AND(P80=TRUE,Q80=TRUE) -> FALSE
A81: a1zNz000000AYWfIAO | B81: 001Nz000002hBVJIA2 | C81: Im5dZnpW0fEy6NFF8CS9 9eAhC7tr8WOSHH0S9TY4 | D81: 006Nz000002e2YEIAY | E81: a1GNz0000000w8rMAA | F81: Completed | G81: TRUE | H81: 46059 | I81: 45611 | J81: TRUE | K81: 45204 | L81: 2023-10-05T12:45:53.000+0000 | M81: 2024-08-15T16:03:46.000+0000 | N81: 0054J000006BkQgQAK | P81: =IF(I81>TODAY(),TRUE,FALSE) -> FALSE | Q81: =NOT(ISERROR(VLOOKUP(B81,'2. RTR with Tenant >1 != Vacatd'!A:A,1,FALSE))) -> FALSE | R81: =AND(P81=TRUE,Q81=TRUE) -> FALSE
A82: a1zNz000000AZffIAG | B82: 001Nz000002eTtVIAU | C82: Lesley Young | D82: 006Nz000002XMLdIAO | E82: a1GNz0000000yfKMAQ | F82: Completed | G82: FALSE | I82: 45611 | J82: TRUE | K82: 45204 | L82: 2023-10-05T13:52:37.000+0000 | M82: 2024-08-15T16:03:46.000+0000 | N82: 0058d00000202rVAAQ | P82: =IF(I82>TODAY(),TRUE,FALSE) -> FALSE | Q82: =NOT(ISERROR(VLOOKUP(B82,'2. RTR with Tenant >1 != Vacatd'!A:A,1,FALSE))) -> FALSE | R82: =AND(P82=TRUE,Q82=TRUE) -> FALSE
A83: a1zNz000000AbSxIAK | B83: 001Nz000002pDJuIAM | C83: Suzanne Bradley | D83: 006Nz000002lChMIAU | E83: a1G4J0000025wYMUAY | F83: Completed | G83: FALSE | I83: 45611 | J83: TRUE | K83: 45209 | L83: 2023-10-05T13:40:08.000+0000 | M83: 2024-08-15T16:03:46.000+0000 | N83: 0058d0000043ssPAAQ | P83: =IF(I83>TODAY(),TRUE,FALSE) -> FALSE | Q83: =NOT(ISERROR(VLOOKUP(B83,'2. RTR with Tenant >1 != Vacatd'!A:A,1,FALSE))) -> FALSE | R83: =AND(P83=TRUE,Q83=TRUE) -> FALSE
A84: a1zNz000000AdUjIAK | B84: 001Nz000001XrbHIAS | C84: Ben McCabe | D84: 006Nz000002lChMIAU | E84: a1G4J0000025wYMUAY | F84: Completed | G84: FALSE | I84: 45611 | J84: FALSE | K84: 45204 | L84: 2023-10-05T13:39:36.000+0000 | M84: 2023-10-06T08:12:09.000+0000 | N84: 0058d0000043ssPAAQ | P84: =IF(I84>TODAY(),TRUE,FALSE) -> FALSE | Q84: =NOT(ISERROR(VLOOKUP(B84,'2. RTR with Tenant >1 != Vacatd'!A:A,1,FALSE))) -> FALSE | R84: =AND(P84=TRUE,Q84=TRUE) -> FALSE
A85: a1zNz000000AdWLIA0 | B85: 001Nz000002pXKAIA2 | C85: Ema Almeida | D85: 006Nz000002lChMIAU | E85: a1G4J0000025wYMUAY | F85: Completed | G85: TRUE | H85: 45944 | I85: 45611 | J85: FALSE | K85: 45204 | L85: 2023-10-05T13:40:37.000+0000 | M85: 2023-10-10T15:26:15.000+0000 | N85: 0058d0000043ssPAAQ | P85: =IF(I85>TODAY(),TRUE,FALSE) -> FALSE | Q85: =NOT(ISERROR(VLOOKUP(B85,'2. RTR with Tenant >1 != Vacatd'!A:A,1,FALSE))) -> FALSE | R85: =AND(P85=TRUE,Q85=TRUE) -> FALSE
A86: a1zNz000000AeSPIA0 | B86: 001Nz000002rHKwIAM | C86: Jess Tilley | D86: 006Nz000002n7QdIAI | E86: a1G4J0000025xkKUAQ | F86: Completed | G86: FALSE | I86: 45611 | J86: FALSE | K86: 45204 | L86: 2023-10-05T13:47:43.000+0000 | M86: 2023-10-06T08:15:46.000+0000 | N86: 0058d0000043ssPAAQ | P86: =IF(I86>TODAY(),TRUE,FALSE) -> FALSE | Q86: =NOT(ISERROR(VLOOKUP(B86,'2. RTR with Tenant >1 != Vacatd'!A:A,1,FALSE))) -> TRUE | R86: =AND(P86=TRUE,Q86=TRUE) -> FALSE
A87: a1zNz000000AeU1IAK | B87: 001Nz000002rLgQIAU | C87: Matthew Birkett | D87: 006Nz000002n7QdIAI | E87: a1G4J0000025xkKUAQ | F87: Completed | G87: FALSE | I87: 45611 | J87: FALSE | K87: 45204 | L87: 2023-10-05T13:48:43.000+0000 | M87: 2023-10-06T08:16:41.000+0000 | N87: 0058d0000043ssPAAQ | P87: =IF(I87>TODAY(),TRUE,FALSE) -> FALSE | Q87: =NOT(ISERROR(VLOOKUP(B87,'2. RTR with Tenant >1 != Vacatd'!A:A,1,FALSE))) -> TRUE | R87: =AND(P87=TRUE,Q87=TRUE) -> FALSE
A88: a1zNz000000AesDIAS | B88: 001Nz000002tRzMIAU | C88: Adam McCrum | D88: 006Nz000002oZawIAE | E88: a1G4J0000025xuQUAQ | F88: Completed | G88: FALSE | I88: 45611 | J88: FALSE | K88: 45204 | L88: 2023-10-05T13:53:28.000+0000 | M88: 2023-10-10T11:16:58.000+0000 | N88: 0058d0000043ssPAAQ | P88: =IF(I88>TODAY(),TRUE,FALSE) -> FALSE | Q88: =NOT(ISERROR(VLOOKUP(B88,'2. RTR with Tenant >1 != Vacatd'!A:A,1,FALSE))) -> FALSE | R88: =AND(P88=TRUE,Q88=TRUE) -> FALSE
A89: a1zNz000000AetpIAC | B89: 001Nz000002k7q9IAA | C89: Sam Collins | D89: 006Nz000002oZawIAE | E89: a1G4J0000025xuQUAQ | F89: Completed | G89: FALSE | I89: 45611 | J89: FALSE | K89: 45204 | L89: 2023-10-05T13:53:46.000+0000 | M89: 2023-10-09T11:21:48.000+0000 | N89: 0058d0000043ssPAAQ | P89: =IF(I89>TODAY(),TRUE,FALSE) -> FALSE | Q89: =NOT(ISERROR(VLOOKUP(B89,'2. RTR with Tenant >1 != Vacatd'!A:A,1,FALSE))) -> FALSE | R89: =AND(P89=TRUE,Q89=TRUE) -> FALSE
A90: a1zNz000000AgHJIA0 | B90: 001Nz0000021Bl4IAE | C90: Jiaxuan Bi | D90: 006Nz000001yYeBIAU | E90: a1GNz0000000xsxMAA | F90: Completed | G90: FALSE | I90: 45611 | J90: TRUE | K90: 45204 | L90: 2023-10-05T14:09:43.000+0000 | M90: 2023-10-05T14:09:43.000+0000 | N90: 0058d00000202rVAAQ | P90: =IF(I90>TODAY(),TRUE,FALSE) -> FALSE | Q90: =NOT(ISERROR(VLOOKUP(B90,'2. RTR with Tenant >1 != Vacatd'!A:A,1,FALSE))) -> FALSE | R90: =AND(P90=TRUE,Q90=TRUE) -> FALSE
A91: a1zNz000000AgIvIAK | B91: 001Nz000002tU4MIAU | C91: Aleena Iqbal | D91: 006Nz000002p0o2IAA | E91: a1G4J0000025y3NUAQ | F91: Completed | G91: FALSE | I91: 45611 | J91: FALSE | K91: 45204 | L91: 2023-10-05T14:10:46.000+0000 | M91: 2023-10-06T08:17:59.000+0000 | N91: 0058d0000043ssPAAQ | P91: =IF(I91>TODAY(),TRUE,FALSE) -> FALSE | Q91: =NOT(ISERROR(VLOOKUP(B91,'2. RTR with Tenant >1 != Vacatd'!A:A,1,FALSE))) -> FALSE | R91: =AND(P91=TRUE,Q91=TRUE) -> FALSE
A92: a1zNz000000AgM9IAK | B92: 001Nz000002tKucIAE | C92: Adnan Salah | D92: 006Nz000002p0o2IAA | E92: a1G4J0000025y3NUAQ | F92: Completed | G92: TRUE | H92: 45570 | I92: 45611 | J92: FALSE | K92: 45204 | L92: 2023-10-05T14:16:27.000+0000 | M92: 2023-10-05T14:24:03.000+0000 | N92: 0058d0000043ssPAAQ | P92: =IF(I92>TODAY(),TRUE,FALSE) -> FALSE | Q92: =NOT(ISERROR(VLOOKUP(B92,'2. RTR with Tenant >1 != Vacatd'!A:A,1,FALSE))) -> FALSE | R92: =AND(P92=TRUE,Q92=TRUE) -> FALSE
A93: a1zNz000000AgSbIAK | B93: 0018d00000IJvBwAAL | C93: Safwan Ally | D93: 006Nz000002nT30IAE | E93: a1G4J0000025xZFUAY | F93: In Progress | G93: FALSE | I93: 45611 | J93: FALSE | K93: 45204 | L93: 2023-10-05T14:28:32.000+0000 | M93: 2023-10-05T14:28:32.000+0000 | N93: 0058d0000043ssPAAQ | P93: =IF(I93>TODAY(),TRUE,FALSE) -> FALSE | Q93: =NOT(ISERROR(VLOOKUP(B93,'2. RTR with Tenant >1 != Vacatd'!A:A,1,FALSE))) -> FALSE | R93: =AND(P93=TRUE,Q93=TRUE) -> FALSE
A94: a1zNz000000AgVpIAK | B94: 001Nz000001yBmVIAU | C94: Ka Po Ngai | D94: 006Nz0000023YnEIAU | E94: a1G4J0000025zIlUAI | F94: Completed | G94: TRUE | H94: 46138 | I94: 45611 | J94: FALSE | K94: 45204 | L94: 2023-10-05T14:37:50.000+0000 | M94: 2024-08-15T16:03:46.000+0000 | N94: 0058d00000202rVAAQ | P94: =IF(I94>TODAY(),TRUE,FALSE) -> FALSE | Q94: =NOT(ISERROR(VLOOKUP(B94,'2. RTR with Tenant >1 != Vacatd'!A:A,1,FALSE))) -> FALSE | R94: =AND(P94=TRUE,Q94=TRUE) -> FALSE
A95: a1zNz000000AhlFIAS | B95: 001Nz0000021qwIIAQ | C95: Nikol Papageorgiou | D95: 006Nz000001zGNUIA2 | E95: a1G4J0000025z2PUAQ | F95: Completed | G95: FALSE | I95: 45611 | J95: TRUE | K95: 45204 | L95: 2023-10-05T17:10:32.000+0000 | M95: 2024-08-15T16:03:46.000+0000 | N95: 005Nz000000R0K6IAK | P95: =IF(I95>TODAY(),TRUE,FALSE) -> FALSE | Q95: =NOT(ISERROR(VLOOKUP(B95,'2. RTR with Tenant >1 != Vacatd'!A:A,1,FALSE))) -> FALSE | R95: =AND(P95=TRUE,Q95=TRUE) -> FALSE
A96: a1zNz000000AlAXIA0 | B96: 0018d00000Jk8SEAAZ | C96: Irina Guseva | D96: 006Nz000002c1wRIAQ | E96: a1G4J0000025zRbUAI | F96: In Progress | G96: TRUE | H96: 46918 | I96: 45611 | J96: TRUE | K96: 45205 | L96: 2023-10-06T09:44:06.000+0000 | M96: 2024-08-15T16:03:46.000+0000 | N96: 0058d00000202rVAAQ | P96: =IF(I96>TODAY(),TRUE,FALSE) -> FALSE | Q96: =NOT(ISERROR(VLOOKUP(B96,'2. RTR with Tenant >1 != Vacatd'!A:A,1,FALSE))) -> TRUE | R96: =AND(P96=TRUE,Q96=TRUE) -> FALSE
A97: a1zNz000000AlTtIAK | B97: 001Nz000002oqezIAA | C97: Amy Austin | D97: 006Nz000002kxojIAA | E97: a1G4J0000025ynNUAQ | F97: Completed | G97: FALSE | I97: 45611 | J97: TRUE | K97: 45205 | L97: 2023-10-06T10:21:57.000+0000 | M97: 2024-08-15T16:03:46.000+0000 | N97: 0054J000004vXOWQA2 | P97: =IF(I97>TODAY(),TRUE,FALSE) -> FALSE | Q97: =NOT(ISERROR(VLOOKUP(B97,'2. RTR with Tenant >1 != Vacatd'!A:A,1,FALSE))) -> FALSE | R97: =AND(P97=TRUE,Q97=TRUE) -> FALSE
A98: a1zNz000000AliPIAS | B98: 001Nz000002WYdPIAW | C98: Sn0oVMBc0XWfzEDYFuqJ dnv9Vyar6Jq3HpzVsIMb | D98: 006Nz000002TrHZIA0 | E98: a1G8d0000004D8YEAU | F98: Completed | G98: FALSE | I98: 45611 | J98: TRUE | K98: 45205 | L98: 2023-10-06T11:00:50.000+0000 | M98: 2024-08-15T16:03:46.000+0000 | N98: 0058d000006cI6JAAU | P98: =IF(I98>TODAY(),TRUE,FALSE) -> FALSE | Q98: =NOT(ISERROR(VLOOKUP(B98,'2. RTR with Tenant >1 != Vacatd'!A:A,1,FALSE))) -> FALSE | R98: =AND(P98=TRUE,Q98=TRUE) -> FALSE
A99: a1zNz000000Alk1IAC | B99: 001Nz000002gvGsIAI | C99: e1seX09zx0WnHzUYWbeB fVg7gSWdNam0gnf4pWlg | D99: 006Nz000002TrHZIA0 | E99: a1G8d0000004D8YEAU | F99: Completed | G99: FALSE | I99: 45611 | J99: TRUE | K99: 45205 | L99: 2023-10-06T11:01:54.000+0000 | M99: 2024-08-15T16:03:46.000+0000 | N99: 0058d000006cI6JAAU | P99: =IF(I99>TODAY(),TRUE,FALSE) -> FALSE | Q99: =NOT(ISERROR(VLOOKUP(B99,'2. RTR with Tenant >1 != Vacatd'!A:A,1,FALSE))) -> FALSE | R99: =AND(P99=TRUE,Q99=TRUE) -> FALSE
A100: a1zNz000000Am9pIAC | B100: 001Nz000002nEOyIAM | C100: Charles Craddock | D100: 006Nz000002jYcNIAU | E100: a1GNz0000000xGFMAY | F100: Completed | G100: FALSE | I100: 45611 | J100: TRUE | K100: 45205 | L100: 2023-10-06T11:55:45.000+0000 | M100: 2024-08-15T16:03:46.000+0000 | N100: 0054J000006BkQgQAK | P100: =IF(I100>TODAY(),TRUE,FALSE) -> FALSE | Q100: =NOT(ISERROR(VLOOKUP(B100,'2. RTR with Tenant >1 != Vacatd'!A:A,1,FALSE))) -> FALSE | R100: =AND(P100=TRUE,Q100=TRUE) -> FALSE
...

Sheet Deduplicated Final Sheet
A1: Id | B1: Tenant__r.Name | C1: Related_Opportunity__c | D1: Related_Unit__c | E1: Status__c | F1: Time_Limited__c | G1: RTR_Expiry__c | H1: Date_Next_RTR_Required__c | I1: Document_Saved__c | J1: Check_Date__c | K1: CreatedDate | L1: LastModifiedDate | M1: OwnerId | N1: Criteria
A2: a1zNz00000095JpIAI | B2: gVcFvfyrV8jNsHt9Vf1X MxYaNpgylHRkz9GNCnmg | C2: 006Nz000002OfSMIA0 | D2: a1G8d0000004XgtEAE | E2: Completed | F2: TRUE | G2: 46656 | I2: FALSE | J2: 45203 | K2: 2023-10-03T12:20:45.000+0000 | L2: 2023-10-03T12:20:45.000+0000 | M2: 0058d00000202rVAAQ
A3: a1zNz000000AdUjIAK | B3: Ben McCabe | C3: 006Nz000002lChMIAU | D3: a1G4J0000025wYMUAY | E3: Completed | F3: FALSE | I3: FALSE | J3: 45206 | K3: 2023-10-05T13:39:36.000+0000 | L3: 2023-10-06T08:12:09.000+0000 | M3: 0058d0000043ssPAAQ
A4: a1zNz000000VZ9ZIAW | B4: Jamal Khoo | C4: 0068d000002cbgIAAQ | D4: a1G4J00000260SjUAI | E4: Completed | F4: TRUE | G4: 45210 | I4: TRUE | K4: 2023-11-10T12:14:46.000+0000 | L4: 2023-11-10T12:14:46.000+0000 | M4: 0058d000004Cx8uAAC
A5: a1zNz000000gz2IIAQ | B5: Austin Rwodzi | C5: 0068d00000Cs6BVAAZ | D5: a1G4J0000025xf0UAA | E5: Completed | F5: TRUE | G5: 45505 | I5: TRUE | K5: 2023-12-07T10:58:53.000+0000 | L5: 2023-12-07T10:58:53.000+0000 | M5: 0058d000004Cx8uAAC
A6: a1zNz000000upZJIAY | B6: Krishnanjana Jayachandran | C6: 0068d00000F4mDIAAZ | E6: Completed | F6: TRUE | G6: 45504 | I6: TRUE | K6: 2024-01-03T11:21:37.000+0000 | L6: 2024-01-03T11:21:37.000+0000 | M6: 0058d000006d4S2AAI
A7: a1zPv000000mh97IAA | B7: Joe Pilkington | C7: 006Pv000009pWwjIAE | E7: Completed | F7: TRUE | G7: 45518 | I7: TRUE | K7: 2024-08-14T08:51:00.000+0000 | L7: 2024-08-14T09:04:15.000+0000 | M7: 00GPv000002kNznMAE
A8: a1zNz0000000OdSIAU | B8: Ruoxi Leng | C8: 006Nz000001UfRlIAK | D8: a1G4J000004jyp9UAA | E8: Completed | F8: TRUE | G8: 45676 | I8: TRUE | K8: 2023-09-05T11:21:04.000+0000 | L8: 2024-08-15T16:03:46.000+0000 | M8: 0054J000006BkQgQAK
A9: a1zNz000000Cm45IAC | B9: Lok Ching Wong | C9: 006Nz000002PqSGIA0 | D9: a1GNz0000000vxZMAQ | E9: Completed | F9: TRUE | G9: 46652 | I9: TRUE | K9: 2023-10-10T13:29:47.000+0000 | L9: 2024-08-15T16:03:46.000+0000 | M9: 0054J000004wSINQA2
A10: a1zNz000000ET5NIAW | B10: Jittrapa Phurkvimolphan | D10: a1G8d000002Q2SZEA0 | E10: Completed | F10: TRUE | G10: 45675 | I10: TRUE | K10: 2023-10-13T13:08:30.000+0000 | L10: 2024-08-15T16:03:46.000+0000 | M10: 0058d000001yXeuAAE
A11: a1zNz000000VZG1IAO | B11: Akhil Vaswani | D11: a1G4J00000260RIUAY | E11: Completed | F11: TRUE | G11: 46233 | I11: TRUE | K11: 2023-11-10T12:18:31.000+0000 | L11: 2024-08-15T16:03:47.000+0000 | M11: 0058d000004Cx8uAAC
A12: a1zNz000000VZHdIAO | B12: Pranav Gattani | D12: a1G4J00000260RIUAY | E12: Completed | F12: TRUE | G12: 46279 | I12: TRUE | K12: 2023-11-10T12:20:23.000+0000 | L12: 2024-08-15T16:03:47.000+0000 | M12: 0058d000004Cx8uAAC
A13: a1zNz000000VaYfIAK | B13: Sihyun Kim | D13: a1G4J0000025xQUUAY | E13: Completed | F13: TRUE | G13: 46149 | I13: TRUE | K13: 2023-11-10T14:09:59.000+0000 | L13: 2024-08-15T16:03:47.000+0000 | M13: 0058d000004Cx8uAAC
A14: a1zNz000000VabtIAC | B14: Yu Hong Leung | C14: 0064J00000DFU4gQAH | D14: a1G4J0000025xQUUAY | E14: Completed | F14: TRUE | G14: 46249 | I14: TRUE | K14: 2023-11-10T14:11:26.000+0000 | L14: 2024-08-15T16:03:47.000+0000 | M14: 0058d000004Cx8uAAC
A15: a1zNz000000WCUHIA4 | B15: Rommel Dy | C15: 006Nz0000011vWjIAI | D15: a1G4J0000025zuiUAA | E15: Completed | F15: TRUE | G15: 46309 | I15: TRUE | K15: 2023-11-14T15:00:07.000+0000 | L15: 2024-08-15T16:03:47.000+0000 | M15: 0058d000004Cx8uAAC
A16: a1zNz000000XeczIAC | B16: Charles Egbuonu | C16: 006Nz000004EGylIAG | D16: a1GNz0000000wDhMAI | E16: Completed | F16: TRUE | G16: 46183 | I16: TRUE | K16: 2023-11-16T14:37:58.000+0000 | L16: 2024-08-15T16:03:48.000+0000 | M16: 0058d00000202rVAAQ
A17: a1zNz000000guXOIAY | B17: Tunde Ganiy | C17: 0068d000003tzz5AAA | D17: a1G4J00000260R8UAI | E17: Completed | F17: TRUE | G17: 46022 | I17: TRUE | K17: 2023-12-07T09:50:57.000+0000 | L17: 2024-08-15T16:03:48.000+0000 | M17: 0058d000004Cx8uAAC
A18: a1zNz000000gvrVIAQ | B18: Zainab Ayodimeji | C18: 0068d000003tzz5AAA | D18: a1G4J00000260R8UAI | E18: Completed | F18: TRUE | G18: 46140 | I18: TRUE | K18: 2023-12-07T09:55:06.000+0000 | L18: 2024-08-15T16:03:48.000+0000 | M18: 0058d000004Cx8uAAC
A19: a1zNz000000nS3BIAU | B19: Mijung Yu | C19: 006Nz000001LEnPIAW | D19: a1G8d0000005rAkEAI | E19: Completed | F19: TRUE | G19: 46226 | I19: TRUE | K19: 2023-12-19T15:48:22.000+0000 | L19: 2024-08-15T16:03:48.000+0000 | M19: 005Nz0000013xmDIAQ
A20: a1zNz000000rdeLIAQ | B20: Andrey Kluban | C20: 006Nz000000jk1wIAA | D20: a1G8d0000005rJIEAY | E20: Completed | F20: TRUE | G20: 46310 | I20: TRUE | K20: 2023-12-28T10:22:05.000+0000 | L20: 2024-08-15T16:03:48.000+0000 | M20: 005Nz0000013xmDIAQ
A21: a1zNz000000s8JxIAI | B21: Lin Hu | D21: a1G4J000004jyeQUAQ | E21: Completed | F21: TRUE | G21: 45687 | I21: TRUE | K21: 2023-12-29T16:05:15.000+0000 | L21: 2024-08-15T16:03:48.000+0000 | M21: 0058d0000034Kn5AAE
A22: a1zNz000000vt6DIAQ | B22: Akshitha Gajula | C22: 006Nz000004wNoMIAU | D22: a1G4J0000025x2OUAQ | E22: Completed | F22: TRUE | G22: 45677 | I22: TRUE | K22: 2024-01-04T11:03:17.000+0000 | L22: 2024-08-15T16:03:48.000+0000 | M22: 0058d0000043sEOAAY
A23: a1zNz000000znBtIAI | B23: Elif Eroglu | C23: 0068d00000Cs1DiAAJ | D23: a1G4J00000260NLUAY | E23: Completed | F23: TRUE | G23: 46005 | I23: TRUE | K23: 2024-01-10T14:07:55.000+0000 | L23: 2024-08-15T16:03:48.000+0000 | M23: 0058d000004Cx8uAAC
A24: a1zNz0000014YP7IAM | B24: Ryan Carlton | D24: a1G4J0000025y4WUAQ | E24: Completed | F24: FALSE | I24: TRUE | K24: 2024-01-19T14:48:05.000+0000 | L24: 2024-08-15T16:03:49.000+0000 | M24: 0058d000004DynQAAS
A25: a1zNz0000014YQjIAM | B25: Sophie Lee | D25: a1G4J0000025y4WUAQ | E25: Completed | F25: FALSE | I25: TRUE | K25: 2024-01-19T14:49:14.000+0000 | L25: 2024-08-15T16:03:49.000+0000 | M25: 0058d000004DynQAAS
A26: a1zNz0000016PG7IAM | B26: Bence Cserkuti | C26: 006Nz000006hHTbIAM | D26: a1G8d0000004qaEEAQ | E26: Completed | F26: FALSE | I26: TRUE | K26: 2024-01-23T14:58:33.000+0000 | L26: 2024-08-15T16:03:49.000+0000 | M26: 005Nz000000eYuFIAU
A27: a1zNz000001DfhVIAS | B27: Alice Belshaw | C27: 006Nz000001ba3yIAA | D27: a1G8d0000004c9mEAA | E27: Completed | F27: TRUE | G27: 45682 | I27: TRUE | K27: 2024-02-02T16:27:04.000+0000 | L27: 2024-08-15T16:03:49.000+0000 | M27: 0058d0000034KZ2AAM
A28: a1zNz000001JSZWIA4 | B28: Xiaotian Xie | D28: a1G8d000002Q2a0EAC | E28: Completed | F28: TRUE | G28: 45657 | I28: TRUE | K28: 2024-02-09T11:00:33.000+0000 | L28: 2024-08-15T16:03:49.000+0000 | M28: 005Nz000000FVd0IAG
A29: a1zNz000001JSzJIAW | B29: Jessica Yan | D29: a1G8d000002Q2a0EAC | E29: Completed | F29: TRUE | G29: 45657 | I29: TRUE | K29: 2024-02-09T11:02:00.000+0000 | L29: 2024-08-15T16:03:49.000+0000 | M29: 005Nz000000FVd0IAG
A30: a1zNz000001Ta5xIAC | B30: Delna Dotivala | C30: 006Nz000007uQwgIAE | D30: a1G4J0000025wxVUAQ | E30: Completed | F30: TRUE | G30: 45995 | I30: TRUE | K30: 2024-02-20T09:48:47.000+0000 | L30: 2024-08-15T16:03:49.000+0000 | M30: 005Nz000002KcrEIAS
A31: a1zNz000001TaPKIA0 | B31: Hamid Siddiqui | C31: 006Nz000007uQwgIAE | D31: a1G4J0000025wxVUAQ | E31: Completed | F31: TRUE | G31: 45995 | I31: TRUE | K31: 2024-02-20T09:51:56.000+0000 | L31: 2024-08-15T16:03:49.000+0000 | M31: 005Nz000002KcrEIAS
A32: a1zNz000001UYA9IAO | B32: Teresa To | D32: a1G4J000002634bUAA | E32: Completed | F32: TRUE | G32: 46145 | I32: TRUE | K32: 2024-02-21T09:05:41.000+0000 | L32: 2024-08-15T16:03:49.000+0000 | M32: 0054J000004vm8oQAA
A33: a1zNz000001WWiXIAW | B33: Terri Sandiford | C33: 006Nz0000089UgnIAE | D33: a1G4J0000025xhtUAA | E33: Completed | F33: FALSE | I33: TRUE | K33: 2024-02-22T13:21:57.000+0000 | L33: 2024-08-15T16:03:49.000+0000 | M33: 0054J000004vXOqQAM
A34: a1zNz000001iVE1IAM | B34: Noor Khalid Abdelmajeed | C34: 006Nz000005MMbnIAG | E34: Completed | F34: TRUE | G34: 45923 | I34: TRUE | K34: 2024-03-06T12:23:47.000+0000 | L34: 2024-08-15T16:03:49.000+0000 | M34: 0054J000004vXP2QAM
A35: a1zNz000001itTFIAY | B35: Amy Johnson | C35: 006Nz000007tRgLIAU | D35: a1G8d0000004cBnEAI | E35: Completed | F35: FALSE | I35: TRUE | K35: 2024-03-06T16:25:57.000+0000 | L35: 2024-08-15T16:03:49.000+0000 | M35: 0058d000006chw3AAA
A36: a1zNz000002PXCXIA4 | B36: Callum Mccafferty | C36: 006Nz00000A7pEdIAJ | D36: a1G4J0000025zxoUAA | E36: Completed | F36: FALSE | I36: TRUE | K36: 2024-04-19T10:44:09.000+0000 | L36: 2024-08-15T16:03:50.000+0000 | M36: 0058d00000204EOAAY
A37: a1zNz000002g4xOIAQ | B37: Baher Hanna | C37: 006Nz0000030Q8tIAE | D37: a1G8d0000005rP1EAI | E37: Completed | F37: TRUE | G37: 46021 | I37: TRUE | K37: 2024-05-06T12:03:47.000+0000 | L37: 2024-08-15T16:03:50.000+0000 | M37: 005Nz000002TJ6AIAW
A38: a1zNz000002j44pIAA | B38: Joseph Kelly | C38: 006Nz00000B2ZJYIA3 | D38: a1G8d0000005rFzEAI | E38: Completed | F38: FALSE | I38: TRUE | K38: 2024-05-09T09:03:50.000+0000 | L38: 2024-08-15T16:03:50.000+0000 | M38: 0054J000004vXP2QAM
A39: a1zNz000002oIAKIA2 | B39: Jose Morales | C39: 006Nz00000B6H34IAF | D39: a1G4J0000025zUhUAI | E39: Completed | F39: TRUE | G39: 46079 | I39: TRUE | K39: 2024-05-14T12:58:06.000+0000 | L39: 2024-08-15T16:03:50.000+0000 | M39: 0058d000004DOMXAA4
A40: a1zNz000002uDBAIA2 | B40: Yun-Chen Lin | C40: 006Nz00000Aqm4PIAR | D40: a1G4J0000025yh3UAA | E40: Completed | F40: TRUE | G40: 46308 | I40: TRUE | K40: 2024-05-20T11:35:10.000+0000 | L40: 2024-08-15T16:03:50.000+0000 | M40: 0058d0000034SvqAAE
A41: a1zNz0000034mM5IAI | B41: Saria Ahmed | C41: 006Nz00000BJwWdIAL | D41: a1G4J0000025zaZUAQ | E41: Completed | F41: TRUE | G41: 45524 | I41: TRUE | K41: 2024-05-29T08:58:42.000+0000 | L41: 2024-08-15T16:03:50.000+0000 | M41: 0058d000004DOMXAA4
A42: a1zNz0000038LggIAE | B42: Phoebe Woollard | C42: 006Nz00000BKFMLIA5 | D42: a1G4J00000262hSUAQ | E42: Completed | F42: FALSE | I42: FALSE | K42: 2024-05-31T13:27:36.000+0000 | L42: 2024-08-15T16:03:50.000+0000 | M42: 0054J000004vXPBQA2
A43: a1zNz000003GVu9IAG | B43: Andrea Monti | C43: 006Nz00000C6qY6IAJ | D43: a1G4J0000025zxOUAQ | E43: Completed | F43: FALSE | I43: FALSE | K43: 2024-06-07T10:38:33.000+0000 | L43: 2024-08-15T16:03:50.000+0000 | M43: 0054J000004vXPBQA2
A44: a1zNz000003II4pIAG | B44: Alex Jacob Parsons | C44: 006Nz000007BPk0IAG | E44: Completed | F44: FALSE | I44: TRUE | K44: 2024-06-10T08:46:07.000+0000 | L44: 2024-08-15T16:03:50.000+0000 | M44: 0054J000004vXP2QAM
A45: a1zPv000000mh5tIAA | B45: Clair Habgood | C45: 006Pv000009pWwjIAE | E45: Completed | F45: FALSE | I45: TRUE | K45: 2024-08-14T08:46:29.000+0000 | L45: 2024-08-15T16:03:50.000+0000 | M45: 00GPv000002kNznMAE
A46: a1zNz00000095JpIAI | B46: gVcFvfyrV8jNsHt9Vf1X MxYaNpgylHRkz9GNCnmg | C46: 006Nz000002OfSMIA0 | D46: a1G8d0000004XgtEAE | E46: Completed | F46: TRUE | G46: 46656 | I46: FALSE | J46: 45203 | K46: 2023-10-03T12:20:45.000+0000 | L46: 2023-10-03T12:20:45.000+0000 | M46: 0058d00000202rVAAQ
A47: a1zNz000000AdUjIAK | B47: Ben McCabe | C47: 006Nz000002lChMIAU | D47: a1G4J0000025wYMUAY | E47: Completed | F47: FALSE | I47: FALSE | J47: 45206 | K47: 2023-10-05T13:39:36.000+0000 | L47: 2023-10-06T08:12:09.000+0000 | M47: 0058d0000043ssPAAQ
A48: a1zNz000000VZ9ZIAW | B48: Jamal Khoo | C48: 0068d000002cbgIAAQ | D48: a1G4J00000260SjUAI | E48: Completed | F48: TRUE | G48: 45210 | I48: TRUE | K48: 2023-11-10T12:14:46.000+0000 | L48: 2023-11-10T12:14:46.000+0000 | M48: 0058d000004Cx8uAAC
A49: a1zNz000000gz2IIAQ | B49: Austin Rwodzi | C49: 0068d00000Cs6BVAAZ | D49: a1G4J0000025xf0UAA | E49: Completed | F49: TRUE | G49: 45505 | I49: TRUE | K49: 2023-12-07T10:58:53.000+0000 | L49: 2023-12-07T10:58:53.000+0000 | M49: 0058d000004Cx8uAAC
A50: a1zNz000000upZJIAY | B50: Krishnanjana Jayachandran | C50: 0068d00000F4mDIAAZ | E50: Completed | F50: TRUE | G50: 45504 | I50: TRUE | K50: 2024-01-03T11:21:37.000+0000 | L50: 2024-01-03T11:21:37.000+0000 | M50: 0058d000006d4S2AAI
A51: a1zPv000000mh97IAA | B51: Joe Pilkington | C51: 006Pv000009pWwjIAE | E51: Completed | F51: TRUE | G51: 45518 | I51: TRUE | K51: 2024-08-14T08:51:00.000+0000 | L51: 2024-08-14T09:04:15.000+0000 | M51: 00GPv000002kNznMAE
A52: a1zNz0000000OdSIAU | B52: Ruoxi Leng | C52: 006Nz000001UfRlIAK | D52: a1G4J000004jyp9UAA | E52: Completed | F52: TRUE | G52: 45676 | I52: TRUE | K52: 2023-09-05T11:21:04.000+0000 | L52: 2024-08-15T16:03:46.000+0000 | M52: 0054J000006BkQgQAK
A53: a1zNz000000Cm45IAC | B53: Lok Ching Wong | C53: 006Nz000002PqSGIA0 | D53: a1GNz0000000vxZMAQ | E53: Completed | F53: TRUE | G53: 46652 | I53: TRUE | K53: 2023-10-10T13:29:47.000+0000 | L53: 2024-08-15T16:03:46.000+0000 | M53: 0054J000004wSINQA2
A54: a1zNz000000ET5NIAW | B54: Jittrapa Phurkvimolphan | D54: a1G8d000002Q2SZEA0 | E54: Completed | F54: TRUE | G54: 45675 | I54: TRUE | K54: 2023-10-13T13:08:30.000+0000 | L54: 2024-08-15T16:03:46.000+0000 | M54: 0058d000001yXeuAAE
A55: a1zNz000000VZG1IAO | B55: Akhil Vaswani | D55: a1G4J00000260RIUAY | E55: Completed | F55: TRUE | G55: 46233 | I55: TRUE | K55: 2023-11-10T12:18:31.000+0000 | L55: 2024-08-15T16:03:47.000+0000 | M55: 0058d000004Cx8uAAC
A56: a1zNz000000VZHdIAO | B56: Pranav Gattani | D56: a1G4J00000260RIUAY | E56: Completed | F56: TRUE | G56: 46279 | I56: TRUE | K56: 2023-11-10T12:20:23.000+0000 | L56: 2024-08-15T16:03:47.000+0000 | M56: 0058d000004Cx8uAAC
A57: a1zNz000000VaYfIAK | B57: Sihyun Kim | D57: a1G4J0000025xQUUAY | E57: Completed | F57: TRUE | G57: 46149 | I57: TRUE | K57: 2023-11-10T14:09:59.000+0000 | L57: 2024-08-15T16:03:47.000+0000 | M57: 0058d000004Cx8uAAC
A58: a1zNz000000VabtIAC | B58: Yu Hong Leung | C58: 0064J00000DFU4gQAH | D58: a1G4J0000025xQUUAY | E58: Completed | F58: TRUE | G58: 46249 | I58: TRUE | K58: 2023-11-10T14:11:26.000+0000 | L58: 2024-08-15T16:03:47.000+0000 | M58: 0058d000004Cx8uAAC
A59: a1zNz000000WCUHIA4 | B59: Rommel Dy | C59: 006Nz0000011vWjIAI | D59: a1G4J0000025zuiUAA | E59: Completed | F59: TRUE | G59: 46309 | I59: TRUE | K59: 2023-11-14T15:00:07.000+0000 | L59: 2024-08-15T16:03:47.000+0000 | M59: 0058d000004Cx8uAAC
A60: a1zNz000000XeczIAC | B60: Charles Egbuonu | C60: 006Nz000004EGylIAG | D60: a1GNz0000000wDhMAI | E60: Completed | F60: TRUE | G60: 46183 | I60: TRUE | K60: 2023-11-16T14:37:58.000+0000 | L60: 2024-08-15T16:03:48.000+0000 | M60: 0058d00000202rVAAQ
A61: a1zNz000000guXOIAY | B61: Tunde Ganiy | C61: 0068d000003tzz5AAA | D61: a1G4J00000260R8UAI | E61: Completed | F61: TRUE | G61: 46022 | I61: TRUE | K61: 2023-12-07T09:50:57.000+0000 | L61: 2024-08-15T16:03:48.000+0000 | M61: 0058d000004Cx8uAAC
A62: a1zNz000000gvrVIAQ | B62: Zainab Ayodimeji | C62: 0068d000003tzz5AAA | D62: a1G4J00000260R8UAI | E62: Completed | F62: TRUE | G62: 46140 | I62: TRUE | K62: 2023-12-07T09:55:06.000+0000 | L62: 2024-08-15T16:03:48.000+0000 | M62: 0058d000004Cx8uAAC
A63: a1zNz000000nS3BIAU | B63: Mijung Yu | C63: 006Nz000001LEnPIAW | D63: a1G8d0000005rAkEAI | E63: Completed | F63: TRUE | G63: 46226 | I63: TRUE | K63: 2023-12-19T15:48:22.000+0000 | L63: 2024-08-15T16:03:48.000+0000 | M63: 005Nz0000013xmDIAQ
A64: a1zNz000000rdeLIAQ | B64: Andrey Kluban | C64: 006Nz000000jk1wIAA | D64: a1G8d0000005rJIEAY | E64: Completed | F64: TRUE | G64: 46310 | I64: TRUE | K64: 2023-12-28T10:22:05.000+0000 | L64: 2024-08-15T16:03:48.000+0000 | M64: 005Nz0000013xmDIAQ
A65: a1zNz000000s8JxIAI | B65: Lin Hu | D65: a1G4J000004jyeQUAQ | E65: Completed | F65: TRUE | G65: 45687 | I65: TRUE | K65: 2023-12-29T16:05:15.000+0000 | L65: 2024-08-15T16:03:48.000+0000 | M65: 0058d0000034Kn5AAE
A66: a1zNz000000vt6DIAQ | B66: Akshitha Gajula | C66: 006Nz000004wNoMIAU | D66: a1G4J0000025x2OUAQ | E66: Completed | F66: TRUE | G66: 45677 | I66: TRUE | K66: 2024-01-04T11:03:17.000+0000 | L66: 2024-08-15T16:03:48.000+0000 | M66: 0058d0000043sEOAAY
A67: a1zNz000000znBtIAI | B67: Elif Eroglu | C67: 0068d00000Cs1DiAAJ | D67: a1G4J00000260NLUAY | E67: Completed | F67: TRUE | G67: 46005 | I67: TRUE | K67: 2024-01-10T14:07:55.000+0000 | L67: 2024-08-15T16:03:48.000+0000 | M67: 0058d000004Cx8uAAC
A68: a1zNz0000014YP7IAM | B68: Ryan Carlton | D68: a1G4J0000025y4WUAQ | E68: Completed | F68: FALSE | I68: TRUE | K68: 2024-01-19T14:48:05.000+0000 | L68: 2024-08-15T16:03:49.000+0000 | M68: 0058d000004DynQAAS
A69: a1zNz0000014YQjIAM | B69: Sophie Lee | D69: a1G4J0000025y4WUAQ | E69: Completed | F69: FALSE | I69: TRUE | K69: 2024-01-19T14:49:14.000+0000 | L69: 2024-08-15T16:03:49.000+0000 | M69: 0058d000004DynQAAS
A70: a1zNz0000016PG7IAM | B70: Bence Cserkuti | C70: 006Nz000006hHTbIAM | D70: a1G8d0000004qaEEAQ | E70: Completed | F70: FALSE | I70: TRUE | K70: 2024-01-23T14:58:33.000+0000 | L70: 2024-08-15T16:03:49.000+0000 | M70: 005Nz000000eYuFIAU
A71: a1zNz000001DfhVIAS | B71: Alice Belshaw | C71: 006Nz000001ba3yIAA | D71: a1G8d0000004c9mEAA | E71: Completed | F71: TRUE | G71: 45682 | I71: TRUE | K71: 2024-02-02T16:27:04.000+0000 | L71: 2024-08-15T16:03:49.000+0000 | M71: 0058d0000034KZ2AAM
A72: a1zNz000001JSZWIA4 | B72: Xiaotian Xie | D72: a1G8d000002Q2a0EAC | E72: Completed | F72: TRUE | G72: 45657 | I72: TRUE | K72: 2024-02-09T11:00:33.000+0000 | L72: 2024-08-15T16:03:49.000+0000 | M72: 005Nz000000FVd0IAG
