Workbook

Sheet Update Related Units
A1: Id | B1: Related_Opportunity__r.Primary_Offer__r.Unit__c | D1: _Update? | E1: Id | F1: Related_Unit__c | J1: Disable validation rule:
A2: a1zNz0000006zqPIAQ | B2: a1G4J0000025z5QUAQ | D2: =F2<>"" -> TRUE | E2: =A2 -> a1zNz0000006zqPIAQ | F2: =IF(NOT(ISBLANK(B2)),B2,"") -> a1G4J0000025z5QUAQ | J2: RTR_Validate_Check_Date
A3: a1zNz000000GTNpIAO | B3: a1G4J0000025y8bUAA | D3: =F3<>"" -> TRUE | E3: =A3 -> a1zNz000000GTNpIAO | F3: =IF(NOT(ISBLANK(B3)),B3,"") -> a1G4J0000025y8bUAA | J3: Document_Saved
A4: a1zNz000000GYCDIA4 | B4: a1G4J000004jyhpUAA | D4: =F4<>"" -> TRUE | E4: =A4 -> a1zNz000000GYCDIA4 | F4: =IF(NOT(ISBLANK(B4)),B4,"") -> a1G4J000004jyhpUAA | J4: RTR_Validate_Related_Opportunity
A5: a1zNz000000PdpNIAS | B5: a1GNz00000017lpMAA | D5: =F5<>"" -> TRUE | E5: =A5 -> a1zNz000000PdpNIAS | F5: =IF(NOT(ISBLANK(B5)),B5,"") -> a1GNz00000017lpMAA | J5: No_Expiry_Date_Time_Limited
A6: a1zNz000000PeIPIA0 | B6: a1GNz00000010UGMAY | D6: =F6<>"" -> TRUE | E6: =A6 -> a1zNz000000PeIPIA0 | F6: =IF(NOT(ISBLANK(B6)),B6,"") -> a1GNz00000010UGMAY | J6: RTR_Expiry_Time_Limited
A7: a1zNz000000UIFeIAO | B7: a1GNz00000012fhMAA | D7: =F7<>"" -> TRUE | E7: =A7 -> a1zNz000000UIFeIAO | F7: =IF(NOT(ISBLANK(B7)),B7,"") -> a1GNz00000012fhMAA
A8: a1zNz000000URvdIAG | B8: a1G4J0000025x92UAA | D8: =F8<>"" -> TRUE | E8: =A8 -> a1zNz000000URvdIAG | F8: =IF(NOT(ISBLANK(B8)),B8,"") -> a1G4J0000025x92UAA
A9: a1zNz000000UYfNIAW | B9: a1G8d000002QBLDEA4 | D9: =F9<>"" -> TRUE | E9: =A9 -> a1zNz000000UYfNIAW | F9: =IF(NOT(ISBLANK(B9)),B9,"") -> a1G8d000002QBLDEA4
A10: a1zNz000000UywPIAS | B10: a1G4J0000025y1kUAA | D10: =F10<>"" -> TRUE | E10: =A10 -> a1zNz000000UywPIAS | F10: =IF(NOT(ISBLANK(B10)),B10,"") -> a1G4J0000025y1kUAA
A11: a1zNz000000V6PJIA0 | B11: a1G4J0000025xyYUAQ | D11: =F11<>"" -> TRUE | E11: =A11 -> a1zNz000000V6PJIA0 | F11: =IF(NOT(ISBLANK(B11)),B11,"") -> a1G4J0000025xyYUAQ
A12: a1zNz000000VNd3IAG | B12: a1G4J0000025x1GUAQ | D12: =F12<>"" -> TRUE | E12: =A12 -> a1zNz000000VNd3IAG | F12: =IF(NOT(ISBLANK(B12)),B12,"") -> a1G4J0000025x1GUAQ
A13: a1zNz000000XDwCIAW | B13: a1G4J0000025ywGUAQ | D13: =F13<>"" -> TRUE | E13: =A13 -> a1zNz000000XDwCIAW | F13: =IF(NOT(ISBLANK(B13)),B13,"") -> a1G4J0000025ywGUAQ
A14: a1zNz000000Yww1IAC | B14: a1G4J0000025xXqUAI | D14: =F14<>"" -> TRUE | E14: =A14 -> a1zNz000000Yww1IAC | F14: =IF(NOT(ISBLANK(B14)),B14,"") -> a1G4J0000025xXqUAI
A15: a1zNz000000amu9IAA | B15: a1G4J0000025wkbUAA | D15: =F15<>"" -> TRUE | E15: =A15 -> a1zNz000000amu9IAA | F15: =IF(NOT(ISBLANK(B15)),B15,"") -> a1G4J0000025wkbUAA
A16: a1zNz000000d4jiIAA | B16: a1G4J0000025zHYUAY | D16: =F16<>"" -> TRUE | E16: =A16 -> a1zNz000000d4jiIAA | F16: =IF(NOT(ISBLANK(B16)),B16,"") -> a1G4J0000025zHYUAY
A17: a1zNz000000fNIPIA2 | B17: a1G4J00000260DRUAY | D17: =F17<>"" -> TRUE | E17: =A17 -> a1zNz000000fNIPIA2 | F17: =IF(NOT(ISBLANK(B17)),B17,"") -> a1G4J00000260DRUAY
A18: a1zNz000000kmHlIAI | B18: a1G4J0000025y09UAA | D18: =F18<>"" -> TRUE | E18: =A18 -> a1zNz000000kmHlIAI | F18: =IF(NOT(ISBLANK(B18)),B18,"") -> a1G4J0000025y09UAA
... A82: a1zNz0000030aZeIAI | B82: a1GNz0000000ynNMAQ | D82: =F82<>"" -> TRUE | E82: =A82 -> a1zNz0000030aZeIAI | F82: =IF(NOT(ISBLANK(B82)),B82,"") -> a1GNz0000000ynNMAQ
A83: a1zNz0000033rMGIAY | D83: =F83<>"" -> FALSE | E83: =A83 -> a1zNz0000033rMGIAY | F83: =IF(NOT(ISBLANK(B83)),B83,"")
A84: a1zNz0000034aUhIAI | B84: a1G8d0000004qm0EAA | D84: =F84<>"" -> TRUE | E84: =A84 -> a1zNz0000034aUhIAI | F84: =IF(NOT(ISBLANK(B84)),B84,"") -> a1G8d0000004qm0EAA
A85: a1zNz0000034cxqIAA | B85: a1G8d0000004qmoEAA | D85: =F85<>"" -> TRUE | E85: =A85 -> a1zNz0000034cxqIAA | F85: =IF(NOT(ISBLANK(B85)),B85,"") -> a1G8d0000004qmoEAA
A86: a1zNz0000034dInIAI | B86: a1G8d0000004qmoEAA | D86: =F86<>"" -> TRUE | E86: =A86 -> a1zNz0000034dInIAI | F86: =IF(NOT(ISBLANK(B86)),B86,"") -> a1G8d0000004qmoEAA
A87: a1zNz0000034wJtIAI | B87: a1G4J0000025yktUAA | D87: =F87<>"" -> TRUE | E87: =A87 -> a1zNz0000034wJtIAI | F87: =IF(NOT(ISBLANK(B87)),B87,"") -> a1G4J0000025yktUAA
A88: a1zNz0000035RlpIAE | B88: a1GNz0000019H4HMAU | D88: =F88<>"" -> TRUE | E88: =A88 -> a1zNz0000035RlpIAE | F88: =IF(NOT(ISBLANK(B88)),B88,"") -> a1GNz0000019H4HMAU
A89: a1zNz0000037xZVIAY | B89: a1G8d0000004qjaEAA | D89: =F89<>"" -> TRUE | E89: =A89 -> a1zNz0000037xZVIAY | F89: =IF(NOT(ISBLANK(B89)),B89,"") -> a1G8d0000004qjaEAA
A90: a1zNz0000038Lf3IAE | B90: a1G4J0000025yitUAA | D90: =F90<>"" -> TRUE | E90: =A90 -> a1zNz0000038Lf3IAE | F90: =IF(NOT(ISBLANK(B90)),B90,"") -> a1G4J0000025yitUAA
A91: a1zNz000003F8A1IAK | B91: a1G4J000004juuWUAQ | D91: =F91<>"" -> TRUE | E91: =A91 -> a1zNz000003F8A1IAK | F91: =IF(NOT(ISBLANK(B91)),B91,"") -> a1G4J000004juuWUAQ
A92: a1zNz000003IHK1IAO | B92: a1G8d000002QBfIEAW | D92: =F92<>"" -> TRUE | E92: =A92 -> a1zNz000003IHK1IAO | F92: =IF(NOT(ISBLANK(B92)),B92,"") -> a1G8d000002QBfIEAW
A93: a1zNz000003II4pIAG | B93: a1G4J0000025z7yUAA | D93: =F93<>"" -> TRUE | E93: =A93 -> a1zNz000003II4pIAG | F93: =IF(NOT(ISBLANK(B93)),B93,"") -> a1G4J0000025z7yUAA
A94: a1zNz000003IKWQIA4 | B94: a1G4J0000025zKeUAI | D94: =F94<>"" -> TRUE | E94: =A94 -> a1zNz000003IKWQIA4 | F94: =IF(NOT(ISBLANK(B94)),B94,"") -> a1G4J0000025zKeUAI
A95: a1zNz000003IMLKIA4 | B95: a1G4J0000025yOvUAI | D95: =F95<>"" -> TRUE | E95: =A95 -> a1zNz000003IMLKIA4 | F95: =IF(NOT(ISBLANK(B95)),B95,"") -> a1G4J0000025yOvUAI
... A129: a1zNz000003rQVhIAM | B129: a1G4J0000025ykRUAQ | D129: =F129<>"" -> TRUE | E129: =A129 -> a1zNz000003rQVhIAM | F129: =IF(NOT(ISBLANK(B129)),B129,"") -> a1G4J0000025ykRUAQ
A130: a1zNz000003sImEIAU | D130: =F130<>"" -> FALSE | E130: =A130 -> a1zNz000003sImEIAU | F130: =IF(NOT(ISBLANK(B130)),B130,"")
A131: a1zNz000003sKXuIAM | B131: a1GNz0000000zOTMAY | D131: =F131<>"" -> TRUE | E131: =A131 -> a1zNz000003sKXuIAM | F131: =IF(NOT(ISBLANK(B131)),B131,"") -> a1GNz0000000zOTMAY
A132: a1zNz000003sMQ1IAM | D132: =F132<>"" -> FALSE | E132: =A132 -> a1zNz000003sMQ1IAM | F132: =IF(NOT(ISBLANK(B132)),B132,"")
A133: a1zNz000003sMeXIAU | B133: a1G4J0000025yzMUAQ | D133: =F133<>"" -> TRUE | E133: =A133 -> a1zNz000003sMeXIAU | F133: =IF(NOT(ISBLANK(B133)),B133,"") -> a1G4J0000025yzMUAQ
A134: a1zNz000003sMufIAE | D134: =F134<>"" -> FALSE | E134: =A134 -> a1zNz000003sMufIAE | F134: =IF(NOT(ISBLANK(B134)),B134,"")
A135: a1zNz000003sMxtIAE | D135: =F135<>"" -> FALSE | E135: =A135 -> a1zNz000003sMxtIAE | F135: =IF(NOT(ISBLANK(B135)),B135,"")
A136: a1zNz000003sNNiIAM | D136: =F136<>"" -> FALSE | E136: =A136 -> a1zNz000003sNNiIAM | F136: =IF(NOT(ISBLANK(B136)),B136,"")
A137: a1zNz000003sNVlIAM | B137: a1G4J0000025yR2UAI | D137: =F137<>"" -> TRUE | E137: =A137 -> a1zNz000003sNVlIAM | F137: =IF(NOT(ISBLANK(B137)),B137,"") -> a1G4J0000025yR2UAI
A138: a1zNz000003sNltIAE | B138: a1GNz000001HP4gMAG | D138: =F138<>"" -> TRUE | E138: =A138 -> a1zNz000003sNltIAE | F138: =IF(NOT(ISBLANK(B138)),B138,"") -> a1GNz000001HP4gMAG
A139: a1zNz000003sNsLIAU | D139: =F139<>"" -> FALSE | E139: =A139 -> a1zNz000003sNsLIAU | F139: =IF(NOT(ISBLANK(B139)),B139,"")
A140: a1zNz000003sO5FIAU | D140: =F140<>"" -> FALSE | E140: =A140 -> a1zNz000003sO5FIAU | F140: =IF(NOT(ISBLANK(B140)),B140,"")
A141: a1zNz000003sOBhIAM | D141: =F141<>"" -> FALSE | E141: =A141 -> a1zNz000003sOBhIAM | F141: =IF(NOT(ISBLANK(B141)),B141,"")
A142: a1zNz000003sOGXIA2 | D142: =F142<>"" -> FALSE | E142: =A142 -> a1zNz000003sOGXIA2 | F142: =IF(NOT(ISBLANK(B142)),B142,"")
A143: a1zNz000003sOlBIAU | D143: =F143<>"" -> FALSE | E143: =A143 -> a1zNz000003sOlBIAU | F143: =IF(NOT(ISBLANK(B143)),B143,"")
A144: a1zNz000003sOmnIAE | D144: =F144<>"" -> FALSE | E144: =A144 -> a1zNz000003sOmnIAE | F144: =IF(NOT(ISBLANK(B144)),B144,"")
A145: a1zNz000003sP7lIAE | D145: =F145<>"" -> FALSE | E145: =A145 -> a1zNz000003sP7lIAE | F145: =IF(NOT(ISBLANK(B145)),B145,"")
A146: a1zNz000003sPAzIAM | D146: =F146<>"" -> FALSE | E146: =A146 -> a1zNz000003sPAzIAM | F146: =IF(NOT(ISBLANK(B146)),B146,"")
A147: a1zNz000003sPHRIA2 | D147: =F147<>"" -> FALSE | E147: =A147 -> a1zNz000003sPHRIA2 | F147: =IF(NOT(ISBLANK(B147)),B147,"")
A148: a1zNz000003sPULIA2 | D148: =F148<>"" -> FALSE | E148: =A148 -> a1zNz000003sPULIA2 | F148: =IF(NOT(ISBLANK(B148)),B148,"")
A149: a1zNz000003sPVxIAM | B149: a1G4J00000260CWUAY | D149: =F149<>"" -> TRUE | E149: =A149 -> a1zNz000003sPVxIAM | F149: =IF(NOT(ISBLANK(B149)),B149,"") -> a1G4J00000260CWUAY
A150: a1zNz000003sPanIAE | D150: =F150<>"" -> FALSE | E150: =A150 -> a1zNz000003sPanIAE | F150: =IF(NOT(ISBLANK(B150)),B150,"")
A151: a1zNz000003sPe1IAE | D151: =F151<>"" -> FALSE | E151: =A151 -> a1zNz000003sPe1IAE | F151: =IF(NOT(ISBLANK(B151)),B151,"")
A152: a1zNz000003sPhFIAU | D152: =F152<>"" -> FALSE | E152: =A152 -> a1zNz000003sPhFIAU | F152: =IF(NOT(ISBLANK(B152)),B152,"")
A153: a1zNz000003sPqvIAE | D153: =F153<>"" -> FALSE | E153: =A153 -> a1zNz000003sPqvIAE | F153: =IF(NOT(ISBLANK(B153)),B153,"")
A154: a1zNz000003sPxNIAU | D154: =F154<>"" -> FALSE | E154: =A154 -> a1zNz000003sPxNIAU | F154: =IF(NOT(ISBLANK(B154)),B154,"")
A155: a1zNz000003sQ5RIAU | D155: =F155<>"" -> FALSE | E155: =A155 -> a1zNz000003sQ5RIAU | F155: =IF(NOT(ISBLANK(B155)),B155,"")
A156: a1zNz000003sQGjIAM | D156: =F156<>"" -> FALSE | E156: =A156 -> a1zNz000003sQGjIAM | F156: =IF(NOT(ISBLANK(B156)),B156,"")
A157: a1zNz000003sQJxIAM | B157: a1G4J0000025yoBUAQ | D157: =F157<>"" -> TRUE | E157: =A157 -> a1zNz000003sQJxIAM | F157: =IF(NOT(ISBLANK(B157)),B157,"") -> a1G4J0000025yoBUAQ
A158: a1zNz000003sQbhIAE | D158: =F158<>"" -> FALSE | E158: =A158 -> a1zNz000003sQbhIAE | F158: =IF(NOT(ISBLANK(B158)),B158,"")
A159: a1zNz000003sQqDIAU | D159: =F159<>"" -> FALSE | E159: =A159 -> a1zNz000003sQqDIAU | F159: =IF(NOT(ISBLANK(B159)),B159,"")
A160: a1zNz000003sQwfIAE | B160: a1G4J0000025yMqUAI | D160: =F160<>"" -> TRUE | E160: =A160 -> a1zNz000003sQwfIAE | F160: =IF(NOT(ISBLANK(B160)),B160,"") -> a1G4J0000025yMqUAI
A161: a1zNz000003sR37IAE | D161: =F161<>"" -> FALSE | E161: =A161 -> a1zNz000003sR37IAE | F161: =IF(NOT(ISBLANK(B161)),B161,"")
A162: a1zNz000003sR7xIAE | B162: a1G4J0000025yRhUAI | D162: =F162<>"" -> TRUE | E162: =A162 -> a1zNz000003sR7xIAE | F162: =IF(NOT(ISBLANK(B162)),B162,"") -> a1G4J0000025yRhUAI
A163: a1zNz000003sRBBIA2 | D163: =F163<>"" -> FALSE | E163: =A163 -> a1zNz000003sRBBIA2 | F163: =IF(NOT(ISBLANK(B163)),B163,"")
A164: a1zNz000003sRG1IAM | D164: =F164<>"" -> FALSE | E164: =A164 -> a1zNz000003sRG1IAM | F164: =IF(NOT(ISBLANK(B164)),B164,"")
A165: a1zNz000003sRRJIA2 | D165: =F165<>"" -> FALSE | E165: =A165 -> a1zNz000003sRRJIA2 | F165: =IF(NOT(ISBLANK(B165)),B165,"")
A166: a1zNz000003sRUXIA2 | B166: a1G4J0000025zByUAI | D166: =F166<>"" -> TRUE | E166: =A166 -> a1zNz000003sRUXIA2 | F166: =IF(NOT(ISBLANK(B166)),B166,"") -> a1G4J0000025zByUAI
A167: a1zNz000003sRcbIAE | B167: a1G4J00000260QLUAY | D167: =F167<>"" -> TRUE | E167: =A167 -> a1zNz000003sRcbIAE | F167: =IF(NOT(ISBLANK(B167)),B167,"") -> a1G4J00000260QLUAY
A168: a1zNz000003sReDIAU | B168: a1G4J00000260QLUAY | D168: =F168<>"" -> TRUE | E168: =A168 -> a1zNz000003sReDIAU | F168: =IF(NOT(ISBLANK(B168)),B168,"") -> a1G4J00000260QLUAY
A169: a1zNz000003sRkfIAE | D169: =F169<>"" -> FALSE | E169: =A169 -> a1zNz000003sRkfIAE | F169: =IF(NOT(ISBLANK(B169)),B169,"")
A170: a1zNz000003sSATIA2 | D170: =F170<>"" -> FALSE | E170: =A170 -> a1zNz000003sSATIA2 | F170: =IF(NOT(ISBLANK(B170)),B170,"")
A171: a1zNz000003sT89IAE | D171: =F171<>"" -> FALSE | E171: =A171 -> a1zNz000003sT89IAE | F171: =IF(NOT(ISBLANK(B171)),B171,"")
A172: a1zNz000003sTL3IAM | D172: =F172<>"" -> FALSE | E172: =A172 -> a1zNz000003sTL3IAM | F172: =IF(NOT(ISBLANK(B172)),B172,"")
A173: a1zNz000003sTMgIAM | D173: =F173<>"" -> FALSE | E173: =A173 -> a1zNz000003sTMgIAM | F173: =IF(NOT(ISBLANK(B173)),B173,"")
A174: a1zNz000003sTOHIA2 | D174: =F174<>"" -> FALSE | E174: =A174 -> a1zNz000003sTOHIA2 | F174: =IF(NOT(ISBLANK(B174)),B174,"")
A175: a1zNz000003sTZZIA2 | D175: =F175<>"" -> FALSE | E175: =A175 -> a1zNz000003sTZZIA2 | F175: =IF(NOT(ISBLANK(B175)),B175,"")
A176: a1zNz000003sTzNIAU | D176: =F176<>"" -> FALSE | E176: =A176 -> a1zNz000003sTzNIAU | F176: =IF(NOT(ISBLANK(B176)),B176,"")
A177: a1zNz000003sU4DIAU | B177: a1G4J0000025zYpUAI | D177: =F177<>"" -> TRUE | E177: =A177 -> a1zNz000003sU4DIAU | F177: =IF(NOT(ISBLANK(B177)),B177,"") -> a1G4J0000025zYpUAI
A178: a1zNz000003sU7RIAU | D178: =F178<>"" -> FALSE | E178: =A178 -> a1zNz000003sU7RIAU | F178: =IF(NOT(ISBLANK(B178)),B178,"")
A179: a1zNz000003sU93IAE | D179: =F179<>"" -> FALSE | E179: =A179 -> a1zNz000003sU93IAE | F179: =IF(NOT(ISBLANK(B179)),B179,"")
A180: a1zNz000003sU95IAE | D180: =F180<>"" -> FALSE | E180: =A180 -> a1zNz000003sU95IAE | F180: =IF(NOT(ISBLANK(B180)),B180,"")
A181: a1zNz000003sUH8IAM | D181: =F181<>"" -> FALSE | E181: =A181 -> a1zNz000003sUH8IAM | F181: =IF(NOT(ISBLANK(B181)),B181,"")
A182: a1zNz000003sUfJIAU | D182: =F182<>"" -> FALSE | E182: =A182 -> a1zNz000003sUfJIAU | F182: =IF(NOT(ISBLANK(B182)),B182,"")
A183: a1zNz000003sUiXIAU | B183: a1G4J0000025yYCUAY | D183: =F183<>"" -> TRUE | E183: =A183 -> a1zNz000003sUiXIAU | F183: =IF(NOT(ISBLANK(B183)),B183,"") -> a1G4J0000025yYCUAY
A184: a1zNz000003sUkCIAU | D184: =F184<>"" -> FALSE | E184: =A184 -> a1zNz000003sUkCIAU | F184: =IF(NOT(ISBLANK(B184)),B184,"")
A185: a1zNz000003sUnNIAU | D185: =F185<>"" -> FALSE | E185: =A185 -> a1zNz000003sUnNIAU | F185: =IF(NOT(ISBLANK(B185)),B185,"")
A186: a1zNz000003sVGPIA2 | D186: =F186<>"" -> FALSE | E186: =A186 -> a1zNz000003sVGPIA2 | F186: =IF(NOT(ISBLANK(B186)),B186,"")
A187: a1zNz000003sVMrIAM | D187: =F187<>"" -> FALSE | E187: =A187 -> a1zNz000003sVMrIAM | F187: =IF(NOT(ISBLANK(B187)),B187,"")
A188: a1zNz000003sVY9IAM | D188: =F188<>"" -> FALSE | E188: =A188 -> a1zNz000003sVY9IAM | F188: =IF(NOT(ISBLANK(B188)),B188,"")
A189: a1zNz000003sVhpIAE | B189: a1G4J0000025xFXUAY | D189: =F189<>"" -> TRUE | E189: =A189 -> a1zNz000003sVhpIAE | F189: =IF(NOT(ISBLANK(B189)),B189,"") -> a1G4J0000025xFXUAY
A190: a1zNz000003sVl3IAE | D190: =F190<>"" -> FALSE | E190: =A190 -> a1zNz000003sVl3IAE | F190: =IF(NOT(ISBLANK(B190)),B190,"")
A191: a1zNz000003sVrVIAU | D191: =F191<>"" -> FALSE | E191: =A191 -> a1zNz000003sVrVIAU | F191: =IF(NOT(ISBLANK(B191)),B191,"")
A192: a1zNz000003sVujIAE | B192: a1GNz000002tEu1MAE | D192: =F192<>"" -> TRUE | E192: =A192 -> a1zNz000003sVujIAE | F192: =IF(NOT(ISBLANK(B192)),B192,"") -> a1GNz000002tEu1MAE
A193: a1zNz000003sWCTIA2 | D193: =F193<>"" -> FALSE | E193: =A193 -> a1zNz000003sWCTIA2 | F193: =IF(NOT(ISBLANK(B193)),B193,"")
A194: a1zNz000003sWQzIAM | D194: =F194<>"" -> FALSE | E194: =A194 -> a1zNz000003sWQzIAM | F194: =IF(NOT(ISBLANK(B194)),B194,"")
A195: a1zNz000003sWvdIAE | B195: a1G4J0000025yMjUAI | D195: =F195<>"" -> TRUE | E195: =A195 -> a1zNz000003sWvdIAE | F195: =IF(NOT(ISBLANK(B195)),B195,"") -> a1G4J0000025yMjUAI
A196: a1zNz000003sXV7IAM | B196: a1G8d0000005r4KEAQ | D196: =F196<>"" -> TRUE | E196: =A196 -> a1zNz000003sXV7IAM | F196: =IF(NOT(ISBLANK(B196)),B196,"") -> a1G8d0000005r4KEAQ
...

Sheet Get Queue Id
A1: Name | B1: DeveloperName | C1: Id
A2: Abbeville Apartments | B2: Abbeville_Apartments | C2: 00GNz0000028cn0MAA
A3: AM: BTR-London | B3: AM_BTR_London | C3: 00GNz0000028cmvMAA
A4: AM: BTR-Regions | B4: AM_BTR_Regions | C4: 00GNz0000028cmwMAA
A5: AM: New Launches | B5: AM_New_Launches | C5: 00GNz0000028cmxMAA
A6: AM: PRS-London | B6: AM_PRS_London | C6: 00GNz0000028cmyMAA
A7: AM: PRS-Regions | B7: AM_PRS_Regions | C7: 00GNz0000028cmzMAA
A8: Apex Gardens Team | B8: Apex_Gardens_Team | C8: 00GNz0000028cn1MAA
A9: Argo Apartments Team | B9: Argo_Apartments_Team | C9: 00GNz0000028cn2MAA
A10: Brook Place Team | B10: Brook_Place_Team | C10: 00GNz0000028cn3MAA
A11: BTR South Lead Queue | B11: Roberto_Lead_Queue | C11: 00GNz0000000AfJMAU
A12: Clippers Quay Team | B12: Clippers_Quay_Team | C12: 00GNz0000028cn4MAA
... A58: Windlass Apartments Team | B58: Windlass_Apartments_Team | C58: 00GNz0000028cnVMAQ

Sheet Update Owner Id
A1: Id | B1: OwnerId | C1: Owner.Name | D1: Related_Unit__r.Building__r.Onsite_PM_Team__c | F1: _update? | G1: Id | H1: OwnerId
A2: a1zNz00000001ddIAA | B2: 0058d00000202rVAAQ | C2: Deanne Coss | D2: The_Headline_Team | F2: =B2<>H2 -> TRUE | G2: =A2 -> a1zNz00000001ddIAA | H2: =IF(ISBLANK(D2),VLOOKUP("Renewal Team",'Get Queue Id'!A:C,3,FALSE), VLOOKUP(D2,'Get Queue Id'!B:C,2,FALSE)) -> 00GNz0000028cnRMAQ
A3: a1zNz00000003AnIAI | B3: 0054J000006BkQgQAK | C3: Jack Howe | D3: Brook_Place_Team | F3: =B3<>H3 -> TRUE | G3: =A3 -> a1zNz00000003AnIAI | H3: =IF(ISBLANK(D3),VLOOKUP("Renewal Team",'Get Queue Id'!A:C,3,FALSE), VLOOKUP(D3,'Get Queue Id'!B:C,2,FALSE)) -> 00GNz0000028cn3MAA
A4: a1zNz00000004RpIAI | B4: 0058d0000034Kn5AAE | C4: Coren Macniven | D4: The_Headline_Team | F4: =B4<>H4 -> TRUE | G4: =A4 -> a1zNz00000004RpIAI | H4: =IF(ISBLANK(D4),VLOOKUP("Renewal Team",'Get Queue Id'!A:C,3,FALSE), VLOOKUP(D4,'Get Queue Id'!B:C,2,FALSE)) -> 00GNz0000028cnRMAQ
A5: a1zNz00000004hxIAA | B5: 0058d00000202rVAAQ | C5: Deanne Coss | D5: The_Forge_Team | F5: =B5<>H5 -> TRUE | G5: =A5 -> a1zNz00000004hxIAA | H5: =IF(ISBLANK(D5),VLOOKUP("Renewal Team",'Get Queue Id'!A:C,3,FALSE), VLOOKUP(D5,'Get Queue Id'!B:C,2,FALSE)) -> 00GNz0000028cnQMAQ
A6: a1zNz00000004tFIAQ | B6: 0058d00000202rVAAQ | C6: Deanne Coss | D6: The_Forge_Team | F6: =B6<>H6 -> TRUE | G6: =A6 -> a1zNz00000004tFIAQ | H6: =IF(ISBLANK(D6),VLOOKUP("Renewal Team",'Get Queue Id'!A:C,3,FALSE), VLOOKUP(D6,'Get Queue Id'!B:C,2,FALSE)) -> 00GNz0000028cnQMAQ
A7: a1zNz00000005FpIAI | B7: 0058d00000202rVAAQ | C7: Deanne Coss | D7: The_Headline_Team | F7: =B7<>H7 -> TRUE | G7: =A7 -> a1zNz00000005FpIAI | H7: =IF(ISBLANK(D7),VLOOKUP("Renewal Team",'Get Queue Id'!A:C,3,FALSE), VLOOKUP(D7,'Get Queue Id'!B:C,2,FALSE)) -> 00GNz0000028cnRMAQ
A8: a1zNz0000000AtpIAE | B8: 0054J000006BkQgQAK | C8: Jack Howe | D8: The_Headline_Team | F8: =B8<>H8 -> TRUE | G8: =A8 -> a1zNz0000000AtpIAE | H8: =IF(ISBLANK(D8),VLOOKUP("Renewal Team",'Get Queue Id'!A:C,3,FALSE), VLOOKUP(D8,'Get Queue Id'!B:C,2,FALSE)) -> 00GNz0000028cnRMAQ
A9: a1zNz0000000CxFIAU | B9: 0054J000006BkQgQAK | C9: Jack Howe | D9: The_Headline_Team | F9: =B9<>H9 -> TRUE | G9: =A9 -> a1zNz0000000CxFIAU | H9: =IF(ISBLANK(D9),VLOOKUP("Renewal Team",'Get Queue Id'!A:C,3,FALSE), VLOOKUP(D9,'Get Queue Id'!B:C,2,FALSE)) -> 00GNz0000028cnRMAQ
A10: a1zNz0000000OdSIAU | B10: 0054J000006BkQgQAK | C10: Jack Howe | D10: The_Headline_Team | F10: =B10<>H10 -> TRUE | G10: =A10 -> a1zNz0000000OdSIAU | H10: =IF(ISBLANK(D10),VLOOKUP("Renewal Team",'Get Queue Id'!A:C,3,FALSE), VLOOKUP(D10,'Get Queue Id'!B:C,2,FALSE)) -> 00GNz0000028cnRMAQ
A11: a1zNz0000000Po1IAE | B11: 0054J000006BkQgQAK | C11: Jack Howe | D11: The_Headline_Team | F11: =B11<>H11 -> TRUE | G11: =A11 -> a1zNz0000000Po1IAE | H11: =IF(ISBLANK(D11),VLOOKUP("Renewal Team",'Get Queue Id'!A:C,3,FALSE), VLOOKUP(D11,'Get Queue Id'!B:C,2,FALSE)) -> 00GNz0000028cnRMAQ
A12: a1zNz0000000PsrIAE | B12: 0054J000006BkQgQAK | C12: Jack Howe | D12: The_Headline_Team | F12: =B12<>H12 -> TRUE | G12: =A12 -> a1zNz0000000PsrIAE | H12: =IF(ISBLANK(D12),VLOOKUP("Renewal Team",'Get Queue Id'!A:C,3,FALSE), VLOOKUP(D12,'Get Queue Id'!B:C,2,FALSE)) -> 00GNz0000028cnRMAQ
A13: a1zNz0000000T5FIAU | B13: 0058d00000202rVAAQ | C13: Deanne Coss | D13: The_Headline_Team | F13: =B13<>H13 -> TRUE | G13: =A13 -> a1zNz0000000T5FIAU | H13: =IF(ISBLANK(D13),VLOOKUP("Renewal Team",'Get Queue Id'!A:C,3,FALSE), VLOOKUP(D13,'Get Queue Id'!B:C,2,FALSE)) -> 00GNz0000028cnRMAQ
... A31: a1zNz0000005eWHIAY | B31: 0054J000006BkQgQAK | C31: Jack Howe | D31: The_Tilt_Works_Team | F31: =B31<>H31 -> TRUE | G31: =A31 -> a1zNz0000005eWHIAY | H31: =IF(ISBLANK(D31),VLOOKUP("Renewal Team",'Get Queue Id'!A:C,3,FALSE), VLOOKUP(D31,'Get Queue Id'!B:C,2,FALSE)) -> 00GNz0000028cnTMAQ
A32: a1zNz0000005rwXIAQ | B32: 0058d0000020QoXAAU | C32: Ruth Friend | F32: =B32<>H32 -> TRUE | G32: =A32 -> a1zNz0000005rwXIAQ | H32: =IF(ISBLANK(D32),VLOOKUP("Renewal Team",'Get Queue Id'!A:C,3,FALSE), VLOOKUP(D32,'Get Queue Id'!B:C,2,FALSE)) -> 00GNz0000048rhaMAA
A33: a1zNz0000006zqPIAQ | B33: 0058d00000202rVAAQ | C33: Deanne Coss | D33: Brook_Place_Team | F33: =B33<>H33 -> TRUE | G33: =A33 -> a1zNz0000006zqPIAQ | H33: =IF(ISBLANK(D33),VLOOKUP("Renewal Team",'Get Queue Id'!A:C,3,FALSE), VLOOKUP(D33,'Get Queue Id'!B:C,2,FALSE)) -> 00GNz0000028cn3MAA
A34: a1zNz0000006zvFIAQ | B34: 0054J000006BkQgQAK | C34: Jack Howe | D34: The_Tilt_Works_Team | F34: =B34<>H34 -> TRUE | G34: =A34 -> a1zNz0000006zvFIAQ | H34: =IF(ISBLANK(D34),VLOOKUP("Renewal Team",'Get Queue Id'!A:C,3,FALSE), VLOOKUP(D34,'Get Queue Id'!B:C,2,FALSE)) -> 00GNz0000028cnTMAQ
A35: a1zNz0000006zwrIAA | B35: 0054J000006BkQgQAK | C35: Jack Howe | D35: The_Tilt_Works_Team | F35: =B35<>H35 -> TRUE | G35: =A35 -> a1zNz0000006zwrIAA | H35: =IF(ISBLANK(D35),VLOOKUP("Renewal Team",'Get Queue Id'!A:C,3,FALSE), VLOOKUP(D35,'Get Queue Id'!B:C,2,FALSE)) -> 00GNz0000028cnTMAQ
A36: a1zNz00000070EbIAI | B36: 0058d00000202rVAAQ | C36: Deanne Coss | D36: The_Tilt_Works_Team | F36: =B36<>H36 -> TRUE | G36: =A36 -> a1zNz00000070EbIAI | H36: =IF(ISBLANK(D36),VLOOKUP("Renewal Team",'Get Queue Id'!A:C,3,FALSE), VLOOKUP(D36,'Get Queue Id'!B:C,2,FALSE)) -> 00GNz0000028cnTMAQ
A37: a1zNz00000070HpIAI | B37: 0058d00000202rVAAQ | C37: Deanne Coss | D37: The_Tilt_Works_Team | F37: =B37<>H37 -> TRUE | G37: =A37 -> a1zNz00000070HpIAI | H37: =IF(ISBLANK(D37),VLOOKUP("Renewal Team",'Get Queue Id'!A:C,3,FALSE), VLOOKUP(D37,'Get Queue Id'!B:C,2,FALSE)) -> 00GNz0000028cnTMAQ
A38: a1zNz00000070T7IAI | B38: 0058d0000034c7KAAQ | C38: Emma Cramer-Mitchell | D38: Brook_Place_Team | F38: =B38<>H38 -> TRUE | G38: =A38 -> a1zNz00000070T7IAI | H38: =IF(ISBLANK(D38),VLOOKUP("Renewal Team",'Get Queue Id'!A:C,3,FALSE), VLOOKUP(D38,'Get Queue Id'!B:C,2,FALSE)) -> 00GNz0000028cn3MAA
A39: a1zNz00000070WLIAY | B39: 0058d00000202rVAAQ | C39: Deanne Coss | D39: The_Tilt_Works_Team | F39: =B39<>H39 -> TRUE | G39: =A39 -> a1zNz00000070WLIAY | H39: =IF(ISBLANK(D39),VLOOKUP("Renewal Team",'Get Queue Id'!A:C,3,FALSE), VLOOKUP(D39,'Get Queue Id'!B:C,2,FALSE)) -> 00GNz0000028cnTMAQ
A40: a1zNz00000070g1IAA | B40: 0058d0000034c7KAAQ | C40: Emma Cramer-Mitchell | D40: Brook_Place_Team | F40: =B40<>H40 -> TRUE | G40: =A40 -> a1zNz00000070g1IAA | H40: =IF(ISBLANK(D40),VLOOKUP("Renewal Team",'Get Queue Id'!A:C,3,FALSE), VLOOKUP(D40,'Get Queue Id'!B:C,2,FALSE)) -> 00GNz0000028cn3MAA
A41: a1zNz00000070krIAA | B41: 0058d00000202rVAAQ | C41: Deanne Coss | D41: The_Tilt_Works_Team | F41: =B41<>H41 -> TRUE | G41: =A41 -> a1zNz00000070krIAA | H41: =IF(ISBLANK(D41),VLOOKUP("Renewal Team",'Get Queue Id'!A:C,3,FALSE), VLOOKUP(D41,'Get Queue Id'!B:C,2,FALSE)) -> 00GNz0000028cnTMAQ
A42: a1zNz00000074GbIAI | B42: 0058d00000202rVAAQ | C42: Deanne Coss | D42: The_Tilt_Works_Team | F42: =B42<>H42 -> TRUE | G42: =A42 -> a1zNz00000074GbIAI | H42: =IF(ISBLANK(D42),VLOOKUP("Renewal Team",'Get Queue Id'!A:C,3,FALSE), VLOOKUP(D42,'Get Queue Id'!B:C,2,FALSE)) -> 00GNz0000028cnTMAQ
A43: a1zNz00000074jdIAA | B43: 0058d00000202rVAAQ | C43: Deanne Coss | D43: The_Tilt_Works_Team | F43: =B43<>H43 -> TRUE | G43: =A43 -> a1zNz00000074jdIAA | H43: =IF(ISBLANK(D43),VLOOKUP("Renewal Team",'Get Queue Id'!A:C,3,FALSE), VLOOKUP(D43,'Get Queue Id'!B:C,2,FALSE)) -> 00GNz0000028cnTMAQ
A44: a1zNz00000076v7IAA | B44: 0058d00000202rVAAQ | C44: Deanne Coss | D44: The_Headline_Team | F44: =B44<>H44 -> TRUE | G44: =A44 -> a1zNz00000076v7IAA | H44: =IF(ISBLANK(D44),VLOOKUP("Renewal Team",'Get Queue Id'!A:C,3,FALSE), VLOOKUP(D44,'Get Queue Id'!B:C,2,FALSE)) -> 00GNz0000028cnRMAQ
... A4563: a1zNz000003iSzlIAE | B4563: 0058d0000020feeAAA | C4563: Corrina Gibson | D4563: Hawkins_and_George_Team | F4563: =B4563<>H4563 -> TRUE | G4563: =A4563 -> a1zNz000003iSzlIAE | H4563: =IF(ISBLANK(D4563),VLOOKUP("Renewal Team",'Get Queue Id'!A:C,3,FALSE), VLOOKUP(D4563,'Get Queue Id'!B:C,2,FALSE)) -> 00GNz0000028cnBMAQ
A4564: a1zNz000003iT6DIAU | B4564: 0058d0000020feeAAA | C4564: Corrina Gibson | F4564: =B4564<>H4564 -> TRUE | G4564: =A4564 -> a1zNz000003iT6DIAU | H4564: =IF(ISBLANK(D4564),VLOOKUP("Renewal Team",'Get Queue Id'!A:C,3,FALSE), VLOOKUP(D4564,'Get Queue Id'!B:C,2,FALSE)) -> 00GNz0000048rhaMAA
A4565: a1zNz000003iTB3IAM | B4565: 0054J000004vXPBQA2 | C4565: Clair Habgood | D4565: PRS_London | F4565: =B4565<>H4565 -> TRUE | G4565: =A4565 -> a1zNz000003iTB3IAM | H4565: =IF(ISBLANK(D4565),VLOOKUP("Renewal Team",'Get Queue Id'!A:C,3,FALSE), VLOOKUP(D4565,'Get Queue Id'!B:C,2,FALSE)) -> 00GNz0000028cnJMAQ
A4566: a1zNz000003iTFtIAM | B4566: 0058d0000034i83AAA | C4566: Honey Campbell | D4566: Clippers_Quay_Team | F4566: =B4566<>H4566 -> TRUE | G4566: =A4566 -> a1zNz000003iTFtIAM | H4566: =IF(ISBLANK(D4566),VLOOKUP("Renewal Team",'Get Queue Id'!A:C,3,FALSE), VLOOKUP(D4566,'Get Queue Id'!B:C,2,FALSE)) -> 00GNz0000028cn4MAA
A4567: a1zNz000003iTNxIAM | B4567: 0058d0000034SvqAAE | C4567: Chiara Rosati | D4567: Solstice_Apartments_Team | F4567: =B4567<>H4567 -> TRUE | G4567: =A4567 -> a1zNz000003iTNxIAM | H4567: =IF(ISBLANK(D4567),VLOOKUP("Renewal Team",'Get Queue Id'!A:C,3,FALSE), VLOOKUP(D4567,'Get Queue Id'!B:C,2,FALSE)) -> 00GNz0000028cnMMAQ
A4568: a1zNz000003iTPZIA2 | B4568: 0058d0000034SvqAAE | C4568: Chiara Rosati | D4568: Solstice_Apartments_Team | F4568: =B4568<>H4568 -> TRUE | G4568: =A4568 -> a1zNz000003iTPZIA2 | H4568: =IF(ISBLANK(D4568),VLOOKUP("Renewal Team",'Get Queue Id'!A:C,3,FALSE), VLOOKUP(D4568,'Get Queue Id'!B:C,2,FALSE)) -> 00GNz0000028cnMMAQ
A4569: a1zNz000003iTe6IAE | B4569: 0054J000004vXPBQA2 | C4569: Clair Habgood | D4569: PRS_London | F4569: =B4569<>H4569 -> TRUE | G4569: =A4569 -> a1zNz000003iTe6IAE | H4569: =IF(ISBLANK(D4569),VLOOKUP("Renewal Team",'Get Queue Id'!A:C,3,FALSE), VLOOKUP(D4569,'Get Queue Id'!B:C,2,FALSE)) -> 00GNz0000028cnJMAQ
A4570: a1zNz000003iTivIAE | B4570: 0058d0000034SvqAAE | C4570: Chiara Rosati | D4570: Hawkins_and_George_Team | F4570: =B4570<>H4570 -> TRUE | G4570: =A4570 -> a1zNz000003iTivIAE | H4570: =IF(ISBLANK(D4570),VLOOKUP("Renewal Team",'Get Queue Id'!A:C,3,FALSE), VLOOKUP(D4570,'Get Queue Id'!B:C,2,FALSE)) -> 00GNz0000028cnBMAQ
A4571: a1zNz000003iTkXIAU | B4571: 0058d0000034SvqAAE | C4571: Chiara Rosati | D4571: Hawkins_and_George_Team | F4571: =B4571<>H4571 -> TRUE | G4571: =A4571 -> a1zNz000003iTkXIAU | H4571: =IF(ISBLANK(D4571),VLOOKUP("Renewal Team",'Get Queue Id'!A:C,3,FALSE), VLOOKUP(D4571,'Get Queue Id'!B:C,2,FALSE)) -> 00GNz0000028cnBMAQ
A4572: a1zNz000003iTqzIAE | B4572: 0054J000004vXPBQA2 | C4572: Clair Habgood | D4572: PRS_London | F4572: =B4572<>H4572 -> TRUE | G4572: =A4572 -> a1zNz000003iTqzIAE | H4572: =IF(ISBLANK(D4572),VLOOKUP("Renewal Team",'Get Queue Id'!A:C,3,FALSE), VLOOKUP(D4572,'Get Queue Id'!B:C,2,FALSE)) -> 00GNz0000028cnJMAQ
A4573: a1zNz000003iTsbIAE | B4573: 0058d0000034SvqAAE | C4573: Chiara Rosati | D4573: Enigma_Square_Team | F4573: =B4573<>H4573 -> TRUE | G4573: =A4573 -> a1zNz000003iTsbIAE | H4573: =IF(ISBLANK(D4573),VLOOKUP("Renewal Team",'Get Queue Id'!A:C,3,FALSE), VLOOKUP(D4573,'Get Queue Id'!B:C,2,FALSE)) -> 00GNz0000028cn7MAA
A4574: a1zNz000003iTuDIAU | B4574: 0054J000004vXPBQA2 | C4574: Clair Habgood | D4574: PRS_London | F4574: =B4574<>H4574 -> TRUE | G4574: =A4574 -> a1zNz000003iTuDIAU | H4574: =IF(ISBLANK(D4574),VLOOKUP("Renewal Team",'Get Queue Id'!A:C,3,FALSE), VLOOKUP(D4574,'Get Queue Id'!B:C,2,FALSE)) -> 00GNz0000028cnJMAQ
A4575: a1zNz000003iU2HIAU | B4575: 0058d0000034SvqAAE | C4575: Chiara Rosati | D4575: Solstice_Apartments_Team | F4575: =B4575<>H4575 -> TRUE | G4575: =A4575 -> a1zNz000003iU2HIAU | H4575: =IF(ISBLANK(D4575),VLOOKUP("Renewal Team",'Get Queue Id'!A:C,3,FALSE), VLOOKUP(D4575,'Get Queue Id'!B:C,2,FALSE)) -> 00GNz0000028cnMMAQ
A4576: a1zNz000003iU5VIAU | B4576: 0058d0000034SvqAAE | C4576: Chiara Rosati | D4576: Solstice_Apartments_Team | F4576: =B4576<>H4576 -> TRUE | G4576: =A4576 -> a1zNz000003iU5VIAU | H4576: =IF(ISBLANK(D4576),VLOOKUP("Renewal Team",'Get Queue Id'!A:C,3,FALSE), VLOOKUP(D4576,'Get Queue Id'!B:C,2,FALSE)) -> 00GNz0000028cnMMAQ
... A4632: a1zNz000003ip9xIAA | B4632: 0054J000004vXOnQAM | C4632: Jemma Herring | D4632: PRS_London | F4632: =B4632<>H4632 -> TRUE | G4632: =A4632 -> a1zNz000003ip9xIAA | H4632: =IF(ISBLANK(D4632),VLOOKUP("Renewal Team",'Get Queue Id'!A:C,3,FALSE), VLOOKUP(D4632,'Get Queue Id'!B:C,2,FALSE)) -> 00GNz0000028cnJMAQ
A4633: a1zNz000003iqE5IAI | B4633: 0058d000006d4S2AAI | C4633: Haginson Mtuku | F4633: =B4633<>H4633 -> TRUE | G4633: =A4633 -> a1zNz000003iqE5IAI | H4633: =IF(ISBLANK(D4633),VLOOKUP("Renewal Team",'Get Queue Id'!A:C,3,FALSE), VLOOKUP(D4633,'Get Queue Id'!B:C,2,FALSE)) -> 00GNz0000048rhaMAA
A4634: a1zNz000003j2rxIAA | B4634: 0058d0000034SvqAAE | C4634: Chiara Rosati | D4634: The_Forge_Team | F4634: =B4634<>H4634 -> TRUE | G4634: =A4634 -> a1zNz000003j2rxIAA | H4634: =IF(ISBLANK(D4634),VLOOKUP("Renewal Team",'Get Queue Id'!A:C,3,FALSE), VLOOKUP(D4634,'Get Queue Id'!B:C,2,FALSE)) -> 00GNz0000028cnQMAQ
A4635: a1zNz000003j2vBIAQ | B4635: 0054J000005JWtDQAW | C4635: Lewis Morton | D4635: The_Silver_Yard | F4635: =B4635<>H4635 -> TRUE | G4635: =A4635 -> a1zNz000003j2vBIAQ | H4635: =IF(ISBLANK(D4635),VLOOKUP("Renewal Team",'Get Queue Id'!A:C,3,FALSE), VLOOKUP(D4635,'Get Queue Id'!B:C,2,FALSE)) -> 00GNz000006whvZMAQ
A4636: a1zNz000003j2yPIAQ | B4636: 0058d0000034SvqAAE | C4636: Chiara Rosati | D4636: Enigma_Square_Team | F4636: =B4636<>H4636 -> TRUE | G4636: =A4636 -> a1zNz000003j2yPIAQ | H4636: =IF(ISBLANK(D4636),VLOOKUP("Renewal Team",'Get Queue Id'!A:C,3,FALSE), VLOOKUP(D4636,'Get Queue Id'!B:C,2,FALSE)) -> 00GNz0000028cn7MAA
A4637: a1zNz000003j3PpIAI | B4637: 0058d0000034SvqAAE | C4637: Chiara Rosati | D4637: Enigma_Square_Team | F4637: =B4637<>H4637 -> TRUE | G4637: =A4637 -> a1zNz000003j3PpIAI | H4637: =IF(ISBLANK(D4637),VLOOKUP("Renewal Team",'Get Queue Id'!A:C,3,FALSE), VLOOKUP(D4637,'Get Queue Id'!B:C,2,FALSE)) -> 00GNz0000028cn7MAA
A4638: a1zNz000003j3UfIAI | B4638: 0058d0000034SvqAAE | C4638: Chiara Rosati | D4638: Manchester_Cluster | F4638: =B4638<>H4638 -> TRUE | G4638: =A4638 -> a1zNz000003j3UfIAI | H4638: =IF(ISBLANK(D4638),VLOOKUP("Renewal Team",'Get Queue Id'!A:C,3,FALSE), VLOOKUP(D4638,'Get Queue Id'!B:C,2,FALSE)) -> 00GNz0000028cnPMAQ
A4639: a1zNz000003j3jBIAQ | B4639: 0054J000005JWtDQAW | C4639: Lewis Morton | D4639: The_Silver_Yard | F4639: =B4639<>H4639 -> TRUE | G4639: =A4639 -> a1zNz000003j3jBIAQ | H4639: =IF(ISBLANK(D4639),VLOOKUP("Renewal Team",'Get Queue Id'!A:C,3,FALSE), VLOOKUP(D4639,'Get Queue Id'!B:C,2,FALSE)) -> 00GNz000006whvZMAQ
A4640: a1zNz000003j3mPIAQ | B4640: 0054J000005JWtDQAW | C4640: Lewis Morton | D4640: The_Barnum_Team | F4640: =B4640<>H4640 -> TRUE | G4640: =A4640 -> a1zNz000003j3mPIAQ | H4640: =IF(ISBLANK(D4640),VLOOKUP("Renewal Team",'Get Queue Id'!A:C,3,FALSE), VLOOKUP(D4640,'Get Queue Id'!B:C,2,FALSE)) -> 00GNz0000028cnNMAQ
A4641: a1zNz000003j4nJIAQ | B4641: 0058d0000020feeAAA | C4641: Corrina Gibson | D4641: Hawkins_and_George_Team | F4641: =B4641<>H4641 -> TRUE | G4641: =A4641 -> a1zNz000003j4nJIAQ | H4641: =IF(ISBLANK(D4641),VLOOKUP("Renewal Team",'Get Queue Id'!A:C,3,FALSE), VLOOKUP(D4641,'Get Queue Id'!B:C,2,FALSE)) -> 00GNz0000028cnBMAQ
A4642: a1zNz000003j5GLIAY | B4642: 0058d0000020feeAAA | C4642: Corrina Gibson | D4642: Hawkins_and_George_Team | F4642: =B4642<>H4642 -> TRUE | G4642: =A4642 -> a1zNz000003j5GLIAY | H4642: =IF(ISBLANK(D4642),VLOOKUP("Renewal Team",'Get Queue Id'!A:C,3,FALSE), VLOOKUP(D4642,'Get Queue Id'!B:C,2,FALSE)) -> 00GNz0000028cnBMAQ
A4643: a1zNz000003j5MnIAI | B4643: 0054J000004vXPBQA2 | C4643: Clair Habgood | D4643: Millet_Place_Team | F4643: =B4643<>H4643 -> TRUE | G4643: =A4643 -> a1zNz000003j5MnIAI | H4643: =IF(ISBLANK(D4643),VLOOKUP("Renewal Team",'Get Queue Id'!A:C,3,FALSE), VLOOKUP(D4643,'Get Queue Id'!B:C,2,FALSE)) -> 00GNz0000028cnHMAQ
A4644: a1zNz000003j5OPIAY | B4644: 0054J000004vXPBQA2 | C4644: Clair Habgood | D4644: Millet_Place_Team | F4644: =B4644<>H4644 -> TRUE | G4644: =A4644 -> a1zNz000003j5OPIAY | H4644: =IF(ISBLANK(D4644),VLOOKUP("Renewal Team",'Get Queue Id'!A:C,3,FALSE), VLOOKUP(D4644,'Get Queue Id'!B:C,2,FALSE)) -> 00GNz0000028cnHMAQ
A4645: a1zNz000003j5TFIAY | B4645: 0058d0000034SvqAAE | C4645: Chiara Rosati | D4645: The_Forge_Team | F4645: =B4645<>H4645 -> TRUE | G4645: =A4645 -> a1zNz000003j5TFIAY | H4645: =IF(ISBLANK(D4645),VLOOKUP("Renewal Team",'Get Queue Id'!A:C,3,FALSE), VLOOKUP(D4645,'Get Queue Id'!B:C,2,FALSE)) -> 00GNz0000028cnQMAQ
... A4767: a1zNz000003jYLZIA2 | B4767: 0054J000005JWtDQAW | C4767: Lewis Morton | D4767: The_Silver_Yard | F4767: =B4767<>H4767 -> TRUE | G4767: =A4767 -> a1zNz000003jYLZIA2 | H4767: =IF(ISBLANK(D4767),VLOOKUP("Renewal Team",'Get Queue Id'!A:C,3,FALSE), VLOOKUP(D4767,'Get Queue Id'!B:C,2,FALSE)) -> 00GNz000006whvZMAQ
A4768: a1zNz000003jYa5IAE | B4768: 0058d0000020feeAAA | C4768: Corrina Gibson | F4768: =B4768<>H4768 -> TRUE | G4768: =A4768 -> a1zNz000003jYa5IAE | H4768: =IF(ISBLANK(D4768),VLOOKUP("Renewal Team",'Get Queue Id'!A:C,3,FALSE), VLOOKUP(D4768,'Get Queue Id'!B:C,2,FALSE)) -> 00GNz0000048rhaMAA
A4769: a1zNz000003jYdJIAU | B4769: 0058d0000034Km2AAE | C4769: Jessica Illingworth | D4769: Manchester_Cluster | F4769: =B4769<>H4769 -> TRUE | G4769: =A4769 -> a1zNz000003jYdJIAU | H4769: =IF(ISBLANK(D4769),VLOOKUP("Renewal Team",'Get Queue Id'!A:C,3,FALSE), VLOOKUP(D4769,'Get Queue Id'!B:C,2,FALSE)) -> 00GNz0000028cnPMAQ
A4770: a1zNz000003jYevIAE | B4770: 0054J000005JWtDQAW | C4770: Lewis Morton | D4770: The_Silver_Yard | F4770: =B4770<>H4770 -> TRUE | G4770: =A4770 -> a1zNz000003jYevIAE | H4770: =IF(ISBLANK(D4770),VLOOKUP("Renewal Team",'Get Queue Id'!A:C,3,FALSE), VLOOKUP(D4770,'Get Queue Id'!B:C,2,FALSE)) -> 00GNz000006whvZMAQ
A4771: a1zNz000003jZHdIAM | B4771: 0058d0000034SvqAAE | C4771: Chiara Rosati | D4771: Gatehouse_Team | F4771: =B4771<>H4771 -> TRUE | G4771: =A4771 -> a1zNz000003jZHdIAM | H4771: =IF(ISBLANK(D4771),VLOOKUP("Renewal Team",'Get Queue Id'!A:C,3,FALSE), VLOOKUP(D4771,'Get Queue Id'!B:C,2,FALSE)) -> 00GNz0000028cn9MAA
A4772: a1zNz000003jZMTIA2 | B4772: 0058d0000034SvqAAE | C4772: Chiara Rosati | D4772: Gatehouse_Team | F4772: =B4772<>H4772 -> TRUE | G4772: =A4772 -> a1zNz000003jZMTIA2 | H4772: =IF(ISBLANK(D4772),VLOOKUP("Renewal Team",'Get Queue Id'!A:C,3,FALSE), VLOOKUP(D4772,'Get Queue Id'!B:C,2,FALSE)) -> 00GNz0000028cn9MAA
A4773: a1zNz000003jZnuIAE | B4773: 0058d0000034SvqAAE | C4773: Chiara Rosati | D4773: The_Forge_Team | F4773: =B4773<>H4773 -> TRUE | G4773: =A4773 -> a1zNz000003jZnuIAE | H4773: =IF(ISBLANK(D4773),VLOOKUP("Renewal Team",'Get Queue Id'!A:C,3,FALSE), VLOOKUP(D4773,'Get Queue Id'!B:C,2,FALSE)) -> 00GNz0000028cnQMAQ
A4774: a1zNz000003jZzBIAU | B4774: 0058d0000034SvqAAE | C4774: Chiara Rosati | D4774: The_Headline_Team | F4774: =B4774<>H4774 -> TRUE | G4774: =A4774 -> a1zNz000003jZzBIAU | H4774: =IF(ISBLANK(D4774),VLOOKUP("Renewal Team",'Get Queue Id'!A:C,3,FALSE), VLOOKUP(D4774,'Get Queue Id'!B:C,2,FALSE)) -> 00GNz0000028cnRMAQ
A4775: a1zNz000003ja8rIAA | B4775: 0058d0000020feeAAA | C4775: Corrina Gibson | D4775: Clippers_Quay_Team | F4775: =B4775<>H4775 -> TRUE | G4775: =A4775 -> a1zNz000003ja8rIAA | H4775: =IF(ISBLANK(D4775),VLOOKUP("Renewal Team",'Get Queue Id'!A:C,3,FALSE), VLOOKUP(D4775,'Get Queue Id'!B:C,2,FALSE)) -> 00GNz0000028cn4MAA
A4776: a1zNz000003jaDhIAI | B4776: 0058d0000034SvqAAE | C4776: Chiara Rosati | D4776: The_Forge_Team | F4776: =B4776<>H4776 -> TRUE | G4776: =A4776 -> a1zNz000003jaDhIAI | H4776: =IF(ISBLANK(D4776),VLOOKUP("Renewal Team",'Get Queue Id'!A:C,3,FALSE), VLOOKUP(D4776,'Get Queue Id'!B:C,2,FALSE)) -> 00GNz0000028cnQMAQ
A4777: a1zNz000003jaFJIAY | B4777: 0058d0000034SvqAAE | C4777: Chiara Rosati | D4777: The_Headline_Team | F4777: =B4777<>H4777 -> TRUE | G4777: =A4777 -> a1zNz000003jaFJIAY | H4777: =IF(ISBLANK(D4777),VLOOKUP("Renewal Team",'Get Queue Id'!A:C,3,FALSE), VLOOKUP(D4777,'Get Queue Id'!B:C,2,FALSE)) -> 00GNz0000028cnRMAQ
A4778: a1zNz000003jaGvIAI | B4778: 0058d0000034SvqAAE | C4778: Chiara Rosati | D4778: The_Headline_Team | F4778: =B4778<>H4778 -> TRUE | G4778: =A4778 -> a1zNz000003jaGvIAI | H4778: =IF(ISBLANK(D4778),VLOOKUP("Renewal Team",'Get Queue Id'!A:C,3,FALSE), VLOOKUP(D4778,'Get Queue Id'!B:C,2,FALSE)) -> 00GNz0000028cnRMAQ
A4779: a1zNz000003jabtIAA | B4779: 0058d0000034c7JAAQ | C4779: Sharon Goyder-Smith | D4779: Solstice_Apartments_Team | F4779: =B4779<>H4779 -> TRUE | G4779: =A4779 -> a1zNz000003jabtIAA | H4779: =IF(ISBLANK(D4779),VLOOKUP("Renewal Team",'Get Queue Id'!A:C,3,FALSE), VLOOKUP(D4779,'Get Queue Id'!B:C,2,FALSE)) -> 00GNz0000028cnMMAQ
A4780: a1zNz000003jaiNIAQ | B4780: 0058d0000034SvqAAE | C4780: Chiara Rosati | D4780: Enigma_Square_Team | F4780: =B4780<>H4780 -> TRUE | G4780: =A4780 -> a1zNz000003jaiNIAQ | H4780: =IF(ISBLANK(D4780),VLOOKUP("Renewal Team",'Get Queue Id'!A:C,3,FALSE), VLOOKUP(D4780,'Get Queue Id'!B:C,2,FALSE)) -> 00GNz0000028cn7MAA
... A4933: a1zNz000003kkJ3IAI | B4933: 0054J000005JWtDQAW | C4933: Lewis Morton | D4933: The_Condor_Team | F4933: =B4933<>H4933 -> TRUE | G4933: =A4933 -> a1zNz000003kkJ3IAI | H4933: =IF(ISBLANK(D4933),VLOOKUP("Renewal Team",'Get Queue Id'!A:C,3,FALSE), VLOOKUP(D4933,'Get Queue Id'!B:C,2,FALSE)) -> 00GNz0000028cnOMAQ
A4934: a1zNz000003kkXZIAY | B4934: 0058d0000020feeAAA | C4934: Corrina Gibson | F4934: =B4934<>H4934 -> TRUE | G4934: =A4934 -> a1zNz000003kkXZIAY | H4934: =IF(ISBLANK(D4934),VLOOKUP("Renewal Team",'Get Queue Id'!A:C,3,FALSE), VLOOKUP(D4934,'Get Queue Id'!B:C,2,FALSE)) -> 00GNz0000048rhaMAA
A4935: a1zNz000003kkZBIAY | B4935: 0058d0000020feeAAA | C4935: Corrina Gibson | F4935: =B4935<>H4935 -> TRUE | G4935: =A4935 -> a1zNz000003kkZBIAY | H4935: =IF(ISBLANK(D4935),VLOOKUP("Renewal Team",'Get Queue Id'!A:C,3,FALSE), VLOOKUP(D4935,'Get Queue Id'!B:C,2,FALSE)) -> 00GNz0000048rhaMAA
A4936: a1zNz000003krh7IAA | B4936: 0054J000005JWtDQAW | C4936: Lewis Morton | D4936: The_Condor_Team | F4936: =B4936<>H4936 -> TRUE | G4936: =A4936 -> a1zNz000003krh7IAA | H4936: =IF(ISBLANK(D4936),VLOOKUP("Renewal Team",'Get Queue Id'!A:C,3,FALSE), VLOOKUP(D4936,'Get Queue Id'!B:C,2,FALSE)) -> 00GNz0000028cnOMAQ
A4937: a1zNz000003krvdIAA | B4937: 0054J000004vXPBQA2 | C4937: Clair Habgood | D4937: PRS_London | F4937: =B4937<>H4937 -> TRUE | G4937: =A4937 -> a1zNz000003krvdIAA | H4937: =IF(ISBLANK(D4937),VLOOKUP("Renewal Team",'Get Queue Id'!A:C,3,FALSE), VLOOKUP(D4937,'Get Queue Id'!B:C,2,FALSE)) -> 00GNz0000028cnJMAQ
A4938: a1zNz000003krxFIAQ | B4938: 0054J000004vXPBQA2 | C4938: Clair Habgood | D4938: PRS_London | F4938: =B4938<>H4938 -> TRUE | G4938: =A4938 -> a1zNz000003krxFIAQ | H4938: =IF(ISBLANK(D4938),VLOOKUP("Renewal Team",'Get Queue Id'!A:C,3,FALSE), VLOOKUP(D4938,'Get Queue Id'!B:C,2,FALSE)) -> 00GNz0000028cnJMAQ
A4939: a1zNz000003ksLRIAY | B4939: 0058d0000020feeAAA | C4939: Corrina Gibson | D4939: Clippers_Quay_Team | F4939: =B4939<>H4939 -> TRUE | G4939: =A4939 -> a1zNz000003ksLRIAY | H4939: =IF(ISBLANK(D4939),VLOOKUP("Renewal Team",'Get Queue Id'!A:C,3,FALSE), VLOOKUP(D4939,'Get Queue Id'!B:C,2,FALSE)) -> 00GNz0000028cn4MAA
A4940: a1zNz000003ksQHIAY | B4940: 0058d0000020feeAAA | C4940: Corrina Gibson | D4940: Clippers_Quay_Team | F4940: =B4940<>H4940 -> TRUE | G4940: =A4940 -> a1zNz000003ksQHIAY | H4940: =IF(ISBLANK(D4940),VLOOKUP("Renewal Team",'Get Queue Id'!A:C,3,FALSE), VLOOKUP(D4940,'Get Queue Id'!B:C,2,FALSE)) -> 00GNz0000028cn4MAA
A4941: a1zNz000003ksTVIAY | B4941: 0058d0000020feeAAA | C4941: Corrina Gibson | D4941: Clippers_Quay_Team | F4941: =B4941<>H4941 -> TRUE | G4941: =A4941 -> a1zNz000003ksTVIAY | H4941: =IF(ISBLANK(D4941),VLOOKUP("Renewal Team",'Get Queue Id'!A:C,3,FALSE), VLOOKUP(D4941,'Get Queue Id'!B:C,2,FALSE)) -> 00GNz0000028cn4MAA
A4942: a1zNz000003ksV7IAI | B4942: 0054J000004vXPBQA2 | C4942: Clair Habgood | D4942: PRS_Regions | F4942: =B4942<>H4942 -> TRUE | G4942: =A4942 -> a1zNz000003ksV7IAI | H4942: =IF(ISBLANK(D4942),VLOOKUP("Renewal Team",'Get Queue Id'!A:C,3,FALSE), VLOOKUP(D4942,'Get Queue Id'!B:C,2,FALSE)) -> 00GNz0000028cnKMAQ
A4943: a1zNz000003ksWjIAI | B4943: 0054J000004vXPBQA2 | C4943: Clair Habgood | D4943: PRS_Regions | F4943: =B4943<>H4943 -> TRUE | G4943: =A4943 -> a1zNz000003ksWjIAI | H4943: =IF(ISBLANK(D4943),VLOOKUP("Renewal Team",'Get Queue Id'!A:C,3,FALSE), VLOOKUP(D4943,'Get Queue Id'!B:C,2,FALSE)) -> 00GNz0000028cnKMAQ
A4944: a1zNz000003ksbZIAQ | B4944: 0058d0000034i83AAA | C4944: Honey Campbell | D4944: Hawkins_and_George_Team | F4944: =B4944<>H4944 -> TRUE | G4944: =A4944 -> a1zNz000003ksbZIAQ | H4944: =IF(ISBLANK(D4944),VLOOKUP("Renewal Team",'Get Queue Id'!A:C,3,FALSE), VLOOKUP(D4944,'Get Queue Id'!B:C,2,FALSE)) -> 00GNz0000028cnBMAQ
A4945: a1zNz000003ksdBIAQ | B4945: 0054J000004vXOqQAM | C4945: Jessica Howe | D4945: The_Tilt_Works_Team | F4945: =B4945<>H4945 -> TRUE | G4945: =A4945 -> a1zNz000003ksdBIAQ | H4945: =IF(ISBLANK(D4945),VLOOKUP("Renewal Team",'Get Queue Id'!A:C,3,FALSE), VLOOKUP(D4945,'Get Queue Id'!B:C,2,FALSE)) -> 00GNz0000028cnTMAQ
A4946: a1zNz000003kslFIAQ | B4946: 0054J000004vXOnQAM | C4946: Jemma Herring | D4946: PRS_London | F4946: =B4946<>H4946 -> TRUE | G4946: =A4946 -> a1zNz000003kslFIAQ | H4946: =IF(ISBLANK(D4946),VLOOKUP("Renewal Team",'Get Queue Id'!A:C,3,FALSE), VLOOKUP(D4946,'Get Queue Id'!B:C,2,FALSE)) -> 00GNz0000028cnJMAQ
A4947: a1zNz000003ksq5IAA | B4947: 0054J000004vXOqQAM | C4947: Jessica Howe | D4947: The_Tilt_Works_Team | F4947: =B4947<>H4947 -> TRUE | G4947: =A4947 -> a1zNz000003ksq5IAA | H4947: =IF(ISBLANK(D4947),VLOOKUP("Renewal Team",'Get Queue Id'!A:C,3,FALSE), VLOOKUP(D4947,'Get Queue Id'!B:C,2,FALSE)) -> 00GNz0000028cnTMAQ
... A5198: a1zNz000003m83BIAQ | B5198: 0058d0000034i83AAA | C5198: Honey Campbell | D5198: Manchester_Cluster | F5198: =B5198<>H5198 -> TRUE | G5198: =A5198 -> a1zNz000003m83BIAQ | H5198: =IF(ISBLANK(D5198),VLOOKUP("Renewal Team",'Get Queue Id'!A:C,3,FALSE), VLOOKUP(D5198,'Get Queue Id'!B:C,2,FALSE)) -> 00GNz0000028cnPMAQ
A5199: a1zNz000003m881IAA | B5199: 0054J000004vXP2QAM | C5199: Sophie Farr | F5199: =B5199<>H5199 -> TRUE | G5199: =A5199 -> a1zNz000003m881IAA | H5199: =IF(ISBLANK(D5199),VLOOKUP("Renewal Team",'Get Queue Id'!A:C,3,FALSE), VLOOKUP(D5199,'Get Queue Id'!B:C,2,FALSE)) -> 00GNz0000048rhaMAA
A5200: a1zNz000003m8ETIAY | B5200: 0058d0000034SvqAAE | C5200: Chiara Rosati | D5200: Pin_Yard_Team | F5200: =B5200<>H5200 -> TRUE | G5200: =A5200 -> a1zNz000003m8ETIAY | H5200: =IF(ISBLANK(D5200),VLOOKUP("Renewal Team",'Get Queue Id'!A:C,3,FALSE), VLOOKUP(D5200,'Get Queue Id'!B:C,2,FALSE)) -> 00GNz0000028cnLMAQ
A5201: a1zNz000003m8G5IAI | B5201: 0058d0000034SvqAAE | C5201: Chiara Rosati | D5201: Pin_Yard_Team | F5201: =B5201<>H5201 -> TRUE | G5201: =A5201 -> a1zNz000003m8G5IAI | H5201: =IF(ISBLANK(D5201),VLOOKUP("Renewal Team",'Get Queue Id'!A:C,3,FALSE), VLOOKUP(D5201,'Get Queue Id'!B:C,2,FALSE)) -> 00GNz0000028cnLMAQ
A5202: a1zNz000003m8MXIAY | B5202: 0058d0000034SvqAAE | C5202: Chiara Rosati | D5202: Manchester_Cluster | F5202: =B5202<>H5202 -> TRUE | G5202: =A5202 -> a1zNz000003m8MXIAY | H5202: =IF(ISBLANK(D5202),VLOOKUP("Renewal Team",'Get Queue Id'!A:C,3,FALSE), VLOOKUP(D5202,'Get Queue Id'!B:C,2,FALSE)) -> 00GNz0000028cnPMAQ
A5203: a1zNz000003m8O9IAI | B5203: 0058d0000034SvqAAE | C5203: Chiara Rosati | D5203: Manchester_Cluster | F5203: =B5203<>H5203 -> TRUE | G5203: =A5203 -> a1zNz000003m8O9IAI | H5203: =IF(ISBLANK(D5203),VLOOKUP("Renewal Team",'Get Queue Id'!A:C,3,FALSE), VLOOKUP(D5203,'Get Queue Id'!B:C,2,FALSE)) -> 00GNz0000028cnPMAQ
A5204: a1zNz000003m8WDIAY | B5204: 0058d0000034SvqAAE | C5204: Chiara Rosati | D5204: Solstice_Apartments_Team | F5204: =B5204<>H5204 -> TRUE | G5204: =A5204 -> a1zNz000003m8WDIAY | H5204: =IF(ISBLANK(D5204),VLOOKUP("Renewal Team",'Get Queue Id'!A:C,3,FALSE), VLOOKUP(D5204,'Get Queue Id'!B:C,2,FALSE)) -> 00GNz0000028cnMMAQ
A5205: a1zNz000003m8hVIAQ | B5205: 0058d000004Cx8uAAC | C5205: Samson Olaniyan | D5205: Millet_Place_Team | F5205: =B5205<>H5205 -> TRUE | G5205: =A5205 -> a1zNz000003m8hVIAQ | H5205: =IF(ISBLANK(D5205),VLOOKUP("Renewal Team",'Get Queue Id'!A:C,3,FALSE), VLOOKUP(D5205,'Get Queue Id'!B:C,2,FALSE)) -> 00GNz0000028cnHMAQ
A5206: a1zNz000003m8zFIAQ | B5206: 0054J000004vXPBQA2 | C5206: Clair Habgood | D5206: PRS_Regions | F5206: =B5206<>H5206 -> TRUE | G5206: =A5206 -> a1zNz000003m8zFIAQ | H5206: =IF(ISBLANK(D5206),VLOOKUP("Renewal Team",'Get Queue Id'!A:C,3,FALSE), VLOOKUP(D5206,'Get Queue Id'!B:C,2,FALSE)) -> 00GNz0000028cnKMAQ
A5207: a1zNz000003m90rIAA | B5207: 0054J000004vXPBQA2 | C5207: Clair Habgood | D5207: PRS_Regions | F5207: =B5207<>H5207 -> TRUE | G5207: =A5207 -> a1zNz000003m90rIAA | H5207: =IF(ISBLANK(D5207),VLOOKUP("Renewal Team",'Get Queue Id'!A:C,3,FALSE), VLOOKUP(D5207,'Get Queue Id'!B:C,2,FALSE)) -> 00GNz0000028cnKMAQ
A5208: a1zNz000003m97JIAQ | B5208: 0054J000004vXOqQAM | C5208: Jessica Howe | D5208: The_Barnum_Team | F5208: =B5208<>H5208 -> TRUE | G5208: =A5208 -> a1zNz000003m97JIAQ | H5208: =IF(ISBLANK(D5208),VLOOKUP("Renewal Team",'Get Queue Id'!A:C,3,FALSE), VLOOKUP(D5208,'Get Queue Id'!B:C,2,FALSE)) -> 00GNz0000028cnNMAQ
A5209: a1zNz000003m9P3IAI | B5209: 0054J000005JWtDQAW | C5209: Lewis Morton | D5209: The_Barnum_Team | F5209: =B5209<>H5209 -> TRUE | G5209: =A5209 -> a1zNz000003m9P3IAI | H5209: =IF(ISBLANK(D5209),VLOOKUP("Renewal Team",'Get Queue Id'!A:C,3,FALSE), VLOOKUP(D5209,'Get Queue Id'!B:C,2,FALSE)) -> 00GNz0000028cnNMAQ
A5210: a1zNz000003mFSrIAM | B5210: 0054J000004vXOqQAM | C5210: Jessica Howe | D5210: Brook_Place_Team | F5210: =B5210<>H5210 -> TRUE | G5210: =A5210 -> a1zNz000003mFSrIAM | H5210: =IF(ISBLANK(D5210),VLOOKUP("Renewal Team",'Get Queue Id'!A:C,3,FALSE), VLOOKUP(D5210,'Get Queue Id'!B:C,2,FALSE)) -> 00GNz0000028cn3MAA
A5211: a1zNz000003mFr4IAE | B5211: 0058d0000034SvqAAE | C5211: Chiara Rosati | D5211: Solstice_Apartments_Team | F5211: =B5211<>H5211 -> TRUE | G5211: =A5211 -> a1zNz000003mFr4IAE | H5211: =IF(ISBLANK(D5211),VLOOKUP("Renewal Team",'Get Queue Id'!A:C,3,FALSE), VLOOKUP(D5211,'Get Queue Id'!B:C,2,FALSE)) -> 00GNz0000028cnMMAQ
... A5296: a1zNz000003mk3dIAA | B5296: 0054J000004vm8VQAQ | C5296: Sam Robson | D5296: The_Forge_Team | F5296: =B5296<>H5296 -> TRUE | G5296: =A5296 -> a1zNz000003mk3dIAA | H5296: =IF(ISBLANK(D5296),VLOOKUP("Renewal Team",'Get Queue Id'!A:C,3,FALSE), VLOOKUP(D5296,'Get Queue Id'!B:C,2,FALSE)) -> 00GNz0000028cnQMAQ
A5297: a1zNz000003mkA5IAI | B5297: 0054J000004vXOqQAM | C5297: Jessica Howe | F5297: =B5297<>H5297 -> TRUE | G5297: =A5297 -> a1zNz000003mkA5IAI | H5297: =IF(ISBLANK(D5297),VLOOKUP("Renewal Team",'Get Queue Id'!A:C,3,FALSE), VLOOKUP(D5297,'Get Queue Id'!B:C,2,FALSE)) -> 00GNz0000048rhaMAA
...

Sheet Extract for Grainger
A1: Id | B1: Name | C1: Tenant__r.Name | D1: Related_Opportunity__c | E1: Related_Opportunity__r | F1: Related_Unit__c | G1: Related_Unit__r | H1: Status__c | I1: Time_Limited__c | J1: RTR_Expiry__c | K1: Date_Next_RTR_Required__c | L1: Document_Saved__c | M1: Check_Date__c | N1: CreatedDate | O1: LastModifiedDate | P1: OwnerId | Q1: Owner.Name
A2: a1zNz000000G0vJIAS | B2: RTR-00000222 | C2: Gizem Salik | H2: Vacated | I2: TRUE | J2: 46156 | K2: 46156 | L2: TRUE | M2: 45215 | N2: 2023-10-16T15:40:06.000+0000 | O2: 2025-02-03T09:53:55.000+0000 | P2: 0058d00000343K8AAI | Q2: Grace Fiske
A3: a1zNz000000LKqBIAW | B3: RTR-00000327 | C3: Saumya Saumya | H3: Completed | I3: TRUE | J3: 45653 | K3: 45734 | L3: TRUE | M3: 45369 | N3: 2023-10-24T11:33:10.000+0000 | O3: 2024-08-22T23:21:53.000+0000 | P3: 0058d000001yXeuAAE | Q3: Kimberley Pope
A4: a1zNz000000LMOvIAO | B4: RTR-00000328 | C4: Rama Rama | H4: Completed | I4: TRUE | J4: 45653 | K4: 45734 | L4: TRUE | M4: 45369 | N4: 2023-10-24T11:35:22.000+0000 | O4: 2024-08-22T23:21:53.000+0000 | P4: 0058d000001yXeuAAE | Q4: Kimberley Pope
A5: a1zNz000000T3LtIAK | B5: RTR-00000462 | C5: Ali Khajah | H5: Not started | I5: TRUE | J5: 45260 | K5: 45600 | L5: TRUE | M5: 45234 | N5: 2023-11-04T11:59:42.000+0000 | O5: 2023-11-04T11:59:42.000+0000 | P5: 005Nz000000kC30IAE | Q5: Rachel Creer
A6: a1zNz000000T4OPIA0 | B6: RTR-00000466 | C6: Zoe Ling Toh | H6: Not started | I6: TRUE | J6: 45911 | K6: 45911 | L6: TRUE | M6: 45234 | N6: 2023-11-04T13:13:05.000+0000 | O6: 2023-11-04T13:13:05.000+0000 | P6: 005Nz000000kC30IAE | Q6: Rachel Creer
A7: a1zNz000000ZWQ1IAO | B7: RTR-00000702 | C7: Elizabeth Egbo | H7: Vacated | I7: TRUE | J7: 46310 | K7: 46310 | L7: TRUE | M7: 45251 | N7: 2023-11-21T16:44:09.000+0000 | O7: 2025-02-03T09:55:41.000+0000 | P7: 005Nz0000013xmCIAQ | Q7: Rachel Steventon
A8: a1zNz0000017lb7IAA | B8: RTR-00001566 | C8: Maryam Musa | H8: Completed | I8: TRUE | J8: 47275 | K8: 47275 | L8: TRUE | M8: 45316 | N8: 2024-01-25T13:51:29.000+0000 | O8: 2024-08-22T23:17:31.000+0000 | P8: 0058d000006d4S2AAI | Q8: Haginson Mtuku
A9: a1zNz00000189OvIAI | B9: RTR-00001585 | C9: Malvika Muralidhar | H9: In Progress | I9: TRUE | J9: 45791 | K9: 45791 | L9: TRUE | M9: 45308 | N9: 2024-01-26T14:19:44.000+0000 | O9: 2024-01-26T14:22:31.000+0000 | P9: 005Nz000000ImixIAC | Q9: Nyijah Bullen
A10: a1zNz00000189bpIAA | B10: RTR-00001586 | C10: Niveditha Nanjunda Kumar | H10: In Progress | I10: TRUE | J10: 45661 | K10: 45674 | L10: TRUE | M10: 45308 | N10: 2024-01-26T14:25:34.000+0000 | O10: 2024-01-26T14:25:34.000+0000 | P10: 005Nz000000ImixIAC | Q10: Nyijah Bullen
A11: a1zNz00000189yPIAQ | B11: RTR-00001589 | C11: L011I1UBXvt7no8fiz4q RHQdg4DoREqQftVDqpKP | H11: In Progress | I11: TRUE | J11: 46047 | K11: 46047 | L11: TRUE | M11: 45308 | N11: 2024-01-26T14:57:29.000+0000 | O11: 2024-01-26T14:57:29.000+0000 | P11: 005Nz000000ImixIAC | Q11: Nyijah Bullen
A12: a1zNz0000018A1dIAE | B12: RTR-00001590 | C12: Krati Doshi | H12: In Progress | I12: TRUE | J12: 46048 | K12: 46048 | L12: TRUE | M12: 45308 | N12: 2024-01-26T14:58:31.000+0000 | O12: 2024-01-26T14:58:31.000+0000 | P12: 005Nz000000ImixIAC | Q12: Nyijah Bullen
A13: a1zNz000001GhoPIAS | B13: RTR-00001769 | C13: Niksa Khemka | H13: In Progress | I13: TRUE | J13: 46431 | K13: 46431 | L13: TRUE | M13: 45348 | N13: 2024-02-06T17:07:54.000+0000 | O13: 2024-02-06T17:07:54.000+0000 | P13: 005Nz000000ImixIAC | Q13: Nyijah Bullen
... A29: a1zNz0000056JzZIAU | B29: RTR-00023213 | C29: Zaynab Ishola | H29: Completed | I29: TRUE | J29: 46587 | K29: 46587 | L29: TRUE | M29: 45685 | N29: 2025-01-28T16:19:51.000+0000 | O29: 2025-01-28T16:19:51.000+0000 | P29: 0054J000004vm9BQAQ | Q29: Louise Spooner

Sheet Result Update Related Unit
A1: Id | B1: Related_Unit__c | C1: __Status | D1: __Id | E1: __Action | F1: __Errors
A2: a1zNz0000006zqPIAQ | B2: a1G4J0000025z5QUAQ | C2: Succeeded | D2: a1zNz0000006zqPIAQ | E2: Updated
A3: a1zNz000000GTNpIAO | B3: a1G4J0000025y8bUAA | C3: Succeeded | D3: a1zNz000000GTNpIAO | E3: Updated
A4: a1zNz000000GYCDIA4 | B4: a1G4J000004jyhpUAA | C4: Succeeded | D4: a1zNz000000GYCDIA4 | E4: Updated
A5: a1zNz000000PdpNIAS | B5: a1GNz00000017lpMAA | C5: Succeeded | D5: a1zNz000000PdpNIAS | E5: Updated
A6: a1zNz000000PeIPIA0 | B6: a1GNz00000010UGMAY | C6: Succeeded | D6: a1zNz000000PeIPIA0 | E6: Updated
A7: a1zNz000000UIFeIAO | B7: a1GNz00000012fhMAA | C7: Succeeded | D7: a1zNz000000UIFeIAO | E7: Updated
A8: a1zNz000000URvdIAG | B8: a1G4J0000025x92UAA | C8: Succeeded | D8: a1zNz000000URvdIAG | E8: Updated
A9: a1zNz000000UYfNIAW | B9: a1G8d000002QBLDEA4 | C9: Succeeded | D9: a1zNz000000UYfNIAW | E9: Updated
A10: a1zNz000000UywPIAS | B10: a1G4J0000025y1kUAA | C10: Succeeded | D10: a1zNz000000UywPIAS | E10: Updated
A11: a1zNz000000V6PJIA0 | B11: a1G4J0000025xyYUAQ | C11: Succeeded | D11: a1zNz000000V6PJIA0 | E11: Updated
A12: a1zNz000000VNd3IAG | B12: a1G4J0000025x1GUAQ | C12: Succeeded | D12: a1zNz000000VNd3IAG | E12: Updated
A13: a1zNz000000XDwCIAW | B13: a1G4J0000025ywGUAQ | C13: Succeeded | D13: a1zNz000000XDwCIAW | E13: Updated
... A3720: a1zNz0000059FY1IAM | B3720: a1GNz000000163OMAQ | C3720: Succeeded | D3720: a1zNz0000059FY1IAM | E3720: Updated

Sheet Result Update Owner Id
A1: _update? | B1: Id | C1: OwnerId | D1: __Status | E1: __Id | F1: __Action | G1: __Errors
A2: TRUE | B2: a1zNz00000001ddIAA | C2: 00GNz0000028cnRMAQ | D2: Succeeded | E2: a1zNz00000001ddIAA | F2: Updated
A3: TRUE | B3: a1zNz00000003AnIAI | C3: 00GNz0000028cn3MAA | D3: Succeeded | E3: a1zNz00000003AnIAI | F3: Updated
A4: TRUE | B4: a1zNz00000004RpIAI | C4: 00GNz0000028cnRMAQ | D4: Succeeded | E4: a1zNz00000004RpIAI | F4: Updated
A5: TRUE | B5: a1zNz00000004hxIAA | C5: 00GNz0000028cnQMAQ | D5: Succeeded | E5: a1zNz00000004hxIAA | F5: Updated
A6: TRUE | B6: a1zNz00000004tFIAQ | C6: 00GNz0000028cnQMAQ | D6: Succeeded | E6: a1zNz00000004tFIAQ | F6: Updated
A7: TRUE | B7: a1zNz00000005FpIAI | C7: 00GNz0000028cnRMAQ | D7: Succeeded | E7: a1zNz00000005FpIAI | F7: Updated
A8: TRUE | B8: a1zNz0000000AtpIAE | C8: 00GNz0000028cnRMAQ | D8: Succeeded | E8: a1zNz0000000AtpIAE | F8: Updated
A9: TRUE | B9: a1zNz0000000CxFIAU | C9: 00GNz0000028cnRMAQ | D9: Succeeded | E9: a1zNz0000000CxFIAU | F9: Updated
A10: TRUE | B10: a1zNz0000000OdSIAU | C10: 00GNz0000028cnRMAQ | D10: Succeeded | E10: a1zNz0000000OdSIAU | F10: Updated
A11: TRUE | B11: a1zNz0000000Po1IAE | C11: 00GNz0000028cnRMAQ | D11: Succeeded | E11: a1zNz0000000Po1IAE | F11: Updated
A12: TRUE | B12: a1zNz0000000PsrIAE | C12: 00GNz0000028cnRMAQ | D12: Succeeded | E12: a1zNz0000000PsrIAE | F12: Updated
A13: TRUE | B13: a1zNz0000000T5FIAU | C13: 00GNz0000028cnRMAQ | D13: Succeeded | E13: a1zNz0000000T5FIAU | F13: Updated
... A14354: TRUE | B14354: a1zNz0000059FY1IAM | C14354: 00GNz0000028cnNMAQ | D14354: Succeeded | E14354: a1zNz0000059FY1IAM | F14354: Updated
